Workbook

Sheet ★TOTAL
B2: 계획환율 | C2: 실적환율
B3: 195 | C3: 195
C5: 2026년 | D5: 당월 누계 | E5: 당월 누계 | F5: 년 계획비 | G5: 누계 계획비 | H5: 전월 | I5: 매출/생산 | J5: 당월 | K5: 매출/생산 | L5: 당월 | M5: 매출/생산
B6: (백만 원,ton) | C6: 계획 | D6: 계획 | E6: 실적 | F6: 진척률 | G6: 진척률 | H6: 실적 | I6: 구성비 | J6: 계획 | K6: 구성비 | L6: 실적 | M6: 구성비 | N6: 전월비 | O6: 계획비 | P6: 비고
B7: 매출액 | C7: 75538.697 | D7: 11062.467 | E7: 8702.6684 | F7: 0.11520808 | G7: 0.78668426 | H7: 4664.3588 | I7: 1 | J7: 4847.3134 | K7: 1 | L7: 4038.3096 | M7: 1 | N7: 0.86578022 | O7: 0.83310263
B8: 전선 | C8: 70374.311 | D8: 10130.356 | E8: 7828.2442 | F8: 0.11123724 | G8: 0.77275118 | H8: 4199.0068 | I8: 0.90023237 | J8: 4380.3348 | K8: 0.90366238 | L8: 3629.2374 | M8: 0.89870213 | N8: 0.86430855 | O8: 0.82852969
B9: 전장 | C9: 5164.386 | D9: 932.11097 | E9: 874.42417 | F9: 0.16931813 | G9: 0.93811166 | H9: 465.35203 | I9: 0.099767632 | J9: 466.97862 | K9: 0.096337617 | L9: 409.07214 | M9: 0.10129787 | N9: 0.87905954 | O9: 0.87599758
B10: * 매출동량 | C10: 5115.836 | D10: 732.6495 | E10: 467.83998 | F10: 0.09144937 | G10: 0.63855907 | H10: 249.86897 | J10: 316.8214 | L10: 217.97101 | N10: 0.87234125 | O10: 0.68799332
B11: 매출원가 | C11: 65633.005 | D11: 9608.8017 | E11: 7429.5251 | F11: 0.113198 | G11: 0.77319996 | H11: 3906.5206 | I11: 0.83752576 | J11: 4238.3198 | K11: 0.87436471 | L11: 3523.0044 | M11: 0.87239583 | N11: 0.90182666 | O11: 0.83122667
B12: 판매관리비 | C12: 5439.1898 | D12: 860.78846 | E12: 702.65876 | F12: 0.12918445 | G12: 0.81629668 | H12: 364.44748 | I12: 0.07813453 | J12: 433.23779 | K12: 0.089376888 | L12: 338.21128 | M12: 0.083750707 | N12: 0.92801102 | O12: 0.7806597
B13: 급여 | C13: 881.85064 | D13: 141.46127 | E13: 137.90227 | F13: 0.15637826 | G13: 0.9748412 | H13: 69.515911 | I13: 0.014903637 | J13: 70.087602 | K13: 0.014459061 | L13: 68.386362 | M13: 0.016934403 | N13: 0.98375121 | O13: 0.97572694
B14: 운반비 | C14: 1578.1842 | D14: 250.55345 | E14: 124.7493 | F14: 0.079046096 | G14: 0.49789496 | H14: 67.072184 | I14: 0.014379722 | J14: 116.02952 | K14: 0.023936873 | L14: 57.677116 | M14: 0.01428249 | N14: 0.85992601 | O14: 0.49708999
B15: 지급수수료 | C15: 365.15299 | D15: 60.858831 | E15: 56.409696 | F15: 0.15448236 | G15: 0.92689417 | H15: 7.1961318 | I15: 0.0015427912 | J15: 30.429416 | K15: 0.0062775837 | L15: 49.213564 | M15: 0.012186674 | N15: 6.8388914 | O15: 1.6173023
B16: 감가상각비 | C16: 218.4763 | D16: 36.412717 | E16: 36.170616 | F16: 0.16555854 | G16: 0.99335122 | H16: 18.085308 | I16: 0.0038773407 | J16: 18.206358 | K16: 0.0037559689 | L16: 18.085308 | M16: 0.0044784353 | N16: 1 | O16: 0.99335122
B17: 후생비 | C17: 377.9584 | D17: 89.436262 | E17: 60.462554 | F17: 0.15997145 | G17: 0.67604071 | H17: 39.843361 | I17: 0.0085420876 | J17: 70.8981 | K17: 0.014626267 | L17: 20.619193 | M17: 0.005105897 | N17: 0.51750636 | O17: 0.29082857
B18: 기타 | C18: 2017.5672 | D18: 282.06593 | E18: 286.96432 | F18: 0.14223284 | G18: 1.0173661 | H18: 162.73458 | I18: 0.034888951 | J18: 127.58679 | K18: 0.026321134 | L18: 124.22974 | M18: 0.030762807 | N18: 0.76338867 | O18: 0.97368811
B19: 영업이익 | C19: 4466.5016 | D19: 592.8764 | E19: 570.48451 | F19: 0.12772513 | G19: 0.96223177 | H19: 393.39067 | I19: 0.084339711 | J19: 175.75585 | K19: 0.036258405 | L19: 177.09384 | M19: 0.043853459 | N19: 0.45017296 | O19: 1.0076128
B21: 생산액 | C21: 65633.005 | D21: 9553.3734 | E21: 4082.3466 | F21: 0.062199599 | G21: 0.4273199 | H21: 4066.4536 | I21: 1 | J21: 4238.3198 | K21: 1 | L21: 3081.988 | M21: 1 | N21: 0.75790562 | O21: 0.72717213
B22: 재료비 | C22: 57561.416 | D22: 8305.0504 | E22: 3033.4561 | F22: 0.05269947 | G22: 0.36525439 | H22: 3443.2355 | I22: 0.84674163 | J22: 3635.0266 | K22: 0.85765747 | L22: 2537.7435 | M22: 0.8234112 | N22: 0.7370229 | O22: 0.69813614
B23: 노무비 | C23: 2192.994 | D23: 325.42269 | E23: 321.38714 | F23: 0.14655177 | G23: 0.98759906 | H23: 166.89904 | I23: 0.041042899 | J23: 156.22115 | K23: 0.036859218 | L23: 154.4881 | M23: 0.05012612 | N23: 0.92563802 | O23: 0.98890641
... B31: 기타 | C31: 1213.7315 | D31: 199.31118 | E31: 130.18512 | F31: 0.10726024 | G31: 0.65317522 | H31: 74.83592 | I31: 0.01840324 | J31: 106.02738 | K31: 0.025016372 | L31: 55.349202 | M31: 0.017958928 | N31: 0.73960742 | O31: 0.52202742
C35: 4466.5016 | D35: 592.8764 | E35: 570.48451 | H35: 393.39067 | J35: 175.75585 | L35: 177.09384
C36: =+C35-C19 -> 0 | D36: =+D35-D19 -> 0 | E36: =+E35-E19 -> 0 | H36: =+H35-H19 -> -5.6843419e-13 | J36: =+J35-J19 -> 0 | L36: =+L35-L19 -> -7.3896445e-13

Sheet ★WIRE SBU
B2: 계획환율 | C2: 실적환율
B3: 195 | C3: 195
C5: 2026년 | D5: 당월 누계 | E5: 당월 누계 | F5: 년 계획비 | G5: 누계 계획비 | H5: 전월 | I5: 매출/생산 | J5: 당월 | K5: 매출/생산 | L5: 당월 | M5: 매출/생산
B6: (백만 원,ton) | C6: 계획 | D6: 계획 | E6: 실적 | F6: 진척률 | G6: 진척률 | H6: 실적 | I6: 구성비 | J6: 계획 | K6: 구성비 | L6: 실적 | M6: 구성비 | N6: 전월비 | O6: 계획비 | P6: 비고
B7: 매출액 | C7: 70374.311 | D7: 10130.356 | E7: 7828.2442 | F7: 0.11123724 | G7: 0.77275118 | H7: 4199.0068 | I7: 1 | J7: 4380.3348 | K7: 1 | L7: 3629.2374 | M7: 1 | N7: 0.86430855 | O7: 0.82852969
B8: └ 江苏京信 | C8: 38240.128 | D8: 5775.0398 | E8: 5016.5944 | F8: 0.13118665 | G8: 0.86866837 | H8: 2706.9135 | I8: 0.64465567 | J8: 2497.3145 | K8: 0.57011955 | L8: 2309.6809 | M8: 0.63640941 | N8: 0.85325255 | O8: 0.92486584
B9: └ KSCI | C9: 17060.875 | D9: 2576.5403 | E9: 1355.8214 | F9: 0.079469632 | G9: 0.52621784 | H9: 758.01558 | I9: 0.18052259 | J9: 1114.1796 | K9: 0.25435946 | L9: 597.80586 | M9: 0.16471941 | N9: 0.78864588 | O9: 0.53654355
B10: └ B/B | C10: 6993.8315 | D10: 176.23703 | E10: 344.88109 | F10: 0.049312182 | G10: 1.9569161 | H10: 109.09542 | I10: 0.025981244 | J10: 76.210607 | K10: 0.017398352 | L10: 235.78567 | M10: 0.064968378 | N10: 2.1612793 | O10: 3.0938694
B11: └ 기타 | C11: 8079.4765 | D11: 1602.5385 | E11: 1110.9473 | F11: 0.13750238 | G11: 0.69324218 | H11: 624.98224 | I11: 0.14884049 | J11: 692.63012 | K11: 0.15812264 | L11: 485.96504 | M11: 0.1339028 | N11: 0.77756615 | O11: 0.70162273
B12: * 매출동량 | C12: 5115.836 | D12: 732.6495 | E12: 467.83998 | F12: 0.09144937 | G12: 0.63855907 | H12: 249.86897 | J12: 316.8214 | L12: 217.97101 | N12: 0.87234125 | O12: 0.68799332
B13: 매출원가 | C13: 60397.168 | D13: 8671.2902 | E13: 6594.0801 | F13: 0.10917863 | G13: 0.76044971 | H13: 3472.5341 | I13: 0.82698941 | J13: 3759.0697 | K13: 0.85816949 | L13: 3121.546 | M13: 0.86011072 | N13: 0.8989245 | O13: 0.83040387
B14: 판매관리비 | C14: 5014.8539 | D14: 788.69616 | E14: 639.2477 | F14: 0.12747085 | G14: 0.81051199 | H14: 332.3115 | I14: 0.079140502 | J14: 394.57432 | K14: 0.090078577 | L14: 306.9362 | M14: 0.084573192 | N14: 0.92364 | O14: 0.77789196
B15: 급여 | C15: 820.1211 | D15: 131.55898 | E15: 128.73491 | F15: 0.15697061 | G15: 0.97853381 | H15: 64.914472 | I15: 0.015459483 | J15: 65.18147 | K15: 0.014880477 | L15: 63.820437 | M15: 0.017585082 | N15: 0.9831465 | O15: 0.97911932
B16: 운반비 | C16: 1437.7842 | D16: 226.25345 | E16: 103.09078 | F16: 0.07170115 | G16: 0.45564291 | H16: 56.190186 | I16: 0.01338178 | J16: 103.87952 | K16: 0.023714974 | L16: 46.900595 | M16: 0.012922989 | N16: 0.83467591 | O16: 0.45149027
B17: 지급수수료 | C17: 339.59228 | D17: 56.598713 | E17: 53.026555 | F17: 0.15614771 | G17: 0.93688623 | H17: 6.5329368 | I17: 0.0015558291 | J17: 28.299356 | K17: 0.0064605465 | L17: 46.493618 | M17: 0.01281085 | N17: 7.116802 | O17: 1.6429214
B18: 감가상각비 | C18: 203.18296 | D18: 33.863826 | E18: 33.95042 | F18: 0.16709285 | G18: 1.0025571 | H18: 16.97521 | I18: 0.0040426728 | J18: 16.931913 | K18: 0.0038654382 | L18: 16.97521 | M18: 0.004677349 | N18: 1 | O18: 1.0025571
B19: 후생비 | C19: 337.99817 | D19: 81.525439 | E19: 51.451719 | F19: 0.15222485 | G19: 0.63111244 | H19: 33.797197 | I19: 0.0080488552 | J19: 64.284948 | K19: 0.014675807 | L19: 17.654522 | M19: 0.0048645266 | N19: 0.52236645 | O19: 0.27462917
B20: 기타 | C20: 1876.1752 | D20: 258.89576 | E20: 268.99331 | F20: 0.14337324 | G20: 1.0390024 | H20: 153.9015 | I20: 0.036651882 | J20: 115.99711 | K20: 0.026481335 | L20: 115.09181 | M20: 0.031712396 | N20: 0.74782776 | O20: 0.99219552
B21: 영업이익 | C21: 4962.2885 | D21: 670.3692 | E21: 594.91633 | F21: 0.11988749 | G21: 0.8874458 | H21: 394.16111 | I21: 0.093870083 | J21: 226.69079 | K21: 0.051751932 | L21: 200.75522 | M21: 0.055316089 | N21: 0.50932275 | O21: 0.88559055
B23: 생산액 | C23: 60397.168 | D23: 8615.862 | E23: 3268.0008 | F23: 0.05410851 | G23: 0.3793005 | H23: 3495.5716 | I23: 1 | J23: 3759.0697 | K23: 1 | L23: 2967.484 | M23: 1 | N23: 0.84892668 | O23: 0.78941979
B24: 재료비 | C24: 53694.89 | D24: 7596.3035 | E24: 2584.3628 | F24: 0.048130516 | G24: 0.34021321 | H24: 3020.8376 | I24: 0.86418989 | J24: 3272.9258 | K24: 0.87067442 | L24: 2511.048 | M24: 0.84618756 | N24: 0.83124231 | O24: 0.76721813
B25: 노무비 | C25: 1617.483 | D25: 234.25473 | E25: 98.443117 | F25: 0.06086192 | G25: 0.42023961 | H25: 110.49561 | I25: 0.031610169 | J25: 110.63717 | K25: 0.029432062 | L25: 98.443117 | M25: 0.033173934 | N25: 0.89092336 | O25: 0.88978337
... B33: 기타 | C33: 980.63952 | D33: 157.87946 | E33: 125.25211 | F33: 0.12772492 | G33: 0.79334009 | H33: 72.267482 | I33: 0.02067401 | J33: 83.10475 | K33: 0.022107797 | L33: 52.984624 | M33: 0.017855066 | N33: 0.7331738 | O33: 0.63756432

Sheet ★COM" SBU
B2: 계획환율 | C2: 실적환율
B3: 195 | C3: 195
C5: 2026년 | D5: 누계 | E5: 누계 | F5: 계 획 | G5: 계 획 | H5: 전월 | I5: 매출/생산 | J5: 당월 | K5: 매출/생산 | L5: 당월 | M5: 매출/생산
B6: (백만 원,ton) | C6: 계획 | D6: 계획 | E6: 실적 | F6: 진척율 | G6: 달성율 | H6: 실적 | I6: 구성비 | J6: 계획 | K6: 구성비 | L6: 실적 | M6: 구성비 | N6: 전월비 | O6: 계획비 | P6: 비고
B7: 매출액 | C7: 5164.386 | D7: 932.11097 | E7: 874.42417 | F7: 0.16931813 | G7: 0.93811166 | H7: 465.35203 | I7: 1 | J7: 466.97862 | K7: 1 | L7: 409.07214 | M7: 1 | N7: 0.87905954 | O7: 0.87599758
B8: └KSCP | C8: 5164.386 | D8: 932.11097 | E8: 841.15365 | F8: 0.16287583 | G8: 0.90241793 | H8: 440.09419 | I8: 0.94572315 | J8: 466.97862 | K8: 1 | L8: 401.05947 | M8: 0.98041256 | N8: 0.91130371 | O8: 0.85883903
B9: └KSCE | C9: 0 | D9: 0 | E9: 0 | F9: 0 | G9: 0 | H9: 0 | I9: 0 | J9: 0 | K9: 0 | L9: 0 | M9: 0 | N9: 0 | O9: 0
B10: └강소 경신 | C10: 0 | D10: 0 | E10: 0 | F10: 0 | G10: 0 | H10: 0 | I10: 0 | J10: 0 | K10: 0 | L10: 0 | M10: 0 | N10: 0 | O10: 0
B11: 기타 | C11: 0 | D11: 0 | E11: 33.27052 | F11: 0 | G11: 0 | H11: 25.257843 | I11: 0.054276851 | J11: 0 | K11: 0 | L11: 8.0126768 | M11: 0.019587442 | N11: 0.3172352 | O11: 0
B12: 매출원가 | C12: 5235.8369 | D12: 937.51148 | E12: 835.44493 | F12: 0.15956282 | G12: 0.89113035 | H12: 433.9865 | I12: 0.93259826 | J12: 479.25009 | K12: 1.0262784 | L12: 401.45844 | M12: 0.98138786 | N12: 0.92504822 | O12: 0.83768045
B13: 판매관리비 | C13: 424.33588 | D13: 72.092296 | E13: 63.411063 | F13: 0.14943601 | G13: 0.87958169 | H13: 32.135979 | I13: 0.069057351 | J13: 38.663464 | K13: 0.082794933 | L13: 31.275085 | M13: 0.076453714 | N13: 0.9732109 | O13: 0.8089054
B14: 급여 | C14: 61.729545 | D14: 9.9022888 | E14: 9.1673634 | F14: 0.14850852 | G14: 0.92578227 | H14: 4.6014384 | I14: 0.0098880806 | J14: 4.9061321 | K14: 0.010506117 | L14: 4.565925 | M14: 0.011161662 | N14: 0.99228211 | O14: 0.93065675
B15: 운반비 | C15: 140.4 | D15: 24.3 | E15: 21.658519 | F15: 0.15426296 | G15: 0.89129709 | H15: 10.881998 | I15: 0.023384444 | J15: 12.15 | K15: 0.026018322 | L15: 10.776521 | M15: 0.026343815 | N15: 0.99030716 | O15: 0.88695646
B16: 지급수수료 | C16: 25.560709 | D16: 4.2601182 | E16: 3.3831408 | F16: 0.13235708 | G16: 0.79414248 | H16: 0.663195 | I16: 0.0014251469 | J16: 2.1300591 | K16: 0.0045613632 | L16: 2.7199458 | M16: 0.0066490614 | N16: 4.1012761 | O16: 1.2769344
B17: 감가상각비 | C17: 15.293341 | D17: 2.5488902 | E17: 2.2201959 | F17: 0.14517403 | G17: 0.87104416 | H17: 1.110098 | I17: 0.0023855015 | J17: 1.2744451 | K17: 0.0027291294 | L17: 1.110098 | M17: 0.0027136973 | N17: 1 | O17: 0.87104416
B18: 후생비 | C18: 39.960236 | D18: 7.9108234 | E18: 9.010835 | F18: 0.22549504 | G18: 1.1390515 | H18: 6.0461642 | I18: 0.012992667 | J18: 6.613152 | K18: 0.014161573 | L18: 2.9646708 | M18: 0.0072473055 | N18: 0.49033912 | O18: 0.44829921
B19: 기타 | C19: 141.39205 | D19: 23.170175 | E19: 17.971009 | F19: 0.12710056 | G19: 0.77560954 | H19: 8.8330846 | I19: 0.018981511 | J19: 11.589675 | K19: 0.024818428 | L19: 9.1379243 | M19: 0.022338173 | N19: 1.0345111 | O19: 0.78845385
B20: 영업이익 | C20: -495.78687 | D20: -77.492799 | E20: -24.431821 | F20: (-) | G20: (-) | H20: -0.77044305 | I20: -0.0016556134 | J20: -50.934936 | K20: -0.10907338 | L20: -23.661378 | M20: -0.057841577 | N20: (-) | O20: (-)
B21: 0
B22: 생산액 | C22: 5235.8369 | D22: 937.51148 | E22: 703.85023 | H22: 570.88202 | J22: 479.25009 | L22: 114.50404
B23: 재료비 | C23: 3866.5261 | D23: 708.74686 | E23: 449.09335 | F23: 0.11614906 | G23: 0.63364422 | H23: 422.39793 | I23: 0.73990406 | J23: 362.10077 | K23: 0.75555702 | L23: 26.695424 | M23: 0.23313958 | N23: 0.063199704 | O23: 0.073723742
B24: 노무비 | C24: 575.51103 | D24: 91.16796 | E24: 112.44842 | F24: 0.19538882 | G24: 1.2334204 | H24: 56.403436 | I24: 0.098800512 | J24: 45.58398 | K24: 0.095115224 | L24: 56.044983 | M24: 0.48945856 | N24: 0.99364484 | O24: 1.2294886
B25: 제조경비 | C25: 793.79987 | D25: 137.59666 | E25: 142.30846 | F25: 0.17927499 | G25: 1.0342436 | H25: 86.390647 | I25: 0.15132837 | J25: 71.56534 | K25: 0.14932775 | L25: 55.917812 | M25: 0.48834794 | N25: 0.64726696 | O25: 0.78135327
B26: 감가상각비 | C26: 268.68479 | D26: 44.780798 | E26: 52.268658 | F26: 0.19453523 | G26: 1.1672114 | H26: 26.134329 | I26: 0.045778861 | J26: 22.390399 | K26: 0.046719655 | L26: 26.134329 | M26: 0.22823936 | N26: 1 | O26: 1.1672114
B27: 동력비 | C27: 150.79452 | D27: 27.641127 | E27: 21.295628 | F27: 0.14122283 | G27: 0.77043269 | H27: 10.516104 | I27: 0.018420801 | J27: 14.12193 | K27: 0.029466724 | L27: 10.779524 | M27: 0.094140992 | N27: 1.0250492 | O27: 0.76331803
B28: 소모품비 | C28: 61.864417 | D28: 11.33995 | E28: 44.642655 | F28: 0.72162087 | G28: 3.9367595 | H28: 41.077766 | I28: 0.071954912 | J28: 5.7936124 | K28: 0.012088912 | L28: 3.5648886 | M28: 0.031133299 | N28: 0.086783897 | O28: 0.61531362
B29: 수선비 | C29: 9.6663151 | D29: 1.7718671 | E29: 0 | F29: 0 | G29: 0 | H29: 0 | I29: 0 | J29: 0.90525194 | K29: 0.0018888926 | L29: 0 | M29: 0 | N29: 0 | O29: 0
B30: 지급수수료 | C30: 11.7 | D30: 0 | E30: 5.9017706 | F30: 0.50442483 | G30: 0 | H30: 0 | I30: 0 | J30: 0 | K30: 0 | L30: 5.9017706 | M30: 0.051542029 | N30: 0 | O30: 0
B31: 소모공구 | C31: 57.997891 | D31: 10.631203 | E31: 13.266731 | F31: 0.22874507 | G31: 1.247905 | H31: 6.0940094 | I31: 0.010674726 | J31: 5.4315116 | K31: 0.011333355 | L31: 7.1727221 | M31: 0.06264165 | N31: 1.177012 | O31: 1.3205757
B32: 기타 | C32: 233.09194 | D32: 41.431715 | E32: 4.9330164 | F32: 0.021163394 | G32: 0.11906378 | H32: 2.5684386 | I32: 0.0044990707 | J32: 22.922634 | K32: 0.047830214 | L32: 2.3645778 | M32: 0.020650606 | N32: 0.92062851 | O32: 0.10315471

Sheet Sheet2
B7: 전기일 | C7: 거래 번호 | D7: 출처 | E7: 원천 번호 | F7: 상계 계정 | G7: 세부사항 | H7: 대변/차변(현지 통화)
D8: OB
B9: 2022.03.31 | C9: 776956 | D9: JE | E9: 776956 | F9: S00186 | G9: 计提3月服务费 | H9: 100000 | I9: 전선 상해
B10: 2022.03.31 | C10: 776956 | D10: JE | E10: 776956 | F10: S00186 | G10: 计提3月服务费 | H10: 100000 | I10: 전장 상해
B11: 2022.03.31 | C11: 776956 | D11: JE | E11: 776956 | F11: S00001 | G11: 计提3月服务费 | H11: 825266 | I11: 전선 로열티
B12: 2022.03.31 | C12: 776956 | D12: JE | E12: 776956 | F12: S00001 | G12: 计提3月服务费 | H12: 444374 | I12: 전장 로열티
L13: 553432 | M13: =+L13*0.05 -> 27671.6 | N13: =+M13*175/1000 -> 4842.53
H14: 81017.628 | L14: 323218 | M14: =+L14*0.05 -> 16160.9 | N14: =+M14*175/1000 -> 2828.1575
M15: =+H21 -> 211365.64 | N15: =+M15*175/1000 -> 36988.988
H16: =+H12-H14 -> 363356.37
H20: =11650417.76*0.02 -> 233008.36
H21: 211365.64

Sheet Sheet1
A1: 업체명 | B1: 판매가에 적용하는 동가 (RMB/kg)세금 미포함 | N1: 적용동가 기준 표기 ( 월,분기 등등)
B2: 1월 | C2: 2월 | D2: 3월 | E2: 4월 | F2: 5월 | G2: 6월 | H2: 7월 | I2: 8월 | J2: 9월 | K2: 10월 | L2: 11월 | M2: 12월
A3: 江苏京信电子有限公司 | B3: 64.554 | C3: 64.554 | D3: 64.554 | E3: 65.270703 | F3: 69556.18 | G3: =+D3-E3 -> -0.71670269 | H3: =+G3*F3*188.8 -> -9411888 | N3: 전분기
A4: 上海李尔 | B4: 62.88 | C4: 62.88 | D4: 62.88 | E4: 65.270703 | F4: 108.08 | G4: =+D4-E4 -> -2.3907027 | H4: =+G4*F4*188.8 -> -48783.493 | N4: 3개월 평균
A5: 安波福连接器系统（中国）有限公司 | B5: 62.96208 | C5: 62.96208 | D5: 62.96208 | E5: 65.270703 | N5: 3개월 평균
A6: 江苏新进 | B6: 61.649 | C6: 62.398 | D6: 63.096 | E6: 65.270703 | F6: 788.28 | G6: =+D6-E6 -> -2.1747027 | H6: =+G6*F6*188.8 -> -323655.05 | N6: 전월
A7: 北京新进 | B7: 61.649 | C7: 63.398 | D7: 63.096 | E7: 65.270703 | F7: 763.38 | G7: =+D7-E7 -> -2.1747027 | H7: =+G7*F7*188.8 -> -313431.51 | N7: 전월
A8: 常州庆福 | B8: 61.649 | C8: 62.398 | D8: 63.096 | E8: 65.270703 | F8: 2836.39 | G8: =+D8-E8 -> -2.1747027 | H8: =+G8*F8*188.8 -> -1164576 | N8: 전월
A9: 盐城市晟广达汽车零部件有限公司 | B9: 61.649 | C9: 62.398 | D9: 63.096 | E9: 65.270703 | F9: 1251.8 | G9: =+D9-E9 -> -2.1747027 | H9: =+G9*F9*188.8 -> -513968.89 | N9: 전월
A10: 경신전선 본사 | B10: 12017 | C10: 11772 | D10: 12165 | E10: =+E9*188.8 -> 12323.109 | F10: 218211.84 | G10: =+D10-E10 -> -158.10867 | H10: =+G10*F10 -> -34501183 | N10: 2개월전월평균 원/KG
A11: KSCI | B11: 9550.31 | C11: 9775.93 | D11: =9941.35/1000 -> 9.94135 | E11: =+E10/1198 -> 10.286401 | F11: 39502.35 | G11: =+D11-E11 -> -0.34505123 | H11: =+G11*F11*1198 -> -16329140 | N11: 전월동가 평균 USD/TON
H12: =SUM(H3:H11) -> -62606627
H13: =+H12/175 -> -357752.15

Sheet ★손익요약
C3: ◇ 2월 손익 요약 | K3: (단위:RMB,톤,KM) | M3: ◇ 한화 환산 매출액 | O3: 195 | R3: (환율:195원, 단위: 백만원)
D4: 2026년 계획 | E4: 누계 실적 | F4: 진척율 | G4: 전 월 실 적 | H4: 계 획 | I4: 당 월 실 적 | J4: 계획비 | K4: 전월비 | N4: 전월 실 적 | O4: 계 획 | P4: 당 월 실 적 | Q4: 계획비 | R4: 전월비
C5: 매 출 액 | D5: =SUM(D6,D13) -> 3.8737793e+08 | E5: =E6+E13 -> 44629068 | F5: =+E5/D5 -> 0.11520808 | G5: 23919789 | H5: =E114 -> 24858017 | I5: =E63 -> 20709280 | J5: =+I5/H5 -> 0.83310263 | K5: =+I5/G5 -> 0.86578022 | M5: 매 출 액 | N5: =+G5*$O$3/1000000 -> 4664.3588 | O5: =+H5*$O$3/1000000 -> 4847.3134 | P5: =+I5*$O$3/1000000 -> 4038.3096 | Q5: =+P5/O5 -> 0.83310263 | R5: =+P5/N5 -> 0.86578022
C6: 일반시판 | D6: =SUM(D7:D11) -> 41433213 | E6: =SUM(E7:E11) -> 4054553.1 | F6: =+E6/D6 -> 0.09785756 | G6: 1933779.7 | H6: =E115 -> 1798464.8 | I6: =E64 -> 2120773.5 | J6: =+I6/H6 -> 1.1792132 | K6: =+I6/G6 -> 1.0966986 | M6: 일반시판 | N6: =+G6*$O$3/1000000 -> 377.08704 | O6: =+H6*$O$3/1000000 -> 350.70064 | P6: =+I6*$O$3/1000000 -> 413.55082 | Q6: =+P6/O6 -> 1.1792132 | R6: =+P6/N6 -> 1.0966986
C7: - 우즈코제 | D7: =P116 -> 13599029 | E7: =SUM(D65:O65) -> 152505.5 | F7: =+E7/D7 -> 0.011214441 | G7: 152505.5 | H7: =E116 -> 0 | I7: =E65 -> 0 | J7: =+I7/H7 -> #DIV/0! | K7: =+I7/G7 -> 0 | M7: - 우즈코제 | N7: =+G7*$O$3/1000000 -> 29.738573 | O7: =+H7*$O$3/1000000 -> 0 | P7: =+I7*$O$3/1000000 -> 0
C8: - 아센텍 | D8: =P117 -> 5984486.8 | E8: =SUM(D66:O66) -> 1768621 | F8: =+E8/D8 -> 0.29553427 | G8: 559463.68 | H8: =E117 -> 390823.63 | I8: =E66 -> 1209157.3 | J8: =+I8/H8 -> 3.0938694 | K8: =+I8/G8 -> 2.1612793 | M8: - 아센텍 | N8: =+G8*$O$3/1000000 -> 109.09542 | O8: =+H8*$O$3/1000000 -> 76.210607 | P8: =+I8*$O$3/1000000 -> 235.78567 | Q8: =+P8/O8 -> 3.0938694 | R8: =+P8/N8 -> 2.1612793
C9: - 성광다 | D9: =P118 -> 4269027.5 | E9: =SUM(D67:O67) -> 339848.03 | F9: =+E9/D9 -> 0.079607834 | G9: 120957.15 | H9: =E118 -> 278793.63 | I9: =E67 -> 218890.88 | J9: =+I9/H9 -> 0.78513587 | K9: =+I9/G9 -> 1.8096564 | M9: - 성광다 | N9: =+G9*$O$3/1000000 -> 23.586644 | O9: =+H9*$O$3/1000000 -> 54.364758 | P9: =+I9*$O$3/1000000 -> 42.683722 | Q9: =+P9/O9 -> 0.78513587 | R9: =+P9/N9 -> 1.8096564
C10: - 신진 | D10: =P119 -> 3120971.1 | E10: =SUM(D68:O68) -> 431601.6 | G10: 324228.2 | H10: =E119 -> 203818.52 | I10: =E68 -> 107373.4 | M10: - 신진 | N10: =+G10*$O$3/1000000 -> 63.224499 | O10: =+H10*$O$3/1000000 -> 39.744612 | P10: =+I10*$O$3/1000000 -> 20.937813 | Q10: =+P10/O10 -> 0.52680884 | R10: =+P10/N10 -> 0.33116614
C11: - 기타 | D11: =P120 -> 14459699 | E11: =SUM(D69:O69) -> 1361977.1 | F11: =+E11/D11 -> 0.094191245 | G11: 776625.16 | H11: =E120 -> 925029.06 | I11: =E69 -> 585351.89 | J11: =+I11/H11 -> 0.63279297 | K11: =+I11/G11 -> 0.75371224 | M11: - 기타 | N11: =+G11*$O$3/1000000 -> 151.44191 | O11: =+H11*$O$3/1000000 -> 180.38067 | P11: =+I11*$O$3/1000000 -> 114.14362 | Q11: =+P11/O11 -> 0.63279297 | R11: =+P11/N11 -> 0.75371224
C13: 경신계열 | D13: =SUM(D14:D18) -> 3.4594472e+08 | E13: =SUM(E14:E18) -> 40574515 | F13: =+E13/D13 -> 0.11728612 | G13: 21986009 | H13: =E122 -> 23059553 | I13: =E71 -> 18588506 | J13: =+I13/H13 -> 0.80610872 | K13: =+I13/G13 -> 0.84546979 | M13: 경신계열 | N13: =+G13*$O$3/1000000 -> 4287.2717 | O13: =+H13*$O$3/1000000 -> 4496.6128 | P13: =+I13*$O$3/1000000 -> 3624.7587 | Q13: =+P13/O13 -> 0.80610872 | R13: =+P13/N13 -> 0.84546979
C14: - 강소경신 | D14: =P123 -> 1.9610322e+08 | E14: =SUM(D72:O72) -> 25726125 | F14: =+E14/D14 -> 0.13118665 | G14: 13881608 | H14: =E123 -> 12806741 | I14: =E72 -> 11844517 | J14: =+I14/H14 -> 0.92486584 | K14: =+I14/G14 -> 0.85325255 | M14: - 강소경신 | N14: =+G14*$O$3/1000000 -> 2706.9135 | O14: =+H14*$O$3/1000000 -> 2497.3145 | P14: =+I14*$O$3/1000000 -> 2309.6809 | Q14: =+P14/O14 -> 0.92486584 | R14: =+P14/N14 -> 0.85325255
C15: - KSCI | D15: =P124 -> 87491665 | E15: =SUM(D73:O73) -> 6952930.4 | F15: =+E15/D15 -> 0.079469632 | G15: 3887259.4 | H15: =E124 -> 5713741.4 | I15: =E73 -> 3065671.1 | J15: =+I15/H15 -> 0.53654355 | K15: =+I15/G15 -> 0.78864588 | M15: - KSCI | N15: =+G15*$O$3/1000000 -> 758.01558 | O15: =+H15*$O$3/1000000 -> 1114.1796 | P15: =+I15*$O$3/1000000 -> 597.80586 | Q15: =+P15/O15 -> 0.53654355 | R15: =+P15/N15 -> 0.78864588
C16: - 경신 보림 B/B | D16: =P125 -> 35865802 | E16: =SUM(D74:O74) -> 3411233.3 | F16: =+E16/D16 -> 0.095111028 | G16: 1830721.1 | H16: =E125 -> 2144308.1 | I16: =E74 -> 1580512.2 | K16: =+I16/G16 -> 0.86332769 | M16: - 경신 보림 B/B | N16: =+G16*$O$3/1000000 -> 356.99062 | O16: =+H16*$O$3/1000000 -> 418.14008 | P16: =+I16*$O$3/1000000 -> 308.19988 | Q16: =+P16/O16 -> 0.73707329 | R16: =+P16/N16 -> 0.86332769
C17: - 전장사업부(상주) | E17: =SUM(D75:O75) -> 0 | G17: 0 | H17: 0 | I17: =E75 -> 0 | M17: - 전장사업부(상주) | N17: =+G17*$O$3/1000000 -> 0 | O17: =+H17*$O$3/1000000 -> 0 | P17: =+I17*$O$3/1000000 -> 0
C18: - KSCP (EV) | D18: =P126 -> 26484031 | E18: =SUM(D76:O76) -> 4484226.5 | F18: =+E18/D18 -> 0.16931813 | G18: 2386420.7 | H18: =E126 -> 2394762.2 | I18: =E76 -> 2097805.9 | J18: =+I18/H18 -> 0.87599758 | K18: =+I18/G18 -> 0.87905954 | M18: - KSCP (EV) | N18: =+G18*$O$3/1000000 -> 465.35203 | O18: =+H18*$O$3/1000000 -> 466.97862 | P18: =+I18*$O$3/1000000 -> 409.07214 | Q18: =+P18/O18 -> 0.87599758 | R18: =+P18/N18 -> 0.87905954
M19: 영업이익 | N19: =G47*195/1000000 -> 393.39067 | O19: =H47*195/1000000 -> 175.75585 | P19: =I47*195/1000000 -> 177.09384 | Q19: =+P19/O19 -> 1.0076128 | R19: =+P19/N19 -> 0.45017296
C20: 동 량(톤) | D20: =SUM(D21,D28) -> 4718118.1 | E20: =E21+E28 -> 467839.98 | F20: =+E20/D20 -> 0.099158175 | G20: 249868.97 | H20: =E128 -> 293011.4 | I20: =E79 -> 217971.01 | J20: =+I20/H20 -> 0.74389942 | K20: =+I20/G20 -> 0.87234125 | M20: 26년 매출계획 | N20: 누계실적 | O20: 영업이익계획 | P20: 누계실적
C21: 일반시판 | D21: =SUM(D22:D26) -> 390058.96 | E21: =SUM(E22:E27) -> 32653.07 | F21: =+E21/D21 -> 0.083713165 | G21: 16713.13 | H21: =E129 -> 15275.178 | I21: =E80 -> 15939.94 | J21: =+I21/H21 -> 1.0435191 | K21: =+I21/G21 -> 0.95373757 | M21: =D5*195 -> 7.5538697e+10 | N21: =E5*195 -> 8.7026684e+09 | O21: =D47*195 -> 4.4665016e+09 | P21: =E47*195 -> 5.7048451e+08
C22: - 우즈코제 | D22: =P130 -> 156157.8 | E22: =P81 -> 1909.42 | F22: =+E22/D22 -> 0.012227504 | G22: 1909.42 | H22: =E130 -> 0 | I22: =E81 -> 0 | J22: =+I22/H22 -> #DIV/0! | K22: =+I22/G22 -> 0 | N22: =N21/M21 -> 0.11520808 | O22: =O21/M21 -> 0.059128656 | P22: =P21/N21 -> 0.065552827 | Q22: =P21/O21 -> 0.12772513
C23: - 아센텍 | D23: =P131 -> 61412.939 | E23: =P82 -> 15347.17 | F23: =+E23/D23 -> 0.24990124 | G23: 4991.95 | H23: =E131 -> 4010.6409 | I23: =E82 -> 10355.22 | J23: =+I23/H23 -> 2.5819364 | K23: =+I23/G23 -> 2.0743838
C24: - 성광다 | D24: =P132 -> 43116.805 | E24: =P83 -> 3102.75 | F24: =+E24/D24 -> 0.071961501 | G24: 1144.84 | H24: =E132 -> 2815.7913 | I24: =E83 -> 1957.91 | J24: =+I24/H24 -> 0.69533206 | K24: =+I24/G24 -> 1.710204
C25: - 신진 | D25: =P133 -> 35545.713 | E25: =P84 -> 4211.31 | G25: 3223.91 | H25: =E133 -> 2321.3527 | I25: =E84 -> 987.4
C26: - 기타 | D26: =P134 -> 93825.706 | E26: =P85 -> 8082.42 | F26: =+E26/D26 -> 0.086142917 | G26: 5443.01 | H26: =E134 -> 6127.3931 | I26: =E85 -> 2639.41 | J26: =+I26/H26 -> 0.43075578 | K26: =+I26/G26 -> 0.48491735
G27: 0 | H27: =D135 -> 0 | I27: =E86 -> 0
C28: 경신계열 | D28: =SUM(D29:D32) -> 4328059.1 | E28: =SUM(E29:E32) -> 435186.91 | F28: =+E28/D28 -> 0.10055013 | G28: 233155.84 | H28: =E136 -> 277736.22 | I28: =E87 -> 202031.07 | J28: =+I28/H28 -> 0.72742068 | K28: =+I28/G28 -> 0.86650658
C29: - 강소경신 | D29: =P137 -> 2131647.1 | E29: =P88 -> 245269.41 | F29: =+E29/D29 -> 0.11506098 | G29: 132642.88 | H29: =E137 -> 139209.61 | I29: =E88 -> 112626.53 | J29: =+I29/H29 -> 0.80904281 | K29: =+I29/G29 -> 0.84909593
C30: - KSCI | D30: =P138 -> 902011.32 | E30: =P89 -> 50193.18 | F30: =+E30/D30 -> 0.055645843 | G30: 28411.88 | H30: =E138 -> 58906.862 | I30: =E89 -> 21781.3 | J30: =+I30/H30 -> 0.36975828 | K30: =+I30/G30 -> 0.7666265
C31: - 경신 보림 B/B | D31: =P139 -> 1294400.7 | E31: =P90 -> 139724.32 | F31: =+E31/D31 -> 0.10794518 | G31: 72101.08 | H31: =E139 -> 79619.752 | I31: =E90 -> 67623.24 | J31: =+I31/H31 -> 0.84932743 | K31: =+I31/G31 -> 0.93789497
C32: - 전장사업부(상주) | D32: =P140 -> 0 | E32: =P91 -> 0 | F32: =+E32/D32 -> #DIV/0! | G32: 0 | H32: =E140 -> 0 | I32: =E91 -> 0 | L32: =G32*1000 -> 0
C34: 수 량(KM) | D34: =SUM(D35,D42) -> 7.1763814e+08 | E34: =E35+E42 -> 78550847 | F34: =+E34/D34 -> 0.10945746 | G34: 41525388 | H34: =E141 -> 44207568 | I34: =E93 -> 37025459 | J34: =+I34/H34 -> 0.83753666 | K34: =+I34/G34 -> 0.89163427
C35: 일반시판 | D35: =SUM(D36:D40) -> 62107898 | E35: =SUM(E36:E41) -> 5363710 | F35: =+E35/D35 -> 0.086361159 | G35: 2881250 | H35: =E142 -> 2766620.6 | I35: =E94 -> 2482460 | J35: =+I35/H35 -> 0.89728964 | K35: =+I35/G35 -> 0.86159132
C36: - 우즈코제 | D36: =P143 -> 19744020 | E36: =P95 -> 117900 | F36: =+E36/D36 -> 0.0059714283 | G36: 117900 | H36: =E143 -> 0 | I36: =E95 -> 0 | J36: =+I36/H36 -> #DIV/0! | K36: =+I36/G36 -> 0
C37: - 아센텍 | D37: =P144 -> 8471367.7 | E37: =P96 -> 2093450 | F37: =+E37/D37 -> 0.24712066 | G37: 830500 | H37: =E144 -> 553232.18 | I37: =E96 -> 1262950 | J37: =+I37/H37 -> 2.2828571 | K37: =+I37/G37 -> 1.5207104
C38: - 성광다 | D38: =P145 -> 10329250 | E38: =P97 -> 893800 | F38: =+E38/D38 -> 0.086530968 | G38: 340500 | H38: =E145 -> 674563.27 | I38: =E97 -> 553300 | J38: =+I38/H38 -> 0.82023441 | K38: =+I38/G38 -> 1.6249633
C39: - 신진 | D39: =P146 -> 8602350 | E39: =P98 -> 1078400 | G39: 798550 | H39: =E146 -> 561786.12 | I39: =E98 -> 279850
C40: - 기타 | D40: =P147 -> 14960910 | E40: =P99 -> 1180160 | F40: =+E40/D40 -> 0.078882902 | G40: 793800 | H40: =E147 -> 977039.02 | I40: =E99 -> 386360 | J40: =+I40/H40 -> 0.39543968 | K40: =+I40/G40 -> 0.4867221
C42: 경신계열 | D42: =SUM(D43:D45) -> 6.5553024e+08 | E42: =SUM(E43:E45) -> 73187137 | F42: =+E42/D42 -> 0.11164571 | G42: 38644138 | H42: =E149 -> 41440948 | I42: =E101 -> 34542999 | J42: =+I42/H42 -> 0.83354752 | K42: =+I42/G42 -> 0.89387423
C43: - 강소경신 | D43: =P150 -> 3.142928e+08 | E43: =P102 -> 37783157 | F43: =+E43/D43 -> 0.12021643 | G43: 20194058 | H43: =E150 -> 20525244 | I43: =E102 -> 17589099 | J43: =+I43/H43 -> 0.85694958 | K43: =+I43/G43 -> 0.87100369
C44: - KSCI | D44: =P151 -> 31700085 | E44: =P103 -> 2252880 | F44: =+E44/D44 -> 0.071068579 | G44: 1319230 | H44: =E151 -> 2070209.6 | I44: =E103 -> 933650 | J44: =+I44/H44 -> 0.45099297 | K44: =+I44/G44 -> 0.70772344
C45: - 경신 보림 B/B | D45: =P152 -> 3.0953736e+08 | E45: =P104 -> 33151100 | F45: =+E45/D45 -> 0.10709886 | G45: 17130850 | H45: =E152 -> 18845494 | I45: =E104 -> 16020250 | K45: =+I45/G45 -> 0.93516959
C46: - 전장사업부(상주) | D46: =P153 -> 0 | E46: =P105 -> 0 | F46: =+E46/D46 -> #DIV/0! | G46: 0 | H46: =E153 -> 0 | I46: =E105 -> 0 | K46: =+I46/G46 -> #DIV/0!
C47: 영업이익 - KSCCZ | D47: =P154 -> 22905137 | E47: ='★손익계산서 (월별)'!C48 -> 2925561.6 | F47: =+E47/D47 -> 0.12772513 | G47: 2017388.1 | H47: =E154 -> 901312.06 | I47: =E107 -> 908173.55 | J47: =+I47/H47 -> 1.0076128 | K47: =+I47/G47 -> 0.45017296
C48: 전선사업부 | D48: =P155 -> 25447633 | E48: ='★손익계산서 (월별)'!C131 -> 3050853 | G48: 2021339 | H48: =E155 -> 1162516.9 | I48: =E108 -> 1029513.9 | J48: =+I48/H48 -> 0.88559055 | K48: =+I48/G48 -> 0.50932275
C49: 전장사업부 | D49: =P156 -> -2542496.8 | E49: ='★손익계산서 (월별)'!C207 -> -125291.39 | G49: -3950.99 | H49: =E156 -> -261204.8 | I49: =E109 -> -121340.4 | J49: =+I49/H49 -> 0.46454123 | K49: =+I49/G49 -> 30.711391
C50: (영업이익률) | D50: =D47/D5 -> 0.059128656 | E50: =E47/E5 -> 0.065552827 | G50: 0.084339711 | H50: =E157 -> 0.036258405 | I50: =E110 -> 0.043853459
C61: 2026년 실적 | D61: 21533368
D62: 1월 | E62: 2월 | F62: 3월 | G62: 4월 | H62: 5월 | I62: 6월 | J62: 7월 | K62: 8월 | L62: 9월 | M62: 10월 | N62: 11월 | O62: 12월 | P62: 합계
C63: 매 출 액 | D63: =D64+D71 -> 23919789 | E63: =E64+E71 -> 20709280 | F63: =F64+F71 -> 0 | G63: =G64+G71 -> 0 | H63: =H64+H71 -> 0 | I63: =I64+I71 -> 0 | J63: =J64+J71 -> 0 | K63: =K64+K71 -> 0 | ... O63: =O64+O71 -> 0 | P63: =SUM(D63:O63) -> 44629068 | R63: =H63/G63 -> #DIV/0!
C64: 일반시판 | D64: =SUM(D65:D69) -> 1933779.7 | E64: =SUM(E65:E69) -> 2120773.5 | F64: =SUM(F65:F69) -> 0 | G64: =SUM(G65:G69) -> 0 | H64: =SUM(H65:H69) -> 0 | I64: =SUM(I65:I69) -> 0 | J64: =SUM(J65:J69) -> 0 | K64: =SUM(K65:K69) -> 0 | ... O64: =SUM(O65:O69) -> 0 | P64: =SUM(D64:O64) -> 4054553.1 | R64: =H64/G64 -> #DIV/0!
C65: - 우즈코제 | D65: 152505.5 | P65: =SUM(D65:O65) -> 152505.5 | R65: =H65/G65 -> #DIV/0!
C66: - 아센텍 | D66: 559463.68 | E66: 1209157.3 | P66: =SUM(D66:O66) -> 1768621 | R66: =H66/G66 -> #DIV/0!
C67: - 성광다 | D67: 120957.15 | E67: 218890.88 | P67: =SUM(D67:O67) -> 339848.03 | R67: =H67/G67 -> #DIV/0!
C68: - 신진 | D68: 324228.2 | E68: 107373.4 | P68: =SUM(D68:O68) -> 431601.6 | R68: =H68/G68 -> #DIV/0!
C69: - 기타 | D69: 776625.16 | E69: 585351.89 | P69: =SUM(D69:O69) -> 1361977.1
P70: =SUM(D70:O70) -> 0
C71: 경신계열 | D71: =SUM(D72:D76) -> 21986009 | E71: =SUM(E72:E76) -> 18588506 | F71: =SUM(F72:F76) -> 0 | G71: =SUM(G72:G76) -> 0 | H71: =SUM(H72:H76) -> 0 | I71: =SUM(I72:I76) -> 0 | J71: =SUM(J72:J76) -> 0 | K71: =SUM(K72:K76) -> 0 | ... O71: =SUM(O72:O76) -> 0 | P71: =SUM(D71:O71) -> 40574515 | R71: =H71/G71 -> #DIV/0!
C72: - 강소경신 | D72: 13881608 | E72: 11844517 | P72: =SUM(D72:O72) -> 25726125 | R72: =H72/G72 -> #DIV/0!
C73: - KSCI | D73: 3887259.4 | E73: 3065671.1 | P73: =SUM(D73:O73) -> 6952930.4 | R73: =H73/G73 -> #DIV/0!
C74: - 경신 보림 B/B | D74: 1830721.1 | E74: 1580512.2 | P74: =SUM(D74:O74) -> 3411233.3 | R74: =H74/G74 -> #DIV/0!
C75: - 전장사업부(상주) | P75: =SUM(D75:O75) -> 0
C76: - KSCP (EV) | D76: 2386420.7 | E76: 2097805.9 | P76: =SUM(D76:O76) -> 4484226.5
P77: =SUM(D77:O77) -> 0
P78: =SUM(D78:O78) -> 0
C79: 동 량(톤) | D79: =SUM(D80,D87) -> 249868.97 | E79: =SUM(E80,E87) -> 217971.01 | F79: =SUM(F80,F87) -> 0 | G79: =SUM(G80,G87) -> 0 | H79: =SUM(H80,H87) -> 0 | I79: =SUM(I80,I87) -> 0 | J79: =SUM(J80,J87) -> 0 | K79: =SUM(K80,K87) -> 0 | ... O79: =SUM(O80,O87) -> 0 | P79: =SUM(D79:O79) -> 467839.98
C80: 일반시판 | D80: =SUM(D81:D85) -> 16713.13 | E80: =SUM(E81:E85) -> 15939.94 | F80: =SUM(F81:F85) -> 0 | G80: =SUM(G81:G85) -> 0 | H80: =SUM(H81:H85) -> 0 | I80: =SUM(I81:I85) -> 0 | J80: =SUM(J81:J85) -> 0 | K80: =SUM(K81:K85) -> 0 | ... O80: =SUM(O81:O85) -> 0 | P80: =SUM(D80:O80) -> 32653.07
C81: - 우즈코제 | D81: 1909.42 | E81: 0 | P81: =SUM(D81:O81) -> 1909.42
C82: - 아센텍 | D82: 4991.95 | E82: 10355.22 | P82: =SUM(D82:O82) -> 15347.17
C83: - 성광다 | D83: 1144.84 | E83: 1957.91 | P83: =SUM(D83:O83) -> 3102.75
C84: - 신진 | D84: 3223.91 | E84: 987.4 | P84: =SUM(D84:O84) -> 4211.31
C85: - 기타 | D85: 5443.01 | E85: 2639.41 | P85: =SUM(D85:O85) -> 8082.42
P86: =SUM(D86:O86) -> 0
C87: 경신계열 | D87: =SUM(D88:D91) -> 233155.84 | E87: =SUM(E88:E91) -> 202031.07 | F87: =SUM(F88:F91) -> 0 | G87: =SUM(G88:G91) -> 0 | H87: =SUM(H88:H91) -> 0 | I87: =SUM(I88:I91) -> 0 | J87: =SUM(J88:J91) -> 0 | K87: =SUM(K88:K91) -> 0 | ... O87: =SUM(O88:O91) -> 0 | P87: =SUM(D87:O87) -> 435186.91
C88: - 강소경신 | D88: 132642.88 | E88: 112626.53 | P88: =SUM(D88:O88) -> 245269.41
C89: - KSCI | D89: 28411.88 | E89: 21781.3 | P89: =SUM(D89:O89) -> 50193.18
C90: - 경신 보림 B/B | D90: 72101.08 | E90: 67623.24 | P90: =SUM(D90:O90) -> 139724.32
C91: - 전장사업부(상주) | P91: =SUM(D91:O91) -> 0
P92: =SUM(D92:O92) -> 0
C93: 수 량(KM) | D93: =SUM(D94,D101) -> 41525388 | E93: =SUM(E94,E101) -> 37025459 | F93: =SUM(F94,F101) -> 0 | G93: =SUM(G94,G101) -> 0 | H93: =SUM(H94,H101) -> 0 | I93: =SUM(I94,I101) -> 0 | J93: =SUM(J94,J101) -> 0 | K93: =SUM(K94,K101) -> 0 | ... O93: =SUM(O94,O101) -> 0 | P93: =SUM(D93:O93) -> 78550847 | Q93: =P93+M93 -> 78550847
C94: 일반시판 | D94: =SUM(D95:D99) -> 2881250 | E94: =SUM(E95:E99) -> 2482460 | F94: =SUM(F95:F99) -> 0 | G94: =SUM(G95:G99) -> 0 | H94: =SUM(H95:H99) -> 0 | I94: =SUM(I95:I99) -> 0 | J94: =SUM(J95:J99) -> 0 | K94: =SUM(K95:K99) -> 0 | ... O94: =SUM(O95:O99) -> 0 | P94: =SUM(D94:O94) -> 5363710
C95: - 우즈코제 | D95: 117900 | E95: 0 | P95: =SUM(D95:O95) -> 117900
C96: - 아센텍 | D96: 830500 | E96: 1262950 | P96: =SUM(D96:O96) -> 2093450
C97: - 성광다 | D97: 340500 | E97: 553300 | P97: =SUM(D97:O97) -> 893800
C98: - 신진 | D98: 798550 | E98: 279850 | P98: =SUM(D98:O98) -> 1078400
C99: - 기타 | D99: 793800 | E99: 386360 | P99: =SUM(D99:O99) -> 1180160
P100: =SUM(D100:O100) -> 0
C101: 경신계열 | D101: =SUM(D102:D105) -> 38644138 | E101: =SUM(E102:E104) -> 34542999 | F101: =SUM(F102:F104) -> 0 | G101: =SUM(G102:G104) -> 0 | H101: =SUM(H102:H104) -> 0 | I101: =SUM(I102:I104) -> 0 | J101: =SUM(J102:J105) -> 0 | K101: =SUM(K102:K104) -> 0 | L101: =SUM(L102:L104) -> 0 | M101: =SUM(M102:M104) -> 0 | N101: =SUM(N102:N104) -> 0 | O101: =SUM(O102:O104) -> 0 | P101: =SUM(D101:O101) -> 73187137
C102: - 강소경신 | D102: 20194058 | E102: 17589099 | P102: =SUM(D102:O102) -> 37783157 | Q102: =P102+M102 -> 37783157
C103: - KSCI | D103: 1319230 | E103: 933650 | P103: =SUM(D103:O103) -> 2252880
C104: - 경신 보림 B/B | D104: 17130850 | E104: 16020250 | P104: =SUM(D104:O104) -> 33151100
C105: - 전장사업부(상주) | P105: =SUM(D105:O105) -> 0
P106: =SUM(D106:O106) -> 0
C107: 영업이익 | D107: =D108+D109 -> 2017388.1 | E107: =E108+E109 -> 908173.55 | F107: =F108+F109 -> 0 | G107: =G108+G109 -> 0 | H107: =H108+H109 -> 0 | I107: =I108+I109 -> 0 | J107: =J108+J109 -> 0 | K107: =K108+K109 -> 0 | ... O107: =O108+O109 -> 0 | P107: =SUM(D107:O107) -> 2925561.6
C108: 전선 | D108: ='★손익계산서 (월별)'!E131 -> 2021339 | E108: ='★손익계산서 (월별)'!F131 -> 1029513.9 | F108: ='★손익계산서 (월별)'!G131 -> 0 | G108: ='★손익계산서 (월별)'!H131 -> 0 | H108: ='★손익계산서 (월별)'!I131 -> 0 | I108: ='★손익계산서 (월별)'!J131 -> 0 | J108: ='★손익계산서 (월별)'!K131 -> 0 | K108: ='★손익계산서 (월별)'!L131 -> 0 | ... O108: ='★손익계산서 (월별)'!P131 -> 0 | P108: =SUM(D108:O108) -> 3050853
C109: 전장 | D109: ='★손익계산서 (월별)'!E207 -> -3950.99 | E109: ='★손익계산서 (월별)'!F207 -> -121340.4 | F109: ='★손익계산서 (월별)'!G207 -> 0 | G109: ='★손익계산서 (월별)'!H207 -> 0 | H109: ='★손익계산서 (월별)'!I207 -> 0 | I109: ='★손익계산서 (월별)'!J207 -> 0 | J109: ='★손익계산서 (월별)'!K207 -> 0 | K109: ='★손익계산서 (월별)'!L207 -> 0 | ... O109: ='★손익계산서 (월별)'!P207 -> 0 | P109: =SUM(D109:O109) -> -125291.39
C110: (영업이익률) | D110: =D107/D63 -> 0.084339711 | E110: =E107/E63 -> 0.043853459 | F110: =F107/F63 -> #DIV/0! | G110: =G107/G63 -> #DIV/0! | H110: =H107/H63 -> #DIV/0! | I110: =I107/I63 -> #DIV/0! | J110: =J107/J63 -> #DIV/0! | K110: =K107/K63 -> #DIV/0! | ... O110: =O107/O63 -> #DIV/0! | P110: =SUM(D110:O110) -> #DIV/0!
C112: 2026년 계획
D113: 1월 | E113: 2월 | F113: 3월 | G113: 4월 | H113: 5월 | I113: 6월 | J113: 7월 | K113: 8월 | L113: 9월 | M113: 10월 | N113: 11월 | O113: 12월 | P113: 합 계
C114: 매 출 액 | D114: =D115+D122 -> 31872580 | E114: =E115+E122 -> 24858017 | F114: =F115+F122 -> 36347429 | G114: =G115+G122 -> 35770609 | H114: =H115+H122 -> 28991636 | I114: =I115+I122 -> 33665318 | J114: =J115+J122 -> 34937848 | K114: =K115+K122 -> 26487330 | ... P114: =P115+P122 -> 3.8737793e+08 | R114: =SUM(D114:M114) -> 3.1727602e+08
C115: 일반시판 | D115: =SUM(D116:D120) -> 2364748.5 | E115: =SUM(E116:E120) -> 1798464.8 | F115: =SUM(F116:F120) -> 4088710.9 | G115: =SUM(G116:G120) -> 4064702.7 | H115: =SUM(H116:H120) -> 3653163 | I115: =SUM(I116:I120) -> 3951312.4 | J115: =SUM(J116:J120) -> 2607975.6 | K115: =SUM(K116:K120) -> 3312992.2 | ... P115: =SUM(P116:P120) -> 41433213 | R115: =SUM(D115:M115) -> 33375177
C116: - 우즈코제 | D116: 0 | E116: 0 | F116: 1487393.7 | G116: 1558222 | H116: 1487393.7 | I116: 1558222 | J116: 0 | K116: 1487393.7 | L116: 1487393.7 | M116: 1487393.7 | N116: 1487393.7 | O116: 1558222 | P116: =SUM(D116:O116) -> 13599029 | R116: =SUM(D116:M116) -> 10553413
...

Sheet ★전선업체별매출현황
A1: ▣ 고객별 매출현황
A3: 고객사 | B3: 매출 | C3: 영업이익 | D3: 영업이익률 | E3: 동가차이 | F3: 원인 | G3: 동가기준
A4: Kyungshin Cable international corporation | B4: 3098002.3 | C4: 492647.94 | D4: =C4/B4 -> 0.15902117 | E4: 50732.69 | G4: 전월 LME
A5: 江苏京信电子有限公司 | B5: 11969432 | C5: 214078.67 | D5: =C5/B5 -> 0.01788545 | E5: -992172.86 | G5: 전분기 상해동가
A6: 江苏新进汽车配件有限公司 | B6: 108505.78 | C6: 16066.076 | D6: =C6/B6 -> 0.14806655 | E6: 1474.61 | G6: 전월평균 상해동가
A7: 江苏阿现特传感器有限公司 | B7: 1221909.3 | C7: -57025.978 | D7: =C7/B7 -> -0.046669568 | E7: 15465.41 | F7: T4컴파운드 수입단가 인상 현지화 컴파운드 적용 예정 | G7: 전월평균 상해동가
A8: 晟广达电子（江苏）有限公司（盐城晟广达） | B8: 221199.35 | C8: 35869.323 | D8: =C8/B8 -> 0.16215836 | E8: 2924.08 | G8: 전월평균 상해동가
A9: 기타 | B9: 395244.85 | C9: 8283.1829 | D9: =C9/B9 -> 0.020957093 | E9: -5236.76 | G9: 전월평균 상해동가, 전분기 상해동가
A10: 安徽京信电子Kyungshin(안휘경신BB) | B10: 626186.5 | C10: -52687.467 | D10: =C10/B10 -> -0.084140215
A11: 青岛京信电子한국경신(QD청도경신BB) | B11: 202876.18 | C11: 75453.69 | D11: =C11/B11 -> 0.3719199
A12: 青岛即墨한국경신(GM즉묵경신BB) | B12: 58321.723 | C12: 23928.811 | D12: =C12/B12 -> 0.41028984
A13: 韩国甫林Bolim Co.,Ltd.(BB） | B13: 709796.21 | C13: 272899.7 | D13: =C13/B13 -> 0.38447613
A14: 합계 | B14: =SUM(B4:B13) -> 18611474 | C14: =SUM(C4:C13) -> 1029514 | D14: =C14/B14 -> 0.055316089

Sheet ★손익계산서
B1: 2 | J1: (단위: RMB)
B2: 구 분 | C2: [ 전 월 ] | D2: 매출구성비 | E2: [ 계 획 ] | F2: 매출구성비 | G2: [ 실 적 ] | H2: 매출구성비 | I2: [ 전월비 ] | J2: [ 계획비 ] | K2: [ 계획비 ]
B3: I. 총 매출액 | C3: 23919789 | D3: =C3/$C$3 -> 1 | E3: =E79+E155 -> 24858017 | F3: =+E3/$E$3 -> 1 | G3: =G79+G155 -> 20709280 | H3: =+G3/G3 -> 1 | I3: =+IF(AND(G3>0,C3>0),G3/C3,"") -> 0.86578022 | K3: =+IF(AND(I3>0,E3>0),G3/E3,"") -> 0.83310263
B4: 제품매출 | C4: 23271091 | D4: =C4/$C$3 -> 0.97288028 | E4: =E80+E156 -> 23682224 | F4: =+E4/$E$3 -> 0.95269964 | G4: =G80+G156 -> 20077030 | H4: =+G4/$G$3 -> 0.96947021 | I4: =+IF(AND(G4>0,C4>0),G4/C4,"") -> 0.86274554 | K4: =+IF(AND(I4>0,E4>0),G4/E4,"") -> 0.84776791
B5: 상품매출 | C5: 389149.87 | D5: =C5/$C$3 -> 0.016268951 | E5: =E81+E157 -> 914402.51 | F5: =+E5/$E$3 -> 0.036785013 | G5: =G81+G157 -> 426644.34 | H5: =+G5/$G$3 -> 0.020601602 | I5: =+IF(AND(G5>0,C5>0),G5/C5,"") -> 1.0963497 | K5: =+IF(AND(I5>0,E5>0),G5/E5,"") -> 0.46658265
B6: 기타매출 | C6: 259547.99 | D6: =C6/$C$3 -> 0.010850764 | E6: =E82+E158 -> 261390.66 | F6: =+E6/$E$3 -> 0.010515346 | G6: =G82+G158 -> 205605.65 | H6: =+G6/$G$3 -> 0.0099281893 | I6: =+IF(AND(G6>0,C6>0),G6/C6,"") -> 0.79216815 | K6: =+IF(AND(I6>0,E6>0),G6/E6,"") -> 0.78658375
B7: 매출수량(M) | I7: =+IF(AND(G7>0,C7>0),G7/C7,"") | K7: =+IF(AND(I7>0,E7>0),G7/E7,"")
B8: 내수 동중량(KG) | C8: 177767.89 | E8: =E83 -> 213392.61 | G8: =G83 -> 150347.77 | I8: =+IF(AND(G8>0,C8>0),G8/C8,"") -> 0.84575325 | K8: =+IF(AND(I8>0,E8>0),G8/E8,"") -> 0.70455939
B9: B/B 동중량(KG) | C9: 72101.08 | E9: =E84 -> 79619.752 | G9: =G84 -> 67623.24 | I9: =+IF(AND(G9>0,C9>0),G9/C9,"") -> 0.93789497 | K9: =+IF(AND(I9>0,E9>0),G9/E9,"") -> 0.84932743
B10: II.총 매출원가 | C10: 20033439 | D10: =C10/$C$3 -> 0.83752576 | E10: =E85+E159 -> 21734973 | F10: =+E10/$E$3 -> 0.87436471 | G10: =G85+G159 -> 18066689 | H10: =+G10/G3 -> 0.87239583 | I10: =+IF(AND(G10>0,C10>0),G10/C10,"") -> 0.90182666 | K10: =+IF(AND(I10>0,E10>0),G10/E10,"") -> 0.83122667
B11: 제품매출원가 | C11: 19807173 | D11: =C11/$C$3 -> 0.82806638 | E11: =E86+E160 -> 20844010 | F11: =+E11/$E$3 -> 0.83852261 | G11: =G86+G160 -> 17570900 | H11: =+G11/$G$3 -> 0.84845538 | I11: =+IF(AND(G11>0,C11>0),G11/C11,"") -> 0.88709782 | K11: =+IF(AND(I11>0,E11>0),G11/E11,"") -> 0.84297119
B12: 상품매출원가 | C12: 375973.11 | D12: =C12/$C$3 -> 0.015718078 | E12: =E87+E161 -> 755314.88 | F12: =+E12/$E$3 -> 0.030385162 | G12: =G87+G161 -> 454276.3 | H12: =+G12/$G$3 -> 0.021935881 | I12: =+IF(AND(G12>0,C12>0),G12/C12,"") -> 1.2082681 | K12: =+IF(AND(I12>0,E12>0),G12/E12,"") -> 0.60143962
B13: 반제품매출원가 | C13: 0 | E13: =E88+E162 -> 0 | G13: =G88+G162 -> 0
B14: 기타매출원가 | C14: -159006.69 | E14: =E89+E163 -> 0 | G14: =G89+G163 -> 10700.47
B15: 영업부가세 | C15: 9300 | D15: =C15/$C$3 -> 0.00038879942 | E15: =E90+E164 -> 135648.48 | F15: =+E15/$E$3 -> 0.0054569307 | G15: =G90+G164 -> 30812.89 | H15: =+G15/$G$3 -> 0.0014878784 | I15: =+IF(AND(G15>0,C15>0),G15/C15,"") -> 3.313214 | K15: =+IF(AND(I15>0,E15>0),G15/E15,"") -> 0.22715249
B16: III.매출 총이익 | C16: 3886349.5 | E16: =E91+E165 -> 3123044.3 | F16: =+E16/$E$3 -> 0.12563529 | G16: =G91+G165 -> 2642590.4 | I16: =+IF(AND(G16>0,C16>0),G16/C16,"") -> 0.67996725 | K16: =+IF(AND(I16>0,E16>0),G16/E16,"") -> 0.84615846
B17: 매출총이익율(%) | C17: 0.16247424 | E17: =E16/E3 -> 0.12563529 | G17: =G16/G3 -> 0.12760417 | I17: =+IF(AND(G17>0,C17>0),G17/C17,"") -> 0.7853809 | K17: =+IF(AND(I17>0,E17>0),G17/E17,"") -> 1.0156713
B18: IV.판매관리비 | C18: 1868961.4 | D18: =C18/$C$3 -> 0.07813453 | E18: =E93+E167 -> 2221732.2 | F18: =+E18/$E$3 -> 0.089376888 | G18: =G93+G167 -> 1734416.8 | H18: =+G18/G3 -> 0.083750707 | I18: =+IF(AND(G18>0,C18>0),G18/C18,"") -> 0.92801102 | K18: =+IF(AND(I18>0,E18>0),G18/E18,"") -> 0.7806597
B19: 급여 (52101000 - 工资板块) | C19: 356491.85 | D19: =C19/$C$3 -> 0.014903637 | E19: =E94+E168 -> 359423.6 | F19: =+E19/$E$3 -> 0.014459061 | G19: =G94+G168 -> 350699.29 | H19: =+G19/G3 -> 0.016934403 | I19: =+IF(AND(G19>0,C19>0),G19/C19,"") -> 0.98375121 | K19: =+IF(AND(I19>0,E19>0),G19/E19,"") -> 0.97572694
B20: 복리후생비 (52105000 - 福利费) | C20: 204324.93 | D20: =C20/$C$3 -> 0.0085420876 | E20: =E95+E169 -> 363580 | F20: =+E20/$E$3 -> 0.014626267 | G20: =G95+G169 -> 105739.45 | H20: =+G20/G3 -> 0.005105897 | I20: =+IF(AND(G20>0,C20>0),G20/C20,"") -> 0.51750636 | K20: =+IF(AND(I20>0,E20>0),G20/E20,"") -> 0.29082857
B21: 여비교통비 (52106000 - 差旅交通费) | C21: 18184.77 | D21: =C21/$C$3 -> 0.00076023958 | E21: =E96+E170 -> 11828.41 | F21: =+E21/$E$3 -> 0.00047583882 | G21: =G96+G170 -> 26166.35 | H21: =+G21/G3 -> 0.0012635084 | I21: =+IF(AND(G21>0,C21>0),G21/C21,"") -> 1.4389156 | K21: =+IF(AND(I21>0,E21>0),G21/E21,"") -> 2.2121613
B22: 접대비 (52107000 - 招待费) | C22: 366.15 | D22: =C22/$C$3 -> 1.530741e-05 | E22: =E97+E171 -> 5776.522 | F22: =+E22/$E$3 -> 0.00023238064 | G22: =G97+G171 -> 1235 | H22: =+G22/G3 -> 5.9635101e-05 | I22: =+IF(AND(G22>0,C22>0),G22/C22,"") -> 3.3729346 | K22: =+IF(AND(I22>0,E22>0),G22/E22,"") -> 0.21379647
B23: 통신비 (52108000 - 通信费) | C23: 8914.1 | D23: =C23/$C$3 -> 0.00037266634 | E23: =E98+E172 -> 7301.315 | F23: =+E23/$E$3 -> 0.00029372073 | G23: =G98+G172 -> 6382.59 | H23: =+G23/G3 -> 0.00030819951 | I23: =+IF(AND(G23>0,C23>0),G23/C23,"") -> 0.71601059 | K23: =+IF(AND(I23>0,E23>0),G23/E23,"") -> 0.87416992
B24: 수도광열비 (52109000 - 水电气费) | C24: 1868.59 | D24: 0 | E24: =E99+E173 -> 1645.0169 | F24: =+E24/$E$3 -> 6.6176512e-05 | G24: =G99+G173 -> 2265.97 | H24: =+G24/G3 -> 0.0001094181 | I24: =+IF(AND(G24>0,C24>0),G24/C24,"") -> 1.212663 | K24: =+IF(AND(I24>0,E24>0),G24/E24,"") -> 1.3774752
B25: 세금과공과 (52110000 - 税与费) | C25: 700 | D25: =C25/$C$3 -> 2.9264473e-05 | E25: =E100+E174 -> 0 | F25: =+E25/$E$3 -> 0 | G25: =G100+G174 -> 700 | H25: =+G25/G3 -> 3.3801272e-05 | I25: =+IF(AND(G25>0,C25>0),G25/C25,"") -> 1 | K25: =+IF(AND(I25>0,E25>0),G25/E25,"")
B26: 감가상각비 (52111000 - 折旧费) | C26: 92745.17 | D26: =C26/$C$3 -> 0.0038773407 | E26: =E101+E175 -> 93365.94 | F26: =+E26/$E$3 -> 0.0037559689 | G26: =G101+G175 -> 92745.17 | H26: =+G26/G3 -> 0.0044784353 | I26: =+IF(AND(G26>0,C26>0),G26/C26,"") -> 1 | K26: =+IF(AND(I26>0,E26>0),G26/E26,"") -> 0.99335122
B27: 지급임차료 (52112000 - 支付租金) | C27: 0 | D27: 0 | E27: =E102+E176 -> 0 | F27: =+E27/$E$3 -> 0 | G27: =G102+G176 -> 0 | H27: =+G27/G3 -> 0 | I27: =+IF(AND(G27>0,C27>0),G27/C27,"") | K27: =+IF(AND(I27>0,E27>0),G27/E27,"")
B28: 수선비 (52113000 - 维修费) | C28: 45699.75 | D28: 0 | E28: =E103+E177 -> 20000 | F28: =+E28/$E$3 -> 0.00080456939 | G28: =G103+G177 -> 93577.1 | H28: =+G28/G3 -> 0.0045186072 | I28: =+IF(AND(G28>0,C28>0),G28/C28,"") -> 2.0476502 | K28: =+IF(AND(I28>0,E28>0),G28/E28,"") -> 4.678855 | L28: 소방유지비 42,453
B29: 보험료 (52114000 - 保险费) | C29: 27342.49 | D29: =C29/$C$3 -> 0.0011430908 | E29: =E104+E178 -> 53267.14 | F29: =+E29/$E$3 -> 0.0021428555 | G29: =G104+G178 -> 25825.84 | H29: =+G29/G3 -> 0.0012470661 | I29: =+IF(AND(G29>0,C29>0),G29/C29,"") -> 0.94453139 | K29: =+IF(AND(I29>0,E29>0),G29/E29,"") -> 0.48483624
B30: 차량유지비 (52115000 - 车辆费) | C30: 31447.37 | D30: =C30/$C$3 -> 0.001314701 | E30: =E105+E179 -> 34734 | F30: =+E30/$E$3 -> 0.0013972957 | G30: =G105+G179 -> 31925.21 | H30: =+G30/G3 -> 0.0015415896 | I30: =+IF(AND(G30>0,C30>0),G30/C30,"") -> 1.0151949 | K30: =+IF(AND(I30>0,E30>0),G30/E30,"") -> 0.91913428
B31: 경상연구개발비 (52116000 - 经常研究开发费用) | C31: 186214 | D31: 0 | E31: =E106+E180 -> 21094.31 | F31: =+E31/$E$3 -> 0.00084859181 | G31: =G106+G180 -> 0 | H31: =+G31/G3 -> 0 | I31: =+IF(AND(G31>0,C31>0),G31/C31,"") | K31: =+IF(AND(I31>0,E31>0),G31/E31,"") -> 0
B32: 운반비 (52117000 - 运费(판)_운반비) | C32: 343959.92 | D32: =C32/$C$3 -> 0.014379722 | E32: =E107+E181 -> 595023.2 | F32: =+E32/$E$3 -> 0.023936873 | G32: =G107+G181 -> 295780.08 | H32: =+G32/G3 -> 0.01428249 | I32: =+IF(AND(G32>0,C32>0),G32/C32,"") -> 0.85992601 | K32: =+IF(AND(I32>0,E32>0),G32/E32,"") -> 0.49708999
B33: 교육훈련비 (52118000 - 教育训练费) | C33: 6944.85 | D33: =C33/$C$3 -> 0.0002903391 | E33: =E108+E182 -> 2450.0152 | F33: =+E33/$E$3 -> 9.8560361e-05 | G33: =G108+G182 -> 2456.31 | H33: =+G33/G3 -> 0.00011860915 | I33: =+IF(AND(G33>0,C33>0),G33/C33,"") -> 0.35368798 | K33: =+IF(AND(I33>0,E33>0),G33/E33,"") -> 1.0025693
B34: 도서인쇄비 (52119000 - 图书印刷费) | C34: 0 | D34: 0 | E34: =E109+E183 -> 0 | F34: =+E34/$E$3 -> 0 | G34: =G109+G183 -> 0 | H34: =+G34/G3 -> 0 | I34: =+IF(AND(G34>0,C34>0),G34/C34,"") | K34: =+IF(AND(I34>0,E34>0),G34/E34,"")
B35: 회의비 (52120000 - 会议费) | C35: 0 | D35: 0 | E35: =E110+E184 -> 0 | F35: =+E35/$E$3 -> 0 | G35: =G110+G184 -> 0 | H35: =+G35/G3 -> 0 | I35: =+IF(AND(G35>0,C35>0),G35/C35,"") | K35: =+IF(AND(I35>0,E35>0),G35/E35,"")
B36: 포장비 (52121000 - 包装费) | C36: 0 | D36: 0 | E36: =E111+E185 -> 0 | F36: =+E36/$E$3 -> 0 | G36: =G111+G185 -> 0 | H36: =+G36/G3 -> 0 | I36: =+IF(AND(G36>0,C36>0),G36/C36,"") | K36: =+IF(AND(I36>0,E36>0),G36/E36,"")
B37: 사무용품비 (52122000 - 办公用品费) | C37: 35614.8 | D37: =C37/$C$3 -> 0.0014889262 | E37: =E112+E186 -> 22550 | F37: =+E37/$E$3 -> 0.00090715199 | G37: =G112+G186 -> 18968.81 | H37: =+G37/G3 -> 0.00091595701 | I37: =+IF(AND(G37>0,C37>0),G37/C37,"") -> 0.53261032 | K37: =+IF(AND(I37>0,E37>0),G37/E37,"") -> 0.84118891
B38: 소모품비 (52123000 - 消耗品费) | C38: 1000.62 | D38: 0 | E38: =E113+E187 -> 0 | F38: =+E38/$E$3 -> 0 | G38: =G113+G187 -> 977.09 | H38: =+G38/G3 -> 4.7181264e-05 | I38: =+IF(AND(G38>0,C38>0),G38/C38,"") -> 0.97648458 | K38: =+IF(AND(I38>0,E38>0),G38/E38,"")
B39: 지급수수료 (52124000 - 手续费) | C39: 36903.24 | D39: =C39/$C$3 -> 0.0015427912 | E39: =E114+E188 -> 156048.28 | F39: =+E39/$E$3 -> 0.0062775837 | G39: =G114+G188 -> 252377.25 | H39: =+G39/G3 -> 0.012186674 | I39: =+IF(AND(G39>0,C39>0),G39/C39,"") -> 6.8388914 | K39: =+IF(AND(I39>0,E39>0),G39/E39,"") -> 1.6173023 | L39: 세무사 연비용, IT 1~2월비용
B40: 보관료 (52125000 - 保管费) | C40: 0 | D40: 0 | E40: =E115+E189 -> 0 | F40: =+E40/$E$3 -> 0 | G40: =G115+G189 -> 0 | H40: =+G40/G3 -> 0 | I40: =+IF(AND(G40>0,C40>0),G40/C40,"") | K40: =+IF(AND(I40>0,E40>0),G40/E40,"")
B41: 광고선전비 (52126000 - 广告宣传费) | C41: 465238.84 | D41: 0 | E41: =E116+E190 -> 473644.49 | F41: =+E41/$E$3 -> 0.019053993 | G41: =G116+G190 -> 426595.31 | H41: =+G41/G3 -> 0.020599234 | I41: =+IF(AND(G41>0,C41>0),G41/C41,"") -> 0.9169383 | K41: =+IF(AND(I41>0,E41>0),G41/E41,"") -> 0.90066563
B42: 수출제비용 (52127000 - 出口收费) | C42: 0 | D42: 0 | E42: =E117+E191 -> 0 | F42: =+E42/$E$3 -> 0 | G42: =G117+G191 -> 0 | H42: =+G42/G3 -> 0 | I42: =+IF(AND(G42>0,C42>0),G42/C42,"") | K42: =+IF(AND(I42>0,E42>0),G42/E42,"")
B43: 견본비 (52128000 - 样品费) | C43: 0 | D43: 0 | E43: =E118+E192 -> 0 | F43: =+E43/$E$3 -> 0 | G43: =G118+G192 -> 0 | H43: =+G43/G3 -> 0 | I43: =+IF(AND(G43>0,C43>0),G43/C43,"") | K43: =+IF(AND(I43>0,E43>0),G43/E43,"")
B44: 기술지원료 (52129010 -技术支援费) | C44: 0 | D44: =C44/$C$3 -> 0 | E44: =E119+E193 -> 0 | F44: =+E44/$E$3 -> 0 | G44: =G119+G193 -> 0 | H44: =+G44/G3 -> 0 | I44: =+IF(AND(G44>0,C44>0),G44/C44,"") | K44: =+IF(AND(I44>0,E44>0),G44/E44,"")
B45: 잡비 (52190000 - 杂费) | C45: 5000 | D45: 0 | E45: =E120+E194 -> 0 | F45: =+E45/$E$3 -> 0 | G45: =G120+G194 -> 0 | H45: =+G45/G4 -> 0 | I45: =+IF(AND(G45>0,C45>0),G45/C45,"") | K45: =+IF(AND(I45>0,E45>0),G45/E45,"")
C46: 0 | E46: =E121+E195 -> 0 | G46: =G121+G195 -> 0
B47: V.영업 이익 | C47: 2017388.1 | D47: =C47/$C$3 -> 0.084339711 | E47: =E122+E196 -> 901312.06 | F47: =+E47/$E$3 -> 0.036258405 | G47: =G122+G196 -> 908173.55 | H47: =+G47/G3 -> 0.043853459 | I47: =+IF(AND(G47>0,C47>0),G47/C47,"") -> 0.45017296 | K47: =+IF(AND(I47>0,E47>0),G47/E47,"") -> 1.0076128
B48: 영업이익율(%) | C48: 0.084339711 | E48: =+E47/E3 -> 0.036258405 | G48: =+G47/G3 -> 0.043853459 | I48: =+IF(AND(G48>0,C48>0),G48/C48,"") -> 0.51996217 | K48: =+IF(AND(I48>0,E48>0),G48/E48,"") -> 1.2094702
B49: - 영업외 수익 | C49: 364965.92 | D49: =C49/$C$3 -> 0.015257907 | E49: =E124+E198 -> 0 | F49: =+E49/$E$3 -> 0 | G49: =G124+G198 -> 394193.87 | H49: =+G49/G3 -> 0.019034649 | I49: =+IF(AND(G49>0,C49>0),G49/C49,"") -> 1.0800841 | K49: =+IF(AND(I49>0,E49>0),G49/E49,"")
B50: 단기투자자산익 | C50: 0 | D50: 0 | E50: =E125+E199 -> 0 | F50: =+E50/$E$3 -> 0 | G50: =G125+G199 -> 0 | H50: =+G50/G3 -> 0 | I50: =+IF(AND(G50>0,C50>0),G50/C50,"") | K50: =+IF(AND(I50>0,E50>0),G50/E50,"")
B51: 외환차익 | C51: 327515.19 | D51: =C51/$C$3 -> 0.013692228 | E51: =E126+E200 -> 0 | F51: =+E51/$E$3 -> 0 | G51: =G126+G200 -> 347180.8 | H51: =+G51/G3 -> 0.016764504 | I51: =+IF(AND(G51>0,C51>0),G51/C51,"") -> 1.0600449 | K51: =+IF(AND(I51>0,E51>0),G51/E51,"")
B52: 외화환산이익 | C52: 0 | D52: 0 | E52: =E127+E201 -> 0 | F52: =+E52/$E$3 -> 0 | G52: =G127+G201 -> 0 | H52: =+G52/G3 -> 0 | I52: =+IF(AND(G52>0,C52>0),G52/C52,"") | K52: =+IF(AND(I52>0,E52>0),G52/E52,"")
B53: 전기오류수정이익 | C53: 0 | D53: 0 | E53: =E128+E202 -> 0 | F53: =+E53/$E$3 -> 0 | G53: =G128+G202 -> 0 | H53: =+G53/G3 -> 0 | I53: =+IF(AND(G53>0,C53>0),G53/C53,"") | K53: =+IF(AND(I53>0,E53>0),G53/E53,"")
B54: 유형자산처분이익 | C54: 0 | D54: 0 | E54: =E129+E203 -> 0 | F54: =+E54/$E$3 -> 0 | G54: =G129+G203 -> 0 | H54: =+G54/G3 -> 0 | I54: =+IF(AND(G54>0,C54>0),G54/C54,"") | K54: =+IF(AND(I54>0,E54>0),G54/E54,"")
B55: 이자수익 | C55: 37450.73 | D55: =C55/$C$3 -> 0.0015656798 | E55: =E130+E204 -> 0 | F55: =+E55/$E$3 -> 0 | G55: =G130+G204 -> 47013.07 | H55: =+G55/G4 -> 0.0023416347 | I55: =+IF(AND(G55>0,C55>0),G55/C55,"") -> 1.2553312 | K55: =+IF(AND(I55>0,E55>0),G55/E55,"")
B56: 잡이익 | C56: 0 | D56: =C56/$C$3 -> 0 | E56: =E131+E205 -> 0 | F56: =+E56/$E$3 -> 0 | G56: =G131+G205 -> 0 | H56: =+G56/G5 -> 0 | I56: =+IF(AND(G56>0,C56>0),G56/C56,"") | K56: =+IF(AND(I56>0,E56>0),G56/E56,"")
B57: - 영업외 비용 | C57: 1252721 | D57: =C57/$C$3 -> 0.052371742 | E57: =E132+E206 -> 553149.26 | F57: =+E57/$E$3 -> 0.022252348 | G57: =G132+G206 -> 1525513 | H57: =+G57/G3 -> 0.073663255 | I57: =+IF(AND(G57>0,C57>0),G57/C57,"") -> 1.2177595 | K57: =+IF(AND(I57>0,E57>0),G57/E57,"") -> 2.7578686
B58: 외환차손 | C58: 7065.2 | D58: =C58/$C$3 -> 0.0002953705 | E58: =E133+E207 -> 0 | F58: =+E58/$E$3 -> 0 | G58: =G133+G207 -> 172249.17 | H58: =+G58/G3 -> 0.0083174872 | I58: =+IF(AND(G58>0,C58>0),G58/C58,"") -> 24.379943 | K58: =+IF(AND(I58>0,E58>0),G58/E58,"")
B59: 기부금 | C59: 0 | D59: 0 | E59: =E134+E208 -> 0 | F59: =+E59/$E$3 -> 0 | G59: =G134+G208 -> 0 | H59: =+G59/G3 -> 0 | I59: =+IF(AND(G59>0,C59>0),G59/C59,"") | K59: =+IF(AND(I59>0,E59>0),G59/E59,"")
B60: 기타의대손상각비 | C60: 0 | D60: 0 | E60: =E135+E209 -> 0 | F60: =+E60/$E$3 -> 0 | G60: =G135+G209 -> 0 | H60: =+G60/G5 -> 0 | I60: =+IF(AND(G60>0,C60>0),G60/C60,"") | K60: =+IF(AND(I60>0,E60>0),G60/E60,"")
B61: 외화환산손실 | C61: 1018066.8 | D61: 0 | E61: =E136+E210 -> 0 | F61: =+E61/$E$3 -> 0 | G61: =G136+G210 -> 738427.72 | H61: =+G61/G3 -> 0.035656852 | I61: =+IF(AND(G61>0,C61>0),G61/C61,"") -> 0.72532342 | K61: =+IF(AND(I61>0,E61>0),G61/E61,"")
B62: 단기투자자산손실 | C62: 0 | D62: 0 | E62: =E137+E211 -> 0 | F62: =+E62/$E$3 -> 0 | G62: =G137+G211 -> 0 | H62: =+G62/G6 -> 0 | I62: =+IF(AND(G62>0,C62>0),G62/C62,"") | K62: =+IF(AND(I62>0,E62>0),G62/E62,"")
B63: 재고자산감모손실 | C63: 0 | D63: 0 | E63: =E138+E212 -> 0 | F63: =+E63/$E$3 -> 0 | G63: =G138+G212 -> 0 | H63: =+G63/G6 -> 0 | I63: =+IF(AND(G63>0,C63>0),G63/C63,"") | K63: =+IF(AND(I63>0,E63>0),G63/E63,"")
B64: 전기오류수정손실 | C64: 0 | D64: 0 | E64: =E139+E213 -> 0 | F64: =+E64/$E$3 -> 0 | G64: =G139+G213 -> 0 | H64: =+G64/G4 -> 0 | I64: =+IF(AND(G64>0,C64>0),G64/C64,"") | K64: =+IF(AND(I64>0,E64>0),G64/E64,"")
B65: 유형자산처분손실 | C65: 0 | D65: 0 | E65: =E140+E214 -> 0 | F65: =+E65/$E$3 -> 0 | G65: =G140+G214 -> 0 | H65: =+G65/G3 -> 0 | I65: =+IF(AND(G65>0,C65>0),G65/C65,"") | K65: =+IF(AND(I65>0,E65>0),G65/E65,"")
B66: 유형자산감액손실 | C66: 0 | E66: =E141+E215 -> 0 | F66: =+E66/$E$3 -> 0 | G66: =G141+G215 -> 0 | I66: =+IF(AND(G66>0,C66>0),G66/C66,"") | K66: =+IF(AND(I66>0,E66>0),G66/E66,"")
B67: 무형자산감액손실 | C67: 0 | D67: 0 | E67: =E142+E216 -> 0 | F67: =+E67/$E$3 -> 0 | G67: =G142+G216 -> 0 | H67: =+G67/G3 -> 0 | I67: =+IF(AND(G67>0,C67>0),G67/C67,"") | K67: =+IF(AND(I67>0,E67>0),G67/E67,"")
B68: 재고자산폐기손실 | C68: 706.58 | D68: 0 | E68: =E143+E217 -> 0 | F68: =+E68/$E$3 -> 0 | G68: =G143+G217 -> 2086.21 | H68: =+G68/G3 -> 0.00010073793 | I68: =+IF(AND(G68>0,C68>0),G68/C68,"") -> 2.9525461 | K68: =+IF(AND(I68>0,E68>0),G68/E68,"")
B69: 잡손실 | C69: 0 | D69: =C69/$C$3 -> 0 | E69: =E144+E218 -> 0 | F69: =+E69/$E$3 -> 0 | G69: =G144+G218 -> 28702.96 | H69: =+G69/G3 -> 0.0013859951 | I69: =+IF(AND(G69>0,C69>0),G69/C69,"") | K69: =+IF(AND(I69>0,E69>0),G69/E69,"")
B70: 이자비용 | C70: 226882.39 | D70: =C70/$C$3 -> 0.0094851336 | E70: =E145+E219 -> 553149.26 | F70: =+E70/$E$3 -> 0.022252348 | G70: =G145+G219 -> 584046.9 | H70: =+G70/G3 -> 0.028202183 | I70: =+IF(AND(G70>0,C70>0),G70/C70,"") -> 2.5742276 | K70: =+IF(AND(I70>0,E70>0),G70/E70,"") -> 1.0558577
B71: VI.법인세 차감전 이익 | C71: 1129633 | D71: =C71/$C$3 -> 0.047225876 | E71: =+E47+E49-E57 -> 348162.8 | F71: =+E71/$E$3 -> 0.014006056 | G71: =+G47+G49-G57 -> -223145.54 | H71: =+G71/G3 -> -0.010775147 | I71: =+IF(AND(G71>0,C71>0),G71/C71,"") | K71: =+IF(AND(I71>0,E71>0),G71/E71,"") -> -0.64092299
B72: 법인세비용 | C72: 282408.24 | D72: =C72/$C$3 -> 0.011806469 | F72: =+E72/$E$3 -> 0 | G72: =G71*0.25 -> -55786.385 | H72: =+G72/G3 -> -0.0026937868 | I72: =+IF(AND(G72>0,C72>0),G72/C72,"") | K72: =+IF(AND(I72>0,E72>0),G72/E72,"")
B73: VII.당기 순이익 | C73: 847224.73 | E73: =+E71-E72 -> 348162.8 | F73: =+E73/$E$3 -> 0.014006056 | G73: =+G71-G72 -> -167359.16 | I73: =+IF(AND(G73>0,C73>0),G73/C73,"") | K73: =+IF(AND(I73>0,E73>0),G73/E73,"") -> -0.48069224
B74: 순이익율(%) | C74: 0.035419407 | E74: =+E73/E3 -> 0.014006056 | F74: =+E74/$E$3 -> 5.6344222e-10 | G74: =+G73/G3 -> -0.0080813604 | I74: =+IF(AND(G74>0,C74>0),G74/C74,"") | K74: =+IF(AND(I74>0,E74>0),G74/E74,"") -> -0.57699042
B77: 전선사업부 손익계산서(WIRE)
B78: 구 분 | C78: [ 실 적 ] | D78: 매출구성비 | E78: [ 계 획 ] | F78: 매출구성비 | G78: [ 실 적 ] | H78: 매출구성비 | I78: [ 전월비 ] | J78: [ 계획비 ] | K78: [ 계획비 ]
B79: I. 총 매출액 | C79: 21533368 | D79: =C79/$C$3 -> 0.90023237 | E79: =+SUM(E80:E82) -> 22463255 | F79: =+E79/$E$79 -> 1 | G79: =+SUM(G80:G82) -> 18611474 | H79: =+G79/$G$79 -> 1 | I79: =+IF(AND(G79>0,C79>0),G79/C79,"") -> 0.86430855 | K79: =+IF(AND(I79>0,E79>0),G79/E79,"") -> 0.82852969
B80: 제품매출 | C80: 20884670 | D80: =C80/$C$3 -> 0.87311265 | E80: 21287462 | F80: =+E80/$E$79 -> 0.94765704 | G80: 17979224 | H80: =+G80/$G$79 -> 0.96602902 | I80: =+IF(AND(G80>0,C80>0),G80/C80,"") -> 0.8608814 | K80: =+IF(AND(I80>0,E80>0),G80/E80,"") -> 0.84459218
B81: 상품매출 | C81: 389149.87 | D81: =C81/$C$3 -> 0.016268951 | E81: 914402.51 | F81: =+E81/$E$79 -> 0.040706589 | G81: 426644.34 | H81: =+G81/$G$79 -> 0.022923727 | I81: =+IF(AND(G81>0,C81>0),G81/C81,"") -> 1.0963497 | K81: =+IF(AND(I81>0,E81>0),G81/E81,"") -> 0.46658265
B82: 기타매출 | C82: 259547.99 | D82: =C82/$C$3 -> 0.010850764 | E82: 261390.66 | F82: =+E82/$E$79 -> 0.011636366 | G82: 205605.65 | H82: =+G82/$G$79 -> 0.011047252 | I82: =+IF(AND(G82>0,C82>0),G82/C82,"") -> 0.79216815 | K82: =+IF(AND(I82>0,E82>0),G82/E82,"") -> 0.78658375
B83: 내수 동중량(KG) | C83: 177767.89 | E83: 213392.61 | G83: 150347.77 | I83: =+IF(AND(G83>0,C83>0),G83/C83,"") -> 0.84575325 | K83: =+IF(AND(I83>0,E83>0),G83/E83,"") -> 0.70455939
B84: B/B 동중량(KG) | C84: 72101.08 | E84: 79619.752 | G84: 67623.24 | I84: =+IF(AND(G84>0,C84>0),G84/C84,"") -> 0.93789497 | K84: =+IF(AND(I84>0,E84>0),G84/E84,"") -> 0.84932743
B85: II.총 매출원가 | C85: 17807867 | D85: =C85/$C$3 -> 0.74448264 | E85: =+E86+E87+E90 -> 19277280 | F85: =+E85/$E$79 -> 0.85816949 | G85: =+G86+G87+G90+G88+G89 -> 16007928 | H85: =+G85/G79 -> 0.86011072 | I85: =+IF(AND(G85>0,C85>0),G85/C85,"") -> 0.8989245 | K85: =+IF(AND(I85>0,E85>0),G85/E85,"") -> 0.83040387
B86: 제품매출원가 | C86: 17581601 | D86: =C86/$C$3 -> 0.73502326 | E86: 18386317 | F86: =+E86/$E$79 -> 0.81850635 | G86: 15512139 | H86: =+G86/$G$79 -> 0.83347179 | I86: =+IF(AND(G86>0,C86>0),G86/C86,"") -> 0.88229386 | K86: =+IF(AND(I86>0,E86>0),G86/E86,"") -> 0.8436784
B87: 상품매출원가 | C87: 375973.11 | D87: =C87/$C$3 -> 0.015718078 | E87: 755314.88 | F87: =+E87/$E$79 -> 0.033624462 | G87: 454276.3 | H87: =+G87/$G$79 -> 0.0244084 | I87: =+IF(AND(G87>0,C87>0),G87/C87,"") -> 1.2082681 | K87: =+IF(AND(I87>0,E87>0),G87/E87,"") -> 0.60143962
B88: 반제품매출원가 | E88: 0 | F88: =+E88/$E$79 -> 0
B89: 기타매출원가 | C89: -159006.69 | E89: 0 | F89: =+E89/$E$79 -> 0 | G89: 10700.47
B90: 영업부가세 | C90: 9300 | D90: =C90/$C$3 -> 0.00038879942 | E90: 135648.48 | F90: =+E90/$E$79 -> 0.0060386831 | G90: 30812.89 | H90: =+G90/$G$79 -> 0.0016555857 | I90: =+IF(AND(G90>0,C90>0),G90/C90,"") -> 3.313214 | K90: =+IF(AND(I90>0,E90>0),G90/E90,"") -> 0.22715249
B91: III.매출 총이익 | C91: 3725500.6 | E91: =+E79-E85 -> 3185974.9 | G91: =+G79-G85 -> 2603545.7 | I91: =+IF(AND(G91>0,C91>0),G91/C91,"") -> 0.69884453 | K91: =+IF(AND(I91>0,E91>0),G91/E91,"") -> 0.81718964
B92: 매출총이익율(%) | C92: 0.17301059 | E92: =+E91/E79 -> 0.14183051 | G92: =+G91/G79 -> 0.13988928 | I92: =+IF(AND(G92>0,C92>0),G92/C92,"") -> 0.80855909 | K92: =+IF(AND(I92>0,E92>0),G92/E92,"") -> 0.98631305
B93: IV.판매관리비 | C93: 1704161.6 | D93: =C93/$C$3 -> 0.071244842 | E93: =+SUM(E94:E121) -> 2023458.1 | F93: =+E93/$E$79 -> 0.090078577 | G93: =+SUM(G94:G121) -> 1574031.8 | H93: =+G93/G79 -> 0.084573192 | I93: =+IF(AND(G93>0,C93>0),G93/C93,"") -> 0.92364 | K93: =+IF(AND(I93>0,E93>0),G93/E93,"") -> 0.77789196
B94: 급여 (52101000 - 工资板块) | C94: 332894.73 | D94: =C94/$C$3 -> 0.013917127 | E94: 334263.95 | F94: =+E94/E79 -> 0.014880477 | G94: 327284.29 | H94: =+G94/G79 -> 0.017585082 | I94: =+IF(AND(G94>0,C94>0),G94/C94,"") -> 0.9831465 | K94: =+IF(AND(I94>0,E94>0),G94/E94,"") -> 0.97911932
B95: 복리후생비 (52105000 - 福利费) | C95: 173318.96 | D95: =C95/$C$3 -> 0.0072458399 | E95: 329666.4 | F95: =+E95/E79 -> 0.014675807 | G95: 90536.01 | H95: =+G95/G79 -> 0.0048645266 | I95: =+IF(AND(G95>0,C95>0),G95/C95,"") -> 0.52236645 | K95: =+IF(AND(I95>0,E95>0),G95/E95,"") -> 0.27462917
B96: 여비교통비 (52106000 - 差旅交通费) | C96: 15755.55 | D96: =C96/$C$3 -> 0.00065868266 | E96: 9433.6475 | F96: =+E96/E79 -> 0.00041995906 | G96: 18937.98 | H96: =+G96/G79 -> 0.0010175433 | I96: =+IF(AND(G96>0,C96>0),G96/C96,"") -> 1.2019879 | K96: =+IF(AND(I96>0,E96>0),G96/E96,"") -> 2.0074929
B97: 접대비 (52107000 - 招待费) | C97: 366.15 | D97: =C97/$C$3 -> 1.530741e-05 | E97: 4818.6171 | F97: =+E97/E79 -> 0.00021451108 | G97: 1235 | H97: =+G97/G79 -> 6.6356915e-05 | I97: =+IF(AND(G97>0,C97>0),G97/C97,"") -> 3.3729346 | K97: =+IF(AND(I97>0,E97>0),G97/E97,"") -> 0.2562976
B98: 통신비 (52108000 - 通信费) | C98: 8290.11 | D98: =C98/$C$3 -> 0.00034657957 | E98: 6790.223 | F98: =+E98/E79 -> 0.00030228134 | G98: 5935.81 | H98: =+G98/G79 -> 0.00031893283 | I98: =+IF(AND(G98>0,C98>0),G98/C98,"") -> 0.71601101 | K98: =+IF(AND(I98>0,E98>0),G98/E98,"") -> 0.87417011
B99: 수도광열비 (52109000 - 水电气费) | C99: 1737.79 | D99: 0 | E99: 1529.8657 | F99: =+E99/E79 -> 6.8105254e-05 | G99: 2107.35 | H99: =+G99/G79 -> 0.00011322854 | I99: =+IF(AND(G99>0,C99>0),G99/C99,"") -> 1.2126609 | K99: =+IF(AND(I99>0,E99>0),G99/E99,"") -> 1.3774739
B100: 세금과공과 (52110000 - 税与费) | C100: 0 | D100: =C100/$C$3 -> 0 | E100: 0 | F100: =+E100/E79 -> 0 | G100: 0 | H100: =+G100/G79 -> 0 | I100: =+IF(AND(G100>0,C100>0),G100/C100,"") | K100: =+IF(AND(I100>0,E100>0),G100/E100,"")
B101: 감가상각비 (52111000 - 折旧费) | C101: 87052.36 | D101: =C101/$C$3 -> 0.0036393449 | E101: 86830.324 | F101: =+E101/E79 -> 0.0038654382 | G101: 87052.36 | H101: =+G101/G79 -> 0.004677349 | I101: =+IF(AND(G101>0,C101>0),G101/C101,"") -> 1 | K101: =+IF(AND(I101>0,E101>0),G101/E101,"") -> 1.0025571
B102: 지급임차료 (52112000 - 支付租金) | C102: 0 | D102: 0 | F102: =+E102/E79 -> 0 | H102: =+G102/G79 -> 0 | I102: =+IF(AND(G102>0,C102>0),G102/C102,"") | K102: =+IF(AND(I102>0,E102>0),G102/E102,"")
...

Sheet ★손익계산서 (월별)
B1: 2026년 월별 손익계산서 | D1: (단위: RMB) | P1: (단위: RMB)
B2: 구 분 | C2: 2026년 누계 | D2: 2025.12 | E2: 2026.01 | F2: 2026.02 | G2: 2026.03 | H2: 2026.04 | I2: 2026.05 | J2: 2026.06 | K2: 2026.07 | L2: 2026.08 | M2: 2026.09 | N2: 2026.10 | O2: 2026.11 | P2: 2026.12
B3: I. 총 매출액 | C3: =SUM(E3:P3) -> 44629068 | D3: =D4+D8+D12 -> 25693686 | E3: =E4+E8+E12 -> 23919789 | F3: =F4+F8+F12 -> 20709280 | G3: =G4+G8+G12 -> 0 | H3: =H4+H8+H12 -> 0 | I3: =I4+I8+I12 -> 0 | J3: =J4+J8+J12 -> 0 | K3: =K4+K8+K12 -> 0 | ... P3: =P4+P8+P12 -> 0
B4: 제품매출 | C4: =SUM(E4:P4) -> 43348121 | D4: =D81+D164 -> 25042763 | E4: =E81+E164 -> 23271091 | F4: =F81+F164 -> 20077030 | G4: =G81+G164 -> 0 | H4: =H81+H164 -> 0 | I4: =I81+I164 -> 0 | J4: =J81+J164 -> 0 | K4: =K81+K164 -> 0 | ... P4: =P81+P164 -> 0
B5: (사업부별) | C5: =SUM(E5:P5) -> 0
B6: 전선 | C6: =SUM(E6:P6) -> 38863894 | D6: =D81 -> 22841240 | E6: =E81 -> 20884670 | F6: =F81 -> 17979224 | G6: =G81 -> 0 | H6: =H81 -> 0 | I6: =I81 -> 0 | J6: =J81 -> 0 | K6: =K81 -> 0 | ... P6: =P81 -> 0
B7: 전장 | C7: =SUM(E7:P7) -> 4484226.5 | D7: =D164 -> 2201522.9 | E7: =E164 -> 2386420.7 | F7: =F164 -> 2097805.9 | G7: =G164 -> 0 | H7: =H164 -> 0 | I7: =I164 -> 0 | J7: =J164 -> 0 | K7: =K164 -> 0 | ... P7: =P164 -> 0
B8: 상품매출 | C8: =SUM(E8:P8) -> 815794.21 | D8: =SUM(D10:D11) -> 239827.8 | E8: =SUM(E10:E11) -> 389149.87 | F8: =SUM(F10:F11) -> 426644.34 | G8: =SUM(G10:G11) -> 0 | H8: =SUM(H10:H11) -> 0 | I8: =SUM(I10:I11) -> 0 | J8: =SUM(J10:J11) -> 0 | K8: =SUM(K10:K11) -> 0 | ... P8: =SUM(P10:P11) -> 0
B9: (사업부별) | C9: =SUM(E9:P9) -> 0
B10: 전선 | C10: =SUM(E10:P10) -> 815794.21 | D10: =D94 -> 239827.8 | E10: =E94 -> 389149.87 | F10: =F94 -> 426644.34 | G10: =G94 -> 0 | H10: =H94 -> 0 | I10: =I94 -> 0 | J10: =J94 -> 0 | K10: =K94 -> 0 | ... P10: =P94 -> 0
B11: 전장 | C11: =SUM(E11:P11) -> 0 | E11: 0
B12: 기타매출 | C12: =SUM(E12:P12) -> 465153.64 | D12: =D95+D170 -> 411095.75 | E12: =E95+E170 -> 259547.99 | F12: =F95+F170 -> 205605.65 | G12: =G95+G170 -> 0 | H12: =H95+H170 -> 0 | I12: =I95+I170 -> 0 | J12: =J95+J170 -> 0 | K12: =K95+K170 -> 0 | ... P12: =P95+P170 -> 0
B13: II.총 매출원가 | C13: =SUM(E13:P13) -> 38100129 | D13: =SUM(D14:D17) -> 22700123 | E13: =SUM(E14:E17) -> 20033439 | F13: =SUM(F14:F17) -> 18066689 | G13: =SUM(G14:G17) -> 0 | H13: =SUM(H14:H17) -> 0 | I13: =SUM(I14:I17) -> 0 | J13: =SUM(J14:J17) -> 0 | K13: =SUM(K14:K17) -> 0 | ... P13: =SUM(P14:P17) -> 0
B14: 제품매출원가 | C14: =SUM(E14:P14) -> 37378073 | D14: =D97+D172 -> 21988989 | E14: =E97+E172 -> 19807173 | F14: =F97+F172 -> 17570900 | G14: =G97+G172 -> 0 | H14: =H97+H172 -> 0 | I14: =I97+I172 -> 0 | J14: =J97+J172 -> 0 | K14: =K97+K172 -> 0 | ... P14: =P97+P172 -> 0
B15: 상품매출원가 | C15: =SUM(E15:P15) -> 830249.41 | D15: =D98+D173 -> 288860.99 | E15: =E98+E173 -> 375973.11 | F15: =F98+F173 -> 454276.3 | G15: =G98+G173 -> 0 | H15: =H98+H173 -> 0 | I15: =I98+I173 -> 0 | J15: =J98+J173 -> 0 | K15: =K98+K173 -> 0 | ... P15: =P98+P173 -> 0
B16: 기타매출원가 | C16: =SUM(E16:P16) -> -148306.22 | D16: =D99+D174 -> 2513.91 | E16: =E99+E174 -> -159006.69 | F16: =F99+F174 -> 10700.47 | G16: =G99+G174 -> 0 | H16: =H99+H174 -> 0 | I16: =I99+I174 -> 0 | J16: =J99+J174 -> 0 | K16: =K99+K174 -> 0 | ... P16: =P99+P174 -> 0
B17: 영업부가세 | C17: =SUM(E17:P17) -> 40112.89 | D17: =D100+D175 -> 419759.64 | E17: =E100+E175 -> 9300 | F17: =F100+F175 -> 30812.89 | G17: =G100+G175 -> 0 | H17: =H100+H175 -> 0 | I17: =I100+I175 -> 0 | J17: =J100+J175 -> 0 | K17: =K100+K175 -> 0 | ... P17: =P100+P175 -> 0
B18: III.매출 총이익 | C18: =+C3-C13 -> 6528939.9 | D18: =D3-D13 -> 2993562.7 | E18: =E3-E13 -> 3886349.5 | F18: =F3-F13 -> 2642590.4 | G18: =G3-G13 -> 0 | H18: =H3-H13 -> 0 | I18: =I3-I13 -> 0 | J18: =J3-J13 -> 0 | K18: =K3-K13 -> 0 | ... P18: =P3-P13 -> 0
B19: 매출총이익율(%) | C19: =+C18/C3 -> 0.14629344 | D19: =+D18/D3 -> 0.11650966 | E19: =+E18/E3 -> 0.16247424 | F19: =+F18/F3 -> 0.12760417 | G19: =+G18/G3 -> #DIV/0! | H19: =+H18/H3 -> #DIV/0! | I19: =+I18/I3 -> #DIV/0! | J19: =+J18/J3 -> #DIV/0! | ... P19: =+P18/P3 -> #DIV/0!
B20: IV.판매관리비 | C20: =SUM(E20:P20) -> 3603378.3 | D20: =SUM(D21:D47) -> 3005587 | E20: =SUM(E21:E47) -> 1868961.4 | F20: =SUM(F21:F47) -> 1734416.8 | G20: =SUM(G21:G47) -> 0 | H20: =SUM(H21:H47) -> 0 | I20: =SUM(I21:I47) -> 0 | J20: =SUM(J21:J47) -> 0 | K20: =SUM(K21:K47) -> 0 | ... P20: =SUM(P21:P47) -> 0
B21: 급여 | C21: =SUM(E21:P21) -> 707191.14 | D21: =D104+D179 -> 455188.93 | E21: =E104+E179 -> 356491.85 | F21: =F104+F179 -> 350699.29 | G21: =G104+G179 -> 0 | H21: =H104+H179 -> 0 | I21: =I104+I179 -> 0 | J21: =J104+J179 -> 0 | K21: =K104+K179 -> 0 | ... P21: =P104+P179 -> 0
B22: 복리후생비 | C22: =SUM(E22:P22) -> 310064.38 | D22: =D105+D180 -> 177065.75 | E22: =E105+E180 -> 204324.93 | F22: =F105+F180 -> 105739.45 | G22: =G105+G180 -> 0 | H22: =H105+H180 -> 0 | I22: =I105+I180 -> 0 | J22: =J105+J180 -> 0 | K22: =K105+K180 -> 0 | ... P22: =P105+P180 -> 0
B23: 여비교통비 | C23: =SUM(E23:P23) -> 44351.12 | D23: =D106+D181 -> 11187.54 | E23: =E106+E181 -> 18184.77 | F23: =F106+F181 -> 26166.35 | G23: =G106+G181 -> 0 | H23: =H106+H181 -> 0 | I23: =I106+I181 -> 0 | J23: =J106+J181 -> 0 | K23: =K106+K181 -> 0 | ... P23: =P106+P181 -> 0
B24: 접대비 | C24: =SUM(E24:P24) -> 1601.15 | D24: =D107+D182 -> 770 | E24: =E107+E182 -> 366.15 | F24: =F107+F182 -> 1235 | G24: =G107+G182 -> 0 | H24: =H107+H182 -> 0 | I24: =I107+I182 -> 0 | J24: =J107+J182 -> 0 | K24: =K107+K182 -> 0 | ... P24: =P107+P182 -> 0
B25: 통신비 | C25: =SUM(E25:P25) -> 15296.69 | D25: =D108+D183 -> 8847.53 | E25: =E108+E183 -> 8914.1 | F25: =F108+F183 -> 6382.59 | G25: =G108+G183 -> 0 | H25: =H108+H183 -> 0 | I25: =I108+I183 -> 0 | J25: =J108+J183 -> 0 | K25: =K108+K183 -> 0 | ... P25: =P108+P183 -> 0
B26: 수도광열비 | C26: =SUM(E26:P26) -> 4134.56 | D26: =D109+D184 -> 2115.84 | E26: =E109+E184 -> 1868.59 | F26: =F109+F184 -> 2265.97 | G26: =G109+G184 -> 0 | H26: =H109+H184 -> 0 | I26: =I109+I184 -> 0 | J26: =J109+J184 -> 0 | K26: =K109+K184 -> 0 | ... P26: =P109+P184 -> 0
B27: 세금과공과 | C27: =SUM(E27:P27) -> 1400 | D27: =D110+D185 -> 0 | E27: =E110+E185 -> 700 | F27: =F110+F185 -> 700 | G27: =G110+G185 -> 0 | H27: =H110+H185 -> 0 | I27: =I110+I185 -> 0 | J27: =J110+J185 -> 0 | K27: =K110+K185 -> 0 | ... P27: =P110+P185 -> 0
B28: 감가상각비 | C28: =SUM(E28:P28) -> 185490.34 | D28: =D111+D186 -> 93365.94 | E28: =E111+E186 -> 92745.17 | F28: =F111+F186 -> 92745.17 | G28: =G111+G186 -> 0 | H28: =H111+H186 -> 0 | I28: =I111+I186 -> 0 | J28: =J111+J186 -> 0 | K28: =K111+K186 -> 0 | ... P28: =P111+P186 -> 0
B29: 지급임차료 | C29: =SUM(E29:P29) -> 0 | D29: =D112+D187 -> 0 | E29: =E112+E187 -> 0 | F29: =F112+F187 -> 0 | G29: =G112+G187 -> 0 | H29: =H112+H187 -> 0 | I29: =I112+I187 -> 0 | J29: =J112+J187 -> 0 | K29: =K112+K187 -> 0 | ... P29: =P112+P187 -> 0
B30: 수선비 | C30: =SUM(E30:P30) -> 139276.85 | D30: =D113+D188 -> 57783.33 | E30: =E113+E188 -> 45699.75 | F30: =F113+F188 -> 93577.1 | G30: =G113+G188 -> 0 | H30: =H113+H188 -> 0 | I30: =I113+I188 -> 0 | J30: =J113+J188 -> 0 | K30: =K113+K188 -> 0 | ... P30: =P113+P188 -> 0
B31: 보험료 | C31: =SUM(E31:P31) -> 53168.33 | D31: =D114+D189 -> 26138.91 | E31: =E114+E189 -> 27342.49 | F31: =F114+F189 -> 25825.84 | G31: =G114+G189 -> 0 | H31: =H114+H189 -> 0 | I31: =I114+I189 -> 0 | J31: =J114+J189 -> 0 | K31: =K114+K189 -> 0 | ... P31: =P114+P189 -> 0
B32: 차량유지비 | C32: =SUM(E32:P32) -> 63372.58 | D32: =D115+D190 -> 36611.24 | E32: =E115+E190 -> 31447.37 | F32: =F115+F190 -> 31925.21 | G32: =G115+G190 -> 0 | H32: =H115+H190 -> 0 | I32: =I115+I190 -> 0 | J32: =J115+J190 -> 0 | K32: =K115+K190 -> 0 | ... P32: =P115+P190 -> 0
... B47: 잡비 | C47: =SUM(E47:P47) -> 5000 | D47: =D130+D205 -> 0 | E47: =E130+E205 -> 5000 | F47: =F130+F205 -> 0 | G47: =G130+G205 -> 0 | H47: =H130+H205 -> 0 | I47: =I130+I205 -> 0 | J47: =J130+J205 -> 0 | K47: =K130+K205 -> 0 | ... P47: =P130+P205 -> 0
B48: V.영업 이익 | C48: =SUM(E48:P48) -> 2925561.6 | D48: =D3-D13-D20 -> -12024.33 | E48: =E3-E13-E20 -> 2017388.1 | F48: =F3-F13-F20 -> 908173.55 | G48: =G3-G13-G20 -> 0 | H48: =H3-H13-H20 -> 0 | I48: =I3-I13-I20 -> 0 | J48: =J3-J13-J20 -> 0 | K48: =K3-K13-K20 -> 0 | ... P48: =P3-P13-P20 -> 0
B49: 영업이익율(%) | C49: =+C48/C3 -> 0.065552827 | D49: =+D48/D3 -> -0.00046798774 | E49: =+E48/E3 -> 0.084339711 | F49: =+F48/F3 -> 0.043853459 | G49: =+G48/G3 -> #DIV/0! | H49: =+H48/H3 -> #DIV/0! | I49: =+I48/I3 -> #DIV/0! | J49: =+J48/J3 -> #DIV/0! | ... P49: =+P48/P3 -> #DIV/0!
B50: - 영업외 수익 | C50: =SUM(E50:P50) -> 759159.79 | D50: =SUM(D51:D57) -> 2489457.8 | E50: =SUM(E51:E57) -> 364965.92 | F50: =SUM(F51:F57) -> 394193.87 | G50: =SUM(G51:G57) -> 0 | H50: =SUM(H51:H57) -> 0 | I50: =SUM(I51:I57) -> 0 | J50: =SUM(J51:J57) -> 0 | K50: =SUM(K51:K57) -> 0 | ... P50: =SUM(P51:P57) -> 0
B51: 단기투자자산익 | C51: =SUM(E51:P51) -> 0 | D51: =D134+D210 -> 0 | E51: =E134+E210 -> 0 | F51: =F134+F210 -> 0 | G51: =G134+G210 -> 0 | H51: =H134+H210 -> 0 | I51: =I134+I210 -> 0 | J51: =J134+J210 -> 0 | K51: =K134+K210 -> 0 | ... P51: =P134+P210 -> 0
B52: 외환차익 | C52: =SUM(E52:P52) -> 674695.99 | D52: =D135+D211 -> 1839249.6 | E52: =E135+E211 -> 327515.19 | F52: =F135+F211 -> 347180.8 | G52: =G135+G211 -> 0 | H52: =H135+H211 -> 0 | I52: =I135+I211 -> 0 | J52: =J135+J211 -> 0 | K52: =K135+K211 -> 0 | ... P52: =P135+P211 -> 0
B53: 외화환산이익 | C53: =SUM(E53:P53) -> 0 | D53: =D136+D212 -> 0 | E53: =E136+E212 -> 0 | F53: =F136+F212 -> 0 | G53: =G136+G212 -> 0 | H53: =H136+H212 -> 0 | I53: =I136+I212 -> 0 | J53: =J136+J212 -> 0 | K53: =K136+K212 -> 0 | ... P53: =P136+P212 -> 0
B54: 전기오류수정이익 | C54: =SUM(E54:P54) -> 0 | D54: =D137+D213 -> 0 | E54: =E137+E213 -> 0 | F54: =F137+F213 -> 0 | G54: =G137+G213 -> 0 | H54: =H137+H213 -> 0 | I54: =I137+I213 -> 0 | J54: =J137+J213 -> 0 | K54: =K137+K213 -> 0 | ... P54: =P137+P213 -> 0
B55: 유형자산처분이익 | C55: =SUM(E55:P55) -> 0 | D55: =D138+D214 -> 0 | E55: =E138+E214 -> 0 | F55: =F138+F214 -> 0 | G55: =G138+G214 -> 0 | H55: =H138+H214 -> 0 | I55: =I138+I214 -> 0 | J55: =J138+J214 -> 0 | K55: =K138+K214 -> 0 | ... P55: =P138+P214 -> 0
B56: 이자수익 | C56: =SUM(E56:P56) -> 84463.8 | D56: =D139+D215 -> 531507.18 | E56: =E139+E215 -> 37450.73 | F56: =F139+F215 -> 47013.07 | G56: =G139+G215 -> 0 | H56: =H139+H215 -> 0 | I56: =I139+I215 -> 0 | J56: =J139+J215 -> 0 | K56: =K139+K215 -> 0 | ... P56: =P139+P215 -> 0
B57: 잡이익 | C57: =SUM(E57:P57) -> 0 | D57: =D140+D216 -> 118701.02 | E57: =E140+E216 -> 0 | F57: =F140+F216 -> 0 | G57: =G140+G216 -> 0 | H57: =H140+H216 -> 0 | I57: =I140+I216 -> 0 | J57: =J140+J216 -> 0 | K57: =K140+K216 -> 0 | ... P57: =P140+P216 -> 0
B58: - 영업외 비용 | C58: =SUM(E58:P58) -> 2778234 | D58: =SUM(D59:D71) -> 1689736.5 | E58: =SUM(E59:E71) -> 1252721 | F58: =SUM(F59:F71) -> 1525513 | G58: =SUM(G59:G71) -> 0 | H58: =SUM(H59:H71) -> 0 | I58: =SUM(I59:I71) -> 0 | J58: =SUM(J59:J71) -> 0 | K58: =SUM(K59:K71) -> 0 | ... P58: =SUM(P59:P71) -> 0
B59: 외환차손 | C59: =SUM(E59:P59) -> 179314.37 | D59: =D142+D218 -> 245563.05 | E59: =E142+E218 -> 7065.2 | F59: =F142+F218 -> 172249.17 | G59: =G142+G218 -> 0 | H59: =H142+H218 -> 0 | I59: =I142+I218 -> 0 | J59: =J142+J218 -> 0 | K59: =K142+K218 -> 0 | ... P59: =P142+P218 -> 0
B60: 기부금 | C60: =SUM(E60:P60) -> 0 | D60: =D143+D219 -> 0 | E60: =E143+E219 -> 0 | F60: =F143+F219 -> 0 | G60: =G143+G219 -> 0 | H60: =H143+H219 -> 0 | I60: =I143+I219 -> 0 | J60: =J143+J219 -> 0 | K60: =K143+K219 -> 0 | ... P60: =P143+P219 -> 0
B61: 기타의대손상각비 | C61: =SUM(E61:P61) -> 0 | D61: =D144+D220 -> 0 | E61: =E144+E220 -> 0 | F61: =F144+F220 -> 0 | G61: =G144+G220 -> 0 | H61: =H144+H220 -> 0 | I61: =I144+I220 -> 0 | J61: =J144+J220 -> 0 | K61: =K144+K220 -> 0 | ... P61: =P144+P220 -> 0
B62: 외화환산손실 | C62: =SUM(E62:P62) -> 1756494.5 | D62: =D145+D221 -> 805057.38 | E62: =E145+E221 -> 1018066.8 | F62: =F145+F221 -> 738427.72 | G62: =G145+G221 -> 0 | H62: =H145+H221 -> 0 | I62: =I145+I221 -> 0 | J62: =J145+J221 -> 0 | K62: =K145+K221 -> 0 | ... P62: =P145+P221 -> 0
B63: 단기투자자산손실 | C63: =SUM(E63:P63) -> 0 | D63: =D146+D222 -> 0 | E63: =E146+E222 -> 0 | F63: =F146+F222 -> 0 | G63: =G146+G222 -> 0 | H63: =H146+H222 -> 0 | I63: =I146+I222 -> 0 | J63: =J146+J222 -> 0 | K63: =K146+K222 -> 0 | ... P63: =P146+P222 -> 0
B64: 재고자산감모손실 | C64: =SUM(E64:P64) -> 0 | D64: =D147+D223 -> 0 | E64: =E147+E223 -> 0 | F64: =F147+F223 -> 0 | G64: =G147+G223 -> 0 | H64: =H147+H223 -> 0 | I64: =I147+I223 -> 0 | J64: =J147+J223 -> 0 | K64: =K147+K223 -> 0 | ... P64: =P147+P223 -> 0
B65: 전기오류수정손실 | C65: =SUM(E65:P65) -> 0 | D65: =D148+D224 -> 0 | E65: =E148+E224 -> 0 | F65: =F148+F224 -> 0 | G65: =G148+G224 -> 0 | H65: =H148+H224 -> 0 | I65: =I148+I224 -> 0 | J65: =J148+J224 -> 0 | K65: =K148+K224 -> 0 | ... P65: =P148+P224 -> 0
B66: 유형자산처분손실 | C66: =SUM(E66:P66) -> 0 | D66: =D149+D225 -> 0 | E66: =E149+E225 -> 0 | F66: =F149+F225 -> 0 | G66: =G149+G225 -> 0 | H66: =H149+H225 -> 0 | I66: =I149+I225 -> 0 | J66: =J149+J225 -> 0 | K66: =K149+K225 -> 0 | ... P66: =P149+P225 -> 0
B67: 유형자산감액손실 | C67: =SUM(E67:P67) -> 0 | D67: =D150+D226 -> 0 | E67: =E150+E226 -> 0 | F67: =F150+F226 -> 0 | G67: =G150+G226 -> 0 | H67: =H150+H226 -> 0 | I67: =I150+I226 -> 0 | J67: =J150+J226 -> 0 | K67: =K150+K226 -> 0 | ... P67: =P150+P226 -> 0
B68: 무형자산감액손실 | C68: =SUM(E68:P68) -> 0 | D68: =D151+D227 -> 0 | E68: =E151+E227 -> 0 | F68: =F151+F227 -> 0 | G68: =G151+G227 -> 0 | H68: =H151+H227 -> 0 | I68: =I151+I227 -> 0 | J68: =J151+J227 -> 0 | K68: =K151+K227 -> 0 | ... P68: =P151+P227 -> 0
B69: 재고자산폐기손실 | C69: =SUM(E69:P69) -> 2792.79 | D69: =D152+D228 -> 184558.56 | E69: =E152+E228 -> 706.58 | F69: =F152+F228 -> 2086.21 | G69: =G152+G228 -> 0 | H69: =H152+H228 -> 0 | I69: =I152+I228 -> 0 | J69: =J152+J228 -> 0 | K69: =K152+K228 -> 0 | ... P69: =P152+P228 -> 0
B70: 잡손실 | C70: =SUM(E70:P70) -> 28702.96 | D70: =D153+D229 -> 0 | E70: =E153+E229 -> 0 | F70: =F153+F229 -> 28702.96 | G70: =G153+G229 -> 0 | H70: =H153+H229 -> 0 | I70: =I153+I229 -> 0 | J70: =J153+J229 -> 0 | K70: =K153+K229 -> 0 | ... P70: =P153+P229 -> 0
B71: 이자비용 | C71: =SUM(E71:P71) -> 810929.29 | D71: =D154+D230 -> 454557.5 | E71: =E154+E230 -> 226882.39 | F71: =F154+F230 -> 584046.9 | G71: =G154+G230 -> 0 | H71: =H154+H230 -> 0 | I71: =I154+I230 -> 0 | J71: =J154+J230 -> 0 | K71: =K154+K230 -> 0 | ... P71: =P154+P230 -> 0
B72: VI.법인세 차감전 이익 | C72: =SUM(E72:P72) -> 906487.43 | D72: =D48+D50-D58 -> 787696.94 | E72: =E48+E50-E58 -> 1129633 | F72: =F48+F50-F58 -> -223145.54 | G72: =G48+G50-G58 -> 0 | H72: =H48+H50-H58 -> 0 | I72: =I48+I50-I58 -> 0 | J72: =J48+J50-J58 -> 0 | K72: =K48+K50-K58 -> 0 | ... P72: =P48+P50-P58 -> 0
B73: 법인세비용 | C73: =SUM(E73:P73) -> 226621.86 | D73: =D72*0.25 -> 196924.24 | E73: =E72*0.25 -> 282408.24 | F73: =F72*0.25 -> -55786.385 | G73: =G72*0.25 -> 0 | H73: =H72*0.25 -> 0 | I73: =I72*0.25 -> 0 | J73: =J72*0.25 -> 0 | K73: =K72*0.25 -> 0 | ... P73: =P72*0.25 -> 0
B74: VII.당기 순이익 | C74: =SUM(E74:P74) -> 679865.57 | D74: =D72-D73 -> 590772.71 | E74: =E72-E73 -> 847224.73 | F74: =F72-F73 -> -167359.16 | G74: =G72-G73 -> 0 | H74: =H72-H73 -> 0 | I74: =I72-I73 -> 0 | J74: =J72-J73 -> 0 | K74: =K72-K73 -> 0 | ... P74: =P72-P73 -> 0
B75: 순이익율(%) | C75: =+C74/C3 -> 0.015233694 | D75: =+D74/D3 -> 0.022992914 | E75: =+E74/E3 -> 0.035419407 | F75: =+F74/F3 -> -0.0080813604 | G75: =+G74/G3 -> #DIV/0! | H75: =+H74/H3 -> #DIV/0! | I75: =+I74/I3 -> #DIV/0! | J75: =+J74/J3 -> #DIV/0! | ... P75: =+P74/P3 -> #DIV/0!
B78: 2026年 业绩 _ 损益表 _电线 | F78: =F80*195 -> 3.6292374e+09
B79: 구 분 | C79: 2026년 누계 | D79: 2025.12 | E79: 2026.01 | F79: 2026.02 | G79: 2026.03 | H79: 2026.04 | I79: 2026.05 | J79: 2026.06 | K79: 2026.07 | L79: 2026.08 | M79: 2026.09 | N79: 2026.10 | O79: 2026.11 | P79: 2026.12
B80: I. 총 매출액 | C80: =SUM(E80:P80) -> 40144842 | D80: =D81+D94+D95 -> 23492163 | E80: =E81+E94+E95 -> 21533368 | F80: =F81+F94+F95 -> 18611474 | G80: =G81+G94+G95 -> 0 | H80: =H81+H94+H95 -> 0 | I80: =I81+I94+I95 -> 0 | J80: =J81+J94+J95 -> 0 | K80: =K81+K94+K95 -> 0 | ... P80: =P81+P94+P95 -> 0
B81: 제품매출 | C81: =SUM(E81:P81) -> 38863894 | D81: 22841240 | E81: 20884670 | F81: 17979224
B82: (업체별)
B83: └ 江苏京信 | C83: =SUM(E83:P83) -> 25726125 | D83: 14272847 | E83: 13881608 | F83: 11844517
B84: └ KSCI | C84: =SUM(E84:P84) -> 6952930.4 | D84: 4903544 | E84: 3887259.4 | F84: 3065671.1
B85: └경신(B/B) | C85: =SUM(E85:P85) -> 3411233.3 | D85: 2456560 | E85: 1830721.1 | F85: 1580512.2
B86: └ UZ KOJE | C86: =SUM(E86:P86) -> 152505.5 | D86: 139186.11 | E86: 152505.5
B87: └ 강소 아센텍 | C87: =SUM(E87:P87) -> 1768621 | E87: 559463.68 | F87: 1209157.3
B88: └ 성광다 | C88: =SUM(E88:P88) -> 339848.03 | E88: 120957.15 | F88: 218890.88
B89: └ 신진 | C89: =SUM(E89:P89) -> 431601.6 | D89: 1309292.2 | E89: 324228.2 | F89: 107373.4
B90: └ 기타 | E90: 530945.48 | F90: 391120.02
B91: (동량) | C91: =SUM(E91:P91) -> 467.83998 | D91: 300.00294 | E91: 249.86897 | F91: 217.97101
B92: OEM | C92: =SUM(E92:P92) -> 328.11566 | D92: 204.9299 | E92: 177.76789 | F92: 150.34777
B93: B/B | C93: =SUM(E93:P93) -> 139.72432 | D93: 95.07304 | E93: 72.10108 | F93: 67.62324
B94: 상품매출 | C94: =SUM(E94:P94) -> 815794.21 | D94: 239827.8 | E94: 389149.87 | F94: 426644.34
B95: 기타매출 | C95: =SUM(E95:P95) -> 465153.64 | D95: 411095.75 | E95: 259547.99 | F95: 205605.65
B96: II.총 매출원가 | C96: =SUM(E96:P96) -> 33815796 | D96: =SUM(D97:D100) -> 20612042 | E96: =SUM(E97:E100) -> 17807867 | F96: =SUM(F97:F100) -> 16007928 | G96: =SUM(G97:G100) -> 0 | H96: =SUM(H97:H100) -> 0 | I96: =SUM(I97:I100) -> 0 | J96: =SUM(J97:J100) -> 0 | K96: =SUM(K97:K100) -> 0 | ... P96: =SUM(P97:P100) -> 0
B97: 제품매출원가 | C97: =SUM(E97:P97) -> 33093740 | D97: 19900907 | E97: 17581601 | F97: 15512139
B98: 상품매출원가 | C98: =SUM(E98:P98) -> 830249.41 | D98: 288860.99 | E98: 375973.11 | F98: 454276.3
B99: 기타매출원가 | C99: =SUM(E99:P99) -> -148306.22 | D99: 2513.91 | E99: -159006.69 | F99: 10700.47
B100: 영업부가세 | C100: =SUM(E100:P100) -> 40112.89 | D100: 419759.64 | E100: 9300 | F100: 30812.89
B101: III.매출 총이익 | C101: =+C80-C96 -> 6329046.3 | D101: =D80-D96 -> 2880121.7 | E101: =E80-E96 -> 3725500.6 | F101: =F80-F96 -> 2603545.7 | G101: =G80-G96 -> 0 | H101: =H80-H96 -> 0 | I101: =I80-I96 -> 0 | J101: =J80-J96 -> 0 | K101: =K80-K96 -> 0 | ... P101: =P80-P96 -> 0
B102: 매출총이익율(%) | C102: =+C101/C80 -> 0.15765528 | D102: =D101/D80 -> 0.12259925 | E102: =E101/E80 -> 0.17301059 | F102: =F101/F80 -> 0.13988928 | G102: =G101/G80 -> #DIV/0! | H102: =H101/H80 -> #DIV/0! | I102: =I101/I80 -> #DIV/0! | J102: =J101/J80 -> #DIV/0! | K102: =K101/K80 -> #DIV/0! | ... P102: =P101/P80 -> #DIV/0!
B103: IV.판매관리비 | C103: =SUM(E103:P103) -> 3278193.3 | D103: =SUM(D104:D130) -> 2906706.1 | E103: =SUM(E104:E130) -> 1704161.6 | F103: =SUM(F104:F130) -> 1574031.8 | G103: =SUM(G104:G130) -> 0 | H103: =SUM(H104:H130) -> 0 | I103: =SUM(I104:I130) -> 0 | J103: =SUM(J104:J130) -> 0 | K103: =SUM(K104:K130) -> 0 | ... P103: =SUM(P104:P130) -> 0
B104: 급여 | C104: =SUM(E104:P104) -> 660179.02 | D104: 455188.93 | E104: 332894.73 | F104: 327284.29
B105: 복리후생비 | C105: =SUM(E105:P105) -> 263854.97 | D105: 166560.75 | E105: 173318.96 | F105: 90536.01
B106: 여비교통비 | C106: =SUM(E106:P106) -> 34693.53 | D106: 3099.2 | E106: 15755.55 | F106: 18937.98
B107: 접대비 | C107: =SUM(E107:P107) -> 1601.15 | E107: 366.15 | F107: 1235
B108: 통신비 | C108: =SUM(E108:P108) -> 14225.92 | D108: 8847.53 | E108: 8290.11 | F108: 5935.81
B109: 수도광열비 | C109: =SUM(E109:P109) -> 3845.14 | D109: 2115.84 | E109: 1737.79 | F109: 2107.35
B110: 세금과공과 | C110: =SUM(E110:P110) -> 0
B111: 감가상각비 | C111: =SUM(E111:P111) -> 174104.72 | D111: 93365.94 | E111: 87052.36 | F111: 87052.36
B112: 지급임차료 | C112: =SUM(E112:P112) -> 0
B113: 수선비 | C113: =SUM(E113:P113) -> 139276.85 | D113: 57783.33 | E113: 45699.75 | F113: 93577.1
B114: 보험료 | C114: =SUM(E114:P114) -> 53168.33 | D114: 26138.91 | E114: 27342.49 | F114: 25825.84
B115: 차량유지비 | C115: =SUM(E115:P115) -> 63372.58 | D115: 36611.24 | E115: 31447.37 | F115: 31925.21
B116: 경상연구개발비 | C116: =SUM(E116:P116) -> 186214 | D116: 94956.02 | E116: 186214
...

Sheet ★제조원가명세서
B1: ■ 2월 제조원가 명세서 | K1: (단위: RMB)
C2: [ 전 월 ] | D2: 구성비 | E2: [ 계 획 ] | F2: 구성비 | G2: [ 실 적 ] | H2: 구성비 | I2: [ 전월비 ] | J2: [ 계획비 ] | K2: 비 고
B3: 1.재료비 | C3: 17281645 | D3: =+C3/$C$38 -> 0.85917743 | E3: =E46+E89 -> 17750199 | F3: =+E3/$E$38 -> 0.85157313 | G3: =G4+G5+G6-G7 -> 12559793 | H3: =+G3/$G$38 -> 0.8314336 | I3: =+IF(AND(C3>0,G3>0),G3/C3,) -> 0.72677067 | J3: =+IF(AND(E3>0,G3>0),G3/E3,) -> 0.70758603
B4: (1) 기초 재고 | C4: 12762105 | D4: =+C4/$C$38 -> 0.63448313 | E4: =E47+E90 -> 1856927 | F4: =+E4/$E$38 -> 0.089086844 | G4: =G47+G90 -> 11024319 | H4: =+G4/$G$38 -> 0.72978824 | I4: =+IF(AND(C4>0,G4>0),G4/C4,) -> 0.86383233 | J4: =+IF(AND(E4>0,G4>0),G4/E4,) -> 5.9368615
B5: (2) 당기 매입액 | C5: 15543749 | D5: =+C5/$C$38 -> 0.77277586 | E5: =E48+E91 -> 0 | F5: =+E5/$E$38 -> 0 | G5: =G48+G91 -> 16059743 | H5: =+G5/$G$38 -> 1.0631235 | I5: =+IF(AND(C5>0,G5>0),G5/C5,) -> 1.0331963 | J5: =+IF(AND(E5>0,G5>0),G5/E5,) -> 0
B6: (3) 타계정대체 원재료 | C6: 110.3 | D6: =+C6/$E$38 -> 5.2916882e-06 | E6: =E49+E92 -> 0 | F6: =+E6/$E$38 -> 0 | G6: =G49+G92 -> 73.82 | H6: =+G6/$G$38 -> 4.886739e-06 | I6: =+IF(AND(C6>0,G6>0),G6/C6,) -> 0.66926564 | J6: =+IF(AND(E6>0,G6>0),G6/E6,) -> 0
B7: (4) 기말 재고액 | C7: 11024319 | D7: =+C7/$C$38 -> 0.54808704 | E7: =E50+E93 -> 0 | F7: =+E7/$E$38 -> 0 | G7: =G50+G93 -> 14524343 | H7: =+G7/$G$38 -> 0.96148298 | I7: =+IF(AND(C7>0,G7>0),G7/C7,) -> 1.3174822 | J7: =+IF(AND(E7>0,G7>0),G7/E7,) -> 0
B8: 2. 노무비 | C8: 855892.53 | D8: =+C8/$C$38 -> 0.04255171 | E8: =E9 -> 801134.12 | F8: =+E8/$E$38 -> 0.038434741 | G8: =+G9 -> 792246.67 | H8: =+G8/$G$38 -> 0.052445173 | I8: =+IF(AND(C8>0,G8>0),G8/C8,) -> 0.92563802 | J8: =+IF(AND(E8>0,G8>0),G8/E8,) -> 0.98890641
B9: 1) 급여 | C9: 855892.53 | D9: =+C9/$C$38 -> 0.04255171 | E9: =E52+E95 -> 801134.12 | F9: =+E9/$E$38 -> 0.038434741 | G9: =G52+G95 -> 792246.67 | H9: =+G9/$G$38 -> 0.052445173 | I9: =+IF(AND(C9>0,G9>0),G9/C9,) -> 0.92563802 | J9: =+IF(AND(E9>0,G9>0),G9/E9,) -> 0.98890641
B10: 3. 제조경비 | C10: 1976637.2 | D10: =+C10/$C$38 -> 0.098270858 | E10: =SUM(E11:E37) -> 2292677 | F10: =+E10/$E$38 -> 0.10999213 | G10: =+SUM(G11:G37) -> 1754149.1 | H10: =+G10/$G$38 -> 0.11612122 | I10: =+IF(AND(C10>0,G10>0),G10/C10,) -> 0.88744109 | J10: =+IF(AND(E10>0,G10>0),G10/E10,) -> 0.76510955
B11: 1) 복리후생비 (61301000 - 福利费) | C11: 96008.11 | D11: =+C11/$C$38 -> 0.0047731568 | E11: =E54+E97 -> 159588 | F11: =+E11/$E$38 -> 0.0076563004 | G11: =G54+G97 -> 94406.66 | H11: =+G11/$G$38 -> 0.0062495354 | I11: =+IF(AND(C11>0,G11>0),G11/C11,) -> 0.98331964 | J11: =+IF(AND(E11>0,G11>0),G11/E11,) -> 0.5915649
B12: 2) 여비교통비 (61302000 - 差旅交通费) | C12: 0 | D12: =+C12/$E$38 -> 0 | E12: =E55+E98 -> 0 | F12: =+E12/$E$38 -> 0 | G12: =G55+G98 -> 0 | H12: =+G12/$G$38 -> 0 | I12: =+IF(AND(C12>0,G12>0),G12/C12,) -> 0 | J12: =+IF(AND(E12>0,G12>0),G12/E12,) -> 0
B13: 3) 접대비 (61303000 - 招待费) | C13: 0 | D13: =+C13/$E$38 -> 0 | E13: =E56+E99 -> 0 | F13: =+E13/$E$38 -> 0 | G13: =G56+G99 -> 0 | H13: =+G13/$G$38 -> 0 | I13: =+IF(AND(C13>0,G13>0),G13/C13,) -> 0 | J13: =+IF(AND(E13>0,G13>0),G13/E13,) -> 0
B14: 4) 통신비 (61304000 - 通信费) | C14: 0 | D14: =+C14/$E$38 -> 0 | E14: =E57+E100 -> 0 | F14: =+E14/$E$38 -> 0 | G14: =G57+G100 -> 0 | H14: =+G14/$G$38 -> 0 | I14: =+IF(AND(C14>0,G14>0),G14/C14,) -> 0 | J14: =+IF(AND(E14>0,G14>0),G14/E14,) -> 0
B15: 5) 수도광열비 (61305000 - 水电气费) | C15: 323033.87 | D15: =+C15/$C$38 -> 0.016060011 | E15: =E58+E101 -> 339876.21 | F15: =+E15/$E$38 -> 0.016305702 | G15: =G58+G101 -> 328478.14 | H15: =+G15/$G$38 -> 0.021744608 | I15: =+IF(AND(C15>0,G15>0),G15/C15,) -> 1.0168536 | J15: =+IF(AND(E15>0,G15>0),G15/E15,) -> 0.96646406
B16: 6) 세금과공과 (61306000 - 税金以及附加) | C16: 0 | D16: =+C16/$C$38 -> 0 | E16: =E59+E102 -> 0 | F16: =+E16/$E$38 -> 0 | G16: =G59+G102 -> 0 | H16: =+G16/$G$38 -> 0 | I16: =+IF(AND(C16>0,G16>0),G16/C16,) -> 0 | J16: =+IF(AND(E16>0,G16>0),G16/E16,) -> 0
B17: 7) 감가상각비 (61307000 - 折旧费) | C17: 923164.16 | D17: =+C17/$C$38 -> 0.045896199 | E17: =E60+E103 -> 931228.21 | F17: =+E17/$E$38 -> 0.044676059 | G17: =G60+G103 -> 931848.98 | H17: =+G17/$G$38 -> 0.061686572 | I17: =+IF(AND(C17>0,G17>0),G17/C17,) -> 1.0094077 | J17: =+IF(AND(E17>0,G17>0),G17/E17,) -> 1.0006666
B18: 8) 지급임차료 (61308000 - 支付租金) | C18: 0 | D18: =+C18/$C$38 -> 0 | E18: =E61+E104 -> 0 | F18: =+E18/$E$38 -> 0 | G18: =G61+G104 -> 13805.31 | H18: =+G18/$G$38 -> 0.0009138844 | I18: =+IF(AND(C18>0,G18>0),G18/C18,) -> 0 | J18: =+IF(AND(E18>0,G18>0),G18/E18,) -> 0
B19: 9) 수선비 (维修费) | C19: 4481.31 | D19: =+C19/$C$38 -> 0.00022279363 | E19: =E62+E105 -> 56803.002 | F19: =+E19/$E$38 -> 0.0027251476 | G19: =G62+G105 -> 9666.09 | H19: =+G19/$G$38 -> 0.00063987617 | I19: =+IF(AND(C19>0,G19>0),G19/C19,) -> 2.1569787 | J19: =+IF(AND(E19>0,G19>0),G19/E19,) -> 0.17016865
B20: 10) 보험료 (61310000 - 保险费) | C20: 138836.4 | D20: =+C20/$C$38 -> 0.0069024159 | E20: =E63+E106 -> 241582.61 | F20: =+E20/$E$38 -> 0.011590026 | G20: =G63+G106 -> 136750.9 | H20: =+G20/$G$38 -> 0.0090526409 | I20: =+IF(AND(C20>0,G20>0),G20/C20,) -> 0.98497872 | J20: =+IF(AND(E20>0,G20>0),G20/E20,) -> 0.56606268
B21: 11) 차량유지비 (61311000 - 车辆维修费) | C21: 0 | D21: =+C21/$E$38 -> 0 | E21: =E64+E107 -> 0 | F21: =+E21/$E$38 -> 0 | G21: =G64+G107 -> 0 | H21: =+G21/$G$38 -> 0 | I21: =+IF(AND(C21>0,G21>0),G21/C21,) -> 0 | J21: =+IF(AND(E21>0,G21>0),G21/E21,) -> 0
B22: 12) 경상연구개발비 (61312000 - 经常研究开发费用) | C22: 0 | D22: =+C22/$E$38 -> 0 | E22: =E65+E108 -> 0 | F22: =+E22/$E$38 -> 0 | G22: =G65+G108 -> 0 | H22: =+G22/$G$38 -> 0 | I22: =+IF(AND(C22>0,G22>0),G22/C22,) -> 0 | J22: =+IF(AND(E22>0,G22>0),G22/E22,) -> 0
B23: 13) 운반비 (61313000 - 运费) | C23: 0 | D23: =+C23/$E$38 -> 0 | E23: =E66+E109 -> 0 | F23: =+E23/$E$38 -> 0 | G23: =G66+G109 -> 0 | H23: =+G23/$G$38 -> 0 | I23: =+IF(AND(C23>0,G23>0),G23/C23,) -> 0 | J23: =+IF(AND(E23>0,G23>0),G23/E23,) -> 0
B24: 14) 교육훈련비 (61314000 - 教育培训费) | C24: 0 | D24: =+C24/$E$38 -> 0 | E24: =E67+E110 -> 0 | F24: =+E24/$E$38 -> 0 | G24: =G67+G110 -> 0 | H24: =+G24/$G$38 -> 0 | I24: =+IF(AND(C24>0,G24>0),G24/C24,) -> 0 | J24: =+IF(AND(E24>0,G24>0),G24/E24,) -> 0
B25: 15) 도서인쇄비 (61315000 - 图书印刷费) | C25: 0 | D25: =+C25/$E$38 -> 0 | E25: =E68+E111 -> 0 | F25: =+E25/$E$38 -> 0 | G25: =G68+G111 -> 0 | H25: =+G25/$G$38 -> 0 | I25: =+IF(AND(C25>0,G25>0),G25/C25,) -> 0 | J25: =+IF(AND(E25>0,G25>0),G25/E25,) -> 0
B26: 16) 회의비 (61316000 - 会议费) | C26: 0 | D26: =+C26/$E$38 -> 0 | E26: =E69+E112 -> 0 | F26: =+E26/$E$38 -> 0 | G26: =G69+G112 -> 0 | H26: =+G26/$G$38 -> 0 | I26: =+IF(AND(C26>0,G26>0),G26/C26,) -> 0 | J26: =+IF(AND(E26>0,G26>0),G26/E26,) -> 0
B27: 17) 포장비 (61317000 - 包装费) | C27: 50982.75 | D27: =+C27/$C$38 -> 0.0025346677 | E27: =E70+E113 -> 122691.07 | F27: =+E27/$E$38 -> 0.0058861547 | G27: =G70+G113 -> 35575.23 | H27: =+G27/$G$38 -> 0.0023550103 | I27: =+IF(AND(C27>0,G27>0),G27/C27,) -> 0.69778955 | J27: =+IF(AND(E27>0,G27>0),G27/E27,) -> 0.28995779
B28: 18) 사무용품비 (61318000 - 办公用品) | C28: 92140.7 | D28: =+C28/$E$38 -> 0.0044204882 | E28: =E71+E114 -> 16410.221 | F28: =+E28/$E$38 -> 0.00078728714 | G28: =G71+G114 -> 0 | H28: =+G28/$G$38 -> 0 | I28: =+IF(AND(C28>0,G28>0),G28/C28,) -> 0 | J28: =+IF(AND(E28>0,G28>0),G28/E28,) -> 0
B29: 19) 소모품비 (61319000 - 消耗品费) | C29: 316738.59 | D29: =+C29/$C$38 -> 0.015747034 | E29: =E72+E115 -> 146173.69 | F29: =+E29/$E$38 -> 0.0070127433 | G29: =G72+G115 -> 18281.48 | H29: =+G29/$G$38 -> 0.0012101981 | I29: =+IF(AND(C29>0,G29>0),G29/C29,) -> 0.05771788 | J29: =+IF(AND(E29>0,G29>0),G29/E29,) -> 0.12506683
B30: 20) 소모공구 (61320000 - 消耗工具) | C30: 31251.33 | D30: =+C30/$E$38 -> 0.0014992955 | E30: =E73+E116 -> 278324.01 | F30: =+E30/$E$38 -> 0.01335271 | G30: =G73+G116 -> 155070.8 | H30: =+G30/$G$38 -> 0.010265382 | I30: =+IF(AND(C30>0,G30>0),G30/C30,) -> 4.9620544 | J30: =+IF(AND(E30>0,G30>0),G30/E30,) -> 0.55715926
B31: 21) 지급수수료 (61321000 - 支付手续费) | C31: 0 | D31: =+C31/$C$38 -> 0 | E31: =E74+E117 -> 0 | F31: =+E31/$E$38 -> 0 | G31: =G74+G117 -> 30265.49 | H31: =+G31/$G$38 -> 0.002003516 | I31: =+IF(AND(C31>0,G31>0),G31/C31,) -> 0 | J31: =+IF(AND(E31>0,G31>0),G31/E31,) -> 0
B32: 22) 보관료 (61322000 - 保管费) | C32: 0 | D32: =+C32/$E$38 -> 0 | E32: =E75+E118 -> 0 | F32: =+E32/$E$38 -> 0 | G32: =G75+G118 -> 0 | H32: =+G32/$G$38 -> 0 | I32: =+IF(AND(C32>0,G32>0),G32/C32,) -> 0 | J32: =+IF(AND(E32>0,G32>0),G32/E32,) -> 0
B33: 23) 광고선전비 (61323000 - 广告宣传费) | C33: 0 | D33: =+C33/$E$38 -> 0 | E33: =E76+E119 -> 0 | F33: =+E33/$E$38 -> 0 | G33: =G76+G119 -> 0 | H33: =+G33/$G$38 -> 0 | I33: =+IF(AND(C33>0,G33>0),G33/C33,) -> 0 | J33: =+IF(AND(E33>0,G33>0),G33/E33,) -> 0
B34: 24) 수출제비용 (61324000 - 出口收费) | C34: 0 | D34: =+C34/$E$38 -> 0 | E34: =E77+E120 -> 0 | F34: =+E34/$E$38 -> 0 | G34: =G77+G120 -> 0 | H34: =+G34/$G$38 -> 0 | I34: =+IF(AND(C34>0,G34>0),G34/C34,) -> 0 | J34: =+IF(AND(E34>0,G34>0),G34/E34,) -> 0
B35: 25) B/B PVC로스 관세 (61325000 - 下脚料补税) | C35: 0 | D35: =+C35/$C$38 -> 0 | E35: =E78+E121 -> 0 | F35: =+E35/$E$38 -> 0 | G35: =G78+G121 -> 0 | H35: =+G35/$G$38 -> 0 | I35: =+IF(AND(C35>0,G35>0),G35/C35,) -> 0 | J35: =+IF(AND(E35>0,G35>0),G35/E35,) -> 0
B36: 26) 외주가공비 (61326000 - 委托加工费) | C36: 0 | D36: =+C36/$E$38 -> 0 | E36: =E79+E122 -> 0 | F36: =+E36/$E$38 -> 0 | G36: =G79+G122 -> 0 | H36: =+G36/$G$38 -> 0 | I36: =+IF(AND(C36>0,G36>0),G36/C36,) -> 0 | J36: =+IF(AND(E36>0,G36>0),G36/E36,) -> 0
B37: 27) 잡비 (61390000 - 杂费) | C37: 0 | D37: =+C37/$C$38 -> 0 | E37: =E80+E123 -> 0 | F37: =+E37/$E$38 -> 0 | G37: =G80+G123 -> 0 | H37: =+G37/$G$38 -> 0 | I37: =+IF(AND(C37>0,G37>0),G37/C37,) -> 0 | J37: =+IF(AND(E37>0,G37>0),G37/E37,) -> 0
B38: 4. 당기총제조비용 | C38: 20114175 | D38: =+C38/$C$38 -> 1 | E38: =+E3+E8+E10 -> 20844010 | F38: =+E38/$E$38 -> 1 | G38: =+G3+G8+G10 -> 15106188 | H38: =+G38/$G$38 -> 1 | I38: =+IF(AND(C38>0,G38>0),G38/C38,) -> 0.75102203 | J38: =+IF(AND(E38>0,G38>0),G38/E38,) -> 0.72472564
B39: (1) 기초재공품 | C39: 15279246 | G39: =G82+G125 -> 15452656 | I39: =+IF(AND(C39>0,G39>0),G39/C39,) -> 1.0113493 | J39: =+IF(AND(E39>0,G39>0),G39/E39,) -> 0
B40: (2) 기말재공품 | C40: 14820140 | G40: =G83+G126 -> 16439431 | I40: =+IF(AND(C40>0,G40>0),G40/C40,) -> 1.1092628 | J40: =+IF(AND(E40>0,G40>0),G40/E40,) -> 0
B41: (3) 타계정대체 | C41: -989565.33 | G41: =G84+G127 -> -1231377.1 | I41: =+IF(AND(C41>0,G41>0),G41/C41,) -> 0 | J41: =+IF(AND(E41>0,G41>0),G41/E41,) -> 0
B42: 5. 당기제품제조원가 | C42: 21562846 | E42: =+E38+E39-E40-E41 -> 20844010 | G42: =+G38+G39-G40-G41 -> 15350791 | I42: =+IF(AND(C42>0,G42>0),G42/C42,) -> 0.71190929 | J42: =+IF(AND(E42>0,G42>0),G42/E42,) -> 0.73646053
B44: 2026年 业绩 _ 制造费用明细书 _电线
C45: [ 실 적 ] | D45: 구성비 | E45: [ 계 획 ] | F45: 구성비 | G45: [ 실 적 ] | H45: 구성비 | I45: [ 전월비 ] | J45: [ 계획비 ] | K45: 비 고
B46: 1.재료비 | C46: 15115502 | D46: =+C46/$C$38 -> 0.75148506 | E46: 15893272 | F46: =+E46/$E$38 -> 0.76248629 | G46: =G47+G48+G49-G50 -> 12422893 | H46: =+G46/$G$38 -> 0.82237112 | I46: =+IF(AND(C46>0,G46>0),G46/C46,) -> 0.82186441 | J46: =+IF(AND(E46>0,G46>0),G46/E46,) -> 0.7816448
B47: (1) 기초 재고 | C47: 8988559.7 | D47: =+C47/$C$38 -> 0.44687688 | F47: =+E47/$E$38 -> 0 | G47: 7590383.8 | H47: =+G47/$G$38 -> 0.5024685 | I47: =+IF(AND(C47>0,G47>0),G47/C47,) -> 0.8444494 | J47: =+IF(AND(E47>0,G47>0),G47/E47,) -> 0
B48: (2) 당기 매입액 | C48: 13717326 | D48: =+C48/$C$38 -> 0.68197309 | F48: =+E48/$E$38 -> 0 | G48: 14371564 | H48: =+G48/$G$38 -> 0.95136929 | I48: =+IF(AND(C48>0,G48>0),G48/C48,) -> 1.0476943 | J48: =+IF(AND(E48>0,G48>0),G48/E48,) -> 0
B49: (3) 타계정대체 원재료 | C49: 0 | D49: =+C49/$E$38 -> 0 | F49: =+E49/$E$38 -> 0 | H49: =+G49/$G$38 -> 0 | I49: =+IF(AND(C49>0,G49>0),G49/C49,) -> 0 | J49: =+IF(AND(E49>0,G49>0),G49/E49,) -> 0
B50: (4) 기말 재고액 | C50: 7590383.8 | D50: =+C50/$C$38 -> 0.37736491 | F50: =+E50/$E$38 -> 0 | G50: 9539054.5 | H50: =+G50/$G$38 -> 0.63146667 | I50: =+IF(AND(C50>0,G50>0),G50/C50,) -> 1.2567289 | J50: =+IF(AND(E50>0,G50>0),G50/E50,) -> 0
B51: 2. 노무비 | C51: 566644.14 | D51: =+C51/$C$38 -> 0.028171384 | E51: =E52 -> 567370.12 | F51: =+E51/$E$38 -> 0.027219816 | G51: =+G52 -> 504836.5 | H51: =+G51/$G$38 -> 0.033419185 | I51: =+IF(AND(C51>0,G51>0),G51/C51,) -> 0.89092336 | J51: =+IF(AND(E51>0,G51>0),G51/E51,) -> 0.88978337
B52: 1) 급여 | C52: 566644.14 | D52: =+C52/$C$38 -> 0.028171384 | E52: 567370.12 | F52: =+E52/$E$38 -> 0.027219816 | G52: 504836.5 | H52: =+G52/$G$38 -> 0.033419185 | I52: =+IF(AND(C52>0,G52>0),G52/C52,) -> 0.89092336 | J52: =+IF(AND(E52>0,G52>0),G52/E52,) -> 0.88978337
B53: 3. 제조경비 | C53: 1533608.3 | D53: =+C53/$C$38 -> 0.076245149 | E53: =SUM(E54:E80) -> 1925675.3 | F53: =+E53/$E$38 -> 0.092385068 | G53: =+SUM(G54:G80) -> 1467391.1 | H53: =+G53/$G$38 -> 0.097138406 | I53: =+IF(AND(C53>0,G53>0),G53/C53,) -> 0.95682262 | J53: =+IF(AND(E53>0,G53>0),G53/E53,) -> 0.76201377
B54: 1) 복리후생비 (61301000 - 福利费) | C54: 83417.23 | D54: =+C54/$C$38 -> 0.0041471863 | E54: 121760 | F54: =+E54/$E$38 -> 0.0058414864 | G54: 82611.02 | H54: =+G54/$G$38 -> 0.0054686872 | I54: =+IF(AND(C54>0,G54>0),G54/C54,) -> 0.99033521 | J54: =+IF(AND(E54>0,G54>0),G54/E54,) -> 0.67847421
B55: 2) 여비교통비 (61302000 - 差旅交通费) | C55: 0 | D55: =+C55/$E$38 -> 0 | F55: =+E55/$E$38 -> 0 | H55: =+G55/$G$38 -> 0 | I55: =+IF(AND(C55>0,G55>0),G55/C55,) -> 0 | J55: =+IF(AND(E55>0,G55>0),G55/E55,) -> 0
B56: 3) 접대비 (61303000 - 招待费) | C56: 0 | D56: =+C56/$E$38 -> 0 | F56: =+E56/$E$38 -> 0 | H56: =+G56/$G$38 -> 0 | I56: =+IF(AND(C56>0,G56>0),G56/C56,) -> 0 | J56: =+IF(AND(E56>0,G56>0),G56/E56,) -> 0
B57: 4) 통신비 (61304000 - 通信费) | C57: 0 | D57: =+C57/$E$38 -> 0 | F57: =+E57/$E$38 -> 0 | H57: =+G57/$G$38 -> 0 | I57: =+IF(AND(C57>0,G57>0),G57/C57,) -> 0 | J57: =+IF(AND(E57>0,G57>0),G57/E57,) -> 0
B58: 5) 수도광열비 (61305000 - 水电气费) | C58: 268524.53 | D58: =+C58/$C$38 -> 0.013350015 | E58: 266861.84 | F58: =+E58/$E$38 -> 0.012802807 | G58: 272868.13 | H58: =+G58/$G$38 -> 0.018063334 | I58: =+IF(AND(C58>0,G58>0),G58/C58,) -> 1.0161758 | J58: =+IF(AND(E58>0,G58>0),G58/E58,) -> 1.0225071
B59: 6) 세금과공과 (61306000 - 税金以及附加) | C59: 0 | D59: =+C59/$C$38 -> 0 | F59: =+E59/$E$38 -> 0 | H59: =+G59/$G$38 -> 0 | I59: =+IF(AND(C59>0,G59>0),G59/C59,) -> 0 | J59: =+IF(AND(E59>0,G59>0),G59/E59,) -> 0
B60: 7) 감가상각비 (61307000 - 折旧费) | C60: 789141.96 | D60: =+C60/$C$38 -> 0.039233126 | E60: 816405.65 | F60: =+E60/$E$38 -> 0.039167399 | G60: 797826.78 | H60: =+G60/$G$38 -> 0.052814566 | I60: =+IF(AND(C60>0,G60>0),G60/C60,) -> 1.0110054 | J60: =+IF(AND(E60>0,G60>0),G60/E60,) -> 0.97724309
B61: 8) 지급임차료 (61308000 - 支付租金) | C61: 0 | D61: =+C61/$C$38 -> 0 | F61: =+E61/$E$38 -> 0 | G61: 13805.31 | H61: =+G61/$G$38 -> 0.0009138844 | I61: =+IF(AND(C61>0,G61>0),G61/C61,) -> 0 | J61: =+IF(AND(E61>0,G61>0),G61/E61,) -> 0
B62: 9) 수선비 (维修费) | C62: 4481.31 | D62: =+C62/$C$38 -> 0.00022279363 | E62: 52160.685 | F62: =+E62/$E$38 -> 0.0025024304 | G62: 9666.09 | H62: =+G62/$G$38 -> 0.00063987617 | I62: =+IF(AND(C62>0,G62>0),G62/C62,) -> 2.1569787 | J62: =+IF(AND(E62>0,G62>0),G62/E62,) -> 0.18531371
B63: 10) 보험료 (61310000 - 保险费) | C63: 138836.4 | D63: =+C63/$C$38 -> 0.0069024159 | E63: 186127.4 | F63: =+E63/$E$38 -> 0.0089295391 | G63: 136750.9 | H63: =+G63/$G$38 -> 0.0090526409 | I63: =+IF(AND(C63>0,G63>0),G63/C63,) -> 0.98497872 | J63: =+IF(AND(E63>0,G63>0),G63/E63,) -> 0.73471665
B64: 11) 차량유지비 (61311000 - 车辆维修费) | C64: 0 | D64: =+C64/$E$38 -> 0 | F64: =+E64/$E$38 -> 0 | H64: =+G64/$G$38 -> 0 | I64: =+IF(AND(C64>0,G64>0),G64/C64,) -> 0 | J64: =+IF(AND(E64>0,G64>0),G64/E64,) -> 0
B65: 12) 경상연구개발비 (61312000 - 经常研究开发费用) | C65: 0 | D65: =+C65/$E$38 -> 0 | F65: =+E65/$E$38 -> 0 | H65: =+G65/$G$38 -> 0 | I65: =+IF(AND(C65>0,G65>0),G65/C65,) -> 0 | J65: =+IF(AND(E65>0,G65>0),G65/E65,) -> 0
B66: 13) 운반비 (61313000 - 运费) | C66: 0 | D66: =+C66/$E$38 -> 0 | F66: =+E66/$E$38 -> 0 | H66: =+G66/$G$38 -> 0 | I66: =+IF(AND(C66>0,G66>0),G66/C66,) -> 0 | J66: =+IF(AND(E66>0,G66>0),G66/E66,) -> 0
B67: 14) 교육훈련비 (61314000 - 教育培训费) | C67: 0 | D67: =+C67/$E$38 -> 0 | F67: =+E67/$E$38 -> 0 | H67: =+G67/$G$38 -> 0 | I67: =+IF(AND(C67>0,G67>0),G67/C67,) -> 0 | J67: =+IF(AND(E67>0,G67>0),G67/E67,) -> 0
B68: 15) 도서인쇄비 (61315000 - 图书印刷费) | C68: 0 | D68: =+C68/$E$38 -> 0 | F68: =+E68/$E$38 -> 0 | H68: =+G68/$G$38 -> 0 | I68: =+IF(AND(C68>0,G68>0),G68/C68,) -> 0 | J68: =+IF(AND(E68>0,G68>0),G68/E68,) -> 0
B69: 16) 회의비 (61316000 - 会议费) | C69: 0 | D69: =+C69/$E$38 -> 0 | F69: =+E69/$E$38 -> 0 | H69: =+G69/$G$38 -> 0 | I69: =+IF(AND(C69>0,G69>0),G69/C69,) -> 0 | J69: =+IF(AND(E69>0,G69>0),G69/E69,) -> 0
B70: 17) 포장비 (61317000 - 包装费) | C70: 50982.75 | D70: =+C70/$C$38 -> 0.0025346677 | E70: 99016.521 | F70: =+E70/$E$38 -> 0.0047503586 | G70: 35575.23 | H70: =+G70/$G$38 -> 0.0023550103 | I70: =+IF(AND(C70>0,G70>0),G70/C70,) -> 0.69778955 | J70: =+IF(AND(E70>0,G70>0),G70/E70,) -> 0.3592858
B71: 18) 사무용품비 (61318000 - 办公用品) | C71: 92140.7 | D71: =+C71/$E$38 -> 0.0044204882 | E71: 16410.221 | F71: =+E71/$E$38 -> 0.00078728714 | H71: =+G71/$G$38 -> 0 | I71: =+IF(AND(C71>0,G71>0),G71/C71,) -> 0 | J71: =+IF(AND(E71>0,G71>0),G71/E71,) -> 0
B72: 19) 소모품비 (61319000 - 消耗品费) | C72: 106083.38 | D72: =+C72/$C$38 -> 0.0052740608 | E72: 116462.86 | F72: =+E72/$E$38 -> 0.0055873538 | H72: =+G72/$G$38 -> 0 | I72: =+IF(AND(C72>0,G72>0),G72/C72,) -> 0 | J72: =+IF(AND(E72>0,G72>0),G72/E72,) -> 0
B73: 20) 소모공구 (61320000 - 消耗工具) | C73: 0 | D73: =+C73/$E$38 -> 0 | E73: 250470.1 | F73: =+E73/$E$38 -> 0.012016407 | G73: 118287.61 | H73: =+G73/$G$38 -> 0.0078304074 | I73: =+IF(AND(C73>0,G73>0),G73/C73,) -> 0 | J73: =+IF(AND(E73>0,G73>0),G73/E73,) -> 0.47226239
B74: 21) 지급수수료 (61321000 - 支付手续费) | C74: 0 | D74: =+C74/$C$38 -> 0 | F74: =+E74/$E$38 -> 0 | H74: =+G74/$G$38 -> 0 | I74: =+IF(AND(C74>0,G74>0),G74/C74,) -> 0 | J74: =+IF(AND(E74>0,G74>0),G74/E74,) -> 0
B75: 22) 보관료 (61322000 - 保管费) | C75: 0 | D75: =+C75/$E$38 -> 0 | F75: =+E75/$E$38 -> 0 | H75: =+G75/$G$38 -> 0 | I75: =+IF(AND(C75>0,G75>0),G75/C75,) -> 0 | J75: =+IF(AND(E75>0,G75>0),G75/E75,) -> 0
B76: 23) 광고선전비 (61323000 - 广告宣传费) | C76: 0 | D76: =+C76/$E$38 -> 0 | F76: =+E76/$E$38 -> 0 | H76: =+G76/$G$38 -> 0 | I76: =+IF(AND(C76>0,G76>0),G76/C76,) -> 0 | J76: =+IF(AND(E76>0,G76>0),G76/E76,) -> 0
B77: 24) 수출제비용 (61324000 - 出口收费) | C77: 0 | D77: =+C77/$E$38 -> 0 | F77: =+E77/$E$38 -> 0 | H77: =+G77/$G$38 -> 0 | I77: =+IF(AND(C77>0,G77>0),G77/C77,) -> 0 | J77: =+IF(AND(E77>0,G77>0),G77/E77,) -> 0
B78: 25) B/B PVC로스 관세 (61325000 - 下脚料补税) | C78: 0 | D78: =+C78/$C$38 -> 0 | F78: =+E78/$E$38 -> 0 | H78: =+G78/$G$38 -> 0 | I78: =+IF(AND(C78>0,G78>0),G78/C78,) -> 0 | J78: =+IF(AND(E78>0,G78>0),G78/E78,) -> 0
B79: 26) 외주가공비 (61326000 - 委托加工费) | C79: 0 | D79: =+C79/$E$38 -> 0 | F79: =+E79/$E$38 -> 0 | H79: =+G79/$G$38 -> 0 | I79: =+IF(AND(C79>0,G79>0),G79/C79,) -> 0 | J79: =+IF(AND(E79>0,G79>0),G79/E79,) -> 0
B80: 27) 잡비 (61390000 - 杂费) | C80: 0 | D80: =+C80/$C$38 -> 0 | F80: =+E80/$E$38 -> 0 | H80: =+G80/$G$38 -> 0 | I80: =+IF(AND(C80>0,G80>0),G80/C80,) -> 0 | J80: =+IF(AND(E80>0,G80>0),G80/E80,) -> 0
B81: 4. 당기총제조비용 | C81: 17215754 | D81: =+C81/$C$38 -> 0.85590159 | E81: =+E46+E51+E53 -> 18386317 | F81: =+E81/$E$38 -> 0.88209117 | G81: 14395121 | H81: =+G81/$G$38 -> 0.95292871 | I81: =+IF(AND(C81>0,G81>0),G81/C81,) -> 0.83615974 | J81: =+IF(AND(E81>0,G81>0),G81/E81,) -> 0.78292573
B82: (1) 기초재공품 | C82: 15279246 | G82: 14820140 | I82: =+IF(AND(C82>0,G82>0),G82/C82,) -> 0.96995231 | J82: =+IF(AND(E82>0,G82>0),G82/E82,) -> 0
B83: (2) 기말재공품 | C83: 14820140 | G83: 15683048 | I83: =+IF(AND(C83>0,G83>0),G83/C83,) -> 1.0582253 | J83: =+IF(AND(E83>0,G83>0),G83/E83,) -> 0
B84: (3) 타계정대체 | C84: -989565.33 | G84: -1231377.1 | I84: =+IF(AND(C84>0,G84>0),G84/C84,) -> 0 | J84: =+IF(AND(E84>0,G84>0),G84/E84,) -> 0
B85: 5. 당기제품제조원가 | C85: 18664426 | E85: =+E81+E82-E83-E84 -> 18386317 | G85: 14763590 | I85: =+IF(AND(C85>0,G85>0),G85/C85,) -> 0.79100159 | J85: =+IF(AND(E85>0,G85>0),G85/E85,) -> 0.80296616
B87: 2026年 业绩 _ 制造费用明细书 _EV
C88: [ 실 적 ] | D88: 구성비 | E88: [ 계 획 ] | F88: 구성비 | G88: [ 실 적 ] | H88: 구성비 | I88: [ 전월비 ] | J88: [ 계획비 ] | K88: 비 고
B89: 1.재료비 | C89: 2166143.2 | D89: =+C89/$C$38 -> 0.10769237 | E89: 1856927 | F89: =+E89/$E$38 -> 0.089086844 | G89: =G90+G91+G92-G93 -> 136899.61 | H89: =+G89/$G$38 -> 0.0090624853 | I89: =+IF(AND(C89>0,G89>0),G89/C89,) -> 0.063199704 | J89: =+IF(AND(E89>0,G89>0),G89/E89,) -> 0.073723742
B90: (1) 기초 재고 | C90: 3773545 | D90: =+C90/$C$38 -> 0.18760625 | E90: 1856927 | F90: =+E90/$E$38 -> 0.089086844 | G90: 3433934.8 | H90: =+G90/$G$38 -> 0.22731974 | I90: =+IF(AND(C90>0,G90>0),G90/C90,) -> 0.91000236 | J90: =+IF(AND(E90>0,G90>0),G90/E90,) -> 1.8492567
B91: (2) 당기 매입액 | C91: 1826422.8 | D91: =+C91/$C$38 -> 0.090802768 | E91: 0 | F91: =+E91/$E$38 -> 0 | G91: 1688179.5 | H91: =+G91/$G$38 -> 0.11175417 | I91: =+IF(AND(C91>0,G91>0),G91/C91,) -> 0.92430928 | J91: =+IF(AND(E91>0,G91>0),G91/E91,) -> 0
B92: (3) 타계정대체 원재료 | C92: 110.3 | D92: =+C92/$E$38 -> 5.2916882e-06 | F92: =+E92/$E$38 -> 0 | G92: 73.82 | H92: =+G92/$G$38 -> 4.886739e-06 | I92: =+IF(AND(C92>0,G92>0),G92/C92,) -> 0.66926564 | J92: =+IF(AND(E92>0,G92>0),G92/E92,) -> 0
B93: (4) 기말 재고액 | C93: 3433934.8 | D93: =+C93/$C$38 -> 0.17072213 | F93: =+E93/$E$38 -> 0 | G93: 4985288.5 | H93: =+G93/$G$38 -> 0.33001631 | I93: =+IF(AND(C93>0,G93>0),G93/C93,) -> 1.4517714 | J93: =+IF(AND(E93>0,G93>0),G93/E93,) -> 0
B94: 2. 노무비 | C94: 289248.39 | D94: =+C94/$C$38 -> 0.014380326 | E94: =E95 -> 233764 | F94: =+E94/$E$38 -> 0.011214925 | G94: =+G95 -> 287410.17 | H94: =+G94/$G$38 -> 0.019025989 | I94: =+IF(AND(C94>0,G94>0),G94/C94,) -> 0.99364484 | J94: =+IF(AND(E94>0,G94>0),G94/E94,) -> 1.2294886
B95: 1) 급여 | C95: 289248.39 | D95: =+C95/$C$38 -> 0.014380326 | E95: 233764 | F95: =+E95/$E$38 -> 0.011214925 | G95: 287410.17 | H95: =+G95/$G$38 -> 0.019025989 | I95: =+IF(AND(C95>0,G95>0),G95/C95,) -> 0.99364484 | J95: =+IF(AND(E95>0,G95>0),G95/E95,) -> 1.2294886
B96: 3. 제조경비 | C96: 443028.96 | D96: =+C96/$C$38 -> 0.022025709 | E96: =SUM(E97:E123) -> 367001.74 | F96: =+E96/$E$38 -> 0.017607061 | G96: =SUM(G97:G123) -> 286758.01 | H96: =+G96/$G$38 -> 0.018982817 | I96: =+IF(AND(C96>0,G96>0),G96/C96,) -> 0.64726696 | J96: =+IF(AND(E96>0,G96>0),G96/E96,) -> 0.78135327
B97: 1) 복리후생비 (61301000 - 福利费) | C97: 12590.88 | D97: =+C97/$C$38 -> 0.0006259705 | E97: 37828 | F97: =+E97/$E$38 -> 0.001814814 | G97: 11795.64 | H97: =+G97/$G$38 -> 0.0007808482 | I97: =+IF(AND(C97>0,G97>0),G97/C97,) -> 0.93684 | J97: =+IF(AND(E97>0,G97>0),G97/E97,) -> 0.31182299
B98: 2) 여비교통비 (61302000 - 差旅交通费) | C98: 0 | D98: =+C98/$E$38 -> 0 | F98: =+E98/$E$38 -> 0 | H98: =+G98/$G$38 -> 0 | I98: =+IF(AND(C98>0,G98>0),G98/C98,) -> 0 | J98: =+IF(AND(E98>0,G98>0),G98/E98,) -> 0
B99: 3) 접대비 (61303000 - 招待费) | C99: 0 | D99: =+C99/$E$38 -> 0 | F99: =+E99/$E$38 -> 0 | H99: =+G99/$G$38 -> 0 | I99: =+IF(AND(C99>0,G99>0),G99/C99,) -> 0 | J99: =+IF(AND(E99>0,G99>0),G99/E99,) -> 0
B100: 4) 통신비 (61304000 - 通信费) | C100: 0 | D100: =+C100/$E$38 -> 0 | F100: =+E100/$E$38 -> 0 | H100: =+G100/$G$38 -> 0 | I100: =+IF(AND(C100>0,G100>0),G100/C100,) -> 0 | J100: =+IF(AND(E100>0,G100>0),G100/E100,) -> 0
B101: 5) 수도광열비 (61305000 - 水电气费) | C101: 54509.34 | D101: =+C101/$C$38 -> 0.0027099963 | E101: 73014.372 | F101: =+E101/$E$38 -> 0.0035028947 | G101: 55610.01 | H101: =+G101/$G$38 -> 0.0036812734 | I101: =+IF(AND(C101>0,G101>0),G101/C101,) -> 1.0201923 | J101: =+IF(AND(E101>0,G101>0),G101/E101,) -> 0.76163102
B102: 6) 세금과공과 (61306000 - 税金以及附加) | C102: 0 | D102: =+C102/$C$38 -> 0 | F102: =+E102/$E$38 -> 0 | H102: =+G102/$G$38 -> 0 | I102: =+IF(AND(C102>0,G102>0),G102/C102,) -> 0 | J102: =+IF(AND(E102>0,G102>0),G102/E102,) -> 0
...

Sheet ★제조원가명세서 (월별)
B1: ■ 2026년 월별 제조원가 명세서 业绩 _ 制造费用明细书 _全体 | P1: (단위: RMB)
C2: 2026년 누계 | D2: 2025.12 | E2: 2026.01 | F2: 2026.02 | G2: 2026.03 | H2: 2026.04 | I2: 2026.05 | J2: 2026.06 | K2: 2026.07 | L2: 2026.08 | M2: 2026.09 | N2: 2026.10 | O2: 2026.11 | P2: 2026.12
B3: 1.재료비 | C3: =+C4+C5+C6-C7 -> 29841438 | D3: =D4+D5+D6-D7 -> 15473570 | E3: =E4+E5+E6-E7 -> 17281645 | F3: =F4+F5+F6-F7 -> 12559793 | G3: =G4+G5+G6-G7 -> 0 | H3: =H4+H5+H6-H7 -> 0 | I3: =I4+I5+I6-I7 -> 0 | J3: =J4+J5+J6-J7 -> 0 | K3: =K4+K5+K6-K7 -> 0 | L3: =L4+L5-L7+L6 -> 0 | M3: =M4+M5+M6-M7 -> 0 | N3: =N4+N5+N6-N7 -> 0 | O3: =O4+O5+O6-O7 -> 0 | P3: =P4+P5+P6-P7 -> 0
B4: (1) 기초 재고 | C4: =+E4 -> 12762105 | D4: =D48+D92 -> 8225102.1 | E4: =E48+E92 -> 12762105 | F4: =F48+F92 -> 11024319 | G4: =G48+G92 -> 0 | H4: =H48+H92 -> 0 | I4: =I48+I92 -> 0 | J4: =J48+J92 -> 0 | K4: =K48+K92 -> 0 | ... P4: =P48+P92 -> 0
B5: (2) 당기 매입액 | C5: =+SUM(E5:P5) -> 31603492 | D5: =D49+D93 -> 20010481 | E5: =E49+E93 -> 15543749 | F5: =F49+F93 -> 16059743 | G5: =G49+G93 -> 0 | H5: =H49+H93 -> 0 | I5: =I49+I93 -> 0 | J5: =J49+J93 -> 0 | K5: =K49+K93 -> 0 | ... P5: =P49+P93 -> 0
B6: (3) 타계정대체 원재료 | C6: =+SUM(E6:P6) -> 184.12 | D6: =D50+D94 -> 91.48 | E6: =E50+E94 -> 110.3 | F6: =F50+F94 -> 73.82 | G6: =G50+G94 -> 0 | H6: =H50+H94 -> 0 | I6: =I50+I94 -> 0 | J6: =J50+J94 -> 0 | K6: =K50+K94 -> 0 | ... P6: =P50+P94 -> 0
B7: (4) 기말 재고액 | C7: =★제조원가명세서!G7 -> 14524343 | D7: =D51+D95 -> 12762105 | E7: =E51+E95 -> 11024319 | F7: =F51+F95 -> 14524343 | G7: =G51+G95 -> 0 | H7: =H51+H95 -> 0 | I7: =I51+I95 -> 0 | J7: =J51+J95 -> 0 | K7: =K51+K95 -> 0 | ... P7: =P51+P95 -> 0
B8: 2. 노무비 | C8: =+C9 -> 1648139.2 | D8: =D9 -> 1205487 | E8: =E9 -> 855892.53 | F8: =F9 -> 792246.67 | G8: =G9 -> 0 | H8: =H9 -> 0 | I8: =I9 -> 0 | J8: =J9 -> 0 | K8: =K9 -> 0 | ... P8: =P9 -> 0
B9: 1) 급여 | C9: =+SUM(E9:P9) -> 1648139.2 | D9: =D53+D97 -> 1205487 | E9: =E53+E97 -> 855892.53 | F9: =F53+F97 -> 792246.67 | G9: =G53+G97 -> 0 | H9: =H53+H97 -> 0 | I9: =I53+I97 -> 0 | J9: =J53+J97 -> 0 | K9: =K53+K97 -> 0 | ... P9: =P53+P97 -> 0
B10: 3. 제조경비 | C10: =SUM(C11:C37) -> 3730786.3 | D10: =SUM(D11:D37) -> 2216851.9 | E10: =SUM(E11:E37) -> 1976637.2 | F10: =SUM(F11:F37) -> 1754149.1 | G10: =SUM(G11:G37) -> 0 | H10: =SUM(H11:H37) -> 0 | I10: =SUM(I11:I37) -> 0 | J10: =SUM(J11:J37) -> 0 | ... P10: =SUM(P11:P37) -> 0
B11: 1) 복리후생비 | C11: =+SUM(E11:P11) -> 190414.77 | D11: =D55+D99 -> 91167.88 | E11: =E55+E99 -> 96008.11 | F11: =F55+F99 -> 94406.66 | G11: =G55+G99 -> 0 | H11: =H55+H99 -> 0 | I11: =I55+I99 -> 0 | J11: =J55+J99 -> 0 | K11: =K55+K99 -> 0 | ... P11: =P55+P99 -> 0
B12: 2) 여비교통비 | C12: =+SUM(E12:P12) -> 0 | D12: =D56+D100 -> 0 | E12: =E56+E100 -> 0 | F12: =F56+F100 -> 0 | G12: =G56+G100 -> 0 | H12: =H56+H100 -> 0 | I12: =I56+I100 -> 0 | J12: =J56+J100 -> 0 | K12: =K56+K100 -> 0 | ... P12: =P56+P100 -> 0
B13: 3) 접대비 | C13: =+SUM(E13:P13) -> 0 | D13: =D57+D101 -> 0 | E13: =E57+E101 -> 0 | F13: =F57+F101 -> 0 | G13: =G57+G101 -> 0 | H13: =H57+H101 -> 0 | I13: =I57+I101 -> 0 | J13: =J57+J101 -> 0 | K13: =K57+K101 -> 0 | ... P13: =P57+P101 -> 0
B14: 4) 통신비 | C14: =+SUM(E14:P14) -> 0 | D14: =D58+D102 -> 0 | E14: =E58+E102 -> 0 | F14: =F58+F102 -> 0 | G14: =G58+G102 -> 0 | H14: =H58+H102 -> 0 | I14: =I58+I102 -> 0 | J14: =J58+J102 -> 0 | K14: =K58+K102 -> 0 | ... P14: =P58+P102 -> 0
B15: 5) 수도광열비 | C15: =+SUM(E15:P15) -> 651512.01 | D15: =D59+D103 -> 331897.29 | E15: =E59+E103 -> 323033.87 | F15: =F59+F103 -> 328478.14 | G15: =G59+G103 -> 0 | H15: =H59+H103 -> 0 | I15: =I59+I103 -> 0 | J15: =J59+J103 -> 0 | K15: =K59+K103 -> 0 | ... P15: =P59+P103 -> 0
B16: 6) 세금과공과 | C16: =+SUM(E16:P16) -> 0 | D16: =D60+D104 -> 0 | E16: =E60+E104 -> 0 | F16: =F60+F104 -> 0 | G16: =G60+G104 -> 0 | H16: =H60+H104 -> 0 | I16: =I60+I104 -> 0 | J16: =J60+J104 -> 0 | K16: =K60+K104 -> 0 | ... P16: =P60+P104 -> 0
B17: 7) 감가상각비 | C17: =+SUM(E17:P17) -> 1855013.1 | D17: =D61+D105 -> 897755.48 | E17: =E61+E105 -> 923164.16 | F17: =F61+F105 -> 931848.98 | G17: =G61+G105 -> 0 | H17: =H61+H105 -> 0 | I17: =I61+I105 -> 0 | J17: =J61+J105 -> 0 | K17: =K61+K105 -> 0 | ... P17: =P61+P105 -> 0
B18: 8) 지급임차료 | C18: =+SUM(E18:P18) -> 13805.31 | D18: =D62+D106 -> 0 | E18: =E62+E106 -> 0 | F18: =F62+F106 -> 13805.31 | G18: =G62+G106 -> 0 | H18: =H62+H106 -> 0 | I18: =I62+I106 -> 0 | J18: =J62+J106 -> 0 | K18: =K62+K106 -> 0 | ... P18: =P62+P106 -> 0
B19: 9) 수선비 | C19: =+SUM(E19:P19) -> 14147.4 | D19: =D63+D107 -> 12264.15 | E19: =E63+E107 -> 4481.31 | F19: =F63+F107 -> 9666.09 | G19: =G63+G107 -> 0 | H19: =H63+H107 -> 0 | I19: =I63+I107 -> 0 | J19: =J63+J107 -> 0 | K19: =K63+K107 -> 0 | ... P19: =P63+P107 -> 0
B20: 10) 보험료 | C20: =+SUM(E20:P20) -> 275587.3 | D20: =D64+D108 -> 124858.63 | E20: =E64+E108 -> 138836.4 | F20: =F64+F108 -> 136750.9 | G20: =G64+G108 -> 0 | H20: =H64+H108 -> 0 | I20: =I64+I108 -> 0 | J20: =J64+J108 -> 0 | K20: =K64+K108 -> 0 | ... P20: =P64+P108 -> 0
B21: 11) 차량유지비 | C21: =+SUM(E21:P21) -> 0 | D21: =D65+D109 -> 0 | E21: =E65+E109 -> 0 | F21: =F65+F109 -> 0 | G21: =G65+G109 -> 0 | H21: =H65+H109 -> 0 | I21: =I65+I109 -> 0 | J21: =J65+J109 -> 0 | K21: =K65+K109 -> 0 | ... P21: =P65+P109 -> 0
B22: 12) 경상연구개발비 | C22: =+SUM(E22:P22) -> 0 | D22: =D66+D110 -> 0 | E22: =E66+E110 -> 0 | F22: =F66+F110 -> 0 | G22: =G66+G110 -> 0 | H22: =H66+H110 -> 0 | I22: =I66+I110 -> 0 | J22: =J66+J110 -> 0 | K22: =K66+K110 -> 0 | ... P22: =P66+P110 -> 0
... B37: 27) 잡비 | C37: =+SUM(E37:P37) -> 0 | D37: =D81+D125 -> 0 | E37: =E81+E125 -> 0 | F37: =F81+F125 -> 0 | G37: =G81+G125 -> 0 | H37: =H81+H125 -> 0 | I37: =I81+I125 -> 0 | J37: =J81+J125 -> 0 | K37: =K81+K125 -> 0 | ... P37: =P81+P125 -> 0
B38: 4. 당기총제조비용 | C38: =+C3+C8+C10 -> 35220363 | D38: =D10+D8+D3 -> 18895908 | E38: =E10+E8+E3 -> 20114175 | F38: =F10+F8+F3 -> 15106188 | G38: =G10+G8+G3 -> 0 | H38: =H10+H8+H3 -> 0 | I38: =I10+I8+I3 -> 0 | J38: =J10+J8+J3 -> 0 | K38: =K10+K8+K3 -> 0 | ... P38: =P10+P8+P3 -> 0
B39: (1) 기초재공품 | C39: =+E39 -> 15940941 | D39: =D83+D127 -> 15745829 | E39: =E83+E127 -> 15940941 | F39: =F83+F127 -> 15452656 | G39: =G83+G127 -> 0 | H39: =H83+H127 -> 0 | I39: =I83+I127 -> 0 | J39: =J83+J127 -> 0 | K39: =K83+K127 -> 0 | ... P39: =P83+P127 -> 0
B40: (2) 기말재공품 | C40: =P40 -> 0 | D40: =D84+D128 -> 15940941 | E40: =E84+E128 -> 15452656 | F40: =F84+F128 -> 16439431 | G40: =G84+G128 -> 0 | H40: =H84+H128 -> 0 | I40: =I84+I128 -> 0 | J40: =J84+J128 -> 0 | K40: =K84+K128 -> 0 | ... P40: =P84+P128 -> 0
B41: (3) 타계정대체 | C41: =SUM(E41:P41) -> -2220942.5 | D41: =D85+D129 -> -1799980.5 | E41: =E85+E129 -> -989565.33 | F41: =F85+F129 -> -1231377.1 | G41: =G85+G129 -> 0 | H41: =H85+H129 -> 0 | I41: =I85+I129 -> 0 | J41: =J85+J129 -> 0 | K41: =K85+K129 -> 0 | ... P41: =P85+P129 -> 0
B42: 5. 당기제품제조원가 | C42: =+C38+C39-C40-C41 -> 53382247 | D42: =D38+D39-D40-D41 -> 20500777 | E42: =E38+E39-E40-E41 -> 21592026 | F42: =F38+F39-F40-F41 -> 15350791 | G42: =G38+G39-G40-G41 -> 0 | H42: =H38+H39-H40-H41 -> 0 | I42: =I38+I39-I40-I41 -> 0 | J42: =J38+J39-J40-J41 -> 0 | K42: =K38+K39-K40-K41 -> 0 | ... P42: =P38+P39-P40-P41 -> 0
F43: =F38+F39-F40-F41 -> 15350791
B45: 2026年 业绩 _ 制造费用明细书 _电线 | D45: =D52+D54 -> 2782020.9 | E45: =E52+E54 -> 2100252.4 | F45: =F52+F54 -> 1972227.6 | G45: =G52+G54 -> 0 | H45: =H52+H54 -> 0 | I45: =I52+I54 -> 0 | J45: =J52+J54 -> 0 | K45: =K52+K54 -> 0 | ... P45: =P52+P54 -> 0
C46: 2026년 누계 | D46: 2025.12 | E46: 2026.01 | F46: 2026.02 | G46: 2026.03 | H46: 2026.04 | I46: 2026.05 | J46: 2026.06 | K46: 2026.07 | L46: 2026.08 | M46: 2026.09 | N46: 2026.10 | O46: 2026.11 | P46: 2026.12
B47: 1.재료비 | C47: =+C48+C49+C50-C51 -> 27538395 | D47: =D48+D49-D51 -> 13158783 | E47: =E48+E49-E51 -> 15115502 | F47: =F48+F49-F51 -> 12422893 | G47: =G48+G49-G51 -> 0 | H47: =H48+H49-H51 -> 0 | I47: =I48+I49-I51 -> 0 | J47: =J48+J49-J51 -> 0 | K47: =K48+K49-K51 -> 0 | L47: =L48+L49-L51+L50 -> 0 | M47: =M48+M49-M51 -> 0 | N47: =N48+N49-N51 -> 0 | O47: =O48+O49-O51 -> 0 | P47: =P48+P49-P51 -> 0
B48: (1) 기초 재고 | C48: =+E48 -> 8988559.7 | D48: 5192448.5 | E48: 8988559.7 | F48: 7590383.8
B49: (2) 당기 매입액 | C49: =+SUM(E49:P49) -> 28088890 | D49: 16954895 | E49: 13717326 | F49: 14371564
B50: (3) 타계정대체 원재료 | C50: =+SUM(E50:P50) -> 0
B51: (4) 기말 재고액 | C51: =★제조원가명세서!G50 -> 9539054.5 | D51: 8988559.7 | E51: 7590383.8 | F51: 9539054.5
B52: 2. 노무비 | C52: =+C53 -> 1071480.6 | D52: =D53 -> 791905.67 | E52: =E53 -> 566644.14 | F52: =F53 -> 504836.5 | G52: =G53 -> 0 | H52: =H53 -> 0 | I52: =I53 -> 0 | J52: =J53 -> 0 | K52: =K53 -> 0 | ... P52: =P53 -> 0
B53: 1) 급여 | C53: =+SUM(E53:P53) -> 1071480.6 | D53: 791905.67 | E53: 566644.14 | F53: 504836.5 | Q53: =C53+O53*2.4 -> 1071480.6
B54: 3. 제조경비 | C54: =SUM(C55:C81) -> 3000999.3 | D54: =SUM(D55:D81) -> 1990115.2 | E54: =SUM(E55:E81) -> 1533608.3 | F54: =SUM(F55:F81) -> 1467391.1 | G54: =SUM(G55:G81) -> 0 | H54: =SUM(H55:H81) -> 0 | I54: =SUM(I55:I81) -> 0 | J54: =SUM(J55:J81) -> 0 | ... P54: =SUM(P55:P81) -> 0
B55: 1) 복리후생비 | C55: =+SUM(E55:P55) -> 166028.25 | D55: 79339.96 | E55: 83417.23 | F55: 82611.02
B56: 2) 여비교통비 | C56: =+SUM(E56:P56) -> 0
B57: 3) 접대비 | C57: =+SUM(E57:P57) -> 0
B58: 4) 통신비 | C58: =+SUM(E58:P58) -> 0
B59: 5) 수도광열비 | C59: =+SUM(E59:P59) -> 541392.66 | D59: 275840.85 | E59: 268524.53 | F59: 272868.13
B60: 6) 세금과공과 | C60: =+SUM(E60:P60) -> 0
B61: 7) 감가상각비 | C61: =+SUM(E61:P61) -> 1586968.7 | D61: 782932.92 | E61: 789141.96 | F61: 797826.78
B62: 8) 지급임차료 | C62: =+SUM(E62:P62) -> 13805.31 | F62: 13805.31
B63: 9) 수선비 | C63: =+SUM(E63:P63) -> 14147.4 | D63: 12264.15 | E63: 4481.31 | F63: 9666.09
B64: 10) 보험료 | C64: =+SUM(E64:P64) -> 275587.3 | D64: 124858.63 | E64: 138836.4 | F64: 136750.9
B65: 11) 차량유지비 | C65: =+SUM(E65:P65) -> 0
B66: 12) 경상연구개발비 | C66: =+SUM(E66:P66) -> 0
B67: 13) 운반비 | C67: =+SUM(E67:P67) -> 0
B68: 14) 교육훈련비 | C68: =+SUM(E68:P68) -> 0
B69: 15) 도서인쇄비 | C69: =+SUM(E69:P69) -> 0
B70: 16) 회의비 | C70: =+SUM(E70:P70) -> 0
B71: 17) 포장비 | C71: =+SUM(E71:P71) -> 86557.98 | D71: 44391.6 | E71: 50982.75 | F71: 35575.23
B72: 18) 사무용품비 | C72: =+SUM(E72:P72) -> 92140.7 | D72: 4956.33 | E72: 92140.7
B73: 19) 소모품비 | C73: =+SUM(E73:P73) -> 106083.38 | D73: 92241.78 | E73: 106083.38
B74: 20) 소모공구 | C74: =+SUM(E74:P74) -> 118287.61 | D74: 573289 | F74: 118287.61
B75: 21) 지급수수료 | C75: =+SUM(E75:P75) -> 0
B76: 22) 보관료 | C76: =+SUM(E76:P76) -> 0
B77: 23) 광고선전비 | C77: =+SUM(E77:P77) -> 0
B78: 24) 수출제비용 | C78: =+SUM(E78:P78) -> 0
B79: 25) B/B PVC로스 관세 | C79: =+SUM(E79:P79) -> 0
B80: 26) 외주가공비 | C80: =+SUM(E80:P80) -> 0
B81: 27) 잡비 | C81: =+SUM(E81:P81) -> 0
B82: 4. 당기총제조비용 | C82: =+C47+C52+C54 -> 31610875 | D82: =D54+D52+D47 -> 15940804 | E82: =E54+E52+E47 -> 17215754 | F82: =F54+F52+F47 -> 14395121 | G82: =G54+G52+G47 -> 0 | H82: =H54+H52+H47 -> 0 | I82: =I54+I52+I47 -> 0 | J82: =J54+J52+J47 -> 0 | K82: =K54+K52+K47 -> 0 | ... P82: =P54+P52+P47 -> 0
B83: (1) 기초재공품 | C83: =+E83 -> 15279246 | D83: 15175609 | E83: 15279246 | F83: 14820140
B84: (2) 기말재공품 | C84: =P84 -> 0 | D84: 15279246 | E84: 14820140 | F84: 15683048
B85: (3) 타계정대체 | C85: =SUM(E85:P85) -> -2220942.5 | D85: -1799980.5 | E85: -989565.33 | F85: =-1242077.59+10700.47 -> -1231377.1
B86: 5. 당기제품제조원가 | C86: =+C82+C83-C84-C85 -> 49111064 | D86: =D82+D83-D84-D85 -> 17637147 | E86: =E82+E83-E84-E85 -> 18664426 | F86: =F82+F83-F84-F85 -> 14763590 | G86: =G82+G83-G84-G85 -> 0 | H86: =H82+H83-H84-H85 -> 0 | I86: =I82+I83-I84-I85 -> 0 | J86: =J82+J83-J84-J85 -> 0 | K86: =K82+K83-K84-K85 -> 0 | ... P86: =P82+P83-P84-P85 -> 0
B89: 2026年 业绩 _ 制造费用明细书 _EV
C90: 2026년 누계 | D90: 2025.12 | E90: 2026.01 | F90: 2026.02 | G90: 2026.03 | H90: 2026.04 | I90: 2026.05 | J90: 2026.06 | K90: 2026.07 | L90: 2026.08 | M90: 2026.09 | N90: 2026.10 | O90: 2026.11 | P90: 2026.12
B91: 1.재료비 | C91: =+C92+C93+C94-C95 -> 2303042.8 | D91: =D92+D93-D95+D94 -> 2314786 | E91: =E92+E93-E95+E94 -> 2166143.2 | F91: =F92+F93-F95+F94 -> 136899.61 | G91: =G92+G93-G95+G94 -> 0 | H91: =H92+H93-H95+H94 -> 0 | I91: =I92+I93-I95+I94 -> 0 | J91: =J92+J93-J95+J94 -> 0 | K91: =K92+K93-K95+K94 -> 0 | ... P91: =P92+P93-P95+P94 -> 0
B92: (1) 기초 재고 | C92: =+E92 -> 3773545 | D92: 3032653.6 | E92: 3773545 | F92: 3433934.8
B93: (2) 당기 매입액 | C93: =+SUM(E93:P93) -> 3514602.2 | D93: 3055586 | E93: 1826422.8 | F93: 1688179.5
B94: (3) 타계정대체 원재료 | C94: =+SUM(E94:P94) -> 184.12 | D94: 91.48 | E94: 110.3 | F94: 73.82
B95: (4) 기말 재고액 | C95: =★제조원가명세서!G93 -> 4985288.5 | D95: 3773545 | E95: 3433934.8 | F95: 4985288.5
B96: 2. 노무비 | C96: =+C97 -> 576658.56 | D96: =D97 -> 413581.3 | E96: =E97 -> 289248.39 | F96: =F97 -> 287410.17 | G96: =G97 -> 0 | H96: =H97 -> 0 | I96: =I97 -> 0 | J96: =J97 -> 0 | K96: =K97 -> 0 | ... P96: =P97 -> 0
B97: 1) 급여 | C97: =+SUM(E97:P97) -> 576658.56 | D97: 413581.3 | E97: 289248.39 | F97: 287410.17
B98: 3. 제조경비 | C98: =SUM(C99:C125) -> 729786.97 | D98: =SUM(D99:D125) -> 226736.72 | E98: =SUM(E99:E125) -> 443028.96 | F98: =SUM(F99:F125) -> 286758.01 | G98: =SUM(G99:G125) -> 0 | H98: =SUM(H99:H125) -> 0 | I98: =SUM(I99:I125) -> 0 | J98: =SUM(J99:J125) -> 0 | ... P98: =SUM(P99:P125) -> 0
B99: 1) 복리후생비 | C99: =+SUM(E99:P99) -> 24386.52 | D99: 11827.92 | E99: 12590.88 | F99: 11795.64
B100: 2) 여비교통비 | C100: =+SUM(E100:P100) -> 0
B101: 3) 접대비 | C101: =+SUM(E101:P101) -> 0
B102: 4) 통신비 | C102: =+SUM(E102:P102) -> 0
B103: 5) 수도광열비 | C103: =+SUM(E103:P103) -> 110119.35 | D103: 56056.44 | E103: 54509.34 | F103: 55610.01
B104: 6) 세금과공과 | C104: =+SUM(E104:P104) -> 0
B105: 7) 감가상각비 | C105: =+SUM(E105:P105) -> 268044.4 | D105: 114822.56 | E105: 134022.2 | F105: 134022.2
B106: 8) 지급임차료 | C106: =+SUM(E106:P106) -> 0
B107: 9) 수선비 | C107: =+SUM(E107:P107) -> 0
B108: 10) 보험료 | C108: =+SUM(E108:P108) -> 0
B109: 11) 차량유지비 | C109: =+SUM(E109:P109) -> 0
B110: 12) 경상연구개발비 | C110: =+SUM(E110:P110) -> 0
B111: 13) 운반비 | C111: =+SUM(E111:P111) -> 0
B112: 14) 교육훈련비 | C112: =+SUM(E112:P112) -> 0
B113: 15) 도서인쇄비 | C113: =+SUM(E113:P113) -> 0
B114: 16) 회의비 | C114: =+SUM(E114:P114) -> 0
B115: 17) 포장비 | C115: =+SUM(E115:P115) -> 0
B116: 18) 사무용품비 | C116: =+SUM(E116:P116) -> 0
B117: 19) 소모품비 | C117: =+SUM(E117:P117) -> 228936.69 | D117: 20099.72 | E117: 210655.21 | F117: 18281.48
...

Sheet Sheet3
A1: 월 | B1: 거래처구분 | C1: 판매유형 | D1: 영업담당자 | E1: 거래처 | F1: 거래처명 | G1: 납품처명 | H1: 품목대분류 | I1: 품목중분류 | J1: 품목코드 | K1: 품명 | L1: 규격 | M1: 색상 | N1: 특기사항 | O1: 조장 | P1: 자재유형 | Q1: 품목그룹 | R1: 문서유형 | S1: 수량 | T1: 판매단위 | U1: 동중량 | V1: 단가 | W1: 공급가액
A2: 2월 | B2: 顾客 | C2: 內需 | D2: -無- | E2: C00045 | F2: 盐城通铭汽车配件有限公司 | G2: 盐城通铭汽车配件有限公司 | H2: 자동차(일반) | I2: AVSS | J2: 100000979 | K2: AVSS | L2: 0.3SQ | M2: R | O2: 1500 | P2: 완제품 | Q2: AVSS 0.3SQ(완제품) | R2: A/R송장 (IN) | S2: 3000 | T2: M | U2: 9.93 | V2: 0.29 | W2: 862.73
A3: 2월 | B3: 顾客 | C3: 內需 | D3: -無- | E3: C00045 | F3: 盐城通铭汽车配件有限公司 | G3: 盐城通铭汽车配件有限公司 | H3: 자동차(일반) | I3: AVSS | J3: 100000936 | K3: AVSS | L3: 0.3SQ | M3: B | O3: 1500 | P3: 완제품 | Q3: AVSS 0.3SQ(완제품) | R3: A/R송장 (IN) | S3: 30000 | T3: M | U3: 99.3 | V3: 0.29 | W3: 8628
A4: 2월 | B4: 顾客 | C4: 內需 | D4: -無- | E4: C00045 | F4: 盐城通铭汽车配件有限公司 | G4: 盐城通铭汽车配件有限公司 | H4: 자동차(일반) | I4: AVSS | J4: 100000929 | K4: AVSS | L4: 0.3SQ | M4: Gr | O4: 1500 | P4: 완제품 | Q4: AVSS 0.3SQ(완제품) | R4: A/R송장 (IN) | S4: 30000 | T4: M | U4: 99.3 | V4: 0.29 | W4: 8628
A5: 2월 | B5: 顾客 | C5: 內需 | D5: -無- | E5: C00045 | F5: 盐城通铭汽车配件有限公司 | G5: 盐城通铭汽车配件有限公司 | H5: 자동차(일반) | I5: AVSS | J5: 100000929 | K5: AVSS | L5: 0.3SQ | M5: Gr | O5: 1500 | P5: 완제품 | Q5: AVSS 0.3SQ(완제품) | R5: A/R송장 (IN) | S5: 3000 | T5: M | U5: 9.93 | V5: 0.29 | W5: 862.76
A6: 2월 | B6: 顾客 | C6: 內需 | D6: -無- | E6: C00045 | F6: 盐城通铭汽车配件有限公司 | G6: 盐城通铭汽车配件有限公司 | H6: 자동차(일반) | I6: AVSS | J6: 100000992 | K6: AVSS | L6: 0.3SQ | M6: W | O6: 1500 | P6: 완제품 | Q6: AVSS 0.3SQ(완제품) | R6: A/R송장 (IN) | S6: 4500 | T6: M | U6: 14.9 | V6: 0.29 | W6: 1294.2
A7: 2월 | B7: 顾客 | C7: 內需 | D7: -無- | E7: C00045 | F7: 盐城通铭汽车配件有限公司 | G7: 盐城通铭汽车配件有限公司 | H7: 자동차(일반) | I7: AVSS | J7: 100000936 | K7: AVSS | L7: 0.3SQ | M7: B | O7: 1500 | P7: 완제품 | Q7: AVSS 0.3SQ(완제품) | R7: A/R송장 (IN) | S7: 15000 | T7: M | U7: 49.65 | V7: 0.29 | W7: 4314
A8: 2월 | B8: 顾客 | C8: 內需 | D8: -無- | E8: C00045 | F8: 盐城通铭汽车配件有限公司 | G8: 盐城通铭汽车配件有限公司 | H8: 자동차(일반) | I8: AVSS | J8: 100000929 | K8: AVSS | L8: 0.3SQ | M8: Gr | O8: 1500 | P8: 완제품 | Q8: AVSS 0.3SQ(완제품) | R8: A/R송장 (IN) | S8: 12000 | T8: M | U8: 39.72 | V8: 0.29 | W8: 3451.2
A9: 2월 | B9: 顾客 | C9: 內需 | D9: -無- | E9: C00045 | F9: 盐城通铭汽车配件有限公司 | G9: 盐城通铭汽车配件有限公司 | H9: 자동차(일반) | I9: AVSS | J9: 100000979 | K9: AVSS | L9: 0.3SQ | M9: R | O9: 1500 | P9: 완제품 | Q9: AVSS 0.3SQ(완제품) | R9: A/R송장 (IN) | S9: 4500 | T9: M | U9: 14.9 | V9: 0.29 | W9: 1294.2
A10: 2월 | B10: 顾客 | C10: 內需 | D10: -無- | E10: C00045 | F10: 盐城通铭汽车配件有限公司 | G10: 盐城通铭汽车配件有限公司 | H10: 자동차(일반) | I10: AVSS | J10: 100000936 | K10: AVSS | L10: 0.3SQ | M10: B | O10: 1500 | P10: 완제품 | Q10: AVSS 0.3SQ(완제품) | R10: A/R송장 (IN) | S10: 15000 | T10: M | U10: 49.65 | V10: 0.29 | W10: 4314
A11: 2월 | B11: 顾客 | C11: 內需 | D11: -無- | E11: C00045 | F11: 盐城通铭汽车配件有限公司 | G11: 盐城通铭汽车配件有限公司 | H11: 자동차(일반) | I11: AVSS | J11: 100000992 | K11: AVSS | L11: 0.3SQ | M11: W | O11: 1500 | P11: 완제품 | Q11: AVSS 0.3SQ(완제품) | R11: A/R송장 (IN) | S11: 4500 | T11: M | U11: 14.9 | V11: 0.29 | W11: 1294.2
A12: 2월 | B12: 顾客 | C12: 內需 | D12: -無- | E12: C00045 | F12: 盐城通铭汽车配件有限公司 | G12: 盐城通铭汽车配件有限公司 | H12: 자동차(일반) | I12: AVSS | J12: 100000929 | K12: AVSS | L12: 0.3SQ | M12: Gr | O12: 1500 | P12: 완제품 | Q12: AVSS 0.3SQ(완제품) | R12: A/R송장 (IN) | S12: 15000 | T12: M | U12: 49.65 | V12: 0.29 | W12: 4314

Sheet Sheet4
A1: 월 | B1: 거래처구분 | C1: 판매유형 | D1: 영업담당자 | E1: 거래처 | F1: 거래처명 | G1: 납품처명 | H1: 품목대분류 | I1: 품목중분류 | J1: 품목코드 | K1: 품명 | L1: 규격 | M1: 색상 | N1: 특기사항 | O1: 조장 | P1: 자재유형 | Q1: 품목그룹 | R1: 문서유형 | S1: 수량 | T1: 판매단위 | U1: 동중량 | V1: 단가 | W1: 공급가액
A2: 2월 | B2: 顾客 | C2: 內需 | D2: -無- | E2: C00039 | F2: Kyungshin(안휘경신)韩国京信电子 | G2: kyungshin(안휘경신)韩国京信电子 | H2: 자동차(일반) | I2: AVSS | J2: 140018229 | K2: AVSS | L2: 0.85SQ | M2: W | N2: (B/B)NPS | O2: 7000 | P2: 완제품 | Q2: AVSS B/B 0.85SQ | R2: A/R송장 (IN) | S2: 7000 | T2: M | U2: 53.83 | V2: 0.01 | W2: 344.88
A3: 2월 | B3: 顾客 | C3: 內需 | D3: -無- | E3: C00039 | F3: Kyungshin(안휘경신)韩国京信电子 | G3: kyungshin(안휘경신)韩国京信电子 | H3: 자동차(일반) | I3: AVSS | J3: 140018235 | K3: AVSS | L3: 0.85SQ | M3: G | N3: (B/B)NPS | O3: 7000 | P3: 완제품 | Q3: AVSS B/B 0.85SQ | R3: A/R송장 (IN) | S3: 14000 | T3: M | U3: 107.66 | V3: 0.01 | W3: 689.77
A4: 2월 | B4: 顾客 | C4: 內需 | D4: -無- | E4: C00039 | F4: Kyungshin(안휘경신)韩国京信电子 | G4: kyungshin(안휘경신)韩国京信电子 | H4: 자동차(일반) | I4: AVSS | J4: 140018220 | K4: AVSS | L4: 0.3SQ | M4: W/O | N4: (B/B)NPS | O4: 10000 | P4: 완제품 | Q4: AVSS B/B 0.3SQ | R4: A/R송장 (IN) | S4: 10000 | T4: M | U4: 33.1 | V4: 0.01 | W4: 357.71
A5: 2월 | B5: 顾客 | C5: 內需 | D5: -無- | E5: C00039 | F5: Kyungshin(안휘경신)韩国京信电子 | G5: kyungshin(안휘경신)韩国京信电子 | H5: 자동차(일반) | I5: AVSS | J5: 140018213 | K5: AVSS | L5: 0.3SQ | M5: W/B | N5: (B/B)NPS | O5: 10000 | P5: 완제품 | Q5: AVSS B/B 0.3SQ | R5: A/R송장 (IN) | S5: 10000 | T5: M | U5: 33.1 | V5: 0.01 | W5: 357.71
A6: 2월 | B6: 顾客 | C6: 內需 | D6: -無- | E6: C00039 | F6: Kyungshin(안휘경신)韩国京信电子 | G6: kyungshin(안휘경신)韩国京信电子 | H6: 자동차(일반) | I6: AVSS | J6: 140015181 | K6: AVSS | L6: 0.3SQ | M6: W | N6: (B/B)NPS | O6: 10000 | P6: 완제품 | Q6: AVSS B/B 0.3SQ | R6: A/R송장 (IN) | S6: 149500 | T6: M | U6: 494.85 | V6: 0.01 | W6: 5347.73
A7: 2월 | B7: 顾客 | C7: 內需 | D7: -無- | E7: C00039 | F7: Kyungshin(안휘경신)韩国京信电子 | G7: kyungshin(안휘경신)韩国京信电子 | H7: 자동차(일반) | I7: AVSS | J7: 140015173 | K7: AVSS | L7: 0.3SQ | M7: B | N7: (B/B)NPS | O7: 10000 | P7: 완제품 | Q7: AVSS B/B 0.3SQ | R7: A/R송장 (IN) | S7: 200000 | T7: M | U7: 662 | V7: 0.01 | W7: 7154.15
A8: 2월 | B8: 顾客 | C8: 內需 | D8: -無- | E8: C00039 | F8: Kyungshin(안휘경신)韩国京信电子 | G8: kyungshin(안휘경신)韩国京信电子 | H8: 자동차(일반) | I8: AVSS | J8: 140018221 | K8: AVSS | L8: 0.3SQ | M8: R/O | N8: (B/B)NPS | O8: 10000 | P8: 완제품 | Q8: AVSS B/B 0.3SQ | R8: A/R송장 (IN) | S8: 30000 | T8: M | U8: 99.3 | V8: 0.01 | W8: 1073.12
A9: 2월 | B9: 顾客 | C9: 內需 | D9: -無- | E9: C00039 | F9: Kyungshin(안휘경신)韩国京信电子 | G9: kyungshin(안휘경신)韩国京信电子 | H9: 자동차(일반) | I9: AVSS | J9: 140018250 | K9: AVSS | L9: 0.3SQ | M9: R/B | N9: (B/B)NPS | O9: 10000 | P9: 완제품 | Q9: AVSS B/B 0.3SQ | R9: A/R송장 (IN) | S9: 30000 | T9: M | U9: 99.3 | V9: 0.01 | W9: 1073.12
A10: 2월 | B10: 顾客 | C10: 內需 | D10: -無- | E10: C00039 | F10: Kyungshin(안휘경신)韩国京信电子 | G10: kyungshin(안휘경신)韩国京信电子 | H10: 자동차(일반) | I10: AVSS | J10: 140018215 | K10: AVSS | L10: 0.3SQ | M10: P/B | N10: (B/B)NPS | O10: 10000 | P10: 완제품 | Q10: AVSS 0.3SQ(완제품) | R10: A/R송장 (IN) | S10: 10000 | T10: M | U10: 33.1 | V10: 0.01 | W10: 357.71
A11: 2월 | B11: 顾客 | C11: 內需 | D11: -無- | E11: C00039 | F11: Kyungshin(안휘경신)韩国京信电子 | G11: kyungshin(안휘경신)韩国京信电子 | H11: 자동차(일반) | I11: AVSS | J11: 140018216 | K11: AVSS | L11: 0.3SQ | M11: P | N11: (B/B)NPS | O11: 10000 | P11: 완제품 | Q11: AVSS B/B 0.3SQ | R11: A/R송장 (IN) | S11: 80000 | T11: M | U11: 264.8 | V11: 0.01 | W11: 2861.66
A12: 2월 | B12: 顾客 | C12: 內需 | D12: -無- | E12: C00039 | F12: Kyungshin(안휘경신)韩国京信电子 | G12: kyungshin(안휘경신)韩国京信电子 | H12: 자동차(일반) | I12: AVSS | J12: 140018222 | K12: AVSS | L12: 0.3SQ | M12: B/O | N12: (B/B)NPS | O12: 10000 | P12: 완제품 | Q12: AVSS B/B 0.3SQ | R12: A/R송장 (IN) | S12: 20000 | T12: M | U12: 66.2 | V12: 0.01 | W12: 715.42
A13: 2월 | B13: 顾客 | C13: 內需 | D13: -無- | E13: C00039 | F13: Kyungshin(안휘경신)韩国京信电子 | G13: kyungshin(안휘경신)韩国京信电子 | H13: 자동차(일반) | I13: AVSS | J13: 140015173 | K13: AVSS | L13: 0.3SQ | M13: B | N13: (B/B)NPS | O13: 10000 | P13: 완제품 | Q13: AVSS B/B 0.3SQ | R13: A/R송장 (IN) | S13: 70000 | T13: M | U13: 231.7 | V13: 0.01 | W13: 2503.95
... A390: 2월 | B390: 顾客 | C390: 內需 | D390: -無- | E390: C00039 | F390: Kyungshin(안휘경신)韩国京信电子 | G390: kyungshin(안휘경신)韩国京信电子 | H390: 자동차(일반) | I390: AVSS | J390: 140018218 | K390: AVSS | L390: 0.3SQ | M390: Br/B | N390: (B/B)NPS | O390: 10000 | P390: 완제품 | Q390: AVSS B/B 0.3SQ | R390: A/R송장 (IN) | S390: 30000 | T390: M | U390: 99.3 | V390: 0.01 | W390: 1073.12

Sheet Sheet5
A1: 월 | B1: 거래처구분 | C1: 판매유형 | D1: 영업담당자 | E1: 거래처 | F1: 거래처명 | G1: 납품처명 | H1: 품목대분류 | I1: 품목중분류 | J1: 품목코드 | K1: 품명 | L1: 규격 | M1: 색상 | N1: 특기사항 | O1: 조장 | P1: 자재유형 | Q1: 품목그룹 | R1: 문서유형 | S1: 수량 | T1: 판매단위 | U1: 동중량 | V1: 단가 | W1: 공급가액
F2: Kyungshin(안휘경신)韩国京信电子

Sheet Sheet6
A1: 월 | B1: 거래처구분 | C1: 판매유형 | D1: 영업담당자 | E1: 거래처 | F1: 거래처명 | G1: 납품처명 | H1: 품목대분류 | I1: 품목중분류 | J1: 품목코드 | K1: 품명 | L1: 규격 | M1: 색상 | N1: 특기사항 | O1: 조장 | P1: 자재유형 | Q1: 품목그룹 | R1: 문서유형 | S1: 수량 | T1: 판매단위 | U1: 동중량 | V1: 단가 | W1: 공급가액
A2: 4월 | B2: 顾客 | C2: 內需 | D2: -無- | E2: C00018 | F2: 上海海拉电子有限公司 | G2: 上海海拉电子有限公司 | H2: 자동차(일반) | I2: 자동차일반전선_기타 | J2: 100002394 | K2: AVUHSF | L2: 25SQ | M2: B | O2: 1000 | P2: 완제품 | Q2: AVUHSF 25SQ(완제품) | R2: A/R송장 (IN) | S2: 2000 | T2: M | U2: 462.84 | V2: 19.56 | W2: 39116.35
A3: 4월 | B3: 顾客 | C3: 內需 | D3: -無- | E3: C00018 | F3: 上海海拉电子有限公司 | G3: 上海海拉电子有限公司 | H3: 자동차(일반) | I3: 자동차일반전선_기타 | J3: 100002394 | K3: AVUHSF | L3: 25SQ | M3: B | O3: 1000 | P3: 완제품 | Q3: AVUHSF 25SQ(완제품) | R3: A/R송장 (IN) | S3: 500 | T3: M | U3: 115.71 | V3: 19.56 | W3: 9779.09
A4: 4월 | B4: 顾客 | C4: 內需 | D4: -無- | E4: C00018 | F4: 上海海拉电子有限公司 | G4: 上海海拉电子有限公司 | H4: 자동차(일반) | I4: 자동차일반전선_기타 | J4: 100002394 | K4: AVUHSF | L4: 25SQ | M4: B | O4: 1000 | P4: 완제품 | Q4: AVUHSF 25SQ(완제품) | R4: A/R송장 (IN) | S4: 1500 | T4: M | U4: 347.13 | V4: 19.56 | W4: 29337.26
A5: 4월 | B5: 顾客 | C5: 內需 | D5: -無- | E5: C00018 | F5: 上海海拉电子有限公司 | G5: 上海海拉电子有限公司 | H5: 자동차(일반) | I5: 자동차일반전선_기타 | J5: 100002394 | K5: AVUHSF | L5: 25SQ | M5: B | O5: 1000 | P5: 완제품 | Q5: AVUHSF 25SQ(완제품) | R5: A/R송장 (IN) | S5: 1800 | T5: M | U5: 416.56 | V5: 19.56 | W5: 35204.71

Sheet Sheet7
A1: 월 | B1: 거래처구분 | C1: 판매유형 | D1: 영업담당자 | E1: 거래처 | F1: 거래처명 | G1: 납품처명 | H1: 품목대분류 | I1: 품목중분류 | J1: 품목코드 | K1: 품명 | L1: 규격 | M1: 색상 | N1: 특기사항 | O1: 조장 | P1: 자재유형 | Q1: 품목그룹 | R1: 문서유형 | S1: 수량 | T1: 판매단위 | U1: 동중량 | V1: 단가 | W1: 공급가액
A2: 7월 | B2: 顾客 | C2: 內需 | D2: -無- | E2: C00011 | F2: Kyungshin Cable CO.,LTD | G2: Kyungshin Cable CO.,LTD | H2: 자동차(일반) | I2: AVS | J2: 100000412 | K2: AVS | L2: 3SQ | M2: P | O2: 300 | P2: 완제품 | Q2: AVS 3SQ(상품) | R2: A/R송장 (IN) | S2: 45000 | T2: M | U2: 1328.85 | V2: 0.3 | W2: 98288.66
A3: 7월 | B3: 顾客 | C3: 內需 | D3: -無- | E3: C00011 | F3: Kyungshin Cable CO.,LTD | G3: Kyungshin Cable CO.,LTD | H3: 자동차(일반) | I3: AVS | J3: 100000403 | K3: AVS | L3: 3SQ | M3: G | O3: 300 | P3: 완제품 | Q3: AVS 3SQ(상품) | R3: A/R송장 (IN) | S3: 45000 | T3: M | U3: 1328.85 | V3: 0.3 | W3: 98288.66
A4: 7월 | B4: 顾客 | C4: 內需 | D4: -無- | E4: C00011 | F4: Kyungshin Cable CO.,LTD | G4: Kyungshin Cable CO.,LTD | H4: 자동차(일반) | I4: AVS | J4: 100000410 | K4: AVS | L4: 3SQ | M4: L | O4: 300 | P4: 완제품 | Q4: AVS 3SQ(상품) | R4: A/R송장 (IN) | S4: 45000 | T4: M | U4: 1328.85 | V4: 0.3 | W4: 98288.66
A5: 7월 | B5: 顾客 | C5: 內需 | D5: -無- | E5: C00011 | F5: Kyungshin Cable CO.,LTD | G5: Kyungshin Cable CO.,LTD | H5: 자동차(일반) | I5: AVS | J5: 100000426 | K5: AVS | L5: 3SQ | M5: W | O5: 300 | P5: 완제품 | Q5: AVS 3SQ(상품) | R5: A/R송장 (IN) | S5: 45000 | T5: M | U5: 1328.85 | V5: 0.3 | W5: 98288.66
A6: 7월 | B6: 顾客 | C6: 內需 | D6: -無- | E6: C00011 | F6: Kyungshin Cable CO.,LTD | G6: Kyungshin Cable CO.,LTD | H6: 자동차(일반) | I6: AVS | J6: 100000397 | K6: AVS | L6: 3SQ | M6: B | O6: 300 | P6: 완제품 | Q6: AVS 3SQ(상품) | R6: A/R송장 (IN) | S6: 60000 | T6: M | U6: 1771.8 | V6: 0.3 | W6: 131051.54
A7: 7월 | B7: 顾客 | C7: 內需 | D7: -無- | E7: C00011 | F7: Kyungshin Cable CO.,LTD | G7: Kyungshin Cable CO.,LTD | H7: 자동차(일반) | I7: AVS | J7: 100000419 | K7: AVS | L7: 3SQ | M7: R | O7: 300 | P7: 완제품 | Q7: AVS 3SQ(상품) | R7: A/R송장 (IN) | S7: 60000 | T7: M | U7: 1771.8 | V7: 0.3 | W7: 131051.54
A8: 7월 | B8: 顾客 | C8: 內需 | D8: -無- | E8: C00011 | F8: Kyungshin Cable CO.,LTD | G8: Kyungshin Cable CO.,LTD | H8: 자동차(일반) | I8: AVS | J8: 100000412 | K8: AVS | L8: 3SQ | M8: P | O8: 300 | P8: 완제품 | Q8: AVS 3SQ(상품) | R8: A/R송장 (IN) | S8: 30000 | T8: M | U8: 885.9 | V8: 0.3 | W8: 65525.77
A9: 7월 | B9: 顾客 | C9: 內需 | D9: -無- | E9: C00011 | F9: Kyungshin Cable CO.,LTD | G9: Kyungshin Cable CO.,LTD | H9: 자동차(일반) | I9: AVS | J9: 100000403 | K9: AVS | L9: 3SQ | M9: G | O9: 300 | P9: 완제품 | Q9: AVS 3SQ(상품) | R9: A/R송장 (IN) | S9: 30000 | T9: M | U9: 885.9 | V9: 0.3 | W9: 65525.77
A10: 7월 | B10: 顾客 | C10: 內需 | D10: -無- | E10: C00011 | F10: Kyungshin Cable CO.,LTD | G10: Kyungshin Cable CO.,LTD | H10: 자동차(일반) | I10: AVS | J10: 100000410 | K10: AVS | L10: 3SQ | M10: L | O10: 300 | P10: 완제품 | Q10: AVS 3SQ(상품) | R10: A/R송장 (IN) | S10: 60000 | T10: M | U10: 1771.8 | V10: 0.3 | W10: 131051.54
A11: 7월 | B11: 顾客 | C11: 內需 | D11: -無- | E11: C00011 | F11: Kyungshin Cable CO.,LTD | G11: Kyungshin Cable CO.,LTD | H11: 자동차(일반) | I11: AVS | J11: 100000426 | K11: AVS | L11: 3SQ | M11: W | O11: 300 | P11: 완제품 | Q11: AVS 3SQ(상품) | R11: A/R송장 (IN) | S11: 60000 | T11: M | U11: 1771.8 | V11: 0.3 | W11: 131051.54
A12: 7월 | B12: 顾客 | C12: 內需 | D12: -無- | E12: C00011 | F12: Kyungshin Cable CO.,LTD | G12: Kyungshin Cable CO.,LTD | H12: 자동차(일반) | I12: AVS | J12: 100000397 | K12: AVS | L12: 3SQ | M12: B | O12: 300 | P12: 완제품 | Q12: AVS 3SQ(상품) | R12: A/R송장 (IN) | S12: 60000 | T12: M | U12: 1771.8 | V12: 0.3 | W12: 131051.54
A13: 7월 | B13: 顾客 | C13: 內需 | D13: -無- | E13: C00011 | F13: Kyungshin Cable CO.,LTD | G13: Kyungshin Cable CO.,LTD | H13: 자동차(일반) | I13: AVS | J13: 100000419 | K13: AVS | L13: 3SQ | M13: R | O13: 300 | P13: 완제품 | Q13: AVS 3SQ(상품) | R13: A/R송장 (IN) | S13: 60000 | T13: M | U13: 1771.8 | V13: 0.3 | W13: 131051.54
... A25: 7월 | B25: 顾客 | C25: 內需 | D25: -無- | E25: C00011 | F25: Kyungshin Cable CO.,LTD | G25: Kyungshin Cable CO.,LTD | H25: 자동차(일반) | I25: AVS | J25: 100000397 | K25: AVS | L25: 3SQ | M25: B | O25: 300 | P25: 완제품 | Q25: AVS 3SQ(상품) | R25: A/R송장 (IN) | S25: 60000 | T25: M | U25: 1771.8 | V25: 0.3 | W25: 131051.54
A26: 7월 | B26: 顾客 | C26: 內需 | D26: -無- | E26: C00011 | F26: Kyungshin Cable CO.,LTD | G26: Kyungshin Cable CO.,LTD | H26: 자동차(일반) | I26: AVSS | J26: 100026368 | K26: AVSS | L26: 1.25SQ | M26: L | N26: (HYVN)NPS | O26: 5000 | P26: 완제품 | Q26: AVSS 1.25SQ(완제품) | R26: A/R송장 (IN) | S26: 15000 | T26: M | U26: 169.05 | V26: 0.12 | W26: 12501.2
A27: 7월 | B27: 顾客 | C27: 內需 | D27: -無- | E27: C00011 | F27: Kyungshin Cable CO.,LTD | G27: Kyungshin Cable CO.,LTD | H27: 자동차(일반) | I27: AVSS | J27: 100026365 | K27: AVSS | L27: 1.25SQ | M27: Br | N27: (HYVN)NPS | O27: 5000 | P27: 완제품 | Q27: AVSS 1.25SQ(완제품) | R27: A/R송장 (IN) | S27: 15000 | T27: M | U27: 169.05 | V27: 0.12 | W27: 12501.2
A28: 7월 | B28: 顾客 | C28: 內需 | D28: -無- | E28: C00011 | F28: Kyungshin Cable CO.,LTD | G28: Kyungshin Cable CO.,LTD | H28: 자동차(일반) | I28: AVSS | J28: 100026361 | K28: AVSS | L28: 0.85SQ | M28: R | N28: (HYVN)NPS | O28: 8000 | P28: 완제품 | Q28: AVSS 0.85SQ(완제품) | R28: A/R송장 (IN) | S28: 24000 | T28: M | U28: 184.85 | V28: 0.08 | W28: 13906.1
A29: 7월 | B29: 顾客 | C29: 內需 | D29: -無- | E29: C00011 | F29: Kyungshin Cable CO.,LTD | G29: Kyungshin Cable CO.,LTD | H29: 자동차(일반) | I29: AVSS | J29: 100026348 | K29: AVSS | L29: 0.5SQ | M29: R/B | N29: (HYVN)NPS | O29: 10000 | P29: 완제품 | Q29: AVSS 0.5SQ(완제품) | R29: A/R송장 (IN) | S29: 30000 | T29: M | U29: 150.39 | V29: 0.05 | W29: 11494.61
A30: 7월 | B30: 顾客 | C30: 內需 | D30: -無- | E30: C00011 | F30: Kyungshin Cable CO.,LTD | G30: Kyungshin Cable CO.,LTD | H30: 자동차(일반) | I30: AVSS | J30: 100026240 | K30: AVSS | L30: 0.5SQ | M30: B | N30: (KSNA)NPS | O30: 10000 | P30: 완제품 | Q30: AVSS 0.5SQ(완제품) | R30: A/R송장 (IN) | S30: 90000 | T30: M | U30: 451.17 | V30: 0.05 | W30: 34483.83
A31: 7월 | B31: 顾客 | C31: 內需 | D31: -無- | E31: C00011 | F31: Kyungshin Cable CO.,LTD | G31: Kyungshin Cable CO.,LTD | H31: 자동차(일반) | I31: AVSS | J31: 100026157 | K31: AVSS | L31: 0.3SQ | M31: G/B | N31: (KSNA)NPS | O31: 12000 | P31: 완제품 | Q31: AVSS 0.3SQ(완제품) | R31: A/R송장 (IN) | S31: 72000 | T31: M | U31: 238.32 | V31: 0.04 | W31: 18807
A32: 7월 | B32: 顾客 | C32: 內需 | D32: -無- | E32: C00011 | F32: Kyungshin Cable CO.,LTD | G32: Kyungshin Cable CO.,LTD | H32: 자동차(일반) | I32: AVSS | J32: 100026151 | K32: AVSS | L32: 0.3SQ | M32: B | N32: (KSNA)NPS | O32: 12000 | P32: 완제품 | Q32: AVSS 0.3SQ(완제품) | R32: A/R송장 (IN) | S32: 108000 | T32: M | U32: 357.48 | V32: 0.04 | W32: 28210.5
A33: 7월 | B33: 顾客 | C33: 內需 | D33: -無- | E33: C00011 | F33: Kyungshin Cable CO.,LTD | G33: Kyungshin Cable CO.,LTD | H33: 자동차(일반) | I33: AVSS | J33: 100019769 | K33: AVSS | L33: 1.25SQ | M33: R | N33: (KSCB)NPS | O33: 5000 | P33: 완제품 | Q33: AVSS 1.25SQ(완제품) | R33: A/R송장 (IN) | S33: 15000 | T33: M | U33: 169.05 | V33: 0.12 | W33: 12501.2
A34: 7월 | B34: 顾客 | C34: 內需 | D34: -無- | E34: C00011 | F34: Kyungshin Cable CO.,LTD | G34: Kyungshin Cable CO.,LTD | H34: 자동차(일반) | I34: AVSS | J34: 100019768 | K34: AVSS | L34: 1.25SQ | M34: P | N34: (KSCB)NPS | O34: 5000 | P34: 완제품 | Q34: AVSS 1.25SQ(완제품) | R34: A/R송장 (IN) | S34: 15000 | T34: M | U34: 169.05 | V34: 0.12 | W34: 12501.2
A35: 7월 | B35: 顾客 | C35: 內需 | D35: -無- | E35: C00011 | F35: Kyungshin Cable CO.,LTD | G35: Kyungshin Cable CO.,LTD | H35: 자동차(일반) | I35: AVSS | J35: 100019767 | K35: AVSS | L35: 1.25SQ | M35: O | N35: (KSCB)NPS | O35: 5000 | P35: 완제품 | Q35: AVSS 1.25SQ(완제품) | R35: A/R송장 (IN) | S35: 15000 | T35: M | U35: 169.05 | V35: 0.12 | W35: 12501.2
A36: 7월 | B36: 顾客 | C36: 內需 | D36: -無- | E36: C00011 | F36: Kyungshin Cable CO.,LTD | G36: Kyungshin Cable CO.,LTD | H36: 자동차(일반) | I36: AVSS | J36: 100019762 | K36: AVSS | L36: 0.85SQ | M36: W | N36: (KSCB)NPS | O36: 8000 | P36: 완제품 | Q36: AVSS 0.85SQ(완제품) | R36: A/R송장 (IN) | S36: 48000 | T36: M | U36: 369.12 | V36: 0.08 | W36: 27812.19
A37: 7월 | B37: 顾客 | C37: 內需 | D37: -無- | E37: C00011 | F37: Kyungshin Cable CO.,LTD | G37: Kyungshin Cable CO.,LTD | H37: 자동차(일반) | I37: AVSS | J37: 100019759 | K37: AVSS | L37: 0.85SQ | M37: O | N37: (KSCB)NPS | O37: 8000 | P37: 완제품 | Q37: AVSS 0.85SQ(완제품) | R37: A/R송장 (IN) | S37: 48000 | T37: M | U37: 369.7 | V37: 0.08 | W37: 27812.19
... A146: 7월 | B146: 顾客 | C146: 內需 | D146: -無- | E146: C00032 | F146: Kyungshin Cable international corporation | G146: Kyungshin Cable international corporation | H146: 자동차(조사) | I146: AESSXF | J146: 100002459 | K146: AESSXF | L146: 0.3SQ | M146: O | N146: (KL)NPS | O146: 12000 | P146: 완제품 | Q146: AESSXF 0.3SQ(완제품) | R146: A/R송장 (IN) | S146: 12000 | T146: M | U146: 41.02 | V146: 0.05 | W146: 4009.04
A147: 7월 | B147: 顾客 | C147: 內需 | D147: -無- | E147: C00032 | F147: Kyungshin Cable international corporation | G147: Kyungshin Cable international corporation | H147: 자동차(특수) | I147: SHIELD WIRE_조사 | J147: 190005508 | K147: AESSXF-BS | L147: 2x0.5SQ | M147: Gr(G,Y) | O147: 300 | P147: 완제품 | Q147: AESSXF-BS 2x0.5SQ(완제 | R147: A/R송장 (IN) | S147: 2100 | T147: M | U147: 38.76 | V147: 0.35 | W147: 5233.11
A148: 7월 | B148: 顾客 | C148: 內需 | D148: -無- | E148: C00032 | F148: Kyungshin Cable international corporation | G148: Kyungshin Cable international corporation | H148: 자동차(특수) | I148: SHIELD WIRE_조사 | J148: 190005511 | K148: AESSXF-BS | L148: 2x0.5SQ | M148: Gr(G,W) | O148: 300 | P148: 완제품 | Q148: AESSXF-BS 2x0.5SQ(완제 | R148: A/R송장 (IN) | S148: 4800 | T148: M | U148: 88.58 | V148: 0.34 | W148: 11942.27
A149: 7월 | B149: 顾客 | C149: 內需 | D149: -無- | E149: C00032 | F149: Kyungshin Cable international corporation | G149: Kyungshin Cable international corporation | H149: 자동차(특수) | I149: SHIELD WIRE_조사 | J149: 190005517 | K149: AESSXF-BS | L149: 2x0.5SQ | M149: Gr(Br,G) | O149: 300 | P149: 완제품 | Q149: AESSXF-BS 2x0.5SQ(완제 | R149: A/R송장 (IN) | S149: 8100 | T149: M | U149: 149.49 | V149: 0.34 | W149: 20152.58
A150: 7월 | B150: 顾客 | C150: 內需 | D150: -無- | E150: C00032 | F150: Kyungshin Cable international corporation | G150: Kyungshin Cable international corporation | H150: 자동차(특수) | I150: SHIELD WIRE_조사 | J150: 190005513 | K150: AESSXF-BS | L150: 2x0.5SQ | M150: Gr(G,L) | O150: 300 | P150: 완제품 | Q150: AESSXF-BS 2x0.5SQ(완제 | R150: A/R송장 (IN) | S150: 300 | T150: M | U150: 5.54 | V150: 0.34 | W150: 746.39
A151: 7월 | B151: 顾客 | C151: 內需 | D151: -無- | E151: C00032 | F151: Kyungshin Cable international corporation | G151: Kyungshin Cable international corporation | H151: 자동차(특수) | I151: SHIELD WIRE_조사 | J151: 190005507 | K151: AESSXF-BS | L151: 2x0.5SQ | M151: Gr(Br,Y) | O151: 300 | P151: 완제품 | Q151: AESSXF-BS 2x0.5SQ(완제 | R151: A/R송장 (IN) | S151: 7200 | T151: M | U151: 132.88 | V151: 0.34 | W151: 17913.41
A152: 7월 | B152: 顾客 | C152: 內需 | D152: -無- | E152: C00032 | F152: Kyungshin Cable international corporation | G152: Kyungshin Cable international corporation | H152: 자동차(특수) | I152: SHIELD WIRE_조사 | J152: 190005507 | K152: AESSXF-BS | L152: 2x0.5SQ | M152: Gr(Br,Y) | O152: 300 | P152: 완제품 | Q152: AESSXF-BS 2x0.5SQ(완제 | R152: A/R송장 (IN) | S152: 900 | T152: M | U152: 16.61 | V152: 0.34 | W152: 2239.18
A153: 7월 | B153: 顾客 | C153: 內需 | D153: -無- | E153: C00032 | F153: Kyungshin Cable international corporation | G153: Kyungshin Cable international corporation | H153: 자동차(특수) | I153: SHIELD WIRE_조사 | J153: 190005511 | K153: AESSXF-BS | L153: 2x0.5SQ | M153: Gr(G,W) | O153: 300 | P153: 완제품 | Q153: AESSXF-BS 2x0.5SQ(완제 | R153: A/R송장 (IN) | S153: 51900 | T153: M | U153: 957.81 | V153: 0.34 | W153: 129125.82
A154: 7월 | B154: 顾客 | C154: 內需 | D154: -無- | E154: C00032 | F154: Kyungshin Cable international corporation | G154: Kyungshin Cable international corporation | H154: 자동차(특수) | I154: SHIELD WIRE_조사 | J154: 190005507 | K154: AESSXF-BS | L154: 2x0.5SQ | M154: Gr(Br,Y) | O154: 300 | P154: 완제품 | Q154: AESSXF-BS 2x0.5SQ(완제 | R154: A/R송장 (IN) | S154: 16200 | T154: M | U154: 298.97 | V154: 0.34 | W154: 40305.17
A155: 7월 | B155: 顾客 | C155: 內需 | D155: -無- | E155: C00032 | F155: Kyungshin Cable international corporation | G155: Kyungshin Cable international corporation | H155: 자동차(특수) | I155: SHIELD WIRE_조사 | J155: 190005530 | K155: AESSXF-BS | L155: 4x0.75SQ | M155: Gr(B,G,R,W) | O155: 200 | P155: 완제품 | Q155: AESSXF-BS 4x0.75SQ(완 | R155: A/R송장 (IN) | S155: 3800 | T155: M | U155: 145.24 | V155: 0.65 | W155: 17894.07
A156: 7월 | B156: 顾客 | C156: 內需 | D156: -無- | E156: C00032 | F156: Kyungshin Cable international corporation | G156: Kyungshin Cable international corporation | H156: 자동차(특수) | I156: SHIELD WIRE_조사 | J156: 190005508 | K156: AESSXF-BS | L156: 2x0.5SQ | M156: Gr(G,Y) | O156: 300 | P156: 완제품 | Q156: AESSXF-BS 2x0.5SQ(완제 | R156: A/R송장 (IN) | S156: 4500 | T156: M | U156: 83.05 | V156: 0.34 | W156: 11195.88
A157: 7월 | B157: 顾客 | C157: 內需 | D157: -無- | E157: C00032 | F157: Kyungshin Cable international corporation | G157: Kyungshin Cable international corporation | H157: 자동차(특수) | I157: SHIELD WIRE_조사 | J157: 190005489 | K157: AESSXF-BS | L157: 1x0.75SQ | M157: Gr(R) | O157: 500 | P157: 완제품 | Q157: AESSXF-BS 1x0.75SQ(완 | R157: A/R송장 (IN) | S157: 1500 | T157: M | U157: 57.33 | V157: 0.2 | W157: 2196.1
A158: 7월 | B158: 顾客 | C158: 內需 | D158: -無- | E158: C00032 | F158: Kyungshin Cable international corporation | G158: Kyungshin Cable international corporation | H158: 자동차(특수) | I158: SHIELD WIRE_조사 | J158: 190005508 | K158: AESSXF-BS | L158: 2x0.5SQ | M158: Gr(G,Y) | O158: 300 | P158: 완제품 | Q158: AESSXF-BS 2x0.5SQ(완제 | R158: A/R송장 (IN) | S158: 900 | T158: M | U158: 16.61 | V158: 0.34 | W158: 2239.18
... A177: 7월 | B177: 顾客 | C177: 內需 | D177: -無- | E177: C00032 | F177: Kyungshin Cable international corporation | G177: Kyungshin Cable international corporation | H177: 자동차(특수) | I177: SHIELD WIRE_조사 | J177: 190005508 | K177: AESSXF-BS | L177: 2x0.5SQ | M177: Gr(G,Y) | O177: 300 | P177: 완제품 | Q177: AESSXF-BS 2x0.5SQ(완제 | R177: A/R송장 (IN) | S177: 8400 | T177: M | U177: 155.02 | V177: 0.34 | W177: 20898.98
A178: 7월 | B178: 顾客 | C178: 內需 | D178: -無- | E178: C00032 | F178: Kyungshin Cable international corporation | G178: Kyungshin Cable international corporation | H178: 자동차(조사) | I178: AEXF | J178: 160003676 | K178: AEXF | L178: 8SQ | M178: B | N178: (KL)NPS | O178: 700 | P178: 완제품 | Q178: AEXF 8SQ(완제품) | R178: A/R송장 (IN) | S178: 700 | T178: M | U178: 50.05 | V178: 0.87 | W178: 4401.43
A179: 7월 | B179: 顾客 | C179: 內需 | D179: -無- | E179: C00032 | F179: Kyungshin Cable international corporation | G179: Kyungshin Cable international corporation | H179: 자동차(조사) | I179: AEXF | J179: 160003676 | K179: AEXF | L179: 8SQ | M179: B | N179: (KL)NPS | O179: 700 | P179: 완제품 | Q179: AEXF 8SQ(완제품) | R179: A/R송장 (IN) | S179: 2100 | T179: M | U179: 150.16 | V179: 0.87 | W179: 13204.3
A180: 7월 | B180: 顾客 | C180: 內需 | D180: -無- | E180: C00032 | F180: Kyungshin Cable international corporation | G180: Kyungshin Cable international corporation | H180: 자동차(조사) | I180: AEXF | J180: 160003676 | K180: AEXF | L180: 8SQ | M180: B | N180: (KL)NPS | O180: 700 | P180: 완제품 | Q180: AEXF 8SQ(완제품) | R180: A/R송장 (IN) | S180: 6300 | T180: M | U180: 450.47 | V180: 0.87 | W180: 39612.89
A181: 7월 | B181: 顾客 | C181: 內需 | D181: -無- | E181: C00032 | F181: Kyungshin Cable international corporation | G181: Kyungshin Cable international corporation | H181: 자동차(조사) | I181: AEXF | J181: 100016094 | K181: AEXF | L181: 5SQ | M181: W | N181: (KL&YM)NPS | O181: 1000 | P181: 완제품 | Q181: AEXF 5SQ(완제품) | R181: A/R송장 (IN) | S181: 4000 | T181: M | U181: 188.27 | V181: 0.57 | W181: 16480.66
A182: 7월 | B182: 顾客 | C182: 內需 | D182: -無- | E182: C00032 | F182: Kyungshin Cable international corporation | G182: Kyungshin Cable international corporation | H182: 자동차(조사) | I182: AEXF | J182: 160003666 | K182: AEXF | L182: 5SQ | M182: L | N182: (KL)NPS | O182: 1000 | P182: 완제품 | Q182: AEXF 5SQ(완제품) | R182: A/R송장 (IN) | S182: 22000 | T182: M | U182: 1035.47 | V182: 0.57 | W182: 90643.62
A183: 7월 | B183: 顾客 | C183: 內需 | D183: -無- | E183: C00032 | F183: Kyungshin Cable international corporation | G183: Kyungshin Cable international corporation | H183: 자동차(조사) | I183: AEXF | J183: 100016050 | K183: AEXF | L183: 5SQ | M183: B | N183: (KL)NPS | O183: 1000 | P183: 완제품 | Q183: AEXF 5SQ(완제품) | R183: A/R송장 (IN) | S183: 20000 | T183: M | U183: 941.34 | V183: 0.57 | W183: 82403.29
A184: 7월 | B184: 顾客 | C184: 內需 | D184: -無- | E184: C00032 | F184: Kyungshin Cable international corporation | G184: Kyungshin Cable international corporation | H184: 자동차(조사) | I184: AEXF | J184: 160003681 | K184: AEXF | L184: 8SQ | M184: R | N184: (KL)NPS | O184: 700 | P184: 완제품 | Q184: AEXF 8SQ(완제품) | R184: A/R송장 (IN) | S184: 7700 | T184: M | U184: 550.57 | V184: 0.87 | W184: 48415.76
A185: 7월 | B185: 顾客 | C185: 內需 | D185: -無- | E185: C00032 | F185: Kyungshin Cable international corporation | G185: Kyungshin Cable international corporation | H185: 자동차(특수) | I185: SHIELD WIRE_일반 | J185: 190005346 | K185: AVSS-BS | L185: 2x0.3SQ | M185: Gr(G,W) | O185: 500 | P185: 완제품 | Q185: AVSS-BS 2x0.3SQ(완제품) | R185: A/R송장 (IN) | S185: 16500 | T185: M | U185: 227.21 | V185: 0.25 | W185: 29657.61
A186: 7월 | B186: 顾客 | C186: 內需 | D186: -無- | E186: C00032 | F186: Kyungshin Cable international corporation | G186: Kyungshin Cable international corporation | H186: 자동차(특수) | I186: SHIELD WIRE_일반 | J186: 190005398 | K186: AVSS-BS | L186: 2x1.25SQ | M186: Gr(G,W) | O186: 300 | P186: 완제품 | Q186: AVSS-BS 2x1.25SQ(완제품 | R186: A/R송장 (IN) | S186: 8700 | T186: M | U186: 289.45 | V186: 0.52 | W186: 32863.54
A187: 7월 | B187: 顾客 | C187: 內需 | D187: -無- | E187: C00032 | F187: Kyungshin Cable international corporation | G187: Kyungshin Cable international corporation | H187: 자동차(특수) | I187: SHIELD WIRE_일반 | J187: 190005346 | K187: AVSS-BS | L187: 2x0.3SQ | M187: Gr(G,W) | O187: 500 | P187: 완제품 | Q187: AVSS-BS 2x0.3SQ(완제품) | R187: A/R송장 (IN) | S187: 97930 | T187: M | U187: 1348.5 | V187: 0.25 | W187: 176022.38
A188: 7월 | B188: 顾客 | C188: 內需 | D188: -無- | E188: C00032 | F188: Kyungshin Cable international corporation | G188: Kyungshin Cable international corporation | H188: 자동차(특수) | I188: SHIELD WIRE_일반 | J188: 190005351 | K188: AVSS-BS | L188: 2x0.3SQ | M188: Gr(Br,Y) | O188: 500 | P188: 완제품 | Q188: AVSS-BS 2x0.3SQ(완제품) | R188: A/R송장 (IN) | S188: 7000 | T188: M | U188: 96.39 | V188: 0.25 | W188: 12582.02
A189: 7월 | B189: 顾客 | C189: 內需 | D189: -無- | E189: C00032 | F189: Kyungshin Cable international corporation | G189: Kyungshin Cable international corporation | H189: 자동차(특수) | I189: SHIELD WIRE_일반 | J189: 190005398 | K189: AVSS-BS | L189: 2x1.25SQ | M189: Gr(G,W) | O189: 300 | P189: 완제품 | Q189: AVSS-BS 2x1.25SQ(완제품 | R189: A/R송장 (IN) | S189: 47100 | T189: M | U189: 1567.02 | V189: 0.52 | W189: 177916.43
A190: 7월 | B190: 顾客 | C190: 內需 | D190: -無- | E190: C00032 | F190: Kyungshin Cable international corporation | G190: Kyungshin Cable international corporation | H190: 자동차(특수) | I190: SHIELD WIRE_일반 | J190: 190005346 | K190: AVSS-BS | L190: 2x0.3SQ | M190: Gr(G,W) | O190: 500 | P190: 완제품 | Q190: AVSS-BS 2x0.3SQ(완제품) | R190: A/R송장 (IN) | S190: 500 | T190: M | U190: 6.89 | V190: 0.25 | W190: 898.72
A191: 7월 | B191: 顾客 | C191: 內需 | D191: -無- | E191: C00032 | F191: Kyungshin Cable international corporation | G191: Kyungshin Cable international corporation | H191: 자동차(특수) | I191: SHIELD WIRE_일반 | J191: 190005351 | K191: AVSS-BS | L191: 2x0.3SQ | M191: Gr(Br,Y) | O191: 500 | P191: 완제품 | Q191: AVSS-BS 2x0.3SQ(완제품) | R191: A/R송장 (IN) | S191: 19000 | T191: M | U191: 261.63 | V191: 0.25 | W191: 34151.19
A192: 7월 | B192: 顾客 | C192: 內需 | D192: -無- | E192: C00032 | F192: Kyungshin Cable international corporation | G192: Kyungshin Cable international corporation | H192: 자동차(특수) | I192: SHIELD WIRE_일반 | J192: 190005398 | K192: AVSS-BS | L192: 2x1.25SQ | M192: Gr(G,W) | O192: 300 | P192: 완제품 | Q192: AVSS-BS 2x1.25SQ(완제품 | R192: A/R송장 (IN) | S192: 36280 | T192: M | U192: 1207.04 | V192: 0.52 | W192: 137044.76
A193: 7월 | B193: 顾客 | C193: 內需 | D193: -無- | E193: C00032 | F193: Kyungshin Cable international corporation | G193: Kyungshin Cable international corporation | H193: 자동차(특수) | I193: SHIELD WIRE_일반 | J193: 190005346 | K193: AVSS-BS | L193: 2x0.3SQ | M193: Gr(G,W) | O193: 500 | P193: 완제품 | Q193: AVSS-BS 2x0.3SQ(완제품) | R193: A/R송장 (IN) | S193: 40000 | T193: M | U193: 550.8 | V193: 0.25 | W193: 71897.23
A194: 7월 | B194: 顾客 | C194: 內需 | D194: -無- | E194: C00032 | F194: Kyungshin Cable international corporation | G194: Kyungshin Cable international corporation | H194: 자동차(특수) | I194: SHIELD WIRE_일반 | J194: 190005398 | K194: AVSS-BS | L194: 2x1.25SQ | M194: Gr(G,W) | O194: 300 | P194: 완제품 | Q194: AVSS-BS 2x1.25SQ(완제품 | R194: A/R송장 (IN) | S194: 300 | T194: M | U194: 9.98 | V194: 0.52 | W194: 1133.23
A195: 7월 | B195: 顾客 | C195: 內需 | D195: -無- | E195: C00032 | F195: Kyungshin Cable international corporation | G195: Kyungshin Cable international corporation | H195: 자동차(특수) | I195: SHIELD WIRE_일반 | J195: 190005398 | K195: AVSS-BS | L195: 2x1.25SQ | M195: Gr(G,W) | O195: 300 | P195: 완제품 | Q195: AVSS-BS 2x1.25SQ(완제품 | R195: A/R송장 (IN) | S195: 20960 | T195: M | U195: 697.34 | V195: 0.52 | W195: 79174.7
A196: 7월 | B196: 顾客 | C196: 內需 | D196: -無- | E196: C00032 | F196: Kyungshin Cable international corporation | G196: Kyungshin Cable international corporation | H196: 자동차(특수) | I196: SHIELD WIRE_일반 | J196: 190005346 | K196: AVSS-BS | L196: 2x0.3SQ | M196: Gr(G,W) | O196: 500 | P196: 완제품 | Q196: AVSS-BS 2x0.3SQ(완제품) | R196: A/R송장 (IN) | S196: 28960 | T196: M | U196: 398.78 | V196: 0.25 | W196: 52053.63
... A210: 7월 | B210: 顾客 | C210: 內需 | D210: -無- | E210: C00032 | F210: Kyungshin Cable international corporation | G210: Kyungshin Cable international corporation | H210: 자동차(특수) | I210: SHIELD WIRE_일반 | J210: 190005398 | K210: AVSS-BS | L210: 2x1.25SQ | M210: Gr(G,W) | O210: 300 | P210: 완제품 | Q210: AVSS-BS 2x1.25SQ(완제품 | R210: A/R송장 (IN) | S210: 92590 | T210: M | U210: 3080.47 | V210: 0.52 | W210: 349751.26
A211: 7월 | B211: 顾客 | C211: 內需 | D211: -無- | E211: C00032 | F211: Kyungshin Cable international corporation | G211: Kyungshin Cable international corporation | H211: 자동차(조사) | I211: AVSSXF | J211: 100013461 | K211: AVSSXF | L211: 1.25SQ | M211: G | N211: (KL&YM)NPS | O211: 5000 | P211: 완제품 | Q211: AVSSXF 1.25SQ(완제품) | R211: A/R송장 (IN) | S211: 5000 | T211: M | U211: 58.2 | V211: 0.13 | W211: 4856.17
A212: 7월 | B212: 顾客 | C212: 內需 | D212: -無- | E212: C00032 | F212: Kyungshin Cable international corporation | G212: Kyungshin Cable international corporation | H212: 자동차(조사) | I212: AVSSXF | J212: 100013461 | K212: AVSSXF | L212: 1.25SQ | M212: G | N212: (KL&YM)NPS | O212: 5000 | P212: 완제품 | Q212: AVSSXF 1.25SQ(완제품) | R212: A/R송장 (IN) | S212: 30000 | T212: M | U212: 349.2 | V212: 0.13 | W212: 29137
A213: 7월 | B213: 顾客 | C213: 內需 | D213: -無- | E213: C00032 | F213: Kyungshin Cable international corporation | G213: Kyungshin Cable international corporation | H213: 자동차(조사) | I213: AVSSXF | J213: 160011202 | K213: AVSSXF | L213: 0.3SQ | M213: Y | N213: (KL)NPS | O213: 12000 | P213: 완제품 | Q213: AVSSXF 0.3SQ(완제품) | R213: A/R송장 (IN) | S213: 12000 | T213: M | U213: 41.04 | V213: 0.04 | W213: 3861.84
A214: 7월 | B214: 顾客 | C214: 內需 | D214: -無- | E214: C00032 | F214: Kyungshin Cable international corporation | G214: Kyungshin Cable international corporation | H214: 자동차(조사) | I214: AVSSXF | J214: 160013455 | K214: AVSSXF | L214: 0.3SQ | M214: R/B | N214: (KL)NPS | O214: 12000 | P214: 완제품 | Q214: AVSSXF 0.3SQ(완제품) | R214: A/R송장 (IN) | S214: 36000 | T214: M | U214: 123.12 | V214: 0.04 | W214: 11585.53
A215: 7월 | B215: 顾客 | C215: 內需 | D215: -無- | E215: C00032 | F215: Kyungshin Cable international corporation | G215: Kyungshin Cable international corporation | H215: 자동차(조사) | I215: AVSSXF | J215: 160011200 | K215: AVSSXF | L215: 0.3SQ | M215: R | N215: (KL)NPS | O215: 12000 | P215: 완제품 | Q215: AVSSXF 0.3SQ(완제품) | R215: A/R송장 (IN) | S215: 24000 | T215: M | U215: 82.08 | V215: 0.04 | W215: 7723.69
A216: 7월 | B216: 顾客 | C216: 內需 | D216: -無- | E216: C00032 | F216: Kyungshin Cable international corporation | G216: Kyungshin Cable international corporation | H216: 자동차(조사) | I216: AVSSXF | J216: 160011197 | K216: AVSSXF | L216: 0.3SQ | M216: L/O | N216: (KL)NPS | O216: 12000 | P216: 완제품 | Q216: AVSSXF 0.3SQ(완제품) | R216: A/R송장 (IN) | S216: 36000 | T216: M | U216: 123.12 | V216: 0.04 | W216: 11585.53
A217: 7월 | B217: 顾客 | C217: 內需 | D217: -無- | E217: C00032 | F217: Kyungshin Cable international corporation | G217: Kyungshin Cable international corporation | H217: 자동차(조사) | I217: AVSSXF | J217: 100014016 | K217: AVSSXF | L217: 0.3SQ | M217: B/O | N217: (KL)NPS | O217: 12000 | P217: 완제품 | Q217: AVSSXF 0.3SQ(완제품) | R217: A/R송장 (IN) | S217: 36000 | T217: M | U217: 123.12 | V217: 0.04 | W217: 11585.53
A218: 7월 | B218: 顾客 | C218: 內需 | D218: -無- | E218: C00032 | F218: Kyungshin Cable international corporation | G218: Kyungshin Cable international corporation | H218: 자동차(조사) | I218: AVSSXF | J218: 160011202 | K218: AVSSXF | L218: 0.3SQ | M218: Y | N218: (KL)NPS | O218: 12000 | P218: 완제품 | Q218: AVSSXF 0.3SQ(완제품) | R218: A/R송장 (IN) | S218: 12000 | T218: M | U218: 41.04 | V218: 0.04 | W218: 3861.84
A219: 7월 | B219: 顾客 | C219: 內需 | D219: -無- | E219: C00032 | F219: Kyungshin Cable international corporation | G219: Kyungshin Cable international corporation | H219: 자동차(조사) | I219: AVSSXF | J219: 100013337 | K219: AVSSXF | L219: 1.25SQ | M219: R | N219: (KL&YM)NPS | O219: 5000 | P219: 완제품 | Q219: AVSSXF 1.25SQ(완제품) | R219: A/R송장 (IN) | S219: 20000 | T219: M | U219: 232.8 | V219: 0.13 | W219: 19424.66
A220: 7월 | B220: 顾客 | C220: 內需 | D220: -無- | E220: C00032 | F220: Kyungshin Cable international corporation | G220: Kyungshin Cable international corporation | H220: 자동차(조사) | I220: AVSSXF | J220: 100013337 | K220: AVSSXF | L220: 1.25SQ | M220: R | N220: (KL&YM)NPS | O220: 5000 | P220: 완제품 | Q220: AVSSXF 1.25SQ(완제품) | R220: A/R송장 (IN) | S220: 20000 | T220: M | U220: 232.8 | V220: 0.13 | W220: 19424.66
A221: 7월 | B221: 顾客 | C221: 內需 | D221: -無- | E221: C00032 | F221: Kyungshin Cable international corporation | G221: Kyungshin Cable international corporation | H221: 자동차(조사) | I221: AVSSXF | J221: 100014836 | K221: AVSSXF | L221: 1.25SQ | M221: O | N221: (KL&YM)NPS | O221: 5000 | P221: 완제품 | Q221: AVSSXF 1.25SQ(완제품) | R221: A/R송장 (IN) | S221: 60000 | T221: M | U221: 698.4 | V221: 0.13 | W221: 58273.99
A222: 7월 | B222: 顾客 | C222: 內需 | D222: -無- | E222: C00032 | F222: Kyungshin Cable international corporation | G222: Kyungshin Cable international corporation | H222: 자동차(조사) | I222: AVSSXF | J222: 100025153 | K222: AVSSXF | L222: 1.25SQ | M222: Gr | N222: (YM)NPS | O222: 5000 | P222: 완제품 | Q222: AVSSXF 1.25SQ(완제품) | R222: A/R송장 (IN) | S222: 10000 | T222: M | U222: 116.4 | V222: 0.13 | W222: 9712.33
... A300: 7월 | B300: 顾客 | C300: 內需 | D300: -無- | E300: C00032 | F300: Kyungshin Cable international corporation | G300: Kyungshin Cable international corporation | H300: 자동차(조사) | I300: AVSSXF | J300: 160011202 | K300: AVSSXF | L300: 0.3SQ | M300: Y | N300: (KL)NPS | O300: 12000 | P300: 완제품 | Q300: AVSSXF 0.3SQ(완제품) | R300: A/R송장 (IN) | S300: 12000 | T300: M | U300: 41.04 | V300: 0.04 | W300: 3861.84
A301: 7월 | B301: 顾客 | C301: 內需 | D301: -無- | E301: C00032 | F301: Kyungshin Cable international corporation | G301: Kyungshin Cable international corporation | H301: 자동차(특수) | I301: SHIELD WIRE_조사 | J301: 190005444 | K301: AVSSXF-BS | L301: 2x0.5SQ | M301: Gr(G,W) | O301: 300 | P301: 완제품 | Q301: AVSSXF-BS 2x0.5SQ(완제 | R301: A/R송장 (IN) | S301: 8650 | T301: M | U301: 159.61 | V301: 0.32 | W301: 20085.41
A302: 7월 | B302: 顾客 | C302: 內需 | D302: -無- | E302: C00032 | F302: Kyungshin Cable international corporation | G302: Kyungshin Cable international corporation | H302: 자동차(특수) | I302: SHIELD WIRE_조사 | J302: 190005444 | K302: AVSSXF-BS | L302: 2x0.5SQ | M302: Gr(G,W) | O302: 300 | P302: 완제품 | Q302: AVSSXF-BS 2x0.5SQ(완제 | R302: A/R송장 (IN) | S302: 26100 | T302: M | U302: 481.6 | V302: 0.32 | W302: 60604.52
A303: 7월 | B303: 顾客 | C303: 內需 | D303: -無- | E303: C00032 | F303: Kyungshin Cable international corporation | G303: Kyungshin Cable international corporation | H303: 자동차(특수) | I303: SHIELD WIRE_조사 | J303: 190005444 | K303: AVSSXF-BS | L303: 2x0.5SQ | M303: Gr(G,W) | O303: 300 | P303: 완제품 | Q303: AVSSXF-BS 2x0.5SQ(완제 | R303: A/R송장 (IN) | S303: 17360 | T303: M | U303: 320.33 | V303: 0.32 | W303: 40310.15
A304: 7월 | B304: 顾客 | C304: 內需 | D304: -無- | E304: C00032 | F304: Kyungshin Cable international corporation | G304: Kyungshin Cable international corporation | H304: 자동차(특수) | I304: SHIELD WIRE_조사 | J304: 190005444 | K304: AVSSXF-BS | L304: 2x0.5SQ | M304: Gr(G,W) | O304: 300 | P304: 완제품 | Q304: AVSSXF-BS 2x0.5SQ(완제 | R304: A/R송장 (IN) | S304: 300 | T304: M | U304: 5.54 | V304: 0.32 | W304: 696.6
A305: 7월 | B305: 顾客 | C305: 內需 | D305: -無- | E305: C00032 | F305: Kyungshin Cable international corporation | G305: Kyungshin Cable international corporation | H305: 자동차(조사) | I305: AVXF | J305: 160002814 | K305: AVXF | L305: 8SQ | M305: B | N305: (KL)NPS | O305: 700 | P305: 완제품 | Q305: AVXF 8SQ(완제품) | R305: A/R송장 (IN) | S305: 700 | T305: M | U305: 50.05 | V305: 0.87 | W305: 4391.84
A306: 7월 | B306: 顾客 | C306: 內需 | D306: -無- | E306: C00032 | F306: Kyungshin Cable international corporation | G306: Kyungshin Cable international corporation | H306: 자동차(조사) | I306: AVXF | J306: 100013713 | K306: AVXF | L306: 3SQ | M306: R | N306: (KL&YM)NPS | O306: 1800 | P306: 완제품 | Q306: AVXF 3SQ(완제품) | R306: A/R송장 (IN) | S306: 21600 | T306: M | U306: 584.71 | V306: 0.31 | W306: 48799.49
A307: 7월 | B307: 顾客 | C307: 內需 | D307: -無- | E307: C00032 | F307: Kyungshin Cable international corporation | G307: Kyungshin Cable international corporation | H307: 자동차(조사) | I307: AVXF | J307: 100013713 | K307: AVXF | L307: 3SQ | M307: R | N307: (KL&YM)NPS | O307: 1800 | P307: 완제품 | Q307: AVXF 3SQ(완제품) | R307: A/R송장 (IN) | S307: 28800 | T307: M | U307: 779.62 | V307: 0.31 | W307: 65065.99
A308: 7월 | B308: 顾客 | C308: 內需 | D308: -無- | E308: C00032 | F308: Kyungshin Cable international corporation | G308: Kyungshin Cable international corporation | H308: 자동차(조사) | I308: AVXF | J308: 100013716 | K308: AVXF | L308: 5SQ | M308: B | N308: (KL&YM)NPS | O308: 1000 | P308: 완제품 | Q308: AVXF 5SQ(완제품) | R308: A/R송장 (IN) | S308: 60000 | T308: M | U308: 2824.02 | V308: 0.54 | W308: 232706.33
A309: 7월 | B309: 顾客 | C309: 內需 | D309: -無- | E309: C00032 | F309: Kyungshin Cable international corporation | G309: Kyungshin Cable international corporation | H309: 자동차(조사) | I309: AVXF | J309: 100013718 | K309: AVXF | L309: 5SQ | M309: R | N309: (KL&YM)NPS | O309: 1000 | P309: 완제품 | Q309: AVXF 5SQ(완제품) | R309: A/R송장 (IN) | S309: 4000 | T309: M | U309: 188.27 | V309: 0.54 | W309: 15513.76
A310: 7월 | B310: 顾客 | C310: 內需 | D310: -無- | E310: C00032 | F310: Kyungshin Cable international corporation | G310: Kyungshin Cable international corporation | H310: 자동차(조사) | I310: AVXF | J310: 160002815 | K310: AVXF | L310: 8SQ | M310: R | N310: (KL)NPS | O310: 700 | P310: 완제품 | Q310: AVXF 8SQ(완제품) | R310: A/R송장 (IN) | S310: 6300 | T310: M | U310: 450.47 | V310: 0.87 | W310: 39526.52
A311: 7월 | B311: 顾客 | C311: 內需 | D311: -無- | E311: C00032 | F311: Kyungshin Cable international corporation | G311: Kyungshin Cable international corporation | H311: 자동차(조사) | I311: AVXF | J311: 100013716 | K311: AVXF | L311: 5SQ | M311: B | N311: (KL&YM)NPS | O311: 1000 | P311: 완제품 | Q311: AVXF 5SQ(완제품) | R311: A/R송장 (IN) | S311: 1000 | T311: M | U311: 47.07 | V311: 0.54 | W311: 3878.44
A312: 7월 | B312: 顾客 | C312: 內需 | D312: -無- | E312: C00032 | F312: Kyungshin Cable international corporation | G312: Kyungshin Cable international corporation | H312: 자동차(조사) | I312: AVXF | J312: 100013719 | K312: AVXF | L312: 5SQ | M312: W | N312: (KL)NPS | O312: 1000 | P312: 완제품 | Q312: AVXF 5SQ(완제품) | R312: A/R송장 (IN) | S312: 16000 | T312: M | U312: 753.07 | V312: 0.54 | W312: 62055.02
A313: 7월 | B313: 顾客 | C313: 內需 | D313: -無- | E313: C00032 | F313: Kyungshin Cable international corporation | G313: Kyungshin Cable international corporation | H313: 자동차(조사) | I313: AVXF | J313: 100013716 | K313: AVXF | L313: 5SQ | M313: B | N313: (KL&YM)NPS | O313: 1000 | P313: 완제품 | Q313: AVXF 5SQ(완제품) | R313: A/R송장 (IN) | S313: 21000 | T313: M | U313: 988.41 | V313: 0.54 | W313: 81447.21
A314: 7월 | B314: 顾客 | C314: 內需 | D314: -無- | E314: C00032 | F314: Kyungshin Cable international corporation | G314: Kyungshin Cable international corporation | H314: 자동차(조사) | I314: AVXF | J314: 100013719 | K314: AVXF | L314: 5SQ | M314: W | N314: (KL)NPS | O314: 1000 | P314: 완제품 | Q314: AVXF 5SQ(완제품) | R314: A/R송장 (IN) | S314: 66000 | T314: M | U314: 3106.42 | V314: 0.54 | W314: 255976.96
A315: 7월 | B315: 顾客 | C315: 內需 | D315: -無- | E315: C00032 | F315: Kyungshin Cable international corporation | G315: Kyungshin Cable international corporation | H315: 자동차(조사) | I315: ISO전선_조사 | J315: 160000019 | K315: TXL | L315: 8SQ | M315: W | N315: (KL)NPS | O315: 800 | P315: 완제품 | Q315: TXL 8SQ(완제품) | R315: A/R송장 (IN) | S315: 5600 | T315: M | U315: 388.19 | V315: 0.85 | W315: 34451.79
A316: 7월 | B316: 顾客 | C316: 內需 | D316: -無- | E316: C00032 | F316: Kyungshin Cable international corporation | G316: Kyungshin Cable international corporation | H316: 자동차(조사) | I316: ISO전선_조사 | J316: 160000018 | K316: TXL | L316: 8SQ | M316: R | N316: (KL)NPS | O316: 800 | P316: 완제품 | Q316: TXL 8SQ(완제품) | R316: A/R송장 (IN) | S316: 65600 | T316: M | U316: 4547.39 | V316: 0.85 | W316: 403618.48
... A406: 7월 | B406: 顾客 | C406: 內需 | D406: -無- | E406: C00032 | F406: Kyungshin Cable international corporation | G406: Kyungshin Cable international corporation | H406: 자동차(조사) | I406: 자동차조사전선 | J406: 190000007 | K406: WXC | L406: 0.5SQ | M406: B | N406: (KL)NPS | O406: 10000 | P406: 완제품 | Q406: WXC 0.5SQ(완제품) | R406: A/R송장 (IN) | S406: 180000 | T406: M | U406: 901.8 | V406: 0.06 | W406: 79747.92
A407: 7월 | B407: 顾客 | C407: 內需 | D407: -無- | E407: C00001 | F407: 江苏京信电子有限公司 | G407: 江苏京信电子有限公司(Cable) | H407: 자동차(조사) | I407: AESSXF | J407: 100003970 | K407: AESSXF | L407: 0.75SQ | M407: R | O407: 1000 | P407: 완제품 | Q407: AESSXF 0.75SQ(완제품) | R407: A/R송장 (IN) | S407: 1000 | T407: M | U407: 7.06 | V407: 0.69 | W407: 686.7
A408: 7월 | B408: 顾客 | C408: 內需 | D408: -無- | E408: C00001 | F408: 江苏京信电子有限公司 | G408: 江苏京信电子有限公司(Cable) | H408: 자동차(조사) | I408: AESSXF | J408: 100003907 | K408: AESSXF | L408: 0.75SQ | M408: Gr | O408: 1000 | P408: 완제품 | Q408: AESSXF 0.75SQ(완제품) | R408: A/R송장 (IN) | S408: 1000 | T408: M | U408: 7.06 | V408: 0.69 | W408: 686.7
A409: 7월 | B409: 顾客 | C409: 內需 | D409: -無- | E409: C00001 | F409: 江苏京信电子有限公司 | G409: 江苏京信电子有限公司(Cable) | H409: 자동차(조사) | I409: AESSXF | J409: 100003740 | K409: AESSXF | L409: 0.3SQ | M409: G/B | O409: 1500 | P409: 완제품 | Q409: AESSXF 0.3SQ(완제품) | R409: A/R송장 (IN) | S409: 1500 | T409: M | U409: 5.13 | V409: 0.38 | W409: 576.75
A410: 7월 | B410: 顾客 | C410: 內需 | D410: -無- | E410: C00001 | F410: 江苏京信电子有限公司 | G410: 江苏京信电子有限公司(Cable) | H410: 자동차(조사) | I410: AESSXF | J410: 100003720 | K410: AESSXF | L410: 0.3SQ | M410: B/O | O410: 1500 | P410: 완제품 | Q410: AESSXF 0.3SQ(완제품) | R410: A/R송장 (IN) | S410: 1500 | T410: M | U410: 5.13 | V410: 0.38 | W410: 576.75
A411: 7월 | B411: 顾客 | C411: 內需 | D411: -無- | E411: C00001 | F411: 江苏京信电子有限公司 | G411: 江苏京信电子有限公司(Cable) | H411: 자동차(조사) | I411: AESSXF | J411: 100003720 | K411: AESSXF | L411: 0.3SQ | M411: B/O | O411: 1500 | P411: 완제품 | Q411: AESSXF 0.3SQ(완제품) | R411: A/R송장 (IN) | S411: 3000 | T411: M | U411: 10.25 | V411: 0.38 | W411: 1153.5
A412: 7월 | B412: 顾客 | C412: 內需 | D412: -無- | E412: C00001 | F412: 江苏京信电子有限公司 | G412: 江苏京信电子有限公司(Cable) | H412: 자동차(조사) | I412: AESSXF | J412: 100018879 | K412: AESSXF | L412: 0.5SQ | M412: L | N412: NPS | O412: 10000 | P412: 완제품 | Q412: AESSXF 0.5SQ(완제품) | R412: A/R송장 (IN) | S412: 10000 | T412: M | U412: 48.17 | V412: 0.5 | W412: 4992
A413: 7월 | B413: 顾客 | C413: 內需 | D413: -無- | E413: C00001 | F413: 江苏京信电子有限公司 | G413: 江苏京信电子有限公司(Cable) | H413: 자동차(조사) | I413: AESSXF | J413: 100004113 | K413: AESSXF | L413: 2.5SQ | M413: B | O413: 400 | P413: 완제품 | Q413: AESSXF 2.5SQ(완제품) | R413: A/R송장 (IN) | S413: 400 | T413: M | U413: 9.57 | V413: 1.86 | W413: 743.2
A414: 7월 | B414: 顾客 | C414: 內需 | D414: -無- | E414: C00001 | F414: 江苏京信电子有限公司 | G414: 江苏京信电子有限公司(Cable) | H414: 자동차(조사) | I414: AESSXF | J414: 100004040 | K414: AESSXF | L414: 1.25SQ | M414: P | O414: 500 | P414: 완제품 | Q414: AESSXF 1.25SQ(완제품) | R414: A/R송장 (IN) | S414: 1000 | T414: M | U414: 11.64 | V414: 0.95 | W414: 949.2
A415: 7월 | B415: 顾客 | C415: 內需 | D415: -無- | E415: C00001 | F415: 江苏京信电子有限公司 | G415: 江苏京信电子有限公司(Cable) | H415: 자동차(조사) | I415: AESSXF | J415: 100003992 | K415: AESSXF | L415: 0.75SQ | M415: Y | O415: 1000 | P415: 완제품 | Q415: AESSXF 0.75SQ(완제품) | R415: A/R송장 (IN) | S415: 1000 | T415: M | U415: 7.06 | V415: 0.69 | W415: 686.7
A416: 7월 | B416: 顾客 | C416: 內需 | D416: -無- | E416: C00001 | F416: 江苏京信电子有限公司 | G416: 江苏京信电子有限公司(Cable) | H416: 자동차(조사) | I416: AESSXF | J416: 100003926 | K416: AESSXF | L416: 0.75SQ | M416: Br | O416: 1000 | P416: 완제품 | Q416: AESSXF 0.75SQ(완제품) | R416: A/R송장 (IN) | S416: 1000 | T416: M | U416: 7.06 | V416: 0.69 | W416: 686.7
...

Sheet Sheet8
B3: 합계 : 동중량 | C3: 열 레이블
B4: 행 레이블 | C4: 1월 | D4: 2월 | E4: 3월 | F4: (비어 있음) | G4: 총합계
B5: (비어 있음) | J5: 1월 | K5: 2월 | L5: 3월
B6: Kyungshin Cable CO.,LTD | C6: 175475.32 | D6: 85345.08 | E6: 46172.53 | G6: 306992.93 | I6: └ 江苏京信(강소경신) | J6: =GETPIVOTDATA("공급가액",$B$3,"월","1월","거래처명","江苏京信电子有限公司") -> #REF! | K6: =GETPIVOTDATA("공급가액",$B$3,"월","2월","거래처명","江苏京信电子有限公司") -> #REF! | L6: =GETPIVOTDATA("공급가액",$B$3,"월","3월","거래처명","江苏京信电子有限公司") -> #REF!
B7: Kyungshin Cable international corporation | C7: 116942.64 | D7: 88103.82 | E7: 125210.98 | G7: 330257.44 | I7: └ KSCI | J7: =GETPIVOTDATA("공급가액",$B$3,"월","1월","거래처명","Kyungshin Cable international corporation") -> #REF! | K7: =GETPIVOTDATA("공급가액",$B$3,"월","2월","거래처명","Kyungshin Cable international corporation") -> #REF! | L7: =GETPIVOTDATA("공급가액",$B$3,"월","3월","거래처명","Kyungshin Cable international corporation") -> #REF!
B8: Kyungshin(안휘경신)韩国京信电子 | C8: 47169.42 | D8: 33374.12 | E8: 41415.26 | G8: 121958.8 | I8: └안휘경신(B/B) | J8: =GETPIVOTDATA("공급가액",$B$3,"월","1월","거래처명","Kyungshin(안휘경신)韩国京信电子") -> #REF! | K8: =GETPIVOTDATA("공급가액",$B$3,"월","2월","거래처명","Kyungshin(안휘경신)韩国京信电子") -> #REF! | L8: =GETPIVOTDATA("공급가액",$B$3,"월","3월","거래처명","Kyungshin(안휘경신)韩国京信电子") -> #REF!
A9: 강소경신전자 | B9: 江苏京信电子有限公司 | C9: 163601.74 | D9: 106492.62 | E9: 179044.9 | G9: 449139.26 | I9: └ 新进(신진) | J9: =GETPIVOTDATA("공급가액",$B$3,"월","1월","거래처명","江苏新进汽车配件有限公司") -> #REF! | K9: =GETPIVOTDATA("공급가액",$B$3,"월","2월","거래처명","江苏新进汽车配件有限公司") -> #REF! | L9: =GETPIVOTDATA("공급가액",$B$3,"월","3월","거래처명","江苏新进汽车配件有限公司") -> #REF!
A10: 강소신진자동차부품유한공사 | B10: 江苏新进汽车配件有限公司 | C10: 2613.41 | D10: 673.29 | E10: 776.08 | G10: 4062.78 | I10: └ KSC | J10: =GETPIVOTDATA("공급가액",$B$3,"월","1월","거래처명","Kyungshin Cable CO.,LTD") -> #REF! | K10: =GETPIVOTDATA("공급가액",$B$3,"월","2월","거래처명","Kyungshin Cable CO.,LTD") -> #REF! | L10: =GETPIVOTDATA("공급가액",$B$3,"월","3월","거래처명","Kyungshin Cable CO.,LTD") -> #REF!
A11: 강소아현특센서유한공사 | B11: 江苏阿现特传感器有限公司 | I11: └ 상해리어 | J11: =GETPIVOTDATA("공급가액",$B$3,"월","1월","거래처명","上海李尔汽车部件有限公司济宁分公司") -> #REF! | K11: =GETPIVOTDATA("공급가액",$B$3,"월","2월","거래처명","上海李尔汽车部件有限公司济宁分公司") -> #REF! | L11: =GETPIVOTDATA("공급가액",$B$3,"월","3월","거래처명","上海李尔汽车部件有限公司济宁分公司") -> #REF!
A12: 곤산신흥전자 | B12: 昆山信兴电子有限公司 | C12: 1033.98 | D12: 1064.57 | E12: 1188.81 | G12: 3287.36 | I12: └ 기타 | J12: =J13-J11-J10-J9-J8-J7-J6 -> #REF! | K12: =K13-K11-K10-K9-K8-K7-K6 -> #REF! | L12: =L13-L11-L10-L9-L8-L7-L6 -> #REF!
A13: 쿤산상하이광자동차전기 | B13: 昆山沪光汽车电器股份有限公司 | J13: =GETPIVOTDATA("공급가액",$B$3,"월","1월") -> #REF! | K13: =GETPIVOTDATA("공급가액",$B$3,"월","2월") -> #REF! | L13: =GETPIVOTDATA("공급가액",$B$3,"월","3월") -> #REF!
A14: 대관자동차전자(다롄)유한공사 | B14: 大观汽车电子（大连）有限公司 | C14: 195.78 | D14: 326.87 | E14: 209.43 | G14: 732.08
A15: 텍사스 홀딩스 | B15: 德州波尼陀电子有限公司
A16: 우후박캉전기 | B16: 芜湖博康机电有限公司
A17: 베이징 신진자동차부품유한공사 | B17: 北京新进汽车零部件有限公司
A18: 상주경복기전 | B18: 常州庆福机电有限公司 | C18: 512.46 | D18: 806.23 | E18: 670.73 | G18: 1989.42
A19: 조슈 게이신 전선 (덴소) | B19: 常州京信电线 (电装) | D19: 502.87 | G19: 502.87
A20: 상해리어자동차부품유한공사 제녕지사 | B20: 上海李尔汽车部件有限公司济宁分公司 | C20: 43947.08 | D20: 24653.46 | E20: 33435.45 | G20: 102035.99
A21: 상해해라전자유한공사 | B21: 上海海拉电子有限公司 | C21: 1268.18 | D21: 925.68 | E21: 960.39 | G21: 3154.25
A22: 러링유라전기조립유한공사 | B22: 乐陵裕罗电器装配有限公司
A23: 앱티브 커넥터 시스템(난퉁)유한공사 | B23: 安波福连接器系统（南通）有限公司 | C23: 1297.78 | D23: 443.95 | E23: 443.95 | G23: 2185.68
A24: 염성세명전자부품유한공사 | B24: 盐城世明电子器件有限公司 | C24: 1817.41 | D24: 646.29 | E24: 1149.95 | G24: 3613.65
A25: 염성시성광달자동차부품 | B25: 盐城市晟广达汽车零部件有限公司 | C25: 2712.7 | D25: 1476.17 | E25: 11356.5 | G25: 15545.37
A26: 염성통명자동차부품유한공사 | B26: 盐城通铭汽车配件有限公司 | C26: 299.17 | D26: 273.09 | E26: 248.26 | G26: 820.52
A27: 웨이하이밍환무역유한공사 | B27: 威海明焕贸易有限公司
A28: 웨이하이 태광전기 | B28: 威海太光机电有限公司 | C28: 243.11 | E28: 316.86 | G28: 559.97
A29: 칭다오징신전선 | B29: 青岛京信电线有限公司 | C29: 1001.72 | D29: 855 | E29: 855 | G29: 2711.72
A30: 허비톈하이글로벌일렉트릭 | B30: 鹤壁天海环球电器有限公司 | E30: 129.86 | G30: 129.86
B31: 총합계 | C31: 560131.9 | D31: 345963.11 | E31: 443584.94 | G31: 1349680
E32: =GETPIVOTDATA("동중량",$B$3,"월","3월")-GETPIVOTDATA("동중량",$B$3,"월","3월","거래처명","Kyungshin(안휘경신)韩国京信电子") -> 402169.68

Sheet 损益表 _年计划(손익 년계획)
B2: 2026年 经营计划 _ 损益表 _全体 | C2: =C4*185/100000000 -> 997.08553 | D2: =D4*185/100000000 -> 805.48209 | E2: =E4*195/100000000 -> 755.38697 | Q2: (단위:RMB)
B3: 区分 | C3: 2025년 계획 | D3: 2025년 실적(예상) | E3: 2026년 계획 | F3: 1月 | G3: 2月 | H3: 3月 | I3: 4月 | J3: 5月 | K3: 6月 | L3: 7月 | M3: 8月 | N3: 9月 | O3: 10月 | P3: 11月 | Q3: 12月 | S3: KRW
B4: Ⅰ. 销售额_매출액 | C4: =+C5+C6 -> 5.3896515e+08 | D4: =+D5+D6 -> 4.3539572e+08 | E4: =SUM(F4:Q4) -> 3.8737793e+08 | F4: =+F5+F6 -> 31872580 | G4: =+G5+G6 -> 24858017 | H4: =+H5+H6 -> 36347429 | I4: =+I5+I6 -> 35770609 | J4: =+J5+J6 -> 28991636 | K4: =+K5+K6 -> 33665318 | L4: =+L5+L6 -> 34937848 | M4: =+M5+M6 -> 26487330 | ... Q4: =+Q5+Q6 -> 36507966 | S4: =E4*195 -> 7.5538697e+10
B5: 전선 | C5: =+C88 -> 5.2620258e+08 | D5: =+D88 -> 4.1249014e+08 | E5: =SUM(F5:Q5) -> 3.608939e+08 | F5: =+F88 -> 29487286 | G5: =+G88 -> 22463255 | H5: =+H88 -> 33794347 | I5: =+I88 -> 32839243 | J5: =+J88 -> 28503902 | K5: =+K88 -> 31417919 | L5: =+L88 -> 32690449 | M5: =+M88 -> 24239931 | ... Q5: =+Q88 -> 34260567 | S5: =E5*195 -> 7.0374311e+10
B6: 전장 | C6: =+C182 -> 12762577 | D6: =+D182 -> 22905584 | E6: =SUM(F6:Q6) -> 26484031 | F6: =+F182 -> 2385294.1 | G6: =+G182 -> 2394762.2 | H6: =+H182 -> 2553081.7 | I6: =+I182 -> 2931366.2 | J6: =+J182 -> 487733.4 | K6: =+K182 -> 2247399 | L6: =+L182 -> 2247399 | M6: =+M182 -> 2247399 | ... Q6: =+Q182 -> 2247399 | S6: =E6*195 -> 5.164386e+09
B7: 1. 产品销售_제품매출 | C7: =+C9+C10 -> 4.5692538e+08 | D7: =+D9+D10 -> 4.0073197e+08 | E7: =SUM(F7:Q7) -> 3.6907841e+08 | F7: =+F9+F10 -> 30325088 | G7: =+G9+G10 -> 23682224 | H7: =+H9+H10 -> 34641202 | I7: =+I9+I10 -> 34120302 | J7: =+J9+J10 -> 27565289 | K7: =+K9+K10 -> 32089484 | L7: =+L9+L10 -> 33224963 | M7: =+M9+M10 -> 25284403 | ... Q7: =+Q9+Q10 -> 34783185 | S7: =E7*195 -> 7.197029e+10
B8: (사업부별) | E8: =SUM(F8:Q8) -> 0
B9: 전선 | C9: =+C89 -> 4.441628e+08 | D9: =+D89 -> 3.7782639e+08 | E9: =SUM(F9:Q9) -> 3.4259438e+08 | F9: =+F89 -> 27939794 | G9: =+G89 -> 21287462 | H9: =+H89 -> 32088121 | I9: =+I89 -> 31188936 | J9: =+J89 -> 27077556 | K9: =+K89 -> 29842085 | L9: =+L89 -> 30977564 | M9: =+M89 -> 23037004 | ... Q9: =+Q89 -> 32535786
B10: 전장 | C10: =+C182 -> 12762577 | D10: =+D182 -> 22905584 | E10: =SUM(F10:Q10) -> 26484031 | F10: =+F182 -> 2385294.1 | G10: =+G182 -> 2394762.2 | H10: =+H182 -> 2553081.7 | I10: =+I182 -> 2931366.2 | J10: =+J182 -> 487733.4 | K10: =+K182 -> 2247399 | L10: =+L182 -> 2247399 | M10: =+M182 -> 2247399 | ... Q10: =+Q182 -> 2247399
B11: 2.商品销售_상품매출 | C11: =+C13+C14 -> 79580635 | D11: =+D13+D14 -> 30442991 | E11: =SUM(F11:Q11) -> 14001788 | F11: =+F13+F14 -> 1200153.3 | G11: =+G13+G14 -> 914402.51 | H11: =+H13+H14 -> 1314453.6 | I11: =+I13+I14 -> 1257303.4 | J11: =+J13+J14 -> 1085853 | K11: =+K13+K14 -> 1200153.3 | L11: =+L13+L14 -> 1314453.6 | M11: =+M13+M14 -> 914402.51 | ... Q11: =+Q13+Q14 -> 1314453.6 | S11: =E11*195 -> 2.7303487e+09
B12: (사업부별) | E12: =SUM(F12:Q12) -> 0
B13: 전선 | C13: =+C104 -> 79580635 | D13: =+D104 -> 30442991 | E13: =SUM(F13:Q13) -> 14001788 | F13: =+F104 -> 1200153.3 | G13: =+G104 -> 914402.51 | H13: =+H104 -> 1314453.6 | I13: =+I104 -> 1257303.4 | J13: =+J104 -> 1085853 | K13: =+K104 -> 1200153.3 | L13: =+L104 -> 1314453.6 | M13: =+M104 -> 914402.51 | ... Q13: =+Q104 -> 1314453.6
B14: 전장 | E14: =SUM(F14:Q14) -> 0
B15: 3.其他销售_기타매출 | C15: =+C105+C190 -> 2459135.8 | D15: =+D105+D190 -> 4261068.1 | E15: =SUM(F15:Q15) -> 4297736 | F15: =+F105+F190 -> 347338.59 | G15: =+G105+G190 -> 261390.66 | H15: =+H105+H190 -> 391773.03 | I15: =+I105+I190 -> 393003.65 | J15: =+J105+J190 -> 340493.63 | K15: =+K105+K190 -> 375680.54 | L15: =+L105+L190 -> 398431.49 | M15: =+M105+M190 -> 288524.31 | ... Q15: =+Q105+Q190 -> 410326.76 | S15: =E15*195 -> 8.3805852e+08
B16: Ⅱ. 销售成本_매출원가 | C16: =SUM(C17:C21) -> 4.9020492e+08 | D16: =SUM(D17:D21) -> 3.8929969e+08 | E16: =SUM(F16:Q16) -> 3.3657951e+08 | F16: =SUM(F17:F21) -> 27540933 | G16: =SUM(G17:G21) -> 21734973 | H16: =SUM(H17:H21) -> 31752613 | I16: =SUM(I17:I21) -> 30798806 | J16: =SUM(J17:J21) -> 25194419 | K16: =SUM(K17:K21) -> 29343630 | L16: =SUM(L17:L21) -> 29822505 | M16: =SUM(M17:M21) -> 23383263 | ... Q16: =SUM(Q17:Q21) -> 32026325 | S16: =E16*195 -> 6.5633005e+10
B17: 1. 产品销售成本_제품매출원가 | C17: =+C107+C192 -> 4.2464409e+08 | D17: =+D107+D192 -> 3.5899559e+08 | E17: =SUM(F17:Q17) -> 3.2188438e+08 | F17: =+F107+F192 -> 26400983 | G17: =+G107+G192 -> 20844010 | H17: =+H107+H192 -> 30200116 | I17: =+I107+I192 -> 29611649 | J17: =+J107+J192 -> 24148884 | K17: =+K107+K192 -> 27888925 | L17: =+L107+L192 -> 28504141 | M17: =+M107+M192 -> 22479349 | ... Q17: =+Q107+Q192 -> 30466532
B18: 2. 상품매출원가 | C18: =+C108+C193 -> 65560832 | D18: =+D108+D193 -> 29206061 | E18: =SUM(F18:Q18) -> 11565759 | F18: =+F108+F193 -> 991350.79 | G18: =+G108+G193 -> 755314.88 | H18: =+H108+H193 -> 1085765.1 | I18: =+I108+I193 -> 1038558 | J18: =+J108+J193 -> 896936.43 | K18: =+K108+K193 -> 991350.79 | L18: =+L108+L193 -> 1085765.1 | M18: =+M108+M193 -> 755314.88 | ... Q18: =+Q108+Q193 -> 1085765.1
B19: 3. 반제품매출원가 | C19: =+C109+C194 -> 0 | D19: =+D109+D194 -> 0 | E19: =SUM(F19:Q19) -> 0 | F19: =+F109+F194 -> 0 | G19: =+G109+G194 -> 0 | H19: =+H109+H194 -> 0 | I19: =+I109+I194 -> 0 | J19: =+J109+J194 -> 0 | K19: =+K109+K194 -> 0 | L19: =+L109+L194 -> 0 | M19: =+M109+M194 -> 0 | ... Q19: =+Q109+Q194 -> 0
B20: 4. 기타매출원가 | C20: =+C110+C195 -> 0 | D20: =+D110+D195 -> -1078706 | E20: =SUM(F20:Q20) -> 0 | F20: =+F110+F195 -> 0 | G20: =+G110+G195 -> 0 | H20: =+H110+H195 -> 0 | I20: =+I110+I195 -> 0 | J20: =+J110+J195 -> 0 | K20: =+K110+K195 -> 0 | L20: =+L110+L195 -> 0 | M20: =+M110+M195 -> 0 | ... Q20: =+Q110+Q195 -> 0
B21: 5. 영업부가세 | C21: =+C111+C196 -> 0 | D21: =+D111+D196 -> 2176739.4 | E21: =SUM(F21:Q21) -> 3129377.6 | F21: =+F111+F196 -> 148598.81 | G21: =+G111+G196 -> 135648.48 | H21: =+H111+H196 -> 466731.33 | I21: =+I111+I196 -> 148598.81 | J21: =+J111+J196 -> 148598.81 | K21: =+K111+K196 -> 463353.82 | L21: =+L111+L196 -> 232598.81 | M21: =+M111+M196 -> 148598.81 | ... Q21: =+Q111+Q196 -> 474027.82 | S21: 매입세 소진으로 세금 증가
B22: Ⅲ.卖出毛利_매출총이익 | C22: =+C4-C16 -> 48760232 | D22: =+D4-D16 -> 46096033 | E22: =SUM(F22:Q22) -> 50798418 | F22: =+F4-F16 -> 4331647.3 | G22: =+G4-G16 -> 3123044.3 | H22: =+H4-H16 -> 4594816.2 | I22: =+I4-I16 -> 4971803.2 | J22: =+J4-J16 -> 3797216.4 | K22: =+K4-K16 -> 4321687.9 | L22: =+L4-L16 -> 5115343.5 | M22: =+M4-M16 -> 3104067 | ... Q22: =+Q4-Q16 -> 4481640.5 | S22: =E22*195 -> 9.9056914e+09
B23: (利润率) | C23: =C22/C4 -> 0.090470101 | D23: =D22/D4 -> 0.10587158 | E23: =E22/E4 -> 0.131134 | F23: =F22/F4 -> 0.13590514 | G23: =G22/G4 -> 0.12563529 | H23: =H22/H4 -> 0.12641379 | I23: =I22/I4 -> 0.13899129 | J23: =J22/J4 -> 0.13097627 | ... Q23: =Q22/Q4 -> 0.12275788
B24: Ⅲ.一般管理费_판매관리비 | C24: =+C114+C199 -> 28743375 | D24: =+D114+D199 -> 28187612 | E24: =SUM(F24:Q24) -> 27893281 | F24: =+F114+F199 -> 2192567.6 | G24: =+G114+G199 -> 2221732.2 | H24: =+H114+H199 -> 2515781.7 | I24: =+I114+I199 -> 2301102.6 | J24: =+J114+J199 -> 2103112.1 | K24: =+K114+K199 -> 2497391.7 | L24: =+L114+L199 -> 2258978.1 | M24: =+M114+M199 -> 2009778.7 | ... Q24: =+Q114+Q199 -> 2501426.5 | S24: =E24*195 -> 5.4391898e+09
B25: 1..급여 | C25: =+C115+C200 -> 4976222.9 | D25: =+D115+D200 -> 4475753.8 | E25: =SUM(F25:Q25) -> 4522311 | F25: =+F115+F200 -> 366018.8 | G25: =+G115+G200 -> 359423.6 | H25: =+H115+H200 -> 365469.2 | I25: =+I115+I200 -> 368275.84 | J25: =+J115+J200 -> 367320 | K25: =+K115+K200 -> 368642 | L25: =+L115+L200 -> 368642 | M25: =+M115+M200 -> 375444.2 | ... Q25: =+Q115+Q200 -> 474047.64 | R25: OK
B26: 2.상여 | C26: =+C116+C201 -> 0 | D26: =+D116+D201 -> 0 | E26: =SUM(F26:Q26) -> 0 | F26: =+F116+F201 -> 0 | G26: =+G116+G201 -> 0 | H26: =+H116+H201 -> 0 | I26: =+I116+I201 -> 0 | J26: =+J116+J201 -> 0 | K26: =+K116+K201 -> 0 | L26: =+L116+L201 -> 0 | M26: =+M116+M201 -> 0 | ... Q26: =+Q116+Q201 -> 0
B27: 3.잡급 | C27: =+C117+C202 -> 0 | D27: =+D117+D202 -> 0 | E27: =SUM(F27:Q27) -> 0 | F27: =+F117+F202 -> 0 | G27: =+G117+G202 -> 0 | H27: =+H117+H202 -> 0 | I27: =+I117+I202 -> 0 | J27: =+J117+J202 -> 0 | K27: =+K117+K202 -> 0 | L27: =+L117+L202 -> 0 | M27: =+M117+M202 -> 0 | ... Q27: =+Q117+Q202 -> 0
B28: 4. 퇴직급여 | C28: =+C118+C203 -> 0 | D28: =+D118+D203 -> 0 | E28: =SUM(F28:Q28) -> 0 | F28: =+F118+F203 -> 0 | G28: =+G118+G203 -> 0 | H28: =+H118+H203 -> 0 | I28: =+I118+I203 -> 0 | J28: =+J118+J203 -> 0 | K28: =+K118+K203 -> 0 | L28: =+L118+L203 -> 0 | M28: =+M118+M203 -> 0 | ... Q28: =+Q118+Q203 -> 0
B29: 5.福利费_복리후생비 | C29: =+C119+C204 -> 1420273.3 | D29: =+D119+D204 -> 1961270.9 | E29: =SUM(F29:Q29) -> 1938248.2 | F29: =+F119+F204 -> 95067.5 | G29: =+G119+G204 -> 363580 | H29: =+H119+H204 -> 129035 | I29: =+I119+I204 -> 95317.5 | J29: =+J119+J204 -> 139953.93 | K29: =+K119+K204 -> 126477.5 | L29: =+L119+L204 -> 96877.5 | M29: =+M119+M204 -> 92830 | ... Q29: =+Q119+Q204 -> 158495.36 | R29: OK
B30: 6.差旅交通费_여비교통비 | C30: =+C120+C205 -> 146011.42 | D30: =+D120+D205 -> 184183.93 | E30: =SUM(F30:Q30) -> 171834.41 | F30: =+F120+F205 -> 14162.295 | G30: =+G120+G205 -> 11828.41 | H30: =+H120+H205 -> 15935.431 | I30: =+I120+I205 -> 16140.865 | J30: =+J120+J205 -> 11942.006 | K30: =+K120+K205 -> 14879.5 | L30: =+L120+L205 -> 15527.53 | M30: =+M120+M205 -> 11969.481 | ... Q30: =+Q120+Q205 -> 16034.294 | R30: OK
B31: 7.招待费_접대비 | C31: =+C121+C206 -> 31091.396 | D31: =+D121+D206 -> 110557.68 | E31: =SUM(F31:Q31) -> 84837.201 | F31: =+F121+F206 -> 6969.6971 | G31: =+G121+G206 -> 5776.522 | H31: =+H121+H206 -> 7856.8089 | I31: =+I121+I206 -> 7919.8322 | J31: =+J121+J206 -> 6045.8265 | K31: =+K121+K206 -> 7351.3164 | L31: =+L121+L206 -> 7682.3238 | M31: =+M121+M206 -> 5864.9061 | ... Q31: =+Q121+Q206 -> 7941.1742 | R31: OK
B32: 8.通信费_통신비 | C32: =+C122+C207 -> 101595.14 | D32: =+D122+D207 -> 106135.14 | E32: =SUM(F32:Q32) -> 112496.14 | F32: =+F122+F207 -> 9114.9887 | G32: =+G122+G207 -> 7301.315 | H32: =+H122+H207 -> 10357.473 | I32: =+I122+I207 -> 10223.692 | J32: =+J122+J207 -> 8865.2086 | K32: =+K122+K207 -> 9776.8071 | L32: =+L122+L207 -> 10278.36 | M32: =+M122+M207 -> 7524.553 | ... Q32: =+Q122+Q207 -> 10670.577 | R32: OK | T32: 1050
B33: 9水电气费_수도광열비 | C33: =+C123+C208 -> 13324.884 | D33: =+D123+D208 -> 23127.26 | E33: =SUM(F33:Q33) -> 25345.852 | F33: =+F123+F208 -> 2053.6452 | G33: =+G123+G208 -> 1645.0169 | H33: =+H123+H208 -> 2333.582 | I33: =+I123+I208 -> 2303.4407 | J33: =+J123+J208 -> 1997.3687 | K33: =+K123+K208 -> 2202.7556 | L33: =+L123+L208 -> 2315.7575 | M33: =+M123+M208 -> 1695.3133 | ... Q33: =+Q123+Q208 -> 2404.1258 | R33: OK | T33: 849 | U33: =T33/T32 -> 0.80857143
B34: 10.电费_전력비 | C34: =+C124+C209 -> 0 | D34: =+D124+D209 -> 0 | E34: =SUM(F34:Q34) -> 0 | F34: =+F124+F209 -> 0 | G34: =+G124+G209 -> 0 | H34: =+H124+H209 -> 0 | I34: =+I124+I209 -> 0 | J34: =+J124+J209 -> 0 | K34: =+K124+K209 -> 0 | L34: =+L124+L209 -> 0 | M34: =+M124+M209 -> 0 | ... Q34: =+Q124+Q209 -> 0 | T34: 941 | U34: =T33/T34 -> 0.90223167
B35: 11.税金以及附加_세금과공과 | C35: =+C125+C210 -> 341154.04 | D35: =+D125+D210 -> 85853.81 | E35: =SUM(F35:Q35) -> 0 | F35: =+F125+F210 -> 0 | G35: =+G125+G210 -> 0 | H35: =+H125+H210 -> 0 | I35: =+I125+I210 -> 0 | J35: =+J125+J210 -> 0 | K35: =+K125+K210 -> 0 | L35: =+L125+L210 -> 0 | M35: =+M125+M210 -> 0 | ... Q35: =+Q125+Q210 -> 0
B36: 12.折旧费_감가상각비 | C36: =+C126+C211 -> 951021.97 | D36: =+D126+D211 -> 1088671.3 | E36: =SUM(F36:Q36) -> 1120391.3 | F36: =+F126+F211 -> 93365.94 | G36: =+G126+G211 -> 93365.94 | H36: =+H126+H211 -> 93365.94 | I36: =+I126+I211 -> 93365.94 | J36: =+J126+J211 -> 93365.94 | K36: =+K126+K211 -> 93365.94 | L36: =+L126+L211 -> 93365.94 | M36: =+M126+M211 -> 93365.94 | ... Q36: =+Q126+Q211 -> 93365.94 | R36: OK
B37: 13.支付租金_지급임차료 | C37: =+C127+C212 -> 0 | D37: =+D127+D212 -> 0 | E37: =SUM(F37:Q37) -> 0 | F37: =+F127+F212 -> 0 | G37: =+G127+G212 -> 0 | H37: =+H127+H212 -> 0 | I37: =+I127+I212 -> 0 | J37: =+J127+J212 -> 0 | K37: =+K127+K212 -> 0 | L37: =+L127+L212 -> 0 | M37: =+M127+M212 -> 0 | ... Q37: =+Q127+Q212 -> 0
B38: 14.维修费_수선비 | C38: =+C128+C213 -> 632928.86 | D38: =+D128+D213 -> 1147433.8 | E38: =SUM(F38:Q38) -> 1060000 | F38: =+F128+F213 -> 20000 | G38: =+G128+G213 -> 20000 | H38: =+H128+H213 -> 220000 | I38: =+I128+I213 -> 30000 | J38: =+J128+J213 -> 20000 | K38: =+K128+K213 -> 240000 | L38: =+L128+L213 -> 20000 | M38: =+M128+M213 -> 30000 | ... Q38: =+Q128+Q213 -> 40000 | R38: OK
B39: 15.保险费_보험료 | C39: =+C129+C214 -> 432256.32 | D39: =+D129+D214 -> 441647.95 | E39: =SUM(F39:Q39) -> 647195.68 | F39: =+F129+F214 -> 53267.14 | G39: =+G129+G214 -> 53267.14 | H39: =+H129+H214 -> 53267.14 | I39: =+I129+I214 -> 53267.14 | J39: =+J129+J214 -> 53267.14 | K39: =+K129+K214 -> 56367.14 | L39: =+L129+L214 -> 54082.14 | M39: =+M129+M214 -> 54082.14 | ... Q39: =+Q129+Q214 -> 54082.14 | R39: OK
B40: 16.车辆维修费_차량유지비 | C40: =+C130+C215 -> 389628.96 | D40: =+D130+D215 -> 419390.55 | E40: =SUM(F40:Q40) -> 416808 | F40: =+F130+F215 -> 34734 | G40: =+G130+G215 -> 34734 | H40: =+H130+H215 -> 34734 | I40: =+I130+I215 -> 34734 | J40: =+J130+J215 -> 34734 | K40: =+K130+K215 -> 34734 | L40: =+L130+L215 -> 34734 | M40: =+M130+M215 -> 34734 | ... Q40: =+Q130+Q215 -> 34734 | R40: OK
B41: 17.经常研究开发费用_경상연구개발비 | C41: =+C131+C216 -> 0 | D41: =+D131+D216 -> 1304248.1 | E41: =SUM(F41:Q41) -> 152064.26 | F41: =+F131+F216 -> 31388.61 | G41: =+G131+G216 -> 21094.31 | H41: =+H131+H216 -> 9663 | I41: =+I131+I216 -> 9853.08 | J41: =+J131+J216 -> 9789.43 | K41: =+K131+K216 -> 9859.77 | L41: =+L131+L216 -> 9859.77 | M41: =+M131+M216 -> 10633.66 | ... Q41: =+Q131+Q216 -> 9942.4 | R41: OK
B42: 18.运费_운반비 | C42: =+C132+C217 -> 7761059.9 | D42: =+D132+D217 -> 7097261.4 | E42: =SUM(F42:Q42) -> 8093252.3 | F42: =+F132+F217 -> 689866.28 | G42: =+G132+G217 -> 595023.2 | H42: =+H132+H217 -> 712866.28 | I42: =+I132+I217 -> 711866.28 | J42: =+J132+J217 -> 628252.43 | K42: =+K132+K217 -> 703866.28 | L42: =+L132+L217 -> 707866.28 | M42: =+M132+M217 -> 601023.2 | ... Q42: =+Q132+Q217 -> 715866.28 | R42: OK
B43: 19.教育培训费_교육훈련비 | C43: =+C133+C218 -> 84192.412 | D43: =+D133+D218 -> 32656.52 | E43: =SUM(F43:Q43) -> 37748.988 | F43: =+F133+F218 -> 3058.608 | G43: =+G133+G218 -> 2450.0152 | H43: =+H133+H218 -> 3475.5335 | I43: =+I133+I218 -> 3430.6424 | J43: =+J133+J218 -> 2974.7923 | K43: =+K133+K218 -> 3280.6865 | L43: =+L133+L218 -> 3448.9865 | M43: =+M133+M218 -> 2524.9245 | ... Q43: =+Q133+Q218 -> 3580.5984 | R43: OK
B44: 20.图书印刷费_도서인쇄비 | C44: =+C134+C219 -> 0 | D44: =+D134+D219 -> 0 | E44: =SUM(F44:Q44) -> 0 | F44: =+F134+F219 -> 0 | G44: =+G134+G219 -> 0 | H44: =+H134+H219 -> 0 | I44: =+I134+I219 -> 0 | J44: =+J134+J219 -> 0 | K44: =+K134+K219 -> 0 | L44: =+L134+L219 -> 0 | M44: =+M134+M219 -> 0 | ... Q44: =+Q134+Q219 -> 0
B45: 21.会议费_회의비 | C45: =+C135+C220 -> 0 | D45: =+D135+D220 -> 0 | E45: =SUM(F45:Q45) -> 0 | F45: =+F135+F220 -> 0 | G45: =+G135+G220 -> 0 | H45: =+H135+H220 -> 0 | I45: =+I135+I220 -> 0 | J45: =+J135+J220 -> 0 | K45: =+K135+K220 -> 0 | L45: =+L135+L220 -> 0 | M45: =+M135+M220 -> 0 | ... Q45: =+Q135+Q220 -> 0
B46: 22.包装费_포장비 | C46: =+C136+C221 -> 0 | D46: =+D136+D221 -> 0 | E46: =SUM(F46:Q46) -> 0 | F46: =+F136+F221 -> 0 | G46: =+G136+G221 -> 0 | H46: =+H136+H221 -> 0 | I46: =+I136+I221 -> 0 | J46: =+J136+J221 -> 0 | K46: =+K136+K221 -> 0 | L46: =+L136+L221 -> 0 | M46: =+M136+M221 -> 0 | ... Q46: =+Q136+Q221 -> 0
B47: 23.办公用品_사무용품비 | C47: =+C137+C222 -> 322865 | D47: =+D137+D222 -> 340440.12 | E47: =SUM(F47:Q47) -> 256600 | F47: =+F137+F222 -> 10950 | G47: =+G137+G222 -> 22550 | H47: =+H137+H222 -> 8550 | I47: =+I137+I222 -> 25950 | J47: =+J137+J222 -> 17250 | K47: =+K137+K222 -> 28750 | L47: =+L137+L222 -> 13750 | M47: =+M137+M222 -> 26350 | ... Q47: =+Q137+Q222 -> 28550 | R47: OK
B48: 24.消耗品费_소모품비 | C48: =+C138+C223 -> 0 | D48: =+D138+D223 -> 0 | E48: =SUM(F48:Q48) -> 0 | F48: =+F138+F223 -> 0 | G48: =+G138+G223 -> 0 | H48: =+H138+H223 -> 0 | I48: =+I138+I223 -> 0 | J48: =+J138+J223 -> 0 | K48: =+K138+K223 -> 0 | L48: =+L138+L223 -> 0 | M48: =+M138+M223 -> 0 | ... Q48: =+Q138+Q223 -> 0
B49: 25.消耗工具_소모공구 | C49: =+C139+C224 -> 0 | D49: =+D139+D224 -> 0 | E49: =SUM(F49:Q49) -> 0 | F49: =+F139+F224 -> 0 | G49: =+G139+G224 -> 0 | H49: =+H139+H224 -> 0 | I49: =+I139+I224 -> 0 | J49: =+J139+J224 -> 0 | K49: =+K139+K224 -> 0 | L49: =+L139+L224 -> 0 | M49: =+M139+M224 -> 0 | ... Q49: =+Q139+Q224 -> 0
B50: 26.支付手续费_지급수수료 | C50: =+C140+C225 -> 2001241.1 | D50: =+D140+D225 -> 1355318.4 | E50: =SUM(F50:Q50) -> 1872579.4 | F50: =+F140+F225 -> 156048.28 | G50: =+G140+G225 -> 156048.28 | H50: =+H140+H225 -> 156048.28 | I50: =+I140+I225 -> 156048.28 | J50: =+J140+J225 -> 156048.28 | K50: =+K140+K225 -> 156048.28 | L50: =+L140+L225 -> 156048.28 | M50: =+M140+M225 -> 156048.28 | ... Q50: =+Q140+Q225 -> 156048.28 | R50: OK
B51: 27.保管费_보관료 | C51: =+C141+C226 -> 0 | D51: =+D141+D226 -> 0 | E51: =SUM(F51:Q51) -> 0 | F51: =+F141+F226 -> 0 | G51: =+G141+G226 -> 0 | H51: =+H141+H226 -> 0 | I51: =+I141+I226 -> 0 | J51: =+J141+J226 -> 0 | K51: =+K141+K226 -> 0 | L51: =+L141+L226 -> 0 | M51: =+M141+M226 -> 0 | ... Q51: =+Q141+Q226 -> 0
B52: 28.广告宣传费_광고선전비 견본비 | C52: =+C142+C227 -> 9138507.6 | D52: =+D142+D227 -> 7972004.5 | E52: =SUM(F52:Q52) -> 7381568.2 | F52: =+F142+F227 -> 606501.76 | G52: =+G142+G227 -> 473644.49 | H52: =+H142+H227 -> 692824.05 | I52: =+I142+I227 -> 682406.04 | J52: =+J142+J227 -> 551305.78 | K52: =+K142+K227 -> 641789.68 | L52: =+L142+L227 -> 664499.27 | M52: =+M142+M227 -> 505688.06 | ... Q52: =+Q142+Q227 -> 695663.71 | R52: OK
B53: 29.出口收费_수출제비용 | C53: =+C143+C228 -> 0 | D53: =+D143+D228 -> 0 | E53: =SUM(F53:Q53) -> 0 | F53: =+F143+F228 -> 0 | G53: =+G143+G228 -> 0 | H53: =+H143+H228 -> 0 | I53: =+I143+I228 -> 0 | J53: =+J143+J228 -> 0 | K53: =+K143+K228 -> 0 | L53: =+L143+L228 -> 0 | M53: =+M143+M228 -> 0 | ... Q53: =+Q143+Q228 -> 0
B54: 30.下脚料补税_B/B PVC로스 관세 | C54: =+C144+C229 -> 0 | D54: =+D144+D229 -> 0 | E54: =SUM(F54:Q54) -> 0 | F54: =+F144+F229 -> 0 | G54: =+G144+G229 -> 0 | H54: =+H144+H229 -> 0 | I54: =+I144+I229 -> 0 | J54: =+J144+J229 -> 0 | K54: =+K144+K229 -> 0 | L54: =+L144+L229 -> 0 | M54: =+M144+M229 -> 0 | ... Q54: =+Q144+Q229 -> 0
B55: 31.委托加工费_erp/등 사용료 | C55: =+C145+C230 -> 0 | D55: =+D145+D230 -> 0 | E55: =SUM(F55:Q55) -> 0 | F55: =+F145+F230 -> 0 | G55: =+G145+G230 -> 0 | H55: =+H145+H230 -> 0 | I55: =+I145+I230 -> 0 | J55: =+J145+J230 -> 0 | K55: =+K145+K230 -> 0 | L55: =+L145+L230 -> 0 | M55: =+M145+M230 -> 0 | ... Q55: =+Q145+Q230 -> 0
B56: 32.杂费_잡비 은행수수료 등 | C56: =+C146+C231 -> 0 | D56: =+D146+D231 -> 41657.31 | E56: =SUM(F56:Q56) -> 0 | F56: =+F146+F231 -> 0 | G56: =+G146+G231 -> 0 | H56: =+H146+H231 -> 0 | I56: =+I146+I231 -> 0 | J56: =+J146+J231 -> 0 | K56: =+K146+K231 -> 0 | L56: =+L146+L231 -> 0 | M56: =+M146+M231 -> 0 | ... Q56: =+Q146+Q231 -> 0
B57: Ⅳ.营业利润 | C57: =+C22-C24 -> 20016857 | D57: =+D22-D24 -> 17908421 | E57: =SUM(F57:Q57) -> 22905137 | F57: =+F22-F24 -> 2139079.7 | G57: =+G22-G24 -> 901312.06 | H57: =+H22-H24 -> 2079034.5 | I57: =+I22-I24 -> 2670700.6 | J57: =+J22-J24 -> 1694104.2 | K57: =+K22-K24 -> 1824296.2 | L57: =+L22-L24 -> 2856365.3 | M57: =+M22-M24 -> 1094288.3 | ... Q57: =+Q22-Q24 -> 1980214 | S57: =E57*195 -> 4.4665016e+09 | T57: =D57*195 -> 3.492142e+09 | U57: =S57-T57 -> 9.7435963e+08
B58: (利润率) | C58: =C57/C4 -> 0.037139426 | D58: =D57/D4 -> 0.041131366 | E58: =E57/E4 -> 0.059128656 | F58: =F57/F4 -> 0.067113479 | G58: =G57/G4 -> 0.036258405 | H58: =H57/H4 -> 0.057198941 | I58: =I57/I4 -> 0.074661872 | J58: =J57/J4 -> 0.058434241 | ... Q58: =Q57/Q4 -> 0.054240601
B59: Ⅳ.其他收入_영업외수익 | C59: =+C149+C234 -> 0 | D59: =+D149+D234 -> 731383.17 | E59: =SUM(F59:Q59) -> 0 | F59: =+F149+F234 -> 0 | G59: =+G149+G234 -> 0 | H59: =+H149+H234 -> 0 | I59: =+I149+I234 -> 0 | J59: =+J149+J234 -> 0 | K59: =+K149+K234 -> 0 | L59: =+L149+L234 -> 0 | M59: =+M149+M234 -> 0 | ... Q59: =+Q149+Q234 -> 0
B60: 1.期投资者收入_단기투자자산익 | C60: =+C150+C235 -> 0 | D60: =+D150+D235 -> 0 | E60: =SUM(F60:Q60) -> 0 | F60: =+F150+F235 -> 0 | G60: =+G150+G235 -> 0 | H60: =+H150+H235 -> 0 | I60: =+I150+I235 -> 0 | J60: =+J150+J235 -> 0 | K60: =+K150+K235 -> 0 | L60: =+L150+L235 -> 0 | M60: =+M150+M235 -> 0 | ... Q60: =+Q150+Q235 -> 0
B61: 2.外汇买卖收益_외환차익 | C61: =+C151+C236 -> 0 | D61: =+D151+D236 -> 191641.63 | E61: =SUM(F61:Q61) -> 0 | F61: =+F151+F236 -> 0 | G61: =+G151+G236 -> 0 | H61: =+H151+H236 -> 0 | I61: =+I151+I236 -> 0 | J61: =+J151+J236 -> 0 | K61: =+K151+K236 -> 0 | L61: =+L151+L236 -> 0 | M61: =+M151+M236 -> 0 | ... Q61: =+Q151+Q236 -> 0
B62: 3.外币折算收益_외화환산이익 | C62: =+C152+C237 -> 0 | D62: =+D152+D237 -> 0 | E62: =SUM(F62:Q62) -> 0 | F62: =+F152+F237 -> 0 | G62: =+G152+G237 -> 0 | H62: =+H152+H237 -> 0 | I62: =+I152+I237 -> 0 | J62: =+J152+J237 -> 0 | K62: =+K152+K237 -> 0 | L62: =+L152+L237 -> 0 | M62: =+M152+M237 -> 0 | ... Q62: =+Q152+Q237 -> 0
B63: 4.前期差错更正的利润_전기오류수정이익 | C63: =+C153+C238 -> 0 | D63: =+D153+D238 -> 0 | E63: =SUM(F63:Q63) -> 0 | F63: =+F153+F238 -> 0 | G63: =+G153+G238 -> 0 | H63: =+H153+H238 -> 0 | I63: =+I153+I238 -> 0 | J63: =+J153+J238 -> 0 | K63: =+K153+K238 -> 0 | L63: =+L153+L238 -> 0 | M63: =+M153+M238 -> 0 | ... Q63: =+Q153+Q238 -> 0
B64: 5.固定资产处理收益_유형자산처분이익 | C64: =+C154+C239 -> 0 | D64: =+D154+D239 -> 182.75 | E64: =SUM(F64:Q64) -> 0 | F64: =+F154+F239 -> 0 | G64: =+G154+G239 -> 0 | H64: =+H154+H239 -> 0 | I64: =+I154+I239 -> 0 | J64: =+J154+J239 -> 0 | K64: =+K154+K239 -> 0 | L64: =+L154+L239 -> 0 | M64: =+M154+M239 -> 0 | ... Q64: =+Q154+Q239 -> 0
B65: 6.利息收益 _이자수익 | C65: =+C155+C240 -> 0 | D65: =+D155+D240 -> 455938.88 | E65: =SUM(F65:Q65) -> 0 | F65: =+F155+F240 -> 0 | G65: =+G155+G240 -> 0 | H65: =+H155+H240 -> 0 | I65: =+I155+I240 -> 0 | J65: =+J155+J240 -> 0 | K65: =+K155+K240 -> 0 | L65: =+L155+L240 -> 0 | M65: =+M155+M240 -> 0 | ... Q65: =+Q155+Q240 -> 0
B66: 7.杂项利润_잡이익 | C66: =+C156+C241 -> 0 | D66: =+D156+D241 -> 83619.91 | E66: =SUM(F66:Q66) -> 0 | F66: =+F156+F241 -> 0 | G66: =+G156+G241 -> 0 | H66: =+H156+H241 -> 0 | I66: =+I156+I241 -> 0 | J66: =+J156+J241 -> 0 | K66: =+K156+K241 -> 0 | L66: =+L156+L241 -> 0 | M66: =+M156+M241 -> 0 | ... Q66: =+Q156+Q241 -> 0
B67: Ⅳ.其他费用_영업외비용 | C67: =+C157+C242 -> 5379528.6 | D67: =+D157+D242 -> 7303601.9 | E67: =SUM(F67:Q67) -> 4235673.7 | F67: =+F157+F242 -> 227283.33 | G67: =+G157+G242 -> 553149.26 | H67: =+H157+H242 -> 265888.89 | I67: =+I157+I242 -> 227283.33 | J67: =+J157+J242 -> 430402.5 | K67: =+K157+K242 -> 380768.15 | L67: =+L157+L242 -> 227283.33 | M67: =+M157+M242 -> 462255.85 | ... Q67: =+Q157+Q242 -> 652321.48 | S67: =E67*195 -> 8.2595637e+08
B68: 1.汇兑损失_외환차손 | C68: =+C158+C243 -> 0 | D68: =+D158+D243 -> 169781.8 | E68: =SUM(F68:Q68) -> 0 | F68: =+F158+F243 -> 0 | G68: =+G158+G243 -> 0 | H68: =+H158+H243 -> 0 | I68: =+I158+I243 -> 0 | J68: =+J158+J243 -> 0 | K68: =+K158+K243 -> 0 | L68: =+L158+L243 -> 0 | M68: =+M158+M243 -> 0 | ... Q68: =+Q158+Q243 -> 0
B69: 2.捐款_기부금 | C69: =+C159+C244 -> 0 | D69: =+D159+D244 -> 0 | E69: =SUM(F69:Q69) -> 0 | F69: =+F159+F244 -> 0 | G69: =+G159+G244 -> 0 | H69: =+H159+H244 -> 0 | I69: =+I159+I244 -> 0 | J69: =+J159+J244 -> 0 | K69: =+K159+K244 -> 0 | L69: =+L159+L244 -> 0 | M69: =+M159+M244 -> 0 | ... Q69: =+Q159+Q244 -> 0
B70: 3.其他的坏账准备_기타의대손상각비 | C70: =+C160+C245 -> 0 | D70: =+D160+D245 -> 0 | E70: =SUM(F70:Q70) -> 0 | F70: =+F160+F245 -> 0 | G70: =+G160+G245 -> 0 | H70: =+H160+H245 -> 0 | I70: =+I160+I245 -> 0 | J70: =+J160+J245 -> 0 | K70: =+K160+K245 -> 0 | L70: =+L160+L245 -> 0 | M70: =+M160+M245 -> 0 | ... Q70: =+Q160+Q245 -> 0
B71: 4.外汇兑换损失_외화환산손실 | C71: =+C161+C246 -> 0 | D71: =+D161+D246 -> 2566014.1 | E71: =SUM(F71:Q71) -> 0 | F71: =+F161+F246 -> 0 | G71: =+G161+G246 -> 0 | H71: =+H161+H246 -> 0 | I71: =+I161+I246 -> 0 | J71: =+J161+J246 -> 0 | K71: =+K161+K246 -> 0 | L71: =+L161+L246 -> 0 | M71: =+M161+M246 -> 0 | ... Q71: =+Q161+Q246 -> 0
B72: 5.短期投资资产损失_단기투자자산손실 | C72: =+C162+C247 -> 0 | D72: =+D162+D247 -> 0 | E72: =SUM(F72:Q72) -> 0 | F72: =+F162+F247 -> 0 | G72: =+G162+G247 -> 0 | H72: =+H162+H247 -> 0 | I72: =+I162+I247 -> 0 | J72: =+J162+J247 -> 0 | K72: =+K162+K247 -> 0 | L72: =+L162+L247 -> 0 | M72: =+M162+M247 -> 0 | ... Q72: =+Q162+Q247 -> 0
B73: 6.盘亏_재고자산감모손실 | C73: =+C163+C248 -> 0 | D73: =+D163+D248 -> 0 | E73: =SUM(F73:Q73) -> 0 | F73: =+F163+F248 -> 0 | G73: =+G163+G248 -> 0 | H73: =+H163+H248 -> 0 | I73: =+I163+I248 -> 0 | J73: =+J163+J248 -> 0 | K73: =+K163+K248 -> 0 | L73: =+L163+L248 -> 0 | M73: =+M163+M248 -> 0 | ... Q73: =+Q163+Q248 -> 0
B74: 7.前期差错更正损失_전기오류수정손실 | C74: =+C164+C249 -> 0 | D74: =+D164+D249 -> 0 | E74: =SUM(F74:Q74) -> 0 | F74: =+F164+F249 -> 0 | G74: =+G164+G249 -> 0 | H74: =+H164+H249 -> 0 | I74: =+I164+I249 -> 0 | J74: =+J164+J249 -> 0 | K74: =+K164+K249 -> 0 | L74: =+L164+L249 -> 0 | M74: =+M164+M249 -> 0 | ... Q74: =+Q164+Q249 -> 0
B75: 8.固定资产处分损失_유형자산처분손실 | C75: =+C165+C250 -> 0 | D75: =+D165+D250 -> 9892.3 | E75: =SUM(F75:Q75) -> 0 | F75: =+F165+F250 -> 0 | G75: =+G165+G250 -> 0 | H75: =+H165+H250 -> 0 | I75: =+I165+I250 -> 0 | J75: =+J165+J250 -> 0 | K75: =+K165+K250 -> 0 | L75: =+L165+L250 -> 0 | M75: =+M165+M250 -> 0 | ... Q75: =+Q165+Q250 -> 0
B76: 9.有形资产减资损失_유형자산감액손실 | C76: =+C166+C251 -> 0 | D76: =+D166+D251 -> 21799.56 | E76: =SUM(F76:Q76) -> 0 | F76: =+F166+F251 -> 0 | G76: =+G166+G251 -> 0 | H76: =+H166+H251 -> 0 | I76: =+I166+I251 -> 0 | J76: =+J166+J251 -> 0 | K76: =+K166+K251 -> 0 | L76: =+L166+L251 -> 0 | M76: =+M166+M251 -> 0 | ... Q76: =+Q166+Q251 -> 0
B77: 10.无形资产减值损失_무형자산감액손실 | C77: =+C167+C252 -> 0 | D77: =+D167+D252 -> 0 | E77: =SUM(F77:Q77) -> 0 | F77: =+F167+F252 -> 0 | G77: =+G167+G252 -> 0 | H77: =+H167+H252 -> 0 | I77: =+I167+I252 -> 0 | J77: =+J167+J252 -> 0 | K77: =+K167+K252 -> 0 | L77: =+L167+L252 -> 0 | M77: =+M167+M252 -> 0 | ... Q77: =+Q167+Q252 -> 0
B78: 11.杂项损失_잡손실 | C78: =+C168+C253 -> 0 | D78: =+D168+D253 -> 80912.85 | E78: =SUM(F78:Q78) -> 0 | F78: =+F168+F253 -> 0 | G78: =+G168+G253 -> 0 | H78: =+H168+H253 -> 0 | I78: =+I168+I253 -> 0 | J78: =+J168+J253 -> 0 | K78: =+K168+K253 -> 0 | L78: =+L168+L253 -> 0 | M78: =+M168+M253 -> 0 | ... Q78: =+Q168+Q253 -> 0
B79: 12.库存资产报废损失_재고자산폐기손실 | C79: =+C169+C254 -> 0 | D79: =+D169+D254 -> 173665.17 | E79: =SUM(F79:Q79) -> 0 | F79: =+F169+F254 -> 0 | G79: =+G169+G254 -> 0 | H79: =+H169+H254 -> 0 | I79: =+I169+I254 -> 0 | J79: =+J169+J254 -> 0 | K79: =+K169+K254 -> 0 | L79: =+L169+L254 -> 0 | M79: =+M169+M254 -> 0 | ... Q79: =+Q169+Q254 -> 0
B80: 13.利息费用_이자비용 | C80: =+C170+C255 -> 5379528.6 | D80: =+D170+D255 -> 4281536.1 | E80: =SUM(F80:Q80) -> 4235673.7 | F80: =+F170+F255 -> 227283.33 | G80: =+G170+G255 -> 553149.26 | H80: =+H170+H255 -> 265888.89 | I80: =+I170+I255 -> 227283.33 | J80: =+J170+J255 -> 430402.5 | K80: =+K170+K255 -> 380768.15 | L80: =+L170+L255 -> 227283.33 | M80: =+M170+M255 -> 462255.85 | ... Q80: =+Q170+Q255 -> 652321.48
B81: 법인세비용 차감전순이익 | C81: =+C57-C67 -> 14637328 | D81: =+D57-D67+D59 -> 11336202 | E81: =SUM(F81:Q81) -> 18669463 | F81: =+F57-F67 -> 1911796.4 | G81: =+G57-G67 -> 348162.8 | H81: =+H57-H67 -> 1813145.6 | I81: =+I57-I67 -> 2443417.3 | J81: =+J57-J67 -> 1263701.7 | K81: =+K57-K67 -> 1443528.1 | L81: =+L57-L67 -> 2629082 | M81: =+M57-M67 -> 632032.47 | ... Q81: =+Q57-Q67 -> 1327892.5 | S81: =E81*195 -> 3.6405453e+09
B82: 1.法人税_기업소득세 | C82: =C81*0.25 -> 3659332 | D82: =D81*0.25 -> 2834050.5 | E82: =SUM(F82:Q82) -> 4667365.7 | F82: =F81*0.25 -> 477949.1 | G82: =G81*0.25 -> 87040.699 | H82: =H81*0.25 -> 453286.39 | I82: =I81*0.25 -> 610854.32 | J82: =J81*0.25 -> 315925.43 | K82: =K81*0.25 -> 360882.02 | L82: =L81*0.25 -> 657270.5 | M82: =M81*0.25 -> 158008.12 | ... Q82: =Q81*0.25 -> 331973.13
B83: 本期纯利-净损失_당기순이익-손실 | C83: =C81-C82 -> 10977996 | D83: =D81-D82 -> 8502151.4 | E83: =SUM(F83:Q83) -> 14002097 | F83: =F81-F82 -> 1433847.3 | G83: =G81-G82 -> 261122.1 | H83: =H81-H82 -> 1359859.2 | I83: =I81-I82 -> 1832563 | J83: =J81-J82 -> 947776.3 | K83: =K81-K82 -> 1082646.1 | L83: =L81-L82 -> 1971811.5 | M83: =M81-M82 -> 474024.35 | ... Q83: =Q81-Q82 -> 995919.39 | S83: =E83*195 -> 2.730409e+09
B84: (利润率)
E85: =+E147+E258 -> 22608639 | F85: =+F147+F258 -> 2123169.9 | G85: =+G147+G258 -> 862591.61 | H85: =+H147+H258 -> 2060422.2 | I85: =+I147+I258 -> 2654790.8 | J85: =+J147+J258 -> 1663976.1 | K85: =+K147+K258 -> 1797642.5 | L85: =+L147+L258 -> 2840455.5 | ... Q85: =+Q147+Q258 -> 1934551.5
B86: 2026年 经营计划 _ 损益表 _电线 | C86: =D88/C88 -> 0.78389988
B87: 区分 | C87: 2025년 계획 | D87: 2025년 실적(예상) | E87: 2026년 계획 | F87: 1月 | G87: 2月 | H87: 3月 | I87: 4月 | J87: 5月 | K87: 6月 | L87: 7月 | M87: 8月 | N87: 9月 | O87: 10月 | P87: 11月 | Q87: 12月
B88: Ⅰ. 销售额_매출액 | C88: 5.2620258e+08 | D88: 4.1249014e+08 | E88: =SUM(F88:Q88) -> 3.608939e+08 | F88: =+F89+F104+F105 -> 29487286 | G88: =+G89+G104+G105 -> 22463255 | H88: =+H89+H104+H105 -> 33794347 | I88: =+I89+I104+I105 -> 32839243 | J88: =+J89+J104+J105 -> 28503902 | K88: =+K89+K104+K105 -> 31417919 | L88: =+L89+L104+L105 -> 32690449 | M88: =+M89+M104+M105 -> 24239931 | ... Q88: =+Q89+Q104+Q105 -> 34260567 | S88: =E88*195 -> 7.0374311e+10
B89: 1. 产品销售_제품매출 | C89: 4.441628e+08 | D89: 3.7782639e+08 | E89: =SUM(F89:Q89) -> 3.4259438e+08 | F89: =F90+F91 -> 27939794 | G89: =G90+G91 -> 21287462 | H89: =H90+H91 -> 32088121 | I89: =I90+I91 -> 31188936 | J89: =J90+J91 -> 27077556 | K89: =K90+K91 -> 29842085 | L89: =L90+L91 -> 30977564 | M89: =M90+M91 -> 23037004 | ... Q89: =Q90+Q91 -> 32535786
B90: 내수매출 | C90: =C89-C91 -> 4.4091976e+08 | D90: =D89-D91 -> 3.712854e+08 | E90: =SUM(F90:Q90) -> 3.0672858e+08 | F90: 25125390 | G90: 19143154 | H90: 29005678 | I90: 27880059 | J90: 24219889 | K90: 26683612 | L90: 27518284 | M90: 20630548 | N90: 27809231 | O90: 23023442 | P90: 26612783 | Q90: 29076506
B91: 경신 BB | C91: 3243043 | D91: 6540987.4 | E91: =SUM(F91:Q91) -> 35865802 | F91: 2814404.4 | G91: 2144308.1 | H91: 3082442.9 | I91: 3308876.9 | J91: 2857666.4 | K91: 3158473.4 | L91: 3459280.4 | M91: 2406456 | N91: 3308876.9 | O91: 2707263 | P91: 3158473.4 | Q91: 3459280.4
B92: (업체별)
B93: └ 江苏京信 | E93: =SUM(F93:Q93) -> 1.9610322e+08 | F93: 16808848 | G93: 12806741 | H93: 18409690 | I93: 17609269 | J93: 15208005 | K93: 16808848 | L93: 18409690 | M93: 12806741 | N93: 17609269 | O93: 14407584 | P93: 16808848 | Q93: 18409690 | S93: =E93*195/1000000 -> 38240.128
B94: └ KSCI | E94: =SUM(F94:Q94) -> 87491665 | F94: 7499285.6 | G94: 5713741.4 | H94: 8213503.3 | I94: 7856394.4 | J94: 6785067.9 | K94: 7499285.6 | L94: 8213503.3 | M94: 5713741.4 | N94: 7856394.4 | O94: 6427959.1 | P94: 7499285.6 | Q94: 8213503.3 | S94: =E94*195/1000000 -> 17060.875
