Workbook

Sheet ★Master Code List
D1: * Maximum Code Capacity 100ea
B2: Don't Delete | D2: ↓ Key in New Code/Project/Item Below | I2: Formula - Don’t delete
B3: No | D3: Code | E3: Project | F3: Item | I3: Code | J3: Project | K3: Item
A4: =IF(E4="Components","2nd","1st") -> 2nd | B4: 1 | D4: BEE22-CT009 | E4: Components | F4: BEV_E_TML_1 | I4: {=_xlfn.SORTBY(D4:F167,A4:A167,1,D4:D167,1)} -> PZ38-10B694-AD | J4: PHEV-E (V710) / (P703) | K4: Main Harness
A5: =IF(E5="Components","2nd","1st") -> 2nd | B5: 2 | D5: BEE22-CT010 | E5: Components | F5: BEV_E_TML_2 | I5: PZ38-10B694-BD | J5: BEV-E1(V710) | K5: Main Harness
A6: =IF(E6="Components","2nd","1st") -> 2nd | B6: 3 | D6: BEE22-CT011 | E6: Components | F6: BEV_E_TML_3 | I6: PZ38-14A033-AB | J6: PHEV-E (V710) / (P703) | K6: BUSBAR - Array to Array (short)
A7: =IF(E7="Components","2nd","1st") -> 1st | B7: 4 | D7: PZ38-10B694-AD | E7: PHEV-E (V710) / (P703) | F7: Main Harness | I7: PZ38-14A033-BB | J7: PHEV-E (V710) / (P703) | K7: BUSBAR - Array to Array (long)
A8: =IF(E8="Components","2nd","1st") -> 1st | B8: 5 | D8: PZ38-14A033-AB | E8: PHEV-E (V710) / (P703) | F8: BUSBAR - Array to Array (short) | I8: PZ38-14A033-CB | J8: PHEV-E (V710) / (P703) | K8: BUSBAR - Array 3 to 4
A9: =IF(E9="Components","2nd","1st") -> 1st | B9: 6 | D9: PZ38-14A033-BB | E9: PHEV-E (V710) / (P703) | F9: BUSBAR - Array to Array (long) | I9: PZ38-14A033-FE | J9: EV-V4 Test Parts | K9: BUSBAR - Array to Array (Straight)_Insert
A10: =IF(E10="Components","2nd","1st") -> 1st | B10: 7 | D10: PZ38-14A033-CB | E10: PHEV-E (V710) / (P703) | F10: BUSBAR - Array 3 to 4 | I10: PZ38-14A033-GD | J10: BEV-E (V710) | K10: BUSBAR - Array to Array (Angled)_Insert
A11: =IF(E11="Components","2nd","1st") -> 1st | B11: 8 | D11: PZ38-14A033-HF | E11: BEV-E (V710) | F11: BUSBAR - Array4 to Array 5_Insert | I11: PZ38-14A033-HF | J11: BEV-E (V710) | K11: BUSBAR - Array4 to Array 5_Insert
A12: =IF(E12="Components","2nd","1st") -> 1st | B12: 9 | D12: PZ38-14A033-LF | E12: BEV-E (V710) | F12: BUSBAR - Array 9 to Pos BEC_Insert | I12: PZ38-14A033-JD | J12: BEV-E1 | K12: BEV-E1 BUSBAR Array 8 to Array 9
A13: =IF(E13="Components","2nd","1st") -> 1st | B13: 10 | D13: PZ38-14A033-MC | E13: BEV-E (V710) | F13: BUSBAR - Pos BEC to DCFC_Protector | I13: PZ38-14A033-KD | J13: BEV-E (V710) | K13: BUSBAR - Array 1 to Neg BEC_Insert
A14: =IF(E14="Components","2nd","1st") -> 1st | B14: 11 | D14: PZ38-14B252-AB | E14: PHEV-E (V710) / (P703) | F14: Jumper | I14: PZ38-14A033-LF | J14: BEV-E (V710) | K14: BUSBAR - Array 9 to Pos BEC_Insert
A15: =IF(E15="Components","2nd","1st") -> 1st | B15: 12 | D15: PZ38-14B680-AD | E15: BEV-E (V710) | F15: PDU | I15: PZ38-14A033-MC | J15: BEV-E (V710) | K15: BUSBAR - Pos BEC to DCFC_Protector
A16: =IF(E16="Components","2nd","1st") -> 1st | B16: 13 | D16: S2X8-14A033-AC | E16: BEV-M | F16: BUS BAR ASY – POS BEC TO ARRAY 6 POS | I16: PZ38-14A033-NB | J16: BEV-E (V710) | K16: BUSBAR - Neg BEC to DCFC_Protector
... A51: =IF(E51="Components","2nd","1st") -> 1st | B51: 48 | D51: PZ38-10B694-BD | E51: BEV-E1(V710) | F51: Main Harness | I51: TZ38-14A033-DA04 | J51: EV-V4 | K51: BUSBAR
A52: =IF(E52="","3rd",IF(E52="Components","2nd","1st")) -> 1st | B52: 49 | D52: PZ38-14A033-GD | E52: BEV-E (V710) | F52: BUSBAR - Array to Array (Angled)_Insert | I52: TZ38-14A033-EA | J52: EV-V4 | K52: BUSBAR ASY
A53: =IF(E53="","3rd",IF(E53="Components","2nd","1st")) -> 1st | B53: 50 | D53: PZ38-14A033-KD | E53: BEV-E (V710) | F53: BUSBAR - Array 1 to Neg BEC_Insert | I53: TZ38-14A033-EA04 | J53: EV-V4 | K53: BUSBAR
A54: =IF(E54="","3rd",IF(E54="Components","2nd","1st")) -> 1st | B54: 51 | D54: PZ38-14A033-NB | E54: BEV-E (V710) | F54: BUSBAR - Neg BEC to DCFC_Protector | I54: TZ38-14A033-FA | J54: BEV-E (AWD/RWD, V710) | K54: BUS BAR ASY
A55: =IF(E55="","3rd",IF(E55="Components","2nd","1st")) -> 1st | B55: 52 | D55: PZ38-14A033-PC | E55: BEV-E (V710) | F55: BUSBAR - CIRCUIT BREAKER_A_Insert | I55: TZ38-14A033-GA | J55: EV-V4 | K55: BUSBAR ASY
A56: =IF(E56="","3rd",IF(E56="Components","2nd","1st")) -> 1st | B56: 53 | D56: PZ38-14A033-RC | E56: BEV-E (V710) | F56: BUSBAR - CIRCUIT BREAKER_B_Insert | I56: TZ38-14A033-GA04 | J56: EV-V4 | K56: BUSBAR
A57: =IF(E57="","3rd",IF(E57="Components","2nd","1st")) -> 1st | B57: 54 | D57: SZ38-10B694-AC | E57: BEV-E2 (V710) | F57: Main Harness | I57: TZ38-14A033-HB | J57: BEV-E (AWD/RWD, V710) | K57: MCA CONNECTOR CLIP
A58: =IF(E58="","3rd",IF(E58="Components","2nd","1st")) -> 1st | B58: 55 | D58: SZ38-14A033-AB | E58: BEV-E2 (V710) | F58: BUSBAR - Array 2 to Array3_Insert | I58: TZ38-14A033-JA | J58: BEV-E (AWD, V710) | K58: BUS BAR ASY
A59: =IF(E59="","3rd",IF(E59="Components","2nd","1st")) -> 1st | B59: 56 | D59: SZ38-14A033-BB | E59: BEV-E2 (V710) | F59: BUSBAR - Array 6 to Pos BEC_Insert | I59: TZ38-14A033-JB | J59: BEV-E (AWD/RWD, V710) | K59: MCA CONNECTOR CLIP
A60: =IF(E60="","3rd",IF(E60="Components","2nd","1st")) -> 1st | B60: 57 | D60: TZ38-10B694-AA | E60: BEV-E1 | F60: V710 AWD MAIN W/H ASSY | I60: TZ38-14A033-KA | J60: EV-V4 | K60: MCA CONNECTOR CLIP
A61: =IF(E61="","3rd",IF(E61="Components","2nd","1st")) -> 1st | B61: 58 | D61: TZ38-10B694-AD | E61: BEV-E (AWD, V710) | F61: Main Harness | I61: TZ38-14A033-LA | J61: EV-V4 | K61: MCA CONNECTOR CLIP
A62: =IF(E62="","3rd",IF(E62="Components","2nd","1st")) -> 1st | B62: 59 | D62: TZ38-10B694-DB | E62: BEV-E (RWD, V710) | F62: Main Harness | I62: TZ38-14A033-MA | J62: EV-V4 | K62: MCA CONNECTOR CLIP
A63: =IF(E63="","3rd",IF(E63="Components","2nd","1st")) -> 1st | B63: 60 | D63: TZ38-14A033-JA | E63: BEV-E (AWD, V710) | F63: BUS BAR ASY | I63: TZ38-14A033-NA | J63: BEV-E (AWD/RWD, V710) | K63: BUSBAR ASY
... A66: =IF(E66="","3rd",IF(E66="Components","2nd","1st")) -> 1st | B66: 63 | D66: TZ38-14A033-TA04 | E66: EV-V4 | F66: BUSBAR | I66: TZ38-14A033-SA | J66: BEV-E (AWD/RWD, V710) | K66: BUSBAR ASY
A67: 2nd | B67: 64 | D67: TUBE0000101 | E67: EV-V4 Test Parts | F67: DBJ033 | I67: TZ38-14A033-TA | J67: EV-V4 | K67: BUSBAR ASY
A68: 2nd | B68: 65 | D68: TUBE0000104 | E68: EV-V4 Test Parts | F68: CG13-38 (5M) | I68: TZ38-14A033-TA04 | J68: EV-V4 | K68: BUSBAR
A69: 2nd | B69: 66 | D69: UKLA0-05011 | E69: EV-V4 Test Parts | F69: CG19-38 (08) (7M) | I69: TZ38-14B680-AA | J69: EV-V4 | K69: PDU_CONN_ASSY
A70: =IF(E70="","3rd",IF(E70="Components","2nd","1st")) -> 2nd | B70: 67 | D70: BEE25-CT001 | E70: Components | F70: Terminal | I70: TZ38-14B680-BA | J70: BEV-E (AWD, V710) | K70: PDU
A71: =IF(E71="","3rd",IF(E71="Components","2nd","1st")) -> 2nd | B71: 68 | D71: BEE22-CP007 | E71: Components | F71: CHANNEL | I71: TZ38-14B680-BB | J71: BEV-E (AWD/RWD, V710) | K71: AWD/RWD PDU CONN ASSY
A72: =IF(E72="","3rd",IF(E72="Components","2nd","1st")) -> 2nd | B72: 69 | D72: BEE24-CP001 | E72: Components | F72: CHANNEL | I72: BEE22-CP007 | J72: Components | K72: CHANNEL
A73: =IF(E73="","3rd",IF(E73="Components","2nd","1st")) -> 2nd | B73: 70 | D73: BEE24-CP002 | E73: Components | F73: CHANNEL | I73: BEE22-CT009 | J73: Components | K73: BEV_E_TML_1
A74: =IF(E74="","3rd",IF(E74="Components","2nd","1st")) -> 2nd | B74: 71 | D74: BEE24-CP003 | E74: Components | F74: CHANNEL | I74: BEE22-CT010 | J74: Components | K74: BEV_E_TML_2
A75: =IF(E75="","3rd",IF(E75="Components","2nd","1st")) -> 1st | B75: 72 | D75: PZ38-14A033-JD | E75: BEV-E1 | F75: BEV-E1 BUSBAR Array 8 to Array 9 | I75: BEE22-CT011 | J75: Components | K75: BEV_E_TML_3
A76: =IF(E76="","3rd",IF(E76="Components","2nd","1st")) -> 1st | B76: 73 | D76: TZ38-14A033-AA04 | E76: EV-V4 | F76: BUSBAR | I76: BEE24-CP001 | J76: Components | K76: CHANNEL
A77: =IF(E77="","3rd",IF(E77="Components","2nd","1st")) -> 1st | B77: 74 | D77: TZ38-14A033-BA04 | E77: EV-V4 | F77: BUSBAR | I77: BEE24-CP002 | J77: Components | K77: CHANNEL
A78: =IF(E78="","3rd",IF(E78="Components","2nd","1st")) -> 1st | B78: 75 | D78: TZ38-14A033-CA04 | E78: EV-V4 | F78: BUSBAR | I78: BEE24-CP003 | J78: Components | K78: CHANNEL
A79: =IF(E79="","3rd",IF(E79="Components","2nd","1st")) -> 1st | B79: 76 | D79: TZ38-14A033-DA04 | E79: EV-V4 | F79: BUSBAR | I79: BEE25-CT001 | J79: Components | K79: Terminal
A80: =IF(E80="","3rd",IF(E80="Components","2nd","1st")) -> 1st | B80: 77 | D80: TZ38-14A033-EA04 | E80: EV-V4 | F80: BUSBAR | I80: TUBE0000101 | J80: EV-V4 Test Parts | K80: DBJ033
A81: =IF(E81="","3rd",IF(E81="Components","2nd","1st")) -> 1st | B81: 78 | D81: TZ38-14A033-GA04 | E81: EV-V4 | F81: BUSBAR | I81: TUBE0000104 | J81: EV-V4 Test Parts | K81: CG13-38 (5M)
A82: =IF(E76="","3rd",IF(E76="Components","2nd","1st")) -> 1st | B82: 79 | D82: TZ38-10B694-BB | E82: BEV-E (AWD/RWD, V710) | F82: MAIN WIRING HARNESS | I82: UKLA0-05011 | J82: EV-V4 Test Parts | K82: CG19-38 (08) (7M)
A83: 3rd | B83: 80 | D83: TZ38-10B694-CB | E83: BEV-E (AWD/RWD, V710) | F83: AWD Main length extended | I83: PZ38-14A033-MD | J83: BEV-E (AWD/RWD, V710) | K83: MCA CONNECTOR CLIP
A84: 3rd | B84: 81 | D84: TZ38-14A033-AB | E84: BEV-E (AWD/RWD, V710) | F84: BUSBAR | I84: SZ38-10B694-AD | J84: BEV-E2 (V710) | K84: BEV-E2 MAIN W/H ASSY
A85: 3rd | B85: 82 | D85: TZ38-14A033-BB | E85: BEV-E (AWD/RWD, V710) | F85: BUSBAR | I85: SZ38-10B694-AE | J85: BEV-E2 (V710) | K85: BEV-E2 MAIN W/H ASSY
A86: 3rd | B86: 83 | D86: TZ38-14A033-CB | E86: BEV-E (AWD/RWD, V710) | F86: BUSBAR | I86: TZ38-10B694-CB | J86: BEV-E (AWD/RWD, V710) | K86: AWD Main length extended
A87: 3rd | B87: 84 | D87: TZ38-14A033-DB | E87: BEV-E (AWD/RWD, V710) | F87: BUSBAR | I87: TZ38-14A033-AB | J87: BEV-E (AWD/RWD, V710) | K87: BUSBAR
A88: 3rd | B88: 85 | D88: TZ38-14A033-EB | E88: BEV-E (AWD/RWD, V710) | F88: BUSBAR | I88: TZ38-14A033-BB | J88: BEV-E (AWD/RWD, V710) | K88: BUSBAR
A89: 3rd | B89: 86 | D89: TZ38-14A033-GB | E89: BEV-E (AWD/RWD, V710) | F89: BUSBAR | I89: TZ38-14A033-CB | J89: BEV-E (AWD/RWD, V710) | K89: BUSBAR
A90: 3rd | B90: 87 | D90: TZ38-14A033-KB | E90: BEV-E (AWD/RWD, V710) | F90: BUSBAR | I90: TZ38-14A033-DB | J90: BEV-E (AWD/RWD, V710) | K90: BUSBAR
A91: 3rd | B91: 88 | D91: TZ38-14A033-LB | E91: BEV-E (AWD/RWD, V710) | F91: BUSBAR | I91: TZ38-14A033-EB | J91: BEV-E (AWD/RWD, V710) | K91: BUSBAR
A92: 3rd | B92: 89 | D92: TZ38-14B680-AB | E92: BEV-E (AWD/RWD, V710) | F92: PDU | I92: TZ38-14A033-GB | J92: BEV-E (AWD/RWD, V710) | K92: BUSBAR
A93: 3rd | B93: 90 | D93: PZ38-14A033-MD | E93: BEV-E (AWD/RWD, V710) | F93: MCA CONNECTOR CLIP | I93: TZ38-14A033-KB | J93: BEV-E (AWD/RWD, V710) | K93: BUSBAR
A94: 3rd | B94: 91 | D94: SZ38-10B694-AD | E94: BEV-E2 (V710) | F94: BEV-E2 MAIN W/H ASSY | I94: TZ38-14A033-LB | J94: BEV-E (AWD/RWD, V710) | K94: BUSBAR
A95: 3rd | B95: 92 | D95: SZ38-10B694-AE | E95: BEV-E2 (V710) | F95: BEV-E2 MAIN W/H ASSY | I95: TZ38-14B680-AB | J95: BEV-E (AWD/RWD, V710) | K95: PDU
A96: 3rd | B96: 93 | I96: 0 | J96: 0 | K96: 0
A97: 3rd | B97: 94 | I97: 0 | J97: 0 | K97: 0
A98: 3rd | B98: 95 | I98: 0 | J98: 0 | K98: 0
A99: 3rd | B99: 96 | I99: 0 | J99: 0 | K99: 0
A100: 3rd | B100: 97 | I100: 0 | J100: 0 | K100: 0
A101: 3rd | B101: 98 | I101: 0 | J101: 0 | K101: 0
A102: 3rd | B102: 99 | I102: 0 | J102: 0 | K102: 0
A103: 3rd | B103: 100 | I103: 0 | J103: 0 | K103: 0
A104: 3rd | B104: 101 | I104: 0 | J104: 0 | K104: 0
A105: 3rd | B105: 102 | I105: 0 | J105: 0 | K105: 0
A106: 3rd | B106: 103 | I106: 0 | J106: 0 | K106: 0
A107: 3rd | B107: 104 | I107: 0 | J107: 0 | K107: 0
... A128: 3rd | B128: 125 | I128: 0 | J128: 0 | K128: 0
A129: =IF(E129="","3rd",IF(E129="Components","2nd","1st")) -> 3rd | B129: =+B128+1 -> 126 | I129: 0 | J129: 0 | K129: 0
A130: =IF(E130="","3rd",IF(E130="Components","2nd","1st")) -> 3rd | B130: =+B129+1 -> 127 | I130: 0 | J130: 0 | K130: 0
A131: =IF(E131="","3rd",IF(E131="Components","2nd","1st")) -> 3rd | B131: =+B130+1 -> 128 | I131: 0 | J131: 0 | K131: 0
A132: =IF(E132="","3rd",IF(E132="Components","2nd","1st")) -> 3rd | B132: =+B131+1 -> 129 | I132: 0 | J132: 0 | K132: 0
A133: =IF(E133="","3rd",IF(E133="Components","2nd","1st")) -> 3rd | B133: =+B132+1 -> 130 | I133: 0 | J133: 0 | K133: 0
A134: =IF(E134="","3rd",IF(E134="Components","2nd","1st")) -> 3rd | B134: =+B133+1 -> 131 | I134: 0 | J134: 0 | K134: 0
A135: =IF(E135="","3rd",IF(E135="Components","2nd","1st")) -> 3rd | B135: =+B134+1 -> 132 | I135: 0 | J135: 0 | K135: 0
A136: =IF(E136="","3rd",IF(E136="Components","2nd","1st")) -> 3rd | B136: =+B135+1 -> 133 | I136: 0 | J136: 0 | K136: 0
A137: =IF(E137="","3rd",IF(E137="Components","2nd","1st")) -> 3rd | B137: =+B136+1 -> 134 | I137: 0 | J137: 0 | K137: 0
A138: =IF(E138="","3rd",IF(E138="Components","2nd","1st")) -> 3rd | B138: =+B137+1 -> 135 | I138: 0 | J138: 0 | K138: 0
A139: =IF(E139="","3rd",IF(E139="Components","2nd","1st")) -> 3rd | B139: =+B138+1 -> 136 | I139: 0 | J139: 0 | K139: 0
A140: =IF(E140="","3rd",IF(E140="Components","2nd","1st")) -> 3rd | B140: =+B139+1 -> 137 | I140: 0 | J140: 0 | K140: 0
... A158: =IF(E158="","3rd",IF(E158="Components","2nd","1st")) -> 3rd | B158: =+B157+1 -> 155 | I158: 0 | J158: 0 | K158: 0
A159: =IF(E159="","3rd",IF(E159="Components","2nd","1st")) -> 3rd | B159: 156 | I159: 0 | J159: 0 | K159: 0
A160: =IF(E160="","3rd",IF(E160="Components","2nd","1st")) -> 3rd | B160: 157 | I160: 0 | J160: 0 | K160: 0
I161: 0 | J161: 0 | K161: 0
I162: 0 | J162: 0 | K162: 0
I163: 0 | J163: 0 | K163: 0
I164: 0 | J164: 0 | K164: 0
I165: 0 | J165: 0 | K165: 0
I166: 0 | J166: 0 | K166: 0
I167: 0 | J167: 0 | K167: 0

Sheet 2026 List
F1: Management Master List | H1: 2026 MAF
A2: Catergory | B2: Code | C2: Project Code | D2: Project Name | E2: Item | F2: Project | G2: Item | H2: Project Name | I2: Item
A3: List of received items | B3: BEE22-CT009 | C3: V769 | D3: Yazaki (BEV-M) | E3: BEV_E_TML_1 | F3: Components | G3: BEV-E1/BEV_E_TML_1 | H3: Components (BEV-M) | I3: BEV_E_TML_1
A4: List of received items | B4: BEE22-CT010 | C4: V769 | D4: Yazaki (BEV-M) | E4: BEV_E_TML_2 | F4: Components | G4: BEV-E1/BEV_E_TML_2 | H4: Components (BEV-M) | I4: BEV_E_TML_2
A5: List of received items | B5: BEE22-CT011 | C5: V769 | D5: Yazaki (BEV-M) | E5: BEV_E_TML_3 | F5: Components | G5: BEV-E1/BEV_E_TML_3 | H5: Components (BEV-M) | I5: BEV_E_TML_3
A6: List of received items | B6: PZ38-10B694-AD | C6: V710 / P703 | D6: PHEV-E | E6: Main Harness | F6: FORD PHEV-E(V710) / (P703) | G6: Main Harness | H6: PHEV-E (V710) / (P703) | I6: Main Harness
A7: List of received items | B7: PZ38-14A033-AB | C7: V710 / P703 | D7: PHEV-E | E7: BUSBAR - Array to Array (short) | F7: FORD PHEV-E(V710) / (P703) | G7: BUSBAR - Array to Array (short) | H7: PHEV-E (V710) / (P703) | I7: BUSBAR - Array to Array (short)
A8: List of received items | B8: PZ38-14A033-BB | C8: V710 / P703 | D8: PHEV-E | E8: BUSBAR - Array to Array (long) | F8: FORD PHEV-E(V710) / (P703) | G8: BUSBAR - Array to Array (long) | H8: PHEV-E (V710) / (P703) | I8: BUSBAR - Array to Array (long)
A9: List of received items | B9: PZ38-14A033-CB | C9: V710 / P703 | D9: PHEV-E | E9: BUSBAR - Array 3 to 4 | F9: FORD PHEV-E(V710) / (P703) | G9: BUSBAR - Array 3 to 4 | H9: PHEV-E (V710) / (P703) | I9: BUSBAR - Array 3 to 4
A10: List of received items | B10: PZ38-14A033-HF | C10: V710 | D10: BEV | E10: BUSBAR - Array4 to Array 5_Insert | F10: BEV-E1(V710) | G10: BUSBAR - Array4 to Array 5_Insert | H10: BEV-E (V710) | I10: BUSBAR - Array4 to Array 5_Insert
A11: List of received items | B11: PZ38-14A033-LF | C11: V710 | D11: BEV | E11: BUSBAR - Array 9 to Pos BEC_Insert | F11: BEV-E1(V710) | G11: BUSBAR - Array 9 to Pos BEC_Insert | H11: BEV-E (V710) | I11: BUSBAR - Array 9 to Pos BEC_Insert
A12: List of received items | B12: PZ38-14A033-MC | C12: V710 | D12: BEV | E12: BUSBAR - Pos BEC to DCFC_Protector | F12: BEV-E1(V710) / E2(V710) | G12: BUSBAR - Pos BEC to DCFC_Protector | H12: BEV-E (V710) | I12: BUSBAR - Pos BEC to DCFC_Protector
A13: List of received items | B13: PZ38-14B252-AB | C13: V710 / P703 | D13: PHEV-E | E13: Jumper | F13: FORD PHEV-E(V710) / (P703) | G13: Jumper | H13: PHEV-E (V710) / (P703) | I13: Jumper
... A46: List of received items | B46: TZ38-14A033-SA | C46: V710 | D46: BEV AWD/RWD | E46: BUSBAR ASY | F46: V710 AWD | G46: BUS BAR ASY | H46: BEV-E (AWD/RWD, V710) | I46: BUSBAR ASY
A47: List of received items | B47: TZ38-14A033-TA | C47: V710 | D47: EV-V4 | E47: BUSBAR ASY | F47: #N/A | G47: #N/A | H47: EV-V4 | I47: BUSBAR ASY
A48: List of received items | B48: TZ38-14B680-AA | C48: V710 | D48: EV-V4 | E48: PDU_CONN_ASSY | F48: BEV-E1 | G48: PDU_CONN_ASSY | H48: EV-V4 | I48: PDU_CONN_ASSY
A49: List of received items | B49: TZ38-14B680-BB | C49: V710 | D49: BEV AWD/RWD | E49: AWD/RWD PDU CONN ASSY | F49: BEV-E1 | G49: V710 BEV-E1 AWD/RWD PDU CONN ASSY | H49: BEV-E (AWD/RWD, V710) | I49: AWD/RWD PDU CONN ASSY
A50: MAF Inventory | B50: PZ38-10B694-BD | E50: Main Harness | F50: BEV-E1(V710) | G50: Main Harness | H50: BEV-E1(V710) | I50: Main Harness
A51: MAF Inventory | B51: PZ38-14A033-GD | E51: BUSBAR - Array to Array (Angled)_Insert | F51: BEV-E1(V710) / E2(V710) | G51: BUSBAR - Array to Array (Angled)_Insert | H51: BEV-E (V710) | I51: BUSBAR - Array to Array (Angled)_Insert
A52: MAF Inventory | B52: PZ38-14A033-KD | E52: BUSBAR - Array 1 to Neg BEC_Insert | F52: BEV-E1(V710) / E2(V710) | G52: BUSBAR - Array 1 to Neg BEC_Insert | H52: BEV-E (V710) | I52: BUSBAR - Array 1 to Neg BEC_Insert
A53: MAF Inventory | B53: PZ38-14A033-NB | E53: BUSBAR - Neg BEC to DCFC_Protector | F53: BEV-E1(V710) | G53: BUSBAR - Neg BEC to DCFC_Protector | H53: BEV-E (V710) | I53: BUSBAR - Neg BEC to DCFC_Protector
A54: MAF Inventory | B54: PZ38-14A033-PC | E54: BUSBAR - CIRCUIT BREAKER_A_Insert | F54: BEV-E1(V710) / E2(V710) | G54: BUSBAR - CIRCUIT BREAKER_A_Insert | H54: BEV-E (V710) | I54: BUSBAR - CIRCUIT BREAKER_A_Insert
A55: MAF Inventory | B55: PZ38-14A033-RC | E55: BUSBAR - CIRCUIT BREAKER_B_Insert | F55: BEV-E1(V710) / E2(V710) | G55: BUSBAR - CIRCUIT BREAKER_B_Insert | H55: BEV-E (V710) | I55: BUSBAR - CIRCUIT BREAKER_B_Insert
A56: MAF Inventory | B56: SZ38-10B694-AC | E56: Main Harness | F56: BEV-E2(V710) | G56: Main Harness | H56: BEV-E2 (V710) | I56: Main Harness
A57: MAF Inventory | B57: SZ38-14A033-AB | E57: BUSBAR - Array 2 to Array3_Insert | F57: BEV-E2(V710) | G57: BUSBAR - Array 2 to Array3_Insert | H57: BEV-E2 (V710) | I57: BUSBAR - Array 2 to Array3_Insert
A58: MAF Inventory | B58: SZ38-14A033-BB | E58: BUSBAR - Array 6 to Pos BEC_Insert | F58: BEV-E2(V710) | G58: BUSBAR - Array 6 to Pos BEC_Insert | H58: BEV-E2 (V710) | I58: BUSBAR - Array 6 to Pos BEC_Insert
A59: MAF Inventory | B59: TZ38-10B694-AA | E59: V710 AWD MAIN W/H ASSY | F59: BEV-E1 | G59: V710 AWD MAIN W/H ASSY | H59: BEV-E1 | I59: V710 AWD MAIN W/H ASSY
A60: MAF Inventory | B60: TZ38-10B694-AD | E60: Main Harness | F60: V710 AWD | G60: Main Harness | H60: BEV-E (AWD, V710) | I60: Main Harness
A61: MAF Inventory | B61: TZ38-10B694-DB | E61: Main Harness | F61: V710 RWD | G61: Main Harness | H61: BEV-E (RWD, V710) | I61: Main Harness
... A64: MAF Inventory | B64: PZ38-14A033-FE | E64: BUSBAR - Array to Array (Straight)_Insert | F64: EV-V4 Test Parts | G64: BUSBAR - Array to Array (Straight)_Insert | H64: EV-V4 Test Parts | I64: BUSBAR - Array to Array (Straight)_Insert
A65: Inventory Report | B65: TUBE0000093 | F65: =_xlfn.XLOOKUP(B65,'★Master Code List'!$D:$D,'★Master Code List'!$E:$E,) -> #N/A | G65: =_xlfn.XLOOKUP(B65,'★Master Code List'!$D$4:$D$160,'★Master Code List'!$F$4:$F$160,) -> #N/A | H65: EV-V4 Test Parts | I65: CG01-38 (5M)
A66: Inventory Report | B66: TUBE0000101 | F66: =_xlfn.XLOOKUP(B66,'★Master Code List'!$D:$D,'★Master Code List'!$E:$E,) -> EV-V4 Test Parts | G66: =_xlfn.XLOOKUP(B66,'★Master Code List'!$D$4:$D$160,'★Master Code List'!$F$4:$F$160,) -> DBJ033 | H66: EV-V4 Test Parts | I66: DBJ033
A67: Inventory Report | B67: TUBE0000104 | F67: =_xlfn.XLOOKUP(B67,'★Master Code List'!$D:$D,'★Master Code List'!$E:$E,) -> EV-V4 Test Parts | G67: =_xlfn.XLOOKUP(B67,'★Master Code List'!$D$4:$D$160,'★Master Code List'!$F$4:$F$160,) -> CG13-38 (5M) | H67: EV-V4 Test Parts | I67: CG13-38 (5M)
A68: Inventory Report | B68: UKLA0-05011 | F68: =_xlfn.XLOOKUP(B68,'★Master Code List'!$D:$D,'★Master Code List'!$E:$E,) -> EV-V4 Test Parts | G68: =_xlfn.XLOOKUP(B68,'★Master Code List'!$D$4:$D$160,'★Master Code List'!$F$4:$F$160,) -> CG19-38 (08) (7M) | H68: EV-V4 Test Parts | I68: CG19-38 (08) (7M)
H74: `

Sheet 2026 Plan PL (New)
F1: 0.76682497 | G1: 0.76611273 | H1: 0.76564981 | I1: 0.76475524 | J1: 0.76203145 | K1: 0.76557737 | L1: 0.7644828 | M1: 0.76573661 | N1: 0.76567589 | O1: 0.83251355 | P1: 0.85948776 | Q1: 0.85913698
B2: Profit and Loss statement FY 2026 | Q2: (Affiliate Company: Kyungshin cable Türkiye)
B4: 구분 | D4: FY | E4: 12 | F4: 1 | G4: 2 | H4: 3 | I4: 4 | J4: 5 | K4: 6 | L4: 7 | M4: 8 | N4: 9 | O4: 10 | P4: 11 | Q4: 12
B5: Ⅰ. 매출액 | C5: Ⅰ. SALES | D5: 1.8562269e+09 | F5: 93531068 | G5: 1.1672241e+08 | H5: 1.6614614e+08 | I5: 1.385977e+08 | J5: 1.2682473e+08 | K5: 1.9324117e+08 | L5: 1.1829519e+08 | M5: 1.7613515e+08 | N5: 1.5905064e+08 | O5: 2.3366351e+08 | P5: 1.6558768e+08 | Q5: 1.6843153e+08
B6: 1.상품매출 | C6: 1. Merchandise | D6: 1.8546969e+09 | F6: 93531068 | G6: 1.1672241e+08 | H6: 1.6614614e+08 | I6: 1.385977e+08 | J6: 1.2682473e+08 | K6: 1.9324117e+08 | L6: 1.1829519e+08 | M6: 1.7613515e+08 | N6: 1.5905064e+08 | O6: 2.3366351e+08 | P6: 1.6558768e+08 | Q6: 1.6690153e+08
C7: FORD PHEV-E (V710) | D7: 3.0822942e+08 | F7: 21737517 | G7: 23596647 | H7: 28172967 | I7: 20593438 | J7: 17018188 | K7: 35466476 | L7: 19592368 | M7: 31891226 | N7: 31176176 | O7: 24254493 | P7: 26571255 | Q7: 28158666
C8: FORD PHEV-E (P703) | D8: 1.6412277e+08 | F8: 11440799 | G8: 10236504 | H8: 12645093 | I8: 12645093 | J8: 13849388 | K8: 18666566 | L8: 13247241 | M8: 13548314 | N8: 14105300 | O8: 14346159 | P8: 14632179 | Q8: 14760136
C9: BEV-E RWD | D9: 6.1849335e+08 | F9: 39254495 | G9: 40331839 | H9: 77686291 | I9: 65698392 | J9: 52476443 | K9: 83131775 | L9: 50556812 | M9: 79958508 | N9: 66619031 | O9: 62779769 | P9: 0 | Q9: 0
C10: BEV-E AWD | D10: 1.4457127e+08 | F10: 1339959 | G10: 11503033 | H10: 20202459 | I10: 16141352 | J10: 12121475 | K10: 20697213 | L10: 11379344 | M10: 19377868 | N10: 15790901 | O10: 16017664 | P10: 0 | Q10: 0
C11: FORD BEV-M | D11: 3.1895775e+08 | F11: 18887593 | G11: 28331389 | H11: 26423506 | I11: 22648720 | J11: 30198293 | K11: 33973080 | L11: 22648720 | M11: 30198293 | N11: 30198293 | O11: 20066661 | P11: 27884925 | Q11: 27498272
C12: EV-V4 | D12: 2.8052389e+08 | F12: 0 | G12: 1378803.9 | H12: 0 | I12: 0 | J12: 0 | K12: 0 | L12: 0 | M12: 0 | N12: 0 | O12: 93048362 | P12: 93048362 | Q12: 93048362
C13: Components | D13: 19798467 | F13: 870704.64 | G13: 1344193.2 | H13: 1015822.1 | I13: 870704.64 | J13: 1160939.5 | K13: 1306057 | L13: 870704.64 | M13: 1160939.5 | N13: 1160939.5 | O13: 3150399.2 | P13: 3450963.6 | Q13: 3436099.1
B15: 2. 기타 매출 | C15: 2. Other sales | D15: 1530000 | F15: 0 | G15: 0 | H15: 0 | I15: 0 | J15: 0 | K15: 0 | L15: 0 | M15: 0 | N15: 0 | O15: 0 | P15: 0 | Q15: 1530000
B16: └ scrap | C16: └ Scrap | D16: 0
B17: └ Test Parts | C17: └ Test Parts | D17: 0
B18: └ 기타 | C18: └ Other | D18: 1530000 | Q18: 1530000 | U18: 30000 | V18: BEV-H RESIDENCE Q.C Contract
B19: └ 기타(투자비) | C19: └ Investment | D19: 0
C20: *(Deductions)
C21: *(Returns)
B23: Ⅱ. 매출원가 | C23: Ⅱ. COST OF SALES | D23: 1.466262e+09 | F23: 71721958 | G23: 89422523 | H23: 1.2720976e+08 | I23: 1.0599332e+08 | J23: 96644431 | K23: 1.4794106e+08 | L23: 90434637 | M23: 1.3487313e+08 | N23: 1.2178124e+08 | O23: 1.9452804e+08 | P23: 1.4232059e+08 | Q23: 1.4339128e+08
C24: % | D24: =IFERROR(D23/D$5,) -> 0.78991526 | F24: =IFERROR(F23/F$5,) -> 0.76682497 | G24: =IFERROR(G23/G$5,) -> 0.76611273 | H24: =IFERROR(H23/H$5,) -> 0.76564981 | I24: =IFERROR(I23/I$5,) -> 0.76475524 | J24: =IFERROR(J23/J$5,) -> 0.76203145 | K24: =IFERROR(K23/K$5,) -> 0.76557737 | L24: =IFERROR(L23/L$5,) -> 0.7644828 | M24: =IFERROR(M23/M$5,) -> 0.76573661 | ... Q24: =IFERROR(Q23/Q$5,) -> 0.85133274
B25: 상품매출원가 | C25: Cost of merchandise sold | D25: 1.466262e+09 | F25: 71721958 | G25: 89422523 | H25: 1.2720976e+08 | I25: 1.0599332e+08 | J25: 96644431 | K25: 1.4794106e+08 | L25: 90434637 | M25: 1.3487313e+08 | N25: 1.2178124e+08 | O25: 1.9452804e+08 | P25: 1.4232059e+08 | Q25: 1.4339128e+08
C26: % | D26: =IFERROR(D25/D$6,) -> 0.79056689 | F26: =IFERROR(F25/F$6,) -> 0.76682497 | G26: =IFERROR(G25/G$6,) -> 0.76611273 | H26: =IFERROR(H25/H$6,) -> 0.76564981 | I26: =IFERROR(I25/I$6,) -> 0.76475524 | J26: =IFERROR(J25/J$6,) -> 0.76203145 | K26: =IFERROR(K25/K$6,) -> 0.76557737 | L26: =IFERROR(L25/L$6,) -> 0.7644828 | M26: =IFERROR(M25/M$6,) -> 0.76573661 | ... Q26: =IFERROR(Q25/Q$6,) -> 0.85913698
B27: 1.기초 상품재고 | C27: 1. Beginning Merchandise | D27: 0
B28: 2.당기 상품매입원가 | C28: 2. Cost of Merchandise | D28: 1.466262e+09 | F28: 71721958 | G28: 89422523 | H28: 1.2720976e+08 | I28: 1.0599332e+08 | J28: 96644431 | K28: 1.4794106e+08 | L28: 90434637 | M28: 1.3487313e+08 | N28: 1.2178124e+08 | O28: 1.9452804e+08 | P28: 1.4232059e+08 | Q28: 1.4339128e+08
B29: 3.타계정전입 (+) | C29: 3. Transferred from other accounts | D29: 0
B30: 4.타계정대체 (-) | C30: 4. Transferred to other accounts | D30: 0
B31: 5.기말 상품재고 | C31: 5. Ending Merchandise | D31: 0
B32: 기타매출원가 | C32: Cost of other sold | D32: 0 | F32: 0 | G32: 0 | H32: 0 | I32: 0 | J32: 0 | K32: 0 | L32: 0 | M32: 0 | N32: 0 | O32: 0 | P32: 0 | Q32: 0
B33: 원재료 매출원가 | C33: Raw material | D33: 0
B34: 반제품 매출원가 | C34: Halb | D34: 0
B35: 기타 | C35: Other | D35: 0
B36: 기타(투자비) | C36: Investment | D36: 0
B37: Ⅲ. 매출총이익 | C37: Ⅲ. GROSS PROFIT (or GROSS LOSS) | D37: 3.8996495e+08 | F37: 21809110 | G37: 27299886 | H37: 38936379 | I37: 32604383 | J37: 30180296 | K37: 45300103 | L37: 27860551 | M37: 41262017 | N37: 37269400 | O37: 39135470 | P37: 23267097 | Q37: 25040255
B38: (이익률) | C38: (Rate) | D38: 0.21008474 | F38: 0.23317503 | G38: 0.23388727 | H38: 0.23435019 | I38: 0.23524476 | J38: 0.23796855 | K38: 0.23442263 | L38: 0.2355172 | M38: 0.23426339 | N38: 0.23432411 | O38: 0.16748645 | P38: 0.14051224 | Q38: 0.14866726
B39: Ⅳ.판매관리비 | C39: SELLING AND MARKETING EXPENSES | D39: =SUM(D40:D46) -> 32457954 | E39: 0 | F39: =SUM(F40:F46) -> 1864869.9 | G39: =SUM(G40:G46) -> 2111319.2 | H39: =SUM(H40:H46) -> 2624130.2 | I39: =SUM(I40:I46) -> 2295347.5 | J39: =SUM(J40:J46) -> 4211534.9 | K39: =SUM(K40:K46) -> 2905578.6 | L39: =SUM(L40:L46) -> 2097975.2 | M39: =SUM(M40:M46) -> 2807689.8 | ... Q39: =SUM(Q40:Q46) -> 2745091.2
C40: Export Expenses | D40: =SUM(F40:Q40) -> 1628307.2 | F40: 95782.779 | G40: 95782.779 | H40: 95782.779 | I40: 95782.779 | J40: 95782.779 | K40: 95782.779 | L40: 95782.779 | M40: 191565.56 | N40: 191565.56 | O40: 191565.56 | P40: 191565.56 | Q40: 191565.56
C41: Import Expenses | D41: =SUM(F41:Q41) -> 334367.46 | F41: 20897.966 | G41: 20897.966 | H41: 20897.966 | I41: 20897.966 | J41: 20897.966 | K41: 20897.966 | L41: 20897.966 | M41: 20897.966 | N41: 41795.933 | O41: 41795.933 | P41: 41795.933 | Q41: 41795.933
C42: Domestic Transportation Expenses | D42: =SUM(F42:Q42) -> 6658033.8 | F42: 554836.15 | G42: 554836.15 | H42: 554836.15 | I42: 554836.15 | J42: 554836.15 | K42: 554836.15 | L42: 554836.15 | M42: 554836.15 | N42: 554836.15 | O42: 554836.15 | P42: 554836.15 | Q42: 554836.15
C43: Sample Expenses | D43: =SUM(F43:Q43) -> 496289.82 | F43: 41357.485 | G43: 41357.485 | H43: 41357.485 | I43: 41357.485 | J43: 41357.485 | K43: 41357.485 | L43: 41357.485 | M43: 41357.485 | N43: 41357.485 | O43: 41357.485 | P43: 41357.485 | Q43: 41357.485
C44: Rework & Sorting Expenses | D44: =SUM(F44:Q44) -> 18562269 | F44: 935310.68 | G44: 1167224.1 | H44: 1661461.4 | I44: 1385977 | J44: 1268247.3 | K44: 1932411.7 | L44: 1182951.9 | M44: 1761351.5 | N44: 1590506.4 | O44: 2336635.1 | P44: 1655876.8 | Q44: 1684315.3
C45: Package Expense | D45: =SUM(F45:Q45) -> 2778686.9 | F45: 216684.87 | G45: 231220.77 | H45: 249794.41 | I45: 196496.12 | J45: 230413.22 | K45: 260292.56 | L45: 202148.97 | M45: 237681.17 | N45: 245756.66 | O45: 245756.66 | P45: 231220.77 | Q45: 231220.77
C46: Other Expenses | D46: =SUM(F46:Q46) -> 2000000 | F46: 0 | G46: 0 | H46: 0 | I46: 0 | J46: 2000000 | K46: 0 | L46: 0 | M46: 0 | N46: 0 | O46: 0 | P46: 0 | Q46: 0
B47: Ⅳ.판매관리비 | C47: GENERAL ADMINISTRATION EXPENSES | D47: =SUM(D48:D64) -> 1.5749754e+08 | E47: 0 | F47: =SUM(F48:F64) -> 9082306.6 | G47: =SUM(G48:G64) -> 10967150 | H47: =SUM(H48:H64) -> 12578191 | I47: =SUM(I48:I64) -> 13145494 | J47: =SUM(J48:J64) -> 11083466 | K47: =SUM(K48:K64) -> 16371539 | L47: =SUM(L48:L64) -> 11408051 | M47: =SUM(M48:M64) -> 13913303 | ... Q47: =SUM(Q48:Q64) -> 16584257
C48: Employee Salaries Expenses | D48: =SUM(F48:Q48) -> 46313241 | F48: 2686136.6 | G48: 3628782.2 | H48: 3184782.2 | I48: 4984782.2 | J48: 3184782.2 | K48: 6064782.2 | L48: 3763198.9 | M48: 3763198.9 | N48: 3763198.9 | O48: 3763198.9 | P48: 3763198.9 | Q48: 3763198.9
C49: Employee Benefits Expense | D49: =SUM(F49:Q49) -> 11831526 | F49: 752656.13 | G49: 945983.25 | H49: 979362.52 | I49: 864378.22 | J49: 873154.97 | K49: 789362.52 | L49: 1149930.2 | M49: 1293118.4 | N49: 1258966.7 | O49: 1048492.4 | P49: 944008.58 | Q49: 932112.52
C50: Rental Expenses | D50: =SUM(F50:Q50) -> 7747000 | F50: 628250 | G50: 628250 | H50: 628250 | I50: 628250 | J50: 654250 | K50: 654250 | L50: 654250 | M50: 654250 | N50: 654250 | O50: 654250 | P50: 654250 | Q50: 654250
C51: Travel and Accomodation Expenses | D51: =SUM(F51:Q51) -> 7174380 | F51: 362260.83 | G51: 362260.83 | H51: 362260.83 | I51: 362260.83 | J51: 362260.83 | K51: 362260.83 | L51: 362260.83 | M51: 362260.83 | N51: 362260.83 | O51: 362260.83 | P51: 362260.83 | Q51: 3189510.8
C52: Business Hospitality Expenses | D52: =SUM(F52:Q52) -> 420000 | F52: 35000 | G52: 35000 | H52: 35000 | I52: 35000 | J52: 35000 | K52: 35000 | L52: 35000 | M52: 35000 | N52: 35000 | O52: 35000 | P52: 35000 | Q52: 35000
C53: Insurance Expenses | D53: =SUM(F53:Q53) -> 0 | F53: 0 | G53: 0 | H53: 0 | I53: 0 | J53: 0 | K53: 0 | L53: 0 | M53: 0 | N53: 0 | O53: 0 | P53: 0 | Q53: 0
C54: Outsource Benefits and Services | D54: =SUM(F54:Q54) -> 275137.2 | F54: 22928.1 | G54: 22928.1 | H54: 22928.1 | I54: 22928.1 | J54: 22928.1 | K54: 22928.1 | L54: 22928.1 | M54: 22928.1 | N54: 22928.1 | O54: 22928.1 | P54: 22928.1 | Q54: 22928.1
C55: Office Supplies | D55: =SUM(F55:Q55) -> 590000 | F55: 48000 | G55: 46000 | H55: 46000 | I55: 58000 | J55: 46000 | K55: 46000 | L55: 46000 | M55: 58000 | N55: 46000 | O55: 46000 | P55: 46000 | Q55: 58000
C56: Vehicle Expenses | D56: =SUM(F56:Q56) -> 704000 | F56: 57000 | G56: 57000 | H56: 77000 | I56: 57000 | J56: 57000 | K56: 57000 | L56: 57000 | M56: 57000 | N56: 57000 | O56: 57000 | P56: 57000 | Q56: 57000
C57: Other Taxes | D57: =SUM(F57:Q57) -> 230258.73 | F57: 13544.631 | G57: 13544.631 | H57: 13544.631 | I57: 13544.631 | J57: 13544.631 | K57: 13544.631 | L57: 13544.631 | M57: 27089.262 | N57: 27089.262 | O57: 27089.262 | P57: 27089.262 | Q57: 27089.262
C58: Commission Expenses | D58: =SUM(F58:Q58) -> 928113.46 | F58: 46765.534 | G58: 58361.205 | H58: 83073.069 | I58: 69298.849 | J58: 63412.363 | K58: 96620.583 | L58: 59147.594 | M58: 88067.574 | N58: 79525.321 | O58: 116831.75 | P58: 82793.842 | Q58: 84215.767
C59: Services | D59: =SUM(F59:Q59) -> 5122095.2 | F59: 554129.54 | G59: 365751.14 | H59: 365751.14 | I59: 371751.14 | J59: 563751.14 | K59: 365751.14 | L59: 378591.14 | M59: 372591.14 | N59: 443547.74 | O59: 378591.14 | P59: 372591.14 | Q59: 589297.59
... C61: Training Expenses | D61: =SUM(F61:Q61) -> 660000 | F61: 30000 | G61: 30000 | H61: 30000 | I61: 30000 | J61: 30000 | K61: 30000 | L61: 30000 | M61: 30000 | N61: 30000 | O61: 30000 | P61: 30000 | Q61: 330000
C63: Depreciation and Amortization Expenses | D63: =SUM(F63:Q63) -> 1252710.6 | F63: 104392.55 | G63: 104392.55 | H63: 104392.55 | I63: 104392.55 | J63: 104392.55 | K63: 104392.55 | L63: 104392.55 | M63: 104392.55 | N63: 104392.55 | O63: 104392.55 | P63: 104392.55 | Q63: 104392.55 | T63: ← 연말 재무재표 매칭
C64: Communication Expenses(Royalty) | D64: =SUM(F64:Q64) -> 74249076 | F64: 3741242.7 | G64: 4668896.4 | H64: 6645845.5 | I64: 5543908 | J64: 5072989.1 | K64: 7729646.7 | L64: 4731807.6 | M64: 7045406 | N64: 6362025.7 | O64: 9346540.3 | P64: 6623507.4 | Q64: 6737261.4 | T64: ← 반기별 재무재표 매칭
B66: Ⅴ.영업이익 | C66: Ⅴ.OPERATING INCOME (or LOSS) | D66: =SUM(F66:Q66) -> 2.0000945e+08 | F66: 10861933 | G66: 14221416 | H66: 23734058 | I66: 17163541 | J66: 14885295 | K66: 26022986 | L66: 14354525 | M66: 24541025 | N66: 21357396 | O66: 19730948 | P66: 7425423.2 | Q66: 5710906.5
B67: (이익률) | C67: (Rate) | D67: =+D66/D$5 -> 0.10775054 | F67: 0.11613182 | G67: 0.12183964 | H67: 0.14285049 | I67: 0.12383713 | J67: 0.11736903 | K67: 0.13466585 | L67: 0.12134496 | M67: 0.13933065 | N67: 0.13428048 | O67: 0.08444172 | P67: 0.044842847 | Q67: 0.033906397
B68: Ⅵ.영업외수익 | C68: Ⅵ. NON-OPERATING INCOME | D68: 21926388 | F68: 1104821 | G68: 1378765.1 | H68: 1962575.1 | I68: 1637163.5 | J68: 1498097.1 | K68: 2282630.9 | L68: 1397343.3 | M68: 2080568.7 | N68: 1878760.7 | O68: 2760113.4 | P68: 1955978.5 | Q68: 1989571
C69: Interest Income | D69: 21926388 | F69: 1104821 | G69: 1378765.1 | H69: 1962575.1 | I69: 1637163.5 | J69: 1498097.1 | K69: 2282630.9 | L69: 1397343.3 | M69: 2080568.7 | N69: 1878760.7 | O69: 2760113.4 | P69: 1955978.5 | Q69: 1989571
C70: Commission Income | D70: 0 | F70: 0 | G70: 0 | H70: 0 | I70: 0 | J70: 0 | K70: 0 | L70: 0 | M70: 0 | N70: 0 | O70: 0 | P70: 0 | Q70: 0
C71: Non-Relevant Provisions | D71: 0 | F71: 0 | G71: 0 | H71: 0 | I71: 0 | J71: 0 | K71: 0 | L71: 0 | M71: 0 | N71: 0 | O71: 0 | P71: 0 | Q71: 0
C72: Exchange Profits | D72: 0 | F72: 0 | G72: 0 | H72: 0 | I72: 0 | J72: 0 | K72: 0 | L72: 0 | M72: 0 | N72: 0 | O72: 0 | P72: 0 | Q72: 0
C73: Foreign Currency Transactions Profit | D73: 0 | F73: 0 | G73: 0 | H73: 0 | I73: 0 | J73: 0 | K73: 0 | L73: 0 | M73: 0 | N73: 0 | O73: 0 | P73: 0 | Q73: 0
C74: Foreign Currency Translation of Profit | D74: 0 | F74: 0 | G74: 0 | H74: 0 | I74: 0 | J74: 0 | K74: 0 | L74: 0 | M74: 0 | N74: 0 | O74: 0 | P74: 0 | Q74: 0
C75: Translation of Foreign Currency Profit | D75: 0 | F75: 0 | G75: 0 | H75: 0 | I75: 0 | J75: 0 | K75: 0 | L75: 0 | M75: 0 | N75: 0 | O75: 0 | P75: 0 | Q75: 0
C76: Translation of Foreign Currency Profit | D76: 0 | F76: 0 | G76: 0 | H76: 0 | I76: 0 | J76: 0 | K76: 0 | L76: 0 | M76: 0 | N76: 0 | O76: 0 | P76: 0 | Q76: 0
C77: Rediscount Interest Income | D77: 0 | F77: 0 | G77: 0 | H77: 0 | I77: 0 | J77: 0 | K77: 0 | L77: 0 | M77: 0 | N77: 0 | O77: 0 | P77: 0 | Q77: 0
C78: Other Ordinary Income and Profits | D78: 0 | F78: 0 | G78: 0 | H78: 0 | I78: 0 | J78: 0 | K78: 0 | L78: 0 | M78: 0 | N78: 0 | O78: 0 | P78: 0 | Q78: 0
C79: OTHER EXTRAORDINARY INCOME AND PROFITS | D79: 0 | F79: 0 | G79: 0 | H79: 0 | I79: 0 | J79: 0 | K79: 0 | L79: 0 | M79: 0 | N79: 0 | O79: 0 | P79: 0 | Q79: 0
B80: Ⅶ. 영업외비용 | C80: Ⅶ. NON-OPERATING EXPENSES | D80: 59299038 | F80: 1870621.4 | G80: 2334448.2 | H80: 8362922.8 | I80: 2771954 | J80: 2536494.5 | K80: 8934823.3 | L80: 2365903.8 | M80: 3522703 | N80: 7381012.8 | O80: 8607770.1 | P80: 3311753.7 | Q80: 7298630.7
C81: Interest Expenses (-) | D81: 3934500 | F81: 0 | G81: 0 | H81: 0 | I81: 0 | J81: 0 | K81: 0 | L81: 0 | M81: 0 | N81: 0 | O81: 3934500 | P81: 0 | Q81: 0
C82: Commission Expenses(-) | D82: 0 | F82: 0 | G82: 0 | H82: 0 | I82: 0 | J82: 0 | K82: 0 | L82: 0 | M82: 0 | N82: 0 | O82: 0 | P82: 0 | Q82: 0
C83: Provision Expenses(-) | D83: 0 | F83: 0 | G83: 0 | H83: 0 | I83: 0 | J83: 0 | K83: 0 | L83: 0 | M83: 0 | N83: 0 | O83: 0 | P83: 0 | Q83: 0
C84: Losses on Sale of Securities(-) | D84: 0 | F84: 0 | G84: 0 | H84: 0 | I84: 0 | J84: 0 | K84: 0 | L84: 0 | M84: 0 | N84: 0 | O84: 0 | P84: 0 | Q84: 0
C85: Exchange Losses(-) | D85: 0 | F85: 0 | G85: 0 | H85: 0 | I85: 0 | J85: 0 | K85: 0 | L85: 0 | M85: 0 | N85: 0 | O85: 0 | P85: 0 | Q85: 0
C86: Foreign Currency Transactions Losses | D86: 37124538 | F86: 1870621.4 | G86: 2334448.2 | H86: 3322922.8 | I86: 2771954 | J86: 2536494.5 | K86: 3864823.3 | L86: 2365903.8 | M86: 3522703 | N86: 3181012.8 | O86: 4673270.1 | P86: 3311753.7 | Q86: 3368630.7
C87: Foreign Currency Translation of Losses | D87: 18240000 | F87: 0 | G87: 0 | H87: 5040000 | I87: 0 | J87: 0 | K87: 5070000 | L87: 0 | M87: 0 | N87: 4200000 | O87: 0 | P87: 0 | Q87: 3930000
C88: Rediscount Interest Expenses(-) | D88: 0 | F88: 0 | G88: 0 | H88: 0 | I88: 0 | J88: 0 | K88: 0 | L88: 0 | M88: 0 | N88: 0 | O88: 0 | P88: 0 | Q88: 0
C89: Other Ordinary Expenses and Losses(-) | D89: 0 | F89: 0 | G89: 0 | H89: 0 | I89: 0 | J89: 0 | K89: 0 | L89: 0 | M89: 0 | N89: 0 | O89: 0 | P89: 0 | Q89: 0
C90: Short-Term Borrowing Expenses(-) | D90: 0 | F90: 0 | G90: 0 | H90: 0 | I90: 0 | J90: 0 | K90: 0 | L90: 0 | M90: 0 | N90: 0 | O90: 0 | P90: 0 | Q90: 0
C91: Long-Term Borrowing Expenses(-) | D91: 0 | F91: 0 | G91: 0 | H91: 0 | I91: 0 | J91: 0 | K91: 0 | L91: 0 | M91: 0 | N91: 0 | O91: 0 | P91: 0 | Q91: 0
C92: Financing Expenses | D92: 0 | F92: 0 | G92: 0 | H92: 0 | I92: 0 | J92: 0 | K92: 0 | L92: 0 | M92: 0 | N92: 0 | O92: 0 | P92: 0 | Q92: 0
C93: OTHER EXTRAORDINARY EXPENSES AND LOSSES (-) | D93: 0 | F93: 0 | G93: 0 | H93: 0 | I93: 0 | J93: 0 | K93: 0 | L93: 0 | M93: 0 | N93: 0 | O93: 0 | P93: 0 | Q93: 0
B94: Ⅸ.당기손익 | C94: Ⅸ.NET INCOME (or LOSS) | D94: 1.626368e+08 | F94: 10096133 | G94: 13265733 | H94: 17333710 | I94: 16028750 | J94: 13846898 | K94: 19370793 | L94: 13385964 | M94: 23098891 | N94: 15855144 | O94: 13883292 | P94: 6069648 | Q94: 401846.78
B95: (이익률) | C95: (rate) | D95: 0.087616876 | F95: 0.10794416 | G95: 0.11365198 | H95: 0.1043281 | I95: 0.11564947 | J95: 0.10918137 | K95: 0.10024155 | L95: 0.1131573 | M95: 0.13114299 | N95: 0.099686139 | O95: 0.059415746 | P95: 0.03665519 | Q95: 0.0023858168

Sheet ★PL(Report)
B3: Profit and Loss statement FY 2026 | N3: (Affiliate Company: Kyungshin cable Türkiye)
B4: MONTH | C4: 2 | N4: (UNIT:TRY)
B5: 구분 | C5: ITEM | D5: Accumulated Plan | E5: Accumulated Actual | F5: Actual /Plan | G5: Prior month Actual | H5: costs /sales | I5: Month plan | J5: costs /sales | K5: Month Actual | L5: costs /sales | M5: Current /Prior | N5: Actual /Plan
B6: Ⅰ. 매출액 | C6: Ⅰ. SALES | D6: =SUM(D7,D16) -> 2.1025348e+08 | E6: =+E7+E16 -> 1.3952397e+08 | F6: =+IFERROR(E6/D6,) -> 0.66359887 | G6: =SUM(G7,G16) -> 75810248 | H6: =+IFERROR(G6/$G$6,) -> 1 | I6: =SUM(I7,I16) -> 1.1672241e+08 | J6: =+IFERROR(I6/$I$6,) -> 1 | K6: =SUM(K7,K16) -> 63713722 | L6: =+IFERROR(K6/$K$6,) -> 1 | M6: =+IFERROR(K6/G6,) -> 0.8404368 | N6: =+IFERROR(K6/I6,) -> 0.54585681
B7: 1. 상품 매출 | C7: 1 Merchandise | D7: =SUM(D8:D15) -> 2.1025348e+08 | E7: =SUM(E8:E15) -> 1.3269795e+08 | F7: =+IFERROR(E7/D7,) -> 0.6311332 | G7: =SUM(G8:G15) -> 68982368 | H7: =+IFERROR(G7/$G$6,) -> 0.9099346 | I7: =SUM(I8:I15) -> 1.1672241e+08 | J7: =+IFERROR(I7/$I$6,) -> 1 | K7: =SUM(K8:K15) -> 63715583 | L7: =+IFERROR(K7/$K$6,) -> 1.0000292 | M7: =+IFERROR(K7/G7,) -> 0.92365028 | N7: =+IFERROR(K7/I7,) -> 0.54587275
C8: FORD PHEV-E (V710) | D8: =IF($C$4=0,0,SUM('2026 Plan PL (New)'!$F7:OFFSET('2026 Plan PL (New)'!$F7,0,$C$4-1))) -> 45334165 | E8: =IF($C$4=0,0,SUM(PL!$F7:OFFSET(PL!$F7,0,$C$4-1))) -> 45828053 | F8: =+IFERROR(E8/D8,) -> 1.0108944 | G8: =OFFSET(PL!F7,0,$C$4-2) -> 23920697 | H8: =+IFERROR(G8/$G$6,) -> 0.31553382 | I8: =OFFSET('2026 Plan PL (New)'!F7,0,$C$4-1) -> 23596647 | J8: =+IFERROR(I8/$I$6,) -> 0.20216038 | K8: =OFFSET(PL!F7,0,$C$4-1) -> 21907356 | L8: =+IFERROR(K8/$K$6,) -> 0.34384047 | M8: =+IFERROR(K8/G8,) -> 0.9158327 | N8: =+IFERROR(K8/I8,) -> 0.92840971
C9: FORD PHEV-E (P703) | D9: =IF($C$4=0,0,SUM('2026 Plan PL (New)'!$F8:OFFSET('2026 Plan PL (New)'!$F8,0,$C$4-1))) -> 21677303 | E9: =IF($C$4=0,0,SUM(PL!$F8:OFFSET(PL!$F8,0,$C$4-1))) -> 25162751 | F9: =+IFERROR(E9/D9,) -> 1.1607879 | G9: =OFFSET(PL!F8,0,$C$4-2) -> 12070960 | H9: =+IFERROR(G9/$G$6,) -> 0.15922597 | I9: =OFFSET('2026 Plan PL (New)'!F8,0,$C$4-1) -> 10236504 | J9: =+IFERROR(I9/$I$6,) -> 0.087699561 | K9: =OFFSET(PL!F8,0,$C$4-1) -> 13091791 | L9: =+IFERROR(K9/$K$6,) -> 0.20547835 | M9: =+IFERROR(K9/G9,) -> 1.0845691 | N9: =+IFERROR(K9/I9,) -> 1.2789318
C10: BEV-E RWD | D10: =IF($C$4=0,0,SUM('2026 Plan PL (New)'!$F9:OFFSET('2026 Plan PL (New)'!$F9,0,$C$4-1))) -> 79586334 | E10: =IF($C$4=0,0,SUM(PL!$F9:OFFSET(PL!$F9,0,$C$4-1))) -> 1747054.9 | F10: =+IFERROR(E10/D10,) -> 0.021951695 | G10: =OFFSET(PL!F9,0,$C$4-2) -> 371310.73 | H10: =+IFERROR(G10/$G$6,) -> 0.0048978963 | I10: =OFFSET('2026 Plan PL (New)'!F9,0,$C$4-1) -> 40331839 | J10: =+IFERROR(I10/$I$6,) -> 0.34553638 | K10: =OFFSET(PL!F9,0,$C$4-1) -> 1375744.2 | L10: =+IFERROR(K10/$K$6,) -> 0.021592588 | M10: =+IFERROR(K10/G10,) -> 3.7051021 | N10: =+IFERROR(K10/I10,) -> 0.034110624
C11: BEV-E AWD | D11: =IF($C$4=0,0,SUM('2026 Plan PL (New)'!$F10:OFFSET('2026 Plan PL (New)'!$F10,0,$C$4-1))) -> 12842992 | E11: =IF($C$4=0,0,SUM(PL!$F10:OFFSET(PL!$F10,0,$C$4-1))) -> 350302.84 | F11: =+IFERROR(E11/D11,) -> 0.027275798 | G11: =OFFSET(PL!F10,0,$C$4-2) -> 240833.21 | H11: =+IFERROR(G11/$G$6,) -> 0.0031767896 | I11: =OFFSET('2026 Plan PL (New)'!F10,0,$C$4-1) -> 11503033 | J11: =+IFERROR(I11/$I$6,) -> 0.098550335 | K11: =OFFSET(PL!F10,0,$C$4-1) -> 109469.63 | L11: =+IFERROR(K11/$K$6,) -> 0.0017181485 | M11: =+IFERROR(K11/G11,) -> 0.45454543 | N11: =+IFERROR(K11/I11,) -> 0.0095165891
C12: FORD BEV-M | D12: =IF($C$4=0,0,SUM('2026 Plan PL (New)'!$F11:OFFSET('2026 Plan PL (New)'!$F11,0,$C$4-1))) -> 47218982 | E12: =IF($C$4=0,0,SUM(PL!$F12:OFFSET(PL!$F12,0,$C$4-1))) -> 35440595 | F12: =+IFERROR(E12/D12,) -> 0.7505582 | G12: =OFFSET(PL!F12,0,$C$4-2) -> 15721984 | H12: =+IFERROR(G12/$G$6,) -> 0.20738599 | I12: =OFFSET('2026 Plan PL (New)'!F11,0,$C$4-1) -> 28331389 | J12: =+IFERROR(I12/$I$6,) -> 0.24272451 | K12: =OFFSET(PL!F12,0,$C$4-1) -> 19718611 | L12: =+IFERROR(K12/$K$6,) -> 0.30948766 | M12: =+IFERROR(K12/G12,) -> 1.2542063 | N12: =+IFERROR(K12/I12,) -> 0.69599873
C13: EV-V4 | D13: =IF($C$4=0,0,SUM('2026 Plan PL (New)'!$F12:OFFSET('2026 Plan PL (New)'!$F12,0,$C$4-1))) -> 1378803.9 | E13: =IF($C$4=0,0,SUM(PL!$F13:OFFSET(PL!$F13,0,$C$4-1))) -> 74025.583 | F13: =+IFERROR(E13/D13,) -> 0.053688262 | G13: =OFFSET(PL!F13,0,$C$4-2) -> 67848.567 | H13: =+IFERROR(G13/$G$6,) -> 0.00089497883 | I13: =OFFSET('2026 Plan PL (New)'!F12,0,$C$4-1) -> 1378803.9 | J13: =+IFERROR(I13/$I$6,) -> 0.011812675 | K13: =OFFSET(PL!F13,0,$C$4-1) -> 6177.0163 | L13: =+IFERROR(K13/$K$6,) -> 9.6949544e-05 | M13: =+IFERROR(K13/G13,) -> 0.091041221 | N13: =+IFERROR(K13/I13,) -> 0.0044799819
C14: Components | D14: =IF($C$4=0,0,SUM('2026 Plan PL (New)'!$F13:OFFSET('2026 Plan PL (New)'!$F13,0,$C$4-1))) -> 2214897.8 | E14: =IF($C$4=0,0,SUM(PL!$F14:OFFSET(PL!$F14,0,$C$4-1))) -> 1628059.3 | F14: =+IFERROR(E14/D14,) -> 0.73504941 | G14: =OFFSET(PL!F14,0,$C$4-2) -> 932361.78 | H14: =+IFERROR(G14/$G$6,) -> 0.012298625 | I14: =OFFSET('2026 Plan PL (New)'!F13,0,$C$4-1) -> 1344193.2 | J14: =+IFERROR(I14/$I$6,) -> 0.011516153 | K14: =OFFSET(PL!F14,0,$C$4-1) -> 695697.55 | L14: =+IFERROR(K14/$K$6,) -> 0.010919116 | M14: =+IFERROR(K14/G14,) -> 0.74616696 | N14: =+IFERROR(K14/I14,) -> 0.51755772
C15: BEV-E1 | D15: 0 | E15: =IF($C$4=0,0,SUM(PL!$F15:OFFSET(PL!$F15,0,$C$4-1))) -> 22467110 | G15: =OFFSET(PL!F15,0,$C$4-2) -> 15656373 | H15: =+IFERROR(G15/$G$6,) -> 0.20652054 | I15: =OFFSET('2026 Plan PL (New)'!F14,0,$C$4-1) -> 0 | J15: =+IFERROR(I15/$I$6,) -> 0 | K15: =OFFSET(PL!F15,0,$C$4-1) -> 6810736.6 | L15: =+IFERROR(K15/$K$6,) -> 0.10689591 | M15: =+IFERROR(K15/G15,) -> 0.43501369 | N15: =+IFERROR(K15/I15,) -> 0
B16: 2. 기타 매출 | C16: 2. Other sales | D16: =SUM(D17:D22) -> 0 | E16: =SUM(E17:E20) -> 6826019.2 | F16: =+IFERROR(E16/D16,) -> 0 | G16: =SUM(G17:G20) -> 6827880.1 | H16: =+IFERROR(G16/$G$6,) -> 0.090065397 | I16: =SUM(I17:I20) -> 0 | J16: =+IFERROR(I16/$I$6,) -> 0 | K16: =SUM(K17:K20) -> -1860.8359 | L16: =+IFERROR(K16/$K$6,) -> -2.9206203e-05 | M16: =+IFERROR(K16/G16,) -> -0.00027253494 | N16: =+IFERROR(K16/I16,) -> 0
B17: └ scrap | C17: └ Scrap | D17: =IF($C$4=0,0,SUM('2026 Plan PL (New)'!$F16:OFFSET('2026 Plan PL (New)'!$F16,0,$C$4-1))) -> 0 | E17: =IF($C$4=0,0,SUM(PL!$F18:OFFSET(PL!$F18,0,$C$4-1))) -> 0 | F17: =+IFERROR(E17/D17,) -> 0 | G17: =OFFSET(PL!F18,0,$C$4-2) -> 0 | H17: =+IFERROR(G17/$G$6,) -> 0 | I17: =OFFSET('2026 Plan PL (New)'!F16,0,$C$4-1) -> 0 | J17: =+IFERROR(I17/$I$6,) -> 0 | K17: =OFFSET(PL!F18,0,$C$4-1) -> 0 | L17: =+IFERROR(K17/$K$6,) -> 0 | M17: =+IFERROR(K17/G17,) -> 0 | N17: =+IFERROR(K17/I17,) -> 0
B18: └ Test Parts | C18: └ Test Parts | D18: =IF($C$4=0,0,SUM('2026 Plan PL (New)'!$F17:OFFSET('2026 Plan PL (New)'!$F17,0,$C$4-1))) -> 0 | E18: =IF($C$4=0,0,SUM(PL!$F19:OFFSET(PL!$F19,0,$C$4-1))) -> 0 | F18: =+IFERROR(E18/D18,) -> 0 | G18: =OFFSET(PL!F19,0,$C$4-2) -> 0 | H18: =+IFERROR(G18/$G$6,) -> 0 | I18: =OFFSET('2026 Plan PL (New)'!F17,0,$C$4-1) -> 0 | J18: =+IFERROR(I18/$I$6,) -> 0 | K18: =OFFSET(PL!F19,0,$C$4-1) -> 0 | L18: =+IFERROR(K18/$K$6,) -> 0 | M18: =+IFERROR(K18/G18,) -> 0 | N18: =+IFERROR(K18/I18,) -> 0
B19: └ 기타 | C19: └ Other | D19: =IF($C$4=0,0,SUM('2026 Plan PL (New)'!$F18:OFFSET('2026 Plan PL (New)'!$F18,0,$C$4-1))) -> 0 | E19: =IF($C$4=0,0,SUM(PL!$F20:OFFSET(PL!$F20,0,$C$4-1))) -> 6826019.2 | F19: =+IFERROR(E19/D19,) -> 0 | G19: =OFFSET(PL!F20,0,$C$4-2) -> 6827880.1 | H19: =+IFERROR(G19/$G$6,) -> 0.090065397 | I19: =OFFSET('2026 Plan PL (New)'!F18,0,$C$4-1) -> 0 | J19: =+IFERROR(I19/$I$6,) -> 0 | K19: =OFFSET(PL!F20,0,$C$4-1) -> -1860.8359 | L19: =+IFERROR(K19/$K$6,) -> -2.9206203e-05 | M19: =+IFERROR(K19/G19,) -> -0.00027253494 | N19: =+IFERROR(K19/I19,) -> 0
B20: └ 기타(투자비) | C20: └ Investment | D20: =IF($C$4=0,0,SUM('2026 Plan PL (New)'!$F19:OFFSET('2026 Plan PL (New)'!$F19,0,$C$4-1))) -> 0 | E20: =IF($C$4=0,0,SUM(PL!$F21:OFFSET(PL!$F21,0,$C$4-1))) -> 0 | F20: =+IFERROR(E20/D20,) -> 0 | G20: =OFFSET(PL!F21,0,$C$4-2) -> 0 | H20: =+IFERROR(G20/$G$6,) -> 0 | I20: =OFFSET('2026 Plan PL (New)'!F19,0,$C$4-1) -> 0 | J20: =+IFERROR(I20/$I$6,) -> 0 | K20: =OFFSET(PL!F21,0,$C$4-1) -> 0 | L20: =+IFERROR(K20/$K$6,) -> 0 | M20: =+IFERROR(K20/G20,) -> 0 | N20: =+IFERROR(K20/I20,) -> 0
C21: *(Deductions) | D21: =IF($C$4=0,0,SUM('2026 Plan PL (New)'!$F20:OFFSET('2026 Plan PL (New)'!$F20,0,$C$4-1))) -> 0 | E21: =IF($C$4=0,0,SUM(PL!$F22:OFFSET(PL!$F22,0,$C$4-1))) -> 0 | F21: =+IFERROR(E21/D21,) -> 0 | G21: =OFFSET(PL!F22,0,$C$4-2) -> 0 | H21: =+IFERROR(G21/$G$6,) -> 0 | I21: =OFFSET('2026 Plan PL (New)'!F20,0,$C$4-1) -> 0 | J21: =+IFERROR(I21/$I$6,) -> 0 | K21: =OFFSET(PL!F22,0,$C$4-1) -> 0 | L21: =+IFERROR(K21/$K$6,) -> 0 | M21: =+IFERROR(K21/G21,) -> 0 | N21: =+IFERROR(K21/I21,) -> 0
C22: *(Returns) | D22: =IF($C$4=0,0,SUM('2026 Plan PL (New)'!$F21:OFFSET('2026 Plan PL (New)'!$F21,0,$C$4-1))) -> 0 | E22: =IF($C$4=0,0,SUM(PL!$F23:OFFSET(PL!$F23,0,$C$4-1))) -> -2259709.7 | F22: =+IFERROR(E22/D22,) -> 0 | G22: =OFFSET(PL!F23,0,$C$4-2) -> -2257848.9 | H22: =+IFERROR(G22/$G$6,) -> -0.029782898 | I22: =OFFSET('2026 Plan PL (New)'!F21,0,$C$4-1) -> 0 | J22: =+IFERROR(I22/$I$6,) -> 0 | K22: =OFFSET(PL!F23,0,$C$4-1) -> -1860.8359 | L22: =+IFERROR(K22/$K$6,) -> -2.9206203e-05 | M22: =+IFERROR(K22/G22,) -> 0.00082416318 | N22: =+IFERROR(K22/I22,) -> 0
B24: Ⅱ. 매출원가 | C24: Ⅱ. COST OF SALES | D24: =+SUM(D26,D33) -> 1.6114448e+08 | E24: =+SUM(E26,E33) -> 1.7824785e+08 | F24: =+IFERROR(E24/D24,) -> 1.1061368 | G24: =+SUM(G26,G33) -> 72379542 | H24: =+IFERROR(G24/$G$6,) -> 0.95474615 | I24: =+SUM(I26,I33) -> 89422523 | J24: =+IFERROR(I24/$I$6,) -> 0.76611273 | K24: =+SUM(K26,K33) -> 1.0586831e+08 | L24: =+IFERROR(K24/$K$6,) -> 1.6616249 | M24: =+IFERROR(K24/G24,) -> 1.4626828 | N24: =+IFERROR(K24/I24,) -> 1.183911
B26: 상품매출원가 | C26: Cost of merchandise sold | D26: =D28+D29+D30-D31-D32 -> 1.6114448e+08 | E26: =E28+E29+E30-E31-E32 -> 1.7820411e+08 | F26: =+IFERROR(E26/D26,) -> 1.1058654 | G26: =G28+G29+G30-G31-G32 -> 72365419 | H26: =+IFERROR(G26/$G$6,) -> 0.95455985 | I26: =I28+I29+I30-I31-I32 -> 89422523 | J26: =+IFERROR(I26/$I$6,) -> 0.76611273 | K26: =K28+K29+K30-K31-K32 -> 1.0583869e+08 | L26: =+IFERROR(K26/$K$6,) -> 1.66116 | M26: =+IFERROR(K26/G26,) -> 1.4625589 | N26: =+IFERROR(K26/I26,) -> 1.1835797
B28: 1.기초 상품재고 | C28: 1. Beginning Merchandise | D28: =IF($C$4=0,0,SUM('2026 Plan PL (New)'!$F27:OFFSET('2026 Plan PL (New)'!$F27,0,$C$4-1))) -> 0 | E28: =IF($C$4=0,0,SUM(PL!$F29:OFFSET(PL!$F29,0,$C$4-1))) -> 33327888 | F28: =+IFERROR(E28/D28,) -> 0 | G28: =OFFSET(PL!F29,0,$C$4-2) -> 25971576 | H28: =+IFERROR(G28/$G$6,) -> 0.34258661 | I28: =OFFSET('2026 Plan PL (New)'!F27,0,$C$4-1) -> 0 | J28: =+IFERROR(I28/$I$6,) -> 0 | K28: =OFFSET(PL!F29,0,$C$4-1) -> 7356311.9 | L28: =+IFERROR(K28/$K$6,) -> 0.11545883 | M28: =+IFERROR(K28/G28,) -> 0.28324472 | N28: =+IFERROR(K28/I28,) -> 0
B29: 2.당기 상품매입원가 | C29: 2. Cost of Merchandise | D29: =IF($C$4=0,0,SUM('2026 Plan PL (New)'!$F28:OFFSET('2026 Plan PL (New)'!$F28,0,$C$4-1))) -> 1.6114448e+08 | E29: =IF($C$4=0,0,SUM(PL!$F30:OFFSET(PL!$F30,0,$C$4-1))) -> 1.6363327e+08 | F29: =+IFERROR(E29/D29,) -> 1.0154445 | G29: =OFFSET(PL!F30,0,$C$4-2) -> 53750154 | H29: =+IFERROR(G29/$G$6,) -> 0.70900909 | I29: =OFFSET('2026 Plan PL (New)'!F28,0,$C$4-1) -> 89422523 | J29: =+IFERROR(I29/$I$6,) -> 0.76611273 | K29: =OFFSET(PL!F30,0,$C$4-1) -> 1.0988312e+08 | L29: =+IFERROR(K29/$K$6,) -> 1.7246382 | M29: =+IFERROR(K29/G29,) -> 2.0443312 | N29: =+IFERROR(K29/I29,) -> 1.2288081
B30: 3.타계정전입 (+) | C30: 3. Transferred from other accounts | D30: =IF($C$4=0,0,SUM('2026 Plan PL (New)'!$F29:OFFSET('2026 Plan PL (New)'!$F29,0,$C$4-1))) -> 0 | E30: =IF($C$4=0,0,SUM(PL!$F31:OFFSET(PL!$F31,0,$C$4-1))) -> 0 | F30: =+IFERROR(E30/D30,) -> 0 | G30: =OFFSET(PL!F31,0,$C$4-2) -> 0 | H30: =+IFERROR(G30/$G$6,) -> 0 | I30: =OFFSET('2026 Plan PL (New)'!F29,0,$C$4-1) -> 0 | J30: =+IFERROR(I30/$I$6,) -> 0 | K30: =OFFSET(PL!F31,0,$C$4-1) -> 0 | L30: =+IFERROR(K30/$K$6,) -> 0 | M30: =+IFERROR(K30/G30,) -> 0 | N30: =+IFERROR(K30/I30,) -> 0
B31: 4.타계정대체 (-) | C31: 4. Transferred to other accounts | D31: =IF($C$4=0,0,SUM('2026 Plan PL (New)'!$F30:OFFSET('2026 Plan PL (New)'!$F30,0,$C$4-1))) -> 0 | E31: =IF($C$4=0,0,SUM(PL!$F32:OFFSET(PL!$F32,0,$C$4-1))) -> 0 | F31: =+IFERROR(E31/D31,) -> 0 | G31: =OFFSET(PL!F32,0,$C$4-2) -> 0 | H31: =+IFERROR(G31/$G$6,) -> 0 | I31: =OFFSET('2026 Plan PL (New)'!F30,0,$C$4-1) -> 0 | J31: =+IFERROR(I31/$I$6,) -> 0 | K31: =OFFSET(PL!F32,0,$C$4-1) -> 0 | L31: =+IFERROR(K31/$K$6,) -> 0 | M31: =+IFERROR(K31/G31,) -> 0 | N31: =+IFERROR(K31/I31,) -> 0
B32: 5.기말 상품재고 | C32: 5. Ending Merchandise | D32: =IF($C$4=0,0,SUM('2026 Plan PL (New)'!$F31:OFFSET('2026 Plan PL (New)'!$F31,0,$C$4-1))) -> 0 | E32: =IF($C$4=0,0,SUM(PL!$F33:OFFSET(PL!$F33,0,$C$4-1))) -> 18757054 | F32: =+IFERROR(E32/D32,) -> 0 | G32: =OFFSET(PL!F33,0,$C$4-2) -> 7356311.9 | H32: =+IFERROR(G32/$G$6,) -> 0.097035851 | I32: =OFFSET('2026 Plan PL (New)'!F31,0,$C$4-1) -> 0 | J32: =+IFERROR(I32/$I$6,) -> 0 | K32: =OFFSET(PL!F33,0,$C$4-1) -> 11400742 | L32: =+IFERROR(K32/$K$6,) -> 0.178937 | M32: =+IFERROR(K32/G32,) -> 1.5497905 | N32: =+IFERROR(K32/I32,) -> 0
B33: 기타매출원가 | C33: Cost of other sold | D33: =+D34+D35+D36 -> 0 | E33: =+E34+E35+E36 -> 43743.03 | F33: =+IFERROR(E33/D33,) -> 0 | G33: =+G34+G35+G36 -> 14123.12 | H33: =++IFERROR(G33/G16,) -> 0.0020684488 | I33: =+I34+I35+I36 -> 0 | J33: =++IFERROR(I33/I16,) -> 0 | K33: =+K34+K35+K36 -> 29619.91 | L33: =++IFERROR(K33/K16,) -> -15.917529 | M33: =+IFERROR(K33/G33,) -> 2.0972639 | N33: =+IFERROR(K33/I33,) -> 0
B34: 원재료 매출원가 | C34: Raw material | D34: =IF($C$4=0,0,SUM('2026 Plan PL (New)'!$F33:OFFSET('2026 Plan PL (New)'!$F33,0,$C$4-1))) -> 0 | E34: =IF($C$4=0,0,SUM(PL!$F35:OFFSET(PL!$F35,0,$C$4-1))) -> 0 | F34: =+IFERROR(E34/D34,) -> 0 | G34: =OFFSET(PL!F35,0,$C$4-2) -> 0 | H34: =+IFERROR(G34/$G$6,) -> 0 | I34: =OFFSET('2026 Plan PL (New)'!F33,0,$C$4-1) -> 0 | J34: =+IFERROR(I34/$I$6,) -> 0 | K34: =OFFSET(PL!F35,0,$C$4-1) -> 0 | L34: =+IFERROR(K34/$K$6,) -> 0 | M34: =+IFERROR(K34/G34,) -> 0 | N34: =+IFERROR(K34/I34,) -> 0
B35: 반제품 매출원가 | C35: Halb | D35: =IF($C$4=0,0,SUM('2026 Plan PL (New)'!$F34:OFFSET('2026 Plan PL (New)'!$F34,0,$C$4-1))) -> 0 | E35: =IF($C$4=0,0,SUM(PL!$F36:OFFSET(PL!$F36,0,$C$4-1))) -> 0 | F35: =+IFERROR(E35/D35,) -> 0 | G35: =OFFSET(PL!F36,0,$C$4-2) -> 0 | H35: =+IFERROR(G35/$G$6,) -> 0 | I35: =OFFSET('2026 Plan PL (New)'!F34,0,$C$4-1) -> 0 | J35: =+IFERROR(I35/$I$6,) -> 0 | K35: =OFFSET(PL!F36,0,$C$4-1) -> 0 | L35: =+IFERROR(K35/$K$6,) -> 0 | M35: =+IFERROR(K35/G35,) -> 0 | N35: =+IFERROR(K35/I35,) -> 0
B36: 기타 | C36: Other | D36: =IF($C$4=0,0,SUM('2026 Plan PL (New)'!$F35:OFFSET('2026 Plan PL (New)'!$F35,0,$C$4-1))) -> 0 | E36: =IF($C$4=0,0,SUM(PL!$F37:OFFSET(PL!$F37,0,$C$4-1))) -> 43743.03 | F36: =+IFERROR(E36/D36,) -> 0 | G36: =OFFSET(PL!F37,0,$C$4-2) -> 14123.12 | H36: =+IFERROR(G36/$G$6,) -> 0.00018629566 | I36: =OFFSET('2026 Plan PL (New)'!F35,0,$C$4-1) -> 0 | J36: =+IFERROR(I36/$I$6,) -> 0 | K36: =OFFSET(PL!F37,0,$C$4-1) -> 29619.91 | L36: =+IFERROR(K36/$K$6,) -> 0.00046489059 | M36: =+IFERROR(K36/G36,) -> 2.0972639 | N36: =+IFERROR(K36/I36,) -> 0
B37: 기타(투자비) | C37: Investment | D37: =IF($C$4=0,0,SUM('2026 Plan PL (New)'!$F36:OFFSET('2026 Plan PL (New)'!$F36,0,$C$4-1))) -> 0 | E37: =IF($C$4=0,0,SUM(PL!$F38:OFFSET(PL!$F38,0,$C$4-1))) -> 0 | F37: =+IFERROR(E37/D37,) -> 0 | G37: =OFFSET(PL!F38,0,$C$4-2) -> 0 | H37: =+IFERROR(G37/$G$6,) -> 0 | I37: =OFFSET('2026 Plan PL (New)'!F36,0,$C$4-1) -> 0 | J37: =+IFERROR(I37/$I$6,) -> 0 | K37: =OFFSET(PL!F38,0,$C$4-1) -> 0 | L37: =+IFERROR(K37/$K$6,) -> 0 | M37: =+IFERROR(K37/G37,) -> 0 | N37: =+IFERROR(K37/I37,) -> 0
B38: Ⅲ. 매출총이익 | C38: Ⅲ. GROSS PROFIT (or GROSS LOSS) | D38: =+D6-D24 -> 49108995 | E38: =+E6-E24 -> -38723879 | F38: =+IFERROR(E38/D38,) -> -0.78852925 | G38: =+G6-G24 -> 3430705.9 | H38: =+IFERROR(G38/$G$6,) -> 0.045253855 | I38: =+I6-I24 -> 27299886 | J38: =+IFERROR(I38/$I$6,) -> 0.23388727 | K38: =+K6-K24 -> -42154585 | L38: =+IFERROR(K38/$K$6,) -> -0.6616249 | M38: =+IFERROR(K38/G38,) -> -12.287438 | N38: =+IFERROR(K38/I38,) -> -1.5441305
B39: (이익률) | C39: (Rate) | D39: =IFERROR(D38/D6,) -> 0.23357043 | E39: =IFERROR(E38/E6,) -> -0.27754284 | G39: =IFERROR(G38/G6,) -> 0.045253855 | I39: =IFERROR(I38/I6,) -> 0.23388727 | K39: =IFERROR(K38/K6,) -> -0.6616249
B40: Ⅳ.판매관리비 | C40: SELLING AND MARKETING EXPENSES | D40: =SUM(D41:D47) -> 3976189.2 | E40: =SUM(E41:E47) -> 3732292.6 | F40: =+IFERROR(E40/D40,) -> 0.93866074 | G40: =SUM(G41:G47) -> 1545174.3 | H40: =+IFERROR(G40/$G$6,) -> 0.02038213 | I40: =SUM(I41:I47) -> 2111319.2 | K40: =SUM(K41:K47) -> 2187118.3 | L40: =+IFERROR(K40/$K$6,) -> 0.034327273 | M40: =+IFERROR(K40/G40,) -> 1.4154509
C41: Export Expenses | D41: =IF($C$4=0,0,SUM('2026 Plan PL (New)'!$F40:OFFSET('2026 Plan PL (New)'!$F40,0,$C$4-1))) -> 191565.56 | E41: =IF($C$4=0,0,SUM(PL!$F42:OFFSET(PL!$F42,0,$C$4-1))) -> 136263.82 | F41: =+IFERROR(E41/D41,) -> 0.71131691 | G41: =OFFSET(PL!F42,0,$C$4-2) -> 74012.66 | H41: =+IFERROR(G41/$G$6,) -> 0.00097628833 | I41: =OFFSET('2026 Plan PL (New)'!F40,0,$C$4-1) -> 95782.779 | J41: =+IFERROR(I41/$I$6,) -> 0.00082060317 | K41: =OFFSET(PL!F42,0,$C$4-1) -> 62251.16 | L41: =+IFERROR(K41/$K$6,) -> 0.00097704479 | M41: =+IFERROR(K41/G41,) -> 0.841088 | N41: =+IFERROR(K41/I41,) -> 0.64992017
C42: Import Expenses | D42: =IF($C$4=0,0,SUM('2026 Plan PL (New)'!$F41:OFFSET('2026 Plan PL (New)'!$F41,0,$C$4-1))) -> 41795.933 | E42: =IF($C$4=0,0,SUM(PL!$F43:OFFSET(PL!$F43,0,$C$4-1))) -> 0 | F42: =+IFERROR(E42/D42,) -> 0 | G42: =OFFSET(PL!F43,0,$C$4-2) -> 0 | H42: =+IFERROR(G42/$G$6,) -> 0 | I42: =OFFSET('2026 Plan PL (New)'!F41,0,$C$4-1) -> 20897.966 | J42: =+IFERROR(I42/$I$6,) -> 0.00017903988 | K42: =OFFSET(PL!F43,0,$C$4-1) -> 0 | L42: =+IFERROR(K42/$K$6,) -> 0 | M42: =+IFERROR(K42/G42,) -> 0 | N42: =+IFERROR(K42/I42,) -> 0
C43: Domestic Transportation Expenses | D43: =IF($C$4=0,0,SUM('2026 Plan PL (New)'!$F42:OFFSET('2026 Plan PL (New)'!$F42,0,$C$4-1))) -> 1109672.3 | E43: =IF($C$4=0,0,SUM(PL!$F44:OFFSET(PL!$F44,0,$C$4-1))) -> 2297201 | F43: =+IFERROR(E43/D43,) -> 2.0701616 | G43: =OFFSET(PL!F44,0,$C$4-2) -> 865151 | H43: =+IFERROR(G43/$G$6,) -> 0.011412059 | I43: =OFFSET('2026 Plan PL (New)'!F42,0,$C$4-1) -> 554836.15 | J43: =+IFERROR(I43/$I$6,) -> 0.0047534673 | K43: =OFFSET(PL!F44,0,$C$4-1) -> 1432050 | L43: =+IFERROR(K43/$K$6,) -> 0.02247632 | M43: =+IFERROR(K43/G43,) -> 1.6552602 | N43: =+IFERROR(K43/I43,) -> 2.5810323
C44: Sample Expenses | D44: =IF($C$4=0,0,SUM('2026 Plan PL (New)'!$F43:OFFSET('2026 Plan PL (New)'!$F43,0,$C$4-1))) -> 82714.97 | E44: =IF($C$4=0,0,SUM(PL!$F45:OFFSET(PL!$F45,0,$C$4-1))) -> 159863.27 | F44: =+IFERROR(E44/D44,) -> 1.9327006 | G44: =OFFSET(PL!F45,0,$C$4-2) -> 0 | H44: =+IFERROR(G44/$G$6,) -> 0 | I44: =OFFSET('2026 Plan PL (New)'!F43,0,$C$4-1) -> 41357.485 | J44: =+IFERROR(I44/$I$6,) -> 0.00035432344 | K44: =OFFSET(PL!F45,0,$C$4-1) -> 159863.27 | L44: =+IFERROR(K44/$K$6,) -> 0.002509087 | M44: =+IFERROR(K44/G44,) -> 0 | N44: =+IFERROR(K44/I44,) -> 3.8654011
C45: Rework & Sorting Expenses | D45: =IF($C$4=0,0,SUM('2026 Plan PL (New)'!$F44:OFFSET('2026 Plan PL (New)'!$F44,0,$C$4-1))) -> 2102534.8 | E45: =IF($C$4=0,0,SUM(PL!$F46:OFFSET(PL!$F46,0,$C$4-1))) -> 100468.19 | F45: =+IFERROR(E45/D45,) -> 0.047784318 | G45: =OFFSET(PL!F46,0,$C$4-2) -> 100468.19 | H45: =+IFERROR(G45/$G$6,) -> 0.0013252587 | I45: =OFFSET('2026 Plan PL (New)'!F44,0,$C$4-1) -> 1167224.1 | J45: =+IFERROR(I45/$I$6,) -> 0.01 | K45: =OFFSET(PL!F46,0,$C$4-1) -> 0 | L45: =+IFERROR(K45/$K$6,) -> 0 | M45: =+IFERROR(K45/G45,) -> 0 | N45: =+IFERROR(K45/I45,) -> 0
C46: Package Expense | D46: =IF($C$4=0,0,SUM('2026 Plan PL (New)'!$F45:OFFSET('2026 Plan PL (New)'!$F45,0,$C$4-1))) -> 447905.63 | E46: =IF($C$4=0,0,SUM(PL!$F47:OFFSET(PL!$F47,0,$C$4-1))) -> 950919.2 | F46: =+IFERROR(E46/D46,) -> 2.1230347 | G46: =OFFSET(PL!F47,0,$C$4-2) -> 420555 | H46: =+IFERROR(G46/$G$6,) -> 0.005547469 | I46: =OFFSET('2026 Plan PL (New)'!F45,0,$C$4-1) -> 231220.77 | J46: =+IFERROR(I46/$I$6,) -> 0.0019809458 | K46: =OFFSET(PL!F47,0,$C$4-1) -> 530364.2 | L46: =+IFERROR(K46/$K$6,) -> 0.0083241754 | M46: =+IFERROR(K46/G46,) -> 1.2611054 | N46: =+IFERROR(K46/I46,) -> 2.2937568
C47: Other Expenses | D47: =IF($C$4=0,0,SUM('2026 Plan PL (New)'!$F46:OFFSET('2026 Plan PL (New)'!$F46,0,$C$4-1))) -> 0 | E47: =IF($C$4=0,0,SUM(PL!$F48:OFFSET(PL!$F48,0,$C$4-1))) -> 87577.17 | F47: =+IFERROR(E47/D47,) -> 0 | G47: =OFFSET(PL!F48,0,$C$4-2) -> 84987.47 | H47: =+IFERROR(G47/$G$6,) -> 0.0011210552 | I47: =OFFSET('2026 Plan PL (New)'!F46,0,$C$4-1) -> 0 | J47: =+IFERROR(I47/$I$6,) -> 0 | K47: =OFFSET(PL!F48,0,$C$4-1) -> 2589.7 | L47: =+IFERROR(K47/$K$6,) -> 4.0645875e-05 | M47: =+IFERROR(K47/G47,) -> 0.030471551 | N47: =+IFERROR(K47/I47,) -> 0
B48: Ⅳ.판매관리비 | C48: Ⅳ. SELLING & ADMINISTRATIVE EXPENSES | D48: =SUM(D49:D65) -> 20049457 | E48: =SUM(E49:E65) -> 16646915 | F48: =+IFERROR(E48/D48,) -> 0.83029258 | G48: =SUM(G49:G65) -> 7891350.1 | H48: =+IFERROR(G48/$G$6,) -> 0.10409345 | I48: =SUM(I49:I65) -> 10967150 | J48: =+IFERROR(I48/$I$6,) -> 0.093959252 | K48: =SUM(K49:K65) -> 8755565.2 | L48: =+IFERROR(K48/$K$6,) -> 0.1374204 | M48: =+IFERROR(K48/G48,) -> 1.1095142 | N48: =+IFERROR(K48/I48,) -> 0.7983446
C49: Employee Salaries Expenses | D49: =IF($C$4=0,0,SUM('2026 Plan PL (New)'!$F48:OFFSET('2026 Plan PL (New)'!$F48,0,$C$4-1))) -> 6314918.8 | E49: =IF($C$4=0,0,SUM(PL!$F50:OFFSET(PL!$F50,0,$C$4-1))) -> 7292146.2 | F49: =+IFERROR(E49/D49,) -> 1.154749 | G49: =OFFSET(PL!F50,0,$C$4-2) -> 3078648.2 | H49: =+IFERROR(G49/$G$6,) -> 0.040609921 | I49: =OFFSET('2026 Plan PL (New)'!F48,0,$C$4-1) -> 3628782.2 | J49: =+IFERROR(I49/$I$6,) -> 0.031088993 | K49: =OFFSET(PL!F50,0,$C$4-1) -> 4213498 | L49: =+IFERROR(K49/$K$6,) -> 0.06613172 | M49: =+IFERROR(K49/G49,) -> 1.3686195 | N49: =+IFERROR(K49/I49,) -> 1.1611328
C50: Employee Benefits Expense | D50: =IF($C$4=0,0,SUM('2026 Plan PL (New)'!$F49:OFFSET('2026 Plan PL (New)'!$F49,0,$C$4-1))) -> 1698639.4 | E50: =IF($C$4=0,0,SUM(PL!$F51:OFFSET(PL!$F51,0,$C$4-1))) -> 333437.81 | F50: =+IFERROR(E50/D50,) -> 0.196297 | G50: =OFFSET(PL!F51,0,$C$4-2) -> 264015.64 | H50: =+IFERROR(G50/$G$6,) -> 0.0034825851 | I50: =OFFSET('2026 Plan PL (New)'!F49,0,$C$4-1) -> 945983.25 | J50: =+IFERROR(I50/$I$6,) -> 0.0081045556 | K50: =OFFSET(PL!F51,0,$C$4-1) -> 69422.17 | L50: =+IFERROR(K50/$K$6,) -> 0.0010895953 | M50: =+IFERROR(K50/G50,) -> 0.26294719 | N50: =+IFERROR(K50/I50,) -> 0.073386257
C51: Rental Expenses | D51: =IF($C$4=0,0,SUM('2026 Plan PL (New)'!$F50:OFFSET('2026 Plan PL (New)'!$F50,0,$C$4-1))) -> 1256500 | E51: =IF($C$4=0,0,SUM(PL!$F52:OFFSET(PL!$F52,0,$C$4-1))) -> 1514422.2 | F51: =+IFERROR(E51/D51,) -> 1.2052703 | G51: =OFFSET(PL!F52,0,$C$4-2) -> 772633.38 | H51: =+IFERROR(G51/$G$6,) -> 0.010191675 | I51: =OFFSET('2026 Plan PL (New)'!F50,0,$C$4-1) -> 628250 | J51: =+IFERROR(I51/$I$6,) -> 0.0053824283 | K51: =OFFSET(PL!F52,0,$C$4-1) -> 741788.78 | L51: =+IFERROR(K51/$K$6,) -> 0.011642528 | M51: =+IFERROR(K51/G51,) -> 0.96007861 | N51: =+IFERROR(K51/I51,) -> 1.1807223
C52: Travel and Accomodation Expenses | D52: =IF($C$4=0,0,SUM('2026 Plan PL (New)'!$F51:OFFSET('2026 Plan PL (New)'!$F51,0,$C$4-1))) -> 724521.67 | E52: =IF($C$4=0,0,SUM(PL!$F53:OFFSET(PL!$F53,0,$C$4-1))) -> 391326.16 | F52: =+IFERROR(E52/D52,) -> 0.54011657 | G52: =OFFSET(PL!F53,0,$C$4-2) -> 124575.94 | H52: =+IFERROR(G52/$G$6,) -> 0.0016432599 | I52: =OFFSET('2026 Plan PL (New)'!F51,0,$C$4-1) -> 362260.83 | J52: =+IFERROR(I52/$I$6,) -> 0.00310361 | K52: =OFFSET(PL!F53,0,$C$4-1) -> 266750.22 | L52: =+IFERROR(K52/$K$6,) -> 0.0041866997 | M52: =+IFERROR(K52/G52,) -> 2.141266 | N52: =+IFERROR(K52/I52,) -> 0.7363485
C53: Business Hospitality Expenses | D53: =IF($C$4=0,0,SUM('2026 Plan PL (New)'!$F52:OFFSET('2026 Plan PL (New)'!$F52,0,$C$4-1))) -> 70000 | E53: =IF($C$4=0,0,SUM(PL!$F54:OFFSET(PL!$F54,0,$C$4-1))) -> 8028.04 | F53: =+IFERROR(E53/D53,) -> 0.11468629 | G53: =OFFSET(PL!F54,0,$C$4-2) -> 4747.03 | H53: =+IFERROR(G53/$G$6,) -> 6.261726e-05 | I53: =OFFSET('2026 Plan PL (New)'!F52,0,$C$4-1) -> 35000 | J53: =+IFERROR(I53/$I$6,) -> 0.00029985673 | K53: =OFFSET(PL!F54,0,$C$4-1) -> 3281.01 | L53: =+IFERROR(K53/$K$6,) -> 5.1496128e-05 | M53: =+IFERROR(K53/G53,) -> 0.69117111 | N53: =+IFERROR(K53/I53,) -> 0.093743143
C54: Insurance Expenses | D54: =IF($C$4=0,0,SUM('2026 Plan PL (New)'!$F53:OFFSET('2026 Plan PL (New)'!$F53,0,$C$4-1))) -> 0 | E54: =IF($C$4=0,0,SUM(PL!$F55:OFFSET(PL!$F55,0,$C$4-1))) -> 0 | F54: =+IFERROR(E54/D54,) -> 0 | G54: =OFFSET(PL!F55,0,$C$4-2) -> 0 | H54: =+IFERROR(G54/$G$6,) -> 0 | I54: =OFFSET('2026 Plan PL (New)'!F53,0,$C$4-1) -> 0 | J54: =+IFERROR(I54/$I$6,) -> 0 | K54: =OFFSET(PL!F55,0,$C$4-1) -> 0 | L54: =+IFERROR(K54/$K$6,) -> 0 | M54: =+IFERROR(K54/G54,) -> 0 | N54: =+IFERROR(K54/I54,) -> 0
C55: Outsource Benefits and Services | D55: =IF($C$4=0,0,SUM('2026 Plan PL (New)'!$F54:OFFSET('2026 Plan PL (New)'!$F54,0,$C$4-1))) -> 45856.2 | E55: =IF($C$4=0,0,SUM(PL!$F56:OFFSET(PL!$F56,0,$C$4-1))) -> 65923.64 | F55: =+IFERROR(E55/D55,) -> 1.4376167 | G55: =OFFSET(PL!F56,0,$C$4-2) -> 23311.69 | H55: =+IFERROR(G55/$G$6,) -> 0.00030750051 | I55: =OFFSET('2026 Plan PL (New)'!F54,0,$C$4-1) -> 22928.1 | J55: =+IFERROR(I55/$I$6,) -> 0.00019643272 | K55: =OFFSET(PL!F56,0,$C$4-1) -> 42611.95 | L55: =+IFERROR(K55/$K$6,) -> 0.00066880334 | M55: =+IFERROR(K55/G55,) -> 1.827922 | N55: =+IFERROR(K55/I55,) -> 1.8585033
C56: Office Supplies | D56: =IF($C$4=0,0,SUM('2026 Plan PL (New)'!$F55:OFFSET('2026 Plan PL (New)'!$F55,0,$C$4-1))) -> 94000 | E56: =IF($C$4=0,0,SUM(PL!$F57:OFFSET(PL!$F57,0,$C$4-1))) -> 129105.2 | F56: =+IFERROR(E56/D56,) -> 1.3734596 | G56: =OFFSET(PL!F57,0,$C$4-2) -> 83456.7 | H56: =+IFERROR(G56/$G$6,) -> 0.001100863 | I56: =OFFSET('2026 Plan PL (New)'!F55,0,$C$4-1) -> 46000 | J56: =+IFERROR(I56/$I$6,) -> 0.00039409742 | K56: =OFFSET(PL!F57,0,$C$4-1) -> 45648.5 | L56: =+IFERROR(K56/$K$6,) -> 0.00071646262 | M56: =+IFERROR(K56/G56,) -> 0.54697226 | N56: =+IFERROR(K56/I56,) -> 0.9923587
C57: Vehicle Expenses | D57: =IF($C$4=0,0,SUM('2026 Plan PL (New)'!$F56:OFFSET('2026 Plan PL (New)'!$F56,0,$C$4-1))) -> 114000 | E57: =IF($C$4=0,0,SUM(PL!$F58:OFFSET(PL!$F58,0,$C$4-1))) -> 66993.36 | F57: =+IFERROR(E57/D57,) -> 0.58766105 | G57: =OFFSET(PL!F58,0,$C$4-2) -> 36140.53 | H57: =+IFERROR(G57/$G$6,) -> 0.00047672354 | I57: =OFFSET('2026 Plan PL (New)'!F56,0,$C$4-1) -> 57000 | J57: =+IFERROR(I57/$I$6,) -> 0.0004883381 | K57: =OFFSET(PL!F58,0,$C$4-1) -> 30852.83 | L57: =+IFERROR(K57/$K$6,) -> 0.00048424153 | M57: =+IFERROR(K57/G57,) -> 0.85369058 | N57: =+IFERROR(K57/I57,) -> 0.54127772
C58: Other Taxes | D58: =IF($C$4=0,0,SUM('2026 Plan PL (New)'!$F57:OFFSET('2026 Plan PL (New)'!$F57,0,$C$4-1))) -> 27089.262 | E58: =IF($C$4=0,0,SUM(PL!$F59:OFFSET(PL!$F59,0,$C$4-1))) -> 25271.91 | F58: =+IFERROR(E58/D58,) -> 0.93291245 | G58: =OFFSET(PL!F59,0,$C$4-2) -> 13969.85 | H58: =+IFERROR(G58/$G$6,) -> 0.0001842739 | I58: =OFFSET('2026 Plan PL (New)'!F57,0,$C$4-1) -> 13544.631 | J58: =+IFERROR(I58/$I$6,) -> 0.00011604139 | K58: =OFFSET(PL!F59,0,$C$4-1) -> 11302.06 | L58: =+IFERROR(K58/$K$6,) -> 0.00017738816 | M58: =+IFERROR(K58/G58,) -> 0.80903231 | N58: =+IFERROR(K58/I58,) -> 0.83443099
C59: Commission Expenses | D59: =IF($C$4=0,0,SUM('2026 Plan PL (New)'!$F58:OFFSET('2026 Plan PL (New)'!$F58,0,$C$4-1))) -> 105126.74 | E59: =IF($C$4=0,0,SUM(PL!$F60:OFFSET(PL!$F60,0,$C$4-1))) -> 11953.62 | F59: =+IFERROR(E59/D59,) -> 0.11370675 | G59: =OFFSET(PL!F60,0,$C$4-2) -> 1989.62 | H59: =+IFERROR(G59/$G$6,) -> 2.6244737e-05 | I59: =OFFSET('2026 Plan PL (New)'!F58,0,$C$4-1) -> 58361.205 | J59: =+IFERROR(I59/$I$6,) -> 0.0005 | K59: =OFFSET(PL!F60,0,$C$4-1) -> 9964 | L59: =+IFERROR(K59/$K$6,) -> 0.00015638703 | M59: =+IFERROR(K59/G59,) -> 5.0079915 | N59: =+IFERROR(K59/I59,) -> 0.17072985
C60: Services | D60: =IF($C$4=0,0,SUM('2026 Plan PL (New)'!$F59:OFFSET('2026 Plan PL (New)'!$F59,0,$C$4-1))) -> 919880.69 | E60: =IF($C$4=0,0,SUM(PL!$F61:OFFSET(PL!$F61,0,$C$4-1))) -> 680439.1 | F60: =+IFERROR(E60/D60,) -> 0.73970365 | G60: =OFFSET(PL!F61,0,$C$4-2) -> 189249.16 | H60: =+IFERROR(G60/$G$6,) -> 0.0024963533 | I60: =OFFSET('2026 Plan PL (New)'!F59,0,$C$4-1) -> 365751.14 | J60: =+IFERROR(I60/$I$6,) -> 0.0031335126 | K60: =OFFSET(PL!F61,0,$C$4-1) -> 491189.94 | L60: =+IFERROR(K60/$K$6,) -> 0.0077093273 | M60: =+IFERROR(K60/G60,) -> 2.5954669 | N60: =+IFERROR(K60/I60,) -> 1.3429621
... C65: Communication Expenses(Royalty) | D65: =IF($C$4=0,0,SUM('2026 Plan PL (New)'!$F64:OFFSET('2026 Plan PL (New)'!$F64,0,$C$4-1))) -> 8410139.1 | E65: =IF($C$4=0,0,SUM(PL!$F66:OFFSET(PL!$F66,0,$C$4-1))) -> 5722146.3 | F65: =+IFERROR(E65/D65,) -> 0.68038665 | G65: =OFFSET(PL!F66,0,$C$4-2) -> 3064155.1 | H65: =+IFERROR(G65/$G$6,) -> 0.040418746 | I65: =OFFSET('2026 Plan PL (New)'!F64,0,$C$4-1) -> 4668896.4 | J65: =+IFERROR(I65/$I$6,) -> 0.04 | K65: =OFFSET(PL!F66,0,$C$4-1) -> 2657991.2 | L65: =+IFERROR(K65/$K$6,) -> 0.04171772 | M65: =+IFERROR(K65/G65,) -> 0.86744669 | N65: =+IFERROR(K65/I65,) -> 0.56929754
B67: Ⅴ.영업이익 | C67: Ⅴ.OPERATING INCOME (or LOSS) | D67: =+D38-D40-D48 -> 25083349 | E67: =+E38-E40-E48 -> -59103087 | F67: =+IFERROR(E67/D67,) -> -2.3562677 | G67: =+G38-G40-G48 -> -6005818.4 | H67: =+IFERROR(G67/$G$6,) -> -0.079221723 | I67: =+I38-I40-I48 -> 14221416 | J67: =+IFERROR(I67/$I$6,) -> 0.12183964 | K67: =+K38-K40-K48 -> -53097269 | L67: =+IFERROR(K67/$K$6,) -> -0.83337257 | M67: =+IFERROR(K67/G67,) -> 8.8409713 | N67: =+IFERROR(K67/I67,) -> -3.7336133
B68: (이익률) | C68: (rate) | D68: =+IFERROR(D67/D$6,) -> 0.11930052 | E68: =+IFERROR(E67/E$6,) -> -0.42360526 | G68: =+IFERROR(G67/G$6,) -> -0.079221723 | I68: =+IFERROR(I67/I$6,) -> 0.12183964 | K68: =+IFERROR(K67/K$6,) -> -0.83337257

Sheet PL
F1: =+F27/F6 -> 1.0371105 | G1: =+G27/G6 -> 1.5927174 | H1: =+H27/H6 -> #DIV/0! | I1: =+I27/I6 -> #DIV/0! | J1: =+J27/J6 -> #DIV/0! | K1: =+K27/K6 -> #DIV/0! | L1: =+L27/L6 -> #DIV/0! | M1: =+M27/M6 -> #DIV/0! | ... Q1: =+Q27/Q6 -> #DIV/0!
B2: Profit and Loss statement FY 2026 | M2: (UNIT:TRY) | Q2: (Affiliate Company: Kyungshin cable Türkiye)
B3: MONTH | C3: 12 | F3: =IF(F4>$C$3,0,F4) -> 1 | G3: =IF(G4>$C$3,0,G4) -> 2 | H3: =IF(H4>$C$3,0,H4) -> 3 | I3: =IF(I4>$C$3,0,I4) -> 4 | J3: =IF(J4>$C$3,0,J4) -> 5 | K3: =IF(K4>$C$3,0,K4) -> 6 | L3: =IF(L4>$C$3,0,L4) -> 7 | M3: =IF(M4>$C$3,0,M4) -> 8 | ... Q3: =IF(Q4>$C$3,0,Q4) -> 12
B4: 구분 | D4: FY | E4: 12 | F4: 1 | G4: 2 | H4: =+G4+1 -> 3 | I4: =+H4+1 -> 4 | J4: =+I4+1 -> 5 | K4: =+J4+1 -> 6 | L4: =+K4+1 -> 7 | M4: =+L4+1 -> 8 | N4: =+M4+1 -> 9 | O4: =+N4+1 -> 10 | ... Q4: =+P4+1 -> 12
B5: Ⅰ. 매출액 | C5: Ⅰ. SALES | D5: =SUM(F5:Q5) -> 1.4305366e+08 | F5: =+F6+F17 -> 76603878 | G5: =+G6+G17 -> 66449780 | H5: =+H6+H17 -> 0 | I5: =+I6+I17 -> 0 | J5: =+J6+J17 -> 0 | K5: =+K6+K17 -> 0 | L5: =+L6+L17 -> 0 | M5: =+M6+M17 -> 0 | ... Q5: =+Q6+Q17 -> 0
B6: 1.상품매출 | C6: 1. Merchandise | D6: =SUM(F6:Q6) -> 1.3622764e+08 | F6: =SUM(F7:F15) -> 69775998 | G6: =SUM(G7:G15) -> 66451641 | H6: =SUM(H7:H15) -> 0 | I6: =SUM(I7:I15) -> 0 | J6: =SUM(J7:J15) -> 0 | K6: =SUM(K7:K15) -> 0 | L6: =SUM(L7:L15) -> 0 | M6: =SUM(M7:M15) -> 0 | ... Q6: =SUM(Q7:Q15) -> 0
C7: FORD PHEV-E (V710) | D7: =SUM(F7:Q7) -> 45828053 | F7: =SUMIFS('sales data'!$N:$N,'sales data'!$B:$B,F$3,'sales data'!$H:$H,$C7,'sales data'!$O:$O,"") -> 23920697 | G7: =SUMIFS('sales data'!$N:$N,'sales data'!$B:$B,G$3,'sales data'!$H:$H,$C7,'sales data'!$O:$O,"") -> 21907356 | H7: =SUMIFS('sales data'!$N:$N,'sales data'!$B:$B,H$3,'sales data'!$H:$H,$C7,'sales data'!$O:$O,"") -> 0 | I7: =SUMIFS('sales data'!$N:$N,'sales data'!$B:$B,I$3,'sales data'!$H:$H,$C7,'sales data'!$O:$O,"") -> 0 | J7: =SUMIFS('sales data'!$N:$N,'sales data'!$B:$B,J$3,'sales data'!$H:$H,$C7,'sales data'!$O:$O,"") -> 0 | K7: =SUMIFS('sales data'!$N:$N,'sales data'!$B:$B,K$3,'sales data'!$H:$H,$C7,'sales data'!$O:$O,"") -> 0 | L7: =SUMIFS('sales data'!$N:$N,'sales data'!$B:$B,L$3,'sales data'!$H:$H,$C7,'sales data'!$O:$O,"") -> 0 | M7: =SUMIFS('sales data'!$N:$N,'sales data'!$B:$B,M$3,'sales data'!$H:$H,$C7,'sales data'!$O:$O,"") -> 0 | ... Q7: =SUMIFS('sales data'!$N:$N,'sales data'!$B:$B,Q$3,'sales data'!$H:$H,$C7,'sales data'!$O:$O,"") -> 0
C8: FORD PHEV-E (P703) | D8: =SUM(F8:Q8) -> 25162751 | F8: =SUMIFS('sales data'!$N:$N,'sales data'!$B:$B,F$3,'sales data'!$H:$H,$C8,'sales data'!$O:$O,"") -> 12070960 | G8: =SUMIFS('sales data'!$N:$N,'sales data'!$B:$B,G$3,'sales data'!$H:$H,$C8,'sales data'!$O:$O,"") -> 13091791 | H8: =SUMIFS('sales data'!$N:$N,'sales data'!$B:$B,H$3,'sales data'!$H:$H,$C8,'sales data'!$O:$O,"") -> 0 | I8: =SUMIFS('sales data'!$N:$N,'sales data'!$B:$B,I$3,'sales data'!$H:$H,$C8,'sales data'!$O:$O,"") -> 0 | J8: =SUMIFS('sales data'!$N:$N,'sales data'!$B:$B,J$3,'sales data'!$H:$H,$C8,'sales data'!$O:$O,"") -> 0 | K8: =SUMIFS('sales data'!$N:$N,'sales data'!$B:$B,K$3,'sales data'!$H:$H,$C8,'sales data'!$O:$O,"") -> 0 | L8: =SUMIFS('sales data'!$N:$N,'sales data'!$B:$B,L$3,'sales data'!$H:$H,$C8,'sales data'!$O:$O,"") -> 0 | M8: =SUMIFS('sales data'!$N:$N,'sales data'!$B:$B,M$3,'sales data'!$H:$H,$C8,'sales data'!$O:$O,"") -> 0 | ... Q8: =SUMIFS('sales data'!$N:$N,'sales data'!$B:$B,Q$3,'sales data'!$H:$H,$C8,'sales data'!$O:$O,"") -> 0
C9: BEV-E RWD | D9: =SUM(F9:Q9) -> 1747054.9 | F9: =SUMIFS('sales data'!$N:$N,'sales data'!$B:$B,F$3,'sales data'!$H:$H,$C9,'sales data'!$O:$O,"") -> 371310.73 | G9: =SUMIFS('sales data'!$N:$N,'sales data'!$B:$B,G$3,'sales data'!$H:$H,$C9,'sales data'!$O:$O,"") -> 1375744.2 | H9: =SUMIFS('sales data'!$N:$N,'sales data'!$B:$B,H$3,'sales data'!$H:$H,$C9,'sales data'!$O:$O,"") -> 0 | I9: =SUMIFS('sales data'!$N:$N,'sales data'!$B:$B,I$3,'sales data'!$H:$H,$C9,'sales data'!$O:$O,"") -> 0 | J9: =SUMIFS('sales data'!$N:$N,'sales data'!$B:$B,J$3,'sales data'!$H:$H,$C9,'sales data'!$O:$O,"") -> 0 | K9: =SUMIFS('sales data'!$N:$N,'sales data'!$B:$B,K$3,'sales data'!$H:$H,$C9,'sales data'!$O:$O,"") -> 0 | L9: =SUMIFS('sales data'!$N:$N,'sales data'!$B:$B,L$3,'sales data'!$H:$H,$C9,'sales data'!$O:$O,"") -> 0 | M9: =SUMIFS('sales data'!$N:$N,'sales data'!$B:$B,M$3,'sales data'!$H:$H,$C9,'sales data'!$O:$O,"") -> 0 | ... Q9: =SUMIFS('sales data'!$N:$N,'sales data'!$B:$B,Q$3,'sales data'!$H:$H,$C9,'sales data'!$O:$O,"") -> 0
C10: BEV-E AWD | D10: =SUM(F10:Q10) -> 350302.84 | F10: =SUMIFS('sales data'!$N:$N,'sales data'!$B:$B,F$3,'sales data'!$H:$H,$C10,'sales data'!$O:$O,"") -> 240833.21 | G10: =SUMIFS('sales data'!$N:$N,'sales data'!$B:$B,G$3,'sales data'!$H:$H,$C10,'sales data'!$O:$O,"") -> 109469.63 | H10: =SUMIFS('sales data'!$N:$N,'sales data'!$B:$B,H$3,'sales data'!$H:$H,$C10,'sales data'!$O:$O,"") -> 0 | I10: =SUMIFS('sales data'!$N:$N,'sales data'!$B:$B,I$3,'sales data'!$H:$H,$C10,'sales data'!$O:$O,"") -> 0 | J10: =SUMIFS('sales data'!$N:$N,'sales data'!$B:$B,J$3,'sales data'!$H:$H,$C10,'sales data'!$O:$O,"") -> 0 | K10: =SUMIFS('sales data'!$N:$N,'sales data'!$B:$B,K$3,'sales data'!$H:$H,$C10,'sales data'!$O:$O,"") -> 0 | L10: =SUMIFS('sales data'!$N:$N,'sales data'!$B:$B,L$3,'sales data'!$H:$H,$C10,'sales data'!$O:$O,"") -> 0 | M10: =SUMIFS('sales data'!$N:$N,'sales data'!$B:$B,M$3,'sales data'!$H:$H,$C10,'sales data'!$O:$O,"") -> 0 | ... Q10: =SUMIFS('sales data'!$N:$N,'sales data'!$B:$B,Q$3,'sales data'!$H:$H,$C10,'sales data'!$O:$O,"") -> 0
C11: BEV (AWD/RWD) | D11: =SUM(F11:Q11) -> 3529688.1 | F11: =SUMIFS('sales data'!$N:$N,'sales data'!$B:$B,F$3,'sales data'!$H:$H,$C11,'sales data'!$O:$O,"") -> 793630.18 | G11: =SUMIFS('sales data'!$N:$N,'sales data'!$B:$B,G$3,'sales data'!$H:$H,$C11,'sales data'!$O:$O,"") -> 2736058 | H11: =SUMIFS('sales data'!$N:$N,'sales data'!$B:$B,H$3,'sales data'!$H:$H,$C11,'sales data'!$O:$O,"") -> 0 | I11: =SUMIFS('sales data'!$N:$N,'sales data'!$B:$B,I$3,'sales data'!$H:$H,$C11,'sales data'!$O:$O,"") -> 0 | J11: =SUMIFS('sales data'!$N:$N,'sales data'!$B:$B,J$3,'sales data'!$H:$H,$C11,'sales data'!$O:$O,"") -> 0 | K11: =SUMIFS('sales data'!$N:$N,'sales data'!$B:$B,K$3,'sales data'!$H:$H,$C11,'sales data'!$O:$O,"") -> 0 | L11: =SUMIFS('sales data'!$N:$N,'sales data'!$B:$B,L$3,'sales data'!$H:$H,$C11,'sales data'!$O:$O,"") -> 0 | M11: =SUMIFS('sales data'!$N:$N,'sales data'!$B:$B,M$3,'sales data'!$H:$H,$C11,'sales data'!$O:$O,"") -> 0 | ... Q11: =SUMIFS('sales data'!$N:$N,'sales data'!$B:$B,Q$3,'sales data'!$H:$H,$C11,'sales data'!$O:$O,"") -> 0
C12: FORD BEV-M | D12: =SUM(F12:Q12) -> 35440595 | F12: =SUMIFS('sales data'!$N:$N,'sales data'!$B:$B,F$3,'sales data'!$H:$H,$C12,'sales data'!$O:$O,"") -> 15721984 | G12: =SUMIFS('sales data'!$N:$N,'sales data'!$B:$B,G$3,'sales data'!$H:$H,$C12,'sales data'!$O:$O,"") -> 19718611 | H12: =SUMIFS('sales data'!$N:$N,'sales data'!$B:$B,H$3,'sales data'!$H:$H,$C12,'sales data'!$O:$O,"") -> 0 | I12: =SUMIFS('sales data'!$N:$N,'sales data'!$B:$B,I$3,'sales data'!$H:$H,$C12,'sales data'!$O:$O,"") -> 0 | J12: =SUMIFS('sales data'!$N:$N,'sales data'!$B:$B,J$3,'sales data'!$H:$H,$C12,'sales data'!$O:$O,"") -> 0 | K12: =SUMIFS('sales data'!$N:$N,'sales data'!$B:$B,K$3,'sales data'!$H:$H,$C12,'sales data'!$O:$O,"") -> 0 | L12: =SUMIFS('sales data'!$N:$N,'sales data'!$B:$B,L$3,'sales data'!$H:$H,$C12,'sales data'!$O:$O,"") -> 0 | M12: =SUMIFS('sales data'!$N:$N,'sales data'!$B:$B,M$3,'sales data'!$H:$H,$C12,'sales data'!$O:$O,"") -> 0 | ... Q12: =SUMIFS('sales data'!$N:$N,'sales data'!$B:$B,Q$3,'sales data'!$H:$H,$C12,'sales data'!$O:$O,"") -> 0
C13: EV-V4 | D13: =SUM(F13:Q13) -> 74025.583 | F13: =SUMIFS('sales data'!$N:$N,'sales data'!$B:$B,F$3,'sales data'!$H:$H,$C13,'sales data'!$O:$O,"") -> 67848.567 | G13: =SUMIFS('sales data'!$N:$N,'sales data'!$B:$B,G$3,'sales data'!$H:$H,$C13,'sales data'!$O:$O,"") -> 6177.0163 | H13: =SUMIFS('sales data'!$N:$N,'sales data'!$B:$B,H$3,'sales data'!$H:$H,$C13,'sales data'!$O:$O,"") -> 0 | I13: =SUMIFS('sales data'!$N:$N,'sales data'!$B:$B,I$3,'sales data'!$H:$H,$C13,'sales data'!$O:$O,"") -> 0 | J13: =SUMIFS('sales data'!$N:$N,'sales data'!$B:$B,J$3,'sales data'!$H:$H,$C13,'sales data'!$O:$O,"") -> 0 | K13: =SUMIFS('sales data'!$N:$N,'sales data'!$B:$B,K$3,'sales data'!$H:$H,$C13,'sales data'!$O:$O,"") -> 0 | L13: =SUMIFS('sales data'!$N:$N,'sales data'!$B:$B,L$3,'sales data'!$H:$H,$C13,'sales data'!$O:$O,"") -> 0 | M13: =SUMIFS('sales data'!$N:$N,'sales data'!$B:$B,M$3,'sales data'!$H:$H,$C13,'sales data'!$O:$O,"") -> 0 | ... Q13: =SUMIFS('sales data'!$N:$N,'sales data'!$B:$B,Q$3,'sales data'!$H:$H,$C13,'sales data'!$O:$O,"") -> 0
C14: Components | D14: =SUM(F14:Q14) -> 1628059.3 | F14: =SUMIFS('sales data'!$N:$N,'sales data'!$B:$B,F$3,'sales data'!$H:$H,$C14,'sales data'!$O:$O,"") -> 932361.78 | G14: =SUMIFS('sales data'!$N:$N,'sales data'!$B:$B,G$3,'sales data'!$H:$H,$C14,'sales data'!$O:$O,"") -> 695697.55 | H14: =SUMIFS('sales data'!$N:$N,'sales data'!$B:$B,H$3,'sales data'!$H:$H,$C14,'sales data'!$O:$O,"") -> 0 | I14: =SUMIFS('sales data'!$N:$N,'sales data'!$B:$B,I$3,'sales data'!$H:$H,$C14,'sales data'!$O:$O,"") -> 0 | J14: =SUMIFS('sales data'!$N:$N,'sales data'!$B:$B,J$3,'sales data'!$H:$H,$C14,'sales data'!$O:$O,"") -> 0 | K14: =SUMIFS('sales data'!$N:$N,'sales data'!$B:$B,K$3,'sales data'!$H:$H,$C14,'sales data'!$O:$O,"") -> 0 | L14: =SUMIFS('sales data'!$N:$N,'sales data'!$B:$B,L$3,'sales data'!$H:$H,$C14,'sales data'!$O:$O,"") -> 0 | M14: =SUMIFS('sales data'!$N:$N,'sales data'!$B:$B,M$3,'sales data'!$H:$H,$C14,'sales data'!$O:$O,"") -> 0 | ... Q14: =SUMIFS('sales data'!$N:$N,'sales data'!$B:$B,Q$3,'sales data'!$H:$H,$C14,'sales data'!$O:$O,"") -> 0
C15: BEV-E1 | D15: =SUM(F15:Q15) -> 22467110 | F15: =SUMIFS('sales data'!$N:$N,'sales data'!$B:$B,F$3,'sales data'!$H:$H,$C15,'sales data'!$O:$O,"") -> 15656373 | G15: =SUMIFS('sales data'!$N:$N,'sales data'!$B:$B,G$3,'sales data'!$H:$H,$C15,'sales data'!$O:$O,"") -> 6810736.6 | H15: =SUMIFS('sales data'!$N:$N,'sales data'!$B:$B,H$3,'sales data'!$H:$H,$C15,'sales data'!$O:$O,"") -> 0 | I15: =SUMIFS('sales data'!$N:$N,'sales data'!$B:$B,I$3,'sales data'!$H:$H,$C15,'sales data'!$O:$O,"") -> 0 | J15: =SUMIFS('sales data'!$N:$N,'sales data'!$B:$B,J$3,'sales data'!$H:$H,$C15,'sales data'!$O:$O,"") -> 0 | K15: =SUMIFS('sales data'!$N:$N,'sales data'!$B:$B,K$3,'sales data'!$H:$H,$C15,'sales data'!$O:$O,"") -> 0 | L15: =SUMIFS('sales data'!$N:$N,'sales data'!$B:$B,L$3,'sales data'!$H:$H,$C15,'sales data'!$O:$O,"") -> 0 | M15: =SUMIFS('sales data'!$N:$N,'sales data'!$B:$B,M$3,'sales data'!$H:$H,$C15,'sales data'!$O:$O,"") -> 0 | ... Q15: =SUMIFS('sales data'!$N:$N,'sales data'!$B:$B,Q$3,'sales data'!$H:$H,$C15,'sales data'!$O:$O,"") -> 0
C16: SALES CHECK | F16: =SUMIFS('sales data'!$N:$N,'sales data'!$B:$B,F3)-F5 -> 0 | G16: =SUMIFS('sales data'!$N:$N,'sales data'!$B:$B,G3)-G5 -> 0 | H16: =SUMIFS('sales data'!$N:$N,'sales data'!$B:$B,H3)=H5 -> TRUE | I16: =SUMIFS('sales data'!$N:$N,'sales data'!$B:$B,I3)=I5 -> TRUE | J16: =SUMIFS('sales data'!$N:$N,'sales data'!$B:$B,J3)=J5 -> TRUE | K16: =SUMIFS('sales data'!$N:$N,'sales data'!$B:$B,K3)=K5 -> TRUE | L16: =SUMIFS('sales data'!$N:$N,'sales data'!$B:$B,L3)=L5 -> TRUE | M16: =SUMIFS('sales data'!$N:$N,'sales data'!$B:$B,M3)=M5 -> TRUE | N16: =SUMIFS('sales data'!$N:$N,'sales data'!$B:$B,N3)=N5 -> TRUE | O16: =SUMIFS('sales data'!$N:$N,'sales data'!$B:$B,O3)=O5 -> TRUE | ... Q16: =SUMIFS('sales data'!$N:$N,'sales data'!$B:$B,Q3)=Q5 -> TRUE
B17: 2. 기타 매출 | C17: 2. Other sales | D17: =SUM(F17:Q17) -> 6826019.2 | F17: =SUM(F18:F21) -> 6827880.1 | G17: =SUM(G18:G21) -> -1860.8359 | H17: =SUM(H18:H21) -> 0 | I17: =SUM(I18:I21) -> 0 | J17: =SUM(J18:J21) -> 0 | K17: =SUM(K18:K21) -> 0 | L17: =SUM(L18:L21) -> 0 | M17: =SUM(M18:M21) -> 0 | ... Q17: =SUM(Q18:Q21) -> 0
B18: └ scrap | C18: └ Scrap | D18: =SUM(F18:Q18) -> 0 | F18: =SUMIFS('sales data'!$N:$N,'sales data'!$B:$B,F$3,'sales data'!$H:$H,$C18,'sales data'!$O:$O,"") -> 0 | G18: =SUMIFS('sales data'!$N:$N,'sales data'!$B:$B,G$3,'sales data'!$H:$H,$C18,'sales data'!$O:$O,"") -> 0 | H18: =SUMIFS('sales data'!$N:$N,'sales data'!$B:$B,H$3,'sales data'!$H:$H,$C18,'sales data'!$O:$O,"") -> 0 | I18: =SUMIFS('sales data'!$N:$N,'sales data'!$B:$B,I$3,'sales data'!$H:$H,$C18,'sales data'!$O:$O,"") -> 0 | J18: =SUMIFS('sales data'!$N:$N,'sales data'!$B:$B,J$3,'sales data'!$H:$H,$C18,'sales data'!$O:$O,"") -> 0 | K18: =SUMIFS('sales data'!$N:$N,'sales data'!$B:$B,K$3,'sales data'!$H:$H,$C18,'sales data'!$O:$O,"") -> 0 | L18: =SUMIFS('sales data'!$N:$N,'sales data'!$B:$B,L$3,'sales data'!$H:$H,$C18,'sales data'!$O:$O,"") -> 0 | M18: =SUMIFS('sales data'!$N:$N,'sales data'!$B:$B,M$3,'sales data'!$H:$H,$C18,'sales data'!$O:$O,"") -> 0 | ... Q18: =SUMIFS('sales data'!$N:$N,'sales data'!$B:$B,Q$3,'sales data'!$H:$H,$C18,'sales data'!$O:$O,"") -> 0
B19: └ Test Parts | C19: └ Test Parts | D19: =SUM(F19:Q19) -> 0 | F19: =SUMIFS('sales data'!$N:$N,'sales data'!$B:$B,F$3,'sales data'!$H:$H,$C19,'sales data'!$O:$O,"") -> 0 | G19: =SUMIFS('sales data'!$N:$N,'sales data'!$B:$B,G$3,'sales data'!$H:$H,$C19,'sales data'!$O:$O,"") -> 0 | H19: =SUMIFS('sales data'!$N:$N,'sales data'!$B:$B,H$3,'sales data'!$H:$H,$C19,'sales data'!$O:$O,"") -> 0 | I19: =SUMIFS('sales data'!$N:$N,'sales data'!$B:$B,I$3,'sales data'!$H:$H,$C19,'sales data'!$O:$O,"") -> 0 | J19: =SUMIFS('sales data'!$N:$N,'sales data'!$B:$B,J$3,'sales data'!$H:$H,$C19,'sales data'!$O:$O,"") -> 0 | K19: =SUMIFS('sales data'!$N:$N,'sales data'!$B:$B,K$3,'sales data'!$H:$H,$C19,'sales data'!$O:$O,"") -> 0 | L19: =SUMIFS('sales data'!$N:$N,'sales data'!$B:$B,L$3,'sales data'!$H:$H,$C19,'sales data'!$O:$O,"") -> 0 | M19: =SUMIFS('sales data'!$N:$N,'sales data'!$B:$B,M$3,'sales data'!$H:$H,$C19,'sales data'!$O:$O,"") -> 0 | ... Q19: =SUMIFS('sales data'!$N:$N,'sales data'!$B:$B,Q$3,'sales data'!$H:$H,$C19,'sales data'!$O:$O,"") -> 0
B20: └ 기타 | C20: └ Other | D20: =SUM(F20:Q20) -> 6826019.2 | F20: =SUMIFS('sales data'!$N:$N,'sales data'!$B:$B,F$3,'sales data'!$H:$H,$C20,'sales data'!$O:$O,"")+F$22+F$23 -> 6827880.1 | G20: =SUMIFS('sales data'!$N:$N,'sales data'!$B:$B,G$3,'sales data'!$H:$H,$C20,'sales data'!$O:$O,"")+G$22+G$23 -> -1860.8359 | H20: =SUMIFS('sales data'!$N:$N,'sales data'!$B:$B,H$3,'sales data'!$H:$H,$C20,'sales data'!$O:$O,"")+H$22+H$23 -> 0 | I20: =SUMIFS('sales data'!$N:$N,'sales data'!$B:$B,I$3,'sales data'!$H:$H,$C20,'sales data'!$O:$O,"")+I$22+I$23 -> 0 | J20: =SUMIFS('sales data'!$N:$N,'sales data'!$B:$B,J$3,'sales data'!$H:$H,$C20,'sales data'!$O:$O,"")+J$22+J$23 -> 0 | K20: =SUMIFS('sales data'!$N:$N,'sales data'!$B:$B,K$3,'sales data'!$H:$H,$C20,'sales data'!$O:$O,"")+K$22+K$23 -> 0 | L20: =SUMIFS('sales data'!$N:$N,'sales data'!$B:$B,L$3,'sales data'!$H:$H,$C20,'sales data'!$O:$O,"")+L$22+L$23 -> 0 | M20: =SUMIFS('sales data'!$N:$N,'sales data'!$B:$B,M$3,'sales data'!$H:$H,$C20,'sales data'!$O:$O,"")+M$22+M$23 -> 0 | ... Q20: =SUMIFS('sales data'!$N:$N,'sales data'!$B:$B,Q$3,'sales data'!$H:$H,$C20,'sales data'!$O:$O,"")+Q$22+Q$23 -> 0
B21: └ 기타(투자비) | C21: └ Investment | D21: =SUM(F21:Q21) -> 0 | F21: =+SUMIFS('sales(mold)'!$O:$O,'sales(mold)'!$B:$B,F$3,'sales(mold)'!$I:$I,$C$21) -> 0 | G21: =+SUMIFS('sales(mold)'!$O:$O,'sales(mold)'!$B:$B,G$3,'sales(mold)'!$I:$I,$C$21) -> 0 | H21: =+SUMIFS('sales(mold)'!$O:$O,'sales(mold)'!$B:$B,H$3,'sales(mold)'!$I:$I,$C$21) -> 0 | I21: =+SUMIFS('sales(mold)'!$O:$O,'sales(mold)'!$B:$B,I$3,'sales(mold)'!$I:$I,$C$21) -> 0 | J21: =+SUMIFS('sales(mold)'!$O:$O,'sales(mold)'!$B:$B,J$3,'sales(mold)'!$I:$I,$C$21) -> 0 | K21: =+SUMIFS('sales(mold)'!$O:$O,'sales(mold)'!$B:$B,K$3,'sales(mold)'!$I:$I,$C$21) -> 0 | L21: =+SUMIFS('sales(mold)'!$O:$O,'sales(mold)'!$B:$B,L$3,'sales(mold)'!$I:$I,$C$21) -> 0 | M21: =+SUMIFS('sales(mold)'!$O:$O,'sales(mold)'!$B:$B,M$3,'sales(mold)'!$I:$I,$C$21) -> 0 | ... Q21: =+SUMIFS('sales(mold)'!$O:$O,'sales(mold)'!$B:$B,Q$3,'sales(mold)'!$I:$I,$C$21) -> 0
C22: *(Deductions) | D22: =SUM(F22:Q22) -> 0 | F22: =SUMIFS('sales data'!$N:$N,'sales data'!$B:$B,F$3,'sales data'!$H:$H,$C22,'sales data'!$O:$O,"") -> 0 | G22: =SUMIFS('sales data'!$N:$N,'sales data'!$B:$B,G$3,'sales data'!$H:$H,$C22,'sales data'!$O:$O,"") -> 0 | H22: =SUMIFS('sales data'!$N:$N,'sales data'!$B:$B,H$3,'sales data'!$H:$H,$C22,'sales data'!$O:$O,"") -> 0 | I22: =SUMIFS('sales data'!$N:$N,'sales data'!$B:$B,I$3,'sales data'!$H:$H,$C22,'sales data'!$O:$O,"") -> 0 | J22: =SUMIFS('sales data'!$N:$N,'sales data'!$B:$B,J$3,'sales data'!$H:$H,$C22,'sales data'!$O:$O,"") -> 0 | K22: =SUMIFS('sales data'!$N:$N,'sales data'!$B:$B,K$3,'sales data'!$H:$H,$C22,'sales data'!$O:$O,"") -> 0 | L22: =SUMIFS('sales data'!$N:$N,'sales data'!$B:$B,L$3,'sales data'!$H:$H,$C22,'sales data'!$O:$O,"") -> 0 | M22: =SUMIFS('sales data'!$N:$N,'sales data'!$B:$B,M$3,'sales data'!$H:$H,$C22,'sales data'!$O:$O,"") -> 0 | ... Q22: =SUMIFS('sales data'!$N:$N,'sales data'!$B:$B,Q$3,'sales data'!$H:$H,$C22,'sales data'!$O:$O,"") -> 0
C23: *(Returns) | D23: =SUM(F23:Q23) -> -2259709.7 | F23: =SUMIFS('sales data'!$N:$N,'sales data'!$B:$B,F$3,'sales data'!$H:$H,$C23,'sales data'!$O:$O,"") -> -2257848.9 | G23: =SUMIFS('sales data'!$N:$N,'sales data'!$B:$B,G$3,'sales data'!$H:$H,$C23,'sales data'!$O:$O,"") -> -1860.8359 | H23: =SUMIFS('sales data'!$N:$N,'sales data'!$B:$B,H$3,'sales data'!$H:$H,$C23,'sales data'!$O:$O,"") -> 0 | I23: =SUMIFS('sales data'!$N:$N,'sales data'!$B:$B,I$3,'sales data'!$H:$H,$C23,'sales data'!$O:$O,"") -> 0 | J23: =SUMIFS('sales data'!$N:$N,'sales data'!$B:$B,J$3,'sales data'!$H:$H,$C23,'sales data'!$O:$O,"") -> 0 | K23: =SUMIFS('sales data'!$N:$N,'sales data'!$B:$B,K$3,'sales data'!$H:$H,$C23,'sales data'!$O:$O,"") -> 0 | L23: =SUMIFS('sales data'!$N:$N,'sales data'!$B:$B,L$3,'sales data'!$H:$H,$C23,'sales data'!$O:$O,"") -> 0 | M23: =SUMIFS('sales data'!$N:$N,'sales data'!$B:$B,M$3,'sales data'!$H:$H,$C23,'sales data'!$O:$O,"") -> 0 | ... Q23: =SUMIFS('sales data'!$N:$N,'sales data'!$B:$B,Q$3,'sales data'!$H:$H,$C23,'sales data'!$O:$O,"") -> 0
B25: Ⅱ. 매출원가 | C25: Ⅱ. COST OF SALES | D25: =SUM(F25:Q25) -> 2.8085453e+08 | F25: =+F27+F34 -> 72379542 | G25: =+G27+G34 -> 1.0586831e+08 | H25: =+H27+H34 -> 1.0260668e+08 | I25: =+I27+I34 -> 0 | J25: =+J27+J34 -> 0 | K25: =+K27+K34 -> 0 | L25: =+L27+L34 -> 0 | M25: =+M27+M34 -> 0 | ... Q25: =+Q27+Q34 -> 0
C26: % | D26: =IFERROR(D25/D$5,) -> 1.963281 | F26: =IFERROR(F25/F$5,) -> 0.9448548 | G26: =IFERROR(G25/G$5,) -> 1.5932078 | H26: =IFERROR(H25/H$5,) -> 0 | I26: =IFERROR(I25/I$5,) -> 0 | J26: =IFERROR(J25/J$5,) -> 0 | K26: =IFERROR(K25/K$5,) -> 0 | L26: =IFERROR(L25/L$5,) -> 0 | M26: =IFERROR(M25/M$5,) -> 0 | ... Q26: =IFERROR(Q25/Q$5,) -> 0
B27: 상품매출원가 | C27: Cost of merchandise sold | D27: =SUM(F27:Q27) -> 2.8081079e+08 | F27: =+F29+F30+F31-F32-F33 -> 72365419 | G27: =+G29+G30+G31-G32-G33 -> 1.0583869e+08 | H27: =+H29+H30+H31-H32-H33 -> 1.0260668e+08 | I27: =+I29+I30+I31-I32-I33 -> 0 | J27: =+J29+J30+J31-J32-J33 -> 0 | K27: =+K29+K30+K31-K32-K33 -> 0 | L27: =+L29+L30+L31-L32-L33 -> 0 | M27: =+M29+M30+M31-M32-M33 -> 0 | ... Q27: =+Q29+Q30+Q31-Q32-Q33 -> 0
C28: % | D28: =IFERROR(D27/D$6,) -> 2.0613349 | F28: =IFERROR(F27/F$6,) -> 1.0371105 | G28: =IFERROR(G27/G$6,) -> 1.5927174 | H28: =IFERROR(H27/H$6,) -> 0 | I28: =IFERROR(I27/I$6,) -> 0 | J28: =IFERROR(J27/J$6,) -> 0 | K28: =IFERROR(K27/K$6,) -> 0 | L28: =IFERROR(L27/L$6,) -> 0 | M28: =IFERROR(M27/M$6,) -> 0 | ... Q28: =IFERROR(Q27/Q$6,) -> 0
B29: 1.기초 상품재고 | C29: 1. Beginning Merchandise | D29: =+F29 -> 25971576 | F29: =SUMIFS('★Merchandise ledger_Low'!$I:$I,'★Merchandise ledger_Low'!$C:$C,F$3,'★Merchandise ledger_Low'!$F:$F,"total") -> 25971576 | G29: =SUMIFS('★Merchandise ledger_Low'!$I:$I,'★Merchandise ledger_Low'!$C:$C,G$3,'★Merchandise ledger_Low'!$F:$F,"total") -> 7356311.9 | H29: =SUMIFS('★Merchandise ledger_Low'!$I:$I,'★Merchandise ledger_Low'!$C:$C,H$3,'★Merchandise ledger_Low'!$F:$F,"total") -> 1.0260668e+08 | I29: =SUMIFS('★Merchandise ledger_Low'!$I:$I,'★Merchandise ledger_Low'!$C:$C,I$3,'★Merchandise ledger_Low'!$F:$F,"total") -> 0 | J29: =SUMIFS('★Merchandise ledger_Low'!$I:$I,'★Merchandise ledger_Low'!$C:$C,J$3,'★Merchandise ledger_Low'!$F:$F,"total") -> 0 | K29: =SUMIFS('★Merchandise ledger_Low'!$I:$I,'★Merchandise ledger_Low'!$C:$C,K$3,'★Merchandise ledger_Low'!$F:$F,"total") -> 0 | L29: =SUMIFS('★Merchandise ledger_Low'!$I:$I,'★Merchandise ledger_Low'!$C:$C,L$3,'★Merchandise ledger_Low'!$F:$F,"total") -> 0 | M29: =SUMIFS('★Merchandise ledger_Low'!$I:$I,'★Merchandise ledger_Low'!$C:$C,M$3,'★Merchandise ledger_Low'!$F:$F,"total") -> 0 | ... Q29: =SUMIFS('★Merchandise ledger_Low'!$I:$I,'★Merchandise ledger_Low'!$C:$C,Q$3,'★Merchandise ledger_Low'!$F:$F,"total") -> 0
B30: 2.당기 상품매입원가 | C30: 2. Cost of Merchandise | D30: =SUM(F30:Q30) -> 1.6363327e+08 | F30: =SUMIFS('★Merchandise ledger_Low'!$K:$K,'★Merchandise ledger_Low'!$C:$C,F$3,'★Merchandise ledger_Low'!$F:$F,"total") -> 53750154 | G30: =SUMIFS('★Merchandise ledger_Low'!$K:$K,'★Merchandise ledger_Low'!$C:$C,G$3,'★Merchandise ledger_Low'!$F:$F,"total") -> 1.0988312e+08 | H30: =SUMIFS('★Merchandise ledger_Low'!$K:$K,'★Merchandise ledger_Low'!$C:$C,H$3,'★Merchandise ledger_Low'!$F:$F,"total") -> 0 | I30: =SUMIFS('★Merchandise ledger_Low'!$K:$K,'★Merchandise ledger_Low'!$C:$C,I$3,'★Merchandise ledger_Low'!$F:$F,"total") -> 0 | J30: =SUMIFS('★Merchandise ledger_Low'!$K:$K,'★Merchandise ledger_Low'!$C:$C,J$3,'★Merchandise ledger_Low'!$F:$F,"total") -> 0 | K30: =SUMIFS('★Merchandise ledger_Low'!$K:$K,'★Merchandise ledger_Low'!$C:$C,K$3,'★Merchandise ledger_Low'!$F:$F,"total") -> 0 | L30: =SUMIFS('★Merchandise ledger_Low'!$K:$K,'★Merchandise ledger_Low'!$C:$C,L$3,'★Merchandise ledger_Low'!$F:$F,"total") -> 0 | M30: =SUMIFS('★Merchandise ledger_Low'!$K:$K,'★Merchandise ledger_Low'!$C:$C,M$3,'★Merchandise ledger_Low'!$F:$F,"total") -> 0 | ... Q30: =SUMIFS('★Merchandise ledger_Low'!$K:$K,'★Merchandise ledger_Low'!$C:$C,Q$3,'★Merchandise ledger_Low'!$F:$F,"total") -> 0
B31: 3.타계정전입 (+) | C31: 3. Transferred from other accounts | D31: =SUM(F31:Q31) -> 0
B32: 4.타계정대체 (-) | C32: 4. Transferred to other accounts | D32: =SUM(F32:Q32) -> 0 | F32: =SUMIFS('★Merchandise ledger_Low'!$T:$T,'★Merchandise ledger_Low'!$C:$C,F$3,'★Merchandise ledger_Low'!$F:$F,"total") -> 0 | G32: =SUMIFS('★Merchandise ledger_Low'!$T:$T,'★Merchandise ledger_Low'!$C:$C,G$3,'★Merchandise ledger_Low'!$F:$F,"total") -> 0 | H32: =SUMIFS('★Merchandise ledger_Low'!$T:$T,'★Merchandise ledger_Low'!$C:$C,H$3,'★Merchandise ledger_Low'!$F:$F,"total") -> 0 | I32: =SUMIFS('★Merchandise ledger_Low'!$T:$T,'★Merchandise ledger_Low'!$C:$C,I$3,'★Merchandise ledger_Low'!$F:$F,"total") -> 0 | J32: =SUMIFS('★Merchandise ledger_Low'!$T:$T,'★Merchandise ledger_Low'!$C:$C,J$3,'★Merchandise ledger_Low'!$F:$F,"total") -> 0 | K32: =SUMIFS('★Merchandise ledger_Low'!$T:$T,'★Merchandise ledger_Low'!$C:$C,K$3,'★Merchandise ledger_Low'!$F:$F,"total") -> 0 | L32: =SUMIFS('★Merchandise ledger_Low'!$T:$T,'★Merchandise ledger_Low'!$C:$C,L$3,'★Merchandise ledger_Low'!$F:$F,"total") -> 0 | M32: =SUMIFS('★Merchandise ledger_Low'!$T:$T,'★Merchandise ledger_Low'!$C:$C,M$3,'★Merchandise ledger_Low'!$F:$F,"total") -> 0 | ... Q32: =SUMIFS('★Merchandise ledger_Low'!$T:$T,'★Merchandise ledger_Low'!$C:$C,Q$3,'★Merchandise ledger_Low'!$F:$F,"total") -> 0
B33: 5.기말 상품재고 | C33: 5. Ending Merchandise | D33: =SUM(F33:Q33) -> 18757054 | F33: =SUMIFS('★Merchandise ledger_Low'!$W:$W,'★Merchandise ledger_Low'!$C:$C,F$3,'★Merchandise ledger_Low'!$F:$F,"total") -> 7356311.9 | G33: =SUMIFS('★Merchandise ledger_Low'!$W:$W,'★Merchandise ledger_Low'!$C:$C,G$3,'★Merchandise ledger_Low'!$F:$F,"total") -> 11400742 | H33: =SUMIFS('★Merchandise ledger_Low'!$W:$W,'★Merchandise ledger_Low'!$C:$C,H$3,'★Merchandise ledger_Low'!$F:$F,"total") -> 0 | I33: =SUMIFS('★Merchandise ledger_Low'!$W:$W,'★Merchandise ledger_Low'!$C:$C,I$3,'★Merchandise ledger_Low'!$F:$F,"total") -> 0 | J33: =SUMIFS('★Merchandise ledger_Low'!$W:$W,'★Merchandise ledger_Low'!$C:$C,J$3,'★Merchandise ledger_Low'!$F:$F,"total") -> 0 | K33: =SUMIFS('★Merchandise ledger_Low'!$W:$W,'★Merchandise ledger_Low'!$C:$C,K$3,'★Merchandise ledger_Low'!$F:$F,"total") -> 0 | L33: =SUMIFS('★Merchandise ledger_Low'!$W:$W,'★Merchandise ledger_Low'!$C:$C,L$3,'★Merchandise ledger_Low'!$F:$F,"total") -> 0 | M33: =SUMIFS('★Merchandise ledger_Low'!$W:$W,'★Merchandise ledger_Low'!$C:$C,M$3,'★Merchandise ledger_Low'!$F:$F,"total") -> 0 | ... Q33: =SUMIFS('★Merchandise ledger_Low'!$W:$W,'★Merchandise ledger_Low'!$C:$C,Q$3,'★Merchandise ledger_Low'!$F:$F,"total") -> 0
B34: 기타매출원가 | C34: Cost of other sold | D34: =SUM(F34:Q34) -> 43743.03 | F34: =SUM(F35:F38) -> 14123.12 | G34: =SUM(G35:G38) -> 29619.91 | H34: =SUM(H35:H38) -> 0 | I34: =SUM(I35:I38) -> 0 | J34: =SUM(J35:J38) -> 0 | K34: =SUM(K35:K38) -> 0 | L34: =SUM(L35:L38) -> 0 | M34: =SUM(M35:M38) -> 0 | ... Q34: =SUM(Q35:Q38) -> 0
B35: 원재료 매출원가 | C35: Raw material | D35: =SUM(F35:Q35) -> 0 | F35: =SUMIFS('purchase data'!$M:$M,'purchase data'!$B:$B,F$3,'purchase data'!$H:$H,$C35) -> 0 | G35: =SUMIFS('purchase data'!$M:$M,'purchase data'!$B:$B,G$3,'purchase data'!$H:$H,$C35) -> 0 | H35: =SUMIFS('purchase data'!$M:$M,'purchase data'!$B:$B,H$3,'purchase data'!$H:$H,$C35) -> 0 | I35: =SUMIFS('purchase data'!$M:$M,'purchase data'!$B:$B,I$3,'purchase data'!$H:$H,$C35) -> 0 | J35: =SUMIFS('purchase data'!$M:$M,'purchase data'!$B:$B,J$3,'purchase data'!$H:$H,$C35) -> 0 | K35: =SUMIFS('purchase data'!$M:$M,'purchase data'!$B:$B,K$3,'purchase data'!$H:$H,$C35) -> 0 | L35: =SUMIFS('purchase data'!$M:$M,'purchase data'!$B:$B,L$3,'purchase data'!$H:$H,$C35) -> 0 | M35: =SUMIFS('purchase data'!$M:$M,'purchase data'!$B:$B,M$3,'purchase data'!$H:$H,$C35) -> 0 | ... Q35: =SUMIFS('purchase data'!$M:$M,'purchase data'!$B:$B,Q$3,'purchase data'!$H:$H,$C35) -> 0
B36: 반제품 매출원가 | C36: Halb | D36: =SUM(F36:Q36) -> 0 | F36: =SUMIFS('purchase data'!$M:$M,'purchase data'!$B:$B,F$3,'purchase data'!$H:$H,$C36) -> 0 | G36: =SUMIFS('purchase data'!$M:$M,'purchase data'!$B:$B,G$3,'purchase data'!$H:$H,$C36) -> 0 | H36: =SUMIFS('purchase data'!$M:$M,'purchase data'!$B:$B,H$3,'purchase data'!$H:$H,$C36) -> 0 | I36: =SUMIFS('purchase data'!$M:$M,'purchase data'!$B:$B,I$3,'purchase data'!$H:$H,$C36) -> 0 | J36: =SUMIFS('purchase data'!$M:$M,'purchase data'!$B:$B,J$3,'purchase data'!$H:$H,$C36) -> 0 | K36: =SUMIFS('purchase data'!$M:$M,'purchase data'!$B:$B,K$3,'purchase data'!$H:$H,$C36) -> 0 | L36: =SUMIFS('purchase data'!$M:$M,'purchase data'!$B:$B,L$3,'purchase data'!$H:$H,$C36) -> 0 | M36: =SUMIFS('purchase data'!$M:$M,'purchase data'!$B:$B,M$3,'purchase data'!$H:$H,$C36) -> 0 | ... Q36: =SUMIFS('purchase data'!$M:$M,'purchase data'!$B:$B,Q$3,'purchase data'!$H:$H,$C36) -> 0
B37: 기타 | C37: Other | D37: =SUM(F37:Q37) -> 43743.03 | F37: =SUMIFS('purchase data'!$M:$M,'purchase data'!$B:$B,F$3,'purchase data'!$H:$H,$C37) -> 14123.12 | G37: =SUMIFS('purchase data'!$M:$M,'purchase data'!$B:$B,G$3,'purchase data'!$H:$H,$C37) -> 29619.91 | H37: =SUMIFS('purchase data'!$M:$M,'purchase data'!$B:$B,H$3,'purchase data'!$H:$H,$C37) -> 0 | I37: =SUMIFS('purchase data'!$M:$M,'purchase data'!$B:$B,I$3,'purchase data'!$H:$H,$C37) -> 0 | J37: =SUMIFS('purchase data'!$M:$M,'purchase data'!$B:$B,J$3,'purchase data'!$H:$H,$C37) -> 0 | K37: =SUMIFS('purchase data'!$M:$M,'purchase data'!$B:$B,K$3,'purchase data'!$H:$H,$C37) -> 0 | L37: =SUMIFS('purchase data'!$M:$M,'purchase data'!$B:$B,L$3,'purchase data'!$H:$H,$C37) -> 0 | M37: =SUMIFS('purchase data'!$M:$M,'purchase data'!$B:$B,M$3,'purchase data'!$H:$H,$C37) -> 0 | ... Q37: =SUMIFS('purchase data'!$M:$M,'purchase data'!$B:$B,Q$3,'purchase data'!$H:$H,$C37) -> 0
B38: 기타(투자비) | C38: Investment | D38: =SUM(F38:Q38) -> 0
B39: Ⅲ. 매출총이익 | C39: Ⅲ. GROSS PROFIT (or GROSS LOSS) | D39: =SUM(F39:Q39) -> -1.3780087e+08 | F39: =+F5-F25 -> 4224336.1 | G39: =+G5-G25 -> -39418527 | H39: =+H5-H25 -> -1.0260668e+08 | I39: =+I5-I25 -> 0 | J39: =+J5-J25 -> 0 | K39: =+K5-K25 -> 0 | L39: =+L5-L25 -> 0 | M39: =+M5-M25 -> 0 | ... Q39: =+Q5-Q25 -> 0
B40: (이익률) | C40: (Rate) | D40: =+IFERROR(D39/D5,) -> -0.963281 | F40: =+IFERROR(F39/F5,) -> 0.055145199 | G40: =+IFERROR(G39/G5,) -> -0.59320779 | H40: =+IFERROR(H39/H5,) -> 0 | I40: =+IFERROR(I39/I5,) -> 0 | J40: =+IFERROR(J39/J5,) -> 0 | K40: =+IFERROR(K39/K5,) -> 0 | L40: =+IFERROR(L39/L5,) -> 0 | M40: =+IFERROR(M39/M5,) -> 0 | ... Q40: =+IFERROR(Q39/Q5,) -> 0
B41: Ⅳ.판매관리비 | C41: SELLING AND MARKETING EXPENSES | D41: =SUM(F41:Q41) -> 3732292.7 | E41: =E42+E43+E44+E45+E46+E47+E48 -> 0 | F41: =SUM(F42:F48) -> 1545174.3 | G41: =SUM(G42:G48) -> 2187118.3 | H41: =SUM(H42:H48) -> 0 | I41: =SUM(I42:I48) -> 0 | J41: =SUM(J42:J48) -> 0 | K41: =SUM(K42:K48) -> 0 | L41: =SUM(L42:L48) -> 0 | M41: =SUM(M42:M48) -> 0 | ... Q41: =SUM(Q42:Q48) -> 0
C42: Export Expenses | D42: =SUM(F42:Q42) -> 136263.82 | F42: 74012.66 | G42: 62251.16
C43: Import Expenses | D43: =SUM(F43:Q43) -> 0
C44: Domestic Transportation Expenses | D44: =SUM(F44:Q44) -> 2297201 | F44: 865151 | G44: 1432050
C45: Sample Expenses | D45: =SUM(F45:Q45) -> 159863.27 | G45: 159863.27
C46: Rework & Sorting Expenses | D46: =SUM(F46:Q46) -> 100468.19 | F46: 100468.19
C47: Package Expense | D47: =SUM(F47:Q47) -> 950919.2 | F47: 420555 | G47: 530364.2
C48: Other Expenses | D48: =SUM(F48:Q48) -> 87577.17 | F48: 84987.47 | G48: 2589.7
B49: Ⅳ.판매관리비 | C49: GENERAL ADMINISTRATION EXPENSES | D49: =SUM(F49:Q49) -> 17690841 | E49: =E50+E51+E52+E53+E54+E55+E56 -> 0 | F49: =SUM(F50:F66) -> 7891350.1 | G49: =SUM(G50:G66) -> 8755565.2 | H49: =SUM(H50:H66) -> 104392.55 | I49: =SUM(I50:I66) -> 104392.55 | J49: =SUM(J50:J66) -> 104392.55 | K49: =SUM(K50:K66) -> 104392.55 | L49: =SUM(L50:L66) -> 104392.55 | M49: =SUM(M50:M66) -> 104392.55 | ... Q49: =SUM(Q50:Q66) -> 104392.55
C50: Employee Salaries Expenses | D50: =SUM(F50:Q50) -> 7292146.2 | F50: 3078648.2 | G50: 4213498
C51: Employee Benefits Expense | D51: =SUM(F51:Q51) -> 333437.81 | F51: 264015.64 | G51: 69422.17
C52: Rental Expenses | D52: =SUM(F52:Q52) -> 1514422.2 | F52: 772633.38 | G52: 741788.78
C53: Travel and Accomodation Expenses | D53: =SUM(F53:Q53) -> 391326.16 | F53: 124575.94 | G53: 266750.22
C54: Business Hospitality Expenses | D54: =SUM(F54:Q54) -> 8028.04 | F54: 4747.03 | G54: 3281.01
C55: Insurance Expenses | D55: =SUM(F55:Q55) -> 0 | F55: 0 | G55: 0
C56: Outsource Benefits and Services | D56: =SUM(F56:Q56) -> 65923.64 | F56: 23311.69 | G56: 42611.95
C57: Office Supplies | D57: =SUM(F57:Q57) -> 129105.2 | F57: 83456.7 | G57: 45648.5
C58: Vehicle Expenses | D58: =SUM(F58:Q58) -> 66993.36 | F58: 36140.53 | G58: 30852.83
C59: Other Taxes | D59: =SUM(F59:Q59) -> 25271.91 | F59: 13969.85 | G59: 11302.06
C60: Commission Expenses | D60: =SUM(F60:Q60) -> 11953.62 | F60: 1989.62 | G60: 9964
C61: Services | D61: =SUM(F61:Q61) -> 680439.1 | F61: 189249.16 | G61: 491189.94
... C64: Non-deductible expenses(KKEG) | D64: =SUM(F64:Q64) -> 185936.64 | F64: 119064.67 | G64: 66871.97
C65: Depreciation and Amortization Expenses | D65: =SUM(F65:Q65) -> 1252710.6 | F65: =+'2026 Plan PL (New)'!F63 -> 104392.55 | G65: =+'2026 Plan PL (New)'!G63 -> 104392.55 | H65: =+'2026 Plan PL (New)'!H63 -> 104392.55 | I65: =+'2026 Plan PL (New)'!I63 -> 104392.55 | J65: =+'2026 Plan PL (New)'!J63 -> 104392.55 | K65: =+'2026 Plan PL (New)'!K63 -> 104392.55 | L65: =+'2026 Plan PL (New)'!L63 -> 104392.55 | M65: =+'2026 Plan PL (New)'!M63 -> 104392.55 | ... Q65: =+'2026 Plan PL (New)'!Q63 -> 104392.55 | R65: ← 연말 재무재표 매칭
C66: Communication Expenses(Royalty) | D66: =SUM(F66:Q66) -> 5722146.3 | F66: =IFERROR(F5*4%,"") -> 3064155.1 | G66: =IFERROR(G5*4%,"") -> 2657991.2 | H66: =IFERROR(H5*4%,"") -> 0 | I66: =IFERROR(I5*4%,"") -> 0 | J66: =IFERROR(J5*4%,"") -> 0 | K66: =IFERROR(K5*4%,"") -> 0 | L66: =IFERROR(L5*4%,"") -> 0 | M66: =IFERROR(M5*4%,"") -> 0 | ... Q66: =IFERROR(Q5*4%,"") -> 0 | R66: ← 반기별 재무재표 매칭
F67: =IFERROR(SUM(F49,F41)/F5,"") -> 0.12318599 | G67: =IFERROR(SUM(G49,G41)/G5,"") -> 0.16467599 | H67: =IFERROR(SUM(H49,H41)/H5,"") | I67: =IFERROR(SUM(I49,I41)/I5,"") | J67: =IFERROR(SUM(J49,J41)/J5,"") | K67: =IFERROR(SUM(K49,K41)/K5,"") | L67: =IFERROR(SUM(L49,L41)/L5,"") | M67: =IFERROR(SUM(M49,M41)/M5,"") | ... Q67: =IFERROR(SUM(Q49,Q41)/Q5,"")
B68: Ⅴ.영업이익 | C68: Ⅴ.OPERATING INCOME (or LOSS) | D68: =SUM(F68:Q68) -> -1.59224e+08 | F68: =+F39-F49-F41 -> -5212188.3 | G68: =+G39-G49-G41 -> -50361211 | H68: =+H39-H49-H41 -> -1.0271107e+08 | I68: =+I39-I49-I41 -> -104392.55 | J68: =+J39-J49-J41 -> -104392.55 | K68: =+K39-K49-K41 -> -104392.55 | L68: =+L39-L49-L41 -> -104392.55 | M68: =+M39-M49-M41 -> -104392.55 | ... Q68: =+Q39-Q49-Q41 -> -104392.55
B69: (이익률) | C69: (Rate) | D69: =+IFERROR(D68/D5,) -> -1.1130369 | F69: =+IFERROR(F68/F5,) -> -0.068040789 | G69: =+IFERROR(G68/G5,) -> -0.75788378 | H69: =+IFERROR(H68/H5,) -> 0 | I69: =+IFERROR(I68/I5,) -> 0 | J69: =+IFERROR(J68/J5,) -> 0 | K69: =+IFERROR(K68/K5,) -> 0 | L69: =+IFERROR(L68/L5,) -> 0 | M69: =+IFERROR(M68/M5,) -> 0 | ... Q69: =+IFERROR(Q68/Q5,) -> 0
B70: Ⅵ.영업외수익 | C70: Ⅵ. NON-OPERATING INCOME | D70: =SUM(F70:Q70) -> 5237808 | F70: =SUM(F71:F81) -> 3502061.2 | G70: =SUM(G71:G81) -> 1735746.8 | H70: =SUM(H71:H81) -> 0 | I70: =SUM(I71:I81) -> 0 | J70: =SUM(J71:J81) -> 0 | K70: =SUM(K71:K81) -> 0 | L70: =SUM(L71:L81) -> 0 | M70: =SUM(M71:M81) -> 0 | ... Q70: =SUM(Q71:Q81) -> 0
C71: Interest Income | D71: =SUM(F71:Q71) -> 2841397.8 | F71: 1473566.8 | G71: 1367831
C72: Commission Income | D72: =SUM(F72:Q72) -> 0
C73: Non-Relevant Provisions | D73: =SUM(F73:Q73) -> 0
C74: Exchange Profits | D74: =SUM(F74:Q74) -> 2056508.2 | F74: 1917650.5 | G74: 138857.75
C75: Foreign Currency Transactions Profit | D75: =SUM(F75:Q75) -> 0
C76: Foreign Currency Translation of Profit | D76: =SUM(F76:Q76) -> 0
C77: Translation of Foreign Currency Profit | D77: =SUM(F77:Q77) -> 0
C78: Translation of Foreign Currency Profit | D78: =SUM(F78:Q78) -> 0
C79: Rediscount Interest Income | D79: =SUM(F79:Q79) -> 0
C80: Other Ordinary Income and Profits | D80: =SUM(F80:Q80) -> 0
C81: OTHER EXTRAORDINARY INCOME AND PROFITS | D81: =SUM(F81:Q81) -> 339901.97 | F81: 110843.95 | G81: 229058.02
B82: Ⅶ. 영업외비용 | C82: Ⅶ. NON-OPERATING EXPENSES | D82: =SUM(F82:Q82) -> 1939009.4 | F82: =SUM(F83:F95) -> 1521395.7 | G82: =SUM(G83:G95) -> 417613.68 | H82: =SUM(H83:H95) -> 0 | I82: =SUM(I83:I95) -> 0 | J82: =SUM(J83:J95) -> 0 | K82: =SUM(K83:K95) -> 0 | L82: =SUM(L83:L95) -> 0 | M82: =SUM(M83:M95) -> 0 | ... Q82: =SUM(Q83:Q95) -> 0
C83: Interest Expenses (-) | D83: =SUM(F83:Q83) -> 0
C84: Commission Expenses(-) | D84: =SUM(F84:Q84) -> 0
C85: Provision Expenses(-) | D85: =SUM(F85:Q85) -> 0
C86: Losses on Sale of Securities(-) | D86: =SUM(F86:Q86) -> 0
C87: Exchange Losses(-) | D87: =SUM(F87:Q87) -> 1569162.2 | F87: 1521395.7 | G87: 47766.49
C88: Foreign Currency Transactions Losses | D88: =SUM(F88:Q88) -> 0
C89: Foreign Currency Translation of Losses | D89: =SUM(F89:Q89) -> 0
C90: Rediscount Interest Expenses(-) | D90: =SUM(F90:Q90) -> 0
C91: Other Ordinary Expenses and Losses(-) | D91: =SUM(F91:Q91) -> 0
C92: Short-Term Borrowing Expenses(-) | D92: =SUM(F92:Q92) -> 0
C93: Long-Term Borrowing Expenses(-) | D93: =SUM(F93:Q93) -> 0
C94: Financing Expenses | D94: =SUM(F94:Q94) -> 4000.24 | G94: 4000.24
C95: OTHER EXTRAORDINARY EXPENSES AND LOSSES (-) | D95: =SUM(F95:Q95) -> 365846.95 | G95: 365846.95
B96: Ⅸ.당기손익 | C96: Ⅸ.NET INCOME (or LOSS) | D96: =SUM(F96:Q96) -> -1.5592521e+08 | F96: =+F68+F70-F82 -> -3231522.7 | G96: =+G68+G70-G82 -> -49043078 | H96: =+H68+H70-H82 -> -1.0271107e+08 | I96: =+I68+I70-I82 -> -104392.55 | J96: =+J68+J70-J82 -> -104392.55 | K96: =+K68+K70-K82 -> -104392.55 | L96: =+L68+L70-L82 -> -104392.55 | M96: =+M68+M70-M82 -> -104392.55 | ... Q96: =+Q68+Q70-Q82 -> -104392.55
B97: (이익률) | C97: (rate) | D97: =+IFERROR(D96/D5,) -> -1.0899771 | F97: =+IFERROR(F96/F5,) -> -0.042184845 | G97: =+IFERROR(G96/G5,) -> -0.73804725 | H97: =+IFERROR(H96/H5,) -> 0 | I97: =+IFERROR(I96/I5,) -> 0 | J97: =+IFERROR(J96/J5,) -> 0 | K97: =+IFERROR(K96/K5,) -> 0 | L97: =+IFERROR(L96/L5,) -> 0 | M97: =+IFERROR(M96/M5,) -> 0 | ... Q97: =+IFERROR(Q96/Q5,) -> 0

Sheet warehouse inventory check
H2: (재고 입고 되었으나 업체가 인보이스 미발행)
G3: *월말 기준 실사 재고 | H3: *업체 인보이스 미발행 재고 | I3: *고객 반품/리워크 재고 | J3: *불량품 창고 | K3: *매입정산후 공급자 창고임시보관 | L3: *운반중 재고 | M3: *고객 출고 후 인보이스 미발행
D4: ↓ 해당 월 재고 기록 후 숫자로 저장 필요 ↓ | F4: Description | G4: End of Month Warehouse Stock | H4: Uninvoiced Stock (supplier) | I4: Return/Rework Stock (customer) | J4: Quality warehouse | K4: In Supplier Warehouse after Invoicing | L4: transit stock | M4: Uninvoiced Stock (customer) | N4: (UNIT: EA)
A5: Don't delete | C5: Month | D5: Code | E5: Item | F5: Location | G5: warehouse (KCTR) | H5: warehouse (KCTR) | I5: warehouse (KCTR) | J5: warehouse (KCTR) | K5: Supplier Warehouse | L5: transit | M5: Customer Warehouse | N5: total Quantity
A6: 1 | C6: 1 | D6: PZ38-10B694-AD | E6: Main Harness | G6: 163 | N6: =SUM(G6,J6:M6)-H6-I6 -> 163
A7: 2 | C7: 1 | D7: PZ38-10B694-BD | E7: Main Harness | G7: 10 | N7: =SUM(G7,J7:M7)-H7-I7 -> 10
A8: 3 | C8: 1 | D8: PZ38-14A033-AB | E8: BUSBAR - Array to Array (short) | G8: 1 | N8: =SUM(G8,J8:M8)-H8-I8 -> 1
A9: 4 | C9: 1 | D9: PZ38-14A033-BB | E9: BUSBAR - Array to Array (long) | G9: 1 | N9: =SUM(G9,J9:M9)-H9-I9 -> 1
A10: 5 | C10: 1 | D10: PZ38-14A033-CB | E10: BUSBAR - Array 3 to 4 | G10: 1153 | N10: =SUM(G10,J10:M10)-H10-I10 -> 1153
A11: 6 | C11: 1 | D11: PZ38-14A033-FE | E11: BUSBAR - Array to Array (Straight)_Insert | N11: =SUM(G11,J11:M11)-H11-I11 -> 0
A12: 7 | C12: 1 | D12: PZ38-14A033-GD | E12: BUSBAR - Array to Array (Angled)_Insert | G12: 3240 | N12: =SUM(G12,J12:M12)-H12-I12 -> 3240
A13: 8 | C13: 1 | D13: PZ38-14A033-HF | E13: BUSBAR - Array4 to Array 5_Insert | N13: =SUM(G13,J13:M13)-H13-I13 -> 0
A14: 9 | C14: 1 | D14: PZ38-14A033-JD | E14: BEV-E1 BUSBAR Array 8 to Array 9 | N14: =SUM(G14,J14:M14)-H14-I14 -> 0
A15: 10 | C15: 1 | D15: PZ38-14A033-KD | E15: BUSBAR - Array 1 to Neg BEC_Insert | N15: =SUM(G15,J15:M15)-H15-I15 -> 0
A16: 11 | C16: 1 | D16: PZ38-14A033-LF | E16: BUSBAR - Array 9 to Pos BEC_Insert | H16: 288 | N16: =SUM(G16,J16:M16)-H16-I16 -> -288 | O16: Nursan’s late invoice.
A17: 12 | C17: 1 | D17: PZ38-14A033-MC | E17: BUSBAR - Pos BEC to DCFC_Protector | H17: 560 | N17: =SUM(G17,J17:M17)-H17-I17 -> -560 | O17: Nursan’s late invoice.
A18: 13 | C18: 1 | D18: PZ38-14A033-NB | E18: BUSBAR - Neg BEC to DCFC_Protector | N18: =SUM(G18,J18:M18)-H18-I18 -> 0
A19: 14 | C19: 1 | D19: PZ38-14A033-PC | E19: BUSBAR - CIRCUIT BREAKER_A_Insert | N19: =SUM(G19,J19:M19)-H19-I19 -> 0
A20: 15 | C20: 1 | D20: PZ38-14A033-RC | E20: BUSBAR - CIRCUIT BREAKER_B_Insert | N20: =SUM(G20,J20:M20)-H20-I20 -> 0
A21: 16 | C21: 1 | D21: PZ38-14B252-AB | E21: Jumper | G21: 1419 | N21: =SUM(G21,J21:M21)-H21-I21 -> 1419
A22: 17 | C22: 1 | D22: PZ38-14B680-AD | E22: PDU | G22: 6 | N22: =SUM(G22,J22:M22)-H22-I22 -> 6
A23: 18 | C23: 1 | D23: S2X8-14A033-AC | E23: BUS BAR ASY – POS BEC TO ARRAY 6 POS | G23: 7 | M23: 720 | N23: =SUM(G23,J23:M23)-H23-I23 -> 727 | O23: Late Customs Clearance Date
A24: 19 | C24: 1 | D24: S2X8-14A033-BC | E24: BUS BAR ASY - COMMON BUSBAR ARRAY 6 TO 4 | G24: 7 | M24: 1440 | N24: =SUM(G24,J24:M24)-H24-I24 -> 1447 | O24: Late Customs Clearance Date
A25: 20 | C25: 1 | D25: S2X8-14A033-CC | E25: BUS BAR ASY – ARRAY 4 NEG TO CIRCUIT BREAKER | G25: 5 | M25: 720 | N25: =SUM(G25,J25:M25)-H25-I25 -> 725 | O25: Late Customs Clearance Date
A26: 21 | C26: 1 | D26: S2X8-14A033-DC | E26: BUS BAR ASY – CIRCUIT BREAKER TO ARRAY 3 POS | G26: 5 | M26: 720 | N26: =SUM(G26,J26:M26)-H26-I26 -> 725 | O26: Late Customs Clearance Date
A27: 22 | C27: 1 | D27: S2X8-14A033-EC | E27: BUS BAR ASY – COMMON BUSBAR ARRAY 3 TO 1 | G27: 7 | M27: 1440 | N27: =SUM(G27,J27:M27)-H27-I27 -> 1447 | O27: Late Customs Clearance Date
A28: 23 | C28: 1 | D28: S2X8-14A033-GC | E28: BUS BAR ASY – ARRAY 1 NEG TO NEG BEC | G28: 7 | M28: 720 | N28: =SUM(G28,J28:M28)-H28-I28 -> 727 | O28: Late Customs Clearance Date
A29: 24 | C29: 1 | D29: S2X8-14A033-HD | E29: BUS BAR ASY – POS BEC TO DCFC POS | M29: 720 | N29: =SUM(G29,J29:M29)-H29-I29 -> 720 | O29: Late Customs Clearance Date
A30: 25 | C30: 1 | D30: S2X8-14A033-JD | E30: BUS BAR ASY – NEG BEC TO DCFC NEG | M30: 720 | N30: =SUM(G30,J30:M30)-H30-I30 -> 720 | O30: Late Customs Clearance Date
A31: 26 | C31: 1 | D31: SZ38-10B694-AC | E31: Main Harness | G31: 94 | N31: =SUM(G31,J31:M31)-H31-I31 -> 94
A32: 27 | C32: 1 | D32: SZ38-14A033-AB | E32: BUSBAR - Array 2 to Array3_Insert | G32: 61 | N32: =SUM(G32,J32:M32)-H32-I32 -> 61
A33: 28 | C33: 1 | D33: SZ38-14A033-BB | E33: BUSBAR - Array 6 to Pos BEC_Insert | G33: 61 | N33: =SUM(G33,J33:M33)-H33-I33 -> 61
A34: 29 | C34: 1 | D34: T2X8-14A033-AA | E34: BUSBAR ASY | N34: =SUM(G34,J34:M34)-H34-I34 -> 0
A35: 30 | C35: 1 | D35: T2X8-14A033-BA | E35: BUSBAR ASY | N35: =SUM(G35,J35:M35)-H35-I35 -> 0
A36: 31 | C36: 1 | D36: T2X8-14A033-EA | E36: BUSBAR ASY | N36: =SUM(G36,J36:M36)-H36-I36 -> 0
A37: 32 | C37: 1 | D37: T2X8-14A033-GA | E37: BUSBAR ASY | N37: =SUM(G37,J37:M37)-H37-I37 -> 0
A38: 33 | C38: 1 | D38: TZ38-10B694-AA | E38: V710 AWD MAIN W/H ASSY | G38: 2 | N38: =SUM(G38,J38:M38)-H38-I38 -> 2
A39: 34 | C39: 1 | D39: TZ38-10B694-AD | E39: Main Harness | G39: 18 | N39: =SUM(G39,J39:M39)-H39-I39 -> 18
A40: 35 | C40: 1 | D40: TZ38-10B694-AF | E40: Main Harness-AWD-RWD | G40: 20 | N40: =SUM(G40,J40:M40)-H40-I40 -> 20
A41: 36 | C41: 1 | D41: TZ38-10B694-BA | E41: Main_Harness-RWD | N41: =SUM(G41,J41:M41)-H41-I41 -> 0
A42: 37 | C42: 1 | D42: TZ38-10B694-CA | E42: Main_Harness-AWD | N42: =SUM(G42,J42:M42)-H42-I42 -> 0
A43: 38 | C43: 1 | D43: TZ38-10B694-DB | E43: Main Harness | G43: 93 | N43: =SUM(G43,J43:M43)-H43-I43 -> 93
A44: 39 | C44: 1 | D44: TZ38-10B694-DC | E44: Main Harness-AWD-RWD | G44: 120 | N44: =SUM(G44,J44:M44)-H44-I44 -> 120
A45: 40 | C45: 1 | D45: TZ38-14A033-AA | E45: BUSBAR ASY | N45: =SUM(G45,J45:M45)-H45-I45 -> 0
A46: 41 | C46: 1 | D46: TZ38-14A033-AA04 | E46: BUSBAR | N46: =SUM(G46,J46:M46)-H46-I46 -> 0
A47: 42 | C47: 1 | D47: TZ38-14A033-BA | E47: BUSBAR ASY | N47: =SUM(G47,J47:M47)-H47-I47 -> 0
A48: 43 | C48: 1 | D48: TZ38-14A033-BA04 | E48: BUSBAR | N48: =SUM(G48,J48:M48)-H48-I48 -> 0
A49: 44 | C49: 1 | D49: TZ38-14A033-CA | E49: BUSBAR ASY | N49: =SUM(G49,J49:M49)-H49-I49 -> 0
A50: 45 | C50: 1 | D50: TZ38-14A033-CA04 | E50: BUSBAR | N50: =SUM(G50,J50:M50)-H50-I50 -> 0
A51: 46 | C51: 1 | D51: TZ38-14A033-DA | E51: BUSBAR ASY | N51: =SUM(G51,J51:M51)-H51-I51 -> 0
A52: 47 | C52: 1 | D52: TZ38-14A033-DA04 | E52: BUSBAR | N52: =SUM(G52,J52:M52)-H52-I52 -> 0
A53: 48 | C53: 1 | D53: TZ38-14A033-EA | E53: BUSBAR ASY | N53: =SUM(G53,J53:M53)-H53-I53 -> 0
A54: 49 | C54: 1 | D54: TZ38-14A033-EA04 | E54: BUSBAR | N54: =SUM(G54,J54:M54)-H54-I54 -> 0
A55: 50 | C55: 1 | D55: TZ38-14A033-FA | E55: BUS BAR ASY | H55: 324 | N55: =SUM(G55,J55:M55)-H55-I55 -> -324 | O55: Nursan’s late invoice.
A56: 51 | C56: 1 | D56: TZ38-14A033-GA | E56: BUSBAR ASY | N56: =SUM(G56,J56:M56)-H56-I56 -> 0
A57: 52 | C57: 1 | D57: TZ38-14A033-GA04 | E57: BUSBAR | N57: =SUM(G57,J57:M57)-H57-I57 -> 0
A58: 53 | C58: 1 | D58: TZ38-14A033-HB | E58: MCA CONNECTOR CLIP | H58: 540 | N58: =SUM(G58,J58:M58)-H58-I58 -> -540 | O58: Nursan’s late invoice.
A59: 54 | C59: 1 | D59: TZ38-14A033-JA | E59: BUS BAR ASY | G59: 40 | N59: =SUM(G59,J59:M59)-H59-I59 -> 40
A60: 55 | C60: 1 | D60: TZ38-14A033-JB | E60: MCA CONNECTOR CLIP | H60: 200 | N60: =SUM(G60,J60:M60)-H60-I60 -> -200 | O60: Nursan’s late invoice.
A61: 56 | C61: 1 | D61: TZ38-14A033-KA | E61: MCA CONNECTOR CLIP | H61: 21 | N61: =SUM(G61,J61:M61)-H61-I61 -> -21 | O61: Nursan’s late invoice.
A62: 57 | C62: 1 | D62: TZ38-14A033-LA | E62: MCA CONNECTOR CLIP | H62: 7 | N62: =SUM(G62,J62:M62)-H62-I62 -> -7 | O62: Nursan’s late invoice.
A63: 58 | C63: 1 | D63: TZ38-14A033-MA | E63: MCA CONNECTOR CLIP | H63: 7 | N63: =SUM(G63,J63:M63)-H63-I63 -> -7 | O63: Nursan’s late invoice.
A64: 59 | C64: 1 | D64: TZ38-14A033-NA | E64: BUSBAR ASY | N64: =SUM(G64,J64:M64)-H64-I64 -> 0
A65: 60 | C65: 1 | D65: TZ38-14A033-PB | E65: BUSBAR ASY | H65: 216 | N65: =SUM(G65,J65:M65)-H65-I65 -> -216 | O65: Nursan’s late invoice.
A66: 61 | C66: 1 | D66: TZ38-14A033-RB | E66: BUSBAR ASY | H66: 216 | N66: =SUM(G66,J66:M66)-H66-I66 -> -216 | O66: Nursan’s late invoice.
A67: 62 | C67: 1 | D67: TZ38-14A033-SA | E67: BUSBAR ASY | N67: =SUM(G67,J67:M67)-H67-I67 -> 0
A68: 63 | C68: 1 | D68: TZ38-14A033-TA | E68: BUSBAR ASY | N68: =SUM(G68,J68:M68)-H68-I68 -> 0
A69: 64 | C69: 1 | D69: TZ38-14A033-TA04 | E69: BUSBAR | N69: =SUM(G69,J69:M69)-H69-I69 -> 0
A70: 65 | C70: 1 | D70: TZ38-14B680-AA | E70: PDU_CONN_ASSY | N70: =SUM(G70,J70:M70)-H70-I70 -> 0
A71: 66 | C71: 1 | D71: TZ38-14B680-BA | E71: PDU | G71: 5 | N71: =SUM(G71,J71:M71)-H71-I71 -> 5
A72: 67 | C72: 1 | D72: TZ38-14B680-BB | E72: AWD/RWD PDU CONN ASSY | N72: =SUM(G72,J72:M72)-H72-I72 -> 0
A73: 69 | C73: 1 | D73: BEE22-CP007 | E73: CHANNEL | N73: =SUM(G73,J73:M73)-H73-I73 -> 0
A74: 70 | C74: 1 | D74: BEE22-CT009 | E74: BEV_E_TML_1 | G74: 4500 | N74: =SUM(G74,J74:M74)-H74-I74 -> 4500
A75: 71 | C75: 1 | D75: BEE22-CT010 | E75: BEV_E_TML_2 | G75: 4500 | N75: =SUM(G75,J75:M75)-H75-I75 -> 4500
A76: 72 | C76: 1 | D76: BEE22-CT011 | E76: BEV_E_TML_3 | G76: 12000 | N76: =SUM(G76,J76:M76)-H76-I76 -> 12000
A77: 73 | C77: 1 | D77: BEE24-CP001 | E77: CHANNEL | N77: =SUM(G77,J77:M77)-H77-I77 -> 0
A78: 74 | C78: 1 | D78: BEE24-CP002 | E78: CHANNEL | N78: =SUM(G78,J78:M78)-H78-I78 -> 0
A79: 75 | C79: 1 | D79: BEE24-CP003 | E79: CHANNEL | N79: =SUM(G79,J79:M79)-H79-I79 -> 0
A80: 76 | C80: 1 | D80: BEE25-CT001 | E80: Terminal | N80: =SUM(G80,J80:M80)-H80-I80 -> 0
A81: 77 | C81: 1 | D81: TUBE0000101 | E81: DBJ033 | N81: =SUM(G81,J81:M81)-H81-I81 -> 0
A82: 78 | C82: 1 | D82: TUBE0000104 | E82: CG13-38 (5M) | N82: =SUM(G82,J82:M82)-H82-I82 -> 0
A83: 79 | C83: 1 | D83: UKLA0-05011 | E83: CG19-38 (08) (7M) | N83: =SUM(G83,J83:M83)-H83-I83 -> 0
A84: 80 | C84: 1 | N84: =SUM(G84,J84:M84)-H84-I84 -> 0
A85: 81 | C85: 1 | N85: =SUM(G85,J85:M85)-H85-I85 -> 0
A86: 82 | C86: 1 | N86: =SUM(G86,J86:M86)-H86-I86 -> 0
A87: 83 | C87: 1 | N87: =SUM(G87,J87:M87)-H87-I87 -> 0
A88: 84 | C88: 1 | N88: =SUM(G88,J88:M88)-H88-I88 -> 0
A89: 85 | C89: 1 | N89: =SUM(G89,J89:M89)-H89-I89 -> 0
A90: 86 | C90: 1 | N90: =SUM(G90,J90:M90)-H90-I90 -> 0
A91: 87 | C91: 1 | N91: =SUM(G91,J91:M91)-H91-I91 -> 0
A92: 88 | C92: 1 | N92: =SUM(G92,J92:M92)-H92-I92 -> 0
A93: 89 | C93: 1 | N93: =SUM(G93,J93:M93)-H93-I93 -> 0
A94: 90 | C94: 1 | N94: =SUM(G94,J94:M94)-H94-I94 -> 0
A95: 91 | C95: 1 | N95: =SUM(G95,J95:M95)-H95-I95 -> 0
... A104: 100 | C104: 1 | N104: =SUM(G104,J104:M104)-H104-I104 -> 0
E105: total | G105: =SUM(G6:G104) -> 27545 | H105: =SUM(H6:H104) -> 2379 | I105: =SUM(I6:I104) -> 0 | J105: =SUM(J6:J104) -> 0 | K105: =SUM(K6:K104) -> 0 | L105: =SUM(L6:L104) -> 0 | M105: =SUM(M6:M104) -> 7200 | N105: =SUM(N6:N104) -> 32366
C108: Month | D108: Code | E108: Item | G108: warehouse (KCTR) | H108: warehouse (KCTR) | I108: warehouse (KCTR) | J108: warehouse (KCTR) | K108: Supplier Warehouse | L108: transit | M108: Customer Warehouse | N108: total Quantity
A109: 1 | C109: 2 | D109: PZ38-10B694-AD | E109: =IF(VLOOKUP($A109,'★Master Code List'!$B$4:$K$167,10,)=0,"",(VLOOKUP($A109,'★Master Code List'!$B$4:$K$167,10,))) -> Main Harness | G109: 371 | N109: =SUM(G109,J109:M109)-H109-I109 -> 371
A110: 2 | C110: 2 | D110: PZ38-10B694-BD | E110: =IF(VLOOKUP($A110,'★Master Code List'!$B$4:$K$167,10,)=0,"",(VLOOKUP($A110,'★Master Code List'!$B$4:$K$167,10,))) -> Main Harness | G110: 3 | N110: =SUM(G110,J110:M110)-H110-I110 -> 3
A111: 3 | C111: 2 | D111: PZ38-14A033-AB | E111: =IF(VLOOKUP($A111,'★Master Code List'!$B$4:$K$167,10,)=0,"",(VLOOKUP($A111,'★Master Code List'!$B$4:$K$167,10,))) -> BUSBAR - Array to Array (short) | G111: 1 | N111: =SUM(G111,J111:M111)-H111-I111 -> 1
...

Sheet WIC(2025)
H2: (재고 입고 되었으나 업체가 인보이스 미발행)
G3: *월말 기준 실사 재고 | H3: *업체 인보이스 미발행 재고 | I3: *고객 반품/리워크 재고 | J3: *불량품 창고 | K3: *매입정산후 공급자 창고임시보관 | L3: *운반중 재고 | M3: *고객 출고 후 인보이스 미발행
D4: ↓ 해당 월 재고 기록 후 숫자로 저장 필요 ↓ | F4: Description | G4: End of Month Warehouse Stock | H4: Uninvoiced Stock (supplier) | I4: Return/Rework Stock (customer) | J4: Quality warehouse | K4: In Supplier Warehouse after Invoicing | L4: transit stock | M4: Uninvoiced Stock (customer) | N4: (UNIT: EA)
A5: Don't delete | C5: Month | D5: Code | E5: Item | F5: Location | G5: warehouse (KCTR) | H5: warehouse (KCTR) | I5: warehouse (KCTR) | J5: warehouse (KCTR) | K5: Supplier Warehouse | L5: transit | M5: Customer Warehouse | N5: total Quantity
A6: 1 | C6: 1 | D6: PZ38-10B694-AB® | E6: Main Harness | G6: 0 | J6: 3 | N6: 3
A7: 2 | C7: 1 | D7: PZ38-10B694-AC | E7: Main Harness | G7: 1061 | J7: 1 | N7: 1062 | O7: 1EA 포드 반품 후 레드존
A8: 3 | C8: 1 | D8: PZ38-10B694-AC® | E8: Main Harness | J8: 4 | N8: 4
A9: 4 | C9: 1 | D9: PZ38-10B694-BC | E9: Main Harness | G9: 2 | N9: 2
A10: 5 | C10: 1 | D10: PZ38-10B694-BC® | E10: Main Harness | J10: 20 | N10: 20
A11: 6 | C11: 1 | D11: PZ38-10B694-BD | E11: Main Harness | G11: 3 | N11: 3
A12: 7 | C12: 1 | D12: PZ38-14A033-AA® | E12: BUSBAR - Array to Array (short) | J12: 6 | N12: 6
A13: 8 | C13: 1 | D13: PZ38-14A033-AB | E13: BUSBAR - Array to Array (short) | G13: 0 | N13: 0
A14: 9 | C14: 1 | D14: PZ38-14A033-AC | E14: BUSBAR - Array to Array (short) | N14: 0
A15: 10 | C15: 1 | D15: PZ38-14A033-BA® | E15: BUSBAR - Array to Array (long) | J15: 7 | N15: 7
A16: 11 | C16: 1 | D16: PZ38-14A033-BB | E16: BUSBAR - Array to Array (long) | G16: 3072 | N16: 3072
A17: 12 | C17: 1 | D17: PZ38-14A033-CA® | E17: BUSBAR - Array 3 to 4 | J17: 8 | N17: 8
A18: 13 | C18: 1 | D18: PZ38-14A033-CB | E18: BUSBAR - Array 3 to 4 | N18: 0
A19: 14 | C19: 1 | D19: PZ38-14A033-FB | E19: BUSBAR - Array to Array (Straight)_Insert | N19: 0
A20: 15 | C20: 1 | D20: PZ38-14A033-FD | E20: BUSBAR - Array to Array (Straight)_Insert | N20: 0
A21: 16 | C21: 1 | D21: PZ38-14A033-FD® | E21: BUSBAR - Array to Array (Straight)_Insert | J21: 1 | N21: 1
A22: 17 | C22: 1 | D22: PZ38-14A033-GB | E22: BUSBAR - Array to Array (Angled)_Insert | N22: 0
A23: 18 | C23: 1 | D23: PZ38-14A033-GD | E23: BUSBAR - Array to Array (Angled)_Insert | N23: 0 | O23: 1 EA 스크랩
A24: 19 | C24: 1 | D24: PZ38-14A033-GD® | E24: BUSBAR - Array to Array (Angled)_Insert | G24: 0 | J24: 11 | N24: 11
A25: 20 | C25: 1 | D25: PZ38-14A033-HD | E25: BUSBAR - Array4 to Array 5_Insert | N25: 0
A26: 21 | C26: 1 | D26: PZ38-14A033-HD® | E26: BUSBAR - Array4 to Array 5_Insert | J26: 5 | N26: 5
A27: 22 | C27: 1 | D27: PZ38-14A033-HE | E27: BUSBAR - Array4 to Array 5_Insert | N27: 0
A28: 23 | C28: 1 | D28: PZ38-14A033-JD | E28: BUSBAR - Array 8 to Array 9_Insert | N28: 0
A29: 24 | C29: 1 | D29: PZ38-14A033-JD® | E29: BUSBAR - Array 8 to Array 9_Insert | J29: 3 | N29: 3
A30: 25 | C30: 1 | D30: PZ38-14A033-KB | E30: BUSBAR - Array 1 to Neg BEC_Insert | N30: 0
A31: 26 | C31: 1 | D31: PZ38-14A033-KD | E31: BUSBAR - Array 1 to Neg BEC_Insert | N31: 0
A32: 27 | C32: 1 | D32: PZ38-14A033-LD | E32: BUSBAR - Array 9 to Pos BEC_Insert | N32: 0
A33: 28 | C33: 1 | D33: PZ38-14A033-LE | E33: BUSBAR - Array 9 to Pos BEC_Insert | N33: 0
A34: 29 | C34: 1 | D34: PZ38-14A033-MB | E34: BUSBAR - Pos BEC to DCFC_Protector | N34: 0
A35: 30 | C35: 1 | D35: PZ38-14A033-MB® | E35: BUSBAR - Pos BEC to DCFC_Protector | J35: 2 | N35: 2
A36: 31 | C36: 1 | D36: PZ38-14A033-MC | E36: BUSBAR - Pos BEC to DCFC_Protector | N36: 0
A37: 32 | C37: 1 | D37: PZ38-14A033-NB | E37: BUSBAR - Neg BEC to DCFC_Protector | N37: 0
A38: 33 | C38: 1 | D38: PZ38-14A033-PA | E38: BUSBAR - CIRCUIT BREAKER_A_Insert | N38: 0
A39: 34 | C39: 1 | D39: PZ38-14A033-PC | E39: BUSBAR - CIRCUIT BREAKER_A_Insert | N39: 0
A40: 35 | C40: 1 | D40: PZ38-14A033-RA | E40: BUSBAR - CIRCUIT BREAKER_B_Insert | N40: 0
A41: 36 | C41: 1 | D41: PZ38-14A033-RC | E41: BUSBAR - CIRCUIT BREAKER_B_Insert | N41: 0
A42: 37 | C42: 1 | D42: PZ38-14B252-AB | E42: Jumper | N42: 0
A43: 38 | C43: 1 | D43: PZ38-14B252-AB® | E43: Jumper | J43: 3 | N43: 3
A44: 39 | C44: 1 | D44: PZ38-14B680-AA | E44: PDU | N44: 0
A45: 40 | C45: 1 | D45: PZ38-14B680-AB | E45: PDU | N45: 0
A46: 41 | C46: 1 | D46: PZ38-14B680-AC | E46: PDU | G46: 0 | N46: 0
A47: 42 | C47: 1 | D47: PZ38-14B680-AD | E47: PDU | G47: 5 | N47: 5
A48: 43 | C48: 1 | D48: PZ38-14B680-AD® | E48: PDU | J48: 1 | N48: 1
A49: 44 | C49: 1 | D49: S2X8-14A033-AC | E49: BUS BAR ASY – POS BEC TO ARRAY 6 POS | M49: 1440 | N49: 1440 | O49: 1월말 선적 인보이스 반영, BEV-M등 해외 선적은 수출일 기준이라 지연 발생
A50: 45 | C50: 1 | D50: S2X8-14A033-BC | E50: BUS BAR ASY - COMMON BUSBAR ARRAY 6 TO 4 | M50: 2880 | N50: 2880 | O50: 1월말 선적 인보이스 반영, BEV-M등 해외 선적은 수출일 기준이라 지연 발생
A51: 46 | C51: 1 | D51: S2X8-14A033-CC | E51: BUS BAR ASY – ARRAY 4 NEG TO CIRCUIT BREAKER | M51: 1440 | N51: 1440 | O51: 1월말 선적 인보이스 반영, BEV-M등 해외 선적은 수출일 기준이라 지연 발생
A52: 47 | C52: 1 | D52: S2X8-14A033-DC | E52: BUS BAR ASY – CIRCUIT BREAKER TO ARRAY 3 POS | N52: 0
A53: 48 | C53: 1 | D53: S2X8-14A033-EC | E53: BUS BAR ASY – COMMON BUSBAR ARRAY 3 TO 1 | N53: 0
A54: 49 | C54: 1 | D54: S2X8-14A033-GC | E54: BUS BAR ASY – ARRAY 1 NEG TO NEG BEC | M54: 1440 | N54: 1440 | O54: 1월말 선적 인보이스 반영, BEV-M등 해외 선적은 수출일 기준이라 지연 발생
A55: 50 | C55: 1 | D55: S2X8-14A033-HC | E55: BUS BAR ASY – POS BEC TO DCFC POS | N55: 0
A56: 51 | C56: 1 | D56: S2X8-14A033-HD | E56: BUS BAR ASY – POS BEC TO DCFC POS | N56: 0
A57: 52 | C57: 1 | D57: S2X8-14A033-JC | E57: BUS BAR ASY – NEG BEC TO DCFC NEG | N57: 0
A58: 53 | C58: 1 | D58: S2X8-14A033-JD | E58: BUS BAR ASY – NEG BEC TO DCFC NEG | N58: 0
A59: 54 | C59: 1 | D59: SZ38-10B694-AB | E59: Main Harness | N59: 0
A60: 55 | C60: 1 | D60: SZ38-10B694-AC | E60: Main Harness | G60: 91 | N60: 91
A61: 56 | C61: 1 | D61: SZ38-10B694-AC® | E61: Main Harness | J61: 2 | N61: 2
A62: 57 | C62: 1 | D62: SZ38-14A033-AA | E62: BUSBAR - Array 2 to Array3_Insert | N62: 0
A63: 58 | C63: 1 | D63: SZ38-14A033-AB | E63: BUSBAR - Array 2 to Array3_Insert | G63: 57 | N63: 57
A64: 59 | C64: 1 | D64: SZ38-14A033-BA | E64: BUSBAR - Array 6 to Pos BEC_Insert | N64: 0
A65: 60 | C65: 1 | D65: SZ38-14A033-BA® | E65: BUSBAR - Array 6 to Pos BEC_Insert | J65: 1 | N65: 1
A66: 61 | C66: 1 | D66: SZ38-14A033-BB | E66: BUSBAR - Array 6 to Pos BEC_Insert | G66: 57 | N66: 57
A67: 62 | C67: 1 | D67: TZ38-10B694-AA1 | E67: Main Harness | N67: 0
A68: 63 | C68: 1 | D68: TZ38-10B694-AA11 | E68: V710 AWD MAIN W/H ASSY | N68: 0
A69: 64 | C69: 1 | D69: BEE22-CT009 | E69: BEV-E1/BEV_E_TML_1 | N69: 0
A70: 65 | C70: 1 | D70: BEE22-CT010 | E70: BEV-E1/BEV_E_TML_2 | N70: 0
A71: 66 | C71: 1 | D71: BEE22-CT011 | E71: BEV-E1/BEV_E_TML_3 | N71: 0
A72: 67 | C72: 1 | N72: 0
A73: 68 | C73: 1 | N73: 0
A74: 69 | C74: 1 | N74: 0
A75: 70 | C75: 1 | N75: 0
A76: 71 | C76: 1 | N76: 0
A77: 72 | C77: 1 | N77: 0
A78: 73 | C78: 1 | N78: 0
A79: 74 | C79: 1 | N79: 0
A80: 75 | C80: 1 | N80: 0
A81: 76 | C81: 1 | N81: 0
A82: 77 | C82: 1 | N82: 0
A83: 78 | C83: 1 | N83: 0
... A105: 100 | C105: 1 | N105: 0
E106: total | G106: 4348 | H106: 0 | I106: 0 | J106: 78 | K106: 0 | L106: 0 | M106: 7200 | N106: 11626
P108: 업체 중복 인보이스 발행 수량 (7월 판매처리)
C109: Month | D109: Code | E109: Item | G109: warehouse (KCTR) | H109: warehouse (KCTR) | I109: warehouse (KCTR) | J109: warehouse (KCTR) | K109: Supplier Warehouse | L109: transit | M109: Customer Warehouse | N109: total Quantity | P109: Duplicates Invoice Stock
A110: 1 | C110: 2 | D110: PZ38-10B694-AB® | E110: Main Harness | N110: 0 | P110: 0
A111: 2 | C111: 2 | D111: PZ38-10B694-AC | E111: Main Harness | G111: 1664 | J111: 2 | N111: 1666 | P111: 0
A112: 3 | C112: 2 | D112: PZ38-10B694-AC® | E112: Main Harness | N112: 0 | P112: 0
A113: 4 | C113: 2 | D113: PZ38-10B694-BC | E113: Main Harness | G113: 0 | J113: 2 | N113: 2 | P113: 0
A114: 5 | C114: 2 | D114: PZ38-10B694-BC® | E114: Main Harness | G114: 3 | N114: 3 | P114: 0
A115: 6 | C115: 2 | D115: PZ38-10B694-BD | E115: Main Harness | G115: 3 | N115: 3 | P115: 0
A116: 7 | C116: 2 | D116: PZ38-14A033-AA® | E116: BUSBAR - Array to Array (short) | N116: 0 | P116: 0
A117: 8 | C117: 2 | D117: PZ38-14A033-AB | E117: BUSBAR - Array to Array (short) | G117: 7680 | N117: 7680 | P117: 0
A118: 9 | C118: 2 | D118: PZ38-14A033-AC | E118: BUSBAR - Array to Array (short) | G118: 0 | N118: 0 | P118: 276
A119: 10 | C119: 2 | D119: PZ38-14A033-BA® | E119: BUSBAR - Array to Array (long) | N119: 0 | P119: 0
A120: 11 | C120: 2 | D120: PZ38-14A033-BB | E120: BUSBAR - Array to Array (long) | G120: 9216 | N120: 9216 | P120: 410
A121: 12 | C121: 2 | D121: PZ38-14A033-CA® | E121: BUSBAR - Array 3 to 4 | N121: 0 | P121: 136
A122: 13 | C122: 2 | D122: PZ38-14A033-CB | E122: BUSBAR - Array 3 to 4 | G122: 4608 | N122: 4608 | P122: 0
A123: 14 | C123: 2 | D123: PZ38-14A033-FB | E123: BUSBAR - Array to Array (Straight)_Insert | G123: 0 | N123: 0 | P123: 136
...

Sheet ★Merchandise ledger_Low
X2: =+V404*Z404 -> 0
N3: by gross average method | O3: =+J335-O335 -> 0
A4: Don't delete | C4: merchandise ledger | G4: Beginning | J4: in-purchase | L4: In - etc | O4: out-sales | Q4: out - etc | S4: out - etc (Expense) | U4: Ending | W4: (UNIT:EA, TRY)
C5: Month | D5: Code | E5: Project | F5: Item | G5: Quantity | H5: unit price | I5: Amount | J5: Quantity | K5: Amount | L5: Quantity | M5: Amount | N5: Average unit price | O5: Quantity | P5: COST OF SALES | Q5: Quantity | R5: Amount | S5: Quantity | T5: Amount | U5: *inventory check Quantity | V5: unit price | W5: Amount | X5: check | Y5: Calculation Quantity | Z5: check
A6: 1 | C6: 1 | D6: PZ38-10B694-AD | E6: PHEV-E (V710) / (P703) | F6: Main Harness | G6: 1482 | H6: 3811.0833 | I6: 5648025.4 | J6: =SUMIFS('purchase data'!K:K,'purchase data'!$B:$B,$C6,'purchase data'!$F:$F,$D6) -> 3633 | K6: =SUMIFS('purchase data'!M:M,'purchase data'!$B:$B,$C6,'purchase data'!$F:$F,$D6) -> 14110217 | L6: =SUMIFS(ETC!$G:$G,ETC!$B:$B,$C6,ETC!$E:$E,$D6) -> 0 | M6: =SUMIFS(ETC!$J:$J,ETC!$E:$E,$D6,ETC!$B:$B,$C6) -> 0 | N6: =IF(IFERROR((I6+K6+M6)/(G6+J6+SUMIFS(ETC!$G:$G,ETC!$C:$C,1,ETC!$B:$B,$C6,ETC!$E:$E,$D6)),)=0,H6,IFERROR((I6+K6+M6)/(G6+J6+SUMIFS(ETC!$G:$G,ETC!$C:$C,1,ETC!$B:$B,$C6,ETC!$E:$E,$D6)),)) -> 3862.804 | O6: =++SUMIFS('sales data'!L:L,'sales data'!$B:$B,$C6,'sales data'!$F:$F,$D6,'sales data'!$O:$O,"") -> 4952 | P6: =+IF(O6<>0,O6*N6,) -> 19128606 | Q6: =+SUMIFS('sales data'!$L:$L,'sales data'!$B:$B,$C6,'sales data'!$F:$F,$D6,'sales data'!$O:$O,"R") -> 0 | R6: =+IF(Q6<>0,Q6*N6,) -> 0 | S6: =SUMIFS('sales data'!$L:$L,'sales data'!$B:$B,$C6,'sales data'!$F:$F,$D6,'sales data'!$O:$O,"N") -> 0 | T6: =+IF(S6<>0,S6*N6,) -> 0 | U6: =SUMIFS('warehouse inventory check'!$N:$N,'warehouse inventory check'!$C:$C,$C6,'warehouse inventory check'!$D:$D,$D6) -> 163 | V6: =+N6 -> 3862.804 | W6: =+IF(U6<>0,U6*N6,) -> 629637.06 | X6: =+I6+K6-P6-R6-W6-T6+M6 -> 5.8207661e-10 | Y6: =+G6+J6+L6-O6-Q6-S6 -> 163 | Z6: =+U6-Y6 -> 0
A7: 2 | C7: 1 | D7: PZ38-10B694-BD | E7: BEV-E1(V710) | F7: Main Harness | G7: 871 | H7: 4814.5306 | I7: 4193456.1 | J7: =SUMIFS('purchase data'!K:K,'purchase data'!$B:$B,$C7,'purchase data'!$F:$F,$D7) -> 40 | K7: =SUMIFS('purchase data'!M:M,'purchase data'!$B:$B,$C7,'purchase data'!$F:$F,$D7) -> 193971.38 | L7: =SUMIFS(ETC!$G:$G,ETC!$B:$B,$C7,ETC!$E:$E,$D7) -> 0 | M7: =SUMIFS(ETC!$J:$J,ETC!$E:$E,$D7,ETC!$B:$B,$C7) -> 0 | N7: =IF(IFERROR((I7+K7+M7)/(G7+J7+SUMIFS(ETC!$G:$G,ETC!$C:$C,1,ETC!$B:$B,$C7,ETC!$E:$E,$D7)),)=0,H7,IFERROR((I7+K7+M7)/(G7+J7+SUMIFS(ETC!$G:$G,ETC!$C:$C,1,ETC!$B:$B,$C7,ETC!$E:$E,$D7)),)) -> 4816.0565 | O7: =++SUMIFS('sales data'!L:L,'sales data'!$B:$B,$C7,'sales data'!$F:$F,$D7,'sales data'!$O:$O,"") -> 901 | P7: =+IF(O7<>0,O7*N7,) -> 4339266.9 | Q7: =+SUMIFS('sales data'!$L:$L,'sales data'!$B:$B,$C7,'sales data'!$F:$F,$D7,'sales data'!$O:$O,"R") -> 0 | R7: =+IF(Q7<>0,Q7*N7,) -> 0 | S7: =SUMIFS('sales data'!$L:$L,'sales data'!$B:$B,$C7,'sales data'!$F:$F,$D7,'sales data'!$O:$O,"N") -> 0 | T7: =+IF(S7<>0,S7*N7,) -> 0 | U7: =SUMIFS('warehouse inventory check'!$N:$N,'warehouse inventory check'!$C:$C,$C7,'warehouse inventory check'!$D:$D,$D7) -> 10 | V7: =+N7 -> 4816.0565 | W7: =+IF(U7<>0,U7*N7,) -> 48160.565 | X7: =+I7+K7-P7-R7-W7-T7+M7 -> -4.292815e-10 | Y7: =+G7+J7+L7-O7-Q7-S7 -> 10 | Z7: =+U7-Y7 -> 0
A8: 3 | C8: 1 | D8: PZ38-14A033-AB | E8: PHEV-E (V710) / (P703) | F8: BUSBAR - Array to Array (short) | G8: 14976 | H8: 132.32737 | I8: 1981734.7 | J8: =SUMIFS('purchase data'!K:K,'purchase data'!$B:$B,$C8,'purchase data'!$F:$F,$D8) -> 5195 | K8: =SUMIFS('purchase data'!M:M,'purchase data'!$B:$B,$C8,'purchase data'!$F:$F,$D8) -> 712838.9 | L8: =SUMIFS(ETC!$G:$G,ETC!$B:$B,$C8,ETC!$E:$E,$D8) -> 0 | M8: =SUMIFS(ETC!$J:$J,ETC!$E:$E,$D8,ETC!$B:$B,$C8) -> 0 | N8: =IF(IFERROR((I8+K8+M8)/(G8+J8+SUMIFS(ETC!$G:$G,ETC!$C:$C,1,ETC!$B:$B,$C8,ETC!$E:$E,$D8)),)=0,H8,IFERROR((I8+K8+M8)/(G8+J8+SUMIFS(ETC!$G:$G,ETC!$C:$C,1,ETC!$B:$B,$C8,ETC!$E:$E,$D8)),)) -> 133.58651 | O8: =++SUMIFS('sales data'!L:L,'sales data'!$B:$B,$C8,'sales data'!$F:$F,$D8,'sales data'!$O:$O,"") -> 20170 | P8: =+IF(O8<>0,O8*N8,) -> 2694440 | Q8: =+SUMIFS('sales data'!$L:$L,'sales data'!$B:$B,$C8,'sales data'!$F:$F,$D8,'sales data'!$O:$O,"R") -> 0 | R8: =+IF(Q8<>0,Q8*N8,) -> 0 | S8: =SUMIFS('sales data'!$L:$L,'sales data'!$B:$B,$C8,'sales data'!$F:$F,$D8,'sales data'!$O:$O,"N") -> 0 | T8: =+IF(S8<>0,S8*N8,) -> 0 | U8: =SUMIFS('warehouse inventory check'!$N:$N,'warehouse inventory check'!$C:$C,$C8,'warehouse inventory check'!$D:$D,$D8) -> 1 | V8: =+N8 -> 133.58651 | W8: =+IF(U8<>0,U8*N8,) -> 133.58651 | X8: =+I8+K8-P8-R8-W8-T8+M8 -> 3.6598635e-10 | Y8: =+G8+J8+L8-O8-Q8-S8 -> 1 | Z8: =+U8-Y8 -> 0
A9: 4 | C9: 1 | D9: PZ38-14A033-BB | E9: PHEV-E (V710) / (P703) | F9: BUSBAR - Array to Array (long) | G9: 3456 | H9: 168.26639 | I9: 581528.63 | J9: =SUMIFS('purchase data'!K:K,'purchase data'!$B:$B,$C9,'purchase data'!$F:$F,$D9) -> 11723 | K9: =SUMIFS('purchase data'!M:M,'purchase data'!$B:$B,$C9,'purchase data'!$F:$F,$D9) -> 2023352.3 | L9: =SUMIFS(ETC!$G:$G,ETC!$B:$B,$C9,ETC!$E:$E,$D9) -> 0 | M9: =SUMIFS(ETC!$J:$J,ETC!$E:$E,$D9,ETC!$B:$B,$C9) -> 0 | N9: =IF(IFERROR((I9+K9+M9)/(G9+J9+SUMIFS(ETC!$G:$G,ETC!$C:$C,1,ETC!$B:$B,$C9,ETC!$E:$E,$D9)),)=0,H9,IFERROR((I9+K9+M9)/(G9+J9+SUMIFS(ETC!$G:$G,ETC!$C:$C,1,ETC!$B:$B,$C9,ETC!$E:$E,$D9)),)) -> 171.61084 | O9: =++SUMIFS('sales data'!L:L,'sales data'!$B:$B,$C9,'sales data'!$F:$F,$D9,'sales data'!$O:$O,"") -> 15178 | P9: =+IF(O9<>0,O9*N9,) -> 2604709.4 | Q9: =+SUMIFS('sales data'!$L:$L,'sales data'!$B:$B,$C9,'sales data'!$F:$F,$D9,'sales data'!$O:$O,"R") -> 0 | R9: =+IF(Q9<>0,Q9*N9,) -> 0 | S9: =SUMIFS('sales data'!$L:$L,'sales data'!$B:$B,$C9,'sales data'!$F:$F,$D9,'sales data'!$O:$O,"N") -> 0 | T9: =+IF(S9<>0,S9*N9,) -> 0 | U9: =SUMIFS('warehouse inventory check'!$N:$N,'warehouse inventory check'!$C:$C,$C9,'warehouse inventory check'!$D:$D,$D9) -> 1 | V9: =+N9 -> 171.61084 | W9: =+IF(U9<>0,U9*N9,) -> 171.61084 | X9: =+I9+K9-P9-R9-W9-T9+M9 -> 3.4995651e-10 | Y9: =+G9+J9+L9-O9-Q9-S9 -> 1 | Z9: =+U9-Y9 -> 0
A10: 5 | C10: 1 | D10: PZ38-14A033-CB | E10: PHEV-E (V710) / (P703) | F10: BUSBAR - Array 3 to 4 | G10: 5760 | H10: 85.283645 | I10: 491233.79 | J10: =SUMIFS('purchase data'!K:K,'purchase data'!$B:$B,$C10,'purchase data'!$F:$F,$D10) -> 1732 | K10: =SUMIFS('purchase data'!M:M,'purchase data'!$B:$B,$C10,'purchase data'!$F:$F,$D10) -> 153469.84 | L10: =SUMIFS(ETC!$G:$G,ETC!$B:$B,$C10,ETC!$E:$E,$D10) -> 0 | M10: =SUMIFS(ETC!$J:$J,ETC!$E:$E,$D10,ETC!$B:$B,$C10) -> 0 | N10: =IF(IFERROR((I10+K10+M10)/(G10+J10+SUMIFS(ETC!$G:$G,ETC!$C:$C,1,ETC!$B:$B,$C10,ETC!$E:$E,$D10)),)=0,H10,IFERROR((I10+K10+M10)/(G10+J10+SUMIFS(ETC!$G:$G,ETC!$C:$C,1,ETC!$B:$B,$C10,ETC!$E:$E,$D10)),)) -> 86.052274 | O10: =++SUMIFS('sales data'!L:L,'sales data'!$B:$B,$C10,'sales data'!$F:$F,$D10,'sales data'!$O:$O,"") -> 6339 | P10: =+IF(O10<>0,O10*N10,) -> 545485.36 | Q10: =+SUMIFS('sales data'!$L:$L,'sales data'!$B:$B,$C10,'sales data'!$F:$F,$D10,'sales data'!$O:$O,"R") -> 0 | R10: =+IF(Q10<>0,Q10*N10,) -> 0 | S10: =SUMIFS('sales data'!$L:$L,'sales data'!$B:$B,$C10,'sales data'!$F:$F,$D10,'sales data'!$O:$O,"N") -> 0 | T10: =+IF(S10<>0,S10*N10,) -> 0 | U10: =SUMIFS('warehouse inventory check'!$N:$N,'warehouse inventory check'!$C:$C,$C10,'warehouse inventory check'!$D:$D,$D10) -> 1153 | V10: =+N10 -> 86.052274 | W10: =+IF(U10<>0,U10*N10,) -> 99218.272 | X10: =+I10+K10-P10-R10-W10-T10+M10 -> 0 | Y10: =+G10+J10+L10-O10-Q10-S10 -> 1153 | Z10: =+U10-Y10 -> 0
A11: 6 | C11: 1 | D11: PZ38-14A033-FE | E11: EV-V4 Test Parts | F11: BUSBAR - Array to Array (Straight)_Insert | G11: 2268 | H11: 444.97411 | I11: 1009201.3 | J11: =SUMIFS('purchase data'!K:K,'purchase data'!$B:$B,$C11,'purchase data'!$F:$F,$D11) -> -324 | K11: =SUMIFS('purchase data'!M:M,'purchase data'!$B:$B,$C11,'purchase data'!$F:$F,$D11) -> -145705.72 | L11: =SUMIFS(ETC!$G:$G,ETC!$B:$B,$C11,ETC!$E:$E,$D11) -> 0 | M11: =SUMIFS(ETC!$J:$J,ETC!$E:$E,$D11,ETC!$B:$B,$C11) -> 0 | N11: =IF(IFERROR((I11+K11+M11)/(G11+J11+SUMIFS(ETC!$G:$G,ETC!$C:$C,1,ETC!$B:$B,$C11,ETC!$E:$E,$D11)),)=0,H11,IFERROR((I11+K11+M11)/(G11+J11+SUMIFS(ETC!$G:$G,ETC!$C:$C,1,ETC!$B:$B,$C11,ETC!$E:$E,$D11)),)) -> 444.18497 | O11: =++SUMIFS('sales data'!L:L,'sales data'!$B:$B,$C11,'sales data'!$F:$F,$D11,'sales data'!$O:$O,"") -> 1944 | P11: =+IF(O11<>0,O11*N11,) -> 863495.58 | Q11: =+SUMIFS('sales data'!$L:$L,'sales data'!$B:$B,$C11,'sales data'!$F:$F,$D11,'sales data'!$O:$O,"R") -> 0 | R11: =+IF(Q11<>0,Q11*N11,) -> 0 | S11: =SUMIFS('sales data'!$L:$L,'sales data'!$B:$B,$C11,'sales data'!$F:$F,$D11,'sales data'!$O:$O,"N") -> 0 | T11: =+IF(S11<>0,S11*N11,) -> 0 | U11: =SUMIFS('warehouse inventory check'!$N:$N,'warehouse inventory check'!$C:$C,$C11,'warehouse inventory check'!$D:$D,$D11) -> 0 | V11: =+N11 -> 444.18497 | W11: =+IF(U11<>0,U11*N11,) -> 0 | X11: =+I11+K11-P11-R11-W11-T11+M11 -> 0 | Y11: =+G11+J11+L11-O11-Q11-S11 -> 0 | Z11: =+U11-Y11 -> 0
A12: 7 | C12: 1 | D12: PZ38-14A033-GD | E12: BEV-E (V710) | F12: BUSBAR - Array to Array (Angled)_Insert | G12: 6804 | H12: 417.17538 | I12: 2838461.3 | J12: =SUMIFS('purchase data'!K:K,'purchase data'!$B:$B,$C12,'purchase data'!$F:$F,$D12) -> -1944 | K12: =SUMIFS('purchase data'!M:M,'purchase data'!$B:$B,$C12,'purchase data'!$F:$F,$D12) -> -818019.65 | L12: =SUMIFS(ETC!$G:$G,ETC!$B:$B,$C12,ETC!$E:$E,$D12) -> 0 | M12: =SUMIFS(ETC!$J:$J,ETC!$E:$E,$D12,ETC!$B:$B,$C12) -> 0 | N12: =IF(IFERROR((I12+K12+M12)/(G12+J12+SUMIFS(ETC!$G:$G,ETC!$C:$C,1,ETC!$B:$B,$C12,ETC!$E:$E,$D12)),)=0,H12,IFERROR((I12+K12+M12)/(G12+J12+SUMIFS(ETC!$G:$G,ETC!$C:$C,1,ETC!$B:$B,$C12,ETC!$E:$E,$D12)),)) -> 415.72874 | O12: =++SUMIFS('sales data'!L:L,'sales data'!$B:$B,$C12,'sales data'!$F:$F,$D12,'sales data'!$O:$O,"") -> 1620 | P12: =+IF(O12<>0,O12*N12,) -> 673480.55 | Q12: =+SUMIFS('sales data'!$L:$L,'sales data'!$B:$B,$C12,'sales data'!$F:$F,$D12,'sales data'!$O:$O,"R") -> 0 | R12: =+IF(Q12<>0,Q12*N12,) -> 0 | S12: =SUMIFS('sales data'!$L:$L,'sales data'!$B:$B,$C12,'sales data'!$F:$F,$D12,'sales data'!$O:$O,"N") -> 0 | T12: =+IF(S12<>0,S12*N12,) -> 0 | U12: =SUMIFS('warehouse inventory check'!$N:$N,'warehouse inventory check'!$C:$C,$C12,'warehouse inventory check'!$D:$D,$D12) -> 3240 | V12: =+N12 -> 415.72874 | W12: =+IF(U12<>0,U12*N12,) -> 1346961.1 | X12: =+I12+K12-P12-R12-W12-T12+M12 -> 2.3283064e-10 | Y12: =+G12+J12+L12-O12-Q12-S12 -> 3240 | Z12: =+U12-Y12 -> 0
A13: 8 | C13: 1 | D13: PZ38-14A033-HF | E13: BEV-E (V710) | F13: BUSBAR - Array4 to Array 5_Insert | G13: 1296 | H13: 493.94743 | I13: 640155.87 | J13: =SUMIFS('purchase data'!K:K,'purchase data'!$B:$B,$C13,'purchase data'!$F:$F,$D13) -> 864 | K13: =SUMIFS('purchase data'!M:M,'purchase data'!$B:$B,$C13,'purchase data'!$F:$F,$D13) -> 436860.22 | L13: =SUMIFS(ETC!$G:$G,ETC!$B:$B,$C13,ETC!$E:$E,$D13) -> 0 | M13: =SUMIFS(ETC!$J:$J,ETC!$E:$E,$D13,ETC!$B:$B,$C13) -> 0 | N13: =IF(IFERROR((I13+K13+M13)/(G13+J13+SUMIFS(ETC!$G:$G,ETC!$C:$C,1,ETC!$B:$B,$C13,ETC!$E:$E,$D13)),)=0,H13,IFERROR((I13+K13+M13)/(G13+J13+SUMIFS(ETC!$G:$G,ETC!$C:$C,1,ETC!$B:$B,$C13,ETC!$E:$E,$D13)),)) -> 498.61856 | O13: =++SUMIFS('sales data'!L:L,'sales data'!$B:$B,$C13,'sales data'!$F:$F,$D13,'sales data'!$O:$O,"") -> 2160 | P13: =+IF(O13<>0,O13*N13,) -> 1077016.1 | Q13: =+SUMIFS('sales data'!$L:$L,'sales data'!$B:$B,$C13,'sales data'!$F:$F,$D13,'sales data'!$O:$O,"R") -> 0 | R13: =+IF(Q13<>0,Q13*N13,) -> 0 | S13: =SUMIFS('sales data'!$L:$L,'sales data'!$B:$B,$C13,'sales data'!$F:$F,$D13,'sales data'!$O:$O,"N") -> 0 | T13: =+IF(S13<>0,S13*N13,) -> 0 | U13: =SUMIFS('warehouse inventory check'!$N:$N,'warehouse inventory check'!$C:$C,$C13,'warehouse inventory check'!$D:$D,$D13) -> 0 | V13: =+N13 -> 498.61856 | W13: =+IF(U13<>0,U13*N13,) -> 0 | X13: =+I13+K13-P13-R13-W13-T13+M13 -> 0 | Y13: =+G13+J13+L13-O13-Q13-S13 -> 0 | Z13: =+U13-Y13 -> 0
A14: 9 | C14: 1 | D14: PZ38-14A033-JD | E14: BEV-E1 | F14: BEV-E1 BUSBAR Array 8 to Array 9 | G14: 0 | H14: 445.10313 | I14: 0 | J14: =SUMIFS('purchase data'!K:K,'purchase data'!$B:$B,$C14,'purchase data'!$F:$F,$D14) -> 280 | K14: =SUMIFS('purchase data'!M:M,'purchase data'!$B:$B,$C14,'purchase data'!$F:$F,$D14) -> 125029.2 | L14: =SUMIFS(ETC!$G:$G,ETC!$B:$B,$C14,ETC!$E:$E,$D14) -> 0 | M14: =SUMIFS(ETC!$J:$J,ETC!$E:$E,$D14,ETC!$B:$B,$C14) -> 0 | N14: =IF(IFERROR((I14+K14+M14)/(G14+J14+SUMIFS(ETC!$G:$G,ETC!$C:$C,1,ETC!$B:$B,$C14,ETC!$E:$E,$D14)),)=0,H14,IFERROR((I14+K14+M14)/(G14+J14+SUMIFS(ETC!$G:$G,ETC!$C:$C,1,ETC!$B:$B,$C14,ETC!$E:$E,$D14)),)) -> 446.53286 | O14: =++SUMIFS('sales data'!L:L,'sales data'!$B:$B,$C14,'sales data'!$F:$F,$D14,'sales data'!$O:$O,"") -> 280 | P14: =+IF(O14<>0,O14*N14,) -> 125029.2 | Q14: =+SUMIFS('sales data'!$L:$L,'sales data'!$B:$B,$C14,'sales data'!$F:$F,$D14,'sales data'!$O:$O,"R") -> 0 | R14: =+IF(Q14<>0,Q14*N14,) -> 0 | S14: =SUMIFS('sales data'!$L:$L,'sales data'!$B:$B,$C14,'sales data'!$F:$F,$D14,'sales data'!$O:$O,"N") -> 0 | T14: =+IF(S14<>0,S14*N14,) -> 0 | U14: =SUMIFS('warehouse inventory check'!$N:$N,'warehouse inventory check'!$C:$C,$C14,'warehouse inventory check'!$D:$D,$D14) -> 0 | V14: =+N14 -> 446.53286 | W14: =+IF(U14<>0,U14*N14,) -> 0 | X14: =+I14+K14-P14-R14-W14-T14+M14 -> 0 | Y14: =+G14+J14+L14-O14-Q14-S14 -> 0 | Z14: =+U14-Y14 -> 0
A15: 10 | C15: 1 | D15: PZ38-14A033-KD | E15: BEV-E (V710) | F15: BUSBAR - Array 1 to Neg BEC_Insert | G15: 648 | H15: 513.57924 | I15: 332799.35 | J15: =SUMIFS('purchase data'!K:K,'purchase data'!$B:$B,$C15,'purchase data'!$F:$F,$D15) -> 864 | K15: =SUMIFS('purchase data'!M:M,'purchase data'!$B:$B,$C15,'purchase data'!$F:$F,$D15) -> 455191.49 | L15: =SUMIFS(ETC!$G:$G,ETC!$B:$B,$C15,ETC!$E:$E,$D15) -> 0 | M15: =SUMIFS(ETC!$J:$J,ETC!$E:$E,$D15,ETC!$B:$B,$C15) -> 0 | N15: =IF(IFERROR((I15+K15+M15)/(G15+J15+SUMIFS(ETC!$G:$G,ETC!$C:$C,1,ETC!$B:$B,$C15,ETC!$E:$E,$D15)),)=0,H15,IFERROR((I15+K15+M15)/(G15+J15+SUMIFS(ETC!$G:$G,ETC!$C:$C,1,ETC!$B:$B,$C15,ETC!$E:$E,$D15)),)) -> 521.15796 | O15: =++SUMIFS('sales data'!L:L,'sales data'!$B:$B,$C15,'sales data'!$F:$F,$D15,'sales data'!$O:$O,"") -> 1512 | P15: =+IF(O15<>0,O15*N15,) -> 787990.84 | Q15: =+SUMIFS('sales data'!$L:$L,'sales data'!$B:$B,$C15,'sales data'!$F:$F,$D15,'sales data'!$O:$O,"R") -> 0 | R15: =+IF(Q15<>0,Q15*N15,) -> 0 | S15: =SUMIFS('sales data'!$L:$L,'sales data'!$B:$B,$C15,'sales data'!$F:$F,$D15,'sales data'!$O:$O,"N") -> 0 | T15: =+IF(S15<>0,S15*N15,) -> 0 | U15: =SUMIFS('warehouse inventory check'!$N:$N,'warehouse inventory check'!$C:$C,$C15,'warehouse inventory check'!$D:$D,$D15) -> 0 | V15: =+N15 -> 521.15796 | W15: =+IF(U15<>0,U15*N15,) -> 0 | X15: =+I15+K15-P15-R15-W15-T15+M15 -> 0 | Y15: =+G15+J15+L15-O15-Q15-S15 -> 0 | Z15: =+U15-Y15 -> 0
A16: 11 | C16: 1 | D16: PZ38-14A033-LF | E16: BEV-E (V710) | F16: BUSBAR - Array 9 to Pos BEC_Insert | G16: 1152 | H16: 353.53374 | I16: 407270.87 | J16: =SUMIFS('purchase data'!K:K,'purchase data'!$B:$B,$C16,'purchase data'!$F:$F,$D16) -> 864 | K16: =SUMIFS('purchase data'!M:M,'purchase data'!$B:$B,$C16,'purchase data'!$F:$F,$D16) -> 312255.65 | L16: =SUMIFS(ETC!$G:$G,ETC!$B:$B,$C16,ETC!$E:$E,$D16) -> 0 | M16: =SUMIFS(ETC!$J:$J,ETC!$E:$E,$D16,ETC!$B:$B,$C16) -> 0 | N16: =IF(IFERROR((I16+K16+M16)/(G16+J16+SUMIFS(ETC!$G:$G,ETC!$C:$C,1,ETC!$B:$B,$C16,ETC!$E:$E,$D16)),)=0,H16,IFERROR((I16+K16+M16)/(G16+J16+SUMIFS(ETC!$G:$G,ETC!$C:$C,1,ETC!$B:$B,$C16,ETC!$E:$E,$D16)),)) -> 356.908 | O16: =++SUMIFS('sales data'!L:L,'sales data'!$B:$B,$C16,'sales data'!$F:$F,$D16,'sales data'!$O:$O,"") -> 2304 | P16: =+IF(O16<>0,O16*N16,) -> 822316.03 | Q16: =+SUMIFS('sales data'!$L:$L,'sales data'!$B:$B,$C16,'sales data'!$F:$F,$D16,'sales data'!$O:$O,"R") -> 0 | R16: =+IF(Q16<>0,Q16*N16,) -> 0 | S16: =SUMIFS('sales data'!$L:$L,'sales data'!$B:$B,$C16,'sales data'!$F:$F,$D16,'sales data'!$O:$O,"N") -> 0 | T16: =+IF(S16<>0,S16*N16,) -> 0 | U16: =SUMIFS('warehouse inventory check'!$N:$N,'warehouse inventory check'!$C:$C,$C16,'warehouse inventory check'!$D:$D,$D16) -> -288 | V16: =+N16 -> 356.908 | W16: =+IF(U16<>0,U16*N16,) -> -102789.5 | X16: =+I16+K16-P16-R16-W16-T16+M16 -> 0 | Y16: =+G16+J16+L16-O16-Q16-S16 -> -288 | Z16: =+U16-Y16 -> 0 | AA16: Nursan’s late invoice.
A17: 12 | C17: 1 | D17: PZ38-14A033-MC | E17: BEV-E (V710) | F17: BUSBAR - Pos BEC to DCFC_Protector | G17: 0 | H17: 675.68454 | I17: 0 | J17: =SUMIFS('purchase data'!K:K,'purchase data'!$B:$B,$C17,'purchase data'!$F:$F,$D17) -> 1520 | K17: =SUMIFS('purchase data'!M:M,'purchase data'!$B:$B,$C17,'purchase data'!$F:$F,$D17) -> 1043213.1 | L17: =SUMIFS(ETC!$G:$G,ETC!$B:$B,$C17,ETC!$E:$E,$D17) -> 0 | M17: =SUMIFS(ETC!$J:$J,ETC!$E:$E,$D17,ETC!$B:$B,$C17) -> 0 | N17: =IF(IFERROR((I17+K17+M17)/(G17+J17+SUMIFS(ETC!$G:$G,ETC!$C:$C,1,ETC!$B:$B,$C17,ETC!$E:$E,$D17)),)=0,H17,IFERROR((I17+K17+M17)/(G17+J17+SUMIFS(ETC!$G:$G,ETC!$C:$C,1,ETC!$B:$B,$C17,ETC!$E:$E,$D17)),)) -> 686.32442 | O17: =++SUMIFS('sales data'!L:L,'sales data'!$B:$B,$C17,'sales data'!$F:$F,$D17,'sales data'!$O:$O,"") -> 2080 | P17: =+IF(O17<>0,O17*N17,) -> 1427554.8 | Q17: =+SUMIFS('sales data'!$L:$L,'sales data'!$B:$B,$C17,'sales data'!$F:$F,$D17,'sales data'!$O:$O,"R") -> 0 | R17: =+IF(Q17<>0,Q17*N17,) -> 0 | S17: =SUMIFS('sales data'!$L:$L,'sales data'!$B:$B,$C17,'sales data'!$F:$F,$D17,'sales data'!$O:$O,"N") -> 0 | T17: =+IF(S17<>0,S17*N17,) -> 0 | U17: =SUMIFS('warehouse inventory check'!$N:$N,'warehouse inventory check'!$C:$C,$C17,'warehouse inventory check'!$D:$D,$D17) -> -560 | V17: =+N17 -> 686.32442 | W17: =+IF(U17<>0,U17*N17,) -> -384341.68 | X17: =+I17+K17-P17-R17-W17-T17+M17 -> 0 | Y17: =+G17+J17+L17-O17-Q17-S17 -> -560 | Z17: =+U17-Y17 -> 0 | AA17: Nursan’s late invoice.
A18: 13 | C18: 1 | D18: PZ38-14A033-NB | E18: BEV-E (V710) | F18: BUSBAR - Neg BEC to DCFC_Protector | G18: 1080 | H18: 440.80508 | I18: 476069.49 | J18: =SUMIFS('purchase data'!K:K,'purchase data'!$B:$B,$C18,'purchase data'!$F:$F,$D18) -> 864 | K18: =SUMIFS('purchase data'!M:M,'purchase data'!$B:$B,$C18,'purchase data'!$F:$F,$D18) -> 388673.86 | L18: =SUMIFS(ETC!$G:$G,ETC!$B:$B,$C18,ETC!$E:$E,$D18) -> 0 | M18: =SUMIFS(ETC!$J:$J,ETC!$E:$E,$D18,ETC!$B:$B,$C18) -> 0 | N18: =IF(IFERROR((I18+K18+M18)/(G18+J18+SUMIFS(ETC!$G:$G,ETC!$C:$C,1,ETC!$B:$B,$C18,ETC!$E:$E,$D18)),)=0,H18,IFERROR((I18+K18+M18)/(G18+J18+SUMIFS(ETC!$G:$G,ETC!$C:$C,1,ETC!$B:$B,$C18,ETC!$E:$E,$D18)),)) -> 444.82682 | O18: =++SUMIFS('sales data'!L:L,'sales data'!$B:$B,$C18,'sales data'!$F:$F,$D18,'sales data'!$O:$O,"") -> 1944 | P18: =+IF(O18<>0,O18*N18,) -> 864743.35 | Q18: =+SUMIFS('sales data'!$L:$L,'sales data'!$B:$B,$C18,'sales data'!$F:$F,$D18,'sales data'!$O:$O,"R") -> 0 | R18: =+IF(Q18<>0,Q18*N18,) -> 0 | S18: =SUMIFS('sales data'!$L:$L,'sales data'!$B:$B,$C18,'sales data'!$F:$F,$D18,'sales data'!$O:$O,"N") -> 0 | T18: =+IF(S18<>0,S18*N18,) -> 0 | U18: =SUMIFS('warehouse inventory check'!$N:$N,'warehouse inventory check'!$C:$C,$C18,'warehouse inventory check'!$D:$D,$D18) -> 0 | V18: =+N18 -> 444.82682 | W18: =+IF(U18<>0,U18*N18,) -> 0 | X18: =+I18+K18-P18-R18-W18-T18+M18 -> 0 | Y18: =+G18+J18+L18-O18-Q18-S18 -> 0 | Z18: =+U18-Y18 -> 0
A19: 14 | C19: 1 | D19: PZ38-14A033-PC | E19: BEV-E (V710) | F19: BUSBAR - CIRCUIT BREAKER_A_Insert | G19: 648 | H19: 388.43999 | I19: 251709.11 | J19: =SUMIFS('purchase data'!K:K,'purchase data'!$B:$B,$C19,'purchase data'!$F:$F,$D19) -> 18 | K19: =SUMIFS('purchase data'!M:M,'purchase data'!$B:$B,$C19,'purchase data'!$F:$F,$D19) -> 7147.64 | L19: =SUMIFS(ETC!$G:$G,ETC!$B:$B,$C19,ETC!$E:$E,$D19) -> 0 | M19: =SUMIFS(ETC!$J:$J,ETC!$E:$E,$D19,ETC!$B:$B,$C19) -> 0 | N19: =IF(IFERROR((I19+K19+M19)/(G19+J19+SUMIFS(ETC!$G:$G,ETC!$C:$C,1,ETC!$B:$B,$C19,ETC!$E:$E,$D19)),)=0,H19,IFERROR((I19+K19+M19)/(G19+J19+SUMIFS(ETC!$G:$G,ETC!$C:$C,1,ETC!$B:$B,$C19,ETC!$E:$E,$D19)),)) -> 388.6738 | O19: =++SUMIFS('sales data'!L:L,'sales data'!$B:$B,$C19,'sales data'!$F:$F,$D19,'sales data'!$O:$O,"") -> 666 | P19: =+IF(O19<>0,O19*N19,) -> 258856.75 | Q19: =+SUMIFS('sales data'!$L:$L,'sales data'!$B:$B,$C19,'sales data'!$F:$F,$D19,'sales data'!$O:$O,"R") -> 0 | R19: =+IF(Q19<>0,Q19*N19,) -> 0 | S19: =SUMIFS('sales data'!$L:$L,'sales data'!$B:$B,$C19,'sales data'!$F:$F,$D19,'sales data'!$O:$O,"N") -> 0 | T19: =+IF(S19<>0,S19*N19,) -> 0 | U19: =SUMIFS('warehouse inventory check'!$N:$N,'warehouse inventory check'!$C:$C,$C19,'warehouse inventory check'!$D:$D,$D19) -> 0 | V19: =+N19 -> 388.6738 | W19: =+IF(U19<>0,U19*N19,) -> 0 | X19: =+I19+K19-P19-R19-W19-T19+M19 -> 0 | Y19: =+G19+J19+L19-O19-Q19-S19 -> 0 | Z19: =+U19-Y19 -> 0
A20: 15 | C20: 1 | D20: PZ38-14A033-RC | E20: BEV-E (V710) | F20: BUSBAR - CIRCUIT BREAKER_B_Insert | G20: 864 | H20: 412.04446 | I20: 356006.42 | J20: =SUMIFS('purchase data'!K:K,'purchase data'!$B:$B,$C20,'purchase data'!$F:$F,$D20) -> 18 | K20: =SUMIFS('purchase data'!M:M,'purchase data'!$B:$B,$C20,'purchase data'!$F:$F,$D20) -> 7573.97 | L20: =SUMIFS(ETC!$G:$G,ETC!$B:$B,$C20,ETC!$E:$E,$D20) -> 0 | M20: =SUMIFS(ETC!$J:$J,ETC!$E:$E,$D20,ETC!$B:$B,$C20) -> 0 | N20: =IF(IFERROR((I20+K20+M20)/(G20+J20+SUMIFS(ETC!$G:$G,ETC!$C:$C,1,ETC!$B:$B,$C20,ETC!$E:$E,$D20)),)=0,H20,IFERROR((I20+K20+M20)/(G20+J20+SUMIFS(ETC!$G:$G,ETC!$C:$C,1,ETC!$B:$B,$C20,ETC!$E:$E,$D20)),)) -> 412.22266 | O20: =++SUMIFS('sales data'!L:L,'sales data'!$B:$B,$C20,'sales data'!$F:$F,$D20,'sales data'!$O:$O,"") -> 882 | P20: =+IF(O20<>0,O20*N20,) -> 363580.39 | Q20: =+SUMIFS('sales data'!$L:$L,'sales data'!$B:$B,$C20,'sales data'!$F:$F,$D20,'sales data'!$O:$O,"R") -> 0 | R20: =+IF(Q20<>0,Q20*N20,) -> 0 | S20: =SUMIFS('sales data'!$L:$L,'sales data'!$B:$B,$C20,'sales data'!$F:$F,$D20,'sales data'!$O:$O,"N") -> 0 | T20: =+IF(S20<>0,S20*N20,) -> 0 | U20: =SUMIFS('warehouse inventory check'!$N:$N,'warehouse inventory check'!$C:$C,$C20,'warehouse inventory check'!$D:$D,$D20) -> 0 | V20: =+N20 -> 412.22266 | W20: =+IF(U20<>0,U20*N20,) -> 0 | X20: =+I20+K20-P20-R20-W20-T20+M20 -> 0 | Y20: =+G20+J20+L20-O20-Q20-S20 -> 0 | Z20: =+U20-Y20 -> 0
A21: 16 | C21: 1 | D21: PZ38-14B252-AB | E21: PHEV-E (V710) / (P703) | F21: Jumper | G21: 5824 | H21: 772.24904 | I21: 4497578.4 | J21: =SUMIFS('purchase data'!K:K,'purchase data'!$B:$B,$C21,'purchase data'!$F:$F,$D21) -> 1575 | K21: =SUMIFS('purchase data'!M:M,'purchase data'!$B:$B,$C21,'purchase data'!$F:$F,$D21) -> 1265260.1 | L21: =SUMIFS(ETC!$G:$G,ETC!$B:$B,$C21,ETC!$E:$E,$D21) -> 0 | M21: =SUMIFS(ETC!$J:$J,ETC!$E:$E,$D21,ETC!$B:$B,$C21) -> 0 | N21: =IF(IFERROR((I21+K21+M21)/(G21+J21+SUMIFS(ETC!$G:$G,ETC!$C:$C,1,ETC!$B:$B,$C21,ETC!$E:$E,$D21)),)=0,H21,IFERROR((I21+K21+M21)/(G21+J21+SUMIFS(ETC!$G:$G,ETC!$C:$C,1,ETC!$B:$B,$C21,ETC!$E:$E,$D21)),)) -> 778.86722 | O21: =++SUMIFS('sales data'!L:L,'sales data'!$B:$B,$C21,'sales data'!$F:$F,$D21,'sales data'!$O:$O,"") -> 5980 | P21: =+IF(O21<>0,O21*N21,) -> 4657626 | Q21: =+SUMIFS('sales data'!$L:$L,'sales data'!$B:$B,$C21,'sales data'!$F:$F,$D21,'sales data'!$O:$O,"R") -> 0 | R21: =+IF(Q21<>0,Q21*N21,) -> 0 | S21: =SUMIFS('sales data'!$L:$L,'sales data'!$B:$B,$C21,'sales data'!$F:$F,$D21,'sales data'!$O:$O,"N") -> 0 | T21: =+IF(S21<>0,S21*N21,) -> 0 | U21: =SUMIFS('warehouse inventory check'!$N:$N,'warehouse inventory check'!$C:$C,$C21,'warehouse inventory check'!$D:$D,$D21) -> 1419 | V21: =+N21 -> 778.86722 | W21: =+IF(U21<>0,U21*N21,) -> 1105212.6 | X21: =+I21+K21-P21-R21-W21-T21+M21 -> 0 | Y21: =+G21+J21+L21-O21-Q21-S21 -> 1419 | Z21: =+U21-Y21 -> 0
A22: 17 | C22: 1 | D22: PZ38-14B680-AD | E22: BEV-E (V710) | F22: PDU | G22: 489 | H22: 1066.6101 | I22: 521572.36 | J22: =SUMIFS('purchase data'!K:K,'purchase data'!$B:$B,$C22,'purchase data'!$F:$F,$D22) -> 240 | K22: =SUMIFS('purchase data'!M:M,'purchase data'!$B:$B,$C22,'purchase data'!$F:$F,$D22) -> 259807.44 | L22: =SUMIFS(ETC!$G:$G,ETC!$B:$B,$C22,ETC!$E:$E,$D22) -> 0 | M22: =SUMIFS(ETC!$J:$J,ETC!$E:$E,$D22,ETC!$B:$B,$C22) -> 0 | N22: =IF(IFERROR((I22+K22+M22)/(G22+J22+SUMIFS(ETC!$G:$G,ETC!$C:$C,1,ETC!$B:$B,$C22,ETC!$E:$E,$D22)),)=0,H22,IFERROR((I22+K22+M22)/(G22+J22+SUMIFS(ETC!$G:$G,ETC!$C:$C,1,ETC!$B:$B,$C22,ETC!$E:$E,$D22)),)) -> 1071.8516 | O22: =++SUMIFS('sales data'!L:L,'sales data'!$B:$B,$C22,'sales data'!$F:$F,$D22,'sales data'!$O:$O,"") -> 723 | P22: =+IF(O22<>0,O22*N22,) -> 774948.69 | Q22: =+SUMIFS('sales data'!$L:$L,'sales data'!$B:$B,$C22,'sales data'!$F:$F,$D22,'sales data'!$O:$O,"R") -> 0 | R22: =+IF(Q22<>0,Q22*N22,) -> 0 | S22: =SUMIFS('sales data'!$L:$L,'sales data'!$B:$B,$C22,'sales data'!$F:$F,$D22,'sales data'!$O:$O,"N") -> 0 | T22: =+IF(S22<>0,S22*N22,) -> 0 | U22: =SUMIFS('warehouse inventory check'!$N:$N,'warehouse inventory check'!$C:$C,$C22,'warehouse inventory check'!$D:$D,$D22) -> 6 | V22: =+N22 -> 1071.8516 | W22: =+IF(U22<>0,U22*N22,) -> 6431.1095 | X22: =+I22+K22-P22-R22-W22-T22+M22 -> -3.8198777e-11 | Y22: =+G22+J22+L22-O22-Q22-S22 -> 6 | Z22: =+U22-Y22 -> 0
A23: 18 | C23: 1 | D23: S2X8-14A033-AC | E23: BEV-M | F23: BUS BAR ASY – POS BEC TO ARRAY 6 POS | G23: 7 | H23: 402.59586 | I23: 2818.171 | J23: =SUMIFS('purchase data'!K:K,'purchase data'!$B:$B,$C23,'purchase data'!$F:$F,$D23) -> 3600 | K23: =SUMIFS('purchase data'!M:M,'purchase data'!$B:$B,$C23,'purchase data'!$F:$F,$D23) -> 1480018.7 | L23: =SUMIFS(ETC!$G:$G,ETC!$B:$B,$C23,ETC!$E:$E,$D23) -> 0 | M23: =SUMIFS(ETC!$J:$J,ETC!$E:$E,$D23,ETC!$B:$B,$C23) -> 0 | N23: =IF(IFERROR((I23+K23+M23)/(G23+J23+SUMIFS(ETC!$G:$G,ETC!$C:$C,1,ETC!$B:$B,$C23,ETC!$E:$E,$D23)),)=0,H23,IFERROR((I23+K23+M23)/(G23+J23+SUMIFS(ETC!$G:$G,ETC!$C:$C,1,ETC!$B:$B,$C23,ETC!$E:$E,$D23)),)) -> 411.09977 | O23: =++SUMIFS('sales data'!L:L,'sales data'!$B:$B,$C23,'sales data'!$F:$F,$D23,'sales data'!$O:$O,"") -> 2880 | P23: =+IF(O23<>0,O23*N23,) -> 1183967.4 | Q23: =+SUMIFS('sales data'!$L:$L,'sales data'!$B:$B,$C23,'sales data'!$F:$F,$D23,'sales data'!$O:$O,"R") -> 0 | R23: =+IF(Q23<>0,Q23*N23,) -> 0 | S23: =SUMIFS('sales data'!$L:$L,'sales data'!$B:$B,$C23,'sales data'!$F:$F,$D23,'sales data'!$O:$O,"N") -> 0 | T23: =+IF(S23<>0,S23*N23,) -> 0 | U23: =SUMIFS('warehouse inventory check'!$N:$N,'warehouse inventory check'!$C:$C,$C23,'warehouse inventory check'!$D:$D,$D23) -> 727 | V23: =+N23 -> 411.09977 | W23: =+IF(U23<>0,U23*N23,) -> 298869.54 | X23: =+I23+K23-P23-R23-W23-T23+M23 -> 5.8207661e-11 | Y23: =+G23+J23+L23-O23-Q23-S23 -> 727 | Z23: =+U23-Y23 -> 0 | AA23: Late Customs Clearance Date
A24: 19 | C24: 1 | D24: S2X8-14A033-BC | E24: BEV-M | F24: BUS BAR ASY - COMMON BUSBAR ARRAY 6 TO 4 | G24: 7 | H24: 405.55066 | I24: 2838.8546 | J24: =SUMIFS('purchase data'!K:K,'purchase data'!$B:$B,$C24,'purchase data'!$F:$F,$D24) -> 7200 | K24: =SUMIFS('purchase data'!M:M,'purchase data'!$B:$B,$C24,'purchase data'!$F:$F,$D24) -> 2981963.6 | L24: =SUMIFS(ETC!$G:$G,ETC!$B:$B,$C24,ETC!$E:$E,$D24) -> 0 | M24: =SUMIFS(ETC!$J:$J,ETC!$E:$E,$D24,ETC!$B:$B,$C24) -> 0 | N24: =IF(IFERROR((I24+K24+M24)/(G24+J24+SUMIFS(ETC!$G:$G,ETC!$C:$C,1,ETC!$B:$B,$C24,ETC!$E:$E,$D24)),)=0,H24,IFERROR((I24+K24+M24)/(G24+J24+SUMIFS(ETC!$G:$G,ETC!$C:$C,1,ETC!$B:$B,$C24,ETC!$E:$E,$D24)),)) -> 414.15325 | O24: =++SUMIFS('sales data'!L:L,'sales data'!$B:$B,$C24,'sales data'!$F:$F,$D24,'sales data'!$O:$O,"") -> 5760 | P24: =+IF(O24<>0,O24*N24,) -> 2385522.7 | Q24: =+SUMIFS('sales data'!$L:$L,'sales data'!$B:$B,$C24,'sales data'!$F:$F,$D24,'sales data'!$O:$O,"R") -> 0 | R24: =+IF(Q24<>0,Q24*N24,) -> 0 | S24: =SUMIFS('sales data'!$L:$L,'sales data'!$B:$B,$C24,'sales data'!$F:$F,$D24,'sales data'!$O:$O,"N") -> 0 | T24: =+IF(S24<>0,S24*N24,) -> 0 | U24: =SUMIFS('warehouse inventory check'!$N:$N,'warehouse inventory check'!$C:$C,$C24,'warehouse inventory check'!$D:$D,$D24) -> 1447 | V24: =+N24 -> 414.15325 | W24: =+IF(U24<>0,U24*N24,) -> 599279.76 | X24: =+I24+K24-P24-R24-W24-T24+M24 -> 1.1641532e-10 | Y24: =+G24+J24+L24-O24-Q24-S24 -> 1447 | Z24: =+U24-Y24 -> 0 | AA24: Late Customs Clearance Date
A25: 20 | C25: 1 | D25: S2X8-14A033-CC | E25: BEV-M | F25: BUS BAR ASY – ARRAY 4 NEG TO CIRCUIT BREAKER | G25: 5 | H25: 267.94828 | I25: 1339.7414 | J25: =SUMIFS('purchase data'!K:K,'purchase data'!$B:$B,$C25,'purchase data'!$F:$F,$D25) -> 3600 | K25: =SUMIFS('purchase data'!M:M,'purchase data'!$B:$B,$C25,'purchase data'!$F:$F,$D25) -> 984851.96 | L25: =SUMIFS(ETC!$G:$G,ETC!$B:$B,$C25,ETC!$E:$E,$D25) -> 0 | M25: =SUMIFS(ETC!$J:$J,ETC!$E:$E,$D25,ETC!$B:$B,$C25) -> 0 | N25: =IF(IFERROR((I25+K25+M25)/(G25+J25+SUMIFS(ETC!$G:$G,ETC!$C:$C,1,ETC!$B:$B,$C25,ETC!$E:$E,$D25)),)=0,H25,IFERROR((I25+K25+M25)/(G25+J25+SUMIFS(ETC!$G:$G,ETC!$C:$C,1,ETC!$B:$B,$C25,ETC!$E:$E,$D25)),)) -> 273.56219 | O25: =++SUMIFS('sales data'!L:L,'sales data'!$B:$B,$C25,'sales data'!$F:$F,$D25,'sales data'!$O:$O,"") -> 2880 | P25: =+IF(O25<>0,O25*N25,) -> 787859.11 | Q25: =+SUMIFS('sales data'!$L:$L,'sales data'!$B:$B,$C25,'sales data'!$F:$F,$D25,'sales data'!$O:$O,"R") -> 0 | R25: =+IF(Q25<>0,Q25*N25,) -> 0 | S25: =SUMIFS('sales data'!$L:$L,'sales data'!$B:$B,$C25,'sales data'!$F:$F,$D25,'sales data'!$O:$O,"N") -> 0 | T25: =+IF(S25<>0,S25*N25,) -> 0 | U25: =SUMIFS('warehouse inventory check'!$N:$N,'warehouse inventory check'!$C:$C,$C25,'warehouse inventory check'!$D:$D,$D25) -> 725 | V25: =+N25 -> 273.56219 | W25: =+IF(U25<>0,U25*N25,) -> 198332.59 | X25: =+I25+K25-P25-R25-W25-T25+M25 -> 8.7311491e-11 | Y25: =+G25+J25+L25-O25-Q25-S25 -> 725 | Z25: =+U25-Y25 -> 0 | AA25: Late Customs Clearance Date
A26: 21 | C26: 1 | D26: S2X8-14A033-DC | E26: BEV-M | F26: BUS BAR ASY – CIRCUIT BREAKER TO ARRAY 3 POS | G26: 5 | H26: 449.33661 | I26: 2246.6831 | J26: =SUMIFS('purchase data'!K:K,'purchase data'!$B:$B,$C26,'purchase data'!$F:$F,$D26) -> 3600 | K26: =SUMIFS('purchase data'!M:M,'purchase data'!$B:$B,$C26,'purchase data'!$F:$F,$D26) -> 1653601.2 | L26: =SUMIFS(ETC!$G:$G,ETC!$B:$B,$C26,ETC!$E:$E,$D26) -> 0 | M26: =SUMIFS(ETC!$J:$J,ETC!$E:$E,$D26,ETC!$B:$B,$C26) -> 0 | N26: =IF(IFERROR((I26+K26+M26)/(G26+J26+SUMIFS(ETC!$G:$G,ETC!$C:$C,1,ETC!$B:$B,$C26,ETC!$E:$E,$D26)),)=0,H26,IFERROR((I26+K26+M26)/(G26+J26+SUMIFS(ETC!$G:$G,ETC!$C:$C,1,ETC!$B:$B,$C26,ETC!$E:$E,$D26)),)) -> 459.31979 | O26: =++SUMIFS('sales data'!L:L,'sales data'!$B:$B,$C26,'sales data'!$F:$F,$D26,'sales data'!$O:$O,"") -> 2880 | P26: =+IF(O26<>0,O26*N26,) -> 1322841 | Q26: =+SUMIFS('sales data'!$L:$L,'sales data'!$B:$B,$C26,'sales data'!$F:$F,$D26,'sales data'!$O:$O,"R") -> 0 | R26: =+IF(Q26<>0,Q26*N26,) -> 0 | S26: =SUMIFS('sales data'!$L:$L,'sales data'!$B:$B,$C26,'sales data'!$F:$F,$D26,'sales data'!$O:$O,"N") -> 0 | T26: =+IF(S26<>0,S26*N26,) -> 0 | U26: =SUMIFS('warehouse inventory check'!$N:$N,'warehouse inventory check'!$C:$C,$C26,'warehouse inventory check'!$D:$D,$D26) -> 725 | V26: =+N26 -> 459.31979 | W26: =+IF(U26<>0,U26*N26,) -> 333006.85 | X26: =+I26+K26-P26-R26-W26-T26+M26 -> 1.1641532e-10 | Y26: =+G26+J26+L26-O26-Q26-S26 -> 725 | Z26: =+U26-Y26 -> 0 | AA26: Late Customs Clearance Date
A27: 22 | C27: 1 | D27: S2X8-14A033-EC | E27: BEV-M | F27: BUS BAR ASY – COMMON BUSBAR ARRAY 3 TO 1 | G27: 7 | H27: 442.65036 | I27: 3098.5525 | J27: =SUMIFS('purchase data'!K:K,'purchase data'!$B:$B,$C27,'purchase data'!$F:$F,$D27) -> 7200 | K27: =SUMIFS('purchase data'!M:M,'purchase data'!$B:$B,$C27,'purchase data'!$F:$F,$D27) -> 3252386.8 | L27: =SUMIFS(ETC!$G:$G,ETC!$B:$B,$C27,ETC!$E:$E,$D27) -> 0 | M27: =SUMIFS(ETC!$J:$J,ETC!$E:$E,$D27,ETC!$B:$B,$C27) -> 0 | N27: =IF(IFERROR((I27+K27+M27)/(G27+J27+SUMIFS(ETC!$G:$G,ETC!$C:$C,1,ETC!$B:$B,$C27,ETC!$E:$E,$D27)),)=0,H27,IFERROR((I27+K27+M27)/(G27+J27+SUMIFS(ETC!$G:$G,ETC!$C:$C,1,ETC!$B:$B,$C27,ETC!$E:$E,$D27)),)) -> 451.71158 | O27: =++SUMIFS('sales data'!L:L,'sales data'!$B:$B,$C27,'sales data'!$F:$F,$D27,'sales data'!$O:$O,"") -> 5760 | P27: =+IF(O27<>0,O27*N27,) -> 2601858.7 | Q27: =+SUMIFS('sales data'!$L:$L,'sales data'!$B:$B,$C27,'sales data'!$F:$F,$D27,'sales data'!$O:$O,"R") -> 0 | R27: =+IF(Q27<>0,Q27*N27,) -> 0 | S27: =SUMIFS('sales data'!$L:$L,'sales data'!$B:$B,$C27,'sales data'!$F:$F,$D27,'sales data'!$O:$O,"N") -> 0 | T27: =+IF(S27<>0,S27*N27,) -> 0 | U27: =SUMIFS('warehouse inventory check'!$N:$N,'warehouse inventory check'!$C:$C,$C27,'warehouse inventory check'!$D:$D,$D27) -> 1447 | V27: =+N27 -> 451.71158 | W27: =+IF(U27<>0,U27*N27,) -> 653626.66 | X27: =+I27+K27-P27-R27-W27-T27+M27 -> -1.1641532e-10 | Y27: =+G27+J27+L27-O27-Q27-S27 -> 1447 | Z27: =+U27-Y27 -> 0 | AA27: Late Customs Clearance Date
A28: 23 | C28: 1 | D28: S2X8-14A033-GC | E28: BEV-M | F28: BUS BAR ASY – ARRAY 1 NEG TO NEG BEC | G28: 7 | H28: 301.94661 | I28: 2113.6263 | J28: =SUMIFS('purchase data'!K:K,'purchase data'!$B:$B,$C28,'purchase data'!$F:$F,$D28) -> 3600 | K28: =SUMIFS('purchase data'!M:M,'purchase data'!$B:$B,$C28,'purchase data'!$F:$F,$D28) -> 1109100.4 | L28: =SUMIFS(ETC!$G:$G,ETC!$B:$B,$C28,ETC!$E:$E,$D28) -> 0 | M28: =SUMIFS(ETC!$J:$J,ETC!$E:$E,$D28,ETC!$B:$B,$C28) -> 0 | N28: =IF(IFERROR((I28+K28+M28)/(G28+J28+SUMIFS(ETC!$G:$G,ETC!$C:$C,1,ETC!$B:$B,$C28,ETC!$E:$E,$D28)),)=0,H28,IFERROR((I28+K28+M28)/(G28+J28+SUMIFS(ETC!$G:$G,ETC!$C:$C,1,ETC!$B:$B,$C28,ETC!$E:$E,$D28)),)) -> 308.07155 | O28: =++SUMIFS('sales data'!L:L,'sales data'!$B:$B,$C28,'sales data'!$F:$F,$D28,'sales data'!$O:$O,"") -> 2880 | P28: =+IF(O28<>0,O28*N28,) -> 887246.06 | Q28: =+SUMIFS('sales data'!$L:$L,'sales data'!$B:$B,$C28,'sales data'!$F:$F,$D28,'sales data'!$O:$O,"R") -> 0 | R28: =+IF(Q28<>0,Q28*N28,) -> 0 | S28: =SUMIFS('sales data'!$L:$L,'sales data'!$B:$B,$C28,'sales data'!$F:$F,$D28,'sales data'!$O:$O,"N") -> 0 | T28: =+IF(S28<>0,S28*N28,) -> 0 | U28: =SUMIFS('warehouse inventory check'!$N:$N,'warehouse inventory check'!$C:$C,$C28,'warehouse inventory check'!$D:$D,$D28) -> 727 | V28: =+N28 -> 308.07155 | W28: =+IF(U28<>0,U28*N28,) -> 223968.01 | X28: =+I28+K28-P28-R28-W28-T28+M28 -> 5.8207661e-11 | Y28: =+G28+J28+L28-O28-Q28-S28 -> 727 | Z28: =+U28-Y28 -> 0 | AA28: Late Customs Clearance Date
A29: 24 | C29: 1 | D29: S2X8-14A033-HD | E29: BEV-M | F29: BUS BAR ASY – POS BEC TO DCFC POS | G29: 0 | H29: 455.50022 | I29: 0 | J29: =SUMIFS('purchase data'!K:K,'purchase data'!$B:$B,$C29,'purchase data'!$F:$F,$D29) -> 3600 | K29: =SUMIFS('purchase data'!M:M,'purchase data'!$B:$B,$C29,'purchase data'!$F:$F,$D29) -> 1671873 | L29: =SUMIFS(ETC!$G:$G,ETC!$B:$B,$C29,ETC!$E:$E,$D29) -> 0 | M29: =SUMIFS(ETC!$J:$J,ETC!$E:$E,$D29,ETC!$B:$B,$C29) -> 0 | N29: =IF(IFERROR((I29+K29+M29)/(G29+J29+SUMIFS(ETC!$G:$G,ETC!$C:$C,1,ETC!$B:$B,$C29,ETC!$E:$E,$D29)),)=0,H29,IFERROR((I29+K29+M29)/(G29+J29+SUMIFS(ETC!$G:$G,ETC!$C:$C,1,ETC!$B:$B,$C29,ETC!$E:$E,$D29)),)) -> 464.40916 | O29: =++SUMIFS('sales data'!L:L,'sales data'!$B:$B,$C29,'sales data'!$F:$F,$D29,'sales data'!$O:$O,"") -> 2880 | P29: =+IF(O29<>0,O29*N29,) -> 1337498.4 | Q29: =+SUMIFS('sales data'!$L:$L,'sales data'!$B:$B,$C29,'sales data'!$F:$F,$D29,'sales data'!$O:$O,"R") -> 0 | R29: =+IF(Q29<>0,Q29*N29,) -> 0 | S29: =SUMIFS('sales data'!$L:$L,'sales data'!$B:$B,$C29,'sales data'!$F:$F,$D29,'sales data'!$O:$O,"N") -> 0 | T29: =+IF(S29<>0,S29*N29,) -> 0 | U29: =SUMIFS('warehouse inventory check'!$N:$N,'warehouse inventory check'!$C:$C,$C29,'warehouse inventory check'!$D:$D,$D29) -> 720 | V29: =+N29 -> 464.40916 | W29: =+IF(U29<>0,U29*N29,) -> 334374.6 | X29: =+I29+K29-P29-R29-W29-T29+M29 -> 5.8207661e-11 | Y29: =+G29+J29+L29-O29-Q29-S29 -> 720 | Z29: =+U29-Y29 -> 0 | AA29: Late Customs Clearance Date
A30: 25 | C30: 1 | D30: S2X8-14A033-JD | E30: BEV-M | F30: BUS BAR ASY – NEG BEC TO DCFC NEG | G30: 0 | H30: 386.24208 | I30: 0 | J30: =SUMIFS('purchase data'!K:K,'purchase data'!$B:$B,$C30,'purchase data'!$F:$F,$D30) -> 3600 | K30: =SUMIFS('purchase data'!M:M,'purchase data'!$B:$B,$C30,'purchase data'!$F:$F,$D30) -> 1417894.5 | L30: =SUMIFS(ETC!$G:$G,ETC!$B:$B,$C30,ETC!$E:$E,$D30) -> 0 | M30: =SUMIFS(ETC!$J:$J,ETC!$E:$E,$D30,ETC!$B:$B,$C30) -> 0 | N30: =IF(IFERROR((I30+K30+M30)/(G30+J30+SUMIFS(ETC!$G:$G,ETC!$C:$C,1,ETC!$B:$B,$C30,ETC!$E:$E,$D30)),)=0,H30,IFERROR((I30+K30+M30)/(G30+J30+SUMIFS(ETC!$G:$G,ETC!$C:$C,1,ETC!$B:$B,$C30,ETC!$E:$E,$D30)),)) -> 393.85958 | O30: =++SUMIFS('sales data'!L:L,'sales data'!$B:$B,$C30,'sales data'!$F:$F,$D30,'sales data'!$O:$O,"") -> 2880 | P30: =+IF(O30<>0,O30*N30,) -> 1134315.6 | Q30: =+SUMIFS('sales data'!$L:$L,'sales data'!$B:$B,$C30,'sales data'!$F:$F,$D30,'sales data'!$O:$O,"R") -> 0 | R30: =+IF(Q30<>0,Q30*N30,) -> 0 | S30: =SUMIFS('sales data'!$L:$L,'sales data'!$B:$B,$C30,'sales data'!$F:$F,$D30,'sales data'!$O:$O,"N") -> 0 | T30: =+IF(S30<>0,S30*N30,) -> 0 | U30: =SUMIFS('warehouse inventory check'!$N:$N,'warehouse inventory check'!$C:$C,$C30,'warehouse inventory check'!$D:$D,$D30) -> 720 | V30: =+N30 -> 393.85958 | W30: =+IF(U30<>0,U30*N30,) -> 283578.89 | X30: =+I30+K30-P30-R30-W30-T30+M30 -> 0 | Y30: =+G30+J30+L30-O30-Q30-S30 -> 720 | Z30: =+U30-Y30 -> 0 | AA30: Late Customs Clearance Date
A31: 26 | C31: 1 | D31: SZ38-10B694-AC | E31: BEV-E2 (V710) | F31: Main Harness | G31: 94 | H31: 1781.5496 | I31: 167465.66 | J31: =SUMIFS('purchase data'!K:K,'purchase data'!$B:$B,$C31,'purchase data'!$F:$F,$D31) -> 0 | K31: =SUMIFS('purchase data'!M:M,'purchase data'!$B:$B,$C31,'purchase data'!$F:$F,$D31) -> 0 | L31: =SUMIFS(ETC!$G:$G,ETC!$B:$B,$C31,ETC!$E:$E,$D31) -> 0 | M31: =SUMIFS(ETC!$J:$J,ETC!$E:$E,$D31,ETC!$B:$B,$C31) -> 0 | N31: =IF(IFERROR((I31+K31+M31)/(G31+J31+SUMIFS(ETC!$G:$G,ETC!$C:$C,1,ETC!$B:$B,$C31,ETC!$E:$E,$D31)),)=0,H31,IFERROR((I31+K31+M31)/(G31+J31+SUMIFS(ETC!$G:$G,ETC!$C:$C,1,ETC!$B:$B,$C31,ETC!$E:$E,$D31)),)) -> 1781.5496 | O31: =++SUMIFS('sales data'!L:L,'sales data'!$B:$B,$C31,'sales data'!$F:$F,$D31,'sales data'!$O:$O,"") -> 0 | P31: =+IF(O31<>0,O31*N31,) -> 0 | Q31: =+SUMIFS('sales data'!$L:$L,'sales data'!$B:$B,$C31,'sales data'!$F:$F,$D31,'sales data'!$O:$O,"R") -> 0 | R31: =+IF(Q31<>0,Q31*N31,) -> 0 | S31: =SUMIFS('sales data'!$L:$L,'sales data'!$B:$B,$C31,'sales data'!$F:$F,$D31,'sales data'!$O:$O,"N") -> 0 | T31: =+IF(S31<>0,S31*N31,) -> 0 | U31: =SUMIFS('warehouse inventory check'!$N:$N,'warehouse inventory check'!$C:$C,$C31,'warehouse inventory check'!$D:$D,$D31) -> 94 | V31: =+N31 -> 1781.5496 | W31: =+IF(U31<>0,U31*N31,) -> 167465.66 | X31: =+I31+K31-P31-R31-W31-T31+M31 -> 0 | Y31: =+G31+J31+L31-O31-Q31-S31 -> 94 | Z31: =+U31-Y31 -> 0
A32: 27 | C32: 1 | D32: SZ38-14A033-AB | E32: BEV-E2 (V710) | F32: BUSBAR - Array 2 to Array3_Insert | G32: 61 | H32: 609.68253 | I32: 37190.635 | J32: =SUMIFS('purchase data'!K:K,'purchase data'!$B:$B,$C32,'purchase data'!$F:$F,$D32) -> 0 | K32: =SUMIFS('purchase data'!M:M,'purchase data'!$B:$B,$C32,'purchase data'!$F:$F,$D32) -> 0 | L32: =SUMIFS(ETC!$G:$G,ETC!$B:$B,$C32,ETC!$E:$E,$D32) -> 0 | M32: =SUMIFS(ETC!$J:$J,ETC!$E:$E,$D32,ETC!$B:$B,$C32) -> 0 | N32: =IF(IFERROR((I32+K32+M32)/(G32+J32+SUMIFS(ETC!$G:$G,ETC!$C:$C,1,ETC!$B:$B,$C32,ETC!$E:$E,$D32)),)=0,H32,IFERROR((I32+K32+M32)/(G32+J32+SUMIFS(ETC!$G:$G,ETC!$C:$C,1,ETC!$B:$B,$C32,ETC!$E:$E,$D32)),)) -> 609.68253 | O32: =++SUMIFS('sales data'!L:L,'sales data'!$B:$B,$C32,'sales data'!$F:$F,$D32,'sales data'!$O:$O,"") -> 0 | P32: =+IF(O32<>0,O32*N32,) -> 0 | Q32: =+SUMIFS('sales data'!$L:$L,'sales data'!$B:$B,$C32,'sales data'!$F:$F,$D32,'sales data'!$O:$O,"R") -> 0 | R32: =+IF(Q32<>0,Q32*N32,) -> 0 | S32: =SUMIFS('sales data'!$L:$L,'sales data'!$B:$B,$C32,'sales data'!$F:$F,$D32,'sales data'!$O:$O,"N") -> 0 | T32: =+IF(S32<>0,S32*N32,) -> 0 | U32: =SUMIFS('warehouse inventory check'!$N:$N,'warehouse inventory check'!$C:$C,$C32,'warehouse inventory check'!$D:$D,$D32) -> 61 | V32: =+N32 -> 609.68253 | W32: =+IF(U32<>0,U32*N32,) -> 37190.635 | X32: =+I32+K32-P32-R32-W32-T32+M32 -> 0 | Y32: =+G32+J32+L32-O32-Q32-S32 -> 61 | Z32: =+U32-Y32 -> 0
A33: 28 | C33: 1 | D33: SZ38-14A033-BB | E33: BEV-E2 (V710) | F33: BUSBAR - Array 6 to Pos BEC_Insert | G33: 61 | H33: 413.75883 | I33: 25239.289 | J33: =SUMIFS('purchase data'!K:K,'purchase data'!$B:$B,$C33,'purchase data'!$F:$F,$D33) -> 0 | K33: =SUMIFS('purchase data'!M:M,'purchase data'!$B:$B,$C33,'purchase data'!$F:$F,$D33) -> 0 | L33: =SUMIFS(ETC!$G:$G,ETC!$B:$B,$C33,ETC!$E:$E,$D33) -> 0 | M33: =SUMIFS(ETC!$J:$J,ETC!$E:$E,$D33,ETC!$B:$B,$C33) -> 0 | N33: =IF(IFERROR((I33+K33+M33)/(G33+J33+SUMIFS(ETC!$G:$G,ETC!$C:$C,1,ETC!$B:$B,$C33,ETC!$E:$E,$D33)),)=0,H33,IFERROR((I33+K33+M33)/(G33+J33+SUMIFS(ETC!$G:$G,ETC!$C:$C,1,ETC!$B:$B,$C33,ETC!$E:$E,$D33)),)) -> 413.75883 | O33: =++SUMIFS('sales data'!L:L,'sales data'!$B:$B,$C33,'sales data'!$F:$F,$D33,'sales data'!$O:$O,"") -> 0 | P33: =+IF(O33<>0,O33*N33,) -> 0 | Q33: =+SUMIFS('sales data'!$L:$L,'sales data'!$B:$B,$C33,'sales data'!$F:$F,$D33,'sales data'!$O:$O,"R") -> 0 | R33: =+IF(Q33<>0,Q33*N33,) -> 0 | S33: =SUMIFS('sales data'!$L:$L,'sales data'!$B:$B,$C33,'sales data'!$F:$F,$D33,'sales data'!$O:$O,"N") -> 0 | T33: =+IF(S33<>0,S33*N33,) -> 0 | U33: =SUMIFS('warehouse inventory check'!$N:$N,'warehouse inventory check'!$C:$C,$C33,'warehouse inventory check'!$D:$D,$D33) -> 61 | V33: =+N33 -> 413.75883 | W33: =+IF(U33<>0,U33*N33,) -> 25239.289 | X33: =+I33+K33-P33-R33-W33-T33+M33 -> 0 | Y33: =+G33+J33+L33-O33-Q33-S33 -> 61 | Z33: =+U33-Y33 -> 0
A34: 29 | C34: 1 | D34: T2X8-14A033-AA | E34: BEV-M | F34: BUSBAR ASY | G34: 0 | H34: 573.96659 | I34: 0 | J34: =SUMIFS('purchase data'!K:K,'purchase data'!$B:$B,$C34,'purchase data'!$F:$F,$D34) -> 24 | K34: =SUMIFS('purchase data'!M:M,'purchase data'!$B:$B,$C34,'purchase data'!$F:$F,$D34) -> 13935.977 | L34: =SUMIFS(ETC!$G:$G,ETC!$B:$B,$C34,ETC!$E:$E,$D34) -> 0 | M34: =SUMIFS(ETC!$J:$J,ETC!$E:$E,$D34,ETC!$B:$B,$C34) -> 0 | N34: =IF(IFERROR((I34+K34+M34)/(G34+J34+SUMIFS(ETC!$G:$G,ETC!$C:$C,1,ETC!$B:$B,$C34,ETC!$E:$E,$D34)),)=0,H34,IFERROR((I34+K34+M34)/(G34+J34+SUMIFS(ETC!$G:$G,ETC!$C:$C,1,ETC!$B:$B,$C34,ETC!$E:$E,$D34)),)) -> 580.66572 | O34: =++SUMIFS('sales data'!L:L,'sales data'!$B:$B,$C34,'sales data'!$F:$F,$D34,'sales data'!$O:$O,"") -> 24 | P34: =+IF(O34<>0,O34*N34,) -> 13935.977 | Q34: =+SUMIFS('sales data'!$L:$L,'sales data'!$B:$B,$C34,'sales data'!$F:$F,$D34,'sales data'!$O:$O,"R") -> 0 | R34: =+IF(Q34<>0,Q34*N34,) -> 0 | S34: =SUMIFS('sales data'!$L:$L,'sales data'!$B:$B,$C34,'sales data'!$F:$F,$D34,'sales data'!$O:$O,"N") -> 0 | T34: =+IF(S34<>0,S34*N34,) -> 0 | U34: =SUMIFS('warehouse inventory check'!$N:$N,'warehouse inventory check'!$C:$C,$C34,'warehouse inventory check'!$D:$D,$D34) -> 0 | V34: =+N34 -> 580.66572 | W34: =+IF(U34<>0,U34*N34,) -> 0 | X34: =+I34+K34-P34-R34-W34-T34+M34 -> 0 | Y34: =+G34+J34+L34-O34-Q34-S34 -> 0 | Z34: =+U34-Y34 -> 0
A35: 30 | C35: 1 | D35: T2X8-14A033-BA | E35: BEV-M | F35: BUSBAR ASY | G35: 0 | H35: 555.88891 | I35: 0 | J35: =SUMIFS('purchase data'!K:K,'purchase data'!$B:$B,$C35,'purchase data'!$F:$F,$D35) -> 24 | K35: =SUMIFS('purchase data'!M:M,'purchase data'!$B:$B,$C35,'purchase data'!$F:$F,$D35) -> 13497.049 | L35: =SUMIFS(ETC!$G:$G,ETC!$B:$B,$C35,ETC!$E:$E,$D35) -> 0 | M35: =SUMIFS(ETC!$J:$J,ETC!$E:$E,$D35,ETC!$B:$B,$C35) -> 0 | N35: =IF(IFERROR((I35+K35+M35)/(G35+J35+SUMIFS(ETC!$G:$G,ETC!$C:$C,1,ETC!$B:$B,$C35,ETC!$E:$E,$D35)),)=0,H35,IFERROR((I35+K35+M35)/(G35+J35+SUMIFS(ETC!$G:$G,ETC!$C:$C,1,ETC!$B:$B,$C35,ETC!$E:$E,$D35)),)) -> 562.37703 | O35: =++SUMIFS('sales data'!L:L,'sales data'!$B:$B,$C35,'sales data'!$F:$F,$D35,'sales data'!$O:$O,"") -> 24 | P35: =+IF(O35<>0,O35*N35,) -> 13497.049 | Q35: =+SUMIFS('sales data'!$L:$L,'sales data'!$B:$B,$C35,'sales data'!$F:$F,$D35,'sales data'!$O:$O,"R") -> 0 | R35: =+IF(Q35<>0,Q35*N35,) -> 0 | S35: =SUMIFS('sales data'!$L:$L,'sales data'!$B:$B,$C35,'sales data'!$F:$F,$D35,'sales data'!$O:$O,"N") -> 0 | T35: =+IF(S35<>0,S35*N35,) -> 0 | U35: =SUMIFS('warehouse inventory check'!$N:$N,'warehouse inventory check'!$C:$C,$C35,'warehouse inventory check'!$D:$D,$D35) -> 0 | V35: =+N35 -> 562.37703 | W35: =+IF(U35<>0,U35*N35,) -> 0 | X35: =+I35+K35-P35-R35-W35-T35+M35 -> 0 | Y35: =+G35+J35+L35-O35-Q35-S35 -> 0 | Z35: =+U35-Y35 -> 0
A36: 31 | C36: 1 | D36: T2X8-14A033-EA | E36: BEV-M | F36: BUSBAR ASY | G36: 0 | H36: 645.77519 | I36: 0 | J36: =SUMIFS('purchase data'!K:K,'purchase data'!$B:$B,$C36,'purchase data'!$F:$F,$D36) -> 48 | K36: =SUMIFS('purchase data'!M:M,'purchase data'!$B:$B,$C36,'purchase data'!$F:$F,$D36) -> 31358.997 | L36: =SUMIFS(ETC!$G:$G,ETC!$B:$B,$C36,ETC!$E:$E,$D36) -> 0 | M36: =SUMIFS(ETC!$J:$J,ETC!$E:$E,$D36,ETC!$B:$B,$C36) -> 0 | N36: =IF(IFERROR((I36+K36+M36)/(G36+J36+SUMIFS(ETC!$G:$G,ETC!$C:$C,1,ETC!$B:$B,$C36,ETC!$E:$E,$D36)),)=0,H36,IFERROR((I36+K36+M36)/(G36+J36+SUMIFS(ETC!$G:$G,ETC!$C:$C,1,ETC!$B:$B,$C36,ETC!$E:$E,$D36)),)) -> 653.31243 | O36: =++SUMIFS('sales data'!L:L,'sales data'!$B:$B,$C36,'sales data'!$F:$F,$D36,'sales data'!$O:$O,"") -> 48 | P36: =+IF(O36<>0,O36*N36,) -> 31358.997 | Q36: =+SUMIFS('sales data'!$L:$L,'sales data'!$B:$B,$C36,'sales data'!$F:$F,$D36,'sales data'!$O:$O,"R") -> 0 | R36: =+IF(Q36<>0,Q36*N36,) -> 0 | S36: =SUMIFS('sales data'!$L:$L,'sales data'!$B:$B,$C36,'sales data'!$F:$F,$D36,'sales data'!$O:$O,"N") -> 0 | T36: =+IF(S36<>0,S36*N36,) -> 0 | U36: =SUMIFS('warehouse inventory check'!$N:$N,'warehouse inventory check'!$C:$C,$C36,'warehouse inventory check'!$D:$D,$D36) -> 0 | V36: =+N36 -> 653.31243 | W36: =+IF(U36<>0,U36*N36,) -> 0 | X36: =+I36+K36-P36-R36-W36-T36+M36 -> 0 | Y36: =+G36+J36+L36-O36-Q36-S36 -> 0 | Z36: =+U36-Y36 -> 0
A37: 32 | C37: 1 | D37: T2X8-14A033-GA | E37: BEV-M | F37: BUSBAR ASY | G37: 0 | H37: 433.36235 | I37: 0 | J37: =SUMIFS('purchase data'!K:K,'purchase data'!$B:$B,$C37,'purchase data'!$F:$F,$D37) -> 24 | K37: =SUMIFS('purchase data'!M:M,'purchase data'!$B:$B,$C37,'purchase data'!$F:$F,$D37) -> 10522.09 | L37: =SUMIFS(ETC!$G:$G,ETC!$B:$B,$C37,ETC!$E:$E,$D37) -> 0 | M37: =SUMIFS(ETC!$J:$J,ETC!$E:$E,$D37,ETC!$B:$B,$C37) -> 0 | N37: =IF(IFERROR((I37+K37+M37)/(G37+J37+SUMIFS(ETC!$G:$G,ETC!$C:$C,1,ETC!$B:$B,$C37,ETC!$E:$E,$D37)),)=0,H37,IFERROR((I37+K37+M37)/(G37+J37+SUMIFS(ETC!$G:$G,ETC!$C:$C,1,ETC!$B:$B,$C37,ETC!$E:$E,$D37)),)) -> 438.4204 | O37: =++SUMIFS('sales data'!L:L,'sales data'!$B:$B,$C37,'sales data'!$F:$F,$D37,'sales data'!$O:$O,"") -> 24 | P37: =+IF(O37<>0,O37*N37,) -> 10522.09 | Q37: =+SUMIFS('sales data'!$L:$L,'sales data'!$B:$B,$C37,'sales data'!$F:$F,$D37,'sales data'!$O:$O,"R") -> 0 | R37: =+IF(Q37<>0,Q37*N37,) -> 0 | S37: =SUMIFS('sales data'!$L:$L,'sales data'!$B:$B,$C37,'sales data'!$F:$F,$D37,'sales data'!$O:$O,"N") -> 0 | T37: =+IF(S37<>0,S37*N37,) -> 0 | U37: =SUMIFS('warehouse inventory check'!$N:$N,'warehouse inventory check'!$C:$C,$C37,'warehouse inventory check'!$D:$D,$D37) -> 0 | V37: =+N37 -> 438.4204 | W37: =+IF(U37<>0,U37*N37,) -> 0 | X37: =+I37+K37-P37-R37-W37-T37+M37 -> 0 | Y37: =+G37+J37+L37-O37-Q37-S37 -> 0 | Z37: =+U37-Y37 -> 0
A38: 33 | C38: 1 | D38: TZ38-10B694-AA | E38: BEV-E1 | F38: V710 AWD MAIN W/H ASSY | G38: 2 | H38: 5137.5179 | I38: 10275.036 | J38: =SUMIFS('purchase data'!K:K,'purchase data'!$B:$B,$C38,'purchase data'!$F:$F,$D38) -> 0 | K38: =SUMIFS('purchase data'!M:M,'purchase data'!$B:$B,$C38,'purchase data'!$F:$F,$D38) -> 0 | L38: =SUMIFS(ETC!$G:$G,ETC!$B:$B,$C38,ETC!$E:$E,$D38) -> 0 | M38: =SUMIFS(ETC!$J:$J,ETC!$E:$E,$D38,ETC!$B:$B,$C38) -> 0 | N38: =IF(IFERROR((I38+K38+M38)/(G38+J38+SUMIFS(ETC!$G:$G,ETC!$C:$C,1,ETC!$B:$B,$C38,ETC!$E:$E,$D38)),)=0,H38,IFERROR((I38+K38+M38)/(G38+J38+SUMIFS(ETC!$G:$G,ETC!$C:$C,1,ETC!$B:$B,$C38,ETC!$E:$E,$D38)),)) -> 5137.5179 | O38: =++SUMIFS('sales data'!L:L,'sales data'!$B:$B,$C38,'sales data'!$F:$F,$D38,'sales data'!$O:$O,"") -> 0 | P38: =+IF(O38<>0,O38*N38,) -> 0 | Q38: =+SUMIFS('sales data'!$L:$L,'sales data'!$B:$B,$C38,'sales data'!$F:$F,$D38,'sales data'!$O:$O,"R") -> 0 | R38: =+IF(Q38<>0,Q38*N38,) -> 0 | S38: =SUMIFS('sales data'!$L:$L,'sales data'!$B:$B,$C38,'sales data'!$F:$F,$D38,'sales data'!$O:$O,"N") -> 0 | T38: =+IF(S38<>0,S38*N38,) -> 0 | U38: =SUMIFS('warehouse inventory check'!$N:$N,'warehouse inventory check'!$C:$C,$C38,'warehouse inventory check'!$D:$D,$D38) -> 2 | V38: =+N38 -> 5137.5179 | W38: =+IF(U38<>0,U38*N38,) -> 10275.036 | X38: =+I38+K38-P38-R38-W38-T38+M38 -> 0 | Y38: =+G38+J38+L38-O38-Q38-S38 -> 2 | Z38: =+U38-Y38 -> 0
A39: 34 | C39: 1 | D39: TZ38-10B694-AD | E39: BEV-E (AWD, V710) | F39: Main Harness | G39: 18 | H39: 6009.041 | I39: 108162.74 | J39: =SUMIFS('purchase data'!K:K,'purchase data'!$B:$B,$C39,'purchase data'!$F:$F,$D39) -> 0 | K39: =SUMIFS('purchase data'!M:M,'purchase data'!$B:$B,$C39,'purchase data'!$F:$F,$D39) -> 0 | L39: =SUMIFS(ETC!$G:$G,ETC!$B:$B,$C39,ETC!$E:$E,$D39) -> 0 | M39: =SUMIFS(ETC!$J:$J,ETC!$E:$E,$D39,ETC!$B:$B,$C39) -> 0 | N39: =IF(IFERROR((I39+K39+M39)/(G39+J39+SUMIFS(ETC!$G:$G,ETC!$C:$C,1,ETC!$B:$B,$C39,ETC!$E:$E,$D39)),)=0,H39,IFERROR((I39+K39+M39)/(G39+J39+SUMIFS(ETC!$G:$G,ETC!$C:$C,1,ETC!$B:$B,$C39,ETC!$E:$E,$D39)),)) -> 6009.041 | O39: =++SUMIFS('sales data'!L:L,'sales data'!$B:$B,$C39,'sales data'!$F:$F,$D39,'sales data'!$O:$O,"") -> 0 | P39: =+IF(O39<>0,O39*N39,) -> 0 | Q39: =+SUMIFS('sales data'!$L:$L,'sales data'!$B:$B,$C39,'sales data'!$F:$F,$D39,'sales data'!$O:$O,"R") -> 0 | R39: =+IF(Q39<>0,Q39*N39,) -> 0 | S39: =SUMIFS('sales data'!$L:$L,'sales data'!$B:$B,$C39,'sales data'!$F:$F,$D39,'sales data'!$O:$O,"N") -> 0 | T39: =+IF(S39<>0,S39*N39,) -> 0 | U39: =SUMIFS('warehouse inventory check'!$N:$N,'warehouse inventory check'!$C:$C,$C39,'warehouse inventory check'!$D:$D,$D39) -> 18 | V39: =+N39 -> 6009.041 | W39: =+IF(U39<>0,U39*N39,) -> 108162.74 | X39: =+I39+K39-P39-R39-W39-T39+M39 -> 0 | Y39: =+G39+J39+L39-O39-Q39-S39 -> 18 | Z39: =+U39-Y39 -> 0
A40: 35 | C40: 1 | D40: TZ38-10B694-AF | E40: BEV-E (AWD/RWD, V710) | F40: Main Harness-AWD-RWD | G40: 20 | H40: 6162.9778 | I40: 123259.55 | J40: =SUMIFS('purchase data'!K:K,'purchase data'!$B:$B,$C40,'purchase data'!$F:$F,$D40) -> 440 | K40: =SUMIFS('purchase data'!M:M,'purchase data'!$B:$B,$C40,'purchase data'!$F:$F,$D40) -> 2870585.1 | L40: =SUMIFS(ETC!$G:$G,ETC!$B:$B,$C40,ETC!$E:$E,$D40) -> 0 | M40: =SUMIFS(ETC!$J:$J,ETC!$E:$E,$D40,ETC!$B:$B,$C40) -> 0 | N40: =IF(IFERROR((I40+K40+M40)/(G40+J40+SUMIFS(ETC!$G:$G,ETC!$C:$C,1,ETC!$B:$B,$C40,ETC!$E:$E,$D40)),)=0,H40,IFERROR((I40+K40+M40)/(G40+J40+SUMIFS(ETC!$G:$G,ETC!$C:$C,1,ETC!$B:$B,$C40,ETC!$E:$E,$D40)),)) -> 6508.3579 | O40: =++SUMIFS('sales data'!L:L,'sales data'!$B:$B,$C40,'sales data'!$F:$F,$D40,'sales data'!$O:$O,"") -> 440 | P40: =+IF(O40<>0,O40*N40,) -> 2863677.5 | Q40: =+SUMIFS('sales data'!$L:$L,'sales data'!$B:$B,$C40,'sales data'!$F:$F,$D40,'sales data'!$O:$O,"R") -> 0 | R40: =+IF(Q40<>0,Q40*N40,) -> 0 | S40: =SUMIFS('sales data'!$L:$L,'sales data'!$B:$B,$C40,'sales data'!$F:$F,$D40,'sales data'!$O:$O,"N") -> 0 | T40: =+IF(S40<>0,S40*N40,) -> 0 | U40: =SUMIFS('warehouse inventory check'!$N:$N,'warehouse inventory check'!$C:$C,$C40,'warehouse inventory check'!$D:$D,$D40) -> 20 | V40: =+N40 -> 6508.3579 | W40: =+IF(U40<>0,U40*N40,) -> 130167.16 | X40: =+I40+K40-P40-R40-W40-T40+M40 -> 1.1641532e-10 | Y40: =+G40+J40+L40-O40-Q40-S40 -> 20 | Z40: =+U40-Y40 -> 0
A41: 36 | C41: 1 | D41: TZ38-10B694-BA | E41: EV-V4 | F41: Main_Harness-RWD | G41: 0 | H41: 18009.589 | I41: 0 | J41: =SUMIFS('purchase data'!K:K,'purchase data'!$B:$B,$C41,'purchase data'!$F:$F,$D41) -> 0 | K41: =SUMIFS('purchase data'!M:M,'purchase data'!$B:$B,$C41,'purchase data'!$F:$F,$D41) -> 0 | L41: =SUMIFS(ETC!$G:$G,ETC!$B:$B,$C41,ETC!$E:$E,$D41) -> 0 | M41: =SUMIFS(ETC!$J:$J,ETC!$E:$E,$D41,ETC!$B:$B,$C41) -> 0 | N41: =IF(IFERROR((I41+K41+M41)/(G41+J41+SUMIFS(ETC!$G:$G,ETC!$C:$C,1,ETC!$B:$B,$C41,ETC!$E:$E,$D41)),)=0,H41,IFERROR((I41+K41+M41)/(G41+J41+SUMIFS(ETC!$G:$G,ETC!$C:$C,1,ETC!$B:$B,$C41,ETC!$E:$E,$D41)),)) -> 18009.589 | O41: =++SUMIFS('sales data'!L:L,'sales data'!$B:$B,$C41,'sales data'!$F:$F,$D41,'sales data'!$O:$O,"") -> 0 | P41: =+IF(O41<>0,O41*N41,) -> 0 | Q41: =+SUMIFS('sales data'!$L:$L,'sales data'!$B:$B,$C41,'sales data'!$F:$F,$D41,'sales data'!$O:$O,"R") -> 0 | R41: =+IF(Q41<>0,Q41*N41,) -> 0 | S41: =SUMIFS('sales data'!$L:$L,'sales data'!$B:$B,$C41,'sales data'!$F:$F,$D41,'sales data'!$O:$O,"N") -> 0 | T41: =+IF(S41<>0,S41*N41,) -> 0 | U41: =SUMIFS('warehouse inventory check'!$N:$N,'warehouse inventory check'!$C:$C,$C41,'warehouse inventory check'!$D:$D,$D41) -> 0 | V41: =+N41 -> 18009.589 | W41: =+IF(U41<>0,U41*N41,) -> 0 | X41: =+I41+K41-P41-R41-W41-T41+M41 -> 0 | Y41: =+G41+J41+L41-O41-Q41-S41 -> 0 | Z41: =+U41-Y41 -> 0
A42: 37 | C42: 1 | D42: TZ38-10B694-CA | E42: EV-V4 | F42: Main_Harness-AWD | G42: 0 | H42: 26020.641 | I42: 0 | J42: =SUMIFS('purchase data'!K:K,'purchase data'!$B:$B,$C42,'purchase data'!$F:$F,$D42) -> 0 | K42: =SUMIFS('purchase data'!M:M,'purchase data'!$B:$B,$C42,'purchase data'!$F:$F,$D42) -> 0 | L42: =SUMIFS(ETC!$G:$G,ETC!$B:$B,$C42,ETC!$E:$E,$D42) -> 0 | M42: =SUMIFS(ETC!$J:$J,ETC!$E:$E,$D42,ETC!$B:$B,$C42) -> 0 | N42: =IF(IFERROR((I42+K42+M42)/(G42+J42+SUMIFS(ETC!$G:$G,ETC!$C:$C,1,ETC!$B:$B,$C42,ETC!$E:$E,$D42)),)=0,H42,IFERROR((I42+K42+M42)/(G42+J42+SUMIFS(ETC!$G:$G,ETC!$C:$C,1,ETC!$B:$B,$C42,ETC!$E:$E,$D42)),)) -> 26020.641 | O42: =++SUMIFS('sales data'!L:L,'sales data'!$B:$B,$C42,'sales data'!$F:$F,$D42,'sales data'!$O:$O,"") -> 0 | P42: =+IF(O42<>0,O42*N42,) -> 0 | Q42: =+SUMIFS('sales data'!$L:$L,'sales data'!$B:$B,$C42,'sales data'!$F:$F,$D42,'sales data'!$O:$O,"R") -> 0 | R42: =+IF(Q42<>0,Q42*N42,) -> 0 | S42: =SUMIFS('sales data'!$L:$L,'sales data'!$B:$B,$C42,'sales data'!$F:$F,$D42,'sales data'!$O:$O,"N") -> 0 | T42: =+IF(S42<>0,S42*N42,) -> 0 | U42: =SUMIFS('warehouse inventory check'!$N:$N,'warehouse inventory check'!$C:$C,$C42,'warehouse inventory check'!$D:$D,$D42) -> 0 | V42: =+N42 -> 26020.641 | W42: =+IF(U42<>0,U42*N42,) -> 0 | X42: =+I42+K42-P42-R42-W42-T42+M42 -> 0 | Y42: =+G42+J42+L42-O42-Q42-S42 -> 0 | Z42: =+U42-Y42 -> 0
... A54: 49 | C54: 1 | D54: TZ38-14A033-EA04 | E54: EV-V4 | F54: BUSBAR | G54: 0 | H54: 0 | I54: 0 | J54: =SUMIFS('purchase data'!K:K,'purchase data'!$B:$B,$C54,'purchase data'!$F:$F,$D54) -> 7 | K54: =SUMIFS('purchase data'!M:M,'purchase data'!$B:$B,$C54,'purchase data'!$F:$F,$D54) -> 29493.293 | L54: =SUMIFS(ETC!$G:$G,ETC!$B:$B,$C54,ETC!$E:$E,$D54) -> 0 | M54: =SUMIFS(ETC!$J:$J,ETC!$E:$E,$D54,ETC!$B:$B,$C54) -> 0 | N54: =IF(IFERROR((I54+K54+M54)/(G54+J54+SUMIFS(ETC!$G:$G,ETC!$C:$C,1,ETC!$B:$B,$C54,ETC!$E:$E,$D54)),)=0,H54,IFERROR((I54+K54+M54)/(G54+J54+SUMIFS(ETC!$G:$G,ETC!$C:$C,1,ETC!$B:$B,$C54,ETC!$E:$E,$D54)),)) -> 4213.3276 | O54: =++SUMIFS('sales data'!L:L,'sales data'!$B:$B,$C54,'sales data'!$F:$F,$D54,'sales data'!$O:$O,"") -> 7 | P54: =+IF(O54<>0,O54*N54,) -> 29493.293 | Q54: =+SUMIFS('sales data'!$L:$L,'sales data'!$B:$B,$C54,'sales data'!$F:$F,$D54,'sales data'!$O:$O,"R") -> 0 | R54: =+IF(Q54<>0,Q54*N54,) -> 0 | S54: =SUMIFS('sales data'!$L:$L,'sales data'!$B:$B,$C54,'sales data'!$F:$F,$D54,'sales data'!$O:$O,"N") -> 0 | T54: =+IF(S54<>0,S54*N54,) -> 0 | U54: =SUMIFS('warehouse inventory check'!$N:$N,'warehouse inventory check'!$C:$C,$C54,'warehouse inventory check'!$D:$D,$D54) -> 0 | V54: =+N54 -> 4213.3276 | W54: =+IF(U54<>0,U54*N54,) -> 0 | X54: =+I54+K54-P54-R54-W54-T54+M54 -> 0 | Y54: =+G54+J54+L54-O54-Q54-S54 -> 0 | Z54: =+U54-Y54 -> 0
A55: 50 | C55: 1 | D55: TZ38-14A033-FA | E55: BEV-E (AWD/RWD, V710) | F55: BUS BAR ASY | G55: 0 | H55: 666.35846 | I55: 0 | J55: =SUMIFS('purchase data'!K:K,'purchase data'!$B:$B,$C55,'purchase data'!$F:$F,$D55) -> 1620 | K55: =SUMIFS('purchase data'!M:M,'purchase data'!$B:$B,$C55,'purchase data'!$F:$F,$D55) -> 1133489.7 | L55: =SUMIFS(ETC!$G:$G,ETC!$B:$B,$C55,ETC!$E:$E,$D55) -> 0 | M55: =SUMIFS(ETC!$J:$J,ETC!$E:$E,$D55,ETC!$B:$B,$C55) -> 0 | N55: =IF(IFERROR((I55+K55+M55)/(G55+J55+SUMIFS(ETC!$G:$G,ETC!$C:$C,1,ETC!$B:$B,$C55,ETC!$E:$E,$D55)),)=0,H55,IFERROR((I55+K55+M55)/(G55+J55+SUMIFS(ETC!$G:$G,ETC!$C:$C,1,ETC!$B:$B,$C55,ETC!$E:$E,$D55)),)) -> 699.68501 | O55: =++SUMIFS('sales data'!L:L,'sales data'!$B:$B,$C55,'sales data'!$F:$F,$D55,'sales data'!$O:$O,"") -> 1944 | P55: =+IF(O55<>0,O55*N55,) -> 1360187.7 | Q55: =+SUMIFS('sales data'!$L:$L,'sales data'!$B:$B,$C55,'sales data'!$F:$F,$D55,'sales data'!$O:$O,"R") -> 0 | R55: =+IF(Q55<>0,Q55*N55,) -> 0 | S55: =SUMIFS('sales data'!$L:$L,'sales data'!$B:$B,$C55,'sales data'!$F:$F,$D55,'sales data'!$O:$O,"N") -> 0 | T55: =+IF(S55<>0,S55*N55,) -> 0 | U55: =SUMIFS('warehouse inventory check'!$N:$N,'warehouse inventory check'!$C:$C,$C55,'warehouse inventory check'!$D:$D,$D55) -> -324 | V55: =+N55 -> 699.68501 | W55: =+IF(U55<>0,U55*N55,) -> -226697.94 | X55: =+I55+K55-P55-R55-W55-T55+M55 -> 1.7462298e-10 | Y55: =+G55+J55+L55-O55-Q55-S55 -> -324 | Z55: =+U55-Y55 -> 0 | AA55: Nursan’s late invoice.
A56: 51 | C56: 1 | D56: TZ38-14A033-GA | E56: EV-V4 | F56: BUSBAR ASY | G56: 0 | H56: 2319.7225 | I56: 0 | J56: =SUMIFS('purchase data'!K:K,'purchase data'!$B:$B,$C56,'purchase data'!$F:$F,$D56) -> 0 | K56: =SUMIFS('purchase data'!M:M,'purchase data'!$B:$B,$C56,'purchase data'!$F:$F,$D56) -> 0 | L56: =SUMIFS(ETC!$G:$G,ETC!$B:$B,$C56,ETC!$E:$E,$D56) -> 0 | M56: =SUMIFS(ETC!$J:$J,ETC!$E:$E,$D56,ETC!$B:$B,$C56) -> 0 | N56: =IF(IFERROR((I56+K56+M56)/(G56+J56+SUMIFS(ETC!$G:$G,ETC!$C:$C,1,ETC!$B:$B,$C56,ETC!$E:$E,$D56)),)=0,H56,IFERROR((I56+K56+M56)/(G56+J56+SUMIFS(ETC!$G:$G,ETC!$C:$C,1,ETC!$B:$B,$C56,ETC!$E:$E,$D56)),)) -> 2319.7225 | O56: =++SUMIFS('sales data'!L:L,'sales data'!$B:$B,$C56,'sales data'!$F:$F,$D56,'sales data'!$O:$O,"") -> 0 | P56: =+IF(O56<>0,O56*N56,) -> 0 | Q56: =+SUMIFS('sales data'!$L:$L,'sales data'!$B:$B,$C56,'sales data'!$F:$F,$D56,'sales data'!$O:$O,"R") -> 0 | R56: =+IF(Q56<>0,Q56*N56,) -> 0 | S56: =SUMIFS('sales data'!$L:$L,'sales data'!$B:$B,$C56,'sales data'!$F:$F,$D56,'sales data'!$O:$O,"N") -> 0 | T56: =+IF(S56<>0,S56*N56,) -> 0 | U56: =SUMIFS('warehouse inventory check'!$N:$N,'warehouse inventory check'!$C:$C,$C56,'warehouse inventory check'!$D:$D,$D56) -> 0 | V56: =+N56 -> 2319.7225 | W56: =+IF(U56<>0,U56*N56,) -> 0 | X56: =+I56+K56-P56-R56-W56-T56+M56 -> 0 | Y56: =+G56+J56+L56-O56-Q56-S56 -> 0 | Z56: =+U56-Y56 -> 0
A57: 52 | C57: 1 | D57: TZ38-14A033-GA04 | E57: EV-V4 | F57: BUSBAR | G57: 0 | H57: 0 | I57: 0 | J57: =SUMIFS('purchase data'!K:K,'purchase data'!$B:$B,$C57,'purchase data'!$F:$F,$D57) -> 7 | K57: =SUMIFS('purchase data'!M:M,'purchase data'!$B:$B,$C57,'purchase data'!$F:$F,$D57) -> 16562.841 | L57: =SUMIFS(ETC!$G:$G,ETC!$B:$B,$C57,ETC!$E:$E,$D57) -> 0 | M57: =SUMIFS(ETC!$J:$J,ETC!$E:$E,$D57,ETC!$B:$B,$C57) -> 0 | N57: =IF(IFERROR((I57+K57+M57)/(G57+J57+SUMIFS(ETC!$G:$G,ETC!$C:$C,1,ETC!$B:$B,$C57,ETC!$E:$E,$D57)),)=0,H57,IFERROR((I57+K57+M57)/(G57+J57+SUMIFS(ETC!$G:$G,ETC!$C:$C,1,ETC!$B:$B,$C57,ETC!$E:$E,$D57)),)) -> 2366.1201 | O57: =++SUMIFS('sales data'!L:L,'sales data'!$B:$B,$C57,'sales data'!$F:$F,$D57,'sales data'!$O:$O,"") -> 7 | P57: =+IF(O57<>0,O57*N57,) -> 16562.841 | Q57: =+SUMIFS('sales data'!$L:$L,'sales data'!$B:$B,$C57,'sales data'!$F:$F,$D57,'sales data'!$O:$O,"R") -> 0 | R57: =+IF(Q57<>0,Q57*N57,) -> 0 | S57: =SUMIFS('sales data'!$L:$L,'sales data'!$B:$B,$C57,'sales data'!$F:$F,$D57,'sales data'!$O:$O,"N") -> 0 | T57: =+IF(S57<>0,S57*N57,) -> 0 | U57: =SUMIFS('warehouse inventory check'!$N:$N,'warehouse inventory check'!$C:$C,$C57,'warehouse inventory check'!$D:$D,$D57) -> 0 | V57: =+N57 -> 2366.1201 | W57: =+IF(U57<>0,U57*N57,) -> 0 | X57: =+I57+K57-P57-R57-W57-T57+M57 -> 0 | Y57: =+G57+J57+L57-O57-Q57-S57 -> 0 | Z57: =+U57-Y57 -> 0
A58: 53 | C58: 1 | D58: TZ38-14A033-HB | E58: BEV-E (AWD/RWD, V710) | F58: MCA CONNECTOR CLIP | G58: 0 | H58: 611.41 | I58: 0 | J58: =SUMIFS('purchase data'!K:K,'purchase data'!$B:$B,$C58,'purchase data'!$F:$F,$D58) -> 2322 | K58: =SUMIFS('purchase data'!M:M,'purchase data'!$B:$B,$C58,'purchase data'!$F:$F,$D58) -> 1499869.8 | L58: =SUMIFS(ETC!$G:$G,ETC!$B:$B,$C58,ETC!$E:$E,$D58) -> 0 | M58: =SUMIFS(ETC!$J:$J,ETC!$E:$E,$D58,ETC!$B:$B,$C58) -> 0 | N58: =IF(IFERROR((I58+K58+M58)/(G58+J58+SUMIFS(ETC!$G:$G,ETC!$C:$C,1,ETC!$B:$B,$C58,ETC!$E:$E,$D58)),)=0,H58,IFERROR((I58+K58+M58)/(G58+J58+SUMIFS(ETC!$G:$G,ETC!$C:$C,1,ETC!$B:$B,$C58,ETC!$E:$E,$D58)),)) -> 645.93877 | O58: =++SUMIFS('sales data'!L:L,'sales data'!$B:$B,$C58,'sales data'!$F:$F,$D58,'sales data'!$O:$O,"") -> 2862 | P58: =+IF(O58<>0,O58*N58,) -> 1848676.8 | Q58: =+SUMIFS('sales data'!$L:$L,'sales data'!$B:$B,$C58,'sales data'!$F:$F,$D58,'sales data'!$O:$O,"R") -> 0 | R58: =+IF(Q58<>0,Q58*N58,) -> 0 | S58: =SUMIFS('sales data'!$L:$L,'sales data'!$B:$B,$C58,'sales data'!$F:$F,$D58,'sales data'!$O:$O,"N") -> 0 | T58: =+IF(S58<>0,S58*N58,) -> 0 | U58: =SUMIFS('warehouse inventory check'!$N:$N,'warehouse inventory check'!$C:$C,$C58,'warehouse inventory check'!$D:$D,$D58) -> -540 | V58: =+N58 -> 645.93877 | W58: =+IF(U58<>0,U58*N58,) -> -348806.94 | X58: =+I58+K58-P58-R58-W58-T58+M58 -> 1.1641532e-10 | Y58: =+G58+J58+L58-O58-Q58-S58 -> -540 | Z58: =+U58-Y58 -> 0 | AA58: Nursan’s late invoice.
A59: 54 | C59: 1 | D59: TZ38-14A033-JA | E59: BEV-E (AWD, V710) | F59: BUS BAR ASY | G59: 40 | H59: 657.795 | I59: 26311.8 | J59: =SUMIFS('purchase data'!K:K,'purchase data'!$B:$B,$C59,'purchase data'!$F:$F,$D59) -> 0 | K59: =SUMIFS('purchase data'!M:M,'purchase data'!$B:$B,$C59,'purchase data'!$F:$F,$D59) -> 0 | L59: =SUMIFS(ETC!$G:$G,ETC!$B:$B,$C59,ETC!$E:$E,$D59) -> 0 | M59: =SUMIFS(ETC!$J:$J,ETC!$E:$E,$D59,ETC!$B:$B,$C59) -> 0 | N59: =IF(IFERROR((I59+K59+M59)/(G59+J59+SUMIFS(ETC!$G:$G,ETC!$C:$C,1,ETC!$B:$B,$C59,ETC!$E:$E,$D59)),)=0,H59,IFERROR((I59+K59+M59)/(G59+J59+SUMIFS(ETC!$G:$G,ETC!$C:$C,1,ETC!$B:$B,$C59,ETC!$E:$E,$D59)),)) -> 657.795 | O59: =++SUMIFS('sales data'!L:L,'sales data'!$B:$B,$C59,'sales data'!$F:$F,$D59,'sales data'!$O:$O,"") -> 0 | P59: =+IF(O59<>0,O59*N59,) -> 0 | Q59: =+SUMIFS('sales data'!$L:$L,'sales data'!$B:$B,$C59,'sales data'!$F:$F,$D59,'sales data'!$O:$O,"R") -> 0 | R59: =+IF(Q59<>0,Q59*N59,) -> 0 | S59: =SUMIFS('sales data'!$L:$L,'sales data'!$B:$B,$C59,'sales data'!$F:$F,$D59,'sales data'!$O:$O,"N") -> 0 | T59: =+IF(S59<>0,S59*N59,) -> 0 | U59: =SUMIFS('warehouse inventory check'!$N:$N,'warehouse inventory check'!$C:$C,$C59,'warehouse inventory check'!$D:$D,$D59) -> 40 | V59: =+N59 -> 657.795 | W59: =+IF(U59<>0,U59*N59,) -> 26311.8 | X59: =+I59+K59-P59-R59-W59-T59+M59 -> 0 | Y59: =+G59+J59+L59-O59-Q59-S59 -> 40 | Z59: =+U59-Y59 -> 0
A60: 55 | C60: 1 | D60: TZ38-14A033-JB | E60: BEV-E (AWD/RWD, V710) | F60: MCA CONNECTOR CLIP | G60: 0 | H60: 684.915 | I60: 0 | J60: =SUMIFS('purchase data'!K:K,'purchase data'!$B:$B,$C60,'purchase data'!$F:$F,$D60) -> 880 | K60: =SUMIFS('purchase data'!M:M,'purchase data'!$B:$B,$C60,'purchase data'!$F:$F,$D60) -> 637246.72 | L60: =SUMIFS(ETC!$G:$G,ETC!$B:$B,$C60,ETC!$E:$E,$D60) -> 0 | M60: =SUMIFS(ETC!$J:$J,ETC!$E:$E,$D60,ETC!$B:$B,$C60) -> 0 | N60: =IF(IFERROR((I60+K60+M60)/(G60+J60+SUMIFS(ETC!$G:$G,ETC!$C:$C,1,ETC!$B:$B,$C60,ETC!$E:$E,$D60)),)=0,H60,IFERROR((I60+K60+M60)/(G60+J60+SUMIFS(ETC!$G:$G,ETC!$C:$C,1,ETC!$B:$B,$C60,ETC!$E:$E,$D60)),)) -> 724.144 | O60: =++SUMIFS('sales data'!L:L,'sales data'!$B:$B,$C60,'sales data'!$F:$F,$D60,'sales data'!$O:$O,"") -> 1080 | P60: =+IF(O60<>0,O60*N60,) -> 782075.52 | Q60: =+SUMIFS('sales data'!$L:$L,'sales data'!$B:$B,$C60,'sales data'!$F:$F,$D60,'sales data'!$O:$O,"R") -> 0 | R60: =+IF(Q60<>0,Q60*N60,) -> 0 | S60: =SUMIFS('sales data'!$L:$L,'sales data'!$B:$B,$C60,'sales data'!$F:$F,$D60,'sales data'!$O:$O,"N") -> 0 | T60: =+IF(S60<>0,S60*N60,) -> 0 | U60: =SUMIFS('warehouse inventory check'!$N:$N,'warehouse inventory check'!$C:$C,$C60,'warehouse inventory check'!$D:$D,$D60) -> -200 | V60: =+N60 -> 724.144 | W60: =+IF(U60<>0,U60*N60,) -> -144828.8 | X60: =+I60+K60-P60-R60-W60-T60+M60 -> -5.8207661e-11 | Y60: =+G60+J60+L60-O60-Q60-S60 -> -200 | Z60: =+U60-Y60 -> 0 | AA60: Nursan’s late invoice.
A61: 56 | C61: 1 | D61: TZ38-14A033-KA | E61: EV-V4 | F61: MCA CONNECTOR CLIP | G61: 0 | H61: 1402.1367 | I61: 0 | J61: =SUMIFS('purchase data'!K:K,'purchase data'!$B:$B,$C61,'purchase data'!$F:$F,$D61) -> 0 | K61: =SUMIFS('purchase data'!M:M,'purchase data'!$B:$B,$C61,'purchase data'!$F:$F,$D61) -> 0 | L61: =SUMIFS(ETC!$G:$G,ETC!$B:$B,$C61,ETC!$E:$E,$D61) -> 0 | M61: =SUMIFS(ETC!$J:$J,ETC!$E:$E,$D61,ETC!$B:$B,$C61) -> 0 | N61: =IF(IFERROR((I61+K61+M61)/(G61+J61+SUMIFS(ETC!$G:$G,ETC!$C:$C,1,ETC!$B:$B,$C61,ETC!$E:$E,$D61)),)=0,H61,IFERROR((I61+K61+M61)/(G61+J61+SUMIFS(ETC!$G:$G,ETC!$C:$C,1,ETC!$B:$B,$C61,ETC!$E:$E,$D61)),)) -> 1402.1367 | O61: =++SUMIFS('sales data'!L:L,'sales data'!$B:$B,$C61,'sales data'!$F:$F,$D61,'sales data'!$O:$O,"") -> 21 | P61: =+IF(O61<>0,O61*N61,) -> 29444.87 | Q61: =+SUMIFS('sales data'!$L:$L,'sales data'!$B:$B,$C61,'sales data'!$F:$F,$D61,'sales data'!$O:$O,"R") -> 0 | R61: =+IF(Q61<>0,Q61*N61,) -> 0 | S61: =SUMIFS('sales data'!$L:$L,'sales data'!$B:$B,$C61,'sales data'!$F:$F,$D61,'sales data'!$O:$O,"N") -> 0 | T61: =+IF(S61<>0,S61*N61,) -> 0 | U61: =SUMIFS('warehouse inventory check'!$N:$N,'warehouse inventory check'!$C:$C,$C61,'warehouse inventory check'!$D:$D,$D61) -> -21 | V61: =+N61 -> 1402.1367 | W61: =+IF(U61<>0,U61*N61,) -> -29444.87 | X61: =+I61+K61-P61-R61-W61-T61+M61 -> 0 | Y61: =+G61+J61+L61-O61-Q61-S61 -> -21 | Z61: =+U61-Y61 -> 0 | AA61: Nursan’s late invoice.
A62: 57 | C62: 1 | D62: TZ38-14A033-LA | E62: EV-V4 | F62: MCA CONNECTOR CLIP | G62: 0 | H62: 1273.55 | I62: 0 | J62: =SUMIFS('purchase data'!K:K,'purchase data'!$B:$B,$C62,'purchase data'!$F:$F,$D62) -> 0 | K62: =SUMIFS('purchase data'!M:M,'purchase data'!$B:$B,$C62,'purchase data'!$F:$F,$D62) -> 0 | L62: =SUMIFS(ETC!$G:$G,ETC!$B:$B,$C62,ETC!$E:$E,$D62) -> 0 | M62: =SUMIFS(ETC!$J:$J,ETC!$E:$E,$D62,ETC!$B:$B,$C62) -> 0 | N62: =IF(IFERROR((I62+K62+M62)/(G62+J62+SUMIFS(ETC!$G:$G,ETC!$C:$C,1,ETC!$B:$B,$C62,ETC!$E:$E,$D62)),)=0,H62,IFERROR((I62+K62+M62)/(G62+J62+SUMIFS(ETC!$G:$G,ETC!$C:$C,1,ETC!$B:$B,$C62,ETC!$E:$E,$D62)),)) -> 1273.55 | O62: =++SUMIFS('sales data'!L:L,'sales data'!$B:$B,$C62,'sales data'!$F:$F,$D62,'sales data'!$O:$O,"") -> 7 | P62: =+IF(O62<>0,O62*N62,) -> 8914.85 | Q62: =+SUMIFS('sales data'!$L:$L,'sales data'!$B:$B,$C62,'sales data'!$F:$F,$D62,'sales data'!$O:$O,"R") -> 0 | R62: =+IF(Q62<>0,Q62*N62,) -> 0 | S62: =SUMIFS('sales data'!$L:$L,'sales data'!$B:$B,$C62,'sales data'!$F:$F,$D62,'sales data'!$O:$O,"N") -> 0 | T62: =+IF(S62<>0,S62*N62,) -> 0 | U62: =SUMIFS('warehouse inventory check'!$N:$N,'warehouse inventory check'!$C:$C,$C62,'warehouse inventory check'!$D:$D,$D62) -> -7 | V62: =+N62 -> 1273.55 | W62: =+IF(U62<>0,U62*N62,) -> -8914.85 | X62: =+I62+K62-P62-R62-W62-T62+M62 -> 0 | Y62: =+G62+J62+L62-O62-Q62-S62 -> -7 | Z62: =+U62-Y62 -> 0 | AA62: Nursan’s late invoice.
A63: 58 | C63: 1 | D63: TZ38-14A033-MA | E63: EV-V4 | F63: MCA CONNECTOR CLIP | G63: 0 | H63: 1176 | I63: 0 | J63: =SUMIFS('purchase data'!K:K,'purchase data'!$B:$B,$C63,'purchase data'!$F:$F,$D63) -> 0 | K63: =SUMIFS('purchase data'!M:M,'purchase data'!$B:$B,$C63,'purchase data'!$F:$F,$D63) -> 0 | L63: =SUMIFS(ETC!$G:$G,ETC!$B:$B,$C63,ETC!$E:$E,$D63) -> 0 | M63: =SUMIFS(ETC!$J:$J,ETC!$E:$E,$D63,ETC!$B:$B,$C63) -> 0 | N63: =IF(IFERROR((I63+K63+M63)/(G63+J63+SUMIFS(ETC!$G:$G,ETC!$C:$C,1,ETC!$B:$B,$C63,ETC!$E:$E,$D63)),)=0,H63,IFERROR((I63+K63+M63)/(G63+J63+SUMIFS(ETC!$G:$G,ETC!$C:$C,1,ETC!$B:$B,$C63,ETC!$E:$E,$D63)),)) -> 1176 | O63: =++SUMIFS('sales data'!L:L,'sales data'!$B:$B,$C63,'sales data'!$F:$F,$D63,'sales data'!$O:$O,"") -> 7 | P63: =+IF(O63<>0,O63*N63,) -> 8232 | Q63: =+SUMIFS('sales data'!$L:$L,'sales data'!$B:$B,$C63,'sales data'!$F:$F,$D63,'sales data'!$O:$O,"R") -> 0 | R63: =+IF(Q63<>0,Q63*N63,) -> 0 | S63: =SUMIFS('sales data'!$L:$L,'sales data'!$B:$B,$C63,'sales data'!$F:$F,$D63,'sales data'!$O:$O,"N") -> 0 | T63: =+IF(S63<>0,S63*N63,) -> 0 | U63: =SUMIFS('warehouse inventory check'!$N:$N,'warehouse inventory check'!$C:$C,$C63,'warehouse inventory check'!$D:$D,$D63) -> -7 | V63: =+N63 -> 1176 | W63: =+IF(U63<>0,U63*N63,) -> -8232 | X63: =+I63+K63-P63-R63-W63-T63+M63 -> 0 | Y63: =+G63+J63+L63-O63-Q63-S63 -> -7 | Z63: =+U63-Y63 -> 0 | AA63: Nursan’s late invoice.
A64: 59 | C64: 1 | D64: TZ38-14A033-NA | E64: BEV-E (AWD/RWD, V710) | F64: BUSBAR ASY | G64: 0 | H64: 689.66438 | I64: 0 | J64: =SUMIFS('purchase data'!K:K,'purchase data'!$B:$B,$C64,'purchase data'!$F:$F,$D64) -> 864 | K64: =SUMIFS('purchase data'!M:M,'purchase data'!$B:$B,$C64,'purchase data'!$F:$F,$D64) -> 628103.37 | L64: =SUMIFS(ETC!$G:$G,ETC!$B:$B,$C64,ETC!$E:$E,$D64) -> 0 | M64: =SUMIFS(ETC!$J:$J,ETC!$E:$E,$D64,ETC!$B:$B,$C64) -> 0 | N64: =IF(IFERROR((I64+K64+M64)/(G64+J64+SUMIFS(ETC!$G:$G,ETC!$C:$C,1,ETC!$B:$B,$C64,ETC!$E:$E,$D64)),)=0,H64,IFERROR((I64+K64+M64)/(G64+J64+SUMIFS(ETC!$G:$G,ETC!$C:$C,1,ETC!$B:$B,$C64,ETC!$E:$E,$D64)),)) -> 726.97149 | O64: =++SUMIFS('sales data'!L:L,'sales data'!$B:$B,$C64,'sales data'!$F:$F,$D64,'sales data'!$O:$O,"") -> 864 | P64: =+IF(O64<>0,O64*N64,) -> 628103.37 | Q64: =+SUMIFS('sales data'!$L:$L,'sales data'!$B:$B,$C64,'sales data'!$F:$F,$D64,'sales data'!$O:$O,"R") -> 0 | R64: =+IF(Q64<>0,Q64*N64,) -> 0 | S64: =SUMIFS('sales data'!$L:$L,'sales data'!$B:$B,$C64,'sales data'!$F:$F,$D64,'sales data'!$O:$O,"N") -> 0 | T64: =+IF(S64<>0,S64*N64,) -> 0 | U64: =SUMIFS('warehouse inventory check'!$N:$N,'warehouse inventory check'!$C:$C,$C64,'warehouse inventory check'!$D:$D,$D64) -> 0 | V64: =+N64 -> 726.97149 | W64: =+IF(U64<>0,U64*N64,) -> 0 | X64: =+I64+K64-P64-R64-W64-T64+M64 -> 0 | Y64: =+G64+J64+L64-O64-Q64-S64 -> 0 | Z64: =+U64-Y64 -> 0
A65: 60 | C65: 1 | D65: TZ38-14A033-PB | E65: BEV-E (AWD/RWD, V710) | F65: BUSBAR ASY | G65: 0 | H65: 623.36 | I65: 0 | J65: =SUMIFS('purchase data'!K:K,'purchase data'!$B:$B,$C65,'purchase data'!$F:$F,$D65) -> 864 | K65: =SUMIFS('purchase data'!M:M,'purchase data'!$B:$B,$C65,'purchase data'!$F:$F,$D65) -> 567413.63 | L65: =SUMIFS(ETC!$G:$G,ETC!$B:$B,$C65,ETC!$E:$E,$D65) -> 0 | M65: =SUMIFS(ETC!$J:$J,ETC!$E:$E,$D65,ETC!$B:$B,$C65) -> 0 | N65: =IF(IFERROR((I65+K65+M65)/(G65+J65+SUMIFS(ETC!$G:$G,ETC!$C:$C,1,ETC!$B:$B,$C65,ETC!$E:$E,$D65)),)=0,H65,IFERROR((I65+K65+M65)/(G65+J65+SUMIFS(ETC!$G:$G,ETC!$C:$C,1,ETC!$B:$B,$C65,ETC!$E:$E,$D65)),)) -> 656.72874 | O65: =++SUMIFS('sales data'!L:L,'sales data'!$B:$B,$C65,'sales data'!$F:$F,$D65,'sales data'!$O:$O,"") -> 1080 | P65: =+IF(O65<>0,O65*N65,) -> 709267.04 | Q65: =+SUMIFS('sales data'!$L:$L,'sales data'!$B:$B,$C65,'sales data'!$F:$F,$D65,'sales data'!$O:$O,"R") -> 0 | R65: =+IF(Q65<>0,Q65*N65,) -> 0 | S65: =SUMIFS('sales data'!$L:$L,'sales data'!$B:$B,$C65,'sales data'!$F:$F,$D65,'sales data'!$O:$O,"N") -> 0 | T65: =+IF(S65<>0,S65*N65,) -> 0 | U65: =SUMIFS('warehouse inventory check'!$N:$N,'warehouse inventory check'!$C:$C,$C65,'warehouse inventory check'!$D:$D,$D65) -> -216 | V65: =+N65 -> 656.72874 | W65: =+IF(U65<>0,U65*N65,) -> -141853.41 | X65: =+I65+K65-P65-R65-W65-T65+M65 -> 2.910383e-11 | Y65: =+G65+J65+L65-O65-Q65-S65 -> -216 | Z65: =+U65-Y65 -> 0 | AA65: Nursan’s late invoice.
A66: 61 | C66: 1 | D66: TZ38-14A033-RB | E66: BEV-E (AWD/RWD, V710) | F66: BUSBAR ASY | G66: 0 | H66: 661.405 | I66: 0 | J66: =SUMIFS('purchase data'!K:K,'purchase data'!$B:$B,$C66,'purchase data'!$F:$F,$D66) -> 864 | K66: =SUMIFS('purchase data'!M:M,'purchase data'!$B:$B,$C66,'purchase data'!$F:$F,$D66) -> 602044.71 | L66: =SUMIFS(ETC!$G:$G,ETC!$B:$B,$C66,ETC!$E:$E,$D66) -> 0 | M66: =SUMIFS(ETC!$J:$J,ETC!$E:$E,$D66,ETC!$B:$B,$C66) -> 0 | N66: =IF(IFERROR((I66+K66+M66)/(G66+J66+SUMIFS(ETC!$G:$G,ETC!$C:$C,1,ETC!$B:$B,$C66,ETC!$E:$E,$D66)),)=0,H66,IFERROR((I66+K66+M66)/(G66+J66+SUMIFS(ETC!$G:$G,ETC!$C:$C,1,ETC!$B:$B,$C66,ETC!$E:$E,$D66)),)) -> 696.81101 | O66: =++SUMIFS('sales data'!L:L,'sales data'!$B:$B,$C66,'sales data'!$F:$F,$D66,'sales data'!$O:$O,"") -> 1080 | P66: =+IF(O66<>0,O66*N66,) -> 752555.89 | Q66: =+SUMIFS('sales data'!$L:$L,'sales data'!$B:$B,$C66,'sales data'!$F:$F,$D66,'sales data'!$O:$O,"R") -> 0 | R66: =+IF(Q66<>0,Q66*N66,) -> 0 | S66: =SUMIFS('sales data'!$L:$L,'sales data'!$B:$B,$C66,'sales data'!$F:$F,$D66,'sales data'!$O:$O,"N") -> 0 | T66: =+IF(S66<>0,S66*N66,) -> 0 | U66: =SUMIFS('warehouse inventory check'!$N:$N,'warehouse inventory check'!$C:$C,$C66,'warehouse inventory check'!$D:$D,$D66) -> -216 | V66: =+N66 -> 696.81101 | W66: =+IF(U66<>0,U66*N66,) -> -150511.18 | X66: =+I66+K66-P66-R66-W66-T66+M66 -> 2.910383e-11 | Y66: =+G66+J66+L66-O66-Q66-S66 -> -216 | Z66: =+U66-Y66 -> 0 | AA66: Nursan’s late invoice.
A67: 62 | C67: 1 | D67: TZ38-14A033-SA | E67: BEV-E (AWD/RWD, V710) | F67: BUSBAR ASY | G67: 0 | H67: 755.4123 | I67: 0 | J67: =SUMIFS('purchase data'!K:K,'purchase data'!$B:$B,$C67,'purchase data'!$F:$F,$D67) -> 936 | K67: =SUMIFS('purchase data'!M:M,'purchase data'!$B:$B,$C67,'purchase data'!$F:$F,$D67) -> 741299.77 | L67: =SUMIFS(ETC!$G:$G,ETC!$B:$B,$C67,ETC!$E:$E,$D67) -> 0 | M67: =SUMIFS(ETC!$J:$J,ETC!$E:$E,$D67,ETC!$B:$B,$C67) -> 0 | N67: =IF(IFERROR((I67+K67+M67)/(G67+J67+SUMIFS(ETC!$G:$G,ETC!$C:$C,1,ETC!$B:$B,$C67,ETC!$E:$E,$D67)),)=0,H67,IFERROR((I67+K67+M67)/(G67+J67+SUMIFS(ETC!$G:$G,ETC!$C:$C,1,ETC!$B:$B,$C67,ETC!$E:$E,$D67)),)) -> 791.98693 | O67: =++SUMIFS('sales data'!L:L,'sales data'!$B:$B,$C67,'sales data'!$F:$F,$D67,'sales data'!$O:$O,"") -> 936 | P67: =+IF(O67<>0,O67*N67,) -> 741299.77 | Q67: =+SUMIFS('sales data'!$L:$L,'sales data'!$B:$B,$C67,'sales data'!$F:$F,$D67,'sales data'!$O:$O,"R") -> 0 | R67: =+IF(Q67<>0,Q67*N67,) -> 0 | S67: =SUMIFS('sales data'!$L:$L,'sales data'!$B:$B,$C67,'sales data'!$F:$F,$D67,'sales data'!$O:$O,"N") -> 0 | T67: =+IF(S67<>0,S67*N67,) -> 0 | U67: =SUMIFS('warehouse inventory check'!$N:$N,'warehouse inventory check'!$C:$C,$C67,'warehouse inventory check'!$D:$D,$D67) -> 0 | V67: =+N67 -> 791.98693 | W67: =+IF(U67<>0,U67*N67,) -> 0 | X67: =+I67+K67-P67-R67-W67-T67+M67 -> 0 | Y67: =+G67+J67+L67-O67-Q67-S67 -> 0 | Z67: =+U67-Y67 -> 0
A68: 63 | C68: 1 | D68: TZ38-14A033-TA | E68: EV-V4 | F68: BUSBAR ASY | G68: 0 | H68: 0 | I68: 0 | J68: =SUMIFS('purchase data'!K:K,'purchase data'!$B:$B,$C68,'purchase data'!$F:$F,$D68) -> 0 | K68: =SUMIFS('purchase data'!M:M,'purchase data'!$B:$B,$C68,'purchase data'!$F:$F,$D68) -> 0 | L68: =SUMIFS(ETC!$G:$G,ETC!$B:$B,$C68,ETC!$E:$E,$D68) -> 0 | M68: =SUMIFS(ETC!$J:$J,ETC!$E:$E,$D68,ETC!$B:$B,$C68) -> 0 | N68: =IF(IFERROR((I68+K68+M68)/(G68+J68+SUMIFS(ETC!$G:$G,ETC!$C:$C,1,ETC!$B:$B,$C68,ETC!$E:$E,$D68)),)=0,H68,IFERROR((I68+K68+M68)/(G68+J68+SUMIFS(ETC!$G:$G,ETC!$C:$C,1,ETC!$B:$B,$C68,ETC!$E:$E,$D68)),)) -> 0 | O68: =++SUMIFS('sales data'!L:L,'sales data'!$B:$B,$C68,'sales data'!$F:$F,$D68,'sales data'!$O:$O,"") -> 0 | P68: =+IF(O68<>0,O68*N68,) -> 0 | Q68: =+SUMIFS('sales data'!$L:$L,'sales data'!$B:$B,$C68,'sales data'!$F:$F,$D68,'sales data'!$O:$O,"R") -> 0 | R68: =+IF(Q68<>0,Q68*N68,) -> 0 | S68: =SUMIFS('sales data'!$L:$L,'sales data'!$B:$B,$C68,'sales data'!$F:$F,$D68,'sales data'!$O:$O,"N") -> 0 | T68: =+IF(S68<>0,S68*N68,) -> 0 | U68: =SUMIFS('warehouse inventory check'!$N:$N,'warehouse inventory check'!$C:$C,$C68,'warehouse inventory check'!$D:$D,$D68) -> 0 | V68: =+N68 -> 0 | W68: =+IF(U68<>0,U68*N68,) -> 0 | X68: =+I68+K68-P68-R68-W68-T68+M68 -> 0 | Y68: =+G68+J68+L68-O68-Q68-S68 -> 0 | Z68: =+U68-Y68 -> 0
