Workbook

Sheet 1. 경신전선 요약_PPT
C4: =CONCATENATE("■ ",'2. 손익계산서'!$C$4,"월 KSCI 손익/원가 요약") -> ■ 2월 KSCI 손익/원가 요약 | K4: ( 1,350 KRW/USD )
D5: 단위 | E5: 연 계획 | F5: 누적 계획 | G5: 누적 실적 | H5: 누적 달성률 | I5: 연 계획 진행률
I6: KSCI | J6: KSCM-DG | K6: KSCM-GP
C7: 매출액 | D7: 백만원 | E7: ='1. 경신전선 요약'!D6 -> 234337.43 | F7: ='1. 경신전선 요약'!F6 -> 39126.549 | G7: ='1. 경신전선 요약'!G6 -> 37335.612 | H7: =G7/F7 -> 0.95422707 | I7: ='1. 경신전선 요약'!E6 -> 0.15932415 | J7: ='1. 경신전선 요약'!E7 -> 0.1558842 | K7: ='1. 경신전선 요약'!E8 -> 0.17890508
C8: 매출동량 | D8: 톤 | E8: ='1. 경신전선 요약'!D9 -> 0 | F8: ='1. 경신전선 요약'!F9 -> 0 | G8: ='1. 경신전선 요약'!G9 -> 1346.4872 | H8: =G8/F8 -> #DIV/0! | I8: ='1. 경신전선 요약'!E9 -> 0 | J8: =I8 -> 0
C9: 영업이익 | D9: 백만원 | E9: ='1. 경신전선 요약'!D22 -> 2134.2692 | F9: ='1. 경신전선 요약'!F22 -> 1279.7307 | G9: ='1. 경신전선 요약'!G22 -> 939.36468 | H9: =IF(AND(F9>0,G9>0),G9/F9,"(-)") -> 0.73403309 | I9: ='1. 경신전선 요약'!E22 -> 0.44013411 | J9: ='1. 경신전선 요약'!E24 -> 0.24100628 | K9: ='1. 경신전선 요약'!E25 -> (-)
C10: 영업이익률 | D10: % | E10: =E9/E7 -> 0.0091076752 | F10: =F9/F7 -> 0.032707478 | G10: =G9/G7 -> 0.025160018
K11: (단위:백만원)
C12: 구 분 | D12: 전 월 실 적 | E12: 구성비 | F12: 당 월 계 획 | G12: 구성비 | H12: 당 월 실 적 | I12: 구성비 | J12: 전 월 대 비 | K12: 계 획 대 비
C13: Ⅰ. 매출액 | D13: ='1. 경신전선 요약'!I6 -> 16877.673 | E13: ='1. 경신전선 요약'!J6 -> 1 | F13: ='1. 경신전선 요약'!K6 -> 19937.239 | G13: ='1. 경신전선 요약'!L6 -> 1 | H13: ='1. 경신전선 요약'!M6 -> 20457.939 | I13: ='1. 경신전선 요약'!N6 -> 1 | J13: ='1. 경신전선 요약'!O6 -> 1.2121303 | K13: ='1. 경신전선 요약'!P6 -> 1.026117
C14: 전선 | D14: ='1. 경신전선 요약'!I7 -> 13944.597 | E14: ='1. 경신전선 요약'!J7 -> 0.82621564 | F14: ='1. 경신전선 요약'!K7 -> 16067.61 | G14: ='1. 경신전선 요약'!L7 -> 0.80590952 | H14: ='1. 경신전선 요약'!M7 -> 17126.399 | I14: ='1. 경신전선 요약'!N7 -> 0.83715173 | J14: ='1. 경신전선 요약'!O7 -> 1.2281745 | K14: ='1. 경신전선 요약'!P7 -> 1.0658958
C15: 전장 | D15: ='1. 경신전선 요약'!I8 -> 2933.0755 | E15: ='1. 경신전선 요약'!J8 -> 0.17378436 | F15: ='1. 경신전선 요약'!K8 -> 3869.6282 | G15: ='1. 경신전선 요약'!L8 -> 0.19409048 | H15: ='1. 경신전선 요약'!M8 -> 3331.54 | I15: ='1. 경신전선 요약'!N8 -> 0.16284827 | J15: ='1. 경신전선 요약'!O8 -> 1.1358521 | K15: ='1. 경신전선 요약'!P8 -> 0.86094576
C16: *매출동량(ton) | D16: ='1. 경신전선 요약'!I9 -> 631.81666 | E16: ='1. 경신전선 요약'!J9 -> 0.037435058 | F16: ='1. 경신전선 요약'!K9 -> 0 | G16: ='1. 경신전선 요약'!L9 -> 0 | H16: ='1. 경신전선 요약'!M9 -> 714.67057 | I16: ='1. 경신전선 요약'!N9 -> 0.034933654 | J16: ='1. 경신전선 요약'!O9 -> 1.131136 | K16: ='1. 경신전선 요약'!P9 -> 0
D17: ='1. 경신전선 요약'!I10 -> 0 | E17: ='1. 경신전선 요약'!J10 -> 0 | F17: ='1. 경신전선 요약'!K10 -> 0 | G17: ='1. 경신전선 요약'!L10 -> 0 | H17: ='1. 경신전선 요약'!M10 -> 0 | I17: ='1. 경신전선 요약'!N10 -> 0 | J17: ='1. 경신전선 요약'!O10 -> 0 | K17: ='1. 경신전선 요약'!P10 -> 0
C18: Ⅱ. 매출원가 | D18: ='1. 경신전선 요약'!I11 -> 15846.995 | E18: ='1. 경신전선 요약'!J11 -> 0.93893244 | F18: ='1. 경신전선 요약'!K11 -> 17905.725 | G18: ='1. 경신전선 요약'!L11 -> 0.89810458 | H18: ='1. 경신전선 요약'!M11 -> 18657.391 | I18: ='1. 경신전선 요약'!N11 -> 0.9119878 | J18: ='1. 경신전선 요약'!O11 -> 1.1773457 | K18: ='1. 경신전선 요약'!P11 -> 1.0419791
C19: 전선 | D19: ='1. 경신전선 요약'!I12 -> 12587.262 | E19: ='1. 경신전선 요약'!J12 -> 0.90266231 | F19: ='1. 경신전선 요약'!K12 -> 14311.216 | G19: ='1. 경신전선 요약'!L12 -> 0.89068723 | H19: ='1. 경신전선 요약'!M12 -> 14848.113 | I19: ='1. 경신전선 요약'!N12 -> 0.86697224 | J19: ='1. 경신전선 요약'!O12 -> 1.1796141 | K19: ='1. 경신전선 요약'!P12 -> 1.0375158
C20: 전장 | D20: ='1. 경신전선 요약'!I13 -> 3259.7321 | E20: ='1. 경신전선 요약'!J13 -> 1.11137 | F20: ='1. 경신전선 요약'!K13 -> 3594.5099 | G20: ='1. 경신전선 요약'!L13 -> 0.92890317 | H20: ='1. 경신전선 요약'!M13 -> 3809.2783 | I20: ='1. 경신전선 요약'!N13 -> 1.1433986 | J20: ='1. 경신전선 요약'!O13 -> 1.1685863 | K20: ='1. 경신전선 요약'!P13 -> 1.059749
C21: └ 기타(GP2) | D21: ='1. 경신전선 요약'!I14 -> -397.8315 | E21: ='1. 경신전선 요약'!J14 -> -0.1356363 | F21: ='1. 경신전선 요약'!K14 -> 98.292417 | G21: ='1. 경신전선 요약'!L14 -> 0.025400998 | H21: ='1. 경신전선 요약'!M14 -> 0 | I21: ='1. 경신전선 요약'!N14 -> 0 | J21: ='1. 경신전선 요약'!O14 -> 0 | K21: ='1. 경신전선 요약'!P14 -> 0
D22: ='1. 경신전선 요약'!I15 -> 0 | E22: ='1. 경신전선 요약'!J15 -> 0 | F22: ='1. 경신전선 요약'!K15 -> 0 | G22: ='1. 경신전선 요약'!L15 -> 0 | H22: ='1. 경신전선 요약'!M15 -> 0 | I22: ='1. 경신전선 요약'!N15 -> 0 | J22: ='1. 경신전선 요약'!O15 -> 0 | K22: ='1. 경신전선 요약'!P15 -> 0
C23: Ⅲ. 매출총이익 | D23: ='1. 경신전선 요약'!I16 -> 1030.6783 | E23: ='1. 경신전선 요약'!J16 -> 0.06106756 | F23: ='1. 경신전선 요약'!K16 -> 2031.5132 | G23: ='1. 경신전선 요약'!L16 -> 0.10189542 | H23: ='1. 경신전선 요약'!M16 -> 1800.5482 | I23: ='1. 경신전선 요약'!N16 -> 0.088012198 | J23: ='1. 경신전선 요약'!O16 -> 1.7469546 | K23: ='1. 경신전선 요약'!P16 -> 0.88630886
C25: Ⅳ.판매관리비 | D25: ='1. 경신전선 요약'!I18 -> 938.54183 | E25: ='1. 경신전선 요약'!J18 -> 0.055608486 | F25: ='1. 경신전선 요약'!K18 -> 1026.875 | G25: ='1. 경신전선 요약'!L18 -> 0.051505376 | H25: ='1. 경신전선 요약'!M18 -> 953.31997 | I25: ='1. 경신전선 요약'!N18 -> 0.046599023 | J25: ='1. 경신전선 요약'!O18 -> 1.0157459 | K25: ='1. 경신전선 요약'!P18 -> 0.92837004
C26: [판매비] | D26: ='1. 경신전선 요약'!I19 -> 0 | E26: ='1. 경신전선 요약'!J19 -> 0 | F26: ='1. 경신전선 요약'!K19 -> 0 | G26: ='1. 경신전선 요약'!L19 -> 0 | H26: ='1. 경신전선 요약'!M19 -> 0 | I26: ='1. 경신전선 요약'!N19 -> 0 | J26: ='1. 경신전선 요약'!O19 -> 0 | K26: ='1. 경신전선 요약'!P19 -> 0
C28: [연구개발비] | D28: ='1. 경신전선 요약'!I21 -> 0 | E28: ='1. 경신전선 요약'!J21 -> 0 | F28: ='1. 경신전선 요약'!K21 -> 0 | G28: ='1. 경신전선 요약'!L21 -> 0 | H28: ='1. 경신전선 요약'!M21 -> 0 | I28: ='1. 경신전선 요약'!N21 -> 0 | J28: ='1. 경신전선 요약'!O21 -> 0 | K28: ='1. 경신전선 요약'!P21 -> 0
C29: Ⅴ.영업이익 | D29: ='1. 경신전선 요약'!I22 -> 92.136474 | E29: ='1. 경신전선 요약'!J22 -> 0.0054590745 | F29: ='1. 경신전선 요약'!K22 -> 1004.6382 | G29: ='1. 경신전선 요약'!L22 -> 0.05039004 | H29: ='1. 경신전선 요약'!M22 -> 847.22821 | I29: ='1. 경신전선 요약'!N22 -> 0.041413175 | J29: ='1. 경신전선 요약'!O22 -> 9.1953617 | K29: ='1. 경신전선 요약'!P22 -> 0.84331669
C30: (영업이익률) | D30: ='1. 경신전선 요약'!I23 -> 0.0054590745 | F30: ='1. 경신전선 요약'!K23 -> 0.05039004 | H30: ='1. 경신전선 요약'!M23 -> 0.041413175
C31: 전선 | D31: ='1. 경신전선 요약'!I24 -> 894.79166 | E31: ='1. 경신전선 요약'!J24 -> 0.064167623 | F31: ='1. 경신전선 요약'!K24 -> 964.3922 | G31: ='1. 경신전선 요약'!L24 -> 0.060020885 | H31: ='1. 경신전선 요약'!M24 -> 1769.0229 | I31: ='1. 경신전선 요약'!N24 -> 0.10329217 | J31: ='1. 경신전선 요약'!O24 -> 1.9770222 | K31: ='1. 경신전선 요약'!P24 -> 1.8343397
C32: 전장 | D32: ='1. 경신전선 요약'!I25 -> -802.65519 | E32: ='1. 경신전선 요약'!J25 -> -0.2736565 | F32: ='1. 경신전선 요약'!K25 -> 40.246044 | G32: ='1. 경신전선 요약'!L25 -> 0.010400494 | H32: ='1. 경신전선 요약'!M25 -> -921.79474 | I32: ='1. 경신전선 요약'!N25 -> -0.27668728 | J32: ='1. 경신전선 요약'!O25 -> (-) | K32: ='1. 경신전선 요약'!P25 -> (-)
C34: 구 분 | D34: 2025년 계 획 | E34: 년계획 진척률 | F34: 누 계 계 획 | G34: 누계 실적 | H34: 달성률 | I34: 전 월 실 적 | J34: 원 가 구성비 | K34: 당 월 계 획 | L34: 당 월 실 적 | M34: 원 가 구성비 | N34: 전 월 대 비 | O34: 계 획 대 비
C35: Ⅰ. 재료비
C36: Ⅱ. 노무비
C37: Ⅲ. 경비
C38: Ⅳ. 당기총제조비용
C39: Ⅴ. 당기제품제조원가
C42: =CONCATENATE("□ ",'2. 손익계산서'!$C$4,"월 KSCM-DG 손익/원가 요약") -> □ 2월 KSCM-DG 손익/원가 요약 | K42: =+K4 -> ( 1,350 KRW/USD )
D43: 단위 | E43: 연 계획 | F43: 누적 계획 | G43: 누적 실적 | H43: 누적 달성률 | I43: 연 계획 진행률
I44: KSCI | J44: KSCM-DG | K44: KSCM-GP
C45: 매출액 | D45: 백만원 | E45: ='1. 경신전선 요약'!D38 -> 199321.01 | F45: ='1. 경신전선 요약'!F38 -> 32075.728 | G45: ='1. 경신전선 요약'!G38 -> 31070.996 | H45: =G45/F45 -> 0.96867627 | I45: =I7 -> 0.15932415 | J45: =J7 -> 0.1558842 | K45: =K7 -> 0.17890508
C46: 매출동량 | D46: 톤 | E46: ='1. 경신전선 요약'!D48 -> 0 | F46: ='1. 경신전선 요약'!F48 -> 0 | G46: ='1. 경신전선 요약'!G48 -> 1346.4872 | H46: =G46/F46 -> #DIV/0! | I46: =I8 -> 0 | J46: =J8 -> 0
C47: 영업이익 | D47: 백만원 | E47: ='1. 경신전선 요약'!D58 -> 11052.884 | F47: ='1. 경신전선 요약'!F58 -> 1726.3818 | G47: ='1. 경신전선 요약'!G58 -> 2663.8146 | H47: =IF(AND(F47>0,G47>0),G47/F47,"(-)") -> 1.5430043 | I47: =I9 -> 0.44013411 | J47: =J9 -> 0.24100628 | K47: =K9 -> (-)
C48: 영업이익률 | D48: % | E48: =E47/E45 -> 0.055452681 | F48: =F47/F45 -> 0.053822062 | G48: =G47/G45 -> 0.085733157
C50: 구 분 | D50: 전 월 실 적 | E50: 매 출 구성비 | F50: 당 월 계 획 | G50: 매 출 구성비 | H50: 당 월 실 적 | I50: 매 출 구성비 | J50: 전 월 대 비 | K50: 계 획 대 비
C51: Ⅰ. 매출액 | D51: ='1. 경신전선 요약'!I38 -> 13944.597 | E51: ='1. 경신전선 요약'!J38 -> 1 | F51: ='1. 경신전선 요약'!K38 -> 16067.61 | G51: ='1. 경신전선 요약'!L38 -> 1 | H51: ='1. 경신전선 요약'!M38 -> 17126.399 | I51: ='1. 경신전선 요약'!N38 -> 1 | J51: ='1. 경신전선 요약'!O38 -> 1.2281745 | K51: ='1. 경신전선 요약'!P38 -> 1.0658958
C52: - 제품 | D52: ='1. 경신전선 요약'!I39 -> 11979.263 | E52: ='1. 경신전선 요약'!J39 -> 0.85906126 | F52: ='1. 경신전선 요약'!K39 -> 13002.955 | G52: ='1. 경신전선 요약'!L39 -> 0.80926501 | H52: ='1. 경신전선 요약'!M39 -> 13146.214 | I52: ='1. 경신전선 요약'!N39 -> 0.76759944 | J52: ='1. 경신전선 요약'!O39 -> 1.0974143 | K52: ='1. 경신전선 요약'!P39 -> 1.0110174
C53: - 상품 | D53: ='1. 경신전선 요약'!I40 -> 1965.3339 | E53: ='1. 경신전선 요약'!J40 -> 0.14093874 | F53: ='1. 경신전선 요약'!K40 -> 3064.6555 | G53: ='1. 경신전선 요약'!L40 -> 0.19073499 | H53: ='1. 경신전선 요약'!M40 -> 3980.1847 | I53: ='1. 경신전선 요약'!N40 -> 0.23240056 | J53: ='1. 경신전선 요약'!O40 -> 2.0251951 | K53: ='1. 경신전선 요약'!P40 -> 1.2987381
C54: DAWS | D54: ='1. 경신전선 요약'!I41 -> 6653.3661 | E54: ='1. 경신전선 요약'!J41 -> 0.47712859 | F54: ='1. 경신전선 요약'!K41 -> 7192.9711 | G54: ='1. 경신전선 요약'!L41 -> 0.447669 | H54: ='1. 경신전선 요약'!M41 -> 9748.5749 | I54: ='1. 경신전선 요약'!N41 -> 0.56921334 | J54: ='1. 경신전선 요약'!O41 -> 1.4652094 | K54: ='1. 경신전선 요약'!P41 -> 1.3552918
C55: HEDS | D55: ='1. 경신전선 요약'!I42 -> 1399.9958 | E55: ='1. 경신전선 요약'!J42 -> 0.10039701 | F55: ='1. 경신전선 요약'!K42 -> 2028.5095 | G55: ='1. 경신전선 요약'!L42 -> 0.12624836 | H55: ='1. 경신전선 요약'!M42 -> 1758.481 | I55: ='1. 경신전선 요약'!N42 -> 0.10267663 | J55: ='1. 경신전선 요약'!O42 -> 1.2560616 | K55: ='1. 경신전선 요약'!P42 -> 0.86688331
C56: CEWS | D56: ='1. 경신전선 요약'!I43 -> 1518.0116 | E56: ='1. 경신전선 요약'!J43 -> 0.10886019 | F56: ='1. 경신전선 요약'!K43 -> 2169.7292 | G56: ='1. 경신전선 요약'!L43 -> 0.13503745 | H56: ='1. 경신전선 요약'!M43 -> 2266.6808 | I56: ='1. 경신전선 요약'!N43 -> 0.13235011 | J56: ='1. 경신전선 요약'!O43 -> 1.4931907 | K56: ='1. 경신전선 요약'!P43 -> 1.0446837
C57: LEAR | D57: ='1. 경신전선 요약'!I44 -> 2584.558 | E57: ='1. 경신전선 요약'!J44 -> 0.18534476 | F57: ='1. 경신전선 요약'!K44 -> 1865.1305 | G57: ='1. 경신전선 요약'!L44 -> 0.11608014 | H57: ='1. 경신전선 요약'!M44 -> 1831.2278 | I57: ='1. 경신전선 요약'!N44 -> 0.10692427 | J57: ='1. 경신전선 요약'!O44 -> 0.70852646 | K57: ='1. 경신전선 요약'!P44 -> 0.98182287
C58: KAC-OB | D58: ='1. 경신전선 요약'!I45 -> 1128.1815 | E58: ='1. 경신전선 요약'!J45 -> 0.08090456 | F58: ='1. 경신전선 요약'!K45 -> 1253.1632 | G58: ='1. 경신전선 요약'!L45 -> 0.077993127 | H58: ='1. 경신전선 요약'!M45 -> 709.85741 | I58: ='1. 경신전선 요약'!N45 -> 0.041448141 | J58: ='1. 경신전선 요약'!O45 -> 0.62920496 | K58: ='1. 경신전선 요약'!P45 -> 0.56645249
C59: SUMITOMO | D59: ='1. 경신전선 요약'!I46 -> 163.25667 | E59: ='1. 경신전선 요약'!J46 -> 0.011707522 | F59: ='1. 경신전선 요약'!K46 -> 941.58537 | G59: ='1. 경신전선 요약'!L46 -> 0.058601456 | H59: ='1. 경신전선 요약'!M46 -> 32.222543 | I59: ='1. 경신전선 요약'!N46 -> 0.0018814546 | J59: ='1. 경신전선 요약'!O46 -> 0.19737351 | K59: ='1. 경신전선 요약'!P46 -> 0.034221584
C60: 기타 | D60: ='1. 경신전선 요약'!I47 -> 497.22756 | E60: ='1. 경신전선 요약'!J47 -> 0.035657362 | F60: ='1. 경신전선 요약'!K47 -> 616.52173 | G60: ='1. 경신전선 요약'!L47 -> 0.038370467 | H60: ='1. 경신전선 요약'!M47 -> 779.35474 | I60: ='1. 경신전선 요약'!N47 -> 0.045506048 | J60: ='1. 경신전선 요약'!O47 -> 1.5674005 | K60: ='1. 경신전선 요약'!P47 -> 1.2641156
C61: (매출동량) | D61: ='1. 경신전선 요약'!I48 -> 631.81666 | E61: ='1. 경신전선 요약'!J48 -> 0.045309065 | F61: ='1. 경신전선 요약'!K48 -> 0 | G61: ='1. 경신전선 요약'!L48 -> 0 | H61: ='1. 경신전선 요약'!M48 -> 714.67057 | I61: ='1. 경신전선 요약'!N48 -> 0.041729179 | J61: ='1. 경신전선 요약'!O48 -> 1.131136 | K61: ='1. 경신전선 요약'!P48 -> 0
D62: ='1. 경신전선 요약'!I49 -> 0 | E62: ='1. 경신전선 요약'!J49 -> 0 | F62: ='1. 경신전선 요약'!K49 -> 0 | G62: ='1. 경신전선 요약'!L49 -> 0 | H62: ='1. 경신전선 요약'!M49 -> 0 | I62: ='1. 경신전선 요약'!N49 -> 0 | J62: ='1. 경신전선 요약'!O49 -> 0 | K62: ='1. 경신전선 요약'!P49 -> 0
C63: Ⅱ. 매출원가 | D63: ='1. 경신전선 요약'!I50 -> 12587.262 | E63: ='1. 경신전선 요약'!J50 -> 0.90266231 | F63: ='1. 경신전선 요약'!K50 -> 14311.216 | G63: ='1. 경신전선 요약'!L50 -> 0.89068723 | H63: ='1. 경신전선 요약'!M50 -> 14848.113 | I63: ='1. 경신전선 요약'!N50 -> 0.86697224 | J63: ='1. 경신전선 요약'!O50 -> 1.1796141 | K63: ='1. 경신전선 요약'!P50 -> 1.0375158
C65: Ⅲ. 매출총이익 | D65: ='1. 경신전선 요약'!I52 -> 1357.3349 | E65: ='1. 경신전선 요약'!J52 -> 0.097337688 | F65: ='1. 경신전선 요약'!K52 -> 1756.3949 | G65: ='1. 경신전선 요약'!L52 -> 0.10931277 | H65: ='1. 경신전선 요약'!M52 -> 2278.2865 | I65: ='1. 경신전선 요약'!N52 -> 0.13302776 | J65: ='1. 경신전선 요약'!O52 -> 1.6784999 | K65: ='1. 경신전선 요약'!P52 -> 1.2971379
C67: Ⅳ.판매관리비 | D67: ='1. 경신전선 요약'!I54 -> 462.5432 | E67: ='1. 경신전선 요약'!J54 -> 0.033170065 | F67: ='1. 경신전선 요약'!K54 -> 792.00274 | G67: ='1. 경신전선 요약'!L54 -> 0.049291881 | H67: ='1. 경신전선 요약'!M54 -> 509.26351 | I67: ='1. 경신전선 요약'!N54 -> 0.029735586 | J67: ='1. 경신전선 요약'!O54 -> 1.1010075 | K67: ='1. 경신전선 요약'!P54 -> 0.64300726
C68: [판매비] | D68: ='2. 손익계산서'!C112*$N$4/1000000 -> 0 | E68: =IFERROR(D68/$I$38,) -> 0 | F68: ='2. 손익계산서'!E112*$N$4/1000000 -> 0 | G68: =IFERROR(F68/$K$38,) -> 0 | H68: ='2. 손익계산서'!G112*$N$4/1000000 -> 0 | I68: =IFERROR(H68/$M$38,) -> 0 | J68: =IFERROR(H68/D68,) -> 0 | K68: =IFERROR(H68/F68,) -> 0
C70: [연구개발비] | D70: ='2. 손익계산서'!C146*$N$4/1000000 -> 0 | E70: =IFERROR(D70/$I$38,) -> 0 | F70: ='2. 손익계산서'!E146*$N$4/1000000 -> 0 | G70: =IFERROR(F70/$K$38,) -> 0 | H70: ='2. 손익계산서'!G146*$N$4/1000000 -> 0 | I70: =IFERROR(H70/$M$38,) -> 0 | J70: =IFERROR(H70/D70,) -> 0 | K70: =IFERROR(H70/F70,) -> 0
C71: Ⅴ.영업이익 | D71: ='1. 경신전선 요약'!I58 -> 894.79166 | E71: ='1. 경신전선 요약'!J58 -> 0.064167623 | F71: ='1. 경신전선 요약'!K58 -> 964.3922 | G71: ='1. 경신전선 요약'!L58 -> 0.060020885 | H71: ='1. 경신전선 요약'!M58 -> 1769.0229 | I71: ='1. 경신전선 요약'!N58 -> 0.10329217 | J71: ='1. 경신전선 요약'!O58 -> 1.9770222 | K71: ='1. 경신전선 요약'!P58 -> 1.8343397
C72: (이익률) | D72: ='1. 경신전선 요약'!I59 -> 0.064167623 | F72: ='1. 경신전선 요약'!K59 -> 0.060020885 | H72: ='1. 경신전선 요약'!M59 -> 0.10329217
C75: ='1. 경신전선 요약'!C62 -> □ 2월 KSCM-GP 손익/원가 요약 | K75: =+K42 -> ( 1,350 KRW/USD )
D76: 단위 | E76: 연 계획 | F76: 누적 계획 | G76: 누적 실적 | H76: 누적 달성률 | I76: 연 계획 진행률
I77: KSCI | J77: KSCM-DG | K77: KSCM-GP
C78: 매출액 | D78: 백만원 | E78: ='1. 경신전선 요약'!D64 -> 35016.42 | F78: ='1. 경신전선 요약'!F64 -> 7050.8207 | G78: ='1. 경신전선 요약'!G64 -> 6264.6155 | H78: =G78/F78 -> 0.88849452 | I78: =I7 -> 0.15932415 | J78: =J7 -> 0.1558842 | K78: =K7 -> 0.17890508
C79: 영업이익 | D79: 백만원 | E79: ='1. 경신전선 요약'!D78 -> -8918.6153 | F79: ='1. 경신전선 요약'!F78 -> -446.65111 | G79: ='1. 경신전선 요약'!G78 -> -1724.4499 | H79: =IF(AND(F79>0,G79>0),G79/F79,"(-)") -> (-) | I79: =I9 -> 0.44013411 | J79: =J9 -> 0.24100628 | K79: =K9 -> (-)
C80: 영업이익률 | D80: % | E80: =E79/E78 -> -0.25469809 | F80: =F79/F78 -> -0.063347392 | G80: =G79/G78 -> -0.27526828
C82: 구 분 | D82: 전 월 실 적 | E82: 매 출 구성비 | F82: 당 월 계 획 | G82: 매 출 구성비 | H82: 당 월 실 적 | I82: 매 출 구성비 | J82: 전 월 대 비 | K82: 계 획 대 비
C83: Ⅰ. 매출액 | D83: ='1. 경신전선 요약'!I64 -> 2933.0755 | E83: ='1. 경신전선 요약'!J64 -> 1 | F83: ='1. 경신전선 요약'!K64 -> 3869.6282 | G83: ='1. 경신전선 요약'!L64 -> 1 | H83: ='1. 경신전선 요약'!M64 -> 3331.54 | I83: ='1. 경신전선 요약'!N64 -> 1 | J83: ='1. 경신전선 요약'!O64 -> 1.1358521 | K83: ='1. 경신전선 요약'!P64 -> 0.86094576
C84: KLSE | D84: ='1. 경신전선 요약'!I65 -> 2880.2947 | E84: ='1. 경신전선 요약'!J65 -> 0.98200494 | F84: ='1. 경신전선 요약'!K65 -> 3008.3442 | G84: ='1. 경신전선 요약'!L65 -> 0.77742461 | H84: ='1. 경신전선 요약'!M65 -> 3109.7147 | I84: ='1. 경신전선 요약'!N65 -> 0.9334166 | J84: ='1. 경신전선 요약'!O65 -> 1.0796516 | K84: ='1. 경신전선 요약'!P65 -> 1.0336965
C85: Ford | D85: ='1. 경신전선 요약'!I66 -> 36.123152 | E85: ='1. 경신전선 요약'!J66 -> 0.012315793 | F85: ='1. 경신전선 요약'!K66 -> 861.28402 | G85: ='1. 경신전선 요약'!L66 -> 0.22257539 | H85: ='1. 경신전선 요약'!M66 -> 206.78756 | I85: ='1. 경신전선 요약'!N66 -> 0.062069662 | J85: ='1. 경신전선 요약'!O66 -> 5.724516 | K85: ='1. 경신전선 요약'!P66 -> 0.24009218
C86: SKI | D86: ='1. 경신전선 요약'!I67 -> -13.496166 | E86: ='1. 경신전선 요약'!J67 -> -0.0046013701 | F86: ='1. 경신전선 요약'!K67 -> 0 | G86: ='1. 경신전선 요약'!L67 -> 0 | H86: ='1. 경신전선 요약'!M67 -> 0 | I86: ='1. 경신전선 요약'!N67 -> 0 | J86: ='1. 경신전선 요약'!O67 -> 0 | K86: ='1. 경신전선 요약'!P67 -> 0
C87: 기타 | D87: ='1. 경신전선 요약'!I68 -> 30.153897 | E87: ='1. 경신전선 요약'!J68 -> 0.010280641 | F87: ='1. 경신전선 요약'!K68 -> 0 | G87: ='1. 경신전선 요약'!L68 -> 0 | H87: ='1. 경신전선 요약'!M68 -> 15.03769 | I87: ='1. 경신전선 요약'!N68 -> 0.0045137356 | J87: ='1. 경신전선 요약'!O68 -> 0.49869808 | K87: ='1. 경신전선 요약'!P68 -> 0
D88: ='1. 경신전선 요약'!I69 -> 0 | E88: ='1. 경신전선 요약'!J69 -> 0 | F88: ='1. 경신전선 요약'!K69 -> 0 | G88: ='1. 경신전선 요약'!L69 -> 0 | H88: ='1. 경신전선 요약'!M69 -> 0 | I88: ='1. 경신전선 요약'!N69 -> 0 | J88: ='1. 경신전선 요약'!O69 -> 0 | K88: ='1. 경신전선 요약'!P69 -> 0
C89: Ⅱ. 매출원가 | D89: ='1. 경신전선 요약'!I70 -> 3259.7321 | E89: ='1. 경신전선 요약'!J70 -> 1.11137 | F89: ='1. 경신전선 요약'!K70 -> 3594.5099 | G89: ='1. 경신전선 요약'!L70 -> 0.92890317 | H89: ='1. 경신전선 요약'!M70 -> 3809.2783 | I89: ='1. 경신전선 요약'!N70 -> 1.1433986 | J89: ='1. 경신전선 요약'!O70 -> 1.1685863 | K89: ='1. 경신전선 요약'!P70 -> 1.059749
C91: Ⅲ. 매출총이익 | D91: ='1. 경신전선 요약'!I72 -> -326.65656 | E91: ='1. 경신전선 요약'!J72 -> -0.11136998 | F91: ='1. 경신전선 요약'!K72 -> 275.11828 | G91: ='1. 경신전선 요약'!L72 -> 0.071096826 | H91: ='1. 경신전선 요약'!M72 -> -477.73828 | I91: ='1. 경신전선 요약'!N72 -> -0.14339863 | J91: ='1. 경신전선 요약'!O72 -> (-) | K91: ='1. 경신전선 요약'!P72 -> (-)
C93: Ⅳ.판매관리비 | D93: ='1. 경신전선 요약'!I74 -> 475.99863 | E93: ='1. 경신전선 요약'!J74 -> 0.16228652 | F93: ='1. 경신전선 요약'!K74 -> 234.87224 | G93: ='1. 경신전선 요약'!L74 -> 0.060696332 | H93: ='1. 경신전선 요약'!M74 -> 444.05646 | I93: ='1. 경신전선 요약'!N74 -> 0.13328865 | J93: ='1. 경신전선 요약'!O74 -> 0.9328944 | K93: ='1. 경신전선 요약'!P74 -> 1.8906298
C94: [판매비] | D94: ='2. 손익계산서'!H188*$N$4/1000000 -> 0 | E94: =IFERROR(D94/$I$64,) -> 0 | F94: ='2. 손익계산서'!J188*$N$4/1000000 -> 0 | G94: =IFERROR(F94/$K$64,) -> 0 | H94: ='2. 손익계산서'!L188*$N$4/1000000 -> 0 | I94: =IFERROR(H94/$M$64,) -> 0 | J94: =IFERROR(H94/D94,) -> 0 | K94: =IFERROR(H94/F94,) -> 0
C96: [연구개발비] | D96: ='2. 손익계산서'!H222*$N$4/1000000 -> 0 | E96: =IFERROR(D96/$I$64,) -> 0 | F96: ='2. 손익계산서'!J222*$N$4/1000000 -> 0 | G96: =IFERROR(F96/$K$64,) -> 0 | H96: ='2. 손익계산서'!L222*$N$4/1000000 -> 0 | I96: =IFERROR(H96/$M$64,) -> 0 | J96: =IFERROR(H96/D96,) -> 0 | K96: =IFERROR(H96/F96,) -> 0
C97: Ⅴ.영업이익 | D97: ='1. 경신전선 요약'!I78 -> -802.65519 | E97: ='1. 경신전선 요약'!J78 -> -0.2736565 | F97: ='1. 경신전선 요약'!K78 -> 40.246044 | G97: ='1. 경신전선 요약'!L78 -> 0.010400494 | H97: ='1. 경신전선 요약'!M78 -> -921.79474 | I97: ='1. 경신전선 요약'!N78 -> -0.27668728 | J97: ='1. 경신전선 요약'!O78 -> (-) | K97: ='1. 경신전선 요약'!P78 -> (-)
C98: (이익률) | D98: ='1. 경신전선 요약'!I79 -> -0.2736565 | F98: ='1. 경신전선 요약'!K79 -> 0.010400494 | H98: ='1. 경신전선 요약'!M79 -> -0.27668728

Sheet 1. 경신전선 요약_PPT_1월임시
C4: =CONCATENATE("■ ",'2. 손익계산서'!$C$4,"월 KSCI 손익/원가 요약") -> ■ 2월 KSCI 손익/원가 요약 | K4: ( 1,350 KRW/USD )
D5: 단위 | E5: 연 계획 | F5: 누적 계획 | G5: 누적 실적 | H5: 누적 달성률 | I5: 연 계획 진행률
I6: KSCI | J6: KSCM-DG | K6: KSCM-GP
C7: 매출액 | D7: 백만원 | E7: ='1. 경신전선 요약'!D6 -> 234337.43 | F7: ='1. 경신전선 요약'!F6 -> 39126.549 | G7: ='1. 경신전선 요약'!G6 -> 37335.612 | H7: =G7/F7 -> 0.95422707 | I7: ='1. 경신전선 요약'!E6 -> 0.15932415 | J7: ='1. 경신전선 요약'!E7 -> 0.1558842 | K7: ='1. 경신전선 요약'!E8 -> 0.17890508
C8: 매출동량 | D8: 톤 | E8: ='1. 경신전선 요약'!D9 -> 0 | F8: ='1. 경신전선 요약'!F9 -> 0 | G8: ='1. 경신전선 요약'!G9 -> 1346.4872 | H8: =G8/F8 -> #DIV/0! | I8: ='1. 경신전선 요약'!E9 -> 0 | J8: =I8 -> 0
C9: 영업이익 | D9: 백만원 | E9: ='1. 경신전선 요약'!D22 -> 2134.2692 | F9: ='1. 경신전선 요약'!F22 -> 1279.7307 | G9: ='1. 경신전선 요약'!G22 -> 939.36468 | H9: =IF(AND(F9>0,G9>0),G9/F9,"(-)") -> 0.73403309 | I9: ='1. 경신전선 요약'!E22 -> 0.44013411 | J9: ='1. 경신전선 요약'!E24 -> 0.24100628 | K9: ='1. 경신전선 요약'!E25 -> (-)
C10: 영업이익률 | D10: % | E10: =E9/E7 -> 0.0091076752 | F10: =F9/F7 -> 0.032707478 | G10: =G9/G7 -> 0.025160018
K11: (단위:백만원)
C12: 구 분 | D12: 전 월 실 적 | E12: 구성비 | F12: 당 월 계 획 | G12: 구성비 | H12: 당 월 실 적 | I12: 구성비 | J12: 전 월 대 비 | K12: 계 획 대 비
C13: Ⅰ. 매출액 | D13: 13091.9 | E13: 1 | F13: ='1. 경신전선 요약'!K6 -> 19937.239 | G13: ='1. 경신전선 요약'!L6 -> 1 | H13: ='1. 경신전선 요약'!M6 -> 20457.939 | I13: ='1. 경신전선 요약'!N6 -> 1 | J13: =IF(D13>0,H13/D13,"(-)") -> 1.562641 | K13: ='1. 경신전선 요약'!P6 -> 1.026117
C14: 전선 | D14: 9928.7936 | E14: 0.75839214 | F14: ='1. 경신전선 요약'!K7 -> 16067.61 | G14: ='1. 경신전선 요약'!L7 -> 0.80590952 | H14: ='1. 경신전선 요약'!M7 -> 17126.399 | I14: ='1. 경신전선 요약'!N7 -> 0.83715173 | J14: =IF(D14>0,H14/D14,"(-)") -> 1.7249225 | K14: ='1. 경신전선 요약'!P7 -> 1.0658958
C15: 전장 | D15: 3163.1059 | E15: 0.24160786 | F15: ='1. 경신전선 요약'!K8 -> 3869.6282 | G15: ='1. 경신전선 요약'!L8 -> 0.19409048 | H15: ='1. 경신전선 요약'!M8 -> 3331.54 | I15: ='1. 경신전선 요약'!N8 -> 0.16284827 | J15: =IF(D15>0,H15/D15,"(-)") -> 1.0532496 | K15: ='1. 경신전선 요약'!P8 -> 0.86094576
C16: *매출동량(ton) | D16: 476.23611 | E16: 0.036376395 | F16: ='1. 경신전선 요약'!K9 -> 0 | G16: ='1. 경신전선 요약'!L9 -> 0 | H16: ='1. 경신전선 요약'!M9 -> 714.67057 | I16: ='1. 경신전선 요약'!N9 -> 0.034933654 | J16: =+H16/D16 -> 1.5006644 | K16: ='1. 경신전선 요약'!P9 -> 0
D17: 0 | E17: 0 | F17: ='1. 경신전선 요약'!K10 -> 0 | G17: ='1. 경신전선 요약'!L10 -> 0 | H17: ='1. 경신전선 요약'!M10 -> 0 | I17: ='1. 경신전선 요약'!N10 -> 0 | J17: =+H17/D17 -> #DIV/0! | K17: ='1. 경신전선 요약'!P10 -> 0
C18: Ⅱ. 매출원가 | D18: 12827.821 | E18: 0.97982887 | F18: ='1. 경신전선 요약'!K11 -> 17905.725 | G18: ='1. 경신전선 요약'!L11 -> 0.89810458 | H18: ='1. 경신전선 요약'!M11 -> 18657.391 | I18: ='1. 경신전선 요약'!N11 -> 0.9119878 | J18: =IF(D18>0,H18/D18,"(-)") -> 1.4544474 | K18: ='1. 경신전선 요약'!P11 -> 1.0419791
C19: 전선 | D19: 9050.1099 | E19: 0.91150146 | F19: ='1. 경신전선 요약'!K12 -> 14311.216 | G19: ='1. 경신전선 요약'!L12 -> 0.89068723 | H19: ='1. 경신전선 요약'!M12 -> 14848.113 | I19: ='1. 경신전선 요약'!N12 -> 0.86697224 | J19: =IF(D19>0,H19/D19,"(-)") -> 1.6406555 | K19: ='1. 경신전선 요약'!P12 -> 1.0375158
C20: 전장 | D20: 3777.7112 | E20: 1.1943044 | F20: ='1. 경신전선 요약'!K13 -> 3594.5099 | G20: ='1. 경신전선 요약'!L13 -> 0.92890317 | H20: ='1. 경신전선 요약'!M13 -> 3809.2783 | I20: ='1. 경신전선 요약'!N13 -> 1.1433986 | J20: =IF(D20>0,H20/D20,"(-)") -> 1.0083561 | K20: ='1. 경신전선 요약'!P13 -> 1.059749
C21: └ 기타(GP2) | D21: -216.33365 | E21: -0.068392793 | F21: ='1. 경신전선 요약'!K14 -> 98.292417 | G21: ='1. 경신전선 요약'!L14 -> 0.025400998 | H21: ='1. 경신전선 요약'!M14 -> 0 | I21: ='1. 경신전선 요약'!N14 -> 0 | J21: =IF(D21>0,H21/D21,"(-)") -> (-) | K21: ='1. 경신전선 요약'!P14 -> 0
D22: 0 | E22: 0 | F22: ='1. 경신전선 요약'!K15 -> 0 | G22: ='1. 경신전선 요약'!L15 -> 0 | H22: ='1. 경신전선 요약'!M15 -> 0 | I22: ='1. 경신전선 요약'!N15 -> 0 | J22: ='1. 경신전선 요약'!O15 -> 0 | K22: ='1. 경신전선 요약'!P15 -> 0
C23: Ⅲ. 매출총이익 | D23: 264.07841 | E23: 0.02017113 | F23: ='1. 경신전선 요약'!K16 -> 2031.5132 | G23: ='1. 경신전선 요약'!L16 -> 0.10189542 | H23: ='1. 경신전선 요약'!M16 -> 1800.5482 | I23: ='1. 경신전선 요약'!N16 -> 0.088012198 | J23: =IF(D23>0,H23/D23,"(-)") -> 6.8182331 | K23: ='1. 경신전선 요약'!P16 -> 0.88630886
C25: Ⅳ.판매관리비 | D25: 1070.2549 | E25: 0.081749399 | F25: ='1. 경신전선 요약'!K18 -> 1026.875 | G25: ='1. 경신전선 요약'!L18 -> 0.051505376 | H25: ='1. 경신전선 요약'!M18 -> 953.31997 | I25: ='1. 경신전선 요약'!N18 -> 0.046599023 | J25: =IF(D25>0,H25/D25,"(-)") -> 0.89074103 | K25: ='1. 경신전선 요약'!P18 -> 0.92837004
C26: [판매비] | D26: 0 | E26: 0 | F26: ='1. 경신전선 요약'!K19 -> 0 | G26: ='1. 경신전선 요약'!L19 -> 0 | H26: ='1. 경신전선 요약'!M19 -> 0 | I26: ='1. 경신전선 요약'!N19 -> 0 | J26: ='1. 경신전선 요약'!O19 -> 0 | K26: ='1. 경신전선 요약'!P19 -> 0
C28: [연구개발비] | D28: 0 | E28: 0 | F28: ='1. 경신전선 요약'!K21 -> 0 | G28: ='1. 경신전선 요약'!L21 -> 0 | H28: ='1. 경신전선 요약'!M21 -> 0 | I28: ='1. 경신전선 요약'!N21 -> 0 | J28: ='1. 경신전선 요약'!O21 -> 0 | K28: ='1. 경신전선 요약'!P21 -> 0
C29: Ⅴ.영업이익 | D29: -806.17651 | E29: -0.061578269 | F29: ='1. 경신전선 요약'!K22 -> 1004.6382 | G29: ='1. 경신전선 요약'!L22 -> 0.05039004 | H29: ='1. 경신전선 요약'!M22 -> 847.22821 | I29: ='1. 경신전선 요약'!N22 -> 0.041413175 | J29: =IF(D29>0,H29/D29,"(-)") -> (-) | K29: ='1. 경신전선 요약'!P22 -> 0.84331669
C30: (영업이익률) | D30: -0.061578269 | F30: ='1. 경신전선 요약'!K23 -> 0.05039004 | H30: ='1. 경신전선 요약'!M23 -> 0.041413175
C31: 전선 | D31: 237.39407 | E31: 0.023909659 | F31: ='1. 경신전선 요약'!K24 -> 964.3922 | G31: ='1. 경신전선 요약'!L24 -> 0.060020885 | H31: ='1. 경신전선 요약'!M24 -> 1769.0229 | I31: ='1. 경신전선 요약'!N24 -> 0.10329217 | J31: =IF(D31>0,H31/D31,"(-)") -> 7.4518414 | K31: ='1. 경신전선 요약'!P24 -> 1.8343397
C32: 전장 | D32: -1043.5706 | E32: -0.32991959 | F32: ='1. 경신전선 요약'!K25 -> 40.246044 | G32: ='1. 경신전선 요약'!L25 -> 0.010400494 | H32: ='1. 경신전선 요약'!M25 -> -921.79474 | I32: ='1. 경신전선 요약'!N25 -> -0.27668728 | J32: =IF(D32>0,H32/D32,"(-)") -> (-) | K32: ='1. 경신전선 요약'!P25 -> (-)
C34: 구 분 | D34: 2025년 계 획 | E34: 년계획 진척률 | F34: 누 계 계 획 | G34: 누계 실적 | H34: 달성률 | I34: 전 월 실 적 | J34: 원 가 구성비 | K34: 당 월 계 획 | L34: 당 월 실 적 | M34: 원 가 구성비 | N34: 전 월 대 비 | O34: 계 획 대 비
C35: Ⅰ. 재료비
C36: Ⅱ. 노무비
C37: Ⅲ. 경비
C38: Ⅳ. 당기총제조비용
C39: Ⅴ. 당기제품제조원가
C42: =CONCATENATE("□ ",'2. 손익계산서'!$C$4,"월 KSCM-DG 손익/원가 요약") -> □ 2월 KSCM-DG 손익/원가 요약 | K42: =+K4 -> ( 1,350 KRW/USD )
D43: 단위 | E43: 연 계획 | F43: 누적 계획 | G43: 누적 실적 | H43: 누적 달성률 | I43: 연 계획 진행률
I44: KSCI | J44: KSCM-DG | K44: KSCM-GP
C45: 매출액 | D45: 백만원 | E45: ='1. 경신전선 요약'!D38 -> 199321.01 | F45: ='1. 경신전선 요약'!F38 -> 32075.728 | G45: ='1. 경신전선 요약'!G38 -> 31070.996 | H45: =G45/F45 -> 0.96867627 | I45: =I7 -> 0.15932415 | J45: =J7 -> 0.1558842 | K45: =K7 -> 0.17890508
C46: 매출동량 | D46: 톤 | E46: ='1. 경신전선 요약'!D48 -> 0 | F46: ='1. 경신전선 요약'!F48 -> 0 | G46: ='1. 경신전선 요약'!G48 -> 1346.4872 | H46: =G46/F46 -> #DIV/0! | I46: =I8 -> 0 | J46: =J8 -> 0
C47: 영업이익 | D47: 백만원 | E47: ='1. 경신전선 요약'!D58 -> 11052.884 | F47: ='1. 경신전선 요약'!F58 -> 1726.3818 | G47: ='1. 경신전선 요약'!G58 -> 2663.8146 | H47: =IF(AND(F47>0,G47>0),G47/F47,"(-)") -> 1.5430043 | I47: =I9 -> 0.44013411 | J47: =J9 -> 0.24100628 | K47: =K9 -> (-)
C48: 영업이익률 | D48: % | E48: =E47/E45 -> 0.055452681 | F48: =F47/F45 -> 0.053822062 | G48: =G47/G45 -> 0.085733157
C50: 구 분 | D50: 전 월 실 적 | E50: 매 출 구성비 | F50: 당 월 계 획 | G50: 매 출 구성비 | H50: 당 월 실 적 | I50: 매 출 구성비 | J50: 전 월 대 비 | K50: 계 획 대 비
C51: Ⅰ. 매출액 | D51: 9928.7936 | E51: 1 | F51: ='1. 경신전선 요약'!K38 -> 16067.61 | G51: ='1. 경신전선 요약'!L38 -> 1 | H51: ='1. 경신전선 요약'!M38 -> 17126.399 | I51: ='1. 경신전선 요약'!N38 -> 1 | J51: =IF(D51>0,H51/D51,"(-)") -> 1.7249225 | K51: ='1. 경신전선 요약'!P38 -> 1.0658958
C52: - 제품 | D52: 7603.2815 | E52: 0.765781 | F52: ='1. 경신전선 요약'!K39 -> 13002.955 | G52: ='1. 경신전선 요약'!L39 -> 0.80926501 | H52: ='1. 경신전선 요약'!M39 -> 13146.214 | I52: ='1. 경신전선 요약'!N39 -> 0.76759944 | J52: =IF(D52>0,H52/D52,"(-)") -> 1.7290185 | K52: ='1. 경신전선 요약'!P39 -> 1.0110174
C53: - 상품 | D53: 2325.5121 | E53: 0.234219 | F53: ='1. 경신전선 요약'!K40 -> 3064.6555 | G53: ='1. 경신전선 요약'!L40 -> 0.19073499 | H53: ='1. 경신전선 요약'!M40 -> 3980.1847 | I53: ='1. 경신전선 요약'!N40 -> 0.23240056 | J53: =IF(D53>0,H53/D53,"(-)") -> 1.7115304 | K53: ='1. 경신전선 요약'!P40 -> 1.2987381
C54: DAWS | D54: 4876.0604 | E54: 0.491103 | F54: ='1. 경신전선 요약'!K41 -> 7192.9711 | G54: ='1. 경신전선 요약'!L41 -> 0.447669 | H54: ='1. 경신전선 요약'!M41 -> 9748.5749 | I54: ='1. 경신전선 요약'!N41 -> 0.56921334 | J54: =IF(D54>0,H54/D54,"(-)") -> 1.9992728 | K54: ='1. 경신전선 요약'!P41 -> 1.3552918
C55: HEDS | D55: 816.36267 | E55: 0.082221738 | F55: ='1. 경신전선 요약'!K42 -> 2028.5095 | G55: ='1. 경신전선 요약'!L42 -> 0.12624836 | H55: ='1. 경신전선 요약'!M42 -> 1758.481 | I55: ='1. 경신전선 요약'!N42 -> 0.10267663 | J55: =IF(D55>0,H55/D55,"(-)") -> 2.1540438 | K55: ='1. 경신전선 요약'!P42 -> 0.86688331
C56: CEWS | D56: 1762.2976 | E56: 0.17749363 | F56: ='1. 경신전선 요약'!K43 -> 2169.7292 | G56: ='1. 경신전선 요약'!L43 -> 0.13503745 | H56: ='1. 경신전선 요약'!M43 -> 2266.6808 | I56: ='1. 경신전선 요약'!N43 -> 0.13235011 | J56: =IF(D56>0,H56/D56,"(-)") -> 1.2862077 | K56: ='1. 경신전선 요약'!P43 -> 1.0446837
C57: LEAR | D57: 1116.1669 | E57: 0.11241718 | F57: ='1. 경신전선 요약'!K44 -> 1865.1305 | G57: ='1. 경신전선 요약'!L44 -> 0.11608014 | H57: ='1. 경신전선 요약'!M44 -> 1831.2278 | I57: ='1. 경신전선 요약'!N44 -> 0.10692427 | J57: =IF(D57>0,H57/D57,"(-)") -> 1.6406397 | K57: ='1. 경신전선 요약'!P44 -> 0.98182287
C58: KAC-OB | D58: 809.37384 | E58: 0.081517843 | F58: ='1. 경신전선 요약'!K45 -> 1253.1632 | G58: ='1. 경신전선 요약'!L45 -> 0.077993127 | H58: ='1. 경신전선 요약'!M45 -> 709.85741 | I58: ='1. 경신전선 요약'!N45 -> 0.041448141 | J58: =IF(D58>0,H58/D58,"(-)") -> 0.87704515 | K58: ='1. 경신전선 요약'!P45 -> 0.56645249
C59: SUMITOMO | D59: 0 | E59: 0 | F59: ='1. 경신전선 요약'!K46 -> 941.58537 | G59: ='1. 경신전선 요약'!L46 -> 0.058601456 | H59: ='1. 경신전선 요약'!M46 -> 32.222543 | I59: ='1. 경신전선 요약'!N46 -> 0.0018814546 | J59: =IF(D59>0,H59/D59,"(-)") -> (-) | K59: ='1. 경신전선 요약'!P46 -> 0.034221584
C60: 기타 | D60: 548.53219 | E60: 0.05524661 | F60: ='1. 경신전선 요약'!K47 -> 616.52173 | G60: ='1. 경신전선 요약'!L47 -> 0.038370467 | H60: ='1. 경신전선 요약'!M47 -> 779.35474 | I60: ='1. 경신전선 요약'!N47 -> 0.045506048 | J60: =IF(D60>0,H60/D60,"(-)") -> 1.4208004 | K60: ='1. 경신전선 요약'!P47 -> 1.2641156
C61: (매출동량) | D61: 476.23611 | E61: 0.047965154 | F61: ='1. 경신전선 요약'!K48 -> 0 | G61: ='1. 경신전선 요약'!L48 -> 0 | H61: ='1. 경신전선 요약'!M48 -> 714.67057 | I61: ='1. 경신전선 요약'!N48 -> 0.041729179 | J61: ='1. 경신전선 요약'!O48 -> 1.131136 | K61: ='1. 경신전선 요약'!P48 -> 0
D62: 0 | E62: 0 | F62: ='1. 경신전선 요약'!K49 -> 0 | G62: ='1. 경신전선 요약'!L49 -> 0 | H62: ='1. 경신전선 요약'!M49 -> 0 | I62: ='1. 경신전선 요약'!N49 -> 0 | J62: ='1. 경신전선 요약'!O49 -> 0 | K62: ='1. 경신전선 요약'!P49 -> 0
C63: Ⅱ. 매출원가 | D63: 9050.1099 | E63: 0.91150146 | F63: ='1. 경신전선 요약'!K50 -> 14311.216 | G63: ='1. 경신전선 요약'!L50 -> 0.89068723 | H63: ='1. 경신전선 요약'!M50 -> 14848.113 | I63: ='1. 경신전선 요약'!N50 -> 0.86697224 | J63: =IF(D63>0,H63/D63,"(-)") -> 1.6406555 | K63: ='1. 경신전선 요약'!P50 -> 1.0375158
C65: Ⅲ. 매출총이익 | D65: 878.68373 | E65: 0.088498539 | F65: ='1. 경신전선 요약'!K52 -> 1756.3949 | G65: ='1. 경신전선 요약'!L52 -> 0.10931277 | H65: ='1. 경신전선 요약'!M52 -> 2278.2865 | I65: ='1. 경신전선 요약'!N52 -> 0.13302776 | J65: =IF(D65>0,H65/D65,"(-)") -> 2.5928402 | K65: ='1. 경신전선 요약'!P52 -> 1.2971379
C67: Ⅳ.판매관리비 | D67: 641.28966 | E67: 0.06458888 | F67: ='1. 경신전선 요약'!K54 -> 792.00274 | G67: ='1. 경신전선 요약'!L54 -> 0.049291881 | H67: ='1. 경신전선 요약'!M54 -> 509.26351 | I67: ='1. 경신전선 요약'!N54 -> 0.029735586 | J67: =IF(D67>0,H67/D67,"(-)") -> 0.794124 | K67: ='1. 경신전선 요약'!P54 -> 0.64300726
C68: [판매비] | D68: 0 | E68: 0 | F68: ='2. 손익계산서'!E112*$N$4/1000000 -> 0 | G68: =IFERROR(F68/$K$38,) -> 0 | H68: ='2. 손익계산서'!G112*$N$4/1000000 -> 0 | I68: =IFERROR(H68/$M$38,) -> 0 | J68: =IFERROR(H68/D68,) -> 0 | K68: =IFERROR(H68/F68,) -> 0
C70: [연구개발비] | D70: 0 | E70: 0 | F70: ='2. 손익계산서'!E146*$N$4/1000000 -> 0 | G70: =IFERROR(F70/$K$38,) -> 0 | H70: ='2. 손익계산서'!G146*$N$4/1000000 -> 0 | I70: =IFERROR(H70/$M$38,) -> 0 | J70: =IFERROR(H70/D70,) -> 0 | K70: =IFERROR(H70/F70,) -> 0
C71: Ⅴ.영업이익 | D71: 237.39407 | E71: 0.023909659 | F71: ='1. 경신전선 요약'!K58 -> 964.3922 | G71: ='1. 경신전선 요약'!L58 -> 0.060020885 | H71: ='1. 경신전선 요약'!M58 -> 1769.0229 | I71: ='1. 경신전선 요약'!N58 -> 0.10329217 | J71: =IF(D71>0,H71/D71,"(-)") -> 7.4518414 | K71: ='1. 경신전선 요약'!P58 -> 1.8343397
C72: (이익률) | D72: 0.023909659 | F72: ='1. 경신전선 요약'!K59 -> 0.060020885 | H72: ='1. 경신전선 요약'!M59 -> 0.10329217
C75: ='1. 경신전선 요약'!C62 -> □ 2월 KSCM-GP 손익/원가 요약 | K75: =+K42 -> ( 1,350 KRW/USD )
D76: 단위 | E76: 연 계획 | F76: 누적 계획 | G76: 누적 실적 | H76: 누적 달성률 | I76: 연 계획 진행률
I77: KSCI | J77: KSCM-DG | K77: KSCM-GP
C78: 매출액 | D78: 백만원 | E78: ='1. 경신전선 요약'!D64 -> 35016.42 | F78: ='1. 경신전선 요약'!F64 -> 7050.8207 | G78: ='1. 경신전선 요약'!G64 -> 6264.6155 | H78: =G78/F78 -> 0.88849452 | I78: =I7 -> 0.15932415 | J78: =J7 -> 0.1558842 | K78: =K7 -> 0.17890508
C79: 영업이익 | D79: 백만원 | E79: ='1. 경신전선 요약'!D78 -> -8918.6153 | F79: ='1. 경신전선 요약'!F78 -> -446.65111 | G79: ='1. 경신전선 요약'!G78 -> -1724.4499 | H79: =IF(AND(F79>0,G79>0),G79/F79,"(-)") -> (-) | I79: =I9 -> 0.44013411 | J79: =J9 -> 0.24100628 | K79: =K9 -> (-)
C80: 영업이익률 | D80: % | E80: =E79/E78 -> -0.25469809 | F80: =F79/F78 -> -0.063347392 | G80: =G79/G78 -> -0.27526828
C82: 구 분 | D82: 전 월 실 적 | E82: 매 출 구성비 | F82: 당 월 계 획 | G82: 매 출 구성비 | H82: 당 월 실 적 | I82: 매 출 구성비 | J82: 전 월 대 비 | K82: 계 획 대 비
C83: Ⅰ. 매출액 | D83: 3163.1059 | E83: 1 | F83: ='1. 경신전선 요약'!K64 -> 3869.6282 | G83: ='1. 경신전선 요약'!L64 -> 1 | H83: ='1. 경신전선 요약'!M64 -> 3331.54 | I83: ='1. 경신전선 요약'!N64 -> 1 | J83: =IF(D83>0,H83/D83,"(-)") -> 1.0532496 | K83: ='1. 경신전선 요약'!P64 -> 0.86094576
C84: KLSE | D84: 1981.7163 | E84: 0.62650964 | F84: ='1. 경신전선 요약'!K65 -> 3008.3442 | G84: ='1. 경신전선 요약'!L65 -> 0.77742461 | H84: ='1. 경신전선 요약'!M65 -> 3109.7147 | I84: ='1. 경신전선 요약'!N65 -> 0.9334166 | J84: =IF(D84>0,H84/D84,"(-)") -> 1.5692028 | K84: ='1. 경신전선 요약'!P65 -> 1.0336965
C85: Ford | D85: 369.54465 | E85: 0.11682968 | F85: ='1. 경신전선 요약'!K66 -> 861.28402 | G85: ='1. 경신전선 요약'!L66 -> 0.22257539 | H85: ='1. 경신전선 요약'!M66 -> 206.78756 | I85: ='1. 경신전선 요약'!N66 -> 0.062069662 | J85: =IF(D85>0,H85/D85,"(-)") -> 0.55957395 | K85: ='1. 경신전선 요약'!P66 -> 0.24009218
C86: SKI | D86: 710.38742 | E86: 0.22458541 | F86: ='1. 경신전선 요약'!K67 -> 0 | G86: ='1. 경신전선 요약'!L67 -> 0 | H86: ='1. 경신전선 요약'!M67 -> 0 | I86: ='1. 경신전선 요약'!N67 -> 0 | J86: =IF(D86>0,H86/D86,"(-)") -> 0 | K86: ='1. 경신전선 요약'!P67 -> 0
C87: 기타 | D87: 101.45749 | E87: 0.032075276 | F87: ='1. 경신전선 요약'!K68 -> 0 | G87: ='1. 경신전선 요약'!L68 -> 0 | H87: ='1. 경신전선 요약'!M68 -> 15.03769 | I87: ='1. 경신전선 요약'!N68 -> 0.0045137356 | J87: =IF(D87>0,H87/D87,"(-)") -> 0.14821666 | K87: ='1. 경신전선 요약'!P68 -> 0
D88: 0 | E88: 0 | F88: ='1. 경신전선 요약'!K69 -> 0 | G88: ='1. 경신전선 요약'!L69 -> 0 | H88: ='1. 경신전선 요약'!M69 -> 0 | I88: ='1. 경신전선 요약'!N69 -> 0 | J88: =+H88/D88 -> #DIV/0! | K88: ='1. 경신전선 요약'!P69 -> 0
C89: Ⅱ. 매출원가 | D89: 3777.7112 | E89: 1.1943044 | F89: ='1. 경신전선 요약'!K70 -> 3594.5099 | G89: ='1. 경신전선 요약'!L70 -> 0.92890317 | H89: ='1. 경신전선 요약'!M70 -> 3809.2783 | I89: ='1. 경신전선 요약'!N70 -> 1.1433986 | J89: =IF(D89>0,H89/D89,"(-)") -> 1.0083561 | K89: ='1. 경신전선 요약'!P70 -> 1.059749
C91: Ⅲ. 매출총이익 | D91: -614.60532 | E91: -0.19430438 | F91: ='1. 경신전선 요약'!K72 -> 275.11828 | G91: ='1. 경신전선 요약'!L72 -> 0.071096826 | H91: ='1. 경신전선 요약'!M72 -> -477.73828 | I91: ='1. 경신전선 요약'!N72 -> -0.14339863 | J91: =IF(D91>0,H91/D91,"(-)") -> (-) | K91: ='1. 경신전선 요약'!P72 -> (-)
C93: Ⅳ.판매관리비 | D93: 428.96526 | E93: 0.13561521 | F93: ='1. 경신전선 요약'!K74 -> 234.87224 | G93: ='1. 경신전선 요약'!L74 -> 0.060696332 | H93: ='1. 경신전선 요약'!M74 -> 444.05646 | I93: ='1. 경신전선 요약'!N74 -> 0.13328865 | J93: =IF(D93>0,H93/D93,"(-)") -> 1.0351805 | K93: ='1. 경신전선 요약'!P74 -> 1.8906298
C94: [판매비] | D94: 0 | E94: 0 | F94: ='2. 손익계산서'!J188*$N$4/1000000 -> 0 | G94: =IFERROR(F94/$K$64,) -> 0 | H94: ='2. 손익계산서'!L188*$N$4/1000000 -> 0 | I94: =IFERROR(H94/$M$64,) -> 0 | J94: =IFERROR(H94/D94,) -> 0 | K94: =IFERROR(H94/F94,) -> 0
C96: [연구개발비] | D96: 0 | E96: 0 | F96: ='2. 손익계산서'!J222*$N$4/1000000 -> 0 | G96: =IFERROR(F96/$K$64,) -> 0 | H96: ='2. 손익계산서'!L222*$N$4/1000000 -> 0 | I96: =IFERROR(H96/$M$64,) -> 0 | J96: =IFERROR(H96/D96,) -> 0 | K96: =IFERROR(H96/F96,) -> 0
C97: Ⅴ.영업이익 | D97: -1043.5706 | E97: -0.32991959 | F97: ='1. 경신전선 요약'!K78 -> 40.246044 | G97: ='1. 경신전선 요약'!L78 -> 0.010400494 | H97: ='1. 경신전선 요약'!M78 -> -921.79474 | I97: ='1. 경신전선 요약'!N78 -> -0.27668728 | J97: =IF(D97>0,H97/D97,"(-)") -> (-) | K97: ='1. 경신전선 요약'!P78 -> (-)
C98: (이익률) | D98: -0.32991959 | F98: ='1. 경신전선 요약'!K79 -> 0.010400494 | H98: ='1. 경신전선 요약'!M79 -> -0.27668728

Sheet 1. 경신전선 요약
C4: =CONCATENATE("■ ",'2. 손익계산서'!$C$4,"월 KSCI 손익/원가 요약") -> ■ 2월 KSCI 손익/원가 요약 | N4: 1350 | O4: KRW/USD | P4: (단위:백만원)
C5: 구 분 | D5: 2026년 계 획 | E5: 년계획 진척률 | F5: 누 계 계 획 | G5: 누 계 실 적 | H5: 달성률 | I5: 전 월 실 적 | J5: 구성비 | K5: 당 월 계 획 | L5: 구성비 | M5: 당 월 실 적 | N5: 구성비 | O5: 전 월 대 비 | P5: 계 획 대 비 | R5: 계획대비 | S5: 전월대비
C6: Ⅰ. 매출액 | D6: =SUM(D7:D8) -> 234337.43 | E6: =IFERROR(G6/D6,) -> 0.15932415 | F6: =SUM(F7:F8) -> 39126.549 | G6: =SUM(G7:G8) -> 37335.612 | H6: =IFERROR(G6/F6,) -> 0.95422707 | I6: =SUM(I7:I8) -> 16877.673 | J6: =IFERROR(I6/$I$6,) -> 1 | K6: =SUM(K7:K8) -> 19937.239 | L6: =IFERROR(K6/$K$6,) -> 1 | M6: =SUM(M7:M8) -> 20457.939 | N6: =IFERROR(M6/$M$6,) -> 1 | O6: =IFERROR(M6/I6,) -> 1.2121303 | P6: =IFERROR(M6/K6,) -> 1.026117 | Q6: =P6-1 -> 0.026116976 | R6: =+M6-K6 -> 520.70039 | S6: =+M6-I6 -> 3580.2663 | T6: =O6-1 -> 0.21213033 | U6: ▲▼
C7: 전선 | D7: ='2. 손익계산서'!C7*$N$4/1000000 -> 199321.01 | E7: =IFERROR(G7/D7,) -> 0.1558842 | F7: ='2. 손익계산서'!E7*$N$4/1000000 -> 32075.728 | G7: ='2. 손익계산서'!F7*$N$4/1000000 -> 31070.996 | H7: =IFERROR(G7/F7,) -> 0.96867627 | I7: ='2. 손익계산서'!H7*$N$4/1000000 -> 13944.597 | J7: =IFERROR(I7/$I$6,) -> 0.82621564 | K7: ='2. 손익계산서'!J7*$N$4/1000000 -> 16067.61 | L7: =IFERROR(K7/$K$6,) -> 0.80590952 | M7: ='2. 손익계산서'!L7*$N$4/1000000 -> 17126.399 | N7: =IFERROR(M7/$M$6,) -> 0.83715173 | O7: =IFERROR(M7/I7,) -> 1.2281745 | P7: =IFERROR(M7/K7,) -> 1.0658958
C8: 전장 | D8: ='2. 손익계산서'!C9*$N$4/1000000 -> 35016.42 | E8: =IFERROR(G8/D8,) -> 0.17890508 | F8: ='2. 손익계산서'!E9*$N$4/1000000 -> 7050.8207 | G8: ='2. 손익계산서'!F9*$N$4/1000000 -> 6264.6155 | H8: =IFERROR(G8/F8,) -> 0.88849452 | I8: ='2. 손익계산서'!H9*$N$4/1000000 -> 2933.0755 | J8: =IFERROR(I8/$I$6,) -> 0.17378436 | K8: ='2. 손익계산서'!J9*$N$4/1000000 -> 3869.6282 | L8: =IFERROR(K8/$K$6,) -> 0.19409048 | M8: ='2. 손익계산서'!L9*$N$4/1000000 -> 3331.54 | N8: =IFERROR(M8/$M$6,) -> 0.16284827 | O8: =IFERROR(M8/I8,) -> 1.1358521 | P8: =IFERROR(M8/K8,) -> 0.86094576
C9: *매출동량(ton) | D9: ='2. 손익계산서'!C8 -> 0 | E9: =IFERROR(G9/D9,) -> 0 | F9: ='2. 손익계산서'!E8 -> 0 | G9: ='2. 손익계산서'!F8 -> 1346.4872 | H9: =IFERROR(G9/F9,) -> 0 | I9: ='2. 손익계산서'!H8 -> 631.81666 | J9: =IFERROR(I9/$I$6,) -> 0.037435058 | K9: ='2. 손익계산서'!J8 -> 0 | L9: =IFERROR(K9/$K$6,) -> 0 | M9: ='2. 손익계산서'!L8 -> 714.67057 | N9: =IFERROR(M9/$M$6,) -> 0.034933654 | O9: =IFERROR(M9/I9,) -> 1.131136 | P9: =IFERROR(M9/K9,) -> 0
C11: Ⅱ. 매출원가 | D11: =SUM(D12:D13) -> 219695.57 | E11: =IFERROR(G11/D11,) -> 0.15705544 | F11: =SUM(F12:F13) -> 35735.271 | G11: =SUM(G12:G13) -> 34504.385 | H11: =IFERROR(G11/F11,) -> 0.96555544 | I11: =SUM(I12:I13) -> 15846.995 | J11: =IFERROR(I11/$I$6,) -> 0.93893244 | K11: =SUM(K12:K13) -> 17905.725 | L11: =IFERROR(K11/K6,) -> 0.89810458 | M11: =SUM(M12:M13) -> 18657.391 | N11: =IFERROR(M11/M6,) -> 0.9119878 | O11: =IFERROR(M11/I11,) -> 1.1773457 | P11: =IFERROR(M11/K11,) -> 1.0419791 | R11: =+M11-K11 -> 751.66544 | S11: =+M11-I11 -> 2810.3964
C12: 전선 | D12: ='2. 손익계산서'!C91*$N$4/1000000 -> 178792.54 | E12: =IFERROR(G12/D12,) -> 0.1534481 | F12: ='2. 손익계산서'!E91*$N$4/1000000 -> 28716.486 | G12: ='2. 손익계산서'!F91*$N$4/1000000 -> 27435.375 | H12: =IFERROR(G12/F12,) -> 0.95538762 | I12: ='2. 손익계산서'!H91*$N$4/1000000 -> 12587.262 | J12: =IFERROR(I12/I7,) -> 0.90266231 | K12: ='2. 손익계산서'!J91*$N$4/1000000 -> 14311.216 | L12: =IFERROR(K12/K7,) -> 0.89068723 | M12: ='2. 손익계산서'!L91*$N$4/1000000 -> 14848.113 | N12: =IFERROR(M12/M7,) -> 0.86697224 | O12: =IFERROR(M12/I12,) -> 1.1796141 | P12: =IFERROR(M12/K12,) -> 1.0375158
C13: 전장 | D13: ='2. 손익계산서'!C160*$N$4/1000000 -> 40903.034 | E13: =IFERROR(G13/D13,) -> 0.17282362 | F13: ='2. 손익계산서'!E160*$N$4/1000000 -> 7018.7855 | G13: ='2. 손익계산서'!F160*$N$4/1000000 -> 7069.0104 | H13: =IFERROR(G13/F13,) -> 1.0071558 | I13: ='2. 손익계산서'!H160*$N$4/1000000 -> 3259.7321 | J13: =IFERROR(I13/I8,) -> 1.11137 | K13: ='2. 손익계산서'!J160*$N$4/1000000 -> 3594.5099 | L13: =IFERROR(K13/K8,) -> 0.92890317 | M13: ='2. 손익계산서'!L160*$N$4/1000000 -> 3809.2783 | N13: =IFERROR(M13/M8,) -> 1.1433986 | O13: =IFERROR(M13/I13,) -> 1.1685863 | P13: =IFERROR(M13/K13,) -> 1.059749
C14: └ 기타(GP2) | D14: ='2. 손익계산서'!C163*$N$4/1000000 -> 2403.7903 | E14: =IFERROR(G14/D14,) -> -0.16550175 | F14: ='2. 손익계산서'!E163*$N$4/1000000 -> 477.65483 | G14: ='2. 손익계산서'!F163*$N$4/1000000 -> -397.8315 | H14: =IFERROR(G14/F14,) -> -0.8328849 | I14: ='2. 손익계산서'!H163*$N$4/1000000 -> -397.8315 | J14: =IFERROR(I14/I8,) -> -0.1356363 | K14: ='2. 손익계산서'!J163*$N$4/1000000 -> 98.292417 | L14: =IFERROR(K14/K8,) -> 0.025400998 | M14: ='2. 손익계산서'!L163*$N$4/1000000 -> 0 | N14: =IFERROR(M14/M8,) -> 0 | O14: =IFERROR(M14/I14,) -> 0 | P14: =IFERROR(M14/K14,) -> 0
C16: Ⅲ. 매출총이익 | D16: =D6-D11 -> 14641.859 | E16: =IF(AND(D16>0,G16>0),G16/D16,"(-)") -> 0.19336524 | F16: =F6-F11 -> 3391.2774 | G16: =G6-G11 -> 2831.2265 | H16: =IF(AND(F16>0,G16>0),G16/F16,"(-)") -> 0.83485547 | I16: =I6-I11 -> 1030.6783 | J16: =IFERROR(I16/$I$6,) -> 0.06106756 | K16: =K6-K11 -> 2031.5132 | L16: =IFERROR(K16/$K$6,) -> 0.10189542 | M16: =M6-M11 -> 1800.5482 | N16: =IFERROR(M16/$M$6,) -> 0.088012198 | O16: =IF(AND(I16>0,M16>0),M16/I16,"(-)") -> 1.7469546 | P16: =IF(AND(K16>0,M16>0),M16/K16,"(-)") -> 0.88630886 | R16: =+M16-K16 -> -230.96505 | S16: =+M16-I16 -> 769.86987
C17: (이익률) | D17: =IFERROR(D16/D$6,) -> 0.062481946 | F17: =IFERROR(F16/F$6,) -> 0.086674585 | G17: =IFERROR(G16/G$6,) -> 0.075831795 | I17: =IFERROR(I16/I$6,) -> 0.06106756 | K17: =IFERROR(K16/K$6,) -> 0.10189542 | M17: =IFERROR(M16/M$6,) -> 0.088012198
C18: Ⅳ.판매관리비 | D18: =SUM(D19:D21) -> 12507.59 | E18: =IFERROR(G18/D18,) -> 0.15125711 | F18: =SUM(F19:F21) -> 2111.5467 | G18: =SUM(G19:G21) -> 1891.8618 | H18: =IFERROR(G18/F18,) -> 0.89596021 | I18: =SUM(I19:I21) -> 938.54183 | J18: =IFERROR(I18/$I$6,) -> 0.055608486 | K18: =SUM(K19:K21) -> 1026.875 | L18: =IFERROR(K18/$K$6,) -> 0.051505376 | M18: =SUM(M19:M21) -> 953.31997 | N18: =IFERROR(M18/$M$6,) -> 0.046599023 | O18: =IFERROR(M18/I18,) -> 1.0157459 | P18: =IFERROR(M18/K18,) -> 0.92837004 | R18: =+M18-K18 -> -73.555011 | S18: =+M18-I18 -> 14.77814
C19: [판매비] | D19: ='2. 손익계산서'!C19*$N$4/1000000 -> 0 | E19: =IFERROR(G19/D19,) -> 0 | F19: ='2. 손익계산서'!E19*$N$4/1000000 -> 0 | G19: ='2. 손익계산서'!F19*$N$4/1000000 -> 0 | H19: =IFERROR(G19/F19,) -> 0 | I19: ='2. 손익계산서'!H19*$N$4/1000000 -> 0 | J19: =IFERROR(I19/$I$6,) -> 0 | K19: ='2. 손익계산서'!J19*$N$4/1000000 -> 0 | L19: =IFERROR(K19/$K$6,) -> 0 | M19: ='2. 손익계산서'!L19*$N$4/1000000 -> 0 | N19: =IFERROR(M19/$M$6,) -> 0 | O19: =IFERROR(M19/I19,) -> 0 | P19: =IFERROR(M19/K19,) -> 0
C20: [관리비] | D20: ='2. 손익계산서'!C35*$N$4/1000000 -> 12507.59 | E20: =IFERROR(G20/D20,) -> 0.15125711 | F20: ='2. 손익계산서'!E35*$N$4/1000000 -> 2111.5467 | G20: ='2. 손익계산서'!F35*$N$4/1000000 -> 1891.8618 | H20: =IFERROR(G20/F20,) -> 0.89596021 | I20: ='2. 손익계산서'!H35*$N$4/1000000 -> 938.54183 | J20: =IFERROR(I20/$I$6,) -> 0.055608486 | K20: ='2. 손익계산서'!J35*$N$4/1000000 -> 1026.875 | L20: =IFERROR(K20/$K$6,) -> 0.051505376 | M20: ='2. 손익계산서'!L35*$N$4/1000000 -> 953.31997 | N20: =IFERROR(M20/$M$6,) -> 0.046599023 | O20: =IFERROR(M20/I20,) -> 1.0157459 | P20: =IFERROR(M20/K20,) -> 0.92837004
C21: [연구개발비] | D21: ='2. 손익계산서'!C53*$N$4/1000000 -> 0 | E21: =IFERROR(G21/D21,) -> 0 | F21: ='2. 손익계산서'!E53*$N$4/1000000 -> 0 | G21: ='2. 손익계산서'!F53*$N$4/1000000 -> 0 | H21: =IFERROR(G21/F21,) -> 0 | I21: ='2. 손익계산서'!H53*$N$4/1000000 -> 0 | J21: =IFERROR(I21/$I$6,) -> 0 | K21: ='2. 손익계산서'!J53*$N$4/1000000 -> 0 | L21: =IFERROR(K21/$K$6,) -> 0 | M21: ='2. 손익계산서'!L53*$N$4/1000000 -> 0 | N21: =IFERROR(M21/$M$6,) -> 0 | O21: =IFERROR(M21/I21,) -> 0 | P21: =IFERROR(M21/K21,) -> 0
C22: Ⅴ.영업이익 | D22: =D16-D18 -> 2134.2692 | E22: =IF(AND(D22>0,G22>0),G22/D22,"(-)") -> 0.44013411 | F22: =F16-F18 -> 1279.7307 | G22: =G16-G18 -> 939.36468 | H22: =IF(AND(F22>0,G22>0),G22/F22,"(-)") -> 0.73403309 | I22: =I16-I18 -> 92.136474 | J22: =IFERROR(I22/$I$6,) -> 0.0054590745 | K22: =K16-K18 -> 1004.6382 | L22: =IFERROR(K22/$K$6,) -> 0.05039004 | M22: =M16-M18 -> 847.22821 | N22: =IFERROR(M22/$M$6,) -> 0.041413175 | O22: =IF(AND(I22>0,M22>0),M22/I22,"(-)") -> 9.1953617 | P22: =IF(AND(K22>0,M22>0),M22/K22,"(-)") -> 0.84331669 | Q22: =P22-1 -> -0.15668331 | R22: =+M22-K22 -> -157.41004 | S22: =+M22-I22 -> 755.09173 | T22: =O22-1 -> 8.1953617
C23: (영업이익률) | D23: =D22/D6 -> 0.0091076752 | F23: =F22/F6 -> 0.032707478 | G23: =G22/G6 -> 0.025160018 | I23: =I22/I6 -> 0.0054590745 | K23: =K22/K6 -> 0.05039004 | M23: =IFERROR(M22/M6,) -> 0.041413175
C24: 전선 | D24: =D58 -> 11052.884 | E24: =IF(AND(D24>0,G24>0),G24/D24,"(-)") -> 0.24100628 | F24: =F58 -> 1726.3818 | G24: =G58 -> 2663.8146 | H24: =IF(AND(F24>0,G24>0),G24/F24,"(-)") -> 1.5430043 | I24: =I58 -> 894.79166 | J24: =IFERROR(I24/I7,) -> 0.064167623 | K24: =K58 -> 964.3922 | L24: =L58 -> 0.060020885 | M24: =M58 -> 1769.0229 | N24: =N58 -> 0.10329217 | O24: =IF(AND(I24>0,M24>0),M24/I24,"(-)") -> 1.9770222 | P24: =IF(AND(K24>0,M24>0),M24/K24,"(-)") -> 1.8343397
C25: 전장 | D25: =D78 -> -8918.6153 | E25: =IF(AND(D25>0,G25>0),G25/D25,"(-)") -> (-) | F25: =F78 -> -446.65111 | G25: =G78 -> -1724.4499 | H25: =IF(AND(F25>0,G25>0),G25/F25,"(-)") -> (-) | I25: =I78 -> -802.65519 | J25: =IFERROR(I25/I8,) -> -0.2736565 | K25: =K78 -> 40.246044 | L25: =L78 -> 0.010400494 | M25: =M78 -> -921.79474 | N25: =N78 -> -0.27668728 | O25: =IF(AND(I25>0,M25>0),M25/I25,"(-)") -> (-) | P25: =IF(AND(K25>0,M25>0),M25/K25,"(-)") -> (-)
C27: 구 분 | D27: 2026년 계 획 | E27: 년계획 진척률 | F27: 누 계 계 획 | G27: 누계 실적 | H27: 달성률 | I27: 전 월 실 적 | J27: 원 가 구성비 | K27: 당 월 계 획 | L27: 원 가 구성비 | M27: 당 월 실 적 | N27: 원 가 구성비 | O27: 전 월 대 비 | P27: 계 획 대 비
C28: Ⅰ. 재료비
C29: Ⅱ. 노무비
C30: Ⅲ. 경비
C31: Ⅳ. 당기총제조비용
C32: Ⅴ. 당기제품제조원가
Q35: =4352-3447 -> 905
C36: =CONCATENATE("□ ",'2. 손익계산서'!$C$4,"월 KSCM-DG 손익/원가 요약") -> □ 2월 KSCM-DG 손익/원가 요약 | N36: =$N$4 -> 1350 | O36: KRW/USD | P36: (단위:백만원)
C37: 구 분 | D37: 2026년 계 획 | E37: 년계획 진척률 | F37: 누 계 계 획 | G37: 누 계 실 적 | H37: 달성률 | I37: 전 월 실 적 | J37: 매출 구성비 | K37: 당 월 계 획 | L37: 매출 구성비 | M37: 당 월 실 적 | N37: 매출 구성비 | O37: 전 월 대 비 | P37: 계 획 대 비
C38: Ⅰ. 매출액 | D38: =SUM(D39:D40) -> 199321.01 | E38: =IFERROR(G38/D38,) -> 0.1558842 | F38: =SUM(F39:F40) -> 32075.728 | G38: =SUM(G39:G40) -> 31070.996 | H38: =IFERROR(G38/F38,) -> 0.96867627 | I38: =SUM(I39:I40) -> 13944.597 | J38: =IFERROR(I38/$I$38,) -> 1 | K38: =SUM(K39:K40) -> 16067.61 | L38: =IFERROR(K38/$K$38,) -> 1 | M38: =SUM(M39:M40) -> 17126.399 | N38: =IFERROR(M38/$M$38,) -> 1 | O38: =IFERROR(M38/I38,) -> 1.2281745 | P38: =IFERROR(M38/K38,) -> 1.0658958
C39: - 제품 | D39: ='2. 손익계산서'!C80*$N$4/1000000 -> 162935.8 | E39: =IFERROR(G39/D39,) -> 0.15420477 | F39: ='2. 손익계산서'!E80*$N$4/1000000 -> 25961.981 | G39: ='2. 손익계산서'!F80*$N$4/1000000 -> 25125.478 | H39: =IFERROR(G39/F39,) -> 0.96777968 | I39: ='2. 손익계산서'!H80*$N$4/1000000 -> 11979.263 | J39: =IFERROR(I39/$I$38,) -> 0.85906126 | K39: ='2. 손익계산서'!J80*$N$4/1000000 -> 13002.955 | L39: =IFERROR(K39/$K$38,) -> 0.80926501 | M39: ='2. 손익계산서'!L80*$N$4/1000000 -> 13146.214 | N39: =IFERROR(M39/$M$38,) -> 0.76759944 | O39: =IFERROR(M39/I39,) -> 1.0974143 | P39: =IFERROR(M39/K39,) -> 1.0110174
C40: - 상품 | D40: ='2. 손익계산서'!C81*$N$4/1000000 -> 36385.213 | E40: =IFERROR(G40/D40,) -> 0.16340481 | F40: ='2. 손익계산서'!E81*$N$4/1000000 -> 6113.7467 | G40: ='2. 손익계산서'!F81*$N$4/1000000 -> 5945.5186 | H40: =IFERROR(G40/F40,) -> 0.97248363 | I40: ='2. 손익계산서'!H81*$N$4/1000000 -> 1965.3339 | J40: =IFERROR(I40/$I$38,) -> 0.14093874 | K40: ='2. 손익계산서'!J81*$N$4/1000000 -> 3064.6555 | L40: =IFERROR(K40/$K$38,) -> 0.19073499 | M40: ='2. 손익계산서'!L81*$N$4/1000000 -> 3980.1847 | N40: =IFERROR(M40/$M$38,) -> 0.23240056 | O40: =IFERROR(M40/I40,) -> 2.0251951 | P40: =IFERROR(M40/K40,) -> 1.2987381
C41: DAWS | D41: ='2. 손익계산서'!C82*$N$4/1000000 -> 88697.11 | E41: =IFERROR(G41/D41,) -> 0.18492081 | F41: ='2. 손익계산서'!E82*$N$4/1000000 -> 14361.642 | G41: ='2. 손익계산서'!F82*$N$4/1000000 -> 16401.941 | H41: =IFERROR(G41/F41,) -> 1.1420659 | I41: ='2. 손익계산서'!H82*$N$4/1000000 -> 6653.3661 | J41: =IFERROR(I41/$I$38,) -> 0.47712859 | K41: ='2. 손익계산서'!J82*$N$4/1000000 -> 7192.9711 | L41: =IFERROR(K41/$K$38,) -> 0.447669 | M41: ='2. 손익계산서'!L82*$N$4/1000000 -> 9748.5749 | N41: =IFERROR(M41/$M$38,) -> 0.56921334 | O41: =IFERROR(M41/I41,) -> 1.4652094 | P41: =IFERROR(M41/K41,) -> 1.3552918
C42: HEDS | D42: ='2. 손익계산서'!C83*$N$4/1000000 -> 18279.223 | E42: =IFERROR(G42/D42,) -> 0.17279054 | F42: ='2. 손익계산서'!E83*$N$4/1000000 -> 4050.1658 | G42: ='2. 손익계산서'!F83*$N$4/1000000 -> 3158.4768 | H42: =IFERROR(G42/F42,) -> 0.77983888 | I42: ='2. 손익계산서'!H83*$N$4/1000000 -> 1399.9958 | J42: =IFERROR(I42/$I$38,) -> 0.10039701 | K42: ='2. 손익계산서'!J83*$N$4/1000000 -> 2028.5095 | L42: =IFERROR(K42/$K$38,) -> 0.12624836 | M42: ='2. 손익계산서'!L83*$N$4/1000000 -> 1758.481 | N42: =IFERROR(M42/$M$38,) -> 0.10267663 | O42: =IFERROR(M42/I42,) -> 1.2560616 | P42: =IFERROR(M42/K42,) -> 0.86688331
C43: CEWS | D43: ='2. 손익계산서'!C84*$N$4/1000000 -> 26755.106 | E43: =IFERROR(G43/D43,) -> 0.14145682 | F43: ='2. 손익계산서'!E84*$N$4/1000000 -> 4332.1282 | G43: ='2. 손익계산서'!F84*$N$4/1000000 -> 3784.6924 | H43: =IFERROR(G43/F43,) -> 0.87363352 | I43: ='2. 손익계산서'!H84*$N$4/1000000 -> 1518.0116 | J43: =IFERROR(I43/$I$38,) -> 0.10886019 | K43: ='2. 손익계산서'!J84*$N$4/1000000 -> 2169.7292 | L43: =IFERROR(K43/$K$38,) -> 0.13503745 | M43: ='2. 손익계산서'!L84*$N$4/1000000 -> 2266.6808 | N43: =IFERROR(M43/$M$38,) -> 0.13235011 | O43: =IFERROR(M43/I43,) -> 1.4931907 | P43: =IFERROR(M43/K43,) -> 1.0446837
C44: LEAR | D44: ='2. 손익계산서'!C85*$N$4/1000000 -> 22999.075 | E44: =IFERROR(G44/D44,) -> 0.19199841 | F44: ='2. 손익계산서'!E85*$N$4/1000000 -> 3723.9598 | G44: ='2. 손익계산서'!F85*$N$4/1000000 -> 4415.7858 | H44: =IFERROR(G44/F44,) -> 1.185777 | I44: ='2. 손익계산서'!H85*$N$4/1000000 -> 2584.558 | J44: =IFERROR(I44/$I$38,) -> 0.18534476 | K44: ='2. 손익계산서'!J85*$N$4/1000000 -> 1865.1305 | L44: =IFERROR(K44/$K$38,) -> 0.11608014 | M44: ='2. 손익계산서'!L85*$N$4/1000000 -> 1831.2278 | N44: =IFERROR(M44/$M$38,) -> 0.10692427 | O44: =IFERROR(M44/I44,) -> 0.70852646 | P44: =IFERROR(M44/K44,) -> 0.98182287
C45: KAC-OB | D45: ='2. 손익계산서'!C86*$N$4/1000000 -> 15452.857 | E45: =IFERROR(G45/D45,) -> 0.11894493 | F45: ='2. 손익계산서'!E86*$N$4/1000000 -> 2502.0927 | G45: ='2. 손익계산서'!F86*$N$4/1000000 -> 1838.0389 | H45: =IFERROR(G45/F45,) -> 0.73460064 | I45: ='2. 손익계산서'!H86*$N$4/1000000 -> 1128.1815 | J45: =IFERROR(I45/$I$38,) -> 0.08090456 | K45: ='2. 손익계산서'!J86*$N$4/1000000 -> 1253.1632 | L45: =IFERROR(K45/$K$38,) -> 0.077993127 | M45: ='2. 손익계산서'!L86*$N$4/1000000 -> 709.85741 | N45: =IFERROR(M45/$M$38,) -> 0.041448141 | O45: =IFERROR(M45/I45,) -> 0.62920496 | P45: =IFERROR(M45/K45,) -> 0.56645249
C46: SUMITOMO | D46: ='2. 손익계산서'!C87*$N$4/1000000 -> 19535.26 | E46: =IFERROR(G46/D46,) -> 0.010006482 | F46: ='2. 손익계산서'!E87*$N$4/1000000 -> 1874.7791 | G46: ='2. 손익계산서'!F87*$N$4/1000000 -> 195.47922 | H46: =IFERROR(G46/F46,) -> 0.10426787 | I46: ='2. 손익계산서'!H87*$N$4/1000000 -> 163.25667 | J46: =IFERROR(I46/$I$38,) -> 0.011707522 | K46: ='2. 손익계산서'!J87*$N$4/1000000 -> 941.58537 | L46: =IFERROR(K46/$K$38,) -> 0.058601456 | M46: ='2. 손익계산서'!L87*$N$4/1000000 -> 32.222543 | N46: =IFERROR(M46/$M$38,) -> 0.0018814546 | O46: =IFERROR(M46/I46,) -> 0.19737351 | P46: =IFERROR(M46/K46,) -> 0.034221584
C47: 기타 | D47: ='2. 손익계산서'!C88*$N$4/1000000 -> 7602.3794 | E47: =IFERROR(G47/D47,) -> 0.16791878 | F47: ='2. 손익계산서'!E88*$N$4/1000000 -> 1230.9606 | G47: ='2. 손익계산서'!F88*$N$4/1000000 -> 1276.5823 | H47: =IFERROR(G47/F47,) -> 1.0370619 | I47: ='2. 손익계산서'!H88*$N$4/1000000 -> 497.22756 | J47: =IFERROR(I47/$I$38,) -> 0.035657362 | K47: ='2. 손익계산서'!J88*$N$4/1000000 -> 616.52173 | L47: =IFERROR(K47/$K$38,) -> 0.038370467 | M47: ='2. 손익계산서'!L88*$N$4/1000000 -> 779.35474 | N47: =IFERROR(M47/$M$38,) -> 0.045506048 | O47: =IFERROR(M47/I47,) -> 1.5674005 | P47: =IFERROR(M47/K47,) -> 1.2641156
C48: (매출동량) | D48: ='2. 손익계산서'!C89 -> 0 | E48: =IFERROR(G48/D48,) -> 0 | F48: ='2. 손익계산서'!E89 -> 0 | G48: ='2. 손익계산서'!F89 -> 1346.4872 | H48: =IFERROR(G48/F48,) -> 0 | I48: ='2. 손익계산서'!H89 -> 631.81666 | J48: =IFERROR(I48/$I$38,) -> 0.045309065 | K48: ='2. 손익계산서'!J89 -> 0 | L48: =IFERROR(K48/$K$38,) -> 0 | M48: ='2. 손익계산서'!L89 -> 714.67057 | N48: =IFERROR(M48/$M$38,) -> 0.041729179 | O48: =IFERROR(M48/I48,) -> 1.131136 | P48: =IFERROR(M48/K48,) -> 0
J49: =IFERROR(I49/$I$38,) -> 0 | L49: =IFERROR(K49/$K$38,) -> 0 | N49: =IFERROR(M49/$M$38,) -> 0
C50: Ⅱ. 매출원가 | D50: ='2. 손익계산서'!C91*$N$4/1000000 -> 178792.54 | E50: =IFERROR(G50/D50,) -> 0.1534481 | F50: ='2. 손익계산서'!E91*$N$4/1000000 -> 28716.486 | G50: ='2. 손익계산서'!F91*$N$4/1000000 -> 27435.375 | H50: =IFERROR(G50/F50,) -> 0.95538762 | I50: ='2. 손익계산서'!H91*$N$4/1000000 -> 12587.262 | J50: =IFERROR(I50/$I$38,) -> 0.90266231 | K50: ='2. 손익계산서'!J91*$N$4/1000000 -> 14311.216 | L50: =IFERROR(K50/$K$38,) -> 0.89068723 | M50: ='2. 손익계산서'!L91*$N$4/1000000 -> 14848.113 | N50: =IFERROR(M50/$M$38,) -> 0.86697224 | O50: =IFERROR(M50/I50,) -> 1.1796141 | P50: =IFERROR(M50/K50,) -> 1.0375158
C52: Ⅲ. 매출총이익 | D52: =D38-D50 -> 20528.473 | E52: =IF(AND(D52>0,G52>0),G52/D52,"(-)") -> 0.1771014 | F52: =F38-F50 -> 3359.2422 | G52: =G38-G50 -> 3635.6213 | H52: =IF(AND(F52>0,G52>0),G52/F52,"(-)") -> 1.0822743 | I52: =I38-I50 -> 1357.3349 | J52: =IFERROR(I52/$I$38,) -> 0.097337688 | K52: =K38-K50 -> 1756.3949 | L52: =IFERROR(K52/$K$38,) -> 0.10931277 | M52: =M38-M50 -> 2278.2865 | N52: =IFERROR(M52/$M$38,) -> 0.13302776 | O52: =IF(AND(I52>0,M52>0),M52/I52,"(-)") -> 1.6784999 | P52: =IF(AND(K52>0,M52>0),M52/K52,"(-)") -> 1.2971379
C53: (이익률) | D53: =IFERROR(D52/D$38,) -> 0.10299202 | F53: =IFERROR(F52/F$38,) -> 0.10472848 | G53: =IFERROR(G52/G$38,) -> 0.11701013 | I53: =IFERROR(I52/I$38,) -> 0.097337688 | K53: =IFERROR(K52/K$38,) -> 0.10931277 | M53: =IFERROR(M52/M$38,) -> 0.13302776
C54: Ⅳ.판매관리비 | D54: =SUM(D55:D57) -> 9475.5886 | E54: =IFERROR(G54/D54,) -> 0.10255898 | F54: =SUM(F55:F57) -> 1632.8603 | G54: =SUM(G55:G57) -> 971.80671 | H54: =IFERROR(G54/F54,) -> 0.59515605 | I54: =SUM(I55:I57) -> 462.5432 | J54: =IFERROR(I54/$I$38,) -> 0.033170065 | K54: =SUM(K55:K57) -> 792.00274 | L54: =IFERROR(K54/$K$38,) -> 0.049291881 | M54: =SUM(M55:M57) -> 509.26351 | N54: =IFERROR(M54/$M$38,) -> 0.029735586 | O54: =IFERROR(M54/I54,) -> 1.1010075 | P54: =IFERROR(M54/K54,) -> 0.64300726
C55: [판매비] | D55: ='2. 손익계산서'!C99*$N$4/1000000 -> 0 | E55: =IFERROR(G55/D55,) -> 0 | F55: ='2. 손익계산서'!E99*$N$4/1000000 -> 0 | G55: ='2. 손익계산서'!F99*$N$4/1000000 -> 0 | H55: =IFERROR(G55/F55,) -> 0 | I55: ='2. 손익계산서'!H99*$N$4/1000000 -> 0 | J55: =IFERROR(I55/$I$38,) -> 0 | K55: ='2. 손익계산서'!J99*$N$4/1000000 -> 0 | L55: =IFERROR(K55/$K$38,) -> 0 | M55: ='2. 손익계산서'!L99*$N$4/1000000 -> 0 | N55: =IFERROR(M55/$M$38,) -> 0 | O55: =IFERROR(M55/I55,) -> 0 | P55: =IFERROR(M55/K55,) -> 0
C56: [관리비] | D56: ='2. 손익계산서'!C115*$N$4/1000000 -> 9475.5886 | E56: =IFERROR(G56/D56,) -> 0.10255898 | F56: ='2. 손익계산서'!E115*$N$4/1000000 -> 1632.8603 | G56: ='2. 손익계산서'!F115*$N$4/1000000 -> 971.80671 | H56: =IFERROR(G56/F56,) -> 0.59515605 | I56: ='2. 손익계산서'!H115*$N$4/1000000 -> 462.5432 | J56: =IFERROR(I56/$I$38,) -> 0.033170065 | K56: ='2. 손익계산서'!J115*$N$4/1000000 -> 792.00274 | L56: =IFERROR(K56/$K$38,) -> 0.049291881 | M56: ='2. 손익계산서'!L115*$N$4/1000000 -> 509.26351 | N56: =IFERROR(M56/$M$38,) -> 0.029735586 | O56: =IFERROR(M56/I56,) -> 1.1010075 | P56: =IFERROR(M56/K56,) -> 0.64300726
C57: [연구개발비] | D57: ='2. 손익계산서'!C133*$N$4/1000000 -> 0 | E57: =IFERROR(G57/D57,) -> 0 | F57: ='2. 손익계산서'!E133*$N$4/1000000 -> 0 | G57: ='2. 손익계산서'!F133*$N$4/1000000 -> 0 | H57: =IFERROR(G57/F57,) -> 0 | I57: ='2. 손익계산서'!H133*$N$4/1000000 -> 0 | J57: =IFERROR(I57/$I$38,) -> 0 | K57: ='2. 손익계산서'!J133*$N$4/1000000 -> 0 | L57: =IFERROR(K57/$K$38,) -> 0 | M57: ='2. 손익계산서'!L133*$N$4/1000000 -> 0 | N57: =IFERROR(M57/$M$38,) -> 0 | O57: =IFERROR(M57/I57,) -> 0 | P57: =IFERROR(M57/K57,) -> 0
C58: Ⅴ.영업이익 | D58: =D52-D54 -> 11052.884 | E58: =IF(AND(D58>0,G58>0),G58/D58,"(-)") -> 0.24100628 | F58: =F52-F54 -> 1726.3818 | G58: =G52-G54 -> 2663.8146 | H58: =IF(AND(F58>0,G58>0),G58/F58,"(-)") -> 1.5430043 | I58: =I52-I54 -> 894.79166 | J58: =IFERROR(I58/$I$38,) -> 0.064167623 | K58: =K52-K54 -> 964.3922 | L58: =IFERROR(K58/$K$38,) -> 0.060020885 | M58: =M52-M54 -> 1769.0229 | N58: =IFERROR(M58/$M$38,) -> 0.10329217 | O58: =IF(AND(I58>0,M58>0),M58/I58,"(-)") -> 1.9770222 | P58: =IF(AND(K58>0,M58>0),M58/K58,"(-)") -> 1.8343397
C59: (이익률) | D59: =IFERROR(D58/D$38,) -> 0.055452681 | F59: =IFERROR(F58/F$38,) -> 0.053822062 | G59: =IFERROR(G58/G$38,) -> 0.085733157 | I59: =IFERROR(I58/I$38,) -> 0.064167623 | K59: =IFERROR(K58/K$38,) -> 0.060020885 | M59: =IFERROR(M58/M$38,) -> 0.10329217
C62: =CONCATENATE("□ ",'2. 손익계산서'!$C$4,"월 KSCM-GP 손익/원가 요약") -> □ 2월 KSCM-GP 손익/원가 요약 | N62: =$N$4 -> 1350 | O62: KRW/USD | P62: (단위:백만원)
C63: 구 분 | D63: 2026년 계 획 | E63: 년계획 진척률 | F63: 누 계 계 획 | G63: 누 계 실 적 | H63: 달성률 | I63: 전 월 실 적 | J63: 매출 구성비 | K63: 당 월 계 획 | L63: 매출 구성비 | M63: 당 월 실 적 | N63: 매출 구성비 | O63: 전 월 대 비 | P63: 계 획 대 비
C64: Ⅰ. 매출액 | D64: =SUM(D65:D68) -> 35016.42 | E64: =IFERROR(G64/D64,) -> 0.17890508 | F64: =SUM(F65:F68) -> 7050.8207 | G64: =SUM(G65:G68) -> 6264.6155 | H64: =IFERROR(G64/F64,) -> 0.88849452 | I64: =SUM(I65:I68) -> 2933.0755 | J64: =IFERROR(I64/$I$64,) -> 1 | K64: =SUM(K65:K68) -> 3869.6282 | L64: =IFERROR(K64/$K$64,) -> 1 | M64: =SUM(M65:M68) -> 3331.54 | N64: =IFERROR(M64/$M$64,) -> 1 | O64: =IFERROR(M64/I64,) -> 1.1358521 | P64: =IFERROR(M64/K64,) -> 0.86094576
C65: KLSE | D65: ='2. 손익계산서'!C155*$N$4/1000000 -> 29722.581 | E65: =IFERROR(G65/D65,) -> 0.2015306 | F65: ='2. 손익계산서'!E155*$N$4/1000000 -> 5318.6677 | G65: ='2. 손익계산서'!F155*$N$4/1000000 -> 5990.0094 | H65: =IFERROR(G65/F65,) -> 1.1262237 | I65: ='2. 손익계산서'!H155*$N$4/1000000 -> 2880.2947 | J65: =IFERROR(I65/$I$64,) -> 0.98200494 | K65: ='2. 손익계산서'!J155*$N$4/1000000 -> 3008.3442 | L65: =IFERROR(K65/$K$64,) -> 0.77742461 | M65: ='2. 손익계산서'!L155*$N$4/1000000 -> 3109.7147 | N65: =IFERROR(M65/$M$64,) -> 0.9334166 | O65: =IFERROR(M65/I65,) -> 1.0796516 | P65: =IFERROR(M65/K65,) -> 1.0336965
C66: Ford | D66: ='2. 손익계산서'!C156*$N$4/1000000 -> 5293.8391 | E66: =IFERROR(G66/D66,) -> 0.045885548 | F66: ='2. 손익계산서'!E156*$N$4/1000000 -> 1732.153 | G66: ='2. 손익계산서'!F156*$N$4/1000000 -> 242.91071 | H66: =IFERROR(G66/F66,) -> 0.14023629 | I66: ='2. 손익계산서'!H156*$N$4/1000000 -> 36.123152 | J66: =IFERROR(I66/$I$64,) -> 0.012315793 | K66: ='2. 손익계산서'!J156*$N$4/1000000 -> 861.28402 | L66: =IFERROR(K66/$K$64,) -> 0.22257539 | M66: ='2. 손익계산서'!L156*$N$4/1000000 -> 206.78756 | N66: =IFERROR(M66/$M$64,) -> 0.062069662 | O66: =IFERROR(M66/I66,) -> 5.724516 | P66: =IFERROR(M66/K66,) -> 0.24009218
C67: SKI | D67: ='2. 손익계산서'!C157*$N$4/1000000 -> 0 | E67: =IFERROR(G67/D67,) -> 0 | F67: ='2. 손익계산서'!E157*$N$4/1000000 -> 0 | G67: ='2. 손익계산서'!F157*$N$4/1000000 -> -13.496166 | H67: =IFERROR(G67/F67,) -> 0 | I67: ='2. 손익계산서'!H157*$N$4/1000000 -> -13.496166 | J67: =IFERROR(I67/$I$64,) -> -0.0046013701 | K67: ='2. 손익계산서'!J157*$N$4/1000000 -> 0 | L67: =IFERROR(K67/$K$64,) -> 0 | M67: ='2. 손익계산서'!L157*$N$4/1000000 -> 0 | N67: =IFERROR(M67/$M$64,) -> 0 | O67: =IFERROR(M67/I67,) -> 0 | P67: =IFERROR(M67/K67,) -> 0
C68: 기타 | D68: ='2. 손익계산서'!C158*$N$4/1000000 -> 0 | E68: =IFERROR(G68/D68,) -> 0 | F68: ='2. 손익계산서'!E158*$N$4/1000000 -> 0 | G68: ='2. 손익계산서'!F158*$N$4/1000000 -> 45.191587 | H68: =IFERROR(G68/F68,) -> 0 | I68: ='2. 손익계산서'!H158*$N$4/1000000 -> 30.153897 | J68: =IFERROR(I68/$I$64,) -> 0.010280641 | K68: ='2. 손익계산서'!J158*$N$4/1000000 -> 0 | L68: =IFERROR(K68/$K$64,) -> 0 | M68: ='2. 손익계산서'!L158*$N$4/1000000 -> 15.03769 | N68: =IFERROR(M68/$M$64,) -> 0.0045137356 | O68: =IFERROR(M68/I68,) -> 0.49869808 | P68: =IFERROR(M68/K68,) -> 0
J69: =IFERROR(I69/$I$64,) -> 0 | L69: =IFERROR(K69/$K$64,) -> 0 | N69: =IFERROR(M69/$M$64,) -> 0
C70: Ⅱ. 매출원가 | D70: ='2. 손익계산서'!C160*$N$4/1000000 -> 40903.034 | E70: =IFERROR(G70/D70,) -> 0.17282362 | F70: ='2. 손익계산서'!E160*$N$4/1000000 -> 7018.7855 | G70: ='2. 손익계산서'!F160*$N$4/1000000 -> 7069.0104 | H70: =IFERROR(G70/F70,) -> 1.0071558 | I70: ='2. 손익계산서'!H160*$N$4/1000000 -> 3259.7321 | J70: =IFERROR(I70/$I$64,) -> 1.11137 | K70: ='2. 손익계산서'!J160*$N$4/1000000 -> 3594.5099 | L70: =IFERROR(K70/$K$64,) -> 0.92890317 | M70: ='2. 손익계산서'!L160*$N$4/1000000 -> 3809.2783 | N70: =IFERROR(M70/$M$64,) -> 1.1433986 | O70: =IFERROR(M70/I70,) -> 1.1685863 | P70: =IFERROR(M70/K70,) -> 1.059749
C72: Ⅲ. 매출총이익 | D72: =D64-D70 -> -5886.6144 | E72: =IF(AND(D72>0,G72>0),G72/D72,"(-)") -> (-) | F72: =F64-F70 -> 32.035216 | G72: =G64-G70 -> -804.39484 | H72: =IF(AND(F72>0,G72>0),G72/F72,"(-)") -> (-) | I72: =I64-I70 -> -326.65656 | J72: =IFERROR(I72/$I$64,) -> -0.11136998 | K72: =K64-K70 -> 275.11828 | L72: =IFERROR(K72/$K$64,) -> 0.071096826 | M72: =M64-M70 -> -477.73828 | N72: =IFERROR(M72/$M$64,) -> -0.14339863 | O72: =IF(AND(I72>0,M72>0),M72/I72,"(-)") -> (-) | P72: =IF(AND(K72>0,M72>0),M72/K72,"(-)") -> (-)
C73: (이익률) | D73: =IFERROR(D72/D$64,) -> -0.16811012 | F73: =IFERROR(F72/F$64,) -> 0.0045434734 | G73: =IFERROR(G72/G$64,) -> -0.12840291 | I73: =IFERROR(I72/I$64,) -> -0.11136998 | K73: =IFERROR(K72/K$64,) -> 0.071096826 | M73: =IFERROR(M72/M$64,) -> -0.14339863
C74: Ⅳ.판매관리비 | D74: =SUM(D75:D77) -> 3032.0009 | E74: =IFERROR(G74/D74,) -> 0.30344816 | F74: =SUM(F75:F77) -> 478.68632 | G74: =SUM(G75:G77) -> 920.05509 | H74: =IFERROR(G74/F74,) -> 1.9220417 | I74: =SUM(I75:I77) -> 475.99863 | J74: =IFERROR(I74/$I$64,) -> 0.16228652 | K74: =SUM(K75:K77) -> 234.87224 | L74: =IFERROR(K74/$K$64,) -> 0.060696332 | M74: =SUM(M75:M77) -> 444.05646 | N74: =IFERROR(M74/$M$64,) -> 0.13328865 | O74: =IFERROR(M74/I74,) -> 0.9328944 | P74: =IFERROR(M74/K74,) -> 1.8906298
C75: [판매비] | D75: ='2. 손익계산서'!C168*$N$4/1000000 -> 0 | E75: =IFERROR(G75/D75,) -> 0 | F75: ='2. 손익계산서'!E168*$N$4/1000000 -> 0 | G75: ='2. 손익계산서'!F168*$N$4/1000000 -> 0 | H75: =IFERROR(G75/F75,) -> 0 | I75: ='2. 손익계산서'!H168*$N$4/1000000 -> 0 | J75: =IFERROR(I75/$I$64,) -> 0 | K75: ='2. 손익계산서'!J168*$N$4/1000000 -> 0 | L75: =IFERROR(K75/$K$64,) -> 0 | M75: ='2. 손익계산서'!L168*$N$4/1000000 -> 0 | N75: =IFERROR(M75/$M$64,) -> 0 | O75: =IFERROR(M75/I75,) -> 0 | P75: =IFERROR(M75/K75,) -> 0
C76: [관리비] | D76: ='2. 손익계산서'!C184*$N$4/1000000 -> 3032.0009 | E76: =IFERROR(G76/D76,) -> 0.30344816 | F76: ='2. 손익계산서'!E184*$N$4/1000000 -> 478.68632 | G76: ='2. 손익계산서'!F184*$N$4/1000000 -> 920.05509 | H76: =IFERROR(G76/F76,) -> 1.9220417 | I76: ='2. 손익계산서'!H184*$N$4/1000000 -> 475.99863 | J76: =IFERROR(I76/$I$64,) -> 0.16228652 | K76: ='2. 손익계산서'!J184*$N$4/1000000 -> 234.87224 | L76: =IFERROR(K76/$K$64,) -> 0.060696332 | M76: ='2. 손익계산서'!L184*$N$4/1000000 -> 444.05646 | N76: =IFERROR(M76/$M$64,) -> 0.13328865 | O76: =IFERROR(M76/I76,) -> 0.9328944 | P76: =IFERROR(M76/K76,) -> 1.8906298
C77: [연구개발비] | D77: ='2. 손익계산서'!C202*$N$4/1000000 -> 0 | E77: =IFERROR(G77/D77,) -> 0 | F77: ='2. 손익계산서'!E202*$N$4/1000000 -> 0 | G77: ='2. 손익계산서'!F202*$N$4/1000000 -> 0 | H77: =IFERROR(G77/F77,) -> 0 | I77: ='2. 손익계산서'!H202*$N$4/1000000 -> 0 | J77: =IFERROR(I77/$I$64,) -> 0 | K77: ='2. 손익계산서'!J202*$N$4/1000000 -> 0 | L77: =IFERROR(K77/$K$64,) -> 0 | M77: ='2. 손익계산서'!L202*$N$4/1000000 -> 0 | N77: =IFERROR(M77/$M$64,) -> 0 | O77: =IFERROR(M77/I77,) -> 0 | P77: =IFERROR(M77/K77,) -> 0
C78: Ⅴ.영업이익 | D78: =D72-D74 -> -8918.6153 | E78: =IF(AND(D78>0,G78>0),G78/D78,"(-)") -> (-) | F78: =F72-F74 -> -446.65111 | G78: =G72-G74 -> -1724.4499 | H78: =IF(AND(F78>0,G78>0),G78/F78,"(-)") -> (-) | I78: =I72-I74 -> -802.65519 | J78: =IFERROR(I78/$I$64,) -> -0.2736565 | K78: =K72-K74 -> 40.246044 | L78: =IFERROR(K78/$K$64,) -> 0.010400494 | M78: =M72-M74 -> -921.79474 | N78: =IFERROR(M78/$M$64,) -> -0.27668728 | O78: =IF(AND(I78>0,M78>0),M78/I78,"(-)") -> (-) | P78: =IF(AND(K78>0,M78>0),M78/K78,"(-)") -> (-)
C79: (이익률) | D79: =IFERROR(D78/D$64,) -> -0.25469809 | F79: =IFERROR(F78/F$64,) -> -0.063347392 | G79: =IFERROR(G78/G$64,) -> -0.27526828 | I79: =IFERROR(I78/I$64,) -> -0.2736565 | K79: =IFERROR(K78/K$64,) -> 0.010400494 | M79: =IFERROR(M78/M$64,) -> -0.27668728
C82: 플랜트간 부가가치 | D82: {=+SUM(D83:D84*1350)} -> 45170001 | E82: 백만원 | N82: DG 마크업 | O82: 26563.62 | P82: =+O82*1350 -> 35860887 | V82: 백만원
D83: 32284.24 | N83: GP 마크업 | O83: 22389.94 | P83: =+O83*1350 -> 30226419 | V83: 백만원
D84: 1175.02 | P84: =SUM(P82:P83) -> 66087306 | V84: 백만원
U95: =+V95*1330 -> 0
U99: =+V99*1330 -> 0

Sheet 2. 손익계산서
B3: Plofit and Loss statement FY 2026
B4: MONTH | C4: 2 | O4: (단위:$)
B5: 구 분 | C5: 2026년 계 획 | D5: 년계획 진척률 | E5: 누 계 계 획 | F5: 누 계 실 적 | G5: 달성률 | H5: 전 월 실 적 | I5: 매 출 구성비 | J5: 당 월 계 획 | K5: 매 출 구성비 | L5: 당 월 실 적 | M5: 매 출 구성비 | N5: 전 월 대 비 | O5: 계 획 대 비 | Y5: 연계획 | Z5: 누계 계획 | AA5: 누계 실적 | AB5: 전월 실적 | AC5: 당월 계획 | AD5: 당월 실적
B6: Ⅰ. 매출액 | C6: =C7+C9 -> 1.7358328e+08 | D6: =+IFERROR(F6/C6,) -> 0.15932415 | E6: =E7+E9 -> 28982629 | F6: =F7+F9 -> 27656009 | G6: =+IFERROR(F6/E6,) -> 0.95422707 | H6: =H7+H9 -> 12501980 | I6: =+IFERROR(H6/$H$6,) -> 1 | J6: =J7+J9 -> 14768325 | K6: =+IFERROR(J6/$J$6,) -> 1 | L6: =L7+L9 -> 15154029 | M6: =+IFERROR(L6/$L$6,) -> 1 | N6: =+IFERROR(L6/H6,) -> 1.2121303 | O6: =+IFERROR(L6/J6,) -> 1.026117 | Q6: 당월실적 | S6: 당월계획 | U6: 전월실적 | Y6: =+C6*1330/1000000 -> 230865.76 | Z6: =+E6*1330/1000000 -> 38546.896 | AA6: =+F6*1330/1000000 -> 36782.492 | AB6: =+H6*1330/1000000 -> 16627.633 | AC6: =+J6*1330/1000000 -> 19641.872 | AD6: =+L6*1330/1000000 -> 20154.859
B7: - 전선 | C7: ='(계획)손익계산서 월별계획'!C7 -> 1.4764519e+08 | D7: =+IFERROR(F7/C7,) -> 0.1558842 | E7: =SUM('(계획)손익계산서 월별계획'!E7:(OFFSET('(계획)손익계산서 월별계획'!E7,0,$C$4-1))) -> 23759798 | F7: =SUM('3. 손익계산서 월별실적'!E7:(OFFSET('3. 손익계산서 월별실적'!E7,0,$C$4-1))) -> 23015553 | G7: =+IFERROR(F7/E7,) -> 0.96867627 | H7: =OFFSET('3. 손익계산서 월별실적'!E7,0,$C$4-2) -> 10329331 | I7: =+IFERROR(H7/$H$6,) -> 0.82621564 | J7: =OFFSET('(계획)손익계산서 월별계획'!E7,0,$C$4-1) -> 11901934 | K7: =+IFERROR(J7/$J$6,) -> 0.80590952 | L7: =OFFSET('3. 손익계산서 월별실적'!E7,0,$C$4-1) -> 12686222 | M7: =+IFERROR(L7/$L$6,) -> 0.83715173 | N7: =+IFERROR(L7/H7,) -> 1.2281745 | O7: =+IFERROR(L7/J7,) -> 1.0658958 | S7: =+Q8-S8 -> -182563.12 | U7: =+Q8-U8 -> -1164932.3
B8: └ 매출동량 | C8: ='(계획)손익계산서 월별계획'!C8 -> 0 | D8: =+IFERROR(F8/C8,) -> 0 | E8: =SUM('(계획)손익계산서 월별계획'!E8:(OFFSET('(계획)손익계산서 월별계획'!E8,0,$C$4-1))) -> 0 | F8: =SUM('3. 손익계산서 월별실적'!E8:(OFFSET('3. 손익계산서 월별실적'!E8,0,$C$4-1))) -> 1346.4872 | G8: =+IFERROR(F8/E8,) -> 0 | H8: =OFFSET('3. 손익계산서 월별실적'!E8,0,$C$4-2) -> 631.81666 | I8: =+IFERROR(H8/$H$6,) -> 5.0537328e-05 | J8: =OFFSET('(계획)손익계산서 월별계획'!E8,0,$C$4-1) -> 0 | K8: =+IFERROR(J8/$J$6,) -> 0 | L8: =OFFSET('3. 손익계산서 월별실적'!E8,0,$C$4-1) -> 714.67057 | M8: =+IFERROR(L8/$L$6,) -> 4.7160433e-05 | N8: =+IFERROR(L8/H8,) -> 1.131136 | O8: =+IFERROR(L8/J8,) -> 0 | Q8: =+L8-L13 -> -2362937.6 | R8: =+Q8/L8 -> -3306.3312 | S8: =+J8-J13 -> -2180374.5 | T8: =+S8/J8 -> #DIV/0! | U8: =+H8-H13 -> -1198005.3 | V8: =+U8/H8 -> -1896.1281
B9: - 전장 | C9: ='(계획)손익계산서 월별계획'!C9 -> 25938089 | D9: =+IFERROR(F9/C9,) -> 0.17890508 | E9: =SUM('(계획)손익계산서 월별계획'!E9:(OFFSET('(계획)손익계산서 월별계획'!E9,0,$C$4-1))) -> 5222830.1 | F9: =SUM('3. 손익계산서 월별실적'!E9:(OFFSET('3. 손익계산서 월별실적'!E9,0,$C$4-1))) -> 4640455.9 | G9: =+IFERROR(F9/E9,) -> 0.88849452 | H9: =OFFSET('3. 손익계산서 월별실적'!E9,0,$C$4-2) -> 2172648.5 | I9: =+IFERROR(H9/$H$6,) -> 0.17378436 | J9: =OFFSET('(계획)손익계산서 월별계획'!E9,0,$C$4-1) -> 2866391.3 | K9: =+IFERROR(J9/$J$6,) -> 0.19409048 | L9: =OFFSET('3. 손익계산서 월별실적'!E9,0,$C$4-1) -> 2467807.4 | M9: =+IFERROR(L9/$L$6,) -> 0.16284827 | N9: =+IFERROR(L9/H9,) -> 1.1358521 | O9: =+IFERROR(L9/J9,) -> 0.86094576 | Q9: =+L9-L14 -> 2467807.4 | R9: =+Q9/L9 -> 1 | S9: =+J9-J14 -> 2793582.1 | T9: =+S9/J9 -> 0.974599 | U9: =+H9-H14 -> 2467338.5 | V9: =+U9/H9 -> 1.1356363
B11: Ⅱ. 매출원가 | C11: =SUM(C12:C14) -> 1.6273746e+08 | D11: =+IFERROR(F11/C11,) -> 0.15705544 | E11: =SUM(E12:E15) -> 26470571 | F11: =SUM(F12:F15) -> 25558804 | G11: =+IFERROR(F11/E11,) -> 0.96555544 | H11: =SUM(H12:H15) -> 11738514 | I11: =+IFERROR(H11/$H$6,) -> 0.93893244 | J11: =SUM(J12:J15) -> 13263500 | K11: =+IFERROR(J11/$J$6,) -> 0.89810458 | L11: =SUM(L12:L15) -> 13820290 | M11: =+IFERROR(L11/$L$6,) -> 0.9119878 | N11: =+IFERROR(L11/H11,) -> 1.1773457 | O11: =+IFERROR(L11/J11,) -> 1.0419791 | S11: =+Q10-S10 -> 0 | U11: =+Q10-U10 -> 0 | Y11: =+C11*1330/1000000 -> 216440.82 | Z11: =+E11*1330/1000000 -> 35205.86 | AA11: =+F11*1330/1000000 -> 33993.209 | AB11: =+H11*1330/1000000 -> 15612.224 | AC11: =+J11*1330/1000000 -> 17640.455 | AD11: =+L11*1330/1000000 -> 18380.985
B12: - 제품 | C12: ='(계획)손익계산서 월별계획'!C12 -> 1.3515827e+08 | D12: =+IFERROR(F12/C12,) -> 0.16492668 | E12: =SUM('(계획)손익계산서 월별계획'!E12:(OFFSET('(계획)손익계산서 월별계획'!E12,0,$C$4-1))) -> 21765122 | F12: =SUM('3. 손익계산서 월별실적'!E12:(OFFSET('3. 손익계산서 월별실적'!E12,0,$C$4-1))) -> 22291205 | G12: =+IFERROR(F12/E12,) -> 1.0241709 | H12: =OFFSET('3. 손익계산서 월별실적'!E12,0,$C$4-2) -> 10834567 | I12: =+IFERROR(H12/$H$6,) -> 0.86662812 | J12: =OFFSET('(계획)손익계산서 월별계획'!E12,0,$C$4-1) -> 11010317 | K12: =+IFERROR(J12/$J$6,) -> 0.74553591 | L12: =OFFSET('3. 손익계산서 월별실적'!E12,0,$C$4-1) -> 11456637 | M12: =+IFERROR(L12/$L$6,) -> 0.75601263 | N12: =+IFERROR(L12/H12,) -> 1.0574153 | O12: =+IFERROR(L12/J12,) -> 1.0405366
B13: - 상품 | C13: ='(계획)손익계산서 월별계획'!C13 -> 25798607 | D13: =+IFERROR(F13/C13,) -> 0.13808069 | E13: =SUM('(계획)손익계산서 월별계획'!E13:(OFFSET('(계획)손익계산서 월별계획'!E13,0,$C$4-1))) -> 4351631.1 | F13: =SUM('3. 손익계산서 월별실적'!E13:(OFFSET('3. 손익계산서 월별실적'!E13,0,$C$4-1))) -> 3562289.4 | G13: =+IFERROR(F13/E13,) -> 0.81861016 | H13: =OFFSET('3. 손익계산서 월별실적'!E13,0,$C$4-2) -> 1198637.1 | I13: =+IFERROR(H13/$H$6,) -> 0.095875785 | J13: =OFFSET('(계획)손익계산서 월별계획'!E13,0,$C$4-1) -> 2180374.5 | K13: =+IFERROR(J13/$J$6,) -> 0.14763858 | L13: =OFFSET('3. 손익계산서 월별실적'!E13,0,$C$4-1) -> 2363652.3 | M13: =+IFERROR(L13/$L$6,) -> 0.15597517 | N13: =+IFERROR(L13/H13,) -> 1.9719498 | O13: =+IFERROR(L13/J13,) -> 1.0840579
B14: - 기타 | C14: ='(계획)손익계산서 월별계획'!C14 -> 1780585.4 | D14: =+IFERROR(F14/C14,) -> -0.16550175 | E14: =SUM('(계획)손익계산서 월별계획'!E14:(OFFSET('(계획)손익계산서 월별계획'!E14,0,$C$4-1))) -> 353818.4 | F14: =SUM('3. 손익계산서 월별실적'!E14:(OFFSET('3. 손익계산서 월별실적'!E14,0,$C$4-1))) -> -294690 | G14: =+IFERROR(F14/E14,) -> -0.8328849 | H14: =OFFSET('3. 손익계산서 월별실적'!E14,0,$C$4-2) -> -294690 | I14: =+IFERROR(H14/$H$6,) -> -0.023571467 | J14: =OFFSET('(계획)손익계산서 월별계획'!E14,0,$C$4-1) -> 72809.198 | K14: =+IFERROR(J14/$J$6,) -> 0.0049300918 | L14: =OFFSET('3. 손익계산서 월별실적'!E14,0,$C$4-1) -> 0 | M14: =+IFERROR(L14/$L$6,) -> 0 | N14: =+IFERROR(L14/H14,) -> 0 | O14: =+IFERROR(L14/J14,) -> 0
B16: Ⅲ. 매출총이익 | C16: =C6-C11 -> 10845821 | D16: =IF(AND(C16>0,F16>0),F16/C16,"(-)") -> 0.19336524 | E16: =+E6-E11 -> 2512057.3 | F16: =+F6-F11 -> 2097204.8 | G16: =IF(AND(E16>0,F16>0),F16/E16,"(-)") -> 0.83485547 | H16: =+H6-H11 -> 763465.41 | I16: =+IFERROR(H16/$H$6,) -> 0.06106756 | J16: =+J6-J11 -> 1504824.6 | K16: =+IFERROR(J16/$J$6,) -> 0.10189542 | L16: =+L6-L11 -> 1333739.4 | M16: =+IFERROR(L16/$L$6,) -> 0.088012198 | N16: =+IF(AND(H16>0,L16>0),L16/H16,"(-)") -> 1.7469546 | O16: =+IF(AND(J16>0,N16>0),L16/J16,"(-)") -> 0.88630886 | Y16: =+C16*1330/1000000 -> 14424.942 | Z16: =+E16*1330/1000000 -> 3341.0362 | AA16: =+F16*1330/1000000 -> 2789.2824 | AB16: =+H16*1330/1000000 -> 1015.409 | AC16: =+J16*1330/1000000 -> 2001.4167 | AD16: =+L16*1330/1000000 -> 1773.8734
B17: (이익률) | C17: =+IFERROR(C16/C6,) -> 0.062481946 | E17: =+IFERROR(E16/E6,) -> 0.086674585 | F17: =+IFERROR(F16/F6,) -> 0.075831795 | G17: =+IFERROR(F17/E17,) -> 0.87490231 | H17: =+IFERROR(H16/H6,) -> 0.06106756 | J17: =+IFERROR(J16/J6,) -> 0.10189542 | L17: =+IFERROR(L16/L6,) -> 0.088012198 | Y17: =+Y6-Y11 -> 14424.942 | Z17: =+Z6-Z11 -> 3341.0362 | AA17: =+AA6-AA11 -> 2789.2824 | AB17: =+AB6-AB11 -> 1015.409 | AC17: =+AC6-AC11 -> 2001.4167 | AD17: =+AD6-AD11 -> 1773.8734
B18: Ⅳ.판매관리비 | C18: =SUM(C19,C35,C53) -> 9264881.1 | D18: =+IFERROR(F18/C18,) -> 0.15125711 | E18: =+E19+E35+E53 -> 1564108.6 | F18: =+F19+F35+F53 -> 1401379.1 | G18: =+IFERROR(F18/E18,) -> 0.89596021 | H18: =+H19+H35+H53 -> 695216.17 | I18: =+IFERROR(H18/$H$6,) -> 0.055608486 | J18: =+J19+J35+J53 -> 760648.13 | K18: =+IFERROR(J18/$J$6,) -> 0.051505376 | L18: =+L19+L35+L53 -> 706162.94 | M18: =+IFERROR(L18/$L$6,) -> 0.046599023 | N18: =+IFERROR(L18/H18,) -> 1.0157459 | O18: =+IFERROR(L18/J18,) -> 0.92837004 | Q18: =+L18-J18 -> -54485.193 | R18: =+L18-H18 -> 10946.77 | Y18: =+C18*1330/1000000 -> 12322.292 | Z18: =+E18*1330/1000000 -> 2080.2645 | AA18: =+F18*1330/1000000 -> 1863.8342 | AB18: =+H18*1330/1000000 -> 924.63751 | AC18: =+J18*1330/1000000 -> 1011.662 | AD18: =+L18*1330/1000000 -> 939.19671
B19: [판매비] | C19: =SUM(C20:C33) -> 0 | D19: =+IFERROR(F19/C19,) -> 0 | E19: =SUM(E20:E34) -> 0 | F19: =SUM(F20:F34) -> 0 | G19: =+IFERROR(F19/E19,) -> 0 | H19: =SUM(H20:H34) -> 0 | I19: =+IFERROR(H19/$H$6,) -> 0 | J19: =SUM(J20:J34) -> 0 | K19: =+IFERROR(J19/$J$6,) -> 0 | L19: =SUM(L20:L34) -> 0 | M19: =+IFERROR(L19/$L$6,) -> 0 | N19: =+IFERROR(L19/H19,) -> 0 | O19: =+IFERROR(L19/J19,) -> 0 | R19: 누계 계획 | S19: 누계 실적
B20: 인건비 | C20: ='(계획)손익계산서 월별계획'!C20 -> 0 | D20: =+IFERROR(F20/C20,) -> 0 | E20: =SUM('(계획)손익계산서 월별계획'!E20:(OFFSET('(계획)손익계산서 월별계획'!E20,0,$C$4-1))) -> 0 | F20: =SUM('3. 손익계산서 월별실적'!E20:(OFFSET('3. 손익계산서 월별실적'!E20,0,$C$4-1))) -> 0 | G20: =+IFERROR(F20/E20,) -> 0 | H20: =OFFSET('3. 손익계산서 월별실적'!E20,0,$C$4-2) -> 0 | I20: =+IFERROR(H20/$H$6,) -> 0 | J20: =OFFSET('(계획)손익계산서 월별계획'!E20,0,$C$4-1) -> 0 | K20: =+IFERROR(J20/$J$6,) -> 0 | L20: =OFFSET('3. 손익계산서 월별실적'!E20,0,$C$4-1) -> 0 | M20: =+IFERROR(L20/$L$6,) -> 0 | N20: =+IFERROR(L20/H20,) -> 0 | O20: =+IFERROR(L20/J20,) -> 0 | Q20: 인건비 | R20: =+E20+E36+E54 -> 694634.81 | S20: =+F20+F36+F54 -> 646352.28 | T20: =+S20/R20 -> 0.93049221
B21: 유지비용 | C21: ='(계획)손익계산서 월별계획'!C21 -> 0 | D21: =+IFERROR(F21/C21,) -> 0 | E21: =SUM('(계획)손익계산서 월별계획'!E21:(OFFSET('(계획)손익계산서 월별계획'!E21,0,$C$4-1))) -> 0 | F21: =SUM('3. 손익계산서 월별실적'!E21:(OFFSET('3. 손익계산서 월별실적'!E21,0,$C$4-1))) -> 0 | G21: =+IFERROR(F21/E21,) -> 0 | H21: =OFFSET('3. 손익계산서 월별실적'!E21,0,$C$4-2) -> 0 | I21: =+IFERROR(H21/$H$6,) -> 0 | J21: =OFFSET('(계획)손익계산서 월별계획'!E21,0,$C$4-1) -> 0 | K21: =+IFERROR(J21/$J$6,) -> 0 | L21: =OFFSET('3. 손익계산서 월별실적'!E21,0,$C$4-1) -> 0 | M21: =+IFERROR(L21/$L$6,) -> 0 | N21: =+IFERROR(L21/H21,) -> 0 | O21: =+IFERROR(L21/J21,) -> 0 | Q21: 지급수수료비 | R21: =SUM(E27,E43,E61) -> 573325.33 | S21: =SUM(F27,F43,F61) -> 478068.05 | T21: =+S21/R21 -> 0.83385126
B22: 세금,보험 | C22: ='(계획)손익계산서 월별계획'!C22 -> 0 | D22: =+IFERROR(F22/C22,) -> 0 | E22: =SUM('(계획)손익계산서 월별계획'!E22:(OFFSET('(계획)손익계산서 월별계획'!E22,0,$C$4-1))) -> 0 | F22: =SUM('3. 손익계산서 월별실적'!E22:(OFFSET('3. 손익계산서 월별실적'!E22,0,$C$4-1))) -> 0 | G22: =+IFERROR(F22/E22,) -> 0 | H22: =OFFSET('3. 손익계산서 월별실적'!E22,0,$C$4-2) -> 0 | I22: =+IFERROR(H22/$H$6,) -> 0 | J22: =OFFSET('(계획)손익계산서 월별계획'!E22,0,$C$4-1) -> 0 | K22: =+IFERROR(J22/$J$6,) -> 0 | L22: =OFFSET('3. 손익계산서 월별실적'!E22,0,$C$4-1) -> 0 | M22: =+IFERROR(L22/$L$6,) -> 0 | N22: =+IFERROR(L22/H22,) -> 0 | O22: =+IFERROR(L22/J22,) -> 0 | Q22: 개발비 | R22: =SUM(E30,E46,E64) -> 0 | S22: =SUM(F30,F46,F64) -> 0 | T22: =+S22/R22 -> #DIV/0!
B23: 복리후생비 | C23: ='(계획)손익계산서 월별계획'!C23 -> 0 | D23: =+IFERROR(F23/C23,) -> 0 | E23: =SUM('(계획)손익계산서 월별계획'!E23:(OFFSET('(계획)손익계산서 월별계획'!E23,0,$C$4-1))) -> 0 | F23: =SUM('3. 손익계산서 월별실적'!E23:(OFFSET('3. 손익계산서 월별실적'!E23,0,$C$4-1))) -> 0 | G23: =+IFERROR(F23/E23,) -> 0 | H23: =OFFSET('3. 손익계산서 월별실적'!E23,0,$C$4-2) -> 0 | I23: =+IFERROR(H23/$H$6,) -> 0 | J23: =OFFSET('(계획)손익계산서 월별계획'!E23,0,$C$4-1) -> 0 | K23: =+IFERROR(J23/$J$6,) -> 0 | L23: =OFFSET('3. 손익계산서 월별실적'!E23,0,$C$4-1) -> 0 | M23: =+IFERROR(L23/$L$6,) -> 0 | N23: =+IFERROR(L23/H23,) -> 0 | O23: =+IFERROR(L23/J23,) -> 0
B24: 운반비 | C24: ='(계획)손익계산서 월별계획'!C24 -> 0 | D24: =+IFERROR(F24/C24,) -> 0 | E24: =SUM('(계획)손익계산서 월별계획'!E24:(OFFSET('(계획)손익계산서 월별계획'!E24,0,$C$4-1))) -> 0 | F24: =SUM('3. 손익계산서 월별실적'!E24:(OFFSET('3. 손익계산서 월별실적'!E24,0,$C$4-1))) -> 0 | G24: =+IFERROR(F24/E24,) -> 0 | H24: =OFFSET('3. 손익계산서 월별실적'!E24,0,$C$4-2) -> 0 | I24: =+IFERROR(H24/$H$6,) -> 0 | J24: =OFFSET('(계획)손익계산서 월별계획'!E24,0,$C$4-1) -> 0 | K24: =+IFERROR(J24/$J$6,) -> 0 | L24: =OFFSET('3. 손익계산서 월별실적'!E24,0,$C$4-1) -> 0 | M24: =+IFERROR(L24/$L$6,) -> 0 | N24: =+IFERROR(L24/H24,) -> 0 | O24: =+IFERROR(L24/J24,) -> 0
B25: 포장비 | C25: ='(계획)손익계산서 월별계획'!C25 -> 0 | D25: =+IFERROR(F25/C25,) -> 0 | E25: =SUM('(계획)손익계산서 월별계획'!E25:(OFFSET('(계획)손익계산서 월별계획'!E25,0,$C$4-1))) -> 0 | F25: =SUM('3. 손익계산서 월별실적'!E25:(OFFSET('3. 손익계산서 월별실적'!E25,0,$C$4-1))) -> 0 | G25: =+IFERROR(F25/E25,) -> 0 | H25: =OFFSET('3. 손익계산서 월별실적'!E25,0,$C$4-2) -> 0 | I25: =+IFERROR(H25/$H$6,) -> 0 | J25: =OFFSET('(계획)손익계산서 월별계획'!E25,0,$C$4-1) -> 0 | K25: =+IFERROR(J25/$J$6,) -> 0 | L25: =OFFSET('3. 손익계산서 월별실적'!E25,0,$C$4-1) -> 0 | M25: =+IFERROR(L25/$L$6,) -> 0 | N25: =+IFERROR(L25/H25,) -> 0 | O25: =+IFERROR(L25/J25,) -> 0
B26: 광고선전비 | C26: ='(계획)손익계산서 월별계획'!C26 -> 0 | D26: =+IFERROR(F26/C26,) -> 0 | E26: =SUM('(계획)손익계산서 월별계획'!E26:(OFFSET('(계획)손익계산서 월별계획'!E26,0,$C$4-1))) -> 0 | F26: =SUM('3. 손익계산서 월별실적'!E26:(OFFSET('3. 손익계산서 월별실적'!E26,0,$C$4-1))) -> 0 | G26: =+IFERROR(F26/E26,) -> 0 | H26: =OFFSET('3. 손익계산서 월별실적'!E26,0,$C$4-2) -> 0 | I26: =+IFERROR(H26/$H$6,) -> 0 | J26: =OFFSET('(계획)손익계산서 월별계획'!E26,0,$C$4-1) -> 0 | K26: =+IFERROR(J26/$J$6,) -> 0 | L26: =OFFSET('3. 손익계산서 월별실적'!E26,0,$C$4-1) -> 0 | M26: =+IFERROR(L26/$L$6,) -> 0 | N26: =+IFERROR(L26/H26,) -> 0 | O26: =+IFERROR(L26/J26,) -> 0
B27: 지급수수료 | C27: ='(계획)손익계산서 월별계획'!C27 -> 0 | D27: =+IFERROR(F27/C27,) -> 0 | E27: =SUM('(계획)손익계산서 월별계획'!E27:(OFFSET('(계획)손익계산서 월별계획'!E27,0,$C$4-1))) -> 0 | F27: =SUM('3. 손익계산서 월별실적'!E27:(OFFSET('3. 손익계산서 월별실적'!E27,0,$C$4-1))) -> 0 | G27: =+IFERROR(F27/E27,) -> 0 | H27: =OFFSET('3. 손익계산서 월별실적'!E27,0,$C$4-2) -> 0 | I27: =+IFERROR(H27/$H$6,) -> 0 | J27: =OFFSET('(계획)손익계산서 월별계획'!E27,0,$C$4-1) -> 0 | K27: =+IFERROR(J27/$J$6,) -> 0 | L27: =OFFSET('3. 손익계산서 월별실적'!E27,0,$C$4-1) -> 0 | M27: =+IFERROR(L27/$L$6,) -> 0 | N27: =+IFERROR(L27/H27,) -> 0 | O27: =+IFERROR(L27/J27,) -> 0
B28: 여비교통비 | C28: ='(계획)손익계산서 월별계획'!C28 -> 0 | D28: =+IFERROR(F28/C28,) -> 0 | E28: =SUM('(계획)손익계산서 월별계획'!E28:(OFFSET('(계획)손익계산서 월별계획'!E28,0,$C$4-1))) -> 0 | F28: =SUM('3. 손익계산서 월별실적'!E28:(OFFSET('3. 손익계산서 월별실적'!E28,0,$C$4-1))) -> 0 | G28: =+IFERROR(F28/E28,) -> 0 | H28: =OFFSET('3. 손익계산서 월별실적'!E28,0,$C$4-2) -> 0 | I28: =+IFERROR(H28/$H$6,) -> 0 | J28: =OFFSET('(계획)손익계산서 월별계획'!E28,0,$C$4-1) -> 0 | K28: =+IFERROR(J28/$J$6,) -> 0 | L28: =OFFSET('3. 손익계산서 월별실적'!E28,0,$C$4-1) -> 0 | M28: =+IFERROR(L28/$L$6,) -> 0 | N28: =+IFERROR(L28/H28,) -> 0 | O28: =+IFERROR(L28/J28,) -> 0
B29: 감가상각비 | C29: ='(계획)손익계산서 월별계획'!C29 -> 0 | D29: =+IFERROR(F29/C29,) -> 0 | E29: =SUM('(계획)손익계산서 월별계획'!E29:(OFFSET('(계획)손익계산서 월별계획'!E29,0,$C$4-1))) -> 0 | F29: =SUM('3. 손익계산서 월별실적'!E29:(OFFSET('3. 손익계산서 월별실적'!E29,0,$C$4-1))) -> 0 | G29: =+IFERROR(F29/E29,) -> 0 | H29: =OFFSET('3. 손익계산서 월별실적'!E29,0,$C$4-2) -> 0 | I29: =+IFERROR(H29/$H$6,) -> 0 | J29: =OFFSET('(계획)손익계산서 월별계획'!E29,0,$C$4-1) -> 0 | K29: =+IFERROR(J29/$J$6,) -> 0 | L29: =OFFSET('3. 손익계산서 월별실적'!E29,0,$C$4-1) -> 0 | M29: =+IFERROR(L29/$L$6,) -> 0 | N29: =+IFERROR(L29/H29,) -> 0 | O29: =+IFERROR(L29/J29,) -> 0
B30: 개발비 | C30: ='(계획)손익계산서 월별계획'!C30 -> 0 | D30: =+IFERROR(F30/C30,) -> 0 | E30: =SUM('(계획)손익계산서 월별계획'!E30:(OFFSET('(계획)손익계산서 월별계획'!E30,0,$C$4-1))) -> 0 | F30: =SUM('3. 손익계산서 월별실적'!E30:(OFFSET('3. 손익계산서 월별실적'!E30,0,$C$4-1))) -> 0 | G30: =+IFERROR(F30/E30,) -> 0 | H30: =OFFSET('3. 손익계산서 월별실적'!E30,0,$C$4-2) -> 0 | I30: =+IFERROR(H30/$H$6,) -> 0 | J30: =OFFSET('(계획)손익계산서 월별계획'!E30,0,$C$4-1) -> 0 | K30: =+IFERROR(J30/$J$6,) -> 0 | L30: =OFFSET('3. 손익계산서 월별실적'!E30,0,$C$4-1) -> 0 | M30: =+IFERROR(L30/$L$6,) -> 0 | N30: =+IFERROR(L30/H30,) -> 0 | O30: =+IFERROR(L30/J30,) -> 0
B31: 충당비용 | C31: ='(계획)손익계산서 월별계획'!C31 -> 0 | D31: =+IFERROR(F31/C31,) -> 0 | E31: =SUM('(계획)손익계산서 월별계획'!E31:(OFFSET('(계획)손익계산서 월별계획'!E31,0,$C$4-1))) -> 0 | F31: =SUM('3. 손익계산서 월별실적'!E31:(OFFSET('3. 손익계산서 월별실적'!E31,0,$C$4-1))) -> 0 | G31: =+IFERROR(F31/E31,) -> 0 | H31: =OFFSET('3. 손익계산서 월별실적'!E31,0,$C$4-2) -> 0 | I31: =+IFERROR(H31/$H$6,) -> 0 | J31: =OFFSET('(계획)손익계산서 월별계획'!E31,0,$C$4-1) -> 0 | K31: =+IFERROR(J31/$J$6,) -> 0 | L31: =OFFSET('3. 손익계산서 월별실적'!E31,0,$C$4-1) -> 0 | M31: =+IFERROR(L31/$L$6,) -> 0 | N31: =+IFERROR(L31/H31,) -> 0 | O31: =+IFERROR(L31/J31,) -> 0
B32: 외주비 | C32: ='(계획)손익계산서 월별계획'!C32 -> 0 | D32: =+IFERROR(F32/C32,) -> 0 | E32: =SUM('(계획)손익계산서 월별계획'!E32:(OFFSET('(계획)손익계산서 월별계획'!E32,0,$C$4-1))) -> 0 | F32: =SUM('3. 손익계산서 월별실적'!E32:(OFFSET('3. 손익계산서 월별실적'!E32,0,$C$4-1))) -> 0 | G32: =+IFERROR(F32/E32,) -> 0 | H32: =OFFSET('3. 손익계산서 월별실적'!E32,0,$C$4-2) -> 0 | I32: =+IFERROR(H32/$H$6,) -> 0 | J32: =OFFSET('(계획)손익계산서 월별계획'!E32,0,$C$4-1) -> 0 | K32: =+IFERROR(J32/$J$6,) -> 0 | L32: =OFFSET('3. 손익계산서 월별실적'!E32,0,$C$4-1) -> 0 | M32: =+IFERROR(L32/$L$6,) -> 0 | N32: =+IFERROR(L32/H32,) -> 0 | O32: =+IFERROR(L32/J32,) -> 0
B33: 기타비용 | C33: ='(계획)손익계산서 월별계획'!C33 -> 0 | D33: =+IFERROR(F33/C33,) -> 0 | E33: =SUM('(계획)손익계산서 월별계획'!E33:(OFFSET('(계획)손익계산서 월별계획'!E33,0,$C$4-1))) -> 0 | F33: =SUM('3. 손익계산서 월별실적'!E33:(OFFSET('3. 손익계산서 월별실적'!E33,0,$C$4-1))) -> 0 | G33: =+IFERROR(F33/E33,) -> 0 | H33: =OFFSET('3. 손익계산서 월별실적'!E33,0,$C$4-2) -> 0 | I33: =+IFERROR(H33/$H$6,) -> 0 | J33: =OFFSET('(계획)손익계산서 월별계획'!E33,0,$C$4-1) -> 0 | K33: =+IFERROR(J33/$J$6,) -> 0 | L33: =OFFSET('3. 손익계산서 월별실적'!E33,0,$C$4-1) -> 0 | M33: =+IFERROR(L33/$L$6,) -> 0 | N33: =+IFERROR(L33/H33,) -> 0 | O33: =+IFERROR(L33/J33,) -> 0
B35: [관리비] | C35: =SUM(C36:C51) -> 9264881.1 | D35: =+IFERROR(F35/C35,) -> 0.15125711 | E35: =SUM(E36:E51) -> 1564108.6 | F35: =SUM(F36:F51) -> 1401379.1 | G35: =+IFERROR(F35/E35,) -> 0.89596021 | H35: =SUM(H36:H51) -> 695216.17 | I35: =+IFERROR(H35/$H$6,) -> 0.055608486 | J35: =SUM(J36:J51) -> 760648.13 | K35: =+IFERROR(J35/$J$6,) -> 0.051505376 | L35: =SUM(L36:L51) -> 706162.94 | M35: =+IFERROR(L35/$L$6,) -> 0.046599023 | N35: =+IFERROR(L35/H35,) -> 1.0157459 | O35: =+IFERROR(L35/J35,) -> 0.92837004
B36: 인건비 | C36: ='(계획)손익계산서 월별계획'!C36 -> 4201174.1 | D36: =+IFERROR(F36/C36,) -> 0.15385039 | E36: =SUM('(계획)손익계산서 월별계획'!E36:(OFFSET('(계획)손익계산서 월별계획'!E36,0,$C$4-1))) -> 694634.81 | F36: =SUM('3. 손익계산서 월별실적'!E36:(OFFSET('3. 손익계산서 월별실적'!E36,0,$C$4-1))) -> 646352.28 | G36: =+IFERROR(F36/E36,) -> 0.93049221 | H36: =OFFSET('3. 손익계산서 월별실적'!E36,0,$C$4-2) -> 325645.54 | I36: =+IFERROR(H36/$H$6,) -> 0.026047518 | J36: =OFFSET('(계획)손익계산서 월별계획'!E36,0,$C$4-1) -> 347317.4 | K36: =+IFERROR(J36/$J$6,) -> 0.023517725 | L36: =OFFSET('3. 손익계산서 월별실적'!E36,0,$C$4-1) -> 320706.74 | M36: =+IFERROR(L36/$L$6,) -> 0.021163134 | N36: =+IFERROR(L36/H36,) -> 0.98483382 | O36: =+IFERROR(L36/J36,) -> 0.92338229
B37: 유지비용 | C37: ='(계획)손익계산서 월별계획'!C37 -> 132669.7 | D37: =+IFERROR(F37/C37,) -> 0.1950468 | E37: =SUM('(계획)손익계산서 월별계획'!E37:(OFFSET('(계획)손익계산서 월별계획'!E37,0,$C$4-1))) -> 22111.616 | F37: =SUM('3. 손익계산서 월별실적'!E37:(OFFSET('3. 손익계산서 월별실적'!E37,0,$C$4-1))) -> 25876.8 | G37: =+IFERROR(F37/E37,) -> 1.1702808 | H37: =OFFSET('3. 손익계산서 월별실적'!E37,0,$C$4-2) -> 12954.35 | I37: =+IFERROR(H37/$H$6,) -> 0.0010361839 | J37: =OFFSET('(계획)손익계산서 월별계획'!E37,0,$C$4-1) -> 11055.808 | K37: =+IFERROR(J37/$J$6,) -> 0.00074861625 | L37: =OFFSET('3. 손익계산서 월별실적'!E37,0,$C$4-1) -> 12922.45 | M37: =+IFERROR(L37/$L$6,) -> 0.00085274022 | N37: =+IFERROR(L37/H37,) -> 0.99753751 | O37: =+IFERROR(L37/J37,) -> 1.1688381
B38: 세금,보험 | C38: ='(계획)손익계산서 월별계획'!C38 -> 976247.63 | D38: =+IFERROR(F38/C38,) -> 0.063038832 | E38: =SUM('(계획)손익계산서 월별계획'!E38:(OFFSET('(계획)손익계산서 월별계획'!E38,0,$C$4-1))) -> 157341.97 | F38: =SUM('3. 손익계산서 월별실적'!E38:(OFFSET('3. 손익계산서 월별실적'!E38,0,$C$4-1))) -> 61541.51 | G38: =+IFERROR(F38/E38,) -> 0.3911322 | H38: =OFFSET('3. 손익계산서 월별실적'!E38,0,$C$4-2) -> 28636.21 | I38: =+IFERROR(H38/$H$6,) -> 0.002290534 | J38: =OFFSET('(계획)손익계산서 월별계획'!E38,0,$C$4-1) -> 79287.119 | K38: =+IFERROR(J38/$J$6,) -> 0.005368728 | L38: =OFFSET('3. 손익계산서 월별실적'!E38,0,$C$4-1) -> 32905.3 | M38: =+IFERROR(L38/$L$6,) -> 0.0021713895 | N38: =+IFERROR(L38/H38,) -> 1.1490801 | O38: =+IFERROR(L38/J38,) -> 0.41501445
B39: 복리후생비 | C39: ='(계획)손익계산서 월별계획'!C39 -> 262838.83 | D39: =+IFERROR(F39/C39,) -> 0.024967886 | E39: =SUM('(계획)손익계산서 월별계획'!E39:(OFFSET('(계획)손익계산서 월별계획'!E39,0,$C$4-1))) -> 41707.292 | F39: =SUM('3. 손익계산서 월별실적'!E39:(OFFSET('3. 손익계산서 월별실적'!E39,0,$C$4-1))) -> 6562.53 | G39: =+IFERROR(F39/E39,) -> 0.15734731 | H39: =OFFSET('3. 손익계산서 월별실적'!E39,0,$C$4-2) -> 2374.41 | I39: =+IFERROR(H39/$H$6,) -> 0.00018992272 | J39: =OFFSET('(계획)손익계산서 월별계획'!E39,0,$C$4-1) -> 20279.416 | K39: =+IFERROR(J39/$J$6,) -> 0.0013731697 | L39: =OFFSET('3. 손익계산서 월별실적'!E39,0,$C$4-1) -> 4188.12 | M39: =+IFERROR(L39/$L$6,) -> 0.00027637007 | N39: =+IFERROR(L39/H39,) -> 1.7638571 | O39: =+IFERROR(L39/J39,) -> 0.20652074
B40: 운반비 | C40: ='(계획)손익계산서 월별계획'!C40 -> 0 | D40: =+IFERROR(F40/C40,) -> 0 | E40: =SUM('(계획)손익계산서 월별계획'!E40:(OFFSET('(계획)손익계산서 월별계획'!E40,0,$C$4-1))) -> 0 | F40: =SUM('3. 손익계산서 월별실적'!E40:(OFFSET('3. 손익계산서 월별실적'!E40,0,$C$4-1))) -> 91123.68 | G40: =+IFERROR(F40/E40,) -> 0 | H40: =OFFSET('3. 손익계산서 월별실적'!E40,0,$C$4-2) -> 58276.9 | I40: =+IFERROR(H40/$H$6,) -> 0.0046614137 | J40: =OFFSET('(계획)손익계산서 월별계획'!E40,0,$C$4-1) -> 0 | K40: =+IFERROR(J40/$J$6,) -> 0 | L40: =OFFSET('3. 손익계산서 월별실적'!E40,0,$C$4-1) -> 32846.78 | M40: =+IFERROR(L40/$L$6,) -> 0.0021675279 | N40: =+IFERROR(L40/H40,) -> 0.56363293 | O40: =+IFERROR(L40/J40,) -> 0
B41: 포장비 | C41: ='(계획)손익계산서 월별계획'!C41 -> 0 | D41: =+IFERROR(F41/C41,) -> 0 | E41: =SUM('(계획)손익계산서 월별계획'!E41:(OFFSET('(계획)손익계산서 월별계획'!E41,0,$C$4-1))) -> 0 | F41: =SUM('3. 손익계산서 월별실적'!E41:(OFFSET('3. 손익계산서 월별실적'!E41,0,$C$4-1))) -> 0 | G41: =+IFERROR(F41/E41,) -> 0 | H41: =OFFSET('3. 손익계산서 월별실적'!E41,0,$C$4-2) -> 0 | I41: =+IFERROR(H41/$H$6,) -> 0 | J41: =OFFSET('(계획)손익계산서 월별계획'!E41,0,$C$4-1) -> 0 | K41: =+IFERROR(J41/$J$6,) -> 0 | L41: =OFFSET('3. 손익계산서 월별실적'!E41,0,$C$4-1) -> 0 | M41: =+IFERROR(L41/$L$6,) -> 0 | N41: =+IFERROR(L41/H41,) -> 0 | O41: =+IFERROR(L41/J41,) -> 0
B42: 광고선전비 | C42: ='(계획)손익계산서 월별계획'!C42 -> 0 | D42: =+IFERROR(F42/C42,) -> 0 | E42: =SUM('(계획)손익계산서 월별계획'!E42:(OFFSET('(계획)손익계산서 월별계획'!E42,0,$C$4-1))) -> 0 | F42: =SUM('3. 손익계산서 월별실적'!E42:(OFFSET('3. 손익계산서 월별실적'!E42,0,$C$4-1))) -> 18646.72 | G42: =+IFERROR(F42/E42,) -> 0 | H42: =OFFSET('3. 손익계산서 월별실적'!E42,0,$C$4-2) -> 4997.23 | I42: =+IFERROR(H42/$H$6,) -> 0.00039971509 | J42: =OFFSET('(계획)손익계산서 월별계획'!E42,0,$C$4-1) -> 0 | K42: =+IFERROR(J42/$J$6,) -> 0 | L42: =OFFSET('3. 손익계산서 월별실적'!E42,0,$C$4-1) -> 13649.49 | M42: =+IFERROR(L42/$L$6,) -> 0.0009007169 | N42: =+IFERROR(L42/H42,) -> 2.7314112 | O42: =+IFERROR(L42/J42,) -> 0
B43: 지급수수료 | C43: ='(계획)손익계산서 월별계획'!C43 -> 3243763.7 | D43: =+IFERROR(F43/C43,) -> 0.14738066 | E43: =SUM('(계획)손익계산서 월별계획'!E43:(OFFSET('(계획)손익계산서 월별계획'!E43,0,$C$4-1))) -> 573325.33 | F43: =SUM('3. 손익계산서 월별실적'!E43:(OFFSET('3. 손익계산서 월별실적'!E43,0,$C$4-1))) -> 478068.05 | G43: =+IFERROR(F43/E43,) -> 0.83385126 | H43: =OFFSET('3. 손익계산서 월별실적'!E43,0,$C$4-2) -> 225126.16 | I43: =+IFERROR(H43/$H$6,) -> 0.018007241 | J43: =OFFSET('(계획)손익계산서 월별계획'!E43,0,$C$4-1) -> 265214.57 | K43: =+IFERROR(J43/$J$6,) -> 0.017958338 | L43: =OFFSET('3. 손익계산서 월별실적'!E43,0,$C$4-1) -> 252941.89 | M43: =+IFERROR(L43/$L$6,) -> 0.016691395 | N43: =+IFERROR(L43/H43,) -> 1.1235562 | O43: =+IFERROR(L43/J43,) -> 0.95372546
B44: 여비교통비 | C44: ='(계획)손익계산서 월별계획'!C44 -> 191128.13 | D44: =+IFERROR(F44/C44,) -> 0.21273985 | E44: =SUM('(계획)손익계산서 월별계획'!E44:(OFFSET('(계획)손익계산서 월별계획'!E44,0,$C$4-1))) -> 31854.688 | F44: =SUM('3. 손익계산서 월별실적'!E44:(OFFSET('3. 손익계산서 월별실적'!E44,0,$C$4-1))) -> 40660.57 | G44: =+IFERROR(F44/E44,) -> 1.2764391 | H44: =OFFSET('3. 손익계산서 월별실적'!E44,0,$C$4-2) -> 18498.97 | I44: =+IFERROR(H44/$H$6,) -> 0.0014796832 | J44: =OFFSET('(계획)손익계산서 월별계획'!E44,0,$C$4-1) -> 15927.344 | K44: =+IFERROR(J44/$J$6,) -> 0.0010784801 | L44: =OFFSET('3. 손익계산서 월별실적'!E44,0,$C$4-1) -> 22161.6 | M44: =+IFERROR(L44/$L$6,) -> 0.001462423 | N44: =+IFERROR(L44/H44,) -> 1.197991 | O44: =+IFERROR(L44/J44,) -> 1.3914184
B45: 감가상각비 | C45: ='(계획)손익계산서 월별계획'!C45 -> 0 | D45: =+IFERROR(F45/C45,) -> 0 | E45: =SUM('(계획)손익계산서 월별계획'!E45:(OFFSET('(계획)손익계산서 월별계획'!E45,0,$C$4-1))) -> 0 | F45: =SUM('3. 손익계산서 월별실적'!E45:(OFFSET('3. 손익계산서 월별실적'!E45,0,$C$4-1))) -> 10328.31 | G45: =+IFERROR(F45/E45,) -> 0 | H45: =OFFSET('3. 손익계산서 월별실적'!E45,0,$C$4-2) -> 5419.12 | I45: =+IFERROR(H45/$H$6,) -> 0.00043346094 | J45: =OFFSET('(계획)손익계산서 월별계획'!E45,0,$C$4-1) -> 0 | K45: =+IFERROR(J45/$J$6,) -> 0 | L45: =OFFSET('3. 손익계산서 월별실적'!E45,0,$C$4-1) -> 4909.19 | M45: =+IFERROR(L45/$L$6,) -> 0.00032395279 | N45: =+IFERROR(L45/H45,) -> 0.9059017 | O45: =+IFERROR(L45/J45,) -> 0
B46: 개발비 | C46: ='(계획)손익계산서 월별계획'!C46 -> 0 | D46: =+IFERROR(F46/C46,) -> 0 | E46: =SUM('(계획)손익계산서 월별계획'!E46:(OFFSET('(계획)손익계산서 월별계획'!E46,0,$C$4-1))) -> 0 | F46: =SUM('3. 손익계산서 월별실적'!E46:(OFFSET('3. 손익계산서 월별실적'!E46,0,$C$4-1))) -> 0 | G46: =+IFERROR(F46/E46,) -> 0 | H46: =OFFSET('3. 손익계산서 월별실적'!E46,0,$C$4-2) -> 0 | I46: =+IFERROR(H46/$H$6,) -> 0 | J46: =OFFSET('(계획)손익계산서 월별계획'!E46,0,$C$4-1) -> 0 | K46: =+IFERROR(J46/$J$6,) -> 0 | L46: =OFFSET('3. 손익계산서 월별실적'!E46,0,$C$4-1) -> 0 | M46: =+IFERROR(L46/$L$6,) -> 0 | N46: =+IFERROR(L46/H46,) -> 0 | O46: =+IFERROR(L46/J46,) -> 0
B47: 충당비용 | C47: ='(계획)손익계산서 월별계획'!C47 -> 0 | D47: =+IFERROR(F47/C47,) -> 0 | E47: =SUM('(계획)손익계산서 월별계획'!E47:(OFFSET('(계획)손익계산서 월별계획'!E47,0,$C$4-1))) -> 0 | F47: =SUM('3. 손익계산서 월별실적'!E47:(OFFSET('3. 손익계산서 월별실적'!E47,0,$C$4-1))) -> 0 | G47: =+IFERROR(F47/E47,) -> 0 | H47: =OFFSET('3. 손익계산서 월별실적'!E47,0,$C$4-2) -> 0 | I47: =+IFERROR(H47/$H$6,) -> 0 | J47: =OFFSET('(계획)손익계산서 월별계획'!E47,0,$C$4-1) -> 0 | K47: =+IFERROR(J47/$J$6,) -> 0 | L47: =OFFSET('3. 손익계산서 월별실적'!E47,0,$C$4-1) -> 0 | M47: =+IFERROR(L47/$L$6,) -> 0 | N47: =+IFERROR(L47/H47,) -> 0 | O47: =+IFERROR(L47/J47,) -> 0
... B50: 투자비지원 | C50: ='(계획)손익계산서 월별계획'!C50 -> 0 | D50: =+IFERROR(F50/C50,) -> 0 | E50: =SUM('(계획)손익계산서 월별계획'!E50:(OFFSET('(계획)손익계산서 월별계획'!E50,0,$C$4-1))) -> 0 | F50: =SUM('3. 손익계산서 월별실적'!E50:(OFFSET('3. 손익계산서 월별실적'!E50,0,$C$4-1))) -> 0 | G50: =+IFERROR(F50/E50,) -> 0 | H50: =OFFSET('3. 손익계산서 월별실적'!E50,0,$C$4-2) -> 0 | I50: =+IFERROR(H50/$H$6,) -> 0 | J50: =OFFSET('(계획)손익계산서 월별계획'!E50,0,$C$4-1) -> 0 | K50: =+IFERROR(J50/$J$6,) -> 0 | L50: =OFFSET('3. 손익계산서 월별실적'!E50,0,$C$4-1) -> 0 | M50: =+IFERROR(L50/$L$6,) -> 0 | N50: =+IFERROR(L50/H50,) -> 0 | O50: =+IFERROR(L50/J50,) -> 0
B53: [연구개발비] | C53: =SUM(C54:C67) -> 0 | D53: =+IFERROR(F53/C53,) -> 0 | E53: =SUM(E54:E67) -> 0 | F53: =SUM(F54:F67) -> 0 | G53: =+IFERROR(F53/E53,) -> 0 | H53: =SUM(H54:H67) -> 0 | I53: =+IFERROR(H53/$H$6,) -> 0 | J53: =SUM(J54:J67) -> 0 | K53: =+IFERROR(J53/$J$6,) -> 0 | L53: =SUM(L54:L67) -> 0 | M53: =+IFERROR(L53/$L$6,) -> 0 | N53: =+IFERROR(L53/H53,) -> 0 | O53: =+IFERROR(L53/J53,) -> 0
B54: 인건비 | C54: ='(계획)손익계산서 월별계획'!C54 -> 0 | D54: =+IFERROR(F54/C54,) -> 0 | E54: =SUM('(계획)손익계산서 월별계획'!E54:(OFFSET('(계획)손익계산서 월별계획'!E54,0,$C$4-1))) -> 0 | F54: =SUM('3. 손익계산서 월별실적'!E54:(OFFSET('3. 손익계산서 월별실적'!E54,0,$C$4-1))) -> 0 | G54: =+IFERROR(F54/E54,) -> 0 | H54: =OFFSET('3. 손익계산서 월별실적'!E54,0,$C$4-2) -> 0 | I54: =+IFERROR(H54/$H$6,) -> 0 | J54: =OFFSET('(계획)손익계산서 월별계획'!E54,0,$C$4-1) -> 0 | K54: =+IFERROR(J54/$J$6,) -> 0 | L54: =OFFSET('3. 손익계산서 월별실적'!E54,0,$C$4-1) -> 0 | M54: =+IFERROR(L54/$L$6,) -> 0 | N54: =+IFERROR(L54/H54,) -> 0 | O54: =+IFERROR(L54/J54,) -> 0
B55: 유지비(금형 등) | C55: ='(계획)손익계산서 월별계획'!C55 -> 0 | D55: =+IFERROR(F55/C55,) -> 0 | E55: =SUM('(계획)손익계산서 월별계획'!E55:(OFFSET('(계획)손익계산서 월별계획'!E55,0,$C$4-1))) -> 0 | F55: =SUM('3. 손익계산서 월별실적'!E55:(OFFSET('3. 손익계산서 월별실적'!E55,0,$C$4-1))) -> 0 | G55: =+IFERROR(F55/E55,) -> 0 | H55: =OFFSET('3. 손익계산서 월별실적'!E55,0,$C$4-2) -> 0 | I55: =+IFERROR(H55/$H$6,) -> 0 | J55: =OFFSET('(계획)손익계산서 월별계획'!E55,0,$C$4-1) -> 0 | K55: =+IFERROR(J55/$J$6,) -> 0 | L55: =OFFSET('3. 손익계산서 월별실적'!E55,0,$C$4-1) -> 0 | M55: =+IFERROR(L55/$L$6,) -> 0 | N55: =+IFERROR(L55/H55,) -> 0 | O55: =+IFERROR(L55/J55,) -> 0
B56: 세금,보험 | C56: ='(계획)손익계산서 월별계획'!C56 -> 0 | D56: =+IFERROR(F56/C56,) -> 0 | E56: =SUM('(계획)손익계산서 월별계획'!E56:(OFFSET('(계획)손익계산서 월별계획'!E56,0,$C$4-1))) -> 0 | F56: =SUM('3. 손익계산서 월별실적'!E56:(OFFSET('3. 손익계산서 월별실적'!E56,0,$C$4-1))) -> 0 | G56: =+IFERROR(F56/E56,) -> 0 | H56: =OFFSET('3. 손익계산서 월별실적'!E56,0,$C$4-2) -> 0 | I56: =+IFERROR(H56/$H$6,) -> 0 | J56: =OFFSET('(계획)손익계산서 월별계획'!E56,0,$C$4-1) -> 0 | K56: =+IFERROR(J56/$J$6,) -> 0 | L56: =OFFSET('3. 손익계산서 월별실적'!E56,0,$C$4-1) -> 0 | M56: =+IFERROR(L56/$L$6,) -> 0 | N56: =+IFERROR(L56/H56,) -> 0 | O56: =+IFERROR(L56/J56,) -> 0
B57: 복리후생비 | C57: ='(계획)손익계산서 월별계획'!C57 -> 0 | D57: =+IFERROR(F57/C57,) -> 0 | E57: =SUM('(계획)손익계산서 월별계획'!E57:(OFFSET('(계획)손익계산서 월별계획'!E57,0,$C$4-1))) -> 0 | F57: =SUM('3. 손익계산서 월별실적'!E57:(OFFSET('3. 손익계산서 월별실적'!E57,0,$C$4-1))) -> 0 | G57: =+IFERROR(F57/E57,) -> 0 | H57: =OFFSET('3. 손익계산서 월별실적'!E57,0,$C$4-2) -> 0 | I57: =+IFERROR(H57/$H$6,) -> 0 | J57: =OFFSET('(계획)손익계산서 월별계획'!E57,0,$C$4-1) -> 0 | K57: =+IFERROR(J57/$J$6,) -> 0 | L57: =OFFSET('3. 손익계산서 월별실적'!E57,0,$C$4-1) -> 0 | M57: =+IFERROR(L57/$L$6,) -> 0 | N57: =+IFERROR(L57/H57,) -> 0 | O57: =+IFERROR(L57/J57,) -> 0
B58: 운반비 | C58: ='(계획)손익계산서 월별계획'!C58 -> 0 | D58: =+IFERROR(F58/C58,) -> 0 | E58: =SUM('(계획)손익계산서 월별계획'!E58:(OFFSET('(계획)손익계산서 월별계획'!E58,0,$C$4-1))) -> 0 | F58: =SUM('3. 손익계산서 월별실적'!E58:(OFFSET('3. 손익계산서 월별실적'!E58,0,$C$4-1))) -> 0 | G58: =+IFERROR(F58/E58,) -> 0 | H58: =OFFSET('3. 손익계산서 월별실적'!E58,0,$C$4-2) -> 0 | I58: =+IFERROR(H58/$H$6,) -> 0 | J58: =OFFSET('(계획)손익계산서 월별계획'!E58,0,$C$4-1) -> 0 | K58: =+IFERROR(J58/$J$6,) -> 0 | L58: =OFFSET('3. 손익계산서 월별실적'!E58,0,$C$4-1) -> 0 | M58: =+IFERROR(L58/$L$6,) -> 0 | N58: =+IFERROR(L58/H58,) -> 0 | O58: =+IFERROR(L58/J58,) -> 0
B59: 포장비 | C59: ='(계획)손익계산서 월별계획'!C59 -> 0 | D59: =+IFERROR(F59/C59,) -> 0 | E59: =SUM('(계획)손익계산서 월별계획'!E59:(OFFSET('(계획)손익계산서 월별계획'!E59,0,$C$4-1))) -> 0 | F59: =SUM('3. 손익계산서 월별실적'!E59:(OFFSET('3. 손익계산서 월별실적'!E59,0,$C$4-1))) -> 0 | G59: =+IFERROR(F59/E59,) -> 0 | H59: =OFFSET('3. 손익계산서 월별실적'!E59,0,$C$4-2) -> 0 | I59: =+IFERROR(H59/$H$6,) -> 0 | J59: =OFFSET('(계획)손익계산서 월별계획'!E59,0,$C$4-1) -> 0 | K59: =+IFERROR(J59/$J$6,) -> 0 | L59: =OFFSET('3. 손익계산서 월별실적'!E59,0,$C$4-1) -> 0 | M59: =+IFERROR(L59/$L$6,) -> 0 | N59: =+IFERROR(L59/H59,) -> 0 | O59: =+IFERROR(L59/J59,) -> 0
B60: 광고선전비 | C60: ='(계획)손익계산서 월별계획'!C60 -> 0 | D60: =+IFERROR(F60/C60,) -> 0 | E60: =SUM('(계획)손익계산서 월별계획'!E60:(OFFSET('(계획)손익계산서 월별계획'!E60,0,$C$4-1))) -> 0 | F60: =SUM('3. 손익계산서 월별실적'!E60:(OFFSET('3. 손익계산서 월별실적'!E60,0,$C$4-1))) -> 0 | G60: =+IFERROR(F60/E60,) -> 0 | H60: =OFFSET('3. 손익계산서 월별실적'!E60,0,$C$4-2) -> 0 | I60: =+IFERROR(H60/$H$6,) -> 0 | J60: =OFFSET('(계획)손익계산서 월별계획'!E60,0,$C$4-1) -> 0 | K60: =+IFERROR(J60/$J$6,) -> 0 | L60: =OFFSET('3. 손익계산서 월별실적'!E60,0,$C$4-1) -> 0 | M60: =+IFERROR(L60/$L$6,) -> 0 | N60: =+IFERROR(L60/H60,) -> 0 | O60: =+IFERROR(L60/J60,) -> 0
B61: 지급수수료 | C61: ='(계획)손익계산서 월별계획'!C61 -> 0 | D61: =+IFERROR(F61/C61,) -> 0 | E61: =SUM('(계획)손익계산서 월별계획'!E61:(OFFSET('(계획)손익계산서 월별계획'!E61,0,$C$4-1))) -> 0 | F61: =SUM('3. 손익계산서 월별실적'!E61:(OFFSET('3. 손익계산서 월별실적'!E61,0,$C$4-1))) -> 0 | G61: =+IFERROR(F61/E61,) -> 0 | H61: =OFFSET('3. 손익계산서 월별실적'!E61,0,$C$4-2) -> 0 | I61: =+IFERROR(H61/$H$6,) -> 0 | J61: =OFFSET('(계획)손익계산서 월별계획'!E61,0,$C$4-1) -> 0 | K61: =+IFERROR(J61/$J$6,) -> 0 | L61: =OFFSET('3. 손익계산서 월별실적'!E61,0,$C$4-1) -> 0 | M61: =+IFERROR(L61/$L$6,) -> 0 | N61: =+IFERROR(L61/H61,) -> 0 | O61: =+IFERROR(L61/J61,) -> 0 | Q61: =+L61-J61 -> 0 | R61: =+L61-H61 -> 0
B62: 여비교통비 | C62: ='(계획)손익계산서 월별계획'!C62 -> 0 | D62: =+IFERROR(F62/C62,) -> 0 | E62: =SUM('(계획)손익계산서 월별계획'!E62:(OFFSET('(계획)손익계산서 월별계획'!E62,0,$C$4-1))) -> 0 | F62: =SUM('3. 손익계산서 월별실적'!E62:(OFFSET('3. 손익계산서 월별실적'!E62,0,$C$4-1))) -> 0 | G62: =+IFERROR(F62/E62,) -> 0 | H62: =OFFSET('3. 손익계산서 월별실적'!E62,0,$C$4-2) -> 0 | I62: =+IFERROR(H62/$H$6,) -> 0 | J62: =OFFSET('(계획)손익계산서 월별계획'!E62,0,$C$4-1) -> 0 | K62: =+IFERROR(J62/$J$6,) -> 0 | L62: =OFFSET('3. 손익계산서 월별실적'!E62,0,$C$4-1) -> 0 | M62: =+IFERROR(L62/$L$6,) -> 0 | N62: =+IFERROR(L62/H62,) -> 0 | O62: =+IFERROR(L62/J62,) -> 0
B63: 감가상각비 | C63: ='(계획)손익계산서 월별계획'!C63 -> 0 | D63: =+IFERROR(F63/C63,) -> 0 | E63: =SUM('(계획)손익계산서 월별계획'!E63:(OFFSET('(계획)손익계산서 월별계획'!E63,0,$C$4-1))) -> 0 | F63: =SUM('3. 손익계산서 월별실적'!E63:(OFFSET('3. 손익계산서 월별실적'!E63,0,$C$4-1))) -> 0 | G63: =+IFERROR(F63/E63,) -> 0 | H63: =OFFSET('3. 손익계산서 월별실적'!E63,0,$C$4-2) -> 0 | I63: =+IFERROR(H63/$H$6,) -> 0 | J63: =OFFSET('(계획)손익계산서 월별계획'!E63,0,$C$4-1) -> 0 | K63: =+IFERROR(J63/$J$6,) -> 0 | L63: =OFFSET('3. 손익계산서 월별실적'!E63,0,$C$4-1) -> 0 | M63: =+IFERROR(L63/$L$6,) -> 0 | N63: =+IFERROR(L63/H63,) -> 0 | O63: =+IFERROR(L63/J63,) -> 0
B64: 개발비 | C64: ='(계획)손익계산서 월별계획'!C64 -> 0 | D64: =+IFERROR(F64/C64,) -> 0 | E64: =SUM('(계획)손익계산서 월별계획'!E64:(OFFSET('(계획)손익계산서 월별계획'!E64,0,$C$4-1))) -> 0 | F64: =SUM('3. 손익계산서 월별실적'!E64:(OFFSET('3. 손익계산서 월별실적'!E64,0,$C$4-1))) -> 0 | G64: =+IFERROR(F64/E64,) -> 0 | H64: =OFFSET('3. 손익계산서 월별실적'!E64,0,$C$4-2) -> 0 | I64: =+IFERROR(H64/$H$6,) -> 0 | J64: =OFFSET('(계획)손익계산서 월별계획'!E64,0,$C$4-1) -> 0 | K64: =+IFERROR(J64/$J$6,) -> 0 | L64: =OFFSET('3. 손익계산서 월별실적'!E64,0,$C$4-1) -> 0 | M64: =+IFERROR(L64/$L$6,) -> 0 | N64: =+IFERROR(L64/H64,) -> 0 | O64: =+IFERROR(L64/J64,) -> 0 | Q64: =+L64-J64 -> 0 | R64: =+L64-H64 -> 0
B65: 충당비용 | C65: ='(계획)손익계산서 월별계획'!C65 -> 0 | D65: =+IFERROR(F65/C65,) -> 0 | E65: =SUM('(계획)손익계산서 월별계획'!E65:(OFFSET('(계획)손익계산서 월별계획'!E65,0,$C$4-1))) -> 0 | F65: =SUM('3. 손익계산서 월별실적'!E65:(OFFSET('3. 손익계산서 월별실적'!E65,0,$C$4-1))) -> 0 | G65: =+IFERROR(F65/E65,) -> 0 | H65: =OFFSET('3. 손익계산서 월별실적'!E65,0,$C$4-2) -> 0 | I65: =+IFERROR(H65/$H$6,) -> 0 | J65: =OFFSET('(계획)손익계산서 월별계획'!E65,0,$C$4-1) -> 0 | K65: =+IFERROR(J65/$J$6,) -> 0 | L65: =OFFSET('3. 손익계산서 월별실적'!E65,0,$C$4-1) -> 0 | M65: =+IFERROR(L65/$L$6,) -> 0 | N65: =+IFERROR(L65/H65,) -> 0 | O65: =+IFERROR(L65/J65,) -> 0
B66: 외주비 | C66: ='(계획)손익계산서 월별계획'!C66 -> 0 | D66: =+IFERROR(F66/C66,) -> 0 | E66: =SUM('(계획)손익계산서 월별계획'!E66:(OFFSET('(계획)손익계산서 월별계획'!E66,0,$C$4-1))) -> 0 | F66: =SUM('3. 손익계산서 월별실적'!E66:(OFFSET('3. 손익계산서 월별실적'!E66,0,$C$4-1))) -> 0 | G66: =+IFERROR(F66/E66,) -> 0 | H66: =OFFSET('3. 손익계산서 월별실적'!E66,0,$C$4-2) -> 0 | I66: =+IFERROR(H66/$H$6,) -> 0 | J66: =OFFSET('(계획)손익계산서 월별계획'!E66,0,$C$4-1) -> 0 | K66: =+IFERROR(J66/$J$6,) -> 0 | L66: =OFFSET('3. 손익계산서 월별실적'!E66,0,$C$4-1) -> 0 | M66: =+IFERROR(L66/$L$6,) -> 0 | N66: =+IFERROR(L66/H66,) -> 0 | O66: =+IFERROR(L66/J66,) -> 0
B67: 기타비용 | C67: ='(계획)손익계산서 월별계획'!C67 -> 0 | D67: =+IFERROR(F67/C67,) -> 0 | E67: =SUM('(계획)손익계산서 월별계획'!E67:(OFFSET('(계획)손익계산서 월별계획'!E67,0,$C$4-1))) -> 0 | F67: =SUM('3. 손익계산서 월별실적'!E67:(OFFSET('3. 손익계산서 월별실적'!E67,0,$C$4-1))) -> 0 | G67: =+IFERROR(F67/E67,) -> 0 | H67: =OFFSET('3. 손익계산서 월별실적'!E67,0,$C$4-2) -> 0 | I67: =+IFERROR(H67/$H$6,) -> 0 | J67: =OFFSET('(계획)손익계산서 월별계획'!E67,0,$C$4-1) -> 0 | K67: =+IFERROR(J67/$J$6,) -> 0 | L67: =OFFSET('3. 손익계산서 월별실적'!E67,0,$C$4-1) -> 0 | M67: =+IFERROR(L67/$L$6,) -> 0 | N67: =+IFERROR(L67/H67,) -> 0 | O67: =+IFERROR(L67/J67,) -> 0 | Q67: =+L64+L61 -> 0 | R67: =+J64+J61 -> 0 | S67: =+Q67-R67 -> 0
B68: Ⅴ.영업이익 | C68: =+C16-C18 -> 1580940.1 | D68: =IF(AND(C68>0,F68>0),F68/C68,"(-)") -> 0.44013411 | E68: =+E16-E18 -> 947948.67 | F68: =+F16-F18 -> 695825.69 | G68: =IF(AND(E68>0,F68>0),F68/E68,"(-)") -> 0.73403309 | H68: =+H16-H18 -> 68249.24 | I68: =+IFERROR(H68/$H$6,) -> 0.0054590745 | J68: =+J16-J18 -> 744176.48 | K68: =+IFERROR(J68/$J$6,) -> 0.05039004 | L68: =+L16-L18 -> 627576.45 | M68: =+IFERROR(L68/$L$6,) -> 0.041413175 | N68: =+IF(AND(H68>0,L68>0),L68/H68,"(-)") -> 9.1953617 | O68: =+IF(AND(J68>0,N68>0),L68/J68,"(-)") -> 0.84331669 | Y68: =+C68*1330/1000000 -> 2102.6504 | Z68: =+E68*1330/1000000 -> 1260.7717 | AA68: =+F68*1330/1000000 -> 925.44817 | AB68: =+H68*1330/1000000 -> 90.771489 | AC68: =+J68*1330/1000000 -> 989.75472 | AD68: =+L68*1330/1000000 -> 834.67668
B69: (이익률) | C69: =+IFERROR(C68/C6,) -> 0.0091076752 | E69: =+IFERROR(E68/E6,) -> 0.032707478 | F69: =+IFERROR(F68/F6,) -> 0.025160018 | H69: =+IFERROR(H68/H6,) -> 0.0054590745 | J69: =+IFERROR(J68/J6,) -> 0.05039004 | L69: =+IFERROR(L68/L6,) -> 0.041413175 | Y69: =+Y16-Y18 -> 2102.6504 | Z69: =+Z16-Z18 -> 1260.7717 | AA69: =+AA16-AA18 -> 925.44817 | AB69: =+AB16-AB18 -> 90.771489 | AC69: =+AC16-AC18 -> 989.75472 | AD69: =+AD16-AD18 -> 834.67668
B70: Ⅵ.영업외수익
B71: Ⅶ. 영업외비용
B72: Ⅷ 법인세
B73: Ⅸ.당기손익
B74: (이익률)
F75: =F68*1350 -> 9.3936468e+08 | J75: =J68*1350 -> 1.0046382e+09
B77: ▶ KSCM-DG (전선) | O77: (단위:$)
B78: 구 분 | C78: 2026년 계 획 | D78: 년계획 진척률 | E78: 누 계 계 획 | F78: 누 계 실 적 | G78: 달성률 | H78: 전 월 실 적 | I78: 매 출 구성비 | J78: 당 월 계 획 | K78: 매 출 구성비 | L78: 당 월 실 적 | M78: 매 출 구성비 | N78: 전 월 대 비 | O78: 계 획 대 비
B79: Ⅰ. 매출액 | C79: =SUM(C80:C81) -> 1.4764519e+08 | D79: =+IFERROR(F79/C79,) -> 0.1558842 | E79: =SUM(E80:E81) -> 23759798 | F79: =SUM(F80:F81) -> 23015553 | G79: =+IFERROR(F79/E79,) -> 0.96867627 | H79: =SUM(H80:H81) -> 10329331 | I79: =+IFERROR(H79/$H$79,) -> 1 | J79: =SUM(J80:J81) -> 11901934 | K79: =+IFERROR(J79/$J$79,) -> 1 | L79: =SUM(L80:L81) -> 12686222 | M79: =+IFERROR(L79/$L$79,) -> 1 | N79: =+IFERROR(L79/H79,) -> 1.2281745 | O79: =+IFERROR(L79/J79,) -> 1.0658958 | Y79: =+C79*1330/1000000 -> 196368.11 | Z79: =+E79*1330/1000000 -> 31600.532 | AA79: =+F79*1330/1000000 -> 30610.685 | AB79: =+H79*1330/1000000 -> 13738.011 | AC79: =+J79*1330/1000000 -> 15829.572 | AD79: =+L79*1330/1000000 -> 16872.675
B80: - 제품 | C80: ='(계획)손익계산서 월별계획'!C80 -> 1.2069318e+08 | D80: =+IFERROR(F80/C80,) -> 0.15420477 | E80: =SUM('(계획)손익계산서 월별계획'!E80:(OFFSET('(계획)손익계산서 월별계획'!E80,0,$C$4-1))) -> 19231097 | F80: =SUM('3. 손익계산서 월별실적'!E80:(OFFSET('3. 손익계산서 월별실적'!E80,0,$C$4-1))) -> 18611465 | G80: =+IFERROR(F80/E80,) -> 0.96777968 | H80: =OFFSET('3. 손익계산서 월별실적'!E80,0,$C$4-2) -> 8873528.4 | I80: =+IFERROR(H80/$H$79,) -> 0.85906126 | J80: =OFFSET('(계획)손익계산서 월별계획'!E80,0,$C$4-1) -> 9631818.5 | K80: =+IFERROR(J80/$J$79,) -> 0.80926501 | L80: =OFFSET('3. 손익계산서 월별실적'!E80,0,$C$4-1) -> 9737936.6 | M80: =OFFSET('3. 손익계산서 월별실적'!F80,0,$C$4-1) -> 0 | N80: =+IFERROR(L80/H80,) -> 1.0974143 | O80: =+IFERROR(L80/J80,) -> 1.0110174
B81: - 상품 | C81: ='(계획)손익계산서 월별계획'!C81 -> 26952009 | D81: =+IFERROR(F81/C81,) -> 0.16340481 | E81: =SUM('(계획)손익계산서 월별계획'!E81:(OFFSET('(계획)손익계산서 월별계획'!E81,0,$C$4-1))) -> 4528701.3 | F81: =SUM('3. 손익계산서 월별실적'!E81:(OFFSET('3. 손익계산서 월별실적'!E81,0,$C$4-1))) -> 4404087.9 | G81: =+IFERROR(F81/E81,) -> 0.97248363 | H81: =OFFSET('3. 손익계산서 월별실적'!E81,0,$C$4-2) -> 1455802.9 | I81: =+IFERROR(H81/$H$79,) -> 0.14093874 | J81: =OFFSET('(계획)손익계산서 월별계획'!E81,0,$C$4-1) -> 2270115.2 | K81: =+IFERROR(J81/$J$79,) -> 0.19073499 | L81: =OFFSET('3. 손익계산서 월별실적'!E81,0,$C$4-1) -> 2948285 | M81: =OFFSET('3. 손익계산서 월별실적'!F81,0,$C$4-1) -> 0 | N81: =+IFERROR(L81/H81,) -> 2.0251951 | O81: =+IFERROR(L81/J81,) -> 1.2987381
B82: DAWS | C82: ='(계획)손익계산서 월별계획'!C82 -> 65701563 | D82: =+IFERROR(F82/C82,) -> 0.18492081 | E82: =SUM('(계획)손익계산서 월별계획'!E82:(OFFSET('(계획)손익계산서 월별계획'!E82,0,$C$4-1))) -> 10638253 | F82: =SUM('3. 손익계산서 월별실적'!E82:(OFFSET('3. 손익계산서 월별실적'!E82,0,$C$4-1))) -> 12149586 | G82: =+IFERROR(F82/E82,) -> 1.1420659 | H82: =OFFSET('3. 손익계산서 월별실적'!E82,0,$C$4-2) -> 4928419.3 | I82: =+IFERROR(H82/$H$79,) -> 0.47712859 | J82: =OFFSET('(계획)손익계산서 월별계획'!E82,0,$C$4-1) -> 5328126.7 | K82: =+IFERROR(J82/$J$79,) -> 0.447669 | L82: =OFFSET('3. 손익계산서 월별실적'!E82,0,$C$4-1) -> 7221166.6 | M82: =OFFSET('3. 손익계산서 월별실적'!F82,0,$C$4-1) -> 0 | N82: =+IFERROR(L82/H82,) -> 1.4652094 | O82: =+IFERROR(L82/J82,) -> 1.3552918
B83: HEDS | C83: ='(계획)손익계산서 월별계획'!C83 -> 13540165 | D83: =+IFERROR(F83/C83,) -> 0.17279054 | E83: =SUM('(계획)손익계산서 월별계획'!E83:(OFFSET('(계획)손익계산서 월별계획'!E83,0,$C$4-1))) -> 3000122.8 | F83: =SUM('3. 손익계산서 월별실적'!E83:(OFFSET('3. 손익계산서 월별실적'!E83,0,$C$4-1))) -> 2339612.5 | G83: =+IFERROR(F83/E83,) -> 0.77983888 | H83: =OFFSET('3. 손익계산서 월별실적'!E83,0,$C$4-2) -> 1037033.9 | I83: =+IFERROR(H83/$H$79,) -> 0.10039701 | J83: =OFFSET('(계획)손익계산서 월별계획'!E83,0,$C$4-1) -> 1502599.6 | K83: =+IFERROR(J83/$J$79,) -> 0.12624836 | L83: =OFFSET('3. 손익계산서 월별실적'!E83,0,$C$4-1) -> 1302578.5 | M83: =OFFSET('3. 손익계산서 월별실적'!F83,0,$C$4-1) -> 0 | N83: =+IFERROR(L83/H83,) -> 1.2560616 | O83: =+IFERROR(L83/J83,) -> 0.86688331
B84: CEWS | C84: ='(계획)손익계산서 월별계획'!C84 -> 19818597 | D84: =+IFERROR(F84/C84,) -> 0.14145682 | E84: =SUM('(계획)손익계산서 월별계획'!E84:(OFFSET('(계획)손익계산서 월별계획'!E84,0,$C$4-1))) -> 3208983.8 | F84: =SUM('3. 손익계산서 월별실적'!E84:(OFFSET('3. 손익계산서 월별실적'!E84,0,$C$4-1))) -> 2803475.8 | G84: =+IFERROR(F84/E84,) -> 0.87363352 | H84: =OFFSET('3. 손익계산서 월별실적'!E84,0,$C$4-2) -> 1124453 | I84: =+IFERROR(H84/$H$79,) -> 0.10886019 | J84: =OFFSET('(계획)손익계산서 월별계획'!E84,0,$C$4-1) -> 1607206.8 | K84: =+IFERROR(J84/$J$79,) -> 0.13503745 | L84: =OFFSET('3. 손익계산서 월별실적'!E84,0,$C$4-1) -> 1679022.8 | M84: =OFFSET('3. 손익계산서 월별실적'!F84,0,$C$4-1) -> 0 | N84: =+IFERROR(L84/H84,) -> 1.4931907 | O84: =+IFERROR(L84/J84,) -> 1.0446837
B85: LEAR | C85: ='(계획)손익계산서 월별계획'!C85 -> 17036352 | D85: =+IFERROR(F85/C85,) -> 0.19199841 | E85: =SUM('(계획)손익계산서 월별계획'!E85:(OFFSET('(계획)손익계산서 월별계획'!E85,0,$C$4-1))) -> 2758488.8 | F85: =SUM('3. 손익계산서 월별실적'!E85:(OFFSET('3. 손익계산서 월별실적'!E85,0,$C$4-1))) -> 3270952.4 | G85: =+IFERROR(F85/E85,) -> 1.185777 | H85: =OFFSET('3. 손익계산서 월별실적'!E85,0,$C$4-2) -> 1914487.4 | I85: =+IFERROR(H85/$H$79,) -> 0.18534476 | J85: =OFFSET('(계획)손익계산서 월별계획'!E85,0,$C$4-1) -> 1381578.1 | K85: =+IFERROR(J85/$J$79,) -> 0.11608014 | L85: =OFFSET('3. 손익계산서 월별실적'!E85,0,$C$4-1) -> 1356465 | M85: =OFFSET('3. 손익계산서 월별실적'!F85,0,$C$4-1) -> 0 | N85: =+IFERROR(L85/H85,) -> 0.70852646 | O85: =+IFERROR(L85/J85,) -> 0.98182287
B86: KAC-OB | C86: ='(계획)손익계산서 월별계획'!C86 -> 11446561 | D86: =+IFERROR(F86/C86,) -> 0.11894493 | E86: =SUM('(계획)손익계산서 월별계획'!E86:(OFFSET('(계획)손익계산서 월별계획'!E86,0,$C$4-1))) -> 1853402 | F86: =SUM('3. 손익계산서 월별실적'!E86:(OFFSET('3. 손익계산서 월별실적'!E86,0,$C$4-1))) -> 1361510.3 | G86: =+IFERROR(F86/E86,) -> 0.73460064 | H86: =OFFSET('3. 손익계산서 월별실적'!E86,0,$C$4-2) -> 835690.01 | I86: =+IFERROR(H86/$H$79,) -> 0.08090456 | J86: =OFFSET('(계획)손익계산서 월별계획'!E86,0,$C$4-1) -> 928269.03 | K86: =+IFERROR(J86/$J$79,) -> 0.077993127 | L86: =OFFSET('3. 손익계산서 월별실적'!E86,0,$C$4-1) -> 525820.3 | M86: =OFFSET('3. 손익계산서 월별실적'!F86,0,$C$4-1) -> 0 | N86: =+IFERROR(L86/H86,) -> 0.62920496 | O86: =+IFERROR(L86/J86,) -> 0.56645249
B87: SUMITOMO | C87: ='(계획)손익계산서 월별계획'!C87 -> 14470563 | D87: =+IFERROR(F87/C87,) -> 0.010006482 | E87: =SUM('(계획)손익계산서 월별계획'!E87:(OFFSET('(계획)손익계산서 월별계획'!E87,0,$C$4-1))) -> 1388725.2 | F87: =SUM('3. 손익계산서 월별실적'!E87:(OFFSET('3. 손익계산서 월별실적'!E87,0,$C$4-1))) -> 144799.42 | G87: =+IFERROR(F87/E87,) -> 0.10426787 | H87: =OFFSET('3. 손익계산서 월별실적'!E87,0,$C$4-2) -> 120930.87 | I87: =+IFERROR(H87/$H$79,) -> 0.011707522 | J87: =OFFSET('(계획)손익계산서 월별계획'!E87,0,$C$4-1) -> 697470.65 | K87: =+IFERROR(J87/$J$79,) -> 0.058601456 | L87: =OFFSET('3. 손익계산서 월별실적'!E87,0,$C$4-1) -> 23868.55 | M87: =OFFSET('3. 손익계산서 월별실적'!F87,0,$C$4-1) -> 0 | N87: =+IFERROR(L87/H87,) -> 0.19737351 | O87: =+IFERROR(L87/J87,) -> 0.034221584
B88: 기타 | C88: ='(계획)손익계산서 월별계획'!C88 -> 5631392.1 | D88: =+IFERROR(F88/C88,) -> 0.16791878 | E88: =SUM('(계획)손익계산서 월별계획'!E88:(OFFSET('(계획)손익계산서 월별계획'!E88,0,$C$4-1))) -> 911822.67 | F88: =SUM('3. 손익계산서 월별실적'!E88:(OFFSET('3. 손익계산서 월별실적'!E88,0,$C$4-1))) -> 945616.52 | G88: =+IFERROR(F88/E88,) -> 1.0370619 | H88: =OFFSET('3. 손익계산서 월별실적'!E88,0,$C$4-2) -> 368316.71 | I88: =+IFERROR(H88/$H$79,) -> 0.035657362 | J88: =OFFSET('(계획)손익계산서 월별계획'!E88,0,$C$4-1) -> 456682.76 | K88: =+IFERROR(J88/$J$79,) -> 0.038370467 | L88: =OFFSET('3. 손익계산서 월별실적'!E88,0,$C$4-1) -> 577299.81 | M88: =OFFSET('3. 손익계산서 월별실적'!F88,0,$C$4-1) -> 0 | N88: =+IFERROR(L88/H88,) -> 1.5674005 | O88: =+IFERROR(L88/J88,) -> 1.2641156
B89: (매출동량) | C89: ='(계획)손익계산서 월별계획'!C89 -> 0 | D89: =+IFERROR(F89/C89,) -> 0 | E89: =SUM('(계획)손익계산서 월별계획'!E89:(OFFSET('(계획)손익계산서 월별계획'!E89,0,$C$4-1))) -> 0 | F89: =SUM('3. 손익계산서 월별실적'!E89:(OFFSET('3. 손익계산서 월별실적'!E89,0,$C$4-1))) -> 1346.4872 | G89: =+IFERROR(F89/E89,) -> 0 | H89: =OFFSET('3. 손익계산서 월별실적'!E89,0,$C$4-2) -> 631.81666 | I89: =+IFERROR(H89/$H$79,) -> 6.1167237e-05 | J89: =OFFSET('(계획)손익계산서 월별계획'!E89,0,$C$4-1) -> 0 | K89: =+IFERROR(J89/$J$79,) -> 0 | L89: =OFFSET('3. 손익계산서 월별실적'!E89,0,$C$4-1) -> 714.67057 | M89: =OFFSET('3. 손익계산서 월별실적'!F89,0,$C$4-1) -> 0 | N89: =+IFERROR(L89/H89,) -> 1.131136 | O89: =+IFERROR(L89/J89,) -> 0
B91: Ⅱ. 매출원가 | C91: =SUM(C92:C95) -> 1.3243892e+08 | D91: =+IFERROR(F91/C91,) -> 0.1534481 | E91: =SUM(E92:E95) -> 21271471 | F91: =SUM(F92:F95) -> 20322500 | G91: =+IFERROR(F91/E91,) -> 0.95538762 | H91: =SUM(H92:H95) -> 9323898.1 | I91: =+IFERROR(H91/$H$79,) -> 0.90266231 | J91: =SUM(J92:J95) -> 10600900 | K91: =+IFERROR(J91/$J$79,) -> 0.89068723 | L91: =SUM(L92:L95) -> 10998602 | M91: =+IFERROR(L91/$L$79,) -> 0.86697224 | N91: =+IFERROR(L91/H91,) -> 1.1796141 | O91: =+IFERROR(L91/J91,) -> 1.0375158 | Y91: =+C91*1330/1000000 -> 176143.76 | Z91: =+E91*1330/1000000 -> 28291.056 | AA91: =+F91*1330/1000000 -> 27028.925 | AB91: =+H91*1330/1000000 -> 12400.784 | AC91: =+J91*1330/1000000 -> 14099.198 | AD91: =+L91*1330/1000000 -> 14628.141
B92: - 제품 | C92: ='(계획)손익계산서 월별계획'!C92 -> 1.0664031e+08 | D92: =+IFERROR(F92/C92,) -> 0.15716581 | E92: =SUM('(계획)손익계산서 월별계획'!E92:(OFFSET('(계획)손익계산서 월별계획'!E92,0,$C$4-1))) -> 16919840 | F92: =SUM('3. 손익계산서 월별실적'!E92:(OFFSET('3. 손익계산서 월별실적'!E92,0,$C$4-1))) -> 16760211 | G92: =+IFERROR(F92/E92,) -> 0.99056556 | H92: =OFFSET('3. 손익계산서 월별실적'!E92,0,$C$4-2) -> 8125261 | I92: =+IFERROR(H92/$H$79,) -> 0.78662023 | J92: =OFFSET('(계획)손익계산서 월별계획'!E92,0,$C$4-1) -> 8420525.9 | K92: =+IFERROR(J92/$J$79,) -> 0.70749225 | L92: =OFFSET('3. 손익계산서 월별실적'!E92,0,$C$4-1) -> 8634949.7 | M92: =+IFERROR(L92/$L$79,) -> 0.68065575 | N92: =+IFERROR(L92/H92,) -> 1.0627289 | O92: =+IFERROR(L92/J92,) -> 1.0254644
B93: - 상품 | C93: ='(계획)손익계산서 월별계획'!C93 -> 25798607 | D93: =+IFERROR(F93/C93,) -> 0.13808069 | E93: =SUM('(계획)손익계산서 월별계획'!E93:(OFFSET('(계획)손익계산서 월별계획'!E93,0,$C$4-1))) -> 4351631.1 | F93: =SUM('3. 손익계산서 월별실적'!E93:(OFFSET('3. 손익계산서 월별실적'!E93,0,$C$4-1))) -> 3562289.4 | G93: =+IFERROR(F93/E93,) -> 0.81861016 | H93: =OFFSET('3. 손익계산서 월별실적'!E93,0,$C$4-2) -> 1198637.1 | I93: =+IFERROR(H93/$H$79,) -> 0.11604208 | J93: =OFFSET('(계획)손익계산서 월별계획'!E93,0,$C$4-1) -> 2180374.5 | K93: =+IFERROR(J93/$J$79,) -> 0.18319498 | L93: =OFFSET('3. 손익계산서 월별실적'!E93,0,$C$4-1) -> 2363652.3 | M93: =+IFERROR(L93/$L$79,) -> 0.18631649 | N93: =+IFERROR(L93/H93,) -> 1.9719498 | O93: =+IFERROR(L93/J93,) -> 1.0840579
B94: - 기타 | C94: ='(계획)손익계산서 월별계획'!C94 -> 0 | D94: =+IFERROR(F94/C94,) -> 0 | E94: =SUM('(계획)손익계산서 월별계획'!E94:(OFFSET('(계획)손익계산서 월별계획'!E94,0,$C$4-1))) -> 0 | F94: =SUM('3. 손익계산서 월별실적'!E94:(OFFSET('3. 손익계산서 월별실적'!E94,0,$C$4-1))) -> 0 | G94: =+IFERROR(F94/E94,) -> 0 | H94: =OFFSET('3. 손익계산서 월별실적'!E94,0,$C$4-2) -> 0 | I94: =+IFERROR(H94/$H$79,) -> 0 | J94: =OFFSET('(계획)손익계산서 월별계획'!E94,0,$C$4-1) -> 0 | K94: =+IFERROR(J94/$J$79,) -> 0 | L94: =OFFSET('3. 손익계산서 월별실적'!E94,0,$C$4-1) -> 0 | M94: =+IFERROR(L94/$L$79,) -> 0 | N94: =+IFERROR(L94/H94,) -> 0 | O94: =+IFERROR(L94/J94,) -> 0
B96: Ⅲ. 매출총이익 | C96: =+C79-C91 -> 15206276 | D96: =IF(AND(C96>0,F96>0),F96/C96,"(-)") -> 0.1771014 | E96: =+E79-E91 -> 2488327.5 | F96: =+F79-F91 -> 2693052.8 | G96: =IF(AND(E96>0,F96>0),F96/E96,"(-)") -> 1.0822743 | H96: =+H79-H91 -> 1005433.2 | I96: =+IFERROR(H96/$H$79,) -> 0.097337688 | J96: =+J79-J91 -> 1301033.3 | K96: =+IFERROR(J96/$J$79,) -> 0.10931277 | L96: =+L79-L91 -> 1687619.6 | M96: =+IFERROR(L96/$L$79,) -> 0.13302776 | N96: =+IF(AND(H96>0,L96>0),L96/H96,"(-)") -> 1.6784999 | O96: =+IF(AND(J96>0,N96>0),L96/J96,"(-)") -> 1.2971379 | Y96: =+C96*1330/1000000 -> 20224.348 | Z96: =+E96*1330/1000000 -> 3309.4756 | AA96: =+F96*1330/1000000 -> 3581.7603 | AB96: =+H96*1330/1000000 -> 1337.2262 | AC96: =+J96*1330/1000000 -> 1730.3743 | AD96: =+L96*1330/1000000 -> 2244.5341
B97: (이익률) | C97: =+IFERROR(C96/C79,) -> 0.10299202 | D97: =+IFERROR(F97/C97,) -> 1.1361087 | E97: =+IFERROR(E96/E79,) -> 0.10472848 | F97: =+IFERROR(F96/F79,) -> 0.11701013 | H97: =+IFERROR(H96/H79,) -> 0.097337688 | J97: =+IFERROR(J96/J79,) -> 0.10931277 | L97: =+IFERROR(L96/L79,) -> 0.13302776
B98: Ⅳ.판매관리비 | C98: =SUM(C99,C115,C133) -> 7018954.5 | D98: =+IFERROR(F98/C98,) -> 0.10255898 | E98: =SUM(E99,E115,E133) -> 1209526.2 | F98: =SUM(F99,F115,F133) -> 719856.82 | G98: =+IFERROR(F98/E98,) -> 0.59515605 | H98: =SUM(H99,H115,H133) -> 342624.59 | I98: =+IFERROR(H98/$H$79,) -> 0.033170065 | J98: =SUM(J99,J115,J133) -> 586668.7 | K98: =+IFERROR(J98/$J$79,) -> 0.049291881 | L98: =SUM(L99,L115,L133) -> 377232.23 | M98: =+IFERROR(L98/$L$79,) -> 0.029735586 | N98: =+IFERROR(L98/H98,) -> 1.1010075 | O98: =+IFERROR(L98/J98,) -> 0.64300726 | Y98: =+C98*1330/1000000 -> 9335.2095 | Z98: =+E98*1330/1000000 -> 1608.6698 | AA98: =+F98*1330/1000000 -> 957.40957 | AB98: =+H98*1330/1000000 -> 455.6907 | AC98: =+J98*1330/1000000 -> 780.26937 | AD98: =+L98*1330/1000000 -> 501.71887
B99: [판매비] | C99: =SUM(C100:C113) -> 0 | D99: =+IFERROR(F99/C99,) -> 0 | E99: =SUM(E100:E113) -> 0 | F99: =SUM(F100:F113) -> 0 | G99: =+IFERROR(F99/E99,) -> 0 | H99: =SUM(H100:H113) -> 0 | I99: =+IFERROR(H99/$H$79,) -> 0 | J99: =SUM(J100:J113) -> 0 | K99: =+IFERROR(J99/$J$79,) -> 0 | L99: =SUM(L100:L113) -> 0 | M99: =+IFERROR(L99/$L$79,) -> 0 | N99: =+IFERROR(L99/H99,) -> 0 | O99: =+IFERROR(L99/J99,) -> 0
B100: 인건비 | C100: ='(계획)손익계산서 월별계획'!C100 -> 0 | D100: =+IFERROR(F100/C100,) -> 0 | E100: =SUM('(계획)손익계산서 월별계획'!E100:(OFFSET('(계획)손익계산서 월별계획'!E100,0,$C$4-1))) -> 0 | F100: =SUM('3. 손익계산서 월별실적'!E100:(OFFSET('3. 손익계산서 월별실적'!E100,0,$C$4-1))) -> 0 | G100: =+IFERROR(F100/E100,) -> 0 | H100: =OFFSET('3. 손익계산서 월별실적'!E100,0,$C$4-2) -> 0 | I100: =+IFERROR(H100/$H$79,) -> 0 | J100: =OFFSET('(계획)손익계산서 월별계획'!E100,0,$C$4-1) -> 0 | K100: =+IFERROR(J100/$J$79,) -> 0 | L100: =OFFSET('3. 손익계산서 월별실적'!E100,0,$C$4-1) -> 0 | M100: =+IFERROR(L100/$L$79,) -> 0 | N100: =+IFERROR(L100/H100,) -> 0 | O100: =+IFERROR(L100/J100,) -> 0
B101: 유지비용 | C101: ='(계획)손익계산서 월별계획'!C101 -> 0 | D101: =+IFERROR(F101/C101,) -> 0 | E101: =SUM('(계획)손익계산서 월별계획'!E101:(OFFSET('(계획)손익계산서 월별계획'!E101,0,$C$4-1))) -> 0 | F101: =SUM('3. 손익계산서 월별실적'!E101:(OFFSET('3. 손익계산서 월별실적'!E101,0,$C$4-1))) -> 0 | G101: =+IFERROR(F101/E101,) -> 0 | H101: =OFFSET('3. 손익계산서 월별실적'!E101,0,$C$4-2) -> 0 | I101: =+IFERROR(H101/$H$79,) -> 0 | J101: =OFFSET('(계획)손익계산서 월별계획'!E101,0,$C$4-1) -> 0 | K101: =+IFERROR(J101/$J$79,) -> 0 | L101: =OFFSET('3. 손익계산서 월별실적'!E101,0,$C$4-1) -> 0 | M101: =+IFERROR(L101/$L$79,) -> 0 | N101: =+IFERROR(L101/H101,) -> 0 | O101: =+IFERROR(L101/J101,) -> 0
B102: 세금,보험 | C102: ='(계획)손익계산서 월별계획'!C102 -> 0 | D102: =+IFERROR(F102/C102,) -> 0 | E102: =SUM('(계획)손익계산서 월별계획'!E102:(OFFSET('(계획)손익계산서 월별계획'!E102,0,$C$4-1))) -> 0 | F102: =SUM('3. 손익계산서 월별실적'!E102:(OFFSET('3. 손익계산서 월별실적'!E102,0,$C$4-1))) -> 0 | G102: =+IFERROR(F102/E102,) -> 0 | H102: =OFFSET('3. 손익계산서 월별실적'!E102,0,$C$4-2) -> 0 | I102: =+IFERROR(H102/$H$79,) -> 0 | J102: =OFFSET('(계획)손익계산서 월별계획'!E102,0,$C$4-1) -> 0 | K102: =+IFERROR(J102/$J$79,) -> 0 | L102: =OFFSET('3. 손익계산서 월별실적'!E102,0,$C$4-1) -> 0 | M102: =+IFERROR(L102/$L$79,) -> 0 | N102: =+IFERROR(L102/H102,) -> 0 | O102: =+IFERROR(L102/J102,) -> 0
B103: 복리후생비 | C103: ='(계획)손익계산서 월별계획'!C103 -> 0 | D103: =+IFERROR(F103/C103,) -> 0 | E103: =SUM('(계획)손익계산서 월별계획'!E103:(OFFSET('(계획)손익계산서 월별계획'!E103,0,$C$4-1))) -> 0 | F103: =SUM('3. 손익계산서 월별실적'!E103:(OFFSET('3. 손익계산서 월별실적'!E103,0,$C$4-1))) -> 0 | G103: =+IFERROR(F103/E103,) -> 0 | H103: =OFFSET('3. 손익계산서 월별실적'!E103,0,$C$4-2) -> 0 | I103: =+IFERROR(H103/$H$79,) -> 0 | J103: =OFFSET('(계획)손익계산서 월별계획'!E103,0,$C$4-1) -> 0 | K103: =+IFERROR(J103/$J$79,) -> 0 | L103: =OFFSET('3. 손익계산서 월별실적'!E103,0,$C$4-1) -> 0 | M103: =+IFERROR(L103/$L$79,) -> 0 | N103: =+IFERROR(L103/H103,) -> 0 | O103: =+IFERROR(L103/J103,) -> 0
B104: 운반비 | C104: ='(계획)손익계산서 월별계획'!C104 -> 0 | D104: =+IFERROR(F104/C104,) -> 0 | E104: =SUM('(계획)손익계산서 월별계획'!E104:(OFFSET('(계획)손익계산서 월별계획'!E104,0,$C$4-1))) -> 0 | F104: =SUM('3. 손익계산서 월별실적'!E104:(OFFSET('3. 손익계산서 월별실적'!E104,0,$C$4-1))) -> 0 | G104: =+IFERROR(F104/E104,) -> 0 | H104: =OFFSET('3. 손익계산서 월별실적'!E104,0,$C$4-2) -> 0 | I104: =+IFERROR(H104/$H$79,) -> 0 | J104: =OFFSET('(계획)손익계산서 월별계획'!E104,0,$C$4-1) -> 0 | K104: =+IFERROR(J104/$J$79,) -> 0 | L104: =OFFSET('3. 손익계산서 월별실적'!E104,0,$C$4-1) -> 0 | M104: =+IFERROR(L104/$L$79,) -> 0 | N104: =+IFERROR(L104/H104,) -> 0 | O104: =+IFERROR(L104/J104,) -> 0
B105: 포장비 | C105: ='(계획)손익계산서 월별계획'!C105 -> 0 | D105: =+IFERROR(F105/C105,) -> 0 | E105: =SUM('(계획)손익계산서 월별계획'!E105:(OFFSET('(계획)손익계산서 월별계획'!E105,0,$C$4-1))) -> 0 | F105: =SUM('3. 손익계산서 월별실적'!E105:(OFFSET('3. 손익계산서 월별실적'!E105,0,$C$4-1))) -> 0 | G105: =+IFERROR(F105/E105,) -> 0 | H105: =OFFSET('3. 손익계산서 월별실적'!E105,0,$C$4-2) -> 0 | I105: =+IFERROR(H105/$H$79,) -> 0 | J105: =OFFSET('(계획)손익계산서 월별계획'!E105,0,$C$4-1) -> 0 | K105: =+IFERROR(J105/$J$79,) -> 0 | L105: =OFFSET('3. 손익계산서 월별실적'!E105,0,$C$4-1) -> 0 | M105: =+IFERROR(L105/$L$79,) -> 0 | N105: =+IFERROR(L105/H105,) -> 0 | O105: =+IFERROR(L105/J105,) -> 0
B106: 광고선전비 | C106: ='(계획)손익계산서 월별계획'!C106 -> 0 | D106: =+IFERROR(F106/C106,) -> 0 | E106: =SUM('(계획)손익계산서 월별계획'!E106:(OFFSET('(계획)손익계산서 월별계획'!E106,0,$C$4-1))) -> 0 | F106: =SUM('3. 손익계산서 월별실적'!E106:(OFFSET('3. 손익계산서 월별실적'!E106,0,$C$4-1))) -> 0 | G106: =+IFERROR(F106/E106,) -> 0 | H106: =OFFSET('3. 손익계산서 월별실적'!E106,0,$C$4-2) -> 0 | I106: =+IFERROR(H106/$H$79,) -> 0 | J106: =OFFSET('(계획)손익계산서 월별계획'!E106,0,$C$4-1) -> 0 | K106: =+IFERROR(J106/$J$79,) -> 0 | L106: =OFFSET('3. 손익계산서 월별실적'!E106,0,$C$4-1) -> 0 | M106: =+IFERROR(L106/$L$79,) -> 0 | N106: =+IFERROR(L106/H106,) -> 0 | O106: =+IFERROR(L106/J106,) -> 0
B107: 지급수수료 | C107: ='(계획)손익계산서 월별계획'!C107 -> 0 | D107: =+IFERROR(F107/C107,) -> 0 | E107: =SUM('(계획)손익계산서 월별계획'!E107:(OFFSET('(계획)손익계산서 월별계획'!E107,0,$C$4-1))) -> 0 | F107: =SUM('3. 손익계산서 월별실적'!E107:(OFFSET('3. 손익계산서 월별실적'!E107,0,$C$4-1))) -> 0 | G107: =+IFERROR(F107/E107,) -> 0 | H107: =OFFSET('3. 손익계산서 월별실적'!E107,0,$C$4-2) -> 0 | I107: =+IFERROR(H107/$H$79,) -> 0 | J107: =OFFSET('(계획)손익계산서 월별계획'!E107,0,$C$4-1) -> 0 | K107: =+IFERROR(J107/$J$79,) -> 0 | L107: =OFFSET('3. 손익계산서 월별실적'!E107,0,$C$4-1) -> 0 | M107: =+IFERROR(L107/$L$79,) -> 0 | N107: =+IFERROR(L107/H107,) -> 0 | O107: =+IFERROR(L107/J107,) -> 0
B108: 여비교통비 | C108: ='(계획)손익계산서 월별계획'!C108 -> 0 | D108: =+IFERROR(F108/C108,) -> 0 | E108: =SUM('(계획)손익계산서 월별계획'!E108:(OFFSET('(계획)손익계산서 월별계획'!E108,0,$C$4-1))) -> 0 | F108: =SUM('3. 손익계산서 월별실적'!E108:(OFFSET('3. 손익계산서 월별실적'!E108,0,$C$4-1))) -> 0 | G108: =+IFERROR(F108/E108,) -> 0 | H108: =OFFSET('3. 손익계산서 월별실적'!E108,0,$C$4-2) -> 0 | I108: =+IFERROR(H108/$H$79,) -> 0 | J108: =OFFSET('(계획)손익계산서 월별계획'!E108,0,$C$4-1) -> 0 | K108: =+IFERROR(J108/$J$79,) -> 0 | L108: =OFFSET('3. 손익계산서 월별실적'!E108,0,$C$4-1) -> 0 | M108: =+IFERROR(L108/$L$79,) -> 0 | N108: =+IFERROR(L108/H108,) -> 0 | O108: =+IFERROR(L108/J108,) -> 0
B109: 감가상각비 | C109: ='(계획)손익계산서 월별계획'!C109 -> 0 | D109: =+IFERROR(F109/C109,) -> 0 | E109: =SUM('(계획)손익계산서 월별계획'!E109:(OFFSET('(계획)손익계산서 월별계획'!E109,0,$C$4-1))) -> 0 | F109: =SUM('3. 손익계산서 월별실적'!E109:(OFFSET('3. 손익계산서 월별실적'!E109,0,$C$4-1))) -> 0 | G109: =+IFERROR(F109/E109,) -> 0 | H109: =OFFSET('3. 손익계산서 월별실적'!E109,0,$C$4-2) -> 0 | I109: =+IFERROR(H109/$H$79,) -> 0 | J109: =OFFSET('(계획)손익계산서 월별계획'!E109,0,$C$4-1) -> 0 | K109: =+IFERROR(J109/$J$79,) -> 0 | L109: =OFFSET('3. 손익계산서 월별실적'!E109,0,$C$4-1) -> 0 | M109: =+IFERROR(L109/$L$79,) -> 0 | N109: =+IFERROR(L109/H109,) -> 0 | O109: =+IFERROR(L109/J109,) -> 0
B110: 개발비 | C110: ='(계획)손익계산서 월별계획'!C110 -> 0 | D110: =+IFERROR(F110/C110,) -> 0 | E110: =SUM('(계획)손익계산서 월별계획'!E110:(OFFSET('(계획)손익계산서 월별계획'!E110,0,$C$4-1))) -> 0 | F110: =SUM('3. 손익계산서 월별실적'!E110:(OFFSET('3. 손익계산서 월별실적'!E110,0,$C$4-1))) -> 0 | G110: =+IFERROR(F110/E110,) -> 0 | H110: =OFFSET('3. 손익계산서 월별실적'!E110,0,$C$4-2) -> 0 | I110: =+IFERROR(H110/$H$79,) -> 0 | J110: =OFFSET('(계획)손익계산서 월별계획'!E110,0,$C$4-1) -> 0 | K110: =+IFERROR(J110/$J$79,) -> 0 | L110: =OFFSET('3. 손익계산서 월별실적'!E110,0,$C$4-1) -> 0 | M110: =+IFERROR(L110/$L$79,) -> 0 | N110: =+IFERROR(L110/H110,) -> 0 | O110: =+IFERROR(L110/J110,) -> 0
B111: 충당비용 | C111: ='(계획)손익계산서 월별계획'!C111 -> 0 | D111: =+IFERROR(F111/C111,) -> 0 | E111: =SUM('(계획)손익계산서 월별계획'!E111:(OFFSET('(계획)손익계산서 월별계획'!E111,0,$C$4-1))) -> 0 | F111: =SUM('3. 손익계산서 월별실적'!E111:(OFFSET('3. 손익계산서 월별실적'!E111,0,$C$4-1))) -> 0 | G111: =+IFERROR(F111/E111,) -> 0 | H111: =OFFSET('3. 손익계산서 월별실적'!E111,0,$C$4-2) -> 0 | I111: =+IFERROR(H111/$H$79,) -> 0 | J111: =OFFSET('(계획)손익계산서 월별계획'!E111,0,$C$4-1) -> 0 | K111: =+IFERROR(J111/$J$79,) -> 0 | L111: =OFFSET('3. 손익계산서 월별실적'!E111,0,$C$4-1) -> 0 | M111: =+IFERROR(L111/$L$79,) -> 0 | N111: =+IFERROR(L111/H111,) -> 0 | O111: =+IFERROR(L111/J111,) -> 0
... B113: 기타비용 | C113: ='(계획)손익계산서 월별계획'!C113 -> 0 | D113: =+IFERROR(F113/C113,) -> 0 | E113: =SUM('(계획)손익계산서 월별계획'!E113:(OFFSET('(계획)손익계산서 월별계획'!E113,0,$C$4-1))) -> 0 | F113: =SUM('3. 손익계산서 월별실적'!E113:(OFFSET('3. 손익계산서 월별실적'!E113,0,$C$4-1))) -> 0 | G113: =+IFERROR(F113/E113,) -> 0 | H113: =OFFSET('3. 손익계산서 월별실적'!E113,0,$C$4-2) -> 0 | I113: =+IFERROR(H113/$H$79,) -> 0 | J113: =OFFSET('(계획)손익계산서 월별계획'!E113,0,$C$4-1) -> 0 | K113: =+IFERROR(J113/$J$79,) -> 0 | L113: =OFFSET('3. 손익계산서 월별실적'!E113,0,$C$4-1) -> 0 | M113: =+IFERROR(L113/$L$79,) -> 0 | N113: =+IFERROR(L113/H113,) -> 0 | O113: =+IFERROR(L113/J113,) -> 0
...

Sheet 2. 손익계산서 (2)
B3: Plofit and Loss statement FY 2026
B4: MONTH | C4: 1 | O4: (단위:$)
B5: 구 분 | C5: 2026년 계 획 | D5: 년계획 진척률 | E5: 누 계 계 획 | F5: 누 계 실 적 | G5: 달성률 | H5: 전 월 실 적 | I5: 매 출 구성비 | J5: 당 월 계 획 | K5: 매 출 구성비 | L5: 당 월 실 적 | M5: 매 출 구성비 | N5: 전 월 대 비 | O5: 계 획 대 비 | Y5: 연계획 | Z5: 누계 계획 | AA5: 누계 실적 | AB5: 전월 실적 | AC5: 당월 계획 | AD5: 당월 실적
B6: Ⅰ. 매출액 | C6: =C7+C9 -> 1.7358328e+08 | D6: =+IFERROR(F6/C6,) -> 0.072022949 | E6: =E7+E9 -> 14214304 | F6: =F7+F9 -> 12501980 | G6: =+IFERROR(F6/E6,) -> 0.87953516 | H6: =H7+H9 -> 9843533.5 | I6: =+IFERROR(H6/$H$6,) -> 1 | J6: =J7+J9 -> 14214304 | K6: =+IFERROR(J6/$J$6,) -> 1 | L6: =L7+L9 -> 12501980 | M6: =+IFERROR(L6/$L$6,) -> 1 | N6: =+IFERROR(L6/H6,) -> 1.2700703 | O6: =+IFERROR(L6/J6,) -> 0.87953516 | Q6: 당월실적 | S6: 당월계획 | U6: 전월실적 | Y6: =+C6*1330/1000000 -> 230865.76 | Z6: =+E6*1330/1000000 -> 18905.024 | AA6: =+F6*1330/1000000 -> 16627.633 | AB6: =+H6*1330/1000000 -> 13091.9 | AC6: =+J6*1330/1000000 -> 18905.024 | AD6: =+L6*1330/1000000 -> 16627.633
B7: - 전선 | C7: ='(계획)손익계산서 월별계획'!C7 -> 1.4764519e+08 | D7: =+IFERROR(F7/C7,) -> 0.069960499 | E7: =SUM('(계획)손익계산서 월별계획'!E7:(OFFSET('(계획)손익계산서 월별계획'!E7,0,$C$4-1))) -> 11857865 | F7: =SUM('3. 손익계산서 월별실적'!E7:(OFFSET('3. 손익계산서 월별실적'!E7,0,$C$4-1))) -> 10329331 | G7: =+IFERROR(F7/E7,) -> 0.87109539 | H7: =OFFSET('3. 손익계산서 월별실적'!E7,0,$C$4-2) -> 7465258.4 | I7: =+IFERROR(H7/$H$6,) -> 0.75839214 | J7: =OFFSET('(계획)손익계산서 월별계획'!E7,0,$C$4-1) -> 11857865 | K7: =+IFERROR(J7/$J$6,) -> 0.83422059 | L7: =OFFSET('3. 손익계산서 월별실적'!E7,0,$C$4-1) -> 10329331 | M7: =+IFERROR(L7/$L$6,) -> 0.82621564 | N7: =+IFERROR(L7/H7,) -> 1.3836536 | O7: =+IFERROR(L7/J7,) -> 0.87109539 | S7: =+Q8-S8 -> 973251.25 | U7: =+Q8-U8 -> 305313.91
B8: └ 매출동량 | C8: ='(계획)손익계산서 월별계획'!C8 -> 0 | D8: =+IFERROR(F8/C8,) -> 0 | E8: =SUM('(계획)손익계산서 월별계획'!E8:(OFFSET('(계획)손익계산서 월별계획'!E8,0,$C$4-1))) -> 0 | F8: =SUM('3. 손익계산서 월별실적'!E8:(OFFSET('3. 손익계산서 월별실적'!E8,0,$C$4-1))) -> 631.81666 | G8: =+IFERROR(F8/E8,) -> 0 | H8: =OFFSET('3. 손익계산서 월별실적'!E8,0,$C$4-2) -> 476.23611 | I8: =+IFERROR(H8/$H$6,) -> 4.8380606e-05 | J8: =OFFSET('(계획)손익계산서 월별계획'!E8,0,$C$4-1) -> 0 | K8: =+IFERROR(J8/$J$6,) -> 0 | L8: =OFFSET('3. 손익계산서 월별실적'!E8,0,$C$4-1) -> 631.81666 | M8: =+IFERROR(L8/$L$6,) -> 5.0537328e-05 | N8: =+IFERROR(L8/H8,) -> 1.3266878 | O8: =+IFERROR(L8/J8,) -> 0 | Q8: =+L8-L13 -> -1198005.3 | R8: =+Q8/L8 -> -1896.1281 | S8: =+J8-J13 -> -2171256.6 | T8: =+S8/J8 -> #DIV/0! | U8: =+H8-H13 -> -1503319.2 | V8: =+U8/H8 -> -3156.6678
B9: - 전장 | C9: ='(계획)손익계산서 월별계획'!C9 -> 25938089 | D9: =+IFERROR(F9/C9,) -> 0.083762862 | E9: =SUM('(계획)손익계산서 월별계획'!E9:(OFFSET('(계획)손익계산서 월별계획'!E9,0,$C$4-1))) -> 2356438.9 | F9: =SUM('3. 손익계산서 월별실적'!E9:(OFFSET('3. 손익계산서 월별실적'!E9,0,$C$4-1))) -> 2172648.5 | G9: =+IFERROR(F9/E9,) -> 0.92200505 | H9: =OFFSET('3. 손익계산서 월별실적'!E9,0,$C$4-2) -> 2378275.1 | I9: =+IFERROR(H9/$H$6,) -> 0.24160786 | J9: =OFFSET('(계획)손익계산서 월별계획'!E9,0,$C$4-1) -> 2356438.9 | K9: =+IFERROR(J9/$J$6,) -> 0.16577941 | L9: =OFFSET('3. 손익계산서 월별실적'!E9,0,$C$4-1) -> 2172648.5 | M9: =+IFERROR(L9/$L$6,) -> 0.17378436 | N9: =+IFERROR(L9/H9,) -> 0.91353963 | O9: =+IFERROR(L9/J9,) -> 0.92200505 | Q9: =+L9-L14 -> 2467338.5 | R9: =+Q9/L9 -> 1.1356363 | S9: =+J9-J14 -> 2075429.7 | T9: =+S9/J9 -> 0.88074836 | U9: =+H9-H14 -> 2540932 | V9: =+U9/H9 -> 1.0683928
B11: Ⅱ. 매출원가 | C11: =SUM(C12:C14) -> 1.6273746e+08 | D11: =+IFERROR(F11/C11,) -> 0.072131606 | E11: =SUM(E12:E15) -> 13207071 | F11: =SUM(F12:F15) -> 11738514 | G11: =+IFERROR(F11/E11,) -> 0.88880529 | H11: =SUM(H12:H15) -> 9644978.3 | I11: =+IFERROR(H11/$H$6,) -> 0.97982887 | J11: =SUM(J12:J15) -> 13207071 | K11: =+IFERROR(J11/$J$6,) -> 0.9291395 | L11: =SUM(L12:L15) -> 11738514 | M11: =+IFERROR(L11/$L$6,) -> 0.93893244 | N11: =+IFERROR(L11/H11,) -> 1.2170597 | O11: =+IFERROR(L11/J11,) -> 0.88880529 | S11: =+Q10-S10 -> 0 | U11: =+Q10-U10 -> 0 | Y11: =+C11*1330/1000000 -> 216440.82 | Z11: =+E11*1330/1000000 -> 17565.404 | AA11: =+F11*1330/1000000 -> 15612.224 | AB11: =+H11*1330/1000000 -> 12827.821 | AC11: =+J11*1330/1000000 -> 17565.404 | AD11: =+L11*1330/1000000 -> 15612.224
B12: - 제품 | C12: ='(계획)손익계산서 월별계획'!C12 -> 1.3515827e+08 | D12: =+IFERROR(F12/C12,) -> 0.080162076 | E12: =SUM('(계획)손익계산서 월별계획'!E12:(OFFSET('(계획)손익계산서 월별계획'!E12,0,$C$4-1))) -> 10754805 | F12: =SUM('3. 손익계산서 월별실적'!E12:(OFFSET('3. 손익계산서 월별실적'!E12,0,$C$4-1))) -> 10834567 | G12: =+IFERROR(F12/E12,) -> 1.0074164 | H12: =OFFSET('3. 손익계산서 월별실적'!E12,0,$C$4-2) -> 8303839.7 | I12: =+IFERROR(H12/$H$6,) -> 0.84358322 | J12: =OFFSET('(계획)손익계산서 월별계획'!E12,0,$C$4-1) -> 10754805 | K12: =+IFERROR(J12/$J$6,) -> 0.75661851 | L12: =OFFSET('3. 손익계산서 월별실적'!E12,0,$C$4-1) -> 10834567 | M12: =+IFERROR(L12/$L$6,) -> 0.86662812 | N12: =+IFERROR(L12/H12,) -> 1.304766 | O12: =+IFERROR(L12/J12,) -> 1.0074164
B13: - 상품 | C13: ='(계획)손익계산서 월별계획'!C13 -> 25798607 | D13: =+IFERROR(F13/C13,) -> 0.046461312 | E13: =SUM('(계획)손익계산서 월별계획'!E13:(OFFSET('(계획)손익계산서 월별계획'!E13,0,$C$4-1))) -> 2171256.6 | F13: =SUM('3. 손익계산서 월별실적'!E13:(OFFSET('3. 손익계산서 월별실적'!E13,0,$C$4-1))) -> 1198637.1 | G13: =+IFERROR(F13/E13,) -> 0.55204767 | H13: =OFFSET('3. 손익계산서 월별실적'!E13,0,$C$4-2) -> 1503795.5 | I13: =+IFERROR(H13/$H$6,) -> 0.15276988 | J13: =OFFSET('(계획)손익계산서 월별계획'!E13,0,$C$4-1) -> 2171256.6 | K13: =+IFERROR(J13/$J$6,) -> 0.15275153 | L13: =OFFSET('3. 손익계산서 월별실적'!E13,0,$C$4-1) -> 1198637.1 | M13: =+IFERROR(L13/$L$6,) -> 0.095875785 | N13: =+IFERROR(L13/H13,) -> 0.79707458 | O13: =+IFERROR(L13/J13,) -> 0.55204767
B14: - 기타 | C14: ='(계획)손익계산서 월별계획'!C14 -> 1780585.4 | D14: =+IFERROR(F14/C14,) -> -0.16550175 | E14: =SUM('(계획)손익계산서 월별계획'!E14:(OFFSET('(계획)손익계산서 월별계획'!E14,0,$C$4-1))) -> 281009.2 | F14: =SUM('3. 손익계산서 월별실적'!E14:(OFFSET('3. 손익계산서 월별실적'!E14,0,$C$4-1))) -> -294690 | G14: =+IFERROR(F14/E14,) -> -1.0486845 | H14: =OFFSET('3. 손익계산서 월별실적'!E14,0,$C$4-2) -> -162656.88 | I14: =+IFERROR(H14/$H$6,) -> -0.016524237 | J14: =OFFSET('(계획)손익계산서 월별계획'!E14,0,$C$4-1) -> 281009.2 | K14: =+IFERROR(J14/$J$6,) -> 0.019769466 | L14: =OFFSET('3. 손익계산서 월별실적'!E14,0,$C$4-1) -> -294690 | M14: =+IFERROR(L14/$L$6,) -> -0.023571467 | N14: =+IFERROR(L14/H14,) -> 1.8117279 | O14: =+IFERROR(L14/J14,) -> -1.0486845
B16: Ⅲ. 매출총이익 | C16: =C6-C11 -> 10845821 | D16: =IF(AND(C16>0,F16>0),F16/C16,"(-)") -> 0.070392586 | E16: =+E6-E11 -> 1007232.7 | F16: =+F6-F11 -> 763465.41 | G16: =IF(AND(E16>0,F16>0),F16/E16,"(-)") -> 0.75798315 | H16: =+H6-H11 -> 198555.2 | I16: =+IFERROR(H16/$H$6,) -> 0.02017113 | J16: =+J6-J11 -> 1007232.7 | K16: =+IFERROR(J16/$J$6,) -> 0.070860503 | L16: =+L6-L11 -> 763465.41 | M16: =+IFERROR(L16/$L$6,) -> 0.06106756 | N16: =+IF(AND(H16>0,L16>0),L16/H16,"(-)") -> 3.8451041 | O16: =+IF(AND(J16>0,N16>0),L16/J16,"(-)") -> 0.75798315 | Y16: =+C16*1330/1000000 -> 14424.942 | Z16: =+E16*1330/1000000 -> 1339.6195 | AA16: =+F16*1330/1000000 -> 1015.409 | AB16: =+H16*1330/1000000 -> 264.07841 | AC16: =+J16*1330/1000000 -> 1339.6195 | AD16: =+L16*1330/1000000 -> 1015.409
B17: (이익률) | C17: =+IFERROR(C16/C6,) -> 0.062481946 | E17: =+IFERROR(E16/E6,) -> 0.070860503 | F17: =+IFERROR(F16/F6,) -> 0.06106756 | G17: =+IFERROR(F17/E17,) -> 0.86179971 | H17: =+IFERROR(H16/H6,) -> 0.02017113 | J17: =+IFERROR(J16/J6,) -> 0.070860503 | L17: =+IFERROR(L16/L6,) -> 0.06106756 | Y17: =+Y6-Y11 -> 14424.942 | Z17: =+Z6-Z11 -> 1339.6195 | AA17: =+AA6-AA11 -> 1015.409 | AB17: =+AB6-AB11 -> 264.07841 | AC17: =+AC6-AC11 -> 1339.6195 | AD17: =+AD6-AD11 -> 1015.409
B18: Ⅳ.판매관리비 | C18: =SUM(C19,C35,C53) -> 9264881.1 | D18: =+IFERROR(F18/C18,) -> 0.075037786 | E18: =+E19+E35+E53 -> 803460.51 | F18: =+F19+F35+F53 -> 695216.17 | G18: =+IFERROR(F18/E18,) -> 0.86527734 | H18: =+H19+H35+H53 -> 804702.95 | I18: =+IFERROR(H18/$H$6,) -> 0.081749399 | J18: =+J19+J35+J53 -> 803460.51 | K18: =+IFERROR(J18/$J$6,) -> 0.056524789 | L18: =+L19+L35+L53 -> 695216.17 | M18: =+IFERROR(L18/$L$6,) -> 0.055608486 | N18: =+IFERROR(L18/H18,) -> 0.86394137 | O18: =+IFERROR(L18/J18,) -> 0.86527734 | Q18: =+L18-J18 -> -108244.34 | R18: =+L18-H18 -> -109486.78 | Y18: =+C18*1330/1000000 -> 12322.292 | Z18: =+E18*1330/1000000 -> 1068.6025 | AA18: =+F18*1330/1000000 -> 924.63751 | AB18: =+H18*1330/1000000 -> 1070.2549 | AC18: =+J18*1330/1000000 -> 1068.6025 | AD18: =+L18*1330/1000000 -> 924.63751
B19: [판매비] | C19: =SUM(C20:C33) -> 0 | D19: =+IFERROR(F19/C19,) -> 0 | E19: =SUM(E20:E34) -> 0 | F19: =SUM(F20:F34) -> 0 | G19: =+IFERROR(F19/E19,) -> 0 | H19: =SUM(H20:H34) -> 0 | I19: =+IFERROR(H19/$H$6,) -> 0 | J19: =SUM(J20:J34) -> 0 | K19: =+IFERROR(J19/$J$6,) -> 0 | L19: =SUM(L20:L34) -> 0 | M19: =+IFERROR(L19/$L$6,) -> 0 | N19: =+IFERROR(L19/H19,) -> 0 | O19: =+IFERROR(L19/J19,) -> 0 | R19: 누계 계획 | S19: 누계 실적
B20: 인건비 | C20: ='(계획)손익계산서 월별계획'!C20 -> 0 | D20: =+IFERROR(F20/C20,) -> 0 | E20: =SUM('(계획)손익계산서 월별계획'!E20:(OFFSET('(계획)손익계산서 월별계획'!E20,0,$C$4-1))) -> 0 | F20: =SUM('3. 손익계산서 월별실적'!E20:(OFFSET('3. 손익계산서 월별실적'!E20,0,$C$4-1))) -> 0 | G20: =+IFERROR(F20/E20,) -> 0 | H20: =OFFSET('3. 손익계산서 월별실적'!E20,0,$C$4-2) -> 0 | I20: =+IFERROR(H20/$H$6,) -> 0 | J20: =OFFSET('(계획)손익계산서 월별계획'!E20,0,$C$4-1) -> 0 | K20: =+IFERROR(J20/$J$6,) -> 0 | L20: =OFFSET('3. 손익계산서 월별실적'!E20,0,$C$4-1) -> 0 | M20: =+IFERROR(L20/$L$6,) -> 0 | N20: =+IFERROR(L20/H20,) -> 0 | O20: =+IFERROR(L20/J20,) -> 0 | Q20: 인건비 | R20: =+E20+E36+E54 -> 347317.4 | S20: =+F20+F36+F54 -> 325645.54 | T20: =+S20/R20 -> 0.93760214
B21: 유지비용 | C21: ='(계획)손익계산서 월별계획'!C21 -> 0 | D21: =+IFERROR(F21/C21,) -> 0 | E21: =SUM('(계획)손익계산서 월별계획'!E21:(OFFSET('(계획)손익계산서 월별계획'!E21,0,$C$4-1))) -> 0 | F21: =SUM('3. 손익계산서 월별실적'!E21:(OFFSET('3. 손익계산서 월별실적'!E21,0,$C$4-1))) -> 0 | G21: =+IFERROR(F21/E21,) -> 0 | H21: =OFFSET('3. 손익계산서 월별실적'!E21,0,$C$4-2) -> 0 | I21: =+IFERROR(H21/$H$6,) -> 0 | J21: =OFFSET('(계획)손익계산서 월별계획'!E21,0,$C$4-1) -> 0 | K21: =+IFERROR(J21/$J$6,) -> 0 | L21: =OFFSET('3. 손익계산서 월별실적'!E21,0,$C$4-1) -> 0 | M21: =+IFERROR(L21/$L$6,) -> 0 | N21: =+IFERROR(L21/H21,) -> 0 | O21: =+IFERROR(L21/J21,) -> 0 | Q21: 지급수수료비 | R21: =SUM(E27,E43,E61) -> 308110.76 | S21: =SUM(F27,F43,F61) -> 225126.16 | T21: =+S21/R21 -> 0.73066634
B22: 세금,보험 | C22: ='(계획)손익계산서 월별계획'!C22 -> 0 | D22: =+IFERROR(F22/C22,) -> 0 | E22: =SUM('(계획)손익계산서 월별계획'!E22:(OFFSET('(계획)손익계산서 월별계획'!E22,0,$C$4-1))) -> 0 | F22: =SUM('3. 손익계산서 월별실적'!E22:(OFFSET('3. 손익계산서 월별실적'!E22,0,$C$4-1))) -> 0 | G22: =+IFERROR(F22/E22,) -> 0 | H22: =OFFSET('3. 손익계산서 월별실적'!E22,0,$C$4-2) -> 0 | I22: =+IFERROR(H22/$H$6,) -> 0 | J22: =OFFSET('(계획)손익계산서 월별계획'!E22,0,$C$4-1) -> 0 | K22: =+IFERROR(J22/$J$6,) -> 0 | L22: =OFFSET('3. 손익계산서 월별실적'!E22,0,$C$4-1) -> 0 | M22: =+IFERROR(L22/$L$6,) -> 0 | N22: =+IFERROR(L22/H22,) -> 0 | O22: =+IFERROR(L22/J22,) -> 0 | Q22: 개발비 | R22: =SUM(E30,E46,E64) -> 0 | S22: =SUM(F30,F46,F64) -> 0 | T22: =+S22/R22 -> #DIV/0!
B23: 복리후생비 | C23: ='(계획)손익계산서 월별계획'!C23 -> 0 | D23: =+IFERROR(F23/C23,) -> 0 | E23: =SUM('(계획)손익계산서 월별계획'!E23:(OFFSET('(계획)손익계산서 월별계획'!E23,0,$C$4-1))) -> 0 | F23: =SUM('3. 손익계산서 월별실적'!E23:(OFFSET('3. 손익계산서 월별실적'!E23,0,$C$4-1))) -> 0 | G23: =+IFERROR(F23/E23,) -> 0 | H23: =OFFSET('3. 손익계산서 월별실적'!E23,0,$C$4-2) -> 0 | I23: =+IFERROR(H23/$H$6,) -> 0 | J23: =OFFSET('(계획)손익계산서 월별계획'!E23,0,$C$4-1) -> 0 | K23: =+IFERROR(J23/$J$6,) -> 0 | L23: =OFFSET('3. 손익계산서 월별실적'!E23,0,$C$4-1) -> 0 | M23: =+IFERROR(L23/$L$6,) -> 0 | N23: =+IFERROR(L23/H23,) -> 0 | O23: =+IFERROR(L23/J23,) -> 0
B24: 운반비 | C24: ='(계획)손익계산서 월별계획'!C24 -> 0 | D24: =+IFERROR(F24/C24,) -> 0 | E24: =SUM('(계획)손익계산서 월별계획'!E24:(OFFSET('(계획)손익계산서 월별계획'!E24,0,$C$4-1))) -> 0 | F24: =SUM('3. 손익계산서 월별실적'!E24:(OFFSET('3. 손익계산서 월별실적'!E24,0,$C$4-1))) -> 0 | G24: =+IFERROR(F24/E24,) -> 0 | H24: =OFFSET('3. 손익계산서 월별실적'!E24,0,$C$4-2) -> 0 | I24: =+IFERROR(H24/$H$6,) -> 0 | J24: =OFFSET('(계획)손익계산서 월별계획'!E24,0,$C$4-1) -> 0 | K24: =+IFERROR(J24/$J$6,) -> 0 | L24: =OFFSET('3. 손익계산서 월별실적'!E24,0,$C$4-1) -> 0 | M24: =+IFERROR(L24/$L$6,) -> 0 | N24: =+IFERROR(L24/H24,) -> 0 | O24: =+IFERROR(L24/J24,) -> 0
B25: 포장비 | C25: ='(계획)손익계산서 월별계획'!C25 -> 0 | D25: =+IFERROR(F25/C25,) -> 0 | E25: =SUM('(계획)손익계산서 월별계획'!E25:(OFFSET('(계획)손익계산서 월별계획'!E25,0,$C$4-1))) -> 0 | F25: =SUM('3. 손익계산서 월별실적'!E25:(OFFSET('3. 손익계산서 월별실적'!E25,0,$C$4-1))) -> 0 | G25: =+IFERROR(F25/E25,) -> 0 | H25: =OFFSET('3. 손익계산서 월별실적'!E25,0,$C$4-2) -> 0 | I25: =+IFERROR(H25/$H$6,) -> 0 | J25: =OFFSET('(계획)손익계산서 월별계획'!E25,0,$C$4-1) -> 0 | K25: =+IFERROR(J25/$J$6,) -> 0 | L25: =OFFSET('3. 손익계산서 월별실적'!E25,0,$C$4-1) -> 0 | M25: =+IFERROR(L25/$L$6,) -> 0 | N25: =+IFERROR(L25/H25,) -> 0 | O25: =+IFERROR(L25/J25,) -> 0
B26: 광고선전비 | C26: ='(계획)손익계산서 월별계획'!C26 -> 0 | D26: =+IFERROR(F26/C26,) -> 0 | E26: =SUM('(계획)손익계산서 월별계획'!E26:(OFFSET('(계획)손익계산서 월별계획'!E26,0,$C$4-1))) -> 0 | F26: =SUM('3. 손익계산서 월별실적'!E26:(OFFSET('3. 손익계산서 월별실적'!E26,0,$C$4-1))) -> 0 | G26: =+IFERROR(F26/E26,) -> 0 | H26: =OFFSET('3. 손익계산서 월별실적'!E26,0,$C$4-2) -> 0 | I26: =+IFERROR(H26/$H$6,) -> 0 | J26: =OFFSET('(계획)손익계산서 월별계획'!E26,0,$C$4-1) -> 0 | K26: =+IFERROR(J26/$J$6,) -> 0 | L26: =OFFSET('3. 손익계산서 월별실적'!E26,0,$C$4-1) -> 0 | M26: =+IFERROR(L26/$L$6,) -> 0 | N26: =+IFERROR(L26/H26,) -> 0 | O26: =+IFERROR(L26/J26,) -> 0
B27: 지급수수료 | C27: ='(계획)손익계산서 월별계획'!C27 -> 0 | D27: =+IFERROR(F27/C27,) -> 0 | E27: =SUM('(계획)손익계산서 월별계획'!E27:(OFFSET('(계획)손익계산서 월별계획'!E27,0,$C$4-1))) -> 0 | F27: =SUM('3. 손익계산서 월별실적'!E27:(OFFSET('3. 손익계산서 월별실적'!E27,0,$C$4-1))) -> 0 | G27: =+IFERROR(F27/E27,) -> 0 | H27: =OFFSET('3. 손익계산서 월별실적'!E27,0,$C$4-2) -> 0 | I27: =+IFERROR(H27/$H$6,) -> 0 | J27: =OFFSET('(계획)손익계산서 월별계획'!E27,0,$C$4-1) -> 0 | K27: =+IFERROR(J27/$J$6,) -> 0 | L27: =OFFSET('3. 손익계산서 월별실적'!E27,0,$C$4-1) -> 0 | M27: =+IFERROR(L27/$L$6,) -> 0 | N27: =+IFERROR(L27/H27,) -> 0 | O27: =+IFERROR(L27/J27,) -> 0
B28: 여비교통비 | C28: ='(계획)손익계산서 월별계획'!C28 -> 0 | D28: =+IFERROR(F28/C28,) -> 0 | E28: =SUM('(계획)손익계산서 월별계획'!E28:(OFFSET('(계획)손익계산서 월별계획'!E28,0,$C$4-1))) -> 0 | F28: =SUM('3. 손익계산서 월별실적'!E28:(OFFSET('3. 손익계산서 월별실적'!E28,0,$C$4-1))) -> 0 | G28: =+IFERROR(F28/E28,) -> 0 | H28: =OFFSET('3. 손익계산서 월별실적'!E28,0,$C$4-2) -> 0 | I28: =+IFERROR(H28/$H$6,) -> 0 | J28: =OFFSET('(계획)손익계산서 월별계획'!E28,0,$C$4-1) -> 0 | K28: =+IFERROR(J28/$J$6,) -> 0 | L28: =OFFSET('3. 손익계산서 월별실적'!E28,0,$C$4-1) -> 0 | M28: =+IFERROR(L28/$L$6,) -> 0 | N28: =+IFERROR(L28/H28,) -> 0 | O28: =+IFERROR(L28/J28,) -> 0
B29: 감가상각비 | C29: ='(계획)손익계산서 월별계획'!C29 -> 0 | D29: =+IFERROR(F29/C29,) -> 0 | E29: =SUM('(계획)손익계산서 월별계획'!E29:(OFFSET('(계획)손익계산서 월별계획'!E29,0,$C$4-1))) -> 0 | F29: =SUM('3. 손익계산서 월별실적'!E29:(OFFSET('3. 손익계산서 월별실적'!E29,0,$C$4-1))) -> 0 | G29: =+IFERROR(F29/E29,) -> 0 | H29: =OFFSET('3. 손익계산서 월별실적'!E29,0,$C$4-2) -> 0 | I29: =+IFERROR(H29/$H$6,) -> 0 | J29: =OFFSET('(계획)손익계산서 월별계획'!E29,0,$C$4-1) -> 0 | K29: =+IFERROR(J29/$J$6,) -> 0 | L29: =OFFSET('3. 손익계산서 월별실적'!E29,0,$C$4-1) -> 0 | M29: =+IFERROR(L29/$L$6,) -> 0 | N29: =+IFERROR(L29/H29,) -> 0 | O29: =+IFERROR(L29/J29,) -> 0
B30: 개발비 | C30: ='(계획)손익계산서 월별계획'!C30 -> 0 | D30: =+IFERROR(F30/C30,) -> 0 | E30: =SUM('(계획)손익계산서 월별계획'!E30:(OFFSET('(계획)손익계산서 월별계획'!E30,0,$C$4-1))) -> 0 | F30: =SUM('3. 손익계산서 월별실적'!E30:(OFFSET('3. 손익계산서 월별실적'!E30,0,$C$4-1))) -> 0 | G30: =+IFERROR(F30/E30,) -> 0 | H30: =OFFSET('3. 손익계산서 월별실적'!E30,0,$C$4-2) -> 0 | I30: =+IFERROR(H30/$H$6,) -> 0 | J30: =OFFSET('(계획)손익계산서 월별계획'!E30,0,$C$4-1) -> 0 | K30: =+IFERROR(J30/$J$6,) -> 0 | L30: =OFFSET('3. 손익계산서 월별실적'!E30,0,$C$4-1) -> 0 | M30: =+IFERROR(L30/$L$6,) -> 0 | N30: =+IFERROR(L30/H30,) -> 0 | O30: =+IFERROR(L30/J30,) -> 0
B31: 충당비용 | C31: ='(계획)손익계산서 월별계획'!C31 -> 0 | D31: =+IFERROR(F31/C31,) -> 0 | E31: =SUM('(계획)손익계산서 월별계획'!E31:(OFFSET('(계획)손익계산서 월별계획'!E31,0,$C$4-1))) -> 0 | F31: =SUM('3. 손익계산서 월별실적'!E31:(OFFSET('3. 손익계산서 월별실적'!E31,0,$C$4-1))) -> 0 | G31: =+IFERROR(F31/E31,) -> 0 | H31: =OFFSET('3. 손익계산서 월별실적'!E31,0,$C$4-2) -> 0 | I31: =+IFERROR(H31/$H$6,) -> 0 | J31: =OFFSET('(계획)손익계산서 월별계획'!E31,0,$C$4-1) -> 0 | K31: =+IFERROR(J31/$J$6,) -> 0 | L31: =OFFSET('3. 손익계산서 월별실적'!E31,0,$C$4-1) -> 0 | M31: =+IFERROR(L31/$L$6,) -> 0 | N31: =+IFERROR(L31/H31,) -> 0 | O31: =+IFERROR(L31/J31,) -> 0
B32: 외주비 | C32: ='(계획)손익계산서 월별계획'!C32 -> 0 | D32: =+IFERROR(F32/C32,) -> 0 | E32: =SUM('(계획)손익계산서 월별계획'!E32:(OFFSET('(계획)손익계산서 월별계획'!E32,0,$C$4-1))) -> 0 | F32: =SUM('3. 손익계산서 월별실적'!E32:(OFFSET('3. 손익계산서 월별실적'!E32,0,$C$4-1))) -> 0 | G32: =+IFERROR(F32/E32,) -> 0 | H32: =OFFSET('3. 손익계산서 월별실적'!E32,0,$C$4-2) -> 0 | I32: =+IFERROR(H32/$H$6,) -> 0 | J32: =OFFSET('(계획)손익계산서 월별계획'!E32,0,$C$4-1) -> 0 | K32: =+IFERROR(J32/$J$6,) -> 0 | L32: =OFFSET('3. 손익계산서 월별실적'!E32,0,$C$4-1) -> 0 | M32: =+IFERROR(L32/$L$6,) -> 0 | N32: =+IFERROR(L32/H32,) -> 0 | O32: =+IFERROR(L32/J32,) -> 0
B33: 기타비용 | C33: ='(계획)손익계산서 월별계획'!C33 -> 0 | D33: =+IFERROR(F33/C33,) -> 0 | E33: =SUM('(계획)손익계산서 월별계획'!E33:(OFFSET('(계획)손익계산서 월별계획'!E33,0,$C$4-1))) -> 0 | F33: =SUM('3. 손익계산서 월별실적'!E33:(OFFSET('3. 손익계산서 월별실적'!E33,0,$C$4-1))) -> 0 | G33: =+IFERROR(F33/E33,) -> 0 | H33: =OFFSET('3. 손익계산서 월별실적'!E33,0,$C$4-2) -> 0 | I33: =+IFERROR(H33/$H$6,) -> 0 | J33: =OFFSET('(계획)손익계산서 월별계획'!E33,0,$C$4-1) -> 0 | K33: =+IFERROR(J33/$J$6,) -> 0 | L33: =OFFSET('3. 손익계산서 월별실적'!E33,0,$C$4-1) -> 0 | M33: =+IFERROR(L33/$L$6,) -> 0 | N33: =+IFERROR(L33/H33,) -> 0 | O33: =+IFERROR(L33/J33,) -> 0
B35: [관리비] | C35: =SUM(C36:C51) -> 9264881.1 | D35: =+IFERROR(F35/C35,) -> 0.075037786 | E35: =SUM(E36:E51) -> 803460.51 | F35: =SUM(F36:F51) -> 695216.17 | G35: =+IFERROR(F35/E35,) -> 0.86527734 | H35: =SUM(H36:H51) -> 804702.95 | I35: =+IFERROR(H35/$H$6,) -> 0.081749399 | J35: =SUM(J36:J51) -> 803460.51 | K35: =+IFERROR(J35/$J$6,) -> 0.056524789 | L35: =SUM(L36:L51) -> 695216.17 | M35: =+IFERROR(L35/$L$6,) -> 0.055608486 | N35: =+IFERROR(L35/H35,) -> 0.86394137 | O35: =+IFERROR(L35/J35,) -> 0.86527734
B36: 인건비 | C36: ='(계획)손익계산서 월별계획'!C36 -> 4201174.1 | D36: =+IFERROR(F36/C36,) -> 0.077512984 | E36: =SUM('(계획)손익계산서 월별계획'!E36:(OFFSET('(계획)손익계산서 월별계획'!E36,0,$C$4-1))) -> 347317.4 | F36: =SUM('3. 손익계산서 월별실적'!E36:(OFFSET('3. 손익계산서 월별실적'!E36,0,$C$4-1))) -> 325645.54 | G36: =+IFERROR(F36/E36,) -> 0.93760214 | H36: =OFFSET('3. 손익계산서 월별실적'!E36,0,$C$4-2) -> 138875.92 | I36: =+IFERROR(H36/$H$6,) -> 0.01410834 | J36: =OFFSET('(계획)손익계산서 월별계획'!E36,0,$C$4-1) -> 347317.4 | K36: =+IFERROR(J36/$J$6,) -> 0.024434359 | L36: =OFFSET('3. 손익계산서 월별실적'!E36,0,$C$4-1) -> 325645.54 | M36: =+IFERROR(L36/$L$6,) -> 0.026047518 | N36: =+IFERROR(L36/H36,) -> 2.3448668 | O36: =+IFERROR(L36/J36,) -> 0.93760214
B37: 유지비용 | C37: ='(계획)손익계산서 월별계획'!C37 -> 132669.7 | D37: =+IFERROR(F37/C37,) -> 0.097643624 | E37: =SUM('(계획)손익계산서 월별계획'!E37:(OFFSET('(계획)손익계산서 월별계획'!E37,0,$C$4-1))) -> 11055.808 | F37: =SUM('3. 손익계산서 월별실적'!E37:(OFFSET('3. 손익계산서 월별실적'!E37,0,$C$4-1))) -> 12954.35 | G37: =+IFERROR(F37/E37,) -> 1.1717235 | H37: =OFFSET('3. 손익계산서 월별실적'!E37,0,$C$4-2) -> 10657.37 | I37: =+IFERROR(H37/$H$6,) -> 0.0010826773 | J37: =OFFSET('(계획)손익계산서 월별계획'!E37,0,$C$4-1) -> 11055.808 | K37: =+IFERROR(J37/$J$6,) -> 0.00077779457 | L37: =OFFSET('3. 손익계산서 월별실적'!E37,0,$C$4-1) -> 12954.35 | M37: =+IFERROR(L37/$L$6,) -> 0.0010361839 | N37: =+IFERROR(L37/H37,) -> 1.2155297 | O37: =+IFERROR(L37/J37,) -> 1.1717235
B38: 세금,보험 | C38: ='(계획)손익계산서 월별계획'!C38 -> 976247.63 | D38: =+IFERROR(F38/C38,) -> 0.029332937 | E38: =SUM('(계획)손익계산서 월별계획'!E38:(OFFSET('(계획)손익계산서 월별계획'!E38,0,$C$4-1))) -> 78054.846 | F38: =SUM('3. 손익계산서 월별실적'!E38:(OFFSET('3. 손익계산서 월별실적'!E38,0,$C$4-1))) -> 28636.21 | G38: =+IFERROR(F38/E38,) -> 0.36687293 | H38: =OFFSET('3. 손익계산서 월별실적'!E38,0,$C$4-2) -> 27643.34 | I38: =+IFERROR(H38/$H$6,) -> 0.0028082741 | J38: =OFFSET('(계획)손익계산서 월별계획'!E38,0,$C$4-1) -> 78054.846 | K38: =+IFERROR(J38/$J$6,) -> 0.0054912888 | L38: =OFFSET('3. 손익계산서 월별실적'!E38,0,$C$4-1) -> 28636.21 | M38: =+IFERROR(L38/$L$6,) -> 0.002290534 | N38: =+IFERROR(L38/H38,) -> 1.0359172 | O38: =+IFERROR(L38/J38,) -> 0.36687293
B39: 복리후생비 | C39: ='(계획)손익계산서 월별계획'!C39 -> 262838.83 | D39: =+IFERROR(F39/C39,) -> 0.0090337109 | E39: =SUM('(계획)손익계산서 월별계획'!E39:(OFFSET('(계획)손익계산서 월별계획'!E39,0,$C$4-1))) -> 21427.876 | F39: =SUM('3. 손익계산서 월별실적'!E39:(OFFSET('3. 손익계산서 월별실적'!E39,0,$C$4-1))) -> 2374.41 | G39: =+IFERROR(F39/E39,) -> 0.1108094 | H39: =OFFSET('3. 손익계산서 월별실적'!E39,0,$C$4-2) -> 3221.41 | I39: =+IFERROR(H39/$H$6,) -> 0.00032726155 | J39: =OFFSET('(계획)손익계산서 월별계획'!E39,0,$C$4-1) -> 21427.876 | K39: =+IFERROR(J39/$J$6,) -> 0.0015074869 | L39: =OFFSET('3. 손익계산서 월별실적'!E39,0,$C$4-1) -> 2374.41 | M39: =+IFERROR(L39/$L$6,) -> 0.00018992272 | N39: =+IFERROR(L39/H39,) -> 0.73707165 | O39: =+IFERROR(L39/J39,) -> 0.1108094
B40: 운반비 | C40: ='(계획)손익계산서 월별계획'!C40 -> 0 | D40: =+IFERROR(F40/C40,) -> 0 | E40: =SUM('(계획)손익계산서 월별계획'!E40:(OFFSET('(계획)손익계산서 월별계획'!E40,0,$C$4-1))) -> 0 | F40: =SUM('3. 손익계산서 월별실적'!E40:(OFFSET('3. 손익계산서 월별실적'!E40,0,$C$4-1))) -> 58276.9 | G40: =+IFERROR(F40/E40,) -> 0 | H40: =OFFSET('3. 손익계산서 월별실적'!E40,0,$C$4-2) -> 25846.87 | I40: =+IFERROR(H40/$H$6,) -> 0.0026257715 | J40: =OFFSET('(계획)손익계산서 월별계획'!E40,0,$C$4-1) -> 0 | K40: =+IFERROR(J40/$J$6,) -> 0 | L40: =OFFSET('3. 손익계산서 월별실적'!E40,0,$C$4-1) -> 58276.9 | M40: =+IFERROR(L40/$L$6,) -> 0.0046614137 | N40: =+IFERROR(L40/H40,) -> 2.2546985 | O40: =+IFERROR(L40/J40,) -> 0
B41: 포장비 | C41: ='(계획)손익계산서 월별계획'!C41 -> 0 | D41: =+IFERROR(F41/C41,) -> 0 | E41: =SUM('(계획)손익계산서 월별계획'!E41:(OFFSET('(계획)손익계산서 월별계획'!E41,0,$C$4-1))) -> 0 | F41: =SUM('3. 손익계산서 월별실적'!E41:(OFFSET('3. 손익계산서 월별실적'!E41,0,$C$4-1))) -> 0 | G41: =+IFERROR(F41/E41,) -> 0 | H41: =OFFSET('3. 손익계산서 월별실적'!E41,0,$C$4-2) -> 0 | I41: =+IFERROR(H41/$H$6,) -> 0 | J41: =OFFSET('(계획)손익계산서 월별계획'!E41,0,$C$4-1) -> 0 | K41: =+IFERROR(J41/$J$6,) -> 0 | L41: =OFFSET('3. 손익계산서 월별실적'!E41,0,$C$4-1) -> 0 | M41: =+IFERROR(L41/$L$6,) -> 0 | N41: =+IFERROR(L41/H41,) -> 0 | O41: =+IFERROR(L41/J41,) -> 0
B42: 광고선전비 | C42: ='(계획)손익계산서 월별계획'!C42 -> 0 | D42: =+IFERROR(F42/C42,) -> 0 | E42: =SUM('(계획)손익계산서 월별계획'!E42:(OFFSET('(계획)손익계산서 월별계획'!E42,0,$C$4-1))) -> 0 | F42: =SUM('3. 손익계산서 월별실적'!E42:(OFFSET('3. 손익계산서 월별실적'!E42,0,$C$4-1))) -> 4997.23 | G42: =+IFERROR(F42/E42,) -> 0 | H42: =OFFSET('3. 손익계산서 월별실적'!E42,0,$C$4-2) -> 7379.83 | I42: =+IFERROR(H42/$H$6,) -> 0.00074971351 | J42: =OFFSET('(계획)손익계산서 월별계획'!E42,0,$C$4-1) -> 0 | K42: =+IFERROR(J42/$J$6,) -> 0 | L42: =OFFSET('3. 손익계산서 월별실적'!E42,0,$C$4-1) -> 4997.23 | M42: =+IFERROR(L42/$L$6,) -> 0.00039971509 | N42: =+IFERROR(L42/H42,) -> 0.67714703 | O42: =+IFERROR(L42/J42,) -> 0
B43: 지급수수료 | C43: ='(계획)손익계산서 월별계획'!C43 -> 3243763.7 | D43: =+IFERROR(F43/C43,) -> 0.069402761 | E43: =SUM('(계획)손익계산서 월별계획'!E43:(OFFSET('(계획)손익계산서 월별계획'!E43,0,$C$4-1))) -> 308110.76 | F43: =SUM('3. 손익계산서 월별실적'!E43:(OFFSET('3. 손익계산서 월별실적'!E43,0,$C$4-1))) -> 225126.16 | G43: =+IFERROR(F43/E43,) -> 0.73066634 | H43: =OFFSET('3. 손익계산서 월별실적'!E43,0,$C$4-2) -> 227988.19 | I43: =+IFERROR(H43/$H$6,) -> 0.023161214 | J43: =OFFSET('(계획)손익계산서 월별계획'!E43,0,$C$4-1) -> 308110.76 | K43: =+IFERROR(J43/$J$6,) -> 0.021676106 | L43: =OFFSET('3. 손익계산서 월별실적'!E43,0,$C$4-1) -> 225126.16 | M43: =+IFERROR(L43/$L$6,) -> 0.018007241 | N43: =+IFERROR(L43/H43,) -> 0.98744659 | O43: =+IFERROR(L43/J43,) -> 0.73066634
B44: 여비교통비 | C44: ='(계획)손익계산서 월별계획'!C44 -> 191128.13 | D44: =+IFERROR(F44/C44,) -> 0.096788317 | E44: =SUM('(계획)손익계산서 월별계획'!E44:(OFFSET('(계획)손익계산서 월별계획'!E44,0,$C$4-1))) -> 15927.344 | F44: =SUM('3. 손익계산서 월별실적'!E44:(OFFSET('3. 손익계산서 월별실적'!E44,0,$C$4-1))) -> 18498.97 | G44: =+IFERROR(F44/E44,) -> 1.1614598 | H44: =OFFSET('3. 손익계산서 월별실적'!E44,0,$C$4-2) -> 15159.41 | I44: =+IFERROR(H44/$H$6,) -> 0.0015400374 | J44: =OFFSET('(계획)손익계산서 월별계획'!E44,0,$C$4-1) -> 15927.344 | K44: =+IFERROR(J44/$J$6,) -> 0.0011205153 | L44: =OFFSET('3. 손익계산서 월별실적'!E44,0,$C$4-1) -> 18498.97 | M44: =+IFERROR(L44/$L$6,) -> 0.0014796832 | N44: =+IFERROR(L44/H44,) -> 1.2202962 | O44: =+IFERROR(L44/J44,) -> 1.1614598
B45: 감가상각비 | C45: ='(계획)손익계산서 월별계획'!C45 -> 0 | D45: =+IFERROR(F45/C45,) -> 0 | E45: =SUM('(계획)손익계산서 월별계획'!E45:(OFFSET('(계획)손익계산서 월별계획'!E45,0,$C$4-1))) -> 0 | F45: =SUM('3. 손익계산서 월별실적'!E45:(OFFSET('3. 손익계산서 월별실적'!E45,0,$C$4-1))) -> 5419.12 | G45: =+IFERROR(F45/E45,) -> 0 | H45: =OFFSET('3. 손익계산서 월별실적'!E45,0,$C$4-2) -> 26706.26 | I45: =+IFERROR(H45/$H$6,) -> 0.0027130766 | J45: =OFFSET('(계획)손익계산서 월별계획'!E45,0,$C$4-1) -> 0 | K45: =+IFERROR(J45/$J$6,) -> 0 | L45: =OFFSET('3. 손익계산서 월별실적'!E45,0,$C$4-1) -> 5419.12 | M45: =+IFERROR(L45/$L$6,) -> 0.00043346094 | N45: =+IFERROR(L45/H45,) -> 0.20291572 | O45: =+IFERROR(L45/J45,) -> 0
B46: 개발비 | C46: ='(계획)손익계산서 월별계획'!C46 -> 0 | D46: =+IFERROR(F46/C46,) -> 0 | E46: =SUM('(계획)손익계산서 월별계획'!E46:(OFFSET('(계획)손익계산서 월별계획'!E46,0,$C$4-1))) -> 0 | F46: =SUM('3. 손익계산서 월별실적'!E46:(OFFSET('3. 손익계산서 월별실적'!E46,0,$C$4-1))) -> 0 | G46: =+IFERROR(F46/E46,) -> 0 | H46: =OFFSET('3. 손익계산서 월별실적'!E46,0,$C$4-2) -> 0 | I46: =+IFERROR(H46/$H$6,) -> 0 | J46: =OFFSET('(계획)손익계산서 월별계획'!E46,0,$C$4-1) -> 0 | K46: =+IFERROR(J46/$J$6,) -> 0 | L46: =OFFSET('3. 손익계산서 월별실적'!E46,0,$C$4-1) -> 0 | M46: =+IFERROR(L46/$L$6,) -> 0 | N46: =+IFERROR(L46/H46,) -> 0 | O46: =+IFERROR(L46/J46,) -> 0
B47: 충당비용 | C47: ='(계획)손익계산서 월별계획'!C47 -> 0 | D47: =+IFERROR(F47/C47,) -> 0 | E47: =SUM('(계획)손익계산서 월별계획'!E47:(OFFSET('(계획)손익계산서 월별계획'!E47,0,$C$4-1))) -> 0 | F47: =SUM('3. 손익계산서 월별실적'!E47:(OFFSET('3. 손익계산서 월별실적'!E47,0,$C$4-1))) -> 0 | G47: =+IFERROR(F47/E47,) -> 0 | H47: =OFFSET('3. 손익계산서 월별실적'!E47,0,$C$4-2) -> 311831.51 | I47: =+IFERROR(H47/$H$6,) -> 0.031678818 | J47: =OFFSET('(계획)손익계산서 월별계획'!E47,0,$C$4-1) -> 0 | K47: =+IFERROR(J47/$J$6,) -> 0 | L47: =OFFSET('3. 손익계산서 월별실적'!E47,0,$C$4-1) -> 0 | M47: =+IFERROR(L47/$L$6,) -> 0 | N47: =+IFERROR(L47/H47,) -> 0 | O47: =+IFERROR(L47/J47,) -> 0
... B50: 투자비지원 | C50: ='(계획)손익계산서 월별계획'!C50 -> 0 | D50: =+IFERROR(F50/C50,) -> 0 | E50: =SUM('(계획)손익계산서 월별계획'!E50:(OFFSET('(계획)손익계산서 월별계획'!E50,0,$C$4-1))) -> 0 | F50: =SUM('3. 손익계산서 월별실적'!E50:(OFFSET('3. 손익계산서 월별실적'!E50,0,$C$4-1))) -> 0 | G50: =+IFERROR(F50/E50,) -> 0 | H50: =OFFSET('3. 손익계산서 월별실적'!E50,0,$C$4-2) -> 0 | I50: =+IFERROR(H50/$H$6,) -> 0 | J50: =OFFSET('(계획)손익계산서 월별계획'!E50,0,$C$4-1) -> 0 | K50: =+IFERROR(J50/$J$6,) -> 0 | L50: =OFFSET('3. 손익계산서 월별실적'!E50,0,$C$4-1) -> 0 | M50: =+IFERROR(L50/$L$6,) -> 0 | N50: =+IFERROR(L50/H50,) -> 0 | O50: =+IFERROR(L50/J50,) -> 0
B53: [연구개발비] | C53: =SUM(C54:C67) -> 0 | D53: =+IFERROR(F53/C53,) -> 0 | E53: =SUM(E54:E67) -> 0 | F53: =SUM(F54:F67) -> 0 | G53: =+IFERROR(F53/E53,) -> 0 | H53: =SUM(H54:H67) -> 0 | I53: =+IFERROR(H53/$H$6,) -> 0 | J53: =SUM(J54:J67) -> 0 | K53: =+IFERROR(J53/$J$6,) -> 0 | L53: =SUM(L54:L67) -> 0 | M53: =+IFERROR(L53/$L$6,) -> 0 | N53: =+IFERROR(L53/H53,) -> 0 | O53: =+IFERROR(L53/J53,) -> 0
B54: 인건비 | C54: ='(계획)손익계산서 월별계획'!C54 -> 0 | D54: =+IFERROR(F54/C54,) -> 0 | E54: =SUM('(계획)손익계산서 월별계획'!E54:(OFFSET('(계획)손익계산서 월별계획'!E54,0,$C$4-1))) -> 0 | F54: =SUM('3. 손익계산서 월별실적'!E54:(OFFSET('3. 손익계산서 월별실적'!E54,0,$C$4-1))) -> 0 | G54: =+IFERROR(F54/E54,) -> 0 | H54: =OFFSET('3. 손익계산서 월별실적'!E54,0,$C$4-2) -> 0 | I54: =+IFERROR(H54/$H$6,) -> 0 | J54: =OFFSET('(계획)손익계산서 월별계획'!E54,0,$C$4-1) -> 0 | K54: =+IFERROR(J54/$J$6,) -> 0 | L54: =OFFSET('3. 손익계산서 월별실적'!E54,0,$C$4-1) -> 0 | M54: =+IFERROR(L54/$L$6,) -> 0 | N54: =+IFERROR(L54/H54,) -> 0 | O54: =+IFERROR(L54/J54,) -> 0
B55: 유지비(금형 등) | C55: ='(계획)손익계산서 월별계획'!C55 -> 0 | D55: =+IFERROR(F55/C55,) -> 0 | E55: =SUM('(계획)손익계산서 월별계획'!E55:(OFFSET('(계획)손익계산서 월별계획'!E55,0,$C$4-1))) -> 0 | F55: =SUM('3. 손익계산서 월별실적'!E55:(OFFSET('3. 손익계산서 월별실적'!E55,0,$C$4-1))) -> 0 | G55: =+IFERROR(F55/E55,) -> 0 | H55: =OFFSET('3. 손익계산서 월별실적'!E55,0,$C$4-2) -> 0 | I55: =+IFERROR(H55/$H$6,) -> 0 | J55: =OFFSET('(계획)손익계산서 월별계획'!E55,0,$C$4-1) -> 0 | K55: =+IFERROR(J55/$J$6,) -> 0 | L55: =OFFSET('3. 손익계산서 월별실적'!E55,0,$C$4-1) -> 0 | M55: =+IFERROR(L55/$L$6,) -> 0 | N55: =+IFERROR(L55/H55,) -> 0 | O55: =+IFERROR(L55/J55,) -> 0
B56: 세금,보험 | C56: ='(계획)손익계산서 월별계획'!C56 -> 0 | D56: =+IFERROR(F56/C56,) -> 0 | E56: =SUM('(계획)손익계산서 월별계획'!E56:(OFFSET('(계획)손익계산서 월별계획'!E56,0,$C$4-1))) -> 0 | F56: =SUM('3. 손익계산서 월별실적'!E56:(OFFSET('3. 손익계산서 월별실적'!E56,0,$C$4-1))) -> 0 | G56: =+IFERROR(F56/E56,) -> 0 | H56: =OFFSET('3. 손익계산서 월별실적'!E56,0,$C$4-2) -> 0 | I56: =+IFERROR(H56/$H$6,) -> 0 | J56: =OFFSET('(계획)손익계산서 월별계획'!E56,0,$C$4-1) -> 0 | K56: =+IFERROR(J56/$J$6,) -> 0 | L56: =OFFSET('3. 손익계산서 월별실적'!E56,0,$C$4-1) -> 0 | M56: =+IFERROR(L56/$L$6,) -> 0 | N56: =+IFERROR(L56/H56,) -> 0 | O56: =+IFERROR(L56/J56,) -> 0
B57: 복리후생비 | C57: ='(계획)손익계산서 월별계획'!C57 -> 0 | D57: =+IFERROR(F57/C57,) -> 0 | E57: =SUM('(계획)손익계산서 월별계획'!E57:(OFFSET('(계획)손익계산서 월별계획'!E57,0,$C$4-1))) -> 0 | F57: =SUM('3. 손익계산서 월별실적'!E57:(OFFSET('3. 손익계산서 월별실적'!E57,0,$C$4-1))) -> 0 | G57: =+IFERROR(F57/E57,) -> 0 | H57: =OFFSET('3. 손익계산서 월별실적'!E57,0,$C$4-2) -> 0 | I57: =+IFERROR(H57/$H$6,) -> 0 | J57: =OFFSET('(계획)손익계산서 월별계획'!E57,0,$C$4-1) -> 0 | K57: =+IFERROR(J57/$J$6,) -> 0 | L57: =OFFSET('3. 손익계산서 월별실적'!E57,0,$C$4-1) -> 0 | M57: =+IFERROR(L57/$L$6,) -> 0 | N57: =+IFERROR(L57/H57,) -> 0 | O57: =+IFERROR(L57/J57,) -> 0
B58: 운반비 | C58: ='(계획)손익계산서 월별계획'!C58 -> 0 | D58: =+IFERROR(F58/C58,) -> 0 | E58: =SUM('(계획)손익계산서 월별계획'!E58:(OFFSET('(계획)손익계산서 월별계획'!E58,0,$C$4-1))) -> 0 | F58: =SUM('3. 손익계산서 월별실적'!E58:(OFFSET('3. 손익계산서 월별실적'!E58,0,$C$4-1))) -> 0 | G58: =+IFERROR(F58/E58,) -> 0 | H58: =OFFSET('3. 손익계산서 월별실적'!E58,0,$C$4-2) -> 0 | I58: =+IFERROR(H58/$H$6,) -> 0 | J58: =OFFSET('(계획)손익계산서 월별계획'!E58,0,$C$4-1) -> 0 | K58: =+IFERROR(J58/$J$6,) -> 0 | L58: =OFFSET('3. 손익계산서 월별실적'!E58,0,$C$4-1) -> 0 | M58: =+IFERROR(L58/$L$6,) -> 0 | N58: =+IFERROR(L58/H58,) -> 0 | O58: =+IFERROR(L58/J58,) -> 0
B59: 포장비 | C59: ='(계획)손익계산서 월별계획'!C59 -> 0 | D59: =+IFERROR(F59/C59,) -> 0 | E59: =SUM('(계획)손익계산서 월별계획'!E59:(OFFSET('(계획)손익계산서 월별계획'!E59,0,$C$4-1))) -> 0 | F59: =SUM('3. 손익계산서 월별실적'!E59:(OFFSET('3. 손익계산서 월별실적'!E59,0,$C$4-1))) -> 0 | G59: =+IFERROR(F59/E59,) -> 0 | H59: =OFFSET('3. 손익계산서 월별실적'!E59,0,$C$4-2) -> 0 | I59: =+IFERROR(H59/$H$6,) -> 0 | J59: =OFFSET('(계획)손익계산서 월별계획'!E59,0,$C$4-1) -> 0 | K59: =+IFERROR(J59/$J$6,) -> 0 | L59: =OFFSET('3. 손익계산서 월별실적'!E59,0,$C$4-1) -> 0 | M59: =+IFERROR(L59/$L$6,) -> 0 | N59: =+IFERROR(L59/H59,) -> 0 | O59: =+IFERROR(L59/J59,) -> 0
B60: 광고선전비 | C60: ='(계획)손익계산서 월별계획'!C60 -> 0 | D60: =+IFERROR(F60/C60,) -> 0 | E60: =SUM('(계획)손익계산서 월별계획'!E60:(OFFSET('(계획)손익계산서 월별계획'!E60,0,$C$4-1))) -> 0 | F60: =SUM('3. 손익계산서 월별실적'!E60:(OFFSET('3. 손익계산서 월별실적'!E60,0,$C$4-1))) -> 0 | G60: =+IFERROR(F60/E60,) -> 0 | H60: =OFFSET('3. 손익계산서 월별실적'!E60,0,$C$4-2) -> 0 | I60: =+IFERROR(H60/$H$6,) -> 0 | J60: =OFFSET('(계획)손익계산서 월별계획'!E60,0,$C$4-1) -> 0 | K60: =+IFERROR(J60/$J$6,) -> 0 | L60: =OFFSET('3. 손익계산서 월별실적'!E60,0,$C$4-1) -> 0 | M60: =+IFERROR(L60/$L$6,) -> 0 | N60: =+IFERROR(L60/H60,) -> 0 | O60: =+IFERROR(L60/J60,) -> 0
B61: 지급수수료 | C61: ='(계획)손익계산서 월별계획'!C61 -> 0 | D61: =+IFERROR(F61/C61,) -> 0 | E61: =SUM('(계획)손익계산서 월별계획'!E61:(OFFSET('(계획)손익계산서 월별계획'!E61,0,$C$4-1))) -> 0 | F61: =SUM('3. 손익계산서 월별실적'!E61:(OFFSET('3. 손익계산서 월별실적'!E61,0,$C$4-1))) -> 0 | G61: =+IFERROR(F61/E61,) -> 0 | H61: =OFFSET('3. 손익계산서 월별실적'!E61,0,$C$4-2) -> 0 | I61: =+IFERROR(H61/$H$6,) -> 0 | J61: =OFFSET('(계획)손익계산서 월별계획'!E61,0,$C$4-1) -> 0 | K61: =+IFERROR(J61/$J$6,) -> 0 | L61: =OFFSET('3. 손익계산서 월별실적'!E61,0,$C$4-1) -> 0 | M61: =+IFERROR(L61/$L$6,) -> 0 | N61: =+IFERROR(L61/H61,) -> 0 | O61: =+IFERROR(L61/J61,) -> 0 | Q61: =+L61-J61 -> 0 | R61: =+L61-H61 -> 0
B62: 여비교통비 | C62: ='(계획)손익계산서 월별계획'!C62 -> 0 | D62: =+IFERROR(F62/C62,) -> 0 | E62: =SUM('(계획)손익계산서 월별계획'!E62:(OFFSET('(계획)손익계산서 월별계획'!E62,0,$C$4-1))) -> 0 | F62: =SUM('3. 손익계산서 월별실적'!E62:(OFFSET('3. 손익계산서 월별실적'!E62,0,$C$4-1))) -> 0 | G62: =+IFERROR(F62/E62,) -> 0 | H62: =OFFSET('3. 손익계산서 월별실적'!E62,0,$C$4-2) -> 0 | I62: =+IFERROR(H62/$H$6,) -> 0 | J62: =OFFSET('(계획)손익계산서 월별계획'!E62,0,$C$4-1) -> 0 | K62: =+IFERROR(J62/$J$6,) -> 0 | L62: =OFFSET('3. 손익계산서 월별실적'!E62,0,$C$4-1) -> 0 | M62: =+IFERROR(L62/$L$6,) -> 0 | N62: =+IFERROR(L62/H62,) -> 0 | O62: =+IFERROR(L62/J62,) -> 0
B63: 감가상각비 | C63: ='(계획)손익계산서 월별계획'!C63 -> 0 | D63: =+IFERROR(F63/C63,) -> 0 | E63: =SUM('(계획)손익계산서 월별계획'!E63:(OFFSET('(계획)손익계산서 월별계획'!E63,0,$C$4-1))) -> 0 | F63: =SUM('3. 손익계산서 월별실적'!E63:(OFFSET('3. 손익계산서 월별실적'!E63,0,$C$4-1))) -> 0 | G63: =+IFERROR(F63/E63,) -> 0 | H63: =OFFSET('3. 손익계산서 월별실적'!E63,0,$C$4-2) -> 0 | I63: =+IFERROR(H63/$H$6,) -> 0 | J63: =OFFSET('(계획)손익계산서 월별계획'!E63,0,$C$4-1) -> 0 | K63: =+IFERROR(J63/$J$6,) -> 0 | L63: =OFFSET('3. 손익계산서 월별실적'!E63,0,$C$4-1) -> 0 | M63: =+IFERROR(L63/$L$6,) -> 0 | N63: =+IFERROR(L63/H63,) -> 0 | O63: =+IFERROR(L63/J63,) -> 0
B64: 개발비 | C64: ='(계획)손익계산서 월별계획'!C64 -> 0 | D64: =+IFERROR(F64/C64,) -> 0 | E64: =SUM('(계획)손익계산서 월별계획'!E64:(OFFSET('(계획)손익계산서 월별계획'!E64,0,$C$4-1))) -> 0 | F64: =SUM('3. 손익계산서 월별실적'!E64:(OFFSET('3. 손익계산서 월별실적'!E64,0,$C$4-1))) -> 0 | G64: =+IFERROR(F64/E64,) -> 0 | H64: =OFFSET('3. 손익계산서 월별실적'!E64,0,$C$4-2) -> 0 | I64: =+IFERROR(H64/$H$6,) -> 0 | J64: =OFFSET('(계획)손익계산서 월별계획'!E64,0,$C$4-1) -> 0 | K64: =+IFERROR(J64/$J$6,) -> 0 | L64: =OFFSET('3. 손익계산서 월별실적'!E64,0,$C$4-1) -> 0 | M64: =+IFERROR(L64/$L$6,) -> 0 | N64: =+IFERROR(L64/H64,) -> 0 | O64: =+IFERROR(L64/J64,) -> 0 | Q64: =+L64-J64 -> 0 | R64: =+L64-H64 -> 0
B65: 충당비용 | C65: ='(계획)손익계산서 월별계획'!C65 -> 0 | D65: =+IFERROR(F65/C65,) -> 0 | E65: =SUM('(계획)손익계산서 월별계획'!E65:(OFFSET('(계획)손익계산서 월별계획'!E65,0,$C$4-1))) -> 0 | F65: =SUM('3. 손익계산서 월별실적'!E65:(OFFSET('3. 손익계산서 월별실적'!E65,0,$C$4-1))) -> 0 | G65: =+IFERROR(F65/E65,) -> 0 | H65: =OFFSET('3. 손익계산서 월별실적'!E65,0,$C$4-2) -> 0 | I65: =+IFERROR(H65/$H$6,) -> 0 | J65: =OFFSET('(계획)손익계산서 월별계획'!E65,0,$C$4-1) -> 0 | K65: =+IFERROR(J65/$J$6,) -> 0 | L65: =OFFSET('3. 손익계산서 월별실적'!E65,0,$C$4-1) -> 0 | M65: =+IFERROR(L65/$L$6,) -> 0 | N65: =+IFERROR(L65/H65,) -> 0 | O65: =+IFERROR(L65/J65,) -> 0
B66: 외주비 | C66: ='(계획)손익계산서 월별계획'!C66 -> 0 | D66: =+IFERROR(F66/C66,) -> 0 | E66: =SUM('(계획)손익계산서 월별계획'!E66:(OFFSET('(계획)손익계산서 월별계획'!E66,0,$C$4-1))) -> 0 | F66: =SUM('3. 손익계산서 월별실적'!E66:(OFFSET('3. 손익계산서 월별실적'!E66,0,$C$4-1))) -> 0 | G66: =+IFERROR(F66/E66,) -> 0 | H66: =OFFSET('3. 손익계산서 월별실적'!E66,0,$C$4-2) -> 0 | I66: =+IFERROR(H66/$H$6,) -> 0 | J66: =OFFSET('(계획)손익계산서 월별계획'!E66,0,$C$4-1) -> 0 | K66: =+IFERROR(J66/$J$6,) -> 0 | L66: =OFFSET('3. 손익계산서 월별실적'!E66,0,$C$4-1) -> 0 | M66: =+IFERROR(L66/$L$6,) -> 0 | N66: =+IFERROR(L66/H66,) -> 0 | O66: =+IFERROR(L66/J66,) -> 0
B67: 기타비용 | C67: ='(계획)손익계산서 월별계획'!C67 -> 0 | D67: =+IFERROR(F67/C67,) -> 0 | E67: =SUM('(계획)손익계산서 월별계획'!E67:(OFFSET('(계획)손익계산서 월별계획'!E67,0,$C$4-1))) -> 0 | F67: =SUM('3. 손익계산서 월별실적'!E67:(OFFSET('3. 손익계산서 월별실적'!E67,0,$C$4-1))) -> 0 | G67: =+IFERROR(F67/E67,) -> 0 | H67: =OFFSET('3. 손익계산서 월별실적'!E67,0,$C$4-2) -> 0 | I67: =+IFERROR(H67/$H$6,) -> 0 | J67: =OFFSET('(계획)손익계산서 월별계획'!E67,0,$C$4-1) -> 0 | K67: =+IFERROR(J67/$J$6,) -> 0 | L67: =OFFSET('3. 손익계산서 월별실적'!E67,0,$C$4-1) -> 0 | M67: =+IFERROR(L67/$L$6,) -> 0 | N67: =+IFERROR(L67/H67,) -> 0 | O67: =+IFERROR(L67/J67,) -> 0 | Q67: =+L64+L61 -> 0 | R67: =+J64+J61 -> 0 | S67: =+Q67-R67 -> 0
B68: Ⅴ.영업이익 | C68: =+C16-C18 -> 1580940.1 | D68: =IF(AND(C68>0,F68>0),F68/C68,"(-)") -> 0.043170034 | E68: =+E16-E18 -> 203772.19 | F68: =+F16-F18 -> 68249.24 | G68: =IF(AND(E68>0,F68>0),F68/E68,"(-)") -> 0.33492911 | H68: =+H16-H18 -> -606147.75 | I68: =+IFERROR(H68/$H$6,) -> -0.061578269 | J68: =+J16-J18 -> 203772.19 | K68: =+IFERROR(J68/$J$6,) -> 0.014335714 | L68: =+L16-L18 -> 68249.24 | M68: =+IFERROR(L68/$L$6,) -> 0.0054590745 | N68: =+IF(AND(H68>0,L68>0),L68/H68,"(-)") -> (-) | O68: =+IF(AND(J68>0,N68>0),L68/J68,"(-)") -> 0.33492911 | Y68: =+C68*1330/1000000 -> 2102.6504 | Z68: =+E68*1330/1000000 -> 271.01702 | AA68: =+F68*1330/1000000 -> 90.771489 | AB68: =+H68*1330/1000000 -> -806.17651 | AC68: =+J68*1330/1000000 -> 271.01702 | AD68: =+L68*1330/1000000 -> 90.771489
B69: (이익률) | C69: =+IFERROR(C68/C6,) -> 0.0091076752 | E69: =+IFERROR(E68/E6,) -> 0.014335714 | F69: =+IFERROR(F68/F6,) -> 0.0054590745 | H69: =+IFERROR(H68/H6,) -> -0.061578269 | J69: =+IFERROR(J68/J6,) -> 0.014335714 | L69: =+IFERROR(L68/L6,) -> 0.0054590745 | Y69: =+Y16-Y18 -> 2102.6504 | Z69: =+Z16-Z18 -> 271.01702 | AA69: =+AA16-AA18 -> 90.771489 | AB69: =+AB16-AB18 -> -806.17651 | AC69: =+AC16-AC18 -> 271.01702 | AD69: =+AD16-AD18 -> 90.771489
B70: Ⅵ.영업외수익
B71: Ⅶ. 영업외비용
B72: Ⅷ 법인세
B73: Ⅸ.당기손익
B74: (이익률)
F75: =F68*1330 -> 90771489 | J75: =J68*1330 -> 2.7101702e+08
B77: ▶ KSCM-DG (전선) | O77: (단위:$)
B78: 구 분 | C78: 2026년 계 획 | D78: 년계획 진척률 | E78: 누 계 계 획 | F78: 누 계 실 적 | G78: 달성률 | H78: 전 월 실 적 | I78: 매 출 구성비 | J78: 당 월 계 획 | K78: 매 출 구성비 | L78: 당 월 실 적 | M78: 매 출 구성비 | N78: 전 월 대 비 | O78: 계 획 대 비
B79: Ⅰ. 매출액 | C79: =SUM(C80:C81) -> 1.4764519e+08 | D79: =+IFERROR(F79/C79,) -> 0.069960499 | E79: =SUM(E80:E81) -> 11857865 | F79: =SUM(F80:F81) -> 10329331 | G79: =+IFERROR(F79/E79,) -> 0.87109539 | H79: =SUM(H80:H81) -> 7465258.4 | I79: =+IFERROR(H79/$H$79,) -> 1 | J79: =SUM(J80:J81) -> 11857865 | K79: =+IFERROR(J79/$J$79,) -> 1 | L79: =SUM(L80:L81) -> 10329331 | M79: =+IFERROR(L79/$L$79,) -> 1 | N79: =+IFERROR(L79/H79,) -> 1.3836536 | O79: =+IFERROR(L79/J79,) -> 0.87109539 | Y79: =+C79*1330/1000000 -> 196368.11 | Z79: =+E79*1330/1000000 -> 15770.96 | AA79: =+F79*1330/1000000 -> 13738.011 | AB79: =+H79*1330/1000000 -> 9928.7936 | AC79: =+J79*1330/1000000 -> 15770.96 | AD79: =+L79*1330/1000000 -> 13738.011
B80: - 제품 | C80: ='(계획)손익계산서 월별계획'!C80 -> 1.2069318e+08 | D80: =+IFERROR(F80/C80,) -> 0.073521372 | E80: =SUM('(계획)손익계산서 월별계획'!E80:(OFFSET('(계획)손익계산서 월별계획'!E80,0,$C$4-1))) -> 9599278.6 | F80: =SUM('3. 손익계산서 월별실적'!E80:(OFFSET('3. 손익계산서 월별실적'!E80,0,$C$4-1))) -> 8873528.4 | G80: =+IFERROR(F80/E80,) -> 0.92439534 | H80: =OFFSET('3. 손익계산서 월별실적'!E80,0,$C$4-2) -> 5716753 | I80: =+IFERROR(H80/$H$79,) -> 0.765781 | J80: =OFFSET('(계획)손익계산서 월별계획'!E80,0,$C$4-1) -> 9599278.6 | K80: =+IFERROR(J80/$J$79,) -> 0.80952843 | L80: =OFFSET('3. 손익계산서 월별실적'!E80,0,$C$4-1) -> 8873528.4 | M80: =OFFSET('3. 손익계산서 월별실적'!F80,0,$C$4-1) -> 9737936.6 | N80: =+IFERROR(L80/H80,) -> 1.5521973 | O80: =+IFERROR(L80/J80,) -> 0.92439534
B81: - 상품 | C81: ='(계획)손익계산서 월별계획'!C81 -> 26952009 | D81: =+IFERROR(F81/C81,) -> 0.054014634 | E81: =SUM('(계획)손익계산서 월별계획'!E81:(OFFSET('(계획)손익계산서 월별계획'!E81,0,$C$4-1))) -> 2258586.1 | F81: =SUM('3. 손익계산서 월별실적'!E81:(OFFSET('3. 손익계산서 월별실적'!E81,0,$C$4-1))) -> 1455802.9 | G81: =+IFERROR(F81/E81,) -> 0.64456383 | H81: =OFFSET('3. 손익계산서 월별실적'!E81,0,$C$4-2) -> 1748505.4 | I81: =+IFERROR(H81/$H$79,) -> 0.234219 | J81: =OFFSET('(계획)손익계산서 월별계획'!E81,0,$C$4-1) -> 2258586.1 | K81: =+IFERROR(J81/$J$79,) -> 0.19047157 | L81: =OFFSET('3. 손익계산서 월별실적'!E81,0,$C$4-1) -> 1455802.9 | M81: =OFFSET('3. 손익계산서 월별실적'!F81,0,$C$4-1) -> 2948285 | N81: =+IFERROR(L81/H81,) -> 0.83259848 | O81: =+IFERROR(L81/J81,) -> 0.64456383
B82: DAWS | C82: ='(계획)손익계산서 월별계획'!C82 -> 65701563 | D82: =+IFERROR(F82/C82,) -> 0.075012209 | E82: =SUM('(계획)손익계산서 월별계획'!E82:(OFFSET('(계획)손익계산서 월별계획'!E82,0,$C$4-1))) -> 5310126.3 | F82: =SUM('3. 손익계산서 월별실적'!E82:(OFFSET('3. 손익계산서 월별실적'!E82,0,$C$4-1))) -> 4928419.3 | G82: =+IFERROR(F82/E82,) -> 0.92811716 | H82: =OFFSET('3. 손익계산서 월별실적'!E82,0,$C$4-2) -> 3666210.8 | I82: =+IFERROR(H82/$H$79,) -> 0.491103 | J82: =OFFSET('(계획)손익계산서 월별계획'!E82,0,$C$4-1) -> 5310126.3 | K82: =+IFERROR(J82/$J$79,) -> 0.44781472 | L82: =OFFSET('3. 손익계산서 월별실적'!E82,0,$C$4-1) -> 4928419.3 | M82: =OFFSET('3. 손익계산서 월별실적'!F82,0,$C$4-1) -> 7221166.6 | N82: =+IFERROR(L82/H82,) -> 1.3442815 | O82: =+IFERROR(L82/J82,) -> 0.92811716
B83: HEDS | C83: ='(계획)손익계산서 월별계획'!C83 -> 13540165 | D83: =+IFERROR(F83/C83,) -> 0.076589459 | E83: =SUM('(계획)손익계산서 월별계획'!E83:(OFFSET('(계획)손익계산서 월별계획'!E83,0,$C$4-1))) -> 1497523.2 | F83: =SUM('3. 손익계산서 월별실적'!E83:(OFFSET('3. 손익계산서 월별실적'!E83,0,$C$4-1))) -> 1037033.9 | G83: =+IFERROR(F83/E83,) -> 0.69249939 | H83: =OFFSET('3. 손익계산서 월별실적'!E83,0,$C$4-2) -> 613806.52 | I83: =+IFERROR(H83/$H$79,) -> 0.082221738 | J83: =OFFSET('(계획)손익계산서 월별계획'!E83,0,$C$4-1) -> 1497523.2 | K83: =+IFERROR(J83/$J$79,) -> 0.12628945 | L83: =OFFSET('3. 손익계산서 월별실적'!E83,0,$C$4-1) -> 1037033.9 | M83: =OFFSET('3. 손익계산서 월별실적'!F83,0,$C$4-1) -> 1302578.5 | N83: =+IFERROR(L83/H83,) -> 1.6895127 | O83: =+IFERROR(L83/J83,) -> 0.69249939
B84: CEWS | C84: ='(계획)손익계산서 월별계획'!C84 -> 19818597 | D84: =+IFERROR(F84/C84,) -> 0.056737266 | E84: =SUM('(계획)손익계산서 월별계획'!E84:(OFFSET('(계획)손익계산서 월별계획'!E84,0,$C$4-1))) -> 1601777 | F84: =SUM('3. 손익계산서 월별실적'!E84:(OFFSET('3. 손익계산서 월별실적'!E84,0,$C$4-1))) -> 1124453 | G84: =+IFERROR(F84/E84,) -> 0.70200346 | H84: =OFFSET('3. 손익계산서 월별실적'!E84,0,$C$4-2) -> 1325035.8 | I84: =+IFERROR(H84/$H$79,) -> 0.17749363 | J84: =OFFSET('(계획)손익계산서 월별계획'!E84,0,$C$4-1) -> 1601777 | K84: =+IFERROR(J84/$J$79,) -> 0.13508141 | L84: =OFFSET('3. 손익계산서 월별실적'!E84,0,$C$4-1) -> 1124453 | M84: =OFFSET('3. 손익계산서 월별실적'!F84,0,$C$4-1) -> 1679022.8 | N84: =+IFERROR(L84/H84,) -> 0.84862086 | O84: =+IFERROR(L84/J84,) -> 0.70200346
B85: LEAR | C85: ='(계획)손익계산서 월별계획'!C85 -> 17036352 | D85: =+IFERROR(F85/C85,) -> 0.11237661 | E85: =SUM('(계획)손익계산서 월별계획'!E85:(OFFSET('(계획)손익계산서 월별계획'!E85,0,$C$4-1))) -> 1376910.6 | F85: =SUM('3. 손익계산서 월별실적'!E85:(OFFSET('3. 손익계산서 월별실적'!E85,0,$C$4-1))) -> 1914487.4 | G85: =+IFERROR(F85/E85,) -> 1.3904224 | H85: =OFFSET('3. 손익계산서 월별실적'!E85,0,$C$4-2) -> 839223.27 | I85: =+IFERROR(H85/$H$79,) -> 0.11241718 | J85: =OFFSET('(계획)손익계산서 월별계획'!E85,0,$C$4-1) -> 1376910.6 | K85: =+IFERROR(J85/$J$79,) -> 0.11611792 | L85: =OFFSET('3. 손익계산서 월별실적'!E85,0,$C$4-1) -> 1914487.4 | M85: =OFFSET('3. 손익계산서 월별실적'!F85,0,$C$4-1) -> 1356465 | N85: =+IFERROR(L85/H85,) -> 2.2812611 | O85: =+IFERROR(L85/J85,) -> 1.3904224
B86: KAC-OB | C86: ='(계획)손익계산서 월별계획'!C86 -> 11446561 | D86: =+IFERROR(F86/C86,) -> 0.073007957 | E86: =SUM('(계획)손익계산서 월별계획'!E86:(OFFSET('(계획)손익계산서 월별계획'!E86,0,$C$4-1))) -> 925132.99 | F86: =SUM('3. 손익계산서 월별실적'!E86:(OFFSET('3. 손익계산서 월별실적'!E86,0,$C$4-1))) -> 835690.01 | G86: =+IFERROR(F86/E86,) -> 0.90331879 | H86: =OFFSET('3. 손익계산서 월별실적'!E86,0,$C$4-2) -> 608551.76 | I86: =+IFERROR(H86/$H$79,) -> 0.081517843 | J86: =OFFSET('(계획)손익계산서 월별계획'!E86,0,$C$4-1) -> 925132.99 | K86: =+IFERROR(J86/$J$79,) -> 0.078018514 | L86: =OFFSET('3. 손익계산서 월별실적'!E86,0,$C$4-1) -> 835690.01 | M86: =OFFSET('3. 손익계산서 월별실적'!F86,0,$C$4-1) -> 525820.3 | N86: =+IFERROR(L86/H86,) -> 1.3732439 | O86: =+IFERROR(L86/J86,) -> 0.90331879
B87: SUMITOMO | C87: ='(계획)손익계산서 월별계획'!C87 -> 14470563 | D87: =+IFERROR(F87/C87,) -> 0.0083570261 | E87: =SUM('(계획)손익계산서 월별계획'!E87:(OFFSET('(계획)손익계산서 월별계획'!E87,0,$C$4-1))) -> 691254.59 | F87: =SUM('3. 손익계산서 월별실적'!E87:(OFFSET('3. 손익계산서 월별실적'!E87,0,$C$4-1))) -> 120930.87 | G87: =+IFERROR(F87/E87,) -> 0.17494404 | H87: =OFFSET('3. 손익계산서 월별실적'!E87,0,$C$4-2) -> 0 | I87: =+IFERROR(H87/$H$79,) -> 0 | J87: =OFFSET('(계획)손익계산서 월별계획'!E87,0,$C$4-1) -> 691254.59 | K87: =+IFERROR(J87/$J$79,) -> 0.058295031 | L87: =OFFSET('3. 손익계산서 월별실적'!E87,0,$C$4-1) -> 120930.87 | M87: =OFFSET('3. 손익계산서 월별실적'!F87,0,$C$4-1) -> 23868.55 | N87: =+IFERROR(L87/H87,) -> 0 | O87: =+IFERROR(L87/J87,) -> 0.17494404
B88: 기타 | C88: ='(계획)손익계산서 월별계획'!C88 -> 5631392.1 | D88: =+IFERROR(F88/C88,) -> 0.065404202 | E88: =SUM('(계획)손익계산서 월별계획'!E88:(OFFSET('(계획)손익계산서 월별계획'!E88,0,$C$4-1))) -> 455139.91 | F88: =SUM('3. 손익계산서 월별실적'!E88:(OFFSET('3. 손익계산서 월별실적'!E88,0,$C$4-1))) -> 368316.71 | G88: =+IFERROR(F88/E88,) -> 0.80923843 | H88: =OFFSET('3. 손익계산서 월별실적'!E88,0,$C$4-2) -> 412430.22 | I88: =+IFERROR(H88/$H$79,) -> 0.05524661 | J88: =OFFSET('(계획)손익계산서 월별계획'!E88,0,$C$4-1) -> 455139.91 | K88: =+IFERROR(J88/$J$79,) -> 0.038382957 | L88: =OFFSET('3. 손익계산서 월별실적'!E88,0,$C$4-1) -> 368316.71 | M88: =OFFSET('3. 손익계산서 월별실적'!F88,0,$C$4-1) -> 577299.81 | N88: =+IFERROR(L88/H88,) -> 0.89304006 | O88: =+IFERROR(L88/J88,) -> 0.80923843
B89: (매출동량) | C89: ='(계획)손익계산서 월별계획'!C89 -> 0 | D89: =+IFERROR(F89/C89,) -> 0 | E89: =SUM('(계획)손익계산서 월별계획'!E89:(OFFSET('(계획)손익계산서 월별계획'!E89,0,$C$4-1))) -> 0 | F89: =SUM('3. 손익계산서 월별실적'!E89:(OFFSET('3. 손익계산서 월별실적'!E89,0,$C$4-1))) -> 631.81666 | G89: =+IFERROR(F89/E89,) -> 0 | H89: =OFFSET('3. 손익계산서 월별실적'!E89,0,$C$4-2) -> 476.23611 | I89: =+IFERROR(H89/$H$79,) -> 6.3793655e-05 | J89: =OFFSET('(계획)손익계산서 월별계획'!E89,0,$C$4-1) -> 0 | K89: =+IFERROR(J89/$J$79,) -> 0 | L89: =OFFSET('3. 손익계산서 월별실적'!E89,0,$C$4-1) -> 631.81666 | M89: =OFFSET('3. 손익계산서 월별실적'!F89,0,$C$4-1) -> 714.67057 | N89: =+IFERROR(L89/H89,) -> 1.3266878 | O89: =+IFERROR(L89/J89,) -> 0
B91: Ⅱ. 매출원가 | C91: =SUM(C92:C95) -> 1.3243892e+08 | D91: =+IFERROR(F91/C91,) -> 0.070401498 | E91: =SUM(E92:E95) -> 10670570 | F91: =SUM(F92:F95) -> 9323898.1 | G91: =+IFERROR(F91/E91,) -> 0.87379565 | H91: =SUM(H92:H95) -> 6804593.9 | I91: =+IFERROR(H91/$H$79,) -> 0.91150146 | J91: =SUM(J92:J95) -> 10670570 | K91: =+IFERROR(J91/$J$79,) -> 0.89987285 | L91: =SUM(L92:L95) -> 9323898.1 | M91: =+IFERROR(L91/$L$79,) -> 0.90266231 | N91: =+IFERROR(L91/H91,) -> 1.3702358 | O91: =+IFERROR(L91/J91,) -> 0.87379565 | Y91: =+C91*1330/1000000 -> 176143.76 | Z91: =+E91*1330/1000000 -> 14191.859 | AA91: =+F91*1330/1000000 -> 12400.784 | AB91: =+H91*1330/1000000 -> 9050.1099 | AC91: =+J91*1330/1000000 -> 14191.859 | AD91: =+L91*1330/1000000 -> 12400.784
B92: - 제품 | C92: ='(계획)손익계산서 월별계획'!C92 -> 1.0664031e+08 | D92: =+IFERROR(F92/C92,) -> 0.076193149 | E92: =SUM('(계획)손익계산서 월별계획'!E92:(OFFSET('(계획)손익계산서 월별계획'!E92,0,$C$4-1))) -> 8499313.9 | F92: =SUM('3. 손익계산서 월별실적'!E92:(OFFSET('3. 손익계산서 월별실적'!E92,0,$C$4-1))) -> 8125261 | G92: =+IFERROR(F92/E92,) -> 0.95599022 | H92: =OFFSET('3. 손익계산서 월별실적'!E92,0,$C$4-2) -> 5300798.5 | I92: =+IFERROR(H92/$H$79,) -> 0.71006229 | J92: =OFFSET('(계획)손익계산서 월별계획'!E92,0,$C$4-1) -> 8499313.9 | K92: =+IFERROR(J92/$J$79,) -> 0.71676597 | L92: =OFFSET('3. 손익계산서 월별실적'!E92,0,$C$4-1) -> 8125261 | M92: =+IFERROR(L92/$L$79,) -> 0.78662023 | N92: =+IFERROR(L92/H92,) -> 1.5328372 | O92: =+IFERROR(L92/J92,) -> 0.95599022
B93: - 상품 | C93: ='(계획)손익계산서 월별계획'!C93 -> 25798607 | D93: =+IFERROR(F93/C93,) -> 0.046461312 | E93: =SUM('(계획)손익계산서 월별계획'!E93:(OFFSET('(계획)손익계산서 월별계획'!E93,0,$C$4-1))) -> 2171256.6 | F93: =SUM('3. 손익계산서 월별실적'!E93:(OFFSET('3. 손익계산서 월별실적'!E93,0,$C$4-1))) -> 1198637.1 | G93: =+IFERROR(F93/E93,) -> 0.55204767 | H93: =OFFSET('3. 손익계산서 월별실적'!E93,0,$C$4-2) -> 1503795.5 | I93: =+IFERROR(H93/$H$79,) -> 0.20143917 | J93: =OFFSET('(계획)손익계산서 월별계획'!E93,0,$C$4-1) -> 2171256.6 | K93: =+IFERROR(J93/$J$79,) -> 0.18310688 | L93: =OFFSET('3. 손익계산서 월별실적'!E93,0,$C$4-1) -> 1198637.1 | M93: =+IFERROR(L93/$L$79,) -> 0.11604208 | N93: =+IFERROR(L93/H93,) -> 0.79707458 | O93: =+IFERROR(L93/J93,) -> 0.55204767
B94: - 기타 | C94: ='(계획)손익계산서 월별계획'!C94 -> 0 | D94: =+IFERROR(F94/C94,) -> 0 | E94: =SUM('(계획)손익계산서 월별계획'!E94:(OFFSET('(계획)손익계산서 월별계획'!E94,0,$C$4-1))) -> 0 | F94: =SUM('3. 손익계산서 월별실적'!E94:(OFFSET('3. 손익계산서 월별실적'!E94,0,$C$4-1))) -> 0 | G94: =+IFERROR(F94/E94,) -> 0 | H94: =OFFSET('3. 손익계산서 월별실적'!E94,0,$C$4-2) -> 0 | I94: =+IFERROR(H94/$H$79,) -> 0 | J94: =OFFSET('(계획)손익계산서 월별계획'!E94,0,$C$4-1) -> 0 | K94: =+IFERROR(J94/$J$79,) -> 0 | L94: =OFFSET('3. 손익계산서 월별실적'!E94,0,$C$4-1) -> 0 | M94: =+IFERROR(L94/$L$79,) -> 0 | N94: =+IFERROR(L94/H94,) -> 0 | O94: =+IFERROR(L94/J94,) -> 0
B96: Ⅲ. 매출총이익 | C96: =+C79-C91 -> 15206276 | D96: =IF(AND(C96>0,F96>0),F96/C96,"(-)") -> 0.066119621 | E96: =+E79-E91 -> 1187294.2 | F96: =+F79-F91 -> 1005433.2 | G96: =IF(AND(E96>0,F96>0),F96/E96,"(-)") -> 0.84682735 | H96: =+H79-H91 -> 660664.46 | I96: =+IFERROR(H96/$H$79,) -> 0.088498539 | J96: =+J79-J91 -> 1187294.2 | K96: =+IFERROR(J96/$J$79,) -> 0.10012715 | L96: =+L79-L91 -> 1005433.2 | M96: =+IFERROR(L96/$L$79,) -> 0.097337688 | N96: =+IF(AND(H96>0,L96>0),L96/H96,"(-)") -> 1.5218515 | O96: =+IF(AND(J96>0,N96>0),L96/J96,"(-)") -> 0.84682735 | Y96: =+C96*1330/1000000 -> 20224.348 | Z96: =+E96*1330/1000000 -> 1579.1013 | AA96: =+F96*1330/1000000 -> 1337.2262 | AB96: =+H96*1330/1000000 -> 878.68373 | AC96: =+J96*1330/1000000 -> 1579.1013 | AD96: =+L96*1330/1000000 -> 1337.2262
B97: (이익률) | C97: =+IFERROR(C96/C79,) -> 0.10299202 | D97: =+IFERROR(F97/C97,) -> 0.94509934 | E97: =+IFERROR(E96/E79,) -> 0.10012715 | F97: =+IFERROR(F96/F79,) -> 0.097337688 | H97: =+IFERROR(H96/H79,) -> 0.088498539 | J97: =+IFERROR(J96/J79,) -> 0.10012715 | L97: =+IFERROR(L96/L79,) -> 0.097337688
B98: Ⅳ.판매관리비 | C98: =SUM(C99,C115,C133) -> 7018954.5 | D98: =+IFERROR(F98/C98,) -> 0.048814191 | E98: =SUM(E99,E115,E133) -> 622857.48 | F98: =SUM(F99,F115,F133) -> 342624.59 | G98: =+IFERROR(F98/E98,) -> 0.55008505 | H98: =SUM(H99,H115,H133) -> 482172.68 | I98: =+IFERROR(H98/$H$79,) -> 0.06458888 | J98: =SUM(J99,J115,J133) -> 622857.48 | K98: =+IFERROR(J98/$J$79,) -> 0.052526951 | L98: =SUM(L99,L115,L133) -> 342624.59 | M98: =+IFERROR(L98/$L$79,) -> 0.033170065 | N98: =+IFERROR(L98/H98,) -> 0.71058483 | O98: =+IFERROR(L98/J98,) -> 0.55008505 | Y98: =+C98*1330/1000000 -> 9335.2095 | Z98: =+E98*1330/1000000 -> 828.40045 | AA98: =+F98*1330/1000000 -> 455.6907 | AB98: =+H98*1330/1000000 -> 641.28966 | AC98: =+J98*1330/1000000 -> 828.40045 | AD98: =+L98*1330/1000000 -> 455.6907
B99: [판매비] | C99: =SUM(C100:C113) -> 0 | D99: =+IFERROR(F99/C99,) -> 0 | E99: =SUM(E100:E113) -> 0 | F99: =SUM(F100:F113) -> 0 | G99: =+IFERROR(F99/E99,) -> 0 | H99: =SUM(H100:H113) -> 0 | I99: =+IFERROR(H99/$H$79,) -> 0 | J99: =SUM(J100:J113) -> 0 | K99: =+IFERROR(J99/$J$79,) -> 0 | L99: =SUM(L100:L113) -> 0 | M99: =+IFERROR(L99/$L$79,) -> 0 | N99: =+IFERROR(L99/H99,) -> 0 | O99: =+IFERROR(L99/J99,) -> 0
B100: 인건비 | C100: ='(계획)손익계산서 월별계획'!C100 -> 0 | D100: =+IFERROR(F100/C100,) -> 0 | E100: =SUM('(계획)손익계산서 월별계획'!E100:(OFFSET('(계획)손익계산서 월별계획'!E100,0,$C$4-1))) -> 0 | F100: =SUM('3. 손익계산서 월별실적'!E100:(OFFSET('3. 손익계산서 월별실적'!E100,0,$C$4-1))) -> 0 | G100: =+IFERROR(F100/E100,) -> 0 | H100: =OFFSET('3. 손익계산서 월별실적'!E100,0,$C$4-2) -> 0 | I100: =+IFERROR(H100/$H$79,) -> 0 | J100: =OFFSET('(계획)손익계산서 월별계획'!E100,0,$C$4-1) -> 0 | K100: =+IFERROR(J100/$J$79,) -> 0 | L100: =OFFSET('3. 손익계산서 월별실적'!E100,0,$C$4-1) -> 0 | M100: =+IFERROR(L100/$L$79,) -> 0 | N100: =+IFERROR(L100/H100,) -> 0 | O100: =+IFERROR(L100/J100,) -> 0
B101: 유지비용 | C101: ='(계획)손익계산서 월별계획'!C101 -> 0 | D101: =+IFERROR(F101/C101,) -> 0 | E101: =SUM('(계획)손익계산서 월별계획'!E101:(OFFSET('(계획)손익계산서 월별계획'!E101,0,$C$4-1))) -> 0 | F101: =SUM('3. 손익계산서 월별실적'!E101:(OFFSET('3. 손익계산서 월별실적'!E101,0,$C$4-1))) -> 0 | G101: =+IFERROR(F101/E101,) -> 0 | H101: =OFFSET('3. 손익계산서 월별실적'!E101,0,$C$4-2) -> 0 | I101: =+IFERROR(H101/$H$79,) -> 0 | J101: =OFFSET('(계획)손익계산서 월별계획'!E101,0,$C$4-1) -> 0 | K101: =+IFERROR(J101/$J$79,) -> 0 | L101: =OFFSET('3. 손익계산서 월별실적'!E101,0,$C$4-1) -> 0 | M101: =+IFERROR(L101/$L$79,) -> 0 | N101: =+IFERROR(L101/H101,) -> 0 | O101: =+IFERROR(L101/J101,) -> 0
B102: 세금,보험 | C102: ='(계획)손익계산서 월별계획'!C102 -> 0 | D102: =+IFERROR(F102/C102,) -> 0 | E102: =SUM('(계획)손익계산서 월별계획'!E102:(OFFSET('(계획)손익계산서 월별계획'!E102,0,$C$4-1))) -> 0 | F102: =SUM('3. 손익계산서 월별실적'!E102:(OFFSET('3. 손익계산서 월별실적'!E102,0,$C$4-1))) -> 0 | G102: =+IFERROR(F102/E102,) -> 0 | H102: =OFFSET('3. 손익계산서 월별실적'!E102,0,$C$4-2) -> 0 | I102: =+IFERROR(H102/$H$79,) -> 0 | J102: =OFFSET('(계획)손익계산서 월별계획'!E102,0,$C$4-1) -> 0 | K102: =+IFERROR(J102/$J$79,) -> 0 | L102: =OFFSET('3. 손익계산서 월별실적'!E102,0,$C$4-1) -> 0 | M102: =+IFERROR(L102/$L$79,) -> 0 | N102: =+IFERROR(L102/H102,) -> 0 | O102: =+IFERROR(L102/J102,) -> 0
B103: 복리후생비 | C103: ='(계획)손익계산서 월별계획'!C103 -> 0 | D103: =+IFERROR(F103/C103,) -> 0 | E103: =SUM('(계획)손익계산서 월별계획'!E103:(OFFSET('(계획)손익계산서 월별계획'!E103,0,$C$4-1))) -> 0 | F103: =SUM('3. 손익계산서 월별실적'!E103:(OFFSET('3. 손익계산서 월별실적'!E103,0,$C$4-1))) -> 0 | G103: =+IFERROR(F103/E103,) -> 0 | H103: =OFFSET('3. 손익계산서 월별실적'!E103,0,$C$4-2) -> 0 | I103: =+IFERROR(H103/$H$79,) -> 0 | J103: =OFFSET('(계획)손익계산서 월별계획'!E103,0,$C$4-1) -> 0 | K103: =+IFERROR(J103/$J$79,) -> 0 | L103: =OFFSET('3. 손익계산서 월별실적'!E103,0,$C$4-1) -> 0 | M103: =+IFERROR(L103/$L$79,) -> 0 | N103: =+IFERROR(L103/H103,) -> 0 | O103: =+IFERROR(L103/J103,) -> 0
B104: 운반비 | C104: ='(계획)손익계산서 월별계획'!C104 -> 0 | D104: =+IFERROR(F104/C104,) -> 0 | E104: =SUM('(계획)손익계산서 월별계획'!E104:(OFFSET('(계획)손익계산서 월별계획'!E104,0,$C$4-1))) -> 0 | F104: =SUM('3. 손익계산서 월별실적'!E104:(OFFSET('3. 손익계산서 월별실적'!E104,0,$C$4-1))) -> 0 | G104: =+IFERROR(F104/E104,) -> 0 | H104: =OFFSET('3. 손익계산서 월별실적'!E104,0,$C$4-2) -> 0 | I104: =+IFERROR(H104/$H$79,) -> 0 | J104: =OFFSET('(계획)손익계산서 월별계획'!E104,0,$C$4-1) -> 0 | K104: =+IFERROR(J104/$J$79,) -> 0 | L104: =OFFSET('3. 손익계산서 월별실적'!E104,0,$C$4-1) -> 0 | M104: =+IFERROR(L104/$L$79,) -> 0 | N104: =+IFERROR(L104/H104,) -> 0 | O104: =+IFERROR(L104/J104,) -> 0
B105: 포장비 | C105: ='(계획)손익계산서 월별계획'!C105 -> 0 | D105: =+IFERROR(F105/C105,) -> 0 | E105: =SUM('(계획)손익계산서 월별계획'!E105:(OFFSET('(계획)손익계산서 월별계획'!E105,0,$C$4-1))) -> 0 | F105: =SUM('3. 손익계산서 월별실적'!E105:(OFFSET('3. 손익계산서 월별실적'!E105,0,$C$4-1))) -> 0 | G105: =+IFERROR(F105/E105,) -> 0 | H105: =OFFSET('3. 손익계산서 월별실적'!E105,0,$C$4-2) -> 0 | I105: =+IFERROR(H105/$H$79,) -> 0 | J105: =OFFSET('(계획)손익계산서 월별계획'!E105,0,$C$4-1) -> 0 | K105: =+IFERROR(J105/$J$79,) -> 0 | L105: =OFFSET('3. 손익계산서 월별실적'!E105,0,$C$4-1) -> 0 | M105: =+IFERROR(L105/$L$79,) -> 0 | N105: =+IFERROR(L105/H105,) -> 0 | O105: =+IFERROR(L105/J105,) -> 0
B106: 광고선전비 | C106: ='(계획)손익계산서 월별계획'!C106 -> 0 | D106: =+IFERROR(F106/C106,) -> 0 | E106: =SUM('(계획)손익계산서 월별계획'!E106:(OFFSET('(계획)손익계산서 월별계획'!E106,0,$C$4-1))) -> 0 | F106: =SUM('3. 손익계산서 월별실적'!E106:(OFFSET('3. 손익계산서 월별실적'!E106,0,$C$4-1))) -> 0 | G106: =+IFERROR(F106/E106,) -> 0 | H106: =OFFSET('3. 손익계산서 월별실적'!E106,0,$C$4-2) -> 0 | I106: =+IFERROR(H106/$H$79,) -> 0 | J106: =OFFSET('(계획)손익계산서 월별계획'!E106,0,$C$4-1) -> 0 | K106: =+IFERROR(J106/$J$79,) -> 0 | L106: =OFFSET('3. 손익계산서 월별실적'!E106,0,$C$4-1) -> 0 | M106: =+IFERROR(L106/$L$79,) -> 0 | N106: =+IFERROR(L106/H106,) -> 0 | O106: =+IFERROR(L106/J106,) -> 0
B107: 지급수수료 | C107: ='(계획)손익계산서 월별계획'!C107 -> 0 | D107: =+IFERROR(F107/C107,) -> 0 | E107: =SUM('(계획)손익계산서 월별계획'!E107:(OFFSET('(계획)손익계산서 월별계획'!E107,0,$C$4-1))) -> 0 | F107: =SUM('3. 손익계산서 월별실적'!E107:(OFFSET('3. 손익계산서 월별실적'!E107,0,$C$4-1))) -> 0 | G107: =+IFERROR(F107/E107,) -> 0 | H107: =OFFSET('3. 손익계산서 월별실적'!E107,0,$C$4-2) -> 0 | I107: =+IFERROR(H107/$H$79,) -> 0 | J107: =OFFSET('(계획)손익계산서 월별계획'!E107,0,$C$4-1) -> 0 | K107: =+IFERROR(J107/$J$79,) -> 0 | L107: =OFFSET('3. 손익계산서 월별실적'!E107,0,$C$4-1) -> 0 | M107: =+IFERROR(L107/$L$79,) -> 0 | N107: =+IFERROR(L107/H107,) -> 0 | O107: =+IFERROR(L107/J107,) -> 0
B108: 여비교통비 | C108: ='(계획)손익계산서 월별계획'!C108 -> 0 | D108: =+IFERROR(F108/C108,) -> 0 | E108: =SUM('(계획)손익계산서 월별계획'!E108:(OFFSET('(계획)손익계산서 월별계획'!E108,0,$C$4-1))) -> 0 | F108: =SUM('3. 손익계산서 월별실적'!E108:(OFFSET('3. 손익계산서 월별실적'!E108,0,$C$4-1))) -> 0 | G108: =+IFERROR(F108/E108,) -> 0 | H108: =OFFSET('3. 손익계산서 월별실적'!E108,0,$C$4-2) -> 0 | I108: =+IFERROR(H108/$H$79,) -> 0 | J108: =OFFSET('(계획)손익계산서 월별계획'!E108,0,$C$4-1) -> 0 | K108: =+IFERROR(J108/$J$79,) -> 0 | L108: =OFFSET('3. 손익계산서 월별실적'!E108,0,$C$4-1) -> 0 | M108: =+IFERROR(L108/$L$79,) -> 0 | N108: =+IFERROR(L108/H108,) -> 0 | O108: =+IFERROR(L108/J108,) -> 0
B109: 감가상각비 | C109: ='(계획)손익계산서 월별계획'!C109 -> 0 | D109: =+IFERROR(F109/C109,) -> 0 | E109: =SUM('(계획)손익계산서 월별계획'!E109:(OFFSET('(계획)손익계산서 월별계획'!E109,0,$C$4-1))) -> 0 | F109: =SUM('3. 손익계산서 월별실적'!E109:(OFFSET('3. 손익계산서 월별실적'!E109,0,$C$4-1))) -> 0 | G109: =+IFERROR(F109/E109,) -> 0 | H109: =OFFSET('3. 손익계산서 월별실적'!E109,0,$C$4-2) -> 0 | I109: =+IFERROR(H109/$H$79,) -> 0 | J109: =OFFSET('(계획)손익계산서 월별계획'!E109,0,$C$4-1) -> 0 | K109: =+IFERROR(J109/$J$79,) -> 0 | L109: =OFFSET('3. 손익계산서 월별실적'!E109,0,$C$4-1) -> 0 | M109: =+IFERROR(L109/$L$79,) -> 0 | N109: =+IFERROR(L109/H109,) -> 0 | O109: =+IFERROR(L109/J109,) -> 0
B110: 개발비 | C110: ='(계획)손익계산서 월별계획'!C110 -> 0 | D110: =+IFERROR(F110/C110,) -> 0 | E110: =SUM('(계획)손익계산서 월별계획'!E110:(OFFSET('(계획)손익계산서 월별계획'!E110,0,$C$4-1))) -> 0 | F110: =SUM('3. 손익계산서 월별실적'!E110:(OFFSET('3. 손익계산서 월별실적'!E110,0,$C$4-1))) -> 0 | G110: =+IFERROR(F110/E110,) -> 0 | H110: =OFFSET('3. 손익계산서 월별실적'!E110,0,$C$4-2) -> 0 | I110: =+IFERROR(H110/$H$79,) -> 0 | J110: =OFFSET('(계획)손익계산서 월별계획'!E110,0,$C$4-1) -> 0 | K110: =+IFERROR(J110/$J$79,) -> 0 | L110: =OFFSET('3. 손익계산서 월별실적'!E110,0,$C$4-1) -> 0 | M110: =+IFERROR(L110/$L$79,) -> 0 | N110: =+IFERROR(L110/H110,) -> 0 | O110: =+IFERROR(L110/J110,) -> 0
B111: 충당비용 | C111: ='(계획)손익계산서 월별계획'!C111 -> 0 | D111: =+IFERROR(F111/C111,) -> 0 | E111: =SUM('(계획)손익계산서 월별계획'!E111:(OFFSET('(계획)손익계산서 월별계획'!E111,0,$C$4-1))) -> 0 | F111: =SUM('3. 손익계산서 월별실적'!E111:(OFFSET('3. 손익계산서 월별실적'!E111,0,$C$4-1))) -> 0 | G111: =+IFERROR(F111/E111,) -> 0 | H111: =OFFSET('3. 손익계산서 월별실적'!E111,0,$C$4-2) -> 0 | I111: =+IFERROR(H111/$H$79,) -> 0 | J111: =OFFSET('(계획)손익계산서 월별계획'!E111,0,$C$4-1) -> 0 | K111: =+IFERROR(J111/$J$79,) -> 0 | L111: =OFFSET('3. 손익계산서 월별실적'!E111,0,$C$4-1) -> 0 | M111: =+IFERROR(L111/$L$79,) -> 0 | N111: =+IFERROR(L111/H111,) -> 0 | O111: =+IFERROR(L111/J111,) -> 0
... B113: 기타비용 | C113: ='(계획)손익계산서 월별계획'!C113 -> 0 | D113: =+IFERROR(F113/C113,) -> 0 | E113: =SUM('(계획)손익계산서 월별계획'!E113:(OFFSET('(계획)손익계산서 월별계획'!E113,0,$C$4-1))) -> 0 | F113: =SUM('3. 손익계산서 월별실적'!E113:(OFFSET('3. 손익계산서 월별실적'!E113,0,$C$4-1))) -> 0 | G113: =+IFERROR(F113/E113,) -> 0 | H113: =OFFSET('3. 손익계산서 월별실적'!E113,0,$C$4-2) -> 0 | I113: =+IFERROR(H113/$H$79,) -> 0 | J113: =OFFSET('(계획)손익계산서 월별계획'!E113,0,$C$4-1) -> 0 | K113: =+IFERROR(J113/$J$79,) -> 0 | L113: =OFFSET('3. 손익계산서 월별실적'!E113,0,$C$4-1) -> 0 | M113: =+IFERROR(L113/$L$79,) -> 0 | N113: =+IFERROR(L113/H113,) -> 0 | O113: =+IFERROR(L113/J113,) -> 0
...

Sheet 3. 손익계산서 월별실적
B3: Plofit and Loss statement FY 2026
B4: ▶ KSCI | P4: (단위:$)
B5: 구분 | C5: 년계 | D5: 12. lst y | E5: 1월 | F5: 2월 | G5: 3월 | H5: 4월 | I5: 5월 | J5: 6월 | K5: 7월 | L5: 8월 | M5: 9월 | N5: 10월 | O5: 11월 | P5: 12월
B6: Ⅰ. 매출액 | C6: =SUM(C7:C10) -> 27657355 | D6: 9843533.5 | E6: =SUM(E7,E9:E10) -> 12501980 | F6: =SUM(F7,F9:F10) -> 15154029 | G6: =SUM(G7,G9:G10) -> 0 | H6: =SUM(H7,H9:H10) -> 0 | I6: =SUM(I7,I9:I10) -> 0 | J6: =SUM(J7,J9:J10) -> 0 | K6: =SUM(K7,K9:K10) -> 0 | L6: =SUM(L7,L9:L10) -> 0 | ... P6: =SUM(P7,P9:P10) -> 0
B7: - 전선 | C7: =SUM(E7:P7) -> 23015553 | D7: 7465258.4 | E7: =E79 -> 10329331 | F7: =F79 -> 12686222 | G7: =G79 -> 0 | H7: =H79 -> 0 | I7: =I79 -> 0 | J7: =J79 -> 0 | K7: =K79 -> 0 | L7: =L79 -> 0 | ... P7: =P79 -> 0
B8: └ 매출동량 | C8: =SUM(E8:P8) -> 1346.4872 | D8: 476.23611 | E8: =E89 -> 631.81666 | F8: =F89 -> 714.67057 | G8: =G89 -> 0 | H8: =H89 -> 0 | I8: =I89 -> 0 | J8: =J89 -> 0 | K8: =K89 -> 0 | L8: =L89 -> 0 | ... P8: =P89 -> 0
B9: - 전장 | C9: =SUM(E9:P9) -> 4640455.9 | D9: 2378275.1 | E9: =E154 -> 2172648.5 | F9: =F154 -> 2467807.4 | G9: =G154 -> 0 | H9: =H154 -> 0 | I9: =I154 -> 0 | J9: =J154 -> 0 | K9: =K154 -> 0 | L9: =L154 -> 0 | ... P9: =P154 -> 0
B11: Ⅱ. 매출원가 | C11: =SUM(C12:C15) -> 25558804 | D11: 9644978.3 | E11: =SUM(E12:E15) -> 11738514 | F11: =SUM(F12:F15) -> 13820290 | G11: =SUM(G12:G15) -> 0 | H11: =SUM(H12:H15) -> 0 | I11: =SUM(I12:I15) -> 0 | J11: =SUM(J12:J15) -> 0 | K11: =SUM(K12:K15) -> 0 | L11: =SUM(L12:L15) -> 0 | ... P11: =SUM(P12:P15) -> 0
B12: - 제품 | C12: =SUM(E12:P12) -> 22291205 | D12: 8303839.7 | E12: =SUM(E92,E161) -> 10834567 | F12: =SUM(F92,F161) -> 11456637 | G12: =SUM(G92,G161) -> 0 | H12: =SUM(H92,H161) -> 0 | I12: =SUM(I92,I161) -> 0 | J12: =SUM(J92,J161) -> 0 | K12: =SUM(K92,K161) -> 0 | L12: =SUM(L92,L161) -> 0 | ... P12: =SUM(P92,P161) -> 0
B13: - 상품 | C13: =SUM(E13:P13) -> 3562289.4 | D13: 1503795.5 | E13: =SUM(E93,E162) -> 1198637.1 | F13: =SUM(F93,F162) -> 2363652.3 | G13: =SUM(G93,G162) -> 0 | H13: =SUM(H93,H162) -> 0 | I13: =SUM(I93,I162) -> 0 | J13: =SUM(J93,J162) -> 0 | K13: =SUM(K93,K162) -> 0 | L13: =SUM(L93,L162) -> 0 | ... P13: =SUM(P93,P162) -> 0
B14: - 기타 | C14: =SUM(E14:P14) -> -294690 | D14: -162656.88 | E14: =SUM(E94,E163) -> -294690 | F14: =SUM(F94,F163) -> 0 | G14: =SUM(G94,G163) -> 0 | H14: =SUM(H94,H163) -> 0 | I14: =SUM(I94,I163) -> 0 | J14: =SUM(J94,J163) -> 0 | K14: =SUM(K94,K163) -> 0 | L14: =SUM(L94,L163) -> 0 | ... P14: =SUM(P94,P163) -> 0
C15: =SUM(E15:P15) -> 0
B16: Ⅲ. 매출총이익 | C16: =+C6-C11 -> 2098551.3 | D16: 198555.2 | E16: =+E6-E11 -> 763465.41 | F16: =+F6-F11 -> 1333739.4 | G16: =+G6-G11 -> 0 | H16: =+H6-H11 -> 0 | I16: =+I6-I11 -> 0 | J16: =+J6-J11 -> 0 | K16: =+K6-K11 -> 0 | L16: =+L6-L11 -> 0 | ... P16: =+P6-P11 -> 0
B17: (이익률) | C17: =+IFERROR(C16/C6,) -> 0.075876788 | D17: 0.02017113 | E17: =+IFERROR(E16/E6,) -> 0.06106756 | F17: =+IFERROR(F16/F6,) -> 0.088012198 | G17: =+IFERROR(G16/G6,) -> 0 | H17: =+IFERROR(H16/H6,) -> 0 | I17: =+IFERROR(I16/I6,) -> 0 | J17: =+IFERROR(J16/J6,) -> 0 | K17: =+IFERROR(K16/K6,) -> 0 | L17: =+IFERROR(L16/L6,) -> 0 | ... P17: =+IFERROR(P16/P6,) -> 0
B18: Ⅳ.판매관리비 | C18: =SUM(E18:P18) -> 1401379.1 | D18: 804702.95 | E18: =+E19+E35+E53 -> 695216.17 | F18: =+F19+F35+F53 -> 706162.94 | G18: =+G19+G35+G53 -> 0 | H18: =+H19+H35+H53 -> 0 | I18: =+I19+I35+I53 -> 0 | J18: =+J19+J35+J53 -> 0 | K18: =+K19+K35+K53 -> 0 | L18: =+L19+L35+L53 -> 0 | ... P18: =+P19+P35+P53 -> 0
B19: [판매비] | C19: =SUM(E19:P19) -> 0 | E19: =SUM(E20:E33) -> 0 | F19: =SUM(F20:F33) -> 0 | G19: =SUM(G20:G33) -> 0 | H19: =SUM(H20:H33) -> 0 | I19: =SUM(I20:I33) -> 0 | J19: =SUM(J20:J33) -> 0 | K19: =SUM(K20:K33) -> 0 | L19: =SUM(L20:L33) -> 0 | ... P19: =SUM(P20:P33) -> 0
B20: 인건비 | C20: =SUM(E20:P20) -> 0 | E20: =SUM(E100,E169) -> 0 | F20: =SUM(F100,F169) -> 0 | G20: =SUM(G100,G169) -> 0 | H20: =SUM(H100,H169) -> 0 | I20: =SUM(I100,I169) -> 0 | J20: =SUM(J100,J169) -> 0 | K20: =SUM(K100,K169) -> 0 | L20: =SUM(L100,L169) -> 0 | ... P20: =SUM(P100,P169) -> 0
B21: 유지비용 | C21: =SUM(E21:P21) -> 0 | E21: =SUM(E101,E170) -> 0 | F21: =SUM(F101,F170) -> 0 | G21: =SUM(G101,G170) -> 0 | H21: =SUM(H101,H170) -> 0 | I21: =SUM(I101,I170) -> 0 | J21: =SUM(J101,J170) -> 0 | K21: =SUM(K101,K170) -> 0 | L21: =SUM(L101,L170) -> 0 | ... P21: =SUM(P101,P170) -> 0
B22: 세금,보험 | C22: =SUM(E22:P22) -> 0 | E22: =SUM(E102,E171) -> 0 | F22: =SUM(F102,F171) -> 0 | G22: =SUM(G102,G171) -> 0 | H22: =SUM(H102,H171) -> 0 | I22: =SUM(I102,I171) -> 0 | J22: =SUM(J102,J171) -> 0 | K22: =SUM(K102,K171) -> 0 | L22: =SUM(L102,L171) -> 0 | ... P22: =SUM(P102,P171) -> 0
B23: 복리후생비 | C23: =SUM(E23:P23) -> 0 | E23: =SUM(E103,E172) -> 0 | F23: =SUM(F103,F172) -> 0 | G23: =SUM(G103,G172) -> 0 | H23: =SUM(H103,H172) -> 0 | I23: =SUM(I103,I172) -> 0 | J23: =SUM(J103,J172) -> 0 | K23: =SUM(K103,K172) -> 0 | L23: =SUM(L103,L172) -> 0 | ... P23: =SUM(P103,P172) -> 0
B24: 운반비 | C24: =SUM(E24:P24) -> 0 | E24: =SUM(E104,E173) -> 0 | F24: =SUM(F104,F173) -> 0 | G24: =SUM(G104,G173) -> 0 | H24: =SUM(H104,H173) -> 0 | I24: =SUM(I104,I173) -> 0 | J24: =SUM(J104,J173) -> 0 | K24: =SUM(K104,K173) -> 0 | L24: =SUM(L104,L173) -> 0 | ... P24: =SUM(P104,P173) -> 0
B25: 포장비 | C25: =SUM(E25:P25) -> 0 | E25: =SUM(E105,E174) -> 0 | F25: =SUM(F105,F174) -> 0 | G25: =SUM(G105,G174) -> 0 | H25: =SUM(H105,H174) -> 0 | I25: =SUM(I105,I174) -> 0 | J25: =SUM(J105,J174) -> 0 | K25: =SUM(K105,K174) -> 0 | L25: =SUM(L105,L174) -> 0 | ... P25: =SUM(P105,P174) -> 0
B26: 광고선전비 | C26: =SUM(E26:P26) -> 0 | E26: =SUM(E106,E175) -> 0 | F26: =SUM(F106,F175) -> 0 | G26: =SUM(G106,G175) -> 0 | H26: =SUM(H106,H175) -> 0 | I26: =SUM(I106,I175) -> 0 | J26: =SUM(J106,J175) -> 0 | K26: =SUM(K106,K175) -> 0 | L26: =SUM(L106,L175) -> 0 | ... P26: =SUM(P106,P175) -> 0
B27: 지급수수료 | C27: =SUM(E27:P27) -> 0 | E27: =SUM(E107,E176) -> 0 | F27: =SUM(F107,F176) -> 0 | G27: =SUM(G107,G176) -> 0 | H27: =SUM(H107,H176) -> 0 | I27: =SUM(I107,I176) -> 0 | J27: =SUM(J107,J176) -> 0 | K27: =SUM(K107,K176) -> 0 | L27: =SUM(L107,L176) -> 0 | ... P27: =SUM(P107,P176) -> 0
B28: 여비교통비 | C28: =SUM(E28:P28) -> 0 | E28: =SUM(E108,E177) -> 0 | F28: =SUM(F108,F177) -> 0 | G28: =SUM(G108,G177) -> 0 | H28: =SUM(H108,H177) -> 0 | I28: =SUM(I108,I177) -> 0 | J28: =SUM(J108,J177) -> 0 | K28: =SUM(K108,K177) -> 0 | L28: =SUM(L108,L177) -> 0 | ... P28: =SUM(P108,P177) -> 0
B29: 감가상각비 | C29: =SUM(E29:P29) -> 0 | E29: =SUM(E109,E178) -> 0 | F29: =SUM(F109,F178) -> 0 | G29: =SUM(G109,G178) -> 0 | H29: =SUM(H109,H178) -> 0 | I29: =SUM(I109,I178) -> 0 | J29: =SUM(J109,J178) -> 0 | K29: =SUM(K109,K178) -> 0 | L29: =SUM(L109,L178) -> 0 | ... P29: =SUM(P109,P178) -> 0
B30: 개발비 | C30: =SUM(E30:P30) -> 0 | E30: =SUM(E110,E179) -> 0 | F30: =SUM(F110,F179) -> 0 | G30: =SUM(G110,G179) -> 0 | H30: =SUM(H110,H179) -> 0 | I30: =SUM(I110,I179) -> 0 | J30: =SUM(J110,J179) -> 0 | K30: =SUM(K110,K179) -> 0 | L30: =SUM(L110,L179) -> 0 | ... P30: =SUM(P110,P179) -> 0
B31: 충당비용 | C31: =SUM(E31:P31) -> 0 | E31: =SUM(E111,E180) -> 0 | F31: =SUM(F111,F180) -> 0 | G31: =SUM(G111,G180) -> 0 | H31: =SUM(H111,H180) -> 0 | I31: =SUM(I111,I180) -> 0 | J31: =SUM(J111,J180) -> 0 | K31: =SUM(K111,K180) -> 0 | L31: =SUM(L111,L180) -> 0 | ... P31: =SUM(P111,P180) -> 0
... B33: 기타비용 | C33: =SUM(E33:P33) -> 0 | E33: =SUM(E113,E182) -> 0 | F33: =SUM(F113,F182) -> 0 | G33: =SUM(G113,G182) -> 0 | H33: =SUM(H113,H182) -> 0 | I33: =SUM(I113,I182) -> 0 | J33: =SUM(J113,J182) -> 0 | K33: =SUM(K113,K182) -> 0 | L33: =SUM(L113,L182) -> 0 | ... P33: =SUM(P113,P182) -> 0
B35: [관리비] | C35: =SUM(E35:P35) -> 1401379.1 | D35: 804702.95 | E35: =SUM(E36:E51) -> 695216.17 | F35: =SUM(F36:F51) -> 706162.94 | G35: =SUM(G36:G51) -> 0 | H35: =SUM(H36:H51) -> 0 | I35: =SUM(I36:I51) -> 0 | J35: =SUM(J36:J51) -> 0 | K35: =SUM(K36:K51) -> 0 | L35: =SUM(L36:L51) -> 0 | ... P35: =SUM(P36:P51) -> 0
B36: 인건비 | C36: =SUM(E36:P36) -> 646352.28 | D36: 138875.92 | E36: =SUM(E116,E185) -> 325645.54 | F36: =SUM(F116,F185) -> 320706.74 | G36: =SUM(G116,G185) -> 0 | H36: =SUM(H116,H185) -> 0 | I36: =SUM(I116,I185) -> 0 | J36: =SUM(J116,J185) -> 0 | K36: =SUM(K116,K185) -> 0 | L36: =SUM(L116,L185) -> 0 | ... P36: =SUM(P116,P185) -> 0
B37: 유지비용 | C37: =SUM(E37:P37) -> 25876.8 | D37: 10657.37 | E37: =SUM(E117,E186) -> 12954.35 | F37: =SUM(F117,F186) -> 12922.45 | G37: =SUM(G117,G186) -> 0 | H37: =SUM(H117,H186) -> 0 | I37: =SUM(I117,I186) -> 0 | J37: =SUM(J117,J186) -> 0 | K37: =SUM(K117,K186) -> 0 | L37: =SUM(L117,L186) -> 0 | ... P37: =SUM(P117,P186) -> 0
B38: 세금,보험 | C38: =SUM(E38:P38) -> 61541.51 | D38: 27643.34 | E38: =SUM(E118,E187) -> 28636.21 | F38: =SUM(F118,F187) -> 32905.3 | G38: =SUM(G118,G187) -> 0 | H38: =SUM(H118,H187) -> 0 | I38: =SUM(I118,I187) -> 0 | J38: =SUM(J118,J187) -> 0 | K38: =SUM(K118,K187) -> 0 | L38: =SUM(L118,L187) -> 0 | ... P38: =SUM(P118,P187) -> 0
B39: 복리후생비 | C39: =SUM(E39:P39) -> 6562.53 | D39: 3221.41 | E39: =SUM(E119,E188) -> 2374.41 | F39: =SUM(F119,F188) -> 4188.12 | G39: =SUM(G119,G188) -> 0 | H39: =SUM(H119,H188) -> 0 | I39: =SUM(I119,I188) -> 0 | J39: =SUM(J119,J188) -> 0 | K39: =SUM(K119,K188) -> 0 | L39: =SUM(L119,L188) -> 0 | ... P39: =SUM(P119,P188) -> 0
B40: 운반비 | C40: =SUM(E40:P40) -> 91123.68 | D40: 25846.87 | E40: =SUM(E120,E189) -> 58276.9 | F40: =SUM(F120,F189) -> 32846.78 | G40: =SUM(G120,G189) -> 0 | H40: =SUM(H120,H189) -> 0 | I40: =SUM(I120,I189) -> 0 | J40: =SUM(J120,J189) -> 0 | K40: =SUM(K120,K189) -> 0 | L40: =SUM(L120,L189) -> 0 | ... P40: =SUM(P120,P189) -> 0
B41: 포장비 | C41: =SUM(E41:P41) -> 0 | D41: 0 | E41: =SUM(E121,E190) -> 0 | F41: =SUM(F121,F190) -> 0 | G41: =SUM(G121,G190) -> 0 | H41: =SUM(H121,H190) -> 0 | I41: =SUM(I121,I190) -> 0 | J41: =SUM(J121,J190) -> 0 | K41: =SUM(K121,K190) -> 0 | L41: =SUM(L121,L190) -> 0 | ... P41: =SUM(P121,P190) -> 0
B42: 광고선전비 | C42: =SUM(E42:P42) -> 18646.72 | D42: 7379.83 | E42: =SUM(E122,E191) -> 4997.23 | F42: =SUM(F122,F191) -> 13649.49 | G42: =SUM(G122,G191) -> 0 | H42: =SUM(H122,H191) -> 0 | I42: =SUM(I122,I191) -> 0 | J42: =SUM(J122,J191) -> 0 | K42: =SUM(K122,K191) -> 0 | L42: =SUM(L122,L191) -> 0 | ... P42: =SUM(P122,P191) -> 0
B43: 지급수수료 | C43: =SUM(E43:P43) -> 478068.05 | D43: 227988.19 | E43: =SUM(E123,E192) -> 225126.16 | F43: =SUM(F123,F192) -> 252941.89 | G43: =SUM(G123,G192) -> 0 | H43: =SUM(H123,H192) -> 0 | I43: =SUM(I123,I192) -> 0 | J43: =SUM(J123,J192) -> 0 | K43: =SUM(K123,K192) -> 0 | L43: =SUM(L123,L192) -> 0 | ... P43: =SUM(P123,P192) -> 0
B44: 여비교통비 | C44: =SUM(E44:P44) -> 40660.57 | D44: 15159.41 | E44: =SUM(E124,E193) -> 18498.97 | F44: =SUM(F124,F193) -> 22161.6 | G44: =SUM(G124,G193) -> 0 | H44: =SUM(H124,H193) -> 0 | I44: =SUM(I124,I193) -> 0 | J44: =SUM(J124,J193) -> 0 | K44: =SUM(K124,K193) -> 0 | L44: =SUM(L124,L193) -> 0 | ... P44: =SUM(P124,P193) -> 0
B45: 감가상각비 | C45: =SUM(E45:P45) -> 10328.31 | D45: 26706.26 | E45: =SUM(E125,E194) -> 5419.12 | F45: =SUM(F125,F194) -> 4909.19 | G45: =SUM(G125,G194) -> 0 | H45: =SUM(H125,H194) -> 0 | I45: =SUM(I125,I194) -> 0 | J45: =SUM(J125,J194) -> 0 | K45: =SUM(K125,K194) -> 0 | L45: =SUM(L125,L194) -> 0 | ... P45: =SUM(P125,P194) -> 0
B46: 개발비 | C46: =SUM(E46:P46) -> 0 | D46: 0 | E46: =SUM(E126,E195) -> 0 | F46: =SUM(F126,F195) -> 0 | G46: =SUM(G126,G195) -> 0 | H46: =SUM(H126,H195) -> 0 | I46: =SUM(I126,I195) -> 0 | J46: =SUM(J126,J195) -> 0 | K46: =SUM(K126,K195) -> 0 | L46: =SUM(L126,L195) -> 0 | ... P46: =SUM(P126,P195) -> 0
B47: 충당비용 | C47: =SUM(E47:P47) -> 0 | D47: 311831.51 | E47: =SUM(E127,E196) -> 0 | F47: =SUM(F127,F196) -> 0 | G47: =SUM(G127,G196) -> 0 | H47: =SUM(H127,H196) -> 0 | I47: =SUM(I127,I196) -> 0 | J47: =SUM(J127,J196) -> 0 | K47: =SUM(K127,K196) -> 0 | L47: =SUM(L127,L196) -> 0 | ... P47: =SUM(P127,P196) -> 0
... B50: 투자비지원 | C50: =SUM(E50:P50) -> 0 | D50: 0 | E50: =SUM(E130,E199) -> 0 | F50: =SUM(F130,F199) -> 0 | G50: =SUM(G130,G199) -> 0 | H50: =SUM(H130,H199) -> 0 | I50: =SUM(I130,I199) -> 0 | J50: =SUM(J130,J199) -> 0 | K50: =SUM(K130,K199) -> 0 | L50: =SUM(L130,L199) -> 0 | ... P50: =SUM(P130,P199) -> 0
B53: [연구개발비] | C53: =SUM(E53:P53) -> 0 | E53: =SUM(E54:E67) -> 0 | F53: =SUM(F54:F67) -> 0 | G53: =SUM(G54:G67) -> 0 | H53: =SUM(H54:H67) -> 0 | I53: =SUM(I54:I67) -> 0 | J53: =SUM(J54:J67) -> 0 | K53: =SUM(K54:K67) -> 0 | L53: =SUM(L54:L67) -> 0 | ... P53: =SUM(P54:P67) -> 0
B54: 인건비 | C54: =SUM(E54:P54) -> 0 | E54: =SUM(E134,E203) -> 0 | F54: =SUM(F134,F203) -> 0 | G54: =SUM(G134,G203) -> 0 | H54: =SUM(H134,H203) -> 0 | I54: =SUM(I134,I203) -> 0 | J54: =SUM(J134,J203) -> 0 | K54: =SUM(K134,K203) -> 0 | L54: =SUM(L134,L203) -> 0 | ... P54: =SUM(P134,P203) -> 0
B55: 유지비(금형 등) | C55: =SUM(E55:P55) -> 0 | E55: =SUM(E135,E204) -> 0 | F55: =SUM(F135,F204) -> 0 | G55: =SUM(G135,G204) -> 0 | H55: =SUM(H135,H204) -> 0 | I55: =SUM(I135,I204) -> 0 | J55: =SUM(J135,J204) -> 0 | K55: =SUM(K135,K204) -> 0 | L55: =SUM(L135,L204) -> 0 | ... P55: =SUM(P135,P204) -> 0
B56: 세금,보험 | C56: =SUM(E56:P56) -> 0 | E56: =SUM(E136,E205) -> 0 | F56: =SUM(F136,F205) -> 0 | G56: =SUM(G136,G205) -> 0 | H56: =SUM(H136,H205) -> 0 | I56: =SUM(I136,I205) -> 0 | J56: =SUM(J136,J205) -> 0 | K56: =SUM(K136,K205) -> 0 | L56: =SUM(L136,L205) -> 0 | ... P56: =SUM(P136,P205) -> 0
B57: 복리후생비 | C57: =SUM(E57:P57) -> 0 | E57: =SUM(E137,E206) -> 0 | F57: =SUM(F137,F206) -> 0 | G57: =SUM(G137,G206) -> 0 | H57: =SUM(H137,H206) -> 0 | I57: =SUM(I137,I206) -> 0 | J57: =SUM(J137,J206) -> 0 | K57: =SUM(K137,K206) -> 0 | L57: =SUM(L137,L206) -> 0 | ... P57: =SUM(P137,P206) -> 0
B58: 운반비 | C58: =SUM(E58:P58) -> 0 | E58: =SUM(E138,E207) -> 0 | F58: =SUM(F138,F207) -> 0 | G58: =SUM(G138,G207) -> 0 | H58: =SUM(H138,H207) -> 0 | I58: =SUM(I138,I207) -> 0 | J58: =SUM(J138,J207) -> 0 | K58: =SUM(K138,K207) -> 0 | L58: =SUM(L138,L207) -> 0 | ... P58: =SUM(P138,P207) -> 0
B59: 포장비 | C59: =SUM(E59:P59) -> 0 | E59: =SUM(E139,E208) -> 0 | F59: =SUM(F139,F208) -> 0 | G59: =SUM(G139,G208) -> 0 | H59: =SUM(H139,H208) -> 0 | I59: =SUM(I139,I208) -> 0 | J59: =SUM(J139,J208) -> 0 | K59: =SUM(K139,K208) -> 0 | L59: =SUM(L139,L208) -> 0 | ... P59: =SUM(P139,P208) -> 0
B60: 광고선전비 | C60: =SUM(E60:P60) -> 0 | E60: =SUM(E140,E209) -> 0 | F60: =SUM(F140,F209) -> 0 | G60: =SUM(G140,G209) -> 0 | H60: =SUM(H140,H209) -> 0 | I60: =SUM(I140,I209) -> 0 | J60: =SUM(J140,J209) -> 0 | K60: =SUM(K140,K209) -> 0 | L60: =SUM(L140,L209) -> 0 | ... P60: =SUM(P140,P209) -> 0
B61: 지급수수료 | C61: =SUM(E61:P61) -> 0 | E61: =SUM(E141,E210) -> 0 | F61: =SUM(F141,F210) -> 0 | G61: =SUM(G141,G210) -> 0 | H61: =SUM(H141,H210) -> 0 | I61: =SUM(I141,I210) -> 0 | J61: =SUM(J141,J210) -> 0 | K61: =SUM(K141,K210) -> 0 | L61: =SUM(L141,L210) -> 0 | ... P61: =SUM(P141,P210) -> 0
B62: 여비교통비 | C62: =SUM(E62:P62) -> 0 | E62: =SUM(E142,E211) -> 0 | F62: =SUM(F142,F211) -> 0 | G62: =SUM(G142,G211) -> 0 | H62: =SUM(H142,H211) -> 0 | I62: =SUM(I142,I211) -> 0 | J62: =SUM(J142,J211) -> 0 | K62: =SUM(K142,K211) -> 0 | L62: =SUM(L142,L211) -> 0 | ... P62: =SUM(P142,P211) -> 0
B63: 감가상각비 | C63: =SUM(E63:P63) -> 0 | E63: =SUM(E143,E212) -> 0 | F63: =SUM(F143,F212) -> 0 | G63: =SUM(G143,G212) -> 0 | H63: =SUM(H143,H212) -> 0 | I63: =SUM(I143,I212) -> 0 | J63: =SUM(J143,J212) -> 0 | K63: =SUM(K143,K212) -> 0 | L63: =SUM(L143,L212) -> 0 | ... P63: =SUM(P143,P212) -> 0
B64: 개발비 | C64: =SUM(E64:P64) -> 0 | E64: =SUM(E144,E213) -> 0 | F64: =SUM(F144,F213) -> 0 | G64: =SUM(G144,G213) -> 0 | H64: =SUM(H144,H213) -> 0 | I64: =SUM(I144,I213) -> 0 | J64: =SUM(J144,J213) -> 0 | K64: =SUM(K144,K213) -> 0 | L64: =SUM(L144,L213) -> 0 | ... P64: =SUM(P144,P213) -> 0
B65: 충당비용 | C65: =SUM(E65:P65) -> 0 | E65: =SUM(E145,E214) -> 0 | F65: =SUM(F145,F214) -> 0 | G65: =SUM(G145,G214) -> 0 | H65: =SUM(H145,H214) -> 0 | I65: =SUM(I145,I214) -> 0 | J65: =SUM(J145,J214) -> 0 | K65: =SUM(K145,K214) -> 0 | L65: =SUM(L145,L214) -> 0 | ... P65: =SUM(P145,P214) -> 0
... B67: 기타비용 | C67: =SUM(E67:P67) -> 0 | E67: =SUM(E147,E216) -> 0 | F67: =SUM(F147,F216) -> 0 | G67: =SUM(G147,G216) -> 0 | H67: =SUM(H147,H216) -> 0 | I67: =SUM(I147,I216) -> 0 | J67: =SUM(J147,J216) -> 0 | K67: =SUM(K147,K216) -> 0 | L67: =SUM(L147,L216) -> 0 | ... P67: =SUM(P147,P216) -> 0
B68: Ⅴ.영업이익 | C68: =SUM(E68:P68) -> 695825.69 | D68: =+D16-D18 -> -606147.75 | E68: =+E16-E18 -> 68249.24 | F68: =+F16-F18 -> 627576.45 | G68: =+G16-G18 -> 0 | H68: =+H16-H18 -> 0 | I68: =+I16-I18 -> 0 | J68: =+J16-J18 -> 0 | K68: =+K16-K18 -> 0 | ... P68: =+P16-P18 -> 0
B69: (이익률) | C69: =+IFERROR(C68/C6,) -> 0.025158793 | D69: =+IFERROR(D68/D6,) -> -0.061578269 | E69: =+IFERROR(E68/E6,) -> 0.0054590745 | F69: =+IFERROR(F68/F6,) -> 0.041413175 | G69: =+IFERROR(G68/G6,) -> 0 | H69: =+IFERROR(H68/H6,) -> 0 | I69: =+IFERROR(I68/I6,) -> 0 | J69: =+IFERROR(J68/J6,) -> 0 | ... P69: =+IFERROR(P68/P6,) -> 0
B70: Ⅵ.영업외수익
B71: Ⅶ. 영업외비용
B72: Ⅷ 법인세
B73: Ⅸ.당기손익
B74: (이익률)
E75: =E68-SUM(E148,E217) -> 1.1641532e-10 | F75: =F68-SUM(F148,F217) -> 9.3132257e-10 | G75: =G68-SUM(G148,G217) -> 0 | H75: =H68-SUM(H148,H217) -> 0 | I75: =I148+I217-I68 -> 0 | J75: =J148+J217-J68 -> 0 | K75: =K148+K217-K68 -> 0 | L75: =L148+L217=L68 -> TRUE | M75: =M148+M217-M68 -> 0 | N75: =N148+N217=N68 -> TRUE | O75: =O148+O217-O68 -> 0 | P75: =P148+P217-P68 -> 0
B77: ▶ KSCM-DG (전선) | E77: 10329331 | F77: 12686222 | P77: (단위:$)
B78: 구분 | C78: 년계 | D78: 12. lst y | E78: 1월 | F78: 2월 | G78: 3월 | H78: 4월 | I78: 5월 | J78: 6월 | K78: 7월 | L78: 8월 | M78: 9월 | N78: 10월 | O78: 11월 | P78: 12월 | T78: =SUM(T79:T94) -> 12686222 | V78: 매출 | W78: 원가 | Z78: =SUM(Z86:Z94) -> 12686222
B79: Ⅰ. 매출액 | C79: =SUM(C80:C81) -> 23015553 | D79: 7465258.4 | E79: =SUM(E82:E88) -> 10329331 | F79: =SUM(F82:F88) -> 12686222 | G79: =SUM(G82:G88) -> 0 | H79: =SUM(H80:H81) -> 0 | I79: =SUM(I80:I81) -> 0 | J79: =SUM(J80:J81) -> 0 | K79: =SUM(K80:K81) -> 0 | L79: =SUM(L80:L81) -> 0 | M79: =SUM(M80:M81) -> 0 | N79: =SUM(N80:N81) -> 0 | O79: =SUM(O80:O81) -> 0 | P79: =SUM(P80:P81) -> 0 | S79: 200406 Kyungshin Cable Inte | T79: 33459.26 | U79: 3000 원자재 | V79: 0 | W79: 7.15
B80: - 제품 | C80: =SUM(E80:P80) -> 18611465 | D80: 5716753 | E80: 8873528.4 | F80: 9737936.6 | S80: 200440 TAESUNG MEXICO S DE | T80: 397410.65 | U80: 3100 상품 | V80: 2948285 | W80: 2363652.3
B81: - 상품 | C81: =SUM(E81:P81) -> 4404087.9 | D81: 1748505.4 | E81: 1455802.9 | F81: 2948285 | S81: 200447 E&K LLC | T81: 146429.9 | U81: 7900 반제품 | V81: 0 | W81: 1.85
B82: DAWS | C82: =SUM(E82:P82) -> 12149586 | D82: 3666210.8 | E82: 4928419.3 | F82: 7221166.6 | S82: 200452 HEDS | T82: 1302578.5 | U82: 7920 완제품 | V82: 9686783.6 | W82: 8634942.2
B83: HEDS | C83: =SUM(E83:P83) -> 2339612.5 | D83: 613806.52 | E83: 1037033.9 | F83: 1302578.5 | S83: 200454 KAC | T83: 525820.3 | U83: 미지정 | V83: 51153.03 | W83: 0
B84: CEWS | C84: =SUM(E84:P84) -> 2803475.8 | D84: 1325035.8 | E84: 1124453 | F84: 1679022.8 | S84: 200458 KLSE_CEWS | T84: 927020.68 | Y84: 제품 | Z84: =+V85-V80 -> 9737936.6 | AA84: =+W85-W80 -> 8634951.2
B85: LEAR | C85: =SUM(E85:P85) -> 3270952.4 | D85: 839223.27 | E85: 1914487.4 | F85: 1356465 | S85: 200460 KLSE_CEWS 3 | T85: 752002.12 | V85: 12686222 | W85: 10998603 | Y85: 상품 | Z85: =+V80 -> 2948285 | AA85: =+W80 -> 2363652.3
B86: KAC-OB | C86: =SUM(E86:P86) -> 1361510.3 | D86: 608551.76 | E86: 835690.01 | F86: 525820.3 | S86: 200461 KLSE_DAWS | T86: 7221166.6 | Y86: DAWS | Z86: =+T86 -> 7221166.6
B87: SUMITOMO | C87: =SUM(E87:P87) -> 144799.42 | E87: 120930.87 | F87: 23868.55 | S87: 200469 LEAR_MATAMOROS | T87: 689718.66 | Y87: HEDS | Z87: =+T82 -> 1302578.5
B88: 기타 | C88: =SUM(E88:P88) -> 945616.52 | D88: 412430.22 | E88: 368316.71 | F88: 577299.81 | S88: 200470 LEAR_MATAMOROS 2 | T88: 236178.06 | V88: =+V85-T78 -> 0 | Y88: CEWS | Z88: =+T84+T85 -> 1679022.8
B89: (매출중량) | C89: =SUM(E89:P89) -> 1346.4872 | D89: 476.23611 | E89: 631.81666 | F89: 714.67057 | S89: 200471 LEAR_MONARCA | T89: 27012.54 | Y89: LEAR | Z89: =+T87+T88+T89+T90+T91+T92 -> 1356465
E90: 9323900 | F90: 10998602 | S90: 200473 LEAR_NOVA | T90: 234617.6 | Y90: KAC-OB | Z90: =+T83 -> 525820.3
B91: Ⅱ. 매출원가 | C91: =SUM(C92:C95) -> 20322500 | D91: 6804593.9 | E91: =SUM(E92:E94) -> 9323898.1 | F91: =SUM(F92:F94) -> 10998602 | G91: =SUM(G92:G94) -> 0 | H91: =SUM(H92:H94) -> 0 | I91: =SUM(I92:I94) -> 0 | J91: =SUM(J92:J94) -> 0 | K91: =SUM(K92:K94) -> 0 | L91: =SUM(L92:L94) -> 0 | ... P91: =SUM(P92:P94) -> 0 | S91: 200475 LEAR_SICOMORO | T91: 3078.1 | Y91: SUMITOMO | Z91: =+T93 -> 23868.55
B92: - 제품 | C92: =SUM(E92:P92) -> 16760211 | D92: 5300798.5 | E92: 8125261 | F92: 8634949.7 | S92: 200476 LEAR_TORRES | T92: 165860.05 | Y92: 기타 | Z92: =+T81+T80+T79 -> 577299.81
B93: - 상품 | C93: =SUM(E93:P93) -> 3562289.4 | D93: 1503795.5 | E93: 1198637.1 | F93: 2363652.3 | S93: 200481 Sumitomo Electric Wi | T93: 23868.55
B94: - 기타 | C94: =SUM(E94:P94) -> 0 | S94: 미지정 | T94: 0
B96: Ⅲ. 매출총이익 | C96: =+C79-C91 -> 2693052.8 | D96: 660664.46 | E96: =E79-E91 -> 1005433.2 | F96: =+F79-F91 -> 1687619.6 | G96: =+G79-G91 -> 0 | H96: =+H79-H91 -> 0 | I96: =+I79-I91 -> 0 | J96: =+J79-J91 -> 0 | K96: =+K79-K91 -> 0 | L96: =+L79-L91 -> 0 | M96: =+M79-M91 -> 0 | ... P96: =+P79-P91 -> 0
B97: (이익률) | C97: =+IFERROR(C96/C79,) -> 0.11701013 | D97: 0.088498539 | E97: =+IFERROR(E96/E79,) -> 0.097337688 | F97: =+IFERROR(F96/F79,) -> 0.13302776 | G97: =+IFERROR(G96/G79,) -> 0 | H97: =+IFERROR(H96/H79,) -> 0 | I97: =+IFERROR(I96/I79,) -> 0 | J97: =+IFERROR(J96/J79,) -> 0 | K97: =+IFERROR(K96/K79,) -> 0 | L97: =+IFERROR(L96/L79,) -> 0 | ... P97: =+IFERROR(P96/P79,) -> 0 | T97: 10329331
B98: Ⅳ.판매관리비 | C98: =SUM(E98:P98) -> 719856.82 | D98: 482172.68 | E98: =+E99+E115+E133 -> 342624.59 | F98: =+F99+F115+F133 -> 377232.23 | G98: =+G99+G115+G133 -> 0 | H98: =+H99+H115+H133 -> 0 | I98: =+I99+I115+I133 -> 0 | J98: =+J99+J115+J133 -> 0 | K98: =+K99+K115+K133 -> 0 | L98: =+L99+L115+L133 -> 0 | ... P98: =+P99+P115+P133 -> 0
B99: [판매비] | C99: =SUM(E99:P99) -> 0 | E99: =SUM(E100:E113) -> 0 | F99: =SUM(F100:F113) -> 0 | G99: =SUM(G100:G113) -> 0 | H99: =SUM(H100:H113) -> 0 | I99: =SUM(I100:I113) -> 0 | J99: =SUM(J100:J113) -> 0 | K99: =SUM(K100:K113) -> 0 | L99: =SUM(L100:L113) -> 0 | ... P99: =SUM(P100:P113) -> 0
B100: 인건비 | C100: =SUM(E100:P100) -> 0
B101: 유지비용 | C101: =SUM(E101:P101) -> 0
B102: 세금,보험 | C102: =SUM(E102:P102) -> 0
B103: 복리후생비 | C103: =SUM(E103:P103) -> 0
B104: 운반비 | C104: =SUM(E104:P104) -> 0
B105: 포장비 | C105: =SUM(E105:P105) -> 0
B106: 광고선전비 | C106: =SUM(E106:P106) -> 0
B107: 지급수수료 | C107: =SUM(E107:P107) -> 0
B108: 여비교통비 | C108: =SUM(E108:P108) -> 0
B109: 감가상각비 | C109: =SUM(E109:P109) -> 0
B110: 개발비 | C110: =SUM(E110:P110) -> 0
B111: 충당비용 | C111: =SUM(E111:P111) -> 0
... B113: 기타비용 | C113: =SUM(E113:P113) -> 0
...

Sheet Sheet1
E7: 15154029 | F7: 15154029 | G7: =+E7-F7 -> 0
E8: 13820290 | F8: 13820291 | G8: =+E8-F8 -> -1.53
E9: 706162.94 | F9: 706162.96 | G9: =+E9-F9 -> -0.02
E10: =+E7-E8-E9 -> 627576.45 | F10: =+F7-F8-F9 -> 627574.9 | G10: =+E10-F10 -> 1.55
F12: 3331 | G12: 3321
E13: =SUM(F13:G13) -> 15154029 | F13: 12686222 | G13: 2467807.4
E14: =SUM(F14:G14) -> 13820290 | F14: =10998603.48+G8 -> 10998602 | G14: 2821687.6
E15: =SUM(F15:G15) -> 706162.94 | F15: =377232.25+G9 -> 377232.23 | G15: 328930.71
E16: =SUM(F16:G16) -> 627576.45 | F16: =+F13-F14-F15 -> 1310387.4 | G16: =+G13-G14-G15 -> -682810.92
E17: =+E16-E10 -> 9.3132257e-10

Sheet Sheet2
B2: ■ KSCI '26년 1월 가결산 실적 | H2: ■ KSCI 12월 결산 실적 | O2: ■ KSCI 11월 결산 실적 | V2: 10월
C3: 구분 | D3: FI (ZYFIR4170) | E3: CO (KE30) | F3: 차액 | I3: 구분 | J3: FI (ZYFIR4170) | K3: CO (KE30) | L3: 차액 | P3: 구분 | Q3: FI (ZYFIR4170) | R3: CO (KE30) | S3: 차액 | V3: 구분 | W3: FI (ZYFIR4170) | X3: CO (KE30) | Y3: 차액
C4: 매출액 | D4: 12501980 | E4: 12501980 | F4: 0 | I4: 매출액 | J4: 9843533.5 | K4: 9843533.5 | L4: 0 | P4: 매출액 | Q4: 14550564 | R4: 14550564 | S4: =+Q4-R4 -> 0 | V4: 매출액 | W4: 14238050 | X4: 14238050 | Y4: 0
