Workbook

Sheet Exchange Rate
B2: '2026년 사업계획 기준 환율
B3: 구 분 | D3: '26 사업계획 | E3: 비 고 | G3: 확정 | H3: 26.09.15
B4: 주요 통화 | C4: KRW/USD | D4: 1350 | E4: 홀딩스 배포 | G4: 1350 | H4: 1381.14 | I4: =G4/H4 -> 0.97745341
C5: KRW/CNY | D5: 195 | G5: 195 | H5: 194.798 | I5: =G5/H5 -> 1.001037
C6: KRW/EUR | D6: 1600 | G6: 1600 | H6: 1627.1 | I6: =G6/H6 -> 0.9833446
C7: MXN/USD | D7: 19 | G7: 19 | H7: 18.4248 | I7: =G7/H7 -> 1.0312188
C8: CNY/USD | D8: 6.9 | G8: 6.9 | H8: 7.12 | I8: =G8/H8 -> 0.96910112
B9: 세르비아 | C9: KRW/RSD | D9: 14 | E9: KSC 배포 | G9: 14 | H9: 13.9 | I9: =G9/H9 -> 1.0071942
C10: RSD/EUR | D10: 117 | G10: 117 | H10: 116.81 | I10: =G10/H10 -> 1.0016266
C11: RSD/USD | D11: 100 | G11: 100 | H11: 99.55 | I11: =G11/H11 -> 1.0045203
B12: 터키 | C12: KRW/TRY | D12: 32 | G12: 32 | H12: 33.55 | I12: =G12/H12 -> 0.9538003
C13: TRY/USD | D13: 43 | G13: 43 | H13: 41.37 | I13: =G13/H13 -> 1.0394005
C14: TRY/EUR | D14: 51 | G14: 51 | H14: 48.58 | I14: =G14/H14 -> 1.0498147
B15: 폴란드 | C15: KRW/PLN | D15: 385 | G15: 385 | H15: 383.45 | I15: =G15/H15 -> 1.0040422
C16: PLN/EUR | D16: 4.2 | G16: 4.2 | H16: 4.24 | I16: =G16/H16 -> 0.99056604
C17: PLN/USD | D17: 3.6 | G17: 3.6 | H17: 3.62 | I17: =G17/H17 -> 0.99447514
B18: ※ 동가 : 13,826[원/kg] / 9,900[$/Ton] - 6/1부 현대차 인정 동가 기준

Sheet Summary
F1: =+F21/F6 -> 0.76682497 | G1: =+G21/G6 -> 0.76611273 | H1: =+H21/H6 -> 0.76564981 | I1: =+I21/I6 -> 0.76475524 | J1: =+J21/J6 -> 0.76203145 | K1: =+K21/K6 -> 0.76557737 | L1: =+L21/L6 -> 0.7644828 | M1: =+M21/M6 -> 0.76573661 | ... Q1: =+Q21/Q6 -> 0.85913698
B2: Profit and Loss statement FY 2026 | Q2: (Affiliate Company: Kyungshin cable Türkiye)
B4: 구분 | D4: FY | E4: 12 | F4: 1 | G4: 2 | H4: =+G4+1 -> 3 | I4: =+H4+1 -> 4 | J4: =+I4+1 -> 5 | K4: =+J4+1 -> 6 | L4: =+K4+1 -> 7 | M4: =+L4+1 -> 8 | N4: =+M4+1 -> 9 | O4: =+N4+1 -> 10 | ... Q4: =+P4+1 -> 12
B5: Ⅰ. 매출액 | C5: Ⅰ. SALES | D5: =SUM(F5:Q5) -> 1.8562269e+09 | F5: =+F6+F14 -> 93531068 | G5: =+G6+G14 -> 1.1672241e+08 | H5: =+H6+H14 -> 1.6614614e+08 | I5: =+I6+I14 -> 1.385977e+08 | J5: =+J6+J14 -> 1.2682473e+08 | K5: =+K6+K14 -> 1.9324117e+08 | L5: =+L6+L14 -> 1.1829519e+08 | M5: =+M6+M14 -> 1.7613515e+08 | ... Q5: =+Q6+Q14 -> 1.6843153e+08
B6: 1.상품매출 | C6: 1. Merchandise | D6: =SUM(F6:Q6) -> 1.8546969e+09 | F6: =SUM(F7:F13) -> 93531068 | G6: =SUM(G7:G13) -> 1.1672241e+08 | H6: =SUM(H7:H13) -> 1.6614614e+08 | I6: =SUM(I7:I13) -> 1.385977e+08 | J6: =SUM(J7:J13) -> 1.2682473e+08 | K6: =SUM(K7:K13) -> 1.9324117e+08 | L6: =SUM(L7:L13) -> 1.1829519e+08 | M6: =SUM(M7:M13) -> 1.7613515e+08 | ... Q6: =SUM(Q7:Q13) -> 1.6690153e+08
C7: FORD PHEV-E (V710) | D7: =SUM(F7:Q7) -> 3.0822942e+08 | F7: ='1. Sales'!J242 -> 21737517 | G7: ='1. Sales'!K242 -> 23596647 | H7: ='1. Sales'!L242 -> 28172967 | I7: ='1. Sales'!M242 -> 20593438 | J7: ='1. Sales'!N242 -> 17018188 | K7: ='1. Sales'!O242 -> 35466476 | L7: ='1. Sales'!P242 -> 19592368 | M7: ='1. Sales'!Q242 -> 31891226 | ... Q7: ='1. Sales'!U242 -> 28158666
C8: FORD PHEV-E (P703) | D8: =SUM(F8:Q8) -> 1.6412277e+08 | F8: ='1. Sales'!J248 -> 11440799 | G8: ='1. Sales'!K248 -> 10236504 | H8: ='1. Sales'!L248 -> 12645093 | I8: ='1. Sales'!M248 -> 12645093 | J8: ='1. Sales'!N248 -> 13849388 | K8: ='1. Sales'!O248 -> 18666566 | L8: ='1. Sales'!P248 -> 13247241 | M8: ='1. Sales'!Q248 -> 13548314 | ... Q8: ='1. Sales'!U248 -> 14760136
C9: BEV-E RWD | D9: =SUM(F9:Q9) -> 6.1849335e+08 | F9: ='1. Sales'!J262 -> 39254495 | G9: ='1. Sales'!K262 -> 40331839 | H9: ='1. Sales'!L262 -> 77686291 | I9: ='1. Sales'!M262 -> 65698392 | J9: ='1. Sales'!N262 -> 52476443 | K9: ='1. Sales'!O262 -> 83131775 | L9: ='1. Sales'!P262 -> 50556812 | M9: ='1. Sales'!Q262 -> 79958508 | ... Q9: ='1. Sales'!U262 -> 0
C10: BEV-E AWD | D10: =SUM(F10:Q10) -> 1.4457127e+08 | F10: ='1. Sales'!J276 -> 1339959 | G10: ='1. Sales'!K276 -> 11503033 | H10: ='1. Sales'!L276 -> 20202459 | I10: ='1. Sales'!M276 -> 16141352 | J10: ='1. Sales'!N276 -> 12121475 | K10: ='1. Sales'!O276 -> 20697213 | L10: ='1. Sales'!P276 -> 11379344 | M10: ='1. Sales'!Q276 -> 19377868 | ... Q10: ='1. Sales'!U276 -> 0
C11: FORD BEV-M | D11: =SUM(F11:Q11) -> 3.1895775e+08 | F11: ='1. Sales'!J290 -> 18887593 | G11: ='1. Sales'!K290 -> 28331389 | H11: ='1. Sales'!L290 -> 26423506 | I11: ='1. Sales'!M290 -> 22648720 | J11: ='1. Sales'!N290 -> 30198293 | K11: ='1. Sales'!O290 -> 33973080 | L11: ='1. Sales'!P290 -> 22648720 | M11: ='1. Sales'!Q290 -> 30198293 | ... Q11: ='1. Sales'!U290 -> 27498272
C12: EV-V4 | D12: =SUM(F12:Q12) -> 2.8052389e+08 | F12: ='1. Sales'!J308 -> 0 | G12: ='1. Sales'!K308 -> 1378803.9 | H12: ='1. Sales'!L308 -> 0 | I12: ='1. Sales'!M308 -> 0 | J12: ='1. Sales'!N308 -> 0 | K12: ='1. Sales'!O308 -> 0 | L12: ='1. Sales'!P308 -> 0 | M12: ='1. Sales'!Q308 -> 0 | ... Q12: ='1. Sales'!U308 -> 93048362
C13: Components | D13: =SUM(F13:Q13) -> 19798467 | F13: ='1. Sales'!J294+'1. Sales'!J317 -> 870704.64 | G13: ='1. Sales'!K294+'1. Sales'!K317 -> 1344193.2 | H13: ='1. Sales'!L294+'1. Sales'!L317 -> 1015822.1 | I13: ='1. Sales'!M294+'1. Sales'!M317 -> 870704.64 | J13: ='1. Sales'!N294+'1. Sales'!N317 -> 1160939.5 | K13: ='1. Sales'!O294+'1. Sales'!O317 -> 1306057 | L13: ='1. Sales'!P294+'1. Sales'!P317 -> 870704.64 | M13: ='1. Sales'!Q294+'1. Sales'!Q317 -> 1160939.5 | ... Q13: ='1. Sales'!U294+'1. Sales'!U317 -> 3436099.1
B14: 2. 기타 매출 | C14: 2. Other sales | D14: =SUM(F14:Q14) -> 1530000 | F14: =SUM(F15:F18) -> 0 | G14: =SUM(G15:G18) -> 0 | H14: =SUM(H15:H18) -> 0 | I14: =SUM(I15:I18) -> 0 | J14: =SUM(J15:J18) -> 0 | K14: =SUM(K15:K18) -> 0 | L14: =SUM(L15:L18) -> 0 | M14: =SUM(M15:M18) -> 0 | ... Q14: =SUM(Q15:Q18) -> 1530000
B15: └ scrap | C15: └ Scrap | D15: =SUM(F15:Q15) -> 0
B16: └ Test Parts | C16: └ Test Parts | D16: =SUM(F16:Q16) -> 0
B17: └ 기타 | C17: └ Other | D17: =SUM(F17:Q17) -> 1530000 | Q17: =30000*'Exchange Rate'!D14 -> 1530000 | U17: 30000 | V17: BEV-H RESIDENCE Q.C Contract
B18: └ 기타(투자비) | C18: └ Investment | D18: =SUM(F18:Q18) -> 0
D19: =+D20/D5 -> 0.78991526 | F19: =IFERROR(F20/F5,"") -> 0.76682497 | G19: =IFERROR(G20/G5,"") -> 0.76611273 | H19: =IFERROR(H20/H5,"") -> 0.76564981 | I19: =IFERROR(I20/I5,"") -> 0.76475524 | J19: =IFERROR(J20/J5,"") -> 0.76203145 | K19: =IFERROR(K20/K5,"") -> 0.76557737 | L19: =IFERROR(L20/L5,"") -> 0.7644828 | M19: =IFERROR(M20/M5,"") -> 0.76573661 | ... Q19: =IFERROR(Q20/Q5,"") -> 0.85133274 | U19: EV-V4 10월 양산반영(수익율 2% 저하요인)
B20: Ⅱ. 매출원가 | C20: Ⅱ. COST OF SALES | D20: =SUM(F20:Q20) -> 1.466262e+09 | F20: =+F21+F27 -> 71721958 | G20: =+G21+G27 -> 89422523 | H20: =+H21+H27 -> 1.2720976e+08 | I20: =+I21+I27 -> 1.0599332e+08 | J20: =+J21+J27 -> 96644431 | K20: =+K21+K27 -> 1.4794106e+08 | L20: =+L21+L27 -> 90434637 | M20: =+M21+M27 -> 1.3487313e+08 | ... Q20: =+Q21+Q27 -> 1.4339128e+08
B21: 상품매출원가 | C21: Cost of merchandise sold | D21: =SUM(F21:Q21) -> 1.466262e+09 | F21: =+F22+F23+F24-F25-F26 -> 71721958 | G21: =+G22+G23+G24-G25-G26 -> 89422523 | H21: =+H22+H23+H24-H25-H26 -> 1.2720976e+08 | I21: =+I22+I23+I24-I25-I26 -> 1.0599332e+08 | J21: =+J22+J23+J24-J25-J26 -> 96644431 | K21: =+K22+K23+K24-K25-K26 -> 1.4794106e+08 | L21: =+L22+L23+L24-L25-L26 -> 90434637 | M21: =+M22+M23+M24-M25-M26 -> 1.3487313e+08 | ... Q21: =+Q22+Q23+Q24-Q25-Q26 -> 1.4339128e+08
B22: 1.기초 상품재고 | C22: 1. Beginning Merchandise | D22: =+F22 -> 0
B23: 2.당기 상품매입원가 | C23: 2. Cost of Merchandise | D23: =SUM(F23:Q23) -> 1.466262e+09 | F23: ='1. Sales'!J559 -> 71721958 | G23: ='1. Sales'!K559 -> 89422523 | H23: ='1. Sales'!L559 -> 1.2720976e+08 | I23: ='1. Sales'!M559 -> 1.0599332e+08 | J23: ='1. Sales'!N559 -> 96644431 | K23: ='1. Sales'!O559 -> 1.4794106e+08 | L23: ='1. Sales'!P559 -> 90434637 | M23: ='1. Sales'!Q559 -> 1.3487313e+08 | ... Q23: ='1. Sales'!U559 -> 1.4339128e+08
B24: 3.타계정전입 (+) | C24: 3. Transferred from other accounts | D24: =SUM(F24:Q24) -> 0
B25: 4.타계정대체 (-) | C25: 4. Transferred to other accounts | D25: =SUM(F25:Q25) -> 0
B26: 5.기말 상품재고 | C26: 5. Ending Merchandise | D26: =SUM(F26:Q26) -> 0
B27: 기타매출원가 | C27: Cost of other sold | D27: =SUM(F27:Q27) -> 0 | F27: =SUM(F28:F31) -> 0 | G27: =SUM(G28:G31) -> 0 | H27: =SUM(H28:H31) -> 0 | I27: =SUM(I28:I31) -> 0 | J27: =SUM(J28:J31) -> 0 | K27: =SUM(K28:K31) -> 0 | L27: =SUM(L28:L31) -> 0 | M27: =SUM(M28:M31) -> 0 | ... Q27: =SUM(Q28:Q31) -> 0
B28: 원재료 매출원가 | C28: Raw material | D28: =SUM(F28:Q28) -> 0
B29: 반제품 매출원가 | C29: Halb | D29: =SUM(F29:Q29) -> 0
B30: 기타 | C30: Other | D30: =SUM(F30:Q30) -> 0
B31: 기타(투자비) | C31: Investment | D31: =SUM(F31:Q31) -> 0
B32: Ⅲ. 매출총이익 | C32: Ⅲ. GROSS PROFIT (or GROSS LOSS) | D32: =SUM(F32:Q32) -> 3.8996495e+08 | F32: =+F5-F20 -> 21809110 | G32: =+G5-G20 -> 27299886 | H32: =+H5-H20 -> 38936379 | I32: =+I5-I20 -> 32604383 | J32: =+J5-J20 -> 30180296 | K32: =+K5-K20 -> 45300103 | L32: =+L5-L20 -> 27860551 | M32: =+M5-M20 -> 41262017 | ... Q32: =+Q5-Q20 -> 25040255
B33: (이익률) | C33: (Rate) | D33: =+IFERROR(D32/D5,) -> 0.21008474 | F33: =+IFERROR(F32/F5,) -> 0.23317503 | G33: =+IFERROR(G32/G5,) -> 0.23388727 | H33: =+IFERROR(H32/H5,) -> 0.23435019 | I33: =+IFERROR(I32/I5,) -> 0.23524476 | J33: =+IFERROR(J32/J5,) -> 0.23796855 | K33: =+IFERROR(K32/K5,) -> 0.23442263 | L33: =+IFERROR(L32/L5,) -> 0.2355172 | M33: =+IFERROR(M32/M5,) -> 0.23426339 | ... Q33: =+IFERROR(Q32/Q5,) -> 0.14866726
B34: Ⅳ.판매관리비 | C34: SELLING AND MARKETING EXPENSES | D34: =SUM(F34:Q34) -> 32457954 | E34: =E35+E36+E37+E38+E39+E40+E41 -> 0 | F34: =SUM(F35:F42) -> 1864869.9 | G34: =SUM(G35:G42) -> 2111319.2 | H34: =SUM(H35:H42) -> 2624130.2 | I34: =SUM(I35:I42) -> 2295347.5 | J34: =SUM(J35:J42) -> 4211534.9 | K34: =SUM(K35:K42) -> 2905578.6 | L34: =SUM(L35:L42) -> 2097975.2 | M34: =SUM(M35:M42) -> 2807689.8 | ... Q34: =SUM(Q35:Q42) -> 2745091.2
C35: Export Expenses | D35: =SUM(F35:Q35) -> 1628307.2 | F35: =+'26 Detail'!B3 -> 95782.779 | G35: =+'26 Detail'!C3 -> 95782.779 | H35: =+'26 Detail'!D3 -> 95782.779 | I35: =+'26 Detail'!E3 -> 95782.779 | J35: =+'26 Detail'!F3 -> 95782.779 | K35: =+'26 Detail'!G3 -> 95782.779 | L35: =+'26 Detail'!H3 -> 95782.779 | M35: =+'26 Detail'!I3 -> 191565.56 | ... Q35: =+'26 Detail'!M3 -> 191565.56
C36: Import Expenses | D36: =SUM(F36:Q36) -> 334367.46 | F36: =+'26 Detail'!B11 -> 20897.966 | G36: =+'26 Detail'!C11 -> 20897.966 | H36: =+'26 Detail'!D11 -> 20897.966 | I36: =+'26 Detail'!E11 -> 20897.966 | J36: =+'26 Detail'!F11 -> 20897.966 | K36: =+'26 Detail'!G11 -> 20897.966 | L36: =+'26 Detail'!H11 -> 20897.966 | M36: =+'26 Detail'!I11 -> 20897.966 | ... Q36: =+'26 Detail'!M11 -> 41795.933
C37: Domestic Transportation Expenses | D37: =SUM(F37:Q37) -> 6658033.8 | F37: =+'26 Detail'!B20 -> 554836.15 | G37: =+'26 Detail'!C20 -> 554836.15 | H37: =+'26 Detail'!D20 -> 554836.15 | I37: =+'26 Detail'!E20 -> 554836.15 | J37: =+'26 Detail'!F20 -> 554836.15 | K37: =+'26 Detail'!G20 -> 554836.15 | L37: =+'26 Detail'!H20 -> 554836.15 | M37: =+'26 Detail'!I20 -> 554836.15 | ... Q37: =+'26 Detail'!M20 -> 554836.15
C38: Sales Return costs | D38: =SUM(F38:Q38) -> 0
C39: Product Sample Expenses | D39: =SUM(F39:Q39) -> 496289.82 | F39: =+'26 Detail'!B27 -> 41357.485 | G39: =+'26 Detail'!C27 -> 41357.485 | H39: =+'26 Detail'!D27 -> 41357.485 | I39: =+'26 Detail'!E27 -> 41357.485 | J39: =+'26 Detail'!F27 -> 41357.485 | K39: =+'26 Detail'!G27 -> 41357.485 | L39: =+'26 Detail'!H27 -> 41357.485 | M39: =+'26 Detail'!I27 -> 41357.485 | ... Q39: =+'26 Detail'!M27 -> 41357.485
C40: Rental Expenses(Boxes) | D40: =SUM(F40:Q40) -> 1457627.6 | F40: =+'26 Detail'!B32 -> 106596.59 | G40: =+'26 Detail'!C32 -> 121132.49 | H40: =+'26 Detail'!D32 -> 139706.13 | I40: =+'26 Detail'!E32 -> 86407.841 | J40: =+'26 Detail'!F32 -> 120324.94 | K40: =+'26 Detail'!G32 -> 150204.28 | L40: =+'26 Detail'!H32 -> 92060.69 | M40: =+'26 Detail'!I32 -> 127592.89 | ... Q40: =+'26 Detail'!M32 -> 121132.49
C41: Other Expenses | D41: =SUM(F41:Q41) -> 3321059.4 | F41: =+'26 Detail'!B35 -> 110088.28 | G41: =+'26 Detail'!C35 -> 110088.28 | H41: =+'26 Detail'!D35 -> 110088.28 | I41: =+'26 Detail'!E35 -> 110088.28 | J41: =+'26 Detail'!F35 -> 2110088.3 | K41: =+'26 Detail'!G35 -> 110088.28 | L41: =+'26 Detail'!H35 -> 110088.28 | M41: =+'26 Detail'!I35 -> 110088.28 | ... Q41: =+'26 Detail'!M35 -> 110088.28
C42: Sorting&Rework Expenses | D42: =SUM(F42:Q42) -> 18562269 | F42: ='26 Detail'!B41 -> 935310.68 | G42: ='26 Detail'!C41 -> 1167224.1 | H42: ='26 Detail'!D41 -> 1661461.4 | I42: ='26 Detail'!E41 -> 1385977 | J42: ='26 Detail'!F41 -> 1268247.3 | K42: ='26 Detail'!G41 -> 1932411.7 | L42: ='26 Detail'!H41 -> 1182951.9 | M42: ='26 Detail'!I41 -> 1761351.5 | ... Q42: ='26 Detail'!M41 -> 1684315.3
B43: Ⅳ.판매관리비 | C43: GENERAL ADMINISTRATION EXPENSES | D43: =SUM(F43:Q43) -> 1.5749754e+08 | E43: =E44+E45+E46+E47+E48+E49+E50 -> 0 | F43: =SUM(F44:F68) -> 9082306.6 | G43: =SUM(G44:G68) -> 10967150 | H43: =SUM(H44:H68) -> 12578191 | I43: =SUM(I44:I68) -> 13145494 | J43: =SUM(J44:J68) -> 11083466 | K43: =SUM(K44:K68) -> 16371539 | L43: =SUM(L44:L68) -> 11408051 | M43: =SUM(M44:M68) -> 13913303 | ... Q43: =SUM(Q44:Q68) -> 16584257
C44: Executive Expenses | D44: =SUM(F44:Q44) -> 23327078 | F44: =+'26 Detail'!B45 -> 1197719.5 | G44: =+'26 Detail'!C45 -> 1770719.5 | H44: =+'26 Detail'!D45 -> 1197719.5 | I44: =+'26 Detail'!E45 -> 2997719.5 | J44: =+'26 Detail'!F45 -> 1197719.5 | K44: =+'26 Detail'!G45 -> 4077719.5 | L44: =+'26 Detail'!H45 -> 1865901.2 | M44: =+'26 Detail'!I45 -> 1994901.2 | ... Q44: =+'26 Detail'!M45 -> 1667101.2
C45: Financial & General Affairs Expenses | D45: =SUM(F45:Q45) -> 16492194 | F45: =+'26 Detail'!B53 -> 1051454.6 | G45: =+'26 Detail'!C53 -> 1382690.4 | H45: =+'26 Detail'!D53 -> 1492505.2 | I45: =+'26 Detail'!E53 -> 1414130.3 | J45: =+'26 Detail'!F53 -> 1405056.4 | K45: =+'26 Detail'!G53 -> 1374505.2 | L45: =+'26 Detail'!H53 -> 1382095.2 | M45: =+'26 Detail'!I53 -> 1402636.1 | ... Q45: =+'26 Detail'!M53 -> 1410390.2
C46: Manufacturing Personel Expenses | D46: =SUM(F46:Q46) -> 17485495 | F46: =+'26 Detail'!B62 -> 1119618.6 | G46: =+'26 Detail'!C62 -> 1351355.5 | H46: =+'26 Detail'!D62 -> 1403919.9 | I46: =+'26 Detail'!E62 -> 1367310.6 | J46: =+'26 Detail'!F62 -> 1385161.2 | K46: =+'26 Detail'!G62 -> 1331919.9 | L46: =+'26 Detail'!H62 -> 1595132.6 | M46: =+'26 Detail'!I62 -> 1588780 | ... Q46: =+'26 Detail'!M62 -> 1547819.9
C47: Executive Rental Expenses | D47: =SUM(F47:Q47) -> 1129000 | F47: =+'26 Detail'!B72 -> 76750 | G47: =+'26 Detail'!C72 -> 76750 | H47: =+'26 Detail'!D72 -> 76750 | I47: =+'26 Detail'!E72 -> 76750 | J47: =+'26 Detail'!F72 -> 102750 | K47: =+'26 Detail'!G72 -> 102750 | L47: =+'26 Detail'!H72 -> 102750 | M47: =+'26 Detail'!I72 -> 102750 | ... Q47: =+'26 Detail'!M72 -> 102750
C48: Financial & General Affairs Rental Expenses | D48: =SUM(F48:Q48) -> 0 | F48: =+'26 Detail'!B77 -> 0 | G48: =+'26 Detail'!C77 -> 0 | H48: =+'26 Detail'!D77 -> 0 | I48: =+'26 Detail'!E77 -> 0 | J48: =+'26 Detail'!F77 -> 0 | K48: =+'26 Detail'!G77 -> 0 | L48: =+'26 Detail'!H77 -> 0 | M48: =+'26 Detail'!I77 -> 0 | ... Q48: =+'26 Detail'!M77 -> 0
C49: Manufacturing Personnel Department Rental Expenses | D49: =SUM(F49:Q49) -> 360000 | F49: =+'26 Detail'!B82 -> 30000 | G49: =+'26 Detail'!C82 -> 30000 | H49: =+'26 Detail'!D82 -> 30000 | I49: =+'26 Detail'!E82 -> 30000 | J49: =+'26 Detail'!F82 -> 30000 | K49: =+'26 Detail'!G82 -> 30000 | L49: =+'26 Detail'!H82 -> 30000 | M49: =+'26 Detail'!I82 -> 30000 | ... Q49: =+'26 Detail'!M82 -> 30000
C50: Other Rental Expenses | D50: =SUM(F50:Q50) -> 6258000 | F50: =+'26 Detail'!B87 -> 521500 | G50: =+'26 Detail'!C87 -> 521500 | H50: =+'26 Detail'!D87 -> 521500 | I50: =+'26 Detail'!E87 -> 521500 | J50: =+'26 Detail'!F87 -> 521500 | K50: =+'26 Detail'!G87 -> 521500 | L50: =+'26 Detail'!H87 -> 521500 | M50: =+'26 Detail'!I87 -> 521500 | ... Q50: =+'26 Detail'!M87 -> 521500
C51: Travel Expenses | D51: =SUM(F51:Q51) -> 7174380 | F51: =+'26 Detail'!B93 -> 362260.83 | G51: =+'26 Detail'!C93 -> 362260.83 | H51: =+'26 Detail'!D93 -> 362260.83 | I51: =+'26 Detail'!E93 -> 362260.83 | J51: =+'26 Detail'!F93 -> 362260.83 | K51: =+'26 Detail'!G93 -> 362260.83 | L51: =+'26 Detail'!H93 -> 362260.83 | M51: =+'26 Detail'!I93 -> 362260.83 | ... Q51: =+'26 Detail'!M93 -> 3189510.8
C52: Entertainment Expenses | D52: =SUM(F52:Q52) -> 1260000 | F52: =+'26 Detail'!B102 -> 105000 | G52: =+'26 Detail'!C102 -> 105000 | H52: =+'26 Detail'!D102 -> 105000 | I52: =+'26 Detail'!E102 -> 105000 | J52: =+'26 Detail'!F102 -> 105000 | K52: =+'26 Detail'!G102 -> 105000 | L52: =+'26 Detail'!H102 -> 105000 | M52: =+'26 Detail'!I102 -> 105000 | ... Q52: =+'26 Detail'!M102 -> 105000
C53: Insurance Expenses | D53: =SUM(F53:Q53) -> 0 | F53: =+'26 Detail'!B106 -> 0 | G53: =+'26 Detail'!C106 -> 0 | H53: =+'26 Detail'!D106 -> 0 | I53: =+'26 Detail'!E106 -> 0 | J53: =+'26 Detail'!F106 -> 0 | K53: =+'26 Detail'!G106 -> 0 | L53: =+'26 Detail'!H106 -> 0 | M53: =+'26 Detail'!I106 -> 0 | ... Q53: =+'26 Detail'!M106 -> 0
C54: Outsourse Benefits&Services | D54: =SUM(F54:Q54) -> 275137.2 | F54: =+'26 Detail'!B111 -> 22928.1 | G54: =+'26 Detail'!C111 -> 22928.1 | H54: =+'26 Detail'!D111 -> 22928.1 | I54: =+'26 Detail'!E111 -> 22928.1 | J54: =+'26 Detail'!F111 -> 22928.1 | K54: =+'26 Detail'!G111 -> 22928.1 | L54: =+'26 Detail'!H111 -> 22928.1 | M54: =+'26 Detail'!I111 -> 22928.1 | ... Q54: =+'26 Detail'!M111 -> 22928.1
C55: Office Supplies | D55: =SUM(F55:Q55) -> 554000 | F55: =+'26 Detail'!B115 -> 48000 | G55: =+'26 Detail'!C115 -> 46000 | H55: =+'26 Detail'!D115 -> 46000 | I55: =+'26 Detail'!E115 -> 46000 | J55: =+'26 Detail'!F115 -> 46000 | K55: =+'26 Detail'!G115 -> 46000 | L55: =+'26 Detail'!H115 -> 46000 | M55: =+'26 Detail'!I115 -> 46000 | ... Q55: =+'26 Detail'!M115 -> 46000
C56: Executive Vehicle Expenses | D56: =SUM(F56:Q56) -> 633000 | F56: =+'26 Detail'!B123 -> 51500 | G56: =+'26 Detail'!C123 -> 51500 | H56: =+'26 Detail'!D123 -> 66500 | I56: =+'26 Detail'!E123 -> 51500 | J56: =+'26 Detail'!F123 -> 51500 | K56: =+'26 Detail'!G123 -> 51500 | L56: =+'26 Detail'!H123 -> 51500 | M56: =+'26 Detail'!I123 -> 51500 | ... Q56: =+'26 Detail'!M123 -> 51500
C57: Financial & General Affairs Personnel Vehicle Expenses | D57: =SUM(F57:Q57) -> 0 | F57: =+'26 Detail'!B132 -> 0 | G57: =+'26 Detail'!C132 -> 0 | H57: =+'26 Detail'!D132 -> 0 | I57: =+'26 Detail'!E132 -> 0 | J57: =+'26 Detail'!F132 -> 0 | K57: =+'26 Detail'!G132 -> 0 | L57: =+'26 Detail'!H132 -> 0 | M57: =+'26 Detail'!I132 -> 0 | ... Q57: =+'26 Detail'!M132 -> 0
C58: Manufacturing Personnel Vehicle Expenses | D58: =SUM(F58:Q58) -> 71000 | F58: =+'26 Detail'!B141 -> 5500 | G58: =+'26 Detail'!C141 -> 5500 | H58: =+'26 Detail'!D141 -> 10500 | I58: =+'26 Detail'!E141 -> 5500 | J58: =+'26 Detail'!F141 -> 5500 | K58: =+'26 Detail'!G141 -> 5500 | L58: =+'26 Detail'!H141 -> 5500 | M58: =+'26 Detail'!I141 -> 5500 | ... Q58: =+'26 Detail'!M141 -> 5500
C59: Other Taxes | D59: =SUM(F59:Q59) -> 230258.73 | F59: =+'26 Detail'!B150 -> 13544.631 | G59: =+'26 Detail'!C150 -> 13544.631 | H59: =+'26 Detail'!D150 -> 13544.631 | I59: =+'26 Detail'!E150 -> 13544.631 | J59: =+'26 Detail'!F150 -> 13544.631 | K59: =+'26 Detail'!G150 -> 13544.631 | L59: =+'26 Detail'!H150 -> 13544.631 | M59: =+'26 Detail'!I150 -> 27089.262 | ... Q59: =+'26 Detail'!M150 -> 27089.262
C60: Commissions | D60: =SUM(F60:Q60) -> 928113.46 | F60: =+'26 Detail'!B157 -> 46765.534 | G60: =+'26 Detail'!C157 -> 58361.205 | H60: =+'26 Detail'!D157 -> 83073.069 | I60: =+'26 Detail'!E157 -> 69298.849 | J60: =+'26 Detail'!F157 -> 63412.363 | K60: =+'26 Detail'!G157 -> 96620.583 | L60: =+'26 Detail'!H157 -> 59147.594 | M60: =+'26 Detail'!I157 -> 88067.574 | ... Q60: =+'26 Detail'!M157 -> 84215.767
C61: Service Expenses | D61: =SUM(F61:Q61) -> 4716753.5 | F61: =+'26 Detail'!B161 -> 520351.07 | G61: =+'26 Detail'!C161 -> 331972.67 | H61: =+'26 Detail'!D161 -> 331972.67 | I61: =+'26 Detail'!E161 -> 337972.67 | J61: =+'26 Detail'!F161 -> 529972.67 | K61: =+'26 Detail'!G161 -> 331972.67 | L61: =+'26 Detail'!H161 -> 344812.67 | M61: =+'26 Detail'!I161 -> 338812.67 | ... Q61: =+'26 Detail'!M161 -> 555519.12
C62: Communication Expenses | D62: =SUM(F62:Q62) -> 309341.64 | F62: =+'26 Detail'!B170 -> 25778.47 | G62: =+'26 Detail'!C170 -> 25778.47 | H62: =+'26 Detail'!D170 -> 25778.47 | I62: =+'26 Detail'!E170 -> 25778.47 | J62: =+'26 Detail'!F170 -> 25778.47 | K62: =+'26 Detail'!G170 -> 25778.47 | L62: =+'26 Detail'!H170 -> 25778.47 | M62: =+'26 Detail'!I170 -> 25778.47 | ... Q62: =+'26 Detail'!M170 -> 25778.47
C63: Repairing Expenses | D63: =SUM(F63:Q63) -> 36000 | F63: =+'26 Detail'!B176 -> 0 | G63: =+'26 Detail'!C176 -> 0 | H63: =+'26 Detail'!D176 -> 0 | I63: =+'26 Detail'!E176 -> 12000 | J63: =+'26 Detail'!F176 -> 0 | K63: =+'26 Detail'!G176 -> 0 | L63: =+'26 Detail'!H176 -> 0 | M63: =+'26 Detail'!I176 -> 12000 | ... Q63: =+'26 Detail'!M176 -> 12000
C64: Training Expenses | D64: =SUM(F64:Q64) -> 660000 | F64: =+'26 Detail'!B180 -> 30000 | G64: =+'26 Detail'!C180 -> 30000 | H64: =+'26 Detail'!D180 -> 30000 | I64: =+'26 Detail'!E180 -> 30000 | J64: =+'26 Detail'!F180 -> 30000 | K64: =+'26 Detail'!G180 -> 30000 | L64: =+'26 Detail'!H180 -> 30000 | M64: =+'26 Detail'!I180 -> 30000 | ... Q64: =+'26 Detail'!M180 -> 330000
C65: Miscellaneous Expenses | D65: =SUM(F65:Q65) -> 96000 | F65: =+'26 Detail'!B184 -> 8000 | G65: =+'26 Detail'!C184 -> 8000 | H65: =+'26 Detail'!D184 -> 8000 | I65: =+'26 Detail'!E184 -> 8000 | J65: =+'26 Detail'!F184 -> 8000 | K65: =+'26 Detail'!G184 -> 8000 | L65: =+'26 Detail'!H184 -> 8000 | M65: =+'26 Detail'!I184 -> 8000 | ... Q65: =+'26 Detail'!M184 -> 8000
C66: Depreciation and Amortization Expenses | D66: =SUM(F66:Q66) -> 1252710.6 | F66: ='26 Detail'!B190 -> 104392.55 | G66: ='26 Detail'!C190 -> 104392.55 | H66: ='26 Detail'!D190 -> 104392.55 | I66: ='26 Detail'!E190 -> 104392.55 | J66: ='26 Detail'!F190 -> 104392.55 | K66: ='26 Detail'!G190 -> 104392.55 | L66: ='26 Detail'!H190 -> 104392.55 | M66: ='26 Detail'!I190 -> 104392.55 | ... Q66: ='26 Detail'!M190 -> 104392.55
C67: Depreciation and Amortization Expenses | T67: ← 연말 재무재표 매칭
C68: Communication Expenses(Royalty) | D68: =SUM(F68:Q68) -> 74249076 | F68: =IFERROR(F5*4%,"") -> 3741242.7 | G68: =IFERROR(G5*4%,"") -> 4668896.4 | H68: =IFERROR(H5*4%,"") -> 6645845.5 | I68: =IFERROR(I5*4%,"") -> 5543908 | J68: =IFERROR(J5*4%,"") -> 5072989.1 | K68: =IFERROR(K5*4%,"") -> 7729646.7 | L68: =IFERROR(L5*4%,"") -> 4731807.6 | M68: =IFERROR(M5*4%,"") -> 7045406 | ... Q68: =IFERROR(Q5*4%,"") -> 6737261.4 | T68: ← 반기별 재무재표 매칭
F69: =IFERROR(SUM(F43,F34)/F5,"") -> 0.11704321 | G69: =IFERROR(SUM(G43,G34)/G5,"") -> 0.11204763 | H69: =IFERROR(SUM(H43,H34)/H5,"") -> 0.091499693 | I69: =IFERROR(SUM(I43,I34)/I5,"") -> 0.11140764 | J69: =IFERROR(SUM(J43,J34)/J5,"") -> 0.12059952 | K69: =IFERROR(SUM(K43,K34)/K5,"") -> 0.099756787 | L69: =IFERROR(SUM(L43,L34)/L5,"") -> 0.11417224 | M69: =IFERROR(SUM(M43,M34)/M5,"") -> 0.094932742 | ... Q69: =IFERROR(SUM(Q43,Q34)/Q5,"") -> 0.11476086
B70: Ⅴ.영업이익 | C70: Ⅴ.OPERATING INCOME (or LOSS) | D70: =SUM(F70:Q70) -> 2.0000945e+08 | F70: =+F32-F43-F34 -> 10861933 | G70: =+G32-G43-G34 -> 14221416 | H70: =+H32-H43-H34 -> 23734058 | I70: =+I32-I43-I34 -> 17163541 | J70: =+J32-J43-J34 -> 14885295 | K70: =+K32-K43-K34 -> 26022986 | L70: =+L32-L43-L34 -> 14354525 | M70: =+M32-M43-M34 -> 24541025 | ... Q70: =+Q32-Q43-Q34 -> 5710906.5
B71: (이익률) | C71: (Rate) | D71: =+IFERROR(D70/D5,) -> 0.10775054 | F71: =+IFERROR(F70/F5,) -> 0.11613182 | G71: =+IFERROR(G70/G5,) -> 0.12183964 | H71: =+IFERROR(H70/H5,) -> 0.14285049 | I71: =+IFERROR(I70/I5,) -> 0.12383713 | J71: =+IFERROR(J70/J5,) -> 0.11736903 | K71: =+IFERROR(K70/K5,) -> 0.13466585 | L71: =+IFERROR(L70/L5,) -> 0.12134496 | M71: =+IFERROR(M70/M5,) -> 0.13933065 | ... Q71: =+IFERROR(Q70/Q5,) -> 0.033906397
B72: Ⅵ.영업외수익 | C72: Ⅵ. NON-OPERATING INCOME | D72: =SUM(F72:Q72) -> 21926388 | F72: =SUM(F73:F83) -> 1104821 | G72: =SUM(G73:G83) -> 1378765.1 | H72: =SUM(H73:H83) -> 1962575.1 | I72: =SUM(I73:I83) -> 1637163.5 | J72: =SUM(J73:J83) -> 1498097.1 | K72: =SUM(K73:K83) -> 2282630.9 | L72: =SUM(L73:L83) -> 1397343.3 | M72: =SUM(M73:M83) -> 2080568.7 | ... Q72: =SUM(Q73:Q83) -> 1989571
C73: Interest Income | D73: =SUM(F73:Q73) -> 21926388 | F73: ='26 Detail'!B201 -> 1104821 | G73: ='26 Detail'!C201 -> 1378765.1 | H73: ='26 Detail'!D201 -> 1962575.1 | I73: ='26 Detail'!E201 -> 1637163.5 | J73: ='26 Detail'!F201 -> 1498097.1 | K73: ='26 Detail'!G201 -> 2282630.9 | L73: ='26 Detail'!H201 -> 1397343.3 | M73: ='26 Detail'!I201 -> 2080568.7 | ... Q73: ='26 Detail'!M201 -> 1989571
C74: Commission Income | D74: =SUM(F74:Q74) -> 0 | F74: ='26 Detail'!B202 -> 0 | G74: ='26 Detail'!C202 -> 0 | H74: ='26 Detail'!D202 -> 0 | I74: ='26 Detail'!E202 -> 0 | J74: ='26 Detail'!F202 -> 0 | K74: ='26 Detail'!G202 -> 0 | L74: ='26 Detail'!H202 -> 0 | M74: ='26 Detail'!I202 -> 0 | ... Q74: ='26 Detail'!M202 -> 0
C75: Non-Relevant Provisions | D75: =SUM(F75:Q75) -> 0 | F75: ='26 Detail'!B203 -> 0 | G75: ='26 Detail'!C203 -> 0 | H75: ='26 Detail'!D203 -> 0 | I75: ='26 Detail'!E203 -> 0 | J75: ='26 Detail'!F203 -> 0 | K75: ='26 Detail'!G203 -> 0 | L75: ='26 Detail'!H203 -> 0 | M75: ='26 Detail'!I203 -> 0 | ... Q75: ='26 Detail'!M203 -> 0
C76: Exchange Profits | D76: =SUM(F76:Q76) -> 0 | F76: ='26 Detail'!B204 -> 0 | G76: ='26 Detail'!C204 -> 0 | H76: ='26 Detail'!D204 -> 0 | I76: ='26 Detail'!E204 -> 0 | J76: ='26 Detail'!F204 -> 0 | K76: ='26 Detail'!G204 -> 0 | L76: ='26 Detail'!H204 -> 0 | M76: ='26 Detail'!I204 -> 0 | ... Q76: ='26 Detail'!M204 -> 0
C77: Foreign Currency Transactions Profit | D77: =SUM(F77:Q77) -> 0 | F77: ='26 Detail'!B205 -> 0 | G77: ='26 Detail'!C205 -> 0 | H77: ='26 Detail'!D205 -> 0 | I77: ='26 Detail'!E205 -> 0 | J77: ='26 Detail'!F205 -> 0 | K77: ='26 Detail'!G205 -> 0 | L77: ='26 Detail'!H205 -> 0 | M77: ='26 Detail'!I205 -> 0 | ... Q77: ='26 Detail'!M205 -> 0
C78: Foreign Currency Translation of Profit | D78: =SUM(F78:Q78) -> 0 | F78: ='26 Detail'!B206 -> 0 | G78: ='26 Detail'!C206 -> 0 | H78: ='26 Detail'!D206 -> 0 | I78: ='26 Detail'!E206 -> 0 | J78: ='26 Detail'!F206 -> 0 | K78: ='26 Detail'!G206 -> 0 | L78: ='26 Detail'!H206 -> 0 | M78: ='26 Detail'!I206 -> 0 | ... Q78: ='26 Detail'!M206 -> 0
C79: Translation of Foreign Currency Profit | D79: =SUM(F79:Q79) -> 0 | F79: ='26 Detail'!B207 -> 0 | G79: ='26 Detail'!C207 -> 0 | H79: ='26 Detail'!D207 -> 0 | I79: ='26 Detail'!E207 -> 0 | J79: ='26 Detail'!F207 -> 0 | K79: ='26 Detail'!G207 -> 0 | L79: ='26 Detail'!H207 -> 0 | M79: ='26 Detail'!I207 -> 0 | ... Q79: ='26 Detail'!M207 -> 0
C80: Translation of Foreign Currency Profit | D80: =SUM(F80:Q80) -> 0 | F80: ='26 Detail'!B208 -> 0 | G80: ='26 Detail'!C208 -> 0 | H80: ='26 Detail'!D208 -> 0 | I80: ='26 Detail'!E208 -> 0 | J80: ='26 Detail'!F208 -> 0 | K80: ='26 Detail'!G208 -> 0 | L80: ='26 Detail'!H208 -> 0 | M80: ='26 Detail'!I208 -> 0 | ... Q80: ='26 Detail'!M208 -> 0
C81: Rediscount Interest Income | D81: =SUM(F81:Q81) -> 0 | F81: ='26 Detail'!B209 -> 0 | G81: ='26 Detail'!C209 -> 0 | H81: ='26 Detail'!D209 -> 0 | I81: ='26 Detail'!E209 -> 0 | J81: ='26 Detail'!F209 -> 0 | K81: ='26 Detail'!G209 -> 0 | L81: ='26 Detail'!H209 -> 0 | M81: ='26 Detail'!I209 -> 0 | ... Q81: ='26 Detail'!M209 -> 0
C82: Other Ordinary Income and Profits | D82: =SUM(F82:K82) -> 0 | F82: ='26 Detail'!B210 -> 0 | G82: ='26 Detail'!C210 -> 0 | H82: ='26 Detail'!D210 -> 0 | I82: ='26 Detail'!E210 -> 0 | J82: ='26 Detail'!F210 -> 0 | K82: ='26 Detail'!G210 -> 0 | L82: ='26 Detail'!H210 -> 0 | M82: ='26 Detail'!I210 -> 0 | ... Q82: ='26 Detail'!M210 -> 0
C83: OTHER EXTRAORDINARY INCOME AND PROFITS | D83: =SUM(F83:Q83) -> 0 | F83: ='26 Detail'!B211 -> 0 | G83: ='26 Detail'!C211 -> 0 | H83: ='26 Detail'!D211 -> 0 | I83: ='26 Detail'!E211 -> 0 | J83: ='26 Detail'!F211 -> 0 | K83: ='26 Detail'!G211 -> 0 | L83: ='26 Detail'!H211 -> 0 | M83: ='26 Detail'!I211 -> 0 | ... Q83: ='26 Detail'!M211 -> 0
B84: Ⅶ. 영업외비용 | C84: Ⅶ. NON-OPERATING EXPENSES | D84: =SUM(F84:Q84) -> 59299038 | F84: =SUM(F85:F97) -> 1870621.4 | G84: =SUM(G85:G97) -> 2334448.2 | H84: =SUM(H85:H97) -> 8362922.8 | I84: =SUM(I85:I97) -> 2771954 | J84: =SUM(J85:J97) -> 2536494.5 | K84: =SUM(K85:K97) -> 8934823.3 | L84: =SUM(L85:L97) -> 2365903.8 | M84: =SUM(M85:M97) -> 3522703 | ... Q84: =SUM(Q85:Q97) -> 7298630.7
C85: Interest Expenses (-) | D85: =SUM(F85:Q85) -> 3934500 | F85: ='26 Detail'!B215 -> 0 | G85: ='26 Detail'!C215 -> 0 | H85: ='26 Detail'!D215 -> 0 | I85: ='26 Detail'!E215 -> 0 | J85: ='26 Detail'!F215 -> 0 | K85: ='26 Detail'!G215 -> 0 | L85: ='26 Detail'!H215 -> 0 | M85: ='26 Detail'!I215 -> 0 | ... Q85: ='26 Detail'!M215 -> 0
C86: Commission Expenses(-) | D86: =SUM(F86:Q86) -> 0 | F86: ='26 Detail'!B216 -> 0 | G86: ='26 Detail'!C216 -> 0 | H86: ='26 Detail'!D216 -> 0 | I86: ='26 Detail'!E216 -> 0 | J86: ='26 Detail'!F216 -> 0 | K86: ='26 Detail'!G216 -> 0 | L86: ='26 Detail'!H216 -> 0 | M86: ='26 Detail'!I216 -> 0 | ... Q86: ='26 Detail'!M216 -> 0
C87: Provision Expenses(-) | D87: =SUM(F87:Q87) -> 0 | F87: ='26 Detail'!B217 -> 0 | G87: ='26 Detail'!C217 -> 0 | H87: ='26 Detail'!D217 -> 0 | I87: ='26 Detail'!E217 -> 0 | J87: ='26 Detail'!F217 -> 0 | K87: ='26 Detail'!G217 -> 0 | L87: ='26 Detail'!H217 -> 0 | M87: ='26 Detail'!I217 -> 0 | ... Q87: ='26 Detail'!M217 -> 0
C88: Losses on Sale of Securities(-) | D88: =SUM(F88:Q88) -> 0 | F88: ='26 Detail'!B218 -> 0 | G88: ='26 Detail'!C218 -> 0 | H88: ='26 Detail'!D218 -> 0 | I88: ='26 Detail'!E218 -> 0 | J88: ='26 Detail'!F218 -> 0 | K88: ='26 Detail'!G218 -> 0 | L88: ='26 Detail'!H218 -> 0 | M88: ='26 Detail'!I218 -> 0 | ... Q88: ='26 Detail'!M218 -> 0
C89: Exchange Losses(-) | D89: =SUM(F89:Q89) -> 0 | F89: ='26 Detail'!B219 -> 0 | G89: ='26 Detail'!C219 -> 0 | H89: ='26 Detail'!D219 -> 0 | I89: ='26 Detail'!E219 -> 0 | J89: ='26 Detail'!F219 -> 0 | K89: ='26 Detail'!G219 -> 0 | L89: ='26 Detail'!H219 -> 0 | M89: ='26 Detail'!I219 -> 0 | ... Q89: ='26 Detail'!M219 -> 0
C90: Foreign Currency Transactions Losses | D90: =SUM(F90:Q90) -> 37124538 | F90: ='26 Detail'!B220 -> 1870621.4 | G90: ='26 Detail'!C220 -> 2334448.2 | H90: ='26 Detail'!D220 -> 3322922.8 | I90: ='26 Detail'!E220 -> 2771954 | J90: ='26 Detail'!F220 -> 2536494.5 | K90: ='26 Detail'!G220 -> 3864823.3 | L90: ='26 Detail'!H220 -> 2365903.8 | M90: ='26 Detail'!I220 -> 3522703 | ... Q90: ='26 Detail'!M220 -> 3368630.7
C91: Foreign Currency Translation of Losses | D91: =SUM(F91:Q91) -> 18240000 | F91: ='26 Detail'!B221 -> 0 | G91: ='26 Detail'!C221 -> 0 | H91: ='26 Detail'!D221 -> 5040000 | I91: ='26 Detail'!E221 -> 0 | J91: ='26 Detail'!F221 -> 0 | K91: ='26 Detail'!G221 -> 5070000 | L91: ='26 Detail'!H221 -> 0 | M91: ='26 Detail'!I221 -> 0 | ... Q91: ='26 Detail'!M221 -> 3930000
C92: Rediscount Interest Expenses(-) | D92: =SUM(F92:Q92) -> 0 | F92: ='26 Detail'!B222 -> 0 | G92: ='26 Detail'!C222 -> 0 | H92: ='26 Detail'!D222 -> 0 | I92: ='26 Detail'!E222 -> 0 | J92: ='26 Detail'!F222 -> 0 | K92: ='26 Detail'!G222 -> 0 | L92: ='26 Detail'!H222 -> 0 | M92: ='26 Detail'!I222 -> 0 | ... Q92: ='26 Detail'!M222 -> 0
C93: Other Ordinary Expenses and Losses(-) | D93: =SUM(F93:K93) -> 0 | F93: ='26 Detail'!B223 -> 0 | G93: ='26 Detail'!C223 -> 0 | H93: ='26 Detail'!D223 -> 0 | I93: ='26 Detail'!E223 -> 0 | J93: ='26 Detail'!F223 -> 0 | K93: ='26 Detail'!G223 -> 0 | L93: ='26 Detail'!H223 -> 0 | M93: ='26 Detail'!I223 -> 0 | ... Q93: ='26 Detail'!M223 -> 0
C94: Short-Term Borrowing Expenses(-) | D94: =SUM(F94:Q94) -> 0 | F94: ='26 Detail'!B223 -> 0 | G94: ='26 Detail'!C223 -> 0 | H94: ='26 Detail'!D223 -> 0 | I94: ='26 Detail'!E223 -> 0 | J94: ='26 Detail'!F223 -> 0 | K94: ='26 Detail'!G223 -> 0 | L94: ='26 Detail'!H223 -> 0 | M94: ='26 Detail'!I223 -> 0 | ... Q94: ='26 Detail'!M223 -> 0
C95: Long-Term Borrowing Expenses(-) | D95: =SUM(F95:Q95) -> 0 | F95: ='26 Detail'!B224 -> 0 | G95: ='26 Detail'!C224 -> 0 | H95: ='26 Detail'!D224 -> 0 | I95: ='26 Detail'!E224 -> 0 | J95: ='26 Detail'!F224 -> 0 | K95: ='26 Detail'!G224 -> 0 | L95: ='26 Detail'!H224 -> 0 | M95: ='26 Detail'!I224 -> 0 | ... Q95: ='26 Detail'!M224 -> 0
C96: Financing Expenses | D96: =SUM(F96:Q96) -> 0 | F96: ='26 Detail'!B225 -> 0 | G96: ='26 Detail'!C225 -> 0 | H96: ='26 Detail'!D225 -> 0 | I96: ='26 Detail'!E225 -> 0 | J96: ='26 Detail'!F225 -> 0 | K96: ='26 Detail'!G225 -> 0 | L96: ='26 Detail'!H225 -> 0 | M96: ='26 Detail'!I225 -> 0 | ... Q96: ='26 Detail'!M225 -> 0
C97: OTHER EXTRAORDINARY EXPENSES AND LOSSES (-) | D97: =SUM(F97:Q97) -> 0 | F97: ='26 Detail'!B226 -> 0 | G97: ='26 Detail'!C226 -> 0 | H97: ='26 Detail'!D226 -> 0 | I97: ='26 Detail'!E226 -> 0 | J97: ='26 Detail'!F226 -> 0 | K97: ='26 Detail'!G226 -> 0 | L97: ='26 Detail'!H226 -> 0 | M97: ='26 Detail'!I226 -> 0 | ... Q97: ='26 Detail'!M226 -> 0
B98: Ⅸ.당기손익 | C98: Ⅸ.NET INCOME (or LOSS) | D98: =SUM(F98:Q98) -> 1.626368e+08 | F98: =+F70+F72-F84 -> 10096133 | G98: =+G70+G72-G84 -> 13265733 | H98: =+H70+H72-H84 -> 17333710 | I98: =+I70+I72-I84 -> 16028750 | J98: =+J70+J72-J84 -> 13846898 | K98: =+K70+K72-K84 -> 19370793 | L98: =+L70+L72-L84 -> 13385964 | M98: =+M70+M72-M84 -> 23098891 | ... Q98: =+Q70+Q72-Q84 -> 401846.78
B99: (이익률) | C99: (rate) | D99: =+IFERROR(D98/D5,) -> 0.087616876 | F99: =+IFERROR(F98/F5,) -> 0.10794416 | G99: =+IFERROR(G98/G5,) -> 0.11365198 | H99: =+IFERROR(H98/H5,) -> 0.1043281 | I99: =+IFERROR(I98/I5,) -> 0.11564947 | J99: =+IFERROR(J98/J5,) -> 0.10918137 | K99: =+IFERROR(K98/K5,) -> 0.10024155 | L99: =+IFERROR(L98/L5,) -> 0.1131573 | M99: =+IFERROR(M98/M5,) -> 0.13114299 | ... Q99: =+IFERROR(Q98/Q5,) -> 0.0023858168

Sheet 26 Detail
B1: 1 | C1: 2 | D1: 3 | E1: 4 | F1: 5 | G1: 6 | H1: 7 | I1: 8 | J1: 9 | K1: 10 | L1: 11 | M1: 12
A2: Ⅳ.판매관리비 _ SELLING AND MARKETING EXPENSES | R2: double check
A3: Export Expenses | B3: =SUM(B4:B9) -> 95782.779 | C3: =SUM(C4:C9) -> 95782.779 | D3: =SUM(D4:D9) -> 95782.779 | E3: =SUM(E4:E9) -> 95782.779 | F3: =SUM(F4:F9) -> 95782.779 | G3: =SUM(G4:G9) -> 95782.779 | H3: =SUM(H4:H9) -> 95782.779 | I3: =SUM(I4:I9) -> 191565.56 | ... M3: =SUM(M4:M9) -> 191565.56 | R3: =+SUM(B3:M3) -> 1628307.2
A4: Shipping Expenses | B4: ='8. Export, Import1'!C6 -> 23901.116 | C4: ='8. Export, Import1'!D6 -> 23901.116 | D4: ='8. Export, Import1'!E6 -> 23901.116 | E4: ='8. Export, Import1'!F6 -> 23901.116 | F4: ='8. Export, Import1'!G6 -> 23901.116 | G4: ='8. Export, Import1'!H6 -> 23901.116 | H4: ='8. Export, Import1'!I6 -> 23901.116 | I4: ='8. Export, Import1'!J6 -> 47802.232 | ... M4: ='8. Export, Import1'!N6 -> 47802.232 | O4: Shipping Expenses 390 TL., Handling Service 3,900 TL one time, EV-V4 (Part Export `26.08~) | P4: 30% Increased | R4: =+R3-SUM(B4:M9) -> 0
A5: Export Charges | B5: ='8. Export, Import1'!C7 -> 0 | C5: ='8. Export, Import1'!D7 -> 0 | D5: ='8. Export, Import1'!E7 -> 0 | E5: ='8. Export, Import1'!F7 -> 0 | F5: ='8. Export, Import1'!G7 -> 0 | G5: ='8. Export, Import1'!H7 -> 0 | H5: ='8. Export, Import1'!I7 -> 0 | I5: ='8. Export, Import1'!J7 -> 0 | ... M5: ='8. Export, Import1'!N7 -> 0
A6: Warehouse Charges | B6: ='8. Export, Import1'!C8 -> 8755.676 | C6: ='8. Export, Import1'!D8 -> 8755.676 | D6: ='8. Export, Import1'!E8 -> 8755.676 | E6: ='8. Export, Import1'!F8 -> 8755.676 | F6: ='8. Export, Import1'!G8 -> 8755.676 | G6: ='8. Export, Import1'!H8 -> 8755.676 | H6: ='8. Export, Import1'!I8 -> 8755.676 | I6: ='8. Export, Import1'!J8 -> 17511.352 | ... M6: ='8. Export, Import1'!N8 -> 17511.352 | O6: Warehouse charges 5,213 TL one time, EV-V4 (Part Export `26.08~) | P6: 30% Increased
A7: Transport labour | B7: ='8. Export, Import1'!C9 -> 32447.412 | C7: ='8. Export, Import1'!D9 -> 32447.412 | D7: ='8. Export, Import1'!E9 -> 32447.412 | E7: ='8. Export, Import1'!F9 -> 32447.412 | F7: ='8. Export, Import1'!G9 -> 32447.412 | G7: ='8. Export, Import1'!H9 -> 32447.412 | H7: ='8. Export, Import1'!I9 -> 32447.412 | I7: ='8. Export, Import1'!J9 -> 64894.825 | ... M7: ='8. Export, Import1'!N9 -> 64894.825 | O7: Security X-Ray, Customs, Declaration, Certificate of Origin, EV-V4 (Part Export `26.08~) | P7: 30% Increased
A8: Other Export Expenses | B8: ='8. Export, Import1'!C10 -> 17133.943 | C8: ='8. Export, Import1'!D10 -> 17133.943 | D8: ='8. Export, Import1'!E10 -> 17133.943 | E8: ='8. Export, Import1'!F10 -> 17133.943 | F8: ='8. Export, Import1'!G10 -> 17133.943 | G8: ='8. Export, Import1'!H10 -> 17133.943 | H8: ='8. Export, Import1'!I10 -> 17133.943 | I8: ='8. Export, Import1'!J10 -> 34267.886 | ... M8: ='8. Export, Import1'!N10 -> 34267.886 | P8: 30% Increased
A9: Other Tax | B9: ='8. Export, Import1'!C11 -> 13544.631 | C9: ='8. Export, Import1'!D11 -> 13544.631 | D9: ='8. Export, Import1'!E11 -> 13544.631 | E9: ='8. Export, Import1'!F11 -> 13544.631 | F9: ='8. Export, Import1'!G11 -> 13544.631 | G9: ='8. Export, Import1'!H11 -> 13544.631 | H9: ='8. Export, Import1'!I11 -> 13544.631 | I9: ='8. Export, Import1'!J11 -> 27089.262 | ... M9: ='8. Export, Import1'!N11 -> 27089.262 | O9: EV-V4 (Part Export `26.08~) | P9: 30% Increased
A11: Import Expenses | B11: =SUM(B12:B18) -> 20897.966 | C11: =SUM(C12:C18) -> 20897.966 | D11: =SUM(D12:D18) -> 20897.966 | E11: =SUM(E12:E18) -> 20897.966 | F11: =SUM(F12:F18) -> 20897.966 | G11: =SUM(G12:G18) -> 20897.966 | H11: =SUM(H12:H18) -> 20897.966 | I11: =SUM(I12:I18) -> 20897.966 | ... M11: =SUM(M12:M18) -> 41795.933 | R11: =+SUM(B11:M11) -> 334367.46
A12: Shipping Expenses | B12: ='8. Export, Import1'!C40 -> 3260.9471 | C12: ='8. Export, Import1'!D40 -> 3260.9471 | D12: ='8. Export, Import1'!E40 -> 3260.9471 | E12: ='8. Export, Import1'!F40 -> 3260.9471 | F12: ='8. Export, Import1'!G40 -> 3260.9471 | G12: ='8. Export, Import1'!H40 -> 3260.9471 | H12: ='8. Export, Import1'!I40 -> 3260.9471 | I12: ='8. Export, Import1'!J40 -> 3260.9471 | ... M12: ='8. Export, Import1'!N40 -> 6521.8942 | O12: - Ev-v4 will start on september | P12: 30% Increased | R12: =+R11-SUM(B12:M18) -> 0
A13: Export Charges | B13: ='8. Export, Import1'!C41 -> 0 | C13: ='8. Export, Import1'!D41 -> 0 | D13: ='8. Export, Import1'!E41 -> 0 | E13: ='8. Export, Import1'!F41 -> 0 | F13: ='8. Export, Import1'!G41 -> 0 | G13: ='8. Export, Import1'!H41 -> 0 | H13: ='8. Export, Import1'!I41 -> 0 | I13: ='8. Export, Import1'!J41 -> 0 | ... M13: ='8. Export, Import1'!N41 -> 0
A14: Warehouse Charges | B14: ='8. Export, Import1'!C42 -> 2443.8245 | C14: ='8. Export, Import1'!D42 -> 2443.8245 | D14: ='8. Export, Import1'!E42 -> 2443.8245 | E14: ='8. Export, Import1'!F42 -> 2443.8245 | F14: ='8. Export, Import1'!G42 -> 2443.8245 | G14: ='8. Export, Import1'!H42 -> 2443.8245 | H14: ='8. Export, Import1'!I42 -> 2443.8245 | I14: ='8. Export, Import1'!J42 -> 2443.8245 | ... M14: ='8. Export, Import1'!N42 -> 4887.649 | P14: 30% Increased
A15: Transport labour | B15: ='8. Export, Import1'!C43 -> 3286.6121 | C15: ='8. Export, Import1'!D43 -> 3286.6121 | D15: ='8. Export, Import1'!E43 -> 3286.6121 | E15: ='8. Export, Import1'!F43 -> 3286.6121 | F15: ='8. Export, Import1'!G43 -> 3286.6121 | G15: ='8. Export, Import1'!H43 -> 3286.6121 | H15: ='8. Export, Import1'!I43 -> 3286.6121 | I15: ='8. Export, Import1'!J43 -> 3286.6121 | ... M15: ='8. Export, Import1'!N43 -> 6573.2242 | P15: 30% Increased
A16: Other Export Expenses | B16: ='8. Export, Import1'!C44 -> 2469.1258 | C16: ='8. Export, Import1'!D44 -> 2469.1258 | D16: ='8. Export, Import1'!E44 -> 2469.1258 | E16: ='8. Export, Import1'!F44 -> 2469.1258 | F16: ='8. Export, Import1'!G44 -> 2469.1258 | G16: ='8. Export, Import1'!H44 -> 2469.1258 | H16: ='8. Export, Import1'!I44 -> 2469.1258 | I16: ='8. Export, Import1'!J44 -> 2469.1258 | ... M16: ='8. Export, Import1'!N44 -> 4938.2515 | P16: 30% Increased
A17: Custom Tax | B17: ='8. Export, Import1'!C45 -> 8320.6184 | C17: ='8. Export, Import1'!D45 -> 8320.6184 | D17: ='8. Export, Import1'!E45 -> 8320.6184 | E17: ='8. Export, Import1'!F45 -> 8320.6184 | F17: ='8. Export, Import1'!G45 -> 8320.6184 | G17: ='8. Export, Import1'!H45 -> 8320.6184 | H17: ='8. Export, Import1'!I45 -> 8320.6184 | I17: ='8. Export, Import1'!J45 -> 8320.6184 | ... M17: ='8. Export, Import1'!N45 -> 16641.237 | P17: 30% Increased
A18: Other Tax | B18: ='8. Export, Import1'!C46 -> 1116.8384 | C18: ='8. Export, Import1'!D46 -> 1116.8384 | D18: ='8. Export, Import1'!E46 -> 1116.8384 | E18: ='8. Export, Import1'!F46 -> 1116.8384 | F18: ='8. Export, Import1'!G46 -> 1116.8384 | G18: ='8. Export, Import1'!H46 -> 1116.8384 | H18: ='8. Export, Import1'!I46 -> 1116.8384 | I18: ='8. Export, Import1'!J46 -> 1116.8384 | ... M18: ='8. Export, Import1'!N46 -> 2233.6769 | P18: 30% Increased
A20: Domestic Transportation Expenses | B20: =SUM(B21) -> 554836.15 | C20: =SUM(C21) -> 554836.15 | D20: =SUM(D21) -> 554836.15 | E20: =SUM(E21) -> 554836.15 | F20: =SUM(F21) -> 554836.15 | G20: =SUM(G21) -> 554836.15 | H20: =SUM(H21) -> 554836.15 | I20: =SUM(I21) -> 554836.15 | ... M20: =SUM(M21) -> 554836.15 | R20: =+SUM(B20:M20) -> 6658033.8
A21: Transportation Expenses | B21: ='9.Transportation'!C5 -> 554836.15 | C21: ='9.Transportation'!D5 -> 554836.15 | D21: ='9.Transportation'!E5 -> 554836.15 | E21: ='9.Transportation'!F5 -> 554836.15 | F21: ='9.Transportation'!G5 -> 554836.15 | G21: ='9.Transportation'!H5 -> 554836.15 | H21: ='9.Transportation'!I5 -> 554836.15 | I21: ='9.Transportation'!J5 -> 554836.15 | ... M21: ='9.Transportation'!N5 -> 554836.15 | O21: Ford-KCTR direct delivery manage `25 performance | P21: 30% Increased | R21: =+R20-SUM(B21:M21) -> 0
A23: Sales Return costs | B23: =SUM(B24:B25) -> 0 | C23: =SUM(C24:C25) -> 0 | D23: =SUM(D24:D25) -> 0 | E23: =SUM(E24:E25) -> 0 | F23: =SUM(F24:F25) -> 0 | G23: =SUM(G24:G25) -> 0 | H23: =SUM(H24:H25) -> 0 | I23: =SUM(I24:I25) -> 0 | ... M23: =SUM(M24:M25) -> 0 | R23: =+SUM(B23:M23) -> 0
A24: Return Material Transportation Expenses | B24: - | C24: - | D24: - | E24: - | F24: - | G24: - | H24: - | I24: - | J24: - | K24: - | L24: - | M24: - | O24: Already applied to shipping expense | R24: =+R23-SUM(B24:M25) -> 0
A25: Other Expenses | B25: - | C25: - | D25: - | E25: - | F25: - | G25: - | H25: - | I25: - | J25: - | K25: - | L25: - | M25: - | O25: Already applied to shipping expense
A27: Product Sample Expenses | B27: =SUM(B28:B30) -> 41357.485 | C27: =SUM(C28:C30) -> 41357.485 | D27: =SUM(D28:D30) -> 41357.485 | E27: =SUM(E28:E30) -> 41357.485 | F27: =SUM(F28:F30) -> 41357.485 | G27: =SUM(G28:G30) -> 41357.485 | H27: =SUM(H28:H30) -> 41357.485 | I27: =SUM(I28:I30) -> 41357.485 | ... M27: =SUM(M28:M30) -> 41357.485 | R27: =+SUM(B27:M27) -> 496289.82
A28: Domestic Sample Expenses | B28: ='9.Transportation'!C28 -> 6790.5596 | C28: ='9.Transportation'!D28 -> 6790.5596 | D28: ='9.Transportation'!E28 -> 6790.5596 | E28: ='9.Transportation'!F28 -> 6790.5596 | F28: ='9.Transportation'!G28 -> 6790.5596 | G28: ='9.Transportation'!H28 -> 6790.5596 | H28: ='9.Transportation'!I28 -> 6790.5596 | I28: ='9.Transportation'!J28 -> 6790.5596 | ... M28: ='9.Transportation'!N28 -> 6790.5596 | O28: Urgent delivery to supplier | P28: 30% Increased | R28: =+R27-SUM(B28:M30) -> 0
A29: Export Sample Expenses | B29: ='9.Transportation'!C29 -> 3457.4614 | C29: ='9.Transportation'!D29 -> 3457.4614 | D29: ='9.Transportation'!E29 -> 3457.4614 | E29: ='9.Transportation'!F29 -> 3457.4614 | F29: ='9.Transportation'!G29 -> 3457.4614 | G29: ='9.Transportation'!H29 -> 3457.4614 | H29: ='9.Transportation'!I29 -> 3457.4614 | I29: ='9.Transportation'!J29 -> 3457.4614 | ... M29: ='9.Transportation'!N29 -> 3457.4614 | O29: Ford Overseas Product Shipping | P29: 30% Increased
A30: Other Sample Expenses | B30: ='9.Transportation'!C30 -> 31109.464 | C30: ='9.Transportation'!D30 -> 31109.464 | D30: ='9.Transportation'!E30 -> 31109.464 | E30: ='9.Transportation'!F30 -> 31109.464 | F30: ='9.Transportation'!G30 -> 31109.464 | G30: ='9.Transportation'!H30 -> 31109.464 | H30: ='9.Transportation'!I30 -> 31109.464 | I30: ='9.Transportation'!J30 -> 31109.464 | ... M30: ='9.Transportation'!N30 -> 31109.464 | O30: Urgent delivery to supplier KSC / KSCE | P30: 30% Increased
A32: Rental Expenses | B32: =SUM(B33) -> 106596.59 | C32: =SUM(C33) -> 121132.49 | D32: =SUM(D33) -> 139706.13 | E32: =SUM(E33) -> 86407.841 | F32: =SUM(F33) -> 120324.94 | G32: =SUM(G33) -> 150204.28 | H32: =SUM(H33) -> 92060.69 | I32: =SUM(I33) -> 127592.89 | ... M32: =SUM(M33) -> 121132.49 | R32: =+SUM(B32:M32) -> 1457627.6
A33: Box Rental Expenses | B33: =SUM('10. Warehouse'!E24,'10. Warehouse'!E26) -> 106596.59 | C33: =SUM('10. Warehouse'!F24,'10. Warehouse'!F26) -> 121132.49 | D33: =SUM('10. Warehouse'!G24,'10. Warehouse'!G26) -> 139706.13 | E33: =SUM('10. Warehouse'!H24,'10. Warehouse'!H26) -> 86407.841 | F33: =SUM('10. Warehouse'!I24,'10. Warehouse'!I26) -> 120324.94 | G33: =SUM('10. Warehouse'!J24,'10. Warehouse'!J26) -> 150204.28 | H33: =SUM('10. Warehouse'!K24,'10. Warehouse'!K26) -> 92060.69 | I33: =SUM('10. Warehouse'!L24,'10. Warehouse'!L26) -> 127592.89 | ... M33: =SUM('10. Warehouse'!P24,'10. Warehouse'!P26) -> 121132.49 | O33: BEV-M Rent/Issue Fee Box payment | P33: 30% Increased | R33: =+R32-SUM(B33:M33) -> 0
A35: Other Expenses | B35: =SUM(B36:B38) -> 110088.28 | C35: =SUM(C36:C38) -> 110088.28 | D35: =SUM(D36:D38) -> 110088.28 | E35: =SUM(E36:E38) -> 110088.28 | F35: =SUM(F36:F38) -> 2110088.3 | G35: =SUM(G36:G38) -> 110088.28 | H35: =SUM(H36:H38) -> 110088.28 | I35: =SUM(I36:I38) -> 110088.28 | ... M35: =SUM(M36:M38) -> 110088.28 | R35: =+SUM(B35:M35) -> 3321059.4
A36: Packaging-Label Expenses | R36: =+R35-SUM(B36:M38) -> 0
A37: Returnable Box Purchasing Expenses | B37: ='10. Warehouse'!E27 -> 110088.28 | C37: ='10. Warehouse'!F27 -> 110088.28 | D37: ='10. Warehouse'!G27 -> 110088.28 | E37: ='10. Warehouse'!H27 -> 110088.28 | F37: ='10. Warehouse'!I27 -> 110088.28 | G37: ='10. Warehouse'!J27 -> 110088.28 | H37: ='10. Warehouse'!K27 -> 110088.28 | I37: ='10. Warehouse'!L27 -> 110088.28 | ... M37: ='10. Warehouse'!P27 -> 110088.28 | O37: PHEV-E (P703) 101,620TL/month | P37: 30% Increased
A38: Annual DV/PV Test | B38: ='15. Test, Royalty '!D6 -> - | C38: ='15. Test, Royalty '!E6 -> - | D38: ='15. Test, Royalty '!F6 -> - | E38: ='15. Test, Royalty '!G6 -> - | F38: ='15. Test, Royalty '!H6 -> 2000000 | G38: ='15. Test, Royalty '!I6 -> - | H38: ='15. Test, Royalty '!J6 -> - | I38: ='15. Test, Royalty '!K6 -> - | ... M38: ='15. Test, Royalty '!O6 -> - | O38: Project DV/PV Test
A40: Sorting&Rework Expenses | B40: =SUM(B41:B44) -> 935310.68 | C40: =SUM(C41:C44) -> 1167224.1 | D40: =SUM(D41:D44) -> 1661461.4 | E40: =SUM(E41:E44) -> 1385977 | F40: =SUM(F41:F44) -> 1268247.3 | G40: =SUM(G41:G44) -> 1932411.7 | H40: =SUM(H41:H44) -> 1182951.9 | I40: =SUM(I41:I44) -> 1761351.5 | ... M40: =SUM(M41:M44) -> 1684315.3 | R40: =+SUM(B40:M40) -> 18562269
A41: Sorting&Rework Expenses | B41: =Summary!F5*0.01 -> 935310.68 | C41: =Summary!G5*0.01 -> 1167224.1 | D41: =Summary!H5*0.01 -> 1661461.4 | E41: =Summary!I5*0.01 -> 1385977 | F41: =Summary!J5*0.01 -> 1268247.3 | G41: =Summary!K5*0.01 -> 1932411.7 | H41: =Summary!L5*0.01 -> 1182951.9 | I41: =Summary!M5*0.01 -> 1761351.5 | ... M41: =Summary!Q5*0.01 -> 1684315.3 | O41: QC sorting Payment | R41: =+R40-SUM(B41:M41) -> 0
A43: Ⅳ.판매관리비 _ GENERAL ADMINISTRATION EXPENSES
A44: Personnel Expenses
A45: Executive Expenses | B45: =+SUM(B46:B51) -> 1197719.5 | C45: =+SUM(C46:C51) -> 1770719.5 | D45: =+SUM(D46:D51) -> 1197719.5 | E45: =+SUM(E46:E51) -> 2997719.5 | F45: =+SUM(F46:F51) -> 1197719.5 | G45: =+SUM(G46:G51) -> 4077719.5 | H45: =+SUM(H46:H51) -> 1865901.2 | I45: =+SUM(I46:I51) -> 1994901.2 | ... M45: =+SUM(M46:M51) -> 1667101.2 | R45: =+SUM(B45:M45) -> 23327078
A46: GROSS SALARIES | B46: ='4. Salary'!H46+'7. Commucation '!E46 -> 1109399 | C46: ='4. Salary'!I46+'7. Commucation '!F46 -> 1553399 | D46: ='4. Salary'!J46+'7. Commucation '!G46 -> 1109399 | E46: ='4. Salary'!K46+'7. Commucation '!H46 -> 2909399 | F46: ='4. Salary'!L46+'7. Commucation '!I46 -> 1109399 | G46: ='4. Salary'!M46+'7. Commucation '!J46 -> 3989399 | H46: ='4. Salary'!N46+'7. Commucation '!K46 -> 1529790.4 | I46: ='4. Salary'!O46+'7. Commucation '!L46 -> 1529790.4 | ... M46: ='4. Salary'!S46+'7. Commucation '!P46 -> 1529790.4 | O46: 26.07 Cost division Executive (Esti.) | R46: =+R45-SUM(B46:M51) -> 0
A47: SSI EMPLOYER PREMIUM SHARE | B47: ='4. Salary'!H47 -> 65338.86 | C47: ='4. Salary'!I47 -> 65338.86 | D47: ='4. Salary'!J47 -> 65338.86 | E47: ='4. Salary'!K47 -> 65338.86 | F47: ='4. Salary'!L47 -> 65338.86 | G47: ='4. Salary'!M47 -> 65338.86 | H47: ='4. Salary'!N47 -> 98008.29 | I47: ='4. Salary'!O47 -> 98008.29 | ... M47: ='4. Salary'!S47 -> 98008.29 | O47: 26.07 Cost division Executive (Esti.)
A48: EMPLOYER UNEMPLOYMENT PREMIUM SHARE | B48: ='4. Salary'!H48 -> 7801.66 | C48: ='4. Salary'!I48 -> 7801.66 | D48: ='4. Salary'!J48 -> 7801.66 | E48: ='4. Salary'!K48 -> 7801.66 | F48: ='4. Salary'!L48 -> 7801.66 | G48: ='4. Salary'!M48 -> 7801.66 | H48: ='4. Salary'!N48 -> 11702.49 | I48: ='4. Salary'!O48 -> 11702.49 | ... M48: ='4. Salary'!S48 -> 11702.49 | O48: 26.07 Cost division Executive (Esti.)
A49: Staff Lunch Expenses | B49: ='5. Social Benefit'!D11 -> 15180 | C49: ='5. Social Benefit'!E11 -> 15180 | D49: ='5. Social Benefit'!F11 -> 15180 | E49: ='5. Social Benefit'!G11 -> 15180 | F49: ='5. Social Benefit'!H11 -> 15180 | G49: ='5. Social Benefit'!I11 -> 15180 | H49: ='5. Social Benefit'!J11 -> 22770 | I49: ='5. Social Benefit'!K11 -> 22770 | ... M49: ='5. Social Benefit'!O11 -> 23805 | O49: Lunch 345 TL | P49: 30% Increased
A50: Other | B50: ='5. Social Benefit'!G41 -> - | C50: =64500*2 -> 129000 | D50: ='5. Social Benefit'!I41 -> - | E50: ='5. Social Benefit'!J41 -> - | F50: ='5. Social Benefit'!K41 -> - | G50: ='5. Social Benefit'!L41 -> - | H50: ='5. Social Benefit'!M41 -> 3630 | I50: ='5. Social Benefit'!N41+129000 -> 132630 | J50: ='5. Social Benefit'!O41 -> 3630 | K50: ='5. Social Benefit'!P41 -> 3630 | L50: ='5. Social Benefit'!Q41 -> 3630 | M50: ='5. Social Benefit'!R41 -> 3795 | O50: Shuttle 3,600 TL, Lee school payment(129,000TL*2) | P50: 30% Increased
A51: Insurance | B51: =+'6. Social Benefit-2'!D43 -> 0 | C51: =+'6. Social Benefit-2'!E43 -> 0 | D51: =+'6. Social Benefit-2'!F43 -> 0 | E51: =+'6. Social Benefit-2'!G43 -> 0 | F51: =+'6. Social Benefit-2'!H43 -> 0 | G51: =+'6. Social Benefit-2'!I43 -> 0 | H51: =+'6. Social Benefit-2'!J43 -> 200000 | I51: =+'6. Social Benefit-2'!K43 -> 200000 | ... M51: =+'6. Social Benefit-2'!O43 -> 0 | O51: - Joe and Lee Insurance
A53: Financial & General Affairs Expenses | B53: =SUM(B54:B60) -> 1051454.6 | C53: =SUM(C54:C60) -> 1382690.4 | D53: =SUM(D54:D60) -> 1492505.2 | E53: =SUM(E54:E60) -> 1414130.3 | F53: =SUM(F54:F60) -> 1405056.4 | G53: =SUM(G54:G60) -> 1374505.2 | H53: =SUM(H54:H60) -> 1382095.2 | I53: =SUM(I54:I60) -> 1402636.1 | ... M53: =SUM(M54:M60) -> 1410390.2 | R53: =+SUM(B53:M53) -> 16492194
A54: GROSS SALARIES & Bonus | B54: ='4. Salary'!H50 -> 749561.63 | C54: ='4. Salary'!I50 -> 1053059.9 | D54: ='4. Salary'!J50 -> 1053059.9 | E54: ='4. Salary'!K50 -> 1053059.9 | F54: ='4. Salary'!L50 -> 1053059.9 | G54: ='4. Salary'!M50 -> 1053059.9 | H54: ='4. Salary'!N50 -> 1053059.9 | I54: ='4. Salary'!O50 -> 1053059.9 | ... M54: ='4. Salary'!S50 -> 1053059.9 | O54: New Employee Cost (Jan, 26), Finance (Feb, 26) | P54: 33% Increased | R54: =+R53-SUM(B54:M60) -> 0
A55: SSI EMPLOYER PREMIUM SHARE | B55: ='4. Salary'!H51 -> 125551.62 | C55: ='4. Salary'!I51 -> 163152.92 | D55: ='4. Salary'!J51 -> 176387.54 | E55: ='4. Salary'!K51 -> 176387.54 | F55: ='4. Salary'!L51 -> 176387.54 | G55: ='4. Salary'!M51 -> 176387.54 | H55: ='4. Salary'!N51 -> 176387.54 | I55: ='4. Salary'!O51 -> 176387.54 | ... M55: ='4. Salary'!S51 -> 176387.54 | O55: New Employee Cost (Jan, 26), Finance (Feb, 26) | P55: 33% Increased
A56: EMPLOYER UNEMPLOYMENT PREMIUM SHARE | B56: ='4. Salary'!H52 -> 14991.25 | C56: ='4. Salary'!I52 -> 19480.95 | D56: ='4. Salary'!J52 -> 21061.2 | E56: ='4. Salary'!K52 -> 21061.2 | F56: ='4. Salary'!L52 -> 21061.2 | G56: ='4. Salary'!M52 -> 21061.2 | H56: ='4. Salary'!N52 -> 21061.2 | I56: ='4. Salary'!O52 -> 21061.2 | ... M56: ='4. Salary'!S52 -> 21061.2 | O56: New Employee Cost (Jan, 26), Finance (Feb, 26) | P56: 33% Increased
A57: Staff Lunch Expenses | B57: ='5. Social Benefit'!D12 -> 75900 | C57: ='5. Social Benefit'!E12 -> 83490 | D57: ='5. Social Benefit'!F12 -> 83490 | E57: ='5. Social Benefit'!G12 -> 83490 | F57: ='5. Social Benefit'!H12 -> 83490 | G57: ='5. Social Benefit'!I12 -> 83490 | H57: ='5. Social Benefit'!J12 -> 91080 | I57: ='5. Social Benefit'!K12 -> 91080 | ... M57: ='5. Social Benefit'!O12 -> 95220 | O57: Lunch 345 TL _total 8 employee, new 3 employee (264TL -> 345TL) | P57: 30% Increased
A58: Transportation | B58: ='5. Social Benefit'!G46 -> 35876.643 | C58: ='5. Social Benefit'!H46 -> 39506.643 | D58: ='5. Social Benefit'!I46 -> 39506.643 | E58: ='5. Social Benefit'!J46 -> 39506.643 | F58: ='5. Social Benefit'!K46 -> 39506.643 | G58: ='5. Social Benefit'!L46 -> 39506.643 | H58: ='5. Social Benefit'!M46 -> 39506.643 | I58: ='5. Social Benefit'!N46 -> 39506.643 | ... M58: ='5. Social Benefit'!R46 -> 40661.643 | O58: Shuttle 3,600 TL, (126TL -> 165TL increased) | P58: 30% Increased
A59: Other & Holiday Gift | B59: ='6. Social Benefit-2'!D17 -> 1000 | C59: ='6. Social Benefit-2'!E17 -> 1000 | D59: ='6. Social Benefit-2'!F17 -> 73000 | E59: ='6. Social Benefit-2'!G17 -> 1000 | F59: ='6. Social Benefit-2'!H17 -> 1000 | G59: ='6. Social Benefit-2'!I17 -> 1000 | H59: ='6. Social Benefit-2'!J17 -> 1000 | I59: ='6. Social Benefit-2'!K17 -> 1000 | ... M59: ='6. Social Benefit-2'!O17 -> 1000 | O59: Burthday (11 Employee), Ramadan Bonus (6,000TL) | P59: 30% Increased
A60: Insurance | B60: =+'6. Social Benefit-2'!D44 -> 48573.504 | C60: =+'6. Social Benefit-2'!E44 -> 23000 | D60: =+'6. Social Benefit-2'!F44 -> 46000 | E60: =+'6. Social Benefit-2'!G44 -> 39625.096 | F60: =+'6. Social Benefit-2'!H44 -> 30551.164 | G60: =+'6. Social Benefit-2'!I44 -> 0 | H60: =+'6. Social Benefit-2'!J44 -> 0 | I60: =+'6. Social Benefit-2'!K44 -> 20540.884 | ... M60: =+'6. Social Benefit-2'!O44 -> 23000 | P60: 30% Increased
A62: Manufacturing Personel Expenses | B62: =SUM(B63:B69) -> 1119618.6 | C62: =SUM(C63:C69) -> 1351355.5 | D62: =SUM(D63:D69) -> 1403919.9 | E62: =SUM(E63:E69) -> 1367310.6 | F62: =SUM(F63:F69) -> 1385161.2 | G62: =SUM(G63:G69) -> 1331919.9 | H62: =SUM(H63:H69) -> 1595132.6 | I62: =SUM(I63:I69) -> 1588780 | ... M62: =SUM(M63:M69) -> 1547819.9 | R62: =+SUM(B62:M62) -> 17485495
A63: GROSS SALARIES & Bonus | B63: ='4. Salary'!H54 -> 827176 | C63: ='4. Salary'!I54 -> 1022323.3 | D63: ='4. Salary'!J54 -> 1022323.3 | E63: ='4. Salary'!K54 -> 1022323.3 | F63: ='4. Salary'!L54 -> 1022323.3 | G63: ='4. Salary'!M54 -> 1022323.3 | H63: ='4. Salary'!N54 -> 1180348.6 | I63: ='4. Salary'!O54 -> 1180348.6 | ... M63: ='4. Salary'!S54 -> 1180348.6 | O63: New Employee MP&L 2 people (Jul, 26) | P63: 33% Increased | R63: =+R62-SUM(B63:M69) -> 0
A64: SSI EMPLOYER PREMIUM SHARE | B64: ='4. Salary'!H55 -> 138552 | C64: ='4. Salary'!I55 -> 171239.16 | D64: ='4. Salary'!J55 -> 171239.16 | E64: ='4. Salary'!K55 -> 171239.16 | F64: ='4. Salary'!L55 -> 171239.16 | G64: ='4. Salary'!M55 -> 171239.16 | H64: ='4. Salary'!N55 -> 197708.4 | I64: ='4. Salary'!O55 -> 197708.4 | ... M64: ='4. Salary'!S55 -> 197708.4 | O64: New Employee MP&L 2 people (Jul, 26) | P64: 33% Increased
A65: EMPLOYER UNEMPLOYMENT PREMIUM SHARE | B65: ='4. Salary'!H56 -> 16544 | C65: ='4. Salary'!I56 -> 20446.46 | D65: ='4. Salary'!J56 -> 20446.46 | E65: ='4. Salary'!K56 -> 20446.46 | F65: ='4. Salary'!L56 -> 20446.46 | G65: ='4. Salary'!M56 -> 20446.46 | H65: ='4. Salary'!N56 -> 23606.96 | I65: ='4. Salary'!O56 -> 23606.96 | ... M65: ='4. Salary'!S56 -> 23606.96 | O65: New Employee MP&L 2 people (Jul, 26) | P65: 33% Increased
A66: Staff Lunch Expenses | B66: ='5. Social Benefit'!D13 -> 83490 | C66: ='5. Social Benefit'!E13 -> 83490 | D66: ='5. Social Benefit'!F13 -> 83490 | E66: ='5. Social Benefit'!G13 -> 83490 | F66: ='5. Social Benefit'!H13 -> 83490 | G66: ='5. Social Benefit'!I13 -> 83490 | H66: ='5. Social Benefit'!J13 -> 83490 | I66: ='5. Social Benefit'!K13 -> 98670 | ... M66: ='5. Social Benefit'!O13 -> 103155 | O66: Lunch 345 TL _total 8 employee, new 2 employee (264TL -> 345TL) | P66: 30% Increased
A67: Transportation | B67: ='5. Social Benefit'!G47 -> 33421 | C67: ='5. Social Benefit'!H47 -> 33421 | D67: ='5. Social Benefit'!I47 -> 33421 | E67: ='5. Social Benefit'!J47 -> 33421 | F67: ='5. Social Benefit'!K47 -> 33421 | G67: ='5. Social Benefit'!L47 -> 33421 | H67: ='5. Social Benefit'!M47 -> 33421 | I67: ='5. Social Benefit'!N47 -> 40681 | ... M67: ='5. Social Benefit'!R47 -> 42001 | O67: Shuttle 3,600 TL, (126TL -> 165TL increased) | P67: 30% Increased
A68: Other & Holiday Gift | B68: ='6. Social Benefit-2'!D18 -> 1000 | C68: ='6. Social Benefit-2'!E18 -> 1000 | D68: ='6. Social Benefit-2'!F18 -> 73000 | E68: ='6. Social Benefit-2'!G18 -> 1000 | F68: ='6. Social Benefit-2'!H18 -> 1000 | G68: ='6. Social Benefit-2'!I18 -> 1000 | H68: ='5. Social Benefit'!M48 -> 76557.643 | I68: ='6. Social Benefit-2'!K18 -> 1000 | J68: ='6. Social Benefit-2'!L18 -> 1000 | K68: ='6. Social Benefit-2'!M18 -> 1000 | L68: ='6. Social Benefit-2'!N18 -> 1000 | M68: ='6. Social Benefit-2'!O18 -> 1000 | O68: Burthday (11 Employee), Ramadan Bonus (6,000TL) | P68: 30% Increased
A69: Insurance | B69: =+'6. Social Benefit-2'!D45 -> 19435.598 | C69: =+'6. Social Benefit-2'!E45 -> 19435.598 | D69: =+'6. Social Benefit-2'!F45 -> 0 | E69: =+'6. Social Benefit-2'!G45 -> 35390.6 | F69: =+'6. Social Benefit-2'!H45 -> 53241.286 | G69: =+'6. Social Benefit-2'!I45 -> 0 | H69: =+'6. Social Benefit-2'!J45 -> 0 | I69: =+'6. Social Benefit-2'!K45 -> 46765.04 | ... M69: =+'6. Social Benefit-2'!O45 -> 0 | P69: 30% Increased
A71: Rental Expenses
A72: Executive Rental Expenses | B72: =+SUM(B73:B75) -> 76750 | C72: =+SUM(C73:C75) -> 76750 | D72: =+SUM(D73:D75) -> 76750 | E72: =+SUM(E73:E75) -> 76750 | F72: =+SUM(F73:F75) -> 102750 | G72: =+SUM(G73:G75) -> 102750 | H72: =+SUM(H73:H75) -> 102750 | I72: =+SUM(I73:I75) -> 102750 | ... M72: =+SUM(M73:M75) -> 102750 | R72: =+SUM(B72:M72) -> 1129000
A73: Company Management Car Rental Expenses | B73: ='7. Commucation '!D17 -> 76750 | C73: ='7. Commucation '!E17 -> 76750 | D73: ='7. Commucation '!F17 -> 76750 | E73: ='7. Commucation '!G17 -> 76750 | F73: ='7. Commucation '!H17 -> 102750 | G73: ='7. Commucation '!I17 -> 102750 | H73: ='7. Commucation '!J17 -> 102750 | I73: ='7. Commucation '!K17 -> 102750 | ... M73: ='7. Commucation '!O17 -> 102750 | O73: Joe (34,000TL) Lee (4,2500TL) | R73: =+R72-SUM(B73:M75) -> 0
A74: Office Machine Rental Expenses
A75: Other Rental Expenses | P75: 30% Increased
A77: Financial & General Affairs Rental Expenses | B77: =SUM(B78:B80) -> 0 | C77: =SUM(C78:C80) -> 0 | D77: =SUM(D78:D80) -> 0 | E77: =SUM(E78:E80) -> 0 | F77: =SUM(F78:F80) -> 0 | G77: =SUM(G78:G80) -> 0 | H77: =SUM(H78:H80) -> 0 | I77: =SUM(I78:I80) -> 0 | ... M77: =SUM(M78:M80) -> 0 | R77: =+SUM(B77:M77) -> 0
A78: Personnel Car Rental Expenses | B78: ='7. Commucation '!D18 -> 0 | C78: ='7. Commucation '!E18 -> 0 | D78: ='7. Commucation '!F18 -> 0 | E78: ='7. Commucation '!G18 -> 0 | F78: ='7. Commucation '!H18 -> 0 | G78: ='7. Commucation '!I18 -> 0 | H78: ='7. Commucation '!J18 -> 0 | I78: ='7. Commucation '!K18 -> 0 | ... M78: ='7. Commucation '!O18 -> 0 | R78: =+R77-SUM(B78:M80) -> 0
A79: Office Machine Rental Expenses
A80: Other Rental Expenses
A82: Manufacturing Personnel Rental Expenses | B82: =SUM(B83:B85) -> 30000 | C82: =SUM(C83:C85) -> 30000 | D82: =SUM(D83:D85) -> 30000 | E82: =SUM(E83:E85) -> 30000 | F82: =SUM(F83:F85) -> 30000 | G82: =SUM(G83:G85) -> 30000 | H82: =SUM(H83:H85) -> 30000 | I82: =SUM(I83:I85) -> 30000 | ... M82: =SUM(M83:M85) -> 30000 | R82: =+SUM(B82:M82) -> 360000
A83: Personnel Car Rental Expense | B83: ='7. Commucation '!D24 -> 30000 | C83: ='7. Commucation '!E24 -> 30000 | D83: ='7. Commucation '!F24 -> 30000 | E83: ='7. Commucation '!G24 -> 30000 | F83: ='7. Commucation '!H24 -> 30000 | G83: ='7. Commucation '!I24 -> 30000 | H83: ='7. Commucation '!J24 -> 30000 | I83: ='7. Commucation '!K24 -> 30000 | ... M83: ='7. Commucation '!O24 -> 30000 | O83: Rental car cost (Park, 30,000TL) | R83: =+R82-SUM(B83:M85) -> 0
A84: Office Machine Rental Expense
A85: Other Rental Expenses
A87: Other Rental Expenses | B87: =SUM(B88:B91) -> 521500 | C87: =SUM(C88:C91) -> 521500 | D87: =SUM(D88:D91) -> 521500 | E87: =SUM(E88:E91) -> 521500 | F87: =SUM(F88:F91) -> 521500 | G87: =SUM(G88:G91) -> 521500 | H87: =SUM(H88:H91) -> 521500 | I87: =SUM(I88:I91) -> 521500 | ... M87: =SUM(M88:M91) -> 521500 | R87: =+SUM(B87:M87) -> 6258000
A88: Office Rental Expenses | B88: ='10. Warehouse'!E5 -> 494500 | C88: ='10. Warehouse'!F5 -> 494500 | D88: ='10. Warehouse'!G5 -> 494500 | E88: ='10. Warehouse'!H5 -> 494500 | F88: ='10. Warehouse'!I5 -> 494500 | G88: ='10. Warehouse'!J5 -> 494500 | H88: ='10. Warehouse'!K5 -> 494500 | I88: ='10. Warehouse'!L5 -> 494500 | ... M88: ='10. Warehouse'!P5 -> 494500 | O88: KCTR Warehouse (494,500TL) | R88: =+R87-SUM(B88:M91) -> 0
A89: Guest Vehicle Expenses
A90: Guesthouse Rental Expenses
A91: Shared Car Rental Fee | B91: ='7. Commucation '!D23 -> 27000 | C91: ='7. Commucation '!E23 -> 27000 | D91: ='7. Commucation '!F23 -> 27000 | E91: ='7. Commucation '!G23 -> 27000 | F91: ='7. Commucation '!H23 -> 27000 | G91: ='7. Commucation '!I23 -> 27000 | H91: ='7. Commucation '!J23 -> 27000 | I91: ='7. Commucation '!K23 -> 27000 | ... M91: ='7. Commucation '!O23 -> 27000 | O91: Rental car cost (Company, 27,000TL)
A93: Travel Expenses | B93: =SUM(B94:B100) -> 362260.83 | C93: =SUM(C94:C100) -> 362260.83 | D93: =SUM(D94:D100) -> 362260.83 | E93: =SUM(E94:E100) -> 362260.83 | F93: =SUM(F94:F100) -> 362260.83 | G93: =SUM(G94:G100) -> 362260.83 | H93: =SUM(H94:H100) -> 362260.83 | I93: =SUM(I94:I100) -> 362260.83 | ... M93: =SUM(M94:M100) -> 3189510.8 | R93: =+SUM(B93:M93) -> 7174380
A94: Travel Expenses (Domestic) | B94: ='11. Trip'!D7 -> 0 | C94: ='11. Trip'!E7 -> 0 | D94: ='11. Trip'!F7 -> 0 | E94: ='11. Trip'!G7 -> 0 | F94: ='11. Trip'!H7 -> 0 | G94: ='11. Trip'!I7 -> 0 | H94: ='11. Trip'!J7 -> 0 | I94: ='11. Trip'!K7 -> 0 | ... M94: ='11. Trip'!O7 -> 0 | R94: =+R93-SUM(B94:M100) -> 0
A95: Travel Expenses:Domestic General | B95: ='11. Trip'!D8 -> 20300 | C95: ='11. Trip'!E8 -> 20300 | D95: ='11. Trip'!F8 -> 20300 | E95: ='11. Trip'!G8 -> 20300 | F95: ='11. Trip'!H8 -> 20300 | G95: ='11. Trip'!I8 -> 20300 | H95: ='11. Trip'!J8 -> 20300 | I95: ='11. Trip'!K8 -> 20300 | ... M95: ='11. Trip'!O8 -> 20300 | O95: Domestic trip Meal 700TL , `25 monthly average 13,400TL | P95: apply plan
A96: Travel Expenses:Domestic Room Charge | B96: ='11. Trip'!D9 -> 43700 | C96: ='11. Trip'!E9 -> 43700 | D96: ='11. Trip'!F9 -> 43700 | E96: ='11. Trip'!G9 -> 43700 | F96: ='11. Trip'!H9 -> 43700 | G96: ='11. Trip'!I9 -> 43700 | H96: ='11. Trip'!J9 -> 43700 | I96: ='11. Trip'!K9 -> 43700 | ... M96: ='11. Trip'!O9 -> 43700 | O96: Domestic trip Hotel 3,800TL (QC/P,3 times/Mon), others (1times/2Mon), `25 monthly average 33,000TL | P96: apply plan
A97: Travel Expenses:Local Transportation | B97: ='11. Trip'!D10 -> 24200 | C97: ='11. Trip'!E10 -> 24200 | D97: ='11. Trip'!F10 -> 24200 | E97: ='11. Trip'!G10 -> 24200 | F97: ='11. Trip'!H10 -> 24200 | G97: ='11. Trip'!I10 -> 24200 | H97: ='11. Trip'!J10 -> 24200 | I97: ='11. Trip'!K10 -> 24200 | ... M97: ='11. Trip'!O10 -> 24200 | O97: Domestic trip Oil 2,000TL (1times x 4weeks) | P97: apply plan
A98: Travel Expenses (Overseas) | B98: ='11. Trip'!D11 -> 190205.83 | C98: ='11. Trip'!E11 -> 190205.83 | D98: ='11. Trip'!F11 -> 190205.83 | E98: ='11. Trip'!G11 -> 190205.83 | F98: ='11. Trip'!H11 -> 190205.83 | G98: ='11. Trip'!I11 -> 190205.83 | H98: ='11. Trip'!J11 -> 190205.83 | I98: ='11. Trip'!K11 -> 190205.83 | ... M98: ='11. Trip'!O11 -> 1843555.8 | O98: - Korea Business Trip Invitation Included
A99: Travel Expenses:Overseas General | B99: ='11. Trip'!D12 -> 16705 | C99: ='11. Trip'!E12 -> 16705 | D99: ='11. Trip'!F12 -> 16705 | E99: ='11. Trip'!G12 -> 16705 | F99: ='11. Trip'!H12 -> 16705 | G99: ='11. Trip'!I12 -> 16705 | H99: ='11. Trip'!J12 -> 16705 | I99: ='11. Trip'!K12 -> 16705 | ... M99: ='11. Trip'!O12 -> 352105 | O99: KSC→KCTR (6 times), KCTR→외국(9 times), Executive 2 times/year | P99: apply plan
A100: Travel Expenses:Overseas Room Charge | B100: ='11. Trip'!D13 -> 67150 | C100: ='11. Trip'!E13 -> 67150 | D100: ='11. Trip'!F13 -> 67150 | E100: ='11. Trip'!G13 -> 67150 | F100: ='11. Trip'!H13 -> 67150 | G100: ='11. Trip'!I13 -> 67150 | H100: ='11. Trip'!J13 -> 67150 | I100: ='11. Trip'!K13 -> 67150 | ... M100: ='11. Trip'!O13 -> 905650
A102: Entertainment Expenses | B102: =SUM(B103:B104) -> 105000 | C102: =SUM(C103:C104) -> 105000 | D102: =SUM(D103:D104) -> 105000 | E102: =SUM(E103:E104) -> 105000 | F102: =SUM(F103:F104) -> 105000 | G102: =SUM(G103:G104) -> 105000 | H102: =SUM(H103:H104) -> 105000 | I102: =SUM(I103:I104) -> 105000 | ... M102: =SUM(M103:M104) -> 105000 | R102: =+SUM(B102:M102) -> 1260000
A103: Domestic Entertainment Expenses | B103: =SUM('6. Social Benefit-2'!D22,'6. Social Benefit-2'!D23,'6. Social Benefit-2'!D24) -> 105000 | C103: =SUM('6. Social Benefit-2'!E22,'6. Social Benefit-2'!E23,'6. Social Benefit-2'!E24) -> 105000 | D103: =SUM('6. Social Benefit-2'!F22,'6. Social Benefit-2'!F23,'6. Social Benefit-2'!F24) -> 105000 | E103: =SUM('6. Social Benefit-2'!G22,'6. Social Benefit-2'!G23,'6. Social Benefit-2'!G24) -> 105000 | F103: =SUM('6. Social Benefit-2'!H22,'6. Social Benefit-2'!H23,'6. Social Benefit-2'!H24) -> 105000 | G103: =SUM('6. Social Benefit-2'!I22,'6. Social Benefit-2'!I23,'6. Social Benefit-2'!I24) -> 105000 | H103: =SUM('6. Social Benefit-2'!J22,'6. Social Benefit-2'!J23,'6. Social Benefit-2'!J24) -> 105000 | I103: =SUM('6. Social Benefit-2'!K22,'6. Social Benefit-2'!K23,'6. Social Benefit-2'!K24) -> 105000 | ... M103: =SUM('6. Social Benefit-2'!O22,'6. Social Benefit-2'!O23,'6. Social Benefit-2'!O24) -> 105000 | O103: KCTR Dinner, Team dinner, Customer dinner (25,000TL) | P103: apply plan | R103: =+R102-SUM(B103:M104) -> 0
A104: Overseas Entertainment Expenses
A106: Insurance Expenses | B106: =SUM(B107:B109) -> 0 | C106: =SUM(C107:C109) -> 0 | D106: =SUM(D107:D109) -> 0 | E106: =SUM(E107:E109) -> 0 | F106: =SUM(F107:F109) -> 0 | G106: =SUM(G107:G109) -> 0 | H106: =SUM(H107:H109) -> 0 | I106: =SUM(I107:I109) -> 0 | ... M106: =SUM(M107:M109) -> 0 | R106: =+SUM(B106:M106) -> 0
A107: Fire Insurance | R107: =+R106-SUM(B107:M109) -> 0
A108: Automobile Insurance
A109: Other Insurance
A111: Outsourse Benefits&Services | B111: =SUM(B112:B113) -> 22928.1 | C111: =SUM(C112:C113) -> 22928.1 | D111: =SUM(D112:D113) -> 22928.1 | E111: =SUM(E112:E113) -> 22928.1 | F111: =SUM(F112:F113) -> 22928.1 | G111: =SUM(G112:G113) -> 22928.1 | H111: =SUM(H112:H113) -> 22928.1 | I111: =SUM(I112:I113) -> 22928.1 | ... M111: =SUM(M112:M113) -> 22928.1 | R111: =+SUM(B111:M111) -> 275137.2
A112: Electricity / Water / Gas Expenses | B112: ='10. Warehouse'!E6+'10. Warehouse'!E7 -> 22928.1 | C112: ='10. Warehouse'!F6+'10. Warehouse'!F7 -> 22928.1 | D112: ='10. Warehouse'!G6+'10. Warehouse'!G7 -> 22928.1 | E112: ='10. Warehouse'!H6+'10. Warehouse'!H7 -> 22928.1 | F112: ='10. Warehouse'!I6+'10. Warehouse'!I7 -> 22928.1 | G112: ='10. Warehouse'!J6+'10. Warehouse'!J7 -> 22928.1 | H112: ='10. Warehouse'!K6+'10. Warehouse'!K7 -> 22928.1 | I112: ='10. Warehouse'!L6+'10. Warehouse'!L7 -> 22928.1 | ... M112: ='10. Warehouse'!P6+'10. Warehouse'!P7 -> 22928.1 | O112: KCTR warehouse electricity and water | R112: =+R111-SUM(B112:M113) -> 0
A113: Other Miscellaneous Expenses
A115: Office Supplies | B115: =SUM(B116:B120) -> 48000 | C115: =SUM(C116:C120) -> 46000 | D115: =SUM(D116:D120) -> 46000 | E115: =SUM(E116:E120) -> 46000 | F115: =SUM(F116:F120) -> 46000 | G115: =SUM(G116:G120) -> 46000 | H115: =SUM(H116:H120) -> 46000 | I115: =SUM(I116:I120) -> 46000 | ... M115: =SUM(M116:M120) -> 46000 | R115: =+SUM(B115:M115) -> 554000
A116: Office Expenses ( stationary) | B116: ='6. Social Benefit-2'!D5 -> 22000 | C116: ='6. Social Benefit-2'!E5 -> 20000 | D116: ='6. Social Benefit-2'!F5 -> 20000 | E116: ='6. Social Benefit-2'!G5 -> 20000 | F116: ='6. Social Benefit-2'!H5 -> 20000 | G116: ='6. Social Benefit-2'!I5 -> 20000 | H116: ='6. Social Benefit-2'!J5 -> 20000 | I116: ='6. Social Benefit-2'!K5 -> 20000 | ... M116: ='6. Social Benefit-2'!O5 -> 20000 | O116: 1000TL/per employees monthly | P116: Applied inflation | R116: =+R115-SUM(B116:M120) -> 0
A117: Building Maintenance | P117: apply plan
A118: Fixtures Writed As Direct Expenses | P118: apply plan
A119: Office General Expenses | B119: =SUM('6. Social Benefit-2'!D6,'6. Social Benefit-2'!D7,'6. Social Benefit-2'!D8,'6. Social Benefit-2'!D9) -> 26000 | C119: =SUM('6. Social Benefit-2'!E6,'6. Social Benefit-2'!E7,'6. Social Benefit-2'!E8,'6. Social Benefit-2'!E9) -> 26000 | D119: =SUM('6. Social Benefit-2'!F6,'6. Social Benefit-2'!F7,'6. Social Benefit-2'!F8,'6. Social Benefit-2'!F9) -> 26000 | E119: =SUM('6. Social Benefit-2'!G6,'6. Social Benefit-2'!G7,'6. Social Benefit-2'!G8,'6. Social Benefit-2'!G9) -> 26000 | F119: =SUM('6. Social Benefit-2'!H6,'6. Social Benefit-2'!H7,'6. Social Benefit-2'!H8,'6. Social Benefit-2'!H9) -> 26000 | G119: =SUM('6. Social Benefit-2'!I6,'6. Social Benefit-2'!I7,'6. Social Benefit-2'!I8,'6. Social Benefit-2'!I9) -> 26000 | H119: =SUM('6. Social Benefit-2'!J6,'6. Social Benefit-2'!J7,'6. Social Benefit-2'!J8,'6. Social Benefit-2'!J9) -> 26000 | I119: =SUM('6. Social Benefit-2'!K6,'6. Social Benefit-2'!K7,'6. Social Benefit-2'!K8,'6. Social Benefit-2'!K9) -> 26000 | ... M119: =SUM('6. Social Benefit-2'!O6,'6. Social Benefit-2'!O7,'6. Social Benefit-2'!O8,'6. Social Benefit-2'!O9) -> 26000 | O119: Office water : 1000TL/per employees monthly, Cleaning tool, Emergency pills | P119: Applied inflation
...

Sheet 1. Sales
A1: ▣ 상품 매출액 | G1: EV-V4 매입가 비율 | H1: 0.98 | J1: USD/EUR | K1: ='Exchange Rate'!$D$6/'Exchange Rate'!$D$4 -> 1.1851852
A2: 1. 매출수량 | W2: 단위 : 대
A3: 구분 | B3: 차종 | C3: LEVEL | F3: 아이템 | G3: 품번 | H3: U/S | I3: 비고 | J3: 매출 계획 (EA) | W3: 비고 | X3: 연결매출 연간 수량 | Y3: 차이
C4: 1 | D4: 2 | E4: 3 | J4: 1월 | K4: 2월 | L4: 3월 | M4: 4월 | N4: 5월 | O4: 6월 | P4: 7월 | Q4: 8월 | R4: 9월 | S4: 10월 | T4: 11월 | U4: 12월 | V4: TOTAL | X4: (영업팀)
A5: Battery | B5: FORD PHEV-E | C5: ● | F5: MAIN W/H | G5: PZ38-10B694-AC | H5: 1 | I5: 터키 현지 외주 | J5: 3040 | K5: 3300 | L5: 3940 | M5: 2880 | N5: 2380 | O5: 4960 | P5: 2740 | Q5: 4460 | R5: 4360 | S5: 3392 | T5: 3716 | U5: 3938 | V5: =SUM(J5:U5) -> 43106 | W5: ▶ 유럽 向 | X5: 43106 | Y5: =V5-X5 -> 0 | Z5: 43106 | AA5: =+Z5*H5 -> 43106
A6: Pack | B6: Ford Otosan | C6: ● | F6: BEC to ISC Conn (JUMPER) | G6: PZ38-14B252-AB | H6: 1 | I6: 터키 현지 외주 | J6: 3040 | K6: 3300 | L6: 3940 | M6: 2880 | N6: 2380 | O6: 4960 | P6: 2740 | Q6: 4460 | R6: 4360 | S6: 3392 | T6: 3716 | U6: 3938 | V6: =SUM(J6:U6) -> 43106 | W6: ↑ | X6: 43106 | Y6: =V6-X6 -> 0 | Z6: 43106 | AA6: =+Z6*H6 -> 43106
C7: ● | F7: BUSBAR - Array to Array (short) | G7: PZ38-14A033-AB | H7: 3 | I7: 터키 현지 외주 | J7: 9120 | K7: 9900 | L7: 11820 | M7: 8640 | N7: 7140 | O7: 14880 | P7: 8220 | Q7: 13380 | R7: 13080 | S7: 10176 | T7: 11148 | U7: 11814 | V7: =SUM(J7:U7) -> 129318 | W7: ↑ | X7: 129318 | Y7: =V7-X7 -> 0 | Z7: 43106 | AA7: =+Z7*H7 -> 129318
C8: ● | F8: BUSBAR - Array to Array (long) | G8: PZ38-14A033-BB | H8: 3 | I8: 터키 현지 외주 | J8: 9120 | K8: 9900 | L8: 11820 | M8: 8640 | N8: 7140 | O8: 14880 | P8: 8220 | Q8: 13380 | R8: 13080 | S8: 10176 | T8: 11148 | U8: 11814 | V8: =SUM(J8:U8) -> 129318 | W8: ↑ | X8: 129318 | Y8: =V8-X8 -> 0 | Z8: 43106 | AA8: =+Z8*H8 -> 129318
C9: ● | F9: BUSBAR - Array 3 to 4 | G9: PZ38-14A033-CB | H9: 1 | I9: 터키 현지 외주 | J9: 3040 | K9: 3300 | L9: 3940 | M9: 2880 | N9: 2380 | O9: 4960 | P9: 2740 | Q9: 4460 | R9: 4360 | S9: 3392 | T9: 3716 | U9: 3938 | V9: =SUM(J9:U9) -> 43106 | W9: ↑ | X9: 43106 | Y9: =V9-X9 -> 0 | Z9: 43106 | AA9: =+Z9*H9 -> 43106
B10: FORD PHEV-E | C10: ● | F10: MAIN W/H | G10: PZ38-10B694-AC | H10: 1 | I10: 터키 현지 외주 | J10: 1520 | K10: 1360 | L10: 1680 | M10: 1680 | N10: 1840 | O10: 2480 | P10: 1760 | Q10: 1800 | R10: 1874 | S10: 1906 | T10: 1944 | U10: 1961 | V10: =SUM(J10:U10) -> 21805 | W10: ▶ 아프리카 向 * P703 Forecast 8월부터 이전 6개월 평균 계산 | X10: 21805 | Y10: =V10-X10 -> 0 | Z10: 21805 | AA10: =+Z10*H10 -> 21805
B11: S/Africa | C11: ● | F11: BEC to ISC Conn (JUMPER) | G11: PZ38-14B252-AB | H11: 1 | I11: 터키 현지 외주 | J11: 1520 | K11: 1360 | L11: 1680 | M11: 1680 | N11: 1840 | O11: 2480 | P11: 1760 | Q11: 1800 | R11: 1874 | S11: 1906 | T11: 1944 | U11: 1961 | V11: =SUM(J11:U11) -> 21805 | W11: ↑ | X11: 21805 | Y11: =V11-X11 -> 0 | Z11: 21805 | AA11: =+Z11*H11 -> 21805
C12: ● | F12: BUSBAR - Array to Array (short) | G12: PZ38-14A033-AB | H12: 3 | I12: 터키 현지 외주 | J12: 4560 | K12: 4080 | L12: 5040 | M12: 5040 | N12: 5520 | O12: 7440 | P12: 5280 | Q12: 5400 | R12: 5622 | S12: 5718 | T12: 5832 | U12: 5883 | V12: =SUM(J12:U12) -> 65415 | W12: ↑ | X12: 65415 | Y12: =V12-X12 -> 0 | Z12: 21805 | AA12: =+Z12*H12 -> 65415
C13: ● | F13: BUSBAR - Array to Array (long) | G13: PZ38-14A033-BB | H13: 3 | I13: 터키 현지 외주 | J13: 4560 | K13: 4080 | L13: 5040 | M13: 5040 | N13: 5520 | O13: 7440 | P13: 5280 | Q13: 5400 | R13: 5622 | S13: 5718 | T13: 5832 | U13: 5883 | V13: =SUM(J13:U13) -> 65415 | W13: ↑ | X13: 65415 | Y13: =V13-X13 -> 0 | Z13: 21805 | AA13: =+Z13*H13 -> 65415
C14: ● | F14: BUSBAR - Array 3 to 4 | G14: PZ38-14A033-CB | H14: 1 | I14: 터키 현지 외주 | J14: 1520 | K14: 1360 | L14: 1680 | M14: 1680 | N14: 1840 | O14: 2480 | P14: 1760 | Q14: 1800 | R14: 1874 | S14: 1906 | T14: 1944 | U14: 1961 | V14: =SUM(J14:U14) -> 21805 | W14: ↑ | X14: 21805 | Y14: =V14-X14 -> 0 | Z14: 21805 | AA14: =+Z14*H14 -> 21805
B15: FORD BEV-E1 RWD | C15: ● | F15: MAIN W/H RWD | G15: TZ38-10B694-DB | H15: 1 | I15: 터키 현지 외주 | J15: 2004 | K15: 2059 | L15: 3966 | M15: 3354 | N15: 2679 | O15: 4244 | P15: 2581 | Q15: 4082 | R15: 3401 | S15: 3205 | T15: 0 | U15: 0 | V15: =SUM(J15:U15) -> 31575 | W15: * RWD 10월 단산 | X15: 31019 | Y15: =V15-X15 -> 556 | Z15: 31019 | AA15: =+Z15*H15 -> 31019
C16: ● | F16: CONN ASSY (PDU) | G16: TZ38-14B680-BB | H16: 1 | I16: 터키 현지 외주 | J16: 2004 | K16: 2059 | L16: 3966 | M16: 3354 | N16: 2679 | O16: 4244 | P16: 2581 | Q16: 4082 | R16: 3401 | S16: 3205 | T16: 0 | U16: 0 | V16: =SUM(J16:U16) -> 31575 | X16: 31019 | Y16: =V16-X16 -> 556 | Z16: 31019 | AA16: =+Z16*H16 -> 31019
C17: ● | F17: BUSBAR - Array to Array (Straight)_Insert | G17: TZ38-14A033-FA | H17: 1 | I17: 터키 현지 외주 | J17: 2004 | K17: 2059 | L17: 3966 | M17: 3354 | N17: 2679 | O17: 4244 | P17: 2581 | Q17: 4082 | R17: 3401 | S17: 3205 | T17: 0 | U17: 0 | V17: =SUM(J17:U17) -> 31575 | X17: 31019 | Y17: =V17-X17 -> 556 | Z17: 31019 | AA17: =+Z17*H17 -> 31019
C18: ● | F18: BUSBAR - Array to Array (Angled)_Insert | G18: TZ38-14A033-HB | H18: 3 | I18: 터키 현지 외주 | J18: 6012 | K18: 6177 | L18: 11898 | M18: 10062 | N18: 8037 | O18: 12732 | P18: 7743 | Q18: 12246 | R18: 10203 | S18: 9615 | T18: 0 | U18: 0 | V18: =SUM(J18:U18) -> 94725 | X18: 93057 | Y18: =V18-X18 -> 1668 | Z18: 31019 | AA18: =+Z18*H18 -> 93057
C19: ● | F19: BUSBAR - Array 1 to Neg BEC_Insert | G19: TZ38-14A033-SA | H19: 1 | I19: 터키 현지 외주 | J19: 2004 | K19: 2059 | L19: 3966 | M19: 3354 | N19: 2679 | O19: 4244 | P19: 2581 | Q19: 4082 | R19: 3401 | S19: 3205 | T19: 0 | U19: 0 | V19: =SUM(J19:U19) -> 31575 | X19: 31019 | Y19: =V19-X19 -> 556 | Z19: 31019 | AA19: =+Z19*H19 -> 31019
C20: ● | F20: BUSBAR - Array4 to Array 5_Insert | G20: PZ38-14A033-HF | H20: 1 | I20: 터키 현지 외주 | J20: 2004 | K20: 2059 | L20: 3966 | M20: 3354 | N20: 2679 | O20: 4244 | P20: 2581 | Q20: 4082 | R20: 3401 | S20: 3205 | T20: 0 | U20: 0 | V20: =SUM(J20:U20) -> 31575 | X20: 31019 | Y20: =V20-X20 -> 556 | Z20: 31019 | AA20: =+Z20*H20 -> 31019
C21: ● | F21: BUSBAR - Array 8 to Array 9_Insert | G21: TZ38-14A033-JB | H21: 1 | I21: 터키 현지 외주 | J21: 2004 | K21: 2059 | L21: 3966 | M21: 3354 | N21: 2679 | O21: 4244 | P21: 2581 | Q21: 4082 | R21: 3401 | S21: 3205 | T21: 0 | U21: 0 | V21: =SUM(J21:U21) -> 31575 | X21: 31019 | Y21: =V21-X21 -> 556 | Z21: 31019 | AA21: =+Z21*H21 -> 31019
C22: ● | F22: BUSBAR - Array 9 to Pos BEC_Insert | G22: PZ38-14A033-LF | H22: 1 | I22: 터키 현지 외주 | J22: 2004 | K22: 2059 | L22: 3966 | M22: 3354 | N22: 2679 | O22: 4244 | P22: 2581 | Q22: 4082 | R22: 3401 | S22: 3205 | T22: 0 | U22: 0 | V22: =SUM(J22:U22) -> 31575 | X22: 31019 | Y22: =V22-X22 -> 556 | Z22: 31019 | AA22: =+Z22*H22 -> 31019
C23: ● | F23: BUSBAR - Pos BEC to DCFC_Protector | G23: PZ38-14A033-MC | H23: 1 | I23: 터키 현지 외주 | J23: 2004 | K23: 2059 | L23: 3966 | M23: 3354 | N23: 2679 | O23: 4244 | P23: 2581 | Q23: 4082 | R23: 3401 | S23: 3205 | T23: 0 | U23: 0 | V23: =SUM(J23:U23) -> 31575 | X23: 31019 | Y23: =V23-X23 -> 556 | Z23: 31019 | AA23: =+Z23*H23 -> 31019
C24: ● | F24: BUSBAR - Neg BEC to DCFC_Protector | G24: TZ38-14A033-NA | H24: 1 | I24: 터키 현지 외주 | J24: 2004 | K24: 2059 | L24: 3966 | M24: 3354 | N24: 2679 | O24: 4244 | P24: 2581 | Q24: 4082 | R24: 3401 | S24: 3205 | T24: 0 | U24: 0 | V24: =SUM(J24:U24) -> 31575 | X24: 31019 | Y24: =V24-X24 -> 556 | Z24: 31019 | AA24: =+Z24*H24 -> 31019
C25: ● | F25: BUSBAR - CIRCUIT BREAKER_A_Insert | G25: TZ38-14A033-PB | H25: 1 | I25: 터키 현지 외주 | J25: 2004 | K25: 2059 | L25: 3966 | M25: 3354 | N25: 2679 | O25: 4244 | P25: 2581 | Q25: 4082 | R25: 3401 | S25: 3205 | T25: 0 | U25: 0 | V25: =SUM(J25:U25) -> 31575 | X25: 31019 | Y25: =V25-X25 -> 556 | Z25: 31019 | AA25: =+Z25*H25 -> 31019
C26: ● | F26: BUSBAR - CIRCUIT BREAKER_B_Insert | G26: TZ38-14A033-RB | H26: 1 | I26: 터키 현지 외주 | J26: 2004 | K26: 2059 | L26: 3966 | M26: 3354 | N26: 2679 | O26: 4244 | P26: 2581 | Q26: 4082 | R26: 3401 | S26: 3205 | T26: 0 | U26: 0 | V26: =SUM(J26:U26) -> 31575 | X26: 31019 | Y26: =V26-X26 -> 556 | Z26: 31019 | AA26: =+Z26*H26 -> 31019
C27: ● | F27: BUSBAR - Array to Array (Straight)_Insert | G27: PZ38-14A033-FD | H27: 1 | I27: 터키 현지 외주 | J27: 2004 | K27: 2059 | L27: 3966 | M27: 3354 | N27: 2679 | O27: 4244 | P27: 2581 | Q27: 4082 | R27: 3401 | S27: 3205 | T27: 0 | U27: 0 | V27: =SUM(J27:U27) -> 31575 | X27: 31019 | Y27: =V27-X27 -> 556 | Z27: 31019 | AA27: =+Z27*H27 -> 31019
B28: FORD BEV-E1 AWD | C28: ● | F28: BUSBAR - Array to Array (Straight)_Insert | G28: PZ38-14A033-FD | H28: 1 | I28: 터키 현지 외주 | J28: 65 | K28: 558 | L28: 980 | M28: 783 | N28: 588 | O28: 1004 | P28: 552 | Q28: 940 | R28: 766 | S28: 777 | T28: 0 | U28: 0 | V28: =SUM(J28:U28) -> 7013 | W28: * AWD 10월 단산 | X28: 7013 | Y28: =V28-X28 -> 0 | Z28: 7013 | AA28: =+Z28*H28 -> 7013
C29: ● | F29: CONN ASSY (PDU) | G29: TZ38-14B680-BB | H29: 1 | I29: 터키 현지 외주 | J29: 65 | K29: 558 | L29: 980 | M29: 783 | N29: 588 | O29: 1004 | P29: 552 | Q29: 940 | R29: 766 | S29: 777 | T29: 0 | U29: 0 | V29: =SUM(J29:U29) -> 7013 | X29: 7013 | Y29: =V29-X29 -> 0 | Z29: 7013 | AA29: =+Z29*H29 -> 7013
C30: ● | F30: BUSBAR - Array to Array (Straight)_Insert | G30: TZ38-14A033-FA | H30: 1 | I30: 터키 현지 외주 | J30: 65 | K30: 558 | L30: 980 | M30: 783 | N30: 588 | O30: 1004 | P30: 552 | Q30: 940 | R30: 766 | S30: 777 | T30: 0 | U30: 0 | V30: =SUM(J30:U30) -> 7013 | X30: 7013 | Y30: =V30-X30 -> 0 | Z30: 7013 | AA30: =+Z30*H30 -> 7013
C31: ● | F31: BUSBAR - Array to Array (Angled)_Insert | G31: TZ38-14A033-HB | H31: 3 | I31: 터키 현지 외주 | J31: 195 | K31: 1674 | L31: 2940 | M31: 2349 | N31: 1764 | O31: 3012 | P31: 1656 | Q31: 2820 | R31: 2298 | S31: 2331 | T31: 0 | U31: 0 | V31: =SUM(J31:U31) -> 21039 | X31: 21039 | Y31: =V31-X31 -> 0 | Z31: 7013 | AA31: =+Z31*H31 -> 21039
C32: ● | F32: BUSBAR - Array 1 to Neg BEC_Insert | G32: TZ38-14A033-SA | H32: 1 | I32: 터키 현지 외주 | J32: 65 | K32: 558 | L32: 980 | M32: 783 | N32: 588 | O32: 1004 | P32: 552 | Q32: 940 | R32: 766 | S32: 777 | T32: 0 | U32: 0 | V32: =SUM(J32:U32) -> 7013 | X32: 7013 | Y32: =V32-X32 -> 0 | Z32: 7013 | AA32: =+Z32*H32 -> 7013
C33: ● | F33: BUSBAR - Array4 to Array 5_Insert | G33: PZ38-14A033-HF | H33: 1 | I33: 터키 현지 외주 | J33: 65 | K33: 558 | L33: 980 | M33: 783 | N33: 588 | O33: 1004 | P33: 552 | Q33: 940 | R33: 766 | S33: 777 | T33: 0 | U33: 0 | V33: =SUM(J33:U33) -> 7013 | X33: 7013 | Y33: =V33-X33 -> 0 | Z33: 7013 | AA33: =+Z33*H33 -> 7013
C34: ● | F34: BUSBAR - Array 8 to Array 9_Insert | G34: TZ38-14A033-JB | H34: 1 | I34: 터키 현지 외주 | J34: 65 | K34: 558 | L34: 980 | M34: 783 | N34: 588 | O34: 1004 | P34: 552 | Q34: 940 | R34: 766 | S34: 777 | T34: 0 | U34: 0 | V34: =SUM(J34:U34) -> 7013 | X34: 7013 | Y34: =V34-X34 -> 0 | Z34: 7013 | AA34: =+Z34*H34 -> 7013
C35: ● | F35: BUSBAR - Array 9 to Pos BEC_Insert | G35: PZ38-14A033-LF | H35: 1 | I35: 터키 현지 외주 | J35: 65 | K35: 558 | L35: 980 | M35: 783 | N35: 588 | O35: 1004 | P35: 552 | Q35: 940 | R35: 766 | S35: 777 | T35: 0 | U35: 0 | V35: =SUM(J35:U35) -> 7013 | X35: 7013 | Y35: =V35-X35 -> 0 | Z35: 7013 | AA35: =+Z35*H35 -> 7013
C36: ● | F36: BUSBAR - Pos BEC to DCFC_Protector | G36: PZ38-14A033-MC | H36: 1 | I36: 터키 현지 외주 | J36: 65 | K36: 558 | L36: 980 | M36: 783 | N36: 588 | O36: 1004 | P36: 552 | Q36: 940 | R36: 766 | S36: 777 | T36: 0 | U36: 0 | V36: =SUM(J36:U36) -> 7013 | X36: 7013 | Y36: =V36-X36 -> 0 | Z36: 7013 | AA36: =+Z36*H36 -> 7013
C37: ● | F37: BUSBAR - Neg BEC to DCFC_Protector | G37: TZ38-14A033-NA | H37: 1 | I37: 터키 현지 외주 | J37: 65 | K37: 558 | L37: 980 | M37: 783 | N37: 588 | O37: 1004 | P37: 552 | Q37: 940 | R37: 766 | S37: 777 | T37: 0 | U37: 0 | V37: =SUM(J37:U37) -> 7013 | X37: 7013 | Y37: =V37-X37 -> 0 | Z37: 7013 | AA37: =+Z37*H37 -> 7013
C38: ● | F38: BUSBAR - CIRCUIT BREAKER_A_Insert | G38: TZ38-14A033-PB | H38: 1 | I38: 터키 현지 외주 | J38: 65 | K38: 558 | L38: 980 | M38: 783 | N38: 588 | O38: 1004 | P38: 552 | Q38: 940 | R38: 766 | S38: 777 | T38: 0 | U38: 0 | V38: =SUM(J38:U38) -> 7013 | X38: 7013 | Y38: =V38-X38 -> 0 | Z38: 7013 | AA38: =+Z38*H38 -> 7013
C39: ● | F39: BUSBAR - CIRCUIT BREAKER_B_Insert | G39: TZ38-14A033-RB | H39: 1 | I39: 터키 현지 외주 | J39: 65 | K39: 558 | L39: 980 | M39: 783 | N39: 588 | O39: 1004 | P39: 552 | Q39: 940 | R39: 766 | S39: 777 | T39: 0 | U39: 0 | V39: =SUM(J39:U39) -> 7013 | X39: 7013 | Y39: =V39-X39 -> 0 | Z39: 7013 | AA39: =+Z39*H39 -> 7013
C40: ● | F40: BUSBAR - Array to Array (Straight)_Insert | G40: PZ38-14A033-FD | H40: 1 | I40: 터키 현지 외주 | J40: 65 | K40: 558 | L40: 980 | M40: 783 | N40: 588 | O40: 1004 | P40: 552 | Q40: 940 | R40: 766 | S40: 777 | V40: =SUM(J40:U40) -> 7013 | X40: 7013 | Y40: =V40-X40 -> 0 | Z40: 7013 | AA40: =+Z40*H40 -> 7013
B41: FORD BEV-M | C41: ● | F41: BUS BAR ASY - ARRAY 4 POS TO ARRAY 5 NEG | G41: S2X8-14A033-BC | H41: 2 | I41: 터키 현지 외주 | J41: 6912 | K41: 10368 | V41: =SUM(J41:U41) -> 17280 | W41: `26년 2월부터 Suffix 변경 | X41: 100210 | Y41: =V41-X41 -> -82930 | Z41: 8640 | AA41: =+Z41*H41 -> 17280
C42: ● | F42: =F41 -> BUS BAR ASY - ARRAY 4 POS TO ARRAY 5 NEG | G42: S2X8-14A033-BC | H42: 1 | I42: =+I41 -> 터키 현지 외주 | L42: 4032 | M42: 3456 | N42: 4608 | O42: 5184 | P42: 3456 | Q42: 4608 | R42: 4608 | S42: 3062 | T42: 4255 | U42: 4196 | V42: =SUM(J42:U42) -> 41465 | Z42: 41465 | AA42: =+Z42*H42 -> 41465
C43: ● | F43: =F42 -> BUS BAR ASY - ARRAY 4 POS TO ARRAY 5 NEG | G43: T2X8-14A033-BA | H43: 1 | I43: =+I42 -> 터키 현지 외주 | L43: 4032 | M43: 3456 | N43: 4608 | O43: 5184 | P43: 3456 | Q43: 4608 | R43: 4608 | S43: 3062 | T43: 4255 | U43: 4196 | V43: =SUM(J43:U43) -> 41465 | Z43: 41465 | AA43: =+Z43*H43 -> 41465
C44: ● | F44: BUS BAR ASY – COMMON BUSBAR ARRAY 3-2, 2-1 | G44: S2X8-14A033-EC | H44: 2 | I44: 터키 현지 외주 | J44: 6912 | K44: 10368 | V44: =SUM(J44:U44) -> 17280 | W44: `26년 2월부터 Suffix 변경 | X44: 100210 | Y44: =V44-X44 -> -82930 | Z44: 8640 | AA44: =+Z44*H44 -> 17280
C45: ● | F45: =+F44 -> BUS BAR ASY – COMMON BUSBAR ARRAY 3-2, 2-1 | G45: T2X8-14A033-EA | H45: 2 | I45: =+I44 -> 터키 현지 외주 | L45: 8064 | M45: 6912 | N45: 9216 | O45: 10368 | P45: 6912 | Q45: 9216 | R45: 9216 | S45: 6124 | T45: 8510 | U45: 8392 | V45: =SUM(J45:U45) -> 82930 | Z45: 41465 | AA45: =+Z45*H45 -> 82930
C46: ● | F46: BUS BAR ASY – POS BEC TO ARRAY 6 POS | G46: S2X8-14A033-AC | H46: 1 | I46: 터키 현지 외주 | J46: 3456 | K46: 5184 | V46: =SUM(J46:U46) -> 8640 | W46: `26년 2월부터 Suffix 변경 | X46: 50105 | Y46: =V46-X46 -> -41465 | Z46: 8640 | AA46: =+Z46*H46 -> 8640
C47: ● | F47: =+F46 -> BUS BAR ASY – POS BEC TO ARRAY 6 POS | G47: T2X8-14A033-AA | H47: 1 | I47: =+I46 -> 터키 현지 외주 | L47: 4032 | M47: 3456 | N47: 4608 | O47: 5184 | P47: 3456 | Q47: 4608 | R47: 4608 | S47: 3062 | T47: 4255 | U47: 4196 | V47: =SUM(J47:U47) -> 41465 | Z47: 41465 | AA47: =+Z47*H47 -> 41465
C48: ● | F48: BUS BAR ASY – ARRAY 4 NEG TO CIRCUIT BREAKER | G48: S2X8-14A033-CC | H48: 1 | I48: 터키 현지 외주 | J48: 3456 | K48: 5184 | L48: 4032 | M48: 3456 | N48: 4608 | O48: 5184 | P48: 3456 | Q48: 4608 | R48: 4608 | S48: 3062 | T48: 4255 | U48: 4196 | V48: =SUM(J48:U48) -> 50105 | X48: 50105 | Y48: =V48-X48 -> 0 | Z48: 50105 | AA48: =+Z48*H48 -> 50105
C49: ● | F49: BUS BAR ASY – CIRCUIT BREAKER TO ARRAY 3 POS | G49: S2X8-14A033-DC | H49: 1 | I49: 터키 현지 외주 | J49: 3456 | K49: 5184 | L49: 4032 | M49: 3456 | N49: 4608 | O49: 5184 | P49: 3456 | Q49: 4608 | R49: 4608 | S49: 3062 | T49: 4255 | U49: 4196 | V49: =SUM(J49:U49) -> 50105 | X49: 50105 | Y49: =V49-X49 -> 0 | Z49: 50105 | AA49: =+Z49*H49 -> 50105
C50: ● | F50: BUS BAR ASY – ARRAY 1 NEG TO NEG BEC | G50: S2X8-14A033-GC | H50: 1 | I50: 터키 현지 외주 | J50: 3456 | K50: 5184 | V50: =SUM(J50:U50) -> 8640 | W50: `26년 2월부터 Suffix 변경 | X50: 50105 | Y50: =V50-X50 -> -41465 | Z50: 8640 | AA50: =+Z50*H50 -> 8640
C51: ● | F51: =+F50 -> BUS BAR ASY – ARRAY 1 NEG TO NEG BEC | G51: T2X8-14A033-GA | H51: 1 | I51: =+I50 -> 터키 현지 외주 | L51: 4032 | M51: 3456 | N51: 4608 | O51: 5184 | P51: 3456 | Q51: 4608 | R51: 4608 | S51: 3062 | T51: 4255 | U51: 4196 | V51: =SUM(J51:U51) -> 41465 | Z51: 41465 | AA51: =+Z51*H51 -> 41465
C52: ● | F52: BUS BAR ASY – POS BEC TO DCFC POS | G52: S2X8-14A033-HD | H52: 1 | I52: 터키 현지 외주 | J52: 3456 | K52: 5184 | L52: 4032 | M52: 3456 | N52: 4608 | O52: 5184 | P52: 3456 | Q52: 4608 | R52: 4608 | S52: 3062 | T52: 4255 | U52: 4196 | V52: =SUM(J52:U52) -> 50105 | X52: 50105 | Y52: =V52-X52 -> 0 | Z52: 50105 | AA52: =+Z52*H52 -> 50105
C53: ● | F53: BUS BAR ASY – POS BEC TO DCFC NEG | G53: S2X8-14A033-JD | H53: 1 | I53: 터키 현지 외주 | J53: 3456 | K53: 5184 | L53: 4032 | M53: 3456 | N53: 4608 | O53: 5184 | P53: 3456 | Q53: 4608 | R53: 4608 | S53: 3062 | T53: 4255 | U53: 4196 | V53: =SUM(J53:U53) -> 50105 | X53: 50105 | Y53: =V53-X53 -> 0 | Z53: 50105 | AA53: =+Z53*H53 -> 50105
B54: FORD BEV-M PARTS | D54: ● | F54: BEV-E1 / BEV_E_TML_1 | G54: BEE22-CT009 | H54: 1 | I54: BALKAN | J54: 3456 | K54: 5184 | L54: 4032 | M54: 3456 | N54: 4608 | O54: 5184 | P54: 3456 | Q54: 4608 | R54: 4608 | S54: 3062 | T54: 4255 | U54: 4196 | V54: =SUM(J54:U54) -> 50105 | X54: 0 | Y54: 연결 매출계획 미반영 | Z54: #N/A | AA54: =+Z54*H54 -> #N/A
B55: YAZAKI | D55: ● | F55: BEV-E1 / BEV_E_TML_2 | G55: BEE22-CT010 | H55: 1 | I55: BALKAN | J55: 3456 | K55: 5184 | L55: 4032 | M55: 3456 | N55: 4608 | O55: 5184 | P55: 3456 | Q55: 4608 | R55: 4608 | S55: 3062 | T55: 4255 | U55: 4196 | V55: =SUM(J55:U55) -> 50105 | X55: 0 | Y55: 연결 매출계획 미반영 | Z55: #N/A | AA55: =+Z55*H55 -> #N/A
D56: ● | F56: BEV-E1 / BEV-E_TML_3 | G56: BEE22-CT011 | H56: 2 | I56: BALKAN | J56: 6912 | K56: 10368 | L56: 8064 | M56: 6912 | N56: 9216 | O56: 10368 | P56: 6912 | Q56: 9216 | R56: 9216 | S56: 6124 | T56: 8510 | U56: 8392 | V56: =SUM(J56:U56) -> 100210 | X56: 0 | Y56: 연결 매출계획 미반영 | Z56: #N/A | AA56: =+Z56*H56 -> #N/A
B57: FORD EV-V4 | C57: ● | F57: MAIN W/H (AWD) | G57: TZ38-10B694-C | H57: 1 | I57: KSCE | J57: 0 | K57: 37 | L57: 0 | M57: 0 | N57: 0 | O57: 0 | P57: 0 | Q57: 0 | R57: 0 | S57: 749 | T57: 749 | U57: 749 | V57: =SUM(J57:U57) -> 2284 | X57: 2247 | Y57: =V57-X57 -> 37 | Z57: 2247 | AA57: =+Z57*H57 -> 2247
C58: ● | F58: MAIN W/H (RWD) | G58: TZ38-10B694-B | H58: 1 | I58: KSCE | J58: 0 | K58: 31 | L58: 0 | M58: 0 | N58: 0 | O58: 0 | P58: 0 | Q58: 0 | R58: 0 | S58: 3931 | T58: 3931 | U58: 3931 | V58: =SUM(J58:U58) -> 11824 | X58: 11793 | Y58: =V58-X58 -> 31 | Z58: 11793 | AA58: =+Z58*H58 -> 11793
C59: ● | F59: BUS BAR ASY_A | G59: TZ38-14A033-A | H59: 1 | I59: KSCE | J59: 0 | K59: 68 | L59: 0 | M59: 0 | N59: 0 | O59: 0 | P59: 0 | Q59: 0 | R59: 0 | S59: 4680 | T59: 4680 | U59: 4680 | V59: =SUM(J59:U59) -> 14108 | X59: 14040 | Y59: =V59-X59 -> 68 | Z59: 14040 | AA59: =+Z59*H59 -> 14040
C60: ● | F60: BUS BAR ASY_B | G60: TZ38-14A033-B | H60: 2 | I60: KSCE | J60: 0 | K60: 136 | L60: 0 | M60: 0 | N60: 0 | O60: 0 | P60: 0 | Q60: 0 | R60: 0 | S60: 9360 | T60: 9360 | U60: 9360 | V60: =SUM(J60:U60) -> 28216 | X60: 28080 | Y60: =V60-X60 -> 136 | Z60: 14040 | AA60: =+Z60*H60 -> 28080
C61: ● | F61: BUS BAR ASY_C | G61: TZ38-14A033-C | H61: 1 | I61: KSCE | J61: 0 | K61: 68 | L61: 0 | M61: 0 | N61: 0 | O61: 0 | P61: 0 | Q61: 0 | R61: 0 | S61: 4680 | T61: 4680 | U61: 4680 | V61: =SUM(J61:U61) -> 14108 | X61: 14040 | Y61: =V61-X61 -> 68 | Z61: 14040 | AA61: =+Z61*H61 -> 14040
C62: ● | F62: BUS BAR ASY_D | G62: TZ38-14A033-D | H62: 1 | I62: KSCE | J62: 0 | K62: 68 | L62: 0 | M62: 0 | N62: 0 | O62: 0 | P62: 0 | Q62: 0 | R62: 0 | S62: 4680 | T62: 4680 | U62: 4680 | V62: =SUM(J62:U62) -> 14108 | X62: 14040 | Y62: =V62-X62 -> 68 | Z62: 14040 | AA62: =+Z62*H62 -> 14040
C63: ● | F63: BUS BAR ASY_E | G63: TZ38-14A033-E | H63: 1 | I63: KSCE | J63: 0 | K63: 68 | L63: 0 | M63: 0 | N63: 0 | O63: 0 | P63: 0 | Q63: 0 | R63: 0 | S63: 4680 | T63: 4680 | U63: 4680 | V63: =SUM(J63:U63) -> 14108 | X63: 14040 | Y63: =V63-X63 -> 68 | Z63: 14040 | AA63: =+Z63*H63 -> 14040
C64: ● | F64: BUS BAR ASY_G | G64: TZ38-14A033-G | H64: 1 | I64: KSCE | J64: 0 | K64: 68 | L64: 0 | M64: 0 | N64: 0 | O64: 0 | P64: 0 | Q64: 0 | R64: 0 | S64: 4680 | T64: 4680 | U64: 4680 | V64: =SUM(J64:U64) -> 14108 | X64: 14040 | Y64: =V64-X64 -> 68 | Z64: 14040 | AA64: =+Z64*H64 -> 14040
C65: ● | F65: BUSBAR - Array to Array (Angled)_Insert | G65: TZ38-14A033-K | H65: 3 | I65: 터키 현지 외주 | J65: 0 | K65: 204 | L65: 0 | M65: 0 | N65: 0 | O65: 0 | P65: 0 | Q65: 0 | R65: 0 | S65: 14040 | T65: 14040 | U65: 14040 | V65: =SUM(J65:U65) -> 42324 | X65: 42120 | Y65: =V65-X65 -> 204 | Z65: 14040 | AA65: =+Z65*H65 -> 42120
C66: ● | F66: BUSBAR - Array 1 to Neg BEC_OVERMOLD | G66: TZ38-14A033-M | H66: 1 | I66: 터키 현지 외주 | J66: 0 | K66: 68 | L66: 0 | M66: 0 | N66: 0 | O66: 0 | P66: 0 | Q66: 0 | R66: 0 | S66: 4680 | T66: 4680 | U66: 4680 | V66: =SUM(J66:U66) -> 14108 | X66: 14040 | Y66: =V66-X66 -> 68 | Z66: 14040 | AA66: =+Z66*H66 -> 14040
C67: ● | F67: BUSBAR - Pos BEC to DCFC_Protector | G67: PZ38-14A033-M | H67: 1 | I67: 터키 현지 외주 | J67: 0 | K67: 68 | L67: 0 | M67: 0 | N67: 0 | O67: 0 | P67: 0 | Q67: 0 | R67: 0 | S67: 4680 | T67: 4680 | U67: 4680 | V67: =SUM(J67:U67) -> 14108 | X67: 14040 | Y67: =V67-X67 -> 68 | Z67: 14040 | AA67: =+Z67*H67 -> 14040
C68: ● | F68: BUSBAR-CIRCUIT BREAKER_R_OVERMOLD | G68: TZ38-14A033-L | H68: 1 | I68: 터키 현지 외주 | J68: 0 | K68: 68 | L68: 0 | M68: 0 | N68: 0 | O68: 0 | P68: 0 | Q68: 0 | R68: 0 | S68: 4680 | T68: 4680 | U68: 4680 | V68: =SUM(J68:U68) -> 14108 | X68: 14040 | Y68: =V68-X68 -> 68 | Z68: 14040 | AA68: =+Z68*H68 -> 14040
C69: ● | F69: PDU ASSY | G69: TZ38-14B680-A | H69: 1 | I69: KSCE | J69: 0 | K69: 68 | L69: 0 | M69: 0 | N69: 0 | O69: 0 | P69: 0 | Q69: 0 | R69: 0 | S69: 4680 | T69: 4680 | U69: 4680 | V69: =SUM(J69:U69) -> 14108 | X69: 14040 | Y69: =V69-X69 -> 68 | Z69: 14040 | AA69: =+Z69*H69 -> 14040
B70: FORD EV-V4 Parts | D70: ● | F70: PZ38-10B694-B-PIA-02 | G70: BEE22-CT009 | H70: 1 | I70: 터키 현지 외주 | J70: 0 | K70: 68 | L70: 0 | M70: 0 | N70: 0 | O70: 0 | P70: 0 | Q70: 0 | R70: 0 | S70: 4680 | T70: 4680 | U70: 4680 | V70: =SUM(J70:U70) -> 14108 | X70: 0 | Y70: 연결 매출계획 미반영 | Z70: #N/A | AA70: =+Z70*H70 -> #N/A
D71: ● | F71: PZ38-10B694-B-PIA-03 | G71: BEE22-CT010 | H71: 1 | I71: 터키 현지 외주 | J71: 0 | K71: 68 | L71: 0 | M71: 0 | N71: 0 | O71: 0 | P71: 0 | Q71: 0 | R71: 0 | S71: 4680 | T71: 4680 | U71: 4680 | V71: =SUM(J71:U71) -> 14108 | X71: 0 | Y71: 연결 매출계획 미반영 | Z71: #N/A | AA71: =+Z71*H71 -> #N/A
D72: ● | F72: PZ38-10B694-B-PIA-04 | G72: BEE22-CT011 | H72: 2 | I72: 터키 현지 외주 | J72: 0 | K72: 136 | L72: 0 | M72: 0 | N72: 0 | O72: 0 | P72: 0 | Q72: 0 | R72: 0 | S72: 9360 | T72: 9360 | U72: 9360 | V72: =SUM(J72:U72) -> 28216 | X72: 0 | Y72: 연결 매출계획 미반영 | Z72: #N/A | AA72: =+Z72*H72 -> #N/A
D73: ● | F73: TZ38-10B694-A-PIA-06 | G73: BEE24-CP002 | H73: 4 | I73: 터키 현지 외주 | J73: 0 | K73: 272 | L73: 0 | M73: 0 | N73: 0 | O73: 0 | P73: 0 | Q73: 0 | R73: 0 | S73: 18720 | T73: 18720 | U73: 18720 | V73: =SUM(J73:U73) -> 56432 | X73: 0 | Y73: 연결 매출계획 미반영 | Z73: #N/A | AA73: =+Z73*H73 -> #N/A
D74: ● | F74: TZ38-10B694-A-PIA-07 | G74: BEE24-CP003-01 | H74: 1 | I74: 터키 현지 외주 | J74: 0 | K74: 68 | L74: 0 | M74: 0 | N74: 0 | O74: 0 | P74: 0 | Q74: 0 | R74: 0 | S74: 4680 | T74: 4680 | U74: 4680 | V74: =SUM(J74:U74) -> 14108 | X74: 0 | Y74: 연결 매출계획 미반영 | Z74: #N/A | AA74: =+Z74*H74 -> #N/A
D75: ● | F75: TZ38-10B694-A-PIA-02 | G75: BEE25-CT001-02 | H75: 2 | I75: 터키 현지 외주 | J75: 0 | K75: 74 | L75: 0 | M75: 0 | N75: 0 | O75: 0 | P75: 0 | Q75: 0 | R75: 0 | S75: 1498 | T75: 1498 | U75: 1498 | V75: =SUM(J75:U75) -> 4568 | X75: 0 | Y75: 연결 매출계획 미반영 | Z75: #N/A | AA75: =+Z75*H75 -> #N/A
D76: ● | F76: TZ38-10B694-A-PIA-05 | G76: BEE24-CP001-01 | H76: 1 | I76: 터키 현지 외주 | J76: 0 | K76: 37 | L76: 0 | M76: 0 | N76: 0 | O76: 0 | P76: 0 | Q76: 0 | R76: 0 | S76: 749 | T76: 749 | U76: 749 | V76: =SUM(J76:U76) -> 2284 | X76: 0 | Y76: 연결 매출계획 미반영 | Z76: #N/A | AA76: =+Z76*H76 -> #N/A
D77: ● | F77: PZ38-14B680-A-PIA-04 | G77: BEE22-CP007 | H77: 1 | I77: 터키 현지 외주 | J77: 0 | K77: 68 | L77: 0 | M77: 0 | N77: 0 | O77: 0 | P77: 0 | Q77: 0 | R77: 0 | S77: 4680 | T77: 4680 | U77: 4680 | V77: =SUM(J77:U77) -> 14108 | X77: 0 | Y77: 연결 매출계획 미반영 | Z77: #N/A | AA77: =+Z77*H77 -> #N/A
A80: 2. 판매가(EURO 기준가) | G80: *LME 동가격, 임률 등 매개변수가 있으나, 매입가 변경 시 매출가도 비례하게 변동되므로 고정된 가격 사용 (현재 하반기 임율 미확정으로, 상반기 임율 € 16.47/hr 사용) | W80: 단위 : EURO
A81: 구분 | B81: 차종 | C81: LEVEL | F81: 아이템 | G81: 품번 | H81: U/S | I81: 비고 | J81: 판매가(EURO) | W81: 비고 | X81: 연결매출 판가 | Y81: 차이
C82: 1 | D82: 2 | E82: 3 | J82: 1월 | K82: 2월 | L82: 3월 | M82: 4월 | N82: 5월 | O82: 6월 | P82: 7월 | Q82: 8월 | R82: 9월 | S82: 10월 | T82: 11월 | U82: 12월 | V82: TOTAL | X82: (영업팀)
A83: Battery | B83: FORD PHEV-E Ford Otosan | C83: ● | F83: MAIN W/H | G83: PZ38-10B694-AC | H83: 1 | I83: 터키 현지 외주 | J83: 92.929 | K83: 92.929 | L83: 92.929 | M83: 92.929 | N83: 92.929 | O83: 92.929 | P83: 92.929 | Q83: 92.929 | R83: 92.929 | S83: 92.929 | T83: 92.929 | U83: 92.929 | W83: ▶ 유럽 向 | Z83: 92.929 | AA83: =+Z83-U83 -> 0
A84: Pack | C84: ● | F84: BEC to ISC Conn (JUMPER) | G84: PZ38-14B252-AB | H84: 1 | I84: 터키 현지 외주 | J84: 18.9525 | K84: 18.9525 | L84: 18.9525 | M84: 18.9525 | N84: 18.9525 | O84: 18.9525 | P84: 18.9525 | Q84: 18.9525 | R84: 18.9525 | S84: 18.9525 | T84: 18.9525 | U84: 18.9525 | W84: ↑ | Z84: 18.9525 | AA84: =+Z84-U84 -> 0
C85: ● | F85: BUSBAR - Array to Array (short) | G85: PZ38-14A033-AB | H85: 3 | I85: 터키 현지 외주 | J85: 3.6399168 | K85: 3.6399168 | L85: 3.6399168 | M85: 3.6399168 | N85: 3.6399168 | O85: 3.6399168 | P85: 3.6399168 | Q85: 3.6399168 | R85: 3.6399168 | S85: 3.6399168 | T85: 3.6399168 | U85: 3.6399168 | W85: ↑ | Z85: 3.6399168 | AA85: =+Z85-U85 -> 0
C86: ● | F86: BUSBAR - Array to Array (long) | G86: PZ38-14A033-BB | H86: 3 | I86: 터키 현지 외주 | J86: 4.9877997 | K86: 4.9877997 | L86: 4.9877997 | M86: 4.9877997 | N86: 4.9877997 | O86: 4.9877997 | P86: 4.9877997 | Q86: 4.9877997 | R86: 4.9877997 | S86: 4.9877997 | T86: 4.9877997 | U86: 4.9877997 | W86: ↑ | Z86: 4.9877997 | AA86: =+Z86-U86 -> 0
C87: ● | F87: BUSBAR - Array 3 to 4 | G87: PZ38-14A033-CB | H87: 1 | I87: 터키 현지 외주 | J87: 2.441216 | K87: 2.441216 | L87: 2.441216 | M87: 2.441216 | N87: 2.441216 | O87: 2.441216 | P87: 2.441216 | Q87: 2.441216 | R87: 2.441216 | S87: 2.441216 | T87: 2.441216 | U87: 2.441216 | W87: ↑ | Z87: 2.441216 | AA87: =+Z87-U87 -> 0
B88: FORD PHEV-E S/Africa | C88: ● | F88: MAIN W/H | G88: PZ38-10B694-AC | H88: 1 | I88: 터키 현지 외주 | J88: 97.82 | K88: 97.82 | L88: 97.82 | M88: 97.82 | N88: 97.82 | O88: 97.82 | P88: 97.82 | Q88: 97.82 | R88: 97.82 | S88: 97.82 | T88: 97.82 | U88: 97.82 | W88: ▶ 아프리카 向 * P703 Forecast 8월부터 이전 6개월 평균 계산 | Z88: 97.82 | AA88: =+Z88-U88 -> 0
C89: ● | F89: BEC to ISC Conn (JUMPER) | G89: PZ38-14B252-AB | H89: 1 | I89: 터키 현지 외주 | J89: 19.95 | K89: 19.95 | L89: 19.95 | M89: 19.95 | N89: 19.95 | O89: 19.95 | P89: 19.95 | Q89: 19.95 | R89: 19.95 | S89: 19.95 | T89: 19.95 | U89: 19.95 | W89: ↑ | Z89: 19.95 | AA89: =+Z89-U89 -> 0
C90: ● | F90: BUSBAR - Array to Array (short) | G90: PZ38-14A033-AB | H90: 3 | I90: 터키 현지 외주 | J90: 3.8314914 | K90: 3.8314914 | L90: 3.8314914 | M90: 3.8314914 | N90: 3.8314914 | O90: 3.8314914 | P90: 3.8314914 | Q90: 3.8314914 | R90: 3.8314914 | S90: 3.8314914 | T90: 3.8314914 | U90: 3.8314914 | W90: ↑ | Z90: 3.8314914 | AA90: =+Z90-U90 -> 0
C91: ● | F91: BUSBAR - Array to Array (long) | G91: PZ38-14A033-BB | H91: 3 | I91: 터키 현지 외주 | J91: 5.2503155 | K91: 5.2503155 | L91: 5.2503155 | M91: 5.2503155 | N91: 5.2503155 | O91: 5.2503155 | P91: 5.2503155 | Q91: 5.2503155 | R91: 5.2503155 | S91: 5.2503155 | T91: 5.2503155 | U91: 5.2503155 | W91: ↑ | Z91: 5.2503155 | AA91: =+Z91-U91 -> 0
C92: ● | F92: BUSBAR - Array 3 to 4 | G92: PZ38-14A033-CB | H92: 1 | I92: 터키 현지 외주 | J92: 2.569701 | K92: 2.569701 | L92: 2.569701 | M92: 2.569701 | N92: 2.569701 | O92: 2.569701 | P92: 2.569701 | Q92: 2.569701 | R92: 2.569701 | S92: 2.569701 | T92: 2.569701 | U92: 2.569701 | W92: ↑ | Z92: 2.569701 | AA92: =+Z92-U92 -> 0
B93: FORD BEV-E1 RWD | C93: ● | F93: MAIN W/H RWD | G93: TZ38-10B694-DB | H93: 1 | I93: 터키 현지 외주 | J93: 133.27 | K93: 133.27 | L93: 133.27 | M93: 133.27 | N93: 133.27 | O93: 133.27 | P93: 133.27 | Q93: 133.27 | R93: 133.27 | S93: 133.27 | T93: 133.27 | U93: 133.27 | W93: * RWD 10월 단산 | Z93: 133.27 | AA93: =+Z93-U93 -> 0
C94: ● | F94: CONN ASSY (PDU) | G94: TZ38-14B680-BB | H94: 1 | I94: 터키 현지 외주 | J94: 27.35 | K94: 27.35 | L94: 27.35 | M94: 27.35 | N94: 27.35 | O94: 27.35 | P94: 27.35 | Q94: 27.35 | R94: 27.35 | S94: 27.35 | T94: 27.35 | U94: 27.35 | Z94: 27.35 | AA94: =+Z94-U94 -> 0
C95: ● | F95: BUSBAR - Array to Array (Straight)_Insert | G95: TZ38-14A033-FA | H95: 1 | I95: 터키 현지 외주 | J95: 18.516391 | K95: 18.516391 | L95: 18.516391 | M95: 18.516391 | N95: 18.516391 | O95: 18.516391 | P95: 18.516391 | Q95: 18.516391 | R95: 18.516391 | S95: 18.516391 | T95: 18.516391 | U95: 18.516391 | Z95: 18.516391 | AA95: =+Z95-U95 -> 0
C96: ● | F96: BUSBAR - Array to Array (Angled)_Insert | G96: TZ38-14A033-HB | H96: 3 | I96: 터키 현지 외주 | J96: 16.057014 | K96: 16.057014 | L96: 16.057014 | M96: 16.057014 | N96: 16.057014 | O96: 16.057014 | P96: 16.057014 | Q96: 16.057014 | R96: 16.057014 | S96: 16.057014 | T96: 16.057014 | U96: 16.057014 | Z96: 16.057014 | AA96: =+Z96-U96 -> 0
C97: ● | F97: BUSBAR - Array 1 to Neg BEC_Insert | G97: TZ38-14A033-SA | H97: 1 | I97: 터키 현지 외주 | J97: 21.85106 | K97: 21.85106 | L97: 21.85106 | M97: 21.85106 | N97: 21.85106 | O97: 21.85106 | P97: 21.85106 | Q97: 21.85106 | R97: 21.85106 | S97: 21.85106 | T97: 21.85106 | U97: 21.85106 | Z97: 21.85106 | AA97: =+Z97-U97 -> 0
C98: ● | F98: BUSBAR - Array4 to Array 5_Insert | G98: PZ38-14A033-HF | H98: 1 | I98: 터키 현지 외주 | J98: 14.817426 | K98: 14.817426 | L98: 14.817426 | M98: 14.817426 | N98: 14.817426 | O98: 14.817426 | P98: 14.817426 | Q98: 14.817426 | R98: 14.817426 | S98: 14.817426 | T98: 14.817426 | U98: 14.817426 | Z98: 14.817426 | AA98: =+Z98-U98 -> 0
C99: ● | F99: BUSBAR - Array 8 to Array 9_Insert | G99: TZ38-14A033-JB | H99: 1 | I99: 터키 현지 외주 | J99: 18.343874 | K99: 18.343874 | L99: 18.343874 | M99: 18.343874 | N99: 18.343874 | O99: 18.343874 | P99: 18.343874 | Q99: 18.343874 | R99: 18.343874 | S99: 18.343874 | T99: 18.343874 | U99: 18.343874 | Z99: 18.343874 | AA99: =+Z99-U99 -> 0
C100: ● | F100: BUSBAR - Array 9 to Pos BEC_Insert | G100: PZ38-14A033-LF | H100: 1 | I100: 터키 현지 외주 | J100: 9.740943 | K100: 9.740943 | L100: 9.740943 | M100: 9.740943 | N100: 9.740943 | O100: 9.740943 | P100: 9.740943 | Q100: 9.740943 | R100: 9.740943 | S100: 9.740943 | T100: 9.740943 | U100: 9.740943 | Z100: 9.740943 | AA100: =+Z100-U100 -> 0
C101: ● | F101: BUSBAR - Pos BEC to DCFC_Protector | G101: PZ38-14A033-MC | H101: 1 | I101: 터키 현지 외주 | J101: 20.249661 | K101: 20.249661 | L101: 20.249661 | M101: 20.249661 | N101: 20.249661 | O101: 20.249661 | P101: 20.249661 | Q101: 20.249661 | R101: 20.249661 | S101: 20.249661 | T101: 20.249661 | U101: 20.249661 | Z101: 20.249661 | AA101: =+Z101-U101 -> 0
C102: ● | F102: BUSBAR - Neg BEC to DCFC_Protector | G102: TZ38-14A033-NA | H102: 1 | I102: 터키 현지 외주 | J102: 15.798673 | K102: 15.798673 | L102: 15.798673 | M102: 15.798673 | N102: 15.798673 | O102: 15.798673 | P102: 15.798673 | Q102: 15.798673 | R102: 15.798673 | S102: 15.798673 | T102: 15.798673 | U102: 15.798673 | Z102: 15.798673 | AA102: =+Z102-U102 -> 0
...

Sheet 2. Service
B1: ▣ Service sumarry
B4: Service Companies | D4: Jan | E4: Feb | F4: Mar | G4: Apr | H4: May | I4: Jun | J4: Jul | K4: Aug | L4: Sep | M4: Oct | N4: Nov | O4: Dec | P4: Total | Q4: Remark | R4: Remark
B5: Tax Accounting & Audit (VDY) | C5: Consultancy | D5: =+D60 -> 121232 | E5: =+E60 -> 121232 | F5: =+F60 -> 121232 | G5: =+G60 -> 121232 | H5: =+H60 -> 121232 | I5: =+I60 -> 121232 | J5: =+J60 -> 121232 | K5: =+K60 -> 121232 | ... O5: =+O60 -> 121232 | P5: =SUM(D5:O5) -> 1454784
B6: Legal Advice Service (Tao-r) | C6: Account | D6: 35512.634 | E6: 35512.634 | F6: 35512.634 | G6: 35512.634 | H6: 35512.634 | I6: 35512.634 | J6: 35512.634 | K6: 35512.634 | L6: 35512.634 | M6: 35512.634 | N6: 35512.634 | O6: 35512.634 | P6: =SUM(D6:O6) -> 426151.61
B7: Notary / Translation expenses | D7: 6000 | E7: - | F7: - | G7: 6000 | H7: - | I7: - | J7: 6000 | K7: - | L7: - | M7: 6000 | N7: - | O7: - | P7: =SUM(D7:O7) -> 24000 | Q7: 4회/년 | R7: Notery payment
B8: Cargo Expenses for urgent service | D8: 5000 | E8: 5000 | F8: 5000 | G8: 5000 | H8: 5000 | I8: 5000 | J8: 5000 | K8: 5000 | L8: 5000 | M8: 5000 | N8: 5000 | O8: 5000 | P8: =SUM(D8:O8) -> 60000
B9: 총합 | C9: - | D9: =SUM(D5:D7) -> 162744.63 | E9: =SUM(E5:E7) -> 156744.63 | F9: =SUM(F5:F7) -> 156744.63 | G9: =SUM(G5:G7) -> 162744.63 | H9: =SUM(H5:H7) -> 156744.63 | I9: =SUM(I5:I7) -> 156744.63 | J9: =SUM(J5:J7) -> 162744.63 | K9: =SUM(K5:K7) -> 156744.63 | ... P9: =SUM(P5:P7) -> 1904935.6
B12: ▣ IT Service
B15: 2025
B16: Company | C16: Detail | D16: Payment Status | E16: Jan | F16: Jan | G16: Feb | H16: Feb | I16: Mar | J16: Mar | K16: Apr | L16: Apr | M16: May | N16: May | O16: Jun | P16: Jun | Q16: July | R16: July | S16: Aug | T16: Aug | U16: Sept | V16: Sept | W16: Oct | X16: Oct | Y16: Nov | Z16: Nov | AA16: Dec | AB16: Dec | AC16: Yearly Avarage | AD16: Contact
E17: USD | F17: TL | G17: USD | H17: TL | I17: USD | J17: TL | K17: USD | L17: TL | M17: USD | N17: TL | O17: USD | P17: TL | Q17: USD | R17: TL | S17: USD | T17: TL | U17: USD | V17: TL | W17: USD | X17: TL | Y17: USD | Z17: TL | AA17: USD | AB17: TL | AD17: 2024.6~2025.6
E18: 35.52 | G18: 36.17 | I18: 37.09 | K18: 38.13 | M18: 38.83 | O18: 39.48 | Q18: 40.24 | S18: 40.86 | U18: 41.35 | W18: 41.85 | Y18: 42.18
B19: RINT | C19: DATA CENTER | D19: Montly | E19: 653.22269 | F19: 23202.47 | G19: 641.48383 | H19: 23202.47 | I19: 625.57212 | J19: 23202.47 | K19: 608.50957 | L19: 23202.47 | M19: 597.53979 | N19: 23202.47 | O19: 587.70187 | P19: 23202.47 | Q19: 576.60214 | R19: 23202.47 | S19: 567.85291 | T19: 23202.47 | U19: 565.34921 | V19: 23202.47 | W19: 562.76965 | X19: 23202.47 | Y19: 562.50901 | Z19: 23202.47 | AA19: 562.50901 | AB19: 23202.47 | AC19: =SUM(F19,H19,J19,L19,N19,P19,R19,T19,V19,X19,Z19,AB19) -> 278429.64
C20: SQL SERVICE | D20: Montly | F20: 6800.79 | H20: 6800.79 | J20: 6800.79 | L20: 6800.79 | N20: 6800.79 | P20: 6800.79 | R20: 6800.79 | T20: 6800.79 | U20: 164.46892 | V20: 6800.79 | X20: 6800.79 | Z20: 6800.79 | AB20: 6800.79 | AC20: =SUM(F20,H20,J20,L20,N20,P20,R20,T20,V20,X20,Z20,AB20) -> 81609.48
B21: Proser | C21: Fortigate | D21: YEARLY | U21: 1100 | V21: 54710 | AC21: =SUM(F21,H21,J21,L21,N21,P21,R21,T21,V21,X21,Z21,AB21) -> 54710
C22: Fortilogger | D22: YEARLY | AC22: =SUM(F22,H22,J22,L22,N22,P22,R22,T22,V22,X22,Z22,AB22) -> 0
C23: IT SERVICE FEE | D23: Montly | O23: 577.5076 | P23: 22800 | Q23: 566.6004 | R23: 22800 | S23: 558.00294 | T23: 22800 | U23: 551.39057 | V23: 22800 | W23: 544.80287 | X23: 22800 | Y23: 540.54054 | Z23: 22800 | AA23: 540.54054 | AB23: 22800 | AC23: =SUM(F23,H23,J23,L23,N23,P23,R23,T23,V23,X23,Z23,AB23) -> 159600
B24: Chip Computer | C24: LICENCE LOGO | D24: YEARLY | M24: 3862.9925 | N24: 150000 | W24: 3022.9746 | X24: 125000 | AC24: =SUM(F24,H24,J24,L24,N24,P24,R24,T24,V24,X24,Z24,AB24) -> 275000
C25: LEM LICENCE | D25: YEARLY | U25: 725.51391 | V25: 30000 | W25: 716.84588 | X25: 30000 | Y25: 711.23755 | Z25: 30000 | AB25: 30000 | AC25: =SUM(F25,H25,J25,L25,N25,P25,R25,T25,V25,X25,Z25,AB25) -> 120000
C26: LOGO TIGER | D26: YEARLY | M26: 2034.5094 | N26: 79000 | AC26: =SUM(F26,H26,J26,L26,N26,P26,R26,T26,V26,X26,Z26,AB26) -> 79000
B27: HRSI (KOLAY İK) | D27: YEARLY | AB27: 26006 | AC27: =AB27 -> 26006
AC28: =SUM(AC19:AC27) -> 1074355.1
B29: 2026
B30: Company | C30: Detail | D30: Payment Status | E30: Jan | F30: Jan | G30: Feb | H30: Feb | I30: Mar | J30: Mar | K30: Apr | L30: Apr | M30: May | N30: May | O30: Jun | P30: Jun | Q30: July | R30: July | S30: Aug | T30: Aug | U30: Sept | V30: Sept | W30: Oct | X30: Oct | Y30: Nov | Z30: Nov | AA30: Dec | AB30: Dec | AC30: Yearly Avarage
E31: USD | F31: TL | G31: USD | H31: TL | I31: USD | J31: TL | K31: USD | L31: TL | M31: USD | N31: TL | O31: USD | P31: TL | Q31: USD | R31: TL | S31: USD | T31: TL | U31: USD | V31: TL | W31: USD | X31: TL | Y31: USD | Z31: TL | AA31: USD | AB31: TL
B33: RINT | C33: DATA CENTER | D33: Montly | F33: =23202.47*1.3 -> 30163.211 | H33: =23202.47*1.3 -> 30163.211 | J33: =23202.47*1.3 -> 30163.211 | L33: =23202.47*1.3 -> 30163.211 | M33: - | N33: =23202.47*1.3 -> 30163.211 | P33: =23202.47*1.3 -> 30163.211 | R33: =23202.47*1.3 -> 30163.211 | T33: =23202.47*1.3 -> 30163.211 | V33: =23202.47*1.3 -> 30163.211 | X33: =23202.47*1.3 -> 30163.211 | Z33: =23202.47*1.3 -> 30163.211 | AB33: =23202.47*1.3 -> 30163.211 | AC33: =SUM(F33,H33,J33,L33,N33,P33,R33,T33,V33,X33,Z33,AB33) -> 361958.53
C34: SQL SERVICE | D34: Montly | F34: =6800.79*1.3 -> 8841.027 | H34: =6800.79*1.3 -> 8841.027 | J34: =6800.79*1.3 -> 8841.027 | L34: =6800.79*1.3 -> 8841.027 | N34: =6800.79*1.3 -> 8841.027 | P34: =6800.79*1.3 -> 8841.027 | R34: =6800.79*1.3 -> 8841.027 | T34: =6800.79*1.3 -> 8841.027 | V34: =6800.79*1.3 -> 8841.027 | X34: =6800.79*1.3 -> 8841.027 | Z34: =6800.79*1.3 -> 8841.027 | AB34: =6800.79*1.3 -> 8841.027 | AC34: =SUM(F34,H34,J34,L34,N34,P34,R34,T34,V34,X34,Z34,AB34) -> 106092.32
B35: Proser | C35: FORTIGATE | D35: YEARLY | F35: - | V35: =54582*1.3 -> 70956.6 | AC35: =SUM(F35,H35,J35,L35,N35,P35,R35,T35,V35,X35,Z35,AB35) -> 70956.6
C36: Fortigate | D36: YEARLY | F36: - | AC36: =SUM(F36,H36,J36,L36,N36,P36,R36,T36,V36,X36,Z36,AB36) -> 0
C37: IT SERVICE FEE | D37: Montly | F37: 22800 | H37: 22800 | J37: 22800 | L37: 22800 | N37: 22800 | P37: 22800 | R37: =P37*1.3 -> 29640 | T37: 29640 | V37: 29640 | X37: 29640 | Z37: 29640 | AB37: 29640 | AC37: =SUM(F37,H37,J37,L37,N37,P37,R37,T37,V37,X37,Z37,AB37) -> 314640 | AD37: 30th Jun 2025 ~ 30th Jun 2026 ~
B38: Chip Computer | C38: LICENCE LOGO | D38: YEARLY | N38: 198000 | AC38: =SUM(F38,H38,J38,L38,N38,P38,R38,T38,V38,X38,Z38,AB38) -> 198000
C39: LEM LICENCE | D39: YEARLY | F39: 39600 | H39: 39600 | J39: 39600 | L39: 39600 | N39: 39600 | P39: 39600 | R39: 39600 | T39: 39600 | V39: 39600 | X39: 39600 | Z39: 39600 | AB39: 39600 | AC39: =SUM(F39,H39,J39,L39,N39,P39,R39,T39,V39,X39,Z39,AB39) -> 475200
C40: Logo system update | D40: YEARLY | AB40: 182378 | AC40: =SUM(F40,H40,J40,L40,N40,P40,R40,T40,V40,X40,Z40,AB40) -> 182378
C41: LOGO TIGER | D41: YEARLY | F41: 182378.4 | AC41: =SUM(F41,H41,J41,L41,N41,P41,R41,T41,V41,X41,Z41,AB41) -> 182378.4
B42: HRSI (KOLAY İK) | D42: YEARLY | M42: - | O42: - | Q42: - | AB42: 34328.448 | AC42: =SUM(F42,H42,J42,L42,N42,P42,R42,T42,V42,X42,Z42,AB42) -> 34328.448
AC43: =SUM(AC32:AC42) -> 1925932.3
D46: IT service | E46: Jan | F46: Feb | G46: Mar | H46: Apr | I46: May | J46: Jun | K46: Jul | L46: Aug | M46: Sep | N46: Oct | O46: Nov | P46: Dec | Q46: Total
D47: Total | E47: =SUM(F33:F42) -> 283782.64 | F47: =SUM(H33:H42) -> 101404.24 | G47: =SUM(J33:J42) -> 101404.24 | H47: =SUM(L33:L42) -> 101404.24 | I47: =SUM(N33:N42) -> 299404.24 | J47: =SUM(P33:P42) -> 101404.24 | K47: =SUM(R33:R42) -> 108244.24 | L47: =SUM(T33:T42) -> 108244.24 | M47: =SUM(V33:V42) -> 179200.84 | N47: =SUM(X33:X42) -> 108244.24 | O47: =SUM(Z33:Z42) -> 108244.24 | P47: =SUM(AB33:AB42) -> 324950.69 | Q47: =SUM(E47:P47) -> 1925932.3
B50: ▣ Tax Accounting & Audit (VDY)
B53: Service Companies | C53: Frequency | D53: Jan | E53: Feb | F53: Mar | G53: Apr | H53: May | I53: Jun | J53: Jul | K53: Aug | L53: Sep | M53: Oct | N53: Nov | O53: Dec | P53: Total
B54: Transfer Pricing Services | C54: Annual (one time) | P54: =SUM(D54:O54) -> 0
B55: Audit Services | C55: Monthly | D55: 30000 | E55: 30000 | F55: 30000 | G55: 30000 | H55: 30000 | I55: 30000 | J55: 30000 | K55: 30000 | L55: 30000 | M55: 30000 | N55: 30000 | O55: 30000 | P55: =SUM(D55:O55) -> 360000
B56: Payroll Services | C56: Monthly | D56: 91232 | E56: 91232 | F56: 91232 | G56: 91232 | H56: 91232 | I56: 91232 | J56: 91232 | K56: 91232 | L56: 91232 | M56: 91232 | N56: 91232 | O56: 91232 | P56: =SUM(D56:O59) -> 1094784
B57: Preparation of Declaration | C57: Monthly
B58: Quarterly Reporting Of Financial Statements | C58: Quarterly
B59: VAT Refund | C59: Just in time
B60: 총합 | C60: - | D60: =SUM(D54:D59) -> 121232 | E60: =SUM(E54:E59) -> 121232 | F60: =SUM(F54:F59) -> 121232 | G60: =SUM(G54:G59) -> 121232 | H60: =SUM(H54:H59) -> 121232 | I60: =SUM(I54:I59) -> 121232 | J60: =SUM(J54:J59) -> 121232 | K60: =SUM(K54:K59) -> 121232 | ... P60: =SUM(P54:P59) -> 1454784

Sheet 3. HR
E1: 26 KCTR H/R Plan
A6: Month | E6: Jan | F6: Feb | G6: Mar | H6: Apr | I6: May | J6: Jun | K6: Jul | L6: Aug | M6: Sept | N6: Oct | O6: Nov | P6: Dec
A7: Total Number of employees | E7: =SUM(E9:E11) -> 23 | F7: =SUM(F9:F11) -> 24 | G7: =SUM(G9:G11) -> 24 | H7: =SUM(H9:H11) -> 24 | I7: =SUM(I9:I11) -> 24 | J7: =SUM(J9:J11) -> 24 | K7: =SUM(K9:K11) -> 25 | L7: =SUM(L9:L11) -> 27 | ... P7: =SUM(P9:P11) -> 27
A8: New employees | E8: 1 | F8: 1 | K8: 1 | L8: 2
A9: 주재원 | E9: =SUM(E13,E14,E36) -> 2 | F9: =SUM(F13,F14,F36) -> 2 | G9: =SUM(G13,G14,G36) -> 2 | H9: =SUM(H13,H14,H36) -> 2 | I9: =SUM(I13,I14,I36) -> 2 | J9: =SUM(J13,J14,J36) -> 2 | K9: =SUM(K13,K14,K36) -> 3 | L9: =SUM(L13,L14,L36) -> 3 | ... P9: =SUM(P13,P14,P36) -> 3
A10: Accounting-Finance Personel | E10: =SUM(E15:E23)+SUM(E37,E38) -> 10 | F10: =SUM(F15:F23)+SUM(F37,F38) -> 11 | G10: =SUM(G15:G23)+SUM(G37,G38) -> 11 | H10: =SUM(H15:H23)+SUM(H37,H38) -> 11 | I10: =SUM(I15:I23)+SUM(I37,I38) -> 11 | J10: =SUM(J15:J23)+SUM(J37,J38) -> 11 | K10: =SUM(K15:K23)+SUM(K37,K38) -> 11 | L10: =SUM(L15:L23)+SUM(L37,L38) -> 11 | ... P10: =SUM(P15:P23)+SUM(P37,P38) -> 11
A11: Manufacturing Personel | E11: =SUM(E24:E34)+SUM(E39,E40) -> 11 | F11: =SUM(F24:F34)+SUM(F39,F40) -> 11 | G11: =SUM(G24:G34)+SUM(G39,G40) -> 11 | H11: =SUM(H24:H34)+SUM(H39,H40) -> 11 | I11: =SUM(I24:I34)+SUM(I39,I40) -> 11 | J11: =SUM(J24:J34)+SUM(J39,J40) -> 11 | K11: =SUM(K24:K34)+SUM(K39,K40) -> 11 | L11: =SUM(L24:L34)+SUM(L39,L40) -> 13 | ... P11: =SUM(P24:P34)+SUM(P39,P40) -> 13
A13: 2026년 계획 | B13: General Manager | C13: HM CHO | D13: 주재원 | E13: 1 | F13: 1 | G13: 1 | H13: 1 | I13: 1 | J13: 1 | K13: 1 | L13: 1 | M13: 1 | N13: 1 | O13: 1 | P13: 1
B14: D. General Manager | C14: SH LEE | D14: 주재원 | E14: 1 | F14: 1 | G14: 1 | H14: 1 | I14: 1 | J14: 1 | K14: 1 | L14: 1 | M14: 1 | N14: 1 | O14: 1 | P14: 1
B15: HR/General Affairs | C15: MERVE | D15: Manager | E15: 1 | F15: 1 | G15: 1 | H15: 1 | I15: 1 | J15: 1 | K15: 1 | L15: 1 | M15: 1 | N15: 1 | O15: 1 | P15: 1
C16: Kübra Ceren | D16: Specialist | E16: 1 | F16: 1 | G16: 1 | H16: 1 | I16: 1 | J16: 1 | K16: 1 | L16: 1 | M16: 1 | N16: 1 | O16: 1 | P16: 1
C17: GÜLSÜM | D17: Technician | E17: 1 | F17: 1 | G17: 1 | H17: 1 | I17: 1 | J17: 1 | K17: 1 | L17: 1 | M17: 1 | N17: 1 | O17: 1 | P17: 1
B18: Finance/Account | C18: Özge | D18: Supervisor | E18: 1 | F18: 1 | G18: 1 | H18: 1 | I18: 1 | J18: 1 | K18: 1 | L18: 1 | M18: 1 | N18: 1 | O18: 1 | P18: 1
C19: ÇAĞLA | D19: Specialist | E19: 1 | F19: 1 | G19: 1 | H19: 1 | I19: 1 | J19: 1 | K19: 1 | L19: 1 | M19: 1 | N19: 1 | O19: 1 | P19: 1
C20: Haticenur | D20: Assistant Specialist | E20: 1 | F20: 1 | G20: 1 | H20: 1 | I20: 1 | J20: 1 | K20: 1 | L20: 1 | M20: 1 | N20: 1 | O20: 1 | P20: 1
B21: Sales/Procurement | C21: Melis | D21: Specialist | E21: 1 | F21: 1 | G21: 1 | H21: 1 | I21: 1 | J21: 1 | K21: 1 | L21: 1 | M21: 1 | N21: 1 | O21: 1 | P21: 1
C22: Cagatay | D22: Assistant Specialist | E22: 1 | F22: 1 | G22: 1 | H22: 1 | I22: 1 | J22: 1 | K22: 1 | L22: 1 | M22: 1 | N22: 1 | O22: 1 | P22: 1
C23: Sonbahar | D23: Supervisor | E23: 1 | F23: 1 | G23: 1 | H23: 1 | I23: 1 | J23: 1 | K23: 1 | L23: 1 | M23: 1 | N23: 1 | O23: 1 | P23: 1
B24: MP&L | C24: OZNUR | D24: Manager | E24: 1 | F24: 1 | G24: 1 | H24: 1 | I24: 1 | J24: 1 | K24: 1 | L24: 1 | M24: 1 | N24: 1 | O24: 1 | P24: 1
C25: Murat Öze | D25: Supervisor | E25: 1 | F25: 1 | G25: 1 | H25: 1 | I25: 1 | J25: 1 | K25: 1 | L25: 1 | M25: 1 | N25: 1 | O25: 1 | P25: 1
C26: MERİÇ | D26: Assistant Specialist | E26: 1 | F26: 1 | G26: 1 | H26: 1 | I26: 1 | J26: 1 | K26: 1 | L26: 1 | M26: 1 | N26: 1 | O26: 1 | P26: 1
C27: Tugay | D27: Engineer | E27: 1 | F27: 1 | G27: 1 | H27: 1 | I27: 1 | J27: 1 | K27: 1 | L27: 1 | M27: 1 | N27: 1 | O27: 1 | P27: 1
B28: P/M | C28: Akin | D28: Supervisor | E28: 1 | F28: 1 | G28: 1 | H28: 1 | I28: 1 | J28: 1 | K28: 1 | L28: 1 | M28: 1 | N28: 1 | O28: 1 | P28: 1
C29: CH Park | D29: Specialist | E29: 1 | F29: 1 | G29: 1 | H29: 1 | I29: 1 | J29: 1 | K29: 1 | L29: 1 | M29: 1 | N29: 1 | O29: 1 | P29: 1
B30: Q.C. | C30: CEREN | D30: Manager | E30: 1 | F30: 1 | G30: 1 | H30: 1 | I30: 1 | J30: 1 | K30: 1 | L30: 1 | M30: 1 | N30: 1 | O30: 1 | P30: 1
C31: Sevde | D31: Engineer | E31: 1 | F31: 1 | G31: 1 | H31: 1 | I31: 1 | J31: 1 | K31: 1 | L31: 1 | M31: 1 | N31: 1 | O31: 1 | P31: 1
C32: MUZAFFER(Residents Otosan) | D32: Technician | E32: 1 | F32: 1 | G32: 1 | H32: 1 | I32: 1 | J32: 1 | K32: 1 | L32: 1 | M32: 1 | N32: 1 | O32: 1 | P32: 1
C33: BAHADIR (Residents Nursan) | D33: Technician | E33: 1 | F33: 1 | G33: 1 | H33: 1 | I33: 1 | J33: 1 | K33: 1 | L33: 1 | M33: 1 | N33: 1 | O33: 1 | P33: 1
C34: İBRAHIM (Residents Takosan) | D34: Technician | E34: 1 | F34: 1 | G34: 1 | H34: 1 | I34: 1 | J34: 1 | K34: 1 | L34: 1 | M34: 1 | N34: 1 | O34: 1 | P34: 1
A36: 2026년 중장기 운영 계획 | B36: 영업 (예상) | C36: Korean Manager | D36: Manager | K36: 1 | L36: 1 | M36: 1 | N36: 1 | O36: 1 | P36: 1
B37: Sales | C37: TBD | D37: Engineer | F37: 1 | G37: 1 | H37: 1 | I37: 1 | J37: 1 | K37: 1 | L37: 1 | M37: 1 | N37: 1 | O37: 1 | P37: 1
B38: Purchasing | C38: TBD | D38: Engineer | E38: 1 | F38: 1 | G38: 1 | H38: 1 | I38: 1 | J38: 1 | K38: 1 | L38: 1 | M38: 1 | N38: 1 | O38: 1 | P38: 1
B39: MP&L | C39: TBD | D39: Engineer | L39: 1 | M39: 1 | N39: 1 | O39: 1 | P39: 1
B40: MP&L | C40: TBD | D40: Engineer | L40: 1 | M40: 1 | N40: 1 | O40: 1 | P40: 1
B42: ※ EV-V4 포장사양 협의결과에 따라 변동(KCTR 포장사양 변경시 2명 충원예정) | H42: 총인원 | J42: 주재원 | K42: Manager | L42: Supervisor | M42: Specialist | N42: Engineer | O42: Technician | P42: Total
H43: ‘25.12 | J43: 2 | K43: 2 | L43: 4 | M43: 5 | N43: 5 | O43: 4 | P43: =SUM(J43:O43) -> 22
H44: 26.01 | J44: 2 | K44: 3 | L44: 4 | M44: 4 | N44: 5 | O44: 4 | P44: =SUM(J44:O44) -> 22
H45: `26 long term ('26.12) | J45: 3 | K45: 3 | L45: 4 | M45: 4 | N45: 9 | O45: 4 | P45: =SUM(J45:O45) -> 27

Sheet 4. Salary
B1: ▣ `26 Salary
O4: SGK 총급여의 약 37%
P5: SGK | V5: INCOME TAX
P6: 4대보험 | R6: 실업급여 | V6: 소득세 | W6: 인지세
P7: 근로자 | Q7: 고용주 | R7: 근로자 | S7: 고용주 | V7: 세금 | W7: 세금
B8: Current Employee
B9: Department | C9: Employee | D9: Position | F9: Title | G9: Gender | H9: Age | I9: Start Date | J9: 근속년수 (26년1월 기준) | K9: MONTHLY (NET) $ | L9: MONTHLY (NET) TL | M9: REMARK | N9: GROSS(MONTH) | O9: GROSS(YEAR) | P9: SSI Ee | Q9: SSI Er | R9: UEe | S9: UEr | T9: CITB | U9: ITB | V9: Income Tax | W9: Stamp Tax | X9: MLA | Y9: Net(MONTH) | Z9: Net(YEAR) | AA9: NET
C10: HM.CHO | D10: GENERAL MANAGER | E10: 주재원 | F10: 정규 | I10: 2022.05 | K10: 8800 | L10: 0 | M10: 0 | N10: 679907.49 | O10: =N10*12 -> 8158889.9 | P10: 27305.8 | Q10: 32669.43 | R10: 1950.41 | S10: 3900.83 | U10: 0 | V10: 141360.15 | W10: 4963.12 | Y10: =L10 -> 0 | Z10: =Y10*12 -> 0
C11: SH.LEE | D11: D.GENERAL MANAGER | E11: 주재원 | F11: 정규 | I11: 2024.07 | K11: 7460 | L11: 0 | M11: 0 | N11: 420391.48 | O11: =N11*12 -> 5044697.8 | P11: 27305.8 | Q11: 32669.43 | R11: 1950.41 | S11: 3900.83 | T11: 0 | U11: 0 | V11: 71290.82 | W11: 2993.39 | Y11: =L11 -> 0 | Z11: =Y11*12 -> 0
B12: HR/GA | C12: MERVE GÜNDÜZ | D12: MANAGER | E12: Accounting-Affair Personel | F12: Team Leader | G12: Female | H12: 36 | I12: 44769 | J12: 3.4356164 | L12: 92000 | M12: 0 | N12: 123773.5 | O12: =N12*12 -> 1485282 | P12: 17328.29 | Q12: 20732.06 | R12: 1237.74 | S12: 2475.47 | T12: 0 | U12: 0 | V12: 12465.42 | W12: 742.06 | Y12: =L12 -> 92000 | Z12: =Y12*12 -> 1104000
B13: QC | C13: CEREN KARAKOÇUM | D13: MANAGER | E13: Manufacturing Personel | F13: Team Leader | G13: Female | H13: 35 | I13: 44823 | J13: 3.290411 | L13: 92000 | M13: 0 | N13: 123773.5 | O13: =N13*12 -> 1485282 | P13: 17328.29 | Q13: 20732.06 | R13: 1237.74 | S13: 2475.47 | T13: 0 | U13: 0 | V13: 12465.42 | W13: 742.06 | Y13: =L13 -> 92000 | Z13: =Y13*12 -> 1104000
B14: MP&L | C14: ÖZNUR KOCAMAN | D14: MANAGER | E14: Manufacturing Personel | F14: Team Leader | G14: Female | H14: 34 | I14: 45152 | J14: 2.3917808 | L14: 92000 | M14: 0 | N14: 123773.5 | O14: =N14*12 -> 1485282 | P14: 17328.29 | Q14: 20732.06 | R14: 1237.74 | S14: 2475.47 | T14: 0 | U14: 0 | V14: 12465.42 | W14: 742.06 | Y14: =L14 -> 92000 | Z14: =Y14*12 -> 1104000
B15: F/A | C15: OZGE REÇBER | D15: SUPERVISOR | E15: Accounting-Affair Personel | F15: Team Leader | G15: Female | H15: 34 | I15: 45356 | J15: 1.8356164 | L15: 86000 | M15: 0 | N15: 115380.84 | O15: =N15*12 -> 1384570.1 | P15: 16153.32 | Q15: 19326.29 | R15: 1153.81 | S15: 2307.62 | T15: 0 | U15: 0 | V15: 11395.36 | W15: 678.36 | Y15: =L15 -> 86000 | Z15: =Y15*12 -> 1032000
B16: MP&L | C16: MURAT ÖZEN | D16: SUPERVISOR | E16: Manufacturing Personel | G16: Male | H16: 32 | I16: 45446 | J16: 1.5917808 | L16: 86000 | M16: 0 | N16: 115380.84 | O16: =N16*12 -> 1384570.1 | P16: 16153.32 | Q16: 19326.29 | R16: 1153.81 | S16: 2307.62 | T16: 0 | U16: 0 | V16: 11395.36 | W16: 678.36 | Y16: =L16 -> 86000 | Z16: =Y16*12 -> 1032000
B17: MP&L | C17: TUGAY BİRBEN | D17: ENGINEER | E17: Accounting-Affair Personel | G17: Male | H17: 32 | I17: 45518 | J17: 1.4 | L17: 60000 | M17: 0 | N17: 79012.63 | O17: =N17*12 -> 948151.56 | P17: 11061.77 | Q17: 13234.62 | R17: 790.13 | S17: 1580.25 | T17: 0 | U17: 0 | V17: 6758.41 | W17: 402.32 | Y17: =L17 -> 60000 | Z17: =Y17*12 -> 720000
B18: HR/GA | C18: KÜBRA CEREN ÖZEN | D18: SPECIALIST | E18: Accounting-Affair Personel | G18: Female | H18: 29 | I18: 45544 | J18: 1.3315068 | L18: 65000 | M18: 0 | N18: 86006.52 | O18: =N18*12 -> 1032078.2 | P18: 12040.91 | Q18: 14406.09 | R18: 860.07 | S18: 1720.13 | T18: 0 | U18: 0 | V18: 7650.13 | W18: 455.41 | Y18: =L18 -> 65000 | Z18: =Y18*12 -> 780000
B19: PM | C19: AKIN ILGAZ | D19: SUPERVISOR | E19: Manufacturing Personel | F19: Team Leader | G19: Male | H19: 29 | I19: 45597 | J19: 1.1890411 | L19: 80000 | M19: 0 | N19: 115380.84 | O19: =N19*12 -> 1384570.1 | P19: 16153.32 | Q19: 19326.29 | R19: 1153.81 | S19: 2307.62 | T19: 0 | U19: 0 | V19: 11395.36 | W19: 678.36 | Y19: =L19 -> 80000 | Z19: =Y19*12 -> 960000
B20: QC | C20: MUZAFFER TÜRK | D20: TECHNICIAN | E20: Manufacturing Personel | G20: Male | H20: 33 | I20: 45629 | J20: 1.1041096 | L20: 60000 | M20: 0 | N20: 79012.63 | O20: =N20*12 -> 948151.56 | P20: 11061.77 | Q20: 13234.62 | R20: 790.13 | S20: 1580.25 | T20: 0 | U20: 0 | V20: 6758.41 | W20: 402.32 | Y20: =L20 -> 60000 | Z20: =Y20*12 -> 720000
B21: QC | C21: İBRAHIM OSMANLI | D21: TECHNICIAN | E21: Manufacturing Personel | G21: Male | H21: 33 | I21: 45635 | J21: 1.090411 | L21: 60000 | M21: 0 | N21: 79012.63 | O21: =N21*12 -> 948151.56 | P21: 11061.77 | Q21: 13234.62 | R21: 790.13 | S21: 1580.25 | T21: 0 | U21: 0 | V21: 6758.41 | W21: 402.32 | Y21: =L21 -> 60000 | Z21: =Y21*12 -> 720000
B22: COST | C22: MELİS BİÇER YILDIZ | D22: SPECIALIST | E22: Accounting-Affair Personel | G22: Female | H22: 29 | I22: 45726 | J22: 0.84383562 | L22: 75000 | M22: 0 | N22: 99994.29 | O22: =N22*12 -> 1199931.5 | P22: 13999.2 | Q22: 16749.04 | R22: 999.94 | S22: 1999.89 | T22: 0 | U22: 0 | V22: 9433.57 | W22: 561.57 | Y22: =L22 -> 75000 | Z22: =Y22*12 -> 900000
B23: F/A | C23: ELİF ÇAĞLA KARAGÖL | D23: SPECIALIST | E23: Accounting-Affair Personel | G23: Female | H23: 32 | I23: 45824 | J23: 0.57808219 | L23: 75000 | M23: 0 | N23: 99994.29 | O23: =N23*12 -> 1199931.5 | P23: 13999.2 | Q23: 16749.04 | R23: 999.94 | S23: 1999.89 | T23: 0 | U23: 0 | V23: 9433.57 | W23: 561.57 | Y23: =L23 -> 75000 | Z23: =Y23*12 -> 900000
B24: MP&L | C24: MERİÇ EMRE BAYAKTAR | D24: ASSISTANT SPECIALIST | E24: Manufacturing Personel | G24: Male | H24: 31 | I24: 45827 | J24: 0.57260274 | L24: 65000 | M24: 0 | N24: 86006.52 | O24: =N24*12 -> 1032078.2 | P24: 12040.91 | Q24: 14406.09 | R24: 860.07 | S24: 1720.13 | T24: 0 | U24: 0 | V24: 7650.13 | W24: 455.41 | Y24: =L24 -> 65000 | Z24: =Y24*12 -> 780000
B25: QC | C25: FEVZİ BAHADIR YILDIRIM | D25: TECHNICIAN | E25: Manufacturing Personel | G25: Male | H25: 29 | I25: 45834 | J25: 0.55616438 | L25: 60000 | M25: 0 | N25: 79012.63 | O25: =N25*12 -> 948151.56 | P25: 11061.77 | Q25: 13234.62 | R25: 790.13 | S25: 1580.25 | T25: 0 | U25: 0 | V25: 6758.41 | W25: 402.32 | Y25: =L25 -> 60000 | Z25: =Y25*12 -> 720000
B26: QC | C26: SEVDENUR AYHAN | D26: ENGINEER | E26: Manufacturing Personel | G26: Female | H26: 22 | I26: 45841 | J26: 0.53972603 | L26: 65000 | M26: 0 | N26: 86006.52 | O26: =N26*12 -> 1032078.2 | P26: 12040.91 | Q26: 14406.09 | R26: 860.07 | S26: 1720.13 | T26: 0 | U26: 0 | V26: 7650.13 | W26: 455.41 | Y26: =L26 -> 65000 | Z26: =Y26*12 -> 780000
B27: PM | C27: CHAN HO PARK | D27: SPECIALIST | E27: Manufacturing Personel | G27: Male | H27: 29 | I27: 45908 | J27: 0.35890411 | L27: 100000 | M27: 0 | N27: 134963.72 | O27: =N27*12 -> 1619564.6 | P27: 18894.92 | Q27: 22606.42 | R27: 1349.64 | S27: 2699.27 | T27: 0 | U27: 0 | V27: 13892.17 | W27: 826.99 | Y27: =L27 -> 100000 | Z27: =Y27*12 -> 1200000
B28: F/A | C28: Hatice | D28: ASSISTANT SPECIALIST | E28: Accounting-Affair Personel | G28: Female | H28: 29 | I28: 45978 | J28: 0 | L28: 60000 | M28: 0 | N28: 79012.63 | O28: =N28*12 -> 948151.56 | P28: 11061.77 | Q28: 13234.62 | R28: 790.13 | S28: 1580.25 | T28: 0 | U28: 0 | V28: 6758.41 | W28: 402.32 | Y28: =L28 -> 60000 | Z28: =Y28*12 -> 720000
B29: COST | C29: Çağatay Çiçek, | D29: ENGINEER | E29: Accounting-Affair Personel | G29: Male | H29: 28 | I29: 46001 | J29: 0 | L29: 60000 | M29: 0 | N29: 79012.63 | O29: =N29*12 -> 948151.56 | P29: 11061.77 | Q29: 13234.62 | R29: 790.13 | S29: 1580.25 | T29: 0 | U29: 0 | V29: 6758.41 | W29: 402.32 | Y29: =L29 -> 60000 | Z29: =Y29*12 -> 720000
B30: COST | C30: Sonbahar İlbey, | D30: SUPERVISOR | E30: Accounting-Affair Personel | G30: Female | H30: 31 | I30: 46006 | J30: 0 | L30: 70000 | M30: 0 | N30: 93000.41 | O30: =N30*12 -> 1116004.9 | P30: 13020.06 | Q30: 15577.57 | R30: 930 | S30: 1860.01 | T30: 0 | U30: 0 | V30: 8541.85 | W30: 508.49 | Y30: =L30 -> 70000 | Z30: =Y30*12 -> 840000
B31: HR/GA | C31: GÜLSÜM ÖZDEMİR | D31: STAFF | E31: Accounting-Affair Personel | G31: Female | H31: 50 | I31: 45917 | J31: 0.3369863 | L31: 32000 | M31: 0 | N31: 39846.86 | O31: =N31*12 -> 478162.32 | P31: 5578.56 | Q31: 6674.35 | R31: 398.47 | S31: 796.94 | T31: 0 | U31: 0 | V31: 1764.77 | W31: 105.06 | Y31: =L31 -> 32000 | Z31: =Y31*12 -> 384000
B34: New hiring Employee
B35: 영업 (예상) | C35: Korean Manager | D35: Manager | E35: 주재원 | F35: Team Leader | G35: - | H35: - | I35: July | L35: =L11 -> 0 | M35: =M11 -> 0 | N35: 420391.48 | O35: =N35*12 -> 5044697.8 | P35: 27305.8 | Q35: 32669.43 | R35: 1950.41 | S35: 3900.83 | T35: 0 | U35: 0 | V35: 71290.82 | W35: 2993.39 | Y35: =L35 -> 0 | Z35: =Y35*12 -> 0 | AA35: =AA11 -> 0
B36: Sales | C36: TBD | D36: Engineer | E36: Accounting-Affair Personel | F36: - | G36: - | H36: - | I36: Feb | L36: 60000 | M36: 0 | N36: 79012.63 | O36: =N36*12 -> 948151.56 | P36: 11061.77 | Q36: 13234.62 | R36: 790.13 | S36: 1580.25 | T36: 0 | U36: 0 | V36: 6758.41 | W36: 402.32 | Y36: =L36 -> 60000 | Z36: =Y36*12 -> 720000
B37: Purchaing | C37: TBD | D37: Engineer | E37: Accounting-Affair Personel | F37: - | G37: - | H37: - | I37: Jan | L37: 60000 | M37: 0 | N37: 79012.63 | O37: =N37*12 -> 948151.56 | P37: 11061.77 | Q37: 13234.62 | R37: 790.13 | S37: 1580.25 | T37: 0 | U37: 0 | V37: 6758.41 | W37: 402.32 | Y37: =L37 -> 60000 | Z37: =Y37*12 -> 720000
B38: MP&L | C38: TBD | D38: Engineer | E38: Manufacturing Personel | F38: - | G38: - | H38: - | I38: Aug | L38: 60000 | M38: 0 | N38: 79012.63 | O38: =N38*12 -> 948151.56 | P38: 11061.77 | Q38: 13234.62 | R38: 790.13 | S38: 1580.25 | T38: 0 | U38: 0 | V38: 6758.41 | W38: 402.32 | Y38: =L38 -> 60000 | Z38: =Y38*12 -> 720000
B39: MP&L | C39: TBD | D39: Engineer | E39: Manufacturing Personel | F39: - | G39: - | H39: - | I39: Aug | L39: 60000 | M39: 0 | N39: 79012.63 | O39: =N39*12 -> 948151.56 | P39: 11061.77 | Q39: 13234.62 | R39: 790.13 | S39: 1580.25 | T39: 0 | U39: 0 | V39: 6758.41 | W39: 402.32 | Y39: =L39 -> 60000 | Z39: =Y39*12 -> 720000
D42: Month | H42: Jan | I42: Feb | J42: Mar | K42: Apr | L42: May | M42: Jun | N42: Jul | O42: Aug | P42: Sept | Q42: Oct | R42: Nov | S42: Dec
D43: Total Number of employees | H43: ='3. HR'!E7 -> 23 | I43: ='3. HR'!F7 -> 24 | J43: ='3. HR'!G7 -> 24 | K43: ='3. HR'!H7 -> 24 | L43: ='3. HR'!I7 -> 24 | M43: ='3. HR'!J7 -> 24 | N43: ='3. HR'!K7 -> 25 | O43: ='3. HR'!L7 -> 27 | ... S43: ='3. HR'!P7 -> 27
D44: New employees | H44: ='3. HR'!E8 -> 1 | I44: ='3. HR'!F8 -> 1 | J44: ='3. HR'!G8 -> 0 | K44: ='3. HR'!H8 -> 0 | L44: ='3. HR'!I8 -> 0 | M44: ='3. HR'!J8 -> 0 | N44: ='3. HR'!K8 -> 1 | O44: ='3. HR'!L8 -> 2 | ... S44: ='3. HR'!P8 -> 0
D45: 주재원 | E45: Executive employees | H45: ='3. HR'!E9 -> 2 | I45: ='3. HR'!F9 -> 2 | J45: ='3. HR'!G9 -> 2 | K45: ='3. HR'!H9 -> 2 | L45: ='3. HR'!I9 -> 2 | M45: ='3. HR'!J9 -> 2 | N45: ='3. HR'!K9 -> 3 | O45: ='3. HR'!L9 -> 3 | ... S45: ='3. HR'!P9 -> 3
E46: GROSS SALARIES | H46: =SUM($N$10:$N$11) -> 1100299 | I46: =SUM($N$10:$N$11) -> 1100299 | J46: =SUM($N$10:$N$11) -> 1100299 | K46: =SUM($N$10:$N$11) -> 1100299 | L46: =SUM($N$10:$N$11) -> 1100299 | M46: =SUM($N$10:$N$11) -> 1100299 | N46: =SUM($N$10:$N$11)+$N$35 -> 1520690.4 | O46: =SUM($N$10:$N$11)+$N$35 -> 1520690.4 | P46: =SUM($N$10:$N$11)+$N$35 -> 1520690.4 | Q46: =SUM($N$10:$N$11)+$N$35 -> 1520690.4 | R46: =SUM($N$10:$N$11)+$N$35 -> 1520690.4 | S46: =SUM($N$10:$N$11)+$N$35 -> 1520690.4
E47: SSI EMPLOYER PREMIUM SHARE | H47: =SUM($Q$10:$Q$11) -> 65338.86 | I47: =SUM($Q$10:$Q$11) -> 65338.86 | J47: =SUM($Q$10:$Q$11) -> 65338.86 | K47: =SUM($Q$10:$Q$11) -> 65338.86 | L47: =SUM($Q$10:$Q$11) -> 65338.86 | M47: =SUM($Q$10:$Q$11) -> 65338.86 | N47: =SUM($Q$10:$Q$11)+$Q$35 -> 98008.29 | O47: =SUM($Q$10:$Q$11)+$Q$35 -> 98008.29 | P47: =SUM($Q$10:$Q$11)+$Q$35 -> 98008.29 | Q47: =SUM($Q$10:$Q$11)+$Q$35 -> 98008.29 | R47: =SUM($Q$10:$Q$11)+$Q$35 -> 98008.29 | S47: =SUM($Q$10:$Q$11)+$Q$35 -> 98008.29
E48: EMPLOYER UNEMPLOYMENT PREMIUM SHARE | H48: =SUM($S$10:$S$11) -> 7801.66 | I48: =SUM($S$10:$S$11) -> 7801.66 | J48: =SUM($S$10:$S$11) -> 7801.66 | K48: =SUM($S$10:$S$11) -> 7801.66 | L48: =SUM($S$10:$S$11) -> 7801.66 | M48: =SUM($S$10:$S$11) -> 7801.66 | N48: =SUM($S$10:$S$11)+$S$35 -> 11702.49 | O48: =SUM($S$10:$S$11)+$S$35 -> 11702.49 | P48: =SUM($S$10:$S$11)+$S$35 -> 11702.49 | Q48: =SUM($S$10:$S$11)+$S$35 -> 11702.49 | R48: =SUM($S$10:$S$11)+$S$35 -> 11702.49 | S48: =SUM($S$10:$S$11)+$S$35 -> 11702.49
D49: Accounting-Finance Personel | E49: employees | H49: ='3. HR'!E10 -> 10 | I49: ='3. HR'!F10 -> 11 | J49: ='3. HR'!G10 -> 11 | K49: ='3. HR'!H10 -> 11 | L49: ='3. HR'!I10 -> 11 | M49: ='3. HR'!J10 -> 11 | N49: ='3. HR'!K10 -> 11 | O49: ='3. HR'!L10 -> 11 | ... S49: ='3. HR'!P10 -> 11
E50: GROSS SALARIES | H50: =670549+N36 -> 749561.63 | I50: =SUM($N$12,$N$15,$N$18,$N$17,$N$22,$N$23,$N$29,$N$30,$N$31)+N28+$N$36+$N$37 -> 1053059.9 | J50: =SUM($N$12,$N$15,$N$18,$N$17,$N$22,$N$23,$N$29,$N$30,$N$31)+N28+$N$36+$N$37 -> 1053059.9 | K50: =SUM($N$12,$N$15,$N$18,$N$17,$N$22,$N$23,$N$29,$N$30,$N$31)+N28+$N$36+$N$37 -> 1053059.9 | L50: =SUM($N$12,$N$15,$N$18,$N$17,$N$22,$N$23,$N$29,$N$30,$N$31)+N28+$N$36+$N$37 -> 1053059.9 | M50: =SUM($N$12,$N$15,$N$18,$N$17,$N$22,$N$23,$N$29,$N$30,$N$31)+N28+$N$36+$N$37 -> 1053059.9 | N50: =SUM($N$12,$N$15,$N$18,$N$17,$N$22,$N$23,$N$29,$N$30,$N$31+N28)+$N$36+$N$37 -> 1053059.9 | O50: =SUM($N$12,$N$15,$N$18,$N$17,$N$22,$N$23,$N$29,$N$30,$N$31+N28)+$N$36+$N$37 -> 1053059.9 | P50: =SUM($N$12,$N$15,$N$18,$N$17,$N$22,$N$23,$N$29,$N$30,$N$31+N28)+$N$36+$N$37 -> 1053059.9 | Q50: =SUM($N$12,$N$15,$N$18,$N$17,$N$22,$N$23,$N$29,$N$30,$N$31+N28)+$N$36+$N$37 -> 1053059.9 | R50: =SUM($N$12,$N$15,$N$18,$N$17,$N$22,$N$23,$N$29,$N$30,$N$31+N28)+$N$36+$N$37 -> 1053059.9 | S50: =SUM($N$12,$N$15,$N$18,$N$17,$N$22,$N$23,$N$29,$N$30,$N$31+N28)+$N$36+$N$37 -> 1053059.9
E51: SSI EMPLOYER PREMIUM SHARE | H51: =112317+Q37 -> 125551.62 | I51: =SUM($Q$12,$Q$15,$Q$18,$Q$17,$Q$22,$Q$23,$Q$29,$Q$30,$Q$31+Q28)+$Q$37 -> 163152.92 | J51: =SUM($Q$12,$Q$15,$Q$18,$Q$17,$Q$22,$Q$23,$Q$29,$Q$30,$Q$31+Q28)+$Q$36+$Q$37 -> 176387.54 | K51: =SUM($Q$12,$Q$15,$Q$18,$Q$17,$Q$22,$Q$23,$Q$29,$Q$30,$Q$31+Q28)+$Q$36+$Q$37 -> 176387.54 | L51: =SUM($Q$12,$Q$15,$Q$18,$Q$17,$Q$22,$Q$23,$Q$29,$Q$30,$Q$31+Q28)+$Q$36+$Q$37 -> 176387.54 | M51: =SUM($Q$12,$Q$15,$Q$18,$Q$17,$Q$22,$Q$23,$Q$29,$Q$30,$Q$31+Q28)+$Q$36+$Q$37 -> 176387.54 | N51: =SUM($Q$12,$Q$15,$Q$18,$Q$17,$Q$22,$Q$23,$Q$29,$Q$30,$Q$31+Q28)+$Q$36+$Q$37 -> 176387.54 | O51: =SUM($Q$12,$Q$15,$Q$18,$Q$17,$Q$22,$Q$23,$Q$29,$Q$30,$Q$31+Q28)+$Q$36+$Q$37 -> 176387.54 | P51: =SUM($Q$12,$Q$15,$Q$18,$Q$17,$Q$22,$Q$23,$Q$29,$Q$30,$Q$31+Q28)+$Q$36+$Q$37 -> 176387.54 | Q51: =SUM($Q$12,$Q$15,$Q$18,$Q$17,$Q$22,$Q$23,$Q$29,$Q$30,$Q$31+Q28)+$Q$36+$Q$37 -> 176387.54 | R51: =SUM($Q$12,$Q$15,$Q$18,$Q$17,$Q$22,$Q$23,$Q$29,$Q$30,$Q$31+Q28)+$Q$36+$Q$37 -> 176387.54 | S51: =SUM($Q$12,$Q$15,$Q$18,$Q$17,$Q$22,$Q$23,$Q$29,$Q$30,$Q$31+Q28)+$Q$36+$Q$37 -> 176387.54
E52: EMPLOYER UNEMPLOYMENT PREMIUM SHARE | H52: =13411+S37 -> 14991.25 | I52: =SUM($S$12,$S$15,$S$18,$S$17,$S$22,$S$23,$S$29,$S$30,$S$31+S28)+$S$37 -> 19480.95 | J52: =SUM($S$12,$S$15,$S$18,$S$17,$S$22,$S$23,$S$29,$S$30,$S$31+S28)+$S$36+$S$37 -> 21061.2 | K52: =SUM($S$12,$S$15,$S$18,$S$17,$S$22,$S$23,$S$29,$S$30,$S$31+S28)+$S$36+$S$37 -> 21061.2 | L52: =SUM($S$12,$S$15,$S$18,$S$17,$S$22,$S$23,$S$29,$S$30,$S$31+S28)+$S$36+$S$37 -> 21061.2 | M52: =SUM($S$12,$S$15,$S$18,$S$17,$S$22,$S$23,$S$29,$S$30,$S$31+S28)+$S$36+$S$37 -> 21061.2 | N52: =SUM($S$12,$S$15,$S$18,$S$17,$S$22,$S$23,$S$29,$S$30,$S$31+S28)+$S$36+$S$37 -> 21061.2 | O52: =SUM($S$12,$S$15,$S$18,$S$17,$S$22,$S$23,$S$29,$S$30,$S$31+S28)+$S$36+$S$37 -> 21061.2 | P52: =SUM($S$12,$S$15,$S$18,$S$17,$S$22,$S$23,$S$29,$S$30,$S$31+S28)+$S$36+$S$37 -> 21061.2 | Q52: =SUM($S$12,$S$15,$S$18,$S$17,$S$22,$S$23,$S$29,$S$30,$S$31+S28)+$S$36+$S$37 -> 21061.2 | R52: =SUM($S$12,$S$15,$S$18,$S$17,$S$22,$S$23,$S$29,$S$30,$S$31+S28)+$S$36+$S$37 -> 21061.2 | S52: =SUM($S$12,$S$15,$S$18,$S$17,$S$22,$S$23,$S$29,$S$30,$S$31+S28)+$S$36+$S$37 -> 21061.2
D53: Manufacturing Personel | E53: employees | H53: ='3. HR'!E11 -> 11 | I53: ='3. HR'!F11 -> 11 | J53: ='3. HR'!G11 -> 11 | K53: ='3. HR'!H11 -> 11 | L53: ='3. HR'!I11 -> 11 | M53: ='3. HR'!J11 -> 11 | N53: ='3. HR'!K11 -> 11 | O53: ='3. HR'!L11 -> 13 | ... S53: ='3. HR'!P11 -> 13
E54: GROSS SALARIES | H54: =827176 -> 827176 | I54: =SUM($N$13,$N$14,$N$16,$N$19,$N$20,$N$21,$N$24,$N$25,$N$26,$N$27) -> 1022323.3 | J54: =SUM($N$13,$N$14,$N$16,$N$19,$N$20,$N$21,$N$24,$N$25,$N$26,$N$27) -> 1022323.3 | K54: =SUM($N$13,$N$14,$N$16,$N$19,$N$20,$N$21,$N$24,$N$25,$N$26,$N$27) -> 1022323.3 | L54: =SUM($N$13,$N$14,$N$16,$N$19,$N$20,$N$21,$N$24,$N$25,$N$26,$N$27) -> 1022323.3 | M54: =SUM($N$13,$N$14,$N$16,$N$19,$N$20,$N$21,$N$24,$N$25,$N$26,$N$27) -> 1022323.3 | N54: =SUM($N$13,$N$14,$N$16,$N$19,$N$20,$N$21,$N$24,$N$25,$N$26,$N$27)+$N$38+$N$39 -> 1180348.6 | O54: =SUM($N$13,$N$14,$N$16,$N$19,$N$20,$N$21,$N$24,$N$25,$N$26,$N$27)+$N$38+$N$39 -> 1180348.6 | P54: =SUM($N$13,$N$14,$N$16,$N$19,$N$20,$N$21,$N$24,$N$25,$N$26,$N$27)+$N$38+$N$39 -> 1180348.6 | Q54: =SUM($N$13,$N$14,$N$16,$N$19,$N$20,$N$21,$N$24,$N$25,$N$26,$N$27)+$N$38+$N$39 -> 1180348.6 | R54: =SUM($N$13,$N$14,$N$16,$N$19,$N$20,$N$21,$N$24,$N$25,$N$26,$N$27)+$N$38+$N$39 -> 1180348.6 | S54: =SUM($N$13,$N$14,$N$16,$N$19,$N$20,$N$21,$N$24,$N$25,$N$26,$N$27)+$N$38+$N$39 -> 1180348.6
E55: SSI EMPLOYER PREMIUM SHARE | H55: =138552 -> 138552 | I55: =SUM($Q$13,$Q$14,$Q$16,$Q$19,$Q$20,$Q$21,$Q$24,$Q$25,$Q$26,$Q$27) -> 171239.16 | J55: =SUM($Q$13,$Q$14,$Q$16,$Q$19,$Q$20,$Q$21,$Q$24,$Q$25,$Q$26,$Q$27) -> 171239.16 | K55: =SUM($Q$13,$Q$14,$Q$16,$Q$19,$Q$20,$Q$21,$Q$24,$Q$25,$Q$26,$Q$27) -> 171239.16 | L55: =SUM($Q$13,$Q$14,$Q$16,$Q$19,$Q$20,$Q$21,$Q$24,$Q$25,$Q$26,$Q$27) -> 171239.16 | M55: =SUM($Q$13,$Q$14,$Q$16,$Q$19,$Q$20,$Q$21,$Q$24,$Q$25,$Q$26,$Q$27) -> 171239.16 | N55: =SUM($Q$13,$Q$14,$Q$16,$Q$19,$Q$20,$Q$21,$Q$24,$Q$25,$Q$26,$Q$27)+$Q$38+$Q$39 -> 197708.4 | O55: =SUM($Q$13,$Q$14,$Q$16,$Q$19,$Q$20,$Q$21,$Q$24,$Q$25,$Q$26,$Q$27)+$Q$38+$Q$39 -> 197708.4 | P55: =SUM($Q$13,$Q$14,$Q$16,$Q$19,$Q$20,$Q$21,$Q$24,$Q$25,$Q$26,$Q$27)+$Q$38+$Q$39 -> 197708.4 | Q55: =SUM($Q$13,$Q$14,$Q$16,$Q$19,$Q$20,$Q$21,$Q$24,$Q$25,$Q$26,$Q$27)+$Q$38+$Q$39 -> 197708.4 | R55: =SUM($Q$13,$Q$14,$Q$16,$Q$19,$Q$20,$Q$21,$Q$24,$Q$25,$Q$26,$Q$27)+$Q$38+$Q$39 -> 197708.4 | S55: =SUM($Q$13,$Q$14,$Q$16,$Q$19,$Q$20,$Q$21,$Q$24,$Q$25,$Q$26,$Q$27)+$Q$38+$Q$39 -> 197708.4
E56: EMPLOYER UNEMPLOYMENT PREMIUM SHARE | H56: =16544 -> 16544 | I56: =SUM($S$13,$S$14,$S$16,$S$19,$S$20,$S$21,$S$24,$S$25,$S$26,$S$27) -> 20446.46 | J56: =SUM($S$13,$S$14,$S$16,$S$19,$S$20,$S$21,$S$24,$S$25,$S$26,$S$27) -> 20446.46 | K56: =SUM($S$13,$S$14,$S$16,$S$19,$S$20,$S$21,$S$24,$S$25,$S$26,$S$27) -> 20446.46 | L56: =SUM($S$13,$S$14,$S$16,$S$19,$S$20,$S$21,$S$24,$S$25,$S$26,$S$27) -> 20446.46 | M56: =SUM($S$13,$S$14,$S$16,$S$19,$S$20,$S$21,$S$24,$S$25,$S$26,$S$27) -> 20446.46 | N56: =SUM($S$13,$S$14,$S$16,$S$19,$S$20,$S$21,$S$24,$S$25,$S$26,$S$27)+$S$38+$S$39 -> 23606.96 | O56: =SUM($S$13,$S$14,$S$16,$S$19,$S$20,$S$21,$S$24,$S$25,$S$26,$S$27)+$S$38+$S$39 -> 23606.96 | P56: =SUM($S$13,$S$14,$S$16,$S$19,$S$20,$S$21,$S$24,$S$25,$S$26,$S$27)+$S$38+$S$39 -> 23606.96 | Q56: =SUM($S$13,$S$14,$S$16,$S$19,$S$20,$S$21,$S$24,$S$25,$S$26,$S$27)+$S$38+$S$39 -> 23606.96 | R56: =SUM($S$13,$S$14,$S$16,$S$19,$S$20,$S$21,$S$24,$S$25,$S$26,$S$27)+$S$38+$S$39 -> 23606.96 | S56: =SUM($S$13,$S$14,$S$16,$S$19,$S$20,$S$21,$S$24,$S$25,$S$26,$S$27)+$S$38+$S$39 -> 23606.96

Sheet 5. Social Benefit
B1: ▣ Lunch Support | N1: `26 Esti | O1: 345
B4: NO | D4: Jan | E4: Feb | F4: Mar | G4: Apr | H4: May | I4: Jun | J4: Jul | K4: Aug | L4: Sep | M4: Oct | N4: Nov | O4: Dec | P4: ToTal
B5: 총 직원수 (Employee) | D5: ='3. HR'!E7 -> 23 | E5: ='3. HR'!F7 -> 24 | F5: ='3. HR'!G7 -> 24 | G5: ='3. HR'!H7 -> 24 | H5: ='3. HR'!I7 -> 24 | I5: ='3. HR'!J7 -> 24 | J5: ='3. HR'!K7 -> 25 | K5: ='3. HR'!L7 -> 27 | ... O5: ='3. HR'!P7 -> 27
B6: Employee | C6: 주재원 | D6: 2 | E6: 2 | F6: 2 | G6: 2 | H6: 2 | I6: 2 | J6: 3 | K6: 3 | L6: 3 | M6: 3 | N6: 3 | O6: 3
C7: Accounting-Finance Personel | D7: ='3. HR'!E10 -> 10 | E7: ='3. HR'!F10 -> 11 | F7: ='3. HR'!G10 -> 11 | G7: ='3. HR'!H10 -> 11 | H7: ='3. HR'!I10 -> 11 | I7: ='3. HR'!J10 -> 11 | J7: 12 | K7: 12 | L7: 12 | M7: 12 | N7: 12 | O7: 12
C8: Manufacturing Personel | D8: ='3. HR'!E11 -> 11 | E8: ='3. HR'!F11 -> 11 | F8: ='3. HR'!G11 -> 11 | G8: ='3. HR'!H11 -> 11 | H8: ='3. HR'!I11 -> 11 | I8: ='3. HR'!J11 -> 11 | J8: ='3. HR'!K11 -> 11 | K8: ='3. HR'!L11 -> 13 | ... O8: ='3. HR'!P11 -> 13
B9: 점심식대 (Lunch) | D9: 345 | E9: 345 | F9: 345 | G9: 345 | H9: 345 | I9: 345 | J9: 345 | K9: 345 | L9: 345 | M9: 345 | N9: 345 | O9: 345
B10: 근무일수 (Working Day) | D10: 22 | E10: 22 | F10: 22 | G10: 22 | H10: 22 | I10: 22 | J10: 22 | K10: 22 | L10: 22 | M10: 22 | N10: 22 | O10: 23
B11: Cost | C11: 주재원 | D11: =D6*D9*D10 -> 15180 | E11: =E6*E9*E10 -> 15180 | F11: =F6*F9*F10 -> 15180 | G11: =G6*G9*G10 -> 15180 | H11: =H6*H9*H10 -> 15180 | I11: =I6*I9*I10 -> 15180 | J11: =J6*J9*J10 -> 22770 | K11: =K6*K9*K10 -> 22770 | ... O11: =O6*O9*O10 -> 23805 | P11: =SUM(D11:O11) -> 228735
C12: Accounting-Finance | D12: =D7*D9*D10 -> 75900 | E12: =E7*E9*E10 -> 83490 | F12: =F7*F9*F10 -> 83490 | G12: =G7*G9*G10 -> 83490 | H12: =H7*H9*H10 -> 83490 | I12: =I7*I9*I10 -> 83490 | J12: =J7*J9*J10 -> 91080 | K12: =K7*K9*K10 -> 91080 | ... O12: =O7*O9*O10 -> 95220 | P12: =SUM(D12:O12) -> 1043970
C13: Manufacturing | D13: =D8*D9*D10 -> 83490 | E13: =E8*E9*E10 -> 83490 | F13: =F8*F9*F10 -> 83490 | G13: =G8*G9*G10 -> 83490 | H13: =H8*H9*H10 -> 83490 | I13: =I8*I9*I10 -> 83490 | J13: =J8*J9*J10 -> 83490 | K13: =K8*K9*K10 -> 98670 | ... O13: =O8*O9*O10 -> 103155 | P13: =SUM(D13:O13) -> 1082265
B14: 총금액 | D14: =SUM(D11:D13) -> 174570 | E14: =SUM(E11:E13) -> 182160 | F14: =SUM(F11:F13) -> 182160 | G14: =SUM(G11:G13) -> 182160 | H14: =SUM(H11:H13) -> 182160 | I14: =SUM(I11:I13) -> 182160 | J14: =SUM(J11:J13) -> 197340 | K14: =SUM(K11:K13) -> 212520 | ... O14: =SUM(O11:O13) -> 222180 | P14: =SUM(D14:O14) -> 2354970
J15: 포드 오토산 2주 셧다운
B16: ▣ KCTR Shuttle (Transportation) | O16: `26 Esti | P16: 165
F19: 근무일수 | G19: =D10 -> 22 | H19: =E10 -> 22 | I19: =F10 -> 22 | J19: =G10 -> 22 | K19: =H10 -> 22 | L19: =I10 -> 22 | M19: =J10 -> 22 | N19: =K10 -> 22 | ... R19: =O10 -> 23
B20: Team | C20: Name | D20: Position | E20: Type | F20: 지급 타입 | G20: Jan | H20: Feb | I20: Mar | J20: Apr | K20: May | L20: Jun | M20: Jul | N20: Aug | O20: Sep | P20: Oct | Q20: Nov | R20: Dec | S20: ToTal
B21: HR/General Affairs | C21: MERVE | D21: Manager | E21: Accounting-Finance | F21: 최소거리 | G21: =$P$16*G19 -> 3630 | H21: =$P$16*H19 -> 3630 | I21: =$P$16*I19 -> 3630 | J21: =$P$16*J19 -> 3630 | K21: =$P$16*K19 -> 3630 | L21: =$P$16*L19 -> 3630 | M21: =$P$16*M19 -> 3630 | N21: =$P$16*N19 -> 3630 | ... R21: =$P$16*R19 -> 3795 | S21: =SUM(G21:R21) -> 43725
C22: Kübra Ceren | D22: Engineer | E22: Accounting-Finance | F22: 거리 Km 당 | G22: 4061 | H22: 4061 | I22: 4061 | J22: 4061 | K22: 4061 | L22: 4061 | M22: 4061 | N22: 4061 | O22: 4061 | P22: 4061 | Q22: 4061 | R22: 4061 | S22: =SUM(G22:R22) -> 48732
C23: GÜLSÜM | D23: Technician | E23: Accounting-Finance | F23: 최소거리 | G23: 3630 | H23: 3630 | I23: 3630 | J23: 3630 | K23: 3630 | L23: 3630 | M23: 3630 | N23: 3630 | O23: 3630 | P23: 3630 | Q23: 3630 | R23: 3795 | S23: =SUM(G23:R23) -> 43725
B24: Finance/Account | C24: Özge | D24: Supervisor | E24: Accounting-Finance | F24: 최소거리 | G24: 3630 | H24: 3630 | I24: 3630 | J24: 3630 | K24: 3630 | L24: 3630 | M24: 3630 | N24: 3630 | O24: 3630 | P24: 3630 | Q24: 3630 | R24: 3795 | S24: =SUM(G24:R24) -> 43725
C25: ÇAĞLA | D25: Specialist | E25: Accounting-Finance | F25: 거리 Km 당 | G25: 4219 | H25: 4219 | I25: 4219 | J25: 4219 | K25: 4219 | L25: 4219 | M25: 4219 | N25: 4219 | O25: 4219 | P25: 4219 | Q25: 4219 | R25: 4219 | S25: =SUM(G25:R25) -> 50628
C26: Haticenur | D26: Assistant Specialist | E26: Accounting-Finance | F26: 최소거리 | G26: 3630 | H26: 3630 | I26: 3630 | J26: 3630 | K26: 3630 | L26: 3630 | M26: 3630 | N26: 3630 | O26: 3630 | P26: 3630 | Q26: 3630 | R26: 3795 | S26: =SUM(G26:R26) -> 43725
B27: Sales/Procurement | C27: Melis | D27: Specialist | E27: Accounting-Finance | F27: 거리 Km 당 | G27: 5816.6429 | H27: 5816.6429 | I27: 5816.6429 | J27: 5816.6429 | K27: 5816.6429 | L27: 5816.6429 | M27: 5816.6429 | N27: 5816.6429 | O27: 5816.6429 | P27: 5816.6429 | Q27: 5816.6429 | R27: 5816.6429 | S27: =SUM(G27:R27) -> 69799.714
C28: New(Dec) | D28: Engineer | E28: Accounting-Finance | F28: 최소거리 | G28: 3630 | H28: 3630 | I28: 3630 | J28: 3630 | K28: 3630 | L28: 3630 | M28: 3630 | N28: 3630 | O28: 3630 | P28: 3630 | Q28: 3630 | R28: 3795 | S28: =SUM(G28:R28) -> 43725
B29: MP&L | C29: OZNUR | D29: Manager | E29: Manufacturing | F29: 기본급 | G29: 3630 | H29: 3630 | I29: 3630 | J29: 3630 | K29: 3630 | L29: 3630 | M29: 3630 | N29: 3630 | O29: 3630 | P29: 3630 | Q29: 3630 | R29: 3795 | S29: =SUM(G29:R29) -> 43725
C30: Murat Öze | D30: Supervisor | E30: Manufacturing | F30: 미지원 | G30: - | H30: - | I30: - | J30: - | K30: - | L30: - | M30: - | N30: - | O30: - | P30: - | Q30: - | R30: - | S30: -
C31: MERİÇ | D31: Assistant Specialist | E31: Manufacturing | F31: 최소거리 | G31: 3630 | H31: 3630 | I31: 3630 | J31: 3630 | K31: 3630 | L31: 3630 | M31: 3630 | N31: 3630 | O31: 3630 | P31: 3630 | Q31: 3630 | R31: 3795 | S31: =SUM(G31:R31) -> 43725
C32: Tugay | D32: Engineer | E32: Manufacturing | F32: 거리 Km 당 | G32: 6340 | H32: 6340 | I32: 6340 | J32: 6340 | K32: 6340 | L32: 6340 | M32: 6340 | N32: 6340 | O32: 6340 | P32: 6340 | Q32: 6340 | R32: 6340 | S32: =SUM(G32:R32) -> 76080
B33: P/M | C33: Akin | D33: Specialist | E33: Manufacturing | F33: 거리 Km 당 | G33: 5301 | H33: 5301 | I33: 5301 | J33: 5301 | K33: 5301 | L33: 5301 | M33: 5301 | N33: 5301 | O33: 5301 | P33: 5301 | Q33: 5301 | R33: 5301 | S33: =SUM(G33:R33) -> 63612
C34: CH Park | D34: Specialist | E34: Manufacturing | F34: 최소거리 | G34: 3630 | H34: 3630 | I34: 3630 | J34: 3630 | K34: 3630 | L34: 3630 | M34: 3630 | N34: 3630 | O34: 3630 | P34: 3630 | Q34: 3630 | R34: 3795 | S34: =SUM(G34:R34) -> 43725
B35: Q.C. | C35: CEREN | D35: Manager | E35: Manufacturing | F35: 최소거리 | G35: 3630 | H35: 3630 | I35: 3630 | J35: 3630 | K35: 3630 | L35: 3630 | M35: 3630 | N35: 3630 | O35: 3630 | P35: 3630 | Q35: 3630 | R35: 3795 | S35: =SUM(G35:R35) -> 43725
C36: Sevde | D36: Engineer | E36: Manufacturing | F36: 최소거리 | G36: 3630 | H36: 3630 | I36: 3630 | J36: 3630 | K36: 3630 | L36: 3630 | M36: 3630 | N36: 3630 | O36: 3630 | P36: 3630 | Q36: 3630 | R36: 3795 | S36: =SUM(G36:R36) -> 43725
C37: MUZAFFER(Residents Otosan) | D37: Technician | E37: Manufacturing | F37: 포드 셔틀 | G37: - | H37: - | I37: - | J37: - | K37: - | L37: - | M37: - | N37: - | O37: - | P37: - | Q37: - | R37: - | S37: -
C38: BAHADIR (Residents Nursan) | D38: Technician | E38: Manufacturing | F38: 널산 셔틀 | G38: - | H38: - | I38: - | J38: - | K38: - | L38: - | M38: - | N38: - | O38: - | P38: - | Q38: - | R38: - | S38: -
C39: İBRAHIM (Residents Takosan) | D39: Technician | E39: Manufacturing | F39: 최소거리 | G39: 3630 | H39: 3630 | I39: 3630 | J39: 3630 | K39: 3630 | L39: 3630 | M39: 3630 | N39: 3630 | O39: 3630 | P39: 3630 | Q39: 3630 | R39: 3795 | S39: =SUM(G39:R39) -> 43725
B41: 영업 (예상) | C41: Korean Manager | D41: Manager | E41: Accounting-Finance | F41: 최소거리 | G41: - | H41: - | I41: - | J41: - | K41: - | L41: - | M41: 3630 | N41: 3630 | O41: 3630 | P41: 3630 | Q41: 3630 | R41: 3795 | S41: =SUM(G41:R41) -> 21945
B42: Sales | C42: TBD | D42: Engineer | E42: Accounting-Finance | F42: 최소거리 | G42: - | H42: 3630 | I42: 3630 | J42: 3630 | K42: 3630 | L42: 3630 | M42: 3630 | N42: 3630 | O42: 3630 | P42: 3630 | Q42: 3630 | R42: 3795 | S42: =SUM(G42:R42) -> 40095
B43: Purchaing | C43: TBD | D43: Engineer | E43: Accounting-Finance | F43: 최소거리 | G43: 3630 | H43: 3630 | I43: 3630 | J43: 3630 | K43: 3630 | L43: 3630 | M43: 3630 | N43: 3630 | O43: 3630 | P43: 3630 | Q43: 3630 | R43: 3795 | S43: =SUM(G43:R43) -> 43725
B44: MP&L | C44: TBD | D44: Engineer | E44: Manufacturing | F44: 최소거리 | G44: - | H44: - | I44: - | J44: - | K44: - | L44: - | M44: - | N44: 3630 | O44: 3630 | P44: 3630 | Q44: 3630 | R44: 3795 | S44: =SUM(G44:R44) -> 18315
B45: MP&L | C45: TBD | D45: Engineer | E45: Manufacturing | F45: 최소거리 | G45: - | H45: - | I45: - | J45: - | K45: - | L45: - | M45: - | N45: 3630 | O45: 3630 | P45: 3630 | Q45: 3630 | R45: 3795 | S45: =SUM(G45:R45) -> 18315
B46: Accounting-Finance Personel Expenses | G46: =SUM(G21:G28,G42:G43) -> 35876.643 | H46: =SUM(H21:H28,H42:H43) -> 39506.643 | I46: =SUM(I21:I28,I42:I43) -> 39506.643 | J46: =SUM(J21:J28,J42:J43) -> 39506.643 | K46: =SUM(K21:K28,K42:K43) -> 39506.643 | L46: =SUM(L21:L28,L42:L43) -> 39506.643 | M46: =SUM(M21:M28,M42:M43) -> 39506.643 | N46: =SUM(N21:N28,N42:N43) -> 39506.643 | ... R46: =SUM(R21:R28,R42:R43) -> 40661.643 | S46: =SUM(S21:S28,S41:S43) -> 493549.71
B47: Manufacturing Personel Expenses | G47: =SUM(G29:G39,G44:G45) -> 33421 | H47: =SUM(H29:H39,H44:H45) -> 33421 | I47: =SUM(I29:I39,I44:I45) -> 33421 | J47: =SUM(J29:J39,J44:J45) -> 33421 | K47: =SUM(K29:K39,K44:K45) -> 33421 | L47: =SUM(L29:L39,L44:L45) -> 33421 | M47: =SUM(M29:M39,M44:M45) -> 33421 | N47: =SUM(N29:N39,N44:N45) -> 40681 | ... S47: =SUM(S29:S39,S44:S45) -> 438672
B48: 총금액 | G48: =SUM(G21:G45) -> 69297.643 | H48: =SUM(H21:H45) -> 72927.643 | I48: =SUM(I21:I45) -> 72927.643 | J48: =SUM(J21:J45) -> 72927.643 | K48: =SUM(K21:K45) -> 72927.643 | L48: =SUM(L21:L45) -> 72927.643 | M48: =SUM(M21:M45) -> 76557.643 | N48: =SUM(N21:N45) -> 83817.643 | ... S48: =SUM(S21:S45) -> 932221.71

Sheet 6. Social Benefit-2
B1: ▣ KCTR stationery/water
D4: January | E4: February | F4: March | G4: April | H4: May | I4: June | J4: July | K4: August | L4: September | M4: October | N4: November | O4: December | P4: Annual Total | Q4: Remark | R4: Remark
B5: Office stationery | D5: =1000*22 -> 22000 | E5: =1000*20 -> 20000 | F5: =1000*20 -> 20000 | G5: =1000*20 -> 20000 | H5: =1000*20 -> 20000 | I5: =1000*20 -> 20000 | J5: =1000*20 -> 20000 | K5: =1000*20 -> 20000 | L5: =1000*20 -> 20000 | ... O5: =1000*20 -> 20000 | P5: =SUM(D5:O5) -> 242000 | Q5: 25 : 5,418 TL | R5: 1000TL/per employees monthly
B6: Water, tea, coffee, and refreshments | D6: =1000*22 -> 22000 | E6: =1000*22 -> 22000 | F6: =1000*22 -> 22000 | G6: =1000*22 -> 22000 | H6: =1000*22 -> 22000 | I6: =1000*22 -> 22000 | J6: =1000*22 -> 22000 | K6: =1000*22 -> 22000 | ... O6: =1000*22 -> 22000 | P6: =SUM(D6:O6) -> 264000 | Q6: 25 : 9,416 TL | R6: 1000TL/per employees monthly
B7: Cleaning supplies | D7: 2000 | E7: 2000 | F7: 2000 | G7: 2000 | H7: 2000 | I7: 2000 | J7: 2000 | K7: 2000 | L7: 2000 | M7: 2000 | N7: 2000 | O7: 2000 | P7: =SUM(D7:O7) -> 24000 | Q7: 25 : 2,131 TL | R7: 2,000TL/Per month
B8: Emergency Pills | D8: 1000 | E8: 1000 | F8: 1000 | G8: 1000 | H8: 1000 | I8: 1000 | J8: 1000 | K8: 1000 | L8: 1000 | M8: 1000 | N8: 1000 | O8: 1000 | P8: =SUM(D8:O8) -> 12000 | Q8: - | R8: 1000TL/Per month
B9: Work Safety Plate etc | D9: 1000 | E9: 1000 | F9: 1000 | G9: 1000 | H9: 1000 | I9: 1000 | J9: 1000 | K9: 1000 | L9: 1000 | M9: 1000 | N9: 1000 | O9: 1000 | P9: =SUM(D9:O9) -> 12000 | Q9: - | R9: 1000TL/Per month
B11: ▣ KCTR Social benefit | F11: Total HR | G11: 24 | I11: Accounting-Finance | J11: 11 | K11: Manufacturing | L11: 11
D14: January | E14: February | F14: March | G14: April | H14: May | I14: June | J14: July | K14: August | L14: September | M14: October | N14: November | O14: December | P14: Annual Total | Q14: Remark | R14: 횟수 | S14: 인원
B15: Other & Holiday Gift | D15: =SUM(D16:D18) -> 2000 | E15: =SUM(E16:E18) -> 2000 | F15: =SUM(F16:F18) -> 146000 | G15: =SUM(G16:G18) -> 2000 | H15: =SUM(H16:H18) -> 2000 | I15: =SUM(I16:I18) -> 2000 | J15: =SUM(J16:J18) -> 2000 | K15: =SUM(K16:K18) -> 2000 | ... O15: =SUM(O16:O18) -> 2000 | P15: =SUM(D15:O15) -> 168000
C16: Executive Expenses | D16: 0 | E16: 0 | F16: 0 | G16: 0 | H16: 0 | I16: 0 | J16: 0 | K16: 0 | L16: 0 | M16: 0 | N16: 0 | O16: 0 | P16: =SUM(D16:O16) -> 0
C17: Accounting-Finance Personel | D17: =((D19+D20)*0.5) -> 1000 | E17: =((E19+E20)*0.5) -> 1000 | F17: =((F19+F20)*0.5) -> 73000 | G17: =((G19+G20)*0.5) -> 1000 | H17: =((H19+H20)*0.5) -> 1000 | I17: =((I19+I20)*0.5) -> 1000 | J17: =((J19+J20)*0.5) -> 1000 | K17: =((K19+K20)*0.5) -> 1000 | ... P17: =((P19+P20)*0.5) -> 84000 | S17: Current 8, plan 3
C18: Manufacturing Personel | D18: =((D19+D20)*0.5) -> 1000 | E18: =((E19+E20)*0.5) -> 1000 | F18: =((F19+F20)*0.5) -> 73000 | G18: =((G19+G20)*0.5) -> 1000 | H18: =((H19+H20)*0.5) -> 1000 | I18: =((I19+I20)*0.5) -> 1000 | J18: =((J19+J20)*0.5) -> 1000 | K18: =((K19+K20)*0.5) -> 1000 | ... P18: =((P19+P20)*0.5) -> 84000 | S18: Current 8, plan 3
B19: Birthday Gift/fee | D19: 2000 | E19: 2000 | F19: 2000 | G19: 2000 | H19: 2000 | I19: 2000 | J19: 2000 | K19: 2000 | L19: 2000 | M19: 2000 | N19: 2000 | O19: 2000 | P19: =SUM(D19:O19) -> 24000 | Q19: 생일 케익 (1,000/인) | R19: 1회/년 | S19: 24
B20: holiday Gift | F20: ='3. HR'!H7*6000 -> 144000 | P20: =SUM(D20:O20) -> 144000 | Q20: 3월 (Ramadan) 3/19 각각 6,000TL | R20: 1회/년 | S20: 23
B22: KCTR 회식(dinner) | D22: 50000 | E22: 50000 | F22: 50000 | G22: 50000 | H22: 50000 | I22: 50000 | J22: 50000 | K22: 50000 | L22: 50000 | M22: 50000 | N22: 50000 | O22: 50000 | P22: =SUM(D22:O22) -> 600000 | Q22: KCTR 회식 : 30,000TL | R22: 1회/월
B23: KCTR 회식 (Team dinner) | D23: 20000 | E23: 20000 | F23: 20000 | G23: 20000 | H23: 20000 | I23: 20000 | J23: 20000 | K23: 20000 | L23: 20000 | M23: 20000 | N23: 20000 | O23: 20000 | P23: =SUM(D23:O23) -> 240000 | Q23: 팀별 회식 : 10,000TL | R23: 2회/월
B24: 손님 접식대 (Guest dinner) | D24: 35000 | E24: 35000 | F24: 35000 | G24: 35000 | H24: 35000 | I24: 35000 | J24: 35000 | K24: 35000 | L24: 35000 | M24: 35000 | N24: 35000 | O24: 35000 | P24: =SUM(D24:O24) -> 420000 | Q24: 필요시 : 10,000TL | R24: 2회/월 | S24: KCTR 외부 이해관계자 (포드, 협력사, 기타)
B25: Car washing | D25: =600*2*8 -> 9600 | E25: =600*2*8 -> 9600 | F25: =600*2*8 -> 9600 | G25: =600*2*8 -> 9600 | H25: =600*2*8 -> 9600 | I25: =600*2*8 -> 9600 | J25: =600*2*8 -> 9600 | K25: =600*2*8 -> 9600 | ... O25: =600*2*8 -> 9600 | P25: =SUM(D25:O25) -> 115200 | Q25: 600 TL | R25: 2 times/team leader
B28: ▣ KCTR Warehouse Maintenance
D31: Jan | E31: Feb | F31: Mar | G31: Apr | H31: May | I31: Jun | J31: Jul | K31: Aug | L31: Sep | M31: Oct | N31: Nov | O31: Dec | P31: Annual Total | Q31: Remark
B32: OHS (Occupational Health and Safety Unit) service fee | D32: =6590*1.3 -> 8567 | E32: =6590*1.3 -> 8567 | F32: =6590*1.3 -> 8567 | G32: =6590*1.3 -> 8567 | H32: =6590*1.3 -> 8567 | I32: =6590*1.3 -> 8567 | J32: =6590*1.3 -> 8567 | K32: =6590*1.3 -> 8567 | ... O32: =6590*1.3 -> 8567 | P32: =SUM(D32:O32) -> 102804 | Q32: 25 : 6,590 TL (new warehouse)
B33: Maintenance fees | D33: =SUM(D34:D35) -> 0 | E33: =SUM(E34:E35) -> 0 | F33: =SUM(F34:F35) -> 0 | G33: =SUM(G34:G35) -> 12000 | H33: =SUM(H34:H35) -> 0 | I33: =SUM(I34:I35) -> 0 | J33: =SUM(J34:J35) -> 0 | K33: =SUM(K34:K35) -> 12000 | ... O33: =SUM(O34:O35) -> 12000 | P33: =SUM(D33:O33) -> 51000
C34: Forklift (n=3/year, Every 300Hr) | D34: 0 | E34: 0 | F34: 0 | G34: 12000 | H34: 0 | I34: 0 | J34: 0 | K34: 12000 | L34: 0 | M34: 0 | N34: 0 | O34: 12000 | P34: =SUM(D34:O34) -> 36000 | Q34: 25 : 9,700 TL
C35: Racking system audit (n=1/year) | L35: 15000 | P35: =SUM(D35:O35) -> 15000 | Q35: 25 : 8,100 TL
B38: ▣ KCTR health insurance
B41: health insurance | D41: Jan | E41: Feb | F41: Mar | G41: Apr | H41: May | I41: Jun | J41: Jul | K41: Aug | L41: Sep | M41: Oct | N41: Nov | O41: Dec | P41: Annual Total | Q41: Remark
B42: Health Insurance | D42: =SUM(D43:D45) -> 68009.102 | E42: =SUM(E43:E45) -> 42435.598 | F42: =SUM(F43:F45) -> 46000 | G42: =SUM(G43:G45) -> 75015.696 | H42: =SUM(H43:H45) -> 83792.45 | I42: =SUM(I43:I45) -> 0 | J42: =SUM(J43:J45) -> 200000 | K42: =SUM(K43:K45) -> 267305.92 | ... O42: =SUM(O43:O45) -> 23000 | P42: =SUM(D42:O42) -> 1366588.9
C43: 주재원 | J43: =I48 -> 200000 | K43: =I71 -> 200000 | L43: =I49 -> 362154.17 | P43: =SUM(D43:O43) -> 762154.17
C44: Finance/General | D44: =I52+I72 -> 48573.504 | E44: =I67 -> 23000 | F44: =I69+I70 -> 46000 | G44: =I54 -> 39625.096 | H44: =I58 -> 30551.164 | K44: =I59 -> 20540.884 | M44: =I60 -> 30444.498 | O44: =I68 -> 23000 | P44: =SUM(D44:O44) -> 261735.15
C45: Manufacturing | D45: =I53 -> 19435.598 | E45: =I53 -> 19435.598 | G45: =I55 -> 35390.6 | H45: =I56+I57 -> 53241.286 | K45: =I73+I74 -> 46765.04 | M45: =I61+I62+I64+I65+I66 -> 121235.36 | N45: =I50+I51 -> 47196.058 | P45: =SUM(D45:O45) -> 342699.54
C47: Staff Information | D47: Title | E47: Job Start Date | F47: Health Insurance Start Date | G47: Health Insurance Expiration Date | H47: Price 2025 | I47: Price 2026 | J47: Renew Date | K47: Type
C48: Hyun Min Cho | D48: General Manager | E48: 44743 | F48: 45867 | G48: 46232 | H48: 80000 | I48: 200000 | J48: Jul | K48: 주재원
C49: Soo Hyung Lee | D49: Deputy General Manager | E49: 45474 | F49: 45902 | G49: 46267 | H49: 258681.55 | I49: =258681.55*1.4 -> 362154.17 | J49: sep | K49: 주재원
C50: Tugay Birben | D50: Staff | E50: 45883 | F50: 45623 | G50: 45988 | H50: 16701.8 | I50: =16701.8*1.4 -> 23382.52 | J50: nov | K50: Manufacturing
C51: Öznur Kocaman | D51: Supervisor | E51: 45883 | F51: 45625 | G51: 45990 | H51: 17009.67 | I51: =17009.67*1.4 -> 23813.538 | J51: nov | K51: Manufacturing
C52: Kübra Ceren Özen | D52: Engineer | E52: 45544 | F52: 45674 | G52: 46039 | H52: 17993.56 | I52: =17993.56*1.4 -> 25190.984 | J52: jan | K52: Finance/General
C53: Akın Ilgaz | D53: Specialist | E53: 45597 | F53: 45691 | G53: 46056 | H53: 13882.57 | I53: =13882.57*1.4 -> 19435.598 | J53: feb | K53: Manufacturing
C54: Merve Gündüz | D54: Manager | E54: 44769 | F54: 45771 | G54: 46136 | H54: 28303.64 | I54: =28303.64*1.4 -> 39625.096 | J54: april | K54: Finance/General
C55: Ceren Karakoçum | D55: Manager | E55: 44823 | F55: 45773 | G55: 46138 | H55: 25279 | I55: =25279*1.4 -> 35390.6 | J55: april | K55: Manufacturing
C56: Muzaffer Türk | D56: Technician | E56: 45630 | F56: 45790 | G56: 46155 | H56: 18983.01 | I56: =18983.01*1.4 -> 26576.214 | J56: may | K56: Manufacturing
C57: İbrahim Osmanlı | D57: Technician | E57: 45635 | F57: 45790 | G57: 46155 | H57: 19046.48 | I57: =19046.48*1.4 -> 26665.072 | J57: may | K57: Manufacturing
C58: Ozge Reçber | D58: Supervisor | E58: 45323 | F58: 45804 | G58: 46169 | H58: 21822.26 | I58: =21822.26*1.4 -> 30551.164 | J58: may | K58: Finance/General
C59: Melis Biçer Yıldız | D59: Engineer | E59: 45726 | F59: 45888 | G59: 46253 | H59: 14672.06 | I59: =14672.06*1.4 -> 20540.884 | J59: aug | K59: Finance/General
C60: Elif Çağla Karagöl | D60: Specialist | E60: 45824 | F60: 45932 | G60: 46297 | H60: 21746.07 | I60: =21746.07*1.4 -> 30444.498 | J60: oct | K60: Finance/General
C61: Meriç Emre Bayraktar | D61: Asistant Specialist | E61: 45827 | F61: 45932 | G61: 46297 | H61: 9751.66 | I61: =9751.66*1.4 -> 13652.324 | J61: oct | K61: Manufacturing
C62: Murat Özen | D62: Specialist | E62: 45446 | F62: 45939 | G62: 46304 | H62: 21441.33 | I62: =21441.33*1.4 -> 30017.862 | J62: oct | K62: Manufacturing
C63: Hee Chan shin | D63: Specialist | E63: 45474 | F63: 45948 | G63: 46313 | H63: 40839.9 | I63: - | J63: - | K63: Finance/General
C64: Chan Ho Park | D64: Specialist | E64: 45908 | F64: 45954 | G64: 46319 | H64: 27771.6 | I64: =27771.6*1.4 -> 38880.24 | J64: oct | K64: Manufacturing
C65: Sevdenur Ayhan | D65: Engineer | E65: 45841 | F65: 45954 | G65: 46319 | H65: 18791.87 | I65: =18791.87*1.4 -> 26308.618 | J65: oct | K65: Manufacturing
C66: Fevzi Bahadır Yılmaz | D66: Technician | E66: 45834 | F66: 45954 | G66: 46319 | H66: 12376.32 | I66: 12376.32 | J66: oct | K66: Manufacturing
C67: Haticenur Şeker | D67: Asistant Specialist | E67: 45978 | F67: =E67+90 -> 46068 | G67: - | H67: - | I67: 23000 | J67: feb | K67: Finance/General
C68: Gülsüm Özdemir | D68: Cleaner | E68: 45917 | F68: =E68+90 -> 46007 | G68: - | H68: - | I68: 23000 | J68: dec | K68: Finance/General
C69: New | D69: Cost | E69: dec | F69: 46082 | G69: - | H69: - | I69: 23000 | J69: mar | K69: Finance/General
C70: New | D70: Cost | E70: dec | F70: 46082 | G70: - | H70: - | I70: 23000 | J70: mar | K70: Finance/General
C71: New | D71: New manager | E71: TBD | F71: 46264 | G71: TBD | H71: - | I71: =I48 -> 200000 | J71: TBD | K71: 주재원
C72: New | D72: Procurement | E72: TBD | F72: 46052 | G72: TBD | H72: - | I72: =$I$50 -> 23382.52 | J72: TBD | K72: Finance/General
C73: New | D73: MP&L | E73: TBD | F73: 46264 | G73: TBD | H73: - | I73: =$I$50 -> 23382.52 | J73: TBD | K73: Manufacturing
C74: New | D74: MP&L | E74: TBD | F74: 46264 | G74: TBD | H74: - | I74: =$I$50 -> 23382.52 | J74: TBD | K74: Manufacturing

Sheet 7. Commucation 
B1: ▣ `26 Telecommunications Services
B4: 2026 | C4: DESCRIPTION | D4: Monthly | E4: Yearly | F4: Remark | G4: Remark
B5: Office İnternet | C5: Fixed monthly internet fee is paid | D5: =11036.72*1.32 -> 14568.47 | E5: =D5*12 -> 174821.64 | F5: Office | G5: `25 : 11,036.72 TL
B6: Company Phone line | C6: There are two separate lines paid through the company | D6: 2200 | E6: =D6*12 -> 26400 | F6: Joe | G6: `25 : 1,521 TL, `26 Nov expired
D7: 2200 | E7: =D7*12 -> 26400 | F7: Lee | G7: `25 : 1,521 TL, `26 Nov expired
D8: 905 | E8: =D8*12 -> 10860 | F8: Merve | G8: `25 : 690 TL, `26 Nov expired
D9: 905 | E9: =D9*12 -> 10860 | F9: Ceren | G9: `25 : 690 TL, `26 Oct expired
C10: Total | D10: =SUM(D5:D9) -> 20778.47 | E10: =SUM(E5:E9) -> 249341.64 | F10: Total
B12: ▣ RENT Car
D15: January | E15: February | F15: March | G15: April | H15: May | I15: June | J15: July | K15: August | L15: September | M15: October | N15: November | O15: December | P15: Annual Total | Q15: 계약 기간 | R15: Remark
B16: Vehicle rental expenses (including leasing) | D16: =SUM(D17:D20) -> 133750 | E16: =SUM(E17:E20) -> 133750 | F16: =SUM(F17:F20) -> 133750 | G16: =SUM(G17:G20) -> 133750 | H16: =SUM(H17:H20) -> 159750 | I16: =SUM(I17:I20) -> 159750 | J16: =SUM(J17:J20) -> 159750 | K16: =SUM(K17:K20) -> 159750 | ... P16: =SUM(P17:P20) -> 1813000
C17: Executive Expenses | D17: =SUM(D21,D22,D25) -> 76750 | E17: =SUM(E21,E22,E25) -> 76750 | F17: =SUM(F21,F22,F25) -> 76750 | G17: =SUM(G21,G22,G25) -> 76750 | H17: =SUM(H21,H22,H25) -> 102750 | I17: =SUM(I21,I22,I25) -> 102750 | J17: =SUM(J21,J22,J25) -> 102750 | K17: =SUM(K21,K22,K25) -> 102750 | ... O17: =SUM(O21,O22,O25) -> 102750 | P17: =SUM(D17:O17) -> 1129000
C18: Accounting-Finance Personel | D18: 0 | E18: 0 | F18: 0 | G18: 0 | H18: 0 | I18: 0 | J18: 0 | K18: 0 | L18: 0 | M18: 0 | N18: 0 | O18: 0 | P18: 0
C19: Manufacturing Personel | D19: =D24 -> 30000 | E19: =E24 -> 30000 | F19: =F24 -> 30000 | G19: =G24 -> 30000 | H19: =H24 -> 30000 | I19: =I24 -> 30000 | J19: =J24 -> 30000 | K19: =K24 -> 30000 | ... O19: =O24 -> 30000 | P19: =SUM(D19:O19) -> 360000
C20: Shared Car Rental Fee | D20: =D23 -> 27000 | E20: =E23 -> 27000 | F20: =F23 -> 27000 | G20: =G23 -> 27000 | H20: =H23 -> 27000 | I20: =I23 -> 27000 | J20: =J23 -> 27000 | K20: =K23 -> 27000 | ... P20: =P23 -> 324000
C21: Hyudai Tucson | D21: 34000 | E21: 34000 | F21: 34000 | G21: 34000 | H21: 60000 | I21: 60000 | J21: 60000 | K21: 60000 | L21: 60000 | M21: 60000 | N21: 60000 | O21: 60000 | P21: =SUM(D21:O21) -> 616000 | Q21: 23.06/01~26.05/31 | R21: `26년 5월 계약 종료
C22: Hyudai Elantra | D22: 42750 | E22: 42750 | F22: 42750 | G22: 42750 | H22: 42750 | I22: 42750 | J22: 42750 | K22: 42750 | L22: 42750 | M22: 42750 | N22: 42750 | O22: 42750 | P22: =SUM(D22:O22) -> 513000 | Q22: 25.01/01~27.12/31 | R22: 주행거리 초과로 변경
C23: Hyudai i20 (신희찬) 공용 | D23: 27000 | E23: 27000 | F23: 27000 | G23: 27000 | H23: 27000 | I23: 27000 | J23: 27000 | K23: 27000 | L23: 27000 | M23: 27000 | N23: 27000 | O23: 27000 | P23: =SUM(D23:O23) -> 324000 | Q23: 24.07/01~27.06/30
C24: Hyudai i20 (Park) | D24: 30000 | E24: 30000 | F24: 30000 | G24: 30000 | H24: 30000 | I24: 30000 | J24: 30000 | K24: 30000 | L24: 30000 | M24: 30000 | N24: 30000 | O24: 30000 | P24: =SUM(D24:O24) -> 360000 | Q24: 24.02/06~27.02/05
C25: KCTR Car (Purchasing) Ford Explorer(기준가) | D25: 0 | E25: 0 | F25: 0 | G25: 0 | H25: 0 | I25: 0 | J25: 0 | K25: 0 | L25: 0 | M25: 0 | N25: 0 | O25: 0 | P25: =SUM(E25:O25) -> 0
C26: new Car Tax | D26: 0 | E26: 0 | F26: 0 | G26: 0 | H26: 0 | I26: 0 | J26: 0 | K26: 0 | L26: 0 | M26: 0 | N26: 0 | O26: 0
B27: Fuel expenses | D27: =SUM(D28:D30) -> 44000 | E27: =SUM(E28:E30) -> 44000 | F27: =SUM(F28:F30) -> 44000 | G27: =SUM(G28:G30) -> 44000 | H27: =SUM(H28:H30) -> 44000 | I27: =SUM(I28:I30) -> 44000 | J27: =SUM(J28:J30) -> 44000 | K27: =SUM(K28:K30) -> 44000 | ... P27: =SUM(P28:P30) -> 484000
C28: Executive | D28: 32000 | E28: 32000 | F28: 32000 | G28: 32000 | H28: 32000 | I28: 32000 | J28: 32000 | K28: 32000 | L28: 32000 | M28: 32000 | N28: 32000 | O28: 32000 | P28: =SUM(E28:O28) -> 352000 | Q28: 자동차 유류대_조현민/이수형 (1회 주유 2,000TL x 2회/주 x 4주) | R28: `25년 동일
C29: Accounting-Finance | D29: 8000 | E29: 8000 | F29: 8000 | G29: 8000 | H29: 8000 | I29: 8000 | J29: 8000 | K29: 8000 | L29: 8000 | M29: 8000 | N29: 8000 | O29: 8000 | P29: =SUM(E29:O29) -> 88000 | R29: `25년 동일
C30: Manufacturing | D30: 4000 | E30: 4000 | F30: 4000 | G30: 4000 | H30: 4000 | I30: 4000 | J30: 4000 | K30: 4000 | L30: 4000 | M30: 4000 | N30: 4000 | O30: 4000 | P30: =SUM(E30:O30) -> 44000 | R30: `25년 동일
B31: Toll & Parking Expenses | D31: =SUM(D32:D34) -> 13000 | E31: =SUM(E32:E34) -> 13000 | F31: =SUM(F32:F34) -> 13000 | G31: =SUM(G32:G34) -> 13000 | H31: =SUM(H32:H34) -> 13000 | I31: =SUM(I32:I34) -> 13000 | J31: =SUM(J32:J34) -> 13000 | K31: =SUM(K32:K34) -> 13000 | ... P31: =SUM(P32:P34) -> 143000
C32: Executive | D32: 10000 | E32: 10000 | F32: 10000 | G32: 10000 | H32: 10000 | I32: 10000 | J32: 10000 | K32: 10000 | L32: 10000 | M32: 10000 | N32: 10000 | O32: 10000 | P32: =SUM(E32:O32) -> 110000 | Q32: 톨비 10,000TL/월 | R32: `25 8,800 TL 평균
C33: Accounting-Finance | D33: 1500 | E33: 1500 | F33: 1500 | G33: 1500 | H33: 1500 | I33: 1500 | J33: 1500 | K33: 1500 | L33: 1500 | M33: 1500 | N33: 1500 | O33: 1500 | P33: =SUM(E33:O33) -> 16500 | R33: `25 710 TL 평균
C34: Manufacturing | D34: 1500 | E34: 1500 | F34: 1500 | G34: 1500 | H34: 1500 | I34: 1500 | J34: 1500 | K34: 1500 | L34: 1500 | M34: 1500 | N34: 1500 | O34: 1500 | P34: =SUM(E34:O34) -> 16500 | R34: `25 1100 TL 평균
B35: Repair Company Car Expenses | D35: =SUM(D36:D38) -> 0 | E35: =SUM(E36:E38) -> 0 | F35: =SUM(F36:F38) -> 20000 | G35: =SUM(G36:G38) -> 0 | H35: =SUM(H36:H38) -> 0 | I35: =SUM(I36:I38) -> 0 | J35: =SUM(J36:J38) -> 0 | K35: =SUM(K36:K38) -> 0 | ... P35: =SUM(P36:P38) -> 20000
C36: Executive | D36: 0 | E36: 0 | F36: 10000 | G36: 0 | H36: 0 | I36: 0 | J36: 0 | K36: 0 | L36: 0 | M36: 0 | N36: 0 | O36: 0 | P36: =SUM(E36:O36) -> 10000 | Q36: 동계 타이어교체
C37: Accounting-Finance | D37: 0 | E37: 0 | F37: 5000 | G37: 0 | H37: 0 | I37: 0 | J37: 0 | K37: 0 | L37: 0 | M37: 0 | N37: 0 | O37: 0 | P37: =SUM(E37:O37) -> 5000
C38: Manufacturing | D38: 0 | E38: 0 | F38: 5000 | G38: 0 | H38: 0 | I38: 0 | J38: 0 | K38: 0 | L38: 0 | M38: 0 | N38: 0 | O38: 0 | P38: =SUM(E38:O38) -> 5000
B42: ▣ 주재원 숙소
B45: Category | D45: DESCRIPTION | E45: January | F45: February | G45: March | H45: April | I45: May | J45: June | K45: July | L45: August | M45: September | N45: October | O45: November | P45: December | Q45: Annual Total | R45: 계약 만료 기간 | S45: Remark
B46: Executive rent house | D46: 합계 | E46: =SUM(E47:E52) -> 9100 | F46: =SUM(F47:F52) -> 453100 | G46: =SUM(G47:G52) -> 9100 | H46: =SUM(H47:H52) -> 1809100 | I46: =SUM(I47:I52) -> 9100 | J46: =SUM(J47:J52) -> 2889100 | K46: =SUM(K47:K52) -> 9100 | L46: =SUM(L47:L52) -> 9100 | ... Q46: =SUM(Q47:Q52) -> 5233200
C47: 렌트 1 | D47: 조현민 책임 | E47: - | F47: - | G47: - | H47: =150000*12 -> 1800000 | I47: - | J47: - | K47: - | L47: - | M47: - | N47: - | O47: - | P47: - | Q47: =SUM(E47:P47) -> 1800000 | R47: 46124 | S47: 1년 렌트비 납부예정(`26년 4월) 25년 : 110,000 TL
C48: 렌트 2 | D48: 조현민 책임 | E48: - | F48: =19000*12 -> 228000 | G48: - | H48: - | I48: - | J48: - | K48: - | L48: - | M48: - | N48: - | O48: - | P48: - | Q48: =SUM(E48:P48) -> 228000 | R48: 46067 | S48: 1년 렌트비 납부예정(`26년 2월) 25년 : 14,000 TL
C49: 렌트 3 | D49: 이수형 선임 | E49: - | F49: - | G49: - | H49: - | I49: - | J49: =120000*12 -> 1440000 | K49: - | L49: - | M49: - | N49: - | O49: - | P49: - | Q49: =SUM(E49:P49) -> 1440000 | R49: 46180 | S49: 1년 렌트비 납부예정(`26년 6월) 25년 : 90,000 TL
C50: 렌트 4 | D50: 이수형 선임 | E50: - | F50: =18000*12 -> 216000 | G50: - | H50: - | I50: - | J50: - | K50: - | L50: - | M50: - | N50: - | O50: - | P50: - | Q50: =SUM(E50:P50) -> 216000 | R50: 46081 | S50: 1년 렌트비 납부예정(`26년 2월), 25년 : 13,541 TL
C51: 렌트 5 | D51: 신규 주재원 | E51: - | F51: - | G51: - | H51: - | I51: - | J51: =120000*12 -> 1440000 | K51: - | L51: - | M51: - | N51: - | O51: - | P51: - | Q51: =SUM(E51:P51) -> 1440000 | R51: 46081 | S51: 1년 렌트비 납부예정(`26년 2월), 25년 : 13,541 TL
C52: Executive rent house management fee(Electricity/water) | D52: 주재원 | E52: =7000*1.3 -> 9100 | F52: =7000*1.3 -> 9100 | G52: =7000*1.3 -> 9100 | H52: =7000*1.3 -> 9100 | I52: =7000*1.3 -> 9100 | J52: =7000*1.3 -> 9100 | K52: =7000*1.3 -> 9100 | L52: =7000*1.3 -> 9100 | ... P52: =7000*1.3 -> 9100 | Q52: =SUM(E52:P52) -> 109200
B54: Rent Support | R54: 계약 만료 기간 | S54: Remark
C55: Accounting-Finance Personel | D55: 0 | E55: 0 | F55: 0 | G55: 0 | H55: 0 | I55: 0 | J55: 0 | K55: 0 | L55: 0 | M55: 0 | N55: 0 | O55: 0 | P55: 0 | Q55: -
C56: Manufacturing Personel | D56: 35000 | E56: 35000 | F56: 35000 | G56: 35000 | H56: 35000 | I56: 35000 | J56: 35000 | K56: 35000 | L56: 35000 | M56: 35000 | N56: 35000 | O56: 35000 | P56: =SUM(D56:O56) -> 420000 | Q56: - | R56: Akin/Park:15,000TL, Murat:5000TL

Sheet 8. Export, Import1
B1: ▣ `26 KCTR Export Expenses | T1: ▣ `25 Export Expenses monthly | AH1: ▣ `26 Export Expenses monthly (Esti.)
B4: Description & Months | C4: 1 | D4: 2 | E4: 3 | F4: 4 | G4: 5 | H4: 6 | I4: 7 | J4: 8 | K4: 9 | L4: 10 | M4: 11 | N4: 12 | O4: Total | T4: 2025 | AG4: Total | AH4: 2026 | AT4: Total
B5: Export Expenses | C5: =+SUM(C6:C10) -> 82238.147 | D5: =+SUM(D6:D10) -> 82238.147 | E5: =+SUM(E6:E10) -> 82238.147 | F5: =+SUM(F6:F10) -> 82238.147 | G5: =+SUM(G6:G10) -> 82238.147 | H5: =+SUM(H6:H10) -> 82238.147 | I5: =+SUM(I6:I10) -> 82238.147 | J5: =+SUM(J6:J10) -> 164476.29 | ... N5: =+SUM(N6:N10) -> 164476.29 | O5: =SUM(C5:N5) -> 1398048.5 | T5: Description & Months | U5: 1 | V5: 2 | W5: 3 | X5: 4 | Y5: 5 | Z5: 6 | AA5: 7 | AB5: 8 | AC5: 9 | AD5: 10 | AE5: 11 | AF5: 12 | AH5: 1 | AI5: 2 | AJ5: 3 | AK5: 4 | AL5: 5 | AM5: 6 | AN5: 7 | AO5: 8 | AP5: 9 | AQ5: 10 | AR5: 11 | AS5: 12
B6: Shipping &Courier Expenses | C6: =AH7 -> 23901.116 | D6: =AI7 -> 23901.116 | E6: =AJ7 -> 23901.116 | F6: =AK7 -> 23901.116 | G6: =AL7 -> 23901.116 | H6: =AM7 -> 23901.116 | I6: =AN7 -> 23901.116 | J6: =AO7 -> 47802.232 | ... N6: =AS7 -> 47802.232 | O6: =+SUM(C6:N6) -> 406318.98 | T6: Export Expenses | U6: =+SUM(U7:U12) -> 34622.36 | V6: =+SUM(V7:V12) -> 36793.81 | W6: =+SUM(W7:W12) -> 118060.41 | X6: =+SUM(X7:X12) -> 97745.91 | Y6: =+SUM(Y7:Y12) -> 58568.5 | Z6: =+SUM(Z7:Z12) -> 66514.86 | AA6: =+SUM(AA7:AA12) -> 85593.89 | AB6: =+SUM(AB7:AB12) -> 22715.52 | ... AD6: =+SUM(AD7:AD12) -> 71372.38 | AE6: =+SUM(AE7:AE13) -> 64607.141 | AF6: =+SUM(AF7:AF13) -> 64607.141 | AH6: =+SUM(AH7:AH12) -> 82238.147 | AI6: =+SUM(AI7:AI12) -> 82238.147 | AJ6: =+SUM(AJ7:AJ12) -> 82238.147 | AK6: =+SUM(AK7:AK12) -> 82238.147 | AL6: =+SUM(AL7:AL12) -> 82238.147 | AM6: =+SUM(AM7:AM12) -> 82238.147 | AN6: =+SUM(AN7:AN12) -> 82238.147 | AO6: =+SUM(AO7:AO12) -> 164476.29 | ... AS6: =+SUM(AS7:AS12) -> 164476.29
B7: Export Charges | C7: =AH8 -> 0 | D7: =AI8 -> 0 | E7: =AJ8 -> 0 | F7: =AK8 -> 0 | G7: =AL8 -> 0 | H7: =AM8 -> 0 | I7: =AN8 -> 0 | J7: =AO8 -> 0 | ... N7: =AS8 -> 0 | O7: =+SUM(C7:N7) -> 0 | T7: Shipping &Courier Expenses | U7: 15323.36 | V7: 3000 | W7: 61029.01 | X7: 49802.01 | Y7: 7800 | Z7: 21255.36 | AA7: 13200 | AB7: 6445 | AC7: 2100 | AD7: 3900 | AE7: =AVERAGE(U7:AD7) -> 18385.474 | AF7: =AVERAGE(U7:AD7) -> 18385.474 | AG7: =+SUM(U7:AF7) -> 220625.69 | AH7: =$AT$7/12 -> 23901.116 | AI7: =$AT$7/12 -> 23901.116 | AJ7: =$AT$7/12 -> 23901.116 | AK7: =$AT$7/12 -> 23901.116 | AL7: =$AT$7/12 -> 23901.116 | AM7: =$AT$7/12 -> 23901.116 | AN7: =$AT$7/12 -> 23901.116 | AO7: =$AT$7/12*2 -> 47802.232 | AP7: =$AT$7/12*2 -> 47802.232 | AQ7: =$AT$7/12*2 -> 47802.232 | AR7: =$AT$7/12*2 -> 47802.232 | AS7: =$AT$7/12*2 -> 47802.232 | AT7: =$AG$7*(1+$N$21) -> 286813.39
B8: Warehouse Charges | C8: =AH9 -> 8755.676 | D8: =AI9 -> 8755.676 | E8: =AJ9 -> 8755.676 | F8: =AK9 -> 8755.676 | G8: =AL9 -> 8755.676 | H8: =AM9 -> 8755.676 | I8: =AN9 -> 8755.676 | J8: =AO9 -> 17511.352 | ... N8: =AS9 -> 17511.352 | O8: =+SUM(C8:N8) -> 148846.49 | T8: Export Charges | AG8: =+SUM(U8:AF8) -> 0 | AT8: =SUM(AH8:AS8) -> 0
B9: Transport labour | C9: =AH10 -> 32447.412 | D9: =AI10 -> 32447.412 | E9: =AJ10 -> 32447.412 | F9: =AK10 -> 32447.412 | G9: =AL10 -> 32447.412 | H9: =AM10 -> 32447.412 | I9: =AN10 -> 32447.412 | J9: =AO10 -> 64894.825 | ... N9: =AS10 -> 64894.825 | O9: =+SUM(C9:N9) -> 551606.01 | T9: Warehouse Charges | U9: 2005 | W9: 9024 | X9: 9024 | Y9: 6016 | Z9: 6016 | AA9: 9024 | AC9: 7509.66 | AD9: 16038.64 | AE9: =AVERAGE(U9:AD9) -> 8082.1625 | AF9: =AVERAGE(U9:AD9) -> 8082.1625 | AG9: =+SUM(U9:AF9) -> 80821.625 | AH9: =$AT$9/12 -> 8755.676 | AI9: =$AT$9/12 -> 8755.676 | AJ9: =$AT$9/12 -> 8755.676 | AK9: =$AT$9/12 -> 8755.676 | AL9: =$AT$9/12 -> 8755.676 | AM9: =$AT$9/12 -> 8755.676 | AN9: =$AT$9/12 -> 8755.676 | AO9: =$AT$9/12*2 -> 17511.352 | AP9: =$AT$9/12*2 -> 17511.352 | AQ9: =$AT$9/12*2 -> 17511.352 | AR9: =$AT$9/12*2 -> 17511.352 | AS9: =$AT$9/12*2 -> 17511.352 | AT9: =AG9*(1+N23) -> 105068.11
B10: Other Export Expenses | C10: =AH11 -> 17133.943 | D10: =AI11 -> 17133.943 | E10: =AJ11 -> 17133.943 | F10: =AK11 -> 17133.943 | G10: =AL11 -> 17133.943 | H10: =AM11 -> 17133.943 | I10: =AN11 -> 17133.943 | J10: =AO11 -> 34267.886 | ... N10: =AS11 -> 34267.886 | O10: =+SUM(C10:N10) -> 291277.03 | T10: Transport labour | U10: 12073 | V10: 20930 | W10: 31178 | X10: 23596 | Y10: 23217 | Z10: 20991 | AA10: 47215.64 | AB10: 7755.02 | AC10: 23500.58 | AD10: 39139.24 | AE10: =AVERAGE(U10:AD10) -> 24959.548 | AF10: =AVERAGE(U10:AD10) -> 24959.548 | AG10: =+SUM(U10:AF10) -> 299514.58 | AH10: =$AT$10/12 -> 32447.412 | AI10: =$AT$10/12 -> 32447.412 | AJ10: =$AT$10/12 -> 32447.412 | AK10: =$AT$10/12 -> 32447.412 | AL10: =$AT$10/12 -> 32447.412 | AM10: =$AT$10/12 -> 32447.412 | AN10: =$AT$10/12 -> 32447.412 | AO10: =$AT$10/12*2 -> 64894.825 | AP10: =$AT$10/12*2 -> 64894.825 | AQ10: =$AT$10/12*2 -> 64894.825 | AR10: =$AT$10/12*2 -> 64894.825 | AS10: =$AT$10/12*2 -> 64894.825 | AT10: =AG10*(1+N24) -> 389368.95
B11: Other Taxes | C11: =+SUM(C12:C16) -> 13544.631 | D11: =+SUM(D12:D16) -> 13544.631 | E11: =+SUM(E12:E16) -> 13544.631 | F11: =+SUM(F12:F16) -> 13544.631 | G11: =+SUM(G12:G16) -> 13544.631 | H11: =+SUM(H12:H16) -> 13544.631 | I11: =+SUM(I12:I16) -> 13544.631 | J11: =+SUM(J12:J16) -> 27089.262 | ... N11: =+SUM(N12:N16) -> 27089.262 | O11: =SUM(C11:N11) -> 230258.73 | T11: Other Export Expenses | U11: 5221 | V11: 12863.81 | W11: 15033 | X11: 13527.5 | Y11: 21535.5 | Z11: 18252.5 | AA11: 16154.25 | AB11: 8515.5 | AC11: 8402 | AD11: 12294.5 | AE11: =AVERAGE(U11:AD11) -> 13179.956 | AF11: =AVERAGE(U11:AD11) -> 13179.956 | AG11: =+SUM(U11:AF11) -> 158159.47 | AH11: =$AT$11/12 -> 17133.943 | AI11: =$AT$11/12 -> 17133.943 | AJ11: =$AT$11/12 -> 17133.943 | AK11: =$AT$11/12 -> 17133.943 | AL11: =$AT$11/12 -> 17133.943 | AM11: =$AT$11/12 -> 17133.943 | AN11: =$AT$11/12 -> 17133.943 | AO11: =$AT$11/12*2 -> 34267.886 | AP11: =$AT$11/12*2 -> 34267.886 | AQ11: =$AT$11/12*2 -> 34267.886 | AR11: =$AT$11/12*2 -> 34267.886 | AS11: =$AT$11/12*2 -> 34267.886 | AT11: =AG11*(1+N24) -> 205607.31
B12: Membership Fee | C12: =$K$29/12 -> 2422.1199 | D12: =$K$29/12 -> 2422.1199 | E12: =$K$29/12 -> 2422.1199 | F12: =$K$29/12 -> 2422.1199 | G12: =$K$29/12 -> 2422.1199 | H12: =$K$29/12 -> 2422.1199 | I12: =$K$29/12 -> 2422.1199 | J12: =$K$29/12*2 -> 4844.2398 | K12: =$K$29/12*2 -> 4844.2398 | L12: =$K$29/12*2 -> 4844.2398 | M12: =$K$29/12*2 -> 4844.2398 | N12: =$K$29/12*2 -> 4844.2398 | O12: =+SUM(C12:N12) -> 41176.039 | T12: Other Tax | W12: 1796.4 | X12: 1796.4 | AG12: =+SUM(U12:AF12) -> 3592.8 | AT12: =AG12*(1+N24) -> 4670.64
B13: Stamp Duty | C13: =26709/12 -> 2225.75 | D13: =26709/12 -> 2225.75 | E13: =26709/12 -> 2225.75 | F13: =26709/12 -> 2225.75 | G13: =26709/12 -> 2225.75 | H13: =26709/12 -> 2225.75 | I13: =26709/12 -> 2225.75 | J13: =26709/12*2 -> 4451.5 | K13: =26709/12*2 -> 4451.5 | L13: =26709/12*2 -> 4451.5 | M13: =26709/12*2 -> 4451.5 | N13: =26709/12*2 -> 4451.5 | O13: =+SUM(C13:N13) -> 37837.75 | AE13: Esti. | AF13: Esti. | AG13: =+SUM(AG7:AG12) -> 762714.16 | AT13: =+SUM(AT7:AT12) -> 991528.41 | AU13: =+AT13/AG13-1 -> 0.3
B14: Penalty | C14: =$K$30/12 -> 2506.8171 | D14: =$K$30/12 -> 2506.8171 | E14: =$K$30/12 -> 2506.8171 | F14: =$K$30/12 -> 2506.8171 | G14: =$K$30/12 -> 2506.8171 | H14: =$K$30/12 -> 2506.8171 | I14: =$K$30/12 -> 2506.8171 | J14: =$K$30/12*2 -> 5013.6342 | K14: =$K$30/12*2 -> 5013.6342 | L14: =$K$30/12*2 -> 5013.6342 | M14: =$K$30/12*2 -> 5013.6342 | N14: =$K$30/12*2 -> 5013.6342 | O14: =+SUM(C14:N14) -> 42615.89
B15: Notary Expenses | C15: =$K$31/12 -> 3307.4665 | D15: =$K$31/12 -> 3307.4665 | E15: =$K$31/12 -> 3307.4665 | F15: =$K$31/12 -> 3307.4665 | G15: =$K$31/12 -> 3307.4665 | H15: =$K$31/12 -> 3307.4665 | I15: =$K$31/12 -> 3307.4665 | J15: =$K$31/12*2 -> 6614.933 | K15: =$K$31/12*2 -> 6614.933 | L15: =$K$31/12*2 -> 6614.933 | M15: =$K$31/12*2 -> 6614.933 | N15: =$K$31/12*2 -> 6614.933 | O15: =+SUM(C15:N15) -> 56226.93
B16: Other | C16: =$K$32/12 -> 3082.4777 | D16: =$K$32/12 -> 3082.4777 | E16: =$K$32/12 -> 3082.4777 | F16: =$K$32/12 -> 3082.4777 | G16: =$K$32/12 -> 3082.4777 | H16: =$K$32/12 -> 3082.4777 | I16: =$K$32/12 -> 3082.4777 | J16: =$K$32/12*2 -> 6164.9553 | K16: =$K$32/12*2 -> 6164.9553 | L16: =$K$32/12*2 -> 6164.9553 | M16: =$K$32/12*2 -> 6164.9553 | N16: =$K$32/12*2 -> 6164.9553 | O16: =+SUM(C16:N16) -> 52402.12
I19: Unit Service Fee
B20: Account Name | C20: Detail | G20: Company | I20: 2024 | J20: 2025 | K20: 2026 (Esti.) | L20: Increased Rate (`24~25) | M20: Average Rate (`24~25) | N20: Average Rate (`25~26) Esti.
B21: Shipping &Courier Expenses | C21: Shipping Expenses | G21: DCS Custom | I21: 200 | J21: 300 | K21: =J21+(J21*N21) -> 390 | L21: =+J21/I21-1 -> 0.5 | M21: =+AVERAGE(L21:L22) -> 0.74975 | N21: 0.3
C22: Handling Service | G22: DCS Custom | I22: 1500 | J22: 2999.25 | K22: =J22+(J22*N21) -> 3899.025 | L22: =+J22/I22-1 -> 0.9995
B23: Warehouse charges | C23: Warehouse charges | G23: DCS Custom | I23: 2005 | J23: 4009.66 | K23: =J23+(J23*N23) -> 5212.558 | L23: =+J23/I23-1 -> 0.99983042 | M23: =+L23 -> 0.99983042 | N23: 0.3
B24: Transport labour | C24: Security X-Ray | G24: DCS Custom | I24: 368 | J24: 735.81 | K24: =J24+(J24*N24) -> 956.553 | L24: =+J24/I24-1 -> 0.9994837 | M24: =+AVERAGE(L24:L28) -> 0.68569649 | N24: 0.3
C25: Customs clearance service | G25: DCS Custom | I25: 1170 | J25: 1580 | K25: =J25+(J25*N24) -> 2054 | L25: =+J25/I25-1 -> 0.35042735
C26: Declaration Service | G26: DCS Custom | I26: 10 | J26: 23 | K26: =J26+(J26*N24) -> 29.9 | L26: =+J26/I26-1 -> 1.3
C27: ATR Certificate | G27: DCS Custom | I27: 105 | J27: 150 | K27: =J27+(J27*N24) -> 195 | L27: =+J27/I27-1 -> 0.42857143
C28: Certification of the Certificate of Origin | G28: DCS Custom | I28: 200 | J28: 270 | K28: =J28+(J28*N24) -> 351 | L28: =+J28/I28-1 -> 0.35
B29: Membership Fee | C29: - | G29: - | I29: - | J29: 22358.03 | K29: =+J29*1.3 -> 29065.439 | M29: The fee was increased by %30.
B30: Penalty | C30: - | G30: - | I30: - | J30: 23139.85 | K30: =+J30*1.3 -> 30081.805
B31: Notary Expenses | C31: - | G31: - | I31: - | J31: 30530.46 | K31: =+J31*1.3 -> 39689.598
B32: Other | C32: - | G32: - | I32: - | J32: 28453.64 | K32: =+J32*1.3 -> 36989.732
B34: ▣ Import Expenses | T34: ▣ `25 Import Expenses monthly | AH34: ▣ `26 Import Expenses monthly (Esti.)
B37: 2025 | O37: Total | T37: 2025 | AG37: Total | AH37: 2026 | AT37: Total
B38: Description & Months | C38: 1 | D38: 2 | E38: 3 | F38: 4 | G38: 5 | H38: 6 | I38: 7 | J38: 8 | K38: 9 | L38: 10 | M38: 11 | N38: 12 | T38: Description & Months | U38: 1 | V38: 2 | W38: 3 | X38: 4 | Y38: 5 | Z38: 6 | AA38: 7 | AB38: 8 | AC38: 9 | AD38: 10 | AE38: 11 | AF38: 12 | AH38: 1 | AI38: 2 | AJ38: 3 | AK38: 4 | AL38: 5 | AM38: 6 | AN38: 7 | AO38: 8 | AP38: 9 | AQ38: 10 | AR38: 11 | AS38: 12
B39: Import Expenses | C39: =SUM(C40:C46) -> 20897.966 | D39: =SUM(D40:D46) -> 20897.966 | E39: =SUM(E40:E46) -> 20897.966 | F39: =SUM(F40:F46) -> 20897.966 | G39: =SUM(G40:G46) -> 20897.966 | H39: =SUM(H40:H46) -> 20897.966 | I39: =SUM(I40:I46) -> 20897.966 | J39: =SUM(J40:J46) -> 20897.966 | ... N39: =SUM(N40:N46) -> 41795.933 | O39: =+SUM(O40:O46) -> 334367.46 | T39: Import Expenses | U39: =SUM(U40:U46) -> 19518.44 | V39: =SUM(V40:V46) -> 0 | W39: =SUM(W40:W46) -> 8573.7 | X39: =SUM(X40:X46) -> 24017.54 | Y39: =SUM(Y40:Y46) -> 0 | Z39: =SUM(Z40:Z46) -> 0 | AA39: =SUM(AA40:AA46) -> 0 | AB39: =SUM(AB40:AB46) -> 40602.3 | ... AF39: =SUM(AF40:AF46) -> 28094.862 | AG39: =+SUM(AG40:AG46) -> 192904.3 | AH39: =SUM(AH40:AH46) -> 20897.966 | AI39: =SUM(AI40:AI46) -> 20897.966 | AJ39: =SUM(AJ40:AJ46) -> 20897.966 | AK39: =SUM(AK40:AK46) -> 20897.966 | AL39: =SUM(AL40:AL46) -> 20897.966 | AM39: =SUM(AM40:AM46) -> 20897.966 | AN39: =SUM(AN40:AN46) -> 20897.966 | AO39: =SUM(AO40:AO46) -> 20897.966 | ... AS39: =SUM(AS40:AS46) -> 41795.933 | AT39: =+SUM(AT40:AT46) -> 250775.6
B40: Shipping Expenses | C40: =AH40 -> 3260.9471 | D40: =AI40 -> 3260.9471 | E40: =AJ40 -> 3260.9471 | F40: =AK40 -> 3260.9471 | G40: =AL40 -> 3260.9471 | H40: =AM40 -> 3260.9471 | I40: =AN40 -> 3260.9471 | J40: =AO40 -> 3260.9471 | ... N40: =AS40 -> 6521.8942 | O40: =+SUM(C40:N40) -> 52175.153 | T40: Shipping Expenses | U40: 13800.75 | W40: 300 | X40: 300 | AB40: 300 | AC40: 6800 | AE40: =AVERAGE(U40:AD40) -> 4300.15 | AF40: =AE40 -> 4300.15 | AG40: =+SUM(U40:AF40) -> 30101.05 | AH40: =$AT40/12 -> 3260.9471 | AI40: =$AT40/12 -> 3260.9471 | AJ40: =$AT40/12 -> 3260.9471 | AK40: =$AT40/12 -> 3260.9471 | AL40: =$AT40/12 -> 3260.9471 | AM40: =$AT40/12 -> 3260.9471 | AN40: =$AT40/12 -> 3260.9471 | AO40: =$AT40/12 -> 3260.9471 | AP40: =$AT40/12*2 -> 6521.8942 | AQ40: =$AT40/12*2 -> 6521.8942 | AR40: =$AT40/12*2 -> 6521.8942 | AS40: =$AT40/12*2 -> 6521.8942 | AT40: =AG40*(1+$N$21) -> 39131.365
B41: Export Charges | C41: =AH41 -> 0 | D41: =AI41 -> 0 | E41: =AJ41 -> 0 | F41: =AK41 -> 0 | G41: =AL41 -> 0 | H41: =AM41 -> 0 | I41: =AN41 -> 0 | J41: =AO41 -> 0 | ... N41: =AS41 -> 0 | O41: =+SUM(C41:N41) -> 0 | T41: Export Charges | AE41: 0 | AF41: 0 | AG41: =+SUM(U41:AF41) -> 0 | AH41: =$AT41/12 -> 0 | AI41: =$AT41/12 -> 0 | AJ41: =$AT41/12 -> 0 | AK41: =$AT41/12 -> 0 | AL41: =$AT41/12 -> 0 | AM41: =$AT41/12 -> 0 | AN41: =$AT41/12 -> 0 | AO41: =$AT41/12 -> 0 | AP41: =$AT41/12*2 -> 0 | AQ41: =$AT41/12*2 -> 0 | AR41: =$AT41/12*2 -> 0 | AS41: =$AT41/12*2 -> 0 | AT41: =AG41*(1+$N$21) -> 0
B42: Warehouse Charges | C42: =AH42 -> 2443.8245 | D42: =AI42 -> 2443.8245 | E42: =AJ42 -> 2443.8245 | F42: =AK42 -> 2443.8245 | G42: =AL42 -> 2443.8245 | H42: =AM42 -> 2443.8245 | I42: =AN42 -> 2443.8245 | J42: =AO42 -> 2443.8245 | ... N42: =AS42 -> 4887.649 | O42: =+SUM(C42:N42) -> 39101.192 | T42: Warehouse Charges | U42: 1637.82 | W42: 2299.41 | X42: 7601.69 | AB42: 3500 | AE42: =AVERAGE(U42:AD42) -> 3759.73 | AF42: =AE42 -> 3759.73 | AG42: =+SUM(U42:AF42) -> 22558.38 | AH42: =$AT42/12 -> 2443.8245 | AI42: =$AT42/12 -> 2443.8245 | AJ42: =$AT42/12 -> 2443.8245 | AK42: =$AT42/12 -> 2443.8245 | AL42: =$AT42/12 -> 2443.8245 | AM42: =$AT42/12 -> 2443.8245 | AN42: =$AT42/12 -> 2443.8245 | AO42: =$AT42/12 -> 2443.8245 | AP42: =$AT42/12*2 -> 4887.649 | AQ42: =$AT42/12*2 -> 4887.649 | AR42: =$AT42/12*2 -> 4887.649 | AS42: =$AT42/12*2 -> 4887.649 | AT42: =AG42*(1+$N$21) -> 29325.894
B43: Transport labour | C43: =AH43 -> 3286.6121 | D43: =AI43 -> 3286.6121 | E43: =AJ43 -> 3286.6121 | F43: =AK43 -> 3286.6121 | G43: =AL43 -> 3286.6121 | H43: =AM43 -> 3286.6121 | I43: =AN43 -> 3286.6121 | J43: =AO43 -> 3286.6121 | ... N43: =AS43 -> 6573.2242 | O43: =+SUM(C43:N43) -> 52585.794 | T43: Transport labour | U43: 2558 | W43: 4263 | X43: 4263 | AB43: 7068.02 | AC43: 3517.95 | AE43: =AVERAGE(U43:AD43) -> 4333.994 | AF43: =AE43 -> 4333.994 | AG43: =+SUM(U43:AF43) -> 30337.958 | AH43: =$AT43/12 -> 3286.6121 | AI43: =$AT43/12 -> 3286.6121 | AJ43: =$AT43/12 -> 3286.6121 | AK43: =$AT43/12 -> 3286.6121 | AL43: =$AT43/12 -> 3286.6121 | AM43: =$AT43/12 -> 3286.6121 | AN43: =$AT43/12 -> 3286.6121 | AO43: =$AT43/12 -> 3286.6121 | AP43: =$AT43/12*2 -> 6573.2242 | AQ43: =$AT43/12*2 -> 6573.2242 | AR43: =$AT43/12*2 -> 6573.2242 | AS43: =$AT43/12*2 -> 6573.2242 | AT43: =AG43*(1+$N$21) -> 39439.345
B44: Other Export Expenses | C44: =AH44 -> 2469.1258 | D44: =AI44 -> 2469.1258 | E44: =AJ44 -> 2469.1258 | F44: =AK44 -> 2469.1258 | G44: =AL44 -> 2469.1258 | H44: =AM44 -> 2469.1258 | I44: =AN44 -> 2469.1258 | J44: =AO44 -> 2469.1258 | ... N44: =AS44 -> 4938.2515 | O44: =+SUM(C44:N44) -> 39506.012 | T44: Other Export Expenses | U44: 158.72 | W44: 0 | X44: 9059.23 | AB44: 5800 | AC44: 1262 | AE44: =AVERAGE(U44:AD44) -> 3255.99 | AF44: =AE44 -> 3255.99 | AG44: =+SUM(U44:AF44) -> 22791.93 | AH44: =$AT44/12 -> 2469.1258 | AI44: =$AT44/12 -> 2469.1258 | AJ44: =$AT44/12 -> 2469.1258 | AK44: =$AT44/12 -> 2469.1258 | AL44: =$AT44/12 -> 2469.1258 | AM44: =$AT44/12 -> 2469.1258 | AN44: =$AT44/12 -> 2469.1258 | AO44: =$AT44/12 -> 2469.1258 | AP44: =$AT44/12*2 -> 4938.2515 | AQ44: =$AT44/12*2 -> 4938.2515 | AR44: =$AT44/12*2 -> 4938.2515 | AS44: =$AT44/12*2 -> 4938.2515 | AT44: =AG44*(1+$N$21) -> 29629.509
B45: Custom Tax | C45: =AH45 -> 8320.6184 | D45: =AI45 -> 8320.6184 | E45: =AJ45 -> 8320.6184 | F45: =AK45 -> 8320.6184 | G45: =AL45 -> 8320.6184 | H45: =AM45 -> 8320.6184 | I45: =AN45 -> 8320.6184 | J45: =AO45 -> 8320.6184 | ... N45: =AS45 -> 16641.237 | O45: =+SUM(C45:N45) -> 133129.89 | T45: Custom Tax | U45: 201.67 | W45: 0 | X45: 1895.42 | AB45: 21239.68 | AC45: 31524.45 | AE45: =AVERAGE(U45:AD45) -> 10972.244 | AF45: =AE45 -> 10972.244 | AG45: =+SUM(U45:AF45) -> 76805.708 | AH45: =$AT45/12 -> 8320.6184 | AI45: =$AT45/12 -> 8320.6184 | AJ45: =$AT45/12 -> 8320.6184 | AK45: =$AT45/12 -> 8320.6184 | AL45: =$AT45/12 -> 8320.6184 | AM45: =$AT45/12 -> 8320.6184 | AN45: =$AT45/12 -> 8320.6184 | AO45: =$AT45/12 -> 8320.6184 | AP45: =$AT45/12*2 -> 16641.237 | AQ45: =$AT45/12*2 -> 16641.237 | AR45: =$AT45/12*2 -> 16641.237 | AS45: =$AT45/12*2 -> 16641.237 | AT45: =AG45*(1+$N$21) -> 99847.42
B46: Other Tax | C46: =AH46 -> 1116.8384 | D46: =AI46 -> 1116.8384 | E46: =AJ46 -> 1116.8384 | F46: =AK46 -> 1116.8384 | G46: =AL46 -> 1116.8384 | H46: =AM46 -> 1116.8384 | I46: =AN46 -> 1116.8384 | J46: =AO46 -> 1116.8384 | ... N46: =AS46 -> 2233.6769 | O46: =+SUM(C46:N46) -> 17869.415 | T46: Other Tax | U46: 1161.48 | W46: 1711.29 | X46: 898.2 | AB46: 2694.6 | AC46: 898.2 | AE46: =AVERAGE(U46:AD46) -> 1472.754 | AF46: =AE46 -> 1472.754 | AG46: =+SUM(U46:AF46) -> 10309.278 | AH46: =$AT46/12 -> 1116.8384 | AI46: =$AT46/12 -> 1116.8384 | AJ46: =$AT46/12 -> 1116.8384 | AK46: =$AT46/12 -> 1116.8384 | AL46: =$AT46/12 -> 1116.8384 | AM46: =$AT46/12 -> 1116.8384 | AN46: =$AT46/12 -> 1116.8384 | AO46: =$AT46/12 -> 1116.8384 | AP46: =$AT46/12*2 -> 2233.6769 | AQ46: =$AT46/12*2 -> 2233.6769 | AR46: =$AT46/12*2 -> 2233.6769 | AS46: =$AT46/12*2 -> 2233.6769 | AT46: =AG46*(1+$N$21) -> 13402.061
AE47: Esti. | AF47: Esti.

Sheet 9.Transportation
B1: ▣ `26 KCTR Transportation | R1: ▣ `25 KCTR Transportation
B4: Description & Months | C4: 1 | D4: 2 | E4: 3 | F4: 4 | G4: 5 | H4: 6 | I4: 7 | J4: 8 | K4: 9 | L4: 10 | M4: 11 | N4: 12 | O4: Total | P4: Remark | R4: Description & Months | S4: 1 | T4: 2 | U4: 3 | V4: 4 | W4: 5 | X4: 6 | Y4: 7 | Z4: 8 | AA4: 9 | AB4: 10 | AC4: 11 | AD4: 12 | AE4: Total
B5: Transportation | C5: =C19 -> 554836.15 | D5: =D19 -> 554836.15 | E5: =E19 -> 554836.15 | F5: =F19 -> 554836.15 | G5: =G19 -> 554836.15 | H5: =H19 -> 554836.15 | I5: =I19 -> 554836.15 | J5: =J19 -> 554836.15 | ... O5: =O19 -> 6658033.8 | R5: Transportation | S5: 486446 | T5: 547529 | U5: 593398 | V5: 599024 | W5: 518578 | X5: 410466 | Y5: 507709 | Z5: 408268 | AA5: 623860 | AB5: 562931 | AC5: =AVERAGE(S5:AB5) -> 525820.9 | AD5: =AC5 -> 525820.9 | AE5: =+SUM(S5:AD5) -> 6309850.8
B6: Maf 대비 운송료 | C6: - | D6: - | E6: - | F6: - | G6: - | H6: - | I6: - | J6: - | K6: - | L6: - | M6: - | N6: - | O6: =+SUM(C6:N6) -> 0 | R6: Maf 대비 운송료 | S6: 0.0064 | T6: 0.0085 | U6: 0.0066 | V6: 0.0093 | W6: 0.0056 | X6: 0.0042 | Y6: 0.0056 | Z6: 0.0046 | AA6: 0.0072 | AB6: 0.0081 | AC6: =AVERAGE(S6:AB6) -> 0.00661 | AD6: =AC6 -> 0.00661 | AE6: =AVERAGE(S6:AD6) -> 0.00661
B7: Truck Usage | R7: Truck Usage | S7: 51 | T7: 53 | U7: 58 | V7: 63 | W7: 55 | X7: 40 | Y7: 56 | Z7: 30 | AA7: 44 | AB7: 46 | AC7: =AVERAGE(S7:AB7) -> 49.6 | AD7: =AC7 -> 49.6 | AE7: =AVERAGE(S7:AD7) -> 49.6
B9: Ford-KCTR | C9: =$O$9/12 -> 49343.5 | D9: =$O$9/12 -> 49343.5 | E9: =$O$9/12 -> 49343.5 | F9: =$O$9/12 -> 49343.5 | G9: =$O$9/12 -> 49343.5 | H9: =$O$9/12 -> 49343.5 | I9: =$O$9/12 -> 49343.5 | J9: =$O$9/12 -> 49343.5 | ... N9: =$O$9/12 -> 49343.5 | O9: =AE9 -> 592122 | R9: Ford-KCTR | S9: 49343.5 | T9: 49343.5 | U9: 49343.5 | V9: 49343.5 | W9: 49343.5 | X9: 49343.5 | Y9: 49343.5 | Z9: 49343.5 | AA9: 49343.5 | AB9: 49343.5 | AC9: 49343.5 | AD9: 49343.5 | AE9: 592122
B11: KCTR | C11: =$O$11/12 -> 235761.72 | D11: =$O$11/12 -> 235761.72 | E11: =$O$11/12 -> 235761.72 | F11: =$O$11/12 -> 235761.72 | G11: =$O$11/12 -> 235761.72 | H11: =$O$11/12 -> 235761.72 | I11: =$O$11/12 -> 235761.72 | J11: =$O$11/12 -> 235761.72 | ... N11: =$O$11/12 -> 235761.72 | O11: =AE11*1.3 -> 2829140.6 | P11: 30% Increase | R11: KCTR | S11: 175972 | T11: 208519 | U11: 219588 | V11: 264944 | W11: 234378 | X11: 145406 | Y11: 270344 | Z11: 196568 | AA11: 233288 | AB11: 227256 | AC11: =AVERAGE(S11:AB11) -> 217626.3 | AD11: =AC11 -> 217626.3 | AE11: 2176262
B12: Takosan | R12: Takosan | S12: 16 | T12: 19 | U12: 20 | V12: 21 | W12: 18 | X12: 10 | Y12: 19 | Z12: 12 | AA12: 13 | AB12: 14 | AC12: =AVERAGE(S12:AB12) -> 16.2 | AD12: =AC12 -> 16.2 | AE12: 162
B13: KCTR | C13: =$O$13/12 -> 222995.5 | D13: =$O$13/12 -> 222995.5 | E13: =$O$13/12 -> 222995.5 | F13: =$O$13/12 -> 222995.5 | G13: =$O$13/12 -> 222995.5 | H13: =$O$13/12 -> 222995.5 | I13: =$O$13/12 -> 222995.5 | J13: =$O$13/12 -> 222995.5 | ... N13: =$O$13/12 -> 222995.5 | O13: =AE13*1.3 -> 2675946 | P13: 30% Increase | R13: KCTR | S13: 236640 | T13: 207640 | U13: 244180 | V13: 236640 | W13: 193140 | X13: 182700 | Y13: 135430 | Z13: 147030 | AA13: 247312 | AB13: 227708 | AC13: =AVERAGE(S13:AB13) -> 205842 | AD13: =AC13 -> 205842 | AE13: 2058420
B14: Nursan | R14: Nursan | S14: 13 | T14: 11 | U14: 12 | V14: 13 | W14: 10 | X14: 9 | Y14: 8 | Z14: 6 | AA14: 10 | AB14: 10 | AC14: =AVERAGE(S14:AB14) -> 10.2 | AD14: =AC14 -> 10.2 | AE14: 102
B15: KCTR | C15: =$O$15/12 -> 39192.292 | D15: =$O$15/12 -> 39192.292 | E15: =$O$15/12 -> 39192.292 | F15: =$O$15/12 -> 39192.292 | G15: =$O$15/12 -> 39192.292 | H15: =$O$15/12 -> 39192.292 | I15: =$O$15/12 -> 39192.292 | J15: =$O$15/12 -> 39192.292 | ... N15: =$O$15/12 -> 39192.292 | O15: =AE15*1.3 -> 470307.5 | P15: 30% Increase | R15: KCTR | S15: 11020 | T15: 66120 | U15: 65540 | V15: 31320 | W15: 26100 | X15: 15660 | Y15: 29580 | Z15: 40919 | AA15: 54636 | AB15: 20880 | AC15: =AVERAGE(S15:AB15) -> 36177.5 | AD15: =AC15 -> 36177.5 | AE15: 361775
B16: Balkan | R16: Balkan | S16: 1 | T16: 6 | U16: 7 | V16: 6 | W16: 5 | X16: 3 | Y16: 5 | Z16: 5 | AA16: 5 | AB16: 3 | AC16: =AVERAGE(S16:AB16) -> 4.6 | AD16: =AC16 -> 4.6 | AE16: 46
B17: Others | C17: =$O$17/12 -> 7543.1417 | D17: =$O$17/12 -> 7543.1417 | E17: =$O$17/12 -> 7543.1417 | F17: =$O$17/12 -> 7543.1417 | G17: =$O$17/12 -> 7543.1417 | H17: =$O$17/12 -> 7543.1417 | I17: =$O$17/12 -> 7543.1417 | J17: =$O$17/12 -> 7543.1417 | ... N17: =$O$17/12 -> 7543.1417 | O17: =AE17*1.3 -> 90517.7 | P17: 30% Increase | R17: Others | S17: 7540 | T17: 10440 | U17: 5220 | V17: 5220 | W17: - | X17: 9860 | Y17: 2320 | Z17: - | AA17: 5278 | AB17: 23751 | AC17: =AVERAGE(S17:AB17) -> 8703.625 | AD17: =AC17 -> 8703.625 | AE17: 69629
S18: 3 | T18: 2 | U18: 2 | V18: 2 | W18: 0 | X18: 2 | Y18: 1 | Z18: 0 | AA18: 1 | AB18: 6 | AC18: =AVERAGE(S18:AB18) -> 1.9 | AD18: =AC18 -> 1.9 | AE18: 19
B19: Total | C19: =SUM(C9,C11,C13,C15,C17) -> 554836.15 | D19: =SUM(D9,D11,D13,D15,D17) -> 554836.15 | E19: =SUM(E9,E11,E13,E15,E17) -> 554836.15 | F19: =SUM(F9,F11,F13,F15,F17) -> 554836.15 | G19: =SUM(G9,G11,G13,G15,G17) -> 554836.15 | H19: =SUM(H9,H11,H13,H15,H17) -> 554836.15 | I19: =SUM(I9,I11,I13,I15,I17) -> 554836.15 | J19: =SUM(J9,J11,J13,J15,J17) -> 554836.15 | ... O19: =SUM(O9,O11,O13,O15,O17) -> 6658033.8 | P19: - | R19: Total | S19: 486446 | T19: 547529 | U19: 593398 | V19: 599024 | W19: 518578 | X19: 410466 | Y19: 507709 | Z19: 408268 | AA19: 623860 | AB19: 562931 | AC19: =AVERAGE(S19:AB19) -> 525820.9 | AD19: =AC19 -> 525820.9 | AE19: 5258208
S20: 51 | T20: 53 | U20: 58 | V20: 63 | W20: 55 | X20: 40 | Y20: 56 | Z20: 30 | AA20: 44 | AB20: 46 | AC20: =AVERAGE(S20:AB20) -> 49.6 | AD20: =AC20 -> 49.6 | AE20: 496
AC21: Esti. | AD21: Esti.
B23: ▣ `26 KCTR Product Sample Expenses
B26: Description & Months | C26: 1 | D26: 2 | E26: 3 | F26: 4 | G26: 5 | H26: 6 | I26: 7 | J26: 8 | K26: 9 | L26: 10 | M26: 11 | N26: 12 | O26: Total | P26: Remark
B27: Product Sample Expenses | C27: =SUM(C28:C30) -> 41357.485 | D27: =SUM(D28:D30) -> 41357.485 | E27: =SUM(E28:E30) -> 41357.485 | F27: =SUM(F28:F30) -> 41357.485 | G27: =SUM(G28:G30) -> 41357.485 | H27: =SUM(H28:H30) -> 41357.485 | I27: =SUM(I28:I30) -> 41357.485 | J27: =SUM(J28:J30) -> 41357.485 | ... N27: =SUM(N28:N30) -> 41357.485 | O27: =SUM(C27:N27) -> 496289.82 | P27: -
B28: Domestic Sample Expenses | C28: 6790.5596 | D28: 6790.5596 | E28: 6790.5596 | F28: 6790.5596 | G28: 6790.5596 | H28: 6790.5596 | I28: 6790.5596 | J28: 6790.5596 | K28: 6790.5596 | L28: 6790.5596 | M28: 6790.5596 | N28: 6790.5596 | O28: =SUM(C28:N28) -> 81486.715 | P28: `25 : 60,361 TL
B29: Export Sample Expenses | C29: 3457.4614 | D29: 3457.4614 | E29: 3457.4614 | F29: 3457.4614 | G29: 3457.4614 | H29: 3457.4614 | I29: 3457.4614 | J29: 3457.4614 | K29: 3457.4614 | L29: 3457.4614 | M29: 3457.4614 | N29: 3457.4614 | O29: =SUM(C29:N29) -> 41489.536 | P29: `25 : 30,732 TL
B30: Other Sample Expenses | C30: 31109.464 | D30: 31109.464 | E30: 31109.464 | F30: 31109.464 | G30: 31109.464 | H30: 31109.464 | I30: 31109.464 | J30: 31109.464 | K30: 31109.464 | L30: 31109.464 | M30: 31109.464 | N30: 31109.464 | O30: =SUM(C30:N30) -> 373313.57 | P30: `25 : 276,528 TL

Sheet 10. Warehouse
B1: ▣ KCTR Warehouse payment
B3: 2025 | D3: Dnit | E3: Jan | F3: Feb | G3: Mar | H3: Apr | I3: May | J3: Jun | K3: Jul | L3: Aug | M3: Sep | N3: Oct | O3: Nov | P3: Dec | Q3: Yearly Avarage | R3: Remark | U3: 1. 현 KCTR 창고 임대차 계약서
B4: 사무실 렌트비 (Warehouse Rent) | D4: USD | E4: 11500 | F4: 11500 | G4: 11500 | H4: 11500 | I4: 11500 | J4: 11500 | K4: 11500 | L4: 11500 | M4: 11500 | N4: 11500 | O4: 11500 | P4: 11500 | Q4: =SUM(E4:P4) -> 138000
D5: TL | E5: =E4*43 -> 494500 | F5: =F4*43 -> 494500 | G5: =G4*43 -> 494500 | H5: =H4*43 -> 494500 | I5: =I4*43 -> 494500 | J5: =J4*43 -> 494500 | K5: =K4*43 -> 494500 | L5: =L4*43 -> 494500 | ... P5: =P4*43 -> 494500 | Q5: =SUM(E5:P5) -> 5934000
B6: 관리비 Warehouse Electricity expenses | D6: TL | E6: =11758*1.3 -> 15285.4 | F6: =11758*1.3 -> 15285.4 | G6: =11758*1.3 -> 15285.4 | H6: =11758*1.3 -> 15285.4 | I6: =11758*1.3 -> 15285.4 | J6: =11758*1.3 -> 15285.4 | K6: =11758*1.3 -> 15285.4 | L6: =11758*1.3 -> 15285.4 | ... P6: =11758*1.3 -> 15285.4 | Q6: =SUM(E6:P6) -> 183424.8 | R6: 25 : 11,758 TL (new warehouse)
B7: 관리비 Warehouse Water expenses | D7: TL | E7: =5879*1.3 -> 7642.7 | F7: =5879*1.3 -> 7642.7 | G7: =5879*1.3 -> 7642.7 | H7: =5879*1.3 -> 7642.7 | I7: =5879*1.3 -> 7642.7 | J7: =5879*1.3 -> 7642.7 | K7: =5879*1.3 -> 7642.7 | L7: =5879*1.3 -> 7642.7 | ... P7: =5879*1.3 -> 7642.7 | Q7: =SUM(E7:P7) -> 91712.4 | R7: 25 : 5,879 TL
B9: ▣ `25 CHEP Box rental and issue payment for BEV-M
E12: Jan | F12: Feb | G12: Mar | H12: Apr | I12: May | J12: Jun | K12: Jul | L12: Aug | M12: Sep | N12: Oct | O12: Nov | P12: Dec | Q12: Annual Total | R12: Remark
B13: CHEP Issue Fee | D13: € | E13: 1225.0973 | F13: 1392.156 | G13: 1605.6199 | H13: 993.07128 | I13: 1382.875 | J13: 1726.2734 | K13: 1058.0386 | L13: 1466.4043 | M13: 1559.2147 | N13: 1559.2147 | O13: 1392.156 | P13: 1392.156 | Q13: =SUM(E13:P13) -> 16752.277
D14: TL | E14: =E13*'Exchange Rate'!$D$14 -> 62479.961 | F14: =F13*'Exchange Rate'!$D$14 -> 70999.956 | G14: =G13*'Exchange Rate'!$D$14 -> 81886.616 | H14: =H13*'Exchange Rate'!$D$14 -> 50646.635 | I14: =I13*'Exchange Rate'!$D$14 -> 70526.623 | J14: =J13*'Exchange Rate'!$D$14 -> 88039.945 | K14: =K13*'Exchange Rate'!$D$14 -> 53959.967 | L14: =L13*'Exchange Rate'!$D$14 -> 74786.62 | ... P14: =P13*'Exchange Rate'!$D$14 -> 70999.956 | Q14: =SUM(E14:P14) -> 854366.14
B15: CHEP Rent Fee | D15: € | E15: 382.6944 | F15: 434.88 | G15: 501.5616 | H15: 310.2144 | I15: 431.9808 | J15: 539.2512 | K15: 330.5088 | L15: 458.0736 | M15: 487.0656 | N15: 487.0656 | O15: 434.88 | P15: 434.88 | Q15: =SUM(E15:P15) -> 5233.056
D16: TL | E16: =E15*'Exchange Rate'!$D$14 -> 19517.414 | F16: =F15*'Exchange Rate'!$D$14 -> 22178.88 | G16: =G15*'Exchange Rate'!$D$14 -> 25579.642 | H16: =H15*'Exchange Rate'!$D$14 -> 15820.934 | I16: =I15*'Exchange Rate'!$D$14 -> 22031.021 | J16: =J15*'Exchange Rate'!$D$14 -> 27501.811 | K16: =K15*'Exchange Rate'!$D$14 -> 16855.949 | L16: =L15*'Exchange Rate'!$D$14 -> 23361.754 | ... P16: =P15*'Exchange Rate'!$D$14 -> 22178.88 | Q16: =SUM(E16:P16) -> 266885.86
B17: P703 Packaging Materials | D17: TL | E17: =$Q$27/12 -> 110088.28 | F17: =$Q$27/12 -> 110088.28 | G17: =$Q$27/12 -> 110088.28 | H17: =$Q$27/12 -> 110088.28 | I17: =$Q$27/12 -> 110088.28 | J17: =$Q$27/12 -> 110088.28 | K17: =$Q$27/12 -> 110088.28 | L17: =$Q$27/12 -> 110088.28 | ... P17: =$Q$27/12 -> 110088.28 | Q17: =SUM(E17:P17) -> 1321059.4
B19: ▣ `26 CHEP Box rental and issue payment for BEV-M
E22: Jan | F22: Feb | G22: Mar | H22: Apr | I22: May | J22: Jun | K22: Jul | L22: Aug | M22: Sep | N22: Oct | O22: Nov | P22: Dec | Q22: Annual Total | R22: Remark
B23: CHEP Issue Fee | D23: € | E23: =E13*1.3 -> 1592.6265 | F23: =F13*1.3 -> 1809.8028 | G23: =G13*1.3 -> 2087.3059 | H23: =H13*1.3 -> 1290.9927 | I23: =I13*1.3 -> 1797.7374 | J23: =J13*1.3 -> 2244.1555 | K23: =K13*1.3 -> 1375.4501 | L23: =L13*1.3 -> 1906.3256 | ... P23: =P13*1.3 -> 1809.8028 | Q23: =SUM(E23:P23) -> 21777.96 | R23: 25년 대비 30% 상승
D24: TL | E24: =E14*1.3 -> 81223.95 | F24: =F14*1.3 -> 92299.943 | G24: =G14*1.3 -> 106452.6 | H24: =H14*1.3 -> 65840.626 | I24: =I14*1.3 -> 91684.61 | J24: =J14*1.3 -> 114451.93 | K24: =K14*1.3 -> 70147.957 | L24: =L14*1.3 -> 97222.606 | ... P24: =P14*1.3 -> 92299.943 | Q24: =SUM(E24:P24) -> 1110676
B25: CHEP Rent Fee | D25: € | E25: =E15*1.3 -> 497.50272 | F25: =F15*1.3 -> 565.344 | G25: =G15*1.3 -> 652.03008 | H25: =H15*1.3 -> 403.27872 | I25: =I15*1.3 -> 561.57504 | J25: =J15*1.3 -> 701.02656 | K25: =K15*1.3 -> 429.66144 | L25: =L15*1.3 -> 595.49568 | ... P25: =P15*1.3 -> 565.344 | Q25: =SUM(E25:P25) -> 6802.9728 | R25: 25년 대비 30% 상승
D26: TL | E26: =E16*1.3 -> 25372.639 | F26: =F16*1.3 -> 28832.544 | G26: =G16*1.3 -> 33253.534 | H26: =H16*1.3 -> 20567.215 | I26: =I16*1.3 -> 28640.327 | J26: =J16*1.3 -> 35752.355 | K26: =K16*1.3 -> 21912.733 | L26: =L16*1.3 -> 30370.28 | ... P26: =P16*1.3 -> 28832.544 | Q26: =SUM(E26:P26) -> 346951.61
B27: P703 Packaging Materials | D27: TL | E27: =$Q$27/12 -> 110088.28 | F27: =$Q$27/12 -> 110088.28 | G27: =$Q$27/12 -> 110088.28 | H27: =$Q$27/12 -> 110088.28 | I27: =$Q$27/12 -> 110088.28 | J27: =$Q$27/12 -> 110088.28 | K27: =$Q$27/12 -> 110088.28 | L27: =$Q$27/12 -> 110088.28 | ... P27: =$Q$27/12 -> 110088.28 | Q27: =G42 -> 1321059.4 | R27: 25년 대비 30% 상승
B29: ▣ `26년 PHEV-E (P703) Packaging Materials list
B30: S/N | C30: ZER Code | D30: MATERIAL | E30: Quantity | F30: Amount | G30: Total Amount
B31: 1 | C31: 770835 | D31: IMC090-HC | E31: 250 | F31: 81.32 | G31: =(E31*F31)*1.3 -> 26429
B32: 2 | C32: 742740 | D32: IMC090 VCI | E32: 250 | F32: 28.68 | G32: =(E32*F32)*1.3 -> 9321
B33: 3 | C33: 742499 | D33: IMC100 | E33: 1150 | F33: 102.18 | G33: =(E33*F33)*1.3 -> 152759.1
B34: 4 | C34: 742741 | D34: IMC100 VCI | E34: 1150 | F34: 34.41 | G34: =(E34*F34)*1.3 -> 51442.95
B35: 5 | C35: 770838 | D35: IMC120HC | E35: 2000 | F35: 132.75 | G35: =(E35*F35)*1.3 -> 345150
B36: 6 | C36: 742743 | D36: IMC120 VCI | E36: 2000 | F36: 51.62 | G36: =(E36*F36)*1.3 -> 134212
B37: 7 | C37: 1836587 | D37: Bubble Layer | E37: 10000 | F37: 34.98 | G37: =(E37*F37)*1.3 -> 454740
B38: 8 | C38: 771350 | D38: 50*50*5,0*130 | E38: 8800 | F38: 1.22 | G38: =(E38*F38)*1.3 -> 13956.8
B39: 9 | C39: 742640 | D39: 50*50*5,0*225 | E39: 5000 | F39: 2.1 | G39: =(E39*F39)*1.3 -> 13650
B40: 10 | C40: 742647 | D40: 50*50*5,0*920 | E40: 700 | F40: 8.61 | G40: =(E40*F40)*1.3 -> 7835.1
B41: 11 | C41: 742630 | D41: 114x98 | E41: 200 | F41: 429.09 | G41: =(E41*F41)*1.3 -> 111563.4
D42: Total | E42: =SUM(E31:E41) -> 31500 | F42: =SUM(F31:F41) -> 906.96 | G42: =SUM(G31:G41) -> 1321059.4

Sheet 11. Trip
B1: ▣ Domestic and Oversea Trip
B5: Travel Expenses | D5: Jan | E5: Feb | F5: Mar | G5: Apr | H5: May | I5: Jun | J5: Jul | K5: Aug | L5: Sep | M5: Oct | N5: Nov | O5: Dec | P5: Yearly TOTAL | Q5: Remark | R5: Remark | T5: 터키 | U5: KRW/TRY | V5: 32
B6: Travel Expenses (Total | D6: =SUM(D7:D12) -> 295110.83 | E6: =SUM(E7:E12) -> 295110.83 | F6: =SUM(F7:F12) -> 295110.83 | G6: =SUM(G7:G12) -> 295110.83 | H6: =SUM(H7:H12) -> 295110.83 | I6: =SUM(I7:I12) -> 295110.83 | J6: =SUM(J7:J12) -> 295110.83 | K6: =SUM(K7:K12) -> 295110.83 | ... P6: =SUM(P7:P12) -> 5530080 | U6: TRY/USD | V6: 43
B7: Domestic | C7: Travel Expenses | P7: =SUM(D7:O7) -> 0 | Q7: General | U7: TRY/EUR | V7: 51
C8: General | D8: =SUM($I$17,$I$20,$I$23,$I$26,$I$29,$I$32,$I$35) -> 20300 | E8: =SUM($I$17,$I$20,$I$23,$I$26,$I$29,$I$32,$I$35) -> 20300 | F8: =SUM($I$17,$I$20,$I$23,$I$26,$I$29,$I$32,$I$35) -> 20300 | G8: =SUM($I$17,$I$20,$I$23,$I$26,$I$29,$I$32,$I$35) -> 20300 | H8: =SUM($I$17,$I$20,$I$23,$I$26,$I$29,$I$32,$I$35) -> 20300 | I8: =SUM($I$17,$I$20,$I$23,$I$26,$I$29,$I$32,$I$35) -> 20300 | J8: =SUM($I$17,$I$20,$I$23,$I$26,$I$29,$I$32,$I$35) -> 20300 | K8: =SUM($I$17,$I$20,$I$23,$I$26,$I$29,$I$32,$I$35) -> 20300 | ... O8: =SUM($I$17,$I$20,$I$23,$I$26,$I$29,$I$32,$I$35) -> 20300 | P8: =SUM(D8:O8) -> 243600 | Q8: Meal | R8: 국내출장시 식대 700TL , `25년 월평균 13,400TL
C9: Room Charge | D9: =SUM($I$18,$I$21,$I$24,$I$27,$I$30,$I$33,$I$36) -> 43700 | E9: =SUM($I$18,$I$21,$I$24,$I$27,$I$30,$I$33,$I$36) -> 43700 | F9: =SUM($I$18,$I$21,$I$24,$I$27,$I$30,$I$33,$I$36) -> 43700 | G9: =SUM($I$18,$I$21,$I$24,$I$27,$I$30,$I$33,$I$36) -> 43700 | H9: =SUM($I$18,$I$21,$I$24,$I$27,$I$30,$I$33,$I$36) -> 43700 | I9: =SUM($I$18,$I$21,$I$24,$I$27,$I$30,$I$33,$I$36) -> 43700 | J9: =SUM($I$18,$I$21,$I$24,$I$27,$I$30,$I$33,$I$36) -> 43700 | K9: =SUM($I$18,$I$21,$I$24,$I$27,$I$30,$I$33,$I$36) -> 43700 | ... O9: =SUM($I$18,$I$21,$I$24,$I$27,$I$30,$I$33,$I$36) -> 43700 | P9: =SUM(D9:O9) -> 524400 | Q9: Accomodation | R9: 국내출장시 숙소 3,800TL (QC/P,3회/월),그외 (1회/2달), `25년 월평균 33,000TL
