Workbook

Sheet 변경사항
A1: REV. | B1: Date | C1: Update | D1: Note | E1: change | G1: change | I1: change | K1: Basic price
A2: R1 | B2: 45983 | C2: Sales price change from KSCP on APR(CR) | D2: EV2020 | E2: 16.92 | F2: usd | G2: =E2*RSDUSD25 -> 1692 | H2: rsd | I2: =G2*KRWRSD25 -> 23688 | J2: krw | K2: 17.44
C3: Sales price change from KSCP on JUN(AS price) | D3: PSA SDN | E3: 144.4 | F3: usd | G3: =E3*RSDUSD25 -> 14440 | H3: rsd | I3: =G3*KRWRSD25 -> 202160 | J3: krw | K3: 98.23
C4: exchange rate for 2026 | D4: PL/MC in KRW
C5: labor change 10% | D5: All
A6: R2 | B6: 45986 | C6: Decrease direct worker | D6: 11 People
C7: Decrease Korean | D7: 2 people from Apr
A8: R3 | B8: 45987 | C8: EV-V4 volume change and decrease direct wokers | D8: EV-V4
A9: R4 | B9: 46013 | C9: LG 2026Y price apply
A10: Final | B10: 46035 | C10: EV-V4 Price Update | D10: EV-V4

Sheet Work Calendar
H2: CY2026 | J2: Jan | L2: Feb | N2: Mar | P2: Apr | R2: May | T2: Jun | V2: Jul | X2: Aug | Z2: Sep | AB2: Oct | AD2: Nov | AF2: Dec
C3: Calendar Days | H3: =SUM(J3:AG3) -> 365 | J3: 31 | L3: 28 | N3: 31 | P3: 30 | R3: 31 | T3: 30 | V3: 31 | X3: 31 | Z3: 30 | AB3: 31 | AD3: 30 | AF3: 31
C4: Working days | H4: =SUM(J4:AG4) -> 240 | J4: 17 | L4: 18 | N4: 22 | P4: 20 | R4: 20 | T4: 22 | V4: 18 | X4: 16 | Z4: 22 | AB4: 22 | AD4: 20 | AF4: 23
C5: Non-working days | H5: =SUM(J5:AG5) -> 125 | J5: 14 | L5: 10 | N5: 9 | P5: 10 | R5: 11 | T5: 8 | V5: 13 | X5: 15 | Z5: 8 | AB5: 9 | AD5: 10 | AF5: 8
C7: WORK Calendar of KSCE | AD7: 2026
C9: January | K9: February | S9: March | AA9: April
C10: Su | D10: Mo | E10: Tu | F10: We | G10: Th | H10: Fr | I10: Sa | K10: Su | L10: Mo | M10: Tu | N10: We | O10: Th | P10: Fr | Q10: Sa | S10: Su | T10: Mo | U10: Tu | V10: We | W10: Th | X10: Fr | Y10: Sa | AA10: Su | AB10: Mo | AC10: Tu | AD10: We | AE10: Th | AF10: Fr | AG10: Sa
B11: CW1 | C11: =IF(DAY(JanSun1)=1,"",IF(AND(YEAR(JanSun1+1)=CalendarYear,MONTH(JanSun1+1)=1),JanSun1+1,"")) | D11: =IF(DAY(JanSun1)=1,"",IF(AND(YEAR(JanSun1+2)=CalendarYear,MONTH(JanSun1+2)=1),JanSun1+2,"")) | E11: =IF(DAY(JanSun1)=1,"",IF(AND(YEAR(JanSun1+3)=CalendarYear,MONTH(JanSun1+3)=1),JanSun1+3,"")) | F11: =IF(DAY(JanSun1)=1,"",IF(AND(YEAR(JanSun1+4)=CalendarYear,MONTH(JanSun1+4)=1),JanSun1+4,"")) | G11: =IF(DAY(JanSun1)=1,"",IF(AND(YEAR(JanSun1+5)=CalendarYear,MONTH(JanSun1+5)=1),JanSun1+5,"")) -> 46023 | H11: =IF(DAY(JanSun1)=1,"",IF(AND(YEAR(JanSun1+6)=CalendarYear,MONTH(JanSun1+6)=1),JanSun1+6,"")) -> 46024 | I11: =IF(DAY(JanSun1)=1,IF(AND(YEAR(JanSun1)=CalendarYear,MONTH(JanSun1)=1),JanSun1,""),IF(AND(YEAR(JanSun1+7)=CalendarYear,MONTH(JanSun1+7)=1),JanSun1+7,"")) -> 46025 | J11: CW5 | K11: =IF(DAY(FebSun1)=1,"",IF(AND(YEAR(FebSun1+1)=CalendarYear,MONTH(FebSun1+1)=2),FebSun1+1,"")) -> 46054 | L11: =IF(DAY(FebSun1)=1,"",IF(AND(YEAR(FebSun1+2)=CalendarYear,MONTH(FebSun1+2)=2),FebSun1+2,"")) -> 46055 | M11: =IF(DAY(FebSun1)=1,"",IF(AND(YEAR(FebSun1+3)=CalendarYear,MONTH(FebSun1+3)=2),FebSun1+3,"")) -> 46056 | N11: =IF(DAY(FebSun1)=1,"",IF(AND(YEAR(FebSun1+4)=CalendarYear,MONTH(FebSun1+4)=2),FebSun1+4,"")) -> 46057 | O11: =IF(DAY(FebSun1)=1,"",IF(AND(YEAR(FebSun1+5)=CalendarYear,MONTH(FebSun1+5)=2),FebSun1+5,"")) -> 46058 | P11: =IF(DAY(FebSun1)=1,"",IF(AND(YEAR(FebSun1+6)=CalendarYear,MONTH(FebSun1+6)=2),FebSun1+6,"")) -> 46059 | Q11: =IF(DAY(FebSun1)=1,IF(AND(YEAR(FebSun1)=CalendarYear,MONTH(FebSun1)=2),FebSun1,""),IF(AND(YEAR(FebSun1+7)=CalendarYear,MONTH(FebSun1+7)=2),FebSun1+7,"")) -> 46060 | R11: CW9 | S11: =IF(DAY(MarSun1)=1,"",IF(AND(YEAR(MarSun1+1)=CalendarYear,MONTH(MarSun1+1)=3),MarSun1+1,"")) -> 46082 | T11: =IF(DAY(MarSun1)=1,"",IF(AND(YEAR(MarSun1+2)=CalendarYear,MONTH(MarSun1+2)=3),MarSun1+2,"")) -> 46083 | U11: =IF(DAY(MarSun1)=1,"",IF(AND(YEAR(MarSun1+3)=CalendarYear,MONTH(MarSun1+3)=3),MarSun1+3,"")) -> 46084 | V11: =IF(DAY(MarSun1)=1,"",IF(AND(YEAR(MarSun1+4)=CalendarYear,MONTH(MarSun1+4)=3),MarSun1+4,"")) -> 46085 | W11: =IF(DAY(MarSun1)=1,"",IF(AND(YEAR(MarSun1+5)=CalendarYear,MONTH(MarSun1+5)=3),MarSun1+5,"")) -> 46086 | X11: =IF(DAY(MarSun1)=1,"",IF(AND(YEAR(MarSun1+6)=CalendarYear,MONTH(MarSun1+6)=3),MarSun1+6,"")) -> 46087 | Y11: =IF(DAY(MarSun1)=1,IF(AND(YEAR(MarSun1)=CalendarYear,MONTH(MarSun1)=3),MarSun1,""),IF(AND(YEAR(MarSun1+7)=CalendarYear,MONTH(MarSun1+7)=3),MarSun1+7,"")) -> 46088 | Z11: CW14 | AA11: =IF(DAY(AprSun1)=1,"",IF(AND(YEAR(AprSun1+1)=CalendarYear,MONTH(AprSun1+1)=4),AprSun1+1,"")) | AB11: =IF(DAY(AprSun1)=1,"",IF(AND(YEAR(AprSun1+2)=CalendarYear,MONTH(AprSun1+2)=4),AprSun1+2,"")) | AC11: =IF(DAY(AprSun1)=1,"",IF(AND(YEAR(AprSun1+3)=CalendarYear,MONTH(AprSun1+3)=4),AprSun1+3,"")) | AD11: =IF(DAY(AprSun1)=1,"",IF(AND(YEAR(AprSun1+4)=CalendarYear,MONTH(AprSun1+4)=4),AprSun1+4,"")) -> 46113 | AE11: =IF(DAY(AprSun1)=1,"",IF(AND(YEAR(AprSun1+5)=CalendarYear,MONTH(AprSun1+5)=4),AprSun1+5,"")) -> 46114 | AF11: =IF(DAY(AprSun1)=1,"",IF(AND(YEAR(AprSun1+6)=CalendarYear,MONTH(AprSun1+6)=4),AprSun1+6,"")) -> 46115 | AG11: =IF(DAY(AprSun1)=1,IF(AND(YEAR(AprSun1)=CalendarYear,MONTH(AprSun1)=4),AprSun1,""),IF(AND(YEAR(AprSun1+7)=CalendarYear,MONTH(AprSun1+7)=4),AprSun1+7,"")) -> 46116
B12: CW2 | C12: =IF(DAY(JanSun1)=1,IF(AND(YEAR(JanSun1+1)=CalendarYear,MONTH(JanSun1+1)=1),JanSun1+1,""),IF(AND(YEAR(JanSun1+8)=CalendarYear,MONTH(JanSun1+8)=1),JanSun1+8,"")) -> 46026 | D12: =IF(DAY(JanSun1)=1,IF(AND(YEAR(JanSun1+2)=CalendarYear,MONTH(JanSun1+2)=1),JanSun1+2,""),IF(AND(YEAR(JanSun1+9)=CalendarYear,MONTH(JanSun1+9)=1),JanSun1+9,"")) -> 46027 | E12: =IF(DAY(JanSun1)=1,IF(AND(YEAR(JanSun1+3)=CalendarYear,MONTH(JanSun1+3)=1),JanSun1+3,""),IF(AND(YEAR(JanSun1+10)=CalendarYear,MONTH(JanSun1+10)=1),JanSun1+10,"")) -> 46028 | F12: =IF(DAY(JanSun1)=1,IF(AND(YEAR(JanSun1+4)=CalendarYear,MONTH(JanSun1+4)=1),JanSun1+4,""),IF(AND(YEAR(JanSun1+11)=CalendarYear,MONTH(JanSun1+11)=1),JanSun1+11,"")) -> 46029 | G12: =IF(DAY(JanSun1)=1,IF(AND(YEAR(JanSun1+5)=CalendarYear,MONTH(JanSun1+5)=1),JanSun1+5,""),IF(AND(YEAR(JanSun1+12)=CalendarYear,MONTH(JanSun1+12)=1),JanSun1+12,"")) -> 46030 | H12: =IF(DAY(JanSun1)=1,IF(AND(YEAR(JanSun1+6)=CalendarYear,MONTH(JanSun1+6)=1),JanSun1+6,""),IF(AND(YEAR(JanSun1+13)=CalendarYear,MONTH(JanSun1+13)=1),JanSun1+13,"")) -> 46031 | I12: =IF(DAY(JanSun1)=1,IF(AND(YEAR(JanSun1+7)=CalendarYear,MONTH(JanSun1+7)=1),JanSun1+7,""),IF(AND(YEAR(JanSun1+14)=CalendarYear,MONTH(JanSun1+14)=1),JanSun1+14,"")) -> 46032 | J12: CW6 | K12: =IF(DAY(FebSun1)=1,IF(AND(YEAR(FebSun1+1)=CalendarYear,MONTH(FebSun1+1)=2),FebSun1+1,""),IF(AND(YEAR(FebSun1+8)=CalendarYear,MONTH(FebSun1+8)=2),FebSun1+8,"")) -> 46061 | L12: =IF(DAY(FebSun1)=1,IF(AND(YEAR(FebSun1+2)=CalendarYear,MONTH(FebSun1+2)=2),FebSun1+2,""),IF(AND(YEAR(FebSun1+9)=CalendarYear,MONTH(FebSun1+9)=2),FebSun1+9,"")) -> 46062 | M12: =IF(DAY(FebSun1)=1,IF(AND(YEAR(FebSun1+3)=CalendarYear,MONTH(FebSun1+3)=2),FebSun1+3,""),IF(AND(YEAR(FebSun1+10)=CalendarYear,MONTH(FebSun1+10)=2),FebSun1+10,"")) -> 46063 | N12: =IF(DAY(FebSun1)=1,IF(AND(YEAR(FebSun1+4)=CalendarYear,MONTH(FebSun1+4)=2),FebSun1+4,""),IF(AND(YEAR(FebSun1+11)=CalendarYear,MONTH(FebSun1+11)=2),FebSun1+11,"")) -> 46064 | O12: =IF(DAY(FebSun1)=1,IF(AND(YEAR(FebSun1+5)=CalendarYear,MONTH(FebSun1+5)=2),FebSun1+5,""),IF(AND(YEAR(FebSun1+12)=CalendarYear,MONTH(FebSun1+12)=2),FebSun1+12,"")) -> 46065 | P12: =IF(DAY(FebSun1)=1,IF(AND(YEAR(FebSun1+6)=CalendarYear,MONTH(FebSun1+6)=2),FebSun1+6,""),IF(AND(YEAR(FebSun1+13)=CalendarYear,MONTH(FebSun1+13)=2),FebSun1+13,"")) -> 46066 | Q12: =IF(DAY(FebSun1)=1,IF(AND(YEAR(FebSun1+7)=CalendarYear,MONTH(FebSun1+7)=2),FebSun1+7,""),IF(AND(YEAR(FebSun1+14)=CalendarYear,MONTH(FebSun1+14)=2),FebSun1+14,"")) -> 46067 | R12: CW10 | S12: =IF(DAY(MarSun1)=1,IF(AND(YEAR(MarSun1+1)=CalendarYear,MONTH(MarSun1+1)=3),MarSun1+1,""),IF(AND(YEAR(MarSun1+8)=CalendarYear,MONTH(MarSun1+8)=3),MarSun1+8,"")) -> 46089 | T12: =IF(DAY(MarSun1)=1,IF(AND(YEAR(MarSun1+2)=CalendarYear,MONTH(MarSun1+2)=3),MarSun1+2,""),IF(AND(YEAR(MarSun1+9)=CalendarYear,MONTH(MarSun1+9)=3),MarSun1+9,"")) -> 46090 | U12: =IF(DAY(MarSun1)=1,IF(AND(YEAR(MarSun1+3)=CalendarYear,MONTH(MarSun1+3)=3),MarSun1+3,""),IF(AND(YEAR(MarSun1+10)=CalendarYear,MONTH(MarSun1+10)=3),MarSun1+10,"")) -> 46091 | V12: =IF(DAY(MarSun1)=1,IF(AND(YEAR(MarSun1+4)=CalendarYear,MONTH(MarSun1+4)=3),MarSun1+4,""),IF(AND(YEAR(MarSun1+11)=CalendarYear,MONTH(MarSun1+11)=3),MarSun1+11,"")) -> 46092 | W12: =IF(DAY(MarSun1)=1,IF(AND(YEAR(MarSun1+5)=CalendarYear,MONTH(MarSun1+5)=3),MarSun1+5,""),IF(AND(YEAR(MarSun1+12)=CalendarYear,MONTH(MarSun1+12)=3),MarSun1+12,"")) -> 46093 | X12: =IF(DAY(MarSun1)=1,IF(AND(YEAR(MarSun1+6)=CalendarYear,MONTH(MarSun1+6)=3),MarSun1+6,""),IF(AND(YEAR(MarSun1+13)=CalendarYear,MONTH(MarSun1+13)=3),MarSun1+13,"")) -> 46094 | Y12: =IF(DAY(MarSun1)=1,IF(AND(YEAR(MarSun1+7)=CalendarYear,MONTH(MarSun1+7)=3),MarSun1+7,""),IF(AND(YEAR(MarSun1+14)=CalendarYear,MONTH(MarSun1+14)=3),MarSun1+14,"")) -> 46095 | Z12: CW15 | AA12: =IF(DAY(AprSun1)=1,IF(AND(YEAR(AprSun1+1)=CalendarYear,MONTH(AprSun1+1)=4),AprSun1+1,""),IF(AND(YEAR(AprSun1+8)=CalendarYear,MONTH(AprSun1+8)=4),AprSun1+8,"")) -> 46117 | AB12: =IF(DAY(AprSun1)=1,IF(AND(YEAR(AprSun1+2)=CalendarYear,MONTH(AprSun1+2)=4),AprSun1+2,""),IF(AND(YEAR(AprSun1+9)=CalendarYear,MONTH(AprSun1+9)=4),AprSun1+9,"")) -> 46118 | AC12: =IF(DAY(AprSun1)=1,IF(AND(YEAR(AprSun1+3)=CalendarYear,MONTH(AprSun1+3)=4),AprSun1+3,""),IF(AND(YEAR(AprSun1+10)=CalendarYear,MONTH(AprSun1+10)=4),AprSun1+10,"")) -> 46119 | AD12: =IF(DAY(AprSun1)=1,IF(AND(YEAR(AprSun1+4)=CalendarYear,MONTH(AprSun1+4)=4),AprSun1+4,""),IF(AND(YEAR(AprSun1+11)=CalendarYear,MONTH(AprSun1+11)=4),AprSun1+11,"")) -> 46120 | AE12: =IF(DAY(AprSun1)=1,IF(AND(YEAR(AprSun1+5)=CalendarYear,MONTH(AprSun1+5)=4),AprSun1+5,""),IF(AND(YEAR(AprSun1+12)=CalendarYear,MONTH(AprSun1+12)=4),AprSun1+12,"")) -> 46121 | AF12: =IF(DAY(AprSun1)=1,IF(AND(YEAR(AprSun1+6)=CalendarYear,MONTH(AprSun1+6)=4),AprSun1+6,""),IF(AND(YEAR(AprSun1+13)=CalendarYear,MONTH(AprSun1+13)=4),AprSun1+13,"")) -> 46122 | AG12: =IF(DAY(AprSun1)=1,IF(AND(YEAR(AprSun1+7)=CalendarYear,MONTH(AprSun1+7)=4),AprSun1+7,""),IF(AND(YEAR(AprSun1+14)=CalendarYear,MONTH(AprSun1+14)=4),AprSun1+14,"")) -> 46123
B13: CW3 | C13: =IF(DAY(JanSun1)=1,IF(AND(YEAR(JanSun1+8)=CalendarYear,MONTH(JanSun1+8)=1),JanSun1+8,""),IF(AND(YEAR(JanSun1+15)=CalendarYear,MONTH(JanSun1+15)=1),JanSun1+15,"")) -> 46033 | D13: =IF(DAY(JanSun1)=1,IF(AND(YEAR(JanSun1+9)=CalendarYear,MONTH(JanSun1+9)=1),JanSun1+9,""),IF(AND(YEAR(JanSun1+16)=CalendarYear,MONTH(JanSun1+16)=1),JanSun1+16,"")) -> 46034 | E13: =IF(DAY(JanSun1)=1,IF(AND(YEAR(JanSun1+10)=CalendarYear,MONTH(JanSun1+10)=1),JanSun1+10,""),IF(AND(YEAR(JanSun1+17)=CalendarYear,MONTH(JanSun1+17)=1),JanSun1+17,"")) -> 46035 | F13: =IF(DAY(JanSun1)=1,IF(AND(YEAR(JanSun1+11)=CalendarYear,MONTH(JanSun1+11)=1),JanSun1+11,""),IF(AND(YEAR(JanSun1+18)=CalendarYear,MONTH(JanSun1+18)=1),JanSun1+18,"")) -> 46036 | G13: =IF(DAY(JanSun1)=1,IF(AND(YEAR(JanSun1+12)=CalendarYear,MONTH(JanSun1+12)=1),JanSun1+12,""),IF(AND(YEAR(JanSun1+19)=CalendarYear,MONTH(JanSun1+19)=1),JanSun1+19,"")) -> 46037 | H13: =IF(DAY(JanSun1)=1,IF(AND(YEAR(JanSun1+13)=CalendarYear,MONTH(JanSun1+13)=1),JanSun1+13,""),IF(AND(YEAR(JanSun1+20)=CalendarYear,MONTH(JanSun1+20)=1),JanSun1+20,"")) -> 46038 | I13: =IF(DAY(JanSun1)=1,IF(AND(YEAR(JanSun1+14)=CalendarYear,MONTH(JanSun1+14)=1),JanSun1+14,""),IF(AND(YEAR(JanSun1+21)=CalendarYear,MONTH(JanSun1+21)=1),JanSun1+21,"")) -> 46039 | J13: CW7 | K13: =IF(DAY(FebSun1)=1,IF(AND(YEAR(FebSun1+8)=CalendarYear,MONTH(FebSun1+8)=2),FebSun1+8,""),IF(AND(YEAR(FebSun1+15)=CalendarYear,MONTH(FebSun1+15)=2),FebSun1+15,"")) -> 46068 | L13: =IF(DAY(FebSun1)=1,IF(AND(YEAR(FebSun1+9)=CalendarYear,MONTH(FebSun1+9)=2),FebSun1+9,""),IF(AND(YEAR(FebSun1+16)=CalendarYear,MONTH(FebSun1+16)=2),FebSun1+16,"")) -> 46069 | M13: =IF(DAY(FebSun1)=1,IF(AND(YEAR(FebSun1+10)=CalendarYear,MONTH(FebSun1+10)=2),FebSun1+10,""),IF(AND(YEAR(FebSun1+17)=CalendarYear,MONTH(FebSun1+17)=2),FebSun1+17,"")) -> 46070 | N13: =IF(DAY(FebSun1)=1,IF(AND(YEAR(FebSun1+11)=CalendarYear,MONTH(FebSun1+11)=2),FebSun1+11,""),IF(AND(YEAR(FebSun1+18)=CalendarYear,MONTH(FebSun1+18)=2),FebSun1+18,"")) -> 46071 | O13: =IF(DAY(FebSun1)=1,IF(AND(YEAR(FebSun1+12)=CalendarYear,MONTH(FebSun1+12)=2),FebSun1+12,""),IF(AND(YEAR(FebSun1+19)=CalendarYear,MONTH(FebSun1+19)=2),FebSun1+19,"")) -> 46072 | P13: =IF(DAY(FebSun1)=1,IF(AND(YEAR(FebSun1+13)=CalendarYear,MONTH(FebSun1+13)=2),FebSun1+13,""),IF(AND(YEAR(FebSun1+20)=CalendarYear,MONTH(FebSun1+20)=2),FebSun1+20,"")) -> 46073 | Q13: =IF(DAY(FebSun1)=1,IF(AND(YEAR(FebSun1+14)=CalendarYear,MONTH(FebSun1+14)=2),FebSun1+14,""),IF(AND(YEAR(FebSun1+21)=CalendarYear,MONTH(FebSun1+21)=2),FebSun1+21,"")) -> 46074 | R13: CW11 | S13: =IF(DAY(MarSun1)=1,IF(AND(YEAR(MarSun1+8)=CalendarYear,MONTH(MarSun1+8)=3),MarSun1+8,""),IF(AND(YEAR(MarSun1+15)=CalendarYear,MONTH(MarSun1+15)=3),MarSun1+15,"")) -> 46096 | T13: =IF(DAY(MarSun1)=1,IF(AND(YEAR(MarSun1+9)=CalendarYear,MONTH(MarSun1+9)=3),MarSun1+9,""),IF(AND(YEAR(MarSun1+16)=CalendarYear,MONTH(MarSun1+16)=3),MarSun1+16,"")) -> 46097 | U13: =IF(DAY(MarSun1)=1,IF(AND(YEAR(MarSun1+10)=CalendarYear,MONTH(MarSun1+10)=3),MarSun1+10,""),IF(AND(YEAR(MarSun1+17)=CalendarYear,MONTH(MarSun1+17)=3),MarSun1+17,"")) -> 46098 | V13: =IF(DAY(MarSun1)=1,IF(AND(YEAR(MarSun1+11)=CalendarYear,MONTH(MarSun1+11)=3),MarSun1+11,""),IF(AND(YEAR(MarSun1+18)=CalendarYear,MONTH(MarSun1+18)=3),MarSun1+18,"")) -> 46099 | W13: =IF(DAY(MarSun1)=1,IF(AND(YEAR(MarSun1+12)=CalendarYear,MONTH(MarSun1+12)=3),MarSun1+12,""),IF(AND(YEAR(MarSun1+19)=CalendarYear,MONTH(MarSun1+19)=3),MarSun1+19,"")) -> 46100 | X13: =IF(DAY(MarSun1)=1,IF(AND(YEAR(MarSun1+13)=CalendarYear,MONTH(MarSun1+13)=3),MarSun1+13,""),IF(AND(YEAR(MarSun1+20)=CalendarYear,MONTH(MarSun1+20)=3),MarSun1+20,"")) -> 46101 | Y13: =IF(DAY(MarSun1)=1,IF(AND(YEAR(MarSun1+14)=CalendarYear,MONTH(MarSun1+14)=3),MarSun1+14,""),IF(AND(YEAR(MarSun1+21)=CalendarYear,MONTH(MarSun1+21)=3),MarSun1+21,"")) -> 46102 | Z13: CW16 | AA13: =IF(DAY(AprSun1)=1,IF(AND(YEAR(AprSun1+8)=CalendarYear,MONTH(AprSun1+8)=4),AprSun1+8,""),IF(AND(YEAR(AprSun1+15)=CalendarYear,MONTH(AprSun1+15)=4),AprSun1+15,"")) -> 46124 | AB13: =IF(DAY(AprSun1)=1,IF(AND(YEAR(AprSun1+9)=CalendarYear,MONTH(AprSun1+9)=4),AprSun1+9,""),IF(AND(YEAR(AprSun1+16)=CalendarYear,MONTH(AprSun1+16)=4),AprSun1+16,"")) -> 46125 | AC13: =IF(DAY(AprSun1)=1,IF(AND(YEAR(AprSun1+10)=CalendarYear,MONTH(AprSun1+10)=4),AprSun1+10,""),IF(AND(YEAR(AprSun1+17)=CalendarYear,MONTH(AprSun1+17)=4),AprSun1+17,"")) -> 46126 | AD13: =IF(DAY(AprSun1)=1,IF(AND(YEAR(AprSun1+11)=CalendarYear,MONTH(AprSun1+11)=4),AprSun1+11,""),IF(AND(YEAR(AprSun1+18)=CalendarYear,MONTH(AprSun1+18)=4),AprSun1+18,"")) -> 46127 | AE13: =IF(DAY(AprSun1)=1,IF(AND(YEAR(AprSun1+12)=CalendarYear,MONTH(AprSun1+12)=4),AprSun1+12,""),IF(AND(YEAR(AprSun1+19)=CalendarYear,MONTH(AprSun1+19)=4),AprSun1+19,"")) -> 46128 | AF13: =IF(DAY(AprSun1)=1,IF(AND(YEAR(AprSun1+13)=CalendarYear,MONTH(AprSun1+13)=4),AprSun1+13,""),IF(AND(YEAR(AprSun1+20)=CalendarYear,MONTH(AprSun1+20)=4),AprSun1+20,"")) -> 46129 | AG13: =IF(DAY(AprSun1)=1,IF(AND(YEAR(AprSun1+14)=CalendarYear,MONTH(AprSun1+14)=4),AprSun1+14,""),IF(AND(YEAR(AprSun1+21)=CalendarYear,MONTH(AprSun1+21)=4),AprSun1+21,"")) -> 46130
B14: CW4 | C14: =IF(DAY(JanSun1)=1,IF(AND(YEAR(JanSun1+15)=CalendarYear,MONTH(JanSun1+15)=1),JanSun1+15,""),IF(AND(YEAR(JanSun1+22)=CalendarYear,MONTH(JanSun1+22)=1),JanSun1+22,"")) -> 46040 | D14: =IF(DAY(JanSun1)=1,IF(AND(YEAR(JanSun1+16)=CalendarYear,MONTH(JanSun1+16)=1),JanSun1+16,""),IF(AND(YEAR(JanSun1+23)=CalendarYear,MONTH(JanSun1+23)=1),JanSun1+23,"")) -> 46041 | E14: =IF(DAY(JanSun1)=1,IF(AND(YEAR(JanSun1+17)=CalendarYear,MONTH(JanSun1+17)=1),JanSun1+17,""),IF(AND(YEAR(JanSun1+24)=CalendarYear,MONTH(JanSun1+24)=1),JanSun1+24,"")) -> 46042 | F14: =IF(DAY(JanSun1)=1,IF(AND(YEAR(JanSun1+18)=CalendarYear,MONTH(JanSun1+18)=1),JanSun1+18,""),IF(AND(YEAR(JanSun1+25)=CalendarYear,MONTH(JanSun1+25)=1),JanSun1+25,"")) -> 46043 | G14: =IF(DAY(JanSun1)=1,IF(AND(YEAR(JanSun1+19)=CalendarYear,MONTH(JanSun1+19)=1),JanSun1+19,""),IF(AND(YEAR(JanSun1+26)=CalendarYear,MONTH(JanSun1+26)=1),JanSun1+26,"")) -> 46044 | H14: =IF(DAY(JanSun1)=1,IF(AND(YEAR(JanSun1+20)=CalendarYear,MONTH(JanSun1+20)=1),JanSun1+20,""),IF(AND(YEAR(JanSun1+27)=CalendarYear,MONTH(JanSun1+27)=1),JanSun1+27,"")) -> 46045 | I14: =IF(DAY(JanSun1)=1,IF(AND(YEAR(JanSun1+21)=CalendarYear,MONTH(JanSun1+21)=1),JanSun1+21,""),IF(AND(YEAR(JanSun1+28)=CalendarYear,MONTH(JanSun1+28)=1),JanSun1+28,"")) -> 46046 | J14: CW8 | K14: =IF(DAY(FebSun1)=1,IF(AND(YEAR(FebSun1+15)=CalendarYear,MONTH(FebSun1+15)=2),FebSun1+15,""),IF(AND(YEAR(FebSun1+22)=CalendarYear,MONTH(FebSun1+22)=2),FebSun1+22,"")) -> 46075 | L14: =IF(DAY(FebSun1)=1,IF(AND(YEAR(FebSun1+16)=CalendarYear,MONTH(FebSun1+16)=2),FebSun1+16,""),IF(AND(YEAR(FebSun1+23)=CalendarYear,MONTH(FebSun1+23)=2),FebSun1+23,"")) -> 46076 | M14: =IF(DAY(FebSun1)=1,IF(AND(YEAR(FebSun1+17)=CalendarYear,MONTH(FebSun1+17)=2),FebSun1+17,""),IF(AND(YEAR(FebSun1+24)=CalendarYear,MONTH(FebSun1+24)=2),FebSun1+24,"")) -> 46077 | N14: =IF(DAY(FebSun1)=1,IF(AND(YEAR(FebSun1+18)=CalendarYear,MONTH(FebSun1+18)=2),FebSun1+18,""),IF(AND(YEAR(FebSun1+25)=CalendarYear,MONTH(FebSun1+25)=2),FebSun1+25,"")) -> 46078 | O14: =IF(DAY(FebSun1)=1,IF(AND(YEAR(FebSun1+19)=CalendarYear,MONTH(FebSun1+19)=2),FebSun1+19,""),IF(AND(YEAR(FebSun1+26)=CalendarYear,MONTH(FebSun1+26)=2),FebSun1+26,"")) -> 46079 | P14: =IF(DAY(FebSun1)=1,IF(AND(YEAR(FebSun1+20)=CalendarYear,MONTH(FebSun1+20)=2),FebSun1+20,""),IF(AND(YEAR(FebSun1+27)=CalendarYear,MONTH(FebSun1+27)=2),FebSun1+27,"")) -> 46080 | Q14: =IF(DAY(FebSun1)=1,IF(AND(YEAR(FebSun1+21)=CalendarYear,MONTH(FebSun1+21)=2),FebSun1+21,""),IF(AND(YEAR(FebSun1+28)=CalendarYear,MONTH(FebSun1+28)=2),FebSun1+28,"")) -> 46081 | R14: CW12 | S14: =IF(DAY(MarSun1)=1,IF(AND(YEAR(MarSun1+15)=CalendarYear,MONTH(MarSun1+15)=3),MarSun1+15,""),IF(AND(YEAR(MarSun1+22)=CalendarYear,MONTH(MarSun1+22)=3),MarSun1+22,"")) -> 46103 | T14: =IF(DAY(MarSun1)=1,IF(AND(YEAR(MarSun1+16)=CalendarYear,MONTH(MarSun1+16)=3),MarSun1+16,""),IF(AND(YEAR(MarSun1+23)=CalendarYear,MONTH(MarSun1+23)=3),MarSun1+23,"")) -> 46104 | U14: =IF(DAY(MarSun1)=1,IF(AND(YEAR(MarSun1+17)=CalendarYear,MONTH(MarSun1+17)=3),MarSun1+17,""),IF(AND(YEAR(MarSun1+24)=CalendarYear,MONTH(MarSun1+24)=3),MarSun1+24,"")) -> 46105 | V14: =IF(DAY(MarSun1)=1,IF(AND(YEAR(MarSun1+18)=CalendarYear,MONTH(MarSun1+18)=3),MarSun1+18,""),IF(AND(YEAR(MarSun1+25)=CalendarYear,MONTH(MarSun1+25)=3),MarSun1+25,"")) -> 46106 | W14: =IF(DAY(MarSun1)=1,IF(AND(YEAR(MarSun1+19)=CalendarYear,MONTH(MarSun1+19)=3),MarSun1+19,""),IF(AND(YEAR(MarSun1+26)=CalendarYear,MONTH(MarSun1+26)=3),MarSun1+26,"")) -> 46107 | X14: =IF(DAY(MarSun1)=1,IF(AND(YEAR(MarSun1+20)=CalendarYear,MONTH(MarSun1+20)=3),MarSun1+20,""),IF(AND(YEAR(MarSun1+27)=CalendarYear,MONTH(MarSun1+27)=3),MarSun1+27,"")) -> 46108 | Y14: =IF(DAY(MarSun1)=1,IF(AND(YEAR(MarSun1+21)=CalendarYear,MONTH(MarSun1+21)=3),MarSun1+21,""),IF(AND(YEAR(MarSun1+28)=CalendarYear,MONTH(MarSun1+28)=3),MarSun1+28,"")) -> 46109 | Z14: CW17 | AA14: =IF(DAY(AprSun1)=1,IF(AND(YEAR(AprSun1+15)=CalendarYear,MONTH(AprSun1+15)=4),AprSun1+15,""),IF(AND(YEAR(AprSun1+22)=CalendarYear,MONTH(AprSun1+22)=4),AprSun1+22,"")) -> 46131 | AB14: =IF(DAY(AprSun1)=1,IF(AND(YEAR(AprSun1+16)=CalendarYear,MONTH(AprSun1+16)=4),AprSun1+16,""),IF(AND(YEAR(AprSun1+23)=CalendarYear,MONTH(AprSun1+23)=4),AprSun1+23,"")) -> 46132 | AC14: =IF(DAY(AprSun1)=1,IF(AND(YEAR(AprSun1+17)=CalendarYear,MONTH(AprSun1+17)=4),AprSun1+17,""),IF(AND(YEAR(AprSun1+24)=CalendarYear,MONTH(AprSun1+24)=4),AprSun1+24,"")) -> 46133 | AD14: =IF(DAY(AprSun1)=1,IF(AND(YEAR(AprSun1+18)=CalendarYear,MONTH(AprSun1+18)=4),AprSun1+18,""),IF(AND(YEAR(AprSun1+25)=CalendarYear,MONTH(AprSun1+25)=4),AprSun1+25,"")) -> 46134 | AE14: =IF(DAY(AprSun1)=1,IF(AND(YEAR(AprSun1+19)=CalendarYear,MONTH(AprSun1+19)=4),AprSun1+19,""),IF(AND(YEAR(AprSun1+26)=CalendarYear,MONTH(AprSun1+26)=4),AprSun1+26,"")) -> 46135 | AF14: =IF(DAY(AprSun1)=1,IF(AND(YEAR(AprSun1+20)=CalendarYear,MONTH(AprSun1+20)=4),AprSun1+20,""),IF(AND(YEAR(AprSun1+27)=CalendarYear,MONTH(AprSun1+27)=4),AprSun1+27,"")) -> 46136 | AG14: =IF(DAY(AprSun1)=1,IF(AND(YEAR(AprSun1+21)=CalendarYear,MONTH(AprSun1+21)=4),AprSun1+21,""),IF(AND(YEAR(AprSun1+28)=CalendarYear,MONTH(AprSun1+28)=4),AprSun1+28,"")) -> 46137
B15: CW5 | C15: =IF(DAY(JanSun1)=1,IF(AND(YEAR(JanSun1+22)=CalendarYear,MONTH(JanSun1+22)=1),JanSun1+22,""),IF(AND(YEAR(JanSun1+29)=CalendarYear,MONTH(JanSun1+29)=1),JanSun1+29,"")) -> 46047 | D15: =IF(DAY(JanSun1)=1,IF(AND(YEAR(JanSun1+23)=CalendarYear,MONTH(JanSun1+23)=1),JanSun1+23,""),IF(AND(YEAR(JanSun1+30)=CalendarYear,MONTH(JanSun1+30)=1),JanSun1+30,"")) -> 46048 | E15: =IF(DAY(JanSun1)=1,IF(AND(YEAR(JanSun1+24)=CalendarYear,MONTH(JanSun1+24)=1),JanSun1+24,""),IF(AND(YEAR(JanSun1+31)=CalendarYear,MONTH(JanSun1+31)=1),JanSun1+31,"")) -> 46049 | F15: =IF(DAY(JanSun1)=1,IF(AND(YEAR(JanSun1+25)=CalendarYear,MONTH(JanSun1+25)=1),JanSun1+25,""),IF(AND(YEAR(JanSun1+32)=CalendarYear,MONTH(JanSun1+32)=1),JanSun1+32,"")) -> 46050 | G15: =IF(DAY(JanSun1)=1,IF(AND(YEAR(JanSun1+26)=CalendarYear,MONTH(JanSun1+26)=1),JanSun1+26,""),IF(AND(YEAR(JanSun1+33)=CalendarYear,MONTH(JanSun1+33)=1),JanSun1+33,"")) -> 46051 | H15: =IF(DAY(JanSun1)=1,IF(AND(YEAR(JanSun1+27)=CalendarYear,MONTH(JanSun1+27)=1),JanSun1+27,""),IF(AND(YEAR(JanSun1+34)=CalendarYear,MONTH(JanSun1+34)=1),JanSun1+34,"")) -> 46052 | I15: =IF(DAY(JanSun1)=1,IF(AND(YEAR(JanSun1+28)=CalendarYear,MONTH(JanSun1+28)=1),JanSun1+28,""),IF(AND(YEAR(JanSun1+35)=CalendarYear,MONTH(JanSun1+35)=1),JanSun1+35,"")) -> 46053 | J15: CW9 | K15: =IF(DAY(FebSun1)=1,IF(AND(YEAR(FebSun1+22)=CalendarYear,MONTH(FebSun1+22)=2),FebSun1+22,""),IF(AND(YEAR(FebSun1+29)=CalendarYear,MONTH(FebSun1+29)=2),FebSun1+29,"")) | L15: =IF(DAY(FebSun1)=1,IF(AND(YEAR(FebSun1+23)=CalendarYear,MONTH(FebSun1+23)=2),FebSun1+23,""),IF(AND(YEAR(FebSun1+30)=CalendarYear,MONTH(FebSun1+30)=2),FebSun1+30,"")) | M15: =IF(DAY(FebSun1)=1,IF(AND(YEAR(FebSun1+24)=CalendarYear,MONTH(FebSun1+24)=2),FebSun1+24,""),IF(AND(YEAR(FebSun1+31)=CalendarYear,MONTH(FebSun1+31)=2),FebSun1+31,"")) | N15: =IF(DAY(FebSun1)=1,IF(AND(YEAR(FebSun1+25)=CalendarYear,MONTH(FebSun1+25)=2),FebSun1+25,""),IF(AND(YEAR(FebSun1+32)=CalendarYear,MONTH(FebSun1+32)=2),FebSun1+32,"")) | O15: =IF(DAY(FebSun1)=1,IF(AND(YEAR(FebSun1+26)=CalendarYear,MONTH(FebSun1+26)=2),FebSun1+26,""),IF(AND(YEAR(FebSun1+33)=CalendarYear,MONTH(FebSun1+33)=2),FebSun1+33,"")) | P15: =IF(DAY(FebSun1)=1,IF(AND(YEAR(FebSun1+27)=CalendarYear,MONTH(FebSun1+27)=2),FebSun1+27,""),IF(AND(YEAR(FebSun1+34)=CalendarYear,MONTH(FebSun1+34)=2),FebSun1+34,"")) | Q15: =IF(DAY(FebSun1)=1,IF(AND(YEAR(FebSun1+28)=CalendarYear,MONTH(FebSun1+28)=2),FebSun1+28,""),IF(AND(YEAR(FebSun1+35)=CalendarYear,MONTH(FebSun1+35)=2),FebSun1+35,"")) | R15: CW13 | S15: =IF(DAY(MarSun1)=1,IF(AND(YEAR(MarSun1+22)=CalendarYear,MONTH(MarSun1+22)=3),MarSun1+22,""),IF(AND(YEAR(MarSun1+29)=CalendarYear,MONTH(MarSun1+29)=3),MarSun1+29,"")) -> 46110 | T15: =IF(DAY(MarSun1)=1,IF(AND(YEAR(MarSun1+23)=CalendarYear,MONTH(MarSun1+23)=3),MarSun1+23,""),IF(AND(YEAR(MarSun1+30)=CalendarYear,MONTH(MarSun1+30)=3),MarSun1+30,"")) -> 46111 | U15: =IF(DAY(MarSun1)=1,IF(AND(YEAR(MarSun1+24)=CalendarYear,MONTH(MarSun1+24)=3),MarSun1+24,""),IF(AND(YEAR(MarSun1+31)=CalendarYear,MONTH(MarSun1+31)=3),MarSun1+31,"")) -> 46112 | V15: =IF(DAY(MarSun1)=1,IF(AND(YEAR(MarSun1+25)=CalendarYear,MONTH(MarSun1+25)=3),MarSun1+25,""),IF(AND(YEAR(MarSun1+32)=CalendarYear,MONTH(MarSun1+32)=3),MarSun1+32,"")) | W15: =IF(DAY(MarSun1)=1,IF(AND(YEAR(MarSun1+26)=CalendarYear,MONTH(MarSun1+26)=3),MarSun1+26,""),IF(AND(YEAR(MarSun1+33)=CalendarYear,MONTH(MarSun1+33)=3),MarSun1+33,"")) | X15: =IF(DAY(MarSun1)=1,IF(AND(YEAR(MarSun1+27)=CalendarYear,MONTH(MarSun1+27)=3),MarSun1+27,""),IF(AND(YEAR(MarSun1+34)=CalendarYear,MONTH(MarSun1+34)=3),MarSun1+34,"")) | Y15: =IF(DAY(MarSun1)=1,IF(AND(YEAR(MarSun1+28)=CalendarYear,MONTH(MarSun1+28)=3),MarSun1+28,""),IF(AND(YEAR(MarSun1+35)=CalendarYear,MONTH(MarSun1+35)=3),MarSun1+35,"")) | Z15: CW18 | AA15: =IF(DAY(AprSun1)=1,IF(AND(YEAR(AprSun1+22)=CalendarYear,MONTH(AprSun1+22)=4),AprSun1+22,""),IF(AND(YEAR(AprSun1+29)=CalendarYear,MONTH(AprSun1+29)=4),AprSun1+29,"")) -> 46138 | AB15: =IF(DAY(AprSun1)=1,IF(AND(YEAR(AprSun1+23)=CalendarYear,MONTH(AprSun1+23)=4),AprSun1+23,""),IF(AND(YEAR(AprSun1+30)=CalendarYear,MONTH(AprSun1+30)=4),AprSun1+30,"")) -> 46139 | AC15: =IF(DAY(AprSun1)=1,IF(AND(YEAR(AprSun1+24)=CalendarYear,MONTH(AprSun1+24)=4),AprSun1+24,""),IF(AND(YEAR(AprSun1+31)=CalendarYear,MONTH(AprSun1+31)=4),AprSun1+31,"")) -> 46140 | AD15: =IF(DAY(AprSun1)=1,IF(AND(YEAR(AprSun1+25)=CalendarYear,MONTH(AprSun1+25)=4),AprSun1+25,""),IF(AND(YEAR(AprSun1+32)=CalendarYear,MONTH(AprSun1+32)=4),AprSun1+32,"")) -> 46141 | AE15: =IF(DAY(AprSun1)=1,IF(AND(YEAR(AprSun1+26)=CalendarYear,MONTH(AprSun1+26)=4),AprSun1+26,""),IF(AND(YEAR(AprSun1+33)=CalendarYear,MONTH(AprSun1+33)=4),AprSun1+33,"")) -> 46142 | AF15: =IF(DAY(AprSun1)=1,IF(AND(YEAR(AprSun1+27)=CalendarYear,MONTH(AprSun1+27)=4),AprSun1+27,""),IF(AND(YEAR(AprSun1+34)=CalendarYear,MONTH(AprSun1+34)=4),AprSun1+34,"")) | AG15: =IF(DAY(AprSun1)=1,IF(AND(YEAR(AprSun1+28)=CalendarYear,MONTH(AprSun1+28)=4),AprSun1+28,""),IF(AND(YEAR(AprSun1+35)=CalendarYear,MONTH(AprSun1+35)=4),AprSun1+35,""))
C16: =IF(DAY(JanSun1)=1,IF(AND(YEAR(JanSun1+29)=CalendarYear,MONTH(JanSun1+29)=1),JanSun1+29,""),IF(AND(YEAR(JanSun1+36)=CalendarYear,MONTH(JanSun1+36)=1),JanSun1+36,"")) | D16: =IF(DAY(JanSun1)=1,IF(AND(YEAR(JanSun1+30)=CalendarYear,MONTH(JanSun1+30)=1),JanSun1+30,""),IF(AND(YEAR(JanSun1+37)=CalendarYear,MONTH(JanSun1+37)=1),JanSun1+37,"")) | E16: =IF(DAY(JanSun1)=1,IF(AND(YEAR(JanSun1+31)=CalendarYear,MONTH(JanSun1+31)=1),JanSun1+31,""),IF(AND(YEAR(JanSun1+38)=CalendarYear,MONTH(JanSun1+38)=1),JanSun1+38,"")) | F16: =IF(DAY(JanSun1)=1,IF(AND(YEAR(JanSun1+32)=CalendarYear,MONTH(JanSun1+32)=1),JanSun1+32,""),IF(AND(YEAR(JanSun1+39)=CalendarYear,MONTH(JanSun1+39)=1),JanSun1+39,"")) | G16: =IF(DAY(JanSun1)=1,IF(AND(YEAR(JanSun1+33)=CalendarYear,MONTH(JanSun1+33)=1),JanSun1+33,""),IF(AND(YEAR(JanSun1+40)=CalendarYear,MONTH(JanSun1+40)=1),JanSun1+40,"")) | H16: =IF(DAY(JanSun1)=1,IF(AND(YEAR(JanSun1+34)=CalendarYear,MONTH(JanSun1+34)=1),JanSun1+34,""),IF(AND(YEAR(JanSun1+41)=CalendarYear,MONTH(JanSun1+41)=1),JanSun1+41,"")) | I16: =IF(DAY(JanSun1)=1,IF(AND(YEAR(JanSun1+35)=CalendarYear,MONTH(JanSun1+35)=1),JanSun1+35,""),IF(AND(YEAR(JanSun1+42)=CalendarYear,MONTH(JanSun1+42)=1),JanSun1+42,"")) | K16: =IF(DAY(FebSun1)=1,IF(AND(YEAR(FebSun1+29)=CalendarYear,MONTH(FebSun1+29)=2),FebSun1+29,""),IF(AND(YEAR(FebSun1+36)=CalendarYear,MONTH(FebSun1+36)=2),FebSun1+36,"")) | L16: =IF(DAY(FebSun1)=1,IF(AND(YEAR(FebSun1+30)=CalendarYear,MONTH(FebSun1+30)=2),FebSun1+30,""),IF(AND(YEAR(FebSun1+37)=CalendarYear,MONTH(FebSun1+37)=2),FebSun1+37,"")) | M16: =IF(DAY(FebSun1)=1,IF(AND(YEAR(FebSun1+31)=CalendarYear,MONTH(FebSun1+31)=2),FebSun1+31,""),IF(AND(YEAR(FebSun1+38)=CalendarYear,MONTH(FebSun1+38)=2),FebSun1+38,"")) | N16: =IF(DAY(FebSun1)=1,IF(AND(YEAR(FebSun1+32)=CalendarYear,MONTH(FebSun1+32)=2),FebSun1+32,""),IF(AND(YEAR(FebSun1+39)=CalendarYear,MONTH(FebSun1+39)=2),FebSun1+39,"")) | O16: =IF(DAY(FebSun1)=1,IF(AND(YEAR(FebSun1+33)=CalendarYear,MONTH(FebSun1+33)=2),FebSun1+33,""),IF(AND(YEAR(FebSun1+40)=CalendarYear,MONTH(FebSun1+40)=2),FebSun1+40,"")) | P16: =IF(DAY(FebSun1)=1,IF(AND(YEAR(FebSun1+34)=CalendarYear,MONTH(FebSun1+34)=2),FebSun1+34,""),IF(AND(YEAR(FebSun1+41)=CalendarYear,MONTH(FebSun1+41)=2),FebSun1+41,"")) | Q16: =IF(DAY(FebSun1)=1,IF(AND(YEAR(FebSun1+35)=CalendarYear,MONTH(FebSun1+35)=2),FebSun1+35,""),IF(AND(YEAR(FebSun1+42)=CalendarYear,MONTH(FebSun1+42)=2),FebSun1+42,"")) | R16: CW14 | S16: =IF(DAY(MarSun1)=1,IF(AND(YEAR(MarSun1+29)=CalendarYear,MONTH(MarSun1+29)=3),MarSun1+29,""),IF(AND(YEAR(MarSun1+36)=CalendarYear,MONTH(MarSun1+36)=3),MarSun1+36,"")) | T16: =IF(DAY(MarSun1)=1,IF(AND(YEAR(MarSun1+30)=CalendarYear,MONTH(MarSun1+30)=3),MarSun1+30,""),IF(AND(YEAR(MarSun1+37)=CalendarYear,MONTH(MarSun1+37)=3),MarSun1+37,"")) | U16: =IF(DAY(MarSun1)=1,IF(AND(YEAR(MarSun1+31)=CalendarYear,MONTH(MarSun1+31)=3),MarSun1+31,""),IF(AND(YEAR(MarSun1+38)=CalendarYear,MONTH(MarSun1+38)=3),MarSun1+38,"")) | V16: =IF(DAY(MarSun1)=1,IF(AND(YEAR(MarSun1+32)=CalendarYear,MONTH(MarSun1+32)=3),MarSun1+32,""),IF(AND(YEAR(MarSun1+39)=CalendarYear,MONTH(MarSun1+39)=3),MarSun1+39,"")) | W16: =IF(DAY(MarSun1)=1,IF(AND(YEAR(MarSun1+33)=CalendarYear,MONTH(MarSun1+33)=3),MarSun1+33,""),IF(AND(YEAR(MarSun1+40)=CalendarYear,MONTH(MarSun1+40)=3),MarSun1+40,"")) | X16: =IF(DAY(MarSun1)=1,IF(AND(YEAR(MarSun1+34)=CalendarYear,MONTH(MarSun1+34)=3),MarSun1+34,""),IF(AND(YEAR(MarSun1+41)=CalendarYear,MONTH(MarSun1+41)=3),MarSun1+41,"")) | Y16: =IF(DAY(MarSun1)=1,IF(AND(YEAR(MarSun1+35)=CalendarYear,MONTH(MarSun1+35)=3),MarSun1+35,""),IF(AND(YEAR(MarSun1+42)=CalendarYear,MONTH(MarSun1+42)=3),MarSun1+42,"")) | AA16: =IF(DAY(AprSun1)=1,IF(AND(YEAR(AprSun1+29)=CalendarYear,MONTH(AprSun1+29)=4),AprSun1+29,""),IF(AND(YEAR(AprSun1+36)=CalendarYear,MONTH(AprSun1+36)=4),AprSun1+36,"")) | AB16: =IF(DAY(AprSun1)=1,IF(AND(YEAR(AprSun1+30)=CalendarYear,MONTH(AprSun1+30)=4),AprSun1+30,""),IF(AND(YEAR(AprSun1+37)=CalendarYear,MONTH(AprSun1+37)=4),AprSun1+37,"")) | AC16: =IF(DAY(AprSun1)=1,IF(AND(YEAR(AprSun1+31)=CalendarYear,MONTH(AprSun1+31)=4),AprSun1+31,""),IF(AND(YEAR(AprSun1+38)=CalendarYear,MONTH(AprSun1+38)=4),AprSun1+38,"")) | AD16: =IF(DAY(AprSun1)=1,IF(AND(YEAR(AprSun1+32)=CalendarYear,MONTH(AprSun1+32)=4),AprSun1+32,""),IF(AND(YEAR(AprSun1+39)=CalendarYear,MONTH(AprSun1+39)=4),AprSun1+39,"")) | AE16: =IF(DAY(AprSun1)=1,IF(AND(YEAR(AprSun1+33)=CalendarYear,MONTH(AprSun1+33)=4),AprSun1+33,""),IF(AND(YEAR(AprSun1+40)=CalendarYear,MONTH(AprSun1+40)=4),AprSun1+40,"")) | AF16: =IF(DAY(AprSun1)=1,IF(AND(YEAR(AprSun1+34)=CalendarYear,MONTH(AprSun1+34)=4),AprSun1+34,""),IF(AND(YEAR(AprSun1+41)=CalendarYear,MONTH(AprSun1+41)=4),AprSun1+41,"")) | AG16: =IF(DAY(AprSun1)=1,IF(AND(YEAR(AprSun1+35)=CalendarYear,MONTH(AprSun1+35)=4),AprSun1+35,""),IF(AND(YEAR(AprSun1+42)=CalendarYear,MONTH(AprSun1+42)=4),AprSun1+42,""))
C17: * New year(1st-2nd) | G17: *Big 5 Slava | K17: * Statehood Day(15th-16th) | S17: * Women’s day(8th) | AA17: * Easter (10th-13st)
C18: * Collective leave (3rd,6th) | K18: * Replacement(17th)
C19: * Christmas(7th)
C21: May | K21: June | S21: July | AA21: August
C22: Su | D22: Mo | E22: Tu | F22: We | G22: Th | H22: Fr | I22: Sa | K22: Su | L22: Mo | M22: Tu | N22: We | O22: Th | P22: Fr | Q22: Sa | S22: Su | T22: Mo | U22: Tu | V22: We | W22: Th | X22: Fr | Y22: Sa | AA22: Su | AB22: Mo | AC22: Tu | AD22: We | AE22: Th | AF22: Fr | AG22: Sa
B23: CW18 | C23: =IF(DAY(MaySun1)=1,"",IF(AND(YEAR(MaySun1+1)=CalendarYear,MONTH(MaySun1+1)=5),MaySun1+1,"")) | D23: =IF(DAY(MaySun1)=1,"",IF(AND(YEAR(MaySun1+2)=CalendarYear,MONTH(MaySun1+2)=5),MaySun1+2,"")) | E23: =IF(DAY(MaySun1)=1,"",IF(AND(YEAR(MaySun1+3)=CalendarYear,MONTH(MaySun1+3)=5),MaySun1+3,"")) | F23: =IF(DAY(MaySun1)=1,"",IF(AND(YEAR(MaySun1+4)=CalendarYear,MONTH(MaySun1+4)=5),MaySun1+4,"")) | G23: =IF(DAY(MaySun1)=1,"",IF(AND(YEAR(MaySun1+5)=CalendarYear,MONTH(MaySun1+5)=5),MaySun1+5,"")) | H23: =IF(DAY(MaySun1)=1,"",IF(AND(YEAR(MaySun1+6)=CalendarYear,MONTH(MaySun1+6)=5),MaySun1+6,"")) -> 46143 | I23: =IF(DAY(MaySun1)=1,IF(AND(YEAR(MaySun1)=CalendarYear,MONTH(MaySun1)=5),MaySun1,""),IF(AND(YEAR(MaySun1+7)=CalendarYear,MONTH(MaySun1+7)=5),MaySun1+7,"")) -> 46144 | J23: CW22 | K23: =IF(DAY(JunSun1)=1,"",IF(AND(YEAR(JunSun1+1)=CalendarYear,MONTH(JunSun1+1)=6),JunSun1+1,"")) | L23: =IF(DAY(JunSun1)=1,"",IF(AND(YEAR(JunSun1+2)=CalendarYear,MONTH(JunSun1+2)=6),JunSun1+2,"")) -> 46174 | M23: =IF(DAY(JunSun1)=1,"",IF(AND(YEAR(JunSun1+3)=CalendarYear,MONTH(JunSun1+3)=6),JunSun1+3,"")) -> 46175 | N23: =IF(DAY(JunSun1)=1,"",IF(AND(YEAR(JunSun1+4)=CalendarYear,MONTH(JunSun1+4)=6),JunSun1+4,"")) -> 46176 | O23: =IF(DAY(JunSun1)=1,"",IF(AND(YEAR(JunSun1+5)=CalendarYear,MONTH(JunSun1+5)=6),JunSun1+5,"")) -> 46177 | P23: =IF(DAY(JunSun1)=1,"",IF(AND(YEAR(JunSun1+6)=CalendarYear,MONTH(JunSun1+6)=6),JunSun1+6,"")) -> 46178 | Q23: =IF(DAY(JunSun1)=1,IF(AND(YEAR(JunSun1)=CalendarYear,MONTH(JunSun1)=6),JunSun1,""),IF(AND(YEAR(JunSun1+7)=CalendarYear,MONTH(JunSun1+7)=6),JunSun1+7,"")) -> 46179 | R23: CW27 | S23: =IF(DAY(JulSun1)=1,"",IF(AND(YEAR(JulSun1+1)=CalendarYear,MONTH(JulSun1+1)=7),JulSun1+1,"")) | T23: =IF(DAY(JulSun1)=1,"",IF(AND(YEAR(JulSun1+2)=CalendarYear,MONTH(JulSun1+2)=7),JulSun1+2,"")) | U23: =IF(DAY(JulSun1)=1,"",IF(AND(YEAR(JulSun1+3)=CalendarYear,MONTH(JulSun1+3)=7),JulSun1+3,"")) | V23: =IF(DAY(JulSun1)=1,"",IF(AND(YEAR(JulSun1+4)=CalendarYear,MONTH(JulSun1+4)=7),JulSun1+4,"")) -> 46204 | W23: =IF(DAY(JulSun1)=1,"",IF(AND(YEAR(JulSun1+5)=CalendarYear,MONTH(JulSun1+5)=7),JulSun1+5,"")) -> 46205 | X23: =IF(DAY(JulSun1)=1,"",IF(AND(YEAR(JulSun1+6)=CalendarYear,MONTH(JulSun1+6)=7),JulSun1+6,"")) -> 46206 | Y23: =IF(DAY(JulSun1)=1,IF(AND(YEAR(JulSun1)=CalendarYear,MONTH(JulSun1)=7),JulSun1,""),IF(AND(YEAR(JulSun1+7)=CalendarYear,MONTH(JulSun1+7)=7),JulSun1+7,"")) -> 46207 | Z23: CW31 | AA23: =IF(DAY(AugSun1)=1,"",IF(AND(YEAR(AugSun1+1)=CalendarYear,MONTH(AugSun1+1)=8),AugSun1+1,"")) | AB23: =IF(DAY(AugSun1)=1,"",IF(AND(YEAR(AugSun1+2)=CalendarYear,MONTH(AugSun1+2)=8),AugSun1+2,"")) | AC23: =IF(DAY(AugSun1)=1,"",IF(AND(YEAR(AugSun1+3)=CalendarYear,MONTH(AugSun1+3)=8),AugSun1+3,"")) | AD23: =IF(DAY(AugSun1)=1,"",IF(AND(YEAR(AugSun1+4)=CalendarYear,MONTH(AugSun1+4)=8),AugSun1+4,"")) | AE23: =IF(DAY(AugSun1)=1,"",IF(AND(YEAR(AugSun1+5)=CalendarYear,MONTH(AugSun1+5)=8),AugSun1+5,"")) | AF23: =IF(DAY(AugSun1)=1,"",IF(AND(YEAR(AugSun1+6)=CalendarYear,MONTH(AugSun1+6)=8),AugSun1+6,"")) | AG23: =IF(DAY(AugSun1)=1,IF(AND(YEAR(AugSun1)=CalendarYear,MONTH(AugSun1)=8),AugSun1,""),IF(AND(YEAR(AugSun1+7)=CalendarYear,MONTH(AugSun1+7)=8),AugSun1+7,"")) -> 46235
B24: CW19 | C24: =IF(DAY(MaySun1)=1,IF(AND(YEAR(MaySun1+1)=CalendarYear,MONTH(MaySun1+1)=5),MaySun1+1,""),IF(AND(YEAR(MaySun1+8)=CalendarYear,MONTH(MaySun1+8)=5),MaySun1+8,"")) -> 46145 | D24: =IF(DAY(MaySun1)=1,IF(AND(YEAR(MaySun1+2)=CalendarYear,MONTH(MaySun1+2)=5),MaySun1+2,""),IF(AND(YEAR(MaySun1+9)=CalendarYear,MONTH(MaySun1+9)=5),MaySun1+9,"")) -> 46146 | E24: =IF(DAY(MaySun1)=1,IF(AND(YEAR(MaySun1+3)=CalendarYear,MONTH(MaySun1+3)=5),MaySun1+3,""),IF(AND(YEAR(MaySun1+10)=CalendarYear,MONTH(MaySun1+10)=5),MaySun1+10,"")) -> 46147 | F24: =IF(DAY(MaySun1)=1,IF(AND(YEAR(MaySun1+4)=CalendarYear,MONTH(MaySun1+4)=5),MaySun1+4,""),IF(AND(YEAR(MaySun1+11)=CalendarYear,MONTH(MaySun1+11)=5),MaySun1+11,"")) -> 46148 | G24: =IF(DAY(MaySun1)=1,IF(AND(YEAR(MaySun1+5)=CalendarYear,MONTH(MaySun1+5)=5),MaySun1+5,""),IF(AND(YEAR(MaySun1+12)=CalendarYear,MONTH(MaySun1+12)=5),MaySun1+12,"")) -> 46149 | H24: =IF(DAY(MaySun1)=1,IF(AND(YEAR(MaySun1+6)=CalendarYear,MONTH(MaySun1+6)=5),MaySun1+6,""),IF(AND(YEAR(MaySun1+13)=CalendarYear,MONTH(MaySun1+13)=5),MaySun1+13,"")) -> 46150 | I24: =IF(DAY(MaySun1)=1,IF(AND(YEAR(MaySun1+7)=CalendarYear,MONTH(MaySun1+7)=5),MaySun1+7,""),IF(AND(YEAR(MaySun1+14)=CalendarYear,MONTH(MaySun1+14)=5),MaySun1+14,"")) -> 46151 | J24: CW23 | K24: =IF(DAY(JunSun1)=1,IF(AND(YEAR(JunSun1+1)=CalendarYear,MONTH(JunSun1+1)=6),JunSun1+1,""),IF(AND(YEAR(JunSun1+8)=CalendarYear,MONTH(JunSun1+8)=6),JunSun1+8,"")) -> 46180 | L24: =IF(DAY(JunSun1)=1,IF(AND(YEAR(JunSun1+2)=CalendarYear,MONTH(JunSun1+2)=6),JunSun1+2,""),IF(AND(YEAR(JunSun1+9)=CalendarYear,MONTH(JunSun1+9)=6),JunSun1+9,"")) -> 46181 | M24: =IF(DAY(JunSun1)=1,IF(AND(YEAR(JunSun1+3)=CalendarYear,MONTH(JunSun1+3)=6),JunSun1+3,""),IF(AND(YEAR(JunSun1+10)=CalendarYear,MONTH(JunSun1+10)=6),JunSun1+10,"")) -> 46182 | N24: =IF(DAY(JunSun1)=1,IF(AND(YEAR(JunSun1+4)=CalendarYear,MONTH(JunSun1+4)=6),JunSun1+4,""),IF(AND(YEAR(JunSun1+11)=CalendarYear,MONTH(JunSun1+11)=6),JunSun1+11,"")) -> 46183 | O24: =IF(DAY(JunSun1)=1,IF(AND(YEAR(JunSun1+5)=CalendarYear,MONTH(JunSun1+5)=6),JunSun1+5,""),IF(AND(YEAR(JunSun1+12)=CalendarYear,MONTH(JunSun1+12)=6),JunSun1+12,"")) -> 46184 | P24: =IF(DAY(JunSun1)=1,IF(AND(YEAR(JunSun1+6)=CalendarYear,MONTH(JunSun1+6)=6),JunSun1+6,""),IF(AND(YEAR(JunSun1+13)=CalendarYear,MONTH(JunSun1+13)=6),JunSun1+13,"")) -> 46185 | Q24: =IF(DAY(JunSun1)=1,IF(AND(YEAR(JunSun1+7)=CalendarYear,MONTH(JunSun1+7)=6),JunSun1+7,""),IF(AND(YEAR(JunSun1+14)=CalendarYear,MONTH(JunSun1+14)=6),JunSun1+14,"")) -> 46186 | R24: CW28 | S24: =IF(DAY(JulSun1)=1,IF(AND(YEAR(JulSun1+1)=CalendarYear,MONTH(JulSun1+1)=7),JulSun1+1,""),IF(AND(YEAR(JulSun1+8)=CalendarYear,MONTH(JulSun1+8)=7),JulSun1+8,"")) -> 46208 | T24: =IF(DAY(JulSun1)=1,IF(AND(YEAR(JulSun1+2)=CalendarYear,MONTH(JulSun1+2)=7),JulSun1+2,""),IF(AND(YEAR(JulSun1+9)=CalendarYear,MONTH(JulSun1+9)=7),JulSun1+9,"")) -> 46209 | U24: =IF(DAY(JulSun1)=1,IF(AND(YEAR(JulSun1+3)=CalendarYear,MONTH(JulSun1+3)=7),JulSun1+3,""),IF(AND(YEAR(JulSun1+10)=CalendarYear,MONTH(JulSun1+10)=7),JulSun1+10,"")) -> 46210 | V24: =IF(DAY(JulSun1)=1,IF(AND(YEAR(JulSun1+4)=CalendarYear,MONTH(JulSun1+4)=7),JulSun1+4,""),IF(AND(YEAR(JulSun1+11)=CalendarYear,MONTH(JulSun1+11)=7),JulSun1+11,"")) -> 46211 | W24: =IF(DAY(JulSun1)=1,IF(AND(YEAR(JulSun1+5)=CalendarYear,MONTH(JulSun1+5)=7),JulSun1+5,""),IF(AND(YEAR(JulSun1+12)=CalendarYear,MONTH(JulSun1+12)=7),JulSun1+12,"")) -> 46212 | X24: =IF(DAY(JulSun1)=1,IF(AND(YEAR(JulSun1+6)=CalendarYear,MONTH(JulSun1+6)=7),JulSun1+6,""),IF(AND(YEAR(JulSun1+13)=CalendarYear,MONTH(JulSun1+13)=7),JulSun1+13,"")) -> 46213 | Y24: =IF(DAY(JulSun1)=1,IF(AND(YEAR(JulSun1+7)=CalendarYear,MONTH(JulSun1+7)=7),JulSun1+7,""),IF(AND(YEAR(JulSun1+14)=CalendarYear,MONTH(JulSun1+14)=7),JulSun1+14,"")) -> 46214 | Z24: CW32 | AA24: =IF(DAY(AugSun1)=1,IF(AND(YEAR(AugSun1+1)=CalendarYear,MONTH(AugSun1+1)=8),AugSun1+1,""),IF(AND(YEAR(AugSun1+8)=CalendarYear,MONTH(AugSun1+8)=8),AugSun1+8,"")) -> 46236 | AB24: =IF(DAY(AugSun1)=1,IF(AND(YEAR(AugSun1+2)=CalendarYear,MONTH(AugSun1+2)=8),AugSun1+2,""),IF(AND(YEAR(AugSun1+9)=CalendarYear,MONTH(AugSun1+9)=8),AugSun1+9,"")) -> 46237 | AC24: =IF(DAY(AugSun1)=1,IF(AND(YEAR(AugSun1+3)=CalendarYear,MONTH(AugSun1+3)=8),AugSun1+3,""),IF(AND(YEAR(AugSun1+10)=CalendarYear,MONTH(AugSun1+10)=8),AugSun1+10,"")) -> 46238 | AD24: =IF(DAY(AugSun1)=1,IF(AND(YEAR(AugSun1+4)=CalendarYear,MONTH(AugSun1+4)=8),AugSun1+4,""),IF(AND(YEAR(AugSun1+11)=CalendarYear,MONTH(AugSun1+11)=8),AugSun1+11,"")) -> 46239 | AE24: =IF(DAY(AugSun1)=1,IF(AND(YEAR(AugSun1+5)=CalendarYear,MONTH(AugSun1+5)=8),AugSun1+5,""),IF(AND(YEAR(AugSun1+12)=CalendarYear,MONTH(AugSun1+12)=8),AugSun1+12,"")) -> 46240 | AF24: =IF(DAY(AugSun1)=1,IF(AND(YEAR(AugSun1+6)=CalendarYear,MONTH(AugSun1+6)=8),AugSun1+6,""),IF(AND(YEAR(AugSun1+13)=CalendarYear,MONTH(AugSun1+13)=8),AugSun1+13,"")) -> 46241 | AG24: =IF(DAY(AugSun1)=1,IF(AND(YEAR(AugSun1+7)=CalendarYear,MONTH(AugSun1+7)=8),AugSun1+7,""),IF(AND(YEAR(AugSun1+14)=CalendarYear,MONTH(AugSun1+14)=8),AugSun1+14,"")) -> 46242
B25: CW20 | C25: =IF(DAY(MaySun1)=1,IF(AND(YEAR(MaySun1+8)=CalendarYear,MONTH(MaySun1+8)=5),MaySun1+8,""),IF(AND(YEAR(MaySun1+15)=CalendarYear,MONTH(MaySun1+15)=5),MaySun1+15,"")) -> 46152 | D25: =IF(DAY(MaySun1)=1,IF(AND(YEAR(MaySun1+9)=CalendarYear,MONTH(MaySun1+9)=5),MaySun1+9,""),IF(AND(YEAR(MaySun1+16)=CalendarYear,MONTH(MaySun1+16)=5),MaySun1+16,"")) -> 46153 | E25: =IF(DAY(MaySun1)=1,IF(AND(YEAR(MaySun1+10)=CalendarYear,MONTH(MaySun1+10)=5),MaySun1+10,""),IF(AND(YEAR(MaySun1+17)=CalendarYear,MONTH(MaySun1+17)=5),MaySun1+17,"")) -> 46154 | F25: =IF(DAY(MaySun1)=1,IF(AND(YEAR(MaySun1+11)=CalendarYear,MONTH(MaySun1+11)=5),MaySun1+11,""),IF(AND(YEAR(MaySun1+18)=CalendarYear,MONTH(MaySun1+18)=5),MaySun1+18,"")) -> 46155 | G25: =IF(DAY(MaySun1)=1,IF(AND(YEAR(MaySun1+12)=CalendarYear,MONTH(MaySun1+12)=5),MaySun1+12,""),IF(AND(YEAR(MaySun1+19)=CalendarYear,MONTH(MaySun1+19)=5),MaySun1+19,"")) -> 46156 | H25: =IF(DAY(MaySun1)=1,IF(AND(YEAR(MaySun1+13)=CalendarYear,MONTH(MaySun1+13)=5),MaySun1+13,""),IF(AND(YEAR(MaySun1+20)=CalendarYear,MONTH(MaySun1+20)=5),MaySun1+20,"")) -> 46157 | I25: =IF(DAY(MaySun1)=1,IF(AND(YEAR(MaySun1+14)=CalendarYear,MONTH(MaySun1+14)=5),MaySun1+14,""),IF(AND(YEAR(MaySun1+21)=CalendarYear,MONTH(MaySun1+21)=5),MaySun1+21,"")) -> 46158 | J25: CW24 | K25: =IF(DAY(JunSun1)=1,IF(AND(YEAR(JunSun1+8)=CalendarYear,MONTH(JunSun1+8)=6),JunSun1+8,""),IF(AND(YEAR(JunSun1+15)=CalendarYear,MONTH(JunSun1+15)=6),JunSun1+15,"")) -> 46187 | L25: =IF(DAY(JunSun1)=1,IF(AND(YEAR(JunSun1+9)=CalendarYear,MONTH(JunSun1+9)=6),JunSun1+9,""),IF(AND(YEAR(JunSun1+16)=CalendarYear,MONTH(JunSun1+16)=6),JunSun1+16,"")) -> 46188 | M25: =IF(DAY(JunSun1)=1,IF(AND(YEAR(JunSun1+10)=CalendarYear,MONTH(JunSun1+10)=6),JunSun1+10,""),IF(AND(YEAR(JunSun1+17)=CalendarYear,MONTH(JunSun1+17)=6),JunSun1+17,"")) -> 46189 | N25: =IF(DAY(JunSun1)=1,IF(AND(YEAR(JunSun1+11)=CalendarYear,MONTH(JunSun1+11)=6),JunSun1+11,""),IF(AND(YEAR(JunSun1+18)=CalendarYear,MONTH(JunSun1+18)=6),JunSun1+18,"")) -> 46190 | O25: =IF(DAY(JunSun1)=1,IF(AND(YEAR(JunSun1+12)=CalendarYear,MONTH(JunSun1+12)=6),JunSun1+12,""),IF(AND(YEAR(JunSun1+19)=CalendarYear,MONTH(JunSun1+19)=6),JunSun1+19,"")) -> 46191 | P25: =IF(DAY(JunSun1)=1,IF(AND(YEAR(JunSun1+13)=CalendarYear,MONTH(JunSun1+13)=6),JunSun1+13,""),IF(AND(YEAR(JunSun1+20)=CalendarYear,MONTH(JunSun1+20)=6),JunSun1+20,"")) -> 46192 | Q25: =IF(DAY(JunSun1)=1,IF(AND(YEAR(JunSun1+14)=CalendarYear,MONTH(JunSun1+14)=6),JunSun1+14,""),IF(AND(YEAR(JunSun1+21)=CalendarYear,MONTH(JunSun1+21)=6),JunSun1+21,"")) -> 46193 | R25: CW29 | S25: =IF(DAY(JulSun1)=1,IF(AND(YEAR(JulSun1+8)=CalendarYear,MONTH(JulSun1+8)=7),JulSun1+8,""),IF(AND(YEAR(JulSun1+15)=CalendarYear,MONTH(JulSun1+15)=7),JulSun1+15,"")) -> 46215 | T25: =IF(DAY(JulSun1)=1,IF(AND(YEAR(JulSun1+9)=CalendarYear,MONTH(JulSun1+9)=7),JulSun1+9,""),IF(AND(YEAR(JulSun1+16)=CalendarYear,MONTH(JulSun1+16)=7),JulSun1+16,"")) -> 46216 | U25: =IF(DAY(JulSun1)=1,IF(AND(YEAR(JulSun1+10)=CalendarYear,MONTH(JulSun1+10)=7),JulSun1+10,""),IF(AND(YEAR(JulSun1+17)=CalendarYear,MONTH(JulSun1+17)=7),JulSun1+17,"")) -> 46217 | V25: =IF(DAY(JulSun1)=1,IF(AND(YEAR(JulSun1+11)=CalendarYear,MONTH(JulSun1+11)=7),JulSun1+11,""),IF(AND(YEAR(JulSun1+18)=CalendarYear,MONTH(JulSun1+18)=7),JulSun1+18,"")) -> 46218 | W25: =IF(DAY(JulSun1)=1,IF(AND(YEAR(JulSun1+12)=CalendarYear,MONTH(JulSun1+12)=7),JulSun1+12,""),IF(AND(YEAR(JulSun1+19)=CalendarYear,MONTH(JulSun1+19)=7),JulSun1+19,"")) -> 46219 | X25: =IF(DAY(JulSun1)=1,IF(AND(YEAR(JulSun1+13)=CalendarYear,MONTH(JulSun1+13)=7),JulSun1+13,""),IF(AND(YEAR(JulSun1+20)=CalendarYear,MONTH(JulSun1+20)=7),JulSun1+20,"")) -> 46220 | Y25: =IF(DAY(JulSun1)=1,IF(AND(YEAR(JulSun1+14)=CalendarYear,MONTH(JulSun1+14)=7),JulSun1+14,""),IF(AND(YEAR(JulSun1+21)=CalendarYear,MONTH(JulSun1+21)=7),JulSun1+21,"")) -> 46221 | Z25: CW33 | AA25: =IF(DAY(AugSun1)=1,IF(AND(YEAR(AugSun1+8)=CalendarYear,MONTH(AugSun1+8)=8),AugSun1+8,""),IF(AND(YEAR(AugSun1+15)=CalendarYear,MONTH(AugSun1+15)=8),AugSun1+15,"")) -> 46243 | AB25: =IF(DAY(AugSun1)=1,IF(AND(YEAR(AugSun1+9)=CalendarYear,MONTH(AugSun1+9)=8),AugSun1+9,""),IF(AND(YEAR(AugSun1+16)=CalendarYear,MONTH(AugSun1+16)=8),AugSun1+16,"")) -> 46244 | AC25: =IF(DAY(AugSun1)=1,IF(AND(YEAR(AugSun1+10)=CalendarYear,MONTH(AugSun1+10)=8),AugSun1+10,""),IF(AND(YEAR(AugSun1+17)=CalendarYear,MONTH(AugSun1+17)=8),AugSun1+17,"")) -> 46245 | AD25: =IF(DAY(AugSun1)=1,IF(AND(YEAR(AugSun1+11)=CalendarYear,MONTH(AugSun1+11)=8),AugSun1+11,""),IF(AND(YEAR(AugSun1+18)=CalendarYear,MONTH(AugSun1+18)=8),AugSun1+18,"")) -> 46246 | AE25: =IF(DAY(AugSun1)=1,IF(AND(YEAR(AugSun1+12)=CalendarYear,MONTH(AugSun1+12)=8),AugSun1+12,""),IF(AND(YEAR(AugSun1+19)=CalendarYear,MONTH(AugSun1+19)=8),AugSun1+19,"")) -> 46247 | AF25: =IF(DAY(AugSun1)=1,IF(AND(YEAR(AugSun1+13)=CalendarYear,MONTH(AugSun1+13)=8),AugSun1+13,""),IF(AND(YEAR(AugSun1+20)=CalendarYear,MONTH(AugSun1+20)=8),AugSun1+20,"")) -> 46248 | AG25: =IF(DAY(AugSun1)=1,IF(AND(YEAR(AugSun1+14)=CalendarYear,MONTH(AugSun1+14)=8),AugSun1+14,""),IF(AND(YEAR(AugSun1+21)=CalendarYear,MONTH(AugSun1+21)=8),AugSun1+21,"")) -> 46249
B26: CW21 | C26: =IF(DAY(MaySun1)=1,IF(AND(YEAR(MaySun1+15)=CalendarYear,MONTH(MaySun1+15)=5),MaySun1+15,""),IF(AND(YEAR(MaySun1+22)=CalendarYear,MONTH(MaySun1+22)=5),MaySun1+22,"")) -> 46159 | D26: =IF(DAY(MaySun1)=1,IF(AND(YEAR(MaySun1+16)=CalendarYear,MONTH(MaySun1+16)=5),MaySun1+16,""),IF(AND(YEAR(MaySun1+23)=CalendarYear,MONTH(MaySun1+23)=5),MaySun1+23,"")) -> 46160 | E26: =IF(DAY(MaySun1)=1,IF(AND(YEAR(MaySun1+17)=CalendarYear,MONTH(MaySun1+17)=5),MaySun1+17,""),IF(AND(YEAR(MaySun1+24)=CalendarYear,MONTH(MaySun1+24)=5),MaySun1+24,"")) -> 46161 | F26: =IF(DAY(MaySun1)=1,IF(AND(YEAR(MaySun1+18)=CalendarYear,MONTH(MaySun1+18)=5),MaySun1+18,""),IF(AND(YEAR(MaySun1+25)=CalendarYear,MONTH(MaySun1+25)=5),MaySun1+25,"")) -> 46162 | G26: =IF(DAY(MaySun1)=1,IF(AND(YEAR(MaySun1+19)=CalendarYear,MONTH(MaySun1+19)=5),MaySun1+19,""),IF(AND(YEAR(MaySun1+26)=CalendarYear,MONTH(MaySun1+26)=5),MaySun1+26,"")) -> 46163 | H26: =IF(DAY(MaySun1)=1,IF(AND(YEAR(MaySun1+20)=CalendarYear,MONTH(MaySun1+20)=5),MaySun1+20,""),IF(AND(YEAR(MaySun1+27)=CalendarYear,MONTH(MaySun1+27)=5),MaySun1+27,"")) -> 46164 | I26: =IF(DAY(MaySun1)=1,IF(AND(YEAR(MaySun1+21)=CalendarYear,MONTH(MaySun1+21)=5),MaySun1+21,""),IF(AND(YEAR(MaySun1+28)=CalendarYear,MONTH(MaySun1+28)=5),MaySun1+28,"")) -> 46165 | J26: CW25 | K26: =IF(DAY(JunSun1)=1,IF(AND(YEAR(JunSun1+15)=CalendarYear,MONTH(JunSun1+15)=6),JunSun1+15,""),IF(AND(YEAR(JunSun1+22)=CalendarYear,MONTH(JunSun1+22)=6),JunSun1+22,"")) -> 46194 | L26: =IF(DAY(JunSun1)=1,IF(AND(YEAR(JunSun1+16)=CalendarYear,MONTH(JunSun1+16)=6),JunSun1+16,""),IF(AND(YEAR(JunSun1+23)=CalendarYear,MONTH(JunSun1+23)=6),JunSun1+23,"")) -> 46195 | M26: =IF(DAY(JunSun1)=1,IF(AND(YEAR(JunSun1+17)=CalendarYear,MONTH(JunSun1+17)=6),JunSun1+17,""),IF(AND(YEAR(JunSun1+24)=CalendarYear,MONTH(JunSun1+24)=6),JunSun1+24,"")) -> 46196 | N26: =IF(DAY(JunSun1)=1,IF(AND(YEAR(JunSun1+18)=CalendarYear,MONTH(JunSun1+18)=6),JunSun1+18,""),IF(AND(YEAR(JunSun1+25)=CalendarYear,MONTH(JunSun1+25)=6),JunSun1+25,"")) -> 46197 | O26: =IF(DAY(JunSun1)=1,IF(AND(YEAR(JunSun1+19)=CalendarYear,MONTH(JunSun1+19)=6),JunSun1+19,""),IF(AND(YEAR(JunSun1+26)=CalendarYear,MONTH(JunSun1+26)=6),JunSun1+26,"")) -> 46198 | P26: =IF(DAY(JunSun1)=1,IF(AND(YEAR(JunSun1+20)=CalendarYear,MONTH(JunSun1+20)=6),JunSun1+20,""),IF(AND(YEAR(JunSun1+27)=CalendarYear,MONTH(JunSun1+27)=6),JunSun1+27,"")) -> 46199 | Q26: =IF(DAY(JunSun1)=1,IF(AND(YEAR(JunSun1+21)=CalendarYear,MONTH(JunSun1+21)=6),JunSun1+21,""),IF(AND(YEAR(JunSun1+28)=CalendarYear,MONTH(JunSun1+28)=6),JunSun1+28,"")) -> 46200 | R26: CW30 | S26: =IF(DAY(JulSun1)=1,IF(AND(YEAR(JulSun1+15)=CalendarYear,MONTH(JulSun1+15)=7),JulSun1+15,""),IF(AND(YEAR(JulSun1+22)=CalendarYear,MONTH(JulSun1+22)=7),JulSun1+22,"")) -> 46222 | T26: =IF(DAY(JulSun1)=1,IF(AND(YEAR(JulSun1+16)=CalendarYear,MONTH(JulSun1+16)=7),JulSun1+16,""),IF(AND(YEAR(JulSun1+23)=CalendarYear,MONTH(JulSun1+23)=7),JulSun1+23,"")) -> 46223 | U26: =IF(DAY(JulSun1)=1,IF(AND(YEAR(JulSun1+17)=CalendarYear,MONTH(JulSun1+17)=7),JulSun1+17,""),IF(AND(YEAR(JulSun1+24)=CalendarYear,MONTH(JulSun1+24)=7),JulSun1+24,"")) -> 46224 | V26: =IF(DAY(JulSun1)=1,IF(AND(YEAR(JulSun1+18)=CalendarYear,MONTH(JulSun1+18)=7),JulSun1+18,""),IF(AND(YEAR(JulSun1+25)=CalendarYear,MONTH(JulSun1+25)=7),JulSun1+25,"")) -> 46225 | W26: =IF(DAY(JulSun1)=1,IF(AND(YEAR(JulSun1+19)=CalendarYear,MONTH(JulSun1+19)=7),JulSun1+19,""),IF(AND(YEAR(JulSun1+26)=CalendarYear,MONTH(JulSun1+26)=7),JulSun1+26,"")) -> 46226 | X26: =IF(DAY(JulSun1)=1,IF(AND(YEAR(JulSun1+20)=CalendarYear,MONTH(JulSun1+20)=7),JulSun1+20,""),IF(AND(YEAR(JulSun1+27)=CalendarYear,MONTH(JulSun1+27)=7),JulSun1+27,"")) -> 46227 | Y26: =IF(DAY(JulSun1)=1,IF(AND(YEAR(JulSun1+21)=CalendarYear,MONTH(JulSun1+21)=7),JulSun1+21,""),IF(AND(YEAR(JulSun1+28)=CalendarYear,MONTH(JulSun1+28)=7),JulSun1+28,"")) -> 46228 | Z26: CW34 | AA26: =IF(DAY(AugSun1)=1,IF(AND(YEAR(AugSun1+15)=CalendarYear,MONTH(AugSun1+15)=8),AugSun1+15,""),IF(AND(YEAR(AugSun1+22)=CalendarYear,MONTH(AugSun1+22)=8),AugSun1+22,"")) -> 46250 | AB26: =IF(DAY(AugSun1)=1,IF(AND(YEAR(AugSun1+16)=CalendarYear,MONTH(AugSun1+16)=8),AugSun1+16,""),IF(AND(YEAR(AugSun1+23)=CalendarYear,MONTH(AugSun1+23)=8),AugSun1+23,"")) -> 46251 | AC26: =IF(DAY(AugSun1)=1,IF(AND(YEAR(AugSun1+17)=CalendarYear,MONTH(AugSun1+17)=8),AugSun1+17,""),IF(AND(YEAR(AugSun1+24)=CalendarYear,MONTH(AugSun1+24)=8),AugSun1+24,"")) -> 46252 | AD26: =IF(DAY(AugSun1)=1,IF(AND(YEAR(AugSun1+18)=CalendarYear,MONTH(AugSun1+18)=8),AugSun1+18,""),IF(AND(YEAR(AugSun1+25)=CalendarYear,MONTH(AugSun1+25)=8),AugSun1+25,"")) -> 46253 | AE26: =IF(DAY(AugSun1)=1,IF(AND(YEAR(AugSun1+19)=CalendarYear,MONTH(AugSun1+19)=8),AugSun1+19,""),IF(AND(YEAR(AugSun1+26)=CalendarYear,MONTH(AugSun1+26)=8),AugSun1+26,"")) -> 46254 | AF26: =IF(DAY(AugSun1)=1,IF(AND(YEAR(AugSun1+20)=CalendarYear,MONTH(AugSun1+20)=8),AugSun1+20,""),IF(AND(YEAR(AugSun1+27)=CalendarYear,MONTH(AugSun1+27)=8),AugSun1+27,"")) -> 46255 | AG26: =IF(DAY(AugSun1)=1,IF(AND(YEAR(AugSun1+21)=CalendarYear,MONTH(AugSun1+21)=8),AugSun1+21,""),IF(AND(YEAR(AugSun1+28)=CalendarYear,MONTH(AugSun1+28)=8),AugSun1+28,"")) -> 46256
B27: CW22 | C27: =IF(DAY(MaySun1)=1,IF(AND(YEAR(MaySun1+22)=CalendarYear,MONTH(MaySun1+22)=5),MaySun1+22,""),IF(AND(YEAR(MaySun1+29)=CalendarYear,MONTH(MaySun1+29)=5),MaySun1+29,"")) -> 46166 | D27: =IF(DAY(MaySun1)=1,IF(AND(YEAR(MaySun1+23)=CalendarYear,MONTH(MaySun1+23)=5),MaySun1+23,""),IF(AND(YEAR(MaySun1+30)=CalendarYear,MONTH(MaySun1+30)=5),MaySun1+30,"")) -> 46167 | E27: =IF(DAY(MaySun1)=1,IF(AND(YEAR(MaySun1+24)=CalendarYear,MONTH(MaySun1+24)=5),MaySun1+24,""),IF(AND(YEAR(MaySun1+31)=CalendarYear,MONTH(MaySun1+31)=5),MaySun1+31,"")) -> 46168 | F27: =IF(DAY(MaySun1)=1,IF(AND(YEAR(MaySun1+25)=CalendarYear,MONTH(MaySun1+25)=5),MaySun1+25,""),IF(AND(YEAR(MaySun1+32)=CalendarYear,MONTH(MaySun1+32)=5),MaySun1+32,"")) -> 46169 | G27: =IF(DAY(MaySun1)=1,IF(AND(YEAR(MaySun1+26)=CalendarYear,MONTH(MaySun1+26)=5),MaySun1+26,""),IF(AND(YEAR(MaySun1+33)=CalendarYear,MONTH(MaySun1+33)=5),MaySun1+33,"")) -> 46170 | H27: =IF(DAY(MaySun1)=1,IF(AND(YEAR(MaySun1+27)=CalendarYear,MONTH(MaySun1+27)=5),MaySun1+27,""),IF(AND(YEAR(MaySun1+34)=CalendarYear,MONTH(MaySun1+34)=5),MaySun1+34,"")) -> 46171 | I27: =IF(DAY(MaySun1)=1,IF(AND(YEAR(MaySun1+28)=CalendarYear,MONTH(MaySun1+28)=5),MaySun1+28,""),IF(AND(YEAR(MaySun1+35)=CalendarYear,MONTH(MaySun1+35)=5),MaySun1+35,"")) -> 46172 | J27: CW26 | K27: =IF(DAY(JunSun1)=1,IF(AND(YEAR(JunSun1+22)=CalendarYear,MONTH(JunSun1+22)=6),JunSun1+22,""),IF(AND(YEAR(JunSun1+29)=CalendarYear,MONTH(JunSun1+29)=6),JunSun1+29,"")) -> 46201 | L27: =IF(DAY(JunSun1)=1,IF(AND(YEAR(JunSun1+23)=CalendarYear,MONTH(JunSun1+23)=6),JunSun1+23,""),IF(AND(YEAR(JunSun1+30)=CalendarYear,MONTH(JunSun1+30)=6),JunSun1+30,"")) -> 46202 | M27: =IF(DAY(JunSun1)=1,IF(AND(YEAR(JunSun1+24)=CalendarYear,MONTH(JunSun1+24)=6),JunSun1+24,""),IF(AND(YEAR(JunSun1+31)=CalendarYear,MONTH(JunSun1+31)=6),JunSun1+31,"")) -> 46203 | N27: =IF(DAY(JunSun1)=1,IF(AND(YEAR(JunSun1+25)=CalendarYear,MONTH(JunSun1+25)=6),JunSun1+25,""),IF(AND(YEAR(JunSun1+32)=CalendarYear,MONTH(JunSun1+32)=6),JunSun1+32,"")) | O27: =IF(DAY(JunSun1)=1,IF(AND(YEAR(JunSun1+26)=CalendarYear,MONTH(JunSun1+26)=6),JunSun1+26,""),IF(AND(YEAR(JunSun1+33)=CalendarYear,MONTH(JunSun1+33)=6),JunSun1+33,"")) | P27: =IF(DAY(JunSun1)=1,IF(AND(YEAR(JunSun1+27)=CalendarYear,MONTH(JunSun1+27)=6),JunSun1+27,""),IF(AND(YEAR(JunSun1+34)=CalendarYear,MONTH(JunSun1+34)=6),JunSun1+34,"")) | Q27: =IF(DAY(JunSun1)=1,IF(AND(YEAR(JunSun1+28)=CalendarYear,MONTH(JunSun1+28)=6),JunSun1+28,""),IF(AND(YEAR(JunSun1+35)=CalendarYear,MONTH(JunSun1+35)=6),JunSun1+35,"")) | R27: CW31 | S27: =IF(DAY(JulSun1)=1,IF(AND(YEAR(JulSun1+22)=CalendarYear,MONTH(JulSun1+22)=7),JulSun1+22,""),IF(AND(YEAR(JulSun1+29)=CalendarYear,MONTH(JulSun1+29)=7),JulSun1+29,"")) -> 46229 | T27: =IF(DAY(JulSun1)=1,IF(AND(YEAR(JulSun1+23)=CalendarYear,MONTH(JulSun1+23)=7),JulSun1+23,""),IF(AND(YEAR(JulSun1+30)=CalendarYear,MONTH(JulSun1+30)=7),JulSun1+30,"")) -> 46230 | U27: =IF(DAY(JulSun1)=1,IF(AND(YEAR(JulSun1+24)=CalendarYear,MONTH(JulSun1+24)=7),JulSun1+24,""),IF(AND(YEAR(JulSun1+31)=CalendarYear,MONTH(JulSun1+31)=7),JulSun1+31,"")) -> 46231 | V27: =IF(DAY(JulSun1)=1,IF(AND(YEAR(JulSun1+25)=CalendarYear,MONTH(JulSun1+25)=7),JulSun1+25,""),IF(AND(YEAR(JulSun1+32)=CalendarYear,MONTH(JulSun1+32)=7),JulSun1+32,"")) -> 46232 | W27: =IF(DAY(JulSun1)=1,IF(AND(YEAR(JulSun1+26)=CalendarYear,MONTH(JulSun1+26)=7),JulSun1+26,""),IF(AND(YEAR(JulSun1+33)=CalendarYear,MONTH(JulSun1+33)=7),JulSun1+33,"")) -> 46233 | X27: =IF(DAY(JulSun1)=1,IF(AND(YEAR(JulSun1+27)=CalendarYear,MONTH(JulSun1+27)=7),JulSun1+27,""),IF(AND(YEAR(JulSun1+34)=CalendarYear,MONTH(JulSun1+34)=7),JulSun1+34,"")) -> 46234 | Y27: =IF(DAY(JulSun1)=1,IF(AND(YEAR(JulSun1+28)=CalendarYear,MONTH(JulSun1+28)=7),JulSun1+28,""),IF(AND(YEAR(JulSun1+35)=CalendarYear,MONTH(JulSun1+35)=7),JulSun1+35,"")) | Z27: CW35 | AA27: =IF(DAY(AugSun1)=1,IF(AND(YEAR(AugSun1+22)=CalendarYear,MONTH(AugSun1+22)=8),AugSun1+22,""),IF(AND(YEAR(AugSun1+29)=CalendarYear,MONTH(AugSun1+29)=8),AugSun1+29,"")) -> 46257 | AB27: =IF(DAY(AugSun1)=1,IF(AND(YEAR(AugSun1+23)=CalendarYear,MONTH(AugSun1+23)=8),AugSun1+23,""),IF(AND(YEAR(AugSun1+30)=CalendarYear,MONTH(AugSun1+30)=8),AugSun1+30,"")) -> 46258 | AC27: =IF(DAY(AugSun1)=1,IF(AND(YEAR(AugSun1+24)=CalendarYear,MONTH(AugSun1+24)=8),AugSun1+24,""),IF(AND(YEAR(AugSun1+31)=CalendarYear,MONTH(AugSun1+31)=8),AugSun1+31,"")) -> 46259 | AD27: =IF(DAY(AugSun1)=1,IF(AND(YEAR(AugSun1+25)=CalendarYear,MONTH(AugSun1+25)=8),AugSun1+25,""),IF(AND(YEAR(AugSun1+32)=CalendarYear,MONTH(AugSun1+32)=8),AugSun1+32,"")) -> 46260 | AE27: =IF(DAY(AugSun1)=1,IF(AND(YEAR(AugSun1+26)=CalendarYear,MONTH(AugSun1+26)=8),AugSun1+26,""),IF(AND(YEAR(AugSun1+33)=CalendarYear,MONTH(AugSun1+33)=8),AugSun1+33,"")) -> 46261 | AF27: =IF(DAY(AugSun1)=1,IF(AND(YEAR(AugSun1+27)=CalendarYear,MONTH(AugSun1+27)=8),AugSun1+27,""),IF(AND(YEAR(AugSun1+34)=CalendarYear,MONTH(AugSun1+34)=8),AugSun1+34,"")) -> 46262 | AG27: =IF(DAY(AugSun1)=1,IF(AND(YEAR(AugSun1+28)=CalendarYear,MONTH(AugSun1+28)=8),AugSun1+28,""),IF(AND(YEAR(AugSun1+35)=CalendarYear,MONTH(AugSun1+35)=8),AugSun1+35,"")) -> 46263
C28: =IF(DAY(MaySun1)=1,IF(AND(YEAR(MaySun1+29)=CalendarYear,MONTH(MaySun1+29)=5),MaySun1+29,""),IF(AND(YEAR(MaySun1+36)=CalendarYear,MONTH(MaySun1+36)=5),MaySun1+36,"")) -> 46173 | D28: =IF(DAY(MaySun1)=1,IF(AND(YEAR(MaySun1+30)=CalendarYear,MONTH(MaySun1+30)=5),MaySun1+30,""),IF(AND(YEAR(MaySun1+37)=CalendarYear,MONTH(MaySun1+37)=5),MaySun1+37,"")) | E28: =IF(DAY(MaySun1)=1,IF(AND(YEAR(MaySun1+31)=CalendarYear,MONTH(MaySun1+31)=5),MaySun1+31,""),IF(AND(YEAR(MaySun1+38)=CalendarYear,MONTH(MaySun1+38)=5),MaySun1+38,"")) | F28: =IF(DAY(MaySun1)=1,IF(AND(YEAR(MaySun1+32)=CalendarYear,MONTH(MaySun1+32)=5),MaySun1+32,""),IF(AND(YEAR(MaySun1+39)=CalendarYear,MONTH(MaySun1+39)=5),MaySun1+39,"")) | G28: =IF(DAY(MaySun1)=1,IF(AND(YEAR(MaySun1+33)=CalendarYear,MONTH(MaySun1+33)=5),MaySun1+33,""),IF(AND(YEAR(MaySun1+40)=CalendarYear,MONTH(MaySun1+40)=5),MaySun1+40,"")) | H28: =IF(DAY(MaySun1)=1,IF(AND(YEAR(MaySun1+34)=CalendarYear,MONTH(MaySun1+34)=5),MaySun1+34,""),IF(AND(YEAR(MaySun1+41)=CalendarYear,MONTH(MaySun1+41)=5),MaySun1+41,"")) | I28: =IF(DAY(MaySun1)=1,IF(AND(YEAR(MaySun1+35)=CalendarYear,MONTH(MaySun1+35)=5),MaySun1+35,""),IF(AND(YEAR(MaySun1+42)=CalendarYear,MONTH(MaySun1+42)=5),MaySun1+42,"")) | J28: CW27 | K28: =IF(DAY(JunSun1)=1,IF(AND(YEAR(JunSun1+29)=CalendarYear,MONTH(JunSun1+29)=6),JunSun1+29,""),IF(AND(YEAR(JunSun1+36)=CalendarYear,MONTH(JunSun1+36)=6),JunSun1+36,"")) | L28: =IF(DAY(JunSun1)=1,IF(AND(YEAR(JunSun1+30)=CalendarYear,MONTH(JunSun1+30)=6),JunSun1+30,""),IF(AND(YEAR(JunSun1+37)=CalendarYear,MONTH(JunSun1+37)=6),JunSun1+37,"")) | M28: =IF(DAY(JunSun1)=1,IF(AND(YEAR(JunSun1+31)=CalendarYear,MONTH(JunSun1+31)=6),JunSun1+31,""),IF(AND(YEAR(JunSun1+38)=CalendarYear,MONTH(JunSun1+38)=6),JunSun1+38,"")) | N28: =IF(DAY(JunSun1)=1,IF(AND(YEAR(JunSun1+32)=CalendarYear,MONTH(JunSun1+32)=6),JunSun1+32,""),IF(AND(YEAR(JunSun1+39)=CalendarYear,MONTH(JunSun1+39)=6),JunSun1+39,"")) | O28: =IF(DAY(JunSun1)=1,IF(AND(YEAR(JunSun1+33)=CalendarYear,MONTH(JunSun1+33)=6),JunSun1+33,""),IF(AND(YEAR(JunSun1+40)=CalendarYear,MONTH(JunSun1+40)=6),JunSun1+40,"")) | P28: =IF(DAY(JunSun1)=1,IF(AND(YEAR(JunSun1+34)=CalendarYear,MONTH(JunSun1+34)=6),JunSun1+34,""),IF(AND(YEAR(JunSun1+41)=CalendarYear,MONTH(JunSun1+41)=6),JunSun1+41,"")) | Q28: =IF(DAY(JunSun1)=1,IF(AND(YEAR(JunSun1+35)=CalendarYear,MONTH(JunSun1+35)=6),JunSun1+35,""),IF(AND(YEAR(JunSun1+42)=CalendarYear,MONTH(JunSun1+42)=6),JunSun1+42,"")) | S28: =IF(DAY(JulSun1)=1,IF(AND(YEAR(JulSun1+29)=CalendarYear,MONTH(JulSun1+29)=7),JulSun1+29,""),IF(AND(YEAR(JulSun1+36)=CalendarYear,MONTH(JulSun1+36)=7),JulSun1+36,"")) | T28: =IF(DAY(JulSun1)=1,IF(AND(YEAR(JulSun1+30)=CalendarYear,MONTH(JulSun1+30)=7),JulSun1+30,""),IF(AND(YEAR(JulSun1+37)=CalendarYear,MONTH(JulSun1+37)=7),JulSun1+37,"")) | U28: =IF(DAY(JulSun1)=1,IF(AND(YEAR(JulSun1+31)=CalendarYear,MONTH(JulSun1+31)=7),JulSun1+31,""),IF(AND(YEAR(JulSun1+38)=CalendarYear,MONTH(JulSun1+38)=7),JulSun1+38,"")) | V28: =IF(DAY(JulSun1)=1,IF(AND(YEAR(JulSun1+32)=CalendarYear,MONTH(JulSun1+32)=7),JulSun1+32,""),IF(AND(YEAR(JulSun1+39)=CalendarYear,MONTH(JulSun1+39)=7),JulSun1+39,"")) | W28: =IF(DAY(JulSun1)=1,IF(AND(YEAR(JulSun1+33)=CalendarYear,MONTH(JulSun1+33)=7),JulSun1+33,""),IF(AND(YEAR(JulSun1+40)=CalendarYear,MONTH(JulSun1+40)=7),JulSun1+40,"")) | X28: =IF(DAY(JulSun1)=1,IF(AND(YEAR(JulSun1+34)=CalendarYear,MONTH(JulSun1+34)=7),JulSun1+34,""),IF(AND(YEAR(JulSun1+41)=CalendarYear,MONTH(JulSun1+41)=7),JulSun1+41,"")) | Y28: =IF(DAY(JulSun1)=1,IF(AND(YEAR(JulSun1+35)=CalendarYear,MONTH(JulSun1+35)=7),JulSun1+35,""),IF(AND(YEAR(JulSun1+42)=CalendarYear,MONTH(JulSun1+42)=7),JulSun1+42,"")) | AA28: =IF(DAY(AugSun1)=1,IF(AND(YEAR(AugSun1+29)=CalendarYear,MONTH(AugSun1+29)=8),AugSun1+29,""),IF(AND(YEAR(AugSun1+36)=CalendarYear,MONTH(AugSun1+36)=8),AugSun1+36,"")) -> 46264 | AB28: =IF(DAY(AugSun1)=1,IF(AND(YEAR(AugSun1+30)=CalendarYear,MONTH(AugSun1+30)=8),AugSun1+30,""),IF(AND(YEAR(AugSun1+37)=CalendarYear,MONTH(AugSun1+37)=8),AugSun1+37,"")) -> 46265 | AC28: =IF(DAY(AugSun1)=1,IF(AND(YEAR(AugSun1+31)=CalendarYear,MONTH(AugSun1+31)=8),AugSun1+31,""),IF(AND(YEAR(AugSun1+38)=CalendarYear,MONTH(AugSun1+38)=8),AugSun1+38,"")) | AD28: =IF(DAY(AugSun1)=1,IF(AND(YEAR(AugSun1+32)=CalendarYear,MONTH(AugSun1+32)=8),AugSun1+32,""),IF(AND(YEAR(AugSun1+39)=CalendarYear,MONTH(AugSun1+39)=8),AugSun1+39,"")) | AE28: =IF(DAY(AugSun1)=1,IF(AND(YEAR(AugSun1+33)=CalendarYear,MONTH(AugSun1+33)=8),AugSun1+33,""),IF(AND(YEAR(AugSun1+40)=CalendarYear,MONTH(AugSun1+40)=8),AugSun1+40,"")) | AF28: =IF(DAY(AugSun1)=1,IF(AND(YEAR(AugSun1+34)=CalendarYear,MONTH(AugSun1+34)=8),AugSun1+34,""),IF(AND(YEAR(AugSun1+41)=CalendarYear,MONTH(AugSun1+41)=8),AugSun1+41,"")) | AG28: =IF(DAY(AugSun1)=1,IF(AND(YEAR(AugSun1+35)=CalendarYear,MONTH(AugSun1+35)=8),AugSun1+35,""),IF(AND(YEAR(AugSun1+42)=CalendarYear,MONTH(AugSun1+42)=8),AugSun1+42,""))
C29: * Labor day(1st-2nd) | G29: *Big 5 Slava | K29: * KSCE Olympics (13th) | S29: * Collective leave (27st-31st): Summer vacation | AA29: * Collective leave (3st-7th): Summer vacation
C33: September | K33: October | S33: November | AA33: December
C34: Su | D34: Mo | E34: Tu | F34: We | G34: Th | H34: Fr | I34: Sa | K34: Su | L34: Mo | M34: Tu | N34: We | O34: Th | P34: Fr | Q34: Sa | S34: Su | T34: Mo | U34: Tu | V34: We | W34: Th | X34: Fr | Y34: Sa | AA34: Su | AB34: Mo | AC34: Tu | AD34: We | AE34: Th | AF34: Fr | AG34: Sa
B35: CW36 | C35: =IF(DAY(SepSun1)=1,"",IF(AND(YEAR(SepSun1+1)=CalendarYear,MONTH(SepSun1+1)=9),SepSun1+1,"")) | D35: =IF(DAY(SepSun1)=1,"",IF(AND(YEAR(SepSun1+2)=CalendarYear,MONTH(SepSun1+2)=9),SepSun1+2,"")) | E35: =IF(DAY(SepSun1)=1,"",IF(AND(YEAR(SepSun1+3)=CalendarYear,MONTH(SepSun1+3)=9),SepSun1+3,"")) -> 46266 | F35: =IF(DAY(SepSun1)=1,"",IF(AND(YEAR(SepSun1+4)=CalendarYear,MONTH(SepSun1+4)=9),SepSun1+4,"")) -> 46267 | G35: =IF(DAY(SepSun1)=1,"",IF(AND(YEAR(SepSun1+5)=CalendarYear,MONTH(SepSun1+5)=9),SepSun1+5,"")) -> 46268 | H35: =IF(DAY(SepSun1)=1,"",IF(AND(YEAR(SepSun1+6)=CalendarYear,MONTH(SepSun1+6)=9),SepSun1+6,"")) -> 46269 | I35: =IF(DAY(SepSun1)=1,IF(AND(YEAR(SepSun1)=CalendarYear,MONTH(SepSun1)=9),SepSun1,""),IF(AND(YEAR(SepSun1+7)=CalendarYear,MONTH(SepSun1+7)=9),SepSun1+7,"")) -> 46270 | J35: CW40 | K35: =IF(DAY(OctSun1)=1,"",IF(AND(YEAR(OctSun1+1)=CalendarYear,MONTH(OctSun1+1)=10),OctSun1+1,"")) | L35: =IF(DAY(OctSun1)=1,"",IF(AND(YEAR(OctSun1+2)=CalendarYear,MONTH(OctSun1+2)=10),OctSun1+2,"")) | M35: =IF(DAY(OctSun1)=1,"",IF(AND(YEAR(OctSun1+3)=CalendarYear,MONTH(OctSun1+3)=10),OctSun1+3,"")) | N35: =IF(DAY(OctSun1)=1,"",IF(AND(YEAR(OctSun1+4)=CalendarYear,MONTH(OctSun1+4)=10),OctSun1+4,"")) | O35: =IF(DAY(OctSun1)=1,"",IF(AND(YEAR(OctSun1+5)=CalendarYear,MONTH(OctSun1+5)=10),OctSun1+5,"")) -> 46296 | P35: =IF(DAY(OctSun1)=1,"",IF(AND(YEAR(OctSun1+6)=CalendarYear,MONTH(OctSun1+6)=10),OctSun1+6,"")) -> 46297 | Q35: =IF(DAY(OctSun1)=1,IF(AND(YEAR(OctSun1)=CalendarYear,MONTH(OctSun1)=10),OctSun1,""),IF(AND(YEAR(OctSun1+7)=CalendarYear,MONTH(OctSun1+7)=10),OctSun1+7,"")) -> 46298 | R35: CW44 | S35: =IF(DAY(NovSun1)=1,"",IF(AND(YEAR(NovSun1+1)=CalendarYear,MONTH(NovSun1+1)=11),NovSun1+1,"")) -> 46327 | T35: =IF(DAY(NovSun1)=1,"",IF(AND(YEAR(NovSun1+2)=CalendarYear,MONTH(NovSun1+2)=11),NovSun1+2,"")) -> 46328 | U35: =IF(DAY(NovSun1)=1,"",IF(AND(YEAR(NovSun1+3)=CalendarYear,MONTH(NovSun1+3)=11),NovSun1+3,"")) -> 46329 | V35: =IF(DAY(NovSun1)=1,"",IF(AND(YEAR(NovSun1+4)=CalendarYear,MONTH(NovSun1+4)=11),NovSun1+4,"")) -> 46330 | W35: =IF(DAY(NovSun1)=1,"",IF(AND(YEAR(NovSun1+5)=CalendarYear,MONTH(NovSun1+5)=11),NovSun1+5,"")) -> 46331 | X35: =IF(DAY(NovSun1)=1,"",IF(AND(YEAR(NovSun1+6)=CalendarYear,MONTH(NovSun1+6)=11),NovSun1+6,"")) -> 46332 | Y35: =IF(DAY(NovSun1)=1,IF(AND(YEAR(NovSun1)=CalendarYear,MONTH(NovSun1)=11),NovSun1,""),IF(AND(YEAR(NovSun1+7)=CalendarYear,MONTH(NovSun1+7)=11),NovSun1+7,"")) -> 46333 | Z35: CW48 | AA35: =IF(DAY(DecSun1)=1,"",IF(AND(YEAR(DecSun1+1)=CalendarYear,MONTH(DecSun1+1)=12),DecSun1+1,"")) | AB35: =IF(DAY(DecSun1)=1,"",IF(AND(YEAR(DecSun1+2)=CalendarYear,MONTH(DecSun1+2)=12),DecSun1+2,"")) | AC35: =IF(DAY(DecSun1)=1,"",IF(AND(YEAR(DecSun1+3)=CalendarYear,MONTH(DecSun1+3)=12),DecSun1+3,"")) -> 46357 | AD35: =IF(DAY(DecSun1)=1,"",IF(AND(YEAR(DecSun1+4)=CalendarYear,MONTH(DecSun1+4)=12),DecSun1+4,"")) -> 46358 | AE35: =IF(DAY(DecSun1)=1,"",IF(AND(YEAR(DecSun1+5)=CalendarYear,MONTH(DecSun1+5)=12),DecSun1+5,"")) -> 46359 | AF35: =IF(DAY(DecSun1)=1,"",IF(AND(YEAR(DecSun1+6)=CalendarYear,MONTH(DecSun1+6)=12),DecSun1+6,"")) -> 46360 | AG35: =IF(DAY(DecSun1)=1,IF(AND(YEAR(DecSun1)=CalendarYear,MONTH(DecSun1)=12),DecSun1,""),IF(AND(YEAR(DecSun1+7)=CalendarYear,MONTH(DecSun1+7)=12),DecSun1+7,"")) -> 46361
B36: CW37 | C36: =IF(DAY(SepSun1)=1,IF(AND(YEAR(SepSun1+1)=CalendarYear,MONTH(SepSun1+1)=9),SepSun1+1,""),IF(AND(YEAR(SepSun1+8)=CalendarYear,MONTH(SepSun1+8)=9),SepSun1+8,"")) -> 46271 | D36: =IF(DAY(SepSun1)=1,IF(AND(YEAR(SepSun1+2)=CalendarYear,MONTH(SepSun1+2)=9),SepSun1+2,""),IF(AND(YEAR(SepSun1+9)=CalendarYear,MONTH(SepSun1+9)=9),SepSun1+9,"")) -> 46272 | E36: =IF(DAY(SepSun1)=1,IF(AND(YEAR(SepSun1+3)=CalendarYear,MONTH(SepSun1+3)=9),SepSun1+3,""),IF(AND(YEAR(SepSun1+10)=CalendarYear,MONTH(SepSun1+10)=9),SepSun1+10,"")) -> 46273 | F36: =IF(DAY(SepSun1)=1,IF(AND(YEAR(SepSun1+4)=CalendarYear,MONTH(SepSun1+4)=9),SepSun1+4,""),IF(AND(YEAR(SepSun1+11)=CalendarYear,MONTH(SepSun1+11)=9),SepSun1+11,"")) -> 46274 | G36: =IF(DAY(SepSun1)=1,IF(AND(YEAR(SepSun1+5)=CalendarYear,MONTH(SepSun1+5)=9),SepSun1+5,""),IF(AND(YEAR(SepSun1+12)=CalendarYear,MONTH(SepSun1+12)=9),SepSun1+12,"")) -> 46275 | H36: =IF(DAY(SepSun1)=1,IF(AND(YEAR(SepSun1+6)=CalendarYear,MONTH(SepSun1+6)=9),SepSun1+6,""),IF(AND(YEAR(SepSun1+13)=CalendarYear,MONTH(SepSun1+13)=9),SepSun1+13,"")) -> 46276 | I36: =IF(DAY(SepSun1)=1,IF(AND(YEAR(SepSun1+7)=CalendarYear,MONTH(SepSun1+7)=9),SepSun1+7,""),IF(AND(YEAR(SepSun1+14)=CalendarYear,MONTH(SepSun1+14)=9),SepSun1+14,"")) -> 46277 | J36: CW41 | K36: =IF(DAY(OctSun1)=1,IF(AND(YEAR(OctSun1+1)=CalendarYear,MONTH(OctSun1+1)=10),OctSun1+1,""),IF(AND(YEAR(OctSun1+8)=CalendarYear,MONTH(OctSun1+8)=10),OctSun1+8,"")) -> 46299 | L36: =IF(DAY(OctSun1)=1,IF(AND(YEAR(OctSun1+2)=CalendarYear,MONTH(OctSun1+2)=10),OctSun1+2,""),IF(AND(YEAR(OctSun1+9)=CalendarYear,MONTH(OctSun1+9)=10),OctSun1+9,"")) -> 46300 | M36: =IF(DAY(OctSun1)=1,IF(AND(YEAR(OctSun1+3)=CalendarYear,MONTH(OctSun1+3)=10),OctSun1+3,""),IF(AND(YEAR(OctSun1+10)=CalendarYear,MONTH(OctSun1+10)=10),OctSun1+10,"")) -> 46301 | N36: =IF(DAY(OctSun1)=1,IF(AND(YEAR(OctSun1+4)=CalendarYear,MONTH(OctSun1+4)=10),OctSun1+4,""),IF(AND(YEAR(OctSun1+11)=CalendarYear,MONTH(OctSun1+11)=10),OctSun1+11,"")) -> 46302 | O36: =IF(DAY(OctSun1)=1,IF(AND(YEAR(OctSun1+5)=CalendarYear,MONTH(OctSun1+5)=10),OctSun1+5,""),IF(AND(YEAR(OctSun1+12)=CalendarYear,MONTH(OctSun1+12)=10),OctSun1+12,"")) -> 46303 | P36: =IF(DAY(OctSun1)=1,IF(AND(YEAR(OctSun1+6)=CalendarYear,MONTH(OctSun1+6)=10),OctSun1+6,""),IF(AND(YEAR(OctSun1+13)=CalendarYear,MONTH(OctSun1+13)=10),OctSun1+13,"")) -> 46304 | Q36: =IF(DAY(OctSun1)=1,IF(AND(YEAR(OctSun1+7)=CalendarYear,MONTH(OctSun1+7)=10),OctSun1+7,""),IF(AND(YEAR(OctSun1+14)=CalendarYear,MONTH(OctSun1+14)=10),OctSun1+14,"")) -> 46305 | R36: CW45 | S36: =IF(DAY(NovSun1)=1,IF(AND(YEAR(NovSun1+1)=CalendarYear,MONTH(NovSun1+1)=11),NovSun1+1,""),IF(AND(YEAR(NovSun1+8)=CalendarYear,MONTH(NovSun1+8)=11),NovSun1+8,"")) -> 46334 | T36: =IF(DAY(NovSun1)=1,IF(AND(YEAR(NovSun1+2)=CalendarYear,MONTH(NovSun1+2)=11),NovSun1+2,""),IF(AND(YEAR(NovSun1+9)=CalendarYear,MONTH(NovSun1+9)=11),NovSun1+9,"")) -> 46335 | U36: =IF(DAY(NovSun1)=1,IF(AND(YEAR(NovSun1+3)=CalendarYear,MONTH(NovSun1+3)=11),NovSun1+3,""),IF(AND(YEAR(NovSun1+10)=CalendarYear,MONTH(NovSun1+10)=11),NovSun1+10,"")) -> 46336 | V36: =IF(DAY(NovSun1)=1,IF(AND(YEAR(NovSun1+4)=CalendarYear,MONTH(NovSun1+4)=11),NovSun1+4,""),IF(AND(YEAR(NovSun1+11)=CalendarYear,MONTH(NovSun1+11)=11),NovSun1+11,"")) -> 46337 | W36: =IF(DAY(NovSun1)=1,IF(AND(YEAR(NovSun1+5)=CalendarYear,MONTH(NovSun1+5)=11),NovSun1+5,""),IF(AND(YEAR(NovSun1+12)=CalendarYear,MONTH(NovSun1+12)=11),NovSun1+12,"")) -> 46338 | X36: =IF(DAY(NovSun1)=1,IF(AND(YEAR(NovSun1+6)=CalendarYear,MONTH(NovSun1+6)=11),NovSun1+6,""),IF(AND(YEAR(NovSun1+13)=CalendarYear,MONTH(NovSun1+13)=11),NovSun1+13,"")) -> 46339 | Y36: =IF(DAY(NovSun1)=1,IF(AND(YEAR(NovSun1+7)=CalendarYear,MONTH(NovSun1+7)=11),NovSun1+7,""),IF(AND(YEAR(NovSun1+14)=CalendarYear,MONTH(NovSun1+14)=11),NovSun1+14,"")) -> 46340 | Z36: CW49 | AA36: =IF(DAY(DecSun1)=1,IF(AND(YEAR(DecSun1+1)=CalendarYear,MONTH(DecSun1+1)=12),DecSun1+1,""),IF(AND(YEAR(DecSun1+8)=CalendarYear,MONTH(DecSun1+8)=12),DecSun1+8,"")) -> 46362 | AB36: =IF(DAY(DecSun1)=1,IF(AND(YEAR(DecSun1+2)=CalendarYear,MONTH(DecSun1+2)=12),DecSun1+2,""),IF(AND(YEAR(DecSun1+9)=CalendarYear,MONTH(DecSun1+9)=12),DecSun1+9,"")) -> 46363 | AC36: =IF(DAY(DecSun1)=1,IF(AND(YEAR(DecSun1+3)=CalendarYear,MONTH(DecSun1+3)=12),DecSun1+3,""),IF(AND(YEAR(DecSun1+10)=CalendarYear,MONTH(DecSun1+10)=12),DecSun1+10,"")) -> 46364 | AD36: =IF(DAY(DecSun1)=1,IF(AND(YEAR(DecSun1+4)=CalendarYear,MONTH(DecSun1+4)=12),DecSun1+4,""),IF(AND(YEAR(DecSun1+11)=CalendarYear,MONTH(DecSun1+11)=12),DecSun1+11,"")) -> 46365 | AE36: =IF(DAY(DecSun1)=1,IF(AND(YEAR(DecSun1+5)=CalendarYear,MONTH(DecSun1+5)=12),DecSun1+5,""),IF(AND(YEAR(DecSun1+12)=CalendarYear,MONTH(DecSun1+12)=12),DecSun1+12,"")) -> 46366 | AF36: =IF(DAY(DecSun1)=1,IF(AND(YEAR(DecSun1+6)=CalendarYear,MONTH(DecSun1+6)=12),DecSun1+6,""),IF(AND(YEAR(DecSun1+13)=CalendarYear,MONTH(DecSun1+13)=12),DecSun1+13,"")) -> 46367 | AG36: =IF(DAY(DecSun1)=1,IF(AND(YEAR(DecSun1+7)=CalendarYear,MONTH(DecSun1+7)=12),DecSun1+7,""),IF(AND(YEAR(DecSun1+14)=CalendarYear,MONTH(DecSun1+14)=12),DecSun1+14,"")) -> 46368
B37: CW38 | C37: =IF(DAY(SepSun1)=1,IF(AND(YEAR(SepSun1+8)=CalendarYear,MONTH(SepSun1+8)=9),SepSun1+8,""),IF(AND(YEAR(SepSun1+15)=CalendarYear,MONTH(SepSun1+15)=9),SepSun1+15,"")) -> 46278 | D37: =IF(DAY(SepSun1)=1,IF(AND(YEAR(SepSun1+9)=CalendarYear,MONTH(SepSun1+9)=9),SepSun1+9,""),IF(AND(YEAR(SepSun1+16)=CalendarYear,MONTH(SepSun1+16)=9),SepSun1+16,"")) -> 46279 | E37: =IF(DAY(SepSun1)=1,IF(AND(YEAR(SepSun1+10)=CalendarYear,MONTH(SepSun1+10)=9),SepSun1+10,""),IF(AND(YEAR(SepSun1+17)=CalendarYear,MONTH(SepSun1+17)=9),SepSun1+17,"")) -> 46280 | F37: =IF(DAY(SepSun1)=1,IF(AND(YEAR(SepSun1+11)=CalendarYear,MONTH(SepSun1+11)=9),SepSun1+11,""),IF(AND(YEAR(SepSun1+18)=CalendarYear,MONTH(SepSun1+18)=9),SepSun1+18,"")) -> 46281 | G37: =IF(DAY(SepSun1)=1,IF(AND(YEAR(SepSun1+12)=CalendarYear,MONTH(SepSun1+12)=9),SepSun1+12,""),IF(AND(YEAR(SepSun1+19)=CalendarYear,MONTH(SepSun1+19)=9),SepSun1+19,"")) -> 46282 | H37: =IF(DAY(SepSun1)=1,IF(AND(YEAR(SepSun1+13)=CalendarYear,MONTH(SepSun1+13)=9),SepSun1+13,""),IF(AND(YEAR(SepSun1+20)=CalendarYear,MONTH(SepSun1+20)=9),SepSun1+20,"")) -> 46283 | I37: =IF(DAY(SepSun1)=1,IF(AND(YEAR(SepSun1+14)=CalendarYear,MONTH(SepSun1+14)=9),SepSun1+14,""),IF(AND(YEAR(SepSun1+21)=CalendarYear,MONTH(SepSun1+21)=9),SepSun1+21,"")) -> 46284 | J37: CW42 | K37: =IF(DAY(OctSun1)=1,IF(AND(YEAR(OctSun1+8)=CalendarYear,MONTH(OctSun1+8)=10),OctSun1+8,""),IF(AND(YEAR(OctSun1+15)=CalendarYear,MONTH(OctSun1+15)=10),OctSun1+15,"")) -> 46306 | L37: =IF(DAY(OctSun1)=1,IF(AND(YEAR(OctSun1+9)=CalendarYear,MONTH(OctSun1+9)=10),OctSun1+9,""),IF(AND(YEAR(OctSun1+16)=CalendarYear,MONTH(OctSun1+16)=10),OctSun1+16,"")) -> 46307 | M37: =IF(DAY(OctSun1)=1,IF(AND(YEAR(OctSun1+10)=CalendarYear,MONTH(OctSun1+10)=10),OctSun1+10,""),IF(AND(YEAR(OctSun1+17)=CalendarYear,MONTH(OctSun1+17)=10),OctSun1+17,"")) -> 46308 | N37: =IF(DAY(OctSun1)=1,IF(AND(YEAR(OctSun1+11)=CalendarYear,MONTH(OctSun1+11)=10),OctSun1+11,""),IF(AND(YEAR(OctSun1+18)=CalendarYear,MONTH(OctSun1+18)=10),OctSun1+18,"")) -> 46309 | O37: =IF(DAY(OctSun1)=1,IF(AND(YEAR(OctSun1+12)=CalendarYear,MONTH(OctSun1+12)=10),OctSun1+12,""),IF(AND(YEAR(OctSun1+19)=CalendarYear,MONTH(OctSun1+19)=10),OctSun1+19,"")) -> 46310 | P37: =IF(DAY(OctSun1)=1,IF(AND(YEAR(OctSun1+13)=CalendarYear,MONTH(OctSun1+13)=10),OctSun1+13,""),IF(AND(YEAR(OctSun1+20)=CalendarYear,MONTH(OctSun1+20)=10),OctSun1+20,"")) -> 46311 | Q37: =IF(DAY(OctSun1)=1,IF(AND(YEAR(OctSun1+14)=CalendarYear,MONTH(OctSun1+14)=10),OctSun1+14,""),IF(AND(YEAR(OctSun1+21)=CalendarYear,MONTH(OctSun1+21)=10),OctSun1+21,"")) -> 46312 | R37: CW46 | S37: =IF(DAY(NovSun1)=1,IF(AND(YEAR(NovSun1+8)=CalendarYear,MONTH(NovSun1+8)=11),NovSun1+8,""),IF(AND(YEAR(NovSun1+15)=CalendarYear,MONTH(NovSun1+15)=11),NovSun1+15,"")) -> 46341 | T37: =IF(DAY(NovSun1)=1,IF(AND(YEAR(NovSun1+9)=CalendarYear,MONTH(NovSun1+9)=11),NovSun1+9,""),IF(AND(YEAR(NovSun1+16)=CalendarYear,MONTH(NovSun1+16)=11),NovSun1+16,"")) -> 46342 | U37: =IF(DAY(NovSun1)=1,IF(AND(YEAR(NovSun1+10)=CalendarYear,MONTH(NovSun1+10)=11),NovSun1+10,""),IF(AND(YEAR(NovSun1+17)=CalendarYear,MONTH(NovSun1+17)=11),NovSun1+17,"")) -> 46343 | V37: =IF(DAY(NovSun1)=1,IF(AND(YEAR(NovSun1+11)=CalendarYear,MONTH(NovSun1+11)=11),NovSun1+11,""),IF(AND(YEAR(NovSun1+18)=CalendarYear,MONTH(NovSun1+18)=11),NovSun1+18,"")) -> 46344 | W37: =IF(DAY(NovSun1)=1,IF(AND(YEAR(NovSun1+12)=CalendarYear,MONTH(NovSun1+12)=11),NovSun1+12,""),IF(AND(YEAR(NovSun1+19)=CalendarYear,MONTH(NovSun1+19)=11),NovSun1+19,"")) -> 46345 | X37: =IF(DAY(NovSun1)=1,IF(AND(YEAR(NovSun1+13)=CalendarYear,MONTH(NovSun1+13)=11),NovSun1+13,""),IF(AND(YEAR(NovSun1+20)=CalendarYear,MONTH(NovSun1+20)=11),NovSun1+20,"")) -> 46346 | Y37: =IF(DAY(NovSun1)=1,IF(AND(YEAR(NovSun1+14)=CalendarYear,MONTH(NovSun1+14)=11),NovSun1+14,""),IF(AND(YEAR(NovSun1+21)=CalendarYear,MONTH(NovSun1+21)=11),NovSun1+21,"")) -> 46347 | Z37: CW50 | AA37: =IF(DAY(DecSun1)=1,IF(AND(YEAR(DecSun1+8)=CalendarYear,MONTH(DecSun1+8)=12),DecSun1+8,""),IF(AND(YEAR(DecSun1+15)=CalendarYear,MONTH(DecSun1+15)=12),DecSun1+15,"")) -> 46369 | AB37: =IF(DAY(DecSun1)=1,IF(AND(YEAR(DecSun1+9)=CalendarYear,MONTH(DecSun1+9)=12),DecSun1+9,""),IF(AND(YEAR(DecSun1+16)=CalendarYear,MONTH(DecSun1+16)=12),DecSun1+16,"")) -> 46370 | AC37: =IF(DAY(DecSun1)=1,IF(AND(YEAR(DecSun1+10)=CalendarYear,MONTH(DecSun1+10)=12),DecSun1+10,""),IF(AND(YEAR(DecSun1+17)=CalendarYear,MONTH(DecSun1+17)=12),DecSun1+17,"")) -> 46371 | AD37: =IF(DAY(DecSun1)=1,IF(AND(YEAR(DecSun1+11)=CalendarYear,MONTH(DecSun1+11)=12),DecSun1+11,""),IF(AND(YEAR(DecSun1+18)=CalendarYear,MONTH(DecSun1+18)=12),DecSun1+18,"")) -> 46372 | AE37: =IF(DAY(DecSun1)=1,IF(AND(YEAR(DecSun1+12)=CalendarYear,MONTH(DecSun1+12)=12),DecSun1+12,""),IF(AND(YEAR(DecSun1+19)=CalendarYear,MONTH(DecSun1+19)=12),DecSun1+19,"")) -> 46373 | AF37: =IF(DAY(DecSun1)=1,IF(AND(YEAR(DecSun1+13)=CalendarYear,MONTH(DecSun1+13)=12),DecSun1+13,""),IF(AND(YEAR(DecSun1+20)=CalendarYear,MONTH(DecSun1+20)=12),DecSun1+20,"")) -> 46374 | AG37: =IF(DAY(DecSun1)=1,IF(AND(YEAR(DecSun1+14)=CalendarYear,MONTH(DecSun1+14)=12),DecSun1+14,""),IF(AND(YEAR(DecSun1+21)=CalendarYear,MONTH(DecSun1+21)=12),DecSun1+21,"")) -> 46375
B38: CW39 | C38: =IF(DAY(SepSun1)=1,IF(AND(YEAR(SepSun1+15)=CalendarYear,MONTH(SepSun1+15)=9),SepSun1+15,""),IF(AND(YEAR(SepSun1+22)=CalendarYear,MONTH(SepSun1+22)=9),SepSun1+22,"")) -> 46285 | D38: =IF(DAY(SepSun1)=1,IF(AND(YEAR(SepSun1+16)=CalendarYear,MONTH(SepSun1+16)=9),SepSun1+16,""),IF(AND(YEAR(SepSun1+23)=CalendarYear,MONTH(SepSun1+23)=9),SepSun1+23,"")) -> 46286 | E38: =IF(DAY(SepSun1)=1,IF(AND(YEAR(SepSun1+17)=CalendarYear,MONTH(SepSun1+17)=9),SepSun1+17,""),IF(AND(YEAR(SepSun1+24)=CalendarYear,MONTH(SepSun1+24)=9),SepSun1+24,"")) -> 46287 | F38: =IF(DAY(SepSun1)=1,IF(AND(YEAR(SepSun1+18)=CalendarYear,MONTH(SepSun1+18)=9),SepSun1+18,""),IF(AND(YEAR(SepSun1+25)=CalendarYear,MONTH(SepSun1+25)=9),SepSun1+25,"")) -> 46288 | G38: =IF(DAY(SepSun1)=1,IF(AND(YEAR(SepSun1+19)=CalendarYear,MONTH(SepSun1+19)=9),SepSun1+19,""),IF(AND(YEAR(SepSun1+26)=CalendarYear,MONTH(SepSun1+26)=9),SepSun1+26,"")) -> 46289 | H38: =IF(DAY(SepSun1)=1,IF(AND(YEAR(SepSun1+20)=CalendarYear,MONTH(SepSun1+20)=9),SepSun1+20,""),IF(AND(YEAR(SepSun1+27)=CalendarYear,MONTH(SepSun1+27)=9),SepSun1+27,"")) -> 46290 | I38: =IF(DAY(SepSun1)=1,IF(AND(YEAR(SepSun1+21)=CalendarYear,MONTH(SepSun1+21)=9),SepSun1+21,""),IF(AND(YEAR(SepSun1+28)=CalendarYear,MONTH(SepSun1+28)=9),SepSun1+28,"")) -> 46291 | J38: CW43 | K38: =IF(DAY(OctSun1)=1,IF(AND(YEAR(OctSun1+15)=CalendarYear,MONTH(OctSun1+15)=10),OctSun1+15,""),IF(AND(YEAR(OctSun1+22)=CalendarYear,MONTH(OctSun1+22)=10),OctSun1+22,"")) -> 46313 | L38: =IF(DAY(OctSun1)=1,IF(AND(YEAR(OctSun1+16)=CalendarYear,MONTH(OctSun1+16)=10),OctSun1+16,""),IF(AND(YEAR(OctSun1+23)=CalendarYear,MONTH(OctSun1+23)=10),OctSun1+23,"")) -> 46314 | M38: =IF(DAY(OctSun1)=1,IF(AND(YEAR(OctSun1+17)=CalendarYear,MONTH(OctSun1+17)=10),OctSun1+17,""),IF(AND(YEAR(OctSun1+24)=CalendarYear,MONTH(OctSun1+24)=10),OctSun1+24,"")) -> 46315 | N38: =IF(DAY(OctSun1)=1,IF(AND(YEAR(OctSun1+18)=CalendarYear,MONTH(OctSun1+18)=10),OctSun1+18,""),IF(AND(YEAR(OctSun1+25)=CalendarYear,MONTH(OctSun1+25)=10),OctSun1+25,"")) -> 46316 | O38: =IF(DAY(OctSun1)=1,IF(AND(YEAR(OctSun1+19)=CalendarYear,MONTH(OctSun1+19)=10),OctSun1+19,""),IF(AND(YEAR(OctSun1+26)=CalendarYear,MONTH(OctSun1+26)=10),OctSun1+26,"")) -> 46317 | P38: =IF(DAY(OctSun1)=1,IF(AND(YEAR(OctSun1+20)=CalendarYear,MONTH(OctSun1+20)=10),OctSun1+20,""),IF(AND(YEAR(OctSun1+27)=CalendarYear,MONTH(OctSun1+27)=10),OctSun1+27,"")) -> 46318 | Q38: =IF(DAY(OctSun1)=1,IF(AND(YEAR(OctSun1+21)=CalendarYear,MONTH(OctSun1+21)=10),OctSun1+21,""),IF(AND(YEAR(OctSun1+28)=CalendarYear,MONTH(OctSun1+28)=10),OctSun1+28,"")) -> 46319 | R38: CW47 | S38: =IF(DAY(NovSun1)=1,IF(AND(YEAR(NovSun1+15)=CalendarYear,MONTH(NovSun1+15)=11),NovSun1+15,""),IF(AND(YEAR(NovSun1+22)=CalendarYear,MONTH(NovSun1+22)=11),NovSun1+22,"")) -> 46348 | T38: =IF(DAY(NovSun1)=1,IF(AND(YEAR(NovSun1+16)=CalendarYear,MONTH(NovSun1+16)=11),NovSun1+16,""),IF(AND(YEAR(NovSun1+23)=CalendarYear,MONTH(NovSun1+23)=11),NovSun1+23,"")) -> 46349 | U38: =IF(DAY(NovSun1)=1,IF(AND(YEAR(NovSun1+17)=CalendarYear,MONTH(NovSun1+17)=11),NovSun1+17,""),IF(AND(YEAR(NovSun1+24)=CalendarYear,MONTH(NovSun1+24)=11),NovSun1+24,"")) -> 46350 | V38: =IF(DAY(NovSun1)=1,IF(AND(YEAR(NovSun1+18)=CalendarYear,MONTH(NovSun1+18)=11),NovSun1+18,""),IF(AND(YEAR(NovSun1+25)=CalendarYear,MONTH(NovSun1+25)=11),NovSun1+25,"")) -> 46351 | W38: =IF(DAY(NovSun1)=1,IF(AND(YEAR(NovSun1+19)=CalendarYear,MONTH(NovSun1+19)=11),NovSun1+19,""),IF(AND(YEAR(NovSun1+26)=CalendarYear,MONTH(NovSun1+26)=11),NovSun1+26,"")) -> 46352 | X38: =IF(DAY(NovSun1)=1,IF(AND(YEAR(NovSun1+20)=CalendarYear,MONTH(NovSun1+20)=11),NovSun1+20,""),IF(AND(YEAR(NovSun1+27)=CalendarYear,MONTH(NovSun1+27)=11),NovSun1+27,"")) -> 46353 | Y38: =IF(DAY(NovSun1)=1,IF(AND(YEAR(NovSun1+21)=CalendarYear,MONTH(NovSun1+21)=11),NovSun1+21,""),IF(AND(YEAR(NovSun1+28)=CalendarYear,MONTH(NovSun1+28)=11),NovSun1+28,"")) -> 46354 | Z38: CW51 | AA38: =IF(DAY(DecSun1)=1,IF(AND(YEAR(DecSun1+15)=CalendarYear,MONTH(DecSun1+15)=12),DecSun1+15,""),IF(AND(YEAR(DecSun1+22)=CalendarYear,MONTH(DecSun1+22)=12),DecSun1+22,"")) -> 46376 | AB38: =IF(DAY(DecSun1)=1,IF(AND(YEAR(DecSun1+16)=CalendarYear,MONTH(DecSun1+16)=12),DecSun1+16,""),IF(AND(YEAR(DecSun1+23)=CalendarYear,MONTH(DecSun1+23)=12),DecSun1+23,"")) -> 46377 | AC38: =IF(DAY(DecSun1)=1,IF(AND(YEAR(DecSun1+17)=CalendarYear,MONTH(DecSun1+17)=12),DecSun1+17,""),IF(AND(YEAR(DecSun1+24)=CalendarYear,MONTH(DecSun1+24)=12),DecSun1+24,"")) -> 46378 | AD38: =IF(DAY(DecSun1)=1,IF(AND(YEAR(DecSun1+18)=CalendarYear,MONTH(DecSun1+18)=12),DecSun1+18,""),IF(AND(YEAR(DecSun1+25)=CalendarYear,MONTH(DecSun1+25)=12),DecSun1+25,"")) -> 46379 | AE38: =IF(DAY(DecSun1)=1,IF(AND(YEAR(DecSun1+19)=CalendarYear,MONTH(DecSun1+19)=12),DecSun1+19,""),IF(AND(YEAR(DecSun1+26)=CalendarYear,MONTH(DecSun1+26)=12),DecSun1+26,"")) -> 46380 | AF38: =IF(DAY(DecSun1)=1,IF(AND(YEAR(DecSun1+20)=CalendarYear,MONTH(DecSun1+20)=12),DecSun1+20,""),IF(AND(YEAR(DecSun1+27)=CalendarYear,MONTH(DecSun1+27)=12),DecSun1+27,"")) -> 46381 | AG38: =IF(DAY(DecSun1)=1,IF(AND(YEAR(DecSun1+21)=CalendarYear,MONTH(DecSun1+21)=12),DecSun1+21,""),IF(AND(YEAR(DecSun1+28)=CalendarYear,MONTH(DecSun1+28)=12),DecSun1+28,"")) -> 46382
B39: CW40 | C39: =IF(DAY(SepSun1)=1,IF(AND(YEAR(SepSun1+22)=CalendarYear,MONTH(SepSun1+22)=9),SepSun1+22,""),IF(AND(YEAR(SepSun1+29)=CalendarYear,MONTH(SepSun1+29)=9),SepSun1+29,"")) -> 46292 | D39: =IF(DAY(SepSun1)=1,IF(AND(YEAR(SepSun1+23)=CalendarYear,MONTH(SepSun1+23)=9),SepSun1+23,""),IF(AND(YEAR(SepSun1+30)=CalendarYear,MONTH(SepSun1+30)=9),SepSun1+30,"")) -> 46293 | E39: =IF(DAY(SepSun1)=1,IF(AND(YEAR(SepSun1+24)=CalendarYear,MONTH(SepSun1+24)=9),SepSun1+24,""),IF(AND(YEAR(SepSun1+31)=CalendarYear,MONTH(SepSun1+31)=9),SepSun1+31,"")) -> 46294 | F39: =IF(DAY(SepSun1)=1,IF(AND(YEAR(SepSun1+25)=CalendarYear,MONTH(SepSun1+25)=9),SepSun1+25,""),IF(AND(YEAR(SepSun1+32)=CalendarYear,MONTH(SepSun1+32)=9),SepSun1+32,"")) -> 46295 | G39: =IF(DAY(SepSun1)=1,IF(AND(YEAR(SepSun1+26)=CalendarYear,MONTH(SepSun1+26)=9),SepSun1+26,""),IF(AND(YEAR(SepSun1+33)=CalendarYear,MONTH(SepSun1+33)=9),SepSun1+33,"")) | H39: =IF(DAY(SepSun1)=1,IF(AND(YEAR(SepSun1+27)=CalendarYear,MONTH(SepSun1+27)=9),SepSun1+27,""),IF(AND(YEAR(SepSun1+34)=CalendarYear,MONTH(SepSun1+34)=9),SepSun1+34,"")) | I39: =IF(DAY(SepSun1)=1,IF(AND(YEAR(SepSun1+28)=CalendarYear,MONTH(SepSun1+28)=9),SepSun1+28,""),IF(AND(YEAR(SepSun1+35)=CalendarYear,MONTH(SepSun1+35)=9),SepSun1+35,"")) | J39: CW44 | K39: =IF(DAY(OctSun1)=1,IF(AND(YEAR(OctSun1+22)=CalendarYear,MONTH(OctSun1+22)=10),OctSun1+22,""),IF(AND(YEAR(OctSun1+29)=CalendarYear,MONTH(OctSun1+29)=10),OctSun1+29,"")) -> 46320 | L39: =IF(DAY(OctSun1)=1,IF(AND(YEAR(OctSun1+23)=CalendarYear,MONTH(OctSun1+23)=10),OctSun1+23,""),IF(AND(YEAR(OctSun1+30)=CalendarYear,MONTH(OctSun1+30)=10),OctSun1+30,"")) -> 46321 | M39: =IF(DAY(OctSun1)=1,IF(AND(YEAR(OctSun1+24)=CalendarYear,MONTH(OctSun1+24)=10),OctSun1+24,""),IF(AND(YEAR(OctSun1+31)=CalendarYear,MONTH(OctSun1+31)=10),OctSun1+31,"")) -> 46322 | N39: =IF(DAY(OctSun1)=1,IF(AND(YEAR(OctSun1+25)=CalendarYear,MONTH(OctSun1+25)=10),OctSun1+25,""),IF(AND(YEAR(OctSun1+32)=CalendarYear,MONTH(OctSun1+32)=10),OctSun1+32,"")) -> 46323 | O39: =IF(DAY(OctSun1)=1,IF(AND(YEAR(OctSun1+26)=CalendarYear,MONTH(OctSun1+26)=10),OctSun1+26,""),IF(AND(YEAR(OctSun1+33)=CalendarYear,MONTH(OctSun1+33)=10),OctSun1+33,"")) -> 46324 | P39: =IF(DAY(OctSun1)=1,IF(AND(YEAR(OctSun1+27)=CalendarYear,MONTH(OctSun1+27)=10),OctSun1+27,""),IF(AND(YEAR(OctSun1+34)=CalendarYear,MONTH(OctSun1+34)=10),OctSun1+34,"")) -> 46325 | Q39: =IF(DAY(OctSun1)=1,IF(AND(YEAR(OctSun1+28)=CalendarYear,MONTH(OctSun1+28)=10),OctSun1+28,""),IF(AND(YEAR(OctSun1+35)=CalendarYear,MONTH(OctSun1+35)=10),OctSun1+35,"")) -> 46326 | R39: CW48 | S39: =IF(DAY(NovSun1)=1,IF(AND(YEAR(NovSun1+22)=CalendarYear,MONTH(NovSun1+22)=11),NovSun1+22,""),IF(AND(YEAR(NovSun1+29)=CalendarYear,MONTH(NovSun1+29)=11),NovSun1+29,"")) -> 46355 | T39: =IF(DAY(NovSun1)=1,IF(AND(YEAR(NovSun1+23)=CalendarYear,MONTH(NovSun1+23)=11),NovSun1+23,""),IF(AND(YEAR(NovSun1+30)=CalendarYear,MONTH(NovSun1+30)=11),NovSun1+30,"")) -> 46356 | U39: =IF(DAY(NovSun1)=1,IF(AND(YEAR(NovSun1+24)=CalendarYear,MONTH(NovSun1+24)=11),NovSun1+24,""),IF(AND(YEAR(NovSun1+31)=CalendarYear,MONTH(NovSun1+31)=11),NovSun1+31,"")) | V39: =IF(DAY(NovSun1)=1,IF(AND(YEAR(NovSun1+25)=CalendarYear,MONTH(NovSun1+25)=11),NovSun1+25,""),IF(AND(YEAR(NovSun1+32)=CalendarYear,MONTH(NovSun1+32)=11),NovSun1+32,"")) | W39: =IF(DAY(NovSun1)=1,IF(AND(YEAR(NovSun1+26)=CalendarYear,MONTH(NovSun1+26)=11),NovSun1+26,""),IF(AND(YEAR(NovSun1+33)=CalendarYear,MONTH(NovSun1+33)=11),NovSun1+33,"")) | X39: =IF(DAY(NovSun1)=1,IF(AND(YEAR(NovSun1+27)=CalendarYear,MONTH(NovSun1+27)=11),NovSun1+27,""),IF(AND(YEAR(NovSun1+34)=CalendarYear,MONTH(NovSun1+34)=11),NovSun1+34,"")) | Y39: =IF(DAY(NovSun1)=1,IF(AND(YEAR(NovSun1+28)=CalendarYear,MONTH(NovSun1+28)=11),NovSun1+28,""),IF(AND(YEAR(NovSun1+35)=CalendarYear,MONTH(NovSun1+35)=11),NovSun1+35,"")) | Z39: CW52 | AA39: =IF(DAY(DecSun1)=1,IF(AND(YEAR(DecSun1+22)=CalendarYear,MONTH(DecSun1+22)=12),DecSun1+22,""),IF(AND(YEAR(DecSun1+29)=CalendarYear,MONTH(DecSun1+29)=12),DecSun1+29,"")) -> 46383 | AB39: =IF(DAY(DecSun1)=1,IF(AND(YEAR(DecSun1+23)=CalendarYear,MONTH(DecSun1+23)=12),DecSun1+23,""),IF(AND(YEAR(DecSun1+30)=CalendarYear,MONTH(DecSun1+30)=12),DecSun1+30,"")) -> 46384 | AC39: =IF(DAY(DecSun1)=1,IF(AND(YEAR(DecSun1+24)=CalendarYear,MONTH(DecSun1+24)=12),DecSun1+24,""),IF(AND(YEAR(DecSun1+31)=CalendarYear,MONTH(DecSun1+31)=12),DecSun1+31,"")) -> 46385 | AD39: =IF(DAY(DecSun1)=1,IF(AND(YEAR(DecSun1+25)=CalendarYear,MONTH(DecSun1+25)=12),DecSun1+25,""),IF(AND(YEAR(DecSun1+32)=CalendarYear,MONTH(DecSun1+32)=12),DecSun1+32,"")) -> 46386 | AE39: =IF(DAY(DecSun1)=1,IF(AND(YEAR(DecSun1+26)=CalendarYear,MONTH(DecSun1+26)=12),DecSun1+26,""),IF(AND(YEAR(DecSun1+33)=CalendarYear,MONTH(DecSun1+33)=12),DecSun1+33,"")) -> 46387 | AF39: =IF(DAY(DecSun1)=1,IF(AND(YEAR(DecSun1+27)=CalendarYear,MONTH(DecSun1+27)=12),DecSun1+27,""),IF(AND(YEAR(DecSun1+34)=CalendarYear,MONTH(DecSun1+34)=12),DecSun1+34,"")) | AG39: =IF(DAY(DecSun1)=1,IF(AND(YEAR(DecSun1+28)=CalendarYear,MONTH(DecSun1+28)=12),DecSun1+28,""),IF(AND(YEAR(DecSun1+35)=CalendarYear,MONTH(DecSun1+35)=12),DecSun1+35,""))
C40: =IF(DAY(SepSun1)=1,IF(AND(YEAR(SepSun1+29)=CalendarYear,MONTH(SepSun1+29)=9),SepSun1+29,""),IF(AND(YEAR(SepSun1+36)=CalendarYear,MONTH(SepSun1+36)=9),SepSun1+36,"")) | D40: =IF(DAY(SepSun1)=1,IF(AND(YEAR(SepSun1+30)=CalendarYear,MONTH(SepSun1+30)=9),SepSun1+30,""),IF(AND(YEAR(SepSun1+37)=CalendarYear,MONTH(SepSun1+37)=9),SepSun1+37,"")) | E40: =IF(DAY(SepSun1)=1,IF(AND(YEAR(SepSun1+31)=CalendarYear,MONTH(SepSun1+31)=9),SepSun1+31,""),IF(AND(YEAR(SepSun1+38)=CalendarYear,MONTH(SepSun1+38)=9),SepSun1+38,"")) | F40: =IF(DAY(SepSun1)=1,IF(AND(YEAR(SepSun1+32)=CalendarYear,MONTH(SepSun1+32)=9),SepSun1+32,""),IF(AND(YEAR(SepSun1+39)=CalendarYear,MONTH(SepSun1+39)=9),SepSun1+39,"")) | G40: =IF(DAY(SepSun1)=1,IF(AND(YEAR(SepSun1+33)=CalendarYear,MONTH(SepSun1+33)=9),SepSun1+33,""),IF(AND(YEAR(SepSun1+40)=CalendarYear,MONTH(SepSun1+40)=9),SepSun1+40,"")) | H40: =IF(DAY(SepSun1)=1,IF(AND(YEAR(SepSun1+34)=CalendarYear,MONTH(SepSun1+34)=9),SepSun1+34,""),IF(AND(YEAR(SepSun1+41)=CalendarYear,MONTH(SepSun1+41)=9),SepSun1+41,"")) | I40: =IF(DAY(SepSun1)=1,IF(AND(YEAR(SepSun1+35)=CalendarYear,MONTH(SepSun1+35)=9),SepSun1+35,""),IF(AND(YEAR(SepSun1+42)=CalendarYear,MONTH(SepSun1+42)=9),SepSun1+42,"")) | K40: =IF(DAY(OctSun1)=1,IF(AND(YEAR(OctSun1+29)=CalendarYear,MONTH(OctSun1+29)=10),OctSun1+29,""),IF(AND(YEAR(OctSun1+36)=CalendarYear,MONTH(OctSun1+36)=10),OctSun1+36,"")) | L40: =IF(DAY(OctSun1)=1,IF(AND(YEAR(OctSun1+30)=CalendarYear,MONTH(OctSun1+30)=10),OctSun1+30,""),IF(AND(YEAR(OctSun1+37)=CalendarYear,MONTH(OctSun1+37)=10),OctSun1+37,"")) | M40: =IF(DAY(OctSun1)=1,IF(AND(YEAR(OctSun1+31)=CalendarYear,MONTH(OctSun1+31)=10),OctSun1+31,""),IF(AND(YEAR(OctSun1+38)=CalendarYear,MONTH(OctSun1+38)=10),OctSun1+38,"")) | N40: =IF(DAY(OctSun1)=1,IF(AND(YEAR(OctSun1+32)=CalendarYear,MONTH(OctSun1+32)=10),OctSun1+32,""),IF(AND(YEAR(OctSun1+39)=CalendarYear,MONTH(OctSun1+39)=10),OctSun1+39,"")) | O40: =IF(DAY(OctSun1)=1,IF(AND(YEAR(OctSun1+33)=CalendarYear,MONTH(OctSun1+33)=10),OctSun1+33,""),IF(AND(YEAR(OctSun1+40)=CalendarYear,MONTH(OctSun1+40)=10),OctSun1+40,"")) | P40: =IF(DAY(OctSun1)=1,IF(AND(YEAR(OctSun1+34)=CalendarYear,MONTH(OctSun1+34)=10),OctSun1+34,""),IF(AND(YEAR(OctSun1+41)=CalendarYear,MONTH(OctSun1+41)=10),OctSun1+41,"")) | Q40: =IF(DAY(OctSun1)=1,IF(AND(YEAR(OctSun1+35)=CalendarYear,MONTH(OctSun1+35)=10),OctSun1+35,""),IF(AND(YEAR(OctSun1+42)=CalendarYear,MONTH(OctSun1+42)=10),OctSun1+42,"")) | S40: =IF(DAY(NovSun1)=1,IF(AND(YEAR(NovSun1+29)=CalendarYear,MONTH(NovSun1+29)=11),NovSun1+29,""),IF(AND(YEAR(NovSun1+36)=CalendarYear,MONTH(NovSun1+36)=11),NovSun1+36,"")) | T40: =IF(DAY(NovSun1)=1,IF(AND(YEAR(NovSun1+30)=CalendarYear,MONTH(NovSun1+30)=11),NovSun1+30,""),IF(AND(YEAR(NovSun1+37)=CalendarYear,MONTH(NovSun1+37)=11),NovSun1+37,"")) | U40: =IF(DAY(NovSun1)=1,IF(AND(YEAR(NovSun1+31)=CalendarYear,MONTH(NovSun1+31)=11),NovSun1+31,""),IF(AND(YEAR(NovSun1+38)=CalendarYear,MONTH(NovSun1+38)=11),NovSun1+38,"")) | V40: =IF(DAY(NovSun1)=1,IF(AND(YEAR(NovSun1+32)=CalendarYear,MONTH(NovSun1+32)=11),NovSun1+32,""),IF(AND(YEAR(NovSun1+39)=CalendarYear,MONTH(NovSun1+39)=11),NovSun1+39,"")) | W40: =IF(DAY(NovSun1)=1,IF(AND(YEAR(NovSun1+33)=CalendarYear,MONTH(NovSun1+33)=11),NovSun1+33,""),IF(AND(YEAR(NovSun1+40)=CalendarYear,MONTH(NovSun1+40)=11),NovSun1+40,"")) | X40: =IF(DAY(NovSun1)=1,IF(AND(YEAR(NovSun1+34)=CalendarYear,MONTH(NovSun1+34)=11),NovSun1+34,""),IF(AND(YEAR(NovSun1+41)=CalendarYear,MONTH(NovSun1+41)=11),NovSun1+41,"")) | Y40: =IF(DAY(NovSun1)=1,IF(AND(YEAR(NovSun1+35)=CalendarYear,MONTH(NovSun1+35)=11),NovSun1+35,""),IF(AND(YEAR(NovSun1+42)=CalendarYear,MONTH(NovSun1+42)=11),NovSun1+42,"")) | AA40: =IF(DAY(DecSun1)=1,IF(AND(YEAR(DecSun1+29)=CalendarYear,MONTH(DecSun1+29)=12),DecSun1+29,""),IF(AND(YEAR(DecSun1+36)=CalendarYear,MONTH(DecSun1+36)=12),DecSun1+36,"")) | AB40: =IF(DAY(DecSun1)=1,IF(AND(YEAR(DecSun1+30)=CalendarYear,MONTH(DecSun1+30)=12),DecSun1+30,""),IF(AND(YEAR(DecSun1+37)=CalendarYear,MONTH(DecSun1+37)=12),DecSun1+37,"")) | AC40: =IF(DAY(DecSun1)=1,IF(AND(YEAR(DecSun1+31)=CalendarYear,MONTH(DecSun1+31)=12),DecSun1+31,""),IF(AND(YEAR(DecSun1+38)=CalendarYear,MONTH(DecSun1+38)=12),DecSun1+38,"")) | AD40: =IF(DAY(DecSun1)=1,IF(AND(YEAR(DecSun1+32)=CalendarYear,MONTH(DecSun1+32)=12),DecSun1+32,""),IF(AND(YEAR(DecSun1+39)=CalendarYear,MONTH(DecSun1+39)=12),DecSun1+39,"")) | AE40: =IF(DAY(DecSun1)=1,IF(AND(YEAR(DecSun1+33)=CalendarYear,MONTH(DecSun1+33)=12),DecSun1+33,""),IF(AND(YEAR(DecSun1+40)=CalendarYear,MONTH(DecSun1+40)=12),DecSun1+40,"")) | AF40: =IF(DAY(DecSun1)=1,IF(AND(YEAR(DecSun1+34)=CalendarYear,MONTH(DecSun1+34)=12),DecSun1+34,""),IF(AND(YEAR(DecSun1+41)=CalendarYear,MONTH(DecSun1+41)=12),DecSun1+41,"")) | AG40: =IF(DAY(DecSun1)=1,IF(AND(YEAR(DecSun1+35)=CalendarYear,MONTH(DecSun1+35)=12),DecSun1+35,""),IF(AND(YEAR(DecSun1+42)=CalendarYear,MONTH(DecSun1+42)=12),DecSun1+42,""))
S41: * Armistice day(11th) | W41: *Big 5 Slava | AA41: * Year-end party(12th) | AE41: *Big 5 Slava

Sheet EX-RATE
B2: *Standard EX-rate for 2026
B3: 구 분 | D3: 2025 | E3: 2026 | F3: 비 고
B4: 주요 통화 | C4: KRW/USD | D4: 1330 | E4: 1350 | F4: 홀딩스 배포 | G4: =E4/D4 -> 1.0150376 | H4: EUR/USD
C5: KRW/EUR | D5: 1420 | E5: 1600 | G5: =E5/D5 -> 1.1267606 | H5: =E4/E5 -> 0.84375
C6: KRW/CNY | D6: 185 | E6: 195 | G6: =E6/D6 -> 1.0540541
C7: MXN/USD | D7: 19 | E7: 19 | G7: =E7/D7 -> 1
C8: CNY/USD | D8: 7.2 | E8: 6.9 | G8: =E8/D8 -> 0.95833333
B9: 세르비아 | C9: KRW/RSD | D9: 12.5 | E9: 14 | F9: KSC 배포 | G9: =E9/D9 -> 1.12
C10: RSD/EUR | D10: 117 | E10: 117 | G10: =E10/D10 -> 1
C11: RSD/USD | D11: 106 | E11: 100 | G11: =E11/D11 -> 0.94339623
B12: 터키 | C12: KRW/TRY | D12: 38 | E12: 32 | G12: =E12/D12 -> 0.84210526
C13: TRY/USD | D13: 35 | E13: 43 | G13: =E13/D13 -> 1.2285714
C14: TRY/EUR | D14: 39 | E14: 51 | G14: =E14/D14 -> 1.3076923
B15: 폴란드 | C15: KRW/PLN | D15: 340 | E15: 385 | G15: =E15/D15 -> 1.1323529
C16: PLN/EUR | D16: 4.3 | E16: 4.2 | G16: =E16/D16 -> 0.97674419
C17: PLN/USD | D17: 4 | E17: 3.6 | G17: =E17/D17 -> 0.9

Sheet COMP
A1: 단위(M, KRW) | B1: 2025Y실적 | E1: 2026Y계획 | H1: 증감 | I1: 증감 | K1: 2025년 | N1: 2026년 | Q1: 증감요인
B2: 실적 | C2: 구성비 | D2: 매출대비 | E2: 계획 | F2: 구성비 | G2: 매출대비 | K2: 실적(E) | L2: 구성비 | M2: 계획비 | N2: 계획 | O2: 구성비 | P2: 전년대비
A3: Ⅰ. 매출액 | B3: =K3*KRWRSD24/1000000 -> 29329.399 | C3: =B3/$B$3 -> 1 | E3: =N3*KRWRSD25/1000000 -> 53814.241 | F3: =E3/$E$3 -> 1 | H3: =E3-B3 -> 24484.842 | I3: =E3/B3-1 -> 0.83482249 | K3: ='PL2026(RS)'!G6 -> 2.3463519e+09 | N3: ='PL2026(RS)'!V6 -> 3.8438744e+09
C4: =B4/$B$3 -> 0 | F4: =E4/$E$3 -> 0
C5: =B5/$B$3 -> 0 | F5: =E5/$E$3 -> 0
A6: Ⅱ. 매출원가 | B6: =K6*KRWRSD24/1000000 -> 34519.077 | C6: =B6/$B$3 -> 1.1769446 | E6: =N6*KRWRSD25/1000000 -> 53430.443 | F6: =E6/$E$3 -> 0.99286809 | H6: =E6-B6 -> 18911.366 | I6: =E6/B6-1 -> 0.54785259 | K6: ='PL2026(RS)'!G24 -> 2.7615262e+09 | N6: ='PL2026(RS)'!V24 -> 3.8164602e+09
A7: Ⅲ. 매출총이익 | B7: =K7*KRWRSD24/1000000 -> -5189.6778 | C7: =B7/$B$3 -> -0.17694457 | E7: =N7*KRWRSD25/1000000 -> 383.79841 | F7: =E7/$E$3 -> 0.0071319115 | H7: =E7-B7 -> 5573.4762 | I7: =E7/B7-1 -> -1.0739542 | K7: =K3-K6 -> -4.1517423e+08 | N7: =N3-N6 -> 27414172
A8: 제조원가 | B8: =K8*KRWRSD24/1000000 -> 34331.845 | C8: =B8/$B$3 -> 1.1705608 | E8: =N8*KRWRSD25/1000000 -> 53430.443 | F8: =E8/$E$3 -> 0.99286809 | H8: =E8-B8 -> 19098.598 | I8: =E8/B8-1 -> 0.55629394 | K8: ='PL2026(RS)'!G25 -> 2.7465476e+09 | N8: ='PL2026(RS)'!V25 -> 3.8164602e+09
A9: 상품원가 | B9: =K9*KRWRSD24/1000000 -> 186.03615 | C9: =B9/$B$3 -> 0.0063429922 | E9: =N9*KRWRSD25/1000000 -> 0 | F9: =E9/$E$3 -> 0 | H9: =E9-B9 -> -186.03615 | I9: =E9/B9-1 -> -1 | K9: ='PL2026(RS)'!G33 -> 14882892 | N9: ='PL2026(RS)'!V33 -> 0
A10: (이익률) | B10: =+IFERROR(B7/B3,) -> -0.17694457 | E10: =N10 -> 0.0071319115 | H10: =E10-B10 -> 0.18407648 | K10: =+IFERROR(K7/K3,) -> -0.17694457 | N10: =+IFERROR(N7/N3,) -> 0.0071319115
A11: Ⅴ.영업이익 | B11: =K11*KRWRSD24/1000000 -> -8429.8971 | E11: ='PL(KR)'!G22 -> -3991.0177 | H11: =E11-B11 -> 4438.8795 | I11: =E11/B11-1 -> -0.52656389 | K11: ='PL2026(RS)'!G86 -> -6.7439177e+08 | N11: ='PL2026(RS)'!V86 -> -2.8507269e+08
A12: (이익률) | B12: =+IFERROR(B11/B3,) -> -0.28742141 | E12: ='PL(KR)'!G23 -> -0.074162853 | H12: =E12-B12 -> 0.21325855 | I12: =E12/B12-1 -> -0.74197171 | K12: =+IFERROR(K11/K3,) -> -0.28742141 | N12: =+IFERROR(N11/N3,) -> -0.074162853
H13: =E13-B13 -> 0
A14: Ⅰ. 재료비 | B14: =K14*KRWRSD24/1000000 -> 17274.341 | C14: =B14/SUM($B$14:$B$16) -> 0.51097192 | D14: =B14/$B$3 -> 0.58897697 | E14: =N14*KRWRSD25/1000000 -> 33106.313 | F14: =E14/SUM($E$14:$E$16) -> 0.61961517 | G14: =E14/$E$3 -> 0.61519613 | H14: =E14-B14 -> 15831.972 | I14: =E14/B14-1 -> 0.91650227 | K14: ='MC2026(RS)'!G6 -> 1.3819472e+09 | N14: ='MC2026(RS)'!V6 -> 2.3647366e+09
A15: Ⅱ. 노무비 | B15: =K15*KRWRSD24/1000000 -> 10240.021 | C15: =B15/SUM($B$14:$B$16) -> 0.302898 | D15: =B15/$B$3 -> 0.34913845 | E15: =N15*KRWRSD25/1000000 -> 12953.036 | F15: =E15/SUM($E$14:$E$16) -> 0.24242802 | G15: =E15/$E$3 -> 0.24069904 | H15: =E15-B15 -> 2713.0154 | I15: =E15/B15-1 -> 0.26494237 | K15: ='MC2026(RS)'!G12 -> 8.1920168e+08 | N15: ='MC2026(RS)'!V12 -> 9.2521688e+08
A16: Ⅲ. 경비 | B16: =K16*KRWRSD24/1000000 -> 6292.4676 | C16: =B16/SUM($B$14:$B$16) -> 0.18613008 | D16: =B16/$B$3 -> 0.21454472 | E16: =N16*KRWRSD25/1000000 -> 7371.0936 | F16: =E16/SUM($E$14:$E$16) -> 0.13795681 | G16: =E16/$E$3 -> 0.13697292 | H16: =E16-B16 -> 1078.626 | I16: =E16/B16-1 -> 0.17141542 | K16: ='MC2026(RS)'!G15 -> 5.0339741e+08 | N16: ='MC2026(RS)'!V15 -> 5.2650669e+08

Sheet PL(KR)
A1: 구 분 | B1: CY2025 | G1: CY2026 | J1: 증감요인 (공통: RSD환율 12% 상승 USD환율 6% 인하) | L1: 2025년 | O1: 2025년 | R1: 2026년 | U1: 증감요인
B2: 계획 | C2: 구성비 | D2: 실적(E) | E2: 구성비 | F2: 계획비 | G2: 계획 | H2: 구성비 | I2: 전년대비 | L2: 계획 | M2: 구성비 | N2: 계획비 | O2: 실적(E) | P2: 구성비 | Q2: 계획비 | R2: 계획 | S2: 구성비 | T2: 전년대비
A3: Ⅰ. 매출액 | B3: =L3*KRWRSD24/1000000 -> 26968.027 | C3: =B3/$B$3 -> 1 | D3: =O3*KRWRSD24/1000000 -> 29329.399 | E3: =D3/$D$3 -> 1 | F3: =D3/B3 -> 1.0875619 | G3: =R3*KRWRSD25/1000000 -> 53814.241 | H3: =G3/$G$3 -> 1 | I3: =G3/D3 -> 1.8348225 | J3: 환율 영향 +28억(2025Y기준대비) | L3: 2.1574422e+09 | O3: ='PL2026(RS)'!G6 -> 2.3463519e+09 | R3: ='PL2026(RS)'!V6 -> 3.8438744e+09
A4: Ⅱ. 매출원가 | B4: =L4*KRWRSD24/1000000 -> 32722.097 | C4: =B4/$B$3 -> 1.2133664 | D4: =O4*KRWRSD24/1000000 -> 34519.077 | E4: =D4/$D$3 -> 1.1769446 | F4: =D4/B4 -> 1.0549164 | G4: =R4*KRWRSD25/1000000 -> 53430.443 | H4: =G4/$G$3 -> 0.99286809 | I4: =G4/D4 -> 1.5478526 | J4: 환율 영향 +49억(2025Y기준대비) | L4: 2.6177678e+09 | O4: ='PL2026(RS)'!G24 -> 2.7615262e+09 | R4: ='PL2026(RS)'!V24 -> 3.8164602e+09
A5: Ⅲ. 매출총이익 | B5: =L5*KRWRSD24/1000000 -> -5754.0698 | C5: =B5/$B$3 -> -0.21336636 | D5: =O5*KRWRSD24/1000000 -> -5189.6778 | E5: =D5/$D$3 -> -0.17694457 | F5: =D5/B5 -> 0.90191429 | G5: =R5*KRWRSD25/1000000 -> 383.79841 | H5: =G5/$G$3 -> 0.0071319115 | I5: =G5/D5 -> -0.073954188 | L5: -4.6032559e+08 | O5: =O3-O4 -> -4.1517423e+08 | R5: =R3-R4 -> 27414172
A6: 제조원가 | B6: =L6*KRWRSD24/1000000 -> 32352.401 | C6: =B6/$B$3 -> 1.1996577 | D6: =O6*KRWRSD24/1000000 -> 34331.845 | E6: =D6/$D$3 -> 1.1705608 | F6: =D6/B6 -> 1.0611838 | G6: =R6*KRWRSD25/1000000 -> 53430.443 | H6: =G6/$G$3 -> 0.99286809 | I6: =G6/D6 -> 1.5562939 | L6: 2.5881921e+09 | O6: ='PL2026(RS)'!G25 -> 2.7465476e+09 | R6: ='PL2026(RS)'!V25 -> 3.8164602e+09
A7: 상품원가 | B7: =L7*KRWRSD24/1000000 -> 369.69565 | C7: =B7/$B$3 -> 0.013708665 | D7: =O7*KRWRSD24/1000000 -> 186.03615 | E7: =D7/$D$3 -> 0.0063429922 | F7: =D7/B7 -> 0.50321434 | G7: =R7*KRWRSD25/1000000 -> 0 | H7: =G7/$G$3 -> 0 | I7: =G7/D7 -> 0 | L7: 29575652 | O7: ='PL2026(RS)'!G33 -> 14882892 | R7: ='PL2026(RS)'!V33 -> 0
A8: (이익률) | B8: =B5/B3 -> -0.21336636 | D8: =D5/D3 -> -0.17694457 | G8: =G5/G3 -> 0.0071319115 | I8: =G8/D8 -> -0.040305909 | L8: =L5/L3 -> -0.21336636 | O8: =+IFERROR(O5/O3,) -> -0.17694457 | R8: =+IFERROR(R5/R3,) -> 0.0071319115
A9: Ⅳ.판매관리비 | B9: =L9*KRWRSD24/1000000 -> 2565.9541 | C9: =B9/$B$3 -> 0.095148008 | D9: =O9*KRWRSD24/1000000 -> 3240.2193 | E9: =D9/$D$3 -> 0.11047684 | F9: =D9/B9 -> 1.2627737 | G9: =R9*KRWRSD25/1000000 -> 4374.8161 | H9: =G9/$G$3 -> 0.081294765 | I9: =G9/D9 -> 1.3501605 | J9: 환율영향 + 4억 | L9: 2.0527633e+08 | O9: ='PL2026(RS)'!G45 -> 2.5921754e+08 | R9: ='PL2026(RS)'!V45 -> 3.1248686e+08
A10: 급여 | B10: =L10*KRWRSD24/1000000 -> 835.44415 | C10: =B10/$B$3 -> 0.030979061 | D10: =O10*KRWRSD24/1000000 -> 903.29593 | E10: =D10/$D$3 -> 0.03079831 | F10: =D10/B10 -> 1.0812164 | G10: =R10*KRWRSD25/1000000 -> 1097.4989 | H10: =G10/$G$3 -> 0.020394209 | I10: =G10/D10 -> 1.2149937 | L10: 66835532 | O10: ='PL2026(RS)'!G46 -> 72263674 | R10: ='PL2026(RS)'!V46 -> 78392777
A11: 동력비 | B11: =L11*KRWRSD24/1000000 -> 38.466315 | C11: =B11/$B$3 -> 0.0014263674 | D11: =O11*KRWRSD24/1000000 -> 34.859425 | E11: =D11/$D$3 -> 0.0011885489 | F11: =D11/B11 -> 0.9062325 | G11: =R11*KRWRSD25/1000000 -> 40.994684 | H11: =G11/$G$3 -> 0.00076178132 | I11: =G11/D11 -> 1.176 | L11: 3077305.2 | O11: ='PL2026(RS)'!G50 -> 2788754 | R11: ='PL2026(RS)'!V50 -> 2928191.7
A12: 여비교통비 | B12: =L12*KRWRSD24/1000000 -> 25.5 | C12: =B12/$B$3 -> 0.00094556416 | D12: =O12*KRWRSD24/1000000 -> 16.224757 | E12: =D12/$D$3 -> 0.0005531909 | F12: =D12/B12 -> 0.63626497 | G12: =R12*KRWRSD25/1000000 -> 41.16 | H12: =G12/$G$3 -> 0.0007648533 | I12: =G12/D12 -> 2.5368639 | L12: 2040000 | O12: ='PL2026(RS)'!G52 -> 1297980.5 | R12: ='PL2026(RS)'!V52 -> 2940000
A13: 수도광열비 | B13: =L13*KRWRSD24/1000000 -> 24.474159 | C13: =B13/$B$3 -> 0.00090752499 | D13: =O13*KRWRSD24/1000000 -> 30.739469 | E13: =D13/$D$3 -> 0.001048077 | F13: =D13/B13 -> 1.255997 | G13: =R13*KRWRSD25/1000000 -> 36.149616 | H13: =G13/$G$3 -> 0.00067174813 | I13: =G13/D13 -> 1.176 | L13: 1957932.7 | O13: ='PL2026(RS)'!G55 -> 2459157.5 | R13: ='PL2026(RS)'!V55 -> 2582115.4
A14: 소모품비 | B14: =L14*KRWRSD24/1000000 -> 17 | C14: =B14/$B$3 -> 0.0006303761 | D14: =O14*KRWRSD24/1000000 -> 29.500108 | E14: =D14/$D$3 -> 0.0010058204 | F14: =D14/B14 -> 1.7353005 | G14: =R14*KRWRSD25/1000000 -> 26.712 | H14: =G14/$G$3 -> 0.00049637418 | I14: =G14/D14 -> 0.9054882 | L14: 1360000 | O14: ='PL2026(RS)'!G56 -> 2360008.7 | R14: ='PL2026(RS)'!V56 -> 1908000
A15: 접대비 | B15: =L15*KRWRSD24/1000000 -> 67.5 | C15: =B15/$B$3 -> 0.0025029639 | D15: =O15*KRWRSD24/1000000 -> 85.851462 | E15: =D15/$D$3 -> 0.002927147 | F15: =D15/B15 -> 1.2718735 | G15: =R15*KRWRSD25/1000000 -> 74.76 | H15: =G15/$G$3 -> 0.0013892233 | I15: =G15/D15 -> 0.87080637 | L15: 5400000 | O15: ='PL2026(RS)'!G57 -> 6868117 | R15: ='PL2026(RS)'!V57 -> 5340000
A16: 세금과공과 | B16: =L16*KRWRSD24/1000000 -> 149.5892 | C16: =B16/$B$3 -> 0.0055469092 | D16: =O16*KRWRSD24/1000000 -> 171.65713 | E16: =D16/$D$3 -> 0.0058527326 | F16: =D16/B16 -> 1.1475236 | G16: =R16*KRWRSD25/1000000 -> 559.86 | H16: =G16/$G$3 -> 0.010403566 | I16: =G16/D16 -> 3.2615016 | J16: IT 비용 추가 | L16: 11967136 | O16: ='PL2026(RS)'!G64 -> 13732570 | R16: ='PL2026(RS)'!V64 -> 39990000
A17: 임차료 | B17: =L17*KRWRSD24/1000000 -> 0 | C17: =B17/$B$3 -> 0 | D17: =O17*KRWRSD24/1000000 -> 22.42714 | E17: =D17/$D$3 -> 0.00076466416 | F17: =IFERROR(D17/B17,0) -> 0 | G17: =R17*KRWRSD25/1000000 -> 26.124 | H17: =G17/$G$3 -> 0.00048544771 | I17: =G17/D17 -> 1.1648386 | L17: 0 | O17: ='PL2026(RS)'!G65 -> 1794171.2 | R17: ='PL2026(RS)'!V65 -> 1866000
A18: 지급수수료 | B18: =L18*KRWRSD24/1000000 -> 875.47084 | C18: =B18/$B$3 -> 0.032463288 | D18: =O18*KRWRSD24/1000000 -> 1236.9623 | E18: =D18/$D$3 -> 0.042174825 | F18: =D18/B18 -> 1.4129109 | G18: =R18*KRWRSD25/1000000 -> 1533.6928 | H18: =G18/$G$3 -> 0.028499757 | I18: =G18/D18 -> 1.2398865 | J18: 로열티 포함 | L18: 70037667 | O18: ='PL2026(RS)'!G76+'PL2026(RS)'!G78 -> 98956982 | R18: ='PL2026(RS)'!V76+'PL2026(RS)'!V78 -> 1.0954949e+08
A19: 운반비 | B19: =L19*KRWRSD24/1000000 -> 367.61361 | C19: =B19/$B$3 -> 0.013631461 | D19: =O19*KRWRSD24/1000000 -> 506.34028 | E19: =D19/$D$3 -> 0.017263916 | F19: =D19/B19 -> 1.3773709 | G19: =R19*KRWRSD25/1000000 -> 638.52156 | H19: =G19/$G$3 -> 0.01186529 | I19: =G19/D19 -> 1.2610523 | J19: KCTR 운반비 추가 | L19: 29409088 | O19: ='PL2026(RS)'!G66 -> 40507222 | R19: ='PL2026(RS)'!V66 -> 45608683
A20: 감가상각비 | B20: =L20*KRWRSD24/1000000 -> 99.390693 | C20: =B20/$B$3 -> 0.0036855011 | D20: =O20*KRWRSD24/1000000 -> 98.037365 | E20: =D20/$D$3 -> 0.0033426312 | F20: =D20/B20 -> 0.98638375 | G20: =R20*KRWRSD25/1000000 -> 97.439 | H20: =G20/$G$3 -> 0.0018106545 | I20: =G20/D20 -> 0.99389656 | L20: 7951255.4 | O20: ='PL2026(RS)'!G59 -> 7842989.2 | R20: ='PL2026(RS)'!V59 -> 6959928.6
A21: 기타 | B21: =L21*KRWRSD24/1000000 -> 65.505113 | C21: =B21/$B$3 -> 0.0024289916 | D21: =O21*KRWRSD24/1000000 -> 104.32396 | E21: =D21/$D$3 -> 0.0035569757 | F21: =D21/B21 -> 1.5926079 | G21: =R21*KRWRSD25/1000000 -> 201.90352 | H21: =G21/$G$3 -> 0.0037518604 | I21: =G21/D21 -> 1.9353514 | L21: =L9-SUM(L10:L20) -> 5240409 | O21: =O9-SUM(O10:O20) -> 8345916.9 | R21: =R9-SUM(R10:R20) -> 14421680
A22: Ⅴ.영업이익 | B22: =L22*KRWRSD24/1000000 -> -8320.0239 | D22: =O22*KRWRSD24/1000000 -> -8429.8971 | G22: =R22*KRWRSD25/1000000 -> -3991.0177 | J22: 환율 영향 -25억(2025Y기준대비) | L22: =L5-L9 -> -6.6560191e+08 | O22: =O5-O9 -> -6.7439177e+08 | R22: =R5-R9 -> -2.8507269e+08
A23: (이익률) | B23: =B22/B3 -> -0.30851437 | D23: =O23 -> -0.28742141 | G23: =R23 -> -0.074162853 | L23: =L22/L3 -> -0.30851437 | O23: =O22/O3 -> -0.28742141 | R23: =R22/R3 -> -0.074162853
I26: 2025년 동일 환율 적용시 계획 | M26: 기준안
D34: 기준안 | E34: 64.6 | G34: 497
D35: 환율영향 | E35: -25 | G35: 525
D36: 주재원감원 | G36: =G34/G35 -> 0.94666667
D37: 작업자5%감원, 추가조정 | E37: -4.9
E38: =E34+E35+E36+E37 -> 34.7 | G38: =498 -> 498

Sheet MC(KR)
A1: 구 분 | B1: CY2025 | G1: CY2026 | J1: 증감요인 (공통 환율 12%상승) | L1: 2025년 | O1: 2025년 | R1: 2026년 | U1: 증감요인
B2: 계획 | C2: 구성비 | D2: 실적(E) | E2: 구성비 | F2: 계획비 | G2: 계획 | H2: 구성비 | I2: 전년대비 | L2: 계획 | M2: 구성비 | N2: 계획비 | O2: 실적(E) | P2: 구성비 | Q2: 계획비 | R2: 계획 | S2: 구성비 | T2: 전년대비
A3: Ⅰ. 재료비 | B3: =L3*KRWRSD24/1000000 -> 17073.931 | C3: =B3/$B$26 -> 0.52774847 | D3: =O3*KRWRSD24/1000000 -> 17274.341 | E3: =D3/$D$26 -> 0.51097192 | F3: =D3/B3 -> 1.0117378 | G3: =R3*KRWRSD25/1000000 -> 33106.313 | H3: =G3/$G$26 -> 0.61961517 | I3: =G3/D3 -> 1.9165023 | L3: 1.3659144e+09 | O3: ='MC2026(RS)'!G6 -> 1.3819472e+09 | R3: ='MC2026(RS)'!V6 -> 2.3647366e+09 | T3: =R3/O3 -> 1.7111627
A4: Ⅱ. 노무비 | B4: =L4*KRWRSD24/1000000 -> 8941.3112 | C4: =B4/$B$26 -> 0.27637241 | D4: =O4*KRWRSD24/1000000 -> 10240.021 | E4: =D4/$D$26 -> 0.302898 | F4: =D4/B4 -> 1.1452482 | G4: =R4*KRWRSD25/1000000 -> 12953.036 | H4: =G4/$G$26 -> 0.24242802 | I4: =G4/D4 -> 1.2649424 | J4: 인건비 상승(10%인상) | L4: 7.153049e+08 | O4: ='MC2026(RS)'!G12 -> 8.1920168e+08 | R4: ='MC2026(RS)'!V12 -> 9.2521688e+08 | T4: =R4/O4 -> 1.1294128 | V4: =G4+'PL(KR)'!G10 -> 14050.535 | W4: =V4-K4 -> 14050.535
A5: Ⅲ. 경비 | B5: =L5*KRWRSD24/1000000 -> 6337.1598 | C5: =B5/$B$26 -> 0.19587911 | D5: =O5*KRWRSD24/1000000 -> 6292.4676 | E5: =D5/$D$26 -> 0.18613008 | F5: =D5/B5 -> 0.99294761 | G5: =R5*KRWRSD25/1000000 -> 7371.0936 | H5: =G5/$G$26 -> 0.13795681 | I5: =G5/D5 -> 1.1714154 | L5: 5.0697278e+08 | O5: ='MC2026(RS)'!G15 -> 5.0339741e+08 | R5: ='MC2026(RS)'!V15 -> 5.2650669e+08 | T5: =R5/O5 -> 1.0459066 | V5: =V4/'PL(KR)'!G3 -> 0.26109325 | W5: =W4/K4 -> #DIV/0!
A6: 1. 전력비 | B6: =L6*KRWRSD24/1000000 -> 340.6084 | C6: =B6/$B$26 -> 0.010528072 | D6: =O6*KRWRSD24/1000000 -> 328.67458 | E6: =D6/$D$26 -> 0.0097221356 | F6: =D6/B6 -> 0.96496321 | G6: =R6*KRWRSD25/1000000 -> 386.5213 | H6: =G6/$G$26 -> 0.0072341026 | I6: =G6/D6 -> 1.176 | L6: 27248672 | O6: ='MC2026(RS)'!G16 -> 26293966 | R6: ='MC2026(RS)'!V16 -> 27608665 | T6: =R6/O6 -> 1.05
A7: 2. 가스수도비 | B7: =L7*KRWRSD24/1000000 -> 66.73912 | C7: =B7/$B$26 -> 0.0020628799 | D7: =O7*KRWRSD24/1000000 -> 78.438692 | E7: =D7/$D$26 -> 0.0023202026 | F7: =D7/B7 -> 1.1753031 | G7: =R7*KRWRSD25/1000000 -> 92.243902 | H7: =G7/$G$26 -> 0.0017264297 | I7: =G7/D7 -> 1.176 | L7: 5339129.6 | O7: ='MC2026(RS)'!G17 -> 6275095.4 | R7: ='MC2026(RS)'!V17 -> 6588850.2 | T7: =R7/O7 -> 1.05
A8: 3. 운임 | B8: =L8*KRWRSD24/1000000 -> 3.4309382 | C8: =B8/$B$26 -> 0.00010604895 | D8: =O8*KRWRSD24/1000000 -> 6.9203535 | E8: =D8/$D$26 -> 0.00020470283 | F8: =D8/B8 -> 2.017044 | G8: =R8*KRWRSD25/1000000 -> 8.1383357 | H8: =G8/$G$26 -> 0.00015231646 | I8: =G8/D8 -> 1.176 | L8: 274475.06 | O8: ='MC2026(RS)'!G18 -> 553628.28 | R8: ='MC2026(RS)'!V18 -> 581309.69 | T8: =R8/O8 -> 1.05
A9: 4. 감가상각비 | B9: =L9*KRWRSD24/1000000 -> 3690.6782 | C9: =B9/$B$26 -> 0.11407741 | D9: =O9*KRWRSD24/1000000 -> 3621.3819 | E9: =D9/$D$26 -> 0.10711983 | F9: =D9/B9 -> 0.98122396 | G9: =R9*KRWRSD25/1000000 -> 3650.353 | H9: =G9/$G$26 -> 0.068319721 | I9: =G9/D9 -> 1.008 | J9: 10%상각, 유형자산투자 9억포함 | L9: 2.9525426e+08 | O9: ='MC2026(RS)'!G19 -> 2.8971055e+08 | R9: ='MC2026(RS)'!V19 -> 2.607395e+08 | T9: =R9/O9 -> 0.9
A10: 6. 수선비 | B10: =L10*KRWRSD24/1000000 -> 151.07563 | C10: =B10/$B$26 -> 0.0046696881 | D10: =O10*KRWRSD24/1000000 -> 23.116386 | E10: =D10/$D$26 -> 0.0006837786 | F10: =D10/B10 -> 0.15301202 | G10: =R10*KRWRSD25/1000000 -> 189.5348 | H10: =G10/$G$26 -> 0.0035473185 | I10: =G10/D10 -> 8.1991535 | J10: 오버홀 실시 | L10: 12086050 | O10: ='MC2026(RS)'!G20 -> 1849310.9 | R10: ='MC2026(RS)'!V20 -> 13538200 | T10: =R10/O10 -> 7.3206728
A11: 7. 소모품비 | B11: =L11*KRWRSD24/1000000 -> 512.85053 | C11: =B11/$B$26 -> 0.015852008 | D11: =O11*KRWRSD24/1000000 -> 591.7821 | E11: =D11/$D$26 -> 0.017504809 | F11: =D11/B11 -> 1.1539075 | G11: =R11*KRWRSD25/1000000 -> 673.5325 | H11: =G11/$G$26 -> 0.012605782 | I11: =G11/D11 -> 1.1381427 | L11: 41028043 | O11: ='MC2026(RS)'!G21 -> 47342568 | R11: ='MC2026(RS)'!V21 -> 48109464 | T11: =R11/O11 -> 1.0161989
A12: 8. 소모재료(포장비 등) | B12: =L12*KRWRSD24/1000000 -> 1054.2178 | C12: =B12/$B$26 -> 0.032585456 | D12: =O12*KRWRSD24/1000000 -> 1146.469 | E12: =D12/$D$26 -> 0.03391235 | F12: =D12/B12 -> 1.0875068 | G12: =R12*KRWRSD25/1000000 -> 1918.3953 | H12: =G12/$G$26 -> 0.035904536 | I12: =G12/D12 -> 1.6733075 | J12: EV-V4 반영 | L12: 84337420 | O12: ='MC2026(RS)'!G22 -> 91717522 | R12: ='MC2026(RS)'!V22 -> 1.3702823e+08 | T12: =R12/O12 -> 1.4940246
A13: 9. 세금과공과 | B13: =L13*KRWRSD24/1000000 -> 0 | C13: =B13/$B$26 -> 0 | D13: =O13*KRWRSD24/1000000 -> 0 | E13: =D13/$D$26 -> 0 | G13: =R13*KRWRSD25/1000000 -> 0 | H13: =G13/$G$26 -> 0 | L13: 0 | O13: ='MC2026(RS)'!G23 -> 0 | R13: ='MC2026(RS)'!V23 -> 0
A14: 10. 지급임차료 | B14: =L14*KRWRSD24/1000000 -> 0 | C14: =B14/$B$26 -> 0 | D14: =O14*KRWRSD24/1000000 -> 85.64758 | E14: =D14/$D$26 -> 0.0025334402 | F14: =IFERROR(D14/B14,0) -> 0 | G14: =R14*KRWRSD25/1000000 -> 103.824 | H14: =G14/$G$26 -> 0.0019431619 | I14: =G14/D14 -> 1.2122234 | L14: 0 | O14: ='MC2026(RS)'!G24 -> 6851806.4 | R14: ='MC2026(RS)'!V24 -> 7416000 | T14: =R14/O14 -> 1.0823423
A15: 11. 보험료 | B15: =L15*KRWRSD24/1000000 -> 0 | C15: =B15/$B$26 -> 0 | D15: =O15*KRWRSD24/1000000 -> 0 | E15: =D15/$D$26 -> 0 | G15: =R15*KRWRSD25/1000000 -> 0 | H15: =G15/$G$26 -> 0 | L15: 0 | O15: ='MC2026(RS)'!G25 -> 0 | R15: ='MC2026(RS)'!V25 -> 0
A16: 12. 복리후생비 | B16: =L16*KRWRSD24/1000000 -> 93.5 | C16: =B16/$B$26 -> 0.0028900482 | D16: =O16*KRWRSD24/1000000 -> 1.9225 | E16: =D16/$D$26 -> 5.6867208e-05 | F16: =D16/B16 -> 0.020561497 | G16: =R16*KRWRSD25/1000000 -> 2.1532 | H16: =G16/$G$26 -> 4.0299123e-05 | I16: =G16/D16 -> 1.12 | L16: 7480000 | O16: ='MC2026(RS)'!G26 -> 153800 | R16: ='MC2026(RS)'!V26 -> 153800 | T16: =R16/O16 -> 1
A17: 13. 여비교통비 | B17: =L17*KRWRSD24/1000000 -> 71.5 | C17: =B17/$B$26 -> 0.0022100369 | D17: =O17*KRWRSD24/1000000 -> 62.380817 | E17: =D17/$D$26 -> 0.0018452135 | F17: =D17/B17 -> 0.87245898 | G17: =R17*KRWRSD25/1000000 -> 57.4 | H17: =G17/$G$26 -> 0.0010742939 | I17: =G17/D17 -> 0.92015467 | L17: 5720000 | O17: ='MC2026(RS)'!G27 -> 4990465.4 | R17: ='MC2026(RS)'!V27 -> 4100000 | T17: =R17/O17 -> 0.82156667
A18: 14. 통신비 | B18: =L18*KRWRSD24/1000000 -> 16.861898 | C18: =B18/$B$26 -> 0.00052119462 | D18: =O18*KRWRSD24/1000000 -> 18.375812 | E18: =D18/$D$26 -> 0.00054355327 | F18: =D18/B18 -> 1.0897832 | G18: =R18*KRWRSD25/1000000 -> 21.609955 | H18: =G18/$G$26 -> 0.00040445024 | I18: =G18/D18 -> 1.176 | L18: 1348951.8 | O18: ='MC2026(RS)'!G28 -> 1470065 | R18: ='MC2026(RS)'!V28 -> 1543568.2 | T18: =R18/O18 -> 1.05
A19: 15. 접대비 | B19: =L19*KRWRSD24/1000000 -> 0 | C19: =B19/$B$26 -> 0 | D19: =O19*KRWRSD24/1000000 -> 0 | E19: =D19/$D$26 -> 0 | G19: =R19*KRWRSD25/1000000 -> 0 | H19: =G19/$G$26 -> 0 | L19: 0 | O19: ='MC2026(RS)'!G29 -> 0 | R19: ='MC2026(RS)'!V29 -> 0
A20: 16. 특허권사용료 | B20: =L20*KRWRSD24/1000000 -> 0 | C20: =B20/$B$26 -> 0 | D20: =O20*KRWRSD24/1000000 -> 0 | E20: =D20/$D$26 -> 0 | G20: =R20*KRWRSD25/1000000 -> 0 | H20: =G20/$G$26 -> 0 | L20: 0 | O20: ='MC2026(RS)'!G30 -> 0 | R20: ='MC2026(RS)'!V30 -> 0
A21: 17. 교육훈련비 | B21: =L21*KRWRSD24/1000000 -> 53.94725 | C21: =B21/$B$26 -> 0.0016674883 | D21: =O21*KRWRSD24/1000000 -> 0 | E21: =D21/$D$26 -> 0 | F21: =D21/B21 -> 0 | G21: =R21*KRWRSD25/1000000 -> 11.06 | H21: =G21/$G$26 -> 0.0002069981 | L21: 4315780 | O21: ='MC2026(RS)'!G31 -> 0 | R21: ='MC2026(RS)'!V31 -> 790000 | T21: =R21/O21 -> #DIV/0!
A22: 18. 차량유지비 | B22: =L22*KRWRSD24/1000000 -> 0 | C22: =B22/$B$26 -> 0 | D22: =O22*KRWRSD24/1000000 -> 0 | E22: =D22/$D$26 -> 0 | G22: =R22*KRWRSD25/1000000 -> 0 | H22: =G22/$G$26 -> 0 | L22: 0 | O22: ='MC2026(RS)'!G32 -> 0 | R22: ='MC2026(RS)'!V32 -> 0
A23: 19. 외주가공비 | B23: =L23*KRWRSD24/1000000 -> 0 | C23: =B23/$B$26 -> 0 | D23: =O23*KRWRSD24/1000000 -> 0 | E23: =D23/$D$26 -> 0 | G23: =R23*KRWRSD25/1000000 -> 0 | H23: =G23/$G$26 -> 0 | L23: 0 | O23: ='MC2026(RS)'!G33 -> 0 | R23: ='MC2026(RS)'!V33 -> 0
A24: 20. 지급수수료 | B24: =L24*KRWRSD24/1000000 -> 281.75 | C24: =B24/$B$26 -> 0.0087087816 | D24: =O24*KRWRSD24/1000000 -> 327.35789 | E24: =D24/$D$26 -> 0.0096831883 | F24: =D24/B24 -> 1.1618736 | G24: =R24*KRWRSD25/1000000 -> 256.3274 | H24: =G24/$G$26 -> 0.0047974036 | I24: =G24/D24 -> 0.78301885 | L24: 22540000 | O24: ='MC2026(RS)'!G34 -> 26188631 | R24: ='MC2026(RS)'!V34 -> 18309100 | T24: =R24/O24 -> 0.69912397
A25: 21. 잡비 | B25: =L25*KRWRSD24/1000000 -> 0 | C25: =B25/$B$26 -> 0 | D25: =O25*KRWRSD24/1000000 -> 0 | E25: =D25/$D$26 -> 0 | G25: =R25*KRWRSD25/1000000 -> 0 | H25: =G25/$G$26 -> 0 | L25: 0 | O25: ='MC2026(RS)'!G35 -> 0 | R25: ='MC2026(RS)'!V35 -> 0 | T25: =R25/O25 -> #DIV/0!
A26: 합계 | B26: =SUM(B3:B5) -> 32352.401 | C26: =B26/$B$26 -> 1 | D26: =SUM(D3:D5) -> 33806.829 | E26: =D26/$D$26 -> 1 | F26: =D26/B26 -> 1.0449558 | G26: =SUM(G3:G5) -> 53430.443 | H26: =G26/$G$26 -> 1 | I26: =G26/D26 -> 1.580463 | L26: =L3+L4+L5 -> 2.5881921e+09 | O26: =O3+O4+O5 -> 2.7045463e+09 | R26: =R3+R4+R5 -> 3.8164602e+09 | T26: =R26/O26 -> 1.4111277

Sheet PL2026(KR)
A1: Plofit and Loss statement (단위: million KRW)
A2: MONTH
H3: Result of 2025 | W3: Plan of 2026
H4: CY2025 | I4: CY2025 | J4: CY2025 | K4: CY2025 | L4: CY2025 | M4: CY2025 | N4: CY2025 | O4: CY2025 | P4: CY2025 | Q4: CY2025 | R4: CY2025 | S4: CY2025 | W4: CY2026 | X4: CY2026 | Y4: CY2026 | Z4: CY2026 | AA4: CY2026 | AB4: CY2026 | AC4: CY2026 | AD4: CY2026 | AE4: CY2026 | AF4: CY2026 | AG4: CY2026 | AH4: CY2026
A5: 구분 | C5: 계정번호 | D5: FY 2022 | G5: CY 2025 | H5: 1 | I5: 2 | J5: 3 | K5: 4 | L5: 5 | M5: 6 | N5: 7 | O5: 8 | P5: 9 | Q5: 10 | R5: 11 | S5: 12 | V5: CY 2026 | W5: 1 | X5: 2 | Y5: 3 | Z5: 4 | AA5: 5 | AB5: 6 | AC5: 7 | AD5: 8 | AE5: 9 | AF5: 10 | AG5: 11 | AH5: 12
A6: Ⅰ. 매출액 | B6: Ⅰ. SALES | D6: 3.0247938e+09 | G6: ='PL2026(RS)'!G6*KRWRSD24 -> 2.9329399e+10 | H6: ='PL2026(RS)'!H6*KRWRSD24 -> 3.0660444e+09 | I6: ='PL2026(RS)'!I6*KRWRSD24 -> 2.2569905e+09 | J6: ='PL2026(RS)'!J6*KRWRSD24 -> 2.3963907e+09 | K6: ='PL2026(RS)'!K6*KRWRSD24 -> 1.4467532e+09 | L6: ='PL2026(RS)'!L6*KRWRSD24 -> 1.6514344e+09 | M6: ='PL2026(RS)'!M6*KRWRSD24 -> 1.7108575e+09 | N6: ='PL2026(RS)'!N6*KRWRSD24 -> 2.3596408e+09 | ... S6: ='PL2026(RS)'!S6*KRWRSD24 -> 3.212541e+09 | V6: ='PL2026(RS)'!V6*KRWRSD25 -> 5.3814241e+10 | W6: ='PL2026(RS)'!W6*KRWRSD25 -> 3366351576 | X6: ='PL2026(RS)'!X6*KRWRSD25 -> 3928693272 | Y6: ='PL2026(RS)'!Y6*KRWRSD25 -> 4607328320 | Z6: ='PL2026(RS)'!Z6*KRWRSD25 -> 4243021020 | AA6: ='PL2026(RS)'!AA6*KRWRSD25 -> 4397314320 | AB6: ='PL2026(RS)'!AB6*KRWRSD25 -> 4615524340 | AC6: ='PL2026(RS)'!AC6*KRWRSD25 -> 3552589180 | ... AH6: ='PL2026(RS)'!AH6*KRWRSD25 -> 6.100704e+09
A7: 1.제품매출 | B7: 1. Product | D7: 2.5401687e+09 | G7: ='PL2026(RS)'!G7*KRWRSD24 -> 2.8864866e+10 | H7: ='PL2026(RS)'!H7*KRWRSD24 -> 3.0096723e+09 | I7: ='PL2026(RS)'!I7*KRWRSD24 -> 2.1820755e+09 | J7: ='PL2026(RS)'!J7*KRWRSD24 -> 2.335705e+09 | K7: ='PL2026(RS)'!K7*KRWRSD24 -> 1.4457442e+09 | L7: ='PL2026(RS)'!L7*KRWRSD24 -> 1.5628302e+09 | M7: ='PL2026(RS)'!M7*KRWRSD24 -> 1.7081514e+09 | N7: ='PL2026(RS)'!N7*KRWRSD24 -> 2.3565901e+09 | ... S7: ='PL2026(RS)'!S7*KRWRSD24 -> 3.1695252e+09 | V7: ='PL2026(RS)'!V7*KRWRSD25 -> 5.3814241e+10 | W7: ='PL2026(RS)'!W7*KRWRSD25 -> 3366351576 | X7: ='PL2026(RS)'!X7*KRWRSD25 -> 3928693272 | Y7: ='PL2026(RS)'!Y7*KRWRSD25 -> 4607328320 | Z7: ='PL2026(RS)'!Z7*KRWRSD25 -> 4243021020 | AA7: ='PL2026(RS)'!AA7*KRWRSD25 -> 4397314320 | AB7: ='PL2026(RS)'!AB7*KRWRSD25 -> 4615524340 | AC7: ='PL2026(RS)'!AC7*KRWRSD25 -> 3552589180 | ... AH7: ='PL2026(RS)'!AH7*KRWRSD25 -> 6.100704e+09
B8: W/H sales (KSCP) | C8: 613000 | D8: 1.6360678e+09 | G8: ='PL2026(RS)'!G8*KRWRSD24 -> 3.231901e+09 | H8: ='PL2026(RS)'!H8*KRWRSD24 -> 769930299 | I8: ='PL2026(RS)'!I8*KRWRSD24 -> 4.9362879e+08 | J8: ='PL2026(RS)'!J8*KRWRSD24 -> 1.4193637e+08 | K8: ='PL2026(RS)'!K8*KRWRSD24 -> 2.082346e+08 | L8: ='PL2026(RS)'!L8*KRWRSD24 -> 3.5904985e+08 | M8: ='PL2026(RS)'!M8*KRWRSD24 -> 4.313292e+08 | N8: ='PL2026(RS)'!N8*KRWRSD24 -> 3.2791591e+08 | ... S8: ='PL2026(RS)'!S8*KRWRSD24 -> 38977524 | V8: ='PL2026(RS)'!V8*KRWRSD25 -> 8035973176 | W8: ='PL2026(RS)'!W8*KRWRSD25 -> 507688776 | X8: ='PL2026(RS)'!X8*KRWRSD25 -> 5.9358667e+08 | Y8: ='PL2026(RS)'!Y8*KRWRSD25 -> 6.3696332e+08 | Z8: ='PL2026(RS)'!Z8*KRWRSD25 -> 6.3525252e+08 | AA8: ='PL2026(RS)'!AA8*KRWRSD25 -> 6.3268632e+08 | AB8: ='PL2026(RS)'!AB8*KRWRSD25 -> 880634440 | AC8: ='PL2026(RS)'!AC8*KRWRSD25 -> 6.6068968e+08 | ... AH8: ='PL2026(RS)'!AH8*KRWRSD25 -> 314594784
B9: SMA sales (KSCP) | C9: 613001 | G9: ='PL2026(RS)'!G9*KRWRSD24 -> 1.0449851e+10 | H9: ='PL2026(RS)'!H9*KRWRSD24 -> 590765925 | I9: ='PL2026(RS)'!I9*KRWRSD24 -> 6.0457063e+08 | J9: ='PL2026(RS)'!J9*KRWRSD24 -> 9.684948e+08 | K9: ='PL2026(RS)'!K9*KRWRSD24 -> 7.7724449e+08 | L9: ='PL2026(RS)'!L9*KRWRSD24 -> 8.5973673e+08 | M9: ='PL2026(RS)'!M9*KRWRSD24 -> 6.0330505e+08 | N9: ='PL2026(RS)'!N9*KRWRSD24 -> 9.2545767e+08 | ... S9: ='PL2026(RS)'!S9*KRWRSD24 -> 1.3404822e+09 | V9: ='PL2026(RS)'!V9*KRWRSD25 -> 15423183300 | W9: ='PL2026(RS)'!W9*KRWRSD25 -> 1179284400 | X9: ='PL2026(RS)'!X9*KRWRSD25 -> 1375831800 | Y9: ='PL2026(RS)'!Y9*KRWRSD25 -> 1637895000 | Z9: ='PL2026(RS)'!Z9*KRWRSD25 -> 1461896100 | AA9: ='PL2026(RS)'!AA9*KRWRSD25 -> 1525456800 | AB9: ='PL2026(RS)'!AB9*KRWRSD25 -> 1589017500 | AC9: ='PL2026(RS)'!AC9*KRWRSD25 -> 1334774700 | ... AH9: ='PL2026(RS)'!AH9*KRWRSD25 -> 1154128500
B10: SMA sales (SKOH) | C10: 615000 | D10: 902893494 | G10: ='PL2026(RS)'!G10*KRWRSD24 -> 8.0198651e+08 | H10: ='PL2026(RS)'!H10*KRWRSD24 -> 3.2041045e+08 | I10: ='PL2026(RS)'!I10*KRWRSD24 -> 2.134634e+08 | J10: ='PL2026(RS)'!J10*KRWRSD24 -> 2.6811266e+08 | K10: ='PL2026(RS)'!K10*KRWRSD24 -> 0 | L10: ='PL2026(RS)'!L10*KRWRSD24 -> 0 | M10: ='PL2026(RS)'!M10*KRWRSD24 -> 0 | N10: ='PL2026(RS)'!N10*KRWRSD24 -> 0 | ... S10: ='PL2026(RS)'!S10*KRWRSD24 -> 0 | V10: ='PL2026(RS)'!V10*KRWRSD25 -> 0 | W10: ='PL2026(RS)'!W10*KRWRSD25 -> 0 | X10: ='PL2026(RS)'!X10*KRWRSD25 -> 0 | Y10: ='PL2026(RS)'!Y10*KRWRSD25 -> 0 | Z10: ='PL2026(RS)'!Z10*KRWRSD25 -> 0 | AA10: ='PL2026(RS)'!AA10*KRWRSD25 -> 0 | AB10: ='PL2026(RS)'!AB10*KRWRSD25 -> 0 | AC10: ='PL2026(RS)'!AC10*KRWRSD25 -> 0 | ... AH10: ='PL2026(RS)'!AH10*KRWRSD25 -> 0
B11: SMA sales (SKBM) | C11: 615001 | G11: ='PL2026(RS)'!G9*KRWRSD24 -> 1.0449851e+10 | H11: ='PL2026(RS)'!H9*KRWRSD24 -> 590765925 | I11: ='PL2026(RS)'!I9*KRWRSD24 -> 6.0457063e+08 | J11: ='PL2026(RS)'!J9*KRWRSD24 -> 9.684948e+08 | K11: ='PL2026(RS)'!K9*KRWRSD24 -> 7.7724449e+08 | L11: ='PL2026(RS)'!L9*KRWRSD24 -> 8.5973673e+08 | M11: ='PL2026(RS)'!M9*KRWRSD24 -> 6.0330505e+08 | N11: ='PL2026(RS)'!N9*KRWRSD24 -> 9.2545767e+08 | ... S11: ='PL2026(RS)'!S9*KRWRSD24 -> 1.3404822e+09 | V11: ='PL2026(RS)'!V11*KRWRSD25 -> 19850124000 | W11: ='PL2026(RS)'!W11*KRWRSD25 -> 1679378400 | X11: ='PL2026(RS)'!X11*KRWRSD25 -> 1959274800 | Y11: ='PL2026(RS)'!Y11*KRWRSD25 -> 2332470000 | Z11: ='PL2026(RS)'!Z11*KRWRSD25 -> 2145872400 | AA11: ='PL2026(RS)'!AA11*KRWRSD25 -> 2239171200 | AB11: ='PL2026(RS)'!AB11*KRWRSD25 -> 2145872400 | AC11: ='PL2026(RS)'!AC11*KRWRSD25 -> 1557124800 | ... AH11: ='PL2026(RS)'!AH11*KRWRSD25 -> 1206450000
B12: SMA sales (KSC) | C12: 611000 | D12: 1207471.8 | G12: ='PL2026(RS)'!G12*KRWRSD24 -> 3977520.5 | H12: ='PL2026(RS)'!H12*KRWRSD24 -> 3815072 | I12: ='PL2026(RS)'!I12*KRWRSD24 -> 0 | J12: ='PL2026(RS)'!J12*KRWRSD24 -> 0 | K12: ='PL2026(RS)'!K12*KRWRSD24 -> 118783.87 | L12: ='PL2026(RS)'!L12*KRWRSD24 -> 0 | M12: ='PL2026(RS)'!M12*KRWRSD24 -> 0 | N12: ='PL2026(RS)'!N12*KRWRSD24 -> 0 | ... S12: ='PL2026(RS)'!S12*KRWRSD24 -> 0 | V12: ='PL2026(RS)'!V12*KRWRSD25 -> 0 | W12: ='PL2026(RS)'!W12*KRWRSD25 -> 0 | X12: ='PL2026(RS)'!X12*KRWRSD25 -> 0 | Y12: ='PL2026(RS)'!Y12*KRWRSD25 -> 0 | Z12: ='PL2026(RS)'!Z12*KRWRSD25 -> 0 | AA12: ='PL2026(RS)'!AA12*KRWRSD25 -> 0 | AB12: ='PL2026(RS)'!AB12*KRWRSD25 -> 0 | AC12: ='PL2026(RS)'!AC12*KRWRSD25 -> 0 | ... AH12: ='PL2026(RS)'!AH12*KRWRSD25 -> 0
B13: W/H sales (KCTR) | C13: 613004 | G13: ='PL2026(RS)'!G13*KRWRSD24 -> 57217728 | H13: ='PL2026(RS)'!H13*KRWRSD24 -> 0 | I13: ='PL2026(RS)'!I13*KRWRSD24 -> 0 | J13: ='PL2026(RS)'!J13*KRWRSD24 -> 0 | K13: ='PL2026(RS)'!K13*KRWRSD24 -> 0 | L13: ='PL2026(RS)'!L13*KRWRSD24 -> 0 | M13: ='PL2026(RS)'!M13*KRWRSD24 -> 0 | N13: ='PL2026(RS)'!N13*KRWRSD24 -> 0 | ... S13: ='PL2026(RS)'!S13*KRWRSD24 -> 0 | V13: ='PL2026(RS)'!V13*KRWRSD25 -> 1.0504961e+10 | W13: ='PL2026(RS)'!W13*KRWRSD25 -> 0 | X13: ='PL2026(RS)'!X13*KRWRSD25 -> 0 | Y13: ='PL2026(RS)'!Y13*KRWRSD25 -> 0 | Z13: ='PL2026(RS)'!Z13*KRWRSD25 -> 0 | AA13: ='PL2026(RS)'!AA13*KRWRSD25 -> 0 | AB13: ='PL2026(RS)'!AB13*KRWRSD25 -> 0 | AC13: ='PL2026(RS)'!AC13*KRWRSD25 -> 0 | ... AH13: ='PL2026(RS)'!AH13*KRWRSD25 -> 3.4255307e+09
B14: W/H sales (FORD) | C14: 615002 | D14: 1207471.8 | G14: ='PL2026(RS)'!G14*KRWRSD24 -> 20890895 | H14: ='PL2026(RS)'!H14*KRWRSD24 -> 0 | I14: ='PL2026(RS)'!I14*KRWRSD24 -> 0 | J14: ='PL2026(RS)'!J14*KRWRSD24 -> 0 | K14: ='PL2026(RS)'!K14*KRWRSD24 -> 0 | L14: ='PL2026(RS)'!L14*KRWRSD24 -> 0 | M14: ='PL2026(RS)'!M14*KRWRSD24 -> 0 | N14: ='PL2026(RS)'!N14*KRWRSD24 -> 0 | ... S14: ='PL2026(RS)'!S14*KRWRSD24 -> 0 | V14: ='PL2026(RS)'!V14*KRWRSD25 -> 0 | W14: ='PL2026(RS)'!W14*KRWRSD25 -> 0 | X14: ='PL2026(RS)'!X14*KRWRSD25 -> 0 | Y14: ='PL2026(RS)'!Y14*KRWRSD25 -> 0 | Z14: ='PL2026(RS)'!Z14*KRWRSD25 -> 0 | AA14: ='PL2026(RS)'!AA14*KRWRSD25 -> 0 | AB14: ='PL2026(RS)'!AB14*KRWRSD25 -> 0 | AC14: ='PL2026(RS)'!AC14*KRWRSD25 -> 0 | ... AH14: ='PL2026(RS)'!AH14*KRWRSD25 -> 0
A15: 2. 상품 매출 | B15: 2 Merchandise | D15: 2.1913182e+08 | G15: ='PL2026(RS)'!G15*KRWRSD24 -> 2.6198426e+08 | H15: ='PL2026(RS)'!H15*KRWRSD24 -> 55864036 | I15: ='PL2026(RS)'!I15*KRWRSD24 -> 71430147 | J15: ='PL2026(RS)'!J15*KRWRSD24 -> 59715494 | K15: ='PL2026(RS)'!K15*KRWRSD24 -> 0 | L15: ='PL2026(RS)'!L15*KRWRSD24 -> 0 | M15: ='PL2026(RS)'!M15*KRWRSD24 -> 0 | N15: ='PL2026(RS)'!N15*KRWRSD24 -> 0 | ... S15: ='PL2026(RS)'!S15*KRWRSD24 -> 35521095 | V15: ='PL2026(RS)'!V15*KRWRSD25 -> 0 | W15: ='PL2026(RS)'!W15*KRWRSD25 -> 0 | X15: ='PL2026(RS)'!X15*KRWRSD25 -> 0 | Y15: ='PL2026(RS)'!Y15*KRWRSD25 -> 0 | Z15: ='PL2026(RS)'!Z15*KRWRSD25 -> 0 | AA15: ='PL2026(RS)'!AA15*KRWRSD25 -> 0 | AB15: ='PL2026(RS)'!AB15*KRWRSD25 -> 0 | AC15: ='PL2026(RS)'!AC15*KRWRSD25 -> 0 | ... AH15: ='PL2026(RS)'!AH15*KRWRSD25 -> 0
B16: W/H sales | C16: 605000 | D16: 0 | G16: ='PL2026(RS)'!G16*KRWRSD24 -> 0 | H16: ='PL2026(RS)'!H16*KRWRSD24 -> 0 | I16: ='PL2026(RS)'!I16*KRWRSD24 -> 0 | J16: ='PL2026(RS)'!J16*KRWRSD24 -> 0 | K16: ='PL2026(RS)'!K16*KRWRSD24 -> 0 | L16: ='PL2026(RS)'!L16*KRWRSD24 -> 0 | M16: ='PL2026(RS)'!M16*KRWRSD24 -> 0 | N16: ='PL2026(RS)'!N16*KRWRSD24 -> 0 | ... S16: ='PL2026(RS)'!S16*KRWRSD24 -> 0 | V16: ='PL2026(RS)'!V16*KRWRSD25 -> 0 | W16: ='PL2026(RS)'!W16*KRWRSD25 -> 0 | X16: ='PL2026(RS)'!X16*KRWRSD25 -> 0 | Y16: ='PL2026(RS)'!Y16*KRWRSD25 -> 0 | Z16: ='PL2026(RS)'!Z16*KRWRSD25 -> 0 | AA16: ='PL2026(RS)'!AA16*KRWRSD25 -> 0 | AB16: ='PL2026(RS)'!AB16*KRWRSD25 -> 0 | AC16: ='PL2026(RS)'!AC16*KRWRSD25 -> 0 | ... AH16: ='PL2026(RS)'!AH16*KRWRSD25 -> 0
B17: W/H sales | C17: 603000 | G17: ='PL2026(RS)'!G17*KRWRSD24 -> 0 | H17: ='PL2026(RS)'!H17*KRWRSD24 -> 0 | I17: ='PL2026(RS)'!I17*KRWRSD24 -> 0 | J17: ='PL2026(RS)'!J17*KRWRSD24 -> 0 | K17: ='PL2026(RS)'!K17*KRWRSD24 -> 0 | L17: ='PL2026(RS)'!L17*KRWRSD24 -> 0 | M17: ='PL2026(RS)'!M17*KRWRSD24 -> 0 | N17: ='PL2026(RS)'!N17*KRWRSD24 -> 0 | ... S17: ='PL2026(RS)'!S17*KRWRSD24 -> 0 | V17: ='PL2026(RS)'!V17*KRWRSD25 -> 0 | W17: ='PL2026(RS)'!W17*KRWRSD25 -> 0 | X17: ='PL2026(RS)'!X17*KRWRSD25 -> 0 | Y17: ='PL2026(RS)'!Y17*KRWRSD25 -> 0 | Z17: ='PL2026(RS)'!Z17*KRWRSD25 -> 0 | AA17: ='PL2026(RS)'!AA17*KRWRSD25 -> 0 | AB17: ='PL2026(RS)'!AB17*KRWRSD25 -> 0 | AC17: ='PL2026(RS)'!AC17*KRWRSD25 -> 0 | ... AH17: ='PL2026(RS)'!AH17*KRWRSD25 -> 0
B18: SMA sales | C18: 605901 | D18: 2.1231184e+08 | G18: ='PL2026(RS)'!G18*KRWRSD24 -> 2.6198426e+08 | H18: ='PL2026(RS)'!H18*KRWRSD24 -> 55864036 | I18: ='PL2026(RS)'!I18*KRWRSD24 -> 71430147 | J18: ='PL2026(RS)'!J18*KRWRSD24 -> 59715494 | K18: ='PL2026(RS)'!K18*KRWRSD24 -> 0 | L18: ='PL2026(RS)'!L18*KRWRSD24 -> 0 | M18: ='PL2026(RS)'!M18*KRWRSD24 -> 0 | N18: ='PL2026(RS)'!N18*KRWRSD24 -> 0 | ... S18: ='PL2026(RS)'!S18*KRWRSD24 -> 35521095 | V18: ='PL2026(RS)'!V18*KRWRSD25 -> 0 | W18: ='PL2026(RS)'!W18*KRWRSD25 -> 0 | X18: ='PL2026(RS)'!X18*KRWRSD25 -> 0 | Y18: ='PL2026(RS)'!Y18*KRWRSD25 -> 0 | Z18: ='PL2026(RS)'!Z18*KRWRSD25 -> 0 | AA18: ='PL2026(RS)'!AA18*KRWRSD25 -> 0 | AB18: ='PL2026(RS)'!AB18*KRWRSD25 -> 0 | AC18: ='PL2026(RS)'!AC18*KRWRSD25 -> 0 | ... AH18: ='PL2026(RS)'!AH18*KRWRSD25 -> 0
A19: 3. 기타 매출 | B19: 2. Other sales | D19: 2.6549321e+08 | G19: ='PL2026(RS)'!G19*KRWRSD24 -> 2.0254906e+08 | H19: ='PL2026(RS)'!H19*KRWRSD24 -> 508062.5 | I19: ='PL2026(RS)'!I19*KRWRSD24 -> 3484855.5 | J19: ='PL2026(RS)'!J19*KRWRSD24 -> 970187.5 | K19: ='PL2026(RS)'!K19*KRWRSD24 -> 1008963.2 | L19: ='PL2026(RS)'!L19*KRWRSD24 -> 88604282 | M19: ='PL2026(RS)'!M19*KRWRSD24 -> 2706140 | N19: ='PL2026(RS)'!N19*KRWRSD24 -> 3050785 | ... S19: ='PL2026(RS)'!S19*KRWRSD24 -> 7494634.9 | V19: ='PL2026(RS)'!V19*KRWRSD25 -> 0 | W19: ='PL2026(RS)'!W19*KRWRSD25 -> 0 | X19: ='PL2026(RS)'!X19*KRWRSD25 -> 0 | Y19: ='PL2026(RS)'!Y19*KRWRSD25 -> 0 | Z19: ='PL2026(RS)'!Z19*KRWRSD25 -> 0 | AA19: ='PL2026(RS)'!AA19*KRWRSD25 -> 0 | AB19: ='PL2026(RS)'!AB19*KRWRSD25 -> 0 | AC19: ='PL2026(RS)'!AC19*KRWRSD25 -> 0 | ... AH19: ='PL2026(RS)'!AH19*KRWRSD25 -> 0
A20: └ Materials | B20: └ Materials | C20: 613100 | D20: 1.7291133e+08 | G20: ='PL2026(RS)'!G20*KRWRSD24 -> 1309445.9 | H20: ='PL2026(RS)'!H20*KRWRSD24 -> 0 | I20: ='PL2026(RS)'!I20*KRWRSD24 -> 542802.25 | J20: ='PL2026(RS)'!J20*KRWRSD24 -> 0 | K20: ='PL2026(RS)'!K20*KRWRSD24 -> 384338.25 | L20: ='PL2026(RS)'!L20*KRWRSD24 -> 0 | M20: ='PL2026(RS)'!M20*KRWRSD24 -> 0 | N20: ='PL2026(RS)'!N20*KRWRSD24 -> 0 | ... S20: ='PL2026(RS)'!S20*KRWRSD24 -> 0 | V20: ='PL2026(RS)'!V20*KRWRSD25 -> 0 | W20: ='PL2026(RS)'!W20*KRWRSD25 -> 0 | X20: ='PL2026(RS)'!X20*KRWRSD25 -> 0 | Y20: ='PL2026(RS)'!Y20*KRWRSD25 -> 0 | Z20: ='PL2026(RS)'!Z20*KRWRSD25 -> 0 | AA20: ='PL2026(RS)'!AA20*KRWRSD25 -> 0 | AB20: ='PL2026(RS)'!AB20*KRWRSD25 -> 0 | AC20: ='PL2026(RS)'!AC20*KRWRSD25 -> 0 | ... AH20: ='PL2026(RS)'!AH20*KRWRSD25 -> 0
A21: └ scrap | B21: └ scrap | C21: 559001 | D21: 2589065.3 | G21: ='PL2026(RS)'!G21*KRWRSD24 -> 0 | H21: ='PL2026(RS)'!H21*KRWRSD24 -> 0 | I21: ='PL2026(RS)'!I21*KRWRSD24 -> 0 | J21: ='PL2026(RS)'!J21*KRWRSD24 -> 0 | K21: ='PL2026(RS)'!K21*KRWRSD24 -> 0 | L21: ='PL2026(RS)'!L21*KRWRSD24 -> 0 | M21: ='PL2026(RS)'!M21*KRWRSD24 -> 0 | N21: ='PL2026(RS)'!N21*KRWRSD24 -> 0 | ... S21: ='PL2026(RS)'!S21*KRWRSD24 -> 0 | V21: ='PL2026(RS)'!V21*KRWRSD25 -> 0 | W21: ='PL2026(RS)'!W21*KRWRSD25 -> 0 | X21: ='PL2026(RS)'!X21*KRWRSD25 -> 0 | Y21: ='PL2026(RS)'!Y21*KRWRSD25 -> 0 | Z21: ='PL2026(RS)'!Z21*KRWRSD25 -> 0 | AA21: ='PL2026(RS)'!AA21*KRWRSD25 -> 0 | AB21: ='PL2026(RS)'!AB21*KRWRSD25 -> 0 | AC21: ='PL2026(RS)'!AC21*KRWRSD25 -> 0 | ... AH21: ='PL2026(RS)'!AH21*KRWRSD25 -> 0
A22: └ scrap | B22: └ scrap | C22: 659000 | D22: 2589065.3 | G22: ='PL2026(RS)'!G22*KRWRSD24 -> 1.1328252e+08 | H22: ='PL2026(RS)'!H22*KRWRSD24 -> 508062.5 | I22: ='PL2026(RS)'!I22*KRWRSD24 -> 2942053.2 | J22: ='PL2026(RS)'!J22*KRWRSD24 -> 970187.5 | K22: ='PL2026(RS)'!K22*KRWRSD24 -> 624625 | L22: ='PL2026(RS)'!L22*KRWRSD24 -> 647187.5 | M22: ='PL2026(RS)'!M22*KRWRSD24 -> 2706140 | N22: ='PL2026(RS)'!N22*KRWRSD24 -> 3050785 | ... S22: ='PL2026(RS)'!S22*KRWRSD24 -> 7494634.9 | V22: ='PL2026(RS)'!V22*KRWRSD25 -> 0 | W22: ='PL2026(RS)'!W22*KRWRSD25 -> 0 | X22: ='PL2026(RS)'!X22*KRWRSD25 -> 0 | Y22: ='PL2026(RS)'!Y22*KRWRSD25 -> 0 | Z22: ='PL2026(RS)'!Z22*KRWRSD25 -> 0 | AA22: ='PL2026(RS)'!AA22*KRWRSD25 -> 0 | AB22: ='PL2026(RS)'!AB22*KRWRSD25 -> 0 | AC22: ='PL2026(RS)'!AC22*KRWRSD25 -> 0 | ... AH22: ='PL2026(RS)'!AH22*KRWRSD25 -> 0
A23: └ 기타 | B23: └ Other | C23: 649000 | D23: 89992815 | G23: ='PL2026(RS)'!G23*KRWRSD24 -> 87957094 | H23: ='PL2026(RS)'!H23*KRWRSD24 -> 0 | I23: ='PL2026(RS)'!I23*KRWRSD24 -> 0 | J23: ='PL2026(RS)'!J23*KRWRSD24 -> 0 | K23: ='PL2026(RS)'!K23*KRWRSD24 -> 0 | L23: ='PL2026(RS)'!L23*KRWRSD24 -> 87957094 | M23: ='PL2026(RS)'!M23*KRWRSD24 -> 0 | N23: ='PL2026(RS)'!N23*KRWRSD24 -> 0 | ... S23: ='PL2026(RS)'!S23*KRWRSD24 -> 0 | V23: ='PL2026(RS)'!V23*KRWRSD25 -> 0 | W23: ='PL2026(RS)'!W23*KRWRSD25 -> 0 | X23: ='PL2026(RS)'!X23*KRWRSD25 -> 0 | Y23: ='PL2026(RS)'!Y23*KRWRSD25 -> 0 | Z23: ='PL2026(RS)'!Z23*KRWRSD25 -> 0 | AA23: ='PL2026(RS)'!AA23*KRWRSD25 -> 0 | AB23: ='PL2026(RS)'!AB23*KRWRSD25 -> 0 | AC23: ='PL2026(RS)'!AC23*KRWRSD25 -> 0 | ... AH23: ='PL2026(RS)'!AH23*KRWRSD25 -> 0
A24: Ⅱ. 매출원가 | B24: Ⅱ. COST OF SALES | D24: 3.3977175e+09 | G24: ='PL2026(RS)'!G24*KRWRSD24 -> 3.4519077e+10 | H24: ='PL2026(RS)'!H24*KRWRSD24 -> 3.4840041e+09 | I24: ='PL2026(RS)'!I24*KRWRSD24 -> 2.5339602e+09 | J24: ='PL2026(RS)'!J24*KRWRSD24 -> 2.8381197e+09 | K24: ='PL2026(RS)'!K24*KRWRSD24 -> 2.1033823e+09 | L24: ='PL2026(RS)'!L24*KRWRSD24 -> 1.988037e+09 | M24: ='PL2026(RS)'!M24*KRWRSD24 -> 2.3016237e+09 | N24: ='PL2026(RS)'!N24*KRWRSD24 -> 2.9788962e+09 | ... S24: ='PL2026(RS)'!S24*KRWRSD24 -> 3.3231593e+09 | V24: ='PL2026(RS)'!V24*KRWRSD25 -> 5.3430443e+10 | W24: ='PL2026(RS)'!W24*KRWRSD25 -> 3.9733834e+09 | X24: ='PL2026(RS)'!X24*KRWRSD25 -> 4.3007489e+09 | Y24: ='PL2026(RS)'!Y24*KRWRSD25 -> 4.697204e+09 | Z24: ='PL2026(RS)'!Z24*KRWRSD25 -> 4.5320945e+09 | AA24: ='PL2026(RS)'!AA24*KRWRSD25 -> 4.6259276e+09 | AB24: ='PL2026(RS)'!AB24*KRWRSD25 -> 4.7634071e+09 | AC24: ='PL2026(RS)'!AC24*KRWRSD25 -> 3.6812016e+09 | ... AH24: ='PL2026(RS)'!AH24*KRWRSD25 -> 5.3116001e+09
A25: 제품매출원가 | B25: Cost of manufactured goods sold | D25: 3.026646e+09 | G25: ='PL2026(RS)'!G25*KRWRSD24 -> 3.4331845e+10 | H25: ='PL2026(RS)'!H25*KRWRSD24 -> 3.4339747e+09 | I25: ='PL2026(RS)'!I25*KRWRSD24 -> 2.4689467e+09 | J25: ='PL2026(RS)'!J25*KRWRSD24 -> 2.7840856e+09 | K25: ='PL2026(RS)'!K25*KRWRSD24 -> 2.1029998e+09 | L25: ='PL2026(RS)'!L25*KRWRSD24 -> 1.9880371e+09 | M25: ='PL2026(RS)'!M25*KRWRSD24 -> 2.3016358e+09 | N25: ='PL2026(RS)'!N25*KRWRSD24 -> 2.9789053e+09 | ... S25: ='PL2026(RS)'!S25*KRWRSD24 -> 3.3231648e+09 | V25: ='PL2026(RS)'!V25*KRWRSD25 -> 5.3430443e+10 | W25: ='PL2026(RS)'!W25*KRWRSD25 -> 3.9733834e+09 | X25: ='PL2026(RS)'!X25*KRWRSD25 -> 4.3007489e+09 | Y25: ='PL2026(RS)'!Y25*KRWRSD25 -> 4.697204e+09 | Z25: ='PL2026(RS)'!Z25*KRWRSD25 -> 4.5320945e+09 | AA25: ='PL2026(RS)'!AA25*KRWRSD25 -> 4.6259276e+09 | AB25: ='PL2026(RS)'!AB25*KRWRSD25 -> 4.7634071e+09 | AC25: ='PL2026(RS)'!AC25*KRWRSD25 -> 3.6812016e+09 | ... AH25: ='PL2026(RS)'!AH25*KRWRSD25 -> 5.3116001e+09
A26: 1.기초 제품재고 | B26: 1. Beginning Manufactured goods | D26: 4.4767263e+08 | G26: ='PL2026(RS)'!G26*KRWRSD24 -> 1.2393836e+09 | H26: ='PL2026(RS)'!H26*KRWRSD24 -> 1.2393836e+09 | I26: ='PL2026(RS)'!I26*KRWRSD24 -> 7.2837096e+08 | J26: ='PL2026(RS)'!J26*KRWRSD24 -> 1.0659702e+09 | K26: ='PL2026(RS)'!K26*KRWRSD24 -> 1.0565496e+09 | L26: ='PL2026(RS)'!L26*KRWRSD24 -> 1.72723e+09 | M26: ='PL2026(RS)'!M26*KRWRSD24 -> 2.4392248e+09 | N26: ='PL2026(RS)'!N26*KRWRSD24 -> 2.9053262e+09 | ... S26: ='PL2026(RS)'!S26*KRWRSD24 -> 0 | V26: ='PL2026(RS)'!V26*KRWRSD25 -> 0 | W26: ='PL2026(RS)'!W26*KRWRSD25 -> 0 | X26: ='PL2026(RS)'!X26*KRWRSD25 -> 0 | Y26: ='PL2026(RS)'!Y26*KRWRSD25 -> 0 | Z26: ='PL2026(RS)'!Z26*KRWRSD25 -> 0 | AA26: ='PL2026(RS)'!AA26*KRWRSD25 -> 0 | AB26: ='PL2026(RS)'!AB26*KRWRSD25 -> 0 | AC26: ='PL2026(RS)'!AC26*KRWRSD25 -> 0 | ... AH26: ='PL2026(RS)'!AH26*KRWRSD25 -> 0
A27: 2.당기 제품제조원가 | B27: 2. Cost of Goods Maunfactured | D27: 2.8148022e+09 | G27: ='PL2026(RS)'!G27*KRWRSD24 -> 3.4140457e+10 | H27: ='PL2026(RS)'!H27*KRWRSD24 -> 2.9229621e+09 | I27: ='PL2026(RS)'!I27*KRWRSD24 -> 2.8149416e+09 | J27: ='PL2026(RS)'!J27*KRWRSD24 -> 2.7770771e+09 | K27: ='PL2026(RS)'!K27*KRWRSD24 -> 2.7764472e+09 | L27: ='PL2026(RS)'!L27*KRWRSD24 -> 2.7001726e+09 | M27: ='PL2026(RS)'!M27*KRWRSD24 -> 2.7697863e+09 | N27: ='PL2026(RS)'!N27*KRWRSD24 -> 2.4377824e+09 | ... S27: ='PL2026(RS)'!S27*KRWRSD24 -> 3.3231648e+09 | V27: ='PL2026(RS)'!V27*KRWRSD25 -> 5.3430443e+10 | W27: ='PL2026(RS)'!W27*KRWRSD25 -> 3.9733834e+09 | X27: ='PL2026(RS)'!X27*KRWRSD25 -> 4.3007489e+09 | Y27: ='PL2026(RS)'!Y27*KRWRSD25 -> 4.697204e+09 | Z27: ='PL2026(RS)'!Z27*KRWRSD25 -> 4.5320945e+09 | AA27: ='PL2026(RS)'!AA27*KRWRSD25 -> 4.6259276e+09 | AB27: ='PL2026(RS)'!AB27*KRWRSD25 -> 4.7634071e+09 | AC27: ='PL2026(RS)'!AC27*KRWRSD25 -> 3.6812016e+09 | ... AH27: ='PL2026(RS)'!AH27*KRWRSD25 -> 5.3116001e+09
A28: 3.타계정전입 (+) | B28: 3. Transferred from other accounts | D28: 0 | G28: ='PL2026(RS)'!G28*KRWRSD24 -> 0 | H28: ='PL2026(RS)'!H28*KRWRSD24 -> 0 | I28: ='PL2026(RS)'!I28*KRWRSD24 -> 0 | J28: ='PL2026(RS)'!J28*KRWRSD24 -> 0 | K28: ='PL2026(RS)'!K28*KRWRSD24 -> 0 | L28: ='PL2026(RS)'!L28*KRWRSD24 -> 0 | M28: ='PL2026(RS)'!M28*KRWRSD24 -> 0 | N28: ='PL2026(RS)'!N28*KRWRSD24 -> 0 | ... S28: ='PL2026(RS)'!S28*KRWRSD24 -> 0 | V28: ='PL2026(RS)'!V28*KRWRSD25 -> 0 | W28: ='PL2026(RS)'!W28*KRWRSD25 -> 0 | X28: ='PL2026(RS)'!X28*KRWRSD25 -> 0 | Y28: ='PL2026(RS)'!Y28*KRWRSD25 -> 0 | Z28: ='PL2026(RS)'!Z28*KRWRSD25 -> 0 | AA28: ='PL2026(RS)'!AA28*KRWRSD25 -> 0 | AB28: ='PL2026(RS)'!AB28*KRWRSD25 -> 0 | AC28: ='PL2026(RS)'!AC28*KRWRSD25 -> 0 | ... AH28: ='PL2026(RS)'!AH28*KRWRSD25 -> 0
A29: 4.타계정대체 (-) | B29: 4. Transferred to other accounts | D29: 5392745.6 | G29: ='PL2026(RS)'!G29*KRWRSD24 -> 23656714 | H29: ='PL2026(RS)'!H29*KRWRSD24 -> 0 | I29: ='PL2026(RS)'!I29*KRWRSD24 -> 8395675.3 | J29: ='PL2026(RS)'!J29*KRWRSD24 -> 2412169.7 | K29: ='PL2026(RS)'!K29*KRWRSD24 -> 2767005 | L29: ='PL2026(RS)'!L29*KRWRSD24 -> 140663.33 | M29: ='PL2026(RS)'!M29*KRWRSD24 -> 2049095.8 | N29: ='PL2026(RS)'!N29*KRWRSD24 -> 1005122.4 | ... S29: ='PL2026(RS)'!S29*KRWRSD24 -> 0 | V29: ='PL2026(RS)'!V29*KRWRSD25 -> 0 | W29: ='PL2026(RS)'!W29*KRWRSD25 -> 0 | X29: ='PL2026(RS)'!X29*KRWRSD25 -> 0 | Y29: ='PL2026(RS)'!Y29*KRWRSD25 -> 0 | Z29: ='PL2026(RS)'!Z29*KRWRSD25 -> 0 | AA29: ='PL2026(RS)'!AA29*KRWRSD25 -> 0 | AB29: ='PL2026(RS)'!AB29*KRWRSD25 -> 0 | AC29: ='PL2026(RS)'!AC29*KRWRSD25 -> 0 | ... AH29: ='PL2026(RS)'!AH29*KRWRSD25 -> 0
A30: 5.재고자산감모손실 | B30: 5. Losses on Inventory Obsolescence | D30: 0 | G30: ='PL2026(RS)'!G30*KRWRSD24 -> 0 | H30: ='PL2026(RS)'!H30*KRWRSD24 -> 0 | I30: ='PL2026(RS)'!I30*KRWRSD24 -> 0 | J30: ='PL2026(RS)'!J30*KRWRSD24 -> 0 | K30: ='PL2026(RS)'!K30*KRWRSD24 -> 0 | L30: ='PL2026(RS)'!L30*KRWRSD24 -> 0 | M30: ='PL2026(RS)'!M30*KRWRSD24 -> 0 | N30: ='PL2026(RS)'!N30*KRWRSD24 -> 0 | ... S30: ='PL2026(RS)'!S30*KRWRSD24 -> 0 | V30: ='PL2026(RS)'!V30*KRWRSD25 -> 0 | W30: ='PL2026(RS)'!W30*KRWRSD25 -> 0 | X30: ='PL2026(RS)'!X30*KRWRSD25 -> 0 | Y30: ='PL2026(RS)'!Y30*KRWRSD25 -> 0 | Z30: ='PL2026(RS)'!Z30*KRWRSD25 -> 0 | AA30: ='PL2026(RS)'!AA30*KRWRSD25 -> 0 | AB30: ='PL2026(RS)'!AB30*KRWRSD25 -> 0 | AC30: ='PL2026(RS)'!AC30*KRWRSD25 -> 0 | ... AH30: ='PL2026(RS)'!AH30*KRWRSD25 -> 0
A31: 6.재고자산평가손실 | B31: 6. Loss on valuation of inventories | D31: 0 | G31: ='PL2026(RS)'!G31*KRWRSD24 -> 0 | H31: ='PL2026(RS)'!H31*KRWRSD24 -> 0 | I31: ='PL2026(RS)'!I31*KRWRSD24 -> 0 | J31: ='PL2026(RS)'!J31*KRWRSD24 -> 0 | K31: ='PL2026(RS)'!K31*KRWRSD24 -> 0 | L31: ='PL2026(RS)'!L31*KRWRSD24 -> 0 | M31: ='PL2026(RS)'!M31*KRWRSD24 -> 0 | N31: ='PL2026(RS)'!N31*KRWRSD24 -> 0 | ... S31: ='PL2026(RS)'!S31*KRWRSD24 -> 0 | V31: ='PL2026(RS)'!V31*KRWRSD25 -> 0 | W31: ='PL2026(RS)'!W31*KRWRSD25 -> 0 | X31: ='PL2026(RS)'!X31*KRWRSD25 -> 0 | Y31: ='PL2026(RS)'!Y31*KRWRSD25 -> 0 | Z31: ='PL2026(RS)'!Z31*KRWRSD25 -> 0 | AA31: ='PL2026(RS)'!AA31*KRWRSD25 -> 0 | AB31: ='PL2026(RS)'!AB31*KRWRSD25 -> 0 | AC31: ='PL2026(RS)'!AC31*KRWRSD25 -> 0 | ... AH31: ='PL2026(RS)'!AH31*KRWRSD25 -> 0
A32: 7.기말 제품재고 | B32: 7. Ending Manufactured goods | D32: 2.3043603e+08 | G32: ='PL2026(RS)'!G32*KRWRSD24 -> 3.2241411e+09 | H32: ='PL2026(RS)'!H32*KRWRSD24 -> 7.2837096e+08 | I32: ='PL2026(RS)'!I32*KRWRSD24 -> 1.0659702e+09 | J32: ='PL2026(RS)'!J32*KRWRSD24 -> 1.0565496e+09 | K32: ='PL2026(RS)'!K32*KRWRSD24 -> 1.72723e+09 | L32: ='PL2026(RS)'!L32*KRWRSD24 -> 2.4392248e+09 | M32: ='PL2026(RS)'!M32*KRWRSD24 -> 2.9053262e+09 | N32: ='PL2026(RS)'!N32*KRWRSD24 -> 2.3631982e+09 | ... S32: ='PL2026(RS)'!S32*KRWRSD24 -> 0 | V32: ='PL2026(RS)'!V32*KRWRSD25 -> 0 | W32: ='PL2026(RS)'!W32*KRWRSD25 -> 0 | X32: ='PL2026(RS)'!X32*KRWRSD25 -> 0 | Y32: ='PL2026(RS)'!Y32*KRWRSD25 -> 0 | Z32: ='PL2026(RS)'!Z32*KRWRSD25 -> 0 | AA32: ='PL2026(RS)'!AA32*KRWRSD25 -> 0 | AB32: ='PL2026(RS)'!AB32*KRWRSD25 -> 0 | AC32: ='PL2026(RS)'!AC32*KRWRSD25 -> 0 | ... AH32: ='PL2026(RS)'!AH32*KRWRSD25 -> 0
A33: 상품매출원가 | B33: Cost of merchandise sold | D33: 2.0356215e+08 | G33: ='PL2026(RS)'!G33*KRWRSD24 -> 1.8603615e+08 | H33: ='PL2026(RS)'!H33*KRWRSD24 -> 50029450 | I33: ='PL2026(RS)'!I33*KRWRSD24 -> 64516707 | J33: ='PL2026(RS)'!J33*KRWRSD24 -> 54038105 | K33: ='PL2026(RS)'!K33*KRWRSD24 -> 0 | L33: ='PL2026(RS)'!L33*KRWRSD24 -> 0 | M33: ='PL2026(RS)'!M33*KRWRSD24 -> 0 | N33: ='PL2026(RS)'!N33*KRWRSD24 -> 0 | ... S33: ='PL2026(RS)'!S33*KRWRSD24 -> 0 | V33: ='PL2026(RS)'!V33*KRWRSD25 -> 0 | W33: ='PL2026(RS)'!W33*KRWRSD25 -> 0 | X33: ='PL2026(RS)'!X33*KRWRSD25 -> 0 | Y33: ='PL2026(RS)'!Y33*KRWRSD25 -> 0 | Z33: ='PL2026(RS)'!Z33*KRWRSD25 -> 0 | AA33: ='PL2026(RS)'!AA33*KRWRSD25 -> 0 | AB33: ='PL2026(RS)'!AB33*KRWRSD25 -> 0 | AC33: ='PL2026(RS)'!AC33*KRWRSD25 -> 0 | ... AH33: ='PL2026(RS)'!AH33*KRWRSD25 -> 0
A34: 1.기초 상품재고 | B34: 1. Beginning Merchandise | D34: 40703217 | G34: ='PL2026(RS)'!G34*KRWRSD24 -> 5.1432916e+09 | H34: ='PL2026(RS)'!H34*KRWRSD24 -> 5.6884567e+08 | I34: ='PL2026(RS)'!I34*KRWRSD24 -> 5.1881622e+08 | J34: ='PL2026(RS)'!J34*KRWRSD24 -> 4.5429952e+08 | K34: ='PL2026(RS)'!K34*KRWRSD24 -> 4.0026141e+08 | L34: ='PL2026(RS)'!L34*KRWRSD24 -> 4.0026141e+08 | M34: ='PL2026(RS)'!M34*KRWRSD24 -> 4.0011534e+08 | N34: ='PL2026(RS)'!N34*KRWRSD24 -> 4.0011534e+08 | ... S34: ='PL2026(RS)'!S34*KRWRSD24 -> 4.0011534e+08 | V34: ='PL2026(RS)'!V34*KRWRSD25 -> 0 | W34: ='PL2026(RS)'!W34*KRWRSD25 -> 0 | X34: ='PL2026(RS)'!X34*KRWRSD25 -> 0 | Y34: ='PL2026(RS)'!Y34*KRWRSD25 -> 0 | Z34: ='PL2026(RS)'!Z34*KRWRSD25 -> 0 | AA34: ='PL2026(RS)'!AA34*KRWRSD25 -> 0 | AB34: ='PL2026(RS)'!AB34*KRWRSD25 -> 0 | AC34: ='PL2026(RS)'!AC34*KRWRSD25 -> 0 | ... AH34: ='PL2026(RS)'!AH34*KRWRSD25 -> 0
A35: 2.당기 상품매입원가 | B35: 2. Cost of Merchandise | D35: 2.1599822e+08 | G35: ='PL2026(RS)'!G35*KRWRSD24 -> 17451889 | H35: ='PL2026(RS)'!H35*KRWRSD24 -> 0 | I35: ='PL2026(RS)'!I35*KRWRSD24 -> 0 | J35: ='PL2026(RS)'!J35*KRWRSD24 -> 0 | K35: ='PL2026(RS)'!K35*KRWRSD24 -> 0 | L35: ='PL2026(RS)'!L35*KRWRSD24 -> 0 | M35: ='PL2026(RS)'!M35*KRWRSD24 -> 0 | N35: ='PL2026(RS)'!N35*KRWRSD24 -> 0 | ... S35: ='PL2026(RS)'!S35*KRWRSD24 -> 0 | V35: ='PL2026(RS)'!V35*KRWRSD25 -> 0 | W35: ='PL2026(RS)'!W35*KRWRSD25 -> 0 | X35: ='PL2026(RS)'!X35*KRWRSD25 -> 0 | Y35: ='PL2026(RS)'!Y35*KRWRSD25 -> 0 | Z35: ='PL2026(RS)'!Z35*KRWRSD25 -> 0 | AA35: ='PL2026(RS)'!AA35*KRWRSD25 -> 0 | AB35: ='PL2026(RS)'!AB35*KRWRSD25 -> 0 | AC35: ='PL2026(RS)'!AC35*KRWRSD25 -> 0 | ... AH35: ='PL2026(RS)'!AH35*KRWRSD25 -> 0
... A43: Ⅲ. 매출총이익 | B43: Ⅲ. GROSS PROFIT (or GROSS LOSS) | D43: -3.7292369e+08 | G43: ='PL2026(RS)'!G43*KRWRSD24 -> -5.1896778e+09 | H43: ='PL2026(RS)'!H43*KRWRSD24 -> -4.1795977e+08 | I43: ='PL2026(RS)'!I43*KRWRSD24 -> -2.7696965e+08 | J43: ='PL2026(RS)'!J43*KRWRSD24 -> -4.4172898e+08 | K43: ='PL2026(RS)'!K43*KRWRSD24 -> -6.566291e+08 | L43: ='PL2026(RS)'!L43*KRWRSD24 -> -3.3660259e+08 | M43: ='PL2026(RS)'!M43*KRWRSD24 -> -5.9076617e+08 | N43: ='PL2026(RS)'!N43*KRWRSD24 -> -6.1925535e+08 | ... S43: ='PL2026(RS)'!S43*KRWRSD24 -> -1.1061837e+08 | V43: ='PL2026(RS)'!V43*KRWRSD25 -> 3.8379841e+08 | W43: ='PL2026(RS)'!W43*KRWRSD25 -> -6.0703182e+08 | X43: ='PL2026(RS)'!X43*KRWRSD25 -> -3.7205566e+08 | Y43: ='PL2026(RS)'!Y43*KRWRSD25 -> -89875707 | Z43: ='PL2026(RS)'!Z43*KRWRSD25 -> -2.8907344e+08 | AA43: ='PL2026(RS)'!AA43*KRWRSD25 -> -2.2861327e+08 | AB43: ='PL2026(RS)'!AB43*KRWRSD25 -> -1.478828e+08 | AC43: ='PL2026(RS)'!AC43*KRWRSD25 -> -1.2861245e+08 | ... AH43: ='PL2026(RS)'!AH43*KRWRSD25 -> 7.8910389e+08
A44: (이익률) | B44: (Rate) | D44: -0.12328897 | G44: ='PL2026(RS)'!G44 -> -0.17694457 | H44: ='PL2026(RS)'!H44 -> -0.13631889 | I44: ='PL2026(RS)'!I44 -> -0.12271635 | J44: ='PL2026(RS)'!J44 -> -0.18433095 | K44: ='PL2026(RS)'!K44 -> -0.45386393 | L44: ='PL2026(RS)'!L44 -> -0.20382437 | M44: ='PL2026(RS)'!M44 -> -0.34530414 | N44: ='PL2026(RS)'!N44 -> -0.26243627 | ... S44: ='PL2026(RS)'!S44 -> -0.034433296 | V44: ='PL2026(RS)'!V44 -> 0.0071319115 | W44: ='PL2026(RS)'!W44 -> -0.18032336 | X44: ='PL2026(RS)'!X44 -> -0.094702139 | Y44: ='PL2026(RS)'!Y44 -> -0.01950712 | Z44: ='PL2026(RS)'!Z44 -> -0.068129157 | AA44: ='PL2026(RS)'!AA44 -> -0.051989295 | AB44: ='PL2026(RS)'!AB44 -> -0.032040303 | AC44: ='PL2026(RS)'!AC44 -> -0.036202455 | ... AH44: ='PL2026(RS)'!AH44 -> 0.12934637
A45: Ⅳ.판매관리비 | B45: Ⅳ. SELLING & ADMINISTRATIVE EXPENSES | D45: 1.9638703e+08 | G45: ='PL2026(RS)'!G45*KRWRSD24 -> 3.2402193e+09 | H45: ='PL2026(RS)'!H45*KRWRSD24 -> 173811521 | I45: ='PL2026(RS)'!I45*KRWRSD24 -> 1.7290694e+08 | J45: ='PL2026(RS)'!J45*KRWRSD24 -> 2.1221907e+08 | K45: ='PL2026(RS)'!K45*KRWRSD24 -> 1.1504816e+08 | L45: ='PL2026(RS)'!L45*KRWRSD24 -> 2.7410866e+08 | M45: ='PL2026(RS)'!M45*KRWRSD24 -> 5.0068849e+08 | N45: ='PL2026(RS)'!N45*KRWRSD24 -> 1.9356792e+08 | ... S45: ='PL2026(RS)'!S45*KRWRSD24 -> 6.3243101e+08 | V45: ='PL2026(RS)'!V45*KRWRSD25 -> 4.3748161e+09 | W45: ='PL2026(RS)'!W45*KRWRSD25 -> 2.5864224e+08 | X45: ='PL2026(RS)'!X45*KRWRSD25 -> 2.4338275e+08 | Y45: ='PL2026(RS)'!Y45*KRWRSD25 -> 3.4954824e+08 | Z45: ='PL2026(RS)'!Z45*KRWRSD25 -> 2.8218317e+08 | AA45: ='PL2026(RS)'!AA45*KRWRSD25 -> 2.7171903e+08 | AB45: ='PL2026(RS)'!AB45*KRWRSD25 -> 7.9426285e+08 | AC45: ='PL2026(RS)'!AC45*KRWRSD25 -> 2.38078e+08 | ... AH45: ='PL2026(RS)'!AH45*KRWRSD25 -> 8.8259872e+08
A46: 급여 | B46: Salaries, Wages, Bonues etc. | D46: 55452921 | G46: ='PL2026(RS)'!G46*KRWRSD24 -> 9.0329593e+08 | H46: ='PL2026(RS)'!H46*KRWRSD24 -> 71121082 | I46: ='PL2026(RS)'!I46*KRWRSD24 -> 67549357 | J46: ='PL2026(RS)'!J46*KRWRSD24 -> 86696443 | K46: ='PL2026(RS)'!K46*KRWRSD24 -> 51540873 | L46: ='PL2026(RS)'!L46*KRWRSD24 -> 72853697 | M46: ='PL2026(RS)'!M46*KRWRSD24 -> 81188240 | N46: ='PL2026(RS)'!N46*KRWRSD24 -> 79147342 | ... S46: ='PL2026(RS)'!S46*KRWRSD24 -> 81204444 | V46: ='PL2026(RS)'!V46*KRWRSD25 -> 1.0974989e+09 | W46: ='PL2026(RS)'!W46*KRWRSD25 -> 81811280 | X46: ='PL2026(RS)'!X46*KRWRSD25 -> 81811280 | Y46: ='PL2026(RS)'!Y46*KRWRSD25 -> 81811280 | Z46: ='PL2026(RS)'!Z46*KRWRSD25 -> 94673892 | AA46: ='PL2026(RS)'!AA46*KRWRSD25 -> 94673892 | AB46: ='PL2026(RS)'!AB46*KRWRSD25 -> 94673892 | AC46: ='PL2026(RS)'!AC46*KRWRSD25 -> 94673892 | ... AH46: ='PL2026(RS)'!AH46*KRWRSD25 -> 94673892 | AI46: =AVERAGE(W46:AH46) -> 91458239 | AJ46: 급여 | AK46: F
A47: 퇴직급여 | B47: Reserve for retirement allowance | D47: 0 | G47: ='PL2026(RS)'!G47*KRWRSD24 -> 0 | H47: ='PL2026(RS)'!H47*KRWRSD24 -> 0 | I47: ='PL2026(RS)'!I47*KRWRSD24 -> 0 | J47: ='PL2026(RS)'!J47*KRWRSD24 -> 0 | K47: ='PL2026(RS)'!K47*KRWRSD24 -> 0 | L47: ='PL2026(RS)'!L47*KRWRSD24 -> 0 | M47: ='PL2026(RS)'!M47*KRWRSD24 -> 0 | N47: ='PL2026(RS)'!N47*KRWRSD24 -> 0 | ... S47: ='PL2026(RS)'!S47*KRWRSD24 -> 0 | V47: ='PL2026(RS)'!V47*KRWRSD25 -> 0 | W47: ='PL2026(RS)'!W47*KRWRSD25 -> 0 | X47: ='PL2026(RS)'!X47*KRWRSD25 -> 0 | Y47: ='PL2026(RS)'!Y47*KRWRSD25 -> 0 | Z47: ='PL2026(RS)'!Z47*KRWRSD25 -> 0 | AA47: ='PL2026(RS)'!AA47*KRWRSD25 -> 0 | AB47: ='PL2026(RS)'!AB47*KRWRSD25 -> 0 | AC47: ='PL2026(RS)'!AC47*KRWRSD25 -> 0 | ... AH47: ='PL2026(RS)'!AH47*KRWRSD25 -> 0 | AJ47: 퇴직급여 | AK47: F
A48: 도급용역비 | B48: Cost of Service | D48: 0 | G48: ='PL2026(RS)'!G48*KRWRSD24 -> 0 | H48: ='PL2026(RS)'!H48*KRWRSD24 -> 0 | I48: ='PL2026(RS)'!I48*KRWRSD24 -> 0 | J48: ='PL2026(RS)'!J48*KRWRSD24 -> 0 | K48: ='PL2026(RS)'!K48*KRWRSD24 -> 0 | L48: ='PL2026(RS)'!L48*KRWRSD24 -> 0 | M48: ='PL2026(RS)'!M48*KRWRSD24 -> 0 | N48: ='PL2026(RS)'!N48*KRWRSD24 -> 0 | ... S48: ='PL2026(RS)'!S48*KRWRSD24 -> 0 | V48: ='PL2026(RS)'!V48*KRWRSD25 -> 0 | W48: ='PL2026(RS)'!W48*KRWRSD25 -> 0 | X48: ='PL2026(RS)'!X48*KRWRSD25 -> 0 | Y48: ='PL2026(RS)'!Y48*KRWRSD25 -> 0 | Z48: ='PL2026(RS)'!Z48*KRWRSD25 -> 0 | AA48: ='PL2026(RS)'!AA48*KRWRSD25 -> 0 | AB48: ='PL2026(RS)'!AB48*KRWRSD25 -> 0 | AC48: ='PL2026(RS)'!AC48*KRWRSD25 -> 0 | ... AH48: ='PL2026(RS)'!AH48*KRWRSD25 -> 0 | AJ48: 도급용역비
A49: 복리후생비 | B49: Fringe benefits | D49: 0 | G49: ='PL2026(RS)'!G49*KRWRSD24 -> 52270556 | H49: ='PL2026(RS)'!H49*KRWRSD24 -> 0 | I49: ='PL2026(RS)'!I49*KRWRSD24 -> 62500 | J49: ='PL2026(RS)'!J49*KRWRSD24 -> 2271150 | K49: ='PL2026(RS)'!K49*KRWRSD24 -> 0 | L49: ='PL2026(RS)'!L49*KRWRSD24 -> 418874.62 | M49: ='PL2026(RS)'!M49*KRWRSD24 -> 17155531 | N49: ='PL2026(RS)'!N49*KRWRSD24 -> 0 | ... S49: ='PL2026(RS)'!S49*KRWRSD24 -> 31737500 | V49: ='PL2026(RS)'!V49*KRWRSD25 -> 115248000 | W49: ='PL2026(RS)'!W49*KRWRSD25 -> 1008000 | X49: ='PL2026(RS)'!X49*KRWRSD25 -> 4900000 | Y49: ='PL2026(RS)'!Y49*KRWRSD25 -> 9240000 | Z49: ='PL2026(RS)'!Z49*KRWRSD25 -> 700000 | AA49: ='PL2026(RS)'!AA49*KRWRSD25 -> 14000000 | AB49: ='PL2026(RS)'!AB49*KRWRSD25 -> 35000000 | AC49: ='PL2026(RS)'!AC49*KRWRSD25 -> 0 | ... AH49: ='PL2026(RS)'!AH49*KRWRSD25 -> 44800000 | AJ49: 복리후생비 | AK49: F
A50: 동력비 | B50: Electricity | D50: 2340841.8 | G50: ='PL2026(RS)'!G50*KRWRSD24 -> 34859425 | H50: ='PL2026(RS)'!H50*KRWRSD24 -> 2636952.9 | I50: ='PL2026(RS)'!I50*KRWRSD24 -> 2636952.9 | J50: ='PL2026(RS)'!J50*KRWRSD24 -> 2185541.8 | K50: ='PL2026(RS)'!K50*KRWRSD24 -> 2448744 | L50: ='PL2026(RS)'!L50*KRWRSD24 -> 2799908.7 | M50: ='PL2026(RS)'!M50*KRWRSD24 -> 3176029.3 | N50: ='PL2026(RS)'!N50*KRWRSD24 -> 3176029.3 | ... S50: ='PL2026(RS)'!S50*KRWRSD24 -> 3473736.9 | V50: ='PL2026(RS)'!V50*KRWRSD25 -> 40994684 | W50: ='PL2026(RS)'!W50*KRWRSD25 -> 3101056.6 | X50: ='PL2026(RS)'!X50*KRWRSD25 -> 3101056.6 | Y50: ='PL2026(RS)'!Y50*KRWRSD25 -> 2570197.1 | Z50: ='PL2026(RS)'!Z50*KRWRSD25 -> 2879722.9 | AA50: ='PL2026(RS)'!AA50*KRWRSD25 -> 3292692.7 | AB50: ='PL2026(RS)'!AB50*KRWRSD25 -> 3735010.4 | AC50: ='PL2026(RS)'!AC50*KRWRSD25 -> 3735010.4 | ... AH50: ='PL2026(RS)'!AH50*KRWRSD25 -> 4085114.6 | AJ50: 동력비 | AK50: F
A51: 연료비 | B51: Fuel | D51: 0 | G51: ='PL2026(RS)'!G51*KRWRSD24 -> 0 | H51: ='PL2026(RS)'!H51*KRWRSD24 -> 0 | I51: ='PL2026(RS)'!I51*KRWRSD24 -> 0 | J51: ='PL2026(RS)'!J51*KRWRSD24 -> 0 | K51: ='PL2026(RS)'!K51*KRWRSD24 -> 0 | L51: ='PL2026(RS)'!L51*KRWRSD24 -> 0 | M51: ='PL2026(RS)'!M51*KRWRSD24 -> 0 | N51: ='PL2026(RS)'!N51*KRWRSD24 -> 0 | ... S51: ='PL2026(RS)'!S51*KRWRSD24 -> 0 | V51: ='PL2026(RS)'!V51*KRWRSD25 -> 0 | W51: ='PL2026(RS)'!W51*KRWRSD25 -> 0 | X51: ='PL2026(RS)'!X51*KRWRSD25 -> 0 | Y51: ='PL2026(RS)'!Y51*KRWRSD25 -> 0 | Z51: ='PL2026(RS)'!Z51*KRWRSD25 -> 0 | AA51: ='PL2026(RS)'!AA51*KRWRSD25 -> 0 | AB51: ='PL2026(RS)'!AB51*KRWRSD25 -> 0 | AC51: ='PL2026(RS)'!AC51*KRWRSD25 -> 0 | ... AH51: ='PL2026(RS)'!AH51*KRWRSD25 -> 0 | AJ51: 연료비
A52: 여비교통비 | B52: Travel | D52: 1440521.8 | G52: ='PL2026(RS)'!G52*KRWRSD24 -> 16224757 | H52: ='PL2026(RS)'!H52*KRWRSD24 -> 1872445.5 | I52: ='PL2026(RS)'!I52*KRWRSD24 -> 3028782 | J52: ='PL2026(RS)'!J52*KRWRSD24 -> 1004470.9 | K52: ='PL2026(RS)'!K52*KRWRSD24 -> 624473.38 | L52: ='PL2026(RS)'!L52*KRWRSD24 -> 3255900.6 | M52: ='PL2026(RS)'!M52*KRWRSD24 -> 785438.13 | N52: ='PL2026(RS)'!N52*KRWRSD24 -> 585188 | ... S52: ='PL2026(RS)'!S52*KRWRSD24 -> 395169.25 | V52: ='PL2026(RS)'!V52*KRWRSD25 -> 41160000 | W52: ='PL2026(RS)'!W52*KRWRSD25 -> 1400000 | X52: ='PL2026(RS)'!X52*KRWRSD25 -> 1400000 | Y52: ='PL2026(RS)'!Y52*KRWRSD25 -> 7840000 | Z52: ='PL2026(RS)'!Z52*KRWRSD25 -> 2240000 | AA52: ='PL2026(RS)'!AA52*KRWRSD25 -> 4200000 | AB52: ='PL2026(RS)'!AB52*KRWRSD25 -> 5600000 | AC52: ='PL2026(RS)'!AC52*KRWRSD25 -> 2240000 | ... AH52: ='PL2026(RS)'!AH52*KRWRSD25 -> 5600000 | AJ52: 여비교통비 | AK52: F
A53: 대손상각비 | B53: Bad debt expense | G53: ='PL2026(RS)'!G53*KRWRSD24 -> 0 | H53: ='PL2026(RS)'!H53*KRWRSD24 -> 0 | I53: ='PL2026(RS)'!I53*KRWRSD24 -> 0 | J53: ='PL2026(RS)'!J53*KRWRSD24 -> 0 | K53: ='PL2026(RS)'!K53*KRWRSD24 -> 0 | L53: ='PL2026(RS)'!L53*KRWRSD24 -> 0 | M53: ='PL2026(RS)'!M53*KRWRSD24 -> 0 | N53: ='PL2026(RS)'!N53*KRWRSD24 -> 0 | ... S53: ='PL2026(RS)'!S53*KRWRSD24 -> 0 | V53: ='PL2026(RS)'!V53*KRWRSD25 -> 0 | W53: ='PL2026(RS)'!W53*KRWRSD25 -> 0 | X53: ='PL2026(RS)'!X53*KRWRSD25 -> 0 | Y53: ='PL2026(RS)'!Y53*KRWRSD25 -> 0 | Z53: ='PL2026(RS)'!Z53*KRWRSD25 -> 0 | AA53: ='PL2026(RS)'!AA53*KRWRSD25 -> 0 | AB53: ='PL2026(RS)'!AB53*KRWRSD25 -> 0 | AC53: ='PL2026(RS)'!AC53*KRWRSD25 -> 0 | ... AH53: ='PL2026(RS)'!AH53*KRWRSD25 -> 0 | AJ53: 대손상각비
A54: 통신비 | B54: Communications | D54: 76512 | G54: ='PL2026(RS)'!G54*KRWRSD24 -> 530787.5 | H54: ='PL2026(RS)'!H54*KRWRSD24 -> 32212.5 | I54: ='PL2026(RS)'!I54*KRWRSD24 -> 38150 | J54: ='PL2026(RS)'!J54*KRWRSD24 -> 61312.5 | K54: ='PL2026(RS)'!K54*KRWRSD24 -> 38712.5 | L54: ='PL2026(RS)'!L54*KRWRSD24 -> 61125 | M54: ='PL2026(RS)'!M54*KRWRSD24 -> 49825 | N54: ='PL2026(RS)'!N54*KRWRSD24 -> 26600 | ... S54: ='PL2026(RS)'!S54*KRWRSD24 -> 38387.5 | V54: ='PL2026(RS)'!V54*KRWRSD25 -> 821520 | W54: ='PL2026(RS)'!W54*KRWRSD25 -> 68460 | X54: ='PL2026(RS)'!X54*KRWRSD25 -> 68460 | Y54: ='PL2026(RS)'!Y54*KRWRSD25 -> 68460 | Z54: ='PL2026(RS)'!Z54*KRWRSD25 -> 68460 | AA54: ='PL2026(RS)'!AA54*KRWRSD25 -> 68460 | AB54: ='PL2026(RS)'!AB54*KRWRSD25 -> 68460 | AC54: ='PL2026(RS)'!AC54*KRWRSD25 -> 68460 | ... AH54: ='PL2026(RS)'!AH54*KRWRSD25 -> 68460 | AJ54: 통신비 | AK54: F
A55: 수도광열비 | B55: Water, electricity, fuel | D55: 1568878.5 | G55: ='PL2026(RS)'!G55*KRWRSD24 -> 30739469 | H55: ='PL2026(RS)'!H55*KRWRSD24 -> 4142251.8 | I55: ='PL2026(RS)'!I55*KRWRSD24 -> 3894794 | J55: ='PL2026(RS)'!J55*KRWRSD24 -> 2909348.8 | K55: ='PL2026(RS)'!K55*KRWRSD24 -> 2192365.9 | L55: ='PL2026(RS)'!L55*KRWRSD24 -> 1752643.6 | M55: ='PL2026(RS)'!M55*KRWRSD24 -> 1593227 | N55: ='PL2026(RS)'!N55*KRWRSD24 -> 1714869.8 | ... S55: ='PL2026(RS)'!S55*KRWRSD24 -> 3206480.3 | V55: ='PL2026(RS)'!V55*KRWRSD25 -> 36149616 | W55: ='PL2026(RS)'!W55*KRWRSD25 -> 4871288.1 | X55: ='PL2026(RS)'!X55*KRWRSD25 -> 4580277.7 | Y55: ='PL2026(RS)'!Y55*KRWRSD25 -> 3421394.1 | Z55: ='PL2026(RS)'!Z55*KRWRSD25 -> 2578222.3 | AA55: ='PL2026(RS)'!AA55*KRWRSD25 -> 2061108.9 | AB55: ='PL2026(RS)'!AB55*KRWRSD25 -> 1873635 | AC55: ='PL2026(RS)'!AC55*KRWRSD25 -> 2016686.8 | ... AH55: ='PL2026(RS)'!AH55*KRWRSD25 -> 3770820.8 | AJ55: 수도광열비 | AK55: F
A56: 소모품비 | B56: Supplies | D56: 2415042.7 | G56: ='PL2026(RS)'!G56*KRWRSD24 -> 29500108 | H56: ='PL2026(RS)'!H56*KRWRSD24 -> 1433005.6 | I56: ='PL2026(RS)'!I56*KRWRSD24 -> 3237960 | J56: ='PL2026(RS)'!J56*KRWRSD24 -> 2296144.6 | K56: ='PL2026(RS)'!K56*KRWRSD24 -> 6364397.8 | L56: ='PL2026(RS)'!L56*KRWRSD24 -> 2063284.9 | M56: ='PL2026(RS)'!M56*KRWRSD24 -> 2978963.5 | N56: ='PL2026(RS)'!N56*KRWRSD24 -> 1450562.5 | ... S56: ='PL2026(RS)'!S56*KRWRSD24 -> 2118512.1 | V56: ='PL2026(RS)'!V56*KRWRSD25 -> 26712000 | W56: ='PL2026(RS)'!W56*KRWRSD25 -> 2996000 | X56: ='PL2026(RS)'!X56*KRWRSD25 -> 2156000 | Y56: ='PL2026(RS)'!Y56*KRWRSD25 -> 2156000 | Z56: ='PL2026(RS)'!Z56*KRWRSD25 -> 2156000 | AA56: ='PL2026(RS)'!AA56*KRWRSD25 -> 2156000 | AB56: ='PL2026(RS)'!AB56*KRWRSD25 -> 2156000 | AC56: ='PL2026(RS)'!AC56*KRWRSD25 -> 2156000 | ... AH56: ='PL2026(RS)'!AH56*KRWRSD25 -> 2156000 | AJ56: 소모품비 | AK56: F
A57: 접대비 | B57: Entertainment | D57: 6136377 | G57: ='PL2026(RS)'!G57*KRWRSD24 -> 85851462 | H57: ='PL2026(RS)'!H57*KRWRSD24 -> 5877548.2 | I57: ='PL2026(RS)'!I57*KRWRSD24 -> 4843022 | J57: ='PL2026(RS)'!J57*KRWRSD24 -> 12449011 | K57: ='PL2026(RS)'!K57*KRWRSD24 -> 5220222.2 | L57: ='PL2026(RS)'!L57*KRWRSD24 -> 5436104.2 | M57: ='PL2026(RS)'!M57*KRWRSD24 -> 7667596.1 | N57: ='PL2026(RS)'!N57*KRWRSD24 -> 5231665.4 | ... S57: ='PL2026(RS)'!S57*KRWRSD24 -> 8444627.1 | V57: ='PL2026(RS)'!V57*KRWRSD25 -> 74760000 | W57: ='PL2026(RS)'!W57*KRWRSD25 -> 6090000 | X57: ='PL2026(RS)'!X57*KRWRSD25 -> 6090000 | Y57: ='PL2026(RS)'!Y57*KRWRSD25 -> 6510000 | Z57: ='PL2026(RS)'!Z57*KRWRSD25 -> 6090000 | AA57: ='PL2026(RS)'!AA57*KRWRSD25 -> 6090000 | AB57: ='PL2026(RS)'!AB57*KRWRSD25 -> 6510000 | AC57: ='PL2026(RS)'!AC57*KRWRSD25 -> 6090000 | ... AH57: ='PL2026(RS)'!AH57*KRWRSD25 -> 6510000 | AJ57: 접대비 | AK57: F
A58: 도서인쇄비 | B58: Books & subscriptions | D58: 0 | G58: ='PL2026(RS)'!G58*KRWRSD24 -> 0 | H58: ='PL2026(RS)'!H58*KRWRSD24 -> 0 | I58: ='PL2026(RS)'!I58*KRWRSD24 -> 0 | J58: ='PL2026(RS)'!J58*KRWRSD24 -> 0 | K58: ='PL2026(RS)'!K58*KRWRSD24 -> 0 | L58: ='PL2026(RS)'!L58*KRWRSD24 -> 0 | M58: ='PL2026(RS)'!M58*KRWRSD24 -> 0 | N58: ='PL2026(RS)'!N58*KRWRSD24 -> 0 | ... S58: ='PL2026(RS)'!S58*KRWRSD24 -> 0 | V58: ='PL2026(RS)'!V58*KRWRSD25 -> 0 | W58: ='PL2026(RS)'!W58*KRWRSD25 -> 0 | X58: ='PL2026(RS)'!X58*KRWRSD25 -> 0 | Y58: ='PL2026(RS)'!Y58*KRWRSD25 -> 0 | Z58: ='PL2026(RS)'!Z58*KRWRSD25 -> 0 | AA58: ='PL2026(RS)'!AA58*KRWRSD25 -> 0 | AB58: ='PL2026(RS)'!AB58*KRWRSD25 -> 0 | AC58: ='PL2026(RS)'!AC58*KRWRSD25 -> 0 | ... AH58: ='PL2026(RS)'!AH58*KRWRSD25 -> 0 | AJ58: 도서인쇄비
A59: 감가상각비 | B59: Depreciation expense | D59: 7452754.2 | G59: ='PL2026(RS)'!G59*KRWRSD24 -> 98037365 | H59: ='PL2026(RS)'!H59*KRWRSD24 -> 8201397 | I59: ='PL2026(RS)'!I59*KRWRSD24 -> 8260284.5 | J59: ='PL2026(RS)'!J59*KRWRSD24 -> 8207919.4 | K59: ='PL2026(RS)'!K59*KRWRSD24 -> 8158936.3 | L59: ='PL2026(RS)'!L59*KRWRSD24 -> 8189145.6 | M59: ='PL2026(RS)'!M59*KRWRSD24 -> 8189145.6 | N59: ='PL2026(RS)'!N59*KRWRSD24 -> 8189145.6 | ... S59: ='PL2026(RS)'!S59*KRWRSD24 -> 8055472.9 | V59: ='PL2026(RS)'!V59*KRWRSD25 -> 97439000 | W59: ='PL2026(RS)'!W59*KRWRSD25 -> 8119916.7 | X59: ='PL2026(RS)'!X59*KRWRSD25 -> 8119916.7 | Y59: ='PL2026(RS)'!Y59*KRWRSD25 -> 8119916.7 | Z59: ='PL2026(RS)'!Z59*KRWRSD25 -> 8119916.7 | AA59: ='PL2026(RS)'!AA59*KRWRSD25 -> 8119916.7 | AB59: ='PL2026(RS)'!AB59*KRWRSD25 -> 8119916.7 | AC59: ='PL2026(RS)'!AC59*KRWRSD25 -> 8119916.7 | ... AH59: ='PL2026(RS)'!AH59*KRWRSD25 -> 8119916.7 | AJ59: 감가상각비 | AK59: F
A60: 무형자산상각비 | B60: Amortization Expenses on Intangible Assets | D60: 0 | G60: ='PL2026(RS)'!G60*KRWRSD24 -> 0 | H60: ='PL2026(RS)'!H60*KRWRSD24 -> 0 | I60: ='PL2026(RS)'!I60*KRWRSD24 -> 0 | J60: ='PL2026(RS)'!J60*KRWRSD24 -> 0 | K60: ='PL2026(RS)'!K60*KRWRSD24 -> 0 | L60: ='PL2026(RS)'!L60*KRWRSD24 -> 0 | M60: ='PL2026(RS)'!M60*KRWRSD24 -> 0 | N60: ='PL2026(RS)'!N60*KRWRSD24 -> 0 | ... S60: ='PL2026(RS)'!S60*KRWRSD24 -> 0 | V60: ='PL2026(RS)'!V60*KRWRSD25 -> 0 | W60: ='PL2026(RS)'!W60*KRWRSD25 -> 0 | X60: ='PL2026(RS)'!X60*KRWRSD25 -> 0 | Y60: ='PL2026(RS)'!Y60*KRWRSD25 -> 0 | Z60: ='PL2026(RS)'!Z60*KRWRSD25 -> 0 | AA60: ='PL2026(RS)'!AA60*KRWRSD25 -> 0 | AB60: ='PL2026(RS)'!AB60*KRWRSD25 -> 0 | AC60: ='PL2026(RS)'!AC60*KRWRSD25 -> 0 | ... AH60: ='PL2026(RS)'!AH60*KRWRSD25 -> 0 | AJ60: 무형자산상각비
A61: 수선비 | B61: Repairs | D61: 0 | G61: ='PL2026(RS)'!G61*KRWRSD24 -> 0 | H61: ='PL2026(RS)'!H61*KRWRSD24 -> 0 | I61: ='PL2026(RS)'!I61*KRWRSD24 -> 0 | J61: ='PL2026(RS)'!J61*KRWRSD24 -> 0 | K61: ='PL2026(RS)'!K61*KRWRSD24 -> 0 | L61: ='PL2026(RS)'!L61*KRWRSD24 -> 0 | M61: ='PL2026(RS)'!M61*KRWRSD24 -> 0 | N61: ='PL2026(RS)'!N61*KRWRSD24 -> 0 | ... S61: ='PL2026(RS)'!S61*KRWRSD24 -> 0 | V61: ='PL2026(RS)'!V61*KRWRSD25 -> 0 | W61: ='PL2026(RS)'!W61*KRWRSD25 -> 0 | X61: ='PL2026(RS)'!X61*KRWRSD25 -> 0 | Y61: ='PL2026(RS)'!Y61*KRWRSD25 -> 0 | Z61: ='PL2026(RS)'!Z61*KRWRSD25 -> 0 | AA61: ='PL2026(RS)'!AA61*KRWRSD25 -> 0 | AB61: ='PL2026(RS)'!AB61*KRWRSD25 -> 0 | AC61: ='PL2026(RS)'!AC61*KRWRSD25 -> 0 | ... AH61: ='PL2026(RS)'!AH61*KRWRSD25 -> 0 | AJ61: 수선비
A62: 보험료 | B62: Insurance | D62: 1659804.2 | G62: ='PL2026(RS)'!G62*KRWRSD24 -> 43545526 | H62: ='PL2026(RS)'!H62*KRWRSD24 -> 0 | I62: ='PL2026(RS)'!I62*KRWRSD24 -> 7936607.8 | J62: ='PL2026(RS)'!J62*KRWRSD24 -> 718696.5 | K62: ='PL2026(RS)'!K62*KRWRSD24 -> 4303248.9 | L62: ='PL2026(RS)'!L62*KRWRSD24 -> 9589277.5 | M62: ='PL2026(RS)'!M62*KRWRSD24 -> 4075282.1 | N62: ='PL2026(RS)'!N62*KRWRSD24 -> 4075282.1 | ... S62: ='PL2026(RS)'!S62*KRWRSD24 -> 0 | V62: ='PL2026(RS)'!V62*KRWRSD25 -> 74760000 | W62: ='PL2026(RS)'!W62*KRWRSD25 -> 5880000 | X62: ='PL2026(RS)'!X62*KRWRSD25 -> 5880000 | Y62: ='PL2026(RS)'!Y62*KRWRSD25 -> 5880000 | Z62: ='PL2026(RS)'!Z62*KRWRSD25 -> 5880000 | AA62: ='PL2026(RS)'!AA62*KRWRSD25 -> 12880000 | AB62: ='PL2026(RS)'!AB62*KRWRSD25 -> 5460000 | AC62: ='PL2026(RS)'!AC62*KRWRSD25 -> 5460000 | ... AH62: ='PL2026(RS)'!AH62*KRWRSD25 -> 5460000 | AJ62: 보험료 | AK62: F
A63: 광고선전비 | B63: Advertising | D63: 572778.63 | G63: ='PL2026(RS)'!G63*KRWRSD24 -> 2430000 | H63: ='PL2026(RS)'!H63*KRWRSD24 -> 0 | I63: ='PL2026(RS)'!I63*KRWRSD24 -> 0 | J63: ='PL2026(RS)'!J63*KRWRSD24 -> 0 | K63: ='PL2026(RS)'!K63*KRWRSD24 -> 0 | L63: ='PL2026(RS)'!L63*KRWRSD24 -> 0 | M63: ='PL2026(RS)'!M63*KRWRSD24 -> 0 | N63: ='PL2026(RS)'!N63*KRWRSD24 -> 0 | ... S63: ='PL2026(RS)'!S63*KRWRSD24 -> 1215000 | V63: ='PL2026(RS)'!V63*KRWRSD25 -> 8400000 | W63: ='PL2026(RS)'!W63*KRWRSD25 -> 4200000 | X63: ='PL2026(RS)'!X63*KRWRSD25 -> 0 | Y63: ='PL2026(RS)'!Y63*KRWRSD25 -> 0 | Z63: ='PL2026(RS)'!Z63*KRWRSD25 -> 0 | AA63: ='PL2026(RS)'!AA63*KRWRSD25 -> 0 | AB63: ='PL2026(RS)'!AB63*KRWRSD25 -> 4200000 | AC63: ='PL2026(RS)'!AC63*KRWRSD25 -> 0 | ... AH63: ='PL2026(RS)'!AH63*KRWRSD25 -> 0 | AJ63: 광고선전비 | AK63: F
A64: 세금과공과 | B64: Taxes & dues | D64: 10492483 | G64: ='PL2026(RS)'!G64*KRWRSD24 -> 1.7165713e+08 | H64: ='PL2026(RS)'!H64*KRWRSD24 -> 8080966.6 | I64: ='PL2026(RS)'!I64*KRWRSD24 -> 8561016.6 | J64: ='PL2026(RS)'!J64*KRWRSD24 -> 16581101 | K64: ='PL2026(RS)'!K64*KRWRSD24 -> -44787326 | L64: ='PL2026(RS)'!L64*KRWRSD24 -> 77367165 | M64: ='PL2026(RS)'!M64*KRWRSD24 -> 20940015 | N64: ='PL2026(RS)'!N64*KRWRSD24 -> 25906112 | ... S64: ='PL2026(RS)'!S64*KRWRSD24 -> 5812706.4 | V64: ='PL2026(RS)'!V64*KRWRSD25 -> 559860000 | W64: ='PL2026(RS)'!W64*KRWRSD25 -> 43855000 | X64: ='PL2026(RS)'!X64*KRWRSD25 -> 36855000 | Y64: ='PL2026(RS)'!Y64*KRWRSD25 -> 92155000 | Z64: ='PL2026(RS)'!Z64*KRWRSD25 -> 43855000 | AA64: ='PL2026(RS)'!AA64*KRWRSD25 -> 36855000 | AB64: ='PL2026(RS)'!AB64*KRWRSD25 -> 40355000 | AC64: ='PL2026(RS)'!AC64*KRWRSD25 -> 43855000 | ... AH64: ='PL2026(RS)'!AH64*KRWRSD25 -> 12355000 | AJ64: 세금과공과 | AK64: F
A65: 임차료 | B65: Rent | D65: 2819630.8 | G65: ='PL2026(RS)'!G65*KRWRSD24 -> 22427140 | H65: ='PL2026(RS)'!H65*KRWRSD24 -> 2335378.8 | I65: ='PL2026(RS)'!I65*KRWRSD24 -> 2554620 | J65: ='PL2026(RS)'!J65*KRWRSD24 -> 1973826.5 | K65: ='PL2026(RS)'!K65*KRWRSD24 -> 1494100.8 | L65: ='PL2026(RS)'!L65*KRWRSD24 -> 1758157.2 | M65: ='PL2026(RS)'!M65*KRWRSD24 -> 1757610 | N65: ='PL2026(RS)'!N65*KRWRSD24 -> 1757601 | ... S65: ='PL2026(RS)'!S65*KRWRSD24 -> 1760812.5 | V65: ='PL2026(RS)'!V65*KRWRSD25 -> 26124000 | W65: ='PL2026(RS)'!W65*KRWRSD25 -> 2177000 | X65: ='PL2026(RS)'!X65*KRWRSD25 -> 2177000 | Y65: ='PL2026(RS)'!Y65*KRWRSD25 -> 2177000 | Z65: ='PL2026(RS)'!Z65*KRWRSD25 -> 2177000 | AA65: ='PL2026(RS)'!AA65*KRWRSD25 -> 2177000 | AB65: ='PL2026(RS)'!AB65*KRWRSD25 -> 2177000 | AC65: ='PL2026(RS)'!AC65*KRWRSD25 -> 2177000 | ... AH65: ='PL2026(RS)'!AH65*KRWRSD25 -> 2177000 | AJ65: 임차료 | AK65: F
A66: 운반비 | B66: Transportation | D66: 34173599 | G66: ='PL2026(RS)'!G66*KRWRSD24 -> 5.0634028e+08 | H66: ='PL2026(RS)'!H66*KRWRSD24 -> 43447675 | I66: ='PL2026(RS)'!I66*KRWRSD24 -> 35117459 | J66: ='PL2026(RS)'!J66*KRWRSD24 -> 42724681 | K66: ='PL2026(RS)'!K66*KRWRSD24 -> 36209702 | L66: ='PL2026(RS)'!L66*KRWRSD24 -> 36034659 | M66: ='PL2026(RS)'!M66*KRWRSD24 -> 39008290 | N66: ='PL2026(RS)'!N66*KRWRSD24 -> 37583039 | ... S66: ='PL2026(RS)'!S66*KRWRSD24 -> 49655987 | V66: ='PL2026(RS)'!V66*KRWRSD25 -> 6.3852156e+08 | W66: ='PL2026(RS)'!W66*KRWRSD25 -> 49888238 | X66: ='PL2026(RS)'!X66*KRWRSD25 -> 52212560 | Y66: ='PL2026(RS)'!Y66*KRWRSD25 -> 50206993 | Z66: ='PL2026(RS)'!Z66*KRWRSD25 -> 57179959 | AA66: ='PL2026(RS)'!AA66*KRWRSD25 -> 57179959 | AB66: ='PL2026(RS)'!AB66*KRWRSD25 -> 59504281 | AC66: ='PL2026(RS)'!AC66*KRWRSD25 -> 42643037 | ... AH66: ='PL2026(RS)'!AH66*KRWRSD25 -> 58662349 | AJ66: 운반비 | AK66: V
A67: 차량유지비 | B67: Vehicle maintenance | D67: 0 | G67: ='PL2026(RS)'!G67*KRWRSD24 -> 0 | H67: ='PL2026(RS)'!H67*KRWRSD24 -> 0 | I67: ='PL2026(RS)'!I67*KRWRSD24 -> 0 | J67: ='PL2026(RS)'!J67*KRWRSD24 -> 0 | K67: ='PL2026(RS)'!K67*KRWRSD24 -> 0 | L67: ='PL2026(RS)'!L67*KRWRSD24 -> 0 | M67: ='PL2026(RS)'!M67*KRWRSD24 -> 0 | N67: ='PL2026(RS)'!N67*KRWRSD24 -> 0 | ... S67: ='PL2026(RS)'!S67*KRWRSD24 -> 0 | V67: ='PL2026(RS)'!V67*KRWRSD25 -> 0 | W67: ='PL2026(RS)'!W67*KRWRSD25 -> 0 | X67: ='PL2026(RS)'!X67*KRWRSD25 -> 0 | Y67: ='PL2026(RS)'!Y67*KRWRSD25 -> 0 | Z67: ='PL2026(RS)'!Z67*KRWRSD25 -> 0 | AA67: ='PL2026(RS)'!AA67*KRWRSD25 -> 0 | AB67: ='PL2026(RS)'!AB67*KRWRSD25 -> 0 | AC67: ='PL2026(RS)'!AC67*KRWRSD25 -> 0 | ... AH67: ='PL2026(RS)'!AH67*KRWRSD25 -> 0 | AJ67: 차량유지비
A68: 수출수수료 | B68: Export expenses | D68: 0 | G68: ='PL2026(RS)'!G68*KRWRSD24 -> 0 | H68: ='PL2026(RS)'!H68*KRWRSD24 -> 0 | I68: ='PL2026(RS)'!I68*KRWRSD24 -> 0 | J68: ='PL2026(RS)'!J68*KRWRSD24 -> 0 | K68: ='PL2026(RS)'!K68*KRWRSD24 -> 0 | L68: ='PL2026(RS)'!L68*KRWRSD24 -> 0 | M68: ='PL2026(RS)'!M68*KRWRSD24 -> 0 | N68: ='PL2026(RS)'!N68*KRWRSD24 -> 0 | ... S68: ='PL2026(RS)'!S68*KRWRSD24 -> 0 | V68: ='PL2026(RS)'!V68*KRWRSD25 -> 0 | W68: ='PL2026(RS)'!W68*KRWRSD25 -> 0 | X68: ='PL2026(RS)'!X68*KRWRSD25 -> 0 | Y68: ='PL2026(RS)'!Y68*KRWRSD25 -> 0 | Z68: ='PL2026(RS)'!Z68*KRWRSD25 -> 0 | AA68: ='PL2026(RS)'!AA68*KRWRSD25 -> 0 | AB68: ='PL2026(RS)'!AB68*KRWRSD25 -> 0 | AC68: ='PL2026(RS)'!AC68*KRWRSD25 -> 0 | ... AH68: ='PL2026(RS)'!AH68*KRWRSD25 -> 0 | AJ68: 수출수수료
A69: 선임및수송비 | B69: Shipping & Transporting | D69: 0 | G69: ='PL2026(RS)'!G69*KRWRSD24 -> 0 | H69: ='PL2026(RS)'!H69*KRWRSD24 -> 0 | I69: ='PL2026(RS)'!I69*KRWRSD24 -> 0 | J69: ='PL2026(RS)'!J69*KRWRSD24 -> 0 | K69: ='PL2026(RS)'!K69*KRWRSD24 -> 0 | L69: ='PL2026(RS)'!L69*KRWRSD24 -> 0 | M69: ='PL2026(RS)'!M69*KRWRSD24 -> 0 | N69: ='PL2026(RS)'!N69*KRWRSD24 -> 0 | ... S69: ='PL2026(RS)'!S69*KRWRSD24 -> 0 | V69: ='PL2026(RS)'!V69*KRWRSD25 -> 0 | W69: ='PL2026(RS)'!W69*KRWRSD25 -> 0 | X69: ='PL2026(RS)'!X69*KRWRSD25 -> 0 | Y69: ='PL2026(RS)'!Y69*KRWRSD25 -> 0 | Z69: ='PL2026(RS)'!Z69*KRWRSD25 -> 0 | AA69: ='PL2026(RS)'!AA69*KRWRSD25 -> 0 | AB69: ='PL2026(RS)'!AB69*KRWRSD25 -> 0 | AC69: ='PL2026(RS)'!AC69*KRWRSD25 -> 0 | ... AH69: ='PL2026(RS)'!AH69*KRWRSD25 -> 0 | AJ69: 선임및수송비
A70: 기타제수출비 | B70: Other export expenses | D70: 0 | G70: ='PL2026(RS)'!G70*KRWRSD24 -> 0 | H70: ='PL2026(RS)'!H70*KRWRSD24 -> 0 | I70: ='PL2026(RS)'!I70*KRWRSD24 -> 0 | J70: ='PL2026(RS)'!J70*KRWRSD24 -> 0 | K70: ='PL2026(RS)'!K70*KRWRSD24 -> 0 | L70: ='PL2026(RS)'!L70*KRWRSD24 -> 0 | M70: ='PL2026(RS)'!M70*KRWRSD24 -> 0 | N70: ='PL2026(RS)'!N70*KRWRSD24 -> 0 | ... S70: ='PL2026(RS)'!S70*KRWRSD24 -> 0 | V70: ='PL2026(RS)'!V70*KRWRSD25 -> 0 | W70: ='PL2026(RS)'!W70*KRWRSD25 -> 0 | X70: ='PL2026(RS)'!X70*KRWRSD25 -> 0 | Y70: ='PL2026(RS)'!Y70*KRWRSD25 -> 0 | Z70: ='PL2026(RS)'!Z70*KRWRSD25 -> 0 | AA70: ='PL2026(RS)'!AA70*KRWRSD25 -> 0 | AB70: ='PL2026(RS)'!AB70*KRWRSD25 -> 0 | AC70: ='PL2026(RS)'!AC70*KRWRSD25 -> 0 | ... AH70: ='PL2026(RS)'!AH70*KRWRSD25 -> 0 | AJ70: 기타제수출비
A71: 포장비 | B71: Packing | D71: 0 | G71: ='PL2026(RS)'!G71*KRWRSD24 -> 0 | H71: ='PL2026(RS)'!H71*KRWRSD24 -> 0 | I71: ='PL2026(RS)'!I71*KRWRSD24 -> 0 | J71: ='PL2026(RS)'!J71*KRWRSD24 -> 0 | K71: ='PL2026(RS)'!K71*KRWRSD24 -> 0 | L71: ='PL2026(RS)'!L71*KRWRSD24 -> 0 | M71: ='PL2026(RS)'!M71*KRWRSD24 -> 0 | N71: ='PL2026(RS)'!N71*KRWRSD24 -> 0 | ... S71: ='PL2026(RS)'!S71*KRWRSD24 -> 0 | V71: ='PL2026(RS)'!V71*KRWRSD25 -> 0 | W71: ='PL2026(RS)'!W71*KRWRSD25 -> 0 | X71: ='PL2026(RS)'!X71*KRWRSD25 -> 0 | Y71: ='PL2026(RS)'!Y71*KRWRSD25 -> 0 | Z71: ='PL2026(RS)'!Z71*KRWRSD25 -> 0 | AA71: ='PL2026(RS)'!AA71*KRWRSD25 -> 0 | AB71: ='PL2026(RS)'!AB71*KRWRSD25 -> 0 | AC71: ='PL2026(RS)'!AC71*KRWRSD25 -> 0 | ... AH71: ='PL2026(RS)'!AH71*KRWRSD25 -> 0 | AJ71: 포장비
A72: 해외시장개척비 | B72: Overseas market development | D72: 0 | G72: ='PL2026(RS)'!G72*KRWRSD24 -> 0 | H72: ='PL2026(RS)'!H72*KRWRSD24 -> 0 | I72: ='PL2026(RS)'!I72*KRWRSD24 -> 0 | J72: ='PL2026(RS)'!J72*KRWRSD24 -> 0 | K72: ='PL2026(RS)'!K72*KRWRSD24 -> 0 | L72: ='PL2026(RS)'!L72*KRWRSD24 -> 0 | M72: ='PL2026(RS)'!M72*KRWRSD24 -> 0 | N72: ='PL2026(RS)'!N72*KRWRSD24 -> 0 | ... S72: ='PL2026(RS)'!S72*KRWRSD24 -> 0 | V72: ='PL2026(RS)'!V72*KRWRSD25 -> 0 | W72: ='PL2026(RS)'!W72*KRWRSD25 -> 0 | X72: ='PL2026(RS)'!X72*KRWRSD25 -> 0 | Y72: ='PL2026(RS)'!Y72*KRWRSD25 -> 0 | Z72: ='PL2026(RS)'!Z72*KRWRSD25 -> 0 | AA72: ='PL2026(RS)'!AA72*KRWRSD25 -> 0 | AB72: ='PL2026(RS)'!AB72*KRWRSD25 -> 0 | AC72: ='PL2026(RS)'!AC72*KRWRSD25 -> 0 | ... AH72: ='PL2026(RS)'!AH72*KRWRSD25 -> 0 | AJ72: 해외시장개척비
A73: 시험분석비 | B73: Ordinary research costs | D73: 0 | G73: ='PL2026(RS)'!G73*KRWRSD24 -> 0 | H73: ='PL2026(RS)'!H73*KRWRSD24 -> 0 | I73: ='PL2026(RS)'!I73*KRWRSD24 -> 0 | J73: ='PL2026(RS)'!J73*KRWRSD24 -> 0 | K73: ='PL2026(RS)'!K73*KRWRSD24 -> 0 | L73: ='PL2026(RS)'!L73*KRWRSD24 -> 0 | M73: ='PL2026(RS)'!M73*KRWRSD24 -> 0 | N73: ='PL2026(RS)'!N73*KRWRSD24 -> 0 | ... S73: ='PL2026(RS)'!S73*KRWRSD24 -> 0 | V73: ='PL2026(RS)'!V73*KRWRSD25 -> 0 | W73: ='PL2026(RS)'!W73*KRWRSD25 -> 0 | X73: ='PL2026(RS)'!X73*KRWRSD25 -> 0 | Y73: ='PL2026(RS)'!Y73*KRWRSD25 -> 0 | Z73: ='PL2026(RS)'!Z73*KRWRSD25 -> 0 | AA73: ='PL2026(RS)'!AA73*KRWRSD25 -> 0 | AB73: ='PL2026(RS)'!AB73*KRWRSD25 -> 0 | AC73: ='PL2026(RS)'!AC73*KRWRSD25 -> 0 | ... AH73: ='PL2026(RS)'!AH73*KRWRSD25 -> 0 | AJ73: 시험분석비
A74: 판매파열품비 | B74: Sales Return costs | D74: 0 | G74: ='PL2026(RS)'!G74*KRWRSD24 -> 0 | H74: ='PL2026(RS)'!H74*KRWRSD24 -> 0 | I74: ='PL2026(RS)'!I74*KRWRSD24 -> 0 | J74: ='PL2026(RS)'!J74*KRWRSD24 -> 0 | K74: ='PL2026(RS)'!K74*KRWRSD24 -> 0 | L74: ='PL2026(RS)'!L74*KRWRSD24 -> 0 | M74: ='PL2026(RS)'!M74*KRWRSD24 -> 0 | N74: ='PL2026(RS)'!N74*KRWRSD24 -> 0 | ... S74: ='PL2026(RS)'!S74*KRWRSD24 -> 0 | V74: ='PL2026(RS)'!V74*KRWRSD25 -> 0 | W74: ='PL2026(RS)'!W74*KRWRSD25 -> 0 | X74: ='PL2026(RS)'!X74*KRWRSD25 -> 0 | Y74: ='PL2026(RS)'!Y74*KRWRSD25 -> 0 | Z74: ='PL2026(RS)'!Z74*KRWRSD25 -> 0 | AA74: ='PL2026(RS)'!AA74*KRWRSD25 -> 0 | AB74: ='PL2026(RS)'!AB74*KRWRSD25 -> 0 | AC74: ='PL2026(RS)'!AC74*KRWRSD25 -> 0 | ... AH74: ='PL2026(RS)'!AH74*KRWRSD25 -> 0 | AJ74: 판매파열품비
A75: 교육훈련비 | B75: Training | D75: 1770153.8 | G75: ='PL2026(RS)'!G75*KRWRSD24 -> 4898666.9 | H75: ='PL2026(RS)'!H75*KRWRSD24 -> 368750 | I75: ='PL2026(RS)'!I75*KRWRSD24 -> 361250 | J75: ='PL2026(RS)'!J75*KRWRSD24 -> 1312500 | K75: ='PL2026(RS)'!K75*KRWRSD24 -> 640625 | L75: ='PL2026(RS)'!L75*KRWRSD24 -> 750000 | M75: ='PL2026(RS)'!M75*KRWRSD24 -> 0 | N75: ='PL2026(RS)'!N75*KRWRSD24 -> 569090 | ... S75: ='PL2026(RS)'!S75*KRWRSD24 -> 0 | V75: ='PL2026(RS)'!V75*KRWRSD25 -> 2674000 | W75: ='PL2026(RS)'!W75*KRWRSD25 -> 0 | X75: ='PL2026(RS)'!X75*KRWRSD25 -> 1680000 | Y75: ='PL2026(RS)'!Y75*KRWRSD25 -> 280000 | Z75: ='PL2026(RS)'!Z75*KRWRSD25 -> 0 | AA75: ='PL2026(RS)'!AA75*KRWRSD25 -> 168000 | AB75: ='PL2026(RS)'!AB75*KRWRSD25 -> 0 | AC75: ='PL2026(RS)'!AC75*KRWRSD25 -> 210000 | ... AH75: ='PL2026(RS)'!AH75*KRWRSD25 -> 0 | AJ75: 교육훈련비 | AK75: F
A76: 지급수수료 | B76: Service Fees | D76: 36323655 | G76: ='PL2026(RS)'!G76*KRWRSD24 -> 7.8533432e+08 | H76: ='PL2026(RS)'!H76*KRWRSD24 -> 24261855 | I76: ='PL2026(RS)'!I76*KRWRSD24 -> 24824182 | J76: ='PL2026(RS)'!J76*KRWRSD24 -> 30321318 | K76: ='PL2026(RS)'!K76*KRWRSD24 -> 40604096 | L76: ='PL2026(RS)'!L76*KRWRSD24 -> 51639070 | M76: ='PL2026(RS)'!M76*KRWRSD24 -> 86309098 | N76: ='PL2026(RS)'!N76*KRWRSD24 -> 24162444 | ... S76: ='PL2026(RS)'!S76*KRWRSD24 -> 2.0949883e+08 | V76: ='PL2026(RS)'!V76*KRWRSD25 -> 457408000 | W76: ='PL2026(RS)'!W76*KRWRSD25 -> 43176000 | X76: ='PL2026(RS)'!X76*KRWRSD25 -> 32351200 | Y76: ='PL2026(RS)'!Y76*KRWRSD25 -> 77112000 | Z76: ='PL2026(RS)'!Z76*KRWRSD25 -> 53585000 | AA76: ='PL2026(RS)'!AA76*KRWRSD25 -> 27797000 | AB76: ='PL2026(RS)'!AB76*KRWRSD25 -> 21665000 | AC76: ='PL2026(RS)'!AC76*KRWRSD25 -> 24633000 | ... AH76: ='PL2026(RS)'!AH76*KRWRSD25 -> 61040000 | AJ76: 지급수수료 | AK76: F
A77: 창고사용료 | B77: Warehouse fees | D77: 0 | G77: ='PL2026(RS)'!G77*KRWRSD24 -> 0 | H77: ='PL2026(RS)'!H77*KRWRSD24 -> 0 | I77: ='PL2026(RS)'!I77*KRWRSD24 -> 0 | J77: ='PL2026(RS)'!J77*KRWRSD24 -> 0 | K77: ='PL2026(RS)'!K77*KRWRSD24 -> 0 | L77: ='PL2026(RS)'!L77*KRWRSD24 -> 0 | M77: ='PL2026(RS)'!M77*KRWRSD24 -> 0 | N77: ='PL2026(RS)'!N77*KRWRSD24 -> 0 | ... S77: ='PL2026(RS)'!S77*KRWRSD24 -> 0 | V77: ='PL2026(RS)'!V77*KRWRSD25 -> 0 | W77: ='PL2026(RS)'!W77*KRWRSD25 -> 0 | X77: ='PL2026(RS)'!X77*KRWRSD25 -> 0 | Y77: ='PL2026(RS)'!Y77*KRWRSD25 -> 0 | Z77: ='PL2026(RS)'!Z77*KRWRSD25 -> 0 | AA77: ='PL2026(RS)'!AA77*KRWRSD25 -> 0 | AB77: ='PL2026(RS)'!AB77*KRWRSD25 -> 0 | AC77: ='PL2026(RS)'!AC77*KRWRSD25 -> 0 | ... AH77: ='PL2026(RS)'!AH77*KRWRSD25 -> 0 | AJ77: 창고사용료
A78: 기술료 | B78: Technical assistance Expenses | D78: 25263127 | G78: ='PL2026(RS)'!G78*KRWRSD24 -> 4.5162796e+08 | H78: ='PL2026(RS)'!H78*KRWRSD24 -> 0 | I78: ='PL2026(RS)'!I78*KRWRSD24 -> 0 | J78: ='PL2026(RS)'!J78*KRWRSD24 -> 0 | K78: ='PL2026(RS)'!K78*KRWRSD24 -> 0 | L78: ='PL2026(RS)'!L78*KRWRSD24 -> 0 | M78: ='PL2026(RS)'!M78*KRWRSD24 -> 2.2581398e+08 | N78: ='PL2026(RS)'!N78*KRWRSD24 -> 0 | ... S78: ='PL2026(RS)'!S78*KRWRSD24 -> 2.2581398e+08 | V78: ='PL2026(RS)'!V78*KRWRSD25 -> 1.0762848e+09 | W78: ='PL2026(RS)'!W78*KRWRSD25 -> 0 | X78: ='PL2026(RS)'!X78*KRWRSD25 -> 0 | Y78: ='PL2026(RS)'!Y78*KRWRSD25 -> 0 | Z78: ='PL2026(RS)'!Z78*KRWRSD25 -> 0 | AA78: ='PL2026(RS)'!AA78*KRWRSD25 -> 0 | AB78: ='PL2026(RS)'!AB78*KRWRSD25 -> 5.0316466e+08 | AC78: ='PL2026(RS)'!AC78*KRWRSD25 -> 0 | ... AH78: ='PL2026(RS)'!AH78*KRWRSD25 -> 5.7312017e+08 | AJ78: 기술료 | AK78: V
A79: 해외지사유지비 | B79: Oversea branch Maintenance Expenses | D79: 0 | G79: ='PL2026(RS)'!G79*KRWRSD24 -> 0 | H79: ='PL2026(RS)'!H79*KRWRSD24 -> 0 | I79: ='PL2026(RS)'!I79*KRWRSD24 -> 0 | J79: ='PL2026(RS)'!J79*KRWRSD24 -> 0 | K79: ='PL2026(RS)'!K79*KRWRSD24 -> 0 | L79: ='PL2026(RS)'!L79*KRWRSD24 -> 0 | M79: ='PL2026(RS)'!M79*KRWRSD24 -> 0 | N79: ='PL2026(RS)'!N79*KRWRSD24 -> 0 | ... S79: ='PL2026(RS)'!S79*KRWRSD24 -> 0 | V79: ='PL2026(RS)'!V79*KRWRSD25 -> 0 | W79: ='PL2026(RS)'!W79*KRWRSD25 -> 0 | X79: ='PL2026(RS)'!X79*KRWRSD25 -> 0 | Y79: ='PL2026(RS)'!Y79*KRWRSD25 -> 0 | Z79: ='PL2026(RS)'!Z79*KRWRSD25 -> 0 | AA79: ='PL2026(RS)'!AA79*KRWRSD25 -> 0 | AB79: ='PL2026(RS)'!AB79*KRWRSD25 -> 0 | AC79: ='PL2026(RS)'!AC79*KRWRSD25 -> 0 | ... AH79: ='PL2026(RS)'!AH79*KRWRSD25 -> 0 | AJ79: 해외지사유지비
A80: 상표사용료 | B80: Trademarks Fees | D80: 0 | G80: ='PL2026(RS)'!G80*KRWRSD24 -> 0 | H80: ='PL2026(RS)'!H80*KRWRSD24 -> 0 | I80: ='PL2026(RS)'!I80*KRWRSD24 -> 0 | J80: ='PL2026(RS)'!J80*KRWRSD24 -> 0 | K80: ='PL2026(RS)'!K80*KRWRSD24 -> 0 | L80: ='PL2026(RS)'!L80*KRWRSD24 -> 0 | M80: ='PL2026(RS)'!M80*KRWRSD24 -> 0 | N80: ='PL2026(RS)'!N80*KRWRSD24 -> 0 | ... S80: ='PL2026(RS)'!S80*KRWRSD24 -> 0 | V80: ='PL2026(RS)'!V80*KRWRSD25 -> 0 | W80: ='PL2026(RS)'!W80*KRWRSD25 -> 0 | X80: ='PL2026(RS)'!X80*KRWRSD25 -> 0 | Y80: ='PL2026(RS)'!Y80*KRWRSD25 -> 0 | Z80: ='PL2026(RS)'!Z80*KRWRSD25 -> 0 | AA80: ='PL2026(RS)'!AA80*KRWRSD25 -> 0 | AB80: ='PL2026(RS)'!AB80*KRWRSD25 -> 0 | AC80: ='PL2026(RS)'!AC80*KRWRSD25 -> 0 | ... AH80: ='PL2026(RS)'!AH80*KRWRSD25 -> 0 | AJ80: 상표사용료
A81: 판매장려금 | B81: Sales promotion | D81: 0 | G81: ='PL2026(RS)'!G81*KRWRSD24 -> 0 | H81: ='PL2026(RS)'!H81*KRWRSD24 -> 0 | I81: ='PL2026(RS)'!I81*KRWRSD24 -> 0 | J81: ='PL2026(RS)'!J81*KRWRSD24 -> 0 | K81: ='PL2026(RS)'!K81*KRWRSD24 -> 0 | L81: ='PL2026(RS)'!L81*KRWRSD24 -> 0 | M81: ='PL2026(RS)'!M81*KRWRSD24 -> 0 | N81: ='PL2026(RS)'!N81*KRWRSD24 -> 0 | ... S81: ='PL2026(RS)'!S81*KRWRSD24 -> 0 | V81: ='PL2026(RS)'!V81*KRWRSD25 -> 0 | W81: ='PL2026(RS)'!W81*KRWRSD25 -> 0 | X81: ='PL2026(RS)'!X81*KRWRSD25 -> 0 | Y81: ='PL2026(RS)'!Y81*KRWRSD25 -> 0 | Z81: ='PL2026(RS)'!Z81*KRWRSD25 -> 0 | AA81: ='PL2026(RS)'!AA81*KRWRSD25 -> 0 | AB81: ='PL2026(RS)'!AB81*KRWRSD25 -> 0 | AC81: ='PL2026(RS)'!AC81*KRWRSD25 -> 0 | ... AH81: ='PL2026(RS)'!AH81*KRWRSD25 -> 0 | AJ81: 판매장려금
A82: 경상개발비 | B82: Ordinary development costs | D82: 0 | G82: ='PL2026(RS)'!G82*KRWRSD24 -> 0 | H82: ='PL2026(RS)'!H82*KRWRSD24 -> 0 | I82: ='PL2026(RS)'!I82*KRWRSD24 -> 0 | J82: ='PL2026(RS)'!J82*KRWRSD24 -> 0 | K82: ='PL2026(RS)'!K82*KRWRSD24 -> 0 | L82: ='PL2026(RS)'!L82*KRWRSD24 -> 0 | M82: ='PL2026(RS)'!M82*KRWRSD24 -> 0 | N82: ='PL2026(RS)'!N82*KRWRSD24 -> 0 | ... S82: ='PL2026(RS)'!S82*KRWRSD24 -> 0 | V82: ='PL2026(RS)'!V82*KRWRSD25 -> 0 | W82: ='PL2026(RS)'!W82*KRWRSD25 -> 0 | X82: ='PL2026(RS)'!X82*KRWRSD25 -> 0 | Y82: ='PL2026(RS)'!Y82*KRWRSD25 -> 0 | Z82: ='PL2026(RS)'!Z82*KRWRSD25 -> 0 | AA82: ='PL2026(RS)'!AA82*KRWRSD25 -> 0 | AB82: ='PL2026(RS)'!AB82*KRWRSD25 -> 0 | AC82: ='PL2026(RS)'!AC82*KRWRSD25 -> 0 | ... AH82: ='PL2026(RS)'!AH82*KRWRSD25 -> 0 | AJ82: 경상개발비
A83: 반품차손비 | B83: Sales rebate | D83: 0 | G83: ='PL2026(RS)'!G83*KRWRSD24 -> 0 | H83: ='PL2026(RS)'!H83*KRWRSD24 -> 0 | I83: ='PL2026(RS)'!I83*KRWRSD24 -> 0 | J83: ='PL2026(RS)'!J83*KRWRSD24 -> 0 | K83: ='PL2026(RS)'!K83*KRWRSD24 -> 0 | L83: ='PL2026(RS)'!L83*KRWRSD24 -> 0 | M83: ='PL2026(RS)'!M83*KRWRSD24 -> 0 | N83: ='PL2026(RS)'!N83*KRWRSD24 -> 0 | ... S83: ='PL2026(RS)'!S83*KRWRSD24 -> 0 | V83: ='PL2026(RS)'!V83*KRWRSD25 -> 0 | W83: ='PL2026(RS)'!W83*KRWRSD25 -> 0 | X83: ='PL2026(RS)'!X83*KRWRSD25 -> 0 | Y83: ='PL2026(RS)'!Y83*KRWRSD25 -> 0 | Z83: ='PL2026(RS)'!Z83*KRWRSD25 -> 0 | AA83: ='PL2026(RS)'!AA83*KRWRSD25 -> 0 | AB83: ='PL2026(RS)'!AB83*KRWRSD25 -> 0 | AC83: ='PL2026(RS)'!AC83*KRWRSD25 -> 0 | ... AH83: ='PL2026(RS)'!AH83*KRWRSD25 -> 0 | AJ83: 반품차손비
A84: 견본비 | B84: Samples | D84: 6415830.3 | G84: ='PL2026(RS)'!G84*KRWRSD24 -> 648424.92 | H84: ='PL2026(RS)'!H84*KRWRSD24 -> 0 | I84: ='PL2026(RS)'!I84*KRWRSD24 -> 0 | J84: ='PL2026(RS)'!J84*KRWRSD24 -> 505605 | K84: ='PL2026(RS)'!K84*KRWRSD24 -> -5012.1929 | L84: ='PL2026(RS)'!L84*KRWRSD24 -> 139646.33 | M84: ='PL2026(RS)'!M84*KRWRSD24 -> 221.15375 | N84: ='PL2026(RS)'!N84*KRWRSD24 -> -7047.319 | ... S84: ='PL2026(RS)'!S84*KRWRSD24 -> -638.12857 | V84: ='PL2026(RS)'!V84*KRWRSD25 -> 0 | W84: ='PL2026(RS)'!W84*KRWRSD25 -> 0 | X84: ='PL2026(RS)'!X84*KRWRSD25 -> 0 | Y84: ='PL2026(RS)'!Y84*KRWRSD25 -> 0 | Z84: ='PL2026(RS)'!Z84*KRWRSD25 -> 0 | AA84: ='PL2026(RS)'!AA84*KRWRSD25 -> 0 | AB84: ='PL2026(RS)'!AB84*KRWRSD25 -> 0 | AC84: ='PL2026(RS)'!AC84*KRWRSD25 -> 0 | ... AH84: ='PL2026(RS)'!AH84*KRWRSD25 -> 0 | AJ84: 견본비 | AK84: F
A85: 잡비 | B85: Miscellaneous expense | D85: 12120 | G85: ='PL2026(RS)'!G85*KRWRSD24 -> 0 | H85: ='PL2026(RS)'!H85*KRWRSD24 -> 0 | I85: ='PL2026(RS)'!I85*KRWRSD24 -> 0 | J85: ='PL2026(RS)'!J85*KRWRSD24 -> 0 | K85: ='PL2026(RS)'!K85*KRWRSD24 -> 0 | L85: ='PL2026(RS)'!L85*KRWRSD24 -> 0 | M85: ='PL2026(RS)'!M85*KRWRSD24 -> 0 | N85: ='PL2026(RS)'!N85*KRWRSD24 -> 0 | ... S85: ='PL2026(RS)'!S85*KRWRSD24 -> 0 | V85: ='PL2026(RS)'!V85*KRWRSD25 -> 0 | W85: ='PL2026(RS)'!W85*KRWRSD25 -> 0 | X85: ='PL2026(RS)'!X85*KRWRSD25 -> 0 | Y85: ='PL2026(RS)'!Y85*KRWRSD25 -> 0 | Z85: ='PL2026(RS)'!Z85*KRWRSD25 -> 0 | AA85: ='PL2026(RS)'!AA85*KRWRSD25 -> 0 | AB85: ='PL2026(RS)'!AB85*KRWRSD25 -> 0 | AC85: ='PL2026(RS)'!AC85*KRWRSD25 -> 0 | ... AH85: ='PL2026(RS)'!AH85*KRWRSD25 -> 0 | AJ85: 잡비 | AK85: F
A86: Ⅴ.영업이익 | B86: Ⅴ.OPERATING INCOME (or LOSS) | D86: -5.6931072e+08 | G86: ='PL2026(RS)'!G86*KRWRSD24 -> -8.4298971e+09 | H86: ='PL2026(RS)'!H86*KRWRSD24 -> -5.9177129e+08 | I86: ='PL2026(RS)'!I86*KRWRSD24 -> -4.4987659e+08 | J86: ='PL2026(RS)'!J86*KRWRSD24 -> -6.5394805e+08 | K86: ='PL2026(RS)'!K86*KRWRSD24 -> -7.7167726e+08 | L86: ='PL2026(RS)'!L86*KRWRSD24 -> -6.1071125e+08 | M86: ='PL2026(RS)'!M86*KRWRSD24 -> -1.0914547e+09 | N86: ='PL2026(RS)'!N86*KRWRSD24 -> -8.1282327e+08 | ... S86: ='PL2026(RS)'!S86*KRWRSD24 -> -7.4304938e+08 | V86: ='PL2026(RS)'!V86*KRWRSD25 -> -3.9910177e+09 | W86: ='PL2026(RS)'!W86*KRWRSD25 -> -8.6567406e+08 | X86: ='PL2026(RS)'!X86*KRWRSD25 -> -6.1543841e+08 | Y86: ='PL2026(RS)'!Y86*KRWRSD25 -> -4.3942395e+08 | Z86: ='PL2026(RS)'!Z86*KRWRSD25 -> -5.7125662e+08 | AA86: ='PL2026(RS)'!AA86*KRWRSD25 -> -5.003323e+08 | AB86: ='PL2026(RS)'!AB86*KRWRSD25 -> -9.4214565e+08 | AC86: ='PL2026(RS)'!AC86*KRWRSD25 -> -3.6669045e+08 | ... AH86: ='PL2026(RS)'!AH86*KRWRSD25 -> -93494836
A87: (이익률) | B87: (Rate) | D87: -0.18821472 | G87: ='PL2026(RS)'!G87 -> -0.28742141 | H87: ='PL2026(RS)'!H87 -> -0.19300806 | I87: ='PL2026(RS)'!I87 -> -0.19932586 | J87: ='PL2026(RS)'!J87 -> -0.27288874 | K87: ='PL2026(RS)'!K87 -> -0.53338555 | L87: ='PL2026(RS)'!L87 -> -0.36980653 | M87: ='PL2026(RS)'!M87 -> -0.63795767 | N87: ='PL2026(RS)'!N87 -> -0.34446906 | ... S87: ='PL2026(RS)'!S87 -> -0.23129647 | V87: ='PL2026(RS)'!V87 -> -0.074162853 | W87: ='PL2026(RS)'!W87 -> -0.25715498 | X87: ='PL2026(RS)'!X87 -> -0.15665219 | Y87: ='PL2026(RS)'!Y87 -> -0.095375002 | Z87: ='PL2026(RS)'!Z87 -> -0.13463441 | AA87: ='PL2026(RS)'!AA87 -> -0.11378134 | AB87: ='PL2026(RS)'!AB87 -> -0.20412538 | AC87: ='PL2026(RS)'!AC87 -> -0.1032178 | ... AH87: ='PL2026(RS)'!AH87 -> -0.015325254

Sheet PL2026(RS)
A1: Plofit and Loss statement(Result & Plan, not fixed yet)
A2: MONTH
H3: Result of 2025 | W3: Plan of 2026
H4: CY2025 | I4: CY2025 | J4: CY2025 | K4: CY2025 | L4: CY2025 | M4: CY2025 | N4: CY2025 | O4: CY2025 | P4: CY2025 | Q4: CY2025 | R4: CY2025 | S4: CY2025 | W4: CY2026 | X4: CY2026 | Y4: CY2026 | Z4: CY2026 | AA4: CY2026 | AB4: CY2026 | AC4: CY2026 | AD4: CY2026 | AE4: CY2026 | AF4: CY2026 | AG4: CY2026 | AH4: CY2026 | AI4: % | AJ4: YoY | AK4: Note
A5: 구분 | C5: 계정번호 | D5: FY 2022 | G5: CY2025 | H5: 1 | I5: 2 | J5: 3 | K5: 4 | L5: 5 | M5: 6 | N5: 7 | O5: 8 | P5: 9 | Q5: 10 | R5: 11 | S5: 12 | V5: CY 2026 | W5: 1 | X5: 2 | Y5: 3 | Z5: 4 | AA5: 5 | AB5: 6 | AC5: 7 | AD5: 8 | AE5: 9 | AF5: 10 | AG5: 11 | AH5: 12
A6: Ⅰ. 매출액 | B6: Ⅰ. SALES | D6: 3.0247938e+09 | G6: =SUM(H6:S6) -> 2.3463519e+09 | H6: 2.4528355e+08 | I6: 1.8055924e+08 | J6: 1.9171126e+08 | K6: 1.1574026e+08 | L6: =+L7+L15+L19 -> 1.3211476e+08 | M6: =+M7+M15+M19 -> 1.368686e+08 | N6: =+N7+N15+N19 -> 1.8877127e+08 | O6: =+O7+O15+O19 -> 1.978604e+08 | P6: =+P7+P15+P19 -> 2.0831078e+08 | Q6: =+Q7+Q15+Q19 -> 2.3512527e+08 | R6: =+R7+R15+R19 -> 2.5700328e+08 | S6: =+S7+S15+S19 -> 2.5700328e+08 | V6: =SUM(W6:AH6) -> 3.8438744e+09 | W6: =W7+W15+W19 -> 240453684 | X6: =X7+X15+X19 -> 280620948 | Y6: =Y7+Y15+Y19 -> 329094880 | Z6: =Z7+Z15+Z19 -> 303072930 | AA6: =AA7+AA15+AA19 -> 314093880 | AB6: =AB7+AB15+AB19 -> 329680310 | AC6: =AC7+AC15+AC19 -> 253756370 | AD6: =AD7+AD15+AD19 -> 218356266 | ... AH6: =AH7+AH15+AH19 -> 4.3576457e+08 | AJ6: =V6/G6 -> 1.6382344
A7: 1.제품매출 | B7: 1. Product | D7: 2.5401687e+09 | G7: =SUM(H7:S7) -> 2.3091893e+09 | H7: 2.4077378e+08 | I7: 1.7456604e+08 | J7: 1.868564e+08 | K7: 1.1565954e+08 | L7: =SUM(L8:L13) -> 1.2502641e+08 | M7: =SUM(M8:M13) -> 1.3665211e+08 | N7: =SUM(N8:N13) -> 1.8852721e+08 | O7: =SUM(O8:O13) -> 1.9115193e+08 | P7: =SUM(P8:P14) -> 2.081033e+08 | Q7: =SUM(Q8:Q14) -> 2.3474851e+08 | R7: =SUM(R8:R14) -> 2.5356202e+08 | S7: =SUM(S8:S14) -> 2.5356202e+08 | V7: =SUM(W7:AH7) -> 3.8438744e+09 | W7: =SUM(W8:W14) -> 240453684 | X7: =SUM(X8:X14) -> 280620948 | Y7: =SUM(Y8:Y14) -> 329094880 | Z7: =SUM(Z8:Z14) -> 303072930 | AA7: =SUM(AA8:AA14) -> 314093880 | AB7: =SUM(AB8:AB14) -> 329680310 | AC7: =SUM(AC8:AC14) -> 253756370 | AD7: =SUM(AD8:AD14) -> 218356266 | ... AH7: =SUM(AH8:AH14) -> 4.3576457e+08 | AJ7: =V7/G7 -> 1.6645991
B8: W/H sales (KSCP) | C8: 613000 | D8: 1.6360678e+09 | G8: =SUM(H8:S8) -> 2.5855208e+08 | H8: 61594424 | I8: 39490303 | J8: 11354909 | K8: 16658768 | L8: 28723988 | M8: 34506336 | N8: 26233273 | O8: 12370463 | P8: 10894738 | Q8: 10488478 | R8: 3118201.9 | S8: =R8 -> 3118201.9 | V8: =SUM(W8:AH8) -> 573998084 | W8: ='RV(RS)'!W7+'RV(RS)'!W10+'RV(RS)'!W14+'RV(RS)'!W32+'RV(RS)'!W34 -> 36263484 | X8: ='RV(RS)'!X7+'RV(RS)'!X10+'RV(RS)'!X14+'RV(RS)'!X32+'RV(RS)'!X34 -> 42399048 | Y8: ='RV(RS)'!Y7+'RV(RS)'!Y10+'RV(RS)'!Y14+'RV(RS)'!Y32+'RV(RS)'!Y34 -> 45497380 | Z8: ='RV(RS)'!Z7+'RV(RS)'!Z10+'RV(RS)'!Z14+'RV(RS)'!Z32+'RV(RS)'!Z34 -> 45375180 | AA8: ='RV(RS)'!AA7+'RV(RS)'!AA10+'RV(RS)'!AA14+'RV(RS)'!AA32+'RV(RS)'!AA34 -> 45191880 | AB8: ='RV(RS)'!AB7+'RV(RS)'!AB10+'RV(RS)'!AB14+'RV(RS)'!AB32+'RV(RS)'!AB34 -> 62902460 | AC8: ='RV(RS)'!AC7+'RV(RS)'!AC10+'RV(RS)'!AC14+'RV(RS)'!AC32+'RV(RS)'!AC34 -> 47192120 | AD8: ='RV(RS)'!AD7+'RV(RS)'!AD10+'RV(RS)'!AD14+'RV(RS)'!AD32+'RV(RS)'!AD34 -> 84762516 | ... AH8: ='RV(RS)'!AH7+'RV(RS)'!AH10+'RV(RS)'!AH14+'RV(RS)'!AH32+'RV(RS)'!AH34 -> 22471056 | AJ8: =V8/G8 -> 2.2200482 | AK8: KSCP 하네스 매출
B9: SMA sales (KSCP) | C9: 613001 | G9: =SUM(H9:S9) -> 8.3598811e+08 | H9: 47261274 | I9: 48365651 | J9: 77479584 | K9: 62179559 | L9: 68778939 | M9: 48264404 | N9: 74036614 | O9: 40818096 | P9: 64441568 | Q9: 89885265 | R9: 1.0723858e+08 | S9: =R9 -> 1.0723858e+08 | V9: =SUM(W9:AH9) -> 1101655950 | W9: ='RV(RS)'!W37 -> 84234600 | X9: ='RV(RS)'!X37 -> 98273700 | Y9: ='RV(RS)'!Y37 -> 116992500 | Z9: ='RV(RS)'!Z37 -> 104421150 | AA9: ='RV(RS)'!AA37 -> 108961200 | AB9: ='RV(RS)'!AB37 -> 113501250 | AC9: ='RV(RS)'!AC37 -> 95341050 | AD9: ='RV(RS)'!AD37 -> 68100750 | ... AH9: ='RV(RS)'!AH37 -> 82437750 | AJ9: =V9/G9 -> 1.317789 | AK9: KSCP EV2020 매출
B10: SMA sales (SKOH) | C10: 615000 | D10: 902893494 | G10: =SUM(H10:S10) -> 64158921 | H10: 25632836 | I10: 17077072 | J10: 21449013 | K10: 0 | L10: 0 | M10: 0 | N10: 0 | O10: 0 | P10: 0 | Q10: 0 | R10: 0 | S10: =R10 -> 0 | V10: =SUM(W10:AH10) -> 0 | W10: ='RV(RS)'!W46 -> 0 | X10: ='RV(RS)'!X46 -> 0 | Y10: ='RV(RS)'!Y46 -> 0 | Z10: ='RV(RS)'!Z46 -> 0 | AA10: ='RV(RS)'!AA46 -> 0 | AB10: ='RV(RS)'!AB46 -> 0 | AC10: ='RV(RS)'!AC46 -> 0 | AD10: ='RV(RS)'!AD46 -> 0 | ... AH10: ='RV(RS)'!AH46 -> 0 | AJ10: =V10/G10 -> 0 | AK10: GEN3
B11: SMA sales (SKBM) | C11: 615001 | G11: =SUM(H11:S11) -> 1.1439233e+09 | H11: 1.0598004e+08 | I11: 69633018 | J11: 76572896 | K11: 36811710 | L11: 27523486 | M11: 53881369 | N11: 88257319 | O11: 1.3338595e+08 | P11: 1.3229607e+08 | Q11: 1.3317093e+08 | R11: 1.4320524e+08 | S11: =R11 -> 1.4320524e+08 | V11: =SUM(W11:AH11) -> 1417866000 | W11: ='RV(RS)'!W42 -> 119955600 | X11: ='RV(RS)'!X42 -> 139948200 | Y11: ='RV(RS)'!Y42 -> 166605000 | Z11: ='RV(RS)'!Z42 -> 153276600 | AA11: ='RV(RS)'!AA42 -> 159940800 | AB11: ='RV(RS)'!AB42 -> 153276600 | AC11: ='RV(RS)'!AC42 -> 111223200 | AD11: ='RV(RS)'!AD42 -> 65493000 | ... AH11: ='RV(RS)'!AH42 -> 86175000 | AJ11: =V11/G11 -> 1.2394765 | AK11: MEB
B12: SMA sales (KSC) | C12: 611000 | D12: 1207471.8 | G12: =SUM(H12:S12) -> 318201.64 | H12: 305205.76 | I12: 0 | J12: 0 | K12: 9502.71 | L12: 0 | M12: 0 | N12: 0 | O12: 0 | P12: 0 | Q12: 3493.17 | R12: 0 | S12: =R12 -> 0 | V12: =SUM(W12:AH12) -> 0 | AJ12: =V12/G12 -> 0
B13: W/H sales (KCTR) | C13: 613004 | D13: 1207471.8 | G13: =SUM(H13:S13) -> 4577418.3 | H13: 0 | I13: 0 | J13: 0 | K13: 0 | L13: 0 | M13: 0 | N13: 0 | O13: 4577418.3 | P13: 0 | Q13: 0 | R13: 0 | S13: =R13 -> 0 | V13: =SUM(W13:AH13) -> 7.5035434e+08 | W13: ='RV(RS)'!W22 -> 0 | X13: ='RV(RS)'!X22 -> 0 | Y13: ='RV(RS)'!Y22 -> 0 | Z13: ='RV(RS)'!Z22 -> 0 | AA13: ='RV(RS)'!AA22 -> 0 | AB13: ='RV(RS)'!AB22 -> 0 | AC13: ='RV(RS)'!AC22 -> 0 | AD13: ='RV(RS)'!AD22 -> 0 | ... AH13: ='RV(RS)'!AH22 -> 2.4468076e+08 | AJ13: =V13/G13 -> 163.92523 | AK13: KCTR Ford
B14: W/H sales (FORD) | C14: 615002 | D14: 1207471.8 | G14: =SUM(H14:S14) -> 1671271.6 | H14: 0 | I14: 0 | J14: 0 | K14: 0 | L14: 0 | M14: 0 | N14: 0 | O14: 0 | P14: 470928.23 | Q14: 1200343.4 | R14: 0 | S14: =R14 -> 0 | V14: =SUM(W14:AH14) -> 0 | AJ14: =V14/G14 -> 0
A15: 2. 상품 매출 | B15: 2 Merchandise | D15: 2.1913182e+08 | G15: =SUM(H15:S15) -> 20958741 | H15: 4469122.8 | I15: 5714411.8 | J15: 4777239.5 | K15: 0 | L15: =SUM(L16:L18) -> 0 | M15: =SUM(M16:M18) -> 0 | N15: =SUM(N16:N18) -> 0 | O15: =SUM(O16:O18) -> 0 | P15: =SUM(P16:P18) -> 0 | Q15: =SUM(Q16:Q18) -> 314591.78 | R15: =SUM(R16:R18) -> 2841687.6 | S15: =SUM(S16:S18) -> 2841687.6 | V15: =SUM(W15:AH15) -> 0 | W15: =SUM(W16:W18) -> 0 | X15: =SUM(X16:X18) -> 0 | Y15: =SUM(Y16:Y18) -> 0 | Z15: =SUM(Z16:Z18) -> 0 | AA15: =SUM(AA16:AA18) -> 0 | AB15: =SUM(AB16:AB18) -> 0 | AC15: =SUM(AC16:AC18) -> 0 | AD15: =SUM(AD16:AD18) -> 0 | ... AH15: =SUM(AH16:AH18) -> 0 | AJ15: =V15/G15 -> 0 | AK15: GEN3
B16: W/H sales | C16: 605000 | D16: 0 | G16: =SUM(H16:S16) -> 0 | H16: 0 | I16: 0 | J16: 0 | K16: 0 | L16: 0 | M16: 0 | N16: 0 | O16: 0 | P16: 0 | Q16: =T16-SUM(H16:P16) -> 0 | R16: 0 | S16: =R16 -> 0 | V16: =SUM(W16:AH16) -> 0
B17: W/H sales | C17: 603000 | G17: =SUM(H17:S17) -> 0 | H17: 0 | I17: 0 | J17: 0 | K17: 0 | L17: 0 | M17: 0 | N17: 0 | O17: 0 | P17: 0 | Q17: =T17-SUM(H17:P17) -> 0 | R17: 0 | S17: =R17 -> 0 | V17: =SUM(W17:AH17) -> 0
B18: SMA sales | C18: 605901 | D18: 2.1231184e+08 | G18: =SUM(H18:S18) -> 20958741 | H18: 4469122.8 | I18: 5714411.8 | J18: 4777239.5 | K18: 0 | L18: 0 | M18: 0 | N18: 0 | O18: 0 | P18: 0 | Q18: 314591.78 | R18: 2841687.6 | S18: =R18 -> 2841687.6 | V18: =SUM(W18:AH18) -> 0 | W18: ='RV(RS)'!W50 -> 0 | X18: ='RV(RS)'!X50 -> 0 | Y18: ='RV(RS)'!Y50 -> 0 | Z18: ='RV(RS)'!Z50 -> 0 | AA18: ='RV(RS)'!AA50 -> 0 | AB18: ='RV(RS)'!AB50 -> 0 | AC18: ='RV(RS)'!AC50 -> 0 | AD18: ='RV(RS)'!AD50 -> 0 | ... AH18: ='RV(RS)'!AH50 -> 0 | AJ18: =V18/G18 -> 0
A19: 3. 기타 매출 | B19: 2. Other sales | D19: 2.6549321e+08 | G19: =SUM(H19:S19) -> 16203925 | H19: 40645 | I19: 278788.44 | J19: 77615 | K19: 80717.06 | L19: =SUM(L20:L23) -> 7088342.5 | M19: =SUM(M20:M23) -> 216491.2 | N19: =SUM(N20:N23) -> 244062.8 | O19: =SUM(O20:O23) -> 6708473 | P19: =SUM(P20:P23) -> 207478.54 | Q19: =SUM(Q20:Q23) -> 62170 | R19: =SUM(R20:R23) -> 599570.79 | S19: =SUM(S20:S23) -> 599570.79 | V19: =SUM(W19:AH19) -> 0 | W19: =SUM(W20:W23) -> 0 | X19: =SUM(X20:X23) -> 0 | Y19: =SUM(Y20:Y23) -> 0 | Z19: =SUM(Z20:Z23) -> 0 | AA19: =SUM(AA20:AA23) -> 0 | AB19: =SUM(AB20:AB23) -> 0 | AC19: =SUM(AC20:AC23) -> 0 | AD19: =SUM(AD20:AD23) -> 0 | ... AH19: =SUM(AH20:AH23) -> 0 | AJ19: =V19/G19 -> 0
A20: └ Materials | B20: └ Materials | C20: 613100 | D20: 1.7291133e+08 | G20: =SUM(H20:S20) -> 104755.67 | H20: 0 | I20: 43424.18 | J20: 0 | K20: 30747.06 | L20: 0 | M20: 0 | N20: 0 | O20: 30584.43 | P20: 0 | Q20: 0 | R20: 0 | S20: =R20 -> 0 | V20: =SUM(W20:AH20) -> 0
A21: └ scrap | B21: └ scrap | C21: 559001 | D21: 2589065.3 | G21: =SUM(H21:S21) -> 0 | H21: 0 | I21: 0 | J21: 0 | K21: 0 | L21: 0 | M21: 0 | N21: 0 | O21: 0 | P21: 0 | Q21: 0 | R21: 0 | S21: =R21 -> 0 | V21: =SUM(W21:AH21) -> 0
A22: └ scrap | B22: └ scrap | C22: 659000 | D22: 2589065.3 | G22: =SUM(H22:S22) -> 9062601.9 | H22: 40645 | I22: 235364.26 | J22: 77615 | K22: 49970 | L22: 51775 | M22: 216491.2 | N22: 244062.8 | O22: 6677888.5 | P22: 207478.54 | Q22: 62170 | R22: 599570.79 | S22: =R22 -> 599570.79 | V22: =SUM(W22:AH22) -> 0
A23: └ 기타 | B23: └ Other | C23: 649000 | D23: 89992815 | G23: =SUM(H23:S23) -> 7036567.5 | H23: 0 | I23: 0 | J23: 0 | K23: 0 | L23: 7036567.5 | M23: 0 | N23: 0 | O23: 0 | P23: 0 | Q23: 0 | R23: 0 | S23: =R23 -> 0 | V23: =SUM(W23:AH23) -> 0
A24: Ⅱ. 매출원가 | B24: Ⅱ. COST OF SALES | D24: 3.3977175e+09 | G24: =SUM(H24:S24) -> 2.7615262e+09 | H24: 2.7872033e+08 | I24: 2.0271682e+08 | J24: 2.2704957e+08 | K24: 1.6827058e+08 | L24: =+L25+L33+L39 -> 1.5904296e+08 | M24: =+M25+M33+M39 -> 1.8412989e+08 | N24: =+N25+N33+N39 -> 2.383117e+08 | O24: =+O25+O33+O39 -> 2.5672973e+08 | P24: =+P25+P33+P39 -> 2.5740864e+08 | Q24: =+Q25+Q33+Q39 -> 2.565562e+08 | R24: =+R25+R33+R39 -> 2.6673698e+08 | S24: =+S25+S33+S39 -> 2.6585275e+08 | V24: =SUM(W24:AH24) -> 3.8164602e+09 | W24: =W25+W33+W39 -> 2.838131e+08 | X24: =X25+X33+X39 -> 3.0719635e+08 | Y24: =Y25+Y33+Y39 -> 3.3551457e+08 | Z24: =Z25+Z33+Z39 -> 3.2372103e+08 | AA24: =AA25+AA33+AA39 -> 3.304234e+08 | AB24: =AB25+AB33+AB39 -> 3.4024337e+08 | AC24: =AC25+AC33+AC39 -> 2.6294297e+08 | AD24: =AD25+AD33+AD39 -> 2.3661629e+08 | ... AH24: =AH25+AH33+AH39 -> 3.7940001e+08 | AJ24: =V24/G24 -> 1.3820112
A25: 제품매출원가 | B25: Cost of manufactured goods sold | D25: 3.026646e+09 | G25: =SUM(H25:S25) -> 2.7465476e+09 | H25: =+H26+H27+H28-H29-H32-H30-H31 -> 2.7471798e+08 | I25: =+I26+I27+I28-I29-I32-I30-I31 -> 1.9751573e+08 | J25: =+J26+J27+J28-J29-J32-J30-J31 -> 2.2272685e+08 | K25: =+K26+K27+K28-K29-K32-K30-K31 -> 1.6823999e+08 | L25: =+L26+L27+L28-L29-L32-L30-L31 -> 1.5904297e+08 | M25: =+M26+M27+M28-M29-M32-M30-M31 -> 1.8413086e+08 | N25: =+N26+N27+N28-N29-N32-N30-N31 -> 2.3831242e+08 | O25: =+O26+O27+O28-O29-O32-O30-O31 -> 2.5670011e+08 | ... S25: =+S26+S27+S28-S29-S32-S30-S31 -> 2.6585318e+08 | T25: =G24/G6 -> 1.1769446 | V25: =SUM(W25:AH25) -> 3.8164602e+09 | W25: =W26+W27-W32 -> 2.838131e+08 | X25: =X26+X27-X32 -> 3.0719635e+08 | Y25: =Y26+Y27-Y32 -> 3.3551457e+08 | Z25: =Z26+Z27-Z32 -> 3.2372103e+08 | AA25: =AA26+AA27-AA32 -> 3.304234e+08 | AB25: =AB26+AB27-AB32 -> 3.4024337e+08 | AC25: =AC26+AC27-AC32 -> 2.6294297e+08 | AD25: =AD26+AD27-AD32 -> 2.3661629e+08 | ... AH25: =AH26+AH27-AH32 -> 3.7940001e+08 | AJ25: =V25/G25 -> 1.3895482 | AK25: 매출손 -8% -> -23% | AL25: =SUM(W6:AH6)/SUM(W24:AH24) -> 1.0071831
A26: 1.기초 제품재고 | B26: 1. Beginning Manufactured goods | D26: 4.4767263e+08 | G26: =H26 -> 99150685 | H26: 99150685 | I26: 58269677 | J26: 85277617 | K26: 84523970 | L26: =K32 -> 1.381784e+08 | M26: 1.9513798e+08 | N26: 2.324261e+08 | O26: 1.8905585e+08 | P26: =O32 -> 1.6915692e+08 | Q26: 1.0758689e+08 | R26: 1.0984176e+08 | V26: =SUM(W26:AH26) -> 0 | AJ26: =V24/V6 -> 0.99286809
A27: 2.당기 제품제조원가 | B27: 2. Cost of Goods Maunfactured | D27: 2.8148022e+09 | G27: =SUM(H27:S27) -> 2.7312365e+09 | H27: 2.3383697e+08 | I27: 2.2519533e+08 | J27: 2.2216617e+08 | K27: 2.2211578e+08 | L27: 2.1601381e+08 | M27: 2.215829e+08 | N27: 1.9502259e+08 | O27: 2.3684146e+08 | P27: 1.9637644e+08 | Q27: 2.5866452e+08 | R27: 2.3756738e+08 | S27: 2.6585318e+08 | V27: =SUM(W27:AH27) -> 3.8164602e+09 | W27: ='MC2026(RS)'!W36 -> 2.838131e+08 | X27: ='MC2026(RS)'!X36 -> 3.0719635e+08 | Y27: ='MC2026(RS)'!Y36 -> 3.3551457e+08 | Z27: ='MC2026(RS)'!Z36 -> 3.2372103e+08 | AA27: ='MC2026(RS)'!AA36 -> 3.304234e+08 | AB27: ='MC2026(RS)'!AB36 -> 3.4024337e+08 | AC27: ='MC2026(RS)'!AC36 -> 2.6294297e+08 | AD27: ='MC2026(RS)'!AD36 -> 2.3661629e+08 | ... AH27: ='MC2026(RS)'!AH36 -> 3.7940001e+08
A28: 3.타계정전입 (+) | B28: 3. Transferred from other accounts | D28: 0 | G28: =SUM(H28:S28) -> 0 | H28: 0 | I28: 0 | J28: 0 | K28: 0 | L28: 0 | M28: 0 | N28: 0 | O28: 0 | P28: 0 | Q28: 0 | R28: 0 | V28: =SUM(W28:AH28) -> 0
A29: 4.타계정대체 (-) | B29: 4. Transferred to other accounts | D29: 5392745.6 | G29: =SUM(H29:S29) -> 1892537.1 | H29: 0 | I29: 671654.02 | J29: 192973.57 | K29: 221360.4 | L29: 11253.067 | M29: 163927.66 | N29: 80409.795 | O29: 40272.614 | P29: 536988.55 | Q29: -19369.314 | R29: -6933.2851 | V29: =SUM(W29:AH29) -> 0
A30: 5.재고자산감모손실 | B30: 5. Losses on Inventory Obsolescence | D30: 0 | G30: =SUM(H30:S30) -> 0 | H30: 0 | I30: 0 | J30: 0 | K30: 0 | L30: 0 | M30: 0 | N30: 0 | O30: 0 | P30: 0 | Q30: 0 | R30: 0 | V30: =SUM(W30:AH30) -> 0
A31: 6.재고자산평가손실 | B31: 6. Loss on valuation of inventories | D31: 0 | G31: =SUM(H31:S31) -> 0 | H31: 0 | I31: 0 | J31: 0 | K31: 0 | L31: 0 | M31: 0 | N31: 0 | O31: 0 | P31: 0 | Q31: 0 | R31: 0 | V31: =SUM(W31:AH31) -> 0
A32: 7.기말 제품재고 | B32: 7. Ending Manufactured goods | D32: 2.3043603e+08 | G32: 2.5793129e+08 | H32: 58269677 | I32: 85277617 | J32: 84523970 | K32: 1.381784e+08 | L32: 1.9513798e+08 | M32: 2.324261e+08 | N32: 1.8905585e+08 | O32: 1.6915692e+08 | P32: 1.0758689e+08 | Q32: 1.0984176e+08 | R32: 81947058 | AJ32: =V32/G32 -> 0
A33: 상품매출원가 | B33: Cost of merchandise sold | D33: 2.0356215e+08 | G33: =SUM(H33:S33) -> 14882892 | H33: 4002356 | I33: 5161336.6 | J33: 4323048.4 | K33: 0 | L33: =+L34+L35+L36-L37-L38 -> 0 | M33: =+M34+M35+M36-M37-M38 -> 0 | N33: =+N34+N35+N36-N37-N38 -> 0 | O33: =+O34+O35+O36-O37-O38 -> 0 | P33: =+P34+P35+P36-P37-P38 -> 0 | Q33: =+Q34+Q35+Q36-Q37-Q38 -> 127754 | R33: =+R34+R35+R36-R37-R38 -> 1268397.1 | S33: 0 | T33: =SUM(H15:S15)/SUM(H33:S33) -> 1.4082438 | V33: =SUM(W33:AH33) -> 0 | W33: =W35 -> 0 | X33: =X35 -> 0 | Y33: =Y35 -> 0 | Z33: =Z35 -> 0 | AA33: =AA35 -> 0 | AB33: =AB35 -> 0 | AC33: =AC35 -> 0 | AD33: =AD35 -> 0 | ... AH33: =AH35 -> 0 | AJ33: =V33/G33 -> 0 | AK33: 매출익 7% -> 8% | AL33: =SUM(W15:AH15)/SUM(W33:AH33) -> #DIV/0!
A34: 1.기초 상품재고 | B34: 1. Beginning Merchandise | D34: 40703217 | G34: =SUM(H34:S34) -> 4.1146333e+08 | H34: 45507654 | I34: 41505298 | J34: 36343961 | K34: 32020913 | L34: 32020913 | M34: 32009227 | N34: 32009227 | O34: 32009227 | P34: 32009227 | Q34: 32009227 | R34: 32009227 | S34: =R34 -> 32009227 | V34: =SUM(W34:AH34) -> 0 | AJ34: =V34/G34 -> 0
A35: 2.당기 상품매입원가 | B35: 2. Cost of Merchandise | D35: 2.1599822e+08 | G35: =SUM(H35:S35) -> 1396151.1 | H35: 0 | I35: 0 | J35: 0 | K35: 0 | L35: 0 | M35: 0 | N35: 0 | O35: 0 | P35: 0 | Q35: 127754 | R35: 1268397.1 | V35: =SUM(W35:AH35) -> 0 | W35: =RMC!K50 -> 0 | X35: =RMC!L50 -> 0 | Y35: =RMC!M50 -> 0 | Z35: =RMC!N50 -> 0 | AA35: =RMC!O50 -> 0 | AB35: =RMC!P50 -> 0 | AC35: =RMC!Q50 -> 0 | AD35: =RMC!R50 -> 0 | ... AH35: =RMC!V50 -> 0
A36: 3.타계정전입 (+) | B36: 3. Transferred from other accounts | D36: 0 | G36: =SUM(H36:S36) -> 0 | H36: 0 | I36: 0 | J36: 0 | K36: 0 | L36: 0 | M36: 0 | N36: 0 | O36: 0 | P36: 0 | Q36: 0 | R36: 0 | V36: =SUM(W36:AH36) -> 0
A37: 4.타계정대체 (-) | B37: 4. Transferred to other accounts | D37: 179525.25 | G37: =SUM(H37:S37) -> 11685.619 | H37: 0 | I37: 0 | J37: 0 | K37: 0 | L37: 11685.619 | M37: 0 | N37: 0 | O37: 0 | P37: 0 | Q37: 0 | R37: 0 | V37: =SUM(W37:AH37) -> 0
A38: 5.기말 상품재고 | B38: 5. Ending Merchandise | D38: 52959757 | G38: =SUM(H38:S38) -> 3.979649e+08 | H38: 41505298 | I38: 36343961 | J38: 32020913 | K38: 32020913 | L38: 32009227 | M38: 32009227 | N38: 32009227 | O38: 32009227 | P38: 32009227 | Q38: 32009227 | R38: 32009227 | S38: =R38 -> 32009227 | V38: =SUM(W38:AH38) -> 0 | AJ38: =V38/G38 -> 0
A39: 기타매출원가 | B39: Cost of other sold | D39: 1.6750927e+08 | G39: =SUM(H39:S39) -> 95639.211 | H39: 0 | I39: 39745.207 | J39: -319.58613 | K39: 30598.138 | L39: =SUM(L40:L42) -> -6.1167979 | M39: =SUM(M40:M42) -> -970.88912 | N39: =SUM(N40:N42) -> -729.20743 | O39: =SUM(O40:O42) -> 29616.995 | P39: =SUM(P40:P42) -> -841.01739 | Q39: =SUM(Q40:Q42) -> -576.46274 | R39: =SUM(R40:R42) -> -438.92461 | S39: =SUM(S40:S42) -> -438.92461 | V39: =SUM(W39:AH39) -> 0 | AJ39: =V39/G39 -> 0
A40: 원재료 매출원가 | B40: raw material | D40: 1.6750927e+08 | G40: =SUM(H40:S40) -> 95639.211 | H40: 0 | I40: 39745.207 | J40: -319.58613 | K40: 30598.138 | L40: -6.1167979 | M40: -970.88912 | N40: -729.20743 | O40: 29616.995 | P40: -841.01739 | Q40: -576.46274 | R40: -438.92461 | S40: =R40 -> -438.92461 | V40: =SUM(W40:AH40) -> 0
A41: 반제품 매출원가 | B41: semi product | D41: 0 | G41: =SUM(H41:S41) -> 0 | H41: 0 | I41: 0 | J41: 0 | K41: 0 | L41: 0 | M41: 0 | N41: 0 | O41: 0 | P41: 0 | Q41: =T41-SUM(H41:P41) -> 0 | R41: 0 | S41: =R41 -> 0 | V41: =SUM(W41:AH41) -> 0
A42: 기타 | B42: other | D42: 0 | G42: =SUM(H42:S42) -> 0 | H42: 0 | I42: 0 | J42: 0 | K42: 0 | L42: 0 | M42: 0 | N42: 0 | O42: 0 | P42: 0 | Q42: =T42-SUM(H42:P42) -> 0 | R42: 0 | S42: =R42 -> 0 | V42: =SUM(W42:AH42) -> 0
A43: Ⅲ. 매출총이익 | B43: Ⅲ. GROSS PROFIT (or GROSS LOSS) | D43: -3.7292369e+08 | G43: =G6-G24 -> -4.1517423e+08 | H43: -33436781 | I43: -22157572 | J43: -35338318 | K43: -52530328 | L43: =+L6-L24 -> -26928207 | M43: =+M6-M24 -> -47261293 | N43: =+N6-N24 -> -49540428 | O43: =+O6-O24 -> -58869330 | P43: =+P6-P24 -> -49097865 | Q43: =+Q6-Q24 -> -21430931 | R43: =R6-R24 -> -9733702 | S43: =S6-S24 -> -8849469.8 | V43: =SUM(W43:AH43) -> 27414172 | W43: =W6-W24 -> -43359416 | X43: =X6-X24 -> -26575404 | Y43: =Y6-Y24 -> -6419693.4 | Z43: =Z6-Z24 -> -20648103 | AA43: =AA6-AA24 -> -16329519 | AB43: =AB6-AB24 -> -10563057 | AC43: =AC6-AC24 -> -9186603.5 | AD43: =AD6-AD24 -> -18260029 | ... AH43: =AH6-AH24 -> 56364563 | AJ43: =V43/G43 -> -0.066030525
A44: (이익률) | B44: (Rate) | D44: -0.12328897 | G44: =+IFERROR(G43/G6,) -> -0.17694457 | H44: -0.13631889 | I44: -0.12271635 | J44: -0.18433095 | K44: -0.45386393 | L44: =+IFERROR(L43/L6,) -> -0.20382437 | M44: =+IFERROR(M43/M6,) -> -0.34530414 | N44: =+IFERROR(N43/N6,) -> -0.26243627 | O44: =+IFERROR(O43/O6,) -> -0.29752962 | P44: =+IFERROR(P43/P6,) -> -0.23569527 | Q44: =+IFERROR(Q43/Q6,) -> -0.091146865 | R44: =+IFERROR(R43/R6,) -> -0.037873844 | S44: =+IFERROR(S43/S6,) -> -0.034433296 | V44: =V43/V6 -> 0.0071319115 | W44: =W43/W6 -> -0.18032336 | X44: =X43/X6 -> -0.094702139 | Y44: =Y43/Y6 -> -0.01950712 | Z44: =Z43/Z6 -> -0.068129157 | AA44: =AA43/AA6 -> -0.051989295 | AB44: =AB43/AB6 -> -0.032040303 | AC44: =AC43/AC6 -> -0.036202455 | ... AH44: =AH43/AH6 -> 0.12934637 | AJ44: =V44/G44 -> -0.040305909
A45: Ⅳ.판매관리비 | B45: Ⅳ. SELLING & ADMINISTRATIVE EXPENSES | D45: 1.9638703e+08 | G45: =SUM(H45:S45) -> 2.5921754e+08 | H45: 13904922 | I45: 13832555 | J45: 16977526 | K45: 9203852.7 | L45: =SUM(L46:L85) -> 21928693 | M45: =SUM(M46:M85) -> 40055079 | N45: =SUM(N46:N85) -> 15485434 | O45: =SUM(O46:O85) -> 15351116 | P45: =SUM(P46:P85) -> 13974309 | Q45: =SUM(Q46:Q85) -> 17894215 | R45: =SUM(R46:R85) -> 30015362 | S45: =SUM(S46:S85) -> 50594481 | V45: =SUM(W45:AH45) -> 3.1248686e+08 | W45: =SUM(W46:W85) -> 18474446 | X45: =SUM(X46:X85) -> 17384482 | Y45: =SUM(Y46:Y85) -> 24967732 | Z45: =SUM(Z46:Z85) -> 20155941 | AA45: =SUM(AA46:AA85) -> 19408502 | AB45: =SUM(AB46:AB85) -> 56733061 | AC45: =SUM(AC46:AC85) -> 17005572 | AD45: =SUM(AD46:AD85) -> 16714192 | ... AH45: =SUM(AH46:AH85) -> 63042766 | AI45: =V45/$V$6 -> 0.081294765 | AJ45: =V45/G45 -> 1.2055004
A46: 급여 | B46: Salaries, Wages, Bonues etc. | D46: 55452921 | G46: =SUM(H46:S46) -> 72263674 | H46: 5689686.6 | I46: 5403948.5 | J46: 6935715.5 | K46: 4123269.8 | L46: 5828295.8 | M46: 6495059.2 | N46: 6331787.3 | O46: 6043516.1 | P46: 5648348.5 | Q46: 6771336.1 | R46: 6496355.5 | S46: =R46 -> 6496355.5 | V46: =SUM(W46:AH46) -> 78392777 | W46: =HR!BG10 -> 5843662.9 | X46: =HR!BH10 -> 5843662.9 | Y46: =HR!BI10 -> 5843662.9 | Z46: =HR!BJ10 -> 6762420.9 | AA46: =HR!BK10 -> 6762420.9 | AB46: =HR!BL10 -> 6762420.9 | AC46: =HR!BM10 -> 6762420.9 | AD46: =HR!BN10 -> 6762420.9 | ... AH46: =HR!BR10 -> 6762420.9 | AI46: =V46/$V$45 -> 0.25086743 | AJ46: =IFERROR(V46/G46,0) -> 1.0848158 | AK46: =G46 -> 72263674 | AM46: 급여 | AN46: F
A47: 퇴직급여 | B47: Reserve for retirement allowance | D47: 0 | G47: =SUM(H47:S47) -> 0 | H47: 0 | I47: 0 | J47: 0 | K47: 0 | L47: 0 | M47: 0 | N47: 0 | O47: 0 | P47: 0 | Q47: 0 | R47: 0 | S47: =R47 -> 0 | V47: =SUM(W47:AH47) -> 0 | W47: =AVERAGE(H47:P47) -> 0 | X47: =W47 -> 0 | Y47: =X47 -> 0 | Z47: =Y47 -> 0 | AA47: =Z47 -> 0 | AB47: =AA47 -> 0 | AC47: =AB47 -> 0 | AD47: =AC47 -> 0 | AE47: =AD47 -> 0 | ... AH47: =AG47 -> 0 | AI47: =V47/$V$45 -> 0 | AJ47: =IFERROR(V47/G47,0) -> 0 | AM47: 퇴직급여 | AN47: F
A48: 도급용역비 | B48: Cost of Service | D48: 0 | G48: =SUM(H48:S48) -> 0 | H48: 0 | I48: 0 | J48: 0 | K48: 0 | L48: 0 | M48: 0 | N48: 0 | O48: 0 | P48: 0 | Q48: 0 | R48: 0 | S48: =R48 -> 0 | V48: =SUM(W48:AH48) -> 0 | W48: =AVERAGE(H48:P48) -> 0 | X48: =W48 -> 0 | Y48: =X48 -> 0 | Z48: =Y48 -> 0 | AA48: =Z48 -> 0 | AB48: =AA48 -> 0 | AC48: =AB48 -> 0 | AD48: =AC48 -> 0 | AE48: =AD48 -> 0 | ... AH48: =AG48 -> 0 | AI48: =V48/$V$45 -> 0 | AJ48: =IFERROR(V48/G48,0) -> 0 | AM48: 도급용역비
A49: 복리후생비 | B49: Fringe benefits | D49: 0 | G49: =SUM(H49:S49) -> 4181644.5 | H49: 0 | I49: 5000 | J49: 181692 | K49: 0 | L49: 33509.97 | M49: 1372442.5 | N49: 0 | O49: 25000 | P49: 0 | Q49: 0 | R49: 25000 | S49: 2539000 | V49: =SUM(W49:AH49) -> 8232000 | W49: ='HR Benefits'!C6 -> 72000 | X49: ='HR Benefits'!D6 -> 350000 | Y49: ='HR Benefits'!E6 -> 660000 | Z49: ='HR Benefits'!F6 -> 50000 | AA49: ='HR Benefits'!G6 -> 1000000 | AB49: ='HR Benefits'!H6 -> 2500000 | AC49: ='HR Benefits'!I6 -> 0 | AD49: ='HR Benefits'!J6 -> 350000 | ... AH49: ='HR Benefits'!N6 -> 3200000 | AI49: =V49/$V$45 -> 0.026343507 | AJ49: =IFERROR(V49/G49,0) -> 1.9686035 | AK49: =AK46-V46 -> -6129102.2 | AM49: 복리후생비 | AN49: F
A50: 동력비 | B50: Electricity | D50: 2340841.8 | G50: =SUM(H50:S50) -> 2788754 | H50: 210956.23 | I50: 210956.23 | J50: 174843.34 | K50: 195899.52 | L50: 223992.7 | M50: 254082.34 | N50: 254082.34 | O50: 193028.13 | P50: 243160.97 | Q50: 271954.3 | R50: 277898.95 | S50: =R50 -> 277898.95 | V50: =SUM(W50:AH50) -> 2928191.7 | W50: =H50*1.05 -> 221504.04 | X50: =I50*1.05 -> 221504.04 | Y50: =J50*1.05 -> 183585.51 | Z50: =K50*1.05 -> 205694.5 | AA50: =L50*1.05 -> 235192.33 | AB50: =M50*1.05 -> 266786.46 | AC50: =N50*1.05 -> 266786.46 | AD50: =O50*1.05 -> 202679.54 | ... AH50: =S50*1.05 -> 291793.9 | AI50: =V50/$V$45 -> 0.0093706074 | AJ50: =IFERROR(V50/G50,0) -> 1.05 | AK50: 전년월별 5%인상 | AM50: 동력비 | AN50: F
A51: 연료비 | B51: Fuel | D51: 0 | G51: =SUM(H51:S51) -> 0 | H51: 0 | I51: 0 | J51: 0 | K51: 0 | L51: 0 | M51: 0 | N51: 0 | O51: 0 | P51: 0 | Q51: 0 | R51: 0 | S51: =R51 -> 0 | V51: =SUM(W51:AH51) -> 0 | W51: =AVERAGE(H51:R51) -> 0 | X51: =W51 -> 0 | Y51: =X51 -> 0 | Z51: =Y51 -> 0 | AA51: =Z51 -> 0 | AB51: =AA51 -> 0 | AC51: =AB51 -> 0 | AD51: =AC51 -> 0 | AE51: =AD51 -> 0 | ... AH51: =AG51 -> 0 | AI51: =V51/$V$45 -> 0 | AJ51: =IFERROR(V51/G51,0) -> 0 | AM51: 연료비
A52: 여비교통비 | B52: Travel | D52: 1440521.8 | G52: =SUM(H52:S52) -> 1297980.5 | H52: 149795.64 | I52: 242302.56 | J52: 80357.67 | K52: 49957.87 | L52: 260472.05 | M52: 62835.05 | N52: 46815.04 | O52: 191466.38 | P52: 102185.26 | Q52: 48565.94 | R52: 31613.54 | S52: =R52 -> 31613.54 | V52: =SUM(W52:AH52) -> 2940000 | W52: =Travel!C5 -> 100000 | X52: =Travel!D5 -> 100000 | Y52: =Travel!E5 -> 560000 | Z52: =Travel!F5 -> 160000 | AA52: =Travel!G5 -> 300000 | AB52: =Travel!H5 -> 400000 | AC52: =Travel!I5 -> 160000 | AD52: =Travel!J5 -> 100000 | ... AH52: =Travel!N5 -> 400000 | AI52: =V52/$V$45 -> 0.0094083955 | AJ52: =IFERROR(V52/G52,0) -> 2.2650571 | AM52: 여비교통비 | AN52: F
A53: 대손상각비 | B53: Bad debt expense | G53: =SUM(H53:S53) -> 0 | H53: 0 | I53: 0 | J53: 0 | K53: 0 | L53: 0 | M53: 0 | N53: 0 | O53: 0 | P53: 0 | Q53: 0 | R53: 0 | S53: =R53 -> 0 | V53: =SUM(W53:AH53) -> 0 | W53: =AVERAGE(H53:R53) -> 0 | X53: =W53 -> 0 | Y53: =X53 -> 0 | Z53: =Y53 -> 0 | AA53: =Z53 -> 0 | AB53: =AA53 -> 0 | AC53: =AB53 -> 0 | AD53: =AC53 -> 0 | AE53: =AD53 -> 0 | ... AH53: =AG53 -> 0 | AI53: =V53/$V$45 -> 0 | AJ53: =IFERROR(V53/G53,0) -> 0 | AM53: 대손상각비
